Workbook

Sheet RESUMEN AL 20-7-2026
C2: PERU FROST
C3: AVANCE COMERCIAL AL 20-7-2026
F5: RENTABILIDAD DEL INVENTARIO | X5: 46206 | AA5: 46209 | AD5: 46215 | AG5: 46216 | AJ5: 46222 | AM5: 46224 | AP5: 46225 | AS5: 46229 | AV5: 46232 | AY5: TBN | BT5: TOTAL PROYECTADO JULIO 2026 | CH5: UNITARIOS POR TM
B6: Código | C6: Producto | D6: TM en Stock Libre | E6: CU | F6: Costo Ventas | G6: Gasto Ventas | H6: Gasto ADM | I6: Gasto Fin | J6: Depreciación | K6: Utilidad Neta | L6: Margen Neto | M6: Venta Equilibrio a Utd Neta | N6: Precio Equilibrio x TM a Utd Neta | O6: Venta Equilibro a EBITDA | P6: Precio Equilibrio x TM a EBITDA | Q6: Precio Mercado | R6: Venta total | S6: Utilidad | T6: Mg Neto | U6: EBITDA | V6: Mg EBITDA | X6: TM | Y6: Venta | Z6: Precio x TM | AA6: TM | AB6: Venta | AC6: Precio x TM | AD6: TM | AE6: Venta | AF6: Precio x TM | AG6: TM | AH6: Venta | AI6: Precio x TM | AJ6: TM | AK6: Venta | AL6: Precio x TM | AM6: TM | AN6: Venta | AO6: Precio x TM | AP6: TM | AQ6: Venta | AR6: Precio x TM | AS6: TM | AT6: Venta | AU6: Precio x TM | AV6: TM | AW6: Venta | AX6: Precio x TM | AY6: TM | AZ6: Venta | BA6: Precio x TM | BB6: TM | BC6: Venta | BD6: Precio x TM | BE6: TM | BF6: Venta | BG6: Precio x TM | BH6: TM | BI6: Venta | BJ6: Precio x TM | BK6: TM | BL6: Venta | BM6: Precio x TM | BN6: TM | BO6: Venta | BP6: Precio x TM | BQ6: TM | BR6: Venta | BS6: Precio x TM | BT6: TM | BU6: Venta | BV6: Precio x TM | BW6: Costo Ventas | BX6: Gasto Ventas | BY6: Gasto Adm | BZ6: Gasto Fin | CA6: Depreciación | CB6: Drawback | CC6: Utilidad Neta | CD6: Mg Neto % | CE6: EBITDA | CF6: MG EBITDA | CH6: Precio x TM | CI6: Costo Ventas | CJ6: Gasto Ventas | CK6: Gasto Adm | CL6: Gasto Fin | CM6: Depreciación | CN6: Drawback | CO6: Utilidad Neta | CP6: EBITDA
B7: 10005721 | C7: POTA FILETE CONGELADO | D7: =TD!F4 -> 462.666 | E7: =IFERROR(F7/D7,0) -> 1937.5523 | F7: =TD!G4 -> 896439.56 | G7: =TD!H4 -> 96160.501 | H7: =TD!I4 -> 20871.593 | I7: =TD!J4 -> 41030.016 | J7: =TD!K4 -> 32799.032 | K7: 0 | L7: 0 | M7: =F7+G7+H7+I7 -> 1054501.7 | N7: =IFERROR(M7/D7,0) -> 2279.1856 | O7: =F7+G7+H7-J7 -> 980672.62 | P7: =IFERROR(O7/D7,0) -> 2119.6125 | Q7: 1400 | R7: =Q7*D7 -> 647732.4 | S7: =R7-M7+(Q7-$BY$19)*D7*0.03 -> -388922.08 | T7: =IFERROR(S7/R7,0) -> -0.60043635 | U7: =R7-(M7-J7-I7)+(Q7-$BY$19)*D7*0.03 -> -315093.03 | V7: =IFERROR(U7/R7,0) -> -0.48645557 | X7: {=SUM([5]Hoja3!$I$6:$I$25*([5]Hoja3!$F$6:$F$25=X$5)*([5]Hoja3!$K$6:$K$25=$C7))} -> 0 | Y7: {=SUM([5]Hoja3!$J$6:$J$25*([5]Hoja3!$F$6:$F$25=X$5)*([5]Hoja3!$K$6:$K$25=$C7))} -> 0 | Z7: =IFERROR(Y7/X7,0) -> 0 | AA7: {=SUM([5]Hoja3!$I$6:$I$25*([5]Hoja3!$F$6:$F$25=AA$5)*([5]Hoja3!$K$6:$K$25=$C7))} -> 0 | AB7: {=SUM([5]Hoja3!$J$6:$J$25*([5]Hoja3!$F$6:$F$25=AA$5)*([5]Hoja3!$K$6:$K$25=$C7))} -> 0 | AC7: =IFERROR(AB7/AA7,0) -> 0 | AD7: {=SUM([5]Hoja3!$I$6:$I$25*([5]Hoja3!$F$6:$F$25=AD$5)*([5]Hoja3!$K$6:$K$25=$C7))} -> 0 | AE7: {=SUM([5]Hoja3!$J$6:$J$25*([5]Hoja3!$F$6:$F$25=AD$5)*([5]Hoja3!$K$6:$K$25=$C7))} -> 0 | AF7: =IFERROR(AE7/AD7,0) -> 0 | AG7: {=SUM([5]Hoja3!$I$6:$I$25*([5]Hoja3!$F$6:$F$25=AG$5)*([5]Hoja3!$K$6:$K$25=$C7))} -> 0 | AH7: {=SUM([5]Hoja3!$J$6:$J$25*([5]Hoja3!$F$6:$F$25=AG$5)*([5]Hoja3!$K$6:$K$25=$C7))} -> 0 | AI7: =IFERROR(AH7/AG7,0) -> 0 | AJ7: {=SUM([5]Hoja3!$I$6:$I$25*([5]Hoja3!$F$6:$F$25=AJ$5)*([5]Hoja3!$K$6:$K$25=$C7))} -> 0 | AK7: {=SUM([5]Hoja3!$J$6:$J$25*([5]Hoja3!$F$6:$F$25=AJ$5)*([5]Hoja3!$K$6:$K$25=$C7))} -> 0 | AL7: =IFERROR(AK7/AJ7,0) -> 0 | AM7: {=SUM([5]Hoja3!$I$6:$I$25*([5]Hoja3!$F$6:$F$25=AM$5)*([5]Hoja3!$K$6:$K$25=$C7))} -> 24 | AN7: {=SUM([5]Hoja3!$J$6:$J$25*([5]Hoja3!$F$6:$F$25=AM$5)*([5]Hoja3!$K$6:$K$25=$C7))} -> 48000 | AO7: =IFERROR(AN7/AM7,0) -> 2000 | AP7: {=SUM([5]Hoja3!$I$6:$I$25*([5]Hoja3!$F$6:$F$25=AP$5)*([5]Hoja3!$K$6:$K$25=$C7))} -> 0 | AQ7: {=SUM([5]Hoja3!$J$6:$J$25*([5]Hoja3!$F$6:$F$25=AP$5)*([5]Hoja3!$K$6:$K$25=$C7))} -> 0 | AR7: =IFERROR(AQ7/AP7,0) -> 0 | AS7: {=SUM([5]Hoja3!$I$6:$I$25*([5]Hoja3!$F$6:$F$25=AS$5)*([5]Hoja3!$K$6:$K$25=$C7))} -> 0 | AT7: {=SUM([5]Hoja3!$J$6:$J$25*([5]Hoja3!$F$6:$F$25=AS$5)*([5]Hoja3!$K$6:$K$25=$C7))} -> 0 | AU7: =IFERROR(AT7/AS7,0) -> 0 | AV7: {=SUM([5]Hoja3!$I$6:$I$25*([5]Hoja3!$F$6:$F$25=AV$5)*([5]Hoja3!$K$6:$K$25=$C7))} -> 0 | AW7: {=SUM([5]Hoja3!$J$6:$J$25*([5]Hoja3!$F$6:$F$25=AV$5)*([5]Hoja3!$K$6:$K$25=$C7))} -> 0 | AX7: =IFERROR(AW7/AV7,0) -> 0 | AY7: {=SUM([5]Hoja3!$I$6:$I$25*([5]Hoja3!$F$6:$F$25=AY$5)*([5]Hoja3!$K$6:$K$25=$C7))} -> 0 | AZ7: {=SUM([5]Hoja3!$J$6:$J$25*([5]Hoja3!$F$6:$F$25=AY$5)*([5]Hoja3!$K$6:$K$25=$C7))} -> 0 | BA7: =IFERROR(AZ7/AY7,0) -> 0 | BB7: {=SUM([2]Hoja2!$I$6:$I$26*([2]Hoja2!$F$6:$F$26=BB$5)*([2]Hoja2!$K$6:$K$26=$C7))} -> 0 | BC7: {=SUM([2]Hoja2!$J$6:$J$26*([2]Hoja2!$F$6:$F$26=BB$5)*([2]Hoja2!$K$6:$K$26=$C7))} -> 0 | BD7: =IFERROR(BC7/BB7,0) -> 0 | BE7: {=SUM([2]Hoja2!$I$6:$I$26*([2]Hoja2!$F$6:$F$26=BE$5)*([2]Hoja2!$K$6:$K$26=$C7))} -> 0 | BF7: {=SUM([2]Hoja2!$J$6:$J$26*([2]Hoja2!$F$6:$F$26=BE$5)*([2]Hoja2!$K$6:$K$26=$C7))} -> 0 | BG7: =IFERROR(BF7/BE7,0) -> 0 | BH7: {=SUM([2]Hoja2!$I$6:$I$26*([2]Hoja2!$F$6:$F$26=BH$5)*([2]Hoja2!$K$6:$K$26=$C7))} -> 0 | BI7: {=SUM([2]Hoja2!$J$6:$J$26*([2]Hoja2!$F$6:$F$26=BH$5)*([2]Hoja2!$K$6:$K$26=$C7))} -> 0 | BJ7: =IFERROR(BI7/BH7,0) -> 0 | BK7: {=SUM([2]Hoja2!$I$6:$I$26*([2]Hoja2!$F$6:$F$26=BK$5)*([2]Hoja2!$K$6:$K$26=$C7))} -> 0 | BL7: {=SUM([2]Hoja2!$J$6:$J$26*([2]Hoja2!$F$6:$F$26=BK$5)*([2]Hoja2!$K$6:$K$26=$C7))} -> 0 | BM7: =IFERROR(BL7/BK7,0) -> 0 | BN7: {=SUM([2]Hoja2!$I$6:$I$26*([2]Hoja2!$F$6:$F$26=BN$5)*([2]Hoja2!$K$6:$K$26=$C7))} -> 0 | BO7: {=SUM([2]Hoja2!$J$6:$J$26*([2]Hoja2!$F$6:$F$26=BN$5)*([2]Hoja2!$K$6:$K$26=$C7))} -> 0 | BP7: =IFERROR(BO7/BN7,0) -> 0 | BQ7: {=SUM([2]Hoja2!$I$6:$I$26*([2]Hoja2!$F$6:$F$26=BQ$5)*([2]Hoja2!$K$6:$K$26=$C7))} -> 0 | BR7: {=SUM([2]Hoja2!$J$6:$J$26*([2]Hoja2!$F$6:$F$26=BQ$5)*([2]Hoja2!$K$6:$K$26=$C7))} -> 0 | BS7: =IFERROR(BR7/BQ7,0) -> 0 | BT7: =X7+AA7+AD7+AG7+AJ7+AM7+AP7+AY7+AS7+AV7 -> 24 | BU7: =Y7+AB7+AE7+AH7+AK7+AN7+AQ7+AZ7+AT7+AW7 -> 48000 | BV7: =IFERROR(BU7/BT7,0) -> 2000 | BW7: =-IFERROR(F7/D7*BT7,0) -> -46501.254 | BX7: =-207.84*BT7 -> -4988.16 | BY7: =$BY$18/$BT$18*$BT7 -> -2143.0636 | BZ7: =$BZ$18/$BT$18*$BT7 -> -4212.9 | CA7: =$CA$18/$BT$18*$BT7 -> -3367.755 | CB7: =(BU7-BT7*$BY$19)*0.03 -> 1357.7921 | CC7: =BU7+SUM(BW7:BZ7,CB7) -> -8487.586 | CD7: =IFERROR(CC7/BU7,0) -> -0.17682471 | CE7: =BU7+BW7+BX7+BY7+CB7-CA7 -> -906.93099 | CF7: =IFERROR(CE7/BU7,0) -> -0.018894396 | CH7: =BV7 -> 2000 | CI7: =IFERROR(BW7/$BT7,0) -> -1937.5523 | CJ7: =IFERROR(BX7/$BT7,0) -> -207.84 | CK7: =IFERROR(BY7/$BT7,0) -> -89.294318 | CL7: =IFERROR(BZ7/$BT7,0) -> -175.5375 | CM7: =IFERROR(CA7/$BT7,0) -> -140.32313 | CN7: =IFERROR(CB7/$BT7,0) -> 56.574672 | CO7: =IFERROR(CC7/$BT7,0) -> -353.64942 | CP7: =IFERROR(CE7/$BT7,0) -> -37.788791 | CQ7: =CP7-CO7 -> 315.86063
B8: 10005779 | C8: POTA NUCAS CONGELADAS | D8: =TD!F5 -> 380.02 | E8: =IFERROR(F8/D8,0) -> 1584.5595 | F8: =TD!G5 -> 602164.3 | G8: =TD!H5 -> 78983.357 | H8: =TD!I5 -> 17143.302 | I8: =TD!J5 -> 33700.827 | J8: =TD!K5 -> 26940.143 | K8: 0 | L8: 0 | M8: =F8+G8+H8+I8 -> 731991.78 | N8: =IFERROR(M8/D8,0) -> 1926.1928 | O8: =F8+G8+H8-J8 -> 671350.81 | P8: =IFERROR(O8/D8,0) -> 1766.6197 | Q8: 1350 | R8: =Q8*D8 -> 513027 | S8: =R8-M8+(Q8-$BY$19)*D8*0.03 -> -204875.66 | T8: =IFERROR(S8/R8,0) -> -0.39934675 | U8: =R8-(M8-J8-I8)+(Q8-$BY$19)*D8*0.03 -> -144234.69 | V8: =IFERROR(U8/R8,0) -> -0.28114445 | X8: {=SUM([5]Hoja3!$I$6:$I$25*([5]Hoja3!$F$6:$F$25=X$5)*([5]Hoja3!$K$6:$K$25=$C8))} -> 0 | Y8: {=SUM([5]Hoja3!$J$6:$J$25*([5]Hoja3!$F$6:$F$25=X$5)*([5]Hoja3!$K$6:$K$25=$C8))} -> 0 | Z8: =IFERROR(Y8/X8,0) -> 0 | AA8: {=SUM([5]Hoja3!$I$6:$I$25*([5]Hoja3!$F$6:$F$25=AA$5)*([5]Hoja3!$K$6:$K$25=$C8))} -> 0 | AB8: {=SUM([5]Hoja3!$J$6:$J$25*([5]Hoja3!$F$6:$F$25=AA$5)*([5]Hoja3!$K$6:$K$25=$C8))} -> 0 | AC8: =IFERROR(AB8/AA8,0) -> 0 | AD8: {=SUM([5]Hoja3!$I$6:$I$25*([5]Hoja3!$F$6:$F$25=AD$5)*([5]Hoja3!$K$6:$K$25=$C8))} -> 0 | AE8: {=SUM([5]Hoja3!$J$6:$J$25*([5]Hoja3!$F$6:$F$25=AD$5)*([5]Hoja3!$K$6:$K$25=$C8))} -> 0 | AF8: =IFERROR(AE8/AD8,0) -> 0 | AG8: {=SUM([5]Hoja3!$I$6:$I$25*([5]Hoja3!$F$6:$F$25=AG$5)*([5]Hoja3!$K$6:$K$25=$C8))} -> 0 | AH8: {=SUM([5]Hoja3!$J$6:$J$25*([5]Hoja3!$F$6:$F$25=AG$5)*([5]Hoja3!$K$6:$K$25=$C8))} -> 0 | AI8: =IFERROR(AH8/AG8,0) -> 0 | AJ8: {=SUM([5]Hoja3!$I$6:$I$25*([5]Hoja3!$F$6:$F$25=AJ$5)*([5]Hoja3!$K$6:$K$25=$C8))} -> 78 | AK8: {=SUM([5]Hoja3!$J$6:$J$25*([5]Hoja3!$F$6:$F$25=AJ$5)*([5]Hoja3!$K$6:$K$25=$C8))} -> 103740 | AL8: =IFERROR(AK8/AJ8,0) -> 1330 | AM8: {=SUM([5]Hoja3!$I$6:$I$25*([5]Hoja3!$F$6:$F$25=AM$5)*([5]Hoja3!$K$6:$K$25=$C8))} -> 0 | AN8: {=SUM([5]Hoja3!$J$6:$J$25*([5]Hoja3!$F$6:$F$25=AM$5)*([5]Hoja3!$K$6:$K$25=$C8))} -> 0 | AO8: =IFERROR(AN8/AM8,0) -> 0 | AP8: {=SUM([5]Hoja3!$I$6:$I$25*([5]Hoja3!$F$6:$F$25=AP$5)*([5]Hoja3!$K$6:$K$25=$C8))} -> 52 | AQ8: {=SUM([5]Hoja3!$J$6:$J$25*([5]Hoja3!$F$6:$F$25=AP$5)*([5]Hoja3!$K$6:$K$25=$C8))} -> 67600 | AR8: =IFERROR(AQ8/AP8,0) -> 1300 | AS8: {=SUM([5]Hoja3!$I$6:$I$25*([5]Hoja3!$F$6:$F$25=AS$5)*([5]Hoja3!$K$6:$K$25=$C8))} -> 0 | AT8: {=SUM([5]Hoja3!$J$6:$J$25*([5]Hoja3!$F$6:$F$25=AS$5)*([5]Hoja3!$K$6:$K$25=$C8))} -> 0 | AU8: =IFERROR(AT8/AS8,0) -> 0 | AV8: {=SUM([5]Hoja3!$I$6:$I$25*([5]Hoja3!$F$6:$F$25=AV$5)*([5]Hoja3!$K$6:$K$25=$C8))} -> 26 | AW8: {=SUM([5]Hoja3!$J$6:$J$25*([5]Hoja3!$F$6:$F$25=AV$5)*([5]Hoja3!$K$6:$K$25=$C8))} -> 34580 | AX8: =IFERROR(AW8/AV8,0) -> 1330 | AY8: {=SUM([5]Hoja3!$I$6:$I$25*([5]Hoja3!$F$6:$F$25=AY$5)*([5]Hoja3!$K$6:$K$25=$C8))} -> 0 | AZ8: {=SUM([5]Hoja3!$J$6:$J$25*([5]Hoja3!$F$6:$F$25=AY$5)*([5]Hoja3!$K$6:$K$25=$C8))} -> 0 | BA8: =IFERROR(AZ8/AY8,0) -> 0 | BB8: {=SUM([2]Hoja2!$I$6:$I$26*([2]Hoja2!$F$6:$F$26=BB$5)*([2]Hoja2!$K$6:$K$26=$C8))} -> 0 | BC8: {=SUM([2]Hoja2!$J$6:$J$26*([2]Hoja2!$F$6:$F$26=BB$5)*([2]Hoja2!$K$6:$K$26=$C8))} -> 0 | BD8: =IFERROR(BC8/BB8,0) -> 0 | BE8: {=SUM([2]Hoja2!$I$6:$I$26*([2]Hoja2!$F$6:$F$26=BE$5)*([2]Hoja2!$K$6:$K$26=$C8))} -> 0 | BF8: {=SUM([2]Hoja2!$J$6:$J$26*([2]Hoja2!$F$6:$F$26=BE$5)*([2]Hoja2!$K$6:$K$26=$C8))} -> 0 | BG8: =IFERROR(BF8/BE8,0) -> 0 | BH8: {=SUM([2]Hoja2!$I$6:$I$26*([2]Hoja2!$F$6:$F$26=BH$5)*([2]Hoja2!$K$6:$K$26=$C8))} -> 0 | BI8: {=SUM([2]Hoja2!$J$6:$J$26*([2]Hoja2!$F$6:$F$26=BH$5)*([2]Hoja2!$K$6:$K$26=$C8))} -> 0 | BJ8: =IFERROR(BI8/BH8,0) -> 0 | BK8: {=SUM([2]Hoja2!$I$6:$I$26*([2]Hoja2!$F$6:$F$26=BK$5)*([2]Hoja2!$K$6:$K$26=$C8))} -> 0 | BL8: {=SUM([2]Hoja2!$J$6:$J$26*([2]Hoja2!$F$6:$F$26=BK$5)*([2]Hoja2!$K$6:$K$26=$C8))} -> 0 | BM8: =IFERROR(BL8/BK8,0) -> 0 | BN8: {=SUM([2]Hoja2!$I$6:$I$26*([2]Hoja2!$F$6:$F$26=BN$5)*([2]Hoja2!$K$6:$K$26=$C8))} -> 0 | BO8: {=SUM([2]Hoja2!$J$6:$J$26*([2]Hoja2!$F$6:$F$26=BN$5)*([2]Hoja2!$K$6:$K$26=$C8))} -> 0 | BP8: =IFERROR(BO8/BN8,0) -> 0 | BQ8: {=SUM([2]Hoja2!$I$6:$I$26*([2]Hoja2!$F$6:$F$26=BQ$5)*([2]Hoja2!$K$6:$K$26=$C8))} -> 0 | BR8: {=SUM([2]Hoja2!$J$6:$J$26*([2]Hoja2!$F$6:$F$26=BQ$5)*([2]Hoja2!$K$6:$K$26=$C8))} -> 0 | BS8: =IFERROR(BR8/BQ8,0) -> 0 | BT8: =X8+AA8+AD8+AG8+AJ8+AM8+AP8+AY8+AS8+AV8 -> 156 | BU8: =Y8+AB8+AE8+AH8+AK8+AN8+AQ8+AZ8+AT8+AW8 -> 205920 | BV8: =IFERROR(BU8/BT8,0) -> 1320 | BW8: =-IFERROR(F8/D8*BT8,0) -> -247191.28 | BX8: =-207.84*BT8 -> -32423.04 | BY8: =$BY$18/$BT$18*$BT8 -> -13929.914 | BZ8: =$BZ$18/$BT$18*$BT8 -> -27383.85 | CA8: =$CA$18/$BT$18*$BT8 -> -21890.408 | CB8: =(BU8-BT8*$BY$19)*0.03 -> 5643.2488 | CC8: =BU8+SUM(BW8:BZ8,CB8) -> -109364.83 | CD8: =IFERROR(CC8/BU8,0) -> -0.53110351 | CE8: =BU8+BW8+BX8+BY8+CB8-CA8 -> -60090.577 | CF8: =IFERROR(CE8/BU8,0) -> -0.29181516 | CH8: =BV8 -> 1320 | CI8: =IFERROR(BW8/$BT8,0) -> -1584.5595 | CJ8: =IFERROR(BX8/$BT8,0) -> -207.84 | CK8: =IFERROR(BY8/$BT8,0) -> -89.294318 | CL8: =IFERROR(BZ8/$BT8,0) -> -175.5375 | CM8: =IFERROR(CA8/$BT8,0) -> -140.32313 | CN8: =IFERROR(CB8/$BT8,0) -> 36.174672 | CO8: =IFERROR(CC8/$BT8,0) -> -701.05663 | CP8: =IFERROR(CE8/$BT8,0) -> -385.19601 | CQ8: =CP8-CO8 -> 315.86062
B9: 10006719 | C9: POTA ALAS CONGELADAS | D9: =TD!F6 -> 539.694 | E9: =IFERROR(F9/D9,0) -> 1835.1853 | F9: =TD!G6 -> 990438.47 | G9: =TD!H6 -> 112170 | H9: =TD!I6 -> 24346.448 | I9: =TD!J6 -> 47860.991 | J9: =TD!K6 -> 38259.653 | K9: 0 | L9: 0 | M9: =F9+G9+H9+I9 -> 1174815.9 | N9: =IFERROR(M9/D9,0) -> 2176.8186 | O9: =F9+G9+H9-J9 -> 1088695.3 | P9: =IFERROR(O9/D9,0) -> 2017.2455 | Q9: 1500 | R9: =Q9*D9 -> 809541 | S9: =R9-M9+(Q9-$BY$19)*D9*0.03 -> -342837.31 | T9: =IFERROR(S9/R9,0) -> -0.42349592 | U9: =R9-(M9-J9-I9)+(Q9-$BY$19)*D9*0.03 -> -256716.67 | V9: =IFERROR(U9/R9,0) -> -0.31711385 | X9: {=SUM([5]Hoja3!$I$6:$I$25*([5]Hoja3!$F$6:$F$25=X$5)*([5]Hoja3!$K$6:$K$25=$C9))} -> 0 | Y9: {=SUM([5]Hoja3!$J$6:$J$25*([5]Hoja3!$F$6:$F$25=X$5)*([5]Hoja3!$K$6:$K$25=$C9))} -> 0 | Z9: =IFERROR(Y9/X9,0) -> 0 | AA9: {=SUM([5]Hoja3!$I$6:$I$25*([5]Hoja3!$F$6:$F$25=AA$5)*([5]Hoja3!$K$6:$K$25=$C9))} -> 0 | AB9: {=SUM([5]Hoja3!$J$6:$J$25*([5]Hoja3!$F$6:$F$25=AA$5)*([5]Hoja3!$K$6:$K$25=$C9))} -> 0 | AC9: =IFERROR(AB9/AA9,0) -> 0 | AD9: {=SUM([5]Hoja3!$I$6:$I$25*([5]Hoja3!$F$6:$F$25=AD$5)*([5]Hoja3!$K$6:$K$25=$C9))} -> 54 | AE9: {=SUM([5]Hoja3!$J$6:$J$25*([5]Hoja3!$F$6:$F$25=AD$5)*([5]Hoja3!$K$6:$K$25=$C9))} -> 94500 | AF9: =IFERROR(AE9/AD9,0) -> 1750 | AG9: {=SUM([5]Hoja3!$I$6:$I$25*([5]Hoja3!$F$6:$F$25=AG$5)*([5]Hoja3!$K$6:$K$25=$C9))} -> 0 | AH9: {=SUM([5]Hoja3!$J$6:$J$25*([5]Hoja3!$F$6:$F$25=AG$5)*([5]Hoja3!$K$6:$K$25=$C9))} -> 0 | AI9: =IFERROR(AH9/AG9,0) -> 0 | AJ9: {=SUM([5]Hoja3!$I$6:$I$25*([5]Hoja3!$F$6:$F$25=AJ$5)*([5]Hoja3!$K$6:$K$25=$C9))} -> 0 | AK9: {=SUM([5]Hoja3!$J$6:$J$25*([5]Hoja3!$F$6:$F$25=AJ$5)*([5]Hoja3!$K$6:$K$25=$C9))} -> 0 | AL9: =IFERROR(AK9/AJ9,0) -> 0 | AM9: {=SUM([5]Hoja3!$I$6:$I$25*([5]Hoja3!$F$6:$F$25=AM$5)*([5]Hoja3!$K$6:$K$25=$C9))} -> 0 | AN9: {=SUM([5]Hoja3!$J$6:$J$25*([5]Hoja3!$F$6:$F$25=AM$5)*([5]Hoja3!$K$6:$K$25=$C9))} -> 0 | AO9: =IFERROR(AN9/AM9,0) -> 0 | AP9: {=SUM([5]Hoja3!$I$6:$I$25*([5]Hoja3!$F$6:$F$25=AP$5)*([5]Hoja3!$K$6:$K$25=$C9))} -> 0 | AQ9: {=SUM([5]Hoja3!$J$6:$J$25*([5]Hoja3!$F$6:$F$25=AP$5)*([5]Hoja3!$K$6:$K$25=$C9))} -> 0 | AR9: =IFERROR(AQ9/AP9,0) -> 0 | AS9: {=SUM([5]Hoja3!$I$6:$I$25*([5]Hoja3!$F$6:$F$25=AS$5)*([5]Hoja3!$K$6:$K$25=$C9))} -> 0 | AT9: {=SUM([5]Hoja3!$J$6:$J$25*([5]Hoja3!$F$6:$F$25=AS$5)*([5]Hoja3!$K$6:$K$25=$C9))} -> 0 | AU9: =IFERROR(AT9/AS9,0) -> 0 | AV9: {=SUM([5]Hoja3!$I$6:$I$25*([5]Hoja3!$F$6:$F$25=AV$5)*([5]Hoja3!$K$6:$K$25=$C9))} -> 0 | AW9: {=SUM([5]Hoja3!$J$6:$J$25*([5]Hoja3!$F$6:$F$25=AV$5)*([5]Hoja3!$K$6:$K$25=$C9))} -> 0 | AX9: =IFERROR(AW9/AV9,0) -> 0 | AY9: {=SUM([5]Hoja3!$I$6:$I$25*([5]Hoja3!$F$6:$F$25=AY$5)*([5]Hoja3!$K$6:$K$25=$C9))} -> 27 | AZ9: {=SUM([5]Hoja3!$J$6:$J$25*([5]Hoja3!$F$6:$F$25=AY$5)*([5]Hoja3!$K$6:$K$25=$C9))} -> 48600 | BA9: =IFERROR(AZ9/AY9,0) -> 1800 | BB9: {=SUM([2]Hoja2!$I$6:$I$26*([2]Hoja2!$F$6:$F$26=BB$5)*([2]Hoja2!$K$6:$K$26=$C9))} -> 0 | BC9: {=SUM([2]Hoja2!$J$6:$J$26*([2]Hoja2!$F$6:$F$26=BB$5)*([2]Hoja2!$K$6:$K$26=$C9))} -> 0 | BD9: =IFERROR(BC9/BB9,0) -> 0 | BE9: {=SUM([2]Hoja2!$I$6:$I$26*([2]Hoja2!$F$6:$F$26=BE$5)*([2]Hoja2!$K$6:$K$26=$C9))} -> 0 | BF9: {=SUM([2]Hoja2!$J$6:$J$26*([2]Hoja2!$F$6:$F$26=BE$5)*([2]Hoja2!$K$6:$K$26=$C9))} -> 0 | BG9: =IFERROR(BF9/BE9,0) -> 0 | BH9: {=SUM([2]Hoja2!$I$6:$I$26*([2]Hoja2!$F$6:$F$26=BH$5)*([2]Hoja2!$K$6:$K$26=$C9))} -> 0 | BI9: {=SUM([2]Hoja2!$J$6:$J$26*([2]Hoja2!$F$6:$F$26=BH$5)*([2]Hoja2!$K$6:$K$26=$C9))} -> 0 | BJ9: =IFERROR(BI9/BH9,0) -> 0 | BK9: {=SUM([2]Hoja2!$I$6:$I$26*([2]Hoja2!$F$6:$F$26=BK$5)*([2]Hoja2!$K$6:$K$26=$C9))} -> 0 | BL9: {=SUM([2]Hoja2!$J$6:$J$26*([2]Hoja2!$F$6:$F$26=BK$5)*([2]Hoja2!$K$6:$K$26=$C9))} -> 0 | BM9: =IFERROR(BL9/BK9,0) -> 0 | BN9: {=SUM([2]Hoja2!$I$6:$I$26*([2]Hoja2!$F$6:$F$26=BN$5)*([2]Hoja2!$K$6:$K$26=$C9))} -> 0 | BO9: {=SUM([2]Hoja2!$J$6:$J$26*([2]Hoja2!$F$6:$F$26=BN$5)*([2]Hoja2!$K$6:$K$26=$C9))} -> 0 | BP9: =IFERROR(BO9/BN9,0) -> 0 | BQ9: {=SUM([2]Hoja2!$I$6:$I$26*([2]Hoja2!$F$6:$F$26=BQ$5)*([2]Hoja2!$K$6:$K$26=$C9))} -> 0 | BR9: {=SUM([2]Hoja2!$J$6:$J$26*([2]Hoja2!$F$6:$F$26=BQ$5)*([2]Hoja2!$K$6:$K$26=$C9))} -> 0 | BS9: =IFERROR(BR9/BQ9,0) -> 0 | BT9: =X9+AA9+AD9+AG9+AJ9+AM9+AP9+AY9+AS9+AV9 -> 81 | BU9: =Y9+AB9+AE9+AH9+AK9+AN9+AQ9+AZ9+AT9+AW9 -> 143100 | BV9: =IFERROR(BU9/BT9,0) -> 1766.6667 | BW9: =-IFERROR(F9/D9*BT9,0) -> -148650.01 | BX9: =-207.84*BT9 -> -16835.04 | BY9: =$BY$18/$BT$18*$BT9 -> -7232.8398 | BZ9: =$BZ$18/$BT$18*$BT9 -> -14218.538 | CA9: =$CA$18/$BT$18*$BT9 -> -11366.173 | CB9: =(BU9-BT9*$BY$19)*0.03 -> 4015.5484 | CC9: =BU9+SUM(BW9:BZ9,CB9) -> -39820.874 | CD9: =IFERROR(CC9/BU9,0) -> -0.27827306 | CE9: =BU9+BW9+BX9+BY9+CB9-CA9 -> -14236.164 | CF9: =IFERROR(CE9/BU9,0) -> -0.099484024 | CH9: =BV9 -> 1766.6667 | CI9: =IFERROR(BW9/$BT9,0) -> -1835.1853 | CJ9: =IFERROR(BX9/$BT9,0) -> -207.84 | CK9: =IFERROR(BY9/$BT9,0) -> -89.294318 | CL9: =IFERROR(BZ9/$BT9,0) -> -175.5375 | CM9: =IFERROR(CA9/$BT9,0) -> -140.32313 | CN9: =IFERROR(CB9/$BT9,0) -> 49.574672 | CO9: =IFERROR(CC9/$BT9,0) -> -491.61573 | CP9: =IFERROR(CE9/$BT9,0) -> -175.75511 | CQ9: =CP9-CO9 -> 315.86063
B10: 10007050 | C10: POTA RECORTES COCIDOS | D10: =TD!F7 -> 11.695 | E10: =IFERROR(F10/D10,0) -> 1408.8571 | F10: =TD!G7 -> 16476.584 | G10: =TD!H7 -> 2430.6888 | H10: =TD!I7 -> 527.5799 | I10: =TD!J7 -> 1037.1327 | J10: =TD!K7 -> 829.0747 | K10: 0 | L10: 0 | M10: =F10+G10+H10+I10 -> 20471.985 | N10: =IFERROR(M10/D10,0) -> 1750.4904 | O10: =F10+G10+H10-J10 -> 18605.778 | P10: =IFERROR(O10/D10,0) -> 1590.9173 | Q10: 1700 | R10: =Q10*D10 -> 19881.5 | S10: =R10-M10+(Q10-$BY$19)*D10*0.03 -> -34.099673 | T10: =IFERROR(S10/R10,0) -> -0.0017151459 | U10: =R10-(M10-J10-I10)+(Q10-$BY$19)*D10*0.03 -> 1832.1077 | V10: =IFERROR(U10/R10,0) -> 0.092151383 | X10: {=SUM([5]Hoja3!$I$6:$I$25*([5]Hoja3!$F$6:$F$25=X$5)*([5]Hoja3!$K$6:$K$25=$C10))} -> 27 | Y10: {=SUM([5]Hoja3!$J$6:$J$25*([5]Hoja3!$F$6:$F$25=X$5)*([5]Hoja3!$K$6:$K$25=$C10))} -> 68850 | Z10: =IFERROR(Y10/X10,0) -> 2550 | AA10: {=SUM([5]Hoja3!$I$6:$I$25*([5]Hoja3!$F$6:$F$25=AA$5)*([5]Hoja3!$K$6:$K$25=$C10))} -> 0 | AB10: {=SUM([5]Hoja3!$J$6:$J$25*([5]Hoja3!$F$6:$F$25=AA$5)*([5]Hoja3!$K$6:$K$25=$C10))} -> 0 | AC10: =IFERROR(AB10/AA10,0) -> 0 | AD10: {=SUM([5]Hoja3!$I$6:$I$25*([5]Hoja3!$F$6:$F$25=AD$5)*([5]Hoja3!$K$6:$K$25=$C10))} -> 0 | AE10: {=SUM([5]Hoja3!$J$6:$J$25*([5]Hoja3!$F$6:$F$25=AD$5)*([5]Hoja3!$K$6:$K$25=$C10))} -> 0 | AF10: =IFERROR(AE10/AD10,0) -> 0 | AG10: {=SUM([5]Hoja3!$I$6:$I$25*([5]Hoja3!$F$6:$F$25=AG$5)*([5]Hoja3!$K$6:$K$25=$C10))} -> 0 | AH10: {=SUM([5]Hoja3!$J$6:$J$25*([5]Hoja3!$F$6:$F$25=AG$5)*([5]Hoja3!$K$6:$K$25=$C10))} -> 0 | AI10: =IFERROR(AH10/AG10,0) -> 0 | AJ10: {=SUM([5]Hoja3!$I$6:$I$25*([5]Hoja3!$F$6:$F$25=AJ$5)*([5]Hoja3!$K$6:$K$25=$C10))} -> 0 | AK10: {=SUM([5]Hoja3!$J$6:$J$25*([5]Hoja3!$F$6:$F$25=AJ$5)*([5]Hoja3!$K$6:$K$25=$C10))} -> 0 | AL10: =IFERROR(AK10/AJ10,0) -> 0 | AM10: {=SUM([5]Hoja3!$I$6:$I$25*([5]Hoja3!$F$6:$F$25=AM$5)*([5]Hoja3!$K$6:$K$25=$C10))} -> 0 | AN10: {=SUM([5]Hoja3!$J$6:$J$25*([5]Hoja3!$F$6:$F$25=AM$5)*([5]Hoja3!$K$6:$K$25=$C10))} -> 0 | AO10: =IFERROR(AN10/AM10,0) -> 0 | AP10: {=SUM([5]Hoja3!$I$6:$I$25*([5]Hoja3!$F$6:$F$25=AP$5)*([5]Hoja3!$K$6:$K$25=$C10))} -> 0 | AQ10: {=SUM([5]Hoja3!$J$6:$J$25*([5]Hoja3!$F$6:$F$25=AP$5)*([5]Hoja3!$K$6:$K$25=$C10))} -> 0 | AR10: =IFERROR(AQ10/AP10,0) -> 0 | AS10: {=SUM([5]Hoja3!$I$6:$I$25*([5]Hoja3!$F$6:$F$25=AS$5)*([5]Hoja3!$K$6:$K$25=$C10))} -> 0 | AT10: {=SUM([5]Hoja3!$J$6:$J$25*([5]Hoja3!$F$6:$F$25=AS$5)*([5]Hoja3!$K$6:$K$25=$C10))} -> 0 | AU10: =IFERROR(AT10/AS10,0) -> 0 | AV10: {=SUM([5]Hoja3!$I$6:$I$25*([5]Hoja3!$F$6:$F$25=AV$5)*([5]Hoja3!$K$6:$K$25=$C10))} -> 0 | AW10: {=SUM([5]Hoja3!$J$6:$J$25*([5]Hoja3!$F$6:$F$25=AV$5)*([5]Hoja3!$K$6:$K$25=$C10))} -> 0 | AX10: =IFERROR(AW10/AV10,0) -> 0 | AY10: {=SUM([5]Hoja3!$I$6:$I$25*([5]Hoja3!$F$6:$F$25=AY$5)*([5]Hoja3!$K$6:$K$25=$C10))} -> 0 | AZ10: {=SUM([5]Hoja3!$J$6:$J$25*([5]Hoja3!$F$6:$F$25=AY$5)*([5]Hoja3!$K$6:$K$25=$C10))} -> 0 | BA10: =IFERROR(AZ10/AY10,0) -> 0 | BB10: {=SUM([2]Hoja2!$I$6:$I$26*([2]Hoja2!$F$6:$F$26=BB$5)*([2]Hoja2!$K$6:$K$26=$C10))} -> 0 | BC10: {=SUM([2]Hoja2!$J$6:$J$26*([2]Hoja2!$F$6:$F$26=BB$5)*([2]Hoja2!$K$6:$K$26=$C10))} -> 0 | BD10: =IFERROR(BC10/BB10,0) -> 0 | BE10: {=SUM([2]Hoja2!$I$6:$I$26*([2]Hoja2!$F$6:$F$26=BE$5)*([2]Hoja2!$K$6:$K$26=$C10))} -> 0 | BF10: {=SUM([2]Hoja2!$J$6:$J$26*([2]Hoja2!$F$6:$F$26=BE$5)*([2]Hoja2!$K$6:$K$26=$C10))} -> 0 | BG10: =IFERROR(BF10/BE10,0) -> 0 | BH10: {=SUM([2]Hoja2!$I$6:$I$26*([2]Hoja2!$F$6:$F$26=BH$5)*([2]Hoja2!$K$6:$K$26=$C10))} -> 0 | BI10: {=SUM([2]Hoja2!$J$6:$J$26*([2]Hoja2!$F$6:$F$26=BH$5)*([2]Hoja2!$K$6:$K$26=$C10))} -> 0 | BJ10: =IFERROR(BI10/BH10,0) -> 0 | BK10: {=SUM([2]Hoja2!$I$6:$I$26*([2]Hoja2!$F$6:$F$26=BK$5)*([2]Hoja2!$K$6:$K$26=$C10))} -> 0 | BL10: {=SUM([2]Hoja2!$J$6:$J$26*([2]Hoja2!$F$6:$F$26=BK$5)*([2]Hoja2!$K$6:$K$26=$C10))} -> 0 | BM10: =IFERROR(BL10/BK10,0) -> 0 | BN10: {=SUM([2]Hoja2!$I$6:$I$26*([2]Hoja2!$F$6:$F$26=BN$5)*([2]Hoja2!$K$6:$K$26=$C10))} -> 0 | BO10: {=SUM([2]Hoja2!$J$6:$J$26*([2]Hoja2!$F$6:$F$26=BN$5)*([2]Hoja2!$K$6:$K$26=$C10))} -> 0 | BP10: =IFERROR(BO10/BN10,0) -> 0 | BQ10: {=SUM([2]Hoja2!$I$6:$I$26*([2]Hoja2!$F$6:$F$26=BQ$5)*([2]Hoja2!$K$6:$K$26=$C10))} -> 0 | BR10: {=SUM([2]Hoja2!$J$6:$J$26*([2]Hoja2!$F$6:$F$26=BQ$5)*([2]Hoja2!$K$6:$K$26=$C10))} -> 0 | BS10: =IFERROR(BR10/BQ10,0) -> 0 | BT10: =X10+AA10+AD10+AG10+AJ10+AM10+AP10+AY10+AS10+AV10 -> 27 | BU10: =Y10+AB10+AE10+AH10+AK10+AN10+AQ10+AZ10+AT10+AW10 -> 68850 | BV10: =IFERROR(BU10/BT10,0) -> 2550 | BW10: =-IFERROR(F10/D10*BT10,0) -> -38039.142 | BX10: =-207.84*BT10 -> -5611.68 | BY10: =$BY$18/$BT$18*$BT10 -> -2410.9466 | BZ10: =$BZ$18/$BT$18*$BT10 -> -4739.5125 | CA10: =$CA$18/$BT$18*$BT10 -> -3788.7244 | CB10: =(BU10-BT10*$BY$19)*0.03 -> 1973.0161 | CC10: =BU10+SUM(BW10:BZ10,CB10) -> 20021.735 | CD10: =IFERROR(CC10/BU10,0) -> 0.29080225 | CE10: =BU10+BW10+BX10+BY10+CB10-CA10 -> 28549.972 | CF10: =IFERROR(CE10/BU10,0) -> 0.41466916 | CH10: =BV10 -> 2550 | CI10: =IFERROR(BW10/$BT10,0) -> -1408.8571 | CJ10: =IFERROR(BX10/$BT10,0) -> -207.84 | CK10: =IFERROR(BY10/$BT10,0) -> -89.294318 | CL10: =IFERROR(BZ10/$BT10,0) -> -175.5375 | CM10: =IFERROR(CA10/$BT10,0) -> -140.32313 | CN10: =IFERROR(CB10/$BT10,0) -> 73.074672 | CO10: =IFERROR(CC10/$BT10,0) -> 741.54573 | CP10: =IFERROR(CE10/$BT10,0) -> 1057.4064 | CQ10: =CP10-CO10 -> 315.86063
B11: 10007162 | C11: POTA REJOS CONGELADOS | D11: =TD!F8 -> 171 | E11: =IFERROR(F11/D11,0) -> 1698.6478 | F11: =TD!G8 -> 290468.78 | G11: =TD!H8 -> 35540.64 | H11: =TD!I8 -> 7714.0798 | I11: =TD!J8 -> 15164.574 | J11: =TD!K8 -> 12122.426 | K11: 0 | L11: 0 | M11: =F11+G11+H11+I11 -> 348888.07 | N11: =IFERROR(M11/D11,0) -> 2040.2811 | O11: =F11+G11+H11-J11 -> 321601.07 | P11: =IFERROR(O11/D11,0) -> 1880.708 | Q11: 2700 | R11: =Q11*D11 -> 461700 | S11: =R11-M11+(Q11-$BY$19)*D11*0.03 -> 126077.19 | T11: =IFERROR(S11/R11,0) -> 0.27307168 | U11: =R11-(M11-J11-I11)+(Q11-$BY$19)*D11*0.03 -> 153364.19 | V11: =IFERROR(U11/R11,0) -> 0.33217283 | X11: {=SUM([5]Hoja3!$I$6:$I$25*([5]Hoja3!$F$6:$F$25=X$5)*([5]Hoja3!$K$6:$K$25=$C11))} -> 0 | Y11: {=SUM([5]Hoja3!$J$6:$J$25*([5]Hoja3!$F$6:$F$25=X$5)*([5]Hoja3!$K$6:$K$25=$C11))} -> 0 | Z11: =IFERROR(Y11/X11,0) -> 0 | AA11: {=SUM([5]Hoja3!$I$6:$I$25*([5]Hoja3!$F$6:$F$25=AA$5)*([5]Hoja3!$K$6:$K$25=$C11))} -> 0 | AB11: {=SUM([5]Hoja3!$J$6:$J$25*([5]Hoja3!$F$6:$F$25=AA$5)*([5]Hoja3!$K$6:$K$25=$C11))} -> 0 | AC11: =IFERROR(AB11/AA11,0) -> 0 | AD11: {=SUM([5]Hoja3!$I$6:$I$25*([5]Hoja3!$F$6:$F$25=AD$5)*([5]Hoja3!$K$6:$K$25=$C11))} -> 108 | AE11: {=SUM([5]Hoja3!$J$6:$J$25*([5]Hoja3!$F$6:$F$25=AD$5)*([5]Hoja3!$K$6:$K$25=$C11))} -> 275400 | AF11: =IFERROR(AE11/AD11,0) -> 2550 | AG11: {=SUM([5]Hoja3!$I$6:$I$25*([5]Hoja3!$F$6:$F$25=AG$5)*([5]Hoja3!$K$6:$K$25=$C11))} -> 0 | AH11: {=SUM([5]Hoja3!$J$6:$J$25*([5]Hoja3!$F$6:$F$25=AG$5)*([5]Hoja3!$K$6:$K$25=$C11))} -> 0 | AI11: =IFERROR(AH11/AG11,0) -> 0 | AJ11: {=SUM([5]Hoja3!$I$6:$I$25*([5]Hoja3!$F$6:$F$25=AJ$5)*([5]Hoja3!$K$6:$K$25=$C11))} -> 0 | AK11: {=SUM([5]Hoja3!$J$6:$J$25*([5]Hoja3!$F$6:$F$25=AJ$5)*([5]Hoja3!$K$6:$K$25=$C11))} -> 0 | AL11: =IFERROR(AK11/AJ11,0) -> 0 | AM11: {=SUM([5]Hoja3!$I$6:$I$25*([5]Hoja3!$F$6:$F$25=AM$5)*([5]Hoja3!$K$6:$K$25=$C11))} -> 0 | AN11: {=SUM([5]Hoja3!$J$6:$J$25*([5]Hoja3!$F$6:$F$25=AM$5)*([5]Hoja3!$K$6:$K$25=$C11))} -> 0 | AO11: =IFERROR(AN11/AM11,0) -> 0 | AP11: {=SUM([5]Hoja3!$I$6:$I$25*([5]Hoja3!$F$6:$F$25=AP$5)*([5]Hoja3!$K$6:$K$25=$C11))} -> 0 | AQ11: {=SUM([5]Hoja3!$J$6:$J$25*([5]Hoja3!$F$6:$F$25=AP$5)*([5]Hoja3!$K$6:$K$25=$C11))} -> 0 | AR11: =IFERROR(AQ11/AP11,0) -> 0 | AS11: {=SUM([5]Hoja3!$I$6:$I$25*([5]Hoja3!$F$6:$F$25=AS$5)*([5]Hoja3!$K$6:$K$25=$C11))} -> 27 | AT11: {=SUM([5]Hoja3!$J$6:$J$25*([5]Hoja3!$F$6:$F$25=AS$5)*([5]Hoja3!$K$6:$K$25=$C11))} -> 81000 | AU11: =IFERROR(AT11/AS11,0) -> 3000 | AV11: {=SUM([5]Hoja3!$I$6:$I$25*([5]Hoja3!$F$6:$F$25=AV$5)*([5]Hoja3!$K$6:$K$25=$C11))} -> 0 | AW11: {=SUM([5]Hoja3!$J$6:$J$25*([5]Hoja3!$F$6:$F$25=AV$5)*([5]Hoja3!$K$6:$K$25=$C11))} -> 0 | AX11: =IFERROR(AW11/AV11,0) -> 0 | AY11: {=SUM([5]Hoja3!$I$6:$I$25*([5]Hoja3!$F$6:$F$25=AY$5)*([5]Hoja3!$K$6:$K$25=$C11))} -> 108 | AZ11: {=SUM([5]Hoja3!$J$6:$J$25*([5]Hoja3!$F$6:$F$25=AY$5)*([5]Hoja3!$K$6:$K$25=$C11))} -> 293910 | BA11: =IFERROR(AZ11/AY11,0) -> 2721.3889 | BB11: {=SUM([2]Hoja2!$I$6:$I$26*([2]Hoja2!$F$6:$F$26=BB$5)*([2]Hoja2!$K$6:$K$26=$C11))} -> 0 | BC11: {=SUM([2]Hoja2!$J$6:$J$26*([2]Hoja2!$F$6:$F$26=BB$5)*([2]Hoja2!$K$6:$K$26=$C11))} -> 0 | BD11: =IFERROR(BC11/BB11,0) -> 0 | BE11: {=SUM([2]Hoja2!$I$6:$I$26*([2]Hoja2!$F$6:$F$26=BE$5)*([2]Hoja2!$K$6:$K$26=$C11))} -> 0 | BF11: {=SUM([2]Hoja2!$J$6:$J$26*([2]Hoja2!$F$6:$F$26=BE$5)*([2]Hoja2!$K$6:$K$26=$C11))} -> 0 | BG11: =IFERROR(BF11/BE11,0) -> 0 | BH11: {=SUM([2]Hoja2!$I$6:$I$26*([2]Hoja2!$F$6:$F$26=BH$5)*([2]Hoja2!$K$6:$K$26=$C11))} -> 0 | BI11: {=SUM([2]Hoja2!$J$6:$J$26*([2]Hoja2!$F$6:$F$26=BH$5)*([2]Hoja2!$K$6:$K$26=$C11))} -> 0 | BJ11: =IFERROR(BI11/BH11,0) -> 0 | BK11: {=SUM([2]Hoja2!$I$6:$I$26*([2]Hoja2!$F$6:$F$26=BK$5)*([2]Hoja2!$K$6:$K$26=$C11))} -> 0 | BL11: {=SUM([2]Hoja2!$J$6:$J$26*([2]Hoja2!$F$6:$F$26=BK$5)*([2]Hoja2!$K$6:$K$26=$C11))} -> 0 | BM11: =IFERROR(BL11/BK11,0) -> 0 | BN11: {=SUM([2]Hoja2!$I$6:$I$26*([2]Hoja2!$F$6:$F$26=BN$5)*([2]Hoja2!$K$6:$K$26=$C11))} -> 0 | BO11: {=SUM([2]Hoja2!$J$6:$J$26*([2]Hoja2!$F$6:$F$26=BN$5)*([2]Hoja2!$K$6:$K$26=$C11))} -> 0 | BP11: =IFERROR(BO11/BN11,0) -> 0 | BQ11: {=SUM([2]Hoja2!$I$6:$I$26*([2]Hoja2!$F$6:$F$26=BQ$5)*([2]Hoja2!$K$6:$K$26=$C11))} -> 0 | BR11: {=SUM([2]Hoja2!$J$6:$J$26*([2]Hoja2!$F$6:$F$26=BQ$5)*([2]Hoja2!$K$6:$K$26=$C11))} -> 0 | BS11: =IFERROR(BR11/BQ11,0) -> 0 | BT11: =X11+AA11+AD11+AG11+AJ11+AM11+AP11+AY11+AS11+AV11 -> 243 | BU11: =Y11+AB11+AE11+AH11+AK11+AN11+AQ11+AZ11+AT11+AW11 -> 650310 | BV11: =IFERROR(BU11/BT11,0) -> 2676.1728 | BW11: =-IFERROR(F11/D11*BT11,0) -> -412771.43 | BX11: =-207.84*BT11 -> -50505.12 | BY11: =$BY$18/$BT$18*$BT11 -> -21698.519 | BZ11: =$BZ$18/$BT$18*$BT11 -> -42655.612 | CA11: =$CA$18/$BT$18*$BT11 -> -34098.519 | CB11: =(BU11-BT11*$BY$19)*0.03 -> 18676.945 | CC11: =BU11+SUM(BW11:BZ11,CB11) -> 141356.27 | CD11: =IFERROR(CC11/BU11,0) -> 0.21736751 | CE11: =BU11+BW11+BX11+BY11+CB11-CA11 -> 218110.4 | CF11: =IFERROR(CE11/BU11,0) -> 0.3353945 | CH11: =BV11 -> 2676.1728 | CI11: =IFERROR(BW11/$BT11,0) -> -1698.6478 | CJ11: =IFERROR(BX11/$BT11,0) -> -207.84 | CK11: =IFERROR(BY11/$BT11,0) -> -89.294318 | CL11: =IFERROR(BZ11/$BT11,0) -> -175.5375 | CM11: =IFERROR(CA11/$BT11,0) -> -140.32313 | CN11: =IFERROR(CB11/$BT11,0) -> 76.859857 | CO11: =IFERROR(CC11/$BT11,0) -> 581.71304 | CP11: =IFERROR(CE11/$BT11,0) -> 897.57366 | CQ11: =CP11-CO11 -> 315.86063
B12: 10007567 | C12: POTA REPRODUCTORES | D12: =TD!F9 -> 108.54 | E12: =IFERROR(F12/D12,0) -> 1641.9707 | F12: =TD!G9 -> 178219.5 | G12: =TD!H9 -> 22558.954 | H12: =TD!I9 -> 4896.4106 | I12: =TD!J9 -> 9625.5137 | J12: =TD!K9 -> 7694.5505 | K12: 0 | L12: 0 | M12: =F12+G12+H12+I12 -> 215300.38 | N12: =IFERROR(M12/D12,0) -> 1983.604 | O12: =F12+G12+H12-J12 -> 197980.32 | P12: =IFERROR(O12/D12,0) -> 1824.0309 | Q12: 2730 | R12: =Q12*D12 -> 296314.2 | S12: =R12-M12+(Q12-$BY$19)*D12*0.03 -> 89531.461 | T12: =IFERROR(S12/R12,0) -> 0.30215042 | U12: =R12-(M12-J12-I12)+(Q12-$BY$19)*D12*0.03 -> 106851.52 | V12: =IFERROR(U12/R12,0) -> 0.36060211 | X12: {=SUM([5]Hoja3!$I$6:$I$25*([5]Hoja3!$F$6:$F$25=X$5)*([5]Hoja3!$K$6:$K$25=$C12))} -> 0 | Y12: {=SUM([5]Hoja3!$J$6:$J$25*([5]Hoja3!$F$6:$F$25=X$5)*([5]Hoja3!$K$6:$K$25=$C12))} -> 0 | Z12: =IFERROR(Y12/X12,0) -> 0 | AA12: {=SUM([5]Hoja3!$I$6:$I$25*([5]Hoja3!$F$6:$F$25=AA$5)*([5]Hoja3!$K$6:$K$25=$C12))} -> 26 | AB12: {=SUM([5]Hoja3!$J$6:$J$25*([5]Hoja3!$F$6:$F$25=AA$5)*([5]Hoja3!$K$6:$K$25=$C12))} -> 74100 | AC12: =IFERROR(AB12/AA12,0) -> 2850 | AD12: {=SUM([5]Hoja3!$I$6:$I$25*([5]Hoja3!$F$6:$F$25=AD$5)*([5]Hoja3!$K$6:$K$25=$C12))} -> 0 | AE12: {=SUM([5]Hoja3!$J$6:$J$25*([5]Hoja3!$F$6:$F$25=AD$5)*([5]Hoja3!$K$6:$K$25=$C12))} -> 0 | AF12: =IFERROR(AE12/AD12,0) -> 0 | AG12: {=SUM([5]Hoja3!$I$6:$I$25*([5]Hoja3!$F$6:$F$25=AG$5)*([5]Hoja3!$K$6:$K$25=$C12))} -> 26 | AH12: {=SUM([5]Hoja3!$J$6:$J$25*([5]Hoja3!$F$6:$F$25=AG$5)*([5]Hoja3!$K$6:$K$25=$C12))} -> 70980 | AI12: =IFERROR(AH12/AG12,0) -> 2730 | AJ12: {=SUM([5]Hoja3!$I$6:$I$25*([5]Hoja3!$F$6:$F$25=AJ$5)*([5]Hoja3!$K$6:$K$25=$C12))} -> 0 | AK12: {=SUM([5]Hoja3!$J$6:$J$25*([5]Hoja3!$F$6:$F$25=AJ$5)*([5]Hoja3!$K$6:$K$25=$C12))} -> 0 | AL12: =IFERROR(AK12/AJ12,0) -> 0 | AM12: {=SUM([5]Hoja3!$I$6:$I$25*([5]Hoja3!$F$6:$F$25=AM$5)*([5]Hoja3!$K$6:$K$25=$C12))} -> 0 | AN12: {=SUM([5]Hoja3!$J$6:$J$25*([5]Hoja3!$F$6:$F$25=AM$5)*([5]Hoja3!$K$6:$K$25=$C12))} -> 0 | AO12: =IFERROR(AN12/AM12,0) -> 0 | AP12: {=SUM([5]Hoja3!$I$6:$I$25*([5]Hoja3!$F$6:$F$25=AP$5)*([5]Hoja3!$K$6:$K$25=$C12))} -> 27 | AQ12: {=SUM([5]Hoja3!$J$6:$J$25*([5]Hoja3!$F$6:$F$25=AP$5)*([5]Hoja3!$K$6:$K$25=$C12))} -> 72360 | AR12: =IFERROR(AQ12/AP12,0) -> 2680 | AS12: {=SUM([5]Hoja3!$I$6:$I$25*([5]Hoja3!$F$6:$F$25=AS$5)*([5]Hoja3!$K$6:$K$25=$C12))} -> 0 | AT12: {=SUM([5]Hoja3!$J$6:$J$25*([5]Hoja3!$F$6:$F$25=AS$5)*([5]Hoja3!$K$6:$K$25=$C12))} -> 0 | AU12: =IFERROR(AT12/AS12,0) -> 0 | AV12: {=SUM([5]Hoja3!$I$6:$I$25*([5]Hoja3!$F$6:$F$25=AV$5)*([5]Hoja3!$K$6:$K$25=$C12))} -> 0 | AW12: {=SUM([5]Hoja3!$J$6:$J$25*([5]Hoja3!$F$6:$F$25=AV$5)*([5]Hoja3!$K$6:$K$25=$C12))} -> 0 | AX12: =IFERROR(AW12/AV12,0) -> 0 | AY12: {=SUM([5]Hoja3!$I$6:$I$25*([5]Hoja3!$F$6:$F$25=AY$5)*([5]Hoja3!$K$6:$K$25=$C12))} -> 0 | AZ12: {=SUM([5]Hoja3!$J$6:$J$25*([5]Hoja3!$F$6:$F$25=AY$5)*([5]Hoja3!$K$6:$K$25=$C12))} -> 0 | BA12: =IFERROR(AZ12/AY12,0) -> 0 | BB12: {=SUM([2]Hoja2!$I$6:$I$26*([2]Hoja2!$F$6:$F$26=BB$5)*([2]Hoja2!$K$6:$K$26=$C12))} -> 0 | BC12: {=SUM([2]Hoja2!$J$6:$J$26*([2]Hoja2!$F$6:$F$26=BB$5)*([2]Hoja2!$K$6:$K$26=$C12))} -> 0 | BD12: =IFERROR(BC12/BB12,0) -> 0 | BE12: {=SUM([2]Hoja2!$I$6:$I$26*([2]Hoja2!$F$6:$F$26=BE$5)*([2]Hoja2!$K$6:$K$26=$C12))} -> 0 | BF12: {=SUM([2]Hoja2!$J$6:$J$26*([2]Hoja2!$F$6:$F$26=BE$5)*([2]Hoja2!$K$6:$K$26=$C12))} -> 0 | BG12: =IFERROR(BF12/BE12,0) -> 0 | BH12: {=SUM([2]Hoja2!$I$6:$I$26*([2]Hoja2!$F$6:$F$26=BH$5)*([2]Hoja2!$K$6:$K$26=$C12))} -> 0 | BI12: {=SUM([2]Hoja2!$J$6:$J$26*([2]Hoja2!$F$6:$F$26=BH$5)*([2]Hoja2!$K$6:$K$26=$C12))} -> 0 | BJ12: =IFERROR(BI12/BH12,0) -> 0 | BK12: {=SUM([2]Hoja2!$I$6:$I$26*([2]Hoja2!$F$6:$F$26=BK$5)*([2]Hoja2!$K$6:$K$26=$C12))} -> 0 | BL12: {=SUM([2]Hoja2!$J$6:$J$26*([2]Hoja2!$F$6:$F$26=BK$5)*([2]Hoja2!$K$6:$K$26=$C12))} -> 0 | BM12: =IFERROR(BL12/BK12,0) -> 0 | BN12: {=SUM([2]Hoja2!$I$6:$I$26*([2]Hoja2!$F$6:$F$26=BN$5)*([2]Hoja2!$K$6:$K$26=$C12))} -> 0 | BO12: {=SUM([2]Hoja2!$J$6:$J$26*([2]Hoja2!$F$6:$F$26=BN$5)*([2]Hoja2!$K$6:$K$26=$C12))} -> 0 | BP12: =IFERROR(BO12/BN12,0) -> 0 | BQ12: {=SUM([2]Hoja2!$I$6:$I$26*([2]Hoja2!$F$6:$F$26=BQ$5)*([2]Hoja2!$K$6:$K$26=$C12))} -> 0 | BR12: {=SUM([2]Hoja2!$J$6:$J$26*([2]Hoja2!$F$6:$F$26=BQ$5)*([2]Hoja2!$K$6:$K$26=$C12))} -> 0 | BS12: =IFERROR(BR12/BQ12,0) -> 0 | BT12: =X12+AA12+AD12+AG12+AJ12+AM12+AP12+AY12+AS12+AV12 -> 79 | BU12: =Y12+AB12+AE12+AH12+AK12+AN12+AQ12+AZ12+AT12+AW12 -> 217440 | BV12: =IFERROR(BU12/BT12,0) -> 2752.4051 | BW12: =-IFERROR(F12/D12*BT12,0) -> -129715.69 | BX12: =-207.84*BT12 -> -16419.36 | BY12: =$BY$18/$BT$18*$BT12 -> -7054.2511 | BZ12: =$BZ$18/$BT$18*$BT12 -> -13867.462 | CA12: =$CA$18/$BT$18*$BT12 -> -11085.527 | CB12: =(BU12-BT12*$BY$19)*0.03 -> 6252.5991 | CC12: =BU12+SUM(BW12:BZ12,CB12) -> 56635.838 | CD12: =IFERROR(CC12/BU12,0) -> 0.26046651 | CE12: =BU12+BW12+BX12+BY12+CB12-CA12 -> 81588.828 | CF12: =IFERROR(CE12/BU12,0) -> 0.37522456 | CH12: =BV12 -> 2752.4051 | CI12: =IFERROR(BW12/$BT12,0) -> -1641.9707 | CJ12: =IFERROR(BX12/$BT12,0) -> -207.84 | CK12: =IFERROR(BY12/$BT12,0) -> -89.294318 | CL12: =IFERROR(BZ12/$BT12,0) -> -175.5375 | CM12: =IFERROR(CA12/$BT12,0) -> -140.32313 | CN12: =IFERROR(CB12/$BT12,0) -> 79.146823 | CO12: =IFERROR(CC12/$BT12,0) -> 716.90935 | CP12: =IFERROR(CE12/$BT12,0) -> 1032.77 | CQ12: =CP12-CO12 -> 315.86063
B13: 10007969 | C13: POTA CONOS | D13: =TD!F10 -> 4.02 | E13: =IFERROR(F13/D13,0) -> 1333.6378 | F13: =TD!G10 -> 5361.2241 | G13: =TD!H10 -> 835.5168 | H13: =TD!I10 -> 181.34854 | I13: =TD!J10 -> 356.50051 | J13: =TD!K10 -> 284.98335 | K13: 0 | L13: 0 | M13: =F13+G13+H13+I13 -> 6734.59 | N13: =IFERROR(M13/D13,0) -> 1675.2711 | O13: =F13+G13+H13-J13 -> 6093.1061 | P13: =IFERROR(O13/D13,0) -> 1515.698 | Q13: 1600 | R13: =Q13*D13 -> 6432 | S13: =R13-M13+(Q13-$BY$19)*D13*0.03 -> -123.3998 | T13: =IFERROR(S13/R13,0) -> -0.019185293 | U13: =R13-(M13-J13-I13)+(Q13-$BY$19)*D13*0.03 -> 518.08405 | V13: =IFERROR(U13/R13,0) -> 0.080547894 | X13: {=SUM([5]Hoja3!$I$6:$I$25*([5]Hoja3!$F$6:$F$25=X$5)*([5]Hoja3!$K$6:$K$25=$C13))} -> 0 | Y13: {=SUM([5]Hoja3!$J$6:$J$25*([5]Hoja3!$F$6:$F$25=X$5)*([5]Hoja3!$K$6:$K$25=$C13))} -> 0 | Z13: =IFERROR(Y13/X13,0) -> 0 | AA13: {=SUM([5]Hoja3!$I$6:$I$25*([5]Hoja3!$F$6:$F$25=AA$5)*([5]Hoja3!$K$6:$K$25=$C13))} -> 0 | AB13: {=SUM([5]Hoja3!$J$6:$J$25*([5]Hoja3!$F$6:$F$25=AA$5)*([5]Hoja3!$K$6:$K$25=$C13))} -> 0 | AC13: =IFERROR(AB13/AA13,0) -> 0 | AD13: {=SUM([5]Hoja3!$I$6:$I$25*([5]Hoja3!$F$6:$F$25=AD$5)*([5]Hoja3!$K$6:$K$25=$C13))} -> 54 | AE13: {=SUM([5]Hoja3!$J$6:$J$25*([5]Hoja3!$F$6:$F$25=AD$5)*([5]Hoja3!$K$6:$K$25=$C13))} -> 86400 | AF13: =IFERROR(AE13/AD13,0) -> 1600 | AG13: {=SUM([5]Hoja3!$I$6:$I$25*([5]Hoja3!$F$6:$F$25=AG$5)*([5]Hoja3!$K$6:$K$25=$C13))} -> 0 | AH13: {=SUM([5]Hoja3!$J$6:$J$25*([5]Hoja3!$F$6:$F$25=AG$5)*([5]Hoja3!$K$6:$K$25=$C13))} -> 0 | AI13: =IFERROR(AH13/AG13,0) -> 0 | AJ13: {=SUM([5]Hoja3!$I$6:$I$25*([5]Hoja3!$F$6:$F$25=AJ$5)*([5]Hoja3!$K$6:$K$25=$C13))} -> 0 | AK13: {=SUM([5]Hoja3!$J$6:$J$25*([5]Hoja3!$F$6:$F$25=AJ$5)*([5]Hoja3!$K$6:$K$25=$C13))} -> 0 | AL13: =IFERROR(AK13/AJ13,0) -> 0 | AM13: {=SUM([5]Hoja3!$I$6:$I$25*([5]Hoja3!$F$6:$F$25=AM$5)*([5]Hoja3!$K$6:$K$25=$C13))} -> 0 | AN13: {=SUM([5]Hoja3!$J$6:$J$25*([5]Hoja3!$F$6:$F$25=AM$5)*([5]Hoja3!$K$6:$K$25=$C13))} -> 0 | AO13: =IFERROR(AN13/AM13,0) -> 0 | AP13: {=SUM([5]Hoja3!$I$6:$I$25*([5]Hoja3!$F$6:$F$25=AP$5)*([5]Hoja3!$K$6:$K$25=$C13))} -> 0 | AQ13: {=SUM([5]Hoja3!$J$6:$J$25*([5]Hoja3!$F$6:$F$25=AP$5)*([5]Hoja3!$K$6:$K$25=$C13))} -> 0 | AR13: =IFERROR(AQ13/AP13,0) -> 0 | AS13: {=SUM([5]Hoja3!$I$6:$I$25*([5]Hoja3!$F$6:$F$25=AS$5)*([5]Hoja3!$K$6:$K$25=$C13))} -> 0 | AT13: {=SUM([5]Hoja3!$J$6:$J$25*([5]Hoja3!$F$6:$F$25=AS$5)*([5]Hoja3!$K$6:$K$25=$C13))} -> 0 | AU13: =IFERROR(AT13/AS13,0) -> 0 | AV13: {=SUM([5]Hoja3!$I$6:$I$25*([5]Hoja3!$F$6:$F$25=AV$5)*([5]Hoja3!$K$6:$K$25=$C13))} -> 0 | AW13: {=SUM([5]Hoja3!$J$6:$J$25*([5]Hoja3!$F$6:$F$25=AV$5)*([5]Hoja3!$K$6:$K$25=$C13))} -> 0 | AX13: =IFERROR(AW13/AV13,0) -> 0 | AY13: {=SUM([5]Hoja3!$I$6:$I$25*([5]Hoja3!$F$6:$F$25=AY$5)*([5]Hoja3!$K$6:$K$25=$C13))} -> 27 | AZ13: {=SUM([5]Hoja3!$J$6:$J$25*([5]Hoja3!$F$6:$F$25=AY$5)*([5]Hoja3!$K$6:$K$25=$C13))} -> 43200 | BA13: =IFERROR(AZ13/AY13,0) -> 1600 | BB13: {=SUM([2]Hoja2!$I$6:$I$26*([2]Hoja2!$F$6:$F$26=BB$5)*([2]Hoja2!$K$6:$K$26=$C13))} -> 0 | BC13: {=SUM([2]Hoja2!$J$6:$J$26*([2]Hoja2!$F$6:$F$26=BB$5)*([2]Hoja2!$K$6:$K$26=$C13))} -> 0 | BD13: =IFERROR(BC13/BB13,0) -> 0 | BE13: {=SUM([2]Hoja2!$I$6:$I$26*([2]Hoja2!$F$6:$F$26=BE$5)*([2]Hoja2!$K$6:$K$26=$C13))} -> 0 | BF13: {=SUM([2]Hoja2!$J$6:$J$26*([2]Hoja2!$F$6:$F$26=BE$5)*([2]Hoja2!$K$6:$K$26=$C13))} -> 0 | BG13: =IFERROR(BF13/BE13,0) -> 0 | BH13: {=SUM([2]Hoja2!$I$6:$I$26*([2]Hoja2!$F$6:$F$26=BH$5)*([2]Hoja2!$K$6:$K$26=$C13))} -> 0 | BI13: {=SUM([2]Hoja2!$J$6:$J$26*([2]Hoja2!$F$6:$F$26=BH$5)*([2]Hoja2!$K$6:$K$26=$C13))} -> 0 | BJ13: =IFERROR(BI13/BH13,0) -> 0 | BK13: {=SUM([2]Hoja2!$I$6:$I$26*([2]Hoja2!$F$6:$F$26=BK$5)*([2]Hoja2!$K$6:$K$26=$C13))} -> 0 | BL13: {=SUM([2]Hoja2!$J$6:$J$26*([2]Hoja2!$F$6:$F$26=BK$5)*([2]Hoja2!$K$6:$K$26=$C13))} -> 0 | BM13: =IFERROR(BL13/BK13,0) -> 0 | BN13: {=SUM([2]Hoja2!$I$6:$I$26*([2]Hoja2!$F$6:$F$26=BN$5)*([2]Hoja2!$K$6:$K$26=$C13))} -> 0 | BO13: {=SUM([2]Hoja2!$J$6:$J$26*([2]Hoja2!$F$6:$F$26=BN$5)*([2]Hoja2!$K$6:$K$26=$C13))} -> 0 | BP13: =IFERROR(BO13/BN13,0) -> 0 | BQ13: {=SUM([2]Hoja2!$I$6:$I$26*([2]Hoja2!$F$6:$F$26=BQ$5)*([2]Hoja2!$K$6:$K$26=$C13))} -> 0 | BR13: {=SUM([2]Hoja2!$J$6:$J$26*([2]Hoja2!$F$6:$F$26=BQ$5)*([2]Hoja2!$K$6:$K$26=$C13))} -> 0 | BS13: =IFERROR(BR13/BQ13,0) -> 0 | BT13: =X13+AA13+AD13+AG13+AJ13+AM13+AP13+AY13+AS13+AV13 -> 81 | BU13: =Y13+AB13+AE13+AH13+AK13+AN13+AQ13+AZ13+AT13+AW13 -> 129600 | BV13: =IFERROR(BU13/BT13,0) -> 1600 | BW13: =-IFERROR(F13/D13*BT13,0) -> -108024.67 | BX13: =-207.84*BT13 -> -16835.04 | BY13: =$BY$18/$BT$18*$BT13 -> -7232.8398 | BZ13: =$BZ$18/$BT$18*$BT13 -> -14218.538 | CA13: =$CA$18/$BT$18*$BT13 -> -11366.173 | CB13: =(BU13-BT13*$BY$19)*0.03 -> 3610.5484 | CC13: =BU13+SUM(BW13:BZ13,CB13) -> -13100.534 | CD13: =IFERROR(CC13/BU13,0) -> -0.10108437 | CE13: =BU13+BW13+BX13+BY13+CB13-CA13 -> 12484.176 | CF13: =IFERROR(CE13/BU13,0) -> 0.096328521 | CH13: =BV13 -> 1600 | CI13: =IFERROR(BW13/$BT13,0) -> -1333.6378 | CJ13: =IFERROR(BX13/$BT13,0) -> -207.84 | CK13: =IFERROR(BY13/$BT13,0) -> -89.294318 | CL13: =IFERROR(BZ13/$BT13,0) -> -175.5375 | CM13: =IFERROR(CA13/$BT13,0) -> -140.32313 | CN13: =IFERROR(CB13/$BT13,0) -> 44.574672 | CO13: =IFERROR(CC13/$BT13,0) -> -161.73499 | CP13: =IFERROR(CE13/$BT13,0) -> 154.12563 | CQ13: =CP13-CO13 -> 315.86063
B14: 10009239 | C14: POTA FILETE DARUMA | D14: =TD!F11 -> 2.8 | E14: =IFERROR(F14/D14,0) -> 3191.5558 | F14: =TD!G11 -> 8936.3563 | G14: =TD!H11 -> 581.952 | H14: =TD!I11 -> 126.31242 | I14: =TD!J11 -> 248.30881 | J14: =TD!K11 -> 198.49587 | K14: 0 | L14: 0 | M14: =F14+G14+H14+I14 -> 9892.9295 | N14: =IFERROR(M14/D14,0) -> 3533.1891 | O14: =F14+G14+H14-J14 -> 9446.1249 | P14: =IFERROR(O14/D14,0) -> 3373.616 | Q14: 3400 | R14: =Q14*D14 -> 9520 | S14: =R14-M14+(Q14-$BY$19)*D14*0.03 -> -96.920454 | T14: =IFERROR(S14/R14,0) -> -0.01018072 | U14: =R14-(M14-J14-I14)+(Q14-$BY$19)*D14*0.03 -> 349.88422 | V14: =IFERROR(U14/R14,0) -> 0.036752545 | X14: {=SUM([5]Hoja3!$I$6:$I$25*([5]Hoja3!$F$6:$F$25=X$5)*([5]Hoja3!$K$6:$K$25=$C14))} -> 0 | Y14: {=SUM([5]Hoja3!$J$6:$J$25*([5]Hoja3!$F$6:$F$25=X$5)*([5]Hoja3!$K$6:$K$25=$C14))} -> 0 | Z14: =IFERROR(Y14/X14,0) -> 0 | AA14: {=SUM([5]Hoja3!$I$6:$I$25*([5]Hoja3!$F$6:$F$25=AA$5)*([5]Hoja3!$K$6:$K$25=$C14))} -> 0 | AB14: {=SUM([5]Hoja3!$J$6:$J$25*([5]Hoja3!$F$6:$F$25=AA$5)*([5]Hoja3!$K$6:$K$25=$C14))} -> 0 | AC14: =IFERROR(AB14/AA14,0) -> 0 | AD14: {=SUM([5]Hoja3!$I$6:$I$25*([5]Hoja3!$F$6:$F$25=AD$5)*([5]Hoja3!$K$6:$K$25=$C14))} -> 0 | AE14: {=SUM([5]Hoja3!$J$6:$J$25*([5]Hoja3!$F$6:$F$25=AD$5)*([5]Hoja3!$K$6:$K$25=$C14))} -> 0 | AF14: =IFERROR(AE14/AD14,0) -> 0 | AG14: {=SUM([5]Hoja3!$I$6:$I$25*([5]Hoja3!$F$6:$F$25=AG$5)*([5]Hoja3!$K$6:$K$25=$C14))} -> 0 | AH14: {=SUM([5]Hoja3!$J$6:$J$25*([5]Hoja3!$F$6:$F$25=AG$5)*([5]Hoja3!$K$6:$K$25=$C14))} -> 0 | AI14: =IFERROR(AH14/AG14,0) -> 0 | AJ14: {=SUM([5]Hoja3!$I$6:$I$25*([5]Hoja3!$F$6:$F$25=AJ$5)*([5]Hoja3!$K$6:$K$25=$C14))} -> 0 | AK14: {=SUM([5]Hoja3!$J$6:$J$25*([5]Hoja3!$F$6:$F$25=AJ$5)*([5]Hoja3!$K$6:$K$25=$C14))} -> 0 | AL14: =IFERROR(AK14/AJ14,0) -> 0 | AM14: {=SUM([5]Hoja3!$I$6:$I$25*([5]Hoja3!$F$6:$F$25=AM$5)*([5]Hoja3!$K$6:$K$25=$C14))} -> 0 | AN14: {=SUM([5]Hoja3!$J$6:$J$25*([5]Hoja3!$F$6:$F$25=AM$5)*([5]Hoja3!$K$6:$K$25=$C14))} -> 0 | AO14: =IFERROR(AN14/AM14,0) -> 0 | AP14: {=SUM([5]Hoja3!$I$6:$I$25*([5]Hoja3!$F$6:$F$25=AP$5)*([5]Hoja3!$K$6:$K$25=$C14))} -> 0 | AQ14: {=SUM([5]Hoja3!$J$6:$J$25*([5]Hoja3!$F$6:$F$25=AP$5)*([5]Hoja3!$K$6:$K$25=$C14))} -> 0 | AR14: =IFERROR(AQ14/AP14,0) -> 0 | AS14: {=SUM([5]Hoja3!$I$6:$I$25*([5]Hoja3!$F$6:$F$25=AS$5)*([5]Hoja3!$K$6:$K$25=$C14))} -> 0 | AT14: {=SUM([5]Hoja3!$J$6:$J$25*([5]Hoja3!$F$6:$F$25=AS$5)*([5]Hoja3!$K$6:$K$25=$C14))} -> 0 | AU14: =IFERROR(AT14/AS14,0) -> 0 | AV14: {=SUM([5]Hoja3!$I$6:$I$25*([5]Hoja3!$F$6:$F$25=AV$5)*([5]Hoja3!$K$6:$K$25=$C14))} -> 0 | AW14: {=SUM([5]Hoja3!$J$6:$J$25*([5]Hoja3!$F$6:$F$25=AV$5)*([5]Hoja3!$K$6:$K$25=$C14))} -> 0 | AX14: =IFERROR(AW14/AV14,0) -> 0 | AY14: {=SUM([5]Hoja3!$I$6:$I$25*([5]Hoja3!$F$6:$F$25=AY$5)*([5]Hoja3!$K$6:$K$25=$C14))} -> 0 | AZ14: {=SUM([5]Hoja3!$J$6:$J$25*([5]Hoja3!$F$6:$F$25=AY$5)*([5]Hoja3!$K$6:$K$25=$C14))} -> 0 | BA14: =IFERROR(AZ14/AY14,0) -> 0 | BB14: {=SUM([2]Hoja2!$I$6:$I$26*([2]Hoja2!$F$6:$F$26=BB$5)*([2]Hoja2!$K$6:$K$26=$C14))} -> 0 | BC14: {=SUM([2]Hoja2!$J$6:$J$26*([2]Hoja2!$F$6:$F$26=BB$5)*([2]Hoja2!$K$6:$K$26=$C14))} -> 0 | BD14: =IFERROR(BC14/BB14,0) -> 0 | BE14: {=SUM([2]Hoja2!$I$6:$I$26*([2]Hoja2!$F$6:$F$26=BE$5)*([2]Hoja2!$K$6:$K$26=$C14))} -> 0 | BF14: {=SUM([2]Hoja2!$J$6:$J$26*([2]Hoja2!$F$6:$F$26=BE$5)*([2]Hoja2!$K$6:$K$26=$C14))} -> 0 | BG14: =IFERROR(BF14/BE14,0) -> 0 | BH14: {=SUM([2]Hoja2!$I$6:$I$26*([2]Hoja2!$F$6:$F$26=BH$5)*([2]Hoja2!$K$6:$K$26=$C14))} -> 0 | BI14: {=SUM([2]Hoja2!$J$6:$J$26*([2]Hoja2!$F$6:$F$26=BH$5)*([2]Hoja2!$K$6:$K$26=$C14))} -> 0 | BJ14: =IFERROR(BI14/BH14,0) -> 0 | BK14: {=SUM([2]Hoja2!$I$6:$I$26*([2]Hoja2!$F$6:$F$26=BK$5)*([2]Hoja2!$K$6:$K$26=$C14))} -> 0 | BL14: {=SUM([2]Hoja2!$J$6:$J$26*([2]Hoja2!$F$6:$F$26=BK$5)*([2]Hoja2!$K$6:$K$26=$C14))} -> 0 | BM14: =IFERROR(BL14/BK14,0) -> 0 | BN14: {=SUM([2]Hoja2!$I$6:$I$26*([2]Hoja2!$F$6:$F$26=BN$5)*([2]Hoja2!$K$6:$K$26=$C14))} -> 0 | BO14: {=SUM([2]Hoja2!$J$6:$J$26*([2]Hoja2!$F$6:$F$26=BN$5)*([2]Hoja2!$K$6:$K$26=$C14))} -> 0 | BP14: =IFERROR(BO14/BN14,0) -> 0 | BQ14: {=SUM([2]Hoja2!$I$6:$I$26*([2]Hoja2!$F$6:$F$26=BQ$5)*([2]Hoja2!$K$6:$K$26=$C14))} -> 0 | BR14: {=SUM([2]Hoja2!$J$6:$J$26*([2]Hoja2!$F$6:$F$26=BQ$5)*([2]Hoja2!$K$6:$K$26=$C14))} -> 0 | BS14: =IFERROR(BR14/BQ14,0) -> 0 | BT14: =X14+AA14+AD14+AG14+AJ14+AM14+AP14+AY14+AS14+AV14 -> 0 | BU14: =Y14+AB14+AE14+AH14+AK14+AN14+AQ14+AZ14+AT14+AW14 -> 0 | BV14: =IFERROR(BU14/BT14,0) -> 0 | BW14: =-BT14*'[3]Stock Libre'!H36*1000 -> 0 | BX14: =-207.84*BT14 -> 0 | BY14: =$BY$18/$BT$18*$BT14 -> 0 | BZ14: =$BZ$18/$BT$18*$BT14 -> 0 | CA14: =$CA$18/$BT$18*$BT14 -> 0 | CB14: =(BU14-BT14*$BY$19)*0.03 -> 0 | CC14: =BU14+SUM(BW14:BZ14,CB14) -> 0 | CD14: =IFERROR(CC14/BU14,0) -> 0 | CE14: =BU14+BW14+BX14+BY14+CB14-CA14 -> 0 | CF14: =IFERROR(CE14/BU14,0) -> 0 | CH14: =BV14 -> 0 | CI14: =IFERROR(BW14/$BT14,0) -> 0 | CJ14: =IFERROR(BX14/$BT14,0) -> 0 | CK14: =IFERROR(BY14/$BT14,0) -> 0 | CL14: =IFERROR(BZ14/$BT14,0) -> 0 | CM14: =IFERROR(CA14/$BT14,0) -> 0 | CN14: =IFERROR(CB14/$BT14,0) -> 0 | CO14: =IFERROR(CC14/$BT14,0) -> 0 | CP14: =IFERROR(CE14/$BT14,0) -> 0 | CQ14: =CP14-CO14 -> 0
B15: 10009334 | C15: POTA ALAS COCIDAS | D15: =TD!F12 -> 14.626 | E15: =IFERROR(F15/D15,0) -> 2756.9568 | F15: =TD!G12 -> 40323.25 | G15: =TD!H12 -> 3039.8678 | H15: =TD!I12 -> 659.80193 | I15: =TD!J12 -> 1297.0588 | J15: =TD!K12 -> 1036.8573 | K15: 0 | L15: 0 | M15: =F15+G15+H15+I15 -> 45319.978 | N15: =IFERROR(M15/D15,0) -> 3098.5901 | O15: =F15+G15+H15-J15 -> 42986.062 | P15: =IFERROR(O15/D15,0) -> 2939.017 | Q15: 3500 | R15: =Q15*D15 -> 51191 | S15: =R15-M15+(Q15-$BY$19)*D15*0.03 -> 7356.6527 | T15: =IFERROR(S15/R15,0) -> 0.14370988 | U15: =R15-(M15-J15-I15)+(Q15-$BY$19)*D15*0.03 -> 9690.5689 | V15: =IFERROR(U15/R15,0) -> 0.1893022 | X15: {=SUM([5]Hoja3!$I$6:$I$25*([5]Hoja3!$F$6:$F$25=X$5)*([5]Hoja3!$K$6:$K$25=$C15))} -> 0 | Y15: {=SUM([5]Hoja3!$J$6:$J$25*([5]Hoja3!$F$6:$F$25=X$5)*([5]Hoja3!$K$6:$K$25=$C15))} -> 0 | Z15: =IFERROR(Y15/X15,0) -> 0 | AA15: {=SUM([5]Hoja3!$I$6:$I$25*([5]Hoja3!$F$6:$F$25=AA$5)*([5]Hoja3!$K$6:$K$25=$C15))} -> 0 | AB15: {=SUM([5]Hoja3!$J$6:$J$25*([5]Hoja3!$F$6:$F$25=AA$5)*([5]Hoja3!$K$6:$K$25=$C15))} -> 0 | AC15: =IFERROR(AB15/AA15,0) -> 0 | AD15: {=SUM([5]Hoja3!$I$6:$I$25*([5]Hoja3!$F$6:$F$25=AD$5)*([5]Hoja3!$K$6:$K$25=$C15))} -> 0 | AE15: {=SUM([5]Hoja3!$J$6:$J$25*([5]Hoja3!$F$6:$F$25=AD$5)*([5]Hoja3!$K$6:$K$25=$C15))} -> 0 | AF15: =IFERROR(AE15/AD15,0) -> 0 | AG15: {=SUM([5]Hoja3!$I$6:$I$25*([5]Hoja3!$F$6:$F$25=AG$5)*([5]Hoja3!$K$6:$K$25=$C15))} -> 0 | AH15: {=SUM([5]Hoja3!$J$6:$J$25*([5]Hoja3!$F$6:$F$25=AG$5)*([5]Hoja3!$K$6:$K$25=$C15))} -> 0 | AI15: =IFERROR(AH15/AG15,0) -> 0 | AJ15: {=SUM([5]Hoja3!$I$6:$I$25*([5]Hoja3!$F$6:$F$25=AJ$5)*([5]Hoja3!$K$6:$K$25=$C15))} -> 0 | AK15: {=SUM([5]Hoja3!$J$6:$J$25*([5]Hoja3!$F$6:$F$25=AJ$5)*([5]Hoja3!$K$6:$K$25=$C15))} -> 0 | AL15: =IFERROR(AK15/AJ15,0) -> 0 | AM15: {=SUM([5]Hoja3!$I$6:$I$25*([5]Hoja3!$F$6:$F$25=AM$5)*([5]Hoja3!$K$6:$K$25=$C15))} -> 0 | AN15: {=SUM([5]Hoja3!$J$6:$J$25*([5]Hoja3!$F$6:$F$25=AM$5)*([5]Hoja3!$K$6:$K$25=$C15))} -> 0 | AO15: =IFERROR(AN15/AM15,0) -> 0 | AP15: {=SUM([5]Hoja3!$I$6:$I$25*([5]Hoja3!$F$6:$F$25=AP$5)*([5]Hoja3!$K$6:$K$25=$C15))} -> 0 | AQ15: {=SUM([5]Hoja3!$J$6:$J$25*([5]Hoja3!$F$6:$F$25=AP$5)*([5]Hoja3!$K$6:$K$25=$C15))} -> 0 | AR15: =IFERROR(AQ15/AP15,0) -> 0 | AS15: {=SUM([5]Hoja3!$I$6:$I$25*([5]Hoja3!$F$6:$F$25=AS$5)*([5]Hoja3!$K$6:$K$25=$C15))} -> 0 | AT15: {=SUM([5]Hoja3!$J$6:$J$25*([5]Hoja3!$F$6:$F$25=AS$5)*([5]Hoja3!$K$6:$K$25=$C15))} -> 0 | AU15: =IFERROR(AT15/AS15,0) -> 0 | AV15: {=SUM([5]Hoja3!$I$6:$I$25*([5]Hoja3!$F$6:$F$25=AV$5)*([5]Hoja3!$K$6:$K$25=$C15))} -> 0 | AW15: {=SUM([5]Hoja3!$J$6:$J$25*([5]Hoja3!$F$6:$F$25=AV$5)*([5]Hoja3!$K$6:$K$25=$C15))} -> 0 | AX15: =IFERROR(AW15/AV15,0) -> 0 | AY15: {=SUM([5]Hoja3!$I$6:$I$25*([5]Hoja3!$F$6:$F$25=AY$5)*([5]Hoja3!$K$6:$K$25=$C15))} -> 0 | AZ15: {=SUM([5]Hoja3!$J$6:$J$25*([5]Hoja3!$F$6:$F$25=AY$5)*([5]Hoja3!$K$6:$K$25=$C15))} -> 0 | BA15: =IFERROR(AZ15/AY15,0) -> 0 | BB15: {=SUM([2]Hoja2!$I$6:$I$26*([2]Hoja2!$F$6:$F$26=BB$5)*([2]Hoja2!$K$6:$K$26=$C15))} -> 0 | BC15: {=SUM([2]Hoja2!$J$6:$J$26*([2]Hoja2!$F$6:$F$26=BB$5)*([2]Hoja2!$K$6:$K$26=$C15))} -> 0 | BD15: =IFERROR(BC15/BB15,0) -> 0 | BE15: {=SUM([2]Hoja2!$I$6:$I$26*([2]Hoja2!$F$6:$F$26=BE$5)*([2]Hoja2!$K$6:$K$26=$C15))} -> 0 | BF15: {=SUM([2]Hoja2!$J$6:$J$26*([2]Hoja2!$F$6:$F$26=BE$5)*([2]Hoja2!$K$6:$K$26=$C15))} -> 0 | BG15: =IFERROR(BF15/BE15,0) -> 0 | BH15: {=SUM([2]Hoja2!$I$6:$I$26*([2]Hoja2!$F$6:$F$26=BH$5)*([2]Hoja2!$K$6:$K$26=$C15))} -> 0 | BI15: {=SUM([2]Hoja2!$J$6:$J$26*([2]Hoja2!$F$6:$F$26=BH$5)*([2]Hoja2!$K$6:$K$26=$C15))} -> 0 | BJ15: =IFERROR(BI15/BH15,0) -> 0 | BK15: {=SUM([2]Hoja2!$I$6:$I$26*([2]Hoja2!$F$6:$F$26=BK$5)*([2]Hoja2!$K$6:$K$26=$C15))} -> 0 | BL15: {=SUM([2]Hoja2!$J$6:$J$26*([2]Hoja2!$F$6:$F$26=BK$5)*([2]Hoja2!$K$6:$K$26=$C15))} -> 0 | BM15: =IFERROR(BL15/BK15,0) -> 0 | BN15: {=SUM([2]Hoja2!$I$6:$I$26*([2]Hoja2!$F$6:$F$26=BN$5)*([2]Hoja2!$K$6:$K$26=$C15))} -> 0 | BO15: {=SUM([2]Hoja2!$J$6:$J$26*([2]Hoja2!$F$6:$F$26=BN$5)*([2]Hoja2!$K$6:$K$26=$C15))} -> 0 | BP15: =IFERROR(BO15/BN15,0) -> 0 | BQ15: {=SUM([2]Hoja2!$I$6:$I$26*([2]Hoja2!$F$6:$F$26=BQ$5)*([2]Hoja2!$K$6:$K$26=$C15))} -> 0 | BR15: {=SUM([2]Hoja2!$J$6:$J$26*([2]Hoja2!$F$6:$F$26=BQ$5)*([2]Hoja2!$K$6:$K$26=$C15))} -> 0 | BS15: =IFERROR(BR15/BQ15,0) -> 0 | BT15: =X15+AA15+AD15+AG15+AJ15+AM15+AP15+AY15+AS15+AV15 -> 0 | BU15: =Y15+AB15+AE15+AH15+AK15+AN15+AQ15+AZ15+AT15+AW15 -> 0 | BV15: =IFERROR(BU15/BT15,0) -> 0 | BW15: =-BT15*'[4]Stock Libre'!H47*1000 -> 0 | BX15: =-207.84*BT15 -> 0 | BY15: =$BY$18/$BT$18*$BT15 -> 0 | BZ15: =$BZ$18/$BT$18*$BT15 -> 0 | CA15: =$CA$18/$BT$18*$BT15 -> 0 | CB15: =(BU15-BT15*$BY$19)*0.03 -> 0 | CC15: =BU15+SUM(BW15:BZ15,CB15) -> 0 | CD15: =IFERROR(CC15/BU15,0) -> 0 | CE15: =BU15+BW15+BX15+BY15+CB15-CA15 -> 0 | CF15: =IFERROR(CE15/BU15,0) -> 0 | CH15: =BV15 -> 0 | CI15: =IFERROR(BW15/$BT15,0) -> 0 | CJ15: =IFERROR(BX15/$BT15,0) -> 0 | CK15: =IFERROR(BY15/$BT15,0) -> 0 | CL15: =IFERROR(BZ15/$BT15,0) -> 0 | CM15: =IFERROR(CA15/$BT15,0) -> 0 | CN15: =IFERROR(CB15/$BT15,0) -> 0 | CO15: =IFERROR(CC15/$BT15,0) -> 0 | CP15: =IFERROR(CE15/$BT15,0) -> 0 | CQ15: =CP15-CO15 -> 0
B16: 10009386 | C16: VENTOSAS | D16: =TD!F13 -> 20.7 | E16: =IFERROR(F16/D16,0) -> 1700.0864 | F16: =TD!G13 -> 35191.789 | G16: =TD!H13 -> 4302.288 | H16: =TD!I13 -> 933.80966 | I16: =TD!J13 -> 1835.7116 | J16: =TD!K13 -> 1467.4516 | K16: 0 | L16: 0 | M16: =F16+G16+H16+I16 -> 42263.598 | N16: =IFERROR(M16/D16,0) -> 2041.7197 | O16: =F16+G16+H16-J16 -> 38960.435 | P16: =IFERROR(O16/D16,0) -> 1882.1466 | Q16: 2000 | R16: =Q16*D16 -> 41400 | S16: =R16-M16+(Q16-$BY$19)*D16*0.03 -> 307.49724 | T16: =IFERROR(S16/R16,0) -> 0.0074274695 | U16: =R16-(M16-J16-I16)+(Q16-$BY$19)*D16*0.03 -> 3610.6604 | V16: =IFERROR(U16/R16,0) -> 0.087214019 | X16: {=SUM([5]Hoja3!$I$6:$I$25*([5]Hoja3!$F$6:$F$25=X$5)*([5]Hoja3!$K$6:$K$25=$C16))} -> 0 | Y16: {=SUM([5]Hoja3!$J$6:$J$25*([5]Hoja3!$F$6:$F$25=X$5)*([5]Hoja3!$K$6:$K$25=$C16))} -> 0 | Z16: =IFERROR(Y16/X16,0) -> 0 | AA16: {=SUM([5]Hoja3!$I$6:$I$25*([5]Hoja3!$F$6:$F$25=AA$5)*([5]Hoja3!$K$6:$K$25=$C16))} -> 0 | AB16: {=SUM([5]Hoja3!$J$6:$J$25*([5]Hoja3!$F$6:$F$25=AA$5)*([5]Hoja3!$K$6:$K$25=$C16))} -> 0 | AC16: =IFERROR(AB16/AA16,0) -> 0 | AD16: {=SUM([5]Hoja3!$I$6:$I$25*([5]Hoja3!$F$6:$F$25=AD$5)*([5]Hoja3!$K$6:$K$25=$C16))} -> 0 | AE16: {=SUM([5]Hoja3!$J$6:$J$25*([5]Hoja3!$F$6:$F$25=AD$5)*([5]Hoja3!$K$6:$K$25=$C16))} -> 0 | AF16: =IFERROR(AE16/AD16,0) -> 0 | AG16: {=SUM([5]Hoja3!$I$6:$I$25*([5]Hoja3!$F$6:$F$25=AG$5)*([5]Hoja3!$K$6:$K$25=$C16))} -> 0 | AH16: {=SUM([5]Hoja3!$J$6:$J$25*([5]Hoja3!$F$6:$F$25=AG$5)*([5]Hoja3!$K$6:$K$25=$C16))} -> 0 | AI16: =IFERROR(AH16/AG16,0) -> 0 | AJ16: {=SUM([5]Hoja3!$I$6:$I$25*([5]Hoja3!$F$6:$F$25=AJ$5)*([5]Hoja3!$K$6:$K$25=$C16))} -> 0 | AK16: {=SUM([5]Hoja3!$J$6:$J$25*([5]Hoja3!$F$6:$F$25=AJ$5)*([5]Hoja3!$K$6:$K$25=$C16))} -> 0 | AL16: =IFERROR(AK16/AJ16,0) -> 0 | AM16: {=SUM([5]Hoja3!$I$6:$I$25*([5]Hoja3!$F$6:$F$25=AM$5)*([5]Hoja3!$K$6:$K$25=$C16))} -> 0 | AN16: {=SUM([5]Hoja3!$J$6:$J$25*([5]Hoja3!$F$6:$F$25=AM$5)*([5]Hoja3!$K$6:$K$25=$C16))} -> 0 | AO16: =IFERROR(AN16/AM16,0) -> 0 | AP16: {=SUM([5]Hoja3!$I$6:$I$25*([5]Hoja3!$F$6:$F$25=AP$5)*([5]Hoja3!$K$6:$K$25=$C16))} -> 0 | AQ16: {=SUM([5]Hoja3!$J$6:$J$25*([5]Hoja3!$F$6:$F$25=AP$5)*([5]Hoja3!$K$6:$K$25=$C16))} -> 0 | AR16: =IFERROR(AQ16/AP16,0) -> 0 | AS16: {=SUM([5]Hoja3!$I$6:$I$25*([5]Hoja3!$F$6:$F$25=AS$5)*([5]Hoja3!$K$6:$K$25=$C16))} -> 0 | AT16: {=SUM([5]Hoja3!$J$6:$J$25*([5]Hoja3!$F$6:$F$25=AS$5)*([5]Hoja3!$K$6:$K$25=$C16))} -> 0 | AU16: =IFERROR(AT16/AS16,0) -> 0 | AV16: {=SUM([5]Hoja3!$I$6:$I$25*([5]Hoja3!$F$6:$F$25=AV$5)*([5]Hoja3!$K$6:$K$25=$C16))} -> 0 | AW16: {=SUM([5]Hoja3!$J$6:$J$25*([5]Hoja3!$F$6:$F$25=AV$5)*([5]Hoja3!$K$6:$K$25=$C16))} -> 0 | AX16: =IFERROR(AW16/AV16,0) -> 0 | AY16: {=SUM([5]Hoja3!$I$6:$I$25*([5]Hoja3!$F$6:$F$25=AY$5)*([5]Hoja3!$K$6:$K$25=$C16))} -> 0 | AZ16: {=SUM([5]Hoja3!$J$6:$J$25*([5]Hoja3!$F$6:$F$25=AY$5)*([5]Hoja3!$K$6:$K$25=$C16))} -> 0 | BA16: =IFERROR(AZ16/AY16,0) -> 0 | BB16: {=SUM([2]Hoja2!$I$6:$I$26*([2]Hoja2!$F$6:$F$26=BB$5)*([2]Hoja2!$K$6:$K$26=$C16))} -> 0 | BC16: {=SUM([2]Hoja2!$J$6:$J$26*([2]Hoja2!$F$6:$F$26=BB$5)*([2]Hoja2!$K$6:$K$26=$C16))} -> 0 | BD16: =IFERROR(BC16/BB16,0) -> 0 | BE16: {=SUM([2]Hoja2!$I$6:$I$26*([2]Hoja2!$F$6:$F$26=BE$5)*([2]Hoja2!$K$6:$K$26=$C16))} -> 0 | BF16: {=SUM([2]Hoja2!$J$6:$J$26*([2]Hoja2!$F$6:$F$26=BE$5)*([2]Hoja2!$K$6:$K$26=$C16))} -> 0 | BG16: =IFERROR(BF16/BE16,0) -> 0 | BH16: {=SUM([2]Hoja2!$I$6:$I$26*([2]Hoja2!$F$6:$F$26=BH$5)*([2]Hoja2!$K$6:$K$26=$C16))} -> 0 | BI16: {=SUM([2]Hoja2!$J$6:$J$26*([2]Hoja2!$F$6:$F$26=BH$5)*([2]Hoja2!$K$6:$K$26=$C16))} -> 0 | BJ16: =IFERROR(BI16/BH16,0) -> 0 | BK16: {=SUM([2]Hoja2!$I$6:$I$26*([2]Hoja2!$F$6:$F$26=BK$5)*([2]Hoja2!$K$6:$K$26=$C16))} -> 0 | BL16: {=SUM([2]Hoja2!$J$6:$J$26*([2]Hoja2!$F$6:$F$26=BK$5)*([2]Hoja2!$K$6:$K$26=$C16))} -> 0 | BM16: =IFERROR(BL16/BK16,0) -> 0 | BN16: {=SUM([2]Hoja2!$I$6:$I$26*([2]Hoja2!$F$6:$F$26=BN$5)*([2]Hoja2!$K$6:$K$26=$C16))} -> 0 | BO16: {=SUM([2]Hoja2!$J$6:$J$26*([2]Hoja2!$F$6:$F$26=BN$5)*([2]Hoja2!$K$6:$K$26=$C16))} -> 0 | BP16: =IFERROR(BO16/BN16,0) -> 0 | BQ16: {=SUM([2]Hoja2!$I$6:$I$26*([2]Hoja2!$F$6:$F$26=BQ$5)*([2]Hoja2!$K$6:$K$26=$C16))} -> 0 | BR16: {=SUM([2]Hoja2!$J$6:$J$26*([2]Hoja2!$F$6:$F$26=BQ$5)*([2]Hoja2!$K$6:$K$26=$C16))} -> 0 | BS16: =IFERROR(BR16/BQ16,0) -> 0 | BT16: =X16+AA16+AD16+AG16+AJ16+AM16+AP16+AY16+AS16+AV16 -> 0 | BU16: =Y16+AB16+AE16+AH16+AK16+AN16+AQ16+AZ16+AT16+AW16 -> 0 | BV16: =IFERROR(BU16/BT16,0) -> 0 | BW16: =-IFERROR(F16/D16*BT16,0) -> 0 | BX16: =-207.84*BT16 -> 0 | BY16: =$BY$18/$BT$18*$BT16 -> 0 | BZ16: =$BZ$18/$BT$18*$BT16 -> 0 | CA16: =$CA$18/$BT$18*$BT16 -> 0 | CB16: =(BU16-BT16*$BY$19)*0.03 -> 0 | CC16: =BU16+SUM(BW16:BZ16,CB16) -> 0 | CD16: =IFERROR(CC16/BU16,0) -> 0 | CE16: =BU16+BW16+BX16+BY16+CB16-CA16 -> 0 | CF16: =IFERROR(CE16/BU16,0) -> 0 | CH16: =BV16 -> 0 | CI16: =IFERROR(BW16/$BT16,0) -> 0 | CJ16: =IFERROR(BX16/$BT16,0) -> 0 | CK16: =IFERROR(BY16/$BT16,0) -> 0 | CL16: =IFERROR(BZ16/$BT16,0) -> 0 | CM16: =IFERROR(CA16/$BT16,0) -> 0 | CN16: =IFERROR(CB16/$BT16,0) -> 0 | CO16: =IFERROR(CC16/$BT16,0) -> 0 | CP16: =IFERROR(CE16/$BT16,0) -> 0 | CQ16: =CP16-CO16 -> 0
B17: 10009386 | C17: OTROS | D17: =TD!F14 -> 26.12 | E17: =IFERROR(F17/D17,0) -> 1380.8173 | F17: =TD!G14 -> 36066.948 | G17: =TD!H14 -> 5428.7808 | H17: =TD!I14 -> 1178.3144 | I17: =TD!J14 -> 2316.3665 | J17: =TD!K14 -> 1851.6829 | K17: 0 | L17: 0 | M17: =F17+G17+H17+I17 -> 44990.409 | N17: =IFERROR(M17/D17,0) -> 1722.4506 | O17: =F17+G17+H17-J17 -> 40822.36 | P17: =IFERROR(O17/D17,0) -> 1562.8775 | Q17: 1700 | R17: =Q17*D17 -> 44404 | S17: =R17-M17+(Q17-$BY$19)*D17*0.03 -> 656.2412 | T17: =IFERROR(S17/R17,0) -> 0.014778876 | U17: =R17-(M17-J17-I17)+(Q17-$BY$19)*D17*0.03 -> 4824.2906 | V17: =IFERROR(U17/R17,0) -> 0.1086454 | X17: {=SUM([5]Hoja3!$I$6:$I$25*([5]Hoja3!$F$6:$F$25=X$5)*([5]Hoja3!$K$6:$K$25=$C17))} -> 0 | Y17: {=SUM([5]Hoja3!$J$6:$J$25*([5]Hoja3!$F$6:$F$25=X$5)*([5]Hoja3!$K$6:$K$25=$C17))} -> 0 | Z17: =IFERROR(Y17/X17,0) -> 0 | AA17: {=SUM([5]Hoja3!$I$6:$I$25*([5]Hoja3!$F$6:$F$25=AA$5)*([5]Hoja3!$K$6:$K$25=$C17))} -> 0 | AB17: {=SUM([5]Hoja3!$J$6:$J$25*([5]Hoja3!$F$6:$F$25=AA$5)*([5]Hoja3!$K$6:$K$25=$C17))} -> 0 | AC17: =IFERROR(AB17/AA17,0) -> 0 | AD17: {=SUM([5]Hoja3!$I$6:$I$25*([5]Hoja3!$F$6:$F$25=AD$5)*([5]Hoja3!$K$6:$K$25=$C17))} -> 54 | AE17: {=SUM([5]Hoja3!$J$6:$J$25*([5]Hoja3!$F$6:$F$25=AD$5)*([5]Hoja3!$K$6:$K$25=$C17))} -> 86400 | AF17: =IFERROR(AE17/AD17,0) -> 1600 | AG17: {=SUM([5]Hoja3!$I$6:$I$25*([5]Hoja3!$F$6:$F$25=AG$5)*([5]Hoja3!$K$6:$K$25=$C17))} -> 0 | AH17: {=SUM([5]Hoja3!$J$6:$J$25*([5]Hoja3!$F$6:$F$25=AG$5)*([5]Hoja3!$K$6:$K$25=$C17))} -> 0 | AI17: =IFERROR(AH17/AG17,0) -> 0 | AJ17: {=SUM([5]Hoja3!$I$6:$I$25*([5]Hoja3!$F$6:$F$25=AJ$5)*([5]Hoja3!$K$6:$K$25=$C17))} -> 54 | AK17: {=SUM([5]Hoja3!$J$6:$J$25*([5]Hoja3!$F$6:$F$25=AJ$5)*([5]Hoja3!$K$6:$K$25=$C17))} -> 86400 | AL17: =IFERROR(AK17/AJ17,0) -> 1600 | AM17: {=SUM([5]Hoja3!$I$6:$I$25*([5]Hoja3!$F$6:$F$25=AM$5)*([5]Hoja3!$K$6:$K$25=$C17))} -> 0 | AN17: {=SUM([5]Hoja3!$J$6:$J$25*([5]Hoja3!$F$6:$F$25=AM$5)*([5]Hoja3!$K$6:$K$25=$C17))} -> 0 | AO17: =IFERROR(AN17/AM17,0) -> 0 | AP17: {=SUM([5]Hoja3!$I$6:$I$25*([5]Hoja3!$F$6:$F$25=AP$5)*([5]Hoja3!$K$6:$K$25=$C17))} -> 0 | AQ17: {=SUM([5]Hoja3!$J$6:$J$25*([5]Hoja3!$F$6:$F$25=AP$5)*([5]Hoja3!$K$6:$K$25=$C17))} -> 0 | AR17: =IFERROR(AQ17/AP17,0) -> 0 | AS17: {=SUM([5]Hoja3!$I$6:$I$25*([5]Hoja3!$F$6:$F$25=AS$5)*([5]Hoja3!$K$6:$K$25=$C17))} -> 27 | AT17: {=SUM([5]Hoja3!$J$6:$J$25*([5]Hoja3!$F$6:$F$25=AS$5)*([5]Hoja3!$K$6:$K$25=$C17))} -> 43200 | AU17: =IFERROR(AT17/AS17,0) -> 1600 | AV17: {=SUM([5]Hoja3!$I$6:$I$25*([5]Hoja3!$F$6:$F$25=AV$5)*([5]Hoja3!$K$6:$K$25=$C17))} -> 0 | AW17: {=SUM([5]Hoja3!$J$6:$J$25*([5]Hoja3!$F$6:$F$25=AV$5)*([5]Hoja3!$K$6:$K$25=$C17))} -> 0 | AX17: =IFERROR(AW17/AV17,0) -> 0 | AY17: {=SUM([5]Hoja3!$I$6:$I$25*([5]Hoja3!$F$6:$F$25=AY$5)*([5]Hoja3!$K$6:$K$25=$C17))} -> 54 | AZ17: {=SUM([5]Hoja3!$J$6:$J$25*([5]Hoja3!$F$6:$F$25=AY$5)*([5]Hoja3!$K$6:$K$25=$C17))} -> 86400 | BA17: =IFERROR(AZ17/AY17,0) -> 1600 | BB17: {=SUM([2]Hoja2!$I$6:$I$26*([2]Hoja2!$F$6:$F$26=BB$5)*([2]Hoja2!$K$6:$K$26=$C17))} -> 0 | BC17: {=SUM([2]Hoja2!$J$6:$J$26*([2]Hoja2!$F$6:$F$26=BB$5)*([2]Hoja2!$K$6:$K$26=$C17))} -> 0 | BD17: =IFERROR(BC17/BB17,0) -> 0 | BE17: {=SUM([2]Hoja2!$I$6:$I$26*([2]Hoja2!$F$6:$F$26=BE$5)*([2]Hoja2!$K$6:$K$26=$C17))} -> 0 | BF17: {=SUM([2]Hoja2!$J$6:$J$26*([2]Hoja2!$F$6:$F$26=BE$5)*([2]Hoja2!$K$6:$K$26=$C17))} -> 0 | BG17: =IFERROR(BF17/BE17,0) -> 0 | BH17: {=SUM([2]Hoja2!$I$6:$I$26*([2]Hoja2!$F$6:$F$26=BH$5)*([2]Hoja2!$K$6:$K$26=$C17))} -> 0 | BI17: {=SUM([2]Hoja2!$J$6:$J$26*([2]Hoja2!$F$6:$F$26=BH$5)*([2]Hoja2!$K$6:$K$26=$C17))} -> 0 | BJ17: =IFERROR(BI17/BH17,0) -> 0 | BK17: {=SUM([2]Hoja2!$I$6:$I$26*([2]Hoja2!$F$6:$F$26=BK$5)*([2]Hoja2!$K$6:$K$26=$C17))} -> 0 | BL17: {=SUM([2]Hoja2!$J$6:$J$26*([2]Hoja2!$F$6:$F$26=BK$5)*([2]Hoja2!$K$6:$K$26=$C17))} -> 0 | BM17: =IFERROR(BL17/BK17,0) -> 0 | BN17: {=SUM([2]Hoja2!$I$6:$I$26*([2]Hoja2!$F$6:$F$26=BN$5)*([2]Hoja2!$K$6:$K$26=$C17))} -> 0 | BO17: {=SUM([2]Hoja2!$J$6:$J$26*([2]Hoja2!$F$6:$F$26=BN$5)*([2]Hoja2!$K$6:$K$26=$C17))} -> 0 | BP17: =IFERROR(BO17/BN17,0) -> 0 | BQ17: {=SUM([2]Hoja2!$I$6:$I$26*([2]Hoja2!$F$6:$F$26=BQ$5)*([2]Hoja2!$K$6:$K$26=$C17))} -> 0 | BR17: {=SUM([2]Hoja2!$J$6:$J$26*([2]Hoja2!$F$6:$F$26=BQ$5)*([2]Hoja2!$K$6:$K$26=$C17))} -> 0 | BS17: =IFERROR(BR17/BQ17,0) -> 0 | BT17: =X17+AA17+AD17+AG17+AJ17+AM17+AP17+AY17+AS17+AV17 -> 189 | BU17: =Y17+AB17+AE17+AH17+AK17+AN17+AQ17+AZ17+AT17+AW17 -> 302400 | BV17: =IFERROR(BU17/BT17,0) -> 1600 | BW17: =-IFERROR(F17/D17*BT17,0) -> -260974.47 | BX17: =-207.84*BT17 -> -39281.76 | BY17: =$BY$18/$BT$18*$BT17 -> -16876.626 | BZ17: =$BZ$18/$BT$18*$BT17 -> -33176.588 | CA17: =$CA$18/$BT$18*$BT17 -> -26521.071 | CB17: =(BU17-BT17*$BY$19)*0.03 -> 8424.6129 | CC17: =BU17+SUM(BW17:BZ17,CB17) -> -39484.828 | CD17: =IFERROR(CC17/BU17,0) -> -0.13057152 | CE17: =BU17+BW17+BX17+BY17+CB17-CA17 -> 20212.83 | CF17: =IFERROR(CE17/BU17,0) -> 0.06684137 | CH17: =BV17 -> 1600 | CI17: =IFERROR(BW17/$BT17,0) -> -1380.8173 | CJ17: =IFERROR(BX17/$BT17,0) -> -207.84 | CK17: =IFERROR(BY17/$BT17,0) -> -89.294318 | CL17: =IFERROR(BZ17/$BT17,0) -> -175.5375 | CM17: =IFERROR(CA17/$BT17,0) -> -140.32313 | CN17: =IFERROR(CB17/$BT17,0) -> 44.574672 | CO17: =IFERROR(CC17/$BT17,0) -> -208.91443 | CP17: =IFERROR(CE17/$BT17,0) -> 106.94619 | CQ17: =CP17-CO17 -> 315.86063
C18: TOTAL | D18: =SUM(D7:D17) -> 1741.881 | E18: =IFERROR(F18/D18,0) -> 1779.7351 | F18: =SUM(F7:F17) -> 3100086.8 | G18: =SUM(G7:G17) -> 362032.55 | H18: =SUM(H7:H17) -> 78579 | I18: =SUM(I7:I17) -> 154473 | J18: =SUM(J7:J17) -> 123484.35 | K18: =SUM(K7:K17) -> 0 | L18: 0 | M18: =SUM(M7:M17) -> 3695171.3 | N18: =IFERROR(M18/D18,0) -> 2121.3684 | O18: =SUM(O7:O17) -> 3417214 | P18: =IFERROR(O18/D18,0) -> 1961.7953 | Q18: =R18/D18 -> 1665.5231 | R18: =SUM(R7:R17) -> 2901143.1 | S18: =SUM(S7:S17) -> -712960.43 | T18: =S18/R18 -> -0.24575155 | U18: =SUM(U7:U17) -> -435003.08 | V18: =IFERROR(U18/R18,0) -> -0.14994196 | X18: =SUM(X7:X17) -> 27 | Y18: =SUM(Y7:Y17) -> 68850 | Z18: =IFERROR(Y18/X18,0) -> 2550 | AA18: =SUM(AA7:AA17) -> 26 | AB18: =SUM(AB7:AB17) -> 74100 | AC18: =IFERROR(AB18/AA18,0) -> 2850 | AD18: =SUM(AD7:AD17) -> 270 | AE18: =SUM(AE7:AE17) -> 542700 | AF18: =IFERROR(AE18/AD18,0) -> 2010 | AG18: =SUM(AG7:AG17) -> 26 | AH18: =SUM(AH7:AH17) -> 70980 | AI18: =IFERROR(AH18/AG18,0) -> 2730 | AJ18: =SUM(AJ7:AJ17) -> 132 | AK18: =SUM(AK7:AK17) -> 190140 | AL18: =IFERROR(AK18/AJ18,0) -> 1440.4545 | AM18: =SUM(AM7:AM17) -> 24 | AN18: =SUM(AN7:AN17) -> 48000 | AO18: =IFERROR(AN18/AM18,0) -> 2000 | AP18: =SUM(AP7:AP17) -> 79 | AQ18: =SUM(AQ7:AQ17) -> 139960 | AR18: =IFERROR(AQ18/AP18,0) -> 1771.6456 | AS18: =SUM(AS7:AS17) -> 54 | AT18: =SUM(AT7:AT17) -> 124200 | AU18: =IFERROR(AT18/AS18,0) -> 2300 | AV18: =SUM(AV7:AV17) -> 26 | AW18: =SUM(AW7:AW17) -> 34580 | AX18: =IFERROR(AW18/AV18,0) -> 1330 | AY18: =SUM(AY7:AY17) -> 216 | AZ18: =SUM(AZ7:AZ17) -> 472110 | BA18: =IFERROR(AZ18/AY18,0) -> 2185.6944 | BB18: =SUM(BB7:BB17) -> 0 | BC18: =SUM(BC7:BC17) -> 0 | BD18: =IFERROR(BC18/BB18,0) -> 0 | BE18: =SUM(BE7:BE17) -> 0 | BF18: =SUM(BF7:BF17) -> 0 | BG18: =IFERROR(BF18/BE18,0) -> 0 | BH18: =SUM(BH7:BH17) -> 0 | BI18: =SUM(BI7:BI17) -> 0 | BJ18: =IFERROR(BI18/BH18,0) -> 0 | BK18: =SUM(BK7:BK17) -> 0 | BL18: =SUM(BL7:BL17) -> 0 | BM18: =IFERROR(BL18/BK18,0) -> 0 | BN18: =SUM(BN7:BN17) -> 0 | BO18: =SUM(BO7:BO17) -> 0 | BP18: =IFERROR(BO18/BN18,0) -> 0 | BQ18: =SUM(BQ7:BQ17) -> 0 | BR18: =SUM(BR7:BR17) -> 0 | BS18: =IFERROR(BR18/BQ18,0) -> 0 | BT18: =SUM(BT7:BT17) -> 880 | BU18: =SUM(BU7:BU17) -> 1765620 | BV18: =IFERROR(BU18/BT18,0) -> 2006.3864 | BW18: =SUM(BW7:BW17) -> -1391867.9 | BX18: =SUM(BX7:BX17) -> -182899.2 | BY18: =-'Stock Libre'!N54 -> -78579 | BZ18: =-'Stock Libre'!O52 -> -154473 | CA18: =-'Stock Libre'!P52 -> -123484.35 | CB18: =SUM(CB7:CB17) -> 49954.311 | CC18: =SUM(CC7:CC17) -> 7755.1842 | CD18: =IFERROR(CC18/BU18,0) -> 0.0043923291 | CE18: =SUM(CE7:CE17) -> 285712.53 | CF18: =IFERROR(CE18/BU18,0) -> 0.16181995 | CH18: =BV18 -> 2006.3864 | CI18: =IFERROR(BW18/$BT18,0) -> -1581.6681 | CJ18: =IFERROR(BX18/$BT18,0) -> -207.84 | CK18: =IFERROR(BY18/$BT18,0) -> -89.294318 | CL18: =IFERROR(BZ18/$BT18,0) -> -175.5375 | CM18: =IFERROR(CA18/$BT18,0) -> -140.32313 | CN18: =IFERROR(CB18/$BT18,0) -> 56.766262 | CO18: =IFERROR(CC18/$BT18,0) -> 8.8127093 | CP18: =IFERROR(CE18/$BT18,0) -> 324.67333 | CQ18: =CP18-CO18 -> 315.86063
N19: =N18-P18 -> 159.5731 | BX19: flete x tm | BY19: 114.17761
C20: TM en Almacén de Yantai | CI20: =SUM(CI7:CL7) -> -2410.2241
C22: Producto | D22: TM en Stock Libre | E22: CU | F22: Costo Ventas | G22: Gasto Ventas | H22: Gasto ADM | I22: Gasto Fin | J22: Depreciación | K22: Utilidad Neta | L22: Margen Neto | M22: Venta Equilibrio a Utd Neta | N22: Precio Equilibrio x TM a Utd Neta | O22: Venta Equilibro a EBITDA | P22: Precio Equilibrio x TM a EBITDA | Q22: Precio Mercado | R22: Venta total | S22: Utilidad | T22: Mg Neto | U22: EBITDA | V22: Mg EBITDA | BT22: Venta Julio | BU22: =BU18-BU14-BU7 -> 1717620 | CI22: =CI7/0.5 -> -3875.1045
C23: POTA FILETE CONGELADO | D23: 540 | E23: =E7 -> 1937.5523 | F23: =E23*D23 -> 1046278.2 | G23: =D23*207.84 -> 112233.6 | H23: =H$18/$D$18*$D23 -> 24360.252 | I23: =I$18/$D$18*$D23 -> 47888.128 | J23: =J$18/$D$18*$D23 -> 38281.346 | K23: 0 | L23: 0 | M23: =F23+G23+H23+I23 -> 1230760.2 | N23: =IFERROR(M23/D23,0) -> 2279.1856 | O23: =F23+G23+H23-J23 -> 1144590.7 | P23: =IFERROR(O23/D23,0) -> 2119.6125 | Q23: 1400 | R23: =Q23*D23 -> 756000 | S23: =R23-M23+(Q23-$BY$19)*D23*0.03 -> -453929.88 | T23: =IFERROR(S23/R23,0) -> -0.60043635 | U23: =R23-(M23-J23-I23)+(Q23-$BY$19)*D23*0.03 -> -367760.41 | V23: =IFERROR(U23/R23,0) -> -0.48645557 | BT23: Cobranza | BU23: 3849629
C24: POTA FILETE DARUMA | D24: 162 | E24: =E14 -> 3191.5558 | F24: =E24*D24 -> 517032.04 | G24: =D24*207.84 -> 33670.08 | H24: =H$18/$D$18*$D24 -> 7308.0756 | I24: =I$18/$D$18*$D24 -> 14366.438 | J24: =J$18/$D$18*$D24 -> 11484.404 | K24: 0 | L24: 0 | M24: =F24+G24+H24+I24 -> 572376.64 | N24: =IFERROR(M24/D24,0) -> 3533.1891 | O24: =F24+G24+H24-J24 -> 546525.8 | P24: =IFERROR(O24/D24,0) -> 3373.616 | Q24: 3500 | R24: =Q24*D24 -> 567000 | S24: =R24-M24+(Q24-$BY$19)*D24*0.03 -> 11078.459 | T24: =IFERROR(S24/R24,0) -> 0.019538729 | U24: =R24-(M24-J24-I24)+(Q24-$BY$19)*D24*0.03 -> 36929.302 | V24: =IFERROR(U24/R24,0) -> 0.065131043 | BT24: Inventario | BU24: =M27 -> 5498308.1
C25: TOTAL | D25: =SUM(D23:D24) -> 702 | E25: =F25/D25 -> 2226.9377 | F25: =SUM(F23:F24) -> 1563310.3 | G25: =SUM(G23:G24) -> 145903.68 | H25: =SUM(H23:H24) -> 31668.328 | I25: =SUM(I23:I24) -> 62254.566 | J25: =SUM(J23:J24) -> 49765.75 | K25: =SUM(K23:K24) -> 0 | L25: 0 | M25: =SUM(M23:M24) -> 1803136.8 | N25: =IFERROR(M25/D25,0) -> 2568.571 | O25: =SUM(O23:O24) -> 1691116.5 | P25: =IFERROR(O25/D25,0) -> 2408.9979 | Q25: =R25/D25 -> 1884.6154 | R25: =SUM(R23:R24) -> 1323000 | S25: =SUM(S23:S24) -> -442851.42 | T25: =S25/R25 -> -0.33473275 | U25: =SUM(U23:U24) -> -330831.11 | V25: =IFERROR(U25/R25,0) -> -0.25006131 | BU25: =SUM(BU22:BU24) -> 11065557
C27: TOTAL | D27: =D18+D25 -> 2443.881 | E27: =F27/D27 -> 1908.1932 | F27: =F18+F25 -> 4663397 | G27: =G18+G25 -> 507936.23 | H27: =H18+H25 -> 110247.33 | I27: =I18+I25 -> 216727.57 | J27: =J18+J25 -> 173250.1 | K27: =K18+K25 -> 0 | L27: =L18+L25 -> 0 | M27: =M18+M25 -> 5498308.1 | N27: =IFERROR(M27/D27,0) -> 2249.8265 | O27: =O18+O25 -> 5108330.5 | P27: =IFERROR(O27/D27,0) -> 2090.2534 | Q27: =R27/D27 -> 1728.457 | R27: =R18+R25 -> 4224143.1 | S27: =S18+S25 -> -1155811.9 | T27: =S27/R27 -> -0.27362043 | U27: =U18+U25 -> -765834.18 | V27: =IFERROR(U27/R27,0) -> -0.1812993

Sheet TD
E3: Etiquetas de fila | F3: Suma de TM en Stock | G3: Suma de Costo Ventas | H3: Suma de Gasto Ventas | I3: Suma de Gasto ADM | J3: Suma de Gasto Fin | K3: Suma de Depreciación
B4: =C4=E4 -> TRUE | C4: 10005721 | D4: POTA FILETE CONGELADO | E4: 10005721 | F4: 462.666 | G4: 896439.56 | H4: 96160.501 | I4: 20871.593 | J4: 41030.016 | K4: 32799.032
B5: =C5=E5 -> TRUE | C5: 10005779 | D5: POTA NUCAS CONGELADAS | E5: 10005779 | F5: 380.02 | G5: 602164.3 | H5: 78983.357 | I5: 17143.302 | J5: 33700.827 | K5: 26940.143
B6: =C6=E6 -> TRUE | C6: 10006719 | D6: POTA ALAS CONGELADAS | E6: 10006719 | F6: 539.694 | G6: 990438.47 | H6: 112170 | I6: 24346.448 | J6: 47860.991 | K6: 38259.653
B7: =C7=E7 -> TRUE | C7: 10007050 | D7: POTA RECORTES COCIDOS | E7: 10007050 | F7: 11.695 | G7: 16476.584 | H7: 2430.6888 | I7: 527.5799 | J7: 1037.1327 | K7: 829.0747
B8: =C8=E8 -> TRUE | C8: 10007162 | D8: POTA REJOS CONGELADOS | E8: 10007162 | F8: 171 | G8: 290468.78 | H8: 35540.64 | I8: 7714.0798 | J8: 15164.574 | K8: 12122.426
B9: =C9=E9 -> TRUE | C9: 10007567 | D9: POTA REPRODUCTORES | E9: 10007567 | F9: 108.54 | G9: 178219.5 | H9: 22558.954 | I9: 4896.4106 | J9: 9625.5137 | K9: 7694.5505
B10: =C10=E10 -> TRUE | C10: 10007969 | D10: POTA CONOS | E10: 10007969 | F10: 4.02 | G10: 5361.2241 | H10: 835.5168 | I10: 181.34854 | J10: 356.50051 | K10: 284.98335
B11: =C11=E11 -> TRUE | C11: 10009239 | D11: POTA FILETE DARUMA | E11: 10009239 | F11: 2.8 | G11: 8936.3563 | H11: 581.952 | I11: 126.31242 | J11: 248.30881 | K11: 198.49587
B12: =C12=E12 -> TRUE | C12: 10009334 | D12: POTA ALAS COCIDAS | E12: 10009334 | F12: 14.626 | G12: 40323.25 | H12: 3039.8678 | I12: 659.80193 | J12: 1297.0588 | K12: 1036.8573
B13: =C13=E13 -> TRUE | C13: 10009386 | D13: VENTOSAS | E13: 10009386 | F13: 20.7 | G13: 35191.789 | H13: 4302.288 | I13: 933.80966 | J13: 1835.7116 | K13: 1467.4516
B14: =C14=E14 -> FALSE | E14: 10009207 | F14: 26.12 | G14: 36066.948 | H14: 5428.7808 | I14: 1178.3144 | J14: 2316.3665 | K14: 1851.6829
E15: Total general | F15: 1741.881 | G15: 3100086.8 | H15: 362032.55 | I15: 78579 | J15: 154473 | K15: 123484.35

Sheet Stock Libre
B1: PRODUCTO | C1: TOTAL STOCK | D1: POR EMBARCAR | E1: STOCK LIBRE | G1: CÓDIGO | H1: CU X TM | I1: % MP | J1: incremento MP | K1: TM en Stock | L1: Costo Ventas | M1: Gasto Ventas | N1: Gasto ADM | O1: Gasto Fin | P1: Depreciación | Q1: Utilidad Neta | R1: Margen Neto | S1: Venta Equilibrio | T1: Precio Equilibrio x TM
B2: POTA ALAS FR C/P C/C (B) S/COD BL10 S20 | C2: 14400 | E2: 14400 | G2: 10006719 | H2: =IFERROR(INDEX([1]Resumen!$K$3:$K$63,MATCH(G2,[1]Resumen!$C$3:$C$63,0)),0)*(1+I2*J2)/1000-51.89/1000 -> 1.8351853 | I2: 0.71 | J2: =$H$59 -> -0.10285454 | K2: =IF(E2<0,0,E2)/1000 -> 14.4 | L2: =IFERROR(H2*K2,0)*1000 -> 26426.668 | M2: =207.84*K2 -> 2992.896 | N2: =$N$54/$K$52*K2 -> 649.60672 | O2: =$O$54/$K$52*K2 -> 1277.0167 | P2: =$P$54/$K$52*K2 -> 1020.8359 | Q2: 0 | R2: 0 | S2: =L2+M2+N2+O2 -> 31346.187 | T2: =IFERROR(S2/K2,0) -> 2176.8186
B3: POTA ALAS FR C/P C/C <0.5 BL10 S20 | C3: 2520 | D3: 0 | E3: 2520 | G3: 10006719 | H3: =IFERROR(INDEX([1]Resumen!$K$3:$K$63,MATCH(G3,[1]Resumen!$C$3:$C$63,0)),0)*(1+I3*J3)/1000-51.89/1000 -> 1.8351853 | I3: 0.71 | J3: =$H$59 -> -0.10285454 | K3: =IF(E3<0,0,E3)/1000 -> 2.52 | L3: =IFERROR(H3*K3,0)*1000 -> 4624.6668 | M3: =207.84*K3 -> 523.7568 | N3: =$N$54/$K$52*K3 -> 113.68118 | O3: =$O$54/$K$52*K3 -> 223.47793 | P3: =$P$54/$K$52*K3 -> 178.64628 | Q3: 0 | R3: 0 | S3: =L3+M3+N3+O3 -> 5485.5827 | T3: =IFERROR(S3/K3,0) -> 2176.8186
B4: POTA ALAS FR C/P C/C 0.5-1 BL10 S20 | C4: 29980 | D4: 27000 | E4: 2980 | G4: 10006719 | H4: =IFERROR(INDEX([1]Resumen!$K$3:$K$63,MATCH(G4,[1]Resumen!$C$3:$C$63,0)),0)*(1+I4*J4)/1000-51.89/1000 -> 1.8351853 | I4: 0.71 | J4: =$H$59 -> -0.10285454 | K4: =IF(E4<0,0,E4)/1000 -> 2.98 | L4: =IFERROR(H4*K4,0)*1000 -> 5468.8521 | M4: =207.84*K4 -> 619.3632 | N4: =$N$54/$K$52*K4 -> 134.4325 | O4: =$O$54/$K$52*K4 -> 264.27152 | P4: =$P$54/$K$52*K4 -> 211.25632 | Q4: 0 | R4: 0 | S4: =L4+M4+N4+O4 -> 6486.9193 | T4: =IFERROR(S4/K4,0) -> 2176.8186
B5: POTA ALAS FR C/P C/C 0.3 - 0.5 BL10 S20 | C5: 0 | E5: 0 | G5: 10006719 | H5: =IFERROR(INDEX([1]Resumen!$K$3:$K$63,MATCH(G5,[1]Resumen!$C$3:$C$63,0)),0)*(1+I5*J5)/1000-51.89/1000 -> 1.8351853 | I5: 0.71 | J5: =$H$59 -> -0.10285454 | K5: =IF(E5<0,0,E5)/1000 -> 0 | L5: =IFERROR(H5*K5,0)*1000 -> 0 | M5: =207.84*K5 -> 0 | N5: =$N$54/$K$52*K5 -> 0 | O5: =$O$54/$K$52*K5 -> 0 | P5: =$P$54/$K$52*K5 -> 0 | Q5: 0 | R5: 0 | S5: =L5+M5+N5+O5 -> 0 | T5: =IFERROR(S5/K5,0) -> 0
B6: POTA ALAS FR C/P C/C 1-2 BL10 S20 | C6: 1900 | D6: 1900 | E6: 0 | G6: 10006719 | H6: =IFERROR(INDEX([1]Resumen!$K$3:$K$63,MATCH(G6,[1]Resumen!$C$3:$C$63,0)),0)*(1+I6*J6)/1000-51.89/1000 -> 1.8351853 | I6: 0.71 | J6: =$H$59 -> -0.10285454 | K6: =IF(E6<0,0,E6)/1000 -> 0 | L6: =IFERROR(H6*K6,0)*1000 -> 0 | M6: =207.84*K6 -> 0 | N6: =$N$54/$K$52*K6 -> 0 | O6: =$O$54/$K$52*K6 -> 0 | P6: =$P$54/$K$52*K6 -> 0 | Q6: 0 | R6: 0 | S6: =L6+M6+N6+O6 -> 0 | T6: =IFERROR(S6/K6,0) -> 0
B7: POTA ALAS FR C/P C/C 1-2 BL10 S20 ENTERA | C7: 26420 | D7: 26420 | E7: 0 | G7: 10006719 | H7: =IFERROR(INDEX([1]Resumen!$K$3:$K$63,MATCH(G7,[1]Resumen!$C$3:$C$63,0)),0)*(1+I7*J7)/1000-51.89/1000 -> 1.8351853 | I7: 0.71 | J7: =$H$59 -> -0.10285454 | K7: =IF(E7<0,0,E7)/1000 -> 0 | L7: =IFERROR(H7*K7,0)*1000 -> 0 | M7: =207.84*K7 -> 0 | N7: =$N$54/$K$52*K7 -> 0 | O7: =$O$54/$K$52*K7 -> 0 | P7: =$P$54/$K$52*K7 -> 0 | Q7: 0 | R7: 0 | S7: =L7+M7+N7+O7 -> 0 | T7: =IFERROR(S7/K7,0) -> 0
B8: POTA ALAS FR C/P C/C 2up | C8: 120 | D8: 120 | E8: 0 | G8: 10006719 | H8: =IFERROR(INDEX([1]Resumen!$K$3:$K$63,MATCH(G8,[1]Resumen!$C$3:$C$63,0)),0)*(1+I8*J8)/1000-51.89/1000 -> 1.8351853 | I8: 0.71 | J8: =$H$59 -> -0.10285454 | K8: =IF(E8<0,0,E8)/1000 -> 0 | L8: =IFERROR(H8*K8,0)*1000 -> 0 | M8: =207.84*K8 -> 0 | N8: =$N$54/$K$52*K8 -> 0 | O8: =$O$54/$K$52*K8 -> 0 | P8: =$P$54/$K$52*K8 -> 0 | Q8: 0 | R8: 0 | S8: =L8+M8+N8+O8 -> 0 | T8: =IFERROR(S8/K8,0) -> 0
B9: POTA LABIOS FR S/COD BL10 S20 | C9: 26120 | E9: 26120 | G9: 10009207 | H9: =IFERROR(INDEX([1]Resumen!$K$3:$K$63,MATCH(G9,[1]Resumen!$C$3:$C$63,0)),0)*(1+I9*J9)/1000-51.89/1000 -> 1.3808173 | I9: 0.71 | J9: =$H$59 -> -0.10285454 | K9: =IF(E9<0,0,E9)/1000 -> 26.12 | L9: =IFERROR(H9*K9,0)*1000 -> 36066.948 | M9: =207.84*K9 -> 5428.7808 | N9: =$N$54/$K$52*K9 -> 1178.3144 | O9: =$O$54/$K$52*K9 -> 2316.3665 | P9: =$P$54/$K$52*K9 -> 1851.6829 | Q9: 0 | R9: 0 | S9: =L9+M9+N9+O9 -> 44990.409 | T9: =IFERROR(S9/K9,0) -> 1722.4506
B10: POTA CONOS | C10: 31020 | D10: 27000 | E10: 4020 | G10: 10007969 | H10: =IFERROR(INDEX([1]Resumen!$K$3:$K$63,MATCH(G10,[1]Resumen!$C$3:$C$63,0)),0)*(1+I10*J10)/1000-51.89/1000 -> 1.3336378 | I10: 0.71 | J10: =$H$59 -> -0.10285454 | K10: =IF(E10<0,0,E10)/1000 -> 4.02 | L10: =IFERROR(H10*K10,0)*1000 -> 5361.2241 | M10: =207.84*K10 -> 835.5168 | N10: =$N$54/$K$52*K10 -> 181.34854 | O10: =$O$54/$K$52*K10 -> 356.50051 | P10: =$P$54/$K$52*K10 -> 284.98335 | Q10: 0 | R10: 0 | S10: =L10+M10+N10+O10 -> 6734.59 | T10: =IFERROR(S10/K10,0) -> 1675.2711
B11: POTA FILETE C/M C/T FR 0.5-1.0 BL10 S20 | C11: 0 | E11: 0 | G11: 10005721 | H11: =IFERROR(INDEX([1]Resumen!$K$3:$K$63,MATCH(G11,[1]Resumen!$C$3:$C$63,0)),0)*(1+I11*J11)/1000-51.89/1000 -> 1.9375523 | I11: 0.67 | J11: =$H$59 -> -0.10285454 | K11: =IF(E11<0,0,E11)/1000 -> 0 | L11: =IFERROR(H11*K11,0)*1000 -> 0 | M11: =207.84*K11 -> 0 | N11: =$N$54/$K$52*K11 -> 0 | O11: =$O$54/$K$52*K11 -> 0 | P11: =$P$54/$K$52*K11 -> 0 | Q11: 0 | R11: 0 | S11: =L11+M11+N11+O11 -> 0 | T11: =IFERROR(S11/K11,0) -> 0
B12: POTA FILETE C/M C/T FR 1-2 BL10 S20 | C12: 1760 | E12: 1760 | G12: 10005721 | H12: =IFERROR(INDEX([1]Resumen!$K$3:$K$63,MATCH(G12,[1]Resumen!$C$3:$C$63,0)),0)*(1+I12*J12)/1000-51.89/1000 -> 1.9375523 | I12: 0.67 | J12: =$H$59 -> -0.10285454 | K12: =IF(E12<0,0,E12)/1000 -> 1.76 | L12: =IFERROR(H12*K12,0)*1000 -> 3410.092 | M12: =207.84*K12 -> 365.7984 | N12: =$N$54/$K$52*K12 -> 79.396377 | O12: =$O$54/$K$52*K12 -> 156.07982 | P12: =$P$54/$K$52*K12 -> 124.76883 | Q12: 0 | R12: 0 | S12: =L12+M12+N12+O12 -> 4011.3666 | T12: =IFERROR(S12/K12,0) -> 2279.1856
B13: POTA FILETE C/M C/T FR 1.0 - 3.0 BL10 S20 | C13: 0 | E13: 0 | G13: 10005721 | H13: =IFERROR(INDEX([1]Resumen!$K$3:$K$63,MATCH(G13,[1]Resumen!$C$3:$C$63,0)),0)*(1+I13*J13)/1000-51.89/1000 -> 1.9375523 | I13: 0.67 | J13: =$H$59 -> -0.10285454 | K13: =IF(E13<0,0,E13)/1000 -> 0 | L13: =IFERROR(H13*K13,0)*1000 -> 0 | M13: =207.84*K13 -> 0 | N13: =$N$54/$K$52*K13 -> 0 | O13: =$O$54/$K$52*K13 -> 0 | P13: =$P$54/$K$52*K13 -> 0 | Q13: 0 | R13: 0 | S13: =L13+M13+N13+O13 -> 0 | T13: =IFERROR(S13/K13,0) -> 0
B14: POTA FILETE C/M C/T FR 2-4 S20 | C14: 19860 | E14: 19860 | G14: 10005721 | H14: =IFERROR(INDEX([1]Resumen!$K$3:$K$63,MATCH(G14,[1]Resumen!$C$3:$C$63,0)),0)*(1+I14*J14)/1000-51.89/1000 -> 1.9375523 | I14: 0.67 | J14: =$H$59 -> -0.10285454 | K14: =IF(E14<0,0,E14)/1000 -> 19.86 | L14: =IFERROR(H14*K14,0)*1000 -> 38479.788 | M14: =207.84*K14 -> 4127.7024 | N14: =$N$54/$K$52*K14 -> 895.91593 | O14: =$O$54/$K$52*K14 -> 1761.2189 | P14: =$P$54/$K$52*K14 -> 1407.9028 | Q14: 0 | R14: 0 | S14: =L14+M14+N14+O14 -> 45264.625 | T14: =IFERROR(S14/K14,0) -> 2279.1856
B15: POTA FILETE C/M C/T FR <0.5 Kg AA BL10 S20 | C15: 1080 | E15: 1080 | G15: 10005721 | H15: =IFERROR(INDEX([1]Resumen!$K$3:$K$63,MATCH(G15,[1]Resumen!$C$3:$C$63,0)),0)*(1+I15*J15)/1000-51.89/1000 -> 1.9375523 | I15: 0.67 | J15: =$H$59 -> -0.10285454 | K15: =IF(E15<0,0,E15)/1000 -> 1.08 | L15: =IFERROR(H15*K15,0)*1000 -> 2092.5565 | M15: =207.84*K15 -> 224.4672 | N15: =$N$54/$K$52*K15 -> 48.720504 | O15: =$O$54/$K$52*K15 -> 95.776256 | P15: =$P$54/$K$52*K15 -> 76.562692 | Q15: 0 | R15: 0 | S15: =L15+M15+N15+O15 -> 2461.5204 | T15: =IFERROR(S15/K15,0) -> 2279.1856
B16: POTA FILETE C/M C/T FR 2-4 (AA) BL10 S20 | C16: 3080 | E16: 3080 | G16: 10005721 | H16: =IFERROR(INDEX([1]Resumen!$K$3:$K$63,MATCH(G16,[1]Resumen!$C$3:$C$63,0)),0)*(1+I16*J16)/1000-51.89/1000 -> 1.9375523 | I16: 0.67 | J16: =$H$59 -> -0.10285454 | K16: =IF(E16<0,0,E16)/1000 -> 3.08 | L16: =IFERROR(H16*K16,0)*1000 -> 5967.661 | M16: =207.84*K16 -> 640.1472 | N16: =$N$54/$K$52*K16 -> 138.94366 | O16: =$O$54/$K$52*K16 -> 273.13969 | P16: =$P$54/$K$52*K16 -> 218.34545 | Q16: 0 | R16: 0 | S16: =L16+M16+N16+O16 -> 7019.8915 | T16: =IFERROR(S16/K16,0) -> 2279.1856
B17: POTA FILETE C/M C/T FR 0.5-1.0 AA BL10 S20 | C17: 0 | E17: 0 | G17: 10005721 | H17: =IFERROR(INDEX([1]Resumen!$K$3:$K$63,MATCH(G17,[1]Resumen!$C$3:$C$63,0)),0)*(1+I17*J17)/1000-51.89/1000 -> 1.9375523 | I17: 0.67 | J17: =$H$59 -> -0.10285454 | K17: =IF(E17<0,0,E17)/1000 -> 0 | L17: =IFERROR(H17*K17,0)*1000 -> 0 | M17: =207.84*K17 -> 0 | N17: =$N$54/$K$52*K17 -> 0 | O17: =$O$54/$K$52*K17 -> 0 | P17: =$P$54/$K$52*K17 -> 0 | Q17: 0 | R17: 0 | S17: =L17+M17+N17+O17 -> 0 | T17: =IFERROR(S17/K17,0) -> 0
B18: POTA FILETE C/M C/T FR 1.0 - 3.0 AA BL10 S20 | C18: 5300 | E18: 5300 | G18: 10005721 | H18: =IFERROR(INDEX([1]Resumen!$K$3:$K$63,MATCH(G18,[1]Resumen!$C$3:$C$63,0)),0)*(1+I18*J18)/1000-51.89/1000 -> 1.9375523 | I18: 0.67 | J18: =$H$59 -> -0.10285454 | K18: =IF(E18<0,0,E18)/1000 -> 5.3 | L18: =IFERROR(H18*K18,0)*1000 -> 10269.027 | M18: =207.84*K18 -> 1101.552 | N18: =$N$54/$K$52*K18 -> 239.09136 | O18: =$O$54/$K$52*K18 -> 470.01311 | P18: =$P$54/$K$52*K18 -> 375.72432 | Q18: 0 | R18: 0 | S18: =L18+M18+N18+O18 -> 12079.683 | T18: =IFERROR(S18/K18,0) -> 2279.1856
B19: POTA FILETE C/M C/T FR 1-2 AA BL10 S20 JAPON | C19: 13260 | D19: 380 | E19: 12880 | G19: 10005721 | H19: =IFERROR(INDEX([1]Resumen!$K$3:$K$63,MATCH(G19,[1]Resumen!$C$3:$C$63,0)),0)*(1+I19*J19)/1000-51.89/1000 -> 1.9375523 | I19: 0.67 | J19: =$H$59 -> -0.10285454 | K19: =IF(E19<0,0,E19)/1000 -> 12.88 | L19: =IFERROR(H19*K19,0)*1000 -> 24955.673 | M19: =207.84*K19 -> 2676.9792 | N19: =$N$54/$K$52*K19 -> 581.03712 | O19: =$O$54/$K$52*K19 -> 1142.2205 | P19: =$P$54/$K$52*K19 -> 913.08099 | Q19: 0 | R19: 0 | S19: =L19+M19+N19+O19 -> 29355.91 | T19: =IFERROR(S19/K19,0) -> 2279.1856
B20: POTA FILETE C/M C/T FR 0.5-1.0 AAA BL10 S20 | C20: 0 | E20: 0 | G20: 10005721 | H20: =IFERROR(INDEX([1]Resumen!$K$3:$K$63,MATCH(G20,[1]Resumen!$C$3:$C$63,0)),0)*(1+I20*J20)/1000-51.89/1000 -> 1.9375523 | I20: 0.67 | J20: =$H$59 -> -0.10285454 | K20: =IF(E20<0,0,E20)/1000 -> 0 | L20: =IFERROR(H20*K20,0)*1000 -> 0 | M20: =207.84*K20 -> 0 | N20: =$N$54/$K$52*K20 -> 0 | O20: =$O$54/$K$52*K20 -> 0 | P20: =$P$54/$K$52*K20 -> 0 | Q20: 0 | R20: 0 | S20: =L20+M20+N20+O20 -> 0 | T20: =IFERROR(S20/K20,0) -> 0
B21: POTA FILETE C/M C/T FR 1-2 AA BL10 S20 50% ROSADO | C21: 29720 | D21: 27000 | E21: 2720 | G21: 10005721 | H21: =IFERROR(INDEX([1]Resumen!$K$3:$K$63,MATCH(G21,[1]Resumen!$C$3:$C$63,0)),0)*(1+I21*J21)/1000-51.89/1000 -> 1.9375523 | I21: 0.67 | J21: =$H$59 -> -0.10285454 | K21: =IF(E21<0,0,E21)/1000 -> 2.72 | L21: =IFERROR(H21*K21,0)*1000 -> 5270.1422 | M21: =207.84*K21 -> 565.3248 | N21: =$N$54/$K$52*K21 -> 122.70349 | O21: =$O$54/$K$52*K21 -> 241.21427 | P21: =$P$54/$K$52*K21 -> 192.82456 | Q21: 0 | R21: 0 | S21: =L21+M21+N21+O21 -> 6199.3847 | T21: =IFERROR(S21/K21,0) -> 2279.1856
B22: POTA FILETE C/M C/T FR 2-4 AAA BL10 S20 | C22: 0 | D22: 0 | E22: 0 | G22: 10005721 | H22: =IFERROR(INDEX([1]Resumen!$K$3:$K$63,MATCH(G22,[1]Resumen!$C$3:$C$63,0)),0)*(1+I22*J22)/1000-51.89/1000 -> 1.9375523 | I22: 0.67 | J22: =$H$59 -> -0.10285454 | K22: =IF(E22<0,0,E22)/1000 -> 0 | L22: =IFERROR(H22*K22,0)*1000 -> 0 | M22: =207.84*K22 -> 0 | N22: =$N$54/$K$52*K22 -> 0 | O22: =$O$54/$K$52*K22 -> 0 | P22: =$P$54/$K$52*K22 -> 0 | Q22: 0 | R22: 0 | S22: =L22+M22+N22+O22 -> 0 | T22: =IFERROR(S22/K22,0) -> 0
B23: POTA FILETE SM ST 1-2 CM/ESP | C23: 3200 | E23: 3200 | G23: 10005721 | H23: =IFERROR(INDEX([1]Resumen!$K$3:$K$63,MATCH(G23,[1]Resumen!$C$3:$C$63,0)),0)*(1+I23*J23)/1000-51.89/1000 -> 1.9375523 | I23: 0.67 | J23: =$H$59 -> -0.10285454 | K23: =IF(E23<0,0,E23)/1000 -> 3.2 | L23: =IFERROR(H23*K23,0)*1000 -> 6200.1673 | M23: =207.84*K23 -> 665.088 | N23: =$N$54/$K$52*K23 -> 144.35705 | O23: =$O$54/$K$52*K23 -> 283.7815 | P23: =$P$54/$K$52*K23 -> 226.85242 | Q23: 0 | R23: 0 | S23: =L23+M23+N23+O23 -> 7293.3938 | T23: =IFERROR(S23/K23,0) -> 2279.1856
B24: POTA NUCAS FR ABIERTAS 0.1 - 0.3 BL10 S2 | C24: 130260 | E24: 130260 | G24: 10005779 | H24: =IFERROR(INDEX([1]Resumen!$K$3:$K$63,MATCH(G24,[1]Resumen!$C$3:$C$63,0)),0)*(1+I24*J24)/1000-51.89/1000 -> 1.5845595 | I24: 0.65 | J24: =$H$59 -> -0.10285454 | K24: =IF(E24<0,0,E24)/1000 -> 130.26 | L24: =IFERROR(H24*K24,0)*1000 -> 206404.72 | M24: =207.84*K24 -> 27073.238 | N24: =$N$54/$K$52*K24 -> 5876.2341 | O24: =$O$54/$K$52*K24 -> 11551.681 | P24: =$P$54/$K$52*K24 -> 9234.3113 | Q24: 0 | R24: 0 | S24: =L24+M24+N24+O24 -> 250905.87 | T24: =IFERROR(S24/K24,0) -> 1926.1928
B25: POTA NUCAS FR CERRADA 0.1 - 0.3 BL10 S2 | C25: 40100 | E25: 40100 | G25: 10005779 | H25: =IFERROR(INDEX([1]Resumen!$K$3:$K$63,MATCH(G25,[1]Resumen!$C$3:$C$63,0)),0)*(1+I25*J25)/1000-51.89/1000 -> 1.5845595 | I25: 0.65 | J25: =$H$59 -> -0.10285454 | K25: =IF(E25<0,0,E25)/1000 -> 40.1 | L25: =IFERROR(H25*K25,0)*1000 -> 63540.835 | M25: =207.84*K25 -> 8334.384 | N25: =$N$54/$K$52*K25 -> 1808.9743 | O25: =$O$54/$K$52*K25 -> 3556.1369 | P25: =$P$54/$K$52*K25 -> 2842.7444 | Q25: 0 | R25: 0 | S25: =L25+M25+N25+O25 -> 77240.33 | T25: =IFERROR(S25/K25,0) -> 1926.1928
B26: POTA NUCAS FR CERRADA <0.1 BL10 S2 | C26: 1040 | E26: 1040 | G26: 10005779 | H26: =IFERROR(INDEX([1]Resumen!$K$3:$K$63,MATCH(G26,[1]Resumen!$C$3:$C$63,0)),0)*(1+I26*J26)/1000-51.89/1000 -> 1.5845595 | I26: 0.65 | J26: =$H$59 -> -0.10285454 | K26: =IF(E26<0,0,E26)/1000 -> 1.04 | L26: =IFERROR(H26*K26,0)*1000 -> 1647.9419 | M26: =207.84*K26 -> 216.1536 | N26: =$N$54/$K$52*K26 -> 46.916041 | O26: =$O$54/$K$52*K26 -> 92.228987 | P26: =$P$54/$K$52*K26 -> 73.727036 | Q26: 0 | R26: 0 | S26: =L26+M26+N26+O26 -> 2003.2405 | T26: =IFERROR(S26/K26,0) -> 1926.1928
B27: POTA NUCAS FR ABIERTAS 0.5-1 BL10 S20 | C27: 73120 | D27: 26000 | E27: 47120 | G27: 10005779 | H27: =IFERROR(INDEX([1]Resumen!$K$3:$K$63,MATCH(G27,[1]Resumen!$C$3:$C$63,0)),0)*(1+I27*J27)/1000-51.89/1000 -> 1.5845595 | I27: 0.65 | J27: =$H$59 -> -0.10285454 | K27: =IF(E27<0,0,E27)/1000 -> 47.12 | L27: =IFERROR(H27*K27,0)*1000 -> 74664.443 | M27: =207.84*K27 -> 9793.4208 | N27: =$N$54/$K$52*K27 -> 2125.6575 | O27: =$O$54/$K$52*K27 -> 4178.6826 | P27: =$P$54/$K$52*K27 -> 3340.4019 | Q27: 0 | R27: 0 | S27: =L27+M27+N27+O27 -> 90762.204 | T27: =IFERROR(S27/K27,0) -> 1926.1928
B28: POTA NUCAS FR ABIERTAS 0.3-0.5 BL10 S20 | C28: 166620 | D28: 10000 | E28: 156620 | G28: 10005779 | H28: =IFERROR(INDEX([1]Resumen!$K$3:$K$63,MATCH(G28,[1]Resumen!$C$3:$C$63,0)),0)*(1+I28*J28)/1000-51.89/1000 -> 1.5845595 | I28: 0.65 | J28: =$H$59 -> -0.10285454 | K28: =IF(E28<0,0,E28)/1000 -> 156.62 | L28: =IFERROR(H28*K28,0)*1000 -> 248173.71 | M28: =207.84*K28 -> 32551.901 | N28: =$N$54/$K$52*K28 -> 7065.3753 | O28: =$O$54/$K$52*K28 -> 13889.331 | P28: =$P$54/$K$52*K28 -> 11103.008 | Q28: 0 | R28: 0 | S28: =L28+M28+N28+O28 -> 301680.31 | T28: =IFERROR(S28/K28,0) -> 1926.1928
B29: POTA NUCAS FR ABIERTAS 1-2 BL10 S20 | C29: 4880 | E29: 4880 | G29: 10005779 | H29: =IFERROR(INDEX([1]Resumen!$K$3:$K$63,MATCH(G29,[1]Resumen!$C$3:$C$63,0)),0)*(1+I29*J29)/1000-51.89/1000 -> 1.5845595 | I29: 0.65 | J29: =$H$59 -> -0.10285454 | K29: =IF(E29<0,0,E29)/1000 -> 4.88 | L29: =IFERROR(H29*K29,0)*1000 -> 7732.6503 | M29: =207.84*K29 -> 1014.2592 | N29: =$N$54/$K$52*K29 -> 220.1445 | O29: =$O$54/$K$52*K29 -> 432.76678 | P29: =$P$54/$K$52*K29 -> 345.94994 | Q29: 0 | R29: 0 | S29: =L29+M29+N29+O29 -> 9399.8208 | T29: =IFERROR(S29/K29,0) -> 1926.1928
B30: POTA REJOS OR FR LIMPIOS S/COD BL10 S20 | C30: 100840 | D30: 27000 | E30: 73840 | G30: 10007567 | H30: =IFERROR(INDEX([1]Resumen!$K$3:$K$63,MATCH(G30,[1]Resumen!$C$3:$C$63,0)),0)*(1+I30*J30)/1000-51.89/1000 -> 1.6419707 | I30: 0.68 | J30: =$H$59 -> -0.10285454 | K30: =IF(E30<0,0,E30)/1000 -> 73.84 | L30: =IFERROR(H30*K30,0)*1000 -> 121243.12 | M30: =207.84*K30 -> 15346.906 | N30: =$N$54/$K$52*K30 -> 3331.0389 | O30: =$O$54/$K$52*K30 -> 6548.2581 | P30: =$P$54/$K$52*K30 -> 5234.6196 | Q30: 0 | R30: 0 | S30: =L30+M30+N30+O30 -> 146469.32 | T30: =IFERROR(S30/K30,0) -> 1983.604
B31: POTA REJOS OR FR LIMPIOS <60 cm BL10 S20 | C31: 34700 | E31: 34700 | G31: 10007567 | H31: =IFERROR(INDEX([1]Resumen!$K$3:$K$63,MATCH(G31,[1]Resumen!$C$3:$C$63,0)),0)*(1+I31*J31)/1000-51.89/1000 -> 1.6419707 | I31: 0.68 | J31: =$H$59 -> -0.10285454 | K31: =IF(E31<0,0,E31)/1000 -> 34.7 | L31: =IFERROR(H31*K31,0)*1000 -> 56976.384 | M31: =207.84*K31 -> 7212.048 | N31: =$N$54/$K$52*K31 -> 1565.3717 | O31: =$O$54/$K$52*K31 -> 3077.2556 | P31: =$P$54/$K$52*K31 -> 2459.9309 | Q31: 0 | R31: 0 | S31: =L31+M31+N31+O31 -> 68831.059 | T31: =IFERROR(S31/K31,0) -> 1983.604
B32: POTA REJOS FR C/U C/V S/OR <0.1 BL10 | C32: 0 | E32: 0 | G32: 10007162 | H32: =IFERROR(INDEX([1]Resumen!$K$3:$K$63,MATCH(G32,[1]Resumen!$C$3:$C$63,0)),0)*(1+I32*J32)/1000-51.89/1000 -> 1.6986478 | I32: 0.68 | J32: =$H$59 -> -0.10285454 | K32: =IF(E32<0,0,E32)/1000 -> 0 | L32: =IFERROR(H32*K32,0)*1000 -> 0 | M32: =207.84*K32 -> 0 | N32: =$N$54/$K$52*K32 -> 0 | O32: =$O$54/$K$52*K32 -> 0 | P32: =$P$54/$K$52*K32 -> 0 | Q32: 0 | R32: 0 | S32: =L32+M32+N32+O32 -> 0 | T32: =IFERROR(S32/K32,0) -> 0
B33: POTA REJOS FR C/U C/V S/OR 0.1-0.3 BL10 | C33: 960 | D33: 960 | E33: 0 | G33: 10007162 | H33: =IFERROR(INDEX([1]Resumen!$K$3:$K$63,MATCH(G33,[1]Resumen!$C$3:$C$63,0)),0)*(1+I33*J33)/1000-51.89/1000 -> 1.6986478 | I33: 0.68 | J33: =$H$59 -> -0.10285454 | K33: =IF(E33<0,0,E33)/1000 -> 0 | L33: =IFERROR(H33*K33,0)*1000 -> 0 | M33: =207.84*K33 -> 0 | N33: =$N$54/$K$52*K33 -> 0 | O33: =$O$54/$K$52*K33 -> 0 | P33: =$P$54/$K$52*K33 -> 0 | Q33: 0 | R33: 0 | S33: =L33+M33+N33+O33 -> 0 | T33: =IFERROR(S33/K33,0) -> 0
B34: POTA REJOS FR C/U C/V S/OR 0.3-0.5BL10 | C34: 51340 | D34: 53040 | E34: -1700 | G34: 10007162 | H34: =IFERROR(INDEX([1]Resumen!$K$3:$K$63,MATCH(G34,[1]Resumen!$C$3:$C$63,0)),0)*(1+I34*J34)/1000-51.89/1000 -> 1.6986478 | I34: 0.68 | J34: =$H$59 -> -0.10285454 | K34: =IF(E34<0,0,E34)/1000 -> 0 | L34: =IFERROR(H34*K34,0)*1000 -> 0 | M34: =207.84*K34 -> 0 | N34: =$N$54/$K$52*K34 -> 0 | O34: =$O$54/$K$52*K34 -> 0 | P34: =$P$54/$K$52*K34 -> 0 | Q34: 0 | R34: 0 | S34: =L34+M34+N34+O34 -> 0 | T34: =IFERROR(S34/K34,0) -> 0
B35: POTA REJOS FR C/U C/V S/OR 0.5-1.0 BL10 | C35: 118340 | D35: 136300 | E35: -17960 | G35: 10007162 | H35: =IFERROR(INDEX([1]Resumen!$K$3:$K$63,MATCH(G35,[1]Resumen!$C$3:$C$63,0)),0)*(1+I35*J35)/1000-51.89/1000 -> 1.6986478 | I35: 0.68 | J35: =$H$59 -> -0.10285454 | K35: =IF(E35<0,0,E35)/1000 -> 0 | L35: =IFERROR(H35*K35,0)*1000 -> 0 | M35: =207.84*K35 -> 0 | N35: =$N$54/$K$52*K35 -> 0 | O35: =$O$54/$K$52*K35 -> 0 | P35: =$P$54/$K$52*K35 -> 0 | Q35: 0 | R35: 0 | S35: =L35+M35+N35+O35 -> 0 | T35: =IFERROR(S35/K35,0) -> 0
B36: POTA REJOS FR C/B S/U S/V S/OR 0.3-0.5 BL10 | C36: 340 | E36: 340 | G36: 10007162 | H36: =IFERROR(INDEX([1]Resumen!$K$3:$K$63,MATCH(G36,[1]Resumen!$C$3:$C$63,0)),0)*(1+I36*J36)/1000-51.89/1000 -> 1.6986478 | I36: 0.68 | J36: =$H$59 -> -0.10285454 | K36: =IF(E36<0,0,E36)/1000 -> 0.34 | L36: =IFERROR(H36*K36,0)*1000 -> 577.54027 | M36: =207.84*K36 -> 70.6656 | N36: =$N$54/$K$52*K36 -> 15.337936 | O36: =$O$54/$K$52*K36 -> 30.151784 | P36: =$P$54/$K$52*K36 -> 24.10307 | Q36: 0 | R36: 0 | S36: =L36+M36+N36+O36 -> 693.69559 | T36: =IFERROR(S36/K36,0) -> 2040.2811
B37: POTA REJOS FR C/B S/U S/V S/OR 0.5-1 BL1 0 | C37: 30700 | D37: 27000 | E37: 3700 | G37: 10007162 | H37: =IFERROR(INDEX([1]Resumen!$K$3:$K$63,MATCH(G37,[1]Resumen!$C$3:$C$63,0)),0)*(1+I37*J37)/1000-51.89/1000 -> 1.6986478 | I37: 0.68 | J37: =$H$59 -> -0.10285454 | K37: =IF(E37<0,0,E37)/1000 -> 3.7 | L37: =IFERROR(H37*K37,0)*1000 -> 6284.997 | M37: =207.84*K37 -> 769.008 | N37: =$N$54/$K$52*K37 -> 166.91284 | O37: =$O$54/$K$52*K37 -> 328.12236 | P37: =$P$54/$K$52*K37 -> 262.29811 | Q37: 0 | R37: 0 | S37: =L37+M37+N37+O37 -> 7549.0402 | T37: =IFERROR(S37/K37,0) -> 2040.2811
B38: POTA REJOS FR C/B C/U C/V S/OR 1.0 up BL 10S20 | C38: 2680 | E38: 2680 | G38: 10007162 | H38: =IFERROR(INDEX([1]Resumen!$K$3:$K$63,MATCH(G38,[1]Resumen!$C$3:$C$63,0)),0)*(1+I38*J38)/1000-51.89/1000 -> 1.6986478 | I38: 0.68 | J38: =$H$59 -> -0.10285454 | K38: =IF(E38<0,0,E38)/1000 -> 2.68 | L38: =IFERROR(H38*K38,0)*1000 -> 4552.3762 | M38: =207.84*K38 -> 557.0112 | N38: =$N$54/$K$52*K38 -> 120.89903 | O38: =$O$54/$K$52*K38 -> 237.667 | P38: =$P$54/$K$52*K38 -> 189.9889 | Q38: 0 | R38: 0 | S38: =L38+M38+N38+O38 -> 5467.9534 | T38: =IFERROR(S38/K38,0) -> 2040.2811
B39: POTA REJOS FR C/B S/U S/V S/OR 2-UP BL10 | C39: 32300 | E39: 32300 | G39: 10007162 | H39: =IFERROR(INDEX([1]Resumen!$K$3:$K$63,MATCH(G39,[1]Resumen!$C$3:$C$63,0)),0)*(1+I39*J39)/1000-51.89/1000 -> 1.6986478 | I39: 0.68 | J39: =$H$59 -> -0.10285454 | K39: =IF(E39<0,0,E39)/1000 -> 32.3 | L39: =IFERROR(H39*K39,0)*1000 -> 54866.325 | M39: =207.84*K39 -> 6713.232 | N39: =$N$54/$K$52*K39 -> 1457.104 | O39: =$O$54/$K$52*K39 -> 2864.4195 | P39: =$P$54/$K$52*K39 -> 2289.7916 | Q39: 0 | R39: 0 | S39: =L39+M39+N39+O39 -> 65901.081 | T39: =IFERROR(S39/K39,0) -> 2040.2811
B40: POTA REJOS FR C/B S/U S/V S/OR 1-2 BL10 | C40: 131980 | E40: 131980 | G40: 10007162 | H40: =IFERROR(INDEX([1]Resumen!$K$3:$K$63,MATCH(G40,[1]Resumen!$C$3:$C$63,0)),0)*(1+I40*J40)/1000-51.89/1000 -> 1.6986478 | I40: 0.68 | J40: =$H$59 -> -0.10285454 | K40: =IF(E40<0,0,E40)/1000 -> 131.98 | L40: =IFERROR(H40*K40,0)*1000 -> 224187.54 | M40: =207.84*K40 -> 27430.723 | N40: =$N$54/$K$52*K40 -> 5953.826 | O40: =$O$54/$K$52*K40 -> 11704.213 | P40: =$P$54/$K$52*K40 -> 9356.2445 | Q40: 0 | R40: 0 | S40: =L40+M40+N40+O40 -> 269276.3 | T40: =IFERROR(S40/K40,0) -> 2040.2811
B41: VENTOSAS DE REJOS | C41: 20700 | E41: 20700 | G41: 10009386 | H41: =IFERROR(INDEX([1]Resumen!$K$3:$K$63,MATCH(G41,[1]Resumen!$C$3:$C$63,0)),0)*(1+I41*J41)/1000-51.89/1000 -> 1.7000864 | I41: 0.68 | J41: =$H$59 -> -0.10285454 | K41: =IF(E41<0,0,E41)/1000 -> 20.7 | L41: =IFERROR(H41*K41,0)*1000 -> 35191.789 | M41: =207.84*K41 -> 4302.288 | N41: =$N$54/$K$52*K41 -> 933.80966 | O41: =$O$54/$K$52*K41 -> 1835.7116 | P41: =$P$54/$K$52*K41 -> 1467.4516 | Q41: 0 | R41: 0 | S41: =L41+M41+N41+O41 -> 42263.598 | T41: =IFERROR(S41/K41,0) -> 2041.7197
B42: POTA FILETE PRE COCIDO S/M S/T C/P S/COD | C42: 141360 | D42: 162000 | E42: -20640 | G42: 10009239 | H42: =IFERROR(INDEX([1]Resumen!$K$3:$K$63,MATCH(G42,[1]Resumen!$C$3:$C$63,0)),0)*(1+I42*J42)/1000-51.89/1000 -> 3.1915558 | I42: 0.56 | J42: =$H$59 -> -0.10285454 | K42: =IF(E42<0,0,E42)/1000 -> 0 | L42: =IFERROR(H42*K42,0)*1000 -> 0 | M42: =207.84*K42 -> 0 | N42: =$N$54/$K$52*K42 -> 0 | O42: =$O$54/$K$52*K42 -> 0 | P42: =$P$54/$K$52*K42 -> 0 | Q42: 0 | R42: 0 | S42: =L42+M42+N42+O42 -> 0 | T42: =IFERROR(S42/K42,0) -> 0
B43: POTA FILETE PRE COCIDO S/M S/T C/P 0.6-1.0 | C43: 2800 | E43: 2800 | G43: 10009239 | H43: =IFERROR(INDEX([1]Resumen!$K$3:$K$63,MATCH(G43,[1]Resumen!$C$3:$C$63,0)),0)*(1+I43*J43)/1000-51.89/1000 -> 3.1915558 | I43: 0.56 | J43: =$H$59 -> -0.10285454 | K43: =IF(E43<0,0,E43)/1000 -> 2.8 | L43: =IFERROR(H43*K43,0)*1000 -> 8936.3563 | M43: =207.84*K43 -> 581.952 | N43: =$N$54/$K$52*K43 -> 126.31242 | O43: =$O$54/$K$52*K43 -> 248.30881 | P43: =$P$54/$K$52*K43 -> 198.49587 | Q43: 0 | R43: 0 | S43: =L43+M43+N43+O43 -> 9892.9295 | T43: =IFERROR(S43/K43,0) -> 3533.1891
B44: POTA ALAS PRE COC S/COD BL10 S20 | C44: 260 | D44: 260 | E44: 0 | G44: 10009334 | H44: =IFERROR(INDEX([1]Resumen!$K$3:$K$63,MATCH(G44,[1]Resumen!$C$3:$C$63,0)),0)*(1+I44*J44)/1000-51.89/1000 -> 2.7569568 | I44: 0.68 | J44: =$H$59 -> -0.10285454 | K44: =IF(E44<0,0,E44)/1000 -> 0 | L44: =IFERROR(H44*K44,0)*1000 -> 0 | M44: =207.84*K44 -> 0 | N44: =$N$54/$K$52*K44 -> 0 | O44: =$O$54/$K$52*K44 -> 0 | P44: =$P$54/$K$52*K44 -> 0 | Q44: 0 | R44: 0 | S44: =L44+M44+N44+O44 -> 0 | T44: =IFERROR(S44/K44,0) -> 0
B45: POTA ALAS PRE COC 0.3up BL9 S18 | C45: 60956 | D45: 54000 | E45: 6956 | G45: 10009334 | H45: =IFERROR(INDEX([1]Resumen!$K$3:$K$63,MATCH(G45,[1]Resumen!$C$3:$C$63,0)),0)*(1+I45*J45)/1000-51.89/1000 -> 2.7569568 | I45: 0.68 | J45: =$H$59 -> -0.10285454 | K45: =IF(E45<0,0,E45)/1000 -> 6.956 | L45: =IFERROR(H45*K45,0)*1000 -> 19177.391 | M45: =207.84*K45 -> 1445.735 | N45: =$N$54/$K$52*K45 -> 313.79613 | O45: =$O$54/$K$52*K45 -> 616.87003 | P45: =$P$54/$K$52*K45 -> 493.12045 | Q45: 0 | R45: 0 | S45: =L45+M45+N45+O45 -> 21553.793 | T45: =IFERROR(S45/K45,0) -> 3098.5901
B46: POTA ALAS PRE COC B BL9 S18 | C46: 7670 | E46: 7670 | G46: 10009334 | H46: =IFERROR(INDEX([1]Resumen!$K$3:$K$63,MATCH(G46,[1]Resumen!$C$3:$C$63,0)),0)*(1+I46*J46)/1000-51.89/1000 -> 2.7569568 | I46: 0.68 | J46: =$H$59 -> -0.10285454 | K46: =IF(E46<0,0,E46)/1000 -> 7.67 | L46: =IFERROR(H46*K46,0)*1000 -> 21145.858 | M46: =207.84*K46 -> 1594.1328 | N46: =$N$54/$K$52*K46 -> 346.0058 | O46: =$O$54/$K$52*K46 -> 680.18878 | P46: =$P$54/$K$52*K46 -> 543.73689 | Q46: 0 | R46: 0 | S46: =L46+M46+N46+O46 -> 23766.186 | T46: =IFERROR(S46/K46,0) -> 3098.5901
B47: POTA RECORTES PRE COC BL10 S20 | C47: 35980 | D47: 27000 | E47: 8980 | G47: 10007050 | H47: =IFERROR(INDEX([1]Resumen!$K$3:$K$63,MATCH(G47,[1]Resumen!$C$3:$C$63,0)),0)*(1+I47*J47)/1000-51.89/1000 -> 1.4088571 | I47: 0.68 | J47: =$H$59 -> -0.10285454 | K47: =IF(E47<0,0,E47)/1000 -> 8.98 | L47: =IFERROR(H47*K47,0)*1000 -> 12651.537 | M47: =207.84*K47 -> 1866.4032 | N47: =$N$54/$K$52*K47 -> 405.10197 | O47: =$O$54/$K$52*K47 -> 796.36183 | P47: =$P$54/$K$52*K47 -> 636.6046 | Q47: 0 | R47: 0 | S47: =L47+M47+N47+O47 -> 15719.404 | T47: =IFERROR(S47/K47,0) -> 1750.4904
B48: POTA RECORTES LAM PRE COC (M) BL7.5 S15 | C48: 70280 | D48: 81000 | E48: -10720 | G48: 10007050 | H48: =IFERROR(INDEX([1]Resumen!$K$3:$K$63,MATCH(G48,[1]Resumen!$C$3:$C$63,0)),0)*(1+I48*J48)/1000-51.89/1000 -> 1.4088571 | I48: 0.68 | J48: =$H$59 -> -0.10285454 | K48: =IF(E48<0,0,E48)/1000 -> 0 | L48: =IFERROR(H48*K48,0)*1000 -> 0 | M48: =207.84*K48 -> 0 | N48: =$N$54/$K$52*K48 -> 0 | O48: =$O$54/$K$52*K48 -> 0 | P48: =$P$54/$K$52*K48 -> 0 | Q48: 0 | R48: 0 | S48: =L48+M48+N48+O48 -> 0 | T48: =IFERROR(S48/K48,0) -> 0
B49: POTA RECORTES LAM PRE COC (T) BL7.5 S15 | C49: 56715 | D49: 54000 | E49: 2715 | G49: 10007050 | H49: =IFERROR(INDEX([1]Resumen!$K$3:$K$63,MATCH(G49,[1]Resumen!$C$3:$C$63,0)),0)*(1+I49*J49)/1000-51.89/1000 -> 1.4088571 | I49: 0.68 | J49: =$H$59 -> -0.10285454 | K49: =IF(E49<0,0,E49)/1000 -> 2.715 | L49: =IFERROR(H49*K49,0)*1000 -> 3825.0471 | M49: =207.84*K49 -> 564.2856 | N49: =$N$54/$K$52*K49 -> 122.47793 | O49: =$O$54/$K$52*K49 -> 240.77086 | P49: =$P$54/$K$52*K49 -> 192.4701 | Q49: 0 | R49: 0 | S49: =L49+M49+N49+O49 -> 4752.5815 | T49: =IFERROR(S49/K49,0) -> 1750.4904
B50: FILETE CM CT PARA REPROCESO | C50: 375260 | E50: 412786 | G50: 10005721 | H50: =IFERROR(INDEX([1]Resumen!$K$3:$K$63,MATCH(G50,[1]Resumen!$C$3:$C$63,0)),0)*(1+I50*J50)/1000-51.89/1000 -> 1.9375523 | I50: 0.67 | J50: =$H$59 -> -0.10285454 | K50: =IF(E50<0,0,E50)/1000 -> 412.786 | L50: =IFERROR(H50*K50,0)*1000 -> 799794.45 | M50: =207.84*K50 -> 85793.442 | N50: =$N$54/$K$52*K50 -> 18621.428 | O50: =$O$54/$K$52*K50 -> 36606.572 | P50: =$P$54/$K$52*K50 -> 29262.97 | Q50: 0 | R50: 0 | S50: =L50+M50+N50+O50 -> 940815.89 | T50: =IFERROR(S50/K50,0) -> 2279.1856
B51: ALAS FR PARA REPROCESO | C51: 472540 | E51: 519794 | G51: 10006719 | H51: =IFERROR(INDEX([1]Resumen!$K$3:$K$63,MATCH(G51,[1]Resumen!$C$3:$C$63,0)),0)*(1+I51*J51)/1000-51.89/1000 -> 1.8351853 | I51: 0.71 | J51: =$H$59 -> -0.10285454 | K51: =IF(E51<0,0,E51)/1000 -> 519.794 | L51: =IFERROR(H51*K51,0)*1000 -> 953918.28 | M51: =207.84*K51 -> 108033.98 | N51: =$N$54/$K$52*K51 -> 23448.727 | O51: =$O$54/$K$52*K51 -> 46096.225 | P51: =$P$54/$K$52*K51 -> 36848.915 | Q51: 0 | R51: 0 | S51: =L51+M51+N51+O51 -> 1131497.2 | T51: =IFERROR(S51/K51,0) -> 2176.8186
B52: TOTAL LIBRE | C52: 2374461 | D52: 768380 | E52: 1741881 | K52: =SUM(K2:K51) -> 1741.881 | L52: =SUM(L2:L51) -> 3100086.8 | M52: =SUM(M2:M51) -> 362032.55 | N52: =SUM(N2:N51) -> 78579 | O52: =SUM(O2:O51) -> 154473 | P52: =SUM(P2:P51) -> 123484.35 | Q52: =SUM(Q2:Q51) -> 0 | R52: =SUM(R2:R51) -> 0 | S52: =SUM(S2:S51) -> 3695171.3 | T52: =IFERROR(S52/K52,0) -> 2121.3684
M54: totales | N54: 78579 | O54: 154473 | P54: 123484.35
G55: COSTO ABRIL | H55: 3.52
G56: JUNIO | H56: 3.301 | I56: 3644 | J56: =I56/$I$58 -> 0.72958795
G57: JULIO | H57: 2.772 | I57: =2251*0.6 -> 1350.6 | J57: =I57/$I$58 -> 0.27041205
G58: PROM JUN Y JUL | H58: =H56*J56+H57*J57 -> 3.157952 | I58: =I56+I57 -> 4994.6
G59: TASA | H59: =(H58-H55)/H55 -> -0.10285454
