Workbook

Sheet RESUMEN AL 6-7-2026
C2: PERU FROST
C3: AVANCE COMERCIAL AL 13-7-2026
F5: RENTABILIDAD DEL INVENTARIO | X5: 46206 | AA5: 46209 | AD5: 46215 | AG5: 46216 | AJ5: 46218 | AM5: 46220 | AP5: 46227 | AS5: TBN | BN5: TOTAL PROYECTADO JULIO 2026 | CB5: UNITARIOS POR TM
B6: Código | C6: Producto | D6: TM en Stock Libre | E6: CU | F6: Costo Ventas | G6: Gasto Ventas | H6: Gasto ADM | I6: Gasto Fin | J6: Depreciación | K6: Utilidad Neta | L6: Margen Neto | M6: Venta Equilibrio a Utd Neta | N6: Precio Equilibrio x TM a Utd Neta | O6: Venta Equilibro a EBITDA | P6: Precio Equilibrio x TM a EBITDA | Q6: Precio Mercado | R6: Venta total | S6: Utilidad | T6: Mg Neto | U6: EBITDA | V6: Mg EBITDA | X6: TM | Y6: Venta | Z6: Precio x TM | AA6: TM | AB6: Venta | AC6: Precio x TM | AD6: TM | AE6: Venta | AF6: Precio x TM | AG6: TM | AH6: Venta | AI6: Precio x TM | AJ6: TM | AK6: Venta | AL6: Precio x TM | AM6: TM | AN6: Venta | AO6: Precio x TM | AP6: TM | AQ6: Venta | AR6: Precio x TM | AS6: TM | AT6: Venta | AU6: Precio x TM | AV6: TM | AW6: Venta | AX6: Precio x TM | AY6: TM | AZ6: Venta | BA6: Precio x TM | BB6: TM | BC6: Venta | BD6: Precio x TM | BE6: TM | BF6: Venta | BG6: Precio x TM | BH6: TM | BI6: Venta | BJ6: Precio x TM | BK6: TM | BL6: Venta | BM6: Precio x TM | BN6: TM | BO6: Venta | BP6: Precio x TM | BQ6: Costo Ventas | BR6: Gasto Ventas | BS6: Gasto Adm | BT6: Gasto Fin | BU6: Depreciación | BV6: Drawback | BW6: Utilidad Neta | BX6: Mg Neto % | BY6: EBITDA | BZ6: MG EBITDA | CB6: Precio x TM | CC6: Costo Ventas | CD6: Gasto Ventas | CE6: Gasto Adm | CF6: Gasto Fin | CG6: Depreciación | CH6: Drawback | CI6: Utilidad Neta | CJ6: EBITDA
B7: 10005721 | C7: POTA FILETE CONGELADO | D7: =TD!F4 -> 377.674 | E7: =IFERROR(F7/D7,0) -> 1984.5862 | F7: =TD!G4 -> 749526.6 | G7: =TD!H4 -> 78495.764 | H7: =TD!I4 -> 17191.005 | I7: =TD!J4 -> 33794.604 | J7: =TD!K4 -> 27015.107 | K7: 0 | L7: 0 | M7: =F7+G7+H7+I7 -> 879007.97 | N7: =IFERROR(M7/D7,0) -> 2327.4252 | O7: =F7+G7+H7-J7 -> 818198.26 | P7: =IFERROR(O7/D7,0) -> 2166.4141 | Q7: 1800 | R7: =Q7*D7 -> 679813.2 | S7: =R7-M7+(Q7-$BS$19)*D7*0.03 -> -180094.03 | T7: =IFERROR(S7/R7,0) -> -0.26491694 | U7: =R7-(M7-J7-I7)+(Q7-$BS$19)*D7*0.03 -> -119284.32 | V7: =IFERROR(U7/R7,0) -> -0.17546632 | X7: {=SUM([6]Hoja3!$I$5:$I$19*([6]Hoja3!$F$5:$F$19=X$5)*([6]Hoja3!$K$5:$K$19=$C7))} -> 0 | Y7: {=SUM([6]Hoja3!$J$5:$J$19*([6]Hoja3!$F$5:$F$19=X$5)*([6]Hoja3!$K$5:$K$19=$C7))} -> 0 | Z7: =IFERROR(Y7/X7,0) -> 0 | AA7: {=SUM([6]Hoja3!$I$5:$I$19*([6]Hoja3!$F$5:$F$19=AA$5)*([6]Hoja3!$K$5:$K$19=$C7))} -> 0 | AB7: {=SUM([6]Hoja3!$J$5:$J$19*([6]Hoja3!$F$5:$F$19=AA$5)*([6]Hoja3!$K$5:$K$19=$C7))} -> 0 | AC7: =IFERROR(AB7/AA7,0) -> 0 | AD7: {=SUM([6]Hoja3!$I$5:$I$19*([6]Hoja3!$F$5:$F$19=AD$5)*([6]Hoja3!$K$5:$K$19=$C7))} -> 0 | AE7: {=SUM([6]Hoja3!$J$5:$J$19*([6]Hoja3!$F$5:$F$19=AD$5)*([6]Hoja3!$K$5:$K$19=$C7))} -> 0 | AF7: =IFERROR(AE7/AD7,0) -> 0 | AG7: {=SUM([6]Hoja3!$I$5:$I$19*([6]Hoja3!$F$5:$F$19=AG$5)*([6]Hoja3!$K$5:$K$19=$C7))} -> 0 | AH7: {=SUM([6]Hoja3!$J$5:$J$19*([6]Hoja3!$F$5:$F$19=AG$5)*([6]Hoja3!$K$5:$K$19=$C7))} -> 0 | AI7: =IFERROR(AH7/AG7,0) -> 0 | AJ7: {=SUM([6]Hoja3!$I$5:$I$19*([6]Hoja3!$F$5:$F$19=AJ$5)*([6]Hoja3!$K$5:$K$19=$C7))} -> 270 | AK7: {=SUM([6]Hoja3!$J$5:$J$19*([6]Hoja3!$F$5:$F$19=AJ$5)*([6]Hoja3!$K$5:$K$19=$C7))} -> 405000 | AL7: =IFERROR(AK7/AJ7,0) -> 1500 | AM7: {=SUM([6]Hoja3!$I$5:$I$19*([6]Hoja3!$F$5:$F$19=AM$5)*([6]Hoja3!$K$5:$K$19=$C7))} -> 0 | AN7: {=SUM([6]Hoja3!$J$5:$J$19*([6]Hoja3!$F$5:$F$19=AM$5)*([6]Hoja3!$K$5:$K$19=$C7))} -> 0 | AO7: =IFERROR(AN7/AM7,0) -> 0 | AP7: {=SUM([6]Hoja3!$I$5:$I$19*([6]Hoja3!$F$5:$F$19=AP$5)*([6]Hoja3!$K$5:$K$19=$C7))} -> 0 | AQ7: {=SUM([6]Hoja3!$J$5:$J$19*([6]Hoja3!$F$5:$F$19=AP$5)*([6]Hoja3!$K$5:$K$19=$C7))} -> 0 | AR7: =IFERROR(AQ7/AP7,0) -> 0 | AS7: {=SUM([6]Hoja3!$I$5:$I$19*([6]Hoja3!$F$5:$F$19=AS$5)*([6]Hoja3!$K$5:$K$19=$C7))} -> 294 | AT7: {=SUM([6]Hoja3!$J$5:$J$19*([6]Hoja3!$F$5:$F$19=AS$5)*([6]Hoja3!$K$5:$K$19=$C7))} -> 460200 | AU7: =IFERROR(AT7/AS7,0) -> 1565.3061 | AV7: {=SUM([2]Hoja2!$I$6:$I$26*([2]Hoja2!$F$6:$F$26=AV$5)*([2]Hoja2!$K$6:$K$26=$C7))} -> 0 | AW7: {=SUM([2]Hoja2!$J$6:$J$26*([2]Hoja2!$F$6:$F$26=AV$5)*([2]Hoja2!$K$6:$K$26=$C7))} -> 0 | AX7: =IFERROR(AW7/AV7,0) -> 0 | AY7: {=SUM([2]Hoja2!$I$6:$I$26*([2]Hoja2!$F$6:$F$26=AY$5)*([2]Hoja2!$K$6:$K$26=$C7))} -> 0 | AZ7: {=SUM([2]Hoja2!$J$6:$J$26*([2]Hoja2!$F$6:$F$26=AY$5)*([2]Hoja2!$K$6:$K$26=$C7))} -> 0 | BA7: =IFERROR(AZ7/AY7,0) -> 0 | BB7: {=SUM([2]Hoja2!$I$6:$I$26*([2]Hoja2!$F$6:$F$26=BB$5)*([2]Hoja2!$K$6:$K$26=$C7))} -> 0 | BC7: {=SUM([2]Hoja2!$J$6:$J$26*([2]Hoja2!$F$6:$F$26=BB$5)*([2]Hoja2!$K$6:$K$26=$C7))} -> 0 | BD7: =IFERROR(BC7/BB7,0) -> 0 | BE7: {=SUM([2]Hoja2!$I$6:$I$26*([2]Hoja2!$F$6:$F$26=BE$5)*([2]Hoja2!$K$6:$K$26=$C7))} -> 0 | BF7: {=SUM([2]Hoja2!$J$6:$J$26*([2]Hoja2!$F$6:$F$26=BE$5)*([2]Hoja2!$K$6:$K$26=$C7))} -> 0 | BG7: =IFERROR(BF7/BE7,0) -> 0 | BH7: {=SUM([2]Hoja2!$I$6:$I$26*([2]Hoja2!$F$6:$F$26=BH$5)*([2]Hoja2!$K$6:$K$26=$C7))} -> 0 | BI7: {=SUM([2]Hoja2!$J$6:$J$26*([2]Hoja2!$F$6:$F$26=BH$5)*([2]Hoja2!$K$6:$K$26=$C7))} -> 0 | BJ7: =IFERROR(BI7/BH7,0) -> 0 | BK7: {=SUM([2]Hoja2!$I$6:$I$26*([2]Hoja2!$F$6:$F$26=BK$5)*([2]Hoja2!$K$6:$K$26=$C7))} -> 0 | BL7: {=SUM([2]Hoja2!$J$6:$J$26*([2]Hoja2!$F$6:$F$26=BK$5)*([2]Hoja2!$K$6:$K$26=$C7))} -> 0 | BM7: =IFERROR(BL7/BK7,0) -> 0 | BN7: =X7+AA7+AD7+AG7+AJ7+AM7+AP7+AS7 -> 564 | BO7: =Y7+AB7+AE7+AH7+AK7+AN7+AQ7+AT7 -> 865200 | BP7: =IFERROR(BO7/BN7,0) -> 1534.0426 | BQ7: =-IFERROR(F7/D7*BN7,0) -> -1119306.6 | BR7: =-207.84*BN7 -> -117221.76 | BS7: =$BS$18/$BN$18*$BN7 -> -55398.195 | BT7: =$BT$18/$BN$18*$BN7 -> -108903.47 | BU7: =$BU$18/$BN$18*$BN7 -> -87056.467 | BV7: =(BO7-BN7*$BS$19)*0.03 -> 24024.115 | BW7: =BO7+SUM(BQ7:BT7,BV7) -> -511605.91 | BX7: =IFERROR(BW7/BO7,0) -> -0.5913152 | BY7: =BO7+BQ7+BR7+BS7+BV7-BU7 -> -315645.98 | BZ7: =IFERROR(BY7/BO7,0) -> -0.36482429 | CB7: =BP7 -> 1534.0426 | CC7: =IFERROR(BQ7/$BN7,0) -> -1984.5862 | CD7: =IFERROR(BR7/$BN7,0) -> -207.84 | CE7: =IFERROR(BS7/$BN7,0) -> -98.22375 | CF7: =IFERROR(BT7/$BN7,0) -> -193.09125 | CG7: =IFERROR(BU7/$BN7,0) -> -154.35544 | CH7: =IFERROR(BV7/$BN7,0) -> 42.595948 | CI7: =IFERROR(BW7/$BN7,0) -> -907.10267 | CJ7: =IFERROR(BY7/$BN7,0) -> -559.65598 | CK7: =CJ7-CI7 -> 347.44669
B8: 10005779 | C8: POTA NUCAS CONGELADAS | D8: =TD!F5 -> 329.24 | E8: =IFERROR(F8/D8,0) -> 1622.0104 | F8: =TD!G5 -> 534030.7 | G8: =TD!H5 -> 68429.242 | H8: =TD!I5 -> 14986.381 | I8: =TD!J5 -> 29460.687 | J8: =TD!K5 -> 23550.612 | K8: 0 | L8: 0 | M8: =F8+G8+H8+I8 -> 646907.01 | N8: =IFERROR(M8/D8,0) -> 1964.8494 | O8: =F8+G8+H8-J8 -> 593895.71 | P8: =IFERROR(O8/D8,0) -> 1803.8383 | Q8: 1300 | R8: =Q8*D8 -> 428012 | S8: =R8-M8+(Q8-$BS$19)*D8*0.03 -> -207182.41 | T8: =IFERROR(S8/R8,0) -> -0.48405747 | U8: =R8-(M8-J8-I8)+(Q8-$BS$19)*D8*0.03 -> -154171.11 | V8: =IFERROR(U8/R8,0) -> -0.36020277 | X8: {=SUM([6]Hoja3!$I$5:$I$19*([6]Hoja3!$F$5:$F$19=X$5)*([6]Hoja3!$K$5:$K$19=$C8))} -> 0 | Y8: {=SUM([6]Hoja3!$J$5:$J$19*([6]Hoja3!$F$5:$F$19=X$5)*([6]Hoja3!$K$5:$K$19=$C8))} -> 0 | Z8: =IFERROR(Y8/X8,0) -> 0 | AA8: {=SUM([6]Hoja3!$I$5:$I$19*([6]Hoja3!$F$5:$F$19=AA$5)*([6]Hoja3!$K$5:$K$19=$C8))} -> 0 | AB8: {=SUM([6]Hoja3!$J$5:$J$19*([6]Hoja3!$F$5:$F$19=AA$5)*([6]Hoja3!$K$5:$K$19=$C8))} -> 0 | AC8: =IFERROR(AB8/AA8,0) -> 0 | AD8: {=SUM([6]Hoja3!$I$5:$I$19*([6]Hoja3!$F$5:$F$19=AD$5)*([6]Hoja3!$K$5:$K$19=$C8))} -> 0 | AE8: {=SUM([6]Hoja3!$J$5:$J$19*([6]Hoja3!$F$5:$F$19=AD$5)*([6]Hoja3!$K$5:$K$19=$C8))} -> 0 | AF8: =IFERROR(AE8/AD8,0) -> 0 | AG8: {=SUM([6]Hoja3!$I$5:$I$19*([6]Hoja3!$F$5:$F$19=AG$5)*([6]Hoja3!$K$5:$K$19=$C8))} -> 0 | AH8: {=SUM([6]Hoja3!$J$5:$J$19*([6]Hoja3!$F$5:$F$19=AG$5)*([6]Hoja3!$K$5:$K$19=$C8))} -> 0 | AI8: =IFERROR(AH8/AG8,0) -> 0 | AJ8: {=SUM([6]Hoja3!$I$5:$I$19*([6]Hoja3!$F$5:$F$19=AJ$5)*([6]Hoja3!$K$5:$K$19=$C8))} -> 0 | AK8: {=SUM([6]Hoja3!$J$5:$J$19*([6]Hoja3!$F$5:$F$19=AJ$5)*([6]Hoja3!$K$5:$K$19=$C8))} -> 0 | AL8: =IFERROR(AK8/AJ8,0) -> 0 | AM8: {=SUM([6]Hoja3!$I$5:$I$19*([6]Hoja3!$F$5:$F$19=AM$5)*([6]Hoja3!$K$5:$K$19=$C8))} -> 0 | AN8: {=SUM([6]Hoja3!$J$5:$J$19*([6]Hoja3!$F$5:$F$19=AM$5)*([6]Hoja3!$K$5:$K$19=$C8))} -> 0 | AO8: =IFERROR(AN8/AM8,0) -> 0 | AP8: {=SUM([6]Hoja3!$I$5:$I$19*([6]Hoja3!$F$5:$F$19=AP$5)*([6]Hoja3!$K$5:$K$19=$C8))} -> 0 | AQ8: {=SUM([6]Hoja3!$J$5:$J$19*([6]Hoja3!$F$5:$F$19=AP$5)*([6]Hoja3!$K$5:$K$19=$C8))} -> 0 | AR8: =IFERROR(AQ8/AP8,0) -> 0 | AS8: {=SUM([6]Hoja3!$I$5:$I$19*([6]Hoja3!$F$5:$F$19=AS$5)*([6]Hoja3!$K$5:$K$19=$C8))} -> 52 | AT8: {=SUM([6]Hoja3!$J$5:$J$19*([6]Hoja3!$F$5:$F$19=AS$5)*([6]Hoja3!$K$5:$K$19=$C8))} -> 67600 | AU8: =IFERROR(AT8/AS8,0) -> 1300 | AV8: {=SUM([2]Hoja2!$I$6:$I$26*([2]Hoja2!$F$6:$F$26=AV$5)*([2]Hoja2!$K$6:$K$26=$C8))} -> 0 | AW8: {=SUM([2]Hoja2!$J$6:$J$26*([2]Hoja2!$F$6:$F$26=AV$5)*([2]Hoja2!$K$6:$K$26=$C8))} -> 0 | AX8: =IFERROR(AW8/AV8,0) -> 0 | AY8: {=SUM([2]Hoja2!$I$6:$I$26*([2]Hoja2!$F$6:$F$26=AY$5)*([2]Hoja2!$K$6:$K$26=$C8))} -> 0 | AZ8: {=SUM([2]Hoja2!$J$6:$J$26*([2]Hoja2!$F$6:$F$26=AY$5)*([2]Hoja2!$K$6:$K$26=$C8))} -> 0 | BA8: =IFERROR(AZ8/AY8,0) -> 0 | BB8: {=SUM([2]Hoja2!$I$6:$I$26*([2]Hoja2!$F$6:$F$26=BB$5)*([2]Hoja2!$K$6:$K$26=$C8))} -> 0 | BC8: {=SUM([2]Hoja2!$J$6:$J$26*([2]Hoja2!$F$6:$F$26=BB$5)*([2]Hoja2!$K$6:$K$26=$C8))} -> 0 | BD8: =IFERROR(BC8/BB8,0) -> 0 | BE8: {=SUM([2]Hoja2!$I$6:$I$26*([2]Hoja2!$F$6:$F$26=BE$5)*([2]Hoja2!$K$6:$K$26=$C8))} -> 0 | BF8: {=SUM([2]Hoja2!$J$6:$J$26*([2]Hoja2!$F$6:$F$26=BE$5)*([2]Hoja2!$K$6:$K$26=$C8))} -> 0 | BG8: =IFERROR(BF8/BE8,0) -> 0 | BH8: {=SUM([2]Hoja2!$I$6:$I$26*([2]Hoja2!$F$6:$F$26=BH$5)*([2]Hoja2!$K$6:$K$26=$C8))} -> 0 | BI8: {=SUM([2]Hoja2!$J$6:$J$26*([2]Hoja2!$F$6:$F$26=BH$5)*([2]Hoja2!$K$6:$K$26=$C8))} -> 0 | BJ8: =IFERROR(BI8/BH8,0) -> 0 | BK8: {=SUM([2]Hoja2!$I$6:$I$26*([2]Hoja2!$F$6:$F$26=BK$5)*([2]Hoja2!$K$6:$K$26=$C8))} -> 0 | BL8: {=SUM([2]Hoja2!$J$6:$J$26*([2]Hoja2!$F$6:$F$26=BK$5)*([2]Hoja2!$K$6:$K$26=$C8))} -> 0 | BM8: =IFERROR(BL8/BK8,0) -> 0 | BN8: =X8+AA8+AD8+AG8+AJ8+AM8+AP8+AS8 -> 52 | BO8: =Y8+AB8+AE8+AH8+AK8+AN8+AQ8+AT8 -> 67600 | BP8: =IFERROR(BO8/BN8,0) -> 1300 | BQ8: =-IFERROR(F8/D8*BN8,0) -> -84344.541 | BR8: =-207.84*BN8 -> -10807.68 | BS8: =$BS$18/$BN$18*$BN8 -> -5107.635 | BT8: =$BT$18/$BN$18*$BN8 -> -10040.745 | BU8: =$BU$18/$BN$18*$BN8 -> -8026.4828 | BV8: =(BO8-BN8*$BS$19)*0.03 -> 1849.8829 | BW8: =BO8+SUM(BQ8:BT8,BV8) -> -40850.718 | BX8: =IFERROR(BW8/BO8,0) -> -0.60430056 | BY8: =BO8+BQ8+BR8+BS8+BV8-BU8 -> -22783.49 | BZ8: =IFERROR(BY8/BO8,0) -> -0.33703387 | CB8: =BP8 -> 1300 | CC8: =IFERROR(BQ8/$BN8,0) -> -1622.0104 | CD8: =IFERROR(BR8/$BN8,0) -> -207.84 | CE8: =IFERROR(BS8/$BN8,0) -> -98.22375 | CF8: =IFERROR(BT8/$BN8,0) -> -193.09125 | CG8: =IFERROR(BU8/$BN8,0) -> -154.35544 | CH8: =IFERROR(BV8/$BN8,0) -> 35.574672 | CI8: =IFERROR(BW8/$BN8,0) -> -785.59072 | CJ8: =IFERROR(BY8/$BN8,0) -> -438.14404 | CK8: =CJ8-CI8 -> 347.44669
B9: 10006719 | C9: POTA ALAS CONGELADAS | D9: =TD!F6 -> 487.452 | E9: =IFERROR(F9/D9,0) -> 1882.6724 | F9: =TD!G6 -> 917712.41 | G9: =TD!H6 -> 101312.02 | H9: =TD!I6 -> 22187.892 | I9: =TD!J6 -> 43617.637 | J9: =TD!K6 -> 34867.553 | K9: 0 | L9: 0 | M9: =F9+G9+H9+I9 -> 1084830 | N9: =IFERROR(M9/D9,0) -> 2225.5114 | O9: =F9+G9+H9-J9 -> 1006344.8 | P9: =IFERROR(O9/D9,0) -> 2064.5002 | Q9: 1750 | R9: =Q9*D9 -> 853041 | S9: =R9-M9+(Q9-$BS$19)*D9*0.03 -> -207867.41 | T9: =IFERROR(S9/R9,0) -> -0.2436781 | U9: =R9-(M9-J9-I9)+(Q9-$BS$19)*D9*0.03 -> -129382.22 | V9: =IFERROR(U9/R9,0) -> -0.15167175 | X9: {=SUM([6]Hoja3!$I$5:$I$19*([6]Hoja3!$F$5:$F$19=X$5)*([6]Hoja3!$K$5:$K$19=$C9))} -> 0 | Y9: {=SUM([6]Hoja3!$J$5:$J$19*([6]Hoja3!$F$5:$F$19=X$5)*([6]Hoja3!$K$5:$K$19=$C9))} -> 0 | Z9: =IFERROR(Y9/X9,0) -> 0 | AA9: {=SUM([6]Hoja3!$I$5:$I$19*([6]Hoja3!$F$5:$F$19=AA$5)*([6]Hoja3!$K$5:$K$19=$C9))} -> 0 | AB9: {=SUM([6]Hoja3!$J$5:$J$19*([6]Hoja3!$F$5:$F$19=AA$5)*([6]Hoja3!$K$5:$K$19=$C9))} -> 0 | AC9: =IFERROR(AB9/AA9,0) -> 0 | AD9: {=SUM([6]Hoja3!$I$5:$I$19*([6]Hoja3!$F$5:$F$19=AD$5)*([6]Hoja3!$K$5:$K$19=$C9))} -> 54 | AE9: {=SUM([6]Hoja3!$J$5:$J$19*([6]Hoja3!$F$5:$F$19=AD$5)*([6]Hoja3!$K$5:$K$19=$C9))} -> 94500 | AF9: =IFERROR(AE9/AD9,0) -> 1750 | AG9: {=SUM([6]Hoja3!$I$5:$I$19*([6]Hoja3!$F$5:$F$19=AG$5)*([6]Hoja3!$K$5:$K$19=$C9))} -> 0 | AH9: {=SUM([6]Hoja3!$J$5:$J$19*([6]Hoja3!$F$5:$F$19=AG$5)*([6]Hoja3!$K$5:$K$19=$C9))} -> 0 | AI9: =IFERROR(AH9/AG9,0) -> 0 | AJ9: {=SUM([6]Hoja3!$I$5:$I$19*([6]Hoja3!$F$5:$F$19=AJ$5)*([6]Hoja3!$K$5:$K$19=$C9))} -> 0 | AK9: {=SUM([6]Hoja3!$J$5:$J$19*([6]Hoja3!$F$5:$F$19=AJ$5)*([6]Hoja3!$K$5:$K$19=$C9))} -> 0 | AL9: =IFERROR(AK9/AJ9,0) -> 0 | AM9: {=SUM([6]Hoja3!$I$5:$I$19*([6]Hoja3!$F$5:$F$19=AM$5)*([6]Hoja3!$K$5:$K$19=$C9))} -> 0 | AN9: {=SUM([6]Hoja3!$J$5:$J$19*([6]Hoja3!$F$5:$F$19=AM$5)*([6]Hoja3!$K$5:$K$19=$C9))} -> 0 | AO9: =IFERROR(AN9/AM9,0) -> 0 | AP9: {=SUM([6]Hoja3!$I$5:$I$19*([6]Hoja3!$F$5:$F$19=AP$5)*([6]Hoja3!$K$5:$K$19=$C9))} -> 0 | AQ9: {=SUM([6]Hoja3!$J$5:$J$19*([6]Hoja3!$F$5:$F$19=AP$5)*([6]Hoja3!$K$5:$K$19=$C9))} -> 0 | AR9: =IFERROR(AQ9/AP9,0) -> 0 | AS9: {=SUM([6]Hoja3!$I$5:$I$19*([6]Hoja3!$F$5:$F$19=AS$5)*([6]Hoja3!$K$5:$K$19=$C9))} -> 0 | AT9: {=SUM([6]Hoja3!$J$5:$J$19*([6]Hoja3!$F$5:$F$19=AS$5)*([6]Hoja3!$K$5:$K$19=$C9))} -> 0 | AU9: =IFERROR(AT9/AS9,0) -> 0 | AV9: {=SUM([2]Hoja2!$I$6:$I$26*([2]Hoja2!$F$6:$F$26=AV$5)*([2]Hoja2!$K$6:$K$26=$C9))} -> 0 | AW9: {=SUM([2]Hoja2!$J$6:$J$26*([2]Hoja2!$F$6:$F$26=AV$5)*([2]Hoja2!$K$6:$K$26=$C9))} -> 0 | AX9: =IFERROR(AW9/AV9,0) -> 0 | AY9: {=SUM([2]Hoja2!$I$6:$I$26*([2]Hoja2!$F$6:$F$26=AY$5)*([2]Hoja2!$K$6:$K$26=$C9))} -> 0 | AZ9: {=SUM([2]Hoja2!$J$6:$J$26*([2]Hoja2!$F$6:$F$26=AY$5)*([2]Hoja2!$K$6:$K$26=$C9))} -> 0 | BA9: =IFERROR(AZ9/AY9,0) -> 0 | BB9: {=SUM([2]Hoja2!$I$6:$I$26*([2]Hoja2!$F$6:$F$26=BB$5)*([2]Hoja2!$K$6:$K$26=$C9))} -> 0 | BC9: {=SUM([2]Hoja2!$J$6:$J$26*([2]Hoja2!$F$6:$F$26=BB$5)*([2]Hoja2!$K$6:$K$26=$C9))} -> 0 | BD9: =IFERROR(BC9/BB9,0) -> 0 | BE9: {=SUM([2]Hoja2!$I$6:$I$26*([2]Hoja2!$F$6:$F$26=BE$5)*([2]Hoja2!$K$6:$K$26=$C9))} -> 0 | BF9: {=SUM([2]Hoja2!$J$6:$J$26*([2]Hoja2!$F$6:$F$26=BE$5)*([2]Hoja2!$K$6:$K$26=$C9))} -> 0 | BG9: =IFERROR(BF9/BE9,0) -> 0 | BH9: {=SUM([2]Hoja2!$I$6:$I$26*([2]Hoja2!$F$6:$F$26=BH$5)*([2]Hoja2!$K$6:$K$26=$C9))} -> 0 | BI9: {=SUM([2]Hoja2!$J$6:$J$26*([2]Hoja2!$F$6:$F$26=BH$5)*([2]Hoja2!$K$6:$K$26=$C9))} -> 0 | BJ9: =IFERROR(BI9/BH9,0) -> 0 | BK9: {=SUM([2]Hoja2!$I$6:$I$26*([2]Hoja2!$F$6:$F$26=BK$5)*([2]Hoja2!$K$6:$K$26=$C9))} -> 0 | BL9: {=SUM([2]Hoja2!$J$6:$J$26*([2]Hoja2!$F$6:$F$26=BK$5)*([2]Hoja2!$K$6:$K$26=$C9))} -> 0 | BM9: =IFERROR(BL9/BK9,0) -> 0 | BN9: =X9+AA9+AD9+AG9+AJ9+AM9+AP9+AS9 -> 54 | BO9: =Y9+AB9+AE9+AH9+AK9+AN9+AQ9+AT9 -> 94500 | BP9: =IFERROR(BO9/BN9,0) -> 1750 | BQ9: =-IFERROR(F9/D9*BN9,0) -> -101664.31 | BR9: =-207.84*BN9 -> -11223.36 | BS9: =$BS$18/$BN$18*$BN9 -> -5304.0825 | BT9: =$BT$18/$BN$18*$BN9 -> -10426.928 | BU9: =$BU$18/$BN$18*$BN9 -> -8335.1936 | BV9: =(BO9-BN9*$BS$19)*0.03 -> 2650.0323 | BW9: =BO9+SUM(BQ9:BT9,BV9) -> -31468.645 | BX9: =IFERROR(BW9/BO9,0) -> -0.33300154 | BY9: =BO9+BQ9+BR9+BS9+BV9-BU9 -> -12706.524 | BZ9: =IFERROR(BY9/BO9,0) -> -0.13446057 | CB9: =BP9 -> 1750 | CC9: =IFERROR(BQ9/$BN9,0) -> -1882.6724 | CD9: =IFERROR(BR9/$BN9,0) -> -207.84 | CE9: =IFERROR(BS9/$BN9,0) -> -98.22375 | CF9: =IFERROR(BT9/$BN9,0) -> -193.09125 | CG9: =IFERROR(BU9/$BN9,0) -> -154.35544 | CH9: =IFERROR(BV9/$BN9,0) -> 49.074672 | CI9: =IFERROR(BW9/$BN9,0) -> -582.75269 | CJ9: =IFERROR(BY9/$BN9,0) -> -235.306 | CK9: =CJ9-CI9 -> 347.44669
B10: 10007050 | C10: POTA RECORTES COCIDOS | D10: =TD!F7 -> 59.01 | E10: =IFERROR(F10/D10,0) -> 1443.946 | F10: =TD!G7 -> 85207.251 | G10: =TD!H7 -> 12264.638 | H10: =TD!I7 -> 2686.0235 | I10: =TD!J7 -> 5280.267 | J10: =TD!K7 -> 4220.9988 | K10: 0 | L10: 0 | M10: =F10+G10+H10+I10 -> 105438.18 | N10: =IFERROR(M10/D10,0) -> 1786.7849 | O10: =F10+G10+H10-J10 -> 95936.914 | P10: =IFERROR(O10/D10,0) -> 1625.7738 | Q10: 1700 | R10: =Q10*D10 -> 100317 | S10: =R10-M10+(Q10-$BS$19)*D10*0.03 -> -2313.7981 | T10: =IFERROR(S10/R10,0) -> -0.023064865 | U10: =R10-(M10-J10-I10)+(Q10-$BS$19)*D10*0.03 -> 7187.4677 | V10: =IFERROR(U10/R10,0) -> 0.071647554 | X10: {=SUM([6]Hoja3!$I$5:$I$19*([6]Hoja3!$F$5:$F$19=X$5)*([6]Hoja3!$K$5:$K$19=$C10))} -> 27 | Y10: {=SUM([6]Hoja3!$J$5:$J$19*([6]Hoja3!$F$5:$F$19=X$5)*([6]Hoja3!$K$5:$K$19=$C10))} -> 68850 | Z10: =IFERROR(Y10/X10,0) -> 2550 | AA10: {=SUM([6]Hoja3!$I$5:$I$19*([6]Hoja3!$F$5:$F$19=AA$5)*([6]Hoja3!$K$5:$K$19=$C10))} -> 0 | AB10: {=SUM([6]Hoja3!$J$5:$J$19*([6]Hoja3!$F$5:$F$19=AA$5)*([6]Hoja3!$K$5:$K$19=$C10))} -> 0 | AC10: =IFERROR(AB10/AA10,0) -> 0 | AD10: {=SUM([6]Hoja3!$I$5:$I$19*([6]Hoja3!$F$5:$F$19=AD$5)*([6]Hoja3!$K$5:$K$19=$C10))} -> 0 | AE10: {=SUM([6]Hoja3!$J$5:$J$19*([6]Hoja3!$F$5:$F$19=AD$5)*([6]Hoja3!$K$5:$K$19=$C10))} -> 0 | AF10: =IFERROR(AE10/AD10,0) -> 0 | AG10: {=SUM([6]Hoja3!$I$5:$I$19*([6]Hoja3!$F$5:$F$19=AG$5)*([6]Hoja3!$K$5:$K$19=$C10))} -> 0 | AH10: {=SUM([6]Hoja3!$J$5:$J$19*([6]Hoja3!$F$5:$F$19=AG$5)*([6]Hoja3!$K$5:$K$19=$C10))} -> 0 | AI10: =IFERROR(AH10/AG10,0) -> 0 | AJ10: {=SUM([6]Hoja3!$I$5:$I$19*([6]Hoja3!$F$5:$F$19=AJ$5)*([6]Hoja3!$K$5:$K$19=$C10))} -> 0 | AK10: {=SUM([6]Hoja3!$J$5:$J$19*([6]Hoja3!$F$5:$F$19=AJ$5)*([6]Hoja3!$K$5:$K$19=$C10))} -> 0 | AL10: =IFERROR(AK10/AJ10,0) -> 0 | AM10: {=SUM([6]Hoja3!$I$5:$I$19*([6]Hoja3!$F$5:$F$19=AM$5)*([6]Hoja3!$K$5:$K$19=$C10))} -> 0 | AN10: {=SUM([6]Hoja3!$J$5:$J$19*([6]Hoja3!$F$5:$F$19=AM$5)*([6]Hoja3!$K$5:$K$19=$C10))} -> 0 | AO10: =IFERROR(AN10/AM10,0) -> 0 | AP10: {=SUM([6]Hoja3!$I$5:$I$19*([6]Hoja3!$F$5:$F$19=AP$5)*([6]Hoja3!$K$5:$K$19=$C10))} -> 0 | AQ10: {=SUM([6]Hoja3!$J$5:$J$19*([6]Hoja3!$F$5:$F$19=AP$5)*([6]Hoja3!$K$5:$K$19=$C10))} -> 0 | AR10: =IFERROR(AQ10/AP10,0) -> 0 | AS10: {=SUM([6]Hoja3!$I$5:$I$19*([6]Hoja3!$F$5:$F$19=AS$5)*([6]Hoja3!$K$5:$K$19=$C10))} -> 0 | AT10: {=SUM([6]Hoja3!$J$5:$J$19*([6]Hoja3!$F$5:$F$19=AS$5)*([6]Hoja3!$K$5:$K$19=$C10))} -> 0 | AU10: =IFERROR(AT10/AS10,0) -> 0 | AV10: {=SUM([2]Hoja2!$I$6:$I$26*([2]Hoja2!$F$6:$F$26=AV$5)*([2]Hoja2!$K$6:$K$26=$C10))} -> 0 | AW10: {=SUM([2]Hoja2!$J$6:$J$26*([2]Hoja2!$F$6:$F$26=AV$5)*([2]Hoja2!$K$6:$K$26=$C10))} -> 0 | AX10: =IFERROR(AW10/AV10,0) -> 0 | AY10: {=SUM([2]Hoja2!$I$6:$I$26*([2]Hoja2!$F$6:$F$26=AY$5)*([2]Hoja2!$K$6:$K$26=$C10))} -> 0 | AZ10: {=SUM([2]Hoja2!$J$6:$J$26*([2]Hoja2!$F$6:$F$26=AY$5)*([2]Hoja2!$K$6:$K$26=$C10))} -> 0 | BA10: =IFERROR(AZ10/AY10,0) -> 0 | BB10: {=SUM([2]Hoja2!$I$6:$I$26*([2]Hoja2!$F$6:$F$26=BB$5)*([2]Hoja2!$K$6:$K$26=$C10))} -> 0 | BC10: {=SUM([2]Hoja2!$J$6:$J$26*([2]Hoja2!$F$6:$F$26=BB$5)*([2]Hoja2!$K$6:$K$26=$C10))} -> 0 | BD10: =IFERROR(BC10/BB10,0) -> 0 | BE10: {=SUM([2]Hoja2!$I$6:$I$26*([2]Hoja2!$F$6:$F$26=BE$5)*([2]Hoja2!$K$6:$K$26=$C10))} -> 0 | BF10: {=SUM([2]Hoja2!$J$6:$J$26*([2]Hoja2!$F$6:$F$26=BE$5)*([2]Hoja2!$K$6:$K$26=$C10))} -> 0 | BG10: =IFERROR(BF10/BE10,0) -> 0 | BH10: {=SUM([2]Hoja2!$I$6:$I$26*([2]Hoja2!$F$6:$F$26=BH$5)*([2]Hoja2!$K$6:$K$26=$C10))} -> 0 | BI10: {=SUM([2]Hoja2!$J$6:$J$26*([2]Hoja2!$F$6:$F$26=BH$5)*([2]Hoja2!$K$6:$K$26=$C10))} -> 0 | BJ10: =IFERROR(BI10/BH10,0) -> 0 | BK10: {=SUM([2]Hoja2!$I$6:$I$26*([2]Hoja2!$F$6:$F$26=BK$5)*([2]Hoja2!$K$6:$K$26=$C10))} -> 0 | BL10: {=SUM([2]Hoja2!$J$6:$J$26*([2]Hoja2!$F$6:$F$26=BK$5)*([2]Hoja2!$K$6:$K$26=$C10))} -> 0 | BM10: =IFERROR(BL10/BK10,0) -> 0 | BN10: =X10+AA10+AD10+AG10+AJ10+AM10+AP10+AS10 -> 27 | BO10: =Y10+AB10+AE10+AH10+AK10+AN10+AQ10+AT10 -> 68850 | BP10: =IFERROR(BO10/BN10,0) -> 2550 | BQ10: =-IFERROR(F10/D10*BN10,0) -> -38986.541 | BR10: =-207.84*BN10 -> -5611.68 | BS10: =$BS$18/$BN$18*$BN10 -> -2652.0413 | BT10: =$BT$18/$BN$18*$BN10 -> -5213.4638 | BU10: =$BU$18/$BN$18*$BN10 -> -4167.5968 | BV10: =(BO10-BN10*$BS$19)*0.03 -> 1973.0161 | BW10: =BO10+SUM(BQ10:BT10,BV10) -> 18359.29 | BX10: =IFERROR(BW10/BO10,0) -> 0.26665636 | BY10: =BO10+BQ10+BR10+BS10+BV10-BU10 -> 27740.351 | BZ10: =IFERROR(BY10/BO10,0) -> 0.40290996 | CB10: =BP10 -> 2550 | CC10: =IFERROR(BQ10/$BN10,0) -> -1443.946 | CD10: =IFERROR(BR10/$BN10,0) -> -207.84 | CE10: =IFERROR(BS10/$BN10,0) -> -98.22375 | CF10: =IFERROR(BT10/$BN10,0) -> -193.09125 | CG10: =IFERROR(BU10/$BN10,0) -> -154.35544 | CH10: =IFERROR(BV10/$BN10,0) -> 73.074672 | CI10: =IFERROR(BW10/$BN10,0) -> 679.97372 | CJ10: =IFERROR(BY10/$BN10,0) -> 1027.4204 | CK10: =CJ10-CI10 -> 347.44669
B11: 10007162 | C11: POTA REJOS CONGELADOS | D11: =TD!F8 -> 235.86 | E11: =IFERROR(F11/D11,0) -> 1740.6978 | F11: =TD!G8 -> 410560.98 | G11: =TD!H8 -> 49021.142 | H11: =TD!I8 -> 10735.901 | I11: =TD!J8 -> 21104.962 | J11: =TD!K8 -> 16871.12 | K11: 0 | L11: 0 | M11: =F11+G11+H11+I11 -> 491422.98 | N11: =IFERROR(M11/D11,0) -> 2083.5368 | O11: =F11+G11+H11-J11 -> 453446.9 | P11: =IFERROR(O11/D11,0) -> 1922.5257 | Q11: 2700 | R11: =Q11*D11 -> 636822 | S11: =R11-M11+(Q11-$BS$19)*D11*0.03 -> 163695.78 | T11: =IFERROR(S11/R11,0) -> 0.25705108 | U11: =R11-(M11-J11-I11)+(Q11-$BS$19)*D11*0.03 -> 201671.86 | V11: =IFERROR(U11/R11,0) -> 0.31668482 | X11: {=SUM([6]Hoja3!$I$5:$I$19*([6]Hoja3!$F$5:$F$19=X$5)*([6]Hoja3!$K$5:$K$19=$C11))} -> 0 | Y11: {=SUM([6]Hoja3!$J$5:$J$19*([6]Hoja3!$F$5:$F$19=X$5)*([6]Hoja3!$K$5:$K$19=$C11))} -> 0 | Z11: =IFERROR(Y11/X11,0) -> 0 | AA11: {=SUM([6]Hoja3!$I$5:$I$19*([6]Hoja3!$F$5:$F$19=AA$5)*([6]Hoja3!$K$5:$K$19=$C11))} -> 0 | AB11: {=SUM([6]Hoja3!$J$5:$J$19*([6]Hoja3!$F$5:$F$19=AA$5)*([6]Hoja3!$K$5:$K$19=$C11))} -> 0 | AC11: =IFERROR(AB11/AA11,0) -> 0 | AD11: {=SUM([6]Hoja3!$I$5:$I$19*([6]Hoja3!$F$5:$F$19=AD$5)*([6]Hoja3!$K$5:$K$19=$C11))} -> 108 | AE11: {=SUM([6]Hoja3!$J$5:$J$19*([6]Hoja3!$F$5:$F$19=AD$5)*([6]Hoja3!$K$5:$K$19=$C11))} -> 275400 | AF11: =IFERROR(AE11/AD11,0) -> 2550 | AG11: {=SUM([6]Hoja3!$I$5:$I$19*([6]Hoja3!$F$5:$F$19=AG$5)*([6]Hoja3!$K$5:$K$19=$C11))} -> 0 | AH11: {=SUM([6]Hoja3!$J$5:$J$19*([6]Hoja3!$F$5:$F$19=AG$5)*([6]Hoja3!$K$5:$K$19=$C11))} -> 0 | AI11: =IFERROR(AH11/AG11,0) -> 0 | AJ11: {=SUM([6]Hoja3!$I$5:$I$19*([6]Hoja3!$F$5:$F$19=AJ$5)*([6]Hoja3!$K$5:$K$19=$C11))} -> 0 | AK11: {=SUM([6]Hoja3!$J$5:$J$19*([6]Hoja3!$F$5:$F$19=AJ$5)*([6]Hoja3!$K$5:$K$19=$C11))} -> 0 | AL11: =IFERROR(AK11/AJ11,0) -> 0 | AM11: {=SUM([6]Hoja3!$I$5:$I$19*([6]Hoja3!$F$5:$F$19=AM$5)*([6]Hoja3!$K$5:$K$19=$C11))} -> 0 | AN11: {=SUM([6]Hoja3!$J$5:$J$19*([6]Hoja3!$F$5:$F$19=AM$5)*([6]Hoja3!$K$5:$K$19=$C11))} -> 0 | AO11: =IFERROR(AN11/AM11,0) -> 0 | AP11: {=SUM([6]Hoja3!$I$5:$I$19*([6]Hoja3!$F$5:$F$19=AP$5)*([6]Hoja3!$K$5:$K$19=$C11))} -> 0 | AQ11: {=SUM([6]Hoja3!$J$5:$J$19*([6]Hoja3!$F$5:$F$19=AP$5)*([6]Hoja3!$K$5:$K$19=$C11))} -> 0 | AR11: =IFERROR(AQ11/AP11,0) -> 0 | AS11: {=SUM([6]Hoja3!$I$5:$I$19*([6]Hoja3!$F$5:$F$19=AS$5)*([6]Hoja3!$K$5:$K$19=$C11))} -> 108 | AT11: {=SUM([6]Hoja3!$J$5:$J$19*([6]Hoja3!$F$5:$F$19=AS$5)*([6]Hoja3!$K$5:$K$19=$C11))} -> 299310 | AU11: =IFERROR(AT11/AS11,0) -> 2771.3889 | AV11: {=SUM([2]Hoja2!$I$6:$I$26*([2]Hoja2!$F$6:$F$26=AV$5)*([2]Hoja2!$K$6:$K$26=$C11))} -> 0 | AW11: {=SUM([2]Hoja2!$J$6:$J$26*([2]Hoja2!$F$6:$F$26=AV$5)*([2]Hoja2!$K$6:$K$26=$C11))} -> 0 | AX11: =IFERROR(AW11/AV11,0) -> 0 | AY11: {=SUM([2]Hoja2!$I$6:$I$26*([2]Hoja2!$F$6:$F$26=AY$5)*([2]Hoja2!$K$6:$K$26=$C11))} -> 0 | AZ11: {=SUM([2]Hoja2!$J$6:$J$26*([2]Hoja2!$F$6:$F$26=AY$5)*([2]Hoja2!$K$6:$K$26=$C11))} -> 0 | BA11: =IFERROR(AZ11/AY11,0) -> 0 | BB11: {=SUM([2]Hoja2!$I$6:$I$26*([2]Hoja2!$F$6:$F$26=BB$5)*([2]Hoja2!$K$6:$K$26=$C11))} -> 0 | BC11: {=SUM([2]Hoja2!$J$6:$J$26*([2]Hoja2!$F$6:$F$26=BB$5)*([2]Hoja2!$K$6:$K$26=$C11))} -> 0 | BD11: =IFERROR(BC11/BB11,0) -> 0 | BE11: {=SUM([2]Hoja2!$I$6:$I$26*([2]Hoja2!$F$6:$F$26=BE$5)*([2]Hoja2!$K$6:$K$26=$C11))} -> 0 | BF11: {=SUM([2]Hoja2!$J$6:$J$26*([2]Hoja2!$F$6:$F$26=BE$5)*([2]Hoja2!$K$6:$K$26=$C11))} -> 0 | BG11: =IFERROR(BF11/BE11,0) -> 0 | BH11: {=SUM([2]Hoja2!$I$6:$I$26*([2]Hoja2!$F$6:$F$26=BH$5)*([2]Hoja2!$K$6:$K$26=$C11))} -> 0 | BI11: {=SUM([2]Hoja2!$J$6:$J$26*([2]Hoja2!$F$6:$F$26=BH$5)*([2]Hoja2!$K$6:$K$26=$C11))} -> 0 | BJ11: =IFERROR(BI11/BH11,0) -> 0 | BK11: {=SUM([2]Hoja2!$I$6:$I$26*([2]Hoja2!$F$6:$F$26=BK$5)*([2]Hoja2!$K$6:$K$26=$C11))} -> 0 | BL11: {=SUM([2]Hoja2!$J$6:$J$26*([2]Hoja2!$F$6:$F$26=BK$5)*([2]Hoja2!$K$6:$K$26=$C11))} -> 0 | BM11: =IFERROR(BL11/BK11,0) -> 0 | BN11: =X11+AA11+AD11+AG11+AJ11+AM11+AP11+AS11 -> 216 | BO11: =Y11+AB11+AE11+AH11+AK11+AN11+AQ11+AT11 -> 574710 | BP11: =IFERROR(BO11/BN11,0) -> 2660.6944 | BQ11: =-IFERROR(F11/D11*BN11,0) -> -375990.72 | BR11: =-207.84*BN11 -> -44893.44 | BS11: =$BS$18/$BN$18*$BN11 -> -21216.33 | BT11: =$BT$18/$BN$18*$BN11 -> -41707.71 | BU11: =$BU$18/$BN$18*$BN11 -> -33340.775 | BV11: =(BO11-BN11*$BS$19)*0.03 -> 16501.429 | BW11: =BO11+SUM(BQ11:BT11,BV11) -> 107403.23 | BX11: =IFERROR(BW11/BO11,0) -> 0.18688248 | BY11: =BO11+BQ11+BR11+BS11+BV11-BU11 -> 182451.71 | BZ11: =IFERROR(BY11/BO11,0) -> 0.31746744 | CB11: =BP11 -> 2660.6944 | CC11: =IFERROR(BQ11/$BN11,0) -> -1740.6978 | CD11: =IFERROR(BR11/$BN11,0) -> -207.84 | CE11: =IFERROR(BS11/$BN11,0) -> -98.22375 | CF11: =IFERROR(BT11/$BN11,0) -> -193.09125 | CG11: =IFERROR(BU11/$BN11,0) -> -154.35544 | CH11: =IFERROR(BV11/$BN11,0) -> 76.395505 | CI11: =IFERROR(BW11/$BN11,0) -> 497.23718 | CJ11: =IFERROR(BY11/$BN11,0) -> 844.68386 | CK11: =CJ11-CI11 -> 347.44669
B12: 10007567 | C12: POTA REPRODUCTORES | D12: =TD!F9 -> 107.14 | E12: =IFERROR(F12/D12,0) -> 1682.6592 | F12: =TD!G9 -> 180280.11 | G12: =TD!H9 -> 22267.978 | H12: =TD!I9 -> 4876.8099 | I12: =TD!J9 -> 9586.9821 | J12: =TD!K9 -> 7663.7487 | K12: 0 | L12: 0 | M12: =F12+G12+H12+I12 -> 217011.88 | N12: =IFERROR(M12/D12,0) -> 2025.4982 | O12: =F12+G12+H12-J12 -> 199761.15 | P12: =IFERROR(O12/D12,0) -> 1864.4871 | Q12: 2730 | R12: =Q12*D12 -> 292492.2 | S12: =R12-M12+(Q12-$BS$19)*D12*0.03 -> 83888.099 | T12: =IFERROR(S12/R12,0) -> 0.28680457 | U12: =R12-(M12-J12-I12)+(Q12-$BS$19)*D12*0.03 -> 101138.83 | V12: =IFERROR(U12/R12,0) -> 0.345783 | X12: {=SUM([6]Hoja3!$I$5:$I$19*([6]Hoja3!$F$5:$F$19=X$5)*([6]Hoja3!$K$5:$K$19=$C12))} -> 0 | Y12: {=SUM([6]Hoja3!$J$5:$J$19*([6]Hoja3!$F$5:$F$19=X$5)*([6]Hoja3!$K$5:$K$19=$C12))} -> 0 | Z12: =IFERROR(Y12/X12,0) -> 0 | AA12: {=SUM([6]Hoja3!$I$5:$I$19*([6]Hoja3!$F$5:$F$19=AA$5)*([6]Hoja3!$K$5:$K$19=$C12))} -> 26 | AB12: {=SUM([6]Hoja3!$J$5:$J$19*([6]Hoja3!$F$5:$F$19=AA$5)*([6]Hoja3!$K$5:$K$19=$C12))} -> 74100 | AC12: =IFERROR(AB12/AA12,0) -> 2850 | AD12: {=SUM([6]Hoja3!$I$5:$I$19*([6]Hoja3!$F$5:$F$19=AD$5)*([6]Hoja3!$K$5:$K$19=$C12))} -> 0 | AE12: {=SUM([6]Hoja3!$J$5:$J$19*([6]Hoja3!$F$5:$F$19=AD$5)*([6]Hoja3!$K$5:$K$19=$C12))} -> 0 | AF12: =IFERROR(AE12/AD12,0) -> 0 | AG12: {=SUM([6]Hoja3!$I$5:$I$19*([6]Hoja3!$F$5:$F$19=AG$5)*([6]Hoja3!$K$5:$K$19=$C12))} -> 27 | AH12: {=SUM([6]Hoja3!$J$5:$J$19*([6]Hoja3!$F$5:$F$19=AG$5)*([6]Hoja3!$K$5:$K$19=$C12))} -> 73710 | AI12: =IFERROR(AH12/AG12,0) -> 2730 | AJ12: {=SUM([6]Hoja3!$I$5:$I$19*([6]Hoja3!$F$5:$F$19=AJ$5)*([6]Hoja3!$K$5:$K$19=$C12))} -> 0 | AK12: {=SUM([6]Hoja3!$J$5:$J$19*([6]Hoja3!$F$5:$F$19=AJ$5)*([6]Hoja3!$K$5:$K$19=$C12))} -> 0 | AL12: =IFERROR(AK12/AJ12,0) -> 0 | AM12: {=SUM([6]Hoja3!$I$5:$I$19*([6]Hoja3!$F$5:$F$19=AM$5)*([6]Hoja3!$K$5:$K$19=$C12))} -> 0 | AN12: {=SUM([6]Hoja3!$J$5:$J$19*([6]Hoja3!$F$5:$F$19=AM$5)*([6]Hoja3!$K$5:$K$19=$C12))} -> 0 | AO12: =IFERROR(AN12/AM12,0) -> 0 | AP12: {=SUM([6]Hoja3!$I$5:$I$19*([6]Hoja3!$F$5:$F$19=AP$5)*([6]Hoja3!$K$5:$K$19=$C12))} -> 0 | AQ12: {=SUM([6]Hoja3!$J$5:$J$19*([6]Hoja3!$F$5:$F$19=AP$5)*([6]Hoja3!$K$5:$K$19=$C12))} -> 0 | AR12: =IFERROR(AQ12/AP12,0) -> 0 | AS12: {=SUM([6]Hoja3!$I$5:$I$19*([6]Hoja3!$F$5:$F$19=AS$5)*([6]Hoja3!$K$5:$K$19=$C12))} -> 0 | AT12: {=SUM([6]Hoja3!$J$5:$J$19*([6]Hoja3!$F$5:$F$19=AS$5)*([6]Hoja3!$K$5:$K$19=$C12))} -> 0 | AU12: =IFERROR(AT12/AS12,0) -> 0 | AV12: {=SUM([2]Hoja2!$I$6:$I$26*([2]Hoja2!$F$6:$F$26=AV$5)*([2]Hoja2!$K$6:$K$26=$C12))} -> 0 | AW12: {=SUM([2]Hoja2!$J$6:$J$26*([2]Hoja2!$F$6:$F$26=AV$5)*([2]Hoja2!$K$6:$K$26=$C12))} -> 0 | AX12: =IFERROR(AW12/AV12,0) -> 0 | AY12: {=SUM([2]Hoja2!$I$6:$I$26*([2]Hoja2!$F$6:$F$26=AY$5)*([2]Hoja2!$K$6:$K$26=$C12))} -> 0 | AZ12: {=SUM([2]Hoja2!$J$6:$J$26*([2]Hoja2!$F$6:$F$26=AY$5)*([2]Hoja2!$K$6:$K$26=$C12))} -> 0 | BA12: =IFERROR(AZ12/AY12,0) -> 0 | BB12: {=SUM([2]Hoja2!$I$6:$I$26*([2]Hoja2!$F$6:$F$26=BB$5)*([2]Hoja2!$K$6:$K$26=$C12))} -> 0 | BC12: {=SUM([2]Hoja2!$J$6:$J$26*([2]Hoja2!$F$6:$F$26=BB$5)*([2]Hoja2!$K$6:$K$26=$C12))} -> 0 | BD12: =IFERROR(BC12/BB12,0) -> 0 | BE12: {=SUM([2]Hoja2!$I$6:$I$26*([2]Hoja2!$F$6:$F$26=BE$5)*([2]Hoja2!$K$6:$K$26=$C12))} -> 0 | BF12: {=SUM([2]Hoja2!$J$6:$J$26*([2]Hoja2!$F$6:$F$26=BE$5)*([2]Hoja2!$K$6:$K$26=$C12))} -> 0 | BG12: =IFERROR(BF12/BE12,0) -> 0 | BH12: {=SUM([2]Hoja2!$I$6:$I$26*([2]Hoja2!$F$6:$F$26=BH$5)*([2]Hoja2!$K$6:$K$26=$C12))} -> 0 | BI12: {=SUM([2]Hoja2!$J$6:$J$26*([2]Hoja2!$F$6:$F$26=BH$5)*([2]Hoja2!$K$6:$K$26=$C12))} -> 0 | BJ12: =IFERROR(BI12/BH12,0) -> 0 | BK12: {=SUM([2]Hoja2!$I$6:$I$26*([2]Hoja2!$F$6:$F$26=BK$5)*([2]Hoja2!$K$6:$K$26=$C12))} -> 0 | BL12: {=SUM([2]Hoja2!$J$6:$J$26*([2]Hoja2!$F$6:$F$26=BK$5)*([2]Hoja2!$K$6:$K$26=$C12))} -> 0 | BM12: =IFERROR(BL12/BK12,0) -> 0 | BN12: =X12+AA12+AD12+AG12+AJ12+AM12+AP12+AS12 -> 53 | BO12: =Y12+AB12+AE12+AH12+AK12+AN12+AQ12+AT12 -> 147810 | BP12: =IFERROR(BO12/BN12,0) -> 2788.8679 | BQ12: =-IFERROR(F12/D12*BN12,0) -> -89180.938 | BR12: =-207.84*BN12 -> -11015.52 | BS12: =$BS$18/$BN$18*$BN12 -> -5205.8588 | BT12: =$BT$18/$BN$18*$BN12 -> -10233.836 | BU12: =$BU$18/$BN$18*$BN12 -> -8180.8382 | BV12: =(BO12-BN12*$BS$19)*0.03 -> 4252.7576 | BW12: =BO12+SUM(BQ12:BT12,BV12) -> 36426.605 | BX12: =IFERROR(BW12/BO12,0) -> 0.24644209 | BY12: =BO12+BQ12+BR12+BS12+BV12-BU12 -> 54841.279 | BZ12: =IFERROR(BY12/BO12,0) -> 0.3710255 | CB12: =BP12 -> 2788.8679 | CC12: =IFERROR(BQ12/$BN12,0) -> -1682.6592 | CD12: =IFERROR(BR12/$BN12,0) -> -207.84 | CE12: =IFERROR(BS12/$BN12,0) -> -98.22375 | CF12: =IFERROR(BT12/$BN12,0) -> -193.09125 | CG12: =IFERROR(BU12/$BN12,0) -> -154.35544 | CH12: =IFERROR(BV12/$BN12,0) -> 80.240709 | CI12: =IFERROR(BW12/$BN12,0) -> 687.29443 | CJ12: =IFERROR(BY12/$BN12,0) -> 1034.7411 | CK12: =CJ12-CI12 -> 347.44669
B13: 10007969 | C13: POTA CONOS | D13: =TD!F10 -> 15.82 | E13: =IFERROR(F13/D13,0) -> 1368.5038 | F13: =TD!G10 -> 21649.73 | G13: =TD!H10 -> 3288.0288 | H13: =TD!I10 -> 720.09645 | I13: =TD!J10 -> 1415.5876 | J13: =TD!K10 -> 1131.6082 | K13: 0 | L13: 0 | M13: =F13+G13+H13+I13 -> 27073.443 | N13: =IFERROR(M13/D13,0) -> 1711.3428 | O13: =F13+G13+H13-J13 -> 24526.247 | P13: =IFERROR(O13/D13,0) -> 1550.3317 | Q13: 1600 | R13: =Q13*D13 -> 25312 | S13: =R13-M13+(Q13-$BS$19)*D13*0.03 -> -1056.2719 | T13: =IFERROR(S13/R13,0) -> -0.041730084 | U13: =R13-(M13-J13-I13)+(Q13-$BS$19)*D13*0.03 -> 1490.9239 | V13: =IFERROR(U13/R13,0) -> 0.058901862 | X13: {=SUM([6]Hoja3!$I$5:$I$19*([6]Hoja3!$F$5:$F$19=X$5)*([6]Hoja3!$K$5:$K$19=$C13))} -> 0 | Y13: {=SUM([6]Hoja3!$J$5:$J$19*([6]Hoja3!$F$5:$F$19=X$5)*([6]Hoja3!$K$5:$K$19=$C13))} -> 0 | Z13: =IFERROR(Y13/X13,0) -> 0 | AA13: {=SUM([6]Hoja3!$I$5:$I$19*([6]Hoja3!$F$5:$F$19=AA$5)*([6]Hoja3!$K$5:$K$19=$C13))} -> 0 | AB13: {=SUM([6]Hoja3!$J$5:$J$19*([6]Hoja3!$F$5:$F$19=AA$5)*([6]Hoja3!$K$5:$K$19=$C13))} -> 0 | AC13: =IFERROR(AB13/AA13,0) -> 0 | AD13: {=SUM([6]Hoja3!$I$5:$I$19*([6]Hoja3!$F$5:$F$19=AD$5)*([6]Hoja3!$K$5:$K$19=$C13))} -> 54 | AE13: {=SUM([6]Hoja3!$J$5:$J$19*([6]Hoja3!$F$5:$F$19=AD$5)*([6]Hoja3!$K$5:$K$19=$C13))} -> 86400 | AF13: =IFERROR(AE13/AD13,0) -> 1600 | AG13: {=SUM([6]Hoja3!$I$5:$I$19*([6]Hoja3!$F$5:$F$19=AG$5)*([6]Hoja3!$K$5:$K$19=$C13))} -> 0 | AH13: {=SUM([6]Hoja3!$J$5:$J$19*([6]Hoja3!$F$5:$F$19=AG$5)*([6]Hoja3!$K$5:$K$19=$C13))} -> 0 | AI13: =IFERROR(AH13/AG13,0) -> 0 | AJ13: {=SUM([6]Hoja3!$I$5:$I$19*([6]Hoja3!$F$5:$F$19=AJ$5)*([6]Hoja3!$K$5:$K$19=$C13))} -> 0 | AK13: {=SUM([6]Hoja3!$J$5:$J$19*([6]Hoja3!$F$5:$F$19=AJ$5)*([6]Hoja3!$K$5:$K$19=$C13))} -> 0 | AL13: =IFERROR(AK13/AJ13,0) -> 0 | AM13: {=SUM([6]Hoja3!$I$5:$I$19*([6]Hoja3!$F$5:$F$19=AM$5)*([6]Hoja3!$K$5:$K$19=$C13))} -> 0 | AN13: {=SUM([6]Hoja3!$J$5:$J$19*([6]Hoja3!$F$5:$F$19=AM$5)*([6]Hoja3!$K$5:$K$19=$C13))} -> 0 | AO13: =IFERROR(AN13/AM13,0) -> 0 | AP13: {=SUM([6]Hoja3!$I$5:$I$19*([6]Hoja3!$F$5:$F$19=AP$5)*([6]Hoja3!$K$5:$K$19=$C13))} -> 0 | AQ13: {=SUM([6]Hoja3!$J$5:$J$19*([6]Hoja3!$F$5:$F$19=AP$5)*([6]Hoja3!$K$5:$K$19=$C13))} -> 0 | AR13: =IFERROR(AQ13/AP13,0) -> 0 | AS13: {=SUM([6]Hoja3!$I$5:$I$19*([6]Hoja3!$F$5:$F$19=AS$5)*([6]Hoja3!$K$5:$K$19=$C13))} -> 0 | AT13: {=SUM([6]Hoja3!$J$5:$J$19*([6]Hoja3!$F$5:$F$19=AS$5)*([6]Hoja3!$K$5:$K$19=$C13))} -> 0 | AU13: =IFERROR(AT13/AS13,0) -> 0 | AV13: {=SUM([2]Hoja2!$I$6:$I$26*([2]Hoja2!$F$6:$F$26=AV$5)*([2]Hoja2!$K$6:$K$26=$C13))} -> 0 | AW13: {=SUM([2]Hoja2!$J$6:$J$26*([2]Hoja2!$F$6:$F$26=AV$5)*([2]Hoja2!$K$6:$K$26=$C13))} -> 0 | AX13: =IFERROR(AW13/AV13,0) -> 0 | AY13: {=SUM([2]Hoja2!$I$6:$I$26*([2]Hoja2!$F$6:$F$26=AY$5)*([2]Hoja2!$K$6:$K$26=$C13))} -> 0 | AZ13: {=SUM([2]Hoja2!$J$6:$J$26*([2]Hoja2!$F$6:$F$26=AY$5)*([2]Hoja2!$K$6:$K$26=$C13))} -> 0 | BA13: =IFERROR(AZ13/AY13,0) -> 0 | BB13: {=SUM([2]Hoja2!$I$6:$I$26*([2]Hoja2!$F$6:$F$26=BB$5)*([2]Hoja2!$K$6:$K$26=$C13))} -> 0 | BC13: {=SUM([2]Hoja2!$J$6:$J$26*([2]Hoja2!$F$6:$F$26=BB$5)*([2]Hoja2!$K$6:$K$26=$C13))} -> 0 | BD13: =IFERROR(BC13/BB13,0) -> 0 | BE13: {=SUM([2]Hoja2!$I$6:$I$26*([2]Hoja2!$F$6:$F$26=BE$5)*([2]Hoja2!$K$6:$K$26=$C13))} -> 0 | BF13: {=SUM([2]Hoja2!$J$6:$J$26*([2]Hoja2!$F$6:$F$26=BE$5)*([2]Hoja2!$K$6:$K$26=$C13))} -> 0 | BG13: =IFERROR(BF13/BE13,0) -> 0 | BH13: {=SUM([2]Hoja2!$I$6:$I$26*([2]Hoja2!$F$6:$F$26=BH$5)*([2]Hoja2!$K$6:$K$26=$C13))} -> 0 | BI13: {=SUM([2]Hoja2!$J$6:$J$26*([2]Hoja2!$F$6:$F$26=BH$5)*([2]Hoja2!$K$6:$K$26=$C13))} -> 0 | BJ13: =IFERROR(BI13/BH13,0) -> 0 | BK13: {=SUM([2]Hoja2!$I$6:$I$26*([2]Hoja2!$F$6:$F$26=BK$5)*([2]Hoja2!$K$6:$K$26=$C13))} -> 0 | BL13: {=SUM([2]Hoja2!$J$6:$J$26*([2]Hoja2!$F$6:$F$26=BK$5)*([2]Hoja2!$K$6:$K$26=$C13))} -> 0 | BM13: =IFERROR(BL13/BK13,0) -> 0 | BN13: =X13+AA13+AD13+AG13+AJ13+AM13+AP13+AS13 -> 54 | BO13: =Y13+AB13+AE13+AH13+AK13+AN13+AQ13+AT13 -> 86400 | BP13: =IFERROR(BO13/BN13,0) -> 1600 | BQ13: =-IFERROR(F13/D13*BN13,0) -> -73899.206 | BR13: =-207.84*BN13 -> -11223.36 | BS13: =$BS$18/$BN$18*$BN13 -> -5304.0825 | BT13: =$BT$18/$BN$18*$BN13 -> -10426.928 | BU13: =$BU$18/$BN$18*$BN13 -> -8335.1936 | BV13: =(BO13-BN13*$BS$19)*0.03 -> 2407.0323 | BW13: =BO13+SUM(BQ13:BT13,BV13) -> -12046.544 | BX13: =IFERROR(BW13/BO13,0) -> -0.13942759 | BY13: =BO13+BQ13+BR13+BS13+BV13-BU13 -> 6715.5774 | BZ13: =IFERROR(BY13/BO13,0) -> 0.07772659 | CB13: =BP13 -> 1600 | CC13: =IFERROR(BQ13/$BN13,0) -> -1368.5038 | CD13: =IFERROR(BR13/$BN13,0) -> -207.84 | CE13: =IFERROR(BS13/$BN13,0) -> -98.22375 | CF13: =IFERROR(BT13/$BN13,0) -> -193.09125 | CG13: =IFERROR(BU13/$BN13,0) -> -154.35544 | CH13: =IFERROR(BV13/$BN13,0) -> 44.574672 | CI13: =IFERROR(BW13/$BN13,0) -> -223.08414 | CJ13: =IFERROR(BY13/$BN13,0) -> 124.36254 | CK13: =CJ13-CI13 -> 347.44669
B14: 10009239 | C14: POTA FILETE DARUMA | D14: =TD!F11 -> 40.66 | E14: =IFERROR(F14/D14,0) -> 3254.8777 | F14: =TD!G11 -> 132343.33 | G14: =TD!H11 -> 8450.7744 | H14: =TD!I11 -> 1850.7662 | I14: =TD!J11 -> 3638.2928 | J14: =TD!K11 -> 2908.4191 | K14: 0 | L14: 0 | M14: =F14+G14+H14+I14 -> 146283.16 | N14: =IFERROR(M14/D14,0) -> 3597.7167 | O14: =F14+G14+H14-J14 -> 139736.45 | P14: =IFERROR(O14/D14,0) -> 3436.7056 | Q14: 3900 | R14: =Q14*D14 -> 158574 | S14: =R14-M14+(Q14-$BS$19)*D14*0.03 -> 16908.784 | T14: =IFERROR(S14/R14,0) -> 0.10663024 | U14: =R14-(M14-J14-I14)+(Q14-$BS$19)*D14*0.03 -> 23455.496 | V14: =IFERROR(U14/R14,0) -> 0.14791514 | X14: {=SUM([6]Hoja3!$I$5:$I$19*([6]Hoja3!$F$5:$F$19=X$5)*([6]Hoja3!$K$5:$K$19=$C14))} -> 0 | Y14: {=SUM([6]Hoja3!$J$5:$J$19*([6]Hoja3!$F$5:$F$19=X$5)*([6]Hoja3!$K$5:$K$19=$C14))} -> 0 | Z14: =IFERROR(Y14/X14,0) -> 0 | AA14: {=SUM([6]Hoja3!$I$5:$I$19*([6]Hoja3!$F$5:$F$19=AA$5)*([6]Hoja3!$K$5:$K$19=$C14))} -> 0 | AB14: {=SUM([6]Hoja3!$J$5:$J$19*([6]Hoja3!$F$5:$F$19=AA$5)*([6]Hoja3!$K$5:$K$19=$C14))} -> 0 | AC14: =IFERROR(AB14/AA14,0) -> 0 | AD14: {=SUM([6]Hoja3!$I$5:$I$19*([6]Hoja3!$F$5:$F$19=AD$5)*([6]Hoja3!$K$5:$K$19=$C14))} -> 0 | AE14: {=SUM([6]Hoja3!$J$5:$J$19*([6]Hoja3!$F$5:$F$19=AD$5)*([6]Hoja3!$K$5:$K$19=$C14))} -> 0 | AF14: =IFERROR(AE14/AD14,0) -> 0 | AG14: {=SUM([6]Hoja3!$I$5:$I$19*([6]Hoja3!$F$5:$F$19=AG$5)*([6]Hoja3!$K$5:$K$19=$C14))} -> 0 | AH14: {=SUM([6]Hoja3!$J$5:$J$19*([6]Hoja3!$F$5:$F$19=AG$5)*([6]Hoja3!$K$5:$K$19=$C14))} -> 0 | AI14: =IFERROR(AH14/AG14,0) -> 0 | AJ14: {=SUM([6]Hoja3!$I$5:$I$19*([6]Hoja3!$F$5:$F$19=AJ$5)*([6]Hoja3!$K$5:$K$19=$C14))} -> 0 | AK14: {=SUM([6]Hoja3!$J$5:$J$19*([6]Hoja3!$F$5:$F$19=AJ$5)*([6]Hoja3!$K$5:$K$19=$C14))} -> 0 | AL14: =IFERROR(AK14/AJ14,0) -> 0 | AM14: {=SUM([6]Hoja3!$I$5:$I$19*([6]Hoja3!$F$5:$F$19=AM$5)*([6]Hoja3!$K$5:$K$19=$C14))} -> 0 | AN14: {=SUM([6]Hoja3!$J$5:$J$19*([6]Hoja3!$F$5:$F$19=AM$5)*([6]Hoja3!$K$5:$K$19=$C14))} -> 0 | AO14: =IFERROR(AN14/AM14,0) -> 0 | AP14: {=SUM([6]Hoja3!$I$5:$I$19*([6]Hoja3!$F$5:$F$19=AP$5)*([6]Hoja3!$K$5:$K$19=$C14))} -> 0 | AQ14: {=SUM([6]Hoja3!$J$5:$J$19*([6]Hoja3!$F$5:$F$19=AP$5)*([6]Hoja3!$K$5:$K$19=$C14))} -> 0 | AR14: =IFERROR(AQ14/AP14,0) -> 0 | AS14: {=SUM([6]Hoja3!$I$5:$I$19*([6]Hoja3!$F$5:$F$19=AS$5)*([6]Hoja3!$K$5:$K$19=$C14))} -> 162 | AT14: {=SUM([6]Hoja3!$J$5:$J$19*([6]Hoja3!$F$5:$F$19=AS$5)*([6]Hoja3!$K$5:$K$19=$C14))} -> 550800 | AU14: =IFERROR(AT14/AS14,0) -> 3400 | AV14: {=SUM([2]Hoja2!$I$6:$I$26*([2]Hoja2!$F$6:$F$26=AV$5)*([2]Hoja2!$K$6:$K$26=$C14))} -> 0 | AW14: {=SUM([2]Hoja2!$J$6:$J$26*([2]Hoja2!$F$6:$F$26=AV$5)*([2]Hoja2!$K$6:$K$26=$C14))} -> 0 | AX14: =IFERROR(AW14/AV14,0) -> 0 | AY14: {=SUM([2]Hoja2!$I$6:$I$26*([2]Hoja2!$F$6:$F$26=AY$5)*([2]Hoja2!$K$6:$K$26=$C14))} -> 0 | AZ14: {=SUM([2]Hoja2!$J$6:$J$26*([2]Hoja2!$F$6:$F$26=AY$5)*([2]Hoja2!$K$6:$K$26=$C14))} -> 0 | BA14: =IFERROR(AZ14/AY14,0) -> 0 | BB14: {=SUM([2]Hoja2!$I$6:$I$26*([2]Hoja2!$F$6:$F$26=BB$5)*([2]Hoja2!$K$6:$K$26=$C14))} -> 0 | BC14: {=SUM([2]Hoja2!$J$6:$J$26*([2]Hoja2!$F$6:$F$26=BB$5)*([2]Hoja2!$K$6:$K$26=$C14))} -> 0 | BD14: =IFERROR(BC14/BB14,0) -> 0 | BE14: {=SUM([2]Hoja2!$I$6:$I$26*([2]Hoja2!$F$6:$F$26=BE$5)*([2]Hoja2!$K$6:$K$26=$C14))} -> 0 | BF14: {=SUM([2]Hoja2!$J$6:$J$26*([2]Hoja2!$F$6:$F$26=BE$5)*([2]Hoja2!$K$6:$K$26=$C14))} -> 0 | BG14: =IFERROR(BF14/BE14,0) -> 0 | BH14: {=SUM([2]Hoja2!$I$6:$I$26*([2]Hoja2!$F$6:$F$26=BH$5)*([2]Hoja2!$K$6:$K$26=$C14))} -> 0 | BI14: {=SUM([2]Hoja2!$J$6:$J$26*([2]Hoja2!$F$6:$F$26=BH$5)*([2]Hoja2!$K$6:$K$26=$C14))} -> 0 | BJ14: =IFERROR(BI14/BH14,0) -> 0 | BK14: {=SUM([2]Hoja2!$I$6:$I$26*([2]Hoja2!$F$6:$F$26=BK$5)*([2]Hoja2!$K$6:$K$26=$C14))} -> 0 | BL14: {=SUM([2]Hoja2!$J$6:$J$26*([2]Hoja2!$F$6:$F$26=BK$5)*([2]Hoja2!$K$6:$K$26=$C14))} -> 0 | BM14: =IFERROR(BL14/BK14,0) -> 0 | BN14: =X14+AA14+AD14+AG14+AJ14+AM14+AP14+AS14 -> 162 | BO14: =Y14+AB14+AE14+AH14+AK14+AN14+AQ14+AT14 -> 550800 | BP14: =IFERROR(BO14/BN14,0) -> 3400 | BQ14: =-BN14*'[3]Stock Libre'!H36*1000 -> -527290.19 | BR14: =-207.84*BN14 -> -33670.08 | BS14: =$BS$18/$BN$18*$BN14 -> -15912.248 | BT14: =$BT$18/$BN$18*$BN14 -> -31280.783 | BU14: =$BU$18/$BN$18*$BN14 -> -25005.581 | BV14: =(BO14-BN14*$BS$19)*0.03 -> 15969.097 | BW14: =BO14+SUM(BQ14:BT14,BV14) -> -41384.208 | BX14: =IFERROR(BW14/BO14,0) -> -0.075134727 | BY14: =BO14+BQ14+BR14+BS14+BV14-BU14 -> 14902.156 | BZ14: =IFERROR(BY14/BO14,0) -> 0.027055475 | CB14: =BP14 -> 3400 | CC14: =IFERROR(BQ14/$BN14,0) -> -3254.8777 | CD14: =IFERROR(BR14/$BN14,0) -> -207.84 | CE14: =IFERROR(BS14/$BN14,0) -> -98.22375 | CF14: =IFERROR(BT14/$BN14,0) -> -193.09125 | CG14: =IFERROR(BU14/$BN14,0) -> -154.35544 | CH14: =IFERROR(BV14/$BN14,0) -> 98.574672 | CI14: =IFERROR(BW14/$BN14,0) -> -255.45807 | CJ14: =IFERROR(BY14/$BN14,0) -> 91.988614 | CK14: =CJ14-CI14 -> 347.44669
B15: 10009334 | C15: POTA ALAS COCIDAS | D15: =TD!F12 -> 32.788 | E15: =IFERROR(F15/D15,0) -> 2824.4285 | F15: =TD!G12 -> 92607.362 | G15: =TD!H12 -> 6814.6579 | H15: =TD!I12 -> 1492.4477 | I15: =TD!J12 -> 2933.8993 | J15: =TD!K12 -> 2345.3331 | K15: 0 | L15: 0 | M15: =F15+G15+H15+I15 -> 103848.37 | N15: =IFERROR(M15/D15,0) -> 3167.2675 | O15: =F15+G15+H15-J15 -> 98569.135 | P15: =IFERROR(O15/D15,0) -> 3006.2564 | Q15: 3900 | R15: =Q15*D15 -> 127873.2 | S15: =R15-M15+(Q15-$BS$19)*D15*0.03 -> 27748.719 | T15: =IFERROR(S15/R15,0) -> 0.21700184 | U15: =R15-(M15-J15-I15)+(Q15-$BS$19)*D15*0.03 -> 33027.952 | V15: =IFERROR(U15/R15,0) -> 0.25828674 | X15: {=SUM([6]Hoja3!$I$5:$I$19*([6]Hoja3!$F$5:$F$19=X$5)*([6]Hoja3!$K$5:$K$19=$C15))} -> 0 | Y15: {=SUM([6]Hoja3!$J$5:$J$19*([6]Hoja3!$F$5:$F$19=X$5)*([6]Hoja3!$K$5:$K$19=$C15))} -> 0 | Z15: =IFERROR(Y15/X15,0) -> 0 | AA15: {=SUM([6]Hoja3!$I$5:$I$19*([6]Hoja3!$F$5:$F$19=AA$5)*([6]Hoja3!$K$5:$K$19=$C15))} -> 0 | AB15: {=SUM([6]Hoja3!$J$5:$J$19*([6]Hoja3!$F$5:$F$19=AA$5)*([6]Hoja3!$K$5:$K$19=$C15))} -> 0 | AC15: =IFERROR(AB15/AA15,0) -> 0 | AD15: {=SUM([6]Hoja3!$I$5:$I$19*([6]Hoja3!$F$5:$F$19=AD$5)*([6]Hoja3!$K$5:$K$19=$C15))} -> 0 | AE15: {=SUM([6]Hoja3!$J$5:$J$19*([6]Hoja3!$F$5:$F$19=AD$5)*([6]Hoja3!$K$5:$K$19=$C15))} -> 0 | AF15: =IFERROR(AE15/AD15,0) -> 0 | AG15: {=SUM([6]Hoja3!$I$5:$I$19*([6]Hoja3!$F$5:$F$19=AG$5)*([6]Hoja3!$K$5:$K$19=$C15))} -> 0 | AH15: {=SUM([6]Hoja3!$J$5:$J$19*([6]Hoja3!$F$5:$F$19=AG$5)*([6]Hoja3!$K$5:$K$19=$C15))} -> 0 | AI15: =IFERROR(AH15/AG15,0) -> 0 | AJ15: {=SUM([6]Hoja3!$I$5:$I$19*([6]Hoja3!$F$5:$F$19=AJ$5)*([6]Hoja3!$K$5:$K$19=$C15))} -> 0 | AK15: {=SUM([6]Hoja3!$J$5:$J$19*([6]Hoja3!$F$5:$F$19=AJ$5)*([6]Hoja3!$K$5:$K$19=$C15))} -> 0 | AL15: =IFERROR(AK15/AJ15,0) -> 0 | AM15: {=SUM([6]Hoja3!$I$5:$I$19*([6]Hoja3!$F$5:$F$19=AM$5)*([6]Hoja3!$K$5:$K$19=$C15))} -> 0 | AN15: {=SUM([6]Hoja3!$J$5:$J$19*([6]Hoja3!$F$5:$F$19=AM$5)*([6]Hoja3!$K$5:$K$19=$C15))} -> 0 | AO15: =IFERROR(AN15/AM15,0) -> 0 | AP15: {=SUM([6]Hoja3!$I$5:$I$19*([6]Hoja3!$F$5:$F$19=AP$5)*([6]Hoja3!$K$5:$K$19=$C15))} -> 0 | AQ15: {=SUM([6]Hoja3!$J$5:$J$19*([6]Hoja3!$F$5:$F$19=AP$5)*([6]Hoja3!$K$5:$K$19=$C15))} -> 0 | AR15: =IFERROR(AQ15/AP15,0) -> 0 | AS15: {=SUM([6]Hoja3!$I$5:$I$19*([6]Hoja3!$F$5:$F$19=AS$5)*([6]Hoja3!$K$5:$K$19=$C15))} -> 0 | AT15: {=SUM([6]Hoja3!$J$5:$J$19*([6]Hoja3!$F$5:$F$19=AS$5)*([6]Hoja3!$K$5:$K$19=$C15))} -> 0 | AU15: =IFERROR(AT15/AS15,0) -> 0 | AV15: {=SUM([2]Hoja2!$I$6:$I$26*([2]Hoja2!$F$6:$F$26=AV$5)*([2]Hoja2!$K$6:$K$26=$C15))} -> 0 | AW15: {=SUM([2]Hoja2!$J$6:$J$26*([2]Hoja2!$F$6:$F$26=AV$5)*([2]Hoja2!$K$6:$K$26=$C15))} -> 0 | AX15: =IFERROR(AW15/AV15,0) -> 0 | AY15: {=SUM([2]Hoja2!$I$6:$I$26*([2]Hoja2!$F$6:$F$26=AY$5)*([2]Hoja2!$K$6:$K$26=$C15))} -> 0 | AZ15: {=SUM([2]Hoja2!$J$6:$J$26*([2]Hoja2!$F$6:$F$26=AY$5)*([2]Hoja2!$K$6:$K$26=$C15))} -> 0 | BA15: =IFERROR(AZ15/AY15,0) -> 0 | BB15: {=SUM([2]Hoja2!$I$6:$I$26*([2]Hoja2!$F$6:$F$26=BB$5)*([2]Hoja2!$K$6:$K$26=$C15))} -> 0 | BC15: {=SUM([2]Hoja2!$J$6:$J$26*([2]Hoja2!$F$6:$F$26=BB$5)*([2]Hoja2!$K$6:$K$26=$C15))} -> 0 | BD15: =IFERROR(BC15/BB15,0) -> 0 | BE15: {=SUM([2]Hoja2!$I$6:$I$26*([2]Hoja2!$F$6:$F$26=BE$5)*([2]Hoja2!$K$6:$K$26=$C15))} -> 0 | BF15: {=SUM([2]Hoja2!$J$6:$J$26*([2]Hoja2!$F$6:$F$26=BE$5)*([2]Hoja2!$K$6:$K$26=$C15))} -> 0 | BG15: =IFERROR(BF15/BE15,0) -> 0 | BH15: {=SUM([2]Hoja2!$I$6:$I$26*([2]Hoja2!$F$6:$F$26=BH$5)*([2]Hoja2!$K$6:$K$26=$C15))} -> 0 | BI15: {=SUM([2]Hoja2!$J$6:$J$26*([2]Hoja2!$F$6:$F$26=BH$5)*([2]Hoja2!$K$6:$K$26=$C15))} -> 0 | BJ15: =IFERROR(BI15/BH15,0) -> 0 | BK15: {=SUM([2]Hoja2!$I$6:$I$26*([2]Hoja2!$F$6:$F$26=BK$5)*([2]Hoja2!$K$6:$K$26=$C15))} -> 0 | BL15: {=SUM([2]Hoja2!$J$6:$J$26*([2]Hoja2!$F$6:$F$26=BK$5)*([2]Hoja2!$K$6:$K$26=$C15))} -> 0 | BM15: =IFERROR(BL15/BK15,0) -> 0 | BN15: =X15+AA15+AD15+AG15+AJ15+AM15+AP15+AS15 -> 0 | BO15: =Y15+AB15+AE15+AH15+AK15+AN15+AQ15+AT15 -> 0 | BP15: =IFERROR(BO15/BN15,0) -> 0 | BQ15: =-BN15*'[4]Stock Libre'!H47*1000 -> 0 | BR15: =-207.84*BN15 -> 0 | BS15: =$BS$18/$BN$18*$BN15 -> 0 | BT15: =$BT$18/$BN$18*$BN15 -> 0 | BU15: =$BU$18/$BN$18*$BN15 -> 0 | BV15: =(BO15-BN15*$BS$19)*0.03 -> 0 | BW15: =BO15+SUM(BQ15:BT15,BV15) -> 0 | BX15: =IFERROR(BW15/BO15,0) -> 0 | BY15: =BO15+BQ15+BR15+BS15+BV15-BU15 -> 0 | BZ15: =IFERROR(BY15/BO15,0) -> 0 | CB15: =BP15 -> 0 | CC15: =IFERROR(BQ15/$BN15,0) -> 0 | CD15: =IFERROR(BR15/$BN15,0) -> 0 | CE15: =IFERROR(BS15/$BN15,0) -> 0 | CF15: =IFERROR(BT15/$BN15,0) -> 0 | CG15: =IFERROR(BU15/$BN15,0) -> 0 | CH15: =IFERROR(BV15/$BN15,0) -> 0 | CI15: =IFERROR(BW15/$BN15,0) -> 0 | CJ15: =IFERROR(BY15/$BN15,0) -> 0 | CK15: =CJ15-CI15 -> 0
B16: 10009386 | C16: VENTOSAS | D16: =TD!F13 -> 19.74 | E16: =IFERROR(F16/D16,0) -> 1742.1709 | F16: =TD!G13 -> 34390.454 | G16: =TD!H13 -> 4102.7616 | H16: =TD!I13 -> 898.52743 | I16: =TD!J13 -> 1766.3527 | J16: =TD!K13 -> 1412.0067 | K16: 0 | L16: 0 | M16: =F16+G16+H16+I16 -> 41158.096 | N16: =IFERROR(M16/D16,0) -> 2085.0099 | O16: =F16+G16+H16-J16 -> 37979.736 | P16: =IFERROR(O16/D16,0) -> 1923.9988 | Q16: 2000 | R16: =Q16*D16 -> 39480 | S16: =R16-M16+(Q16-$BS$19)*D16*0.03 -> -561.31178 | T16: =IFERROR(S16/R16,0) -> -0.014217624 | U16: =R16-(M16-J16-I16)+(Q16-$BS$19)*D16*0.03 -> 2617.0476 | V16: =IFERROR(U16/R16,0) -> 0.066287933 | X16: {=SUM([6]Hoja3!$I$5:$I$19*([6]Hoja3!$F$5:$F$19=X$5)*([6]Hoja3!$K$5:$K$19=$C16))} -> 0 | Y16: {=SUM([6]Hoja3!$J$5:$J$19*([6]Hoja3!$F$5:$F$19=X$5)*([6]Hoja3!$K$5:$K$19=$C16))} -> 0 | Z16: =IFERROR(Y16/X16,0) -> 0 | AA16: {=SUM([6]Hoja3!$I$5:$I$19*([6]Hoja3!$F$5:$F$19=AA$5)*([6]Hoja3!$K$5:$K$19=$C16))} -> 0 | AB16: {=SUM([6]Hoja3!$J$5:$J$19*([6]Hoja3!$F$5:$F$19=AA$5)*([6]Hoja3!$K$5:$K$19=$C16))} -> 0 | AC16: =IFERROR(AB16/AA16,0) -> 0 | AD16: {=SUM([6]Hoja3!$I$5:$I$19*([6]Hoja3!$F$5:$F$19=AD$5)*([6]Hoja3!$K$5:$K$19=$C16))} -> 0 | AE16: {=SUM([6]Hoja3!$J$5:$J$19*([6]Hoja3!$F$5:$F$19=AD$5)*([6]Hoja3!$K$5:$K$19=$C16))} -> 0 | AF16: =IFERROR(AE16/AD16,0) -> 0 | AG16: {=SUM([6]Hoja3!$I$5:$I$19*([6]Hoja3!$F$5:$F$19=AG$5)*([6]Hoja3!$K$5:$K$19=$C16))} -> 0 | AH16: {=SUM([6]Hoja3!$J$5:$J$19*([6]Hoja3!$F$5:$F$19=AG$5)*([6]Hoja3!$K$5:$K$19=$C16))} -> 0 | AI16: =IFERROR(AH16/AG16,0) -> 0 | AJ16: {=SUM([6]Hoja3!$I$5:$I$19*([6]Hoja3!$F$5:$F$19=AJ$5)*([6]Hoja3!$K$5:$K$19=$C16))} -> 0 | AK16: {=SUM([6]Hoja3!$J$5:$J$19*([6]Hoja3!$F$5:$F$19=AJ$5)*([6]Hoja3!$K$5:$K$19=$C16))} -> 0 | AL16: =IFERROR(AK16/AJ16,0) -> 0 | AM16: {=SUM([6]Hoja3!$I$5:$I$19*([6]Hoja3!$F$5:$F$19=AM$5)*([6]Hoja3!$K$5:$K$19=$C16))} -> 0 | AN16: {=SUM([6]Hoja3!$J$5:$J$19*([6]Hoja3!$F$5:$F$19=AM$5)*([6]Hoja3!$K$5:$K$19=$C16))} -> 0 | AO16: =IFERROR(AN16/AM16,0) -> 0 | AP16: {=SUM([6]Hoja3!$I$5:$I$19*([6]Hoja3!$F$5:$F$19=AP$5)*([6]Hoja3!$K$5:$K$19=$C16))} -> 0 | AQ16: {=SUM([6]Hoja3!$J$5:$J$19*([6]Hoja3!$F$5:$F$19=AP$5)*([6]Hoja3!$K$5:$K$19=$C16))} -> 0 | AR16: =IFERROR(AQ16/AP16,0) -> 0 | AS16: {=SUM([6]Hoja3!$I$5:$I$19*([6]Hoja3!$F$5:$F$19=AS$5)*([6]Hoja3!$K$5:$K$19=$C16))} -> 0 | AT16: {=SUM([6]Hoja3!$J$5:$J$19*([6]Hoja3!$F$5:$F$19=AS$5)*([6]Hoja3!$K$5:$K$19=$C16))} -> 0 | AU16: =IFERROR(AT16/AS16,0) -> 0 | AV16: {=SUM([2]Hoja2!$I$6:$I$26*([2]Hoja2!$F$6:$F$26=AV$5)*([2]Hoja2!$K$6:$K$26=$C16))} -> 0 | AW16: {=SUM([2]Hoja2!$J$6:$J$26*([2]Hoja2!$F$6:$F$26=AV$5)*([2]Hoja2!$K$6:$K$26=$C16))} -> 0 | AX16: =IFERROR(AW16/AV16,0) -> 0 | AY16: {=SUM([2]Hoja2!$I$6:$I$26*([2]Hoja2!$F$6:$F$26=AY$5)*([2]Hoja2!$K$6:$K$26=$C16))} -> 0 | AZ16: {=SUM([2]Hoja2!$J$6:$J$26*([2]Hoja2!$F$6:$F$26=AY$5)*([2]Hoja2!$K$6:$K$26=$C16))} -> 0 | BA16: =IFERROR(AZ16/AY16,0) -> 0 | BB16: {=SUM([2]Hoja2!$I$6:$I$26*([2]Hoja2!$F$6:$F$26=BB$5)*([2]Hoja2!$K$6:$K$26=$C16))} -> 0 | BC16: {=SUM([2]Hoja2!$J$6:$J$26*([2]Hoja2!$F$6:$F$26=BB$5)*([2]Hoja2!$K$6:$K$26=$C16))} -> 0 | BD16: =IFERROR(BC16/BB16,0) -> 0 | BE16: {=SUM([2]Hoja2!$I$6:$I$26*([2]Hoja2!$F$6:$F$26=BE$5)*([2]Hoja2!$K$6:$K$26=$C16))} -> 0 | BF16: {=SUM([2]Hoja2!$J$6:$J$26*([2]Hoja2!$F$6:$F$26=BE$5)*([2]Hoja2!$K$6:$K$26=$C16))} -> 0 | BG16: =IFERROR(BF16/BE16,0) -> 0 | BH16: {=SUM([2]Hoja2!$I$6:$I$26*([2]Hoja2!$F$6:$F$26=BH$5)*([2]Hoja2!$K$6:$K$26=$C16))} -> 0 | BI16: {=SUM([2]Hoja2!$J$6:$J$26*([2]Hoja2!$F$6:$F$26=BH$5)*([2]Hoja2!$K$6:$K$26=$C16))} -> 0 | BJ16: =IFERROR(BI16/BH16,0) -> 0 | BK16: {=SUM([2]Hoja2!$I$6:$I$26*([2]Hoja2!$F$6:$F$26=BK$5)*([2]Hoja2!$K$6:$K$26=$C16))} -> 0 | BL16: {=SUM([2]Hoja2!$J$6:$J$26*([2]Hoja2!$F$6:$F$26=BK$5)*([2]Hoja2!$K$6:$K$26=$C16))} -> 0 | BM16: =IFERROR(BL16/BK16,0) -> 0 | BN16: =X16+AA16+AD16+AG16+AJ16+AM16+AP16+AS16 -> 0 | BO16: =Y16+AB16+AE16+AH16+AK16+AN16+AQ16+AT16 -> 0 | BP16: =IFERROR(BO16/BN16,0) -> 0 | BQ16: =-IFERROR(F16/D16*BN16,0) -> 0 | BR16: =-207.84*BN16 -> 0 | BS16: =$BS$18/$BN$18*$BN16 -> 0 | BT16: =$BT$18/$BN$18*$BN16 -> 0 | BU16: =$BU$18/$BN$18*$BN16 -> 0 | BV16: =(BO16-BN16*$BS$19)*0.03 -> 0 | BW16: =BO16+SUM(BQ16:BT16,BV16) -> 0 | BX16: =IFERROR(BW16/BO16,0) -> 0 | BY16: =BO16+BQ16+BR16+BS16+BV16-BU16 -> 0 | BZ16: =IFERROR(BY16/BO16,0) -> 0 | CB16: =BP16 -> 0 | CC16: =IFERROR(BQ16/$BN16,0) -> 0 | CD16: =IFERROR(BR16/$BN16,0) -> 0 | CE16: =IFERROR(BS16/$BN16,0) -> 0 | CF16: =IFERROR(BT16/$BN16,0) -> 0 | CG16: =IFERROR(BU16/$BN16,0) -> 0 | CH16: =IFERROR(BV16/$BN16,0) -> 0 | CI16: =IFERROR(BW16/$BN16,0) -> 0 | CJ16: =IFERROR(BY16/$BN16,0) -> 0 | CK16: =CJ16-CI16 -> 0
B17: 10009386 | C17: OTROS | D17: =TD!F14 -> 20.94 | E17: =IFERROR(F17/D17,0) -> 1416.8705 | F17: =TD!G14 -> 29669.268 | G17: =TD!H14 -> 4352.1696 | H17: =TD!I14 -> 953.14915 | I17: =TD!J14 -> 1873.7297 | J17: =TD!K14 -> 1497.843 | K17: 0 | L17: 0 | M17: =F17+G17+H17+I17 -> 36848.317 | N17: =IFERROR(M17/D17,0) -> 1759.7095 | O17: =F17+G17+H17-J17 -> 33476.744 | P17: =IFERROR(O17/D17,0) -> 1598.6984 | Q17: 1700 | R17: =Q17*D17 -> 35598 | S17: =R17-M17+(Q17-$BS$19)*D17*0.03 -> -254.10311 | T17: =IFERROR(S17/R17,0) -> -0.0071381289 | U17: =R17-(M17-J17-I17)+(Q17-$BS$19)*D17*0.03 -> 3117.4696 | V17: =IFERROR(U17/R17,0) -> 0.087574291 | X17: {=SUM([6]Hoja3!$I$5:$I$19*([6]Hoja3!$F$5:$F$19=X$5)*([6]Hoja3!$K$5:$K$19=$C17))} -> 0 | Y17: {=SUM([6]Hoja3!$J$5:$J$19*([6]Hoja3!$F$5:$F$19=X$5)*([6]Hoja3!$K$5:$K$19=$C17))} -> 0 | Z17: =IFERROR(Y17/X17,0) -> 0 | AA17: {=SUM([6]Hoja3!$I$5:$I$19*([6]Hoja3!$F$5:$F$19=AA$5)*([6]Hoja3!$K$5:$K$19=$C17))} -> 0 | AB17: {=SUM([6]Hoja3!$J$5:$J$19*([6]Hoja3!$F$5:$F$19=AA$5)*([6]Hoja3!$K$5:$K$19=$C17))} -> 0 | AC17: =IFERROR(AB17/AA17,0) -> 0 | AD17: {=SUM([6]Hoja3!$I$5:$I$19*([6]Hoja3!$F$5:$F$19=AD$5)*([6]Hoja3!$K$5:$K$19=$C17))} -> 54 | AE17: {=SUM([6]Hoja3!$J$5:$J$19*([6]Hoja3!$F$5:$F$19=AD$5)*([6]Hoja3!$K$5:$K$19=$C17))} -> 91800 | AF17: =IFERROR(AE17/AD17,0) -> 1700 | AG17: {=SUM([6]Hoja3!$I$5:$I$19*([6]Hoja3!$F$5:$F$19=AG$5)*([6]Hoja3!$K$5:$K$19=$C17))} -> 0 | AH17: {=SUM([6]Hoja3!$J$5:$J$19*([6]Hoja3!$F$5:$F$19=AG$5)*([6]Hoja3!$K$5:$K$19=$C17))} -> 0 | AI17: =IFERROR(AH17/AG17,0) -> 0 | AJ17: {=SUM([6]Hoja3!$I$5:$I$19*([6]Hoja3!$F$5:$F$19=AJ$5)*([6]Hoja3!$K$5:$K$19=$C17))} -> 0 | AK17: {=SUM([6]Hoja3!$J$5:$J$19*([6]Hoja3!$F$5:$F$19=AJ$5)*([6]Hoja3!$K$5:$K$19=$C17))} -> 0 | AL17: =IFERROR(AK17/AJ17,0) -> 0 | AM17: {=SUM([6]Hoja3!$I$5:$I$19*([6]Hoja3!$F$5:$F$19=AM$5)*([6]Hoja3!$K$5:$K$19=$C17))} -> 54 | AN17: {=SUM([6]Hoja3!$J$5:$J$19*([6]Hoja3!$F$5:$F$19=AM$5)*([6]Hoja3!$K$5:$K$19=$C17))} -> 91800 | AO17: =IFERROR(AN17/AM17,0) -> 1700 | AP17: {=SUM([6]Hoja3!$I$5:$I$19*([6]Hoja3!$F$5:$F$19=AP$5)*([6]Hoja3!$K$5:$K$19=$C17))} -> 27 | AQ17: {=SUM([6]Hoja3!$J$5:$J$19*([6]Hoja3!$F$5:$F$19=AP$5)*([6]Hoja3!$K$5:$K$19=$C17))} -> 45900 | AR17: =IFERROR(AQ17/AP17,0) -> 1700 | AS17: {=SUM([6]Hoja3!$I$5:$I$19*([6]Hoja3!$F$5:$F$19=AS$5)*([6]Hoja3!$K$5:$K$19=$C17))} -> 27 | AT17: {=SUM([6]Hoja3!$J$5:$J$19*([6]Hoja3!$F$5:$F$19=AS$5)*([6]Hoja3!$K$5:$K$19=$C17))} -> 45900 | AU17: =IFERROR(AT17/AS17,0) -> 1700 | AV17: {=SUM([2]Hoja2!$I$6:$I$26*([2]Hoja2!$F$6:$F$26=AV$5)*([2]Hoja2!$K$6:$K$26=$C17))} -> 0 | AW17: {=SUM([2]Hoja2!$J$6:$J$26*([2]Hoja2!$F$6:$F$26=AV$5)*([2]Hoja2!$K$6:$K$26=$C17))} -> 0 | AX17: =IFERROR(AW17/AV17,0) -> 0 | AY17: {=SUM([2]Hoja2!$I$6:$I$26*([2]Hoja2!$F$6:$F$26=AY$5)*([2]Hoja2!$K$6:$K$26=$C17))} -> 0 | AZ17: {=SUM([2]Hoja2!$J$6:$J$26*([2]Hoja2!$F$6:$F$26=AY$5)*([2]Hoja2!$K$6:$K$26=$C17))} -> 0 | BA17: =IFERROR(AZ17/AY17,0) -> 0 | BB17: {=SUM([2]Hoja2!$I$6:$I$26*([2]Hoja2!$F$6:$F$26=BB$5)*([2]Hoja2!$K$6:$K$26=$C17))} -> 0 | BC17: {=SUM([2]Hoja2!$J$6:$J$26*([2]Hoja2!$F$6:$F$26=BB$5)*([2]Hoja2!$K$6:$K$26=$C17))} -> 0 | BD17: =IFERROR(BC17/BB17,0) -> 0 | BE17: {=SUM([2]Hoja2!$I$6:$I$26*([2]Hoja2!$F$6:$F$26=BE$5)*([2]Hoja2!$K$6:$K$26=$C17))} -> 0 | BF17: {=SUM([2]Hoja2!$J$6:$J$26*([2]Hoja2!$F$6:$F$26=BE$5)*([2]Hoja2!$K$6:$K$26=$C17))} -> 0 | BG17: =IFERROR(BF17/BE17,0) -> 0 | BH17: {=SUM([2]Hoja2!$I$6:$I$26*([2]Hoja2!$F$6:$F$26=BH$5)*([2]Hoja2!$K$6:$K$26=$C17))} -> 0 | BI17: {=SUM([2]Hoja2!$J$6:$J$26*([2]Hoja2!$F$6:$F$26=BH$5)*([2]Hoja2!$K$6:$K$26=$C17))} -> 0 | BJ17: =IFERROR(BI17/BH17,0) -> 0 | BK17: {=SUM([2]Hoja2!$I$6:$I$26*([2]Hoja2!$F$6:$F$26=BK$5)*([2]Hoja2!$K$6:$K$26=$C17))} -> 0 | BL17: {=SUM([2]Hoja2!$J$6:$J$26*([2]Hoja2!$F$6:$F$26=BK$5)*([2]Hoja2!$K$6:$K$26=$C17))} -> 0 | BM17: =IFERROR(BL17/BK17,0) -> 0 | BN17: =X17+AA17+AD17+AG17+AJ17+AM17+AP17+AS17 -> 162 | BO17: =Y17+AB17+AE17+AH17+AK17+AN17+AQ17+AT17 -> 275400 | BP17: =IFERROR(BO17/BN17,0) -> 1700 | BQ17: =-IFERROR(F17/D17*BN17,0) -> -229533.02 | BR17: =-207.84*BN17 -> -33670.08 | BS17: =$BS$18/$BN$18*$BN17 -> -15912.248 | BT17: =$BT$18/$BN$18*$BN17 -> -31280.783 | BU17: =$BU$18/$BN$18*$BN17 -> -25005.581 | BV17: =(BO17-BN17*$BS$19)*0.03 -> 7707.0968 | BW17: =BO17+SUM(BQ17:BT17,BV17) -> -27289.034 | BX17: =IFERROR(BW17/BO17,0) -> -0.099088722 | BY17: =BO17+BQ17+BR17+BS17+BV17-BU17 -> 28997.329 | BZ17: =IFERROR(BY17/BO17,0) -> 0.10529168 | CB17: =BP17 -> 1700 | CC17: =IFERROR(BQ17/$BN17,0) -> -1416.8705 | CD17: =IFERROR(BR17/$BN17,0) -> -207.84 | CE17: =IFERROR(BS17/$BN17,0) -> -98.22375 | CF17: =IFERROR(BT17/$BN17,0) -> -193.09125 | CG17: =IFERROR(BU17/$BN17,0) -> -154.35544 | CH17: =IFERROR(BV17/$BN17,0) -> 47.574672 | CI17: =IFERROR(BW17/$BN17,0) -> -168.45083 | CJ17: =IFERROR(BY17/$BN17,0) -> 178.99586 | CK17: =CJ17-CI17 -> 347.44669
C18: TOTAL | D18: =SUM(D7:D17) -> 1726.324 | E18: =IFERROR(F18/D18,0) -> 1846.6859 | F18: =SUM(F7:F17) -> 3187978.2 | G18: =SUM(G7:G17) -> 358799.18 | H18: =SUM(H7:H17) -> 78579 | I18: =SUM(I7:I17) -> 154473 | J18: =SUM(J7:J17) -> 123484.35 | K18: =SUM(K7:K17) -> 0 | L18: 0 | M18: =SUM(M7:M17) -> 3779829.4 | N18: =IFERROR(M18/D18,0) -> 2189.5249 | O18: =SUM(O7:O17) -> 3501872 | P18: =IFERROR(O18/D18,0) -> 2028.5138 | Q18: =R18/D18 -> 1956.3735 | R18: =SUM(R7:R17) -> 3377334.6 | S18: =SUM(S7:S17) -> -307087.96 | T18: =S18/R18 -> -0.090926127 | U18: =SUM(U7:U17) -> -29130.606 | V18: =IFERROR(U18/R18,0) -> -0.0086253243 | X18: =SUM(X7:X17) -> 27 | Y18: =SUM(Y7:Y17) -> 68850 | Z18: =IFERROR(Y18/X18,0) -> 2550 | AA18: =SUM(AA7:AA17) -> 26 | AB18: =SUM(AB7:AB17) -> 74100 | AC18: =IFERROR(AB18/AA18,0) -> 2850 | AD18: =SUM(AD7:AD17) -> 270 | AE18: =SUM(AE7:AE17) -> 548100 | AF18: =IFERROR(AE18/AD18,0) -> 2030 | AG18: =SUM(AG7:AG17) -> 27 | AH18: =SUM(AH7:AH17) -> 73710 | AI18: =IFERROR(AH18/AG18,0) -> 2730 | AJ18: =SUM(AJ7:AJ17) -> 270 | AK18: =SUM(AK7:AK17) -> 405000 | AL18: =IFERROR(AK18/AJ18,0) -> 1500 | AM18: =SUM(AM7:AM17) -> 54 | AN18: =SUM(AN7:AN17) -> 91800 | AO18: =IFERROR(AN18/AM18,0) -> 1700 | AP18: =SUM(AP7:AP17) -> 27 | AQ18: =SUM(AQ7:AQ17) -> 45900 | AR18: =IFERROR(AQ18/AP18,0) -> 1700 | AS18: =SUM(AS7:AS17) -> 643 | AT18: =SUM(AT7:AT17) -> 1423810 | AU18: =IFERROR(AT18/AS18,0) -> 2214.3235 | AV18: =SUM(AV7:AV17) -> 0 | AW18: =SUM(AW7:AW17) -> 0 | AX18: =IFERROR(AW18/AV18,0) -> 0 | AY18: =SUM(AY7:AY17) -> 0 | AZ18: =SUM(AZ7:AZ17) -> 0 | BA18: =IFERROR(AZ18/AY18,0) -> 0 | BB18: =SUM(BB7:BB17) -> 0 | BC18: =SUM(BC7:BC17) -> 0 | BD18: =IFERROR(BC18/BB18,0) -> 0 | BE18: =SUM(BE7:BE17) -> 0 | BF18: =SUM(BF7:BF17) -> 0 | BG18: =IFERROR(BF18/BE18,0) -> 0 | BH18: =SUM(BH7:BH17) -> 0 | BI18: =SUM(BI7:BI17) -> 0 | BJ18: =IFERROR(BI18/BH18,0) -> 0 | BK18: =SUM(BK7:BK17) -> 0 | BL18: =SUM(BL7:BL17) -> 0 | BM18: =IFERROR(BL18/BK18,0) -> 0 | BN18: =SUM(BN7:BN17) -> 1344 | BO18: =SUM(BO7:BO17) -> 2731270 | BP18: =IFERROR(BO18/BN18,0) -> 2032.1949 | BQ18: =SUM(BQ7:BQ17) -> -2640196.1 | BR18: =SUM(BR7:BR17) -> -279336.96 | BS18: =-'[5]Stock Libre'!N54/800*BN18 -> -132012.72 | BT18: =-'[5]Stock Libre'!O54/800*BN18 -> -259514.64 | BU18: =-'[5]Stock Libre'!P54/800*BN18 -> -207453.71 | BV18: =SUM(BV7:BV17) -> 77334.459 | BW18: =SUM(BW7:BW17) -> -502455.93 | BX18: =IFERROR(BW18/BO18,0) -> -0.18396421 | BY18: =SUM(BY7:BY17) -> -35487.582 | BZ18: =IFERROR(BY18/BO18,0) -> -0.01299307 | CB18: =BP18 -> 2032.1949 | CC18: =IFERROR(BQ18/$BN18,0) -> -1964.4316 | CD18: =IFERROR(BR18/$BN18,0) -> -207.84 | CE18: =IFERROR(BS18/$BN18,0) -> -98.22375 | CF18: =IFERROR(BT18/$BN18,0) -> -193.09125 | CG18: =IFERROR(BU18/$BN18,0) -> -154.35544 | CH18: =IFERROR(BV18/$BN18,0) -> 57.54052 | CI18: =IFERROR(BW18/$BN18,0) -> -373.85114 | CJ18: =IFERROR(BY18/$BN18,0) -> -26.404451 | CK18: =CJ18-CI18 -> 347.44669
N19: =N18-P18 -> 161.01111 | BR19: flete x tm | BS19: 114.17761
C20: TM en Almacén de Yantai | AU20: Neto del despacho a Almacén Yantai | BN20: =BN18-BN14-BN7 -> 618 | BO20: =BO18-BO14-BO7 -> 1315270 | BP20: =IFERROR(BO20/BN20,0) -> 2128.2686 | BQ20: =BQ18-BQ14-BQ7 -> -993599.27 | BR20: =BR18-BR14-BR7 -> -128445.12 | BS20: =BS18-BS14-BS7 -> -60702.278 | BT20: =BT18-BT14-BT7 -> -119330.39 | BU20: =BU18-BU14-BU7 -> -95391.66 | BV20: =BV18-BV14-BV7 -> 37341.247 | BW20: =BW18-BW14-BW7 -> 50534.184 | BX20: =IFERROR(BW20/BO20,0) -> 0.038421149 | BY20: =BY18-BY14-BY7 -> 265256.24 | BZ20: =IFERROR(BY20/BO20,0) -> 0.20167436 | CC20: =SUM(CC7:CF7) -> -2483.7412
C22: Producto | D22: TM en Stock Libre | E22: CU | F22: Costo Ventas | G22: Gasto Ventas | H22: Gasto ADM | I22: Gasto Fin | J22: Depreciación | K22: Utilidad Neta | L22: Margen Neto | M22: Venta Equilibrio a Utd Neta | N22: Precio Equilibrio x TM a Utd Neta | O22: Venta Equilibro a EBITDA | P22: Precio Equilibrio x TM a EBITDA | Q22: Precio Mercado | R22: Venta total | S22: Utilidad | T22: Mg Neto | U22: EBITDA | V22: Mg EBITDA | BN22: Venta Julio | BO22: =BO18-BO14-BO7 -> 1315270 | CC22: =CC7/0.5 -> -3969.1723
C23: POTA FILETE CONGELADO | D23: =26*20 -> 520 | E23: =E7 -> 1984.5862 | F23: =E23*D23 -> 1031984.8 | G23: =D23*207.84 -> 108076.8 | H23: =H$18/$D$18*$D23 -> 23669.415 | I23: =I$18/$D$18*$D23 -> 46530.06 | J23: =J$18/$D$18*$D23 -> 37195.719 | K23: 0 | L23: 0 | M23: =F23+G23+H23+I23 -> 1210261.1 | N23: =IFERROR(M23/D23,0) -> 2327.4252 | O23: =F23+G23+H23-J23 -> 1126535.3 | P23: =IFERROR(O23/D23,0) -> 2166.4141 | Q23: 1800 | R23: =Q23*D23 -> 936000 | S23: =R23-M23+(Q23-$BS$19)*D23*0.03 -> -247962.26 | T23: =IFERROR(S23/R23,0) -> -0.26491694 | U23: =R23-(M23-J23-I23)+(Q23-$BS$19)*D23*0.03 -> -164236.48 | V23: =IFERROR(U23/R23,0) -> -0.17546632 | BN23: Cobranza | BO23: 3849629
C24: POTA FILETE DARUMA | D24: =6*26 -> 156 | E24: =E14 -> 3254.8777 | F24: =E24*D24 -> 507760.93 | G24: =D24*207.84 -> 32423.04 | H24: =H$18/$D$18*$D24 -> 7100.8246 | I24: =I$18/$D$18*$D24 -> 13959.018 | J24: =J$18/$D$18*$D24 -> 11158.716 | K24: 0 | L24: 0 | M24: =F24+G24+H24+I24 -> 561243.81 | N24: =IFERROR(M24/D24,0) -> 3597.7167 | O24: =F24+G24+H24-J24 -> 536126.08 | P24: =IFERROR(O24/D24,0) -> 3436.7056 | Q24: 3900 | R24: =Q24*D24 -> 608400 | S24: =R24-M24+(Q24-$BS$19)*D24*0.03 -> 64873.838 | T24: =IFERROR(S24/R24,0) -> 0.10663024 | U24: =R24-(M24-J24-I24)+(Q24-$BS$19)*D24*0.03 -> 89991.572 | V24: =IFERROR(U24/R24,0) -> 0.14791514 | BN24: Inventario | BO24: =M27 -> 5551334.3
C25: TOTAL | D25: =SUM(D23:D24) -> 676 | E25: =F25/D25 -> 2277.7304 | F25: =SUM(F23:F24) -> 1539745.7 | G25: =SUM(G23:G24) -> 140499.84 | H25: =SUM(H23:H24) -> 30770.24 | I25: =SUM(I23:I24) -> 60489.079 | J25: =SUM(J23:J24) -> 48354.434 | K25: =SUM(K23:K24) -> 0 | L25: 0 | M25: =SUM(M23:M24) -> 1771504.9 | N25: =IFERROR(M25/D25,0) -> 2620.5694 | O25: =SUM(O23:O24) -> 1662661.4 | P25: =IFERROR(O25/D25,0) -> 2459.5583 | Q25: =R25/D25 -> 2284.6154 | R25: =SUM(R23:R24) -> 1544400 | S25: =SUM(S23:S24) -> -183088.42 | T25: =S25/R25 -> -0.11854987 | U25: =SUM(U23:U24) -> -74244.906 | V25: =IFERROR(U25/R25,0) -> -0.048073625 | BO25: =SUM(BO22:BO24) -> 10716233
C27: TOTAL | D27: =D18+D25 -> 2402.324 | E27: =F27/D27 -> 1967.9793 | F27: =F18+F25 -> 4727723.9 | G27: =G18+G25 -> 499299.02 | H27: =H18+H25 -> 109349.24 | I27: =I18+I25 -> 214962.08 | J27: =J18+J25 -> 171838.78 | K27: =K18+K25 -> 0 | L27: =L18+L25 -> 0 | M27: =M18+M25 -> 5551334.3 | N27: =IFERROR(M27/D27,0) -> 2310.8183 | O27: =O18+O25 -> 5164533.4 | P27: =IFERROR(O27/D27,0) -> 2149.8072 | Q27: =R27/D27 -> 2048.7389 | R27: =R18+R25 -> 4921734.6 | S27: =S18+S25 -> -490176.38 | T27: =S27/R27 -> -0.099594232 | U27: =U18+U25 -> -103375.51 | V27: =IFERROR(U27/R27,0) -> -0.021003878

Sheet TD
E3: Etiquetas de fila | F3: Suma de TM en Stock | G3: Suma de Costo Ventas | H3: Suma de Gasto Ventas | I3: Suma de Gasto ADM | J3: Suma de Gasto Fin | K3: Suma de Depreciación
B4: =C4=E4 -> TRUE | C4: 10005721 | D4: POTA FILETE CONGELADO | E4: 10005721 | F4: 377.674 | G4: 749526.6 | H4: 78495.764 | I4: 17191.005 | J4: 33794.604 | K4: 27015.107
B5: =C5=E5 -> TRUE | C5: 10005779 | D5: POTA NUCAS CONGELADAS | E5: 10005779 | F5: 329.24 | G5: 534030.7 | H5: 68429.242 | I5: 14986.381 | J5: 29460.687 | K5: 23550.612
B6: =C6=E6 -> TRUE | C6: 10006719 | D6: POTA ALAS CONGELADAS | E6: 10006719 | F6: 487.452 | G6: 917712.41 | H6: 101312.02 | I6: 22187.892 | J6: 43617.637 | K6: 34867.553
B7: =C7=E7 -> TRUE | C7: 10007050 | D7: POTA RECORTES COCIDOS | E7: 10007050 | F7: 59.01 | G7: 85207.251 | H7: 12264.638 | I7: 2686.0235 | J7: 5280.267 | K7: 4220.9988
B8: =C8=E8 -> TRUE | C8: 10007162 | D8: POTA REJOS CONGELADOS | E8: 10007162 | F8: 235.86 | G8: 410560.98 | H8: 49021.142 | I8: 10735.901 | J8: 21104.962 | K8: 16871.12
B9: =C9=E9 -> TRUE | C9: 10007567 | D9: POTA REPRODUCTORES | E9: 10007567 | F9: 107.14 | G9: 180280.11 | H9: 22267.978 | I9: 4876.8099 | J9: 9586.9821 | K9: 7663.7487
B10: =C10=E10 -> TRUE | C10: 10007969 | D10: POTA CONOS | E10: 10007969 | F10: 15.82 | G10: 21649.73 | H10: 3288.0288 | I10: 720.09645 | J10: 1415.5876 | K10: 1131.6082
B11: =C11=E11 -> TRUE | C11: 10009239 | D11: POTA FILETE DARUMA | E11: 10009239 | F11: 40.66 | G11: 132343.33 | H11: 8450.7744 | I11: 1850.7662 | J11: 3638.2928 | K11: 2908.4191
B12: =C12=E12 -> TRUE | C12: 10009334 | D12: POTA ALAS COCIDAS | E12: 10009334 | F12: 32.788 | G12: 92607.362 | H12: 6814.6579 | I12: 1492.4477 | J12: 2933.8993 | K12: 2345.3331
B13: =C13=E13 -> TRUE | C13: 10009386 | D13: VENTOSAS | E13: 10009386 | F13: 19.74 | G13: 34390.454 | H13: 4102.7616 | I13: 898.52743 | J13: 1766.3527 | K13: 1412.0067
B14: =C14=E14 -> FALSE | E14: 10009207 | F14: 20.94 | G14: 29669.268 | H14: 4352.1696 | I14: 953.14915 | J14: 1873.7297 | K14: 1497.843
E15: (en blanco) | F15: 1726.324 | G15: 3187978.2 | H15: 358799.18 | I15: 78579 | J15: 154473 | K15: 123484.35
E16: Total general | F16: 3452.648 | G16: 6375956.4 | H16: 717598.36 | I16: 157158 | J16: 308946 | K16: 246968.7

Sheet Stock Libre
A1: CODIGO | B1: PRODUCTO | C1: TOTAL STOCK | D1: POR EMBARCAR | E1: STOCK LIBRE | G1: CÓDIGO | H1: CU X TM | I1: % MP | J1: incremento MP | K1: TM en Stock | L1: Costo Ventas | M1: Gasto Ventas | N1: Gasto ADM | O1: Gasto Fin | P1: Depreciación | Q1: Utilidad Neta | R1: Margen Neto | S1: Venta Equilibrio | T1: Precio Equilibrio x TM
A2: 10009178 | B2: POTA ALAS FR C/P C/C (B) S/COD BL10 S20 | C2: 14400 | E2: 14400 | G2: 10006719 | H2: =IFERROR(INDEX([1]Resumen!$K$3:$K$63,MATCH(G2,[1]Resumen!$C$3:$C$63,0)),0)*(1+I2*J2)/1000-51.89/1000 -> 1.8826724 | I2: 0.71 | J2: -0.07 | K2: =IF(E2<0,0,E2)/1000 -> 14.4 | L2: =IFERROR(H2*K2,0)*1000 -> 27110.482 | M2: =207.84*K2 -> 2992.896 | N2: =$N$54/$K$52*K2 -> 655.46074 | O2: =$O$54/$K$52*K2 -> 1288.5247 | P2: =$P$54/$K$52*K2 -> 1030.0353 | Q2: 0 | R2: 0 | S2: =L2+M2+N2+O2 -> 32047.363 | T2: =IFERROR(S2/K2,0) -> 2225.5114
A3: 10006668 | B3: POTA ALAS FR C/P C/C <0.5 BL10 S20 | C3: 1260 | D3: 0 | E3: 1260 | G3: 10006719 | H3: =IFERROR(INDEX([1]Resumen!$K$3:$K$63,MATCH(G3,[1]Resumen!$C$3:$C$63,0)),0)*(1+I3*J3)/1000-51.89/1000 -> 1.8826724 | I3: 0.71 | J3: -0.07 | K3: =IF(E3<0,0,E3)/1000 -> 1.26 | L3: =IFERROR(H3*K3,0)*1000 -> 2372.1672 | M3: =207.84*K3 -> 261.8784 | N3: =$N$54/$K$52*K3 -> 57.352814 | O3: =$O$54/$K$52*K3 -> 112.74592 | P3: =$P$54/$K$52*K3 -> 90.128088 | Q3: 0 | R3: 0 | S3: =L3+M3+N3+O3 -> 2804.1443 | T3: =IFERROR(S3/K3,0) -> 2225.5114
A4: 10006719 | B4: POTA ALAS FR C/P C/C 0.5-1 BL10 S20 | C4: 11200 | E4: 11200 | G4: 10006719 | H4: =IFERROR(INDEX([1]Resumen!$K$3:$K$63,MATCH(G4,[1]Resumen!$C$3:$C$63,0)),0)*(1+I4*J4)/1000-51.89/1000 -> 1.8826724 | I4: 0.71 | J4: -0.07 | K4: =IF(E4<0,0,E4)/1000 -> 11.2 | L4: =IFERROR(H4*K4,0)*1000 -> 21085.93 | M4: =207.84*K4 -> 2327.808 | N4: =$N$54/$K$52*K4 -> 509.80279 | O4: =$O$54/$K$52*K4 -> 1002.1859 | P4: =$P$54/$K$52*K4 -> 801.13856 | Q4: 0 | R4: 0 | S4: =L4+M4+N4+O4 -> 24925.727 | T4: =IFERROR(S4/K4,0) -> 2225.5114
A5: 10009265 | B5: POTA ALAS FR C/P C/C 0.3 - 0.5 BL10 S20 | C5: 0 | E5: 0 | G5: 10006719 | H5: =IFERROR(INDEX([1]Resumen!$K$3:$K$63,MATCH(G5,[1]Resumen!$C$3:$C$63,0)),0)*(1+I5*J5)/1000-51.89/1000 -> 1.8826724 | I5: 0.71 | J5: -0.07 | K5: =IF(E5<0,0,E5)/1000 -> 0 | L5: =IFERROR(H5*K5,0)*1000 -> 0 | M5: =207.84*K5 -> 0 | N5: =$N$54/$K$52*K5 -> 0 | O5: =$O$54/$K$52*K5 -> 0 | P5: =$P$54/$K$52*K5 -> 0 | Q5: 0 | R5: 0 | S5: =L5+M5+N5+O5 -> 0 | T5: =IFERROR(S5/K5,0) -> 0
A6: 10006720 | B6: POTA ALAS FR C/P C/C 1-2 BL10 S20 | C6: 1900 | D6: 1900 | E6: 0 | G6: 10006719 | H6: =IFERROR(INDEX([1]Resumen!$K$3:$K$63,MATCH(G6,[1]Resumen!$C$3:$C$63,0)),0)*(1+I6*J6)/1000-51.89/1000 -> 1.8826724 | I6: 0.71 | J6: -0.07 | K6: =IF(E6<0,0,E6)/1000 -> 0 | L6: =IFERROR(H6*K6,0)*1000 -> 0 | M6: =207.84*K6 -> 0 | N6: =$N$54/$K$52*K6 -> 0 | O6: =$O$54/$K$52*K6 -> 0 | P6: =$P$54/$K$52*K6 -> 0 | Q6: 0 | R6: 0 | S6: =L6+M6+N6+O6 -> 0 | T6: =IFERROR(S6/K6,0) -> 0
A7: 10010005 | B7: POTA ALAS FR C/P C/C 1-2 BL10 S20 ENTERA | C7: 20020 | E7: 20020 | G7: 10006719 | H7: =IFERROR(INDEX([1]Resumen!$K$3:$K$63,MATCH(G7,[1]Resumen!$C$3:$C$63,0)),0)*(1+I7*J7)/1000-51.89/1000 -> 1.8826724 | I7: 0.71 | J7: -0.07 | K7: =IF(E7<0,0,E7)/1000 -> 20.02 | L7: =IFERROR(H7*K7,0)*1000 -> 37691.101 | M7: =207.84*K7 -> 4160.9568 | N7: =$N$54/$K$52*K7 -> 911.2725 | O7: =$O$54/$K$52*K7 -> 1791.4073 | P7: =$P$54/$K$52*K7 -> 1432.0352 | Q7: 0 | R7: 0 | S7: =L7+M7+N7+O7 -> 44554.737 | T7: =IFERROR(S7/K7,0) -> 2225.5114
A8: 10006722 | B8: POTA ALAS FR C/P C/C 2up | C8: 120 | D8: 120 | E8: 0 | G8: 10006719 | H8: =IFERROR(INDEX([1]Resumen!$K$3:$K$63,MATCH(G8,[1]Resumen!$C$3:$C$63,0)),0)*(1+I8*J8)/1000-51.89/1000 -> 1.8826724 | I8: 0.71 | J8: -0.07 | K8: =IF(E8<0,0,E8)/1000 -> 0 | L8: =IFERROR(H8*K8,0)*1000 -> 0 | M8: =207.84*K8 -> 0 | N8: =$N$54/$K$52*K8 -> 0 | O8: =$O$54/$K$52*K8 -> 0 | P8: =$P$54/$K$52*K8 -> 0 | Q8: 0 | R8: 0 | S8: =L8+M8+N8+O8 -> 0 | T8: =IFERROR(S8/K8,0) -> 0
A9: 10009207 | B9: POTA LABIOS FR S/COD BL10 S20 | C9: 20940 | E9: 20940 | G9: 10009207 | H9: =IFERROR(INDEX([1]Resumen!$K$3:$K$63,MATCH(G9,[1]Resumen!$C$3:$C$63,0)),0)*(1+I9*J9)/1000-51.89/1000 -> 1.4168705 | I9: 0.71 | J9: -0.07 | K9: =IF(E9<0,0,E9)/1000 -> 20.94 | L9: =IFERROR(H9*K9,0)*1000 -> 29669.268 | M9: =207.84*K9 -> 4352.1696 | N9: =$N$54/$K$52*K9 -> 953.14915 | O9: =$O$54/$K$52*K9 -> 1873.7297 | P9: =$P$54/$K$52*K9 -> 1497.843 | Q9: 0 | R9: 0 | S9: =L9+M9+N9+O9 -> 36848.317 | T9: =IFERROR(S9/K9,0) -> 1759.7095
A10: 10007969 | B10: POTA CONOS | C10: 15820 | E10: 15820 | G10: 10007969 | H10: =IFERROR(INDEX([1]Resumen!$K$3:$K$63,MATCH(G10,[1]Resumen!$C$3:$C$63,0)),0)*(1+I10*J10)/1000-51.89/1000 -> 1.3685038 | I10: 0.71 | J10: -0.07 | K10: =IF(E10<0,0,E10)/1000 -> 15.82 | L10: =IFERROR(H10*K10,0)*1000 -> 21649.73 | M10: =207.84*K10 -> 3288.0288 | N10: =$N$54/$K$52*K10 -> 720.09645 | O10: =$O$54/$K$52*K10 -> 1415.5876 | P10: =$P$54/$K$52*K10 -> 1131.6082 | Q10: 0 | R10: 0 | S10: =L10+M10+N10+O10 -> 27073.443 | T10: =IFERROR(S10/K10,0) -> 1711.3428
A11: 10004433 | B11: POTA FILETE C/M C/T FR 0.5-1.0 BL10 S20 | C11: 1400 | D11: 1400 | E11: 0 | G11: 10005721 | H11: =IFERROR(INDEX([1]Resumen!$K$3:$K$63,MATCH(G11,[1]Resumen!$C$3:$C$63,0)),0)*(1+I11*J11)/1000-51.89/1000 -> 1.9845862 | I11: 0.67 | J11: -0.07 | K11: =IF(E11<0,0,E11)/1000 -> 0 | L11: =IFERROR(H11*K11,0)*1000 -> 0 | M11: =207.84*K11 -> 0 | N11: =$N$54/$K$52*K11 -> 0 | O11: =$O$54/$K$52*K11 -> 0 | P11: =$P$54/$K$52*K11 -> 0 | Q11: 0 | R11: 0 | S11: =L11+M11+N11+O11 -> 0 | T11: =IFERROR(S11/K11,0) -> 0
A12: 10004434 | B12: POTA FILETE C/M C/T FR 1-2 BL10 S20 | C12: 3500 | D12: 2140 | E12: 1360 | G12: 10005721 | H12: =IFERROR(INDEX([1]Resumen!$K$3:$K$63,MATCH(G12,[1]Resumen!$C$3:$C$63,0)),0)*(1+I12*J12)/1000-51.89/1000 -> 1.9845862 | I12: 0.67 | J12: -0.07 | K12: =IF(E12<0,0,E12)/1000 -> 1.36 | L12: =IFERROR(H12*K12,0)*1000 -> 2699.0372 | M12: =207.84*K12 -> 282.6624 | N12: =$N$54/$K$52*K12 -> 61.904625 | O12: =$O$54/$K$52*K12 -> 121.694 | P12: =$P$54/$K$52*K12 -> 97.281111 | Q12: 0 | R12: 0 | S12: =L12+M12+N12+O12 -> 3165.2982 | T12: =IFERROR(S12/K12,0) -> 2327.4252
A13: 10010125 | B13: POTA FILETE C/M C/T FR 1.0 - 3.0 BL10 S20 | C13: 2460 | D13: 2460 | E13: 0 | G13: 10005721 | H13: =IFERROR(INDEX([1]Resumen!$K$3:$K$63,MATCH(G13,[1]Resumen!$C$3:$C$63,0)),0)*(1+I13*J13)/1000-51.89/1000 -> 1.9845862 | I13: 0.67 | J13: -0.07 | K13: =IF(E13<0,0,E13)/1000 -> 0 | L13: =IFERROR(H13*K13,0)*1000 -> 0 | M13: =207.84*K13 -> 0 | N13: =$N$54/$K$52*K13 -> 0 | O13: =$O$54/$K$52*K13 -> 0 | P13: =$P$54/$K$52*K13 -> 0 | Q13: 0 | R13: 0 | S13: =L13+M13+N13+O13 -> 0 | T13: =IFERROR(S13/K13,0) -> 0
A14: 10004435 | B14: POTA FILETE C/M C/T FR 2-4 S20 | C14: 16840 | E14: 16840 | G14: 10005721 | H14: =IFERROR(INDEX([1]Resumen!$K$3:$K$63,MATCH(G14,[1]Resumen!$C$3:$C$63,0)),0)*(1+I14*J14)/1000-51.89/1000 -> 1.9845862 | I14: 0.67 | J14: -0.07 | K14: =IF(E14<0,0,E14)/1000 -> 16.84 | L14: =IFERROR(H14*K14,0)*1000 -> 33420.431 | M14: =207.84*K14 -> 3500.0256 | N14: =$N$54/$K$52*K14 -> 766.52492 | O14: =$O$54/$K$52*K14 -> 1506.8581 | P14: =$P$54/$K$52*K14 -> 1204.569 | Q14: 0 | R14: 0 | S14: =L14+M14+N14+O14 -> 39193.84 | T14: =IFERROR(S14/K14,0) -> 2327.4252
A15: 10005708 | B15: POTA FILETE C/M C/T FR <0.5 Kg AA BL10 S20 | C15: 1080 | E15: 1080 | G15: 10005721 | H15: =IFERROR(INDEX([1]Resumen!$K$3:$K$63,MATCH(G15,[1]Resumen!$C$3:$C$63,0)),0)*(1+I15*J15)/1000-51.89/1000 -> 1.9845862 | I15: 0.67 | J15: -0.07 | K15: =IF(E15<0,0,E15)/1000 -> 1.08 | L15: =IFERROR(H15*K15,0)*1000 -> 2143.3531 | M15: =207.84*K15 -> 224.4672 | N15: =$N$54/$K$52*K15 -> 49.159555 | O15: =$O$54/$K$52*K15 -> 96.639356 | P15: =$P$54/$K$52*K15 -> 77.252647 | Q15: 0 | R15: 0 | S15: =L15+M15+N15+O15 -> 2513.6192 | T15: =IFERROR(S15/K15,0) -> 2327.4252
A16: 10005721 | B16: POTA FILETE C/M C/T FR 2-4 (AA) BL10 S20 | C16: 260460 | D16: 257260 | E16: 3200 | G16: 10005721 | H16: =IFERROR(INDEX([1]Resumen!$K$3:$K$63,MATCH(G16,[1]Resumen!$C$3:$C$63,0)),0)*(1+I16*J16)/1000-51.89/1000 -> 1.9845862 | I16: 0.67 | J16: -0.07 | K16: =IF(E16<0,0,E16)/1000 -> 3.2 | L16: =IFERROR(H16*K16,0)*1000 -> 6350.6758 | M16: =207.84*K16 -> 665.088 | N16: =$N$54/$K$52*K16 -> 145.65794 | O16: =$O$54/$K$52*K16 -> 286.33883 | P16: =$P$54/$K$52*K16 -> 228.89673 | Q16: 0 | R16: 0 | S16: =L16+M16+N16+O16 -> 7447.7605 | T16: =IFERROR(S16/K16,0) -> 2327.4252
A17: 10005711 | B17: POTA FILETE C/M C/T FR 0.5-1.0 AA BL10 S20 | C17: 11340 | D17: 11340 | E17: 0 | G17: 10005721 | H17: =IFERROR(INDEX([1]Resumen!$K$3:$K$63,MATCH(G17,[1]Resumen!$C$3:$C$63,0)),0)*(1+I17*J17)/1000-51.89/1000 -> 1.9845862 | I17: 0.67 | J17: -0.07 | K17: =IF(E17<0,0,E17)/1000 -> 0 | L17: =IFERROR(H17*K17,0)*1000 -> 0 | M17: =207.84*K17 -> 0 | N17: =$N$54/$K$52*K17 -> 0 | O17: =$O$54/$K$52*K17 -> 0 | P17: =$P$54/$K$52*K17 -> 0 | Q17: 0 | R17: 0 | S17: =L17+M17+N17+O17 -> 0 | T17: =IFERROR(S17/K17,0) -> 0
A18: 10010126 | B18: POTA FILETE C/M C/T FR 1.0 - 3.0 AA BL10 S20 | C18: 35920 | D18: 35920 | E18: 0 | G18: 10005721 | H18: =IFERROR(INDEX([1]Resumen!$K$3:$K$63,MATCH(G18,[1]Resumen!$C$3:$C$63,0)),0)*(1+I18*J18)/1000-51.89/1000 -> 1.9845862 | I18: 0.67 | J18: -0.07 | K18: =IF(E18<0,0,E18)/1000 -> 0 | L18: =IFERROR(H18*K18,0)*1000 -> 0 | M18: =207.84*K18 -> 0 | N18: =$N$54/$K$52*K18 -> 0 | O18: =$O$54/$K$52*K18 -> 0 | P18: =$P$54/$K$52*K18 -> 0 | Q18: 0 | R18: 0 | S18: =L18+M18+N18+O18 -> 0 | T18: =IFERROR(S18/K18,0) -> 0
A19: 10005718 | B19: POTA FILETE C/M C/T FR 1-2 AA BL10 S20 JAPON | C19: 3500 | D19: 380 | E19: 3120 | G19: 10005721 | H19: =IFERROR(INDEX([1]Resumen!$K$3:$K$63,MATCH(G19,[1]Resumen!$C$3:$C$63,0)),0)*(1+I19*J19)/1000-51.89/1000 -> 1.9845862 | I19: 0.67 | J19: -0.07 | K19: =IF(E19<0,0,E19)/1000 -> 3.12 | L19: =IFERROR(H19*K19,0)*1000 -> 6191.9089 | M19: =207.84*K19 -> 648.4608 | N19: =$N$54/$K$52*K19 -> 142.01649 | O19: =$O$54/$K$52*K19 -> 279.18036 | P19: =$P$54/$K$52*K19 -> 223.17431 | Q19: 0 | R19: 0 | S19: =L19+M19+N19+O19 -> 7261.5665 | T19: =IFERROR(S19/K19,0) -> 2327.4252
A20: 10009971 | B20: POTA FILETE C/M C/T FR 0.5-1.0 AAA BL10 S20 | C20: 0 | E20: 0 | G20: 10005721 | H20: =IFERROR(INDEX([1]Resumen!$K$3:$K$63,MATCH(G20,[1]Resumen!$C$3:$C$63,0)),0)*(1+I20*J20)/1000-51.89/1000 -> 1.9845862 | I20: 0.67 | J20: -0.07 | K20: =IF(E20<0,0,E20)/1000 -> 0 | L20: =IFERROR(H20*K20,0)*1000 -> 0 | M20: =207.84*K20 -> 0 | N20: =$N$54/$K$52*K20 -> 0 | O20: =$O$54/$K$52*K20 -> 0 | P20: =$P$54/$K$52*K20 -> 0 | Q20: 0 | R20: 0 | S20: =L20+M20+N20+O20 -> 0 | T20: =IFERROR(S20/K20,0) -> 0
A21: 10009972 | B21: POTA FILETE C/M C/T FR 1-2 AA BL10 S20 50% ROSADO | C21: 29720 | E21: 29720 | G21: 10005721 | H21: =IFERROR(INDEX([1]Resumen!$K$3:$K$63,MATCH(G21,[1]Resumen!$C$3:$C$63,0)),0)*(1+I21*J21)/1000-51.89/1000 -> 1.9845862 | I21: 0.67 | J21: -0.07 | K21: =IF(E21<0,0,E21)/1000 -> 29.72 | L21: =IFERROR(H21*K21,0)*1000 -> 58981.901 | M21: =207.84*K21 -> 6177.0048 | N21: =$N$54/$K$52*K21 -> 1352.7981 | O21: =$O$54/$K$52*K21 -> 2659.3719 | P21: =$P$54/$K$52*K21 -> 2125.8784 | Q21: 0 | R21: 0 | S21: =L21+M21+N21+O21 -> 69171.076 | T21: =IFERROR(S21/K21,0) -> 2327.4252
A22: 10010063 | B22: POTA FILETE C/M C/T FR 2-4 AAA BL10 S20 | C22: 0 | D22: 0 | E22: 0 | G22: 10005721 | H22: =IFERROR(INDEX([1]Resumen!$K$3:$K$63,MATCH(G22,[1]Resumen!$C$3:$C$63,0)),0)*(1+I22*J22)/1000-51.89/1000 -> 1.9845862 | I22: 0.67 | J22: -0.07 | K22: =IF(E22<0,0,E22)/1000 -> 0 | L22: =IFERROR(H22*K22,0)*1000 -> 0 | M22: =207.84*K22 -> 0 | N22: =$N$54/$K$52*K22 -> 0 | O22: =$O$54/$K$52*K22 -> 0 | P22: =$P$54/$K$52*K22 -> 0 | Q22: 0 | R22: 0 | S22: =L22+M22+N22+O22 -> 0 | T22: =IFERROR(S22/K22,0) -> 0
A23: 10009298 | B23: POTA FILETE SM ST 1-2 CM/ESP | C23: 3200 | E23: 3200 | G23: 10005721 | H23: =IFERROR(INDEX([1]Resumen!$K$3:$K$63,MATCH(G23,[1]Resumen!$C$3:$C$63,0)),0)*(1+I23*J23)/1000-51.89/1000 -> 1.9845862 | I23: 0.67 | J23: -0.07 | K23: =IF(E23<0,0,E23)/1000 -> 3.2 | L23: =IFERROR(H23*K23,0)*1000 -> 6350.6758 | M23: =207.84*K23 -> 665.088 | N23: =$N$54/$K$52*K23 -> 145.65794 | O23: =$O$54/$K$52*K23 -> 286.33883 | P23: =$P$54/$K$52*K23 -> 228.89673 | Q23: 0 | R23: 0 | S23: =L23+M23+N23+O23 -> 7447.7605 | T23: =IFERROR(S23/K23,0) -> 2327.4252
A24: 10009184 | B24: POTA NUCAS FR ABIERTAS 0.1 - 0.3 BL10 S2 | C24: 114060 | E24: 114060 | G24: 10005779 | H24: =IFERROR(INDEX([1]Resumen!$K$3:$K$63,MATCH(G24,[1]Resumen!$C$3:$C$63,0)),0)*(1+I24*J24)/1000-51.89/1000 -> 1.6220104 | I24: 0.65 | J24: -0.07 | K24: =IF(E24<0,0,E24)/1000 -> 114.06 | L24: =IFERROR(H24*K24,0)*1000 -> 185006.51 | M24: =207.84*K24 -> 23706.23 | N24: =$N$54/$K$52*K24 -> 5191.7952 | O24: =$O$54/$K$52*K24 -> 10206.19 | P24: =$P$54/$K$52*K24 -> 8158.7379 | Q24: 0 | R24: 0 | S24: =L24+M24+N24+O24 -> 224110.72 | T24: =IFERROR(S24/K24,0) -> 1964.8494
A25: 10009271 | B25: POTA NUCAS FR CERRADA 0.1 - 0.3 BL10 S2 | C25: 40100 | E25: 40100 | G25: 10005779 | H25: =IFERROR(INDEX([1]Resumen!$K$3:$K$63,MATCH(G25,[1]Resumen!$C$3:$C$63,0)),0)*(1+I25*J25)/1000-51.89/1000 -> 1.6220104 | I25: 0.65 | J25: -0.07 | K25: =IF(E25<0,0,E25)/1000 -> 40.1 | L25: =IFERROR(H25*K25,0)*1000 -> 65042.617 | M25: =207.84*K25 -> 8334.384 | N25: =$N$54/$K$52*K25 -> 1825.2761 | O25: =$O$54/$K$52*K25 -> 3588.1835 | P25: =$P$54/$K$52*K25 -> 2868.3622 | Q25: 0 | R25: 0 | S25: =L25+M25+N25+O25 -> 78790.46 | T25: =IFERROR(S25/K25,0) -> 1964.8494
A26: 10009183 | B26: POTA NUCAS FR CERRADA <0.1 BL10 S2 | C26: 1040 | E26: 1040 | G26: 10005779 | H26: =IFERROR(INDEX([1]Resumen!$K$3:$K$63,MATCH(G26,[1]Resumen!$C$3:$C$63,0)),0)*(1+I26*J26)/1000-51.89/1000 -> 1.6220104 | I26: 0.65 | J26: -0.07 | K26: =IF(E26<0,0,E26)/1000 -> 1.04 | L26: =IFERROR(H26*K26,0)*1000 -> 1686.8908 | M26: =207.84*K26 -> 216.1536 | N26: =$N$54/$K$52*K26 -> 47.338831 | O26: =$O$54/$K$52*K26 -> 93.060121 | P26: =$P$54/$K$52*K26 -> 74.391438 | Q26: 0 | R26: 0 | S26: =L26+M26+N26+O26 -> 2043.4434 | T26: =IFERROR(S26/K26,0) -> 1964.8494
A27: 10005779 | B27: POTA NUCAS FR ABIERTAS 0.5-1 BL10 S20 | C27: 96900 | D27: 52000 | E27: 44900 | G27: 10005779 | H27: =IFERROR(INDEX([1]Resumen!$K$3:$K$63,MATCH(G27,[1]Resumen!$C$3:$C$63,0)),0)*(1+I27*J27)/1000-51.89/1000 -> 1.6220104 | I27: 0.65 | J27: -0.07 | K27: =IF(E27<0,0,E27)/1000 -> 44.9 | L27: =IFERROR(H27*K27,0)*1000 -> 72828.267 | M27: =207.84*K27 -> 9332.016 | N27: =$N$54/$K$52*K27 -> 2043.763 | O27: =$O$54/$K$52*K27 -> 4017.6918 | P27: =$P$54/$K$52*K27 -> 3211.7073 | Q27: 0 | R27: 0 | S27: =L27+M27+N27+O27 -> 88221.738 | T27: =IFERROR(S27/K27,0) -> 1964.8494
A28: 10005776 | B28: POTA NUCAS FR ABIERTAS 0.3-0.5 BL10 S20 | C28: 187140 | D28: 58000 | E28: 129140 | G28: 10005779 | H28: =IFERROR(INDEX([1]Resumen!$K$3:$K$63,MATCH(G28,[1]Resumen!$C$3:$C$63,0)),0)*(1+I28*J28)/1000-51.89/1000 -> 1.6220104 | I28: 0.65 | J28: -0.07 | K28: =IF(E28<0,0,E28)/1000 -> 129.14 | L28: =IFERROR(H28*K28,0)*1000 -> 209466.42 | M28: =207.84*K28 -> 26840.458 | N28: =$N$54/$K$52*K28 -> 5878.2083 | O28: =$O$54/$K$52*K28 -> 11555.562 | P28: =$P$54/$K$52*K28 -> 9237.4137 | Q28: 0 | R28: 0 | S28: =L28+M28+N28+O28 -> 253740.65 | T28: =IFERROR(S28/K28,0) -> 1964.8494
A29: 10005781 | B29: POTA NUCAS FR ABIERTAS 1-2 BL10 S20 | C29: 25680 | D29: 52000 | E29: 0 | G29: 10005779 | H29: =IFERROR(INDEX([1]Resumen!$K$3:$K$63,MATCH(G29,[1]Resumen!$C$3:$C$63,0)),0)*(1+I29*J29)/1000-51.89/1000 -> 1.6220104 | I29: 0.65 | J29: -0.07 | K29: =IF(E29<0,0,E29)/1000 -> 0 | L29: =IFERROR(H29*K29,0)*1000 -> 0 | M29: =207.84*K29 -> 0 | N29: =$N$54/$K$52*K29 -> 0 | O29: =$O$54/$K$52*K29 -> 0 | P29: =$P$54/$K$52*K29 -> 0 | Q29: 0 | R29: 0 | S29: =L29+M29+N29+O29 -> 0 | T29: =IFERROR(S29/K29,0) -> 0
A30: 10007567 | B30: POTA REJOS OR FR LIMPIOS S/COD BL10 S20 | C30: 73020 | E30: 73020 | G30: 10007567 | H30: =IFERROR(INDEX([1]Resumen!$K$3:$K$63,MATCH(G30,[1]Resumen!$C$3:$C$63,0)),0)*(1+I30*J30)/1000-51.89/1000 -> 1.6826592 | I30: 0.68 | J30: -0.07 | K30: =IF(E30<0,0,E30)/1000 -> 73.02 | L30: =IFERROR(H30*K30,0)*1000 -> 122867.78 | M30: =207.84*K30 -> 15176.477 | N30: =$N$54/$K$52*K30 -> 3323.7321 | O30: =$O$54/$K$52*K30 -> 6533.8943 | P30: =$P$54/$K$52*K30 -> 5223.1373 | Q30: 0 | R30: 0 | S30: =L30+M30+N30+O30 -> 147901.88 | T30: =IFERROR(S30/K30,0) -> 2025.4982
A31: 10010107 | B31: POTA REJOS OR FR LIMPIOS <60 cm BL10 S20 | C31: 34120 | E31: 34120 | G31: 10007567 | H31: =IFERROR(INDEX([1]Resumen!$K$3:$K$63,MATCH(G31,[1]Resumen!$C$3:$C$63,0)),0)*(1+I31*J31)/1000-51.89/1000 -> 1.6826592 | I31: 0.68 | J31: -0.07 | K31: =IF(E31<0,0,E31)/1000 -> 34.12 | L31: =IFERROR(H31*K31,0)*1000 -> 57412.332 | M31: =207.84*K31 -> 7091.5008 | N31: =$N$54/$K$52*K31 -> 1553.0778 | O31: =$O$54/$K$52*K31 -> 3053.0878 | P31: =$P$54/$K$52*K31 -> 2440.6114 | Q31: 0 | R31: 0 | S31: =L31+M31+N31+O31 -> 69109.999 | T31: =IFERROR(S31/K31,0) -> 2025.4982
A32: 10009185 | B32: POTA REJOS FR C/U C/V S/OR <0.1 BL10 | C32: 0 | E32: 0 | G32: 10007162 | H32: =IFERROR(INDEX([1]Resumen!$K$3:$K$63,MATCH(G32,[1]Resumen!$C$3:$C$63,0)),0)*(1+I32*J32)/1000-51.89/1000 -> 1.7406978 | I32: 0.68 | J32: -0.07 | K32: =IF(E32<0,0,E32)/1000 -> 0 | L32: =IFERROR(H32*K32,0)*1000 -> 0 | M32: =207.84*K32 -> 0 | N32: =$N$54/$K$52*K32 -> 0 | O32: =$O$54/$K$52*K32 -> 0 | P32: =$P$54/$K$52*K32 -> 0 | Q32: 0 | R32: 0 | S32: =L32+M32+N32+O32 -> 0 | T32: =IFERROR(S32/K32,0) -> 0
A33: 10009186 | B33: POTA REJOS FR C/U C/V S/OR 0.1-0.3 BL10 | C33: 2080 | E33: 2080 | G33: 10007162 | H33: =IFERROR(INDEX([1]Resumen!$K$3:$K$63,MATCH(G33,[1]Resumen!$C$3:$C$63,0)),0)*(1+I33*J33)/1000-51.89/1000 -> 1.7406978 | I33: 0.68 | J33: -0.07 | K33: =IF(E33<0,0,E33)/1000 -> 2.08 | L33: =IFERROR(H33*K33,0)*1000 -> 3620.6514 | M33: =207.84*K33 -> 432.3072 | N33: =$N$54/$K$52*K33 -> 94.677662 | O33: =$O$54/$K$52*K33 -> 186.12024 | P33: =$P$54/$K$52*K33 -> 148.78288 | Q33: 0 | R33: 0 | S33: =L33+M33+N33+O33 -> 4333.7565 | T33: =IFERROR(S33/K33,0) -> 2083.5368
A34: 10009777 | B34: POTA REJOS FR C/U C/V S/OR 0.3-0.5BL10 | C34: 46660 | D34: 25700 | E34: 20960 | G34: 10007162 | H34: =IFERROR(INDEX([1]Resumen!$K$3:$K$63,MATCH(G34,[1]Resumen!$C$3:$C$63,0)),0)*(1+I34*J34)/1000-51.89/1000 -> 1.7406978 | I34: 0.68 | J34: -0.07 | K34: =IF(E34<0,0,E34)/1000 -> 20.96 | L34: =IFERROR(H34*K34,0)*1000 -> 36485.025 | M34: =207.84*K34 -> 4356.3264 | N34: =$N$54/$K$52*K34 -> 954.05952 | O34: =$O$54/$K$52*K34 -> 1875.5194 | P34: =$P$54/$K$52*K34 -> 1499.2736 | Q34: 0 | R34: 0 | S34: =L34+M34+N34+O34 -> 43670.931 | T34: =IFERROR(S34/K34,0) -> 2083.5368
A35: 10010108 | B35: POTA REJOS FR C/U C/V S/OR 0.5-1.0 BL10 | C35: 52220 | D35: 1300 | E35: 50920 | G35: 10007162 | H35: =IFERROR(INDEX([1]Resumen!$K$3:$K$63,MATCH(G35,[1]Resumen!$C$3:$C$63,0)),0)*(1+I35*J35)/1000-51.89/1000 -> 1.7406978 | I35: 0.68 | J35: -0.07 | K35: =IF(E35<0,0,E35)/1000 -> 50.92 | L35: =IFERROR(H35*K35,0)*1000 -> 88636.331 | M35: =207.84*K35 -> 10583.213 | N35: =$N$54/$K$52*K35 -> 2317.782 | O35: =$O$54/$K$52*K35 -> 4556.3667 | P35: =$P$54/$K$52*K35 -> 3642.3192 | Q35: 0 | R35: 0 | S35: =L35+M35+N35+O35 -> 106093.69 | T35: =IFERROR(S35/K35,0) -> 2083.5368
A36: 10009187 | B36: POTA REJOS FR C/B S/U S/V S/OR 0.3-0.5 BL10 | C36: 340 | E36: 340 | G36: 10007162 | H36: =IFERROR(INDEX([1]Resumen!$K$3:$K$63,MATCH(G36,[1]Resumen!$C$3:$C$63,0)),0)*(1+I36*J36)/1000-51.89/1000 -> 1.7406978 | I36: 0.68 | J36: -0.07 | K36: =IF(E36<0,0,E36)/1000 -> 0.34 | L36: =IFERROR(H36*K36,0)*1000 -> 591.83724 | M36: =207.84*K36 -> 70.6656 | N36: =$N$54/$K$52*K36 -> 15.476156 | O36: =$O$54/$K$52*K36 -> 30.423501 | P36: =$P$54/$K$52*K36 -> 24.320278 | Q36: 0 | R36: 0 | S36: =L36+M36+N36+O36 -> 708.4025 | T36: =IFERROR(S36/K36,0) -> 2083.5368
A37: 10007161 | B37: POTA REJOS FR C/B S/U S/V S/OR 0.5-1 BL1 0 | C37: 30020 | E37: 30020 | G37: 10007162 | H37: =IFERROR(INDEX([1]Resumen!$K$3:$K$63,MATCH(G37,[1]Resumen!$C$3:$C$63,0)),0)*(1+I37*J37)/1000-51.89/1000 -> 1.7406978 | I37: 0.68 | J37: -0.07 | K37: =IF(E37<0,0,E37)/1000 -> 30.02 | L37: =IFERROR(H37*K37,0)*1000 -> 52255.747 | M37: =207.84*K37 -> 6239.3568 | N37: =$N$54/$K$52*K37 -> 1366.4536 | O37: =$O$54/$K$52*K37 -> 2686.2162 | P37: =$P$54/$K$52*K37 -> 2147.3375 | Q37: 0 | R37: 0 | S37: =L37+M37+N37+O37 -> 62547.774 | T37: =IFERROR(S37/K37,0) -> 2083.5368
A38: 10009658 | B38: POTA REJOS FR C/B C/U C/V S/OR 1.0 up BL 10S20 | C38: 2680 | E38: 2680 | G38: 10007162 | H38: =IFERROR(INDEX([1]Resumen!$K$3:$K$63,MATCH(G38,[1]Resumen!$C$3:$C$63,0)),0)*(1+I38*J38)/1000-51.89/1000 -> 1.7406978 | I38: 0.68 | J38: -0.07 | K38: =IF(E38<0,0,E38)/1000 -> 2.68 | L38: =IFERROR(H38*K38,0)*1000 -> 4665.07 | M38: =207.84*K38 -> 557.0112 | N38: =$N$54/$K$52*K38 -> 121.98853 | O38: =$O$54/$K$52*K38 -> 239.80877 | P38: =$P$54/$K$52*K38 -> 191.70101 | Q38: 0 | R38: 0 | S38: =L38+M38+N38+O38 -> 5583.8785 | T38: =IFERROR(S38/K38,0) -> 2083.5368
A39: 10009639 | B39: POTA REJOS FR C/B S/U S/V S/OR 2-UP BL10 | C39: 30200 | E39: 30200 | G39: 10007162 | H39: =IFERROR(INDEX([1]Resumen!$K$3:$K$63,MATCH(G39,[1]Resumen!$C$3:$C$63,0)),0)*(1+I39*J39)/1000-51.89/1000 -> 1.7406978 | I39: 0.68 | J39: -0.07 | K39: =IF(E39<0,0,E39)/1000 -> 30.2 | L39: =IFERROR(H39*K39,0)*1000 -> 52569.073 | M39: =207.84*K39 -> 6276.768 | N39: =$N$54/$K$52*K39 -> 1374.6468 | O39: =$O$54/$K$52*K39 -> 2702.3227 | P39: =$P$54/$K$52*K39 -> 2160.2129 | Q39: 0 | R39: 0 | S39: =L39+M39+N39+O39 -> 62922.81 | T39: =IFERROR(S39/K39,0) -> 2083.5368
A40: 10007162 | B40: POTA REJOS FR C/B S/U S/V S/OR 1-2 BL10 | C40: 98660 | E40: 98660 | G40: 10007162 | H40: =IFERROR(INDEX([1]Resumen!$K$3:$K$63,MATCH(G40,[1]Resumen!$C$3:$C$63,0)),0)*(1+I40*J40)/1000-51.89/1000 -> 1.7406978 | I40: 0.68 | J40: -0.07 | K40: =IF(E40<0,0,E40)/1000 -> 98.66 | L40: =IFERROR(H40*K40,0)*1000 -> 171737.24 | M40: =207.84*K40 -> 20505.494 | N40: =$N$54/$K$52*K40 -> 4490.8164 | O40: =$O$54/$K$52*K40 -> 8828.1842 | P40: =$P$54/$K$52*K40 -> 7057.1723 | Q40: 0 | R40: 0 | S40: =L40+M40+N40+O40 -> 205561.74 | T40: =IFERROR(S40/K40,0) -> 2083.5368
A41: 10009336 | B41: VENTOSAS DE REJOS | C41: 19740 | E41: 19740 | G41: 10009386 | H41: =IFERROR(INDEX([1]Resumen!$K$3:$K$63,MATCH(G41,[1]Resumen!$C$3:$C$63,0)),0)*(1+I41*J41)/1000-51.89/1000 -> 1.7421709 | I41: 0.68 | J41: -0.07 | K41: =IF(E41<0,0,E41)/1000 -> 19.74 | L41: =IFERROR(H41*K41,0)*1000 -> 34390.454 | M41: =207.84*K41 -> 4102.7616 | N41: =$N$54/$K$52*K41 -> 898.52743 | O41: =$O$54/$K$52*K41 -> 1766.3527 | P41: =$P$54/$K$52*K41 -> 1412.0067 | Q41: 0 | R41: 0 | S41: =L41+M41+N41+O41 -> 41158.096 | T41: =IFERROR(S41/K41,0) -> 2085.0099
A42: 10009239 | B42: POTA FILETE PRE COCIDO S/M S/T C/P S/COD | C42: 200660 | D42: 160000 | E42: 40660 | G42: 10009239 | H42: =IFERROR(INDEX([1]Resumen!$K$3:$K$63,MATCH(G42,[1]Resumen!$C$3:$C$63,0)),0)*(1+I42*J42)/1000-51.89/1000 -> 3.2548777 | I42: 0.56 | J42: -0.07 | K42: =IF(E42<0,0,E42)/1000 -> 40.66 | L42: =IFERROR(H42*K42,0)*1000 -> 132343.33 | M42: =207.84*K42 -> 8450.7744 | N42: =$N$54/$K$52*K42 -> 1850.7662 | O42: =$O$54/$K$52*K42 -> 3638.2928 | P42: =$P$54/$K$52*K42 -> 2908.4191 | Q42: 0 | R42: 0 | S42: =L42+M42+N42+O42 -> 146283.16 | T42: =IFERROR(S42/K42,0) -> 3597.7167
A43: 10009251 | B43: POTA FILETE PRE COCIDO S/M S/T C/P 0.6-1.0 | C43: 2000 | D43: 2000 | E43: 0 | G43: 10009239 | H43: =IFERROR(INDEX([1]Resumen!$K$3:$K$63,MATCH(G43,[1]Resumen!$C$3:$C$63,0)),0)*(1+I43*J43)/1000-51.89/1000 -> 3.2548777 | I43: 0.56 | J43: -0.07 | K43: =IF(E43<0,0,E43)/1000 -> 0 | L43: =IFERROR(H43*K43,0)*1000 -> 0 | M43: =207.84*K43 -> 0 | N43: =$N$54/$K$52*K43 -> 0 | O43: =$O$54/$K$52*K43 -> 0 | P43: =$P$54/$K$52*K43 -> 0 | Q43: 0 | R43: 0 | S43: =L43+M43+N43+O43 -> 0 | T43: =IFERROR(S43/K43,0) -> 0
A44: 10009241 | B44: POTA ALAS PRE COC S/COD BL10 S20 | C44: 260 | D44: 260 | E44: 0 | G44: 10009334 | H44: =IFERROR(INDEX([1]Resumen!$K$3:$K$63,MATCH(G44,[1]Resumen!$C$3:$C$63,0)),0)*(1+I44*J44)/1000-51.89/1000 -> 2.8244285 | I44: 0.68 | J44: -0.07 | K44: =IF(E44<0,0,E44)/1000 -> 0 | L44: =IFERROR(H44*K44,0)*1000 -> 0 | M44: =207.84*K44 -> 0 | N44: =$N$54/$K$52*K44 -> 0 | O44: =$O$54/$K$52*K44 -> 0 | P44: =$P$54/$K$52*K44 -> 0 | Q44: 0 | R44: 0 | S44: =L44+M44+N44+O44 -> 0 | T44: =IFERROR(S44/K44,0) -> 0
A45: 10009331 | B45: POTA ALAS PRE COC 0.3up BL9 S18 | C45: 27980 | E45: 27980 | G45: 10009334 | H45: =IFERROR(INDEX([1]Resumen!$K$3:$K$63,MATCH(G45,[1]Resumen!$C$3:$C$63,0)),0)*(1+I45*J45)/1000-51.89/1000 -> 2.8244285 | I45: 0.68 | J45: -0.07 | K45: =IF(E45<0,0,E45)/1000 -> 27.98 | L45: =IFERROR(H45*K45,0)*1000 -> 79027.51 | M45: =207.84*K45 -> 5815.3632 | N45: =$N$54/$K$52*K45 -> 1273.5966 | O45: =$O$54/$K$52*K45 -> 2503.6752 | P45: =$P$54/$K$52*K45 -> 2001.4158 | Q45: 0 | R45: 0 | S45: =L45+M45+N45+O45 -> 88620.145 | T45: =IFERROR(S45/K45,0) -> 3167.2675
A46: 10009334 | B46: POTA ALAS PRE COC B BL9 S18 | C46: 4808 | E46: 4808 | G46: 10009334 | H46: =IFERROR(INDEX([1]Resumen!$K$3:$K$63,MATCH(G46,[1]Resumen!$C$3:$C$63,0)),0)*(1+I46*J46)/1000-51.89/1000 -> 2.8244285 | I46: 0.68 | J46: -0.07 | K46: =IF(E46<0,0,E46)/1000 -> 4.808 | L46: =IFERROR(H46*K46,0)*1000 -> 13579.852 | M46: =207.84*K46 -> 999.29472 | N46: =$N$54/$K$52*K46 -> 218.85106 | O46: =$O$54/$K$52*K46 -> 430.2241 | P46: =$P$54/$K$52*K46 -> 343.91734 | Q46: 0 | R46: 0 | S46: =L46+M46+N46+O46 -> 15228.222 | T46: =IFERROR(S46/K46,0) -> 3167.2675
A47: 10007050 | B47: POTA RECORTES PRE COC BL10 S20 | C47: 20460 | E47: 20460 | G47: 10007050 | H47: =IFERROR(INDEX([1]Resumen!$K$3:$K$63,MATCH(G47,[1]Resumen!$C$3:$C$63,0)),0)*(1+I47*J47)/1000-51.89/1000 -> 1.443946 | I47: 0.68 | J47: -0.07 | K47: =IF(E47<0,0,E47)/1000 -> 20.46 | L47: =IFERROR(H47*K47,0)*1000 -> 29543.134 | M47: =207.84*K47 -> 4252.4064 | N47: =$N$54/$K$52*K47 -> 931.30046 | O47: =$O$54/$K$52*K47 -> 1830.7789 | P47: =$P$54/$K$52*K47 -> 1463.5085 | Q47: 0 | R47: 0 | S47: =L47+M47+N47+O47 -> 36557.62 | T47: =IFERROR(S47/K47,0) -> 1786.7849
A48: 10009337 | B48: POTA RECORTES LAM PRE COC (M) BL7.5 S15 | C48: 106235 | D48: 81000 | E48: 25235 | G48: 10007050 | H48: =IFERROR(INDEX([1]Resumen!$K$3:$K$63,MATCH(G48,[1]Resumen!$C$3:$C$63,0)),0)*(1+I48*J48)/1000-51.89/1000 -> 1.443946 | I48: 0.68 | J48: -0.07 | K48: =IF(E48<0,0,E48)/1000 -> 25.235 | L48: =IFERROR(H48*K48,0)*1000 -> 36437.976 | M48: =207.84*K48 -> 5244.8424 | N48: =$N$54/$K$52*K48 -> 1148.6494 | O48: =$O$54/$K$52*K48 -> 2258.0501 | P48: =$P$54/$K$52*K48 -> 1805.0653 | Q48: 0 | R48: 0 | S48: =L48+M48+N48+O48 -> 45089.518 | T48: =IFERROR(S48/K48,0) -> 1786.7849
A49: 10009332 | B49: POTA RECORTES LAM PRE COC (T) BL7.5 S15 | C49: 40315 | D49: 27000 | E49: 13315 | G49: 10007050 | H49: =IFERROR(INDEX([1]Resumen!$K$3:$K$63,MATCH(G49,[1]Resumen!$C$3:$C$63,0)),0)*(1+I49*J49)/1000-51.89/1000 -> 1.443946 | I49: 0.68 | J49: -0.07 | K49: =IF(E49<0,0,E49)/1000 -> 13.315 | L49: =IFERROR(H49*K49,0)*1000 -> 19226.14 | M49: =207.84*K49 -> 2767.3896 | N49: =$N$54/$K$52*K49 -> 606.07359 | O49: =$O$54/$K$52*K49 -> 1191.438 | P49: =$P$54/$K$52*K49 -> 952.42499 | Q49: 0 | R49: 0 | S49: =L49+M49+N49+O49 -> 23791.042 | T49: =IFERROR(S49/K49,0) -> 1786.7849
A50: 10009650 | B50: FILETE CM CT PARA REPROCESO | C50: 290140 | E50: 319154 | G50: 10005721 | H50: =IFERROR(INDEX([1]Resumen!$K$3:$K$63,MATCH(G50,[1]Resumen!$C$3:$C$63,0)),0)*(1+I50*J50)/1000-51.89/1000 -> 1.9845862 | I50: 0.67 | J50: -0.07 | K50: =IF(E50<0,0,E50)/1000 -> 319.154 | L50: =IFERROR(H50*K50,0)*1000 -> 633388.62 | M50: =207.84*K50 -> 66332.967 | N50: =$N$54/$K$52*K50 -> 14527.286 | O50: =$O$54/$K$52*K50 -> 28558.182 | P50: =$P$54/$K$52*K50 -> 22829.159 | Q50: 0 | R50: 0 | S50: =L50+M50+N50+O50 -> 742807.05 | T50: =IFERROR(S50/K50,0) -> 2327.4252
A51: 10009649 | B51: ALAS FR PARA REPROCESO | C51: 400520 | E51: 440572 | G51: 10006719 | H51: =IFERROR(INDEX([1]Resumen!$K$3:$K$63,MATCH(G51,[1]Resumen!$C$3:$C$63,0)),0)*(1+I51*J51)/1000-51.89/1000 -> 1.8826724 | I51: 0.71 | J51: -0.07 | K51: =IF(E51<0,0,E51)/1000 -> 440.572 | L51: =IFERROR(H51*K51,0)*1000 -> 829452.73 | M51: =207.84*K51 -> 91568.484 | N51: =$N$54/$K$52*K51 -> 20054.003 | O51: =$O$54/$K$52*K51 -> 39422.773 | P51: =$P$54/$K$52*K51 -> 31514.216 | Q51: 0 | R51: 0 | S51: =L51+M51+N51+O51 -> 980497.99 | T51: =IFERROR(S51/K51,0) -> 2225.5114
C52: 2403118 | D52: 772180 | E52: 1726324 | K52: =SUM(K2:K51) -> 1726.324 | L52: =SUM(L2:L51) -> 3187978.2 | M52: =SUM(M2:M51) -> 358799.18 | N52: =SUM(N2:N51) -> 78579 | O52: =SUM(O2:O51) -> 154473 | P52: =SUM(P2:P51) -> 123484.35 | Q52: =SUM(Q2:Q51) -> 0 | R52: =SUM(R2:R51) -> 0 | S52: =SUM(S2:S51) -> 3779829.4 | T52: =IFERROR(S52/K52,0) -> 2189.5249
M54: totales | N54: 78579 | O54: 154473 | P54: 123484.35
