Workbook

Sheet RESUMEN AL 3-8-2026
C2: PERU FROST
C3: AVANCE COMERCIAL AL 3-8-2026
F5: RENTABILIDAD DEL INVENTARIO | X5: 46206 | AA5: 46209 | AD5: 46215 | AG5: 46216 | AJ5: 46219 | AM5: 46222 | AP5: 46224 | AS5: 46225 | AV5: 46229 | AY5: 46232 | BB5: TOTAL PROYECTADO JULIO 2026 | BP5: UNITARIOS POR TM
B6: Código | C6: Producto | D6: TM en Stock Libre | E6: CU | F6: Costo Ventas | G6: Gasto Ventas | H6: Gasto ADM | I6: Gasto Fin | J6: Depreciación | K6: Utilidad Neta | L6: Margen Neto | M6: Venta Equilibrio a Utd Neta | N6: Precio Equilibrio x TM a Utd Neta | O6: Venta Equilibro a EBITDA | P6: Precio Equilibrio x TM a EBITDA | Q6: Precio Mercado | R6: Venta total | S6: Utilidad | T6: Mg Neto | U6: EBITDA | V6: Mg EBITDA | X6: TM | Y6: Venta | Z6: Precio x TM | AA6: TM | AB6: Venta | AC6: Precio x TM | AD6: TM | AE6: Venta | AF6: Precio x TM | AG6: TM | AH6: Venta | AI6: Precio x TM | AJ6: TM | AK6: Venta | AL6: Precio x TM | AM6: TM | AN6: Venta | AO6: Precio x TM | AP6: TM | AQ6: Venta | AR6: Precio x TM | AS6: TM | AT6: Venta | AU6: Precio x TM | AV6: TM | AW6: Venta | AX6: Precio x TM | AY6: TM | AZ6: Venta | BA6: Precio x TM | BB6: TM | BC6: Venta | BD6: Precio x TM | BE6: Costo Ventas | BF6: Gasto Ventas | BG6: Gasto Adm | BH6: Gasto Fin | BI6: Depreciación | BJ6: Drawback | BK6: Utilidad Neta | BL6: Mg Neto % | BM6: EBITDA | BN6: MG EBITDA | BP6: Precio x TM | BQ6: Costo Ventas | BR6: Gasto Ventas | BS6: Gasto Adm | BT6: Gasto Fin | BU6: Depreciación | BV6: Drawback | BW6: Utilidad Neta | BX6: EBITDA
B7: 10005721 | C7: POTA FILETE CONGELADO | D7: =TD!F4 -> 66.6 | E7: =IFERROR(F7/D7,0) -> 1834.431 | F7: =TD!G4 -> 122173.11 | G7: =TD!H4 -> 13842.144 | H7: =TD!I4 -> 2324.682 | I7: =TD!J4 -> 4569.931 | J7: =TD!K4 -> 3653.1624 | K7: 0 | L7: 0 | M7: =F7+G7+H7+I7 -> 142909.86 | N7: =IFERROR(M7/D7,0) -> 2145.7937 | O7: =F7+G7+H7-J7 -> 134686.77 | P7: =IFERROR(O7/D7,0) -> 2022.3239 | Q7: 1800 | R7: =Q7*D7 -> 119880 | S7: =R7-M7 -> -23029.862 | T7: =IFERROR(S7/R7,0) -> -0.19210762 | U7: =R7-(M7-J7-I7) -> -14806.769 | V7: =IFERROR(U7/R7,0) -> -0.12351325 | X7: {=SUM([1]Hoja6!$H$6:$H$24*(X$5=[1]Hoja6!$E$6:$E$24)*($C7=[1]Hoja6!$J$6:$J$24))} -> 0 | Y7: {=SUM([1]Hoja6!$I$6:$I$24*(X$5=[1]Hoja6!$E$6:$E$24)*($C7=[1]Hoja6!$J$6:$J$24))} -> 0 | Z7: =IFERROR(Y7/X7,0) -> 0 | AA7: {=SUM([1]Hoja6!$H$6:$H$24*(AA$5=[1]Hoja6!$E$6:$E$24)*($C7=[1]Hoja6!$J$6:$J$24))} -> 0 | AB7: {=SUM([1]Hoja6!$I$6:$I$24*(AA$5=[1]Hoja6!$E$6:$E$24)*($C7=[1]Hoja6!$J$6:$J$24))} -> 0 | AC7: =IFERROR(AB7/AA7,0) -> 0 | AD7: {=SUM([1]Hoja6!$H$6:$H$24*(AD$5=[1]Hoja6!$E$6:$E$24)*($C7=[1]Hoja6!$J$6:$J$24))} -> 0 | AE7: {=SUM([1]Hoja6!$I$6:$I$24*(AD$5=[1]Hoja6!$E$6:$E$24)*($C7=[1]Hoja6!$J$6:$J$24))} -> 0 | AF7: =IFERROR(AE7/AD7,0) -> 0 | AG7: {=SUM([1]Hoja6!$H$6:$H$24*(AG$5=[1]Hoja6!$E$6:$E$24)*($C7=[1]Hoja6!$J$6:$J$24))} -> 0 | AH7: {=SUM([1]Hoja6!$I$6:$I$24*(AG$5=[1]Hoja6!$E$6:$E$24)*($C7=[1]Hoja6!$J$6:$J$24))} -> 0 | AI7: =IFERROR(AH7/AG7,0) -> 0 | AJ7: {=SUM([1]Hoja6!$H$6:$H$24*(AJ$5=[1]Hoja6!$E$6:$E$24)*($C7=[1]Hoja6!$J$6:$J$24))} -> 0 | AK7: {=SUM([1]Hoja6!$I$6:$I$24*(AJ$5=[1]Hoja6!$E$6:$E$24)*($C7=[1]Hoja6!$J$6:$J$24))} -> 0 | AL7: =IFERROR(AK7/AJ7,0) -> 0 | AM7: {=SUM([1]Hoja6!$H$6:$H$24*(AM$5=[1]Hoja6!$E$6:$E$24)*($C7=[1]Hoja6!$J$6:$J$24))} -> 0 | AN7: {=SUM([1]Hoja6!$I$6:$I$24*(AM$5=[1]Hoja6!$E$6:$E$24)*($C7=[1]Hoja6!$J$6:$J$24))} -> 0 | AO7: =IFERROR(AN7/AM7,0) -> 0 | AP7: {=SUM([1]Hoja6!$H$6:$H$24*(AP$5=[1]Hoja6!$E$6:$E$24)*($C7=[1]Hoja6!$J$6:$J$24))} -> 38 | AQ7: {=SUM([1]Hoja6!$I$6:$I$24*(AP$5=[1]Hoja6!$E$6:$E$24)*($C7=[1]Hoja6!$J$6:$J$24))} -> 78800 | AR7: =IFERROR(AQ7/AP7,0) -> 2073.6842 | AS7: {=SUM([1]Hoja6!$H$6:$H$24*(AS$5=[1]Hoja6!$E$6:$E$24)*($C7=[1]Hoja6!$J$6:$J$24))} -> 0 | AT7: {=SUM([1]Hoja6!$I$6:$I$24*(AS$5=[1]Hoja6!$E$6:$E$24)*($C7=[1]Hoja6!$J$6:$J$24))} -> 0 | AU7: =IFERROR(AT7/AS7,0) -> 0 | AV7: {=SUM([1]Hoja6!$H$6:$H$24*(AV$5=[1]Hoja6!$E$6:$E$24)*($C7=[1]Hoja6!$J$6:$J$24))} -> 0 | AW7: {=SUM([1]Hoja6!$I$6:$I$24*(AV$5=[1]Hoja6!$E$6:$E$24)*($C7=[1]Hoja6!$J$6:$J$24))} -> 0 | AX7: =IFERROR(AW7/AV7,0) -> 0 | AY7: {=SUM([1]Hoja6!$H$6:$H$24*(AY$5=[1]Hoja6!$E$6:$E$24)*($C7=[1]Hoja6!$J$6:$J$24))} -> 0 | AZ7: {=SUM([1]Hoja6!$I$6:$I$24*(AY$5=[1]Hoja6!$E$6:$E$24)*($C7=[1]Hoja6!$J$6:$J$24))} -> 0 | BA7: =IFERROR(AZ7/AY7,0) -> 0 | BB7: =X7+AA7+AD7+AG7+AJ7+AM7+AP7+AY7+AS7+AV7 -> 38 | BC7: =Y7+AB7+AE7+AH7+AK7+AN7+AQ7+AZ7+AT7+AW7 -> 78800 | BD7: =IFERROR(BC7/BB7,0) -> 2073.6842 | BE7: =-IFERROR(F7/D7*BB7,0) -> -69708.378 | BF7: =-207.84*BB7 -> -7897.92 | BG7: =$BG$20/$BB$20*$BB7 -> -3823.7711 | BH7: =$BH$20/$BB$20*$BB7 -> -7516.8862 | BI7: =$BI$20/$BB$20*$BB7 -> -6008.9323 | BJ7: =(BC7-BB7*$BG$21)*0.03 -> 2233.8375 | BK7: =BC7+SUM(BE7:BH7,BJ7) -> -7913.118 | BL7: =IFERROR(BK7/BC7,0) -> -0.10042028 | BM7: =BC7+BE7+BF7+BG7+BJ7-BI7 -> 5612.7005 | BN7: =IFERROR(BM7/BC7,0) -> 0.071227163 | BP7: =BD7 -> 2073.6842 | BQ7: =IFERROR(BE7/$BB7,0) -> -1834.431 | BR7: =IFERROR(BF7/$BB7,0) -> -207.84 | BS7: =IFERROR(BG7/$BB7,0) -> -100.62556 | BT7: =IFERROR(BH7/$BB7,0) -> -197.81279 | BU7: =IFERROR(BI7/$BB7,0) -> -158.1298 | BV7: =IFERROR(BJ7/$BB7,0) -> 58.785198 | BW7: =IFERROR(BK7/$BB7,0) -> -208.23995 | BX7: =IFERROR(BM7/$BB7,0) -> 147.70264
B8: 10005779 | C8: POTA NUCAS CONGELADAS | D8: =TD!F5 -> 439.26 | E8: =IFERROR(F8/D8,0) -> 1483.423 | F8: =TD!G5 -> 651608.37 | G8: =TD!H5 -> 91295.798 | H8: =TD!I5 -> 15332.43 | I8: =TD!J5 -> 30140.959 | J8: =TD!K5 -> 24094.416 | K8: 0 | L8: 0 | M8: =F8+G8+H8+I8 -> 788377.56 | N8: =IFERROR(M8/D8,0) -> 1794.7857 | O8: =F8+G8+H8-J8 -> 734142.19 | P8: =IFERROR(O8/D8,0) -> 1671.3158 | Q8: 1400 | R8: =Q8*D8 -> 614964 | S8: =R8-M8 -> -173413.56 | T8: =IFERROR(S8/R8,0) -> -0.28198978 | U8: =R8-(M8-J8-I8) -> -119178.19 | V8: =IFERROR(U8/R8,0) -> -0.19379701 | X8: {=SUM([1]Hoja6!$H$6:$H$24*(X$5=[1]Hoja6!$E$6:$E$24)*($C8=[1]Hoja6!$J$6:$J$24))} -> 0 | Y8: {=SUM([1]Hoja6!$I$6:$I$24*(X$5=[1]Hoja6!$E$6:$E$24)*($C8=[1]Hoja6!$J$6:$J$24))} -> 0 | Z8: =IFERROR(Y8/X8,0) -> 0 | AA8: {=SUM([1]Hoja6!$H$6:$H$24*(AA$5=[1]Hoja6!$E$6:$E$24)*($C8=[1]Hoja6!$J$6:$J$24))} -> 0 | AB8: {=SUM([1]Hoja6!$I$6:$I$24*(AA$5=[1]Hoja6!$E$6:$E$24)*($C8=[1]Hoja6!$J$6:$J$24))} -> 0 | AC8: =IFERROR(AB8/AA8,0) -> 0 | AD8: {=SUM([1]Hoja6!$H$6:$H$24*(AD$5=[1]Hoja6!$E$6:$E$24)*($C8=[1]Hoja6!$J$6:$J$24))} -> 0 | AE8: {=SUM([1]Hoja6!$I$6:$I$24*(AD$5=[1]Hoja6!$E$6:$E$24)*($C8=[1]Hoja6!$J$6:$J$24))} -> 0 | AF8: =IFERROR(AE8/AD8,0) -> 0 | AG8: {=SUM([1]Hoja6!$H$6:$H$24*(AG$5=[1]Hoja6!$E$6:$E$24)*($C8=[1]Hoja6!$J$6:$J$24))} -> 0 | AH8: {=SUM([1]Hoja6!$I$6:$I$24*(AG$5=[1]Hoja6!$E$6:$E$24)*($C8=[1]Hoja6!$J$6:$J$24))} -> 0 | AI8: =IFERROR(AH8/AG8,0) -> 0 | AJ8: {=SUM([1]Hoja6!$H$6:$H$24*(AJ$5=[1]Hoja6!$E$6:$E$24)*($C8=[1]Hoja6!$J$6:$J$24))} -> 0 | AK8: {=SUM([1]Hoja6!$I$6:$I$24*(AJ$5=[1]Hoja6!$E$6:$E$24)*($C8=[1]Hoja6!$J$6:$J$24))} -> 0 | AL8: =IFERROR(AK8/AJ8,0) -> 0 | AM8: {=SUM([1]Hoja6!$H$6:$H$24*(AM$5=[1]Hoja6!$E$6:$E$24)*($C8=[1]Hoja6!$J$6:$J$24))} -> 67.5 | AN8: {=SUM([1]Hoja6!$I$6:$I$24*(AM$5=[1]Hoja6!$E$6:$E$24)*($C8=[1]Hoja6!$J$6:$J$24))} -> 89775 | AO8: =IFERROR(AN8/AM8,0) -> 1330 | AP8: {=SUM([1]Hoja6!$H$6:$H$24*(AP$5=[1]Hoja6!$E$6:$E$24)*($C8=[1]Hoja6!$J$6:$J$24))} -> 10 | AQ8: {=SUM([1]Hoja6!$I$6:$I$24*(AP$5=[1]Hoja6!$E$6:$E$24)*($C8=[1]Hoja6!$J$6:$J$24))} -> 14000 | AR8: =IFERROR(AQ8/AP8,0) -> 1400 | AS8: {=SUM([1]Hoja6!$H$6:$H$24*(AS$5=[1]Hoja6!$E$6:$E$24)*($C8=[1]Hoja6!$J$6:$J$24))} -> 52 | AT8: {=SUM([1]Hoja6!$I$6:$I$24*(AS$5=[1]Hoja6!$E$6:$E$24)*($C8=[1]Hoja6!$J$6:$J$24))} -> 67600 | AU8: =IFERROR(AT8/AS8,0) -> 1300 | AV8: {=SUM([1]Hoja6!$H$6:$H$24*(AV$5=[1]Hoja6!$E$6:$E$24)*($C8=[1]Hoja6!$J$6:$J$24))} -> 0 | AW8: {=SUM([1]Hoja6!$I$6:$I$24*(AV$5=[1]Hoja6!$E$6:$E$24)*($C8=[1]Hoja6!$J$6:$J$24))} -> 0 | AX8: =IFERROR(AW8/AV8,0) -> 0 | AY8: {=SUM([1]Hoja6!$H$6:$H$24*(AY$5=[1]Hoja6!$E$6:$E$24)*($C8=[1]Hoja6!$J$6:$J$24))} -> 22.5 | AZ8: {=SUM([1]Hoja6!$I$6:$I$24*(AY$5=[1]Hoja6!$E$6:$E$24)*($C8=[1]Hoja6!$J$6:$J$24))} -> 29925 | BA8: =IFERROR(AZ8/AY8,0) -> 1330 | BB8: =X8+AA8+AD8+AG8+AJ8+AM8+AP8+AY8+AS8+AV8 -> 152 | BC8: =Y8+AB8+AE8+AH8+AK8+AN8+AQ8+AZ8+AT8+AW8 -> 201300 | BD8: =IFERROR(BC8/BB8,0) -> 1324.3421 | BE8: =-IFERROR(F8/D8*BB8,0) -> -225480.29 | BF8: =-207.84*BB8 -> -31591.68 | BG8: =$BG$20/$BB$20*$BB8 -> -15295.085 | BH8: =$BH$20/$BB$20*$BB8 -> -30067.545 | BI8: =$BI$20/$BB$20*$BB8 -> -24035.729 | BJ8: =(BC8-BB8*$BG$21)*0.03 -> 5518.3501 | BK8: =BC8+SUM(BE8:BH8,BJ8) -> -95616.25 | BL8: =IFERROR(BK8/BC8,0) -> -0.47499379 | BM8: =BC8+BE8+BF8+BG8+BJ8-BI8 -> -41512.976 | BN8: =IFERROR(BM8/BC8,0) -> -0.20622442 | BP8: =BD8 -> 1324.3421 | BQ8: =IFERROR(BE8/$BB8,0) -> -1483.423 | BR8: =IFERROR(BF8/$BB8,0) -> -207.84 | BS8: =IFERROR(BG8/$BB8,0) -> -100.62556 | BT8: =IFERROR(BH8/$BB8,0) -> -197.81279 | BU8: =IFERROR(BI8/$BB8,0) -> -158.1298 | BV8: =IFERROR(BJ8/$BB8,0) -> 36.304935 | BW8: =IFERROR(BK8/$BB8,0) -> -629.05428 | BX8: =IFERROR(BM8/$BB8,0) -> -273.11169
B9: 10006719 | C9: POTA ALAS CONGELADAS | D9: =TD!F6 -> 15.1 | E9: =IFERROR(F9/D9,0) -> 1731.9701 | F9: =TD!G6 -> 26152.749 | G9: =TD!H6 -> 3138.384 | H9: =TD!I6 -> 527.06755 | I9: =TD!J6 -> 1036.1255 | J9: =TD!K6 -> 828.26956 | K9: 0 | L9: 0 | M9: =F9+G9+H9+I9 -> 30854.326 | N9: =IFERROR(M9/D9,0) -> 2043.3328 | O9: =F9+G9+H9-J9 -> 28989.931 | P9: =IFERROR(O9/D9,0) -> 1919.863 | Q9: 1950 | R9: =Q9*D9 -> 29445 | S9: =R9-M9 -> -1409.326 | T9: =IFERROR(S9/R9,0) -> -0.047862998 | U9: =R9-(M9-J9-I9) -> 455.06909 | V9: =IFERROR(U9/R9,0) -> 0.015454885 | X9: {=SUM([1]Hoja6!$H$6:$H$24*(X$5=[1]Hoja6!$E$6:$E$24)*($C9=[1]Hoja6!$J$6:$J$24))} -> 0 | Y9: {=SUM([1]Hoja6!$I$6:$I$24*(X$5=[1]Hoja6!$E$6:$E$24)*($C9=[1]Hoja6!$J$6:$J$24))} -> 0 | Z9: =IFERROR(Y9/X9,0) -> 0 | AA9: {=SUM([1]Hoja6!$H$6:$H$24*(AA$5=[1]Hoja6!$E$6:$E$24)*($C9=[1]Hoja6!$J$6:$J$24))} -> 0 | AB9: {=SUM([1]Hoja6!$I$6:$I$24*(AA$5=[1]Hoja6!$E$6:$E$24)*($C9=[1]Hoja6!$J$6:$J$24))} -> 0 | AC9: =IFERROR(AB9/AA9,0) -> 0 | AD9: {=SUM([1]Hoja6!$H$6:$H$24*(AD$5=[1]Hoja6!$E$6:$E$24)*($C9=[1]Hoja6!$J$6:$J$24))} -> 54 | AE9: {=SUM([1]Hoja6!$I$6:$I$24*(AD$5=[1]Hoja6!$E$6:$E$24)*($C9=[1]Hoja6!$J$6:$J$24))} -> 94500 | AF9: =IFERROR(AE9/AD9,0) -> 1750 | AG9: {=SUM([1]Hoja6!$H$6:$H$24*(AG$5=[1]Hoja6!$E$6:$E$24)*($C9=[1]Hoja6!$J$6:$J$24))} -> 0 | AH9: {=SUM([1]Hoja6!$I$6:$I$24*(AG$5=[1]Hoja6!$E$6:$E$24)*($C9=[1]Hoja6!$J$6:$J$24))} -> 0 | AI9: =IFERROR(AH9/AG9,0) -> 0 | AJ9: {=SUM([1]Hoja6!$H$6:$H$24*(AJ$5=[1]Hoja6!$E$6:$E$24)*($C9=[1]Hoja6!$J$6:$J$24))} -> 0 | AK9: {=SUM([1]Hoja6!$I$6:$I$24*(AJ$5=[1]Hoja6!$E$6:$E$24)*($C9=[1]Hoja6!$J$6:$J$24))} -> 0 | AL9: =IFERROR(AK9/AJ9,0) -> 0 | AM9: {=SUM([1]Hoja6!$H$6:$H$24*(AM$5=[1]Hoja6!$E$6:$E$24)*($C9=[1]Hoja6!$J$6:$J$24))} -> 0 | AN9: {=SUM([1]Hoja6!$I$6:$I$24*(AM$5=[1]Hoja6!$E$6:$E$24)*($C9=[1]Hoja6!$J$6:$J$24))} -> 0 | AO9: =IFERROR(AN9/AM9,0) -> 0 | AP9: {=SUM([1]Hoja6!$H$6:$H$24*(AP$5=[1]Hoja6!$E$6:$E$24)*($C9=[1]Hoja6!$J$6:$J$24))} -> 0 | AQ9: {=SUM([1]Hoja6!$I$6:$I$24*(AP$5=[1]Hoja6!$E$6:$E$24)*($C9=[1]Hoja6!$J$6:$J$24))} -> 0 | AR9: =IFERROR(AQ9/AP9,0) -> 0 | AS9: {=SUM([1]Hoja6!$H$6:$H$24*(AS$5=[1]Hoja6!$E$6:$E$24)*($C9=[1]Hoja6!$J$6:$J$24))} -> 0 | AT9: {=SUM([1]Hoja6!$I$6:$I$24*(AS$5=[1]Hoja6!$E$6:$E$24)*($C9=[1]Hoja6!$J$6:$J$24))} -> 0 | AU9: =IFERROR(AT9/AS9,0) -> 0 | AV9: {=SUM([1]Hoja6!$H$6:$H$24*(AV$5=[1]Hoja6!$E$6:$E$24)*($C9=[1]Hoja6!$J$6:$J$24))} -> 0 | AW9: {=SUM([1]Hoja6!$I$6:$I$24*(AV$5=[1]Hoja6!$E$6:$E$24)*($C9=[1]Hoja6!$J$6:$J$24))} -> 0 | AX9: =IFERROR(AW9/AV9,0) -> 0 | AY9: {=SUM([1]Hoja6!$H$6:$H$24*(AY$5=[1]Hoja6!$E$6:$E$24)*($C9=[1]Hoja6!$J$6:$J$24))} -> 0 | AZ9: {=SUM([1]Hoja6!$I$6:$I$24*(AY$5=[1]Hoja6!$E$6:$E$24)*($C9=[1]Hoja6!$J$6:$J$24))} -> 0 | BA9: =IFERROR(AZ9/AY9,0) -> 0 | BB9: =X9+AA9+AD9+AG9+AJ9+AM9+AP9+AY9+AS9+AV9 -> 54 | BC9: =Y9+AB9+AE9+AH9+AK9+AN9+AQ9+AZ9+AT9+AW9 -> 94500 | BD9: =IFERROR(BC9/BB9,0) -> 1750 | BE9: =-IFERROR(F9/D9*BB9,0) -> -93526.387 | BF9: =-207.84*BB9 -> -11223.36 | BG9: =$BG$20/$BB$20*$BB9 -> -5433.78 | BH9: =$BH$20/$BB$20*$BB9 -> -10681.891 | BI9: =$BI$20/$BB$20*$BB9 -> -8539.0091 | BJ9: =(BC9-BB9*$BG$21)*0.03 -> 2650.0323 | BK9: =BC9+SUM(BE9:BH9,BJ9) -> -23715.386 | BL9: =IFERROR(BK9/BC9,0) -> -0.25095646 | BM9: =BC9+BE9+BF9+BG9+BJ9-BI9 -> -4494.4855 | BN9: =IFERROR(BM9/BC9,0) -> -0.047560693 | BP9: =BD9 -> 1750 | BQ9: =IFERROR(BE9/$BB9,0) -> -1731.9701 | BR9: =IFERROR(BF9/$BB9,0) -> -207.84 | BS9: =IFERROR(BG9/$BB9,0) -> -100.62556 | BT9: =IFERROR(BH9/$BB9,0) -> -197.81279 | BU9: =IFERROR(BI9/$BB9,0) -> -158.1298 | BV9: =IFERROR(BJ9/$BB9,0) -> 49.074672 | BW9: =IFERROR(BK9/$BB9,0) -> -439.17381 | BX9: =IFERROR(BM9/$BB9,0) -> -83.231214
B10: 10007050 | C10: POTA RECORTES COCIDOS | D10: =TD!F7 -> 57.26 | E10: =IFERROR(F10/D10,0) -> 1308.2098 | F10: =TD!G7 -> 74908.094 | G10: =TD!H7 -> 11900.918 | H10: =TD!I7 -> 1998.6681 | I10: =TD!J7 -> 3929.0428 | J10: =TD!K7 -> 3140.8421 | K10: 0 | L10: 0 | M10: =F10+G10+H10+I10 -> 92736.724 | N10: =IFERROR(M10/D10,0) -> 1619.5725 | O10: =F10+G10+H10-J10 -> 85666.839 | P10: =IFERROR(O10/D10,0) -> 1496.1027 | Q10: 1700 | R10: =Q10*D10 -> 97342 | S10: =R10-M10 -> 4605.2763 | T10: =IFERROR(S10/R10,0) -> 0.04731027 | U10: =R10-(M10-J10-I10) -> 11675.161 | V10: =IFERROR(U10/R10,0) -> 0.11993961 | X10: {=SUM([1]Hoja6!$H$6:$H$24*(X$5=[1]Hoja6!$E$6:$E$24)*($C10=[1]Hoja6!$J$6:$J$24))} -> 27 | Y10: {=SUM([1]Hoja6!$I$6:$I$24*(X$5=[1]Hoja6!$E$6:$E$24)*($C10=[1]Hoja6!$J$6:$J$24))} -> 68850 | Z10: =IFERROR(Y10/X10,0) -> 2550 | AA10: {=SUM([1]Hoja6!$H$6:$H$24*(AA$5=[1]Hoja6!$E$6:$E$24)*($C10=[1]Hoja6!$J$6:$J$24))} -> 0 | AB10: {=SUM([1]Hoja6!$I$6:$I$24*(AA$5=[1]Hoja6!$E$6:$E$24)*($C10=[1]Hoja6!$J$6:$J$24))} -> 0 | AC10: =IFERROR(AB10/AA10,0) -> 0 | AD10: {=SUM([1]Hoja6!$H$6:$H$24*(AD$5=[1]Hoja6!$E$6:$E$24)*($C10=[1]Hoja6!$J$6:$J$24))} -> 0 | AE10: {=SUM([1]Hoja6!$I$6:$I$24*(AD$5=[1]Hoja6!$E$6:$E$24)*($C10=[1]Hoja6!$J$6:$J$24))} -> 0 | AF10: =IFERROR(AE10/AD10,0) -> 0 | AG10: {=SUM([1]Hoja6!$H$6:$H$24*(AG$5=[1]Hoja6!$E$6:$E$24)*($C10=[1]Hoja6!$J$6:$J$24))} -> 27 | AH10: {=SUM([1]Hoja6!$I$6:$I$24*(AG$5=[1]Hoja6!$E$6:$E$24)*($C10=[1]Hoja6!$J$6:$J$24))} -> 67500 | AI10: =IFERROR(AH10/AG10,0) -> 2500 | AJ10: {=SUM([1]Hoja6!$H$6:$H$24*(AJ$5=[1]Hoja6!$E$6:$E$24)*($C10=[1]Hoja6!$J$6:$J$24))} -> 0 | AK10: {=SUM([1]Hoja6!$I$6:$I$24*(AJ$5=[1]Hoja6!$E$6:$E$24)*($C10=[1]Hoja6!$J$6:$J$24))} -> 0 | AL10: =IFERROR(AK10/AJ10,0) -> 0 | AM10: {=SUM([1]Hoja6!$H$6:$H$24*(AM$5=[1]Hoja6!$E$6:$E$24)*($C10=[1]Hoja6!$J$6:$J$24))} -> 0 | AN10: {=SUM([1]Hoja6!$I$6:$I$24*(AM$5=[1]Hoja6!$E$6:$E$24)*($C10=[1]Hoja6!$J$6:$J$24))} -> 0 | AO10: =IFERROR(AN10/AM10,0) -> 0 | AP10: {=SUM([1]Hoja6!$H$6:$H$24*(AP$5=[1]Hoja6!$E$6:$E$24)*($C10=[1]Hoja6!$J$6:$J$24))} -> 0 | AQ10: {=SUM([1]Hoja6!$I$6:$I$24*(AP$5=[1]Hoja6!$E$6:$E$24)*($C10=[1]Hoja6!$J$6:$J$24))} -> 0 | AR10: =IFERROR(AQ10/AP10,0) -> 0 | AS10: {=SUM([1]Hoja6!$H$6:$H$24*(AS$5=[1]Hoja6!$E$6:$E$24)*($C10=[1]Hoja6!$J$6:$J$24))} -> 0 | AT10: {=SUM([1]Hoja6!$I$6:$I$24*(AS$5=[1]Hoja6!$E$6:$E$24)*($C10=[1]Hoja6!$J$6:$J$24))} -> 0 | AU10: =IFERROR(AT10/AS10,0) -> 0 | AV10: {=SUM([1]Hoja6!$H$6:$H$24*(AV$5=[1]Hoja6!$E$6:$E$24)*($C10=[1]Hoja6!$J$6:$J$24))} -> 0 | AW10: {=SUM([1]Hoja6!$I$6:$I$24*(AV$5=[1]Hoja6!$E$6:$E$24)*($C10=[1]Hoja6!$J$6:$J$24))} -> 0 | AX10: =IFERROR(AW10/AV10,0) -> 0 | AY10: {=SUM([1]Hoja6!$H$6:$H$24*(AY$5=[1]Hoja6!$E$6:$E$24)*($C10=[1]Hoja6!$J$6:$J$24))} -> 0 | AZ10: {=SUM([1]Hoja6!$I$6:$I$24*(AY$5=[1]Hoja6!$E$6:$E$24)*($C10=[1]Hoja6!$J$6:$J$24))} -> 0 | BA10: =IFERROR(AZ10/AY10,0) -> 0 | BB10: =X10+AA10+AD10+AG10+AJ10+AM10+AP10+AY10+AS10+AV10 -> 54 | BC10: =Y10+AB10+AE10+AH10+AK10+AN10+AQ10+AZ10+AT10+AW10 -> 136350 | BD10: =IFERROR(BC10/BB10,0) -> 2525 | BE10: =-IFERROR(F10/D10*BB10,0) -> -70643.33 | BF10: =-207.84*BB10 -> -11223.36 | BG10: =$BG$20/$BB$20*$BB10 -> -5433.78 | BH10: =$BH$20/$BB$20*$BB10 -> -10681.891 | BI10: =$BI$20/$BB$20*$BB10 -> -8539.0091 | BJ10: =(BC10-BB10*$BG$21)*0.03 -> 3905.5323 | BK10: =BC10+SUM(BE10:BH10,BJ10) -> 42273.171 | BL10: =IFERROR(BK10/BC10,0) -> 0.31003426 | BM10: =BC10+BE10+BF10+BG10+BJ10-BI10 -> 61494.071 | BN10: =IFERROR(BM10/BC10,0) -> 0.45100162 | BP10: =BD10 -> 2525 | BQ10: =IFERROR(BE10/$BB10,0) -> -1308.2098 | BR10: =IFERROR(BF10/$BB10,0) -> -207.84 | BS10: =IFERROR(BG10/$BB10,0) -> -100.62556 | BT10: =IFERROR(BH10/$BB10,0) -> -197.81279 | BU10: =IFERROR(BI10/$BB10,0) -> -158.1298 | BV10: =IFERROR(BJ10/$BB10,0) -> 72.324672 | BW10: =IFERROR(BK10/$BB10,0) -> 782.8365 | BX10: =IFERROR(BM10/$BB10,0) -> 1138.7791
B11: 10007162 | C11: POTA REJOS CONGELADOS | D11: =TD!F8 -> 272.36 | E11: =IFERROR(F11/D11,0) -> 1596.5588 | F11: =TD!G8 -> 434838.76 | G11: =TD!H8 -> 56607.302 | H11: =TD!I8 -> 9506.7628 | I11: =TD!J8 -> 18688.685 | J11: =TD!K8 -> 14939.569 | K11: 0 | L11: 0 | M11: =F11+G11+H11+I11 -> 519641.51 | N11: =IFERROR(M11/D11,0) -> 1907.9215 | O11: =F11+G11+H11-J11 -> 486013.25 | P11: =IFERROR(O11/D11,0) -> 1784.4517 | Q11: 2700 | R11: =Q11*D11 -> 735372 | S11: =R11-M11 -> 215730.49 | T11: =IFERROR(S11/R11,0) -> 0.2933624 | U11: =R11-(M11-J11-I11) -> 249358.75 | V11: =IFERROR(U11/R11,0) -> 0.33909198 | X11: {=SUM([1]Hoja6!$H$6:$H$24*(X$5=[1]Hoja6!$E$6:$E$24)*($C11=[1]Hoja6!$J$6:$J$24))} -> 0 | Y11: {=SUM([1]Hoja6!$I$6:$I$24*(X$5=[1]Hoja6!$E$6:$E$24)*($C11=[1]Hoja6!$J$6:$J$24))} -> 0 | Z11: =IFERROR(Y11/X11,0) -> 0 | AA11: {=SUM([1]Hoja6!$H$6:$H$24*(AA$5=[1]Hoja6!$E$6:$E$24)*($C11=[1]Hoja6!$J$6:$J$24))} -> 0 | AB11: {=SUM([1]Hoja6!$I$6:$I$24*(AA$5=[1]Hoja6!$E$6:$E$24)*($C11=[1]Hoja6!$J$6:$J$24))} -> 0 | AC11: =IFERROR(AB11/AA11,0) -> 0 | AD11: {=SUM([1]Hoja6!$H$6:$H$24*(AD$5=[1]Hoja6!$E$6:$E$24)*($C11=[1]Hoja6!$J$6:$J$24))} -> 108 | AE11: {=SUM([1]Hoja6!$I$6:$I$24*(AD$5=[1]Hoja6!$E$6:$E$24)*($C11=[1]Hoja6!$J$6:$J$24))} -> 275400 | AF11: =IFERROR(AE11/AD11,0) -> 2550 | AG11: {=SUM([1]Hoja6!$H$6:$H$24*(AG$5=[1]Hoja6!$E$6:$E$24)*($C11=[1]Hoja6!$J$6:$J$24))} -> 0 | AH11: {=SUM([1]Hoja6!$I$6:$I$24*(AG$5=[1]Hoja6!$E$6:$E$24)*($C11=[1]Hoja6!$J$6:$J$24))} -> 0 | AI11: =IFERROR(AH11/AG11,0) -> 0 | AJ11: {=SUM([1]Hoja6!$H$6:$H$24*(AJ$5=[1]Hoja6!$E$6:$E$24)*($C11=[1]Hoja6!$J$6:$J$24))} -> 0 | AK11: {=SUM([1]Hoja6!$I$6:$I$24*(AJ$5=[1]Hoja6!$E$6:$E$24)*($C11=[1]Hoja6!$J$6:$J$24))} -> 0 | AL11: =IFERROR(AK11/AJ11,0) -> 0 | AM11: {=SUM([1]Hoja6!$H$6:$H$24*(AM$5=[1]Hoja6!$E$6:$E$24)*($C11=[1]Hoja6!$J$6:$J$24))} -> 27 | AN11: {=SUM([1]Hoja6!$I$6:$I$24*(AM$5=[1]Hoja6!$E$6:$E$24)*($C11=[1]Hoja6!$J$6:$J$24))} -> 80610 | AO11: =IFERROR(AN11/AM11,0) -> 2985.5556 | AP11: {=SUM([1]Hoja6!$H$6:$H$24*(AP$5=[1]Hoja6!$E$6:$E$24)*($C11=[1]Hoja6!$J$6:$J$24))} -> 0 | AQ11: {=SUM([1]Hoja6!$I$6:$I$24*(AP$5=[1]Hoja6!$E$6:$E$24)*($C11=[1]Hoja6!$J$6:$J$24))} -> 0 | AR11: =IFERROR(AQ11/AP11,0) -> 0 | AS11: {=SUM([1]Hoja6!$H$6:$H$24*(AS$5=[1]Hoja6!$E$6:$E$24)*($C11=[1]Hoja6!$J$6:$J$24))} -> 0 | AT11: {=SUM([1]Hoja6!$I$6:$I$24*(AS$5=[1]Hoja6!$E$6:$E$24)*($C11=[1]Hoja6!$J$6:$J$24))} -> 0 | AU11: =IFERROR(AT11/AS11,0) -> 0 | AV11: {=SUM([1]Hoja6!$H$6:$H$24*(AV$5=[1]Hoja6!$E$6:$E$24)*($C11=[1]Hoja6!$J$6:$J$24))} -> 27 | AW11: {=SUM([1]Hoja6!$I$6:$I$24*(AV$5=[1]Hoja6!$E$6:$E$24)*($C11=[1]Hoja6!$J$6:$J$24))} -> 81000 | AX11: =IFERROR(AW11/AV11,0) -> 3000 | AY11: {=SUM([1]Hoja6!$H$6:$H$24*(AY$5=[1]Hoja6!$E$6:$E$24)*($C11=[1]Hoja6!$J$6:$J$24))} -> 0 | AZ11: {=SUM([1]Hoja6!$I$6:$I$24*(AY$5=[1]Hoja6!$E$6:$E$24)*($C11=[1]Hoja6!$J$6:$J$24))} -> 0 | BA11: =IFERROR(AZ11/AY11,0) -> 0 | BB11: =X11+AA11+AD11+AG11+AJ11+AM11+AP11+AY11+AS11+AV11 -> 162 | BC11: =Y11+AB11+AE11+AH11+AK11+AN11+AQ11+AZ11+AT11+AW11 -> 437010 | BD11: =IFERROR(BC11/BB11,0) -> 2697.5926 | BE11: =-IFERROR(F11/D11*BB11,0) -> -258642.53 | BF11: =-207.84*BB11 -> -33670.08 | BG11: =$BG$20/$BB$20*$BB11 -> -16301.34 | BH11: =$BH$20/$BB$20*$BB11 -> -32045.673 | BI11: =$BI$20/$BB$20*$BB11 -> -25617.027 | BJ11: =(BC11-BB11*$BG$21)*0.03 -> 12555.397 | BK11: =BC11+SUM(BE11:BH11,BJ11) -> 108905.78 | BL11: =IFERROR(BK11/BC11,0) -> 0.2492066 | BM11: =BC11+BE11+BF11+BG11+BJ11-BI11 -> 166568.48 | BN11: =IFERROR(BM11/BC11,0) -> 0.38115484 | BP11: =BD11 -> 2697.5926 | BQ11: =IFERROR(BE11/$BB11,0) -> -1596.5588 | BR11: =IFERROR(BF11/$BB11,0) -> -207.84 | BS11: =IFERROR(BG11/$BB11,0) -> -100.62556 | BT11: =IFERROR(BH11/$BB11,0) -> -197.81279 | BU11: =IFERROR(BI11/$BB11,0) -> -158.1298 | BV11: =IFERROR(BJ11/$BB11,0) -> 77.502449 | BW11: =IFERROR(BK11/$BB11,0) -> 672.25788 | BX11: =IFERROR(BM11/$BB11,0) -> 1028.2005
B12: 10007567 | C12: POTA REPRODUCTORES | D12: =TD!F9 -> 132.38 | E12: =IFERROR(F12/D12,0) -> 1540.1637 | F12: =TD!G9 -> 203886.87 | G12: =TD!H9 -> 27513.859 | H12: =TD!I9 -> 4620.7419 | I12: =TD!J9 -> 9083.5956 | J12: =TD!K9 -> 7261.346 | K12: 0 | L12: 0 | M12: =F12+G12+H12+I12 -> 245105.06 | N12: =IFERROR(M12/D12,0) -> 1851.5264 | O12: =F12+G12+H12-J12 -> 228760.12 | P12: =IFERROR(O12/D12,0) -> 1728.0565 | Q12: 2800 | R12: =Q12*D12 -> 370664 | S12: =R12-M12 -> 125558.94 | T12: =IFERROR(S12/R12,0) -> 0.33874058 | U12: =R12-(M12-J12-I12) -> 141903.88 | V12: =IFERROR(U12/R12,0) -> 0.38283696 | X12: {=SUM([1]Hoja6!$H$6:$H$24*(X$5=[1]Hoja6!$E$6:$E$24)*($C12=[1]Hoja6!$J$6:$J$24))} -> 0 | Y12: {=SUM([1]Hoja6!$I$6:$I$24*(X$5=[1]Hoja6!$E$6:$E$24)*($C12=[1]Hoja6!$J$6:$J$24))} -> 0 | Z12: =IFERROR(Y12/X12,0) -> 0 | AA12: {=SUM([1]Hoja6!$H$6:$H$24*(AA$5=[1]Hoja6!$E$6:$E$24)*($C12=[1]Hoja6!$J$6:$J$24))} -> 26 | AB12: {=SUM([1]Hoja6!$I$6:$I$24*(AA$5=[1]Hoja6!$E$6:$E$24)*($C12=[1]Hoja6!$J$6:$J$24))} -> 74100 | AC12: =IFERROR(AB12/AA12,0) -> 2850 | AD12: {=SUM([1]Hoja6!$H$6:$H$24*(AD$5=[1]Hoja6!$E$6:$E$24)*($C12=[1]Hoja6!$J$6:$J$24))} -> 0 | AE12: {=SUM([1]Hoja6!$I$6:$I$24*(AD$5=[1]Hoja6!$E$6:$E$24)*($C12=[1]Hoja6!$J$6:$J$24))} -> 0 | AF12: =IFERROR(AE12/AD12,0) -> 0 | AG12: {=SUM([1]Hoja6!$H$6:$H$24*(AG$5=[1]Hoja6!$E$6:$E$24)*($C12=[1]Hoja6!$J$6:$J$24))} -> 26 | AH12: {=SUM([1]Hoja6!$I$6:$I$24*(AG$5=[1]Hoja6!$E$6:$E$24)*($C12=[1]Hoja6!$J$6:$J$24))} -> 70980 | AI12: =IFERROR(AH12/AG12,0) -> 2730 | AJ12: {=SUM([1]Hoja6!$H$6:$H$24*(AJ$5=[1]Hoja6!$E$6:$E$24)*($C12=[1]Hoja6!$J$6:$J$24))} -> 0 | AK12: {=SUM([1]Hoja6!$I$6:$I$24*(AJ$5=[1]Hoja6!$E$6:$E$24)*($C12=[1]Hoja6!$J$6:$J$24))} -> 0 | AL12: =IFERROR(AK12/AJ12,0) -> 0 | AM12: {=SUM([1]Hoja6!$H$6:$H$24*(AM$5=[1]Hoja6!$E$6:$E$24)*($C12=[1]Hoja6!$J$6:$J$24))} -> 0 | AN12: {=SUM([1]Hoja6!$I$6:$I$24*(AM$5=[1]Hoja6!$E$6:$E$24)*($C12=[1]Hoja6!$J$6:$J$24))} -> 0 | AO12: =IFERROR(AN12/AM12,0) -> 0 | AP12: {=SUM([1]Hoja6!$H$6:$H$24*(AP$5=[1]Hoja6!$E$6:$E$24)*($C12=[1]Hoja6!$J$6:$J$24))} -> 0 | AQ12: {=SUM([1]Hoja6!$I$6:$I$24*(AP$5=[1]Hoja6!$E$6:$E$24)*($C12=[1]Hoja6!$J$6:$J$24))} -> 0 | AR12: =IFERROR(AQ12/AP12,0) -> 0 | AS12: {=SUM([1]Hoja6!$H$6:$H$24*(AS$5=[1]Hoja6!$E$6:$E$24)*($C12=[1]Hoja6!$J$6:$J$24))} -> 27 | AT12: {=SUM([1]Hoja6!$I$6:$I$24*(AS$5=[1]Hoja6!$E$6:$E$24)*($C12=[1]Hoja6!$J$6:$J$24))} -> 69336 | AU12: =IFERROR(AT12/AS12,0) -> 2568 | AV12: {=SUM([1]Hoja6!$H$6:$H$24*(AV$5=[1]Hoja6!$E$6:$E$24)*($C12=[1]Hoja6!$J$6:$J$24))} -> 0 | AW12: {=SUM([1]Hoja6!$I$6:$I$24*(AV$5=[1]Hoja6!$E$6:$E$24)*($C12=[1]Hoja6!$J$6:$J$24))} -> 0 | AX12: =IFERROR(AW12/AV12,0) -> 0 | AY12: {=SUM([1]Hoja6!$H$6:$H$24*(AY$5=[1]Hoja6!$E$6:$E$24)*($C12=[1]Hoja6!$J$6:$J$24))} -> 0 | AZ12: {=SUM([1]Hoja6!$I$6:$I$24*(AY$5=[1]Hoja6!$E$6:$E$24)*($C12=[1]Hoja6!$J$6:$J$24))} -> 0 | BA12: =IFERROR(AZ12/AY12,0) -> 0 | BB12: =X12+AA12+AD12+AG12+AJ12+AM12+AP12+AY12+AS12+AV12 -> 79 | BC12: =Y12+AB12+AE12+AH12+AK12+AN12+AQ12+AZ12+AT12+AW12 -> 214416 | BD12: =IFERROR(BC12/BB12,0) -> 2714.1266 | BE12: =-IFERROR(F12/D12*BB12,0) -> -121672.93 | BF12: =-207.84*BB12 -> -16419.36 | BG12: =$BG$20/$BB$20*$BB12 -> -7949.4189 | BH12: =$BH$20/$BB$20*$BB12 -> -15627.211 | BI12: =$BI$20/$BB$20*$BB12 -> -12492.254 | BJ12: =(BC12-BB12*$BG$21)*0.03 -> 6161.8791 | BK12: =BC12+SUM(BE12:BH12,BJ12) -> 58908.96 | BL12: =IFERROR(BK12/BC12,0) -> 0.27474143 | BM12: =BC12+BE12+BF12+BG12+BJ12-BI12 -> 87028.424 | BN12: =IFERROR(BM12/BC12,0) -> 0.40588587 | BP12: =BD12 -> 2714.1266 | BQ12: =IFERROR(BE12/$BB12,0) -> -1540.1637 | BR12: =IFERROR(BF12/$BB12,0) -> -207.84 | BS12: =IFERROR(BG12/$BB12,0) -> -100.62556 | BT12: =IFERROR(BH12/$BB12,0) -> -197.81279 | BU12: =IFERROR(BI12/$BB12,0) -> -158.1298 | BV12: =IFERROR(BJ12/$BB12,0) -> 77.998469 | BW12: =IFERROR(BK12/$BB12,0) -> 745.68303 | BX12: =IFERROR(BM12/$BB12,0) -> 1101.6256
B13: 10007969 | C13: POTA CONOS | D13: =TD!F10 -> 19.34 | E13: =IFERROR(F13/D13,0) -> 1233.0367 | F13: =TD!G10 -> 23846.93 | G13: =TD!H10 -> 4019.6256 | H13: =TD!I10 -> 675.06532 | I13: =TD!J10 -> 1327.064 | J13: =TD!K10 -> 1060.8433 | K13: 0 | L13: 0 | M13: =F13+G13+H13+I13 -> 29868.685 | N13: =IFERROR(M13/D13,0) -> 1544.3994 | O13: =F13+G13+H13-J13 -> 27480.777 | P13: =IFERROR(O13/D13,0) -> 1420.9295 | Q13: 1700 | R13: =Q13*D13 -> 32878 | S13: =R13-M13 -> 3009.3152 | T13: =IFERROR(S13/R13,0) -> 0.091529754 | U13: =R13-(M13-J13-I13) -> 5397.2226 | V13: =IFERROR(U13/R13,0) -> 0.16415909 | X13: {=SUM([1]Hoja6!$H$6:$H$24*(X$5=[1]Hoja6!$E$6:$E$24)*($C13=[1]Hoja6!$J$6:$J$24))} -> 0 | Y13: {=SUM([1]Hoja6!$I$6:$I$24*(X$5=[1]Hoja6!$E$6:$E$24)*($C13=[1]Hoja6!$J$6:$J$24))} -> 0 | Z13: =IFERROR(Y13/X13,0) -> 0 | AA13: {=SUM([1]Hoja6!$H$6:$H$24*(AA$5=[1]Hoja6!$E$6:$E$24)*($C13=[1]Hoja6!$J$6:$J$24))} -> 0 | AB13: {=SUM([1]Hoja6!$I$6:$I$24*(AA$5=[1]Hoja6!$E$6:$E$24)*($C13=[1]Hoja6!$J$6:$J$24))} -> 0 | AC13: =IFERROR(AB13/AA13,0) -> 0 | AD13: {=SUM([1]Hoja6!$H$6:$H$24*(AD$5=[1]Hoja6!$E$6:$E$24)*($C13=[1]Hoja6!$J$6:$J$24))} -> 54 | AE13: {=SUM([1]Hoja6!$I$6:$I$24*(AD$5=[1]Hoja6!$E$6:$E$24)*($C13=[1]Hoja6!$J$6:$J$24))} -> 86400 | AF13: =IFERROR(AE13/AD13,0) -> 1600 | AG13: {=SUM([1]Hoja6!$H$6:$H$24*(AG$5=[1]Hoja6!$E$6:$E$24)*($C13=[1]Hoja6!$J$6:$J$24))} -> 0 | AH13: {=SUM([1]Hoja6!$I$6:$I$24*(AG$5=[1]Hoja6!$E$6:$E$24)*($C13=[1]Hoja6!$J$6:$J$24))} -> 0 | AI13: =IFERROR(AH13/AG13,0) -> 0 | AJ13: {=SUM([1]Hoja6!$H$6:$H$24*(AJ$5=[1]Hoja6!$E$6:$E$24)*($C13=[1]Hoja6!$J$6:$J$24))} -> 0 | AK13: {=SUM([1]Hoja6!$I$6:$I$24*(AJ$5=[1]Hoja6!$E$6:$E$24)*($C13=[1]Hoja6!$J$6:$J$24))} -> 0 | AL13: =IFERROR(AK13/AJ13,0) -> 0 | AM13: {=SUM([1]Hoja6!$H$6:$H$24*(AM$5=[1]Hoja6!$E$6:$E$24)*($C13=[1]Hoja6!$J$6:$J$24))} -> 0 | AN13: {=SUM([1]Hoja6!$I$6:$I$24*(AM$5=[1]Hoja6!$E$6:$E$24)*($C13=[1]Hoja6!$J$6:$J$24))} -> 0 | AO13: =IFERROR(AN13/AM13,0) -> 0 | AP13: {=SUM([1]Hoja6!$H$6:$H$24*(AP$5=[1]Hoja6!$E$6:$E$24)*($C13=[1]Hoja6!$J$6:$J$24))} -> 0 | AQ13: {=SUM([1]Hoja6!$I$6:$I$24*(AP$5=[1]Hoja6!$E$6:$E$24)*($C13=[1]Hoja6!$J$6:$J$24))} -> 0 | AR13: =IFERROR(AQ13/AP13,0) -> 0 | AS13: {=SUM([1]Hoja6!$H$6:$H$24*(AS$5=[1]Hoja6!$E$6:$E$24)*($C13=[1]Hoja6!$J$6:$J$24))} -> 0 | AT13: {=SUM([1]Hoja6!$I$6:$I$24*(AS$5=[1]Hoja6!$E$6:$E$24)*($C13=[1]Hoja6!$J$6:$J$24))} -> 0 | AU13: =IFERROR(AT13/AS13,0) -> 0 | AV13: {=SUM([1]Hoja6!$H$6:$H$24*(AV$5=[1]Hoja6!$E$6:$E$24)*($C13=[1]Hoja6!$J$6:$J$24))} -> 0 | AW13: {=SUM([1]Hoja6!$I$6:$I$24*(AV$5=[1]Hoja6!$E$6:$E$24)*($C13=[1]Hoja6!$J$6:$J$24))} -> 0 | AX13: =IFERROR(AW13/AV13,0) -> 0 | AY13: {=SUM([1]Hoja6!$H$6:$H$24*(AY$5=[1]Hoja6!$E$6:$E$24)*($C13=[1]Hoja6!$J$6:$J$24))} -> 0 | AZ13: {=SUM([1]Hoja6!$I$6:$I$24*(AY$5=[1]Hoja6!$E$6:$E$24)*($C13=[1]Hoja6!$J$6:$J$24))} -> 0 | BA13: =IFERROR(AZ13/AY13,0) -> 0 | BB13: =X13+AA13+AD13+AG13+AJ13+AM13+AP13+AY13+AS13+AV13 -> 54 | BC13: =Y13+AB13+AE13+AH13+AK13+AN13+AQ13+AZ13+AT13+AW13 -> 86400 | BD13: =IFERROR(BC13/BB13,0) -> 1600 | BE13: =-IFERROR(F13/D13*BB13,0) -> -66583.982 | BF13: =-207.84*BB13 -> -11223.36 | BG13: =$BG$20/$BB$20*$BB13 -> -5433.78 | BH13: =$BH$20/$BB$20*$BB13 -> -10681.891 | BI13: =$BI$20/$BB$20*$BB13 -> -8539.0091 | BJ13: =(BC13-BB13*$BG$21)*0.03 -> 2407.0323 | BK13: =BC13+SUM(BE13:BH13,BJ13) -> -5115.9805 | BL13: =IFERROR(BK13/BC13,0) -> -0.059212737 | BM13: =BC13+BE13+BF13+BG13+BJ13-BI13 -> 14104.92 | BN13: =IFERROR(BM13/BC13,0) -> 0.16325138 | BP13: =BD13 -> 1600 | BQ13: =IFERROR(BE13/$BB13,0) -> -1233.0367 | BR13: =IFERROR(BF13/$BB13,0) -> -207.84 | BS13: =IFERROR(BG13/$BB13,0) -> -100.62556 | BT13: =IFERROR(BH13/$BB13,0) -> -197.81279 | BU13: =IFERROR(BI13/$BB13,0) -> -158.1298 | BV13: =IFERROR(BJ13/$BB13,0) -> 44.574672 | BW13: =IFERROR(BK13/$BB13,0) -> -94.740379 | BX13: =IFERROR(BM13/$BB13,0) -> 261.20221
B14: 10009239 | C14: POTA FILETE DARUMA | D14: =TD!F11 -> 102.9 | E14: =IFERROR(F14/D14,0) -> 3085.0611 | F14: =TD!G11 -> 317452.79 | G14: =TD!H11 -> 21386.736 | H14: =TD!I11 -> 3591.7385 | I14: =TD!J11 -> 7060.7493 | J14: =TD!K11 -> 5644.3005 | K14: 0 | L14: 0 | M14: =F14+G14+H14+I14 -> 349492.01 | N14: =IFERROR(M14/D14,0) -> 3396.4238 | O14: =F14+G14+H14-J14 -> 336786.96 | P14: =IFERROR(O14/D14,0) -> 3272.954 | Q14: 3500 | R14: =Q14*D14 -> 360150 | S14: =R14-M14 -> 10657.987 | T14: =IFERROR(S14/R14,0) -> 0.029593188 | U14: =R14-(M14-J14-I14) -> 23363.036 | V14: =IFERROR(U14/R14,0) -> 0.064870294 | X14: {=SUM([1]Hoja6!$H$6:$H$24*(X$5=[1]Hoja6!$E$6:$E$24)*($C14=[1]Hoja6!$J$6:$J$24))} -> 0 | Y14: {=SUM([1]Hoja6!$I$6:$I$24*(X$5=[1]Hoja6!$E$6:$E$24)*($C14=[1]Hoja6!$J$6:$J$24))} -> 0 | Z14: =IFERROR(Y14/X14,0) -> 0 | AA14: {=SUM([1]Hoja6!$H$6:$H$24*(AA$5=[1]Hoja6!$E$6:$E$24)*($C14=[1]Hoja6!$J$6:$J$24))} -> 0 | AB14: {=SUM([1]Hoja6!$I$6:$I$24*(AA$5=[1]Hoja6!$E$6:$E$24)*($C14=[1]Hoja6!$J$6:$J$24))} -> 0 | AC14: =IFERROR(AB14/AA14,0) -> 0 | AD14: {=SUM([1]Hoja6!$H$6:$H$24*(AD$5=[1]Hoja6!$E$6:$E$24)*($C14=[1]Hoja6!$J$6:$J$24))} -> 0 | AE14: {=SUM([1]Hoja6!$I$6:$I$24*(AD$5=[1]Hoja6!$E$6:$E$24)*($C14=[1]Hoja6!$J$6:$J$24))} -> 0 | AF14: =IFERROR(AE14/AD14,0) -> 0 | AG14: {=SUM([1]Hoja6!$H$6:$H$24*(AG$5=[1]Hoja6!$E$6:$E$24)*($C14=[1]Hoja6!$J$6:$J$24))} -> 0 | AH14: {=SUM([1]Hoja6!$I$6:$I$24*(AG$5=[1]Hoja6!$E$6:$E$24)*($C14=[1]Hoja6!$J$6:$J$24))} -> 0 | AI14: =IFERROR(AH14/AG14,0) -> 0 | AJ14: {=SUM([1]Hoja6!$H$6:$H$24*(AJ$5=[1]Hoja6!$E$6:$E$24)*($C14=[1]Hoja6!$J$6:$J$24))} -> 0 | AK14: {=SUM([1]Hoja6!$I$6:$I$24*(AJ$5=[1]Hoja6!$E$6:$E$24)*($C14=[1]Hoja6!$J$6:$J$24))} -> 0 | AL14: =IFERROR(AK14/AJ14,0) -> 0 | AM14: {=SUM([1]Hoja6!$H$6:$H$24*(AM$5=[1]Hoja6!$E$6:$E$24)*($C14=[1]Hoja6!$J$6:$J$24))} -> 0 | AN14: {=SUM([1]Hoja6!$I$6:$I$24*(AM$5=[1]Hoja6!$E$6:$E$24)*($C14=[1]Hoja6!$J$6:$J$24))} -> 0 | AO14: =IFERROR(AN14/AM14,0) -> 0 | AP14: {=SUM([1]Hoja6!$H$6:$H$24*(AP$5=[1]Hoja6!$E$6:$E$24)*($C14=[1]Hoja6!$J$6:$J$24))} -> 0 | AQ14: {=SUM([1]Hoja6!$I$6:$I$24*(AP$5=[1]Hoja6!$E$6:$E$24)*($C14=[1]Hoja6!$J$6:$J$24))} -> 0 | AR14: =IFERROR(AQ14/AP14,0) -> 0 | AS14: {=SUM([1]Hoja6!$H$6:$H$24*(AS$5=[1]Hoja6!$E$6:$E$24)*($C14=[1]Hoja6!$J$6:$J$24))} -> 0 | AT14: {=SUM([1]Hoja6!$I$6:$I$24*(AS$5=[1]Hoja6!$E$6:$E$24)*($C14=[1]Hoja6!$J$6:$J$24))} -> 0 | AU14: =IFERROR(AT14/AS14,0) -> 0 | AV14: {=SUM([1]Hoja6!$H$6:$H$24*(AV$5=[1]Hoja6!$E$6:$E$24)*($C14=[1]Hoja6!$J$6:$J$24))} -> 0 | AW14: {=SUM([1]Hoja6!$I$6:$I$24*(AV$5=[1]Hoja6!$E$6:$E$24)*($C14=[1]Hoja6!$J$6:$J$24))} -> 0 | AX14: =IFERROR(AW14/AV14,0) -> 0 | AY14: {=SUM([1]Hoja6!$H$6:$H$24*(AY$5=[1]Hoja6!$E$6:$E$24)*($C14=[1]Hoja6!$J$6:$J$24))} -> 0 | AZ14: {=SUM([1]Hoja6!$I$6:$I$24*(AY$5=[1]Hoja6!$E$6:$E$24)*($C14=[1]Hoja6!$J$6:$J$24))} -> 0 | BA14: =IFERROR(AZ14/AY14,0) -> 0 | BB14: =X14+AA14+AD14+AG14+AJ14+AM14+AP14+AY14+AS14+AV14 -> 0 | BC14: =Y14+AB14+AE14+AH14+AK14+AN14+AQ14+AZ14+AT14+AW14 -> 0 | BD14: =IFERROR(BC14/BB14,0) -> 0 | BE14: =-BB14*'[2]Stock Libre'!H36*1000 -> 0 | BF14: =-207.84*BB14 -> 0 | BG14: =$BG$20/$BB$20*$BB14 -> 0 | BH14: =$BH$20/$BB$20*$BB14 -> 0 | BI14: =$BI$20/$BB$20*$BB14 -> 0 | BJ14: =(BC14-BB14*$BG$21)*0.03 -> 0 | BK14: =BC14+SUM(BE14:BH14,BJ14) -> 0 | BL14: =IFERROR(BK14/BC14,0) -> 0 | BM14: =BC14+BE14+BF14+BG14+BJ14-BI14 -> 0 | BN14: =IFERROR(BM14/BC14,0) -> 0 | BP14: =BD14 -> 0 | BQ14: =IFERROR(BE14/$BB14,0) -> 0 | BR14: =IFERROR(BF14/$BB14,0) -> 0 | BS14: =IFERROR(BG14/$BB14,0) -> 0 | BT14: =IFERROR(BH14/$BB14,0) -> 0 | BU14: =IFERROR(BI14/$BB14,0) -> 0 | BV14: =IFERROR(BJ14/$BB14,0) -> 0 | BW14: =IFERROR(BK14/$BB14,0) -> 0 | BX14: =IFERROR(BM14/$BB14,0) -> 0
B15: 10009334 | C15: POTA ALAS COCIDAS | D15: =TD!F12 -> 19.036 | E15: =IFERROR(F15/D15,0) -> 2649.6026 | F15: =TD!G12 -> 50437.835 | G15: =TD!H12 -> 3956.4422 | H15: =TD!I12 -> 664.45416 | I15: =TD!J12 -> 1306.2043 | J15: =TD!K12 -> 1044.1682 | K15: 0 | L15: 0 | M15: =F15+G15+H15+I15 -> 56364.936 | N15: =IFERROR(M15/D15,0) -> 2960.9653 | O15: =F15+G15+H15-J15 -> 54014.563 | P15: =IFERROR(O15/D15,0) -> 2837.4955 | Q15: 3500 | R15: =Q15*D15 -> 66626 | S15: =R15-M15 -> 10261.064 | T15: =IFERROR(S15/R15,0) -> 0.15400991 | U15: =R15-(M15-J15-I15) -> 12611.437 | V15: =IFERROR(U15/R15,0) -> 0.18928701 | X15: {=SUM([1]Hoja6!$H$6:$H$24*(X$5=[1]Hoja6!$E$6:$E$24)*($C15=[1]Hoja6!$J$6:$J$24))} -> 0 | Y15: {=SUM([1]Hoja6!$I$6:$I$24*(X$5=[1]Hoja6!$E$6:$E$24)*($C15=[1]Hoja6!$J$6:$J$24))} -> 0 | Z15: =IFERROR(Y15/X15,0) -> 0 | AA15: {=SUM([1]Hoja6!$H$6:$H$24*(AA$5=[1]Hoja6!$E$6:$E$24)*($C15=[1]Hoja6!$J$6:$J$24))} -> 0 | AB15: {=SUM([1]Hoja6!$I$6:$I$24*(AA$5=[1]Hoja6!$E$6:$E$24)*($C15=[1]Hoja6!$J$6:$J$24))} -> 0 | AC15: =IFERROR(AB15/AA15,0) -> 0 | AD15: {=SUM([1]Hoja6!$H$6:$H$24*(AD$5=[1]Hoja6!$E$6:$E$24)*($C15=[1]Hoja6!$J$6:$J$24))} -> 0 | AE15: {=SUM([1]Hoja6!$I$6:$I$24*(AD$5=[1]Hoja6!$E$6:$E$24)*($C15=[1]Hoja6!$J$6:$J$24))} -> 0 | AF15: =IFERROR(AE15/AD15,0) -> 0 | AG15: {=SUM([1]Hoja6!$H$6:$H$24*(AG$5=[1]Hoja6!$E$6:$E$24)*($C15=[1]Hoja6!$J$6:$J$24))} -> 0 | AH15: {=SUM([1]Hoja6!$I$6:$I$24*(AG$5=[1]Hoja6!$E$6:$E$24)*($C15=[1]Hoja6!$J$6:$J$24))} -> 0 | AI15: =IFERROR(AH15/AG15,0) -> 0 | AJ15: {=SUM([1]Hoja6!$H$6:$H$24*(AJ$5=[1]Hoja6!$E$6:$E$24)*($C15=[1]Hoja6!$J$6:$J$24))} -> 0 | AK15: {=SUM([1]Hoja6!$I$6:$I$24*(AJ$5=[1]Hoja6!$E$6:$E$24)*($C15=[1]Hoja6!$J$6:$J$24))} -> 0 | AL15: =IFERROR(AK15/AJ15,0) -> 0 | AM15: {=SUM([1]Hoja6!$H$6:$H$24*(AM$5=[1]Hoja6!$E$6:$E$24)*($C15=[1]Hoja6!$J$6:$J$24))} -> 0 | AN15: {=SUM([1]Hoja6!$I$6:$I$24*(AM$5=[1]Hoja6!$E$6:$E$24)*($C15=[1]Hoja6!$J$6:$J$24))} -> 0 | AO15: =IFERROR(AN15/AM15,0) -> 0 | AP15: {=SUM([1]Hoja6!$H$6:$H$24*(AP$5=[1]Hoja6!$E$6:$E$24)*($C15=[1]Hoja6!$J$6:$J$24))} -> 0 | AQ15: {=SUM([1]Hoja6!$I$6:$I$24*(AP$5=[1]Hoja6!$E$6:$E$24)*($C15=[1]Hoja6!$J$6:$J$24))} -> 0 | AR15: =IFERROR(AQ15/AP15,0) -> 0 | AS15: {=SUM([1]Hoja6!$H$6:$H$24*(AS$5=[1]Hoja6!$E$6:$E$24)*($C15=[1]Hoja6!$J$6:$J$24))} -> 0 | AT15: {=SUM([1]Hoja6!$I$6:$I$24*(AS$5=[1]Hoja6!$E$6:$E$24)*($C15=[1]Hoja6!$J$6:$J$24))} -> 0 | AU15: =IFERROR(AT15/AS15,0) -> 0 | AV15: {=SUM([1]Hoja6!$H$6:$H$24*(AV$5=[1]Hoja6!$E$6:$E$24)*($C15=[1]Hoja6!$J$6:$J$24))} -> 0 | AW15: {=SUM([1]Hoja6!$I$6:$I$24*(AV$5=[1]Hoja6!$E$6:$E$24)*($C15=[1]Hoja6!$J$6:$J$24))} -> 0 | AX15: =IFERROR(AW15/AV15,0) -> 0 | AY15: {=SUM([1]Hoja6!$H$6:$H$24*(AY$5=[1]Hoja6!$E$6:$E$24)*($C15=[1]Hoja6!$J$6:$J$24))} -> 0 | AZ15: {=SUM([1]Hoja6!$I$6:$I$24*(AY$5=[1]Hoja6!$E$6:$E$24)*($C15=[1]Hoja6!$J$6:$J$24))} -> 0 | BA15: =IFERROR(AZ15/AY15,0) -> 0 | BB15: =X15+AA15+AD15+AG15+AJ15+AM15+AP15+AY15+AS15+AV15 -> 0 | BC15: =Y15+AB15+AE15+AH15+AK15+AN15+AQ15+AZ15+AT15+AW15 -> 0 | BD15: =IFERROR(BC15/BB15,0) -> 0 | BE15: =-BB15*'[3]Stock Libre'!H47*1000 -> 0 | BF15: =-207.84*BB15 -> 0 | BG15: =$BG$20/$BB$20*$BB15 -> 0 | BH15: =$BH$20/$BB$20*$BB15 -> 0 | BI15: =$BI$20/$BB$20*$BB15 -> 0 | BJ15: =(BC15-BB15*$BG$21)*0.03 -> 0 | BK15: =BC15+SUM(BE15:BH15,BJ15) -> 0 | BL15: =IFERROR(BK15/BC15,0) -> 0 | BM15: =BC15+BE15+BF15+BG15+BJ15-BI15 -> 0 | BN15: =IFERROR(BM15/BC15,0) -> 0 | BP15: =BD15 -> 0 | BQ15: =IFERROR(BE15/$BB15,0) -> 0 | BR15: =IFERROR(BF15/$BB15,0) -> 0 | BS15: =IFERROR(BG15/$BB15,0) -> 0 | BT15: =IFERROR(BH15/$BB15,0) -> 0 | BU15: =IFERROR(BI15/$BB15,0) -> 0 | BV15: =IFERROR(BJ15/$BB15,0) -> 0 | BW15: =IFERROR(BK15/$BB15,0) -> 0 | BX15: =IFERROR(BM15/$BB15,0) -> 0
B16: 10009386 | C16: VENTOSAS | D16: =TD!F13 -> 21.32 | E16: =IFERROR(F16/D16,0) -> 1597.9903 | F16: =TD!G13 -> 34069.152 | G16: =TD!H13 -> 4431.1488 | H16: =TD!I13 -> 744.17749 | I16: =TD!J13 -> 1462.9269 | J16: =TD!K13 -> 1169.4508 | K16: 0 | L16: 0 | M16: =F16+G16+H16+I16 -> 40707.405 | N16: =IFERROR(M16/D16,0) -> 1909.353 | O16: =F16+G16+H16-J16 -> 38075.028 | P16: =IFERROR(O16/D16,0) -> 1785.8831 | Q16: 2000 | R16: =Q16*D16 -> 42640 | S16: =R16-M16 -> 1932.5946 | T16: =IFERROR(S16/R16,0) -> 0.045323514 | U16: =R16-(M16-J16-I16) -> 4564.9723 | V16: =IFERROR(U16/R16,0) -> 0.10705845 | X16: {=SUM([1]Hoja6!$H$6:$H$24*(X$5=[1]Hoja6!$E$6:$E$24)*($C16=[1]Hoja6!$J$6:$J$24))} -> 0 | Y16: {=SUM([1]Hoja6!$I$6:$I$24*(X$5=[1]Hoja6!$E$6:$E$24)*($C16=[1]Hoja6!$J$6:$J$24))} -> 0 | Z16: =IFERROR(Y16/X16,0) -> 0 | AA16: {=SUM([1]Hoja6!$H$6:$H$24*(AA$5=[1]Hoja6!$E$6:$E$24)*($C16=[1]Hoja6!$J$6:$J$24))} -> 0 | AB16: {=SUM([1]Hoja6!$I$6:$I$24*(AA$5=[1]Hoja6!$E$6:$E$24)*($C16=[1]Hoja6!$J$6:$J$24))} -> 0 | AC16: =IFERROR(AB16/AA16,0) -> 0 | AD16: {=SUM([1]Hoja6!$H$6:$H$24*(AD$5=[1]Hoja6!$E$6:$E$24)*($C16=[1]Hoja6!$J$6:$J$24))} -> 0 | AE16: {=SUM([1]Hoja6!$I$6:$I$24*(AD$5=[1]Hoja6!$E$6:$E$24)*($C16=[1]Hoja6!$J$6:$J$24))} -> 0 | AF16: =IFERROR(AE16/AD16,0) -> 0 | AG16: {=SUM([1]Hoja6!$H$6:$H$24*(AG$5=[1]Hoja6!$E$6:$E$24)*($C16=[1]Hoja6!$J$6:$J$24))} -> 0 | AH16: {=SUM([1]Hoja6!$I$6:$I$24*(AG$5=[1]Hoja6!$E$6:$E$24)*($C16=[1]Hoja6!$J$6:$J$24))} -> 0 | AI16: =IFERROR(AH16/AG16,0) -> 0 | AJ16: {=SUM([1]Hoja6!$H$6:$H$24*(AJ$5=[1]Hoja6!$E$6:$E$24)*($C16=[1]Hoja6!$J$6:$J$24))} -> 0 | AK16: {=SUM([1]Hoja6!$I$6:$I$24*(AJ$5=[1]Hoja6!$E$6:$E$24)*($C16=[1]Hoja6!$J$6:$J$24))} -> 0 | AL16: =IFERROR(AK16/AJ16,0) -> 0 | AM16: {=SUM([1]Hoja6!$H$6:$H$24*(AM$5=[1]Hoja6!$E$6:$E$24)*($C16=[1]Hoja6!$J$6:$J$24))} -> 0 | AN16: {=SUM([1]Hoja6!$I$6:$I$24*(AM$5=[1]Hoja6!$E$6:$E$24)*($C16=[1]Hoja6!$J$6:$J$24))} -> 0 | AO16: =IFERROR(AN16/AM16,0) -> 0 | AP16: {=SUM([1]Hoja6!$H$6:$H$24*(AP$5=[1]Hoja6!$E$6:$E$24)*($C16=[1]Hoja6!$J$6:$J$24))} -> 0 | AQ16: {=SUM([1]Hoja6!$I$6:$I$24*(AP$5=[1]Hoja6!$E$6:$E$24)*($C16=[1]Hoja6!$J$6:$J$24))} -> 0 | AR16: =IFERROR(AQ16/AP16,0) -> 0 | AS16: {=SUM([1]Hoja6!$H$6:$H$24*(AS$5=[1]Hoja6!$E$6:$E$24)*($C16=[1]Hoja6!$J$6:$J$24))} -> 0 | AT16: {=SUM([1]Hoja6!$I$6:$I$24*(AS$5=[1]Hoja6!$E$6:$E$24)*($C16=[1]Hoja6!$J$6:$J$24))} -> 0 | AU16: =IFERROR(AT16/AS16,0) -> 0 | AV16: {=SUM([1]Hoja6!$H$6:$H$24*(AV$5=[1]Hoja6!$E$6:$E$24)*($C16=[1]Hoja6!$J$6:$J$24))} -> 0 | AW16: {=SUM([1]Hoja6!$I$6:$I$24*(AV$5=[1]Hoja6!$E$6:$E$24)*($C16=[1]Hoja6!$J$6:$J$24))} -> 0 | AX16: =IFERROR(AW16/AV16,0) -> 0 | AY16: {=SUM([1]Hoja6!$H$6:$H$24*(AY$5=[1]Hoja6!$E$6:$E$24)*($C16=[1]Hoja6!$J$6:$J$24))} -> 0 | AZ16: {=SUM([1]Hoja6!$I$6:$I$24*(AY$5=[1]Hoja6!$E$6:$E$24)*($C16=[1]Hoja6!$J$6:$J$24))} -> 0 | BA16: =IFERROR(AZ16/AY16,0) -> 0 | BB16: =X16+AA16+AD16+AG16+AJ16+AM16+AP16+AY16+AS16+AV16 -> 0 | BC16: =Y16+AB16+AE16+AH16+AK16+AN16+AQ16+AZ16+AT16+AW16 -> 0 | BD16: =IFERROR(BC16/BB16,0) -> 0 | BE16: =-IFERROR(F16/D16*BB16,0) -> 0 | BF16: =-207.84*BB16 -> 0 | BG16: =$BG$20/$BB$20*$BB16 -> 0 | BH16: =$BH$20/$BB$20*$BB16 -> 0 | BI16: =$BI$20/$BB$20*$BB16 -> 0 | BJ16: =(BC16-BB16*$BG$21)*0.03 -> 0 | BK16: =BC16+SUM(BE16:BH16,BJ16) -> 0 | BL16: =IFERROR(BK16/BC16,0) -> 0 | BM16: =BC16+BE16+BF16+BG16+BJ16-BI16 -> 0 | BN16: =IFERROR(BM16/BC16,0) -> 0 | BP16: =BD16 -> 0 | BQ16: =IFERROR(BE16/$BB16,0) -> 0 | BR16: =IFERROR(BF16/$BB16,0) -> 0 | BS16: =IFERROR(BG16/$BB16,0) -> 0 | BT16: =IFERROR(BH16/$BB16,0) -> 0 | BU16: =IFERROR(BI16/$BB16,0) -> 0 | BV16: =IFERROR(BJ16/$BB16,0) -> 0 | BW16: =IFERROR(BK16/$BB16,0) -> 0 | BX16: =IFERROR(BM16/$BB16,0) -> 0
B17: 10009386 | C17: OTROS | D17: =TD!F14 -> 30.58 | E17: =IFERROR(F17/D17,0) -> 1279.9703 | F17: =TD!G14 -> 39141.49 | G17: =TD!H14 -> 6355.7472 | H17: =TD!I14 -> 1067.3991 | I17: =TD!J14 -> 2098.3257 | J17: =TD!K14 -> 1677.383 | K17: 0 | L17: 0 | M17: =F17+G17+H17+I17 -> 48662.962 | N17: =IFERROR(M17/D17,0) -> 1591.333 | O17: =F17+G17+H17-J17 -> 44887.254 | P17: =IFERROR(O17/D17,0) -> 1467.8631 | Q17: 1700 | R17: =Q17*D17 -> 51986 | S17: =R17-M17 -> 3323.0378 | T17: =IFERROR(S17/R17,0) -> 0.063921783 | U17: =R17-(M17-J17-I17) -> 7098.7465 | V17: =IFERROR(U17/R17,0) -> 0.13655112 | X17: {=SUM([1]Hoja6!$H$6:$H$24*(X$5=[1]Hoja6!$E$6:$E$24)*($C17=[1]Hoja6!$J$6:$J$24))} -> 0 | Y17: {=SUM([1]Hoja6!$I$6:$I$24*(X$5=[1]Hoja6!$E$6:$E$24)*($C17=[1]Hoja6!$J$6:$J$24))} -> 0 | Z17: =IFERROR(Y17/X17,0) -> 0 | AA17: {=SUM([1]Hoja6!$H$6:$H$24*(AA$5=[1]Hoja6!$E$6:$E$24)*($C17=[1]Hoja6!$J$6:$J$24))} -> 0 | AB17: {=SUM([1]Hoja6!$I$6:$I$24*(AA$5=[1]Hoja6!$E$6:$E$24)*($C17=[1]Hoja6!$J$6:$J$24))} -> 0 | AC17: =IFERROR(AB17/AA17,0) -> 0 | AD17: {=SUM([1]Hoja6!$H$6:$H$24*(AD$5=[1]Hoja6!$E$6:$E$24)*($C17=[1]Hoja6!$J$6:$J$24))} -> 54 | AE17: {=SUM([1]Hoja6!$I$6:$I$24*(AD$5=[1]Hoja6!$E$6:$E$24)*($C17=[1]Hoja6!$J$6:$J$24))} -> 86400 | AF17: =IFERROR(AE17/AD17,0) -> 1600 | AG17: {=SUM([1]Hoja6!$H$6:$H$24*(AG$5=[1]Hoja6!$E$6:$E$24)*($C17=[1]Hoja6!$J$6:$J$24))} -> 0 | AH17: {=SUM([1]Hoja6!$I$6:$I$24*(AG$5=[1]Hoja6!$E$6:$E$24)*($C17=[1]Hoja6!$J$6:$J$24))} -> 0 | AI17: =IFERROR(AH17/AG17,0) -> 0 | AJ17: {=SUM([1]Hoja6!$H$6:$H$24*(AJ$5=[1]Hoja6!$E$6:$E$24)*($C17=[1]Hoja6!$J$6:$J$24))} -> 54 | AK17: {=SUM([1]Hoja6!$I$6:$I$24*(AJ$5=[1]Hoja6!$E$6:$E$24)*($C17=[1]Hoja6!$J$6:$J$24))} -> 99900 | AL17: =IFERROR(AK17/AJ17,0) -> 1850 | AM17: {=SUM([1]Hoja6!$H$6:$H$24*(AM$5=[1]Hoja6!$E$6:$E$24)*($C17=[1]Hoja6!$J$6:$J$24))} -> 54 | AN17: {=SUM([1]Hoja6!$I$6:$I$24*(AM$5=[1]Hoja6!$E$6:$E$24)*($C17=[1]Hoja6!$J$6:$J$24))} -> 86400 | AO17: =IFERROR(AN17/AM17,0) -> 1600 | AP17: {=SUM([1]Hoja6!$H$6:$H$24*(AP$5=[1]Hoja6!$E$6:$E$24)*($C17=[1]Hoja6!$J$6:$J$24))} -> 0 | AQ17: {=SUM([1]Hoja6!$I$6:$I$24*(AP$5=[1]Hoja6!$E$6:$E$24)*($C17=[1]Hoja6!$J$6:$J$24))} -> 0 | AR17: =IFERROR(AQ17/AP17,0) -> 0 | AS17: {=SUM([1]Hoja6!$H$6:$H$24*(AS$5=[1]Hoja6!$E$6:$E$24)*($C17=[1]Hoja6!$J$6:$J$24))} -> 0 | AT17: {=SUM([1]Hoja6!$I$6:$I$24*(AS$5=[1]Hoja6!$E$6:$E$24)*($C17=[1]Hoja6!$J$6:$J$24))} -> 0 | AU17: =IFERROR(AT17/AS17,0) -> 0 | AV17: {=SUM([1]Hoja6!$H$6:$H$24*(AV$5=[1]Hoja6!$E$6:$E$24)*($C17=[1]Hoja6!$J$6:$J$24))} -> 25.905 | AW17: {=SUM([1]Hoja6!$I$6:$I$24*(AV$5=[1]Hoja6!$E$6:$E$24)*($C17=[1]Hoja6!$J$6:$J$24))} -> 41448 | AX17: =IFERROR(AW17/AV17,0) -> 1600 | AY17: {=SUM([1]Hoja6!$H$6:$H$24*(AY$5=[1]Hoja6!$E$6:$E$24)*($C17=[1]Hoja6!$J$6:$J$24))} -> 0 | AZ17: {=SUM([1]Hoja6!$I$6:$I$24*(AY$5=[1]Hoja6!$E$6:$E$24)*($C17=[1]Hoja6!$J$6:$J$24))} -> 0 | BA17: =IFERROR(AZ17/AY17,0) -> 0 | BB17: =X17+AA17+AD17+AG17+AJ17+AM17+AP17+AY17+AS17+AV17 -> 187.905 | BC17: =Y17+AB17+AE17+AH17+AK17+AN17+AQ17+AZ17+AT17+AW17 -> 314148 | BD17: =IFERROR(BC17/BB17,0) -> 1671.8448 | BE17: =-IFERROR(F17/D17*BB17,0) -> -240512.81 | BF17: =-207.84*BB17 -> -39054.175 | BG17: =$BG$20/$BB$20*$BB17 -> -18908.045 | BH17: =$BH$20/$BB$20*$BB17 -> -37170.013 | BI17: =$BI$20/$BB$20*$BB17 -> -29713.38 | BJ17: =(BC17-BB17*$BG$21)*0.03 -> 8780.8037 | BK17: =BC17+SUM(BE17:BH17,BJ17) -> -12716.24 | BL17: =IFERROR(BK17/BC17,0) -> -0.0404785 | BM17: =BC17+BE17+BF17+BG17+BJ17-BI17 -> 54167.153 | BN17: =IFERROR(BM17/BC17,0) -> 0.17242559 | BP17: =BD17 -> 1671.8448 | BQ17: =IFERROR(BE17/$BB17,0) -> -1279.9703 | BR17: =IFERROR(BF17/$BB17,0) -> -207.84 | BS17: =IFERROR(BG17/$BB17,0) -> -100.62556 | BT17: =IFERROR(BH17/$BB17,0) -> -197.81279 | BU17: =IFERROR(BI17/$BB17,0) -> -158.1298 | BV17: =IFERROR(BJ17/$BB17,0) -> 46.730016 | BW17: =IFERROR(BK17/$BB17,0) -> -67.67377 | BX17: =IFERROR(BM17/$BB17,0) -> 288.26882
C18: FILETE PARA REPROCESO | D18: =TD!F15 -> 462.5 | E18: =IFERROR(F18/D18,0) -> 1834.431 | F18: =TD!G15 -> 848424.34 | G18: =TD!H15 -> 96126 | H18: =TD!I15 -> 16143.625 | I18: =TD!J15 -> 31735.632 | J18: =TD!K15 -> 25369.184 | K18: 0 | L18: 0 | M18: =F18+G18+H18+I18 -> 992429.6 | N18: =IFERROR(M18/D18,0) -> 2145.7937 | O18: =F18+G18+H18-J18 -> 935324.78 | P18: =IFERROR(O18/D18,0) -> 2022.3239 | Q18: 1800 | R18: =Q18*D18 -> 832500 | S18: =R18-M18 -> -159929.6 | T18: =IFERROR(S18/R18,0) -> -0.19210762 | U18: =R18-(M18-J18-I18) -> -102824.78 | V18: =IFERROR(U18/R18,0) -> -0.12351325 | X18: {=SUM([1]Hoja6!$H$6:$H$24*(X$5=[1]Hoja6!$E$6:$E$24)*($C18=[1]Hoja6!$J$6:$J$24))} -> 0 | Y18: {=SUM([1]Hoja6!$I$6:$I$24*(X$5=[1]Hoja6!$E$6:$E$24)*($C18=[1]Hoja6!$J$6:$J$24))} -> 0 | Z18: =IFERROR(Y18/X18,0) -> 0 | AA18: {=SUM([1]Hoja6!$H$6:$H$24*(AA$5=[1]Hoja6!$E$6:$E$24)*($C18=[1]Hoja6!$J$6:$J$24))} -> 0 | AB18: {=SUM([1]Hoja6!$I$6:$I$24*(AA$5=[1]Hoja6!$E$6:$E$24)*($C18=[1]Hoja6!$J$6:$J$24))} -> 0 | AC18: =IFERROR(AB18/AA18,0) -> 0 | AD18: {=SUM([1]Hoja6!$H$6:$H$24*(AD$5=[1]Hoja6!$E$6:$E$24)*($C18=[1]Hoja6!$J$6:$J$24))} -> 0 | AE18: {=SUM([1]Hoja6!$I$6:$I$24*(AD$5=[1]Hoja6!$E$6:$E$24)*($C18=[1]Hoja6!$J$6:$J$24))} -> 0 | AF18: =IFERROR(AE18/AD18,0) -> 0 | AG18: {=SUM([1]Hoja6!$H$6:$H$24*(AG$5=[1]Hoja6!$E$6:$E$24)*($C18=[1]Hoja6!$J$6:$J$24))} -> 0 | AH18: {=SUM([1]Hoja6!$I$6:$I$24*(AG$5=[1]Hoja6!$E$6:$E$24)*($C18=[1]Hoja6!$J$6:$J$24))} -> 0 | AI18: =IFERROR(AH18/AG18,0) -> 0 | AJ18: {=SUM([1]Hoja6!$H$6:$H$24*(AJ$5=[1]Hoja6!$E$6:$E$24)*($C18=[1]Hoja6!$J$6:$J$24))} -> 0 | AK18: {=SUM([1]Hoja6!$I$6:$I$24*(AJ$5=[1]Hoja6!$E$6:$E$24)*($C18=[1]Hoja6!$J$6:$J$24))} -> 0 | AL18: =IFERROR(AK18/AJ18,0) -> 0 | AM18: {=SUM([1]Hoja6!$H$6:$H$24*(AM$5=[1]Hoja6!$E$6:$E$24)*($C18=[1]Hoja6!$J$6:$J$24))} -> 0 | AN18: {=SUM([1]Hoja6!$I$6:$I$24*(AM$5=[1]Hoja6!$E$6:$E$24)*($C18=[1]Hoja6!$J$6:$J$24))} -> 0 | AO18: =IFERROR(AN18/AM18,0) -> 0 | AP18: {=SUM([1]Hoja6!$H$6:$H$24*(AP$5=[1]Hoja6!$E$6:$E$24)*($C18=[1]Hoja6!$J$6:$J$24))} -> 0 | AQ18: {=SUM([1]Hoja6!$I$6:$I$24*(AP$5=[1]Hoja6!$E$6:$E$24)*($C18=[1]Hoja6!$J$6:$J$24))} -> 0 | AR18: =IFERROR(AQ18/AP18,0) -> 0 | AS18: {=SUM([1]Hoja6!$H$6:$H$24*(AS$5=[1]Hoja6!$E$6:$E$24)*($C18=[1]Hoja6!$J$6:$J$24))} -> 0 | AT18: {=SUM([1]Hoja6!$I$6:$I$24*(AS$5=[1]Hoja6!$E$6:$E$24)*($C18=[1]Hoja6!$J$6:$J$24))} -> 0 | AU18: =IFERROR(AT18/AS18,0) -> 0 | AV18: {=SUM([1]Hoja6!$H$6:$H$24*(AV$5=[1]Hoja6!$E$6:$E$24)*($C18=[1]Hoja6!$J$6:$J$24))} -> 0 | AW18: {=SUM([1]Hoja6!$I$6:$I$24*(AV$5=[1]Hoja6!$E$6:$E$24)*($C18=[1]Hoja6!$J$6:$J$24))} -> 0 | AX18: =IFERROR(AW18/AV18,0) -> 0 | AY18: {=SUM([1]Hoja6!$H$6:$H$24*(AY$5=[1]Hoja6!$E$6:$E$24)*($C18=[1]Hoja6!$J$6:$J$24))} -> 0 | AZ18: {=SUM([1]Hoja6!$I$6:$I$24*(AY$5=[1]Hoja6!$E$6:$E$24)*($C18=[1]Hoja6!$J$6:$J$24))} -> 0 | BA18: =IFERROR(AZ18/AY18,0) -> 0 | BB18: =X18+AA18+AD18+AG18+AJ18+AM18+AP18+AY18+AS18+AV18 -> 0 | BC18: =Y18+AB18+AE18+AH18+AK18+AN18+AQ18+AZ18+AT18+AW18 -> 0 | BD18: =IFERROR(BC18/BB18,0) -> 0 | BE18: =-IFERROR(F18/D18*BB18,0) -> 0 | BF18: =-207.84*BB18 -> 0 | BG18: =$BG$20/$BB$20*$BB18 -> 0 | BH18: =$BH$20/$BB$20*$BB18 -> 0 | BI18: =$BI$20/$BB$20*$BB18 -> 0 | BJ18: =(BC18-BB18*$BG$21)*0.03 -> 0 | BK18: =BC18+SUM(BE18:BH18,BJ18) -> 0 | BL18: =IFERROR(BK18/BC18,0) -> 0 | BM18: =BC18+BE18+BF18+BG18+BJ18-BI18 -> 0 | BN18: =IFERROR(BM18/BC18,0) -> 0 | BP18: =BD18 -> 0 | BQ18: =IFERROR(BE18/$BB18,0) -> 0 | BR18: =IFERROR(BF18/$BB18,0) -> 0 | BS18: =IFERROR(BG18/$BB18,0) -> 0 | BT18: =IFERROR(BH18/$BB18,0) -> 0 | BU18: =IFERROR(BI18/$BB18,0) -> 0 | BV18: =IFERROR(BJ18/$BB18,0) -> 0 | BW18: =IFERROR(BK18/$BB18,0) -> 0 | BX18: =IFERROR(BM18/$BB18,0) -> 0
C19: ALAS PARA REPROCESO | D19: =TD!F16 -> 612.58 | E19: =IFERROR(F19/D19,0) -> 1731.9701 | F19: =TD!G16 -> 1060970.3 | G19: =TD!H16 -> 127318.63 | H19: =TD!I16 -> 21382.188 | I19: =TD!J16 -> 42033.759 | J19: =TD!K16 -> 33601.415 | K19: 0 | L19: 0 | M19: =F19+G19+H19+I19 -> 1251704.8 | N19: =IFERROR(M19/D19,0) -> 2043.3328 | O19: =F19+G19+H19-J19 -> 1176069.7 | P19: =IFERROR(O19/D19,0) -> 1919.863 | Q19: 1950 | R19: =Q19*D19 -> 1194531 | S19: =R19-M19 -> -57173.834 | T19: =IFERROR(S19/R19,0) -> -0.047862998 | U19: =R19-(M19-J19-I19) -> 18461.339 | V19: =IFERROR(U19/R19,0) -> 0.015454885 | X19: {=SUM([1]Hoja6!$H$6:$H$24*(X$5=[1]Hoja6!$E$6:$E$24)*($C19=[1]Hoja6!$J$6:$J$24))} -> 0 | Y19: {=SUM([1]Hoja6!$I$6:$I$24*(X$5=[1]Hoja6!$E$6:$E$24)*($C19=[1]Hoja6!$J$6:$J$24))} -> 0 | Z19: =IFERROR(Y19/X19,0) -> 0 | AA19: {=SUM([1]Hoja6!$H$6:$H$24*(AA$5=[1]Hoja6!$E$6:$E$24)*($C19=[1]Hoja6!$J$6:$J$24))} -> 0 | AB19: {=SUM([1]Hoja6!$I$6:$I$24*(AA$5=[1]Hoja6!$E$6:$E$24)*($C19=[1]Hoja6!$J$6:$J$24))} -> 0 | AC19: =IFERROR(AB19/AA19,0) -> 0 | AD19: {=SUM([1]Hoja6!$H$6:$H$24*(AD$5=[1]Hoja6!$E$6:$E$24)*($C19=[1]Hoja6!$J$6:$J$24))} -> 0 | AE19: {=SUM([1]Hoja6!$I$6:$I$24*(AD$5=[1]Hoja6!$E$6:$E$24)*($C19=[1]Hoja6!$J$6:$J$24))} -> 0 | AF19: =IFERROR(AE19/AD19,0) -> 0 | AG19: {=SUM([1]Hoja6!$H$6:$H$24*(AG$5=[1]Hoja6!$E$6:$E$24)*($C19=[1]Hoja6!$J$6:$J$24))} -> 0 | AH19: {=SUM([1]Hoja6!$I$6:$I$24*(AG$5=[1]Hoja6!$E$6:$E$24)*($C19=[1]Hoja6!$J$6:$J$24))} -> 0 | AI19: =IFERROR(AH19/AG19,0) -> 0 | AJ19: {=SUM([1]Hoja6!$H$6:$H$24*(AJ$5=[1]Hoja6!$E$6:$E$24)*($C19=[1]Hoja6!$J$6:$J$24))} -> 0 | AK19: {=SUM([1]Hoja6!$I$6:$I$24*(AJ$5=[1]Hoja6!$E$6:$E$24)*($C19=[1]Hoja6!$J$6:$J$24))} -> 0 | AL19: =IFERROR(AK19/AJ19,0) -> 0 | AM19: {=SUM([1]Hoja6!$H$6:$H$24*(AM$5=[1]Hoja6!$E$6:$E$24)*($C19=[1]Hoja6!$J$6:$J$24))} -> 0 | AN19: {=SUM([1]Hoja6!$I$6:$I$24*(AM$5=[1]Hoja6!$E$6:$E$24)*($C19=[1]Hoja6!$J$6:$J$24))} -> 0 | AO19: =IFERROR(AN19/AM19,0) -> 0 | AP19: {=SUM([1]Hoja6!$H$6:$H$24*(AP$5=[1]Hoja6!$E$6:$E$24)*($C19=[1]Hoja6!$J$6:$J$24))} -> 0 | AQ19: {=SUM([1]Hoja6!$I$6:$I$24*(AP$5=[1]Hoja6!$E$6:$E$24)*($C19=[1]Hoja6!$J$6:$J$24))} -> 0 | AR19: =IFERROR(AQ19/AP19,0) -> 0 | AS19: {=SUM([1]Hoja6!$H$6:$H$24*(AS$5=[1]Hoja6!$E$6:$E$24)*($C19=[1]Hoja6!$J$6:$J$24))} -> 0 | AT19: {=SUM([1]Hoja6!$I$6:$I$24*(AS$5=[1]Hoja6!$E$6:$E$24)*($C19=[1]Hoja6!$J$6:$J$24))} -> 0 | AU19: =IFERROR(AT19/AS19,0) -> 0 | AV19: {=SUM([1]Hoja6!$H$6:$H$24*(AV$5=[1]Hoja6!$E$6:$E$24)*($C19=[1]Hoja6!$J$6:$J$24))} -> 0 | AW19: {=SUM([1]Hoja6!$I$6:$I$24*(AV$5=[1]Hoja6!$E$6:$E$24)*($C19=[1]Hoja6!$J$6:$J$24))} -> 0 | AX19: =IFERROR(AW19/AV19,0) -> 0 | AY19: {=SUM([1]Hoja6!$H$6:$H$24*(AY$5=[1]Hoja6!$E$6:$E$24)*($C19=[1]Hoja6!$J$6:$J$24))} -> 0 | AZ19: {=SUM([1]Hoja6!$I$6:$I$24*(AY$5=[1]Hoja6!$E$6:$E$24)*($C19=[1]Hoja6!$J$6:$J$24))} -> 0 | BA19: =IFERROR(AZ19/AY19,0) -> 0 | BB19: =X19+AA19+AD19+AG19+AJ19+AM19+AP19+AY19+AS19+AV19 -> 0 | BC19: =Y19+AB19+AE19+AH19+AK19+AN19+AQ19+AZ19+AT19+AW19 -> 0 | BD19: =IFERROR(BC19/BB19,0) -> 0 | BE19: =-IFERROR(F19/D19*BB19,0) -> 0 | BF19: =-207.84*BB19 -> 0 | BG19: =$BG$20/$BB$20*$BB19 -> 0 | BH19: =$BH$20/$BB$20*$BB19 -> 0 | BI19: =$BI$20/$BB$20*$BB19 -> 0 | BJ19: =(BC19-BB19*$BG$21)*0.03 -> 0 | BK19: =BC19+SUM(BE19:BH19,BJ19) -> 0 | BL19: =IFERROR(BK19/BC19,0) -> 0 | BM19: =BC19+BE19+BF19+BG19+BJ19-BI19 -> 0 | BN19: =IFERROR(BM19/BC19,0) -> 0 | BP19: =BD19 -> 0 | BQ19: =IFERROR(BE19/$BB19,0) -> 0 | BR19: =IFERROR(BF19/$BB19,0) -> 0 | BS19: =IFERROR(BG19/$BB19,0) -> 0 | BT19: =IFERROR(BH19/$BB19,0) -> 0 | BU19: =IFERROR(BI19/$BB19,0) -> 0 | BV19: =IFERROR(BJ19/$BB19,0) -> 0 | BW19: =IFERROR(BK19/$BB19,0) -> 0 | BX19: =IFERROR(BM19/$BB19,0) -> 0
C20: TOTAL | D20: =SUM(D7:D19) -> 2251.216 | E20: =IFERROR(F20/D20,0) -> 1727.027 | F20: =SUM(F7:F19) -> 3887910.7 | G20: =SUM(G7:G19) -> 467892.73 | H20: =SUM(H7:H19) -> 78579 | I20: =SUM(I7:I19) -> 154473 | J20: =SUM(J7:J19) -> 123484.35 | K20: =SUM(K7:K19) -> 0 | L20: 0 | M20: =SUM(M7:M19) -> 4588855.5 | N20: =IFERROR(M20/D20,0) -> 2038.3897 | O20: =SUM(O7:O19) -> 4310898.1 | P20: =IFERROR(O20/D20,0) -> 1914.9198 | Q20: =R20/D20 -> 2020.6759 | R20: =SUM(R7:R19) -> 4548978 | S20: =SUM(S7:S19) -> -39877.478 | T20: =S20/R20 -> -0.0087662499 | U20: =SUM(U7:U19) -> 238079.87 | V20: =IFERROR(U20/R20,0) -> 0.052337002 | X20: =SUM(X7:X19) -> 27 | Y20: =SUM(Y7:Y19) -> 68850 | Z20: =IFERROR(Y20/X20,0) -> 2550 | AA20: =SUM(AA7:AA19) -> 26 | AB20: =SUM(AB7:AB19) -> 74100 | AC20: =IFERROR(AB20/AA20,0) -> 2850 | AD20: =SUM(AD7:AD19) -> 270 | AE20: =SUM(AE7:AE19) -> 542700 | AF20: =IFERROR(AE20/AD20,0) -> 2010 | AG20: =SUM(AG7:AG19) -> 53 | AH20: =SUM(AH7:AH19) -> 138480 | AI20: =IFERROR(AH20/AG20,0) -> 2612.8302 | AJ20: =SUM(AJ7:AJ19) -> 54 | AK20: =SUM(AK7:AK19) -> 99900 | AL20: =IFERROR(AK20/AJ20,0) -> 1850 | AM20: =SUM(AM7:AM19) -> 148.5 | AN20: =SUM(AN7:AN19) -> 256785 | AO20: =IFERROR(AN20/AM20,0) -> 1729.1919 | AP20: =SUM(AP7:AP19) -> 48 | AQ20: =SUM(AQ7:AQ19) -> 92800 | AR20: =IFERROR(AQ20/AP20,0) -> 1933.3333 | AS20: =SUM(AS7:AS19) -> 79 | AT20: =SUM(AT7:AT19) -> 136936 | AU20: =IFERROR(AT20/AS20,0) -> 1733.3671 | AV20: =SUM(AV7:AV19) -> 52.905 | AW20: =SUM(AW7:AW19) -> 122448 | AX20: =IFERROR(AW20/AV20,0) -> 2314.4882 | AY20: =SUM(AY7:AY19) -> 22.5 | AZ20: =SUM(AZ7:AZ19) -> 29925 | BA20: =IFERROR(AZ20/AY20,0) -> 1330 | BB20: =SUM(BB7:BB19) -> 780.905 | BC20: =SUM(BC7:BC19) -> 1562924 | BD20: =IFERROR(BC20/BB20,0) -> 2001.4265 | BE20: =SUM(BE7:BE19) -> -1146770.6 | BF20: =SUM(BF7:BF19) -> -162303.3 | BG20: =-'Stock Libre'!O54 -> -78579 | BH20: =-'Stock Libre'!P54 -> -154473 | BI20: =-'Stock Libre'!Q54 -> -123484.35 | BJ20: =SUM(BJ7:BJ19) -> 44212.864 | BK20: =SUM(BK7:BK19) -> 65010.932 | BL20: =IFERROR(BK20/BC20,0) -> 0.041595709 | BM20: =SUM(BM7:BM19) -> 342968.28 | BN20: =IFERROR(BM20/BC20,0) -> 0.21944015 | BP20: =BD20 -> 2001.4265 | BQ20: =IFERROR(BE20/$BB20,0) -> -1468.5149 | BR20: =IFERROR(BF20/$BB20,0) -> -207.84 | BS20: =IFERROR(BG20/$BB20,0) -> -100.62556 | BT20: =IFERROR(BH20/$BB20,0) -> -197.81279 | BU20: =IFERROR(BI20/$BB20,0) -> -158.1298 | BV20: =IFERROR(BJ20/$BB20,0) -> 56.617468 | BW20: =IFERROR(BK20/$BB20,0) -> 83.250757 | BX20: =IFERROR(BM20/$BB20,0) -> 439.19335
N21: =M20-R20 -> 39877.478 | BF21: flete x tm | BG21: 114.17761
C22: TM en Almacén de Yantai Jiahong | BQ22: =SUM(BQ7:BT7) -> -2340.7094
C24: Producto | D24: TM en Stock Libre | E24: CU | F24: Costo Ventas | G24: Gasto Ventas | H24: Gasto ADM | I24: Gasto Fin | J24: Depreciación | K24: Utilidad Neta | L24: Margen Neto | M24: Venta Equilibrio a Utd Neta | N24: Precio Equilibrio x TM a Utd Neta | O24: Venta Equilibro a EBITDA | P24: Precio Equilibrio x TM a EBITDA | Q24: Precio Mercado | R24: Venta total | S24: Utilidad | T24: Mg Neto | U24: EBITDA | V24: Mg EBITDA | BB24: Venta Julio | BC24: =BC20-BC14-BC7 -> 1484124 | BQ24: =BQ7/0.5 -> -3668.862
C25: POTA FILETE CONGELADO | D25: 540 | E25: =E7 -> 1834.431 | F25: =E25*D25 -> 990592.74 | G25: =D25*207.84 -> 112233.6 | H25: =H$20/$D$20*$D25 -> 18848.773 | I25: =I$20/$D$20*$D25 -> 37053.495 | J25: =J$20/$D$20*$D25 -> 29620.236 | K25: 0 | L25: 0 | M25: =F25+G25+H25+I25 -> 1158728.6 | N25: =IFERROR(M25/D25,0) -> 2145.7937 | O25: =F25+G25+H25-J25 -> 1092054.9 | P25: =IFERROR(O25/D25,0) -> 2022.3239 | Q25: 1800 | R25: =Q25*D25 -> 972000 | S25: =R25-M25 -> -186728.61 | T25: =IFERROR(S25/R25,0) -> -0.19210762 | U25: =R25-(M25-J25-I25) -> -120054.88 | V25: =IFERROR(U25/R25,0) -> -0.12351325 | BB25: Cobranza | BC25: 2000000
C26: POTA REJOS CONGELADOS | D26: 108 | E26: =E11 -> 1596.5588 | F26: =E26*D26 -> 172428.35 | G26: =D26*207.84 -> 22446.72 | H26: =H$20/$D$20*$D26 -> 3769.7547 | I26: =I$20/$D$20*$D26 -> 7410.6989 | J26: =J$20/$D$20*$D26 -> 5924.0472 | K26: 0 | L26: 0 | M26: =F26+G26+H26+I26 -> 206055.53 | N26: =IFERROR(M26/D26,0) -> 1907.9215 | O26: =F26+G26+H26-J26 -> 192720.78 | P26: =IFERROR(O26/D26,0) -> 1784.4517 | Q26: 2700 | R26: =Q26*D26 -> 291600 | S26: =R26-M26 -> 85544.475 | T26: =IFERROR(S26/R26,0) -> 0.2933624 | U26: =R26-(M26-J26-I26) -> 98879.221 | V26: =IFERROR(U26/R26,0) -> 0.33909198
C27: POTA FILETE DARUMA | D27: 270 | E27: =E14 -> 3085.0611 | F27: =E27*D27 -> 832966.5 | G27: =D27*207.84 -> 56116.8 | H27: =H$20/$D$20*$D27 -> 9424.3866 | I27: =I$20/$D$20*$D27 -> 18526.747 | J27: =J$20/$D$20*$D27 -> 14810.118 | K27: 0 | L27: 0 | M27: =F27+G27+H27+I27 -> 917034.44 | N27: =IFERROR(M27/D27,0) -> 3396.4238 | O27: =F27+G27+H27-J27 -> 883697.57 | P27: =IFERROR(O27/D27,0) -> 3272.954 | Q27: 3500 | R27: =Q27*D27 -> 945000 | S27: =R27-M27 -> 27965.563 | T27: =IFERROR(S27/R27,0) -> 0.029593188 | U27: =R27-(M27-J27-I27) -> 61302.428 | V27: =IFERROR(U27/R27,0) -> 0.064870294 | BB27: Inventario | BC27: =M30 -> 6870674.1
C28: TOTAL | D28: =SUM(D25:D27) -> 918 | E28: =F28/D28 -> 2174.2784 | F28: =SUM(F25:F27) -> 1995987.6 | G28: =SUM(G25:G27) -> 190797.12 | H28: =SUM(H25:H27) -> 32042.915 | I28: =SUM(I25:I27) -> 62990.941 | J28: =SUM(J25:J27) -> 50354.401 | K28: =SUM(K25:K27) -> 0 | L28: 0 | M28: =SUM(M25:M27) -> 2281818.6 | N28: =IFERROR(M28/D28,0) -> 2485.6411 | O28: =SUM(O25:O27) -> 2168473.2 | P28: =IFERROR(O28/D28,0) -> 2362.1713 | Q28: =R28/D28 -> 2405.8824 | R28: =SUM(R25:R27) -> 2208600 | S28: =SUM(S25:S27) -> -73218.574 | T28: =S28/R28 -> -0.033151578 | U28: =SUM(U25:U27) -> 40126.768 | V28: =IFERROR(U28/R28,0) -> 0.018168418 | BC28: =SUM(BC24:BC27) -> 10354798
C30: TOTAL | D30: =D20+D28 -> 3169.216 | E30: =F30/D30 -> 1856.5785 | F30: =F20+F28 -> 5883898.3 | G30: =G20+G28 -> 658689.85 | H30: =H20+H28 -> 110621.91 | I30: =I20+I28 -> 217463.94 | J30: =J20+J28 -> 173838.75 | K30: =K20+K28 -> 0 | L30: =L20+L28 -> 0 | M30: =M20+M28 -> 6870674.1 | N30: =IFERROR(M30/D30,0) -> 2167.9412 | O30: =O20+O28 -> 6479371.4 | P30: =IFERROR(O30/D30,0) -> 2044.4714 | Q30: =R30/D30 -> 2132.2554 | R30: =R20+R28 -> 6757578 | S30: =S20+S28 -> -113096.05 | T30: =S30/R30 -> -0.016736182 | U30: =U20+U28 -> 278206.64 | V30: =IFERROR(U30/R30,0) -> 0.041169579

Sheet TD
E3: Etiquetas de fila | F3: Suma de TM en Stock | G3: Suma de Costo Ventas | H3: Suma de Gasto Ventas | I3: Suma de Gasto ADM | J3: Suma de Gasto Fin | K3: Suma de Depreciación
B4: =C4=E4 -> TRUE | C4: 10005721 | D4: POTA FILETE CONGELADO | E4: 10005721 | F4: 66.6 | G4: 122173.11 | H4: 13842.144 | I4: 2324.682 | J4: 4569.931 | K4: 3653.1624
B5: =C5=E5 -> TRUE | C5: 10005779 | D5: POTA NUCAS CONGELADAS | E5: 10005779 | F5: 439.26 | G5: 651608.37 | H5: 91295.798 | I5: 15332.43 | J5: 30140.959 | K5: 24094.416
B6: =C6=E6 -> TRUE | C6: 10006719 | D6: POTA ALAS CONGELADAS | E6: 10006719 | F6: 15.1 | G6: 26152.749 | H6: 3138.384 | I6: 527.06755 | J6: 1036.1255 | K6: 828.26956
B7: =C7=E7 -> TRUE | C7: 10007050 | D7: POTA RECORTES COCIDOS | E7: 10007050 | F7: 57.26 | G7: 74908.094 | H7: 11900.918 | I7: 1998.6681 | J7: 3929.0428 | K7: 3140.8421
B8: =C8=E8 -> TRUE | C8: 10007162 | D8: POTA REJOS CONGELADOS | E8: 10007162 | F8: 272.36 | G8: 434838.76 | H8: 56607.302 | I8: 9506.7628 | J8: 18688.685 | K8: 14939.569
B9: =C9=E9 -> TRUE | C9: 10007567 | D9: POTA REPRODUCTORES | E9: 10007567 | F9: 132.38 | G9: 203886.87 | H9: 27513.859 | I9: 4620.7419 | J9: 9083.5956 | K9: 7261.346
B10: =C10=E10 -> TRUE | C10: 10007969 | D10: POTA CONOS | E10: 10007969 | F10: 19.34 | G10: 23846.93 | H10: 4019.6256 | I10: 675.06532 | J10: 1327.064 | K10: 1060.8433
B11: =C11=E11 -> TRUE | C11: 10009239 | D11: POTA FILETE DARUMA | E11: 10009239 | F11: 102.9 | G11: 317452.79 | H11: 21386.736 | I11: 3591.7385 | J11: 7060.7493 | K11: 5644.3005
B12: =C12=E12 -> TRUE | C12: 10009334 | D12: POTA ALAS COCIDAS | E12: 10009334 | F12: 19.036 | G12: 50437.835 | H12: 3956.4422 | I12: 664.45416 | J12: 1306.2043 | K12: 1044.1682
B13: =C13=E13 -> TRUE | C13: 10009386 | D13: VENTOSAS | E13: 10009386 | F13: 21.32 | G13: 34069.152 | H13: 4431.1488 | I13: 744.17749 | J13: 1462.9269 | K13: 1169.4508
B14: =C14=E14 -> FALSE | D14: OTROS | E14: 10009207 | F14: 30.58 | G14: 39141.49 | H14: 6355.7472 | I14: 1067.3991 | J14: 2098.3257 | K14: 1677.383
D15: FILETE PARA REPROCESO | E15: 10009650 | F15: 462.5 | G15: 848424.34 | H15: 96126 | I15: 16143.625 | J15: 31735.632 | K15: 25369.184
D16: ALAS PARA REPROCESO | E16: 10009649 | F16: 612.58 | G16: 1060970.3 | H16: 127318.63 | I16: 21382.188 | J16: 42033.759 | K16: 33601.415
E17: Total general | F17: 2251.216 | G17: 3887910.7 | H17: 467892.73 | I17: 78579 | J17: 154473 | K17: 123484.35

Sheet Stock Libre
B1: PRODUCTO | C1: TOTAL STOCK | D1: POR EMBARCAR | E1: STOCK LIBRE | G1: CÓDIGO | H1: CU X TM | I1: % MP | J1: incremento MP | K1: TM en Stock Total | L1: TM en Stock | M1: Costo Ventas | N1: Gasto Ventas | O1: Gasto ADM | P1: Gasto Fin | Q1: Depreciación | R1: Utilidad Neta | S1: Margen Neto | T1: Venta Equilibrio | U1: Precio Equilibrio x TM
B2: POTA ALAS FR C/P C/C (B) S/COD BL10 S20 | C2: 14400 | E2: 14400 | G2: 10006719 | H2: =IFERROR(INDEX([4]Resumen!$K$3:$K$63,MATCH(G2,[4]Resumen!$C$3:$C$63,0)),0)*(1+I2*J2)/1000-51.89/1000-93.38/1000 -> 1.7319701 | I2: 0.71 | J2: =$H$59 -> -0.10965909 | K2: =C2 -> 14400 | L2: =IF(E2<0,0,E2)/1000 -> 14.4 | M2: =IFERROR(H2*L2,0)*1000 -> 24940.37 | N2: =207.84*L2 -> 2992.896 | O2: =$O$54/$L$52*L2 -> 502.63395 | P2: =$P$54/$L$52*L2 -> 988.09319 | Q2: =$Q$54/$L$52*L2 -> 789.87296 | R2: 0 | S2: 0 | T2: =M2+N2+O2+P2 -> 29423.993 | U2: =IFERROR(T2/L2,0) -> 2043.3328
B3: POTA ALAS FR C/P C/C <0.5 BL10 S20 | C3: 2880 | D3: 2180 | E3: 700 | G3: 10006719 | H3: =IFERROR(INDEX([4]Resumen!$K$3:$K$63,MATCH(G3,[4]Resumen!$C$3:$C$63,0)),0)*(1+I3*J3)/1000-51.89/1000-93.38/1000 -> 1.7319701 | I3: 0.71 | J3: =$H$59 -> -0.10965909 | K3: =C3 -> 2880 | L3: =IF(E3<0,0,E3)/1000 -> 0.7 | M3: =IFERROR(H3*L3,0)*1000 -> 1212.3791 | N3: =207.84*L3 -> 145.488 | O3: =$O$54/$L$52*L3 -> 24.433595 | P3: =$P$54/$L$52*L3 -> 48.032308 | Q3: =$Q$54/$L$52*L3 -> 38.396602 | R3: 0 | S3: 0 | T3: =M3+N3+O3+P3 -> 1430.333 | U3: =IFERROR(T3/L3,0) -> 2043.3328
B4: POTA ALAS FR C/P C/C 0.5-1 BL10 S20 | C4: 51820 | D4: 51820 | E4: 0 | G4: 10006719 | H4: =IFERROR(INDEX([4]Resumen!$K$3:$K$63,MATCH(G4,[4]Resumen!$C$3:$C$63,0)),0)*(1+I4*J4)/1000-51.89/1000-93.38/1000 -> 1.7319701 | I4: 0.71 | J4: =$H$59 -> -0.10965909 | K4: =C4 -> 51820 | L4: =IF(E4<0,0,E4)/1000 -> 0 | M4: =IFERROR(H4*L4,0)*1000 -> 0 | N4: =207.84*L4 -> 0 | O4: =$O$54/$L$52*L4 -> 0 | P4: =$P$54/$L$52*L4 -> 0 | Q4: =$Q$54/$L$52*L4 -> 0 | R4: 0 | S4: 0 | T4: =M4+N4+O4+P4 -> 0 | U4: =IFERROR(T4/L4,0) -> 0
B5: POTA ALAS FR C/P C/C 0.3 - 0.5 BL10 S20 | C5: 0 | E5: 0 | G5: 10006719 | H5: =IFERROR(INDEX([4]Resumen!$K$3:$K$63,MATCH(G5,[4]Resumen!$C$3:$C$63,0)),0)*(1+I5*J5)/1000-51.89/1000-93.38/1000 -> 1.7319701 | I5: 0.71 | J5: =$H$59 -> -0.10965909 | K5: =C5 -> 0 | L5: =IF(E5<0,0,E5)/1000 -> 0 | M5: =IFERROR(H5*L5,0)*1000 -> 0 | N5: =207.84*L5 -> 0 | O5: =$O$54/$L$52*L5 -> 0 | P5: =$P$54/$L$52*L5 -> 0 | Q5: =$Q$54/$L$52*L5 -> 0 | R5: 0 | S5: 0 | T5: =M5+N5+O5+P5 -> 0 | U5: =IFERROR(T5/L5,0) -> 0
B6: POTA ALAS FR C/P C/C 1-2 BL10 S20 | C6: 1900 | D6: 1900 | E6: 0 | G6: 10006719 | H6: =IFERROR(INDEX([4]Resumen!$K$3:$K$63,MATCH(G6,[4]Resumen!$C$3:$C$63,0)),0)*(1+I6*J6)/1000-51.89/1000-93.38/1000 -> 1.7319701 | I6: 0.71 | J6: =$H$59 -> -0.10965909 | K6: =C6 -> 1900 | L6: =IF(E6<0,0,E6)/1000 -> 0 | M6: =IFERROR(H6*L6,0)*1000 -> 0 | N6: =207.84*L6 -> 0 | O6: =$O$54/$L$52*L6 -> 0 | P6: =$P$54/$L$52*L6 -> 0 | Q6: =$Q$54/$L$52*L6 -> 0 | R6: 0 | S6: 0 | T6: =M6+N6+O6+P6 -> 0 | U6: =IFERROR(T6/L6,0) -> 0
B7: POTA ALAS FR C/P C/C 1-2 BL10 S20 ENTERA | C7: 26420 | D7: 26420 | E7: 0 | G7: 10006719 | H7: =IFERROR(INDEX([4]Resumen!$K$3:$K$63,MATCH(G7,[4]Resumen!$C$3:$C$63,0)),0)*(1+I7*J7)/1000-51.89/1000-93.38/1000 -> 1.7319701 | I7: 0.71 | J7: =$H$59 -> -0.10965909 | K7: =C7 -> 26420 | L7: =IF(E7<0,0,E7)/1000 -> 0 | M7: =IFERROR(H7*L7,0)*1000 -> 0 | N7: =207.84*L7 -> 0 | O7: =$O$54/$L$52*L7 -> 0 | P7: =$P$54/$L$52*L7 -> 0 | Q7: =$Q$54/$L$52*L7 -> 0 | R7: 0 | S7: 0 | T7: =M7+N7+O7+P7 -> 0 | U7: =IFERROR(T7/L7,0) -> 0
B8: POTA ALAS FR C/P C/C 2up | C8: 120 | D8: 120 | E8: 0 | G8: 10006719 | H8: =IFERROR(INDEX([4]Resumen!$K$3:$K$63,MATCH(G8,[4]Resumen!$C$3:$C$63,0)),0)*(1+I8*J8)/1000-51.89/1000-93.38/1000 -> 1.7319701 | I8: 0.71 | J8: =$H$59 -> -0.10965909 | K8: =C8 -> 120 | L8: =IF(E8<0,0,E8)/1000 -> 0 | M8: =IFERROR(H8*L8,0)*1000 -> 0 | N8: =207.84*L8 -> 0 | O8: =$O$54/$L$52*L8 -> 0 | P8: =$P$54/$L$52*L8 -> 0 | Q8: =$Q$54/$L$52*L8 -> 0 | R8: 0 | S8: 0 | T8: =M8+N8+O8+P8 -> 0 | U8: =IFERROR(T8/L8,0) -> 0
B9: POTA LABIOS FR S/COD BL10 S20 | C9: 30580 | E9: 30580 | G9: 10009207 | H9: =IFERROR(INDEX([4]Resumen!$K$3:$K$63,MATCH(G9,[4]Resumen!$C$3:$C$63,0)),0)*(1+I9*J9)/1000-51.89/1000-93.38/1000 -> 1.2799703 | I9: 0.71 | J9: =$H$59 -> -0.10965909 | K9: =C9 -> 30580 | L9: =IF(E9<0,0,E9)/1000 -> 30.58 | M9: =IFERROR(H9*L9,0)*1000 -> 39141.49 | N9: =207.84*L9 -> 6355.7472 | O9: =$O$54/$L$52*L9 -> 1067.3991 | P9: =$P$54/$L$52*L9 -> 2098.3257 | Q9: =$Q$54/$L$52*L9 -> 1677.383 | R9: 0 | S9: 0 | T9: =M9+N9+O9+P9 -> 48662.962 | U9: =IFERROR(T9/L9,0) -> 1591.333
B10: POTA CONOS | C10: 19340 | E10: 19340 | G10: 10007969 | H10: =IFERROR(INDEX([4]Resumen!$K$3:$K$63,MATCH(G10,[4]Resumen!$C$3:$C$63,0)),0)*(1+I10*J10)/1000-51.89/1000-93.38/1000 -> 1.2330367 | I10: 0.71 | J10: =$H$59 -> -0.10965909 | K10: =C10 -> 19340 | L10: =IF(E10<0,0,E10)/1000 -> 19.34 | M10: =IFERROR(H10*L10,0)*1000 -> 23846.93 | N10: =207.84*L10 -> 4019.6256 | O10: =$O$54/$L$52*L10 -> 675.06532 | P10: =$P$54/$L$52*L10 -> 1327.064 | Q10: =$Q$54/$L$52*L10 -> 1060.8433 | R10: 0 | S10: 0 | T10: =M10+N10+O10+P10 -> 29868.685 | U10: =IFERROR(T10/L10,0) -> 1544.3994
B11: POTA FILETE C/M C/T FR 0.5-1.0 BL10 S20 | C11: 0 | E11: 0 | G11: 10005721 | H11: =IFERROR(INDEX([4]Resumen!$K$3:$K$63,MATCH(G11,[4]Resumen!$C$3:$C$63,0)),0)*(1+I11*J11)/1000-51.89/1000-93.38/1000 -> 1.834431 | I11: 0.67 | J11: =$H$59 -> -0.10965909 | K11: =C11 -> 0 | L11: =IF(E11<0,0,E11)/1000 -> 0 | M11: =IFERROR(H11*L11,0)*1000 -> 0 | N11: =207.84*L11 -> 0 | O11: =$O$54/$L$52*L11 -> 0 | P11: =$P$54/$L$52*L11 -> 0 | Q11: =$Q$54/$L$52*L11 -> 0 | R11: 0 | S11: 0 | T11: =M11+N11+O11+P11 -> 0 | U11: =IFERROR(T11/L11,0) -> 0
B12: POTA FILETE C/M C/T FR 1-2 BL10 S20 | C12: 1760 | E12: 1760 | G12: 10005721 | H12: =IFERROR(INDEX([4]Resumen!$K$3:$K$63,MATCH(G12,[4]Resumen!$C$3:$C$63,0)),0)*(1+I12*J12)/1000-51.89/1000-93.38/1000 -> 1.834431 | I12: 0.67 | J12: =$H$59 -> -0.10965909 | K12: =C12 -> 1760 | L12: =IF(E12<0,0,E12)/1000 -> 1.76 | M12: =IFERROR(H12*L12,0)*1000 -> 3228.5986 | N12: =207.84*L12 -> 365.7984 | O12: =$O$54/$L$52*L12 -> 61.433039 | P12: =$P$54/$L$52*L12 -> 120.76695 | Q12: =$Q$54/$L$52*L12 -> 96.540028 | R12: 0 | S12: 0 | T12: =M12+N12+O12+P12 -> 3776.597 | U12: =IFERROR(T12/L12,0) -> 2145.7937
B13: POTA FILETE C/M C/T FR 1.0 - 3.0 BL10 S20 | C13: 0 | E13: 0 | G13: 10005721 | H13: =IFERROR(INDEX([4]Resumen!$K$3:$K$63,MATCH(G13,[4]Resumen!$C$3:$C$63,0)),0)*(1+I13*J13)/1000-51.89/1000-93.38/1000 -> 1.834431 | I13: 0.67 | J13: =$H$59 -> -0.10965909 | K13: =C13 -> 0 | L13: =IF(E13<0,0,E13)/1000 -> 0 | M13: =IFERROR(H13*L13,0)*1000 -> 0 | N13: =207.84*L13 -> 0 | O13: =$O$54/$L$52*L13 -> 0 | P13: =$P$54/$L$52*L13 -> 0 | Q13: =$Q$54/$L$52*L13 -> 0 | R13: 0 | S13: 0 | T13: =M13+N13+O13+P13 -> 0 | U13: =IFERROR(T13/L13,0) -> 0
B14: POTA FILETE C/M C/T FR 2-4 S20 | C14: 32200 | E14: 32200 | G14: 10005721 | H14: =IFERROR(INDEX([4]Resumen!$K$3:$K$63,MATCH(G14,[4]Resumen!$C$3:$C$63,0)),0)*(1+I14*J14)/1000-51.89/1000-93.38/1000 -> 1.834431 | I14: 0.67 | J14: =$H$59 -> -0.10965909 | K14: =C14 -> 32200 | L14: =IF(E14<0,0,E14)/1000 -> 32.2 | M14: =IFERROR(H14*L14,0)*1000 -> 59068.678 | N14: =207.84*L14 -> 6692.448 | O14: =$O$54/$L$52*L14 -> 1123.9454 | P14: =$P$54/$L$52*L14 -> 2209.4862 | Q14: =$Q$54/$L$52*L14 -> 1766.2437 | R14: 0 | S14: 0 | T14: =M14+N14+O14+P14 -> 69094.558 | U14: =IFERROR(T14/L14,0) -> 2145.7937
B15: POTA FILETE C/M C/T FR <0.5 Kg AA BL10 S20 | C15: 1080 | E15: 1080 | G15: 10005721 | H15: =IFERROR(INDEX([4]Resumen!$K$3:$K$63,MATCH(G15,[4]Resumen!$C$3:$C$63,0)),0)*(1+I15*J15)/1000-51.89/1000-93.38/1000 -> 1.834431 | I15: 0.67 | J15: =$H$59 -> -0.10965909 | K15: =C15 -> 1080 | L15: =IF(E15<0,0,E15)/1000 -> 1.08 | M15: =IFERROR(H15*L15,0)*1000 -> 1981.1855 | N15: =207.84*L15 -> 224.4672 | O15: =$O$54/$L$52*L15 -> 37.697547 | P15: =$P$54/$L$52*L15 -> 74.106989 | Q15: =$Q$54/$L$52*L15 -> 59.240472 | R15: 0 | S15: 0 | T15: =M15+N15+O15+P15 -> 2317.4572 | U15: =IFERROR(T15/L15,0) -> 2145.7937
B16: POTA FILETE C/M C/T FR 2-4 (AA) BL10 S20 | C16: 3080 | E16: 3080 | G16: 10005721 | H16: =IFERROR(INDEX([4]Resumen!$K$3:$K$63,MATCH(G16,[4]Resumen!$C$3:$C$63,0)),0)*(1+I16*J16)/1000-51.89/1000-93.38/1000 -> 1.834431 | I16: 0.67 | J16: =$H$59 -> -0.10965909 | K16: =C16 -> 3080 | L16: =IF(E16<0,0,E16)/1000 -> 3.08 | M16: =IFERROR(H16*L16,0)*1000 -> 5650.0475 | N16: =207.84*L16 -> 640.1472 | O16: =$O$54/$L$52*L16 -> 107.50782 | P16: =$P$54/$L$52*L16 -> 211.34215 | Q16: =$Q$54/$L$52*L16 -> 168.94505 | R16: 0 | S16: 0 | T16: =M16+N16+O16+P16 -> 6609.0447 | U16: =IFERROR(T16/L16,0) -> 2145.7937
B17: POTA FILETE C/M C/T FR 0.5-1.0 AA BL10 S20 | C17: 0 | E17: 0 | G17: 10005721 | H17: =IFERROR(INDEX([4]Resumen!$K$3:$K$63,MATCH(G17,[4]Resumen!$C$3:$C$63,0)),0)*(1+I17*J17)/1000-51.89/1000-93.38/1000 -> 1.834431 | I17: 0.67 | J17: =$H$59 -> -0.10965909 | K17: =C17 -> 0 | L17: =IF(E17<0,0,E17)/1000 -> 0 | M17: =IFERROR(H17*L17,0)*1000 -> 0 | N17: =207.84*L17 -> 0 | O17: =$O$54/$L$52*L17 -> 0 | P17: =$P$54/$L$52*L17 -> 0 | Q17: =$Q$54/$L$52*L17 -> 0 | R17: 0 | S17: 0 | T17: =M17+N17+O17+P17 -> 0 | U17: =IFERROR(T17/L17,0) -> 0
B18: POTA FILETE C/M C/T FR 1.0 - 3.0 AA BL10 S20 | C18: 5300 | E18: 5300 | G18: 10005721 | H18: =IFERROR(INDEX([4]Resumen!$K$3:$K$63,MATCH(G18,[4]Resumen!$C$3:$C$63,0)),0)*(1+I18*J18)/1000-51.89/1000-93.38/1000 -> 1.834431 | I18: 0.67 | J18: =$H$59 -> -0.10965909 | K18: =C18 -> 5300 | L18: =IF(E18<0,0,E18)/1000 -> 5.3 | M18: =IFERROR(H18*L18,0)*1000 -> 9722.4843 | N18: =207.84*L18 -> 1101.552 | O18: =$O$54/$L$52*L18 -> 184.99722 | P18: =$P$54/$L$52*L18 -> 363.67319 | Q18: =$Q$54/$L$52*L18 -> 290.71713 | R18: 0 | S18: 0 | T18: =M18+N18+O18+P18 -> 11372.707 | U18: =IFERROR(T18/L18,0) -> 2145.7937
B19: POTA FILETE C/M C/T FR 1-2 AA BL10 S20 JAPON | C19: 17640 | D19: 380 | E19: 17260 | G19: 10005721 | H19: =IFERROR(INDEX([4]Resumen!$K$3:$K$63,MATCH(G19,[4]Resumen!$C$3:$C$63,0)),0)*(1+I19*J19)/1000-51.89/1000-93.38/1000 -> 1.834431 | I19: 0.67 | J19: =$H$59 -> -0.10965909 | K19: =C19 -> 17640 | L19: =IF(E19<0,0,E19)/1000 -> 17.26 | M19: =IFERROR(H19*L19,0)*1000 -> 31662.279 | N19: =207.84*L19 -> 3587.3184 | O19: =$O$54/$L$52*L19 -> 602.46264 | P19: =$P$54/$L$52*L19 -> 1184.3395 | Q19: =$Q$54/$L$52*L19 -> 946.7505 | R19: 0 | S19: 0 | T19: =M19+N19+O19+P19 -> 37036.4 | U19: =IFERROR(T19/L19,0) -> 2145.7937
B20: POTA FILETE C/M C/T FR 0.5-1.0 AAA BL10 S20 | C20: 0 | E20: 0 | G20: 10005721 | H20: =IFERROR(INDEX([4]Resumen!$K$3:$K$63,MATCH(G20,[4]Resumen!$C$3:$C$63,0)),0)*(1+I20*J20)/1000-51.89/1000-93.38/1000 -> 1.834431 | I20: 0.67 | J20: =$H$59 -> -0.10965909 | K20: =C20 -> 0 | L20: =IF(E20<0,0,E20)/1000 -> 0 | M20: =IFERROR(H20*L20,0)*1000 -> 0 | N20: =207.84*L20 -> 0 | O20: =$O$54/$L$52*L20 -> 0 | P20: =$P$54/$L$52*L20 -> 0 | Q20: =$Q$54/$L$52*L20 -> 0 | R20: 0 | S20: 0 | T20: =M20+N20+O20+P20 -> 0 | U20: =IFERROR(T20/L20,0) -> 0
B21: POTA FILETE C/M C/T FR 1-2 AA BL10 S20 50% ROSADO | C21: 29720 | D21: 27000 | E21: 2720 | G21: 10005721 | H21: =IFERROR(INDEX([4]Resumen!$K$3:$K$63,MATCH(G21,[4]Resumen!$C$3:$C$63,0)),0)*(1+I21*J21)/1000-51.89/1000-93.38/1000 -> 1.834431 | I21: 0.67 | J21: =$H$59 -> -0.10965909 | K21: =C21 -> 29720 | L21: =IF(E21<0,0,E21)/1000 -> 2.72 | M21: =IFERROR(H21*L21,0)*1000 -> 4989.6523 | N21: =207.84*L21 -> 565.3248 | O21: =$O$54/$L$52*L21 -> 94.941969 | P21: =$P$54/$L$52*L21 -> 186.63982 | Q21: =$Q$54/$L$52*L21 -> 149.19823 | R21: 0 | S21: 0 | T21: =M21+N21+O21+P21 -> 5836.5589 | U21: =IFERROR(T21/L21,0) -> 2145.7937
B22: POTA FILETE C/M C/T FR 2-4 AAA BL10 S20 | C22: 0 | D22: 0 | E22: 0 | G22: 10005721 | H22: =IFERROR(INDEX([4]Resumen!$K$3:$K$63,MATCH(G22,[4]Resumen!$C$3:$C$63,0)),0)*(1+I22*J22)/1000-51.89/1000-93.38/1000 -> 1.834431 | I22: 0.67 | J22: =$H$59 -> -0.10965909 | K22: =C22 -> 0 | L22: =IF(E22<0,0,E22)/1000 -> 0 | M22: =IFERROR(H22*L22,0)*1000 -> 0 | N22: =207.84*L22 -> 0 | O22: =$O$54/$L$52*L22 -> 0 | P22: =$P$54/$L$52*L22 -> 0 | Q22: =$Q$54/$L$52*L22 -> 0 | R22: 0 | S22: 0 | T22: =M22+N22+O22+P22 -> 0 | U22: =IFERROR(T22/L22,0) -> 0
B23: POTA FILETE SM ST 1-2 CM/ESP | C23: 3200 | E23: 3200 | G23: 10005721 | H23: =IFERROR(INDEX([4]Resumen!$K$3:$K$63,MATCH(G23,[4]Resumen!$C$3:$C$63,0)),0)*(1+I23*J23)/1000-51.89/1000-93.38/1000 -> 1.834431 | I23: 0.67 | J23: =$H$59 -> -0.10965909 | K23: =C23 -> 3200 | L23: =IF(E23<0,0,E23)/1000 -> 3.2 | M23: =IFERROR(H23*L23,0)*1000 -> 5870.1792 | N23: =207.84*L23 -> 665.088 | O23: =$O$54/$L$52*L23 -> 111.69643 | P23: =$P$54/$L$52*L23 -> 219.57626 | Q23: =$Q$54/$L$52*L23 -> 175.52732 | R23: 0 | S23: 0 | T23: =M23+N23+O23+P23 -> 6866.5399 | U23: =IFERROR(T23/L23,0) -> 2145.7937
B24: POTA NUCAS FR ABIERTAS 0.1 - 0.3 BL10 S2 | C24: 138340 | E24: 138340 | G24: 10005779 | H24: =IFERROR(INDEX([4]Resumen!$K$3:$K$63,MATCH(G24,[4]Resumen!$C$3:$C$63,0)),0)*(1+I24*J24)/1000-51.89/1000-93.38/1000 -> 1.483423 | I24: 0.65 | J24: =$H$59 -> -0.10965909 | K24: =C24 -> 138340 | L24: =IF(E24<0,0,E24)/1000 -> 138.34 | M24: =IFERROR(H24*L24,0)*1000 -> 205216.73 | N24: =207.84*L24 -> 28752.586 | O24: =$O$54/$L$52*L24 -> 4828.7765 | P24: =$P$54/$L$52*L24 -> 9492.5564 | Q24: =$Q$54/$L$52*L24 -> 7588.2656 | R24: 0 | S24: 0 | T24: =M24+N24+O24+P24 -> 248290.65 | U24: =IFERROR(T24/L24,0) -> 1794.7857
B25: POTA NUCAS FR CERRADA 0.1 - 0.3 BL10 S2 | C25: 40100 | E25: 40100 | G25: 10005779 | H25: =IFERROR(INDEX([4]Resumen!$K$3:$K$63,MATCH(G25,[4]Resumen!$C$3:$C$63,0)),0)*(1+I25*J25)/1000-51.89/1000-93.38/1000 -> 1.483423 | I25: 0.65 | J25: =$H$59 -> -0.10965909 | K25: =C25 -> 40100 | L25: =IF(E25<0,0,E25)/1000 -> 40.1 | M25: =IFERROR(H25*L25,0)*1000 -> 59485.261 | N25: =207.84*L25 -> 8334.384 | O25: =$O$54/$L$52*L25 -> 1399.6959 | P25: =$P$54/$L$52*L25 -> 2751.5651 | Q25: =$Q$54/$L$52*L25 -> 2199.5768 | R25: 0 | S25: 0 | T25: =M25+N25+O25+P25 -> 71970.906 | U25: =IFERROR(T25/L25,0) -> 1794.7857
B26: POTA NUCAS FR CERRADA <0.1 BL10 S2 | C26: 1040 | E26: 1040 | G26: 10005779 | H26: =IFERROR(INDEX([4]Resumen!$K$3:$K$63,MATCH(G26,[4]Resumen!$C$3:$C$63,0)),0)*(1+I26*J26)/1000-51.89/1000-93.38/1000 -> 1.483423 | I26: 0.65 | J26: =$H$59 -> -0.10965909 | K26: =C26 -> 1040 | L26: =IF(E26<0,0,E26)/1000 -> 1.04 | M26: =IFERROR(H26*L26,0)*1000 -> 1542.7599 | N26: =207.84*L26 -> 216.1536 | O26: =$O$54/$L$52*L26 -> 36.301341 | P26: =$P$54/$L$52*L26 -> 71.362286 | Q26: =$Q$54/$L$52*L26 -> 57.04638 | R26: 0 | S26: 0 | T26: =M26+N26+O26+P26 -> 1866.5771 | U26: =IFERROR(T26/L26,0) -> 1794.7857
B27: POTA NUCAS FR ABIERTAS 0.5-1 BL10 S20 | C27: 77440 | E27: 77440 | G27: 10005779 | H27: =IFERROR(INDEX([4]Resumen!$K$3:$K$63,MATCH(G27,[4]Resumen!$C$3:$C$63,0)),0)*(1+I27*J27)/1000-51.89/1000-93.38/1000 -> 1.483423 | I27: 0.65 | J27: =$H$59 -> -0.10965909 | K27: =C27 -> 77440 | L27: =IF(E27<0,0,E27)/1000 -> 77.44 | M27: =IFERROR(H27*L27,0)*1000 -> 114876.27 | N27: =207.84*L27 -> 16095.13 | O27: =$O$54/$L$52*L27 -> 2703.0537 | P27: =$P$54/$L$52*L27 -> 5313.7456 | Q27: =$Q$54/$L$52*L27 -> 4247.7612 | R27: 0 | S27: 0 | T27: =M27+N27+O27+P27 -> 138988.2 | U27: =IFERROR(T27/L27,0) -> 1794.7857
B28: POTA NUCAS FR ABIERTAS 0.3-0.5 BL10 S20 | C28: 184360 | D28: 10000 | E28: 174360 | G28: 10005779 | H28: =IFERROR(INDEX([4]Resumen!$K$3:$K$63,MATCH(G28,[4]Resumen!$C$3:$C$63,0)),0)*(1+I28*J28)/1000-51.89/1000-93.38/1000 -> 1.483423 | I28: 0.65 | J28: =$H$59 -> -0.10965909 | K28: =C28 -> 184360 | L28: =IF(E28<0,0,E28)/1000 -> 174.36 | M28: =IFERROR(H28*L28,0)*1000 -> 258649.63 | N28: =207.84*L28 -> 36238.982 | O28: =$O$54/$L$52*L28 -> 6086.0595 | P28: =$P$54/$L$52*L28 -> 11964.162 | Q28: =$Q$54/$L$52*L28 -> 9564.0451 | R28: 0 | S28: 0 | T28: =M28+N28+O28+P28 -> 312938.83 | U28: =IFERROR(T28/L28,0) -> 1794.7857
B29: POTA NUCAS FR ABIERTAS 1-2 BL10 S20 | C29: 7980 | E29: 7980 | G29: 10005779 | H29: =IFERROR(INDEX([4]Resumen!$K$3:$K$63,MATCH(G29,[4]Resumen!$C$3:$C$63,0)),0)*(1+I29*J29)/1000-51.89/1000-93.38/1000 -> 1.483423 | I29: 0.65 | J29: =$H$59 -> -0.10965909 | K29: =C29 -> 7980 | L29: =IF(E29<0,0,E29)/1000 -> 7.98 | M29: =IFERROR(H29*L29,0)*1000 -> 11837.715 | N29: =207.84*L29 -> 1658.5632 | O29: =$O$54/$L$52*L29 -> 278.54298 | P29: =$P$54/$L$52*L29 -> 547.56831 | Q29: =$Q$54/$L$52*L29 -> 437.72126 | R29: 0 | S29: 0 | T29: =M29+N29+O29+P29 -> 14322.39 | U29: =IFERROR(T29/L29,0) -> 1794.7857
B30: POTA REJOS OR FR LIMPIOS S/COD BL10 S20 | C30: 123720 | D30: 27000 | E30: 96720 | G30: 10007567 | H30: =IFERROR(INDEX([4]Resumen!$K$3:$K$63,MATCH(G30,[4]Resumen!$C$3:$C$63,0)),0)*(1+I30*J30)/1000-51.89/1000-93.38/1000 -> 1.5401637 | I30: 0.68 | J30: =$H$59 -> -0.10965909 | K30: =C30 -> 123720 | L30: =IF(E30<0,0,E30)/1000 -> 96.72 | M30: =IFERROR(H30*L30,0)*1000 -> 148964.63 | N30: =207.84*L30 -> 20102.285 | O30: =$O$54/$L$52*L30 -> 3376.0247 | P30: =$P$54/$L$52*L30 -> 6636.6926 | Q30: =$Q$54/$L$52*L30 -> 5305.3134 | R30: 0 | S30: 0 | T30: =M30+N30+O30+P30 -> 179079.63 | U30: =IFERROR(T30/L30,0) -> 1851.5264
B31: POTA REJOS OR FR LIMPIOS <60 cm BL10 S20 | C31: 35660 | E31: 35660 | G31: 10007567 | H31: =IFERROR(INDEX([4]Resumen!$K$3:$K$63,MATCH(G31,[4]Resumen!$C$3:$C$63,0)),0)*(1+I31*J31)/1000-51.89/1000-93.38/1000 -> 1.5401637 | I31: 0.68 | J31: =$H$59 -> -0.10965909 | K31: =C31 -> 35660 | L31: =IF(E31<0,0,E31)/1000 -> 35.66 | M31: =IFERROR(H31*L31,0)*1000 -> 54922.236 | N31: =207.84*L31 -> 7411.5744 | O31: =$O$54/$L$52*L31 -> 1244.7171 | P31: =$P$54/$L$52*L31 -> 2446.903 | Q31: =$Q$54/$L$52*L31 -> 1956.0326 | R31: 0 | S31: 0 | T31: =M31+N31+O31+P31 -> 66025.431 | U31: =IFERROR(T31/L31,0) -> 1851.5264
B32: POTA REJOS FR C/U C/V S/OR <0.1 BL10 | C32: 0 | E32: 0 | G32: 10007162 | H32: =IFERROR(INDEX([4]Resumen!$K$3:$K$63,MATCH(G32,[4]Resumen!$C$3:$C$63,0)),0)*(1+I32*J32)/1000-51.89/1000-93.38/1000 -> 1.5965588 | I32: 0.68 | J32: =$H$59 -> -0.10965909 | K32: =C32 -> 0 | L32: =IF(E32<0,0,E32)/1000 -> 0 | M32: =IFERROR(H32*L32,0)*1000 -> 0 | N32: =207.84*L32 -> 0 | O32: =$O$54/$L$52*L32 -> 0 | P32: =$P$54/$L$52*L32 -> 0 | Q32: =$Q$54/$L$52*L32 -> 0 | R32: 0 | S32: 0 | T32: =M32+N32+O32+P32 -> 0 | U32: =IFERROR(T32/L32,0) -> 0
B33: POTA REJOS FR C/U C/V S/OR 0.1-0.3 BL10 | C33: 0 | E33: 0 | G33: 10007162 | H33: =IFERROR(INDEX([4]Resumen!$K$3:$K$63,MATCH(G33,[4]Resumen!$C$3:$C$63,0)),0)*(1+I33*J33)/1000-51.89/1000-93.38/1000 -> 1.5965588 | I33: 0.68 | J33: =$H$59 -> -0.10965909 | K33: =C33 -> 0 | L33: =IF(E33<0,0,E33)/1000 -> 0 | M33: =IFERROR(H33*L33,0)*1000 -> 0 | N33: =207.84*L33 -> 0 | O33: =$O$54/$L$52*L33 -> 0 | P33: =$P$54/$L$52*L33 -> 0 | Q33: =$Q$54/$L$52*L33 -> 0 | R33: 0 | S33: 0 | T33: =M33+N33+O33+P33 -> 0 | U33: =IFERROR(T33/L33,0) -> 0
B34: POTA REJOS FR C/U C/V S/OR 0.3-0.5BL10 | C34: 12660 | E34: 12660 | G34: 10007162 | H34: =IFERROR(INDEX([4]Resumen!$K$3:$K$63,MATCH(G34,[4]Resumen!$C$3:$C$63,0)),0)*(1+I34*J34)/1000-51.89/1000-93.38/1000 -> 1.5965588 | I34: 0.68 | J34: =$H$59 -> -0.10965909 | K34: =C34 -> 12660 | L34: =IF(E34<0,0,E34)/1000 -> 12.66 | M34: =IFERROR(H34*L34,0)*1000 -> 20212.435 | N34: =207.84*L34 -> 2631.2544 | O34: =$O$54/$L$52*L34 -> 441.89902 | P34: =$P$54/$L$52*L34 -> 868.6986 | Q34: =$Q$54/$L$52*L34 -> 694.42998 | R34: 0 | S34: 0 | T34: =M34+N34+O34+P34 -> 24154.287 | U34: =IFERROR(T34/L34,0) -> 1907.9215
B35: POTA REJOS FR C/U C/V S/OR 0.5-1.0 BL10 | C35: 43520 | E35: 43860 | G35: 10007162 | H35: =IFERROR(INDEX([4]Resumen!$K$3:$K$63,MATCH(G35,[4]Resumen!$C$3:$C$63,0)),0)*(1+I35*J35)/1000-51.89/1000-93.38/1000 -> 1.5965588 | I35: 0.68 | J35: =$H$59 -> -0.10965909 | K35: =C35 -> 43520 | L35: =IF(E35<0,0,E35)/1000 -> 43.86 | M35: =IFERROR(H35*L35,0)*1000 -> 70025.07 | N35: =207.84*L35 -> 9115.8624 | O35: =$O$54/$L$52*L35 -> 1530.9393 | P35: =$P$54/$L$52*L35 -> 3009.5672 | Q35: =$Q$54/$L$52*L35 -> 2405.8214 | R35: 0 | S35: 0 | T35: =M35+N35+O35+P35 -> 83681.438 | U35: =IFERROR(T35/L35,0) -> 1907.9215
B36: POTA REJOS FR C/B S/U S/V S/OR 0.3-0.5 BL10 | C36: 340 | E36: 340 | G36: 10007162 | H36: =IFERROR(INDEX([4]Resumen!$K$3:$K$63,MATCH(G36,[4]Resumen!$C$3:$C$63,0)),0)*(1+I36*J36)/1000-51.89/1000-93.38/1000 -> 1.5965588 | I36: 0.68 | J36: =$H$59 -> -0.10965909 | K36: =C36 -> 340 | L36: =IF(E36<0,0,E36)/1000 -> 0.34 | M36: =IFERROR(H36*L36,0)*1000 -> 542.83 | N36: =207.84*L36 -> 70.6656 | O36: =$O$54/$L$52*L36 -> 11.867746 | P36: =$P$54/$L$52*L36 -> 23.329978 | Q36: =$Q$54/$L$52*L36 -> 18.649778 | R36: 0 | S36: 0 | T36: =M36+N36+O36+P36 -> 648.69332 | U36: =IFERROR(T36/L36,0) -> 1907.9215
B37: POTA REJOS FR C/B S/U S/V S/OR 0.5-1 BL1 0 | C37: 3780 | E37: 3780 | G37: 10007162 | H37: =IFERROR(INDEX([4]Resumen!$K$3:$K$63,MATCH(G37,[4]Resumen!$C$3:$C$63,0)),0)*(1+I37*J37)/1000-51.89/1000-93.38/1000 -> 1.5965588 | I37: 0.68 | J37: =$H$59 -> -0.10965909 | K37: =C37 -> 3780 | L37: =IF(E37<0,0,E37)/1000 -> 3.78 | M37: =IFERROR(H37*L37,0)*1000 -> 6034.9923 | N37: =207.84*L37 -> 785.6352 | O37: =$O$54/$L$52*L37 -> 131.94141 | P37: =$P$54/$L$52*L37 -> 259.37446 | Q37: =$Q$54/$L$52*L37 -> 207.34165 | R37: 0 | S37: 0 | T37: =M37+N37+O37+P37 -> 7211.9434 | U37: =IFERROR(T37/L37,0) -> 1907.9215
B38: POTA REJOS FR C/B C/U C/V S/OR 1.0 up BL 10S20 | C38: 2680 | E38: 2680 | G38: 10007162 | H38: =IFERROR(INDEX([4]Resumen!$K$3:$K$63,MATCH(G38,[4]Resumen!$C$3:$C$63,0)),0)*(1+I38*J38)/1000-51.89/1000-93.38/1000 -> 1.5965588 | I38: 0.68 | J38: =$H$59 -> -0.10965909 | K38: =C38 -> 2680 | L38: =IF(E38<0,0,E38)/1000 -> 2.68 | M38: =IFERROR(H38*L38,0)*1000 -> 4278.7776 | N38: =207.84*L38 -> 557.0112 | O38: =$O$54/$L$52*L38 -> 93.545764 | P38: =$P$54/$L$52*L38 -> 183.89512 | Q38: =$Q$54/$L$52*L38 -> 147.00413 | R38: 0 | S38: 0 | T38: =M38+N38+O38+P38 -> 5113.2297 | U38: =IFERROR(T38/L38,0) -> 1907.9215
B39: POTA REJOS FR C/B S/U S/V S/OR 2-UP BL10 | C39: 36360 | E39: 36360 | G39: 10007162 | H39: =IFERROR(INDEX([4]Resumen!$K$3:$K$63,MATCH(G39,[4]Resumen!$C$3:$C$63,0)),0)*(1+I39*J39)/1000-51.89/1000-93.38/1000 -> 1.5965588 | I39: 0.68 | J39: =$H$59 -> -0.10965909 | K39: =C39 -> 36360 | L39: =IF(E39<0,0,E39)/1000 -> 36.36 | M39: =IFERROR(H39*L39,0)*1000 -> 58050.878 | N39: =207.84*L39 -> 7557.0624 | O39: =$O$54/$L$52*L39 -> 1269.1507 | P39: =$P$54/$L$52*L39 -> 2494.9353 | Q39: =$Q$54/$L$52*L39 -> 1994.4292 | R39: 0 | S39: 0 | T39: =M39+N39+O39+P39 -> 69372.027 | U39: =IFERROR(T39/L39,0) -> 1907.9215
B40: POTA REJOS FR C/B S/U S/V S/OR 1-2 BL10 | C40: 172680 | E40: 172680 | G40: 10007162 | H40: =IFERROR(INDEX([4]Resumen!$K$3:$K$63,MATCH(G40,[4]Resumen!$C$3:$C$63,0)),0)*(1+I40*J40)/1000-51.89/1000-93.38/1000 -> 1.5965588 | I40: 0.68 | J40: =$H$59 -> -0.10965909 | K40: =C40 -> 172680 | L40: =IF(E40<0,0,E40)/1000 -> 172.68 | M40: =IFERROR(H40*L40,0)*1000 -> 275693.78 | N40: =207.84*L40 -> 35889.811 | O40: =$O$54/$L$52*L40 -> 6027.4188 | P40: =$P$54/$L$52*L40 -> 11848.884 | Q40: =$Q$54/$L$52*L40 -> 9471.8932 | R40: 0 | S40: 0 | T40: =M40+N40+O40+P40 -> 329459.89 | U40: =IFERROR(T40/L40,0) -> 1907.9215
B41: VENTOSAS DE REJOS | C41: 21320 | E41: 21320 | G41: 10009386 | H41: =IFERROR(INDEX([4]Resumen!$K$3:$K$63,MATCH(G41,[4]Resumen!$C$3:$C$63,0)),0)*(1+I41*J41)/1000-51.89/1000-93.38/1000 -> 1.5979903 | I41: 0.68 | J41: =$H$59 -> -0.10965909 | K41: =C41 -> 21320 | L41: =IF(E41<0,0,E41)/1000 -> 21.32 | M41: =IFERROR(H41*L41,0)*1000 -> 34069.152 | N41: =207.84*L41 -> 4431.1488 | O41: =$O$54/$L$52*L41 -> 744.17749 | P41: =$P$54/$L$52*L41 -> 1462.9269 | Q41: =$Q$54/$L$52*L41 -> 1169.4508 | R41: 0 | S41: 0 | T41: =M41+N41+O41+P41 -> 40707.405 | U41: =IFERROR(T41/L41,0) -> 1909.353
B42: POTA FILETE PRE COCIDO S/M S/T C/P S/COD | C42: 156240 | D42: 54000 | E42: 102240 | G42: 10009239 | H42: =IFERROR(INDEX([4]Resumen!$K$3:$K$63,MATCH(G42,[4]Resumen!$C$3:$C$63,0)),0)*(1+I42*J42)/1000-51.89/1000-93.38/1000 -> 3.0850611 | I42: 0.56 | J42: =$H$59 -> -0.10965909 | K42: =C42 -> 156240 | L42: =IF(E42<0,0,E42)/1000 -> 102.24 | M42: =IFERROR(H42*L42,0)*1000 -> 315416.65 | N42: =207.84*L42 -> 21249.562 | O42: =$O$54/$L$52*L42 -> 3568.7011 | P42: =$P$54/$L$52*L42 -> 7015.4617 | Q42: =$Q$54/$L$52*L42 -> 5608.098 | R42: 0 | S42: 0 | T42: =M42+N42+O42+P42 -> 347250.37 | U42: =IFERROR(T42/L42,0) -> 3396.4238
B43: POTA FILETE PRE COCIDO S/M S/T C/P 0.6-1.0 | C43: 660 | E43: 660 | G43: 10009239 | H43: =IFERROR(INDEX([4]Resumen!$K$3:$K$63,MATCH(G43,[4]Resumen!$C$3:$C$63,0)),0)*(1+I43*J43)/1000-51.89/1000-93.38/1000 -> 3.0850611 | I43: 0.56 | J43: =$H$59 -> -0.10965909 | K43: =C43 -> 660 | L43: =IF(E43<0,0,E43)/1000 -> 0.66 | M43: =IFERROR(H43*L43,0)*1000 -> 2036.1403 | N43: =207.84*L43 -> 137.1744 | O43: =$O$54/$L$52*L43 -> 23.03739 | P43: =$P$54/$L$52*L43 -> 45.287605 | Q43: =$Q$54/$L$52*L43 -> 36.202511 | R43: 0 | S43: 0 | T43: =M43+N43+O43+P43 -> 2241.6397 | U43: =IFERROR(T43/L43,0) -> 3396.4238
B44: POTA ALAS PRE COC S/COD BL10 S20 | C44: 260 | D44: 260 | E44: 0 | G44: 10009334 | H44: =IFERROR(INDEX([4]Resumen!$K$3:$K$63,MATCH(G44,[4]Resumen!$C$3:$C$63,0)),0)*(1+I44*J44)/1000-51.89/1000-93.38/1000 -> 2.6496026 | I44: 0.68 | J44: =$H$59 -> -0.10965909 | K44: =C44 -> 260 | L44: =IF(E44<0,0,E44)/1000 -> 0 | M44: =IFERROR(H44*L44,0)*1000 -> 0 | N44: =207.84*L44 -> 0 | O44: =$O$54/$L$52*L44 -> 0 | P44: =$P$54/$L$52*L44 -> 0 | Q44: =$Q$54/$L$52*L44 -> 0 | R44: 0 | S44: 0 | T44: =M44+N44+O44+P44 -> 0 | U44: =IFERROR(T44/L44,0) -> 0
B45: POTA ALAS PRE COC 0.3up BL9 S18 | C45: 14642 | E45: 14642 | G45: 10009334 | H45: =IFERROR(INDEX([4]Resumen!$K$3:$K$63,MATCH(G45,[4]Resumen!$C$3:$C$63,0)),0)*(1+I45*J45)/1000-51.89/1000-93.38/1000 -> 2.6496026 | I45: 0.68 | J45: =$H$59 -> -0.10965909 | K45: =C45 -> 14642 | L45: =IF(E45<0,0,E45)/1000 -> 14.642 | M45: =IFERROR(H45*L45,0)*1000 -> 38795.481 | N45: =207.84*L45 -> 3043.1933 | O45: =$O$54/$L$52*L45 -> 511.081 | P45: =$P$54/$L$52*L45 -> 1004.6986 | Q45: =$Q$54/$L$52*L45 -> 803.14721 | R45: 0 | S45: 0 | T45: =M45+N45+O45+P45 -> 43354.454 | U45: =IFERROR(T45/L45,0) -> 2960.9653
B46: POTA ALAS PRE COC B BL9 S18 | C46: 4394 | E46: 4394 | G46: 10009334 | H46: =IFERROR(INDEX([4]Resumen!$K$3:$K$63,MATCH(G46,[4]Resumen!$C$3:$C$63,0)),0)*(1+I46*J46)/1000-51.89/1000-93.38/1000 -> 2.6496026 | I46: 0.68 | J46: =$H$59 -> -0.10965909 | K46: =C46 -> 4394 | L46: =IF(E46<0,0,E46)/1000 -> 4.394 | M46: =IFERROR(H46*L46,0)*1000 -> 11642.354 | N46: =207.84*L46 -> 913.24896 | O46: =$O$54/$L$52*L46 -> 153.37317 | P46: =$P$54/$L$52*L46 -> 301.50566 | Q46: =$Q$54/$L$52*L46 -> 241.02096 | R46: 0 | S46: 0 | T46: =M46+N46+O46+P46 -> 13010.482 | U46: =IFERROR(T46/L46,0) -> 2960.9653
B47: POTA RECORTES PRE COC BL10 S20 | C47: 56560 | D47: 27000 | E47: 29560 | G47: 10007050 | H47: =IFERROR(INDEX([4]Resumen!$K$3:$K$63,MATCH(G47,[4]Resumen!$C$3:$C$63,0)),0)*(1+I47*J47)/1000-51.89/1000-93.38/1000 -> 1.3082098 | I47: 0.68 | J47: =$H$59 -> -0.10965909 | K47: =C47 -> 56560 | L47: =IF(E47<0,0,E47)/1000 -> 29.56 | M47: =IFERROR(H47*L47,0)*1000 -> 38670.682 | N47: =207.84*L47 -> 6143.7504 | O47: =$O$54/$L$52*L47 -> 1031.7958 | P47: =$P$54/$L$52*L47 -> 2028.3357 | Q47: =$Q$54/$L$52*L47 -> 1621.4337 | R47: 0 | S47: 0 | T47: =M47+N47+O47+P47 -> 47874.564 | U47: =IFERROR(T47/L47,0) -> 1619.5725
B48: POTA RECORTES LAM PRE COC (M) BL7.5 S15 | C48: 34355 | D48: 27000 | E48: 7355 | G48: 10007050 | H48: =IFERROR(INDEX([4]Resumen!$K$3:$K$63,MATCH(G48,[4]Resumen!$C$3:$C$63,0)),0)*(1+I48*J48)/1000-51.89/1000-93.38/1000 -> 1.3082098 | I48: 0.68 | J48: =$H$59 -> -0.10965909 | K48: =C48 -> 34355 | L48: =IF(E48<0,0,E48)/1000 -> 7.355 | M48: =IFERROR(H48*L48,0)*1000 -> 9621.8832 | N48: =207.84*L48 -> 1528.6632 | O48: =$O$54/$L$52*L48 -> 256.72727 | P48: =$P$54/$L$52*L48 -> 504.68232 | Q48: =$Q$54/$L$52*L48 -> 403.43858 | R48: 0 | S48: 0 | T48: =M48+N48+O48+P48 -> 11911.956 | U48: =IFERROR(T48/L48,0) -> 1619.5725
B49: POTA RECORTES LAM PRE COC (T) BL7.5 S15 | C49: 20345 | E49: 20345 | G49: 10007050 | H49: =IFERROR(INDEX([4]Resumen!$K$3:$K$63,MATCH(G49,[4]Resumen!$C$3:$C$63,0)),0)*(1+I49*J49)/1000-51.89/1000-93.38/1000 -> 1.3082098 | I49: 0.68 | J49: =$H$59 -> -0.10965909 | K49: =C49 -> 20345 | L49: =IF(E49<0,0,E49)/1000 -> 20.345 | M49: =IFERROR(H49*L49,0)*1000 -> 26615.529 | N49: =207.84*L49 -> 4228.5048 | O49: =$O$54/$L$52*L49 -> 710.14499 | P49: =$P$54/$L$52*L49 -> 1396.0247 | Q49: =$Q$54/$L$52*L49 -> 1115.9698 | R49: 0 | S49: 0 | T49: =M49+N49+O49+P49 -> 32950.203 | U49: =IFERROR(T49/L49,0) -> 1619.5725
B50: FILETE CM CT PARA REPROCESO | C50: 462500 | E50: =+C50 -> 462500 | G50: 10009650 | H50: =H11 -> 1.834431 | I50: =I11 -> 0.67 | J50: =$H$59 -> -0.10965909 | K50: =C50 -> 462500 | L50: =IF(E50<0,0,E50)/1000 -> 462.5 | M50: =IFERROR(H50*L50,0)*1000 -> 848424.34 | N50: =207.84*L50 -> 96126 | O50: =$O$54/$L$52*L50 -> 16143.625 | P50: =$P$54/$L$52*L50 -> 31735.632 | Q50: =$Q$54/$L$52*L50 -> 25369.184 | R50: 0 | S50: 0 | T50: =M50+N50+O50+P50 -> 992429.6 | U50: =IFERROR(T50/L50,0) -> 2145.7937
B51: ALAS FR PARA REPROCESO | C51: 612580 | E51: =+C51 -> 612580 | G51: 10009649 | H51: =H2 -> 1.7319701 | I51: =I2 -> 0.71 | J51: =$H$59 -> -0.10965909 | K51: =C51 -> 612580 | L51: =IF(E51<0,0,E51)/1000 -> 612.58 | M51: =IFERROR(H51*L51,0)*1000 -> 1060970.3 | N51: =207.84*L51 -> 127318.63 | O51: =$O$54/$L$52*L51 -> 21382.188 | P51: =$P$54/$L$52*L51 -> 42033.759 | Q51: =$Q$54/$L$52*L51 -> 33601.415 | R51: 0 | S51: 0 | T51: =M51+N51+O51+P51 -> 1251704.8 | U51: =IFERROR(T51/L51,0) -> 2043.3328
B52: TOTAL LIBRE | C52: =SUM(C2:C51) -> 2505956 | D52: =SUM(D2:D51) -> 255080 | E52: =SUM(E2:E51) -> 2251216 | L52: =SUM(L2:L51) -> 2251.216 | M52: =SUM(M2:M51) -> 3887910.7 | N52: =SUM(N2:N51) -> 467892.73 | O52: =SUM(O2:O51) -> 78579 | P52: =SUM(P2:P51) -> 154473 | Q52: =SUM(Q2:Q51) -> 123484.35 | R52: =SUM(R2:R51) -> 0 | S52: =SUM(S2:S51) -> 0 | T52: =SUM(T2:T51) -> 4588855.5 | U52: =IFERROR(T52/L52,0) -> 2038.3897
N54: totales | O54: 78579 | P54: 154473 | Q54: 123484.35
G55: COSTO ABRIL | H55: 3.52 | I55: tm | J55: Asignación
G56: JUNIO | H56: 3.301 | I56: 3644 | J56: 0.75
G57: JULIO | H57: 2.633 | I57: =3218 -> 3218 | J57: =1-J56 -> 0.25
G58: PROM JUN Y JUL | H58: =H56*J56+H57*J57 -> 3.134 | I58: =I56+I57 -> 6862
G59: TASA | H59: =(H58-H55)/H55 -> -0.10965909
