Workbook

Sheet RESUMEN AL 13-4-2026
C2: INVENTARIO PRODUCTO TERMINADO
F3: RENTABILIDAD DEL INVENTARIO | U3: 46119 | X3: 46122 | AA3: 46125 | AD3: 46129 | AG3: 46132 | AJ3: 46136 | AM3: 46139 | AP3: EMBARCADO | AS3: POR EMBARCAR CON FECHA | AV3: POR EMBARCAR SIN FECHA | AY3: VENTA ABRIL PROYECTADA | BB3: RENTABILIDAD ABRIL | BI3: RENTABILIDAD STOCK FALTANTE
B4: Código | C4: Producto | D4: TM en Stock | E4: CU | F4: Costo Ventas | G4: Gasto Ventas | H4: Gasto ADM | I4: Gasto Fin | J4: Depreciación | K4: Utilidad Neta | L4: Margen Neto | M4: Venta Equilibrio | N4: Precio Equilibrio x TM | P4: Precio Abril x TM | Q4: Venta Abril | R4: Utilidad Neta | S4: Margen Neto | U4: TM | V4: Venta | W4: Precio x TM | X4: TM | Y4: Venta | Z4: Precio x TM | AA4: TM | AB4: Venta | AC4: Precio x TM | AD4: TM | AE4: Venta | AF4: Precio x TM | AG4: TM | AH4: Venta | AI4: Precio x TM | AJ4: TM | AK4: Venta | AL4: Precio x TM | AM4: TM | AN4: Venta | AO4: Precio x TM | AP4: TM | AQ4: Venta | AR4: Precio x TM | AS4: TM | AT4: Venta | AU4: Precio x TM | AV4: TM | AW4: Venta | AX4: Precio x TM | AY4: TM | AZ4: Venta | BA4: Precio x TM | BB4: Costo Ventas | BC4: Gasto Ventas | BD4: Gasto ADM | BE4: Gasto Fin | BF4: Depreciación | BG4: Utilidad Neta | BH4: Margen Neto | BI4: TM | BJ4: Venta | BK4: Utilidad | BL4: Margen Neto
B5: 10005721 | C5: POTA FILETE CONGELADO | D5: 396.6 | E5: =IFERROR(F5/D5,0) -> 1740 | F5: 690084 | G5: 72181.2 | H5: 14485.365 | I5: 32795.362 | J5: 27418.624 | K5: 0 | L5: 0 | M5: =F5+G5+H5+I5 -> 809545.93 | N5: =IFERROR(M5/D5,0) -> 2041.2151 | P5: 2100 | Q5: =D5*P5 -> 832860 | R5: =Q5-M5 -> 23314.073 | S5: =IFERROR(R5/Q5,0) -> 0.027992787 | U5: {=SUM([2]Hoja3!$I$5:$I$19*([2]Hoja3!$F$5:$F$19=$B5)*([2]Hoja3!$G$5:$G$19=$U$3))} -> 293 | V5: {=SUM([2]Hoja3!$J$5:$J$19*([2]Hoja3!$F$5:$F$19=$B5)*([2]Hoja3!$G$5:$G$19=$U$3))} -> 436600 | W5: =IFERROR(V5/U5,0) -> 1490.1024 | X5: {=SUM([2]Hoja3!$I$5:$I$19*([2]Hoja3!$F$5:$F$19=$B5)*([2]Hoja3!$G$5:$G$19=$X$3))} -> 27 | Y5: {=SUM([2]Hoja3!$J$5:$J$19*([2]Hoja3!$F$5:$F$19=$B5)*([2]Hoja3!$G$5:$G$19=$X$3))} -> 43200 | Z5: =IFERROR(Y5/X5,0) -> 1600 | AA5: {=SUM([2]Hoja3!$I$5:$I$19*([2]Hoja3!$F$5:$F$19=$B5)*([2]Hoja3!$G$5:$G$19=$AA$3))} -> 26 | AB5: {=SUM([2]Hoja3!$J$5:$J$19*([2]Hoja3!$F$5:$F$19=$B5)*([2]Hoja3!$G$5:$G$19=$AA$3))} -> 36400 | AC5: =IFERROR(AB5/AA5,0) -> 1400 | AD5: {=SUM([2]Hoja3!$I$5:$I$19*([2]Hoja3!$F$5:$F$19=$B5)*([2]Hoja3!$G$5:$G$19=$AD$3))} -> 0 | AE5: {=SUM([2]Hoja3!$J$5:$J$19*([2]Hoja3!$F$5:$F$19=$B5)*([2]Hoja3!$G$5:$G$19=$AD$3))} -> 0 | AF5: =IFERROR(AE5/AD5,0) -> 0 | AG5: {=SUM([2]Hoja3!$I$5:$I$19*([2]Hoja3!$F$5:$F$19=$B5)*([2]Hoja3!$G$5:$G$19=$AG$3))} -> 131 | AH5: {=SUM([2]Hoja3!$J$5:$J$19*([2]Hoja3!$F$5:$F$19=$B5)*([2]Hoja3!$G$5:$G$19=$AG$3))} -> 257800 | AI5: =IFERROR(AH5/AG5,0) -> 1967.9389 | AJ5: {=SUM([2]Hoja3!$I$5:$I$19*([2]Hoja3!$F$5:$F$19=$B5)*([2]Hoja3!$G$5:$G$19=$AJ$3))} -> 0 | AK5: {=SUM([2]Hoja3!$J$5:$J$19*([2]Hoja3!$F$5:$F$19=$B5)*([2]Hoja3!$G$5:$G$19=$AJ$3))} -> 0 | AL5: =IFERROR(AK5/AJ5,0) -> 0 | AM5: {=SUM([2]Hoja3!$I$5:$I$19*([2]Hoja3!$F$5:$F$19=$B5)*([2]Hoja3!$G$5:$G$19=$AM$3))} -> 26 | AN5: {=SUM([2]Hoja3!$J$5:$J$19*([2]Hoja3!$F$5:$F$19=$B5)*([2]Hoja3!$G$5:$G$19=$AM$3))} -> 36400 | AO5: =IFERROR(AN5/AM5,0) -> 1400 | AP5: =U5+X5+AA5 -> 346 | AQ5: =V5+Y5+AB5 -> 516200 | AR5: =IFERROR(AQ5/AP5,0) -> 1491.9075 | AS5: =AD5+AG5+AJ5+AM5 -> 157 | AT5: =AE5+AH5+AK5+AN5 -> 294200 | AU5: =IFERROR(AT5/AS5,0) -> 1873.8854 | AV5: {=SUM([2]Hoja3!$I$27:$I$34*([2]Hoja3!$F$27:$F$34=$B5))} -> 294 | AW5: {=SUM([2]Hoja3!$J$27:$J$34*([2]Hoja3!$F$27:$F$34=$B5))} -> 622200 | AX5: =IFERROR(AW5/AV5,0) -> 2116.3265 | AY5: =AP5+AS5+AV5 -> 797 | AZ5: =AQ5+AT5+AW5 -> 1432600 | BA5: =IFERROR(AZ5/AY5,0) -> 1797.4906 | BB5: =AY5*E5 -> 1386780 | BC5: =IFERROR(G5/$D5*$AY5,0) -> 145054 | BD5: =$BD$22/$AY$22*AY5 -> 24087.847 | BE5: =$BE$22/$AY$22*AY5 -> 54535.709 | BF5: =$BF$22/$AY$22*AY5 -> 45594.681 | BG5: =AZ5-BB5-BC5-BD5-BE5 -> -177857.56 | BH5: =IFERROR(BG5/AZ5,0) -> -0.12415019 | BI5: =IF((AS5+AV5)>D5,AS5+AV5-D5,0) -> 54.4 | BJ5: =IFERROR(AW5/AV5*BI5,0) -> 115128.16 | BK5: =IFERROR(BJ5-(BB5+BC5+BD5+BE5)/AY5*BI5,0) -> 5204.837 | BL5: =IFERROR(BK5/BJ5,0) -> 0.045209068
B6: 10005779 | C6: POTA NUCAS CONGELADAS | D6: 158.72 | E6: =IFERROR(F6/D6,0) -> 1860 | F6: 295219.2 | G6: 28887.04 | H6: 5797.0681 | I6: 13124.76 | J6: 10972.98 | K6: 0 | L6: 0 | M6: =F6+G6+H6+I6 -> 343028.07 | N6: =IFERROR(M6/D6,0) -> 2161.2151 | P6: 1200 | Q6: =D6*P6 -> 190464 | R6: =Q6-M6 -> -152564.07 | S6: =IFERROR(R6/Q6,0) -> -0.80101262 | U6: {=SUM([2]Hoja3!$I$5:$I$19*([2]Hoja3!$F$5:$F$19=$B6)*([2]Hoja3!$G$5:$G$19=$U$3))} -> 0 | V6: {=SUM([2]Hoja3!$J$5:$J$19*([2]Hoja3!$F$5:$F$19=$B6)*([2]Hoja3!$G$5:$G$19=$U$3))} -> 0 | W6: =IFERROR(V6/U6,0) -> 0 | X6: {=SUM([2]Hoja3!$I$5:$I$19*([2]Hoja3!$F$5:$F$19=$B6)*([2]Hoja3!$G$5:$G$19=$X$3))} -> 0 | Y6: {=SUM([2]Hoja3!$J$5:$J$19*([2]Hoja3!$F$5:$F$19=$B6)*([2]Hoja3!$G$5:$G$19=$X$3))} -> 0 | Z6: =IFERROR(Y6/X6,0) -> 0 | AA6: {=SUM([2]Hoja3!$I$5:$I$19*([2]Hoja3!$F$5:$F$19=$B6)*([2]Hoja3!$G$5:$G$19=$AA$3))} -> 0 | AB6: {=SUM([2]Hoja3!$J$5:$J$19*([2]Hoja3!$F$5:$F$19=$B6)*([2]Hoja3!$G$5:$G$19=$AA$3))} -> 0 | AC6: =IFERROR(AB6/AA6,0) -> 0 | AD6: {=SUM([2]Hoja3!$I$5:$I$19*([2]Hoja3!$F$5:$F$19=$B6)*([2]Hoja3!$G$5:$G$19=$AD$3))} -> 0 | AE6: {=SUM([2]Hoja3!$J$5:$J$19*([2]Hoja3!$F$5:$F$19=$B6)*([2]Hoja3!$G$5:$G$19=$AD$3))} -> 0 | AF6: =IFERROR(AE6/AD6,0) -> 0 | AG6: {=SUM([2]Hoja3!$I$5:$I$19*([2]Hoja3!$F$5:$F$19=$B6)*([2]Hoja3!$G$5:$G$19=$AG$3))} -> 0 | AH6: {=SUM([2]Hoja3!$J$5:$J$19*([2]Hoja3!$F$5:$F$19=$B6)*([2]Hoja3!$G$5:$G$19=$AG$3))} -> 0 | AI6: =IFERROR(AH6/AG6,0) -> 0 | AJ6: {=SUM([2]Hoja3!$I$5:$I$19*([2]Hoja3!$F$5:$F$19=$B6)*([2]Hoja3!$G$5:$G$19=$AJ$3))} -> 0 | AK6: {=SUM([2]Hoja3!$J$5:$J$19*([2]Hoja3!$F$5:$F$19=$B6)*([2]Hoja3!$G$5:$G$19=$AJ$3))} -> 0 | AL6: =IFERROR(AK6/AJ6,0) -> 0 | AM6: {=SUM([2]Hoja3!$I$5:$I$19*([2]Hoja3!$F$5:$F$19=$B6)*([2]Hoja3!$G$5:$G$19=$AM$3))} -> 0 | AN6: {=SUM([2]Hoja3!$J$5:$J$19*([2]Hoja3!$F$5:$F$19=$B6)*([2]Hoja3!$G$5:$G$19=$AM$3))} -> 0 | AO6: =IFERROR(AN6/AM6,0) -> 0 | AP6: =U6+X6+AA6 -> 0 | AQ6: =V6+Y6+AB6 -> 0 | AR6: =IFERROR(AQ6/AP6,0) -> 0 | AS6: =AD6+AG6+AJ6+AM6 -> 0 | AT6: =AE6+AH6+AK6+AN6 -> 0 | AU6: =IFERROR(AT6/AS6,0) -> 0 | AV6: {=SUM([2]Hoja3!$I$27:$I$34*([2]Hoja3!$F$27:$F$34=$B6))} -> 0 | AW6: {=SUM([2]Hoja3!$J$27:$J$34*([2]Hoja3!$F$27:$F$34=$B6))} -> 0 | AX6: =IFERROR(AW6/AV6,0) -> 0 | AY6: =AP6+AS6+AV6 -> 0 | AZ6: =AQ6+AT6+AW6 -> 0 | BA6: =IFERROR(AZ6/AY6,0) -> 0 | BB6: =AY6*E6 -> 0 | BC6: =IFERROR(G6/$D6*$AY6,0) -> 0 | BD6: =$BD$22/$AY$22*AY6 -> 0 | BE6: =$BE$22/$AY$22*AY6 -> 0 | BF6: =$BF$22/$AY$22*AY6 -> 0 | BG6: =AZ6-BB6-BC6-BD6-BE6 -> 0 | BH6: =IFERROR(BG6/AZ6,0) -> 0 | BI6: =IF((AS6+AV6)>D6,AS6+AV6-D6,0) -> 0 | BJ6: =IFERROR(AW6/AV6*BI6,0) -> 0 | BK6: =IFERROR(BJ6-(BB6+BC6+BD6+BE6)/AY6*BI6,0) -> 0 | BL6: =IFERROR(BK6/BJ6,0) -> 0
B7: 10005781 | C7: POTA NUCAS CONGELADAS FR<0.1 BL10 S20 | D7: 5.48 | E7: =IFERROR(F7/D7,0) -> 1860 | F7: 10192.8 | G7: 997.36 | H7: 200.15079 | I7: 453.14822 | J7: 378.85542 | K7: 0 | L7: 0 | M7: =F7+G7+H7+I7 -> 11843.459 | N7: =IFERROR(M7/D7,0) -> 2161.2151 | P7: 1200 | Q7: =D7*P7 -> 6576 | R7: =Q7-M7 -> -5267.459 | S7: =IFERROR(R7/Q7,0) -> -0.80101262 | U7: {=SUM([2]Hoja3!$I$5:$I$19*([2]Hoja3!$F$5:$F$19=$B7)*([2]Hoja3!$G$5:$G$19=$U$3))} -> 0 | V7: {=SUM([2]Hoja3!$J$5:$J$19*([2]Hoja3!$F$5:$F$19=$B7)*([2]Hoja3!$G$5:$G$19=$U$3))} -> 0 | W7: =IFERROR(V7/U7,0) -> 0 | X7: {=SUM([2]Hoja3!$I$5:$I$19*([2]Hoja3!$F$5:$F$19=$B7)*([2]Hoja3!$G$5:$G$19=$X$3))} -> 0 | Y7: {=SUM([2]Hoja3!$J$5:$J$19*([2]Hoja3!$F$5:$F$19=$B7)*([2]Hoja3!$G$5:$G$19=$X$3))} -> 0 | Z7: =IFERROR(Y7/X7,0) -> 0 | AA7: {=SUM([2]Hoja3!$I$5:$I$19*([2]Hoja3!$F$5:$F$19=$B7)*([2]Hoja3!$G$5:$G$19=$AA$3))} -> 0 | AB7: {=SUM([2]Hoja3!$J$5:$J$19*([2]Hoja3!$F$5:$F$19=$B7)*([2]Hoja3!$G$5:$G$19=$AA$3))} -> 0 | AC7: =IFERROR(AB7/AA7,0) -> 0 | AD7: {=SUM([2]Hoja3!$I$5:$I$19*([2]Hoja3!$F$5:$F$19=$B7)*([2]Hoja3!$G$5:$G$19=$AD$3))} -> 0 | AE7: {=SUM([2]Hoja3!$J$5:$J$19*([2]Hoja3!$F$5:$F$19=$B7)*([2]Hoja3!$G$5:$G$19=$AD$3))} -> 0 | AF7: =IFERROR(AE7/AD7,0) -> 0 | AG7: {=SUM([2]Hoja3!$I$5:$I$19*([2]Hoja3!$F$5:$F$19=$B7)*([2]Hoja3!$G$5:$G$19=$AG$3))} -> 0 | AH7: {=SUM([2]Hoja3!$J$5:$J$19*([2]Hoja3!$F$5:$F$19=$B7)*([2]Hoja3!$G$5:$G$19=$AG$3))} -> 0 | AI7: =IFERROR(AH7/AG7,0) -> 0 | AJ7: {=SUM([2]Hoja3!$I$5:$I$19*([2]Hoja3!$F$5:$F$19=$B7)*([2]Hoja3!$G$5:$G$19=$AJ$3))} -> 0 | AK7: {=SUM([2]Hoja3!$J$5:$J$19*([2]Hoja3!$F$5:$F$19=$B7)*([2]Hoja3!$G$5:$G$19=$AJ$3))} -> 0 | AL7: =IFERROR(AK7/AJ7,0) -> 0 | AM7: {=SUM([2]Hoja3!$I$5:$I$19*([2]Hoja3!$F$5:$F$19=$B7)*([2]Hoja3!$G$5:$G$19=$AM$3))} -> 0 | AN7: {=SUM([2]Hoja3!$J$5:$J$19*([2]Hoja3!$F$5:$F$19=$B7)*([2]Hoja3!$G$5:$G$19=$AM$3))} -> 0 | AO7: =IFERROR(AN7/AM7,0) -> 0 | AP7: =U7+X7+AA7 -> 0 | AQ7: =V7+Y7+AB7 -> 0 | AR7: =IFERROR(AQ7/AP7,0) -> 0 | AS7: =AD7+AG7+AJ7+AM7 -> 0 | AT7: =AE7+AH7+AK7+AN7 -> 0 | AU7: =IFERROR(AT7/AS7,0) -> 0 | AV7: {=SUM([2]Hoja3!$I$27:$I$34*([2]Hoja3!$F$27:$F$34=$B7))} -> 0 | AW7: {=SUM([2]Hoja3!$J$27:$J$34*([2]Hoja3!$F$27:$F$34=$B7))} -> 0 | AX7: =IFERROR(AW7/AV7,0) -> 0 | AY7: =AP7+AS7+AV7 -> 0 | AZ7: =AQ7+AT7+AW7 -> 0 | BA7: =IFERROR(AZ7/AY7,0) -> 0 | BB7: =AY7*E7 -> 0 | BC7: =IFERROR(G7/$D7*$AY7,0) -> 0 | BD7: =$BD$22/$AY$22*AY7 -> 0 | BE7: =$BE$22/$AY$22*AY7 -> 0 | BF7: =$BF$22/$AY$22*AY7 -> 0 | BG7: =AZ7-BB7-BC7-BD7-BE7 -> 0 | BH7: =IFERROR(BG7/AZ7,0) -> 0 | BI7: =IF((AS7+AV7)>D7,AS7+AV7-D7,0) -> 0 | BJ7: =IFERROR(AW7/AV7*BI7,0) -> 0 | BK7: =IFERROR(BJ7-(BB7+BC7+BD7+BE7)/AY7*BI7,0) -> 0 | BL7: =IFERROR(BK7/BJ7,0) -> 0
B8: 10006720 | C8: POTA ALAS CONGELADAS | D8: 247.26 | E8: =IFERROR(F8/D8,0) -> 1640 | F8: 405506.4 | G8: 45001.32 | H8: 9030.8912 | I8: 20446.246 | J8: 17094.122 | K8: 0 | L8: 0 | M8: =F8+G8+H8+I8 -> 479984.86 | N8: =IFERROR(M8/D8,0) -> 1941.2151 | P8: 2150 | Q8: =D8*P8 -> 531609 | R8: =Q8-M8 -> 51624.143 | S8: =IFERROR(R8/Q8,0) -> 0.097109234 | U8: {=SUM([2]Hoja3!$I$5:$I$19*([2]Hoja3!$F$5:$F$19=$B8)*([2]Hoja3!$G$5:$G$19=$U$3))} -> 0 | V8: {=SUM([2]Hoja3!$J$5:$J$19*([2]Hoja3!$F$5:$F$19=$B8)*([2]Hoja3!$G$5:$G$19=$U$3))} -> 0 | W8: =IFERROR(V8/U8,0) -> 0 | X8: {=SUM([2]Hoja3!$I$5:$I$19*([2]Hoja3!$F$5:$F$19=$B8)*([2]Hoja3!$G$5:$G$19=$X$3))} -> 27 | Y8: {=SUM([2]Hoja3!$J$5:$J$19*([2]Hoja3!$F$5:$F$19=$B8)*([2]Hoja3!$G$5:$G$19=$X$3))} -> 45900 | Z8: =IFERROR(Y8/X8,0) -> 1700 | AA8: {=SUM([2]Hoja3!$I$5:$I$19*([2]Hoja3!$F$5:$F$19=$B8)*([2]Hoja3!$G$5:$G$19=$AA$3))} -> 0 | AB8: {=SUM([2]Hoja3!$J$5:$J$19*([2]Hoja3!$F$5:$F$19=$B8)*([2]Hoja3!$G$5:$G$19=$AA$3))} -> 0 | AC8: =IFERROR(AB8/AA8,0) -> 0 | AD8: {=SUM([2]Hoja3!$I$5:$I$19*([2]Hoja3!$F$5:$F$19=$B8)*([2]Hoja3!$G$5:$G$19=$AD$3))} -> 0 | AE8: {=SUM([2]Hoja3!$J$5:$J$19*([2]Hoja3!$F$5:$F$19=$B8)*([2]Hoja3!$G$5:$G$19=$AD$3))} -> 0 | AF8: =IFERROR(AE8/AD8,0) -> 0 | AG8: {=SUM([2]Hoja3!$I$5:$I$19*([2]Hoja3!$F$5:$F$19=$B8)*([2]Hoja3!$G$5:$G$19=$AG$3))} -> 192 | AH8: {=SUM([2]Hoja3!$J$5:$J$19*([2]Hoja3!$F$5:$F$19=$B8)*([2]Hoja3!$G$5:$G$19=$AG$3))} -> 313200 | AI8: =IFERROR(AH8/AG8,0) -> 1631.25 | AJ8: {=SUM([2]Hoja3!$I$5:$I$19*([2]Hoja3!$F$5:$F$19=$B8)*([2]Hoja3!$G$5:$G$19=$AJ$3))} -> 0 | AK8: {=SUM([2]Hoja3!$J$5:$J$19*([2]Hoja3!$F$5:$F$19=$B8)*([2]Hoja3!$G$5:$G$19=$AJ$3))} -> 0 | AL8: =IFERROR(AK8/AJ8,0) -> 0 | AM8: {=SUM([2]Hoja3!$I$5:$I$19*([2]Hoja3!$F$5:$F$19=$B8)*([2]Hoja3!$G$5:$G$19=$AM$3))} -> 0 | AN8: {=SUM([2]Hoja3!$J$5:$J$19*([2]Hoja3!$F$5:$F$19=$B8)*([2]Hoja3!$G$5:$G$19=$AM$3))} -> 0 | AO8: =IFERROR(AN8/AM8,0) -> 0 | AP8: =U8+X8+AA8 -> 27 | AQ8: =V8+Y8+AB8 -> 45900 | AR8: =IFERROR(AQ8/AP8,0) -> 1700 | AS8: =AD8+AG8+AJ8+AM8 -> 192 | AT8: =AE8+AH8+AK8+AN8 -> 313200 | AU8: =IFERROR(AT8/AS8,0) -> 1631.25 | AV8: {=SUM([2]Hoja3!$I$27:$I$34*([2]Hoja3!$F$27:$F$34=$B8))} -> 105 | AW8: {=SUM([2]Hoja3!$J$27:$J$34*([2]Hoja3!$F$27:$F$34=$B8))} -> 227700 | AX8: =IFERROR(AW8/AV8,0) -> 2168.5714 | AY8: =AP8+AS8+AV8 -> 324 | AZ8: =AQ8+AT8+AW8 -> 586800 | BA8: =IFERROR(AZ8/AY8,0) -> 1811.1111 | BB8: =AY8*E8 -> 531360 | BC8: =IFERROR(G8/$D8*$AY8,0) -> 58968 | BD8: =$BD$22/$AY$22*AY8 -> 9792.2992 | BE8: =$BE$22/$AY$22*AY8 -> 22170.1 | BF8: =$BF$22/$AY$22*AY8 -> 18535.353 | BG8: =AZ8-BB8-BC8-BD8-BE8 -> -35490.399 | BH8: =IFERROR(BG8/AZ8,0) -> -0.060481253 | BI8: =IF((AS8+AV8)>D8,AS8+AV8-D8,0) -> 49.74 | BJ8: =IFERROR(AW8/AV8*BI8,0) -> 107864.74 | BK8: =IFERROR(BJ8-(BB8+BC8+BD8+BE8)/AY8*BI8,0) -> 12331.643 | BL8: =IFERROR(BK8/BJ8,0) -> 0.11432506
B9: 10006722 | C9: POTA ALAS CONGELADAS FR C/P C/C 2-UP BL10 S20 | D9: 0.12 | E9: =IFERROR(F9/D9,0) -> 1870 | F9: 224.4 | G9: 21.84 | H9: 4.382864 | I9: 9.9229537 | J9: 8.296104 | K9: 0 | L9: 0 | M9: =F9+G9+H9+I9 -> 260.54582 | N9: =IFERROR(M9/D9,0) -> 2171.2151 | P9: 2150 | Q9: =D9*P9 -> 258 | R9: =Q9-M9 -> -2.5458177 | S9: =IFERROR(R9/Q9,0) -> -0.0098675105 | U9: {=SUM([2]Hoja3!$I$5:$I$19*([2]Hoja3!$F$5:$F$19=$B9)*([2]Hoja3!$G$5:$G$19=$U$3))} -> 0 | V9: {=SUM([2]Hoja3!$J$5:$J$19*([2]Hoja3!$F$5:$F$19=$B9)*([2]Hoja3!$G$5:$G$19=$U$3))} -> 0 | W9: =IFERROR(V9/U9,0) -> 0 | X9: {=SUM([2]Hoja3!$I$5:$I$19*([2]Hoja3!$F$5:$F$19=$B9)*([2]Hoja3!$G$5:$G$19=$X$3))} -> 0 | Y9: {=SUM([2]Hoja3!$J$5:$J$19*([2]Hoja3!$F$5:$F$19=$B9)*([2]Hoja3!$G$5:$G$19=$X$3))} -> 0 | Z9: =IFERROR(Y9/X9,0) -> 0 | AA9: {=SUM([2]Hoja3!$I$5:$I$19*([2]Hoja3!$F$5:$F$19=$B9)*([2]Hoja3!$G$5:$G$19=$AA$3))} -> 0 | AB9: {=SUM([2]Hoja3!$J$5:$J$19*([2]Hoja3!$F$5:$F$19=$B9)*([2]Hoja3!$G$5:$G$19=$AA$3))} -> 0 | AC9: =IFERROR(AB9/AA9,0) -> 0 | AD9: {=SUM([2]Hoja3!$I$5:$I$19*([2]Hoja3!$F$5:$F$19=$B9)*([2]Hoja3!$G$5:$G$19=$AD$3))} -> 0 | AE9: {=SUM([2]Hoja3!$J$5:$J$19*([2]Hoja3!$F$5:$F$19=$B9)*([2]Hoja3!$G$5:$G$19=$AD$3))} -> 0 | AF9: =IFERROR(AE9/AD9,0) -> 0 | AG9: {=SUM([2]Hoja3!$I$5:$I$19*([2]Hoja3!$F$5:$F$19=$B9)*([2]Hoja3!$G$5:$G$19=$AG$3))} -> 0 | AH9: {=SUM([2]Hoja3!$J$5:$J$19*([2]Hoja3!$F$5:$F$19=$B9)*([2]Hoja3!$G$5:$G$19=$AG$3))} -> 0 | AI9: =IFERROR(AH9/AG9,0) -> 0 | AJ9: {=SUM([2]Hoja3!$I$5:$I$19*([2]Hoja3!$F$5:$F$19=$B9)*([2]Hoja3!$G$5:$G$19=$AJ$3))} -> 0 | AK9: {=SUM([2]Hoja3!$J$5:$J$19*([2]Hoja3!$F$5:$F$19=$B9)*([2]Hoja3!$G$5:$G$19=$AJ$3))} -> 0 | AL9: =IFERROR(AK9/AJ9,0) -> 0 | AM9: {=SUM([2]Hoja3!$I$5:$I$19*([2]Hoja3!$F$5:$F$19=$B9)*([2]Hoja3!$G$5:$G$19=$AM$3))} -> 0 | AN9: {=SUM([2]Hoja3!$J$5:$J$19*([2]Hoja3!$F$5:$F$19=$B9)*([2]Hoja3!$G$5:$G$19=$AM$3))} -> 0 | AO9: =IFERROR(AN9/AM9,0) -> 0 | AP9: =U9+X9+AA9 -> 0 | AQ9: =V9+Y9+AB9 -> 0 | AR9: =IFERROR(AQ9/AP9,0) -> 0 | AS9: =AD9+AG9+AJ9+AM9 -> 0 | AT9: =AE9+AH9+AK9+AN9 -> 0 | AU9: =IFERROR(AT9/AS9,0) -> 0 | AV9: {=SUM([2]Hoja3!$I$27:$I$34*([2]Hoja3!$F$27:$F$34=$B9))} -> 0 | AW9: {=SUM([2]Hoja3!$J$27:$J$34*([2]Hoja3!$F$27:$F$34=$B9))} -> 0 | AX9: =IFERROR(AW9/AV9,0) -> 0 | AY9: =AP9+AS9+AV9 -> 0 | AZ9: =AQ9+AT9+AW9 -> 0 | BA9: =IFERROR(AZ9/AY9,0) -> 0 | BB9: =AY9*E9 -> 0 | BC9: =IFERROR(G9/$D9*$AY9,0) -> 0 | BD9: =$BD$22/$AY$22*AY9 -> 0 | BE9: =$BE$22/$AY$22*AY9 -> 0 | BF9: =$BF$22/$AY$22*AY9 -> 0 | BG9: =AZ9-BB9-BC9-BD9-BE9 -> 0 | BH9: =IFERROR(BG9/AZ9,0) -> 0 | BI9: =IF((AS9+AV9)>D9,AS9+AV9-D9,0) -> 0 | BJ9: =IFERROR(AW9/AV9*BI9,0) -> 0 | BK9: =IFERROR(BJ9-(BB9+BC9+BD9+BE9)/AY9*BI9,0) -> 0 | BL9: =IFERROR(BK9/BJ9,0) -> 0
B10: 10009178 | C10: POTA ALAS CONGELADAS FR C/P C/C 0.5-1 BL10 S20 | D10: 61.86 | E10: =IFERROR(F10/D10,0) -> 1730 | F10: 107017.8 | G10: 11258.52 | H10: 2259.3664 | I10: 5115.2826 | J10: 4276.6416 | K10: 0 | L10: 0 | M10: =F10+G10+H10+I10 -> 125650.97 | N10: =IFERROR(M10/D10,0) -> 2031.2151 | P10: 2150 | Q10: =D10*P10 -> 132999 | R10: =Q10-M10 -> 7348.031 | S10: =IFERROR(R10/Q10,0) -> 0.055248769 | U10: {=SUM([2]Hoja3!$I$5:$I$19*([2]Hoja3!$F$5:$F$19=$B10)*([2]Hoja3!$G$5:$G$19=$U$3))} -> 0 | V10: {=SUM([2]Hoja3!$J$5:$J$19*([2]Hoja3!$F$5:$F$19=$B10)*([2]Hoja3!$G$5:$G$19=$U$3))} -> 0 | W10: =IFERROR(V10/U10,0) -> 0 | X10: {=SUM([2]Hoja3!$I$5:$I$19*([2]Hoja3!$F$5:$F$19=$B10)*([2]Hoja3!$G$5:$G$19=$X$3))} -> 0 | Y10: {=SUM([2]Hoja3!$J$5:$J$19*([2]Hoja3!$F$5:$F$19=$B10)*([2]Hoja3!$G$5:$G$19=$X$3))} -> 0 | Z10: =IFERROR(Y10/X10,0) -> 0 | AA10: {=SUM([2]Hoja3!$I$5:$I$19*([2]Hoja3!$F$5:$F$19=$B10)*([2]Hoja3!$G$5:$G$19=$AA$3))} -> 0 | AB10: {=SUM([2]Hoja3!$J$5:$J$19*([2]Hoja3!$F$5:$F$19=$B10)*([2]Hoja3!$G$5:$G$19=$AA$3))} -> 0 | AC10: =IFERROR(AB10/AA10,0) -> 0 | AD10: {=SUM([2]Hoja3!$I$5:$I$19*([2]Hoja3!$F$5:$F$19=$B10)*([2]Hoja3!$G$5:$G$19=$AD$3))} -> 0 | AE10: {=SUM([2]Hoja3!$J$5:$J$19*([2]Hoja3!$F$5:$F$19=$B10)*([2]Hoja3!$G$5:$G$19=$AD$3))} -> 0 | AF10: =IFERROR(AE10/AD10,0) -> 0 | AG10: {=SUM([2]Hoja3!$I$5:$I$19*([2]Hoja3!$F$5:$F$19=$B10)*([2]Hoja3!$G$5:$G$19=$AG$3))} -> 0 | AH10: {=SUM([2]Hoja3!$J$5:$J$19*([2]Hoja3!$F$5:$F$19=$B10)*([2]Hoja3!$G$5:$G$19=$AG$3))} -> 0 | AI10: =IFERROR(AH10/AG10,0) -> 0 | AJ10: {=SUM([2]Hoja3!$I$5:$I$19*([2]Hoja3!$F$5:$F$19=$B10)*([2]Hoja3!$G$5:$G$19=$AJ$3))} -> 0 | AK10: {=SUM([2]Hoja3!$J$5:$J$19*([2]Hoja3!$F$5:$F$19=$B10)*([2]Hoja3!$G$5:$G$19=$AJ$3))} -> 0 | AL10: =IFERROR(AK10/AJ10,0) -> 0 | AM10: {=SUM([2]Hoja3!$I$5:$I$19*([2]Hoja3!$F$5:$F$19=$B10)*([2]Hoja3!$G$5:$G$19=$AM$3))} -> 0 | AN10: {=SUM([2]Hoja3!$J$5:$J$19*([2]Hoja3!$F$5:$F$19=$B10)*([2]Hoja3!$G$5:$G$19=$AM$3))} -> 0 | AO10: =IFERROR(AN10/AM10,0) -> 0 | AP10: =U10+X10+AA10 -> 0 | AQ10: =V10+Y10+AB10 -> 0 | AR10: =IFERROR(AQ10/AP10,0) -> 0 | AS10: =AD10+AG10+AJ10+AM10 -> 0 | AT10: =AE10+AH10+AK10+AN10 -> 0 | AU10: =IFERROR(AT10/AS10,0) -> 0 | AV10: {=SUM([2]Hoja3!$I$27:$I$34*([2]Hoja3!$F$27:$F$34=$B10))} -> 0 | AW10: {=SUM([2]Hoja3!$J$27:$J$34*([2]Hoja3!$F$27:$F$34=$B10))} -> 0 | AX10: =IFERROR(AW10/AV10,0) -> 0 | AY10: =AP10+AS10+AV10 -> 0 | AZ10: =AQ10+AT10+AW10 -> 0 | BA10: =IFERROR(AZ10/AY10,0) -> 0 | BB10: =AY10*E10 -> 0 | BC10: =IFERROR(G10/$D10*$AY10,0) -> 0 | BD10: =$BD$22/$AY$22*AY10 -> 0 | BE10: =$BE$22/$AY$22*AY10 -> 0 | BF10: =$BF$22/$AY$22*AY10 -> 0 | BG10: =AZ10-BB10-BC10-BD10-BE10 -> 0 | BH10: =IFERROR(BG10/AZ10,0) -> 0 | BI10: =IF((AS10+AV10)>D10,AS10+AV10-D10,0) -> 0 | BJ10: =IFERROR(AW10/AV10*BI10,0) -> 0 | BK10: =IFERROR(BJ10-(BB10+BC10+BD10+BE10)/AY10*BI10,0) -> 0 | BL10: =IFERROR(BK10/BJ10,0) -> 0
B11: 10007162 | C11: POTA REJOS CONGELADOS | D11: 371.8 | E11: =IFERROR(F11/D11,0) -> 1720 | F11: 639496 | G11: 67667.6 | H11: 13579.574 | I11: 30744.618 | J11: 25704.096 | K11: 0 | L11: 0 | M11: =F11+G11+H11+I11 -> 751487.79 | N11: =IFERROR(M11/D11,0) -> 2021.2151 | P11: 2700 | Q11: =D11*P11 -> 1003860 | R11: =Q11-M11 -> 252372.21 | S11: =IFERROR(R11/Q11,0) -> 0.2514018 | U11: {=SUM([2]Hoja3!$I$5:$I$19*([2]Hoja3!$F$5:$F$19=$B11)*([2]Hoja3!$G$5:$G$19=$U$3))} -> 0 | V11: {=SUM([2]Hoja3!$J$5:$J$19*([2]Hoja3!$F$5:$F$19=$B11)*([2]Hoja3!$G$5:$G$19=$U$3))} -> 0 | W11: =IFERROR(V11/U11,0) -> 0 | X11: {=SUM([2]Hoja3!$I$5:$I$19*([2]Hoja3!$F$5:$F$19=$B11)*([2]Hoja3!$G$5:$G$19=$X$3))} -> 0 | Y11: {=SUM([2]Hoja3!$J$5:$J$19*([2]Hoja3!$F$5:$F$19=$B11)*([2]Hoja3!$G$5:$G$19=$X$3))} -> 0 | Z11: =IFERROR(Y11/X11,0) -> 0 | AA11: {=SUM([2]Hoja3!$I$5:$I$19*([2]Hoja3!$F$5:$F$19=$B11)*([2]Hoja3!$G$5:$G$19=$AA$3))} -> 0 | AB11: {=SUM([2]Hoja3!$J$5:$J$19*([2]Hoja3!$F$5:$F$19=$B11)*([2]Hoja3!$G$5:$G$19=$AA$3))} -> 0 | AC11: =IFERROR(AB11/AA11,0) -> 0 | AD11: {=SUM([2]Hoja3!$I$5:$I$19*([2]Hoja3!$F$5:$F$19=$B11)*([2]Hoja3!$G$5:$G$19=$AD$3))} -> 0 | AE11: {=SUM([2]Hoja3!$J$5:$J$19*([2]Hoja3!$F$5:$F$19=$B11)*([2]Hoja3!$G$5:$G$19=$AD$3))} -> 0 | AF11: =IFERROR(AE11/AD11,0) -> 0 | AG11: {=SUM([2]Hoja3!$I$5:$I$19*([2]Hoja3!$F$5:$F$19=$B11)*([2]Hoja3!$G$5:$G$19=$AG$3))} -> 0 | AH11: {=SUM([2]Hoja3!$J$5:$J$19*([2]Hoja3!$F$5:$F$19=$B11)*([2]Hoja3!$G$5:$G$19=$AG$3))} -> 0 | AI11: =IFERROR(AH11/AG11,0) -> 0 | AJ11: {=SUM([2]Hoja3!$I$5:$I$19*([2]Hoja3!$F$5:$F$19=$B11)*([2]Hoja3!$G$5:$G$19=$AJ$3))} -> 0 | AK11: {=SUM([2]Hoja3!$J$5:$J$19*([2]Hoja3!$F$5:$F$19=$B11)*([2]Hoja3!$G$5:$G$19=$AJ$3))} -> 0 | AL11: =IFERROR(AK11/AJ11,0) -> 0 | AM11: {=SUM([2]Hoja3!$I$5:$I$19*([2]Hoja3!$F$5:$F$19=$B11)*([2]Hoja3!$G$5:$G$19=$AM$3))} -> 0 | AN11: {=SUM([2]Hoja3!$J$5:$J$19*([2]Hoja3!$F$5:$F$19=$B11)*([2]Hoja3!$G$5:$G$19=$AM$3))} -> 0 | AO11: =IFERROR(AN11/AM11,0) -> 0 | AP11: =U11+X11+AA11 -> 0 | AQ11: =V11+Y11+AB11 -> 0 | AR11: =IFERROR(AQ11/AP11,0) -> 0 | AS11: =AD11+AG11+AJ11+AM11 -> 0 | AT11: =AE11+AH11+AK11+AN11 -> 0 | AU11: =IFERROR(AT11/AS11,0) -> 0 | AV11: {=SUM([2]Hoja3!$I$27:$I$34*([2]Hoja3!$F$27:$F$34=$B11))} -> 135 | AW11: {=SUM([2]Hoja3!$J$27:$J$34*([2]Hoja3!$F$27:$F$34=$B11))} -> 380700 | AX11: =IFERROR(AW11/AV11,0) -> 2820 | AY11: =AP11+AS11+AV11 -> 135 | AZ11: =AQ11+AT11+AW11 -> 380700 | BA11: =IFERROR(AZ11/AY11,0) -> 2820 | BB11: =AY11*E11 -> 232200 | BC11: =IFERROR(G11/$D11*$AY11,0) -> 24570 | BD11: =$BD$22/$AY$22*AY11 -> 4080.1247 | BE11: =$BE$22/$AY$22*AY11 -> 9237.5416 | BF11: =$BF$22/$AY$22*AY11 -> 7723.0639 | BG11: =AZ11-BB11-BC11-BD11-BE11 -> 110612.33 | BH11: =IFERROR(BG11/AZ11,0) -> 0.29054987 | BI11: =IF((AS11+AV11)>D11,AS11+AV11-D11,0) -> 0 | BJ11: =IFERROR(AW11/AV11*BI11,0) -> 0 | BK11: =IFERROR(BJ11-(BB11+BC11+BD11+BE11)/AY11*BI11,0) -> 0 | BL11: =IFERROR(BK11/BJ11,0) -> 0
B12: 10007567 | C12: POTA REJOS CONGELADOS FR LIMPIOS S/COD BL10 S20 | D12: 88.76 | E12: =IFERROR(F12/D12,0) -> 1700 | F12: 150892 | G12: 16154.32 | H12: 3241.8584 | I12: 7339.6781 | J12: 6136.3516 | K12: 0 | L12: 0 | M12: =F12+G12+H12+I12 -> 177627.86 | N12: =IFERROR(M12/D12,0) -> 2001.2151 | P12: 2700 | Q12: =D12*P12 -> 239652 | R12: =Q12-M12 -> 62024.144 | S12: =IFERROR(R12/Q12,0) -> 0.2588092 | U12: {=SUM([2]Hoja3!$I$5:$I$19*([2]Hoja3!$F$5:$F$19=$B12)*([2]Hoja3!$G$5:$G$19=$U$3))} -> 0 | V12: {=SUM([2]Hoja3!$J$5:$J$19*([2]Hoja3!$F$5:$F$19=$B12)*([2]Hoja3!$G$5:$G$19=$U$3))} -> 0 | W12: =IFERROR(V12/U12,0) -> 0 | X12: {=SUM([2]Hoja3!$I$5:$I$19*([2]Hoja3!$F$5:$F$19=$B12)*([2]Hoja3!$G$5:$G$19=$X$3))} -> 0 | Y12: {=SUM([2]Hoja3!$J$5:$J$19*([2]Hoja3!$F$5:$F$19=$B12)*([2]Hoja3!$G$5:$G$19=$X$3))} -> 0 | Z12: =IFERROR(Y12/X12,0) -> 0 | AA12: {=SUM([2]Hoja3!$I$5:$I$19*([2]Hoja3!$F$5:$F$19=$B12)*([2]Hoja3!$G$5:$G$19=$AA$3))} -> 26 | AB12: {=SUM([2]Hoja3!$J$5:$J$19*([2]Hoja3!$F$5:$F$19=$B12)*([2]Hoja3!$G$5:$G$19=$AA$3))} -> 80600 | AC12: =IFERROR(AB12/AA12,0) -> 3100 | AD12: {=SUM([2]Hoja3!$I$5:$I$19*([2]Hoja3!$F$5:$F$19=$B12)*([2]Hoja3!$G$5:$G$19=$AD$3))} -> 0 | AE12: {=SUM([2]Hoja3!$J$5:$J$19*([2]Hoja3!$F$5:$F$19=$B12)*([2]Hoja3!$G$5:$G$19=$AD$3))} -> 0 | AF12: =IFERROR(AE12/AD12,0) -> 0 | AG12: {=SUM([2]Hoja3!$I$5:$I$19*([2]Hoja3!$F$5:$F$19=$B12)*([2]Hoja3!$G$5:$G$19=$AG$3))} -> 0 | AH12: {=SUM([2]Hoja3!$J$5:$J$19*([2]Hoja3!$F$5:$F$19=$B12)*([2]Hoja3!$G$5:$G$19=$AG$3))} -> 0 | AI12: =IFERROR(AH12/AG12,0) -> 0 | AJ12: {=SUM([2]Hoja3!$I$5:$I$19*([2]Hoja3!$F$5:$F$19=$B12)*([2]Hoja3!$G$5:$G$19=$AJ$3))} -> 0 | AK12: {=SUM([2]Hoja3!$J$5:$J$19*([2]Hoja3!$F$5:$F$19=$B12)*([2]Hoja3!$G$5:$G$19=$AJ$3))} -> 0 | AL12: =IFERROR(AK12/AJ12,0) -> 0 | AM12: {=SUM([2]Hoja3!$I$5:$I$19*([2]Hoja3!$F$5:$F$19=$B12)*([2]Hoja3!$G$5:$G$19=$AM$3))} -> 0 | AN12: {=SUM([2]Hoja3!$J$5:$J$19*([2]Hoja3!$F$5:$F$19=$B12)*([2]Hoja3!$G$5:$G$19=$AM$3))} -> 0 | AO12: =IFERROR(AN12/AM12,0) -> 0 | AP12: =U12+X12+AA12 -> 26 | AQ12: =V12+Y12+AB12 -> 80600 | AR12: =IFERROR(AQ12/AP12,0) -> 3100 | AS12: =AD12+AG12+AJ12+AM12 -> 0 | AT12: =AE12+AH12+AK12+AN12 -> 0 | AU12: =IFERROR(AT12/AS12,0) -> 0 | AV12: {=SUM([2]Hoja3!$I$27:$I$34*([2]Hoja3!$F$27:$F$34=$B12))} -> 106 | AW12: {=SUM([2]Hoja3!$J$27:$J$34*([2]Hoja3!$F$27:$F$34=$B12))} -> 314980 | AX12: =IFERROR(AW12/AV12,0) -> 2971.5094 | AY12: =AP12+AS12+AV12 -> 132 | AZ12: =AQ12+AT12+AW12 -> 395580 | BA12: =IFERROR(AZ12/AY12,0) -> 2996.8182 | BB12: =AY12*E12 -> 224400 | BC12: =IFERROR(G12/$D12*$AY12,0) -> 24024 | BD12: =$BD$22/$AY$22*AY12 -> 3989.4552 | BE12: =$BE$22/$AY$22*AY12 -> 9032.2629 | BF12: =$BF$22/$AY$22*AY12 -> 7551.4403 | BG12: =AZ12-BB12-BC12-BD12-BE12 -> 134134.28 | BH12: =IFERROR(BG12/AZ12,0) -> 0.33908257 | BI12: =IF((AS12+AV12)>D12,AS12+AV12-D12,0) -> 17.24 | BJ12: =IFERROR(AW12/AV12*BI12,0) -> 51228.823 | BK12: =IFERROR(BJ12-(BB12+BC12+BD12+BE12)/AY12*BI12,0) -> 17082.427 | BL12: =IFERROR(BK12/BJ12,0) -> 0.33345344
B13: 10009639 | C13: POTA REJOS CONGELADOS FR C/B S/U S/V S/OR 0.3 - 0.5 | D13: 4.7 | E13: =IFERROR(F13/D13,0) -> 1750 | F13: 8225 | G13: 855.4 | H13: 171.66217 | I13: 388.64902 | J13: 324.93074 | K13: 0 | L13: 0 | M13: =F13+G13+H13+I13 -> 9640.7112 | N13: =IFERROR(M13/D13,0) -> 2051.2151 | P13: 2700 | Q13: =D13*P13 -> 12690 | R13: =Q13-M13 -> 3049.2888 | S13: =IFERROR(R13/Q13,0) -> 0.24029069 | U13: {=SUM([2]Hoja3!$I$5:$I$19*([2]Hoja3!$F$5:$F$19=$B13)*([2]Hoja3!$G$5:$G$19=$U$3))} -> 0 | V13: {=SUM([2]Hoja3!$J$5:$J$19*([2]Hoja3!$F$5:$F$19=$B13)*([2]Hoja3!$G$5:$G$19=$U$3))} -> 0 | W13: =IFERROR(V13/U13,0) -> 0 | X13: {=SUM([2]Hoja3!$I$5:$I$19*([2]Hoja3!$F$5:$F$19=$B13)*([2]Hoja3!$G$5:$G$19=$X$3))} -> 0 | Y13: {=SUM([2]Hoja3!$J$5:$J$19*([2]Hoja3!$F$5:$F$19=$B13)*([2]Hoja3!$G$5:$G$19=$X$3))} -> 0 | Z13: =IFERROR(Y13/X13,0) -> 0 | AA13: {=SUM([2]Hoja3!$I$5:$I$19*([2]Hoja3!$F$5:$F$19=$B13)*([2]Hoja3!$G$5:$G$19=$AA$3))} -> 0 | AB13: {=SUM([2]Hoja3!$J$5:$J$19*([2]Hoja3!$F$5:$F$19=$B13)*([2]Hoja3!$G$5:$G$19=$AA$3))} -> 0 | AC13: =IFERROR(AB13/AA13,0) -> 0 | AD13: {=SUM([2]Hoja3!$I$5:$I$19*([2]Hoja3!$F$5:$F$19=$B13)*([2]Hoja3!$G$5:$G$19=$AD$3))} -> 0 | AE13: {=SUM([2]Hoja3!$J$5:$J$19*([2]Hoja3!$F$5:$F$19=$B13)*([2]Hoja3!$G$5:$G$19=$AD$3))} -> 0 | AF13: =IFERROR(AE13/AD13,0) -> 0 | AG13: {=SUM([2]Hoja3!$I$5:$I$19*([2]Hoja3!$F$5:$F$19=$B13)*([2]Hoja3!$G$5:$G$19=$AG$3))} -> 0 | AH13: {=SUM([2]Hoja3!$J$5:$J$19*([2]Hoja3!$F$5:$F$19=$B13)*([2]Hoja3!$G$5:$G$19=$AG$3))} -> 0 | AI13: =IFERROR(AH13/AG13,0) -> 0 | AJ13: {=SUM([2]Hoja3!$I$5:$I$19*([2]Hoja3!$F$5:$F$19=$B13)*([2]Hoja3!$G$5:$G$19=$AJ$3))} -> 0 | AK13: {=SUM([2]Hoja3!$J$5:$J$19*([2]Hoja3!$F$5:$F$19=$B13)*([2]Hoja3!$G$5:$G$19=$AJ$3))} -> 0 | AL13: =IFERROR(AK13/AJ13,0) -> 0 | AM13: {=SUM([2]Hoja3!$I$5:$I$19*([2]Hoja3!$F$5:$F$19=$B13)*([2]Hoja3!$G$5:$G$19=$AM$3))} -> 0 | AN13: {=SUM([2]Hoja3!$J$5:$J$19*([2]Hoja3!$F$5:$F$19=$B13)*([2]Hoja3!$G$5:$G$19=$AM$3))} -> 0 | AO13: =IFERROR(AN13/AM13,0) -> 0 | AP13: =U13+X13+AA13 -> 0 | AQ13: =V13+Y13+AB13 -> 0 | AR13: =IFERROR(AQ13/AP13,0) -> 0 | AS13: =AD13+AG13+AJ13+AM13 -> 0 | AT13: =AE13+AH13+AK13+AN13 -> 0 | AU13: =IFERROR(AT13/AS13,0) -> 0 | AV13: {=SUM([2]Hoja3!$I$27:$I$34*([2]Hoja3!$F$27:$F$34=$B13))} -> 0 | AW13: {=SUM([2]Hoja3!$J$27:$J$34*([2]Hoja3!$F$27:$F$34=$B13))} -> 0 | AX13: =IFERROR(AW13/AV13,0) -> 0 | AY13: =AP13+AS13+AV13 -> 0 | AZ13: =AQ13+AT13+AW13 -> 0 | BA13: =IFERROR(AZ13/AY13,0) -> 0 | BB13: =AY13*E13 -> 0 | BC13: =IFERROR(G13/$D13*$AY13,0) -> 0 | BD13: =$BD$22/$AY$22*AY13 -> 0 | BE13: =$BE$22/$AY$22*AY13 -> 0 | BF13: =$BF$22/$AY$22*AY13 -> 0 | BG13: =AZ13-BB13-BC13-BD13-BE13 -> 0 | BH13: =IFERROR(BG13/AZ13,0) -> 0 | BI13: =IF((AS13+AV13)>D13,AS13+AV13-D13,0) -> 0 | BJ13: =IFERROR(AW13/AV13*BI13,0) -> 0 | BK13: =IFERROR(BJ13-(BB13+BC13+BD13+BE13)/AY13*BI13,0) -> 0 | BL13: =IFERROR(BK13/BJ13,0) -> 0
B14: 10007050 | C14: POTA ALAS COCIDAS | D14: 70.744 | E14: =IFERROR(F14/D14,0) -> 1310 | F14: 92674.64 | G14: 12875.408 | H14: 2583.8444 | I14: 5849.912 | J14: 4890.8298 | K14: 0 | L14: 0 | M14: =F14+G14+H14+I14 -> 113983.8 | N14: =IFERROR(M14/D14,0) -> 1611.2151 | P14: 3950 | Q14: =D14*P14 -> 279438.8 | R14: =Q14-M14 -> 165455 | S14: =IFERROR(R14/Q14,0) -> 0.59209743 | U14: {=SUM([2]Hoja3!$I$5:$I$19*([2]Hoja3!$F$5:$F$19=$B14)*([2]Hoja3!$G$5:$G$19=$U$3))} -> 0 | V14: {=SUM([2]Hoja3!$J$5:$J$19*([2]Hoja3!$F$5:$F$19=$B14)*([2]Hoja3!$G$5:$G$19=$U$3))} -> 0 | W14: =IFERROR(V14/U14,0) -> 0 | X14: {=SUM([2]Hoja3!$I$5:$I$19*([2]Hoja3!$F$5:$F$19=$B14)*([2]Hoja3!$G$5:$G$19=$X$3))} -> 0 | Y14: {=SUM([2]Hoja3!$J$5:$J$19*([2]Hoja3!$F$5:$F$19=$B14)*([2]Hoja3!$G$5:$G$19=$X$3))} -> 0 | Z14: =IFERROR(Y14/X14,0) -> 0 | AA14: {=SUM([2]Hoja3!$I$5:$I$19*([2]Hoja3!$F$5:$F$19=$B14)*([2]Hoja3!$G$5:$G$19=$AA$3))} -> 0 | AB14: {=SUM([2]Hoja3!$J$5:$J$19*([2]Hoja3!$F$5:$F$19=$B14)*([2]Hoja3!$G$5:$G$19=$AA$3))} -> 0 | AC14: =IFERROR(AB14/AA14,0) -> 0 | AD14: {=SUM([2]Hoja3!$I$5:$I$19*([2]Hoja3!$F$5:$F$19=$B14)*([2]Hoja3!$G$5:$G$19=$AD$3))} -> 27 | AE14: {=SUM([2]Hoja3!$J$5:$J$19*([2]Hoja3!$F$5:$F$19=$B14)*([2]Hoja3!$G$5:$G$19=$AD$3))} -> 97200 | AF14: =IFERROR(AE14/AD14,0) -> 3600 | AG14: {=SUM([2]Hoja3!$I$5:$I$19*([2]Hoja3!$F$5:$F$19=$B14)*([2]Hoja3!$G$5:$G$19=$AG$3))} -> 0 | AH14: {=SUM([2]Hoja3!$J$5:$J$19*([2]Hoja3!$F$5:$F$19=$B14)*([2]Hoja3!$G$5:$G$19=$AG$3))} -> 0 | AI14: =IFERROR(AH14/AG14,0) -> 0 | AJ14: {=SUM([2]Hoja3!$I$5:$I$19*([2]Hoja3!$F$5:$F$19=$B14)*([2]Hoja3!$G$5:$G$19=$AJ$3))} -> 0 | AK14: {=SUM([2]Hoja3!$J$5:$J$19*([2]Hoja3!$F$5:$F$19=$B14)*([2]Hoja3!$G$5:$G$19=$AJ$3))} -> 0 | AL14: =IFERROR(AK14/AJ14,0) -> 0 | AM14: {=SUM([2]Hoja3!$I$5:$I$19*([2]Hoja3!$F$5:$F$19=$B14)*([2]Hoja3!$G$5:$G$19=$AM$3))} -> 0 | AN14: {=SUM([2]Hoja3!$J$5:$J$19*([2]Hoja3!$F$5:$F$19=$B14)*([2]Hoja3!$G$5:$G$19=$AM$3))} -> 0 | AO14: =IFERROR(AN14/AM14,0) -> 0 | AP14: =U14+X14+AA14 -> 0 | AQ14: =V14+Y14+AB14 -> 0 | AR14: =IFERROR(AQ14/AP14,0) -> 0 | AS14: =AD14+AG14+AJ14+AM14 -> 27 | AT14: =AE14+AH14+AK14+AN14 -> 97200 | AU14: =IFERROR(AT14/AS14,0) -> 3600 | AV14: {=SUM([2]Hoja3!$I$27:$I$34*([2]Hoja3!$F$27:$F$34=$B14))} -> 216 | AW14: {=SUM([2]Hoja3!$J$27:$J$34*([2]Hoja3!$F$27:$F$34=$B14))} -> 820800 | AX14: =IFERROR(AW14/AV14,0) -> 3800 | AY14: =AP14+AS14+AV14 -> 243 | AZ14: =AQ14+AT14+AW14 -> 918000 | BA14: =IFERROR(AZ14/AY14,0) -> 3777.7778 | BB14: =AY14*E14 -> 318330 | BC14: =IFERROR(G14/$D14*$AY14,0) -> 44226 | BD14: =$BD$22/$AY$22*AY14 -> 7344.2244 | BE14: =$BE$22/$AY$22*AY14 -> 16627.575 | BF14: =$BF$22/$AY$22*AY14 -> 13901.515 | BG14: =AZ14-BB14-BC14-BD14-BE14 -> 531472.2 | BH14: =IFERROR(BG14/AZ14,0) -> 0.57894575 | BI14: =IF((AS14+AV14)>D14,AS14+AV14-D14,0) -> 172.256 | BJ14: =IFERROR(AW14/AV14*BI14,0) -> 654572.8 | BK14: =IFERROR(BJ14-(BB14+BC14+BD14+BE14)/AY14*BI14,0) -> 380573.9 | BL14: =IFERROR(BK14/BJ14,0) -> 0.58140806
B15: 10009239 | C15: POTA FILETE DARUMA | D15: 203.7 | E15: =IFERROR(F15/D15,0) -> 2110 | F15: 429807 | G15: 37073.4 | H15: 7439.9116 | I15: 16844.214 | J15: 14082.637 | K15: 0 | L15: 0 | M15: =F15+G15+H15+I15 -> 491164.53 | N15: =IFERROR(M15/D15,0) -> 2411.2151 | P15: 3950 | Q15: =D15*P15 -> 804615 | R15: =Q15-M15 -> 313450.47 | S15: =IFERROR(R15/Q15,0) -> 0.38956579 | U15: {=SUM([2]Hoja3!$I$5:$I$19*([2]Hoja3!$F$5:$F$19=$B15)*([2]Hoja3!$G$5:$G$19=$U$3))} -> 0 | V15: {=SUM([2]Hoja3!$J$5:$J$19*([2]Hoja3!$F$5:$F$19=$B15)*([2]Hoja3!$G$5:$G$19=$U$3))} -> 0 | W15: =IFERROR(V15/U15,0) -> 0 | X15: {=SUM([2]Hoja3!$I$5:$I$19*([2]Hoja3!$F$5:$F$19=$B15)*([2]Hoja3!$G$5:$G$19=$X$3))} -> 27 | Y15: {=SUM([2]Hoja3!$J$5:$J$19*([2]Hoja3!$F$5:$F$19=$B15)*([2]Hoja3!$G$5:$G$19=$X$3))} -> 94500 | Z15: =IFERROR(Y15/X15,0) -> 3500 | AA15: {=SUM([2]Hoja3!$I$5:$I$19*([2]Hoja3!$F$5:$F$19=$B15)*([2]Hoja3!$G$5:$G$19=$AA$3))} -> 0 | AB15: {=SUM([2]Hoja3!$J$5:$J$19*([2]Hoja3!$F$5:$F$19=$B15)*([2]Hoja3!$G$5:$G$19=$AA$3))} -> 0 | AC15: =IFERROR(AB15/AA15,0) -> 0 | AD15: {=SUM([2]Hoja3!$I$5:$I$19*([2]Hoja3!$F$5:$F$19=$B15)*([2]Hoja3!$G$5:$G$19=$AD$3))} -> 162 | AE15: {=SUM([2]Hoja3!$J$5:$J$19*([2]Hoja3!$F$5:$F$19=$B15)*([2]Hoja3!$G$5:$G$19=$AD$3))} -> 631800 | AF15: =IFERROR(AE15/AD15,0) -> 3900 | AG15: {=SUM([2]Hoja3!$I$5:$I$19*([2]Hoja3!$F$5:$F$19=$B15)*([2]Hoja3!$G$5:$G$19=$AG$3))} -> 0 | AH15: {=SUM([2]Hoja3!$J$5:$J$19*([2]Hoja3!$F$5:$F$19=$B15)*([2]Hoja3!$G$5:$G$19=$AG$3))} -> 0 | AI15: =IFERROR(AH15/AG15,0) -> 0 | AJ15: {=SUM([2]Hoja3!$I$5:$I$19*([2]Hoja3!$F$5:$F$19=$B15)*([2]Hoja3!$G$5:$G$19=$AJ$3))} -> 0 | AK15: {=SUM([2]Hoja3!$J$5:$J$19*([2]Hoja3!$F$5:$F$19=$B15)*([2]Hoja3!$G$5:$G$19=$AJ$3))} -> 0 | AL15: =IFERROR(AK15/AJ15,0) -> 0 | AM15: {=SUM([2]Hoja3!$I$5:$I$19*([2]Hoja3!$F$5:$F$19=$B15)*([2]Hoja3!$G$5:$G$19=$AM$3))} -> 0 | AN15: {=SUM([2]Hoja3!$J$5:$J$19*([2]Hoja3!$F$5:$F$19=$B15)*([2]Hoja3!$G$5:$G$19=$AM$3))} -> 0 | AO15: =IFERROR(AN15/AM15,0) -> 0 | AP15: =U15+X15+AA15 -> 27 | AQ15: =V15+Y15+AB15 -> 94500 | AR15: =IFERROR(AQ15/AP15,0) -> 3500 | AS15: =AD15+AG15+AJ15+AM15 -> 162 | AT15: =AE15+AH15+AK15+AN15 -> 631800 | AU15: =IFERROR(AT15/AS15,0) -> 3900 | AV15: {=SUM([2]Hoja3!$I$27:$I$34*([2]Hoja3!$F$27:$F$34=$B15))} -> 243 | AW15: {=SUM([2]Hoja3!$J$27:$J$34*([2]Hoja3!$F$27:$F$34=$B15))} -> 904500 | AX15: =IFERROR(AW15/AV15,0) -> 3722.2222 | AY15: =AP15+AS15+AV15 -> 432 | AZ15: =AQ15+AT15+AW15 -> 1630800 | BA15: =IFERROR(AZ15/AY15,0) -> 3775 | BB15: =AY15*E15 -> 911520 | BC15: =IFERROR(G15/$D15*$AY15,0) -> 78624 | BD15: =$BD$22/$AY$22*AY15 -> 13056.399 | BE15: =$BE$22/$AY$22*AY15 -> 29560.133 | BF15: =$BF$22/$AY$22*AY15 -> 24713.805 | BG15: =AZ15-BB15-BC15-BD15-BE15 -> 598039.47 | BH15: =IFERROR(BG15/AZ15,0) -> 0.3667154 | BI15: =IF((AS15+AV15)>D15,AS15+AV15-D15,0) -> 201.3 | BJ15: =IFERROR(AW15/AV15*BI15,0) -> 749283.33 | BK15: =IFERROR(BJ15-(BB15+BC15+BD15+BE15)/AY15*BI15,0) -> 268045.61 | BL15: =IFERROR(BK15/BJ15,0) -> 0.35773599
B16: 10009332 | C16: POTA RECORTE COCIDO | D16: 63.555 | E16: =IFERROR(F16/D16,0) -> 1530 | F16: 97239.15 | G16: 11567.01 | H16: 2321.2743 | I16: 5255.4444 | J16: 4393.8241 | K16: 0 | L16: 0 | M16: =F16+G16+H16+I16 -> 116382.88 | N16: =IFERROR(M16/D16,0) -> 1831.2151 | P16: 2000 | Q16: =D16*P16 -> 127110 | R16: =Q16-M16 -> 10727.121 | S16: =IFERROR(R16/Q16,0) -> 0.084392426 | U16: {=SUM([2]Hoja3!$I$5:$I$19*([2]Hoja3!$F$5:$F$19=$B16)*([2]Hoja3!$G$5:$G$19=$U$3))} -> 0 | V16: {=SUM([2]Hoja3!$J$5:$J$19*([2]Hoja3!$F$5:$F$19=$B16)*([2]Hoja3!$G$5:$G$19=$U$3))} -> 0 | W16: =IFERROR(V16/U16,0) -> 0 | X16: {=SUM([2]Hoja3!$I$5:$I$19*([2]Hoja3!$F$5:$F$19=$B16)*([2]Hoja3!$G$5:$G$19=$X$3))} -> 0 | Y16: {=SUM([2]Hoja3!$J$5:$J$19*([2]Hoja3!$F$5:$F$19=$B16)*([2]Hoja3!$G$5:$G$19=$X$3))} -> 0 | Z16: =IFERROR(Y16/X16,0) -> 0 | AA16: {=SUM([2]Hoja3!$I$5:$I$19*([2]Hoja3!$F$5:$F$19=$B16)*([2]Hoja3!$G$5:$G$19=$AA$3))} -> 0 | AB16: {=SUM([2]Hoja3!$J$5:$J$19*([2]Hoja3!$F$5:$F$19=$B16)*([2]Hoja3!$G$5:$G$19=$AA$3))} -> 0 | AC16: =IFERROR(AB16/AA16,0) -> 0 | AD16: {=SUM([2]Hoja3!$I$5:$I$19*([2]Hoja3!$F$5:$F$19=$B16)*([2]Hoja3!$G$5:$G$19=$AD$3))} -> 0 | AE16: {=SUM([2]Hoja3!$J$5:$J$19*([2]Hoja3!$F$5:$F$19=$B16)*([2]Hoja3!$G$5:$G$19=$AD$3))} -> 0 | AF16: =IFERROR(AE16/AD16,0) -> 0 | AG16: {=SUM([2]Hoja3!$I$5:$I$19*([2]Hoja3!$F$5:$F$19=$B16)*([2]Hoja3!$G$5:$G$19=$AG$3))} -> 0 | AH16: {=SUM([2]Hoja3!$J$5:$J$19*([2]Hoja3!$F$5:$F$19=$B16)*([2]Hoja3!$G$5:$G$19=$AG$3))} -> 0 | AI16: =IFERROR(AH16/AG16,0) -> 0 | AJ16: {=SUM([2]Hoja3!$I$5:$I$19*([2]Hoja3!$F$5:$F$19=$B16)*([2]Hoja3!$G$5:$G$19=$AJ$3))} -> 0 | AK16: {=SUM([2]Hoja3!$J$5:$J$19*([2]Hoja3!$F$5:$F$19=$B16)*([2]Hoja3!$G$5:$G$19=$AJ$3))} -> 0 | AL16: =IFERROR(AK16/AJ16,0) -> 0 | AM16: {=SUM([2]Hoja3!$I$5:$I$19*([2]Hoja3!$F$5:$F$19=$B16)*([2]Hoja3!$G$5:$G$19=$AM$3))} -> 0 | AN16: {=SUM([2]Hoja3!$J$5:$J$19*([2]Hoja3!$F$5:$F$19=$B16)*([2]Hoja3!$G$5:$G$19=$AM$3))} -> 0 | AO16: =IFERROR(AN16/AM16,0) -> 0 | AP16: =U16+X16+AA16 -> 0 | AQ16: =V16+Y16+AB16 -> 0 | AR16: =IFERROR(AQ16/AP16,0) -> 0 | AS16: =AD16+AG16+AJ16+AM16 -> 0 | AT16: =AE16+AH16+AK16+AN16 -> 0 | AU16: =IFERROR(AT16/AS16,0) -> 0 | AV16: {=SUM([2]Hoja3!$I$27:$I$34*([2]Hoja3!$F$27:$F$34=$B16))} -> 0 | AW16: {=SUM([2]Hoja3!$J$27:$J$34*([2]Hoja3!$F$27:$F$34=$B16))} -> 0 | AX16: =IFERROR(AW16/AV16,0) -> 0 | AY16: =AP16+AS16+AV16 -> 0 | AZ16: =AQ16+AT16+AW16 -> 0 | BA16: =IFERROR(AZ16/AY16,0) -> 0 | BB16: =AY16*E16 -> 0 | BC16: =IFERROR(G16/$D16*$AY16,0) -> 0 | BD16: =$BD$22/$AY$22*AY16 -> 0 | BE16: =$BE$22/$AY$22*AY16 -> 0 | BF16: =$BF$22/$AY$22*AY16 -> 0 | BG16: =AZ16-BB16-BC16-BD16-BE16 -> 0 | BH16: =IFERROR(BG16/AZ16,0) -> 0 | BI16: =IF((AS16+AV16)>D16,AS16+AV16-D16,0) -> 0 | BJ16: =IFERROR(AW16/AV16*BI16,0) -> 0 | BK16: =IFERROR(BJ16-(BB16+BC16+BD16+BE16)/AY16*BI16,0) -> 0 | BL16: =IFERROR(BK16/BJ16,0) -> 0
... B20: 10009224 | C20: BONITO ENT | D20: 0 | E20: =IFERROR(F20/D20,0) -> 0 | F20: 0 | G20: 0 | H20: 0 | I20: 0 | J20: 0 | K20: 0 | L20: 0 | M20: =F20+G20+H20+I20 -> 0 | N20: =IFERROR(M20/D20,0) -> 0 | P20: 0 | Q20: =D20*P20 -> 0 | R20: =Q20-M20 -> 0 | S20: =IFERROR(R20/Q20,0) -> 0 | U20: {=SUM([2]Hoja3!$I$5:$I$19*([2]Hoja3!$F$5:$F$19=$B20)*([2]Hoja3!$G$5:$G$19=$U$3))} -> 0 | V20: {=SUM([2]Hoja3!$J$5:$J$19*([2]Hoja3!$F$5:$F$19=$B20)*([2]Hoja3!$G$5:$G$19=$U$3))} -> 0 | W20: =IFERROR(V20/U20,0) -> 0 | X20: {=SUM([2]Hoja3!$I$5:$I$19*([2]Hoja3!$F$5:$F$19=$B20)*([2]Hoja3!$G$5:$G$19=$X$3))} -> 0 | Y20: {=SUM([2]Hoja3!$J$5:$J$19*([2]Hoja3!$F$5:$F$19=$B20)*([2]Hoja3!$G$5:$G$19=$X$3))} -> 0 | Z20: =IFERROR(Y20/X20,0) -> 0 | AA20: {=SUM([2]Hoja3!$I$5:$I$19*([2]Hoja3!$F$5:$F$19=$B20)*([2]Hoja3!$G$5:$G$19=$AA$3))} -> 0 | AB20: {=SUM([2]Hoja3!$J$5:$J$19*([2]Hoja3!$F$5:$F$19=$B20)*([2]Hoja3!$G$5:$G$19=$AA$3))} -> 0 | AC20: =IFERROR(AB20/AA20,0) -> 0 | AD20: {=SUM([2]Hoja3!$I$5:$I$19*([2]Hoja3!$F$5:$F$19=$B20)*([2]Hoja3!$G$5:$G$19=$AD$3))} -> 0 | AE20: {=SUM([2]Hoja3!$J$5:$J$19*([2]Hoja3!$F$5:$F$19=$B20)*([2]Hoja3!$G$5:$G$19=$AD$3))} -> 0 | AF20: =IFERROR(AE20/AD20,0) -> 0 | AG20: {=SUM([2]Hoja3!$I$5:$I$19*([2]Hoja3!$F$5:$F$19=$B20)*([2]Hoja3!$G$5:$G$19=$AG$3))} -> 0 | AH20: {=SUM([2]Hoja3!$J$5:$J$19*([2]Hoja3!$F$5:$F$19=$B20)*([2]Hoja3!$G$5:$G$19=$AG$3))} -> 0 | AI20: =IFERROR(AH20/AG20,0) -> 0 | AJ20: {=SUM([2]Hoja3!$I$5:$I$19*([2]Hoja3!$F$5:$F$19=$B20)*([2]Hoja3!$G$5:$G$19=$AJ$3))} -> 0 | AK20: {=SUM([2]Hoja3!$J$5:$J$19*([2]Hoja3!$F$5:$F$19=$B20)*([2]Hoja3!$G$5:$G$19=$AJ$3))} -> 0 | AL20: =IFERROR(AK20/AJ20,0) -> 0 | AM20: {=SUM([2]Hoja3!$I$5:$I$19*([2]Hoja3!$F$5:$F$19=$B20)*([2]Hoja3!$G$5:$G$19=$AM$3))} -> 0 | AN20: {=SUM([2]Hoja3!$J$5:$J$19*([2]Hoja3!$F$5:$F$19=$B20)*([2]Hoja3!$G$5:$G$19=$AM$3))} -> 0 | AO20: =IFERROR(AN20/AM20,0) -> 0 | AP20: =U20+X20+AA20 -> 0 | AQ20: =V20+Y20+AB20 -> 0 | AR20: =IFERROR(AQ20/AP20,0) -> 0 | AS20: =AD20+AG20+AJ20+AM20 -> 0 | AT20: =AE20+AH20+AK20+AN20 -> 0 | AU20: =IFERROR(AT20/AS20,0) -> 0 | AV20: {=SUM([2]Hoja3!$I$27:$I$34*([2]Hoja3!$F$27:$F$34=$B20))} -> 0 | AW20: {=SUM([2]Hoja3!$J$27:$J$34*([2]Hoja3!$F$27:$F$34=$B20))} -> 0 | AX20: =IFERROR(AW20/AV20,0) -> 0 | AY20: =AP20+AS20+AV20 -> 0 | AZ20: =AQ20+AT20+AW20 -> 0 | BA20: =IFERROR(AZ20/AY20,0) -> 0 | BB20: =AY20*E20 -> 0 | BC20: =IFERROR(G20/$D20*$AY20,0) -> 0 | BD20: =$BD$22/$AY$22*AY20 -> 0 | BE20: =$BE$22/$AY$22*AY20 -> 0 | BF20: =$BF$22/$AY$22*AY20 -> 0 | BG20: =AZ20-BB20-BC20-BD20-BE20 -> 0 | BH20: =IFERROR(BG20/AZ20,0) -> 0 | BI20: =IF((AS20+AV20)>D20,AS20+AV20-D20,0) -> 0 | BJ20: =IFERROR(AW20/AV20*BI20,0) -> 0 | BK20: =IFERROR(BJ20-(BB20+BC20+BD20+BE20)/AY20*BI20,0) -> 0 | BL20: =IFERROR(BK20/BJ20,0) -> 0
C21: OTROS | D21: =Abril2026!Q59/1000-SUM(D5:D19) -> 6.1288 | E21: =IFERROR(F21/D21,0) -> 0 | U21: {=SUM([2]Hoja3!$I$5:$I$19*([2]Hoja3!$F$5:$F$19=$B21)*([2]Hoja3!$G$5:$G$19=$U$3))} -> 0 | V21: {=SUM([2]Hoja3!$J$5:$J$19*([2]Hoja3!$F$5:$F$19=$B21)*([2]Hoja3!$G$5:$G$19=$U$3))} -> 0 | W21: =IFERROR(V21/U21,0) -> 0 | X21: {=SUM([2]Hoja3!$I$5:$I$19*([2]Hoja3!$F$5:$F$19=$B21)*([2]Hoja3!$G$5:$G$19=$X$3))} -> 0 | Y21: {=SUM([2]Hoja3!$J$5:$J$19*([2]Hoja3!$F$5:$F$19=$B21)*([2]Hoja3!$G$5:$G$19=$X$3))} -> 0 | Z21: =IFERROR(Y21/X21,0) -> 0 | AA21: {=SUM([2]Hoja3!$I$5:$I$19*([2]Hoja3!$F$5:$F$19=$B21)*([2]Hoja3!$G$5:$G$19=$AA$3))} -> 0 | AB21: {=SUM([2]Hoja3!$J$5:$J$19*([2]Hoja3!$F$5:$F$19=$B21)*([2]Hoja3!$G$5:$G$19=$AA$3))} -> 0 | AC21: =IFERROR(AB21/AA21,0) -> 0 | AD21: {=SUM([2]Hoja3!$I$5:$I$19*([2]Hoja3!$F$5:$F$19=$B21)*([2]Hoja3!$G$5:$G$19=$AD$3))} -> 0 | AE21: {=SUM([2]Hoja3!$J$5:$J$19*([2]Hoja3!$F$5:$F$19=$B21)*([2]Hoja3!$G$5:$G$19=$AD$3))} -> 0 | AF21: =IFERROR(AE21/AD21,0) -> 0 | AG21: {=SUM([2]Hoja3!$I$5:$I$19*([2]Hoja3!$F$5:$F$19=$B21)*([2]Hoja3!$G$5:$G$19=$AG$3))} -> 0 | AH21: {=SUM([2]Hoja3!$J$5:$J$19*([2]Hoja3!$F$5:$F$19=$B21)*([2]Hoja3!$G$5:$G$19=$AG$3))} -> 0 | AI21: =IFERROR(AH21/AG21,0) -> 0 | AJ21: {=SUM([2]Hoja3!$I$5:$I$19*([2]Hoja3!$F$5:$F$19=$B21)*([2]Hoja3!$G$5:$G$19=$AJ$3))} -> 54 | AK21: {=SUM([2]Hoja3!$J$5:$J$19*([2]Hoja3!$F$5:$F$19=$B21)*([2]Hoja3!$G$5:$G$19=$AJ$3))} -> 108000 | AL21: =IFERROR(AK21/AJ21,0) -> 2000 | AM21: {=SUM([2]Hoja3!$I$5:$I$19*([2]Hoja3!$F$5:$F$19=$B21)*([2]Hoja3!$G$5:$G$19=$AM$3))} -> 0 | AN21: {=SUM([2]Hoja3!$J$5:$J$19*([2]Hoja3!$F$5:$F$19=$B21)*([2]Hoja3!$G$5:$G$19=$AM$3))} -> 0 | AO21: =IFERROR(AN21/AM21,0) -> 0 | AP21: =U21+X21+AA21 -> 0 | AQ21: =V21+Y21+AB21 -> 0 | AR21: =IFERROR(AQ21/AP21,0) -> 0 | AS21: =AD21+AG21+AJ21+AM21 -> 54 | AT21: =AE21+AH21+AK21+AN21 -> 108000 | AU21: =IFERROR(AT21/AS21,0) -> 2000 | AV21: {=SUM([2]Hoja3!$I$27:$I$34*([2]Hoja3!$F$27:$F$34=$B21))} -> 0 | AW21: {=SUM([2]Hoja3!$J$27:$J$34*([2]Hoja3!$F$27:$F$34=$B21))} -> 0 | AX21: =IFERROR(AW21/AV21,0) -> 0 | AY21: =AP21+AS21+AV21 -> 54 | AZ21: =AQ21+AT21+AW21 -> 108000 | BA21: =IFERROR(AZ21/AY21,0) -> 2000 | BB21: =AY21*E21 -> 0 | BC21: =IFERROR(G21/$D21*$AY21,0) -> 0 | BD21: =$BD$22/$AY$22*AY21 -> 1632.0499 | BE21: =$BE$22/$AY$22*AY21 -> 3695.0166 | BF21: =$BF$22/$AY$22*AY21 -> 3089.2256 | BG21: =AZ21-BB21-BC21-BD21-BE21 -> 102672.93 | BH21: =IFERROR(BG21/AZ21,0) -> 0.95067531 | BI21: =IF((AS21+AV21)>D21,AS21+AV21-D21,0) -> 47.8712 | BJ21: =IFERROR(AW21/AV21*BI21,0) -> 0 | BK21: =IFERROR(BJ21-(BB21+BC21+BD21+BE21)/AY21*BI21,0) -> -4722.4642 | BL21: =IFERROR(BK21/BJ21,0) -> 0
C22: TOTAL | D22: =SUM(D5:D21) -> 1800.1278 | E22: =IFERROR(F22/D22,0) -> 1665.3475 | F22: =SUM(F5:F21) -> 2997838.4 | G22: =SUM(G5:G21) -> 326507.82 | H22: =SUM(H5:H21) -> 65523.78 | I22: =SUM(I5:I21) -> 148348.08 | J22: =SUM(J5:J21) -> 124026.69 | K22: =SUM(K5:K21) -> 0 | L22: 0 | M22: =SUM(M5:M21) -> 3538218.1 | N22: =IFERROR(M22/D22,0) -> 1965.5371 | P22: =Q22/D22 -> 2401.8027 | Q22: =SUM(Q5:Q21) -> 4323551.8 | R22: =SUM(R5:R21) -> 785333.74 | S22: =IFERROR(R22/Q22,0) -> 0.18164088 | U22: =SUM(U5:U21) -> 293 | V22: =SUM(V5:V21) -> 436600 | W22: =IFERROR(V22/U22,0) -> 1490.1024 | X22: =SUM(X5:X21) -> 81 | Y22: =SUM(Y5:Y21) -> 183600 | Z22: =IFERROR(Y22/X22,0) -> 2266.6667 | AA22: =SUM(AA5:AA21) -> 52 | AB22: =SUM(AB5:AB21) -> 117000 | AC22: =IFERROR(AB22/AA22,0) -> 2250 | AD22: =SUM(AD5:AD21) -> 189 | AE22: =SUM(AE5:AE21) -> 729000 | AF22: =IFERROR(AE22/AD22,0) -> 3857.1429 | AG22: =SUM(AG5:AG21) -> 347 | AH22: =SUM(AH5:AH21) -> 609400 | AI22: =IFERROR(AH22/AG22,0) -> 1756.196 | AJ22: =SUM(AJ5:AJ21) -> 54 | AK22: =SUM(AK5:AK21) -> 108000 | AL22: =IFERROR(AK22/AJ22,0) -> 2000 | AM22: =SUM(AM5:AM21) -> 26 | AN22: =SUM(AN5:AN21) -> 36400 | AO22: =IFERROR(AN22/AM22,0) -> 1400 | AP22: =SUM(AP5:AP21) -> 426 | AQ22: =SUM(AQ5:AQ21) -> 737200 | AR22: =IFERROR(AQ22/AP22,0) -> 1730.5164 | AS22: =SUM(AS5:AS21) -> 616 | AT22: =SUM(AT5:AT21) -> 1482800 | AU22: =IFERROR(AT22/AS22,0) -> 2407.1429 | AV22: =SUM(AV5:AV21) -> 1126 | AW22: =SUM(AW5:AW21) -> 3304630 | AX22: =IFERROR(AW22/AV22,0) -> 2934.8401 | AY22: =SUM(AY5:AY21) -> 2168 | AZ22: =SUM(AZ5:AZ21) -> 5524630 | BA22: =IFERROR(AZ22/AY22,0) -> 2548.2611 | BB22: =SUM(BB5:BB21) -> 3638190 | BC22: =SUM(BC5:BC21) -> 384748 | BD22: =H22 -> 65523.78 | BE22: =I22 -> 148348.08 | BF22: =J22 -> 124026.69 | BG22: =SUM(BG5:BG21) -> 1287820.1 | BH22: =IFERROR(BG22/AZ22,0) -> 0.23310523 | BI22: =SUM(BI5:BI21) -> 542.8072 | BJ22: =SUM(BJ5:BJ21) -> 1678077.9 | BK22: =SUM(BK5:BK21) -> 678515.96 | BL22: =IFERROR(BK22/BJ22,0) -> 0.40434116

Sheet TD
A3: Etiquetas de fila | B3: Suma de TM en Stock | C3: Suma de Costo Ventas | D3: Suma de Gasto Ventas | E3: Suma de Gasto ADM | F3: Suma de Gasto Fin | G3: Suma de Depreciación
A4: 10005721 | B4: 396.6 | C4: 690084 | D4: 72181.2 | E4: 14485.365 | F4: 32795.362 | G4: 27418.624
A5: 10005779 | B5: 158.72 | C5: 295219.2 | D5: 28887.04 | E5: 5797.0681 | F5: 13124.76 | G5: 10972.98
A6: 10005781 | B6: 5.48 | C6: 10192.8 | D6: 997.36 | E6: 200.15079 | F6: 453.14822 | G6: 378.85542
A7: 10006720 | B7: 247.26 | C7: 405506.4 | D7: 45001.32 | E7: 9030.8912 | F7: 20446.246 | G7: 17094.122
A8: 10006722 | B8: 0.12 | C8: 224.4 | D8: 21.84 | E8: 4.382864 | F8: 9.9229537 | G8: 8.296104
A9: 10007050 | B9: 70.744 | C9: 92674.64 | D9: 12875.408 | E9: 2583.8444 | F9: 5849.912 | G9: 4890.8298
A10: 10007162 | B10: 371.8 | C10: 639496 | D10: 67667.6 | E10: 13579.574 | F10: 30744.618 | G10: 25704.096
A11: 10007567 | B11: 88.76 | C11: 150892 | D11: 16154.32 | E11: 3241.8584 | F11: 7339.6781 | G11: 6136.3516
A12: 10007969 | B12: 50.9 | C12: 71260 | D12: 9263.8 | E12: 1859.0648 | F12: 4208.9862 | G12: 3518.9308
A13: 10009178 | B13: 61.86 | C13: 107017.8 | D13: 11258.52 | E13: 2259.3664 | F13: 5115.2826 | G13: 4276.6416
A14: 10009207 | B14: 32.44 | C14: 0 | D14: 5904.08 | E14: 1184.8342 | F14: 2682.5052 | G14: 2242.7134
A15: 10009224 | B15: 0 | C15: 0 | D15: 0 | E15: 0 | F15: 0 | G15: 0
... A19: 10009639 | B19: 4.7 | C19: 8225 | D19: 855.4 | E19: 171.66217 | F19: 388.64902 | G19: 324.93074
A20: (en blanco) | B20: 0 | C20: 0 | D20: 0 | E20: 0 | F20: 0 | G20: 0
A21: Total general | B21: 1793.999 | C21: 2997838.4 | D21: 326507.82 | E21: 65523.78 | F21: 148348.08 | G21: 124026.69

Sheet Abril2026
A1: ID | B1: CODIGO | C1: MATERIAL | D1: FECHAS DIAS RECEPCION PRODUCCION ENERO 2026 | N1: MOVIMIENTO INVENTARIO | S1: DATA | T1: DIFERENCIA | AW1: 46119 | AZ1: 46122 | BC1: 46125 | BF1: 46129 | BI1: 46132 | BL1: 46136 | BO1: 46139
B2: SAP | D2: STOCK INICIO | E2: 46118 | F2: 46119 | G2: 46120 | H2: 46121 | I2: 46122 | J2: 46123 | N2: Stock Inicial | O2: INGRESOS | P2: SALIDAS | Q2: STOCK KG | S2: MANUAL | U2: REPROCESO | V2: MUESTREO | W2: EMBARQUE | Y2: STOCK KG | AD2: CÓDIGO | AE2: MATCH | AF2: CPU | AG2: TM en Stock | AH2: Costo Ventas | AI2: Gasto Ventas | AJ2: Gasto ADM | AK2: Gasto Fin | AL2: Depreciación | AM2: Utilidad Neta | AN2: Margen Neto | AO2: Venta Equilibrio | AP2: Precio Equilibrio x TM | AR2: Precio Abril x TM | AS2: Venta Abril | AT2: Utilidad Neta | AU2: Margen Neto | AW2: TM | AX2: Venta | AY2: Precio x TM | AZ2: TM | BA2: Venta | BB2: Precio x TM | BC2: TM | BD2: Venta | BE2: Precio x TM | BF2: TM | BG2: Venta | BH2: Precio x TM | BI2: TM | BJ2: Venta | BK2: Precio x TM | BL2: TM | BM2: Venta | BN2: Precio x TM | BO2: TM | BP2: Venta | BQ2: Precio x TM
A3: 1 | B3: 10006668 | C3: POTA ALAS FR C/P C/C < 0.5 BL10 S20 | D3: 620 | E3: 1780 | F3: =280+120 -> 400 | G3: =2640+180 -> 2820 | H3: =1680+0 -> 1680 | I3: =2860+1900 -> 4760 | J3: 1620 | N3: =+D3 -> 620 | O3: =SUM(E3:L3) -> 13060 | Q3: =+N3+O3-P3 -> 13680 | R3: =+N3-Q3 -> -13060 | T3: =+Q3-S3 -> 13680 | Y3: =SUM(U3:W3) -> 0 | Z3: =+Y3-P3 -> 0 | AD3: 10009178 | AE3: ="FEBRERO"&AD3&"Inventario final" -> FEBRERO10009178Inventario final | AF3: =INDEX('[1]Detalle Costos'!$L$5:$L$158,MATCH(AE3,'[1]Detalle Costos'!$C$5:$C$158,0)) -> 1.73 | AG3: =IF(ISERROR(AF3),0,Q3/1000) -> 13.68 | AH3: =IFERROR(AF3*AG3,0)*1000 -> 23666.4 | AI3: =182*AG3 -> 2489.76 | AJ3: =$AJ$59/$AG$59*AG3 -> 499.64649 | AK3: =$AK$59/$AG$59*AG3 -> 1131.2167 | AL3: =$AL$59/$AG$59*AG3 -> 945.75586 | AM3: 0 | AN3: =$BC$50 -> 0 | AO3: =AH3+AI3+AJ3+AK3 -> 27787.023 | AP3: =IFERROR(AO3/AG3,0) -> 2031.2151 | AR3: 2150 | AS3: =AR3*AG3 -> 29412 | AT3: =AS3-AO3 -> 1624.9768 | AU3: =IFERROR(AT3/AS3,0) -> 0.055248769
A4: =+A3+1 -> 2 | B4: 10009178 | C4: POTA ALAS FR C/P C/C (B) S/COD BL10 S20 | D4: 29100 | E4: 400 | F4: 80 | G4: 240 | H4: =100+0 -> 100 | I4: =220+200 -> 420 | J4: 400 | N4: =+D4 -> 29100 | O4: =SUM(E4:L4) -> 1640 | Q4: =+N4+O4-P4 -> 30740 | T4: =+Q4-S4 -> 30740 | Y4: =SUM(U4:W4) -> 0 | Z4: =+Y4-P4 -> 0 | AD4: 10009178 | AE4: ="FEBRERO"&AD4&"Inventario final" -> FEBRERO10009178Inventario final | AF4: =INDEX('[1]Detalle Costos'!$L$5:$L$158,MATCH(AE4,'[1]Detalle Costos'!$C$5:$C$158,0)) -> 1.73 | AG4: =IF(ISERROR(AF4),0,Q4/1000) -> 30.74 | AH4: =IFERROR(AF4*AG4,0)*1000 -> 53180.2 | AI4: =182*AG4 -> 5594.68 | AJ4: =$AJ$59/$AG$59*AG4 -> 1122.7437 | AK4: =$AK$59/$AG$59*AG4 -> 2541.93 | AL4: =$AL$59/$AG$59*AG4 -> 2125.1853 | AM4: 0 | AN4: =$BC$50 -> 0 | AO4: =AH4+AI4+AJ4+AK4 -> 62439.554 | AP4: =IFERROR(AO4/AG4,0) -> 2031.2151 | AR4: 2150 | AS4: =AR4*AG4 -> 66091 | AT4: =AS4-AO4 -> 3651.4464 | AU4: =IFERROR(AT4/AS4,0) -> 0.055248769
A5: =+A4+1 -> 3 | B5: 10006719 | C5: POTA ALAS FR C/P C/C 0.5-1 BL10 S20 | D5: 680 | E5: 1540 | F5: =60+400 -> 460 | G5: =1940+180 -> 2120 | H5: =2820+0 -> 2820 | I5: =3880+2760 -> 6640 | J5: 2500 | N5: =+D5 -> 680 | O5: =SUM(E5:L5) -> 16080 | Q5: =+N5+O5-P5 -> 16760 | T5: =+Q5-S5 -> 16760 | Y5: =SUM(U5:W5) -> 0 | Z5: =+Y5-P5 -> 0 | AD5: 10009178 | AE5: ="FEBRERO"&AD5&"Inventario final" -> FEBRERO10009178Inventario final | AF5: =INDEX('[1]Detalle Costos'!$L$5:$L$158,MATCH(AE5,'[1]Detalle Costos'!$C$5:$C$158,0)) -> 1.73 | AG5: =IF(ISERROR(AF5),0,Q5/1000) -> 16.76 | AH5: =IFERROR(AF5*AG5,0)*1000 -> 28994.8 | AI5: =182*AG5 -> 3050.32 | AJ5: =$AJ$59/$AG$59*AG5 -> 612.14 | AK5: =$AK$59/$AG$59*AG5 -> 1385.9059 | AL5: =$AL$59/$AG$59*AG5 -> 1158.6892 | AM5: 0 | AN5: =$BC$50 -> 0 | AO5: =AH5+AI5+AJ5+AK5 -> 34043.166 | AP5: =IFERROR(AO5/AG5,0) -> 2031.2151 | AR5: 2150 | AS5: =AR5*AG5 -> 36034 | AT5: =AS5-AO5 -> 1990.8341 | AU5: =IFERROR(AT5/AS5,0) -> 0.055248769
A6: =+A5+1 -> 4 | B6: 10009265 | C6: POTA ALAS FR C/P C/C 0.3 - 0.5 BL10 S20 | D6: 680 | N6: =+D6 -> 680 | O6: =SUM(E6:L6) -> 0 | Q6: =+N6+O6-P6 -> 680 | T6: =+Q6-S6 -> 680 | Y6: =SUM(U6:W6) -> 0 | Z6: =+Y6-P6 -> 0 | AD6: 10009178 | AE6: ="FEBRERO"&AD6&"Inventario final" -> FEBRERO10009178Inventario final | AF6: =INDEX('[1]Detalle Costos'!$L$5:$L$158,MATCH(AE6,'[1]Detalle Costos'!$C$5:$C$158,0)) -> 1.73 | AG6: =IF(ISERROR(AF6),0,Q6/1000) -> 0.68 | AH6: =IFERROR(AF6*AG6,0)*1000 -> 1176.4 | AI6: =182*AG6 -> 123.76 | AJ6: =$AJ$59/$AG$59*AG6 -> 24.836229 | AK6: =$AK$59/$AG$59*AG6 -> 56.230071 | AL6: =$AL$59/$AG$59*AG6 -> 47.011256 | AM6: 0 | AN6: =$BC$50 -> 0 | AO6: =AH6+AI6+AJ6+AK6 -> 1381.2263 | AP6: =IFERROR(AO6/AG6,0) -> 2031.2151 | AR6: 2150 | AS6: =AR6*AG6 -> 1462 | AT6: =AS6-AO6 -> 80.7737 | AU6: =IFERROR(AT6/AS6,0) -> 0.055248769
A7: =+A6+1 -> 5 | B7: 10006720 | C7: POTA ALAS FR C/P C/C 1-2 BL10 S20 | D7: 274200 | E7: 60 | N7: =+D7 -> 274200 | O7: =SUM(E7:L7) -> 60 | P7: 27000 | Q7: =+N7+O7-P7 -> 247260 | T7: =+Q7-S7 -> 247260 | Y7: =SUM(U7:W7) -> 0 | Z7: =+Y7-P7 -> -27000 | AD7: 10006720 | AE7: ="FEBRERO"&AD7&"Inventario final" -> FEBRERO10006720Inventario final | AF7: =INDEX('[1]Detalle Costos'!$L$5:$L$158,MATCH(AE7,'[1]Detalle Costos'!$C$5:$C$158,0)) -> 1.64 | AG7: =IF(ISERROR(AF7),0,Q7/1000) -> 247.26 | AH7: =IFERROR(AF7*AG7,0)*1000 -> 405506.4 | AI7: =182*AG7 -> 45001.32 | AJ7: =$AJ$59/$AG$59*AG7 -> 9030.8912 | AK7: =$AK$59/$AG$59*AG7 -> 20446.246 | AL7: =$AL$59/$AG$59*AG7 -> 17094.122 | AM7: 0 | AN7: =$BC$50 -> 0 | AO7: =AH7+AI7+AJ7+AK7 -> 479984.86 | AP7: =IFERROR(AO7/AG7,0) -> 1941.2151 | AR7: 2150 | AS7: =AR7*AG7 -> 531609 | AT7: =AS7-AO7 -> 51624.143 | AU7: =IFERROR(AT7/AS7,0) -> 0.097109234
A8: =+A7+1 -> 6 | B8: 10006722 | C8: POTA ALAS FR C/P C/C 2-UP BL10 S20 | D8: 120 | N8: =+D8 -> 120 | O8: =SUM(E8:L8) -> 0 | Q8: =+N8+O8-P8 -> 120 | T8: =+Q8-S8 -> 120 | Y8: =SUM(U8:W8) -> 0 | Z8: =+Y8-P8 -> 0 | AD8: 10006722 | AE8: ="FEBRERO"&AD8&"Inventario final" -> FEBRERO10006722Inventario final | AF8: =INDEX('[1]Detalle Costos'!$L$5:$L$158,MATCH(AE8,'[1]Detalle Costos'!$C$5:$C$158,0)) -> 1.87 | AG8: =IF(ISERROR(AF8),0,Q8/1000) -> 0.12 | AH8: =IFERROR(AF8*AG8,0)*1000 -> 224.4 | AI8: =182*AG8 -> 21.84 | AJ8: =$AJ$59/$AG$59*AG8 -> 4.382864 | AK8: =$AK$59/$AG$59*AG8 -> 9.9229537 | AL8: =$AL$59/$AG$59*AG8 -> 8.296104 | AM8: 0 | AN8: =$BC$50 -> 0 | AO8: =AH8+AI8+AJ8+AK8 -> 260.54582 | AP8: =IFERROR(AO8/AG8,0) -> 2171.2151 | AR8: 2150 | AS8: =AR8*AG8 -> 258 | AT8: =AS8-AO8 -> -2.5458177 | AU8: =IFERROR(AT8/AS8,0) -> -0.0098675105
A9: =+A8+1 -> 7 | B9: 10009331 | C9: POTA ALAS PRE COC 3-UP BL9 S18 | D9: 15138 | F9: =4086+3078 -> 7164 | G9: =2088+2376 -> 4464 | H9: 2916 | I9: 3124 | J9: 3114 | N9: =+D9 -> 15138 | O9: =SUM(E9:L9) -> 20782 | Q9: =+N9+O9-P9 -> 35920 | T9: =+Q9-S9 -> 35920 | Y9: =SUM(U9:W9) -> 0 | Z9: =+Y9-P9 -> 0 | AD9: 10007050 | AE9: ="FEBRERO"&AD9&"Inventario final" -> FEBRERO10007050Inventario final | AF9: =INDEX('[1]Detalle Costos'!$L$5:$L$158,MATCH(AE9,'[1]Detalle Costos'!$C$5:$C$158,0)) -> 1.31 | AG9: =IF(ISERROR(AF9),0,Q9/1000) -> 35.92 | AH9: =IFERROR(AF9*AG9,0)*1000 -> 47055.2 | AI9: =182*AG9 -> 6537.44 | AJ9: =$AJ$59/$AG$59*AG9 -> 1311.9373 | AK9: =$AK$59/$AG$59*AG9 -> 2970.2708 | AL9: =$AL$59/$AG$59*AG9 -> 2483.3005 | AM9: 0 | AN9: =$BC$50 -> 0 | AO9: =AH9+AI9+AJ9+AK9 -> 57874.848 | AP9: =IFERROR(AO9/AG9,0) -> 1611.2151 | AR9: 3950 | AS9: =AR9*AG9 -> 141884 | AT9: =AS9-AO9 -> 84009.152 | AU9: =IFERROR(AT9/AS9,0) -> 0.59209743
A10: =+A9+1 -> 8 | C10: POTA ALAS PRE COC 3-UP BL10 S20 | D10: 0 | N10: =+D10 -> 0 | O10: =SUM(E10:L10) -> 0 | Q10: =+N10+O10-P10 -> 0 | T10: =+Q10-S10 -> 0 | Y10: =SUM(U10:W10) -> 0 | Z10: =+Y10-P10 -> 0 | AD10: 10007050 | AE10: ="FEBRERO"&AD10&"Inventario final" -> FEBRERO10007050Inventario final | AF10: =INDEX('[1]Detalle Costos'!$L$5:$L$158,MATCH(AE10,'[1]Detalle Costos'!$C$5:$C$158,0)) -> 1.31 | AG10: =IF(ISERROR(AF10),0,Q10/1000) -> 0 | AH10: =IFERROR(AF10*AG10,0)*1000 -> 0 | AI10: =182*AG10 -> 0 | AJ10: =$AJ$59/$AG$59*AG10 -> 0 | AK10: =$AK$59/$AG$59*AG10 -> 0 | AL10: =$AL$59/$AG$59*AG10 -> 0 | AM10: 0 | AN10: =$BC$50 -> 0 | AO10: =AH10+AI10+AJ10+AK10 -> 0 | AP10: =IFERROR(AO10/AG10,0) -> 0 | AS10: =AR10*AG10 -> 0 | AT10: =AS10-AO10 -> 0 | AU10: =IFERROR(AT10/AS10,0) -> 0
A11: =+A10+1 -> 9 | B11: 10009334 | C11: POTA ALAS PRE COC B BL9 S18 | D11: 5472 | F11: =324+342 -> 666 | G11: =540+36 -> 576 | H11: 216 | J11: 234 | N11: =+D11 -> 5472 | O11: =SUM(E11:L11) -> 1692 | Q11: =+N11+O11-P11 -> 7164 | T11: =+Q11-S11 -> 7164 | Y11: =SUM(U11:W11) -> 0 | Z11: =+Y11-P11 -> 0 | AD11: 10007050 | AE11: ="FEBRERO"&AD11&"Inventario final" -> FEBRERO10007050Inventario final | AF11: =INDEX('[1]Detalle Costos'!$L$5:$L$158,MATCH(AE11,'[1]Detalle Costos'!$C$5:$C$158,0)) -> 1.31 | AG11: =IF(ISERROR(AF11),0,Q11/1000) -> 7.164 | AH11: =IFERROR(AF11*AG11,0)*1000 -> 9384.84 | AI11: =182*AG11 -> 1303.848 | AJ11: =$AJ$59/$AG$59*AG11 -> 261.65698 | AK11: =$AK$59/$AG$59*AG11 -> 592.40034 | AL11: =$AL$59/$AG$59*AG11 -> 495.27741 | AM11: 0 | AN11: =$BC$50 -> 0 | AO11: =AH11+AI11+AJ11+AK11 -> 11542.745 | AP11: =IFERROR(AO11/AG11,0) -> 1611.2151 | AR11: 3950 | AS11: =AR11*AG11 -> 28297.8 | AT11: =AS11-AO11 -> 16755.055 | AU11: =IFERROR(AT11/AS11,0) -> 0.59209743
A12: =+A11+1 -> 10 | B12: 10009207 | C12: POTA LABIOS FR S/COD BL10 S20 | D12: 30840 | E12: 320 | F12: 0 | G12: =260+140 -> 400 | H12: 280 | I12: =160+360 -> 520 | J12: 80 | N12: =+D12 -> 30840 | O12: =SUM(E12:L12) -> 1600 | Q12: =+N12+O12-P12 -> 32440 | T12: =+Q12-S12 -> 32440 | Y12: =SUM(U12:W12) -> 0 | Z12: =+Y12-P12 -> 0 | AD12: 10009207 | AE12: ="FEBRERO"&AD12&"Inventario final" -> FEBRERO10009207Inventario final | AF12: 0 | AG12: =IF(ISERROR(AF12),0,Q12/1000) -> 32.44 | AH12: =IFERROR(AF12*AG12,0)*1000 -> 0 | AI12: =182*AG12 -> 5904.08 | AJ12: =$AJ$59/$AG$59*AG12 -> 1184.8342 | AK12: =$AK$59/$AG$59*AG12 -> 2682.5052 | AL12: =$AL$59/$AG$59*AG12 -> 2242.7134 | AM12: 0 | AN12: =$BC$50 -> 0 | AO12: =AH12+AI12+AJ12+AK12 -> 9771.4194 | AP12: =IFERROR(AO12/AG12,0) -> 301.21515 | AR12: 1000 | AS12: =AR12*AG12 -> 32440 | AT12: =AS12-AO12 -> 22668.581 | AU12: =IFERROR(AT12/AS12,0) -> 0.69878485
A13: =+A12+1 -> 11 | B13: 10007969 | C13: POTA CONOS | D13: 48300 | E13: 640 | F13: 280 | G13: =340+300 -> 640 | H13: 340 | I13: 700 | N13: =+D13 -> 48300 | O13: =SUM(E13:L13) -> 2600 | Q13: =+N13+O13-P13 -> 50900 | T13: =+Q13-S13 -> 50900 | Y13: =SUM(U13:W13) -> 0 | Z13: =+Y13-P13 -> 0 | AD13: 10007969 | AE13: ="FEBRERO"&AD13&"Inventario final" -> FEBRERO10007969Inventario final | AF13: =INDEX('[1]Detalle Costos'!$L$5:$L$158,MATCH(AE13,'[1]Detalle Costos'!$C$5:$C$158,0)) -> 1.4 | AG13: =IF(ISERROR(AF13),0,Q13/1000) -> 50.9 | AH13: =IFERROR(AF13*AG13,0)*1000 -> 71260 | AI13: =182*AG13 -> 9263.8 | AJ13: =$AJ$59/$AG$59*AG13 -> 1859.0648 | AK13: =$AK$59/$AG$59*AG13 -> 4208.9862 | AL13: =$AL$59/$AG$59*AG13 -> 3518.9308 | AM13: 0 | AN13: =$BC$50 -> 0 | AO13: =AH13+AI13+AJ13+AK13 -> 86591.851 | AP13: =IFERROR(AO13/AG13,0) -> 1701.2151 | AR13: 1800 | AS13: =AR13*AG13 -> 91620 | AT13: =AS13-AO13 -> 5028.149 | AU13: =IFERROR(AT13/AS13,0) -> 0.054880474
A14: =+A13+1 -> 12 | B14: 10004433 | C14: POTA FILETE C/M C/T FR 0.5-1 BL10 S20 | D14: 300 | F14: =40+160 -> 200 | I14: 60 | N14: =+D14 -> 300 | O14: =SUM(E14:L14) -> 260 | Q14: =+N14+O14-P14 -> 560 | T14: =+Q14-S14 -> 560 | Y14: =SUM(U14:W14) -> 0 | Z14: =+Y14-P14 -> 0 | AD14: 10005721 | AE14: ="FEBRERO"&AD14&"Inventario final" -> FEBRERO10005721Inventario final | AF14: =INDEX('[1]Detalle Costos'!$L$5:$L$158,MATCH(AE14,'[1]Detalle Costos'!$C$5:$C$158,0)) -> 1.74 | AG14: =IF(ISERROR(AF14),0,Q14/1000) -> 0.56 | AH14: =IFERROR(AF14*AG14,0)*1000 -> 974.4 | AI14: =182*AG14 -> 101.92 | AJ14: =$AJ$59/$AG$59*AG14 -> 20.453365 | AK14: =$AK$59/$AG$59*AG14 -> 46.307117 | AL14: =$AL$59/$AG$59*AG14 -> 38.715152 | AM14: 0 | AN14: =$BC$50 -> 0 | AO14: =AH14+AI14+AJ14+AK14 -> 1143.0805 | AP14: =IFERROR(AO14/AG14,0) -> 2041.2151 | AR14: 2100 | AS14: =AR14*AG14 -> 1176 | AT14: =AS14-AO14 -> 32.919517 | AU14: =IFERROR(AT14/AS14,0) -> 0.027992787
B15: 10005711 | C15: POTA FILETE C/M C/T FR 0.5-1AA BL10 S20 | D15: 0 | E15: 1100 | F15: =140+1180 -> 1320 | G15: =700+520 -> 1220 | H15: 1000 | I15: =260+1840 -> 2100 | J15: 1140 | N15: =+D15 -> 0 | O15: =SUM(E15:L15) -> 7880 | Q15: =+N15+O15-P15 -> 7880 | T15: =+Q15-S15 -> 7880 | AD15: 10005721 | AE15: ="FEBRERO"&AD15&"Inventario final" -> FEBRERO10005721Inventario final | AF15: =INDEX('[1]Detalle Costos'!$L$5:$L$158,MATCH(AE15,'[1]Detalle Costos'!$C$5:$C$158,0)) -> 1.74 | AG15: =IF(ISERROR(AF15),0,Q15/1000) -> 7.88 | AH15: =IFERROR(AF15*AG15,0)*1000 -> 13711.2 | AI15: =182*AG15 -> 1434.16 | AJ15: =$AJ$59/$AG$59*AG15 -> 287.80807 | AK15: =$AK$59/$AG$59*AG15 -> 651.60729 | AL15: =$AL$59/$AG$59*AG15 -> 544.7775 | AM15: 0 | AN15: =$BC$50 -> 0 | AO15: =AH15+AI15+AJ15+AK15 -> 16084.775 | AP15: =IFERROR(AO15/AG15,0) -> 2041.2151 | AR15: 2100 | AS15: =AR15*AG15 -> 16548 | AT15: =AS15-AO15 -> 463.22464 | AU15: =IFERROR(AT15/AS15,0) -> 0.027992787
A16: =+A14+1 -> 13 | B16: 10004434 | C16: POTA FILETE C/M C/T FR 1-2 BL10 S20 | D16: 1120 | F16: =280+840 -> 1120 | G16: 280 | I16: 1720 | N16: =+D16 -> 1120 | O16: =SUM(E16:L16) -> 3120 | Q16: =+N16+O16-P16 -> 4240 | T16: =+Q16-S16 -> 4240 | Y16: =SUM(U16:W16) -> 0 | Z16: =+Y16-P16 -> 0 | AD16: 10005721 | AE16: ="FEBRERO"&AD16&"Inventario final" -> FEBRERO10005721Inventario final | AF16: =INDEX('[1]Detalle Costos'!$L$5:$L$158,MATCH(AE16,'[1]Detalle Costos'!$C$5:$C$158,0)) -> 1.74 | AG16: =IF(ISERROR(AF16),0,Q16/1000) -> 4.24 | AH16: =IFERROR(AF16*AG16,0)*1000 -> 7377.6 | AI16: =182*AG16 -> 771.68 | AJ16: =$AJ$59/$AG$59*AG16 -> 154.86119 | AK16: =$AK$59/$AG$59*AG16 -> 350.61103 | AL16: =$AL$59/$AG$59*AG16 -> 293.12901 | AM16: 0 | AN16: =$BC$50 -> 0 | AO16: =AH16+AI16+AJ16+AK16 -> 8654.7522 | AP16: =IFERROR(AO16/AG16,0) -> 2041.2151 | AR16: 2100 | AS16: =AR16*AG16 -> 8904 | AT16: =AS16-AO16 -> 249.24777 | AU16: =IFERROR(AT16/AS16,0) -> 0.027992787
A17: =+A16+1 -> 14 | B17: 10005721 | C17: POTA FILETE C/M C/T FR 2-4 AA BL10 S20 | D17: 486640 | E17: =4760+7800 -> 12560 | F17: =4320+6300 -> 10620 | G17: =1920+2900 -> 4820 | H17: =1280+6180 -> 7460 | I17: =1160+11780 -> 12940 | J17: 1460 | N17: =+D17 -> 486640 | O17: =SUM(E17:L17) -> 49860 | P17: =125000+120000+26000 -> 271000 | Q17: =+N17+O17-P17 -> 265500 | T17: =+Q17-S17 -> 265500 | W17: 125000 | Y17: =SUM(U17:W17) -> 125000 | Z17: =+Y17-P17 -> -146000 | AD17: 10005721 | AE17: ="FEBRERO"&AD17&"Inventario final" -> FEBRERO10005721Inventario final | AF17: =INDEX('[1]Detalle Costos'!$L$5:$L$158,MATCH(AE17,'[1]Detalle Costos'!$C$5:$C$158,0)) -> 1.74 | AG17: =IF(ISERROR(AF17),0,Q17/1000) -> 265.5 | AH17: =IFERROR(AF17*AG17,0)*1000 -> 461970 | AI17: =182*AG17 -> 48321 | AJ17: =$AJ$59/$AG$59*AG17 -> 9697.0865 | AK17: =$AK$59/$AG$59*AG17 -> 21954.535 | AL17: =$AL$59/$AG$59*AG17 -> 18355.13 | AM17: 0 | AN17: =$BC$50 -> 0 | AO17: =AH17+AI17+AJ17+AK17 -> 541942.62 | AP17: =IFERROR(AO17/AG17,0) -> 2041.2151 | AR17: 2100 | AS17: =AR17*AG17 -> 557550 | AT17: =AS17-AO17 -> 15607.378 | AU17: =IFERROR(AT17/AS17,0) -> 0.027992787
A18: =+A17+1 -> 15 | B18: 10004435 | C18: POTA FILETE C/M C/T FR 2-4 BL10 S20 | D18: 121200 | E18: 280 | F18: =320+2480 -> 2800 | G18: 740 | H18: 720 | I18: 1340 | N18: =+D18 -> 121200 | O18: =SUM(E18:L18) -> 5880 | P18: =46000+27000 -> 73000 | Q18: =+N18+O18-P18 -> 54080 | T18: =+Q18-S18 -> 54080 | W18: 46000 | Y18: =SUM(U18:W18) -> 46000 | Z18: =+Y18-P18 -> -27000 | AD18: 10005721 | AE18: ="FEBRERO"&AD18&"Inventario final" -> FEBRERO10005721Inventario final | AF18: =INDEX('[1]Detalle Costos'!$L$5:$L$158,MATCH(AE18,'[1]Detalle Costos'!$C$5:$C$158,0)) -> 1.74 | AG18: =IF(ISERROR(AF18),0,Q18/1000) -> 54.08 | AH18: =IFERROR(AF18*AG18,0)*1000 -> 94099.2 | AI18: =182*AG18 -> 9842.56 | AJ18: =$AJ$59/$AG$59*AG18 -> 1975.2107 | AK18: =$AK$59/$AG$59*AG18 -> 4471.9445 | AL18: =$AL$59/$AG$59*AG18 -> 3738.7775 | AM18: 0 | AN18: =$BC$50 -> 0 | AO18: =AH18+AI18+AJ18+AK18 -> 110388.92 | AP18: =IFERROR(AO18/AG18,0) -> 2041.2151 | AR18: 1200 | AS18: =AR18*AG18 -> 64896 | AT18: =AS18-AO18 -> -45492.915 | AU18: =IFERROR(AT18/AS18,0) -> -0.70101262
C19: POTA FILETE C/M C/T FR 0.5-1AAA BL10 S20 | D19: 0 | H19: 40 | I19: 120 | J19: 720 | N19: =+D19 -> 0 | O19: =SUM(E19:L19) -> 880 | Q19: =+N19+O19-P19 -> 880 | T19: =+Q19-S19 -> 880 | AD19: 10005721 | AE19: ="FEBRERO"&AD19&"Inventario final" -> FEBRERO10005721Inventario final | AF19: =INDEX('[1]Detalle Costos'!$L$5:$L$158,MATCH(AE19,'[1]Detalle Costos'!$C$5:$C$158,0)) -> 1.74 | AG19: =IF(ISERROR(AF19),0,Q19/1000) -> 0.88 | AH19: =IFERROR(AF19*AG19,0)*1000 -> 1531.2 | AI19: =182*AG19 -> 160.16 | AJ19: =$AJ$59/$AG$59*AG19 -> 32.141002 | AK19: =$AK$59/$AG$59*AG19 -> 72.768327 | AL19: =$AL$59/$AG$59*AG19 -> 60.838096 | AM19: 0 | AN19: =$BC$50 -> 0 | AO19: =AH19+AI19+AJ19+AK19 -> 1796.2693 | AP19: =IFERROR(AO19/AG19,0) -> 2041.2151 | AR19: 1200 | AS19: =AR19*AG19 -> 1056 | AT19: =AS19-AO19 -> -740.26933 | AU19: =IFERROR(AT19/AS19,0) -> -0.70101262
C20: POTA FILETE C/M C/T FR 1-2 AABL10 S20 | D20: 0 | E20: 7820 | F20: =1040+3620 -> 4660 | G20: =5080+940 -> 6020 | H20: =1100+9100 -> 10200 | I20: =8680+12460 -> 21140 | J20: 11180 | N20: =+D20 -> 0 | O20: =SUM(E20:L20) -> 61020 | Q20: =+N20+O20-P20 -> 61020 | T20: =+Q20-S20 -> 61020 | AD20: 10005721 | AE20: ="FEBRERO"&AD20&"Inventario final" -> FEBRERO10005721Inventario final | AF20: =INDEX('[1]Detalle Costos'!$L$5:$L$158,MATCH(AE20,'[1]Detalle Costos'!$C$5:$C$158,0)) -> 1.74 | AG20: =IF(ISERROR(AF20),0,Q20/1000) -> 61.02 | AH20: =IFERROR(AF20*AG20,0)*1000 -> 106174.8 | AI20: =182*AG20 -> 11105.64 | AJ20: =$AJ$59/$AG$59*AG20 -> 2228.6863 | AK20: =$AK$59/$AG$59*AG20 -> 5045.822 | AL20: =$AL$59/$AG$59*AG20 -> 4218.5689 | AM20: 0 | AN20: =$BC$50 -> 0 | AO20: =AH20+AI20+AJ20+AK20 -> 124554.95 | AP20: =IFERROR(AO20/AG20,0) -> 2041.2151 | AR20: 1200 | AS20: =AR20*AG20 -> 73224 | AT20: =AS20-AO20 -> -51330.948 | AU20: =IFERROR(AT20/AS20,0) -> -0.70101262
C21: POTA FILETE C/M C/T FR 1-2 AAABL10 S20 | D21: 0 | H21: 320 | J21: 1560 | N21: =+D21 -> 0 | O21: =SUM(E21:L21) -> 1880 | Q21: =+N21+O21-P21 -> 1880 | T21: =+Q21-S21 -> 1880 | AD21: 10005721 | AE21: ="FEBRERO"&AD21&"Inventario final" -> FEBRERO10005721Inventario final | AF21: =INDEX('[1]Detalle Costos'!$L$5:$L$158,MATCH(AE21,'[1]Detalle Costos'!$C$5:$C$158,0)) -> 1.74 | AG21: =IF(ISERROR(AF21),0,Q21/1000) -> 1.88 | AH21: =IFERROR(AF21*AG21,0)*1000 -> 3271.2 | AI21: =182*AG21 -> 342.16 | AJ21: =$AJ$59/$AG$59*AG21 -> 68.664869 | AK21: =$AK$59/$AG$59*AG21 -> 155.45961 | AL21: =$AL$59/$AG$59*AG21 -> 129.9723 | AM21: 0 | AN21: =$BC$50 -> 0 | AO21: =AH21+AI21+AJ21+AK21 -> 3837.4845 | AP21: =IFERROR(AO21/AG21,0) -> 2041.2151 | AR21: 1200 | AS21: =AR21*AG21 -> 2256 | AT21: =AS21-AO21 -> -1581.4845 | AU21: =IFERROR(AT21/AS21,0) -> -0.70101262
C22: POTA FILETE C/M C/T FR < 0.5 BL10 S20 | D22: 0 | I22: 460 | J22: 100 | N22: =+D22 -> 0 | O22: =SUM(E22:L22) -> 560 | Q22: =+N22+O22-P22 -> 560 | T22: =+Q22-S22 -> 560 | AD22: 10005721 | AE22: ="FEBRERO"&AD22&"Inventario final" -> FEBRERO10005721Inventario final | AF22: =INDEX('[1]Detalle Costos'!$L$5:$L$158,MATCH(AE22,'[1]Detalle Costos'!$C$5:$C$158,0)) -> 1.74 | AG22: =IF(ISERROR(AF22),0,Q22/1000) -> 0.56 | AH22: =IFERROR(AF22*AG22,0)*1000 -> 974.4 | AI22: =182*AG22 -> 101.92 | AJ22: =$AJ$59/$AG$59*AG22 -> 20.453365 | AK22: =$AK$59/$AG$59*AG22 -> 46.307117 | AL22: =$AL$59/$AG$59*AG22 -> 38.715152 | AM22: 0 | AN22: =$BC$50 -> 0 | AO22: =AH22+AI22+AJ22+AK22 -> 1143.0805 | AP22: =IFERROR(AO22/AG22,0) -> 2041.2151 | AR22: 1200 | AS22: =AR22*AG22 -> 672 | AT22: =AS22-AO22 -> -471.08048 | AU22: =IFERROR(AT22/AS22,0) -> -0.70101262
A23: =+A18+1 -> 16 | B23: 10009184 | C23: POTA NUCAS FR ABIERTAS 0.1 - 0.3 BL10 S2 | D23: 940 | G23: 20 | I23: 100 | J23: 100 | N23: =+D23 -> 940 | O23: =SUM(E23:L23) -> 220 | Q23: =+N23+O23-P23 -> 1160 | T23: =+Q23-S23 -> 1160 | Y23: =SUM(U23:W23) -> 0 | Z23: =+Y23-P23 -> 0 | AD23: 10005779 | AE23: ="FEBRERO"&AD23&"Inventario final" -> FEBRERO10005779Inventario final | AF23: =INDEX('[1]Detalle Costos'!$L$5:$L$158,MATCH(AE23,'[1]Detalle Costos'!$C$5:$C$158,0)) -> 1.86 | AG23: =IF(ISERROR(AF23),0,Q23/1000) -> 1.16 | AH23: =IFERROR(AF23*AG23,0)*1000 -> 2157.6 | AI23: =182*AG23 -> 211.12 | AJ23: =$AJ$59/$AG$59*AG23 -> 42.367685 | AK23: =$AK$59/$AG$59*AG23 -> 95.921886 | AL23: =$AL$59/$AG$59*AG23 -> 80.195672 | AM23: 0 | AN23: =$BC$50 -> 0 | AO23: =AH23+AI23+AJ23+AK23 -> 2507.0096 | AP23: =IFERROR(AO23/AG23,0) -> 2161.2151 | AR23: 1200 | AS23: =AR23*AG23 -> 1392 | AT23: =AS23-AO23 -> -1115.0096 | AU23: =IFERROR(AT23/AS23,0) -> -0.80101262
A24: =+A23+1 -> 17 | B24: 10009271 | C24: POTA NUCAS FR CERRADA 0.1 - 0.3 BL10 S2 | D24: 560 | E24: 1220 | F24: 1160 | G24: =220+800 -> 1020 | H24: 1460 | I24: 140 | N24: =+D24 -> 560 | O24: =SUM(E24:L24) -> 5000 | Q24: =+N24+O24-P24 -> 5560 | T24: =+Q24-S24 -> 5560 | Y24: =SUM(U24:W24) -> 0 | Z24: =+Y24-P24 -> 0 | AD24: 10005779 | AE24: ="FEBRERO"&AD24&"Inventario final" -> FEBRERO10005779Inventario final | AF24: =INDEX('[1]Detalle Costos'!$L$5:$L$158,MATCH(AE24,'[1]Detalle Costos'!$C$5:$C$158,0)) -> 1.86 | AG24: =IF(ISERROR(AF24),0,Q24/1000) -> 5.56 | AH24: =IFERROR(AF24*AG24,0)*1000 -> 10341.6 | AI24: =182*AG24 -> 1011.92 | AJ24: =$AJ$59/$AG$59*AG24 -> 203.0727 | AK24: =$AK$59/$AG$59*AG24 -> 459.76352 | AL24: =$AL$59/$AG$59*AG24 -> 384.38615 | AM24: 0 | AN24: =$BC$50 -> 0 | AO24: =AH24+AI24+AJ24+AK24 -> 12016.356 | AP24: =IFERROR(AO24/AG24,0) -> 2161.2151 | AR24: 1200 | AS24: =AR24*AG24 -> 6672 | AT24: =AS24-AO24 -> -5344.3562 | AU24: =IFERROR(AT24/AS24,0) -> -0.80101262
A25: =+A24+1 -> 18 | B25: 10005779 | C25: POTA NUCAS FR ABIERTAS 0.5-1 BL10 S20 | D25: 78780 | E25: 1280 | F25: =120+1040 -> 1160 | G25: =140+380 -> 520 | H25: 720 | I25: 1160 | J25: 260 | N25: =+D25 -> 78780 | O25: =SUM(E25:L25) -> 5100 | Q25: =+N25+O25-P25 -> 83880 | T25: =+Q25-S25 -> 83880 | Y25: =SUM(U25:W25) -> 0 | Z25: =+Y25-P25 -> 0 | AD25: 10005779 | AE25: ="FEBRERO"&AD25&"Inventario final" -> FEBRERO10005779Inventario final | AF25: =INDEX('[1]Detalle Costos'!$L$5:$L$158,MATCH(AE25,'[1]Detalle Costos'!$C$5:$C$158,0)) -> 1.86 | AG25: =IF(ISERROR(AF25),0,Q25/1000) -> 83.88 | AH25: =IFERROR(AF25*AG25,0)*1000 -> 156016.8 | AI25: =182*AG25 -> 15266.16 | AJ25: =$AJ$59/$AG$59*AG25 -> 3063.6219 | AK25: =$AK$59/$AG$59*AG25 -> 6936.1447 | AL25: =$AL$59/$AG$59*AG25 -> 5798.9767 | AM25: 0 | AN25: =$BC$50 -> 0 | AO25: =AH25+AI25+AJ25+AK25 -> 181282.73 | AP25: =IFERROR(AO25/AG25,0) -> 2161.2151 | AR25: 1200 | AS25: =AR25*AG25 -> 100656 | AT25: =AS25-AO25 -> -80626.727 | AU25: =IFERROR(AT25/AS25,0) -> -0.80101262
A26: =+A25+1 -> 19 | B26: 10005776 | C26: POTA NUCAS FR ABIERTAS 0.3-0.5 BL10 S20 | D26: 3620 | E26: 160 | F26: =20+180 -> 200 | G26: 40 | H26: 120 | I26: 380 | J26: 40 | N26: =+D26 -> 3620 | O26: =SUM(E26:L26) -> 940 | Q26: =+N26+O26-P26 -> 4560 | T26: =+Q26-S26 -> 4560 | Y26: =SUM(U26:W26) -> 0 | Z26: =+Y26-P26 -> 0 | AD26: 10005779 | AE26: ="FEBRERO"&AD26&"Inventario final" -> FEBRERO10005779Inventario final | AF26: =INDEX('[1]Detalle Costos'!$L$5:$L$158,MATCH(AE26,'[1]Detalle Costos'!$C$5:$C$158,0)) -> 1.86 | AG26: =IF(ISERROR(AF26),0,Q26/1000) -> 4.56 | AH26: =IFERROR(AF26*AG26,0)*1000 -> 8481.6 | AI26: =182*AG26 -> 829.92 | AJ26: =$AJ$59/$AG$59*AG26 -> 166.54883 | AK26: =$AK$59/$AG$59*AG26 -> 377.07224 | AL26: =$AL$59/$AG$59*AG26 -> 315.25195 | AM26: 0 | AN26: =$BC$50 -> 0 | AO26: =AH26+AI26+AJ26+AK26 -> 9855.1411 | AP26: =IFERROR(AO26/AG26,0) -> 2161.2151 | AR26: 1200 | AS26: =AR26*AG26 -> 5472 | AT26: =AS26-AO26 -> -4383.1411 | AU26: =IFERROR(AT26/AS26,0) -> -0.80101262
A27: =+A26+1 -> 20 | B27: 10005781 | C27: POTA NUCAS FR ABIERTAS 1-2 BL10 S20 | D27: 57080 | E27: 1400 | F27: =280+1540 -> 1820 | G27: =200+580 -> 780 | H27: 1020 | I27: 1240 | J27: 220 | N27: =+D27 -> 57080 | O27: =SUM(E27:L27) -> 6480 | Q27: =+N27+O27-P27 -> 63560 | T27: =+Q27-S27 -> 63560 | Y27: =SUM(U27:W27) -> 0 | Z27: =+Y27-P27 -> 0 | AD27: 10005779 | AE27: ="FEBRERO"&AD27&"Inventario final" -> FEBRERO10005779Inventario final | AF27: =INDEX('[1]Detalle Costos'!$L$5:$L$158,MATCH(AE27,'[1]Detalle Costos'!$C$5:$C$158,0)) -> 1.86 | AG27: =IF(ISERROR(AF27),0,Q27/1000) -> 63.56 | AH27: =IFERROR(AF27*AG27,0)*1000 -> 118221.6 | AI27: =182*AG27 -> 11567.92 | AJ27: =$AJ$59/$AG$59*AG27 -> 2321.457 | AK27: =$AK$59/$AG$59*AG27 -> 5255.8578 | AL27: =$AL$59/$AG$59*AG27 -> 4394.1698 | AM27: 0 | AN27: =$BC$50 -> 0 | AO27: =AH27+AI27+AJ27+AK27 -> 137366.83 | AP27: =IFERROR(AO27/AG27,0) -> 2161.2151 | AR27: 1200 | AS27: =AR27*AG27 -> 76272 | AT27: =AS27-AO27 -> -61094.835 | AU27: =IFERROR(AT27/AS27,0) -> -0.80101262
C28: POTA NUCAS FR <0.1 BL10 S20 | D28: 0 | E28: 40 | F28: 60 | H28: 160 | I28: 5220 | N28: =+D28 -> 0 | O28: =SUM(E28:L28) -> 5480 | Q28: =+N28+O28-P28 -> 5480 | T28: =+Q28-S28 -> 5480 | AD28: 10005781 | AE28: ="FEBRERO"&AD28&"Inventario final" -> FEBRERO10005781Inventario final | AF28: =INDEX('[1]Detalle Costos'!$L$5:$L$158,MATCH(AE28,'[1]Detalle Costos'!$C$5:$C$158,0)) -> 1.86 | AG28: =IF(ISERROR(AF28),0,Q28/1000) -> 5.48 | AH28: =IFERROR(AF28*AG28,0)*1000 -> 10192.8 | AI28: =182*AG28 -> 997.36 | AJ28: =$AJ$59/$AG$59*AG28 -> 200.15079 | AK28: =$AK$59/$AG$59*AG28 -> 453.14822 | AL28: =$AL$59/$AG$59*AG28 -> 378.85542 | AM28: 0 | AN28: =$BC$50 -> 0 | AO28: =AH28+AI28+AJ28+AK28 -> 11843.459 | AP28: =IFERROR(AO28/AG28,0) -> 2161.2151 | AR28: 1000 | AS28: =AR28*AG28 -> 5480 | AT28: =AS28-AO28 -> -6363.459 | AU28: =IFERROR(AT28/AS28,0) -> -1.1612151
A29: =+A27+1 -> 21 | B29: 10009386 | C29: VENTOSAS | D29: 36360 | E29: 140 | F29: 360 | G29: 100 | H29: 200 | I29: 200 | N29: =+D29 -> 36360 | O29: =SUM(E29:L29) -> 1000 | Q29: =+N29+O29-P29 -> 37360 | T29: =+Q29-S29 -> 37360 | Y29: =SUM(U29:W29) -> 0 | Z29: =+Y29-P29 -> 0 | AD29: 10009386 | AE29: ="FEBRERO"&AD29&"Inventario final" -> FEBRERO10009386Inventario final | AF29: 0 | AG29: =IF(ISERROR(AF29),0,Q29/1000) -> 37.36 | AH29: =IFERROR(AF29*AG29,0)*1000 -> 0 | AI29: =182*AG29 -> 6799.52 | AJ29: =$AJ$59/$AG$59*AG29 -> 1364.5317 | AK29: =$AK$59/$AG$59*AG29 -> 3089.3463 | AL29: =$AL$59/$AG$59*AG29 -> 2582.8537 | AM29: 0 | AN29: =$BC$50 -> 0 | AO29: =AH29+AI29+AJ29+AK29 -> 11253.398 | AP29: =IFERROR(AO29/AG29,0) -> 301.21515 | AR29: 1000 | AS29: =AR29*AG29 -> 37360 | AT29: =AS29-AO29 -> 26106.602 | AU29: =IFERROR(AT29/AS29,0) -> 0.69878485
A30: =+A29+1 -> 22 | B30: 10007567 | C30: POTA REJOS OR FR LIMPIOS S/COD BL10 S20 | D30: 107860 | E30: 1220 | F30: =60+1740 -> 1800 | G30: =260+700 -> 960 | H30: 1440 | I30: =380+960 -> 1340 | J30: 140 | N30: =+D30 -> 107860 | O30: =SUM(E30:L30) -> 6900 | P30: 26000 | Q30: =+N30+O30-P30 -> 88760 | T30: =+Q30-S30 -> 88760 | Y30: =SUM(U30:W30) -> 0 | Z30: =+Y30-P30 -> -26000 | AD30: 10007567 | AE30: ="FEBRERO"&AD30&"Inventario final" -> FEBRERO10007567Inventario final | AF30: =INDEX('[1]Detalle Costos'!$L$5:$L$158,MATCH(AE30,'[1]Detalle Costos'!$C$5:$C$158,0)) -> 1.7 | AG30: =IF(ISERROR(AF30),0,Q30/1000) -> 88.76 | AH30: =IFERROR(AF30*AG30,0)*1000 -> 150892 | AI30: =182*AG30 -> 16154.32 | AJ30: =$AJ$59/$AG$59*AG30 -> 3241.8584 | AK30: =$AK$59/$AG$59*AG30 -> 7339.6781 | AL30: =$AL$59/$AG$59*AG30 -> 6136.3516 | AM30: 0 | AN30: =$BC$50 -> 0 | AO30: =AH30+AI30+AJ30+AK30 -> 177627.86 | AP30: =IFERROR(AO30/AG30,0) -> 2001.2151 | AR30: 2700 | AS30: =AR30*AG30 -> 239652 | AT30: =AS30-AO30 -> 62024.144 | AU30: =IFERROR(AT30/AS30,0) -> 0.2588092
A31: =+A30+1 -> 23 | B31: 10009187 | C31: POTA REJOS FR C/B S/U S/V S/OR 0.3 - 0.5 | D31: 140 | F31: 100 | G31: =180+40 -> 220 | H31: 100 | I31: 500 | N31: =+D31 -> 140 | O31: =SUM(E31:L31) -> 920 | Q31: =+N31+O31-P31 -> 1060 | T31: =+Q31-S31 -> 1060 | Y31: =SUM(U31:W31) -> 0 | Z31: =+Y31-P31 -> 0 | AD31: 10007162 | AE31: ="FEBRERO"&AD31&"Inventario final" -> FEBRERO10007162Inventario final | AF31: =INDEX('[1]Detalle Costos'!$L$5:$L$158,MATCH(AE31,'[1]Detalle Costos'!$C$5:$C$158,0)) -> 1.72 | AG31: =IF(ISERROR(AF31),0,Q31/1000) -> 1.06 | AH31: =IFERROR(AF31*AG31,0)*1000 -> 1823.2 | AI31: =182*AG31 -> 192.92 | AJ31: =$AJ$59/$AG$59*AG31 -> 38.715298 | AK31: =$AK$59/$AG$59*AG31 -> 87.652758 | AL31: =$AL$59/$AG$59*AG31 -> 73.282252 | AM31: 0 | AN31: =$BC$50 -> 0 | AO31: =AH31+AI31+AJ31+AK31 -> 2142.4881 | AP31: =IFERROR(AO31/AG31,0) -> 2021.2151 | AR31: 2700 | AS31: =AR31*AG31 -> 2862 | AT31: =AS31-AO31 -> 719.51194 | AU31: =IFERROR(AT31/AS31,0) -> 0.2514018
A32: =+A31+1 -> 24 | B32: 10009777 | C32: POTA REJOS FR C/B S/U S/V S/OR 0.3 - 0.5 | D32: 220 | F32: =300+1240 -> 1540 | G32: =1420+380 -> 1800 | H32: 1920 | I32: =2000+1880 -> 3880 | J32: 3980 | N32: =+D32 -> 220 | O32: =SUM(E32:L32) -> 13120 | Q32: =+N32+O32-P32 -> 13340 | T32: =+Q32-S32 -> 13340 | Y32: =SUM(U32:W32) -> 0 | Z32: =+Y32-P32 -> 0 | AD32: 10007162 | AE32: ="FEBRERO"&AD32&"Inventario final" -> FEBRERO10007162Inventario final | AF32: =INDEX('[1]Detalle Costos'!$L$5:$L$158,MATCH(AE32,'[1]Detalle Costos'!$C$5:$C$158,0)) -> 1.72 | AG32: =IF(ISERROR(AF32),0,Q32/1000) -> 13.34 | AH32: =IFERROR(AF32*AG32,0)*1000 -> 22944.8 | AI32: =182*AG32 -> 2427.88 | AJ32: =$AJ$59/$AG$59*AG32 -> 487.22838 | AK32: =$AK$59/$AG$59*AG32 -> 1103.1017 | AL32: =$AL$59/$AG$59*AG32 -> 922.25023 | AM32: 0 | AN32: =$BC$50 -> 0 | AO32: =AH32+AI32+AJ32+AK32 -> 26963.01 | AP32: =IFERROR(AO32/AG32,0) -> 2021.2151 | AR32: 2700 | AS32: =AR32*AG32 -> 36018 | AT32: =AS32-AO32 -> 9054.9899 | AU32: =IFERROR(AT32/AS32,0) -> 0.2514018
A33: =+A31+1 -> 24 | B33: 10007161 | C33: POTA REJOS FR C/B S/U S/V S/OR 0.5-1 BL1 | D33: 11080 | E33: =620+0 -> 620 | F33: =220+400 -> 620 | G33: =40+280 -> 320 | H33: 720 | I33: 2000 | J33: 220 | N33: =+D33 -> 11080 | O33: =SUM(E33:L33) -> 4500 | Q33: =+N33+O33-P33 -> 15580 | T33: =+Q33-S33 -> 15580 | Y33: =SUM(U33:W33) -> 0 | Z33: =+Y33-P33 -> 0 | AD33: 10007162 | AE33: ="FEBRERO"&AD33&"Inventario final" -> FEBRERO10007162Inventario final | AF33: =INDEX('[1]Detalle Costos'!$L$5:$L$158,MATCH(AE33,'[1]Detalle Costos'!$C$5:$C$158,0)) -> 1.72 | AG33: =IF(ISERROR(AF33),0,Q33/1000) -> 15.58 | AH33: =IFERROR(AF33*AG33,0)*1000 -> 26797.6 | AI33: =182*AG33 -> 2835.56 | AJ33: =$AJ$59/$AG$59*AG33 -> 569.04184 | AK33: =$AK$59/$AG$59*AG33 -> 1288.3302 | AL33: =$AL$59/$AG$59*AG33 -> 1077.1108 | AM33: 0 | AN33: =$BC$50 -> 0 | AO33: =AH33+AI33+AJ33+AK33 -> 31490.532 | AP33: =IFERROR(AO33/AG33,0) -> 2021.2151 | AR33: 2700 | AS33: =AR33*AG33 -> 42066 | AT33: =AS33-AO33 -> 10575.468 | AU33: =IFERROR(AT33/AS33,0) -> 0.2514018
A34: =+A33+1 -> 25 | B34: 10009186 | C34: POTA REJOS FR S-S/POR C/UV 0.1 - 0.3 BL1 | D34: 740 | F34: =140+660 -> 800 | G34: =300+300 -> 600 | H34: 800 | I34: =780+500 -> 1280 | J34: 720 | N34: =+D34 -> 740 | O34: =SUM(E34:L34) -> 4200 | Q34: =+N34+O34-P34 -> 4940 | T34: =+Q34-S34 -> 4940 | Y34: =SUM(U34:W34) -> 0 | Z34: =+Y34-P34 -> 0 | AD34: 10007162 | AE34: ="FEBRERO"&AD34&"Inventario final" -> FEBRERO10007162Inventario final | AF34: =INDEX('[1]Detalle Costos'!$L$5:$L$158,MATCH(AE34,'[1]Detalle Costos'!$C$5:$C$158,0)) -> 1.72 | AG34: =IF(ISERROR(AF34),0,Q34/1000) -> 4.94 | AH34: =IFERROR(AF34*AG34,0)*1000 -> 8496.8 | AI34: =182*AG34 -> 899.08 | AJ34: =$AJ$59/$AG$59*AG34 -> 180.4279 | AK34: =$AK$59/$AG$59*AG34 -> 408.49493 | AL34: =$AL$59/$AG$59*AG34 -> 341.52295 | AM34: 0 | AN34: =$BC$50 -> 0 | AO34: =AH34+AI34+AJ34+AK34 -> 9984.8028 | AP34: =IFERROR(AO34/AG34,0) -> 2021.2151 | AR34: 2700 | AS34: =AR34*AG34 -> 13338 | AT34: =AS34-AO34 -> 3353.1972 | AU34: =IFERROR(AT34/AS34,0) -> 0.2514018
A35: =+A34+1 -> 26 | B35: 10007162 | C35: POTA REJOS FR C/B S/U S/V S/OR 1-2 BL10 | D35: 267680 | E35: 3660 | F35: =800+2720 -> 3520 | G35: =500+1000 -> 1500 | H35: 2080 | I35: 3620 | J35: 220 | N35: =+D35 -> 267680 | O35: =SUM(E35:L35) -> 14600 | Q35: =+N35+O35-P35 -> 282280 | T35: =+Q35-S35 -> 282280 | Y35: =SUM(U35:W35) -> 0 | Z35: =+Y35-P35 -> 0 | AD35: 10007162 | AE35: ="FEBRERO"&AD35&"Inventario final" -> FEBRERO10007162Inventario final | AF35: =INDEX('[1]Detalle Costos'!$L$5:$L$158,MATCH(AE35,'[1]Detalle Costos'!$C$5:$C$158,0)) -> 1.72 | AG35: =IF(ISERROR(AF35),0,Q35/1000) -> 282.28 | AH35: =IFERROR(AF35*AG35,0)*1000 -> 485521.6 | AI35: =182*AG35 -> 51374.96 | AJ35: =$AJ$59/$AG$59*AG35 -> 10309.957 | AK35: =$AK$59/$AG$59*AG35 -> 23342.095 | AL35: =$AL$59/$AG$59*AG35 -> 19515.202 | AM35: 0 | AN35: =$BC$50 -> 0 | AO35: =AH35+AI35+AJ35+AK35 -> 570548.61 | AP35: =IFERROR(AO35/AG35,0) -> 2021.2151 | AR35: 2700 | AS35: =AR35*AG35 -> 762156 | AT35: =AS35-AO35 -> 191607.39 | AU35: =IFERROR(AT35/AS35,0) -> 0.2514018
A36: =+A35+1 -> 27 | B36: 10009658 | C36: POTA REJOS FR 1 UP | D36: 1960 | N36: =+D36 -> 1960 | O36: =SUM(E36:L36) -> 0 | Q36: =+N36+O36-P36 -> 1960 | T36: =+Q36-S36 -> 1960 | Y36: =SUM(U36:W36) -> 0 | Z36: =+Y36-P36 -> 0 | AD36: 10007162 | AE36: ="FEBRERO"&AD36&"Inventario final" -> FEBRERO10007162Inventario final | AF36: =INDEX('[1]Detalle Costos'!$L$5:$L$158,MATCH(AE36,'[1]Detalle Costos'!$C$5:$C$158,0)) -> 1.72 | AG36: =IF(ISERROR(AF36),0,Q36/1000) -> 1.96 | AH36: =IFERROR(AF36*AG36,0)*1000 -> 3371.2 | AI36: =182*AG36 -> 356.72 | AJ36: =$AJ$59/$AG$59*AG36 -> 71.586778 | AK36: =$AK$59/$AG$59*AG36 -> 162.07491 | AL36: =$AL$59/$AG$59*AG36 -> 135.50303 | AM36: 0 | AN36: =$BC$50 -> 0 | AO36: =AH36+AI36+AJ36+AK36 -> 3961.5817 | AP36: =IFERROR(AO36/AG36,0) -> 2021.2151 | AR36: 2700 | AS36: =AR36*AG36 -> 5292 | AT36: =AS36-AO36 -> 1330.4183 | AU36: =IFERROR(AT36/AS36,0) -> 0.2514018
A37: =+A36+1 -> 28 | B37: 10009639 | C37: POTA REJOS FR 2 UP | D37: 44660 | E37: 1780 | F37: =460+1520 -> 1980 | G37: =380+500 -> 880 | H37: 1220 | I37: =140+1840 -> 1980 | J37: 140 | N37: =+D37 -> 44660 | O37: =SUM(E37:L37) -> 7980 | Q37: =+N37+O37-P37 -> 52640 | T37: =+Q37-S37 -> 52640 | Y37: =SUM(U37:W37) -> 0 | Z37: =+Y37-P37 -> 0 | AD37: 10007162 | AE37: ="FEBRERO"&AD37&"Inventario final" -> FEBRERO10007162Inventario final | AF37: =INDEX('[1]Detalle Costos'!$L$5:$L$158,MATCH(AE37,'[1]Detalle Costos'!$C$5:$C$158,0)) -> 1.72 | AG37: =IF(ISERROR(AF37),0,Q37/1000) -> 52.64 | AH37: =IFERROR(AF37*AG37,0)*1000 -> 90540.8 | AI37: =182*AG37 -> 9580.48 | AJ37: =$AJ$59/$AG$59*AG37 -> 1922.6163 | AK37: =$AK$59/$AG$59*AG37 -> 4352.869 | AL37: =$AL$59/$AG$59*AG37 -> 3639.2243 | AM37: 0 | AN37: =$BC$50 -> 0 | AO37: =AH37+AI37+AJ37+AK37 -> 106396.77 | AP37: =IFERROR(AO37/AG37,0) -> 2021.2151 | AR37: 2700 | AS37: =AR37*AG37 -> 142128 | AT37: =AS37-AO37 -> 35731.235 | AU37: =IFERROR(AT37/AS37,0) -> 0.2514018
C38: POTA REJOS FR S-S/POR C/UV 0.1 - 0.3 BL1 | D38: 0 | E38: 300 | F38: 160 | N38: =+D38 -> 0 | O38: =SUM(E38:L38) -> 460 | Q38: =+N38+O38-P38 -> 460 | T38: =+Q38-S38 -> 460 | AD38: 10009639 | AE38: ="FEBRERO"&AD38&"Inventario final" -> FEBRERO10009639Inventario final | AF38: =INDEX('[1]Detalle Costos'!$L$5:$L$158,MATCH(AE38,'[1]Detalle Costos'!$C$5:$C$158,0)) -> 1.75 | AG38: =IF(ISERROR(AF38),0,Q38/1000) -> 0.46 | AH38: =IFERROR(AF38*AG38,0)*1000 -> 805 | AI38: =182*AG38 -> 83.72 | AJ38: =$AJ$59/$AG$59*AG38 -> 16.800979 | AK38: =$AK$59/$AG$59*AG38 -> 38.037989 | AL38: =$AL$59/$AG$59*AG38 -> 31.801732 | AM38: 0 | AN38: =$BC$50 -> 0 | AO38: =AH38+AI38+AJ38+AK38 -> 943.55897 | AP38: =IFERROR(AO38/AG38,0) -> 2051.2151 | AR38: 2700 | AS38: =AR38*AG38 -> 1242 | AT38: =AS38-AO38 -> 298.44103 | AU38: =IFERROR(AT38/AS38,0) -> 0.24029069
C39: POTA REJOS FR C/B S/U S/V S/OR 0.3 - 0.5 | D39: 0 | E39: 1060 | F39: 600 | G39: 280 | N39: =+D39 -> 0 | O39: =SUM(E39:L39) -> 1940 | Q39: =+N39+O39-P39 -> 1940 | T39: =+Q39-S39 -> 1940 | AD39: 10009639 | AE39: ="FEBRERO"&AD39&"Inventario final" -> FEBRERO10009639Inventario final | AF39: =INDEX('[1]Detalle Costos'!$L$5:$L$158,MATCH(AE39,'[1]Detalle Costos'!$C$5:$C$158,0)) -> 1.75 | AG39: =IF(ISERROR(AF39),0,Q39/1000) -> 1.94 | AH39: =IFERROR(AF39*AG39,0)*1000 -> 3395 | AI39: =182*AG39 -> 353.08 | AJ39: =$AJ$59/$AG$59*AG39 -> 70.856301 | AK39: =$AK$59/$AG$59*AG39 -> 160.42109 | AL39: =$AL$59/$AG$59*AG39 -> 134.12035 | AM39: 0 | AN39: =$BC$50 -> 0 | AO39: =AH39+AI39+AJ39+AK39 -> 3979.3574 | AP39: =IFERROR(AO39/AG39,0) -> 2051.2151 | AR39: 2700 | AS39: =AR39*AG39 -> 5238 | AT39: =AS39-AO39 -> 1258.6426 | AU39: =IFERROR(AT39/AS39,0) -> 0.24029069
C40: POTA REJOS OR < 60 FR LIMPIOS S/COD BL10 S20 | D40: 0 | I40: 2300 | N40: =+D40 -> 0 | O40: =SUM(E40:L40) -> 2300 | Q40: =+N40+O40-P40 -> 2300 | T40: =+Q40-S40 -> 2300 | AD40: 10009639 | AE40: ="FEBRERO"&AD40&"Inventario final" -> FEBRERO10009639Inventario final | AF40: =INDEX('[1]Detalle Costos'!$L$5:$L$158,MATCH(AE40,'[1]Detalle Costos'!$C$5:$C$158,0)) -> 1.75 | AG40: =IF(ISERROR(AF40),0,Q40/1000) -> 2.3 | AH40: =IFERROR(AF40*AG40,0)*1000 -> 4025 | AI40: =182*AG40 -> 418.6 | AJ40: =$AJ$59/$AG$59*AG40 -> 84.004893 | AK40: =$AK$59/$AG$59*AG40 -> 190.18995 | AL40: =$AL$59/$AG$59*AG40 -> 159.00866 | AM40: 0 | AN40: =$BC$50 -> 0 | AO40: =AH40+AI40+AJ40+AK40 -> 4717.7948 | AP40: =IFERROR(AO40/AG40,0) -> 2051.2151 | AR40: 3950 | AS40: =AR40*AG40 -> 9085 | AT40: =AS40-AO40 -> 4367.2052 | AU40: =IFERROR(AT40/AS40,0) -> 0.48070503
A41: =+A37+1 -> 29 | B41: 10009239 | C41: POTA FILETE PRE COCIDO S/M S/T C/P S/COD | D41: 194440 | E41: 1620 | F41: =860+2360 -> 3220 | G41: =2040+2340 -> 4380 | H41: 960 | J41: 2040 | N41: =+D41 -> 194440 | O41: =SUM(E41:L41) -> 12220 | P41: 27000 | Q41: =+N41+O41-P41 -> 179660 | T41: =+Q41-S41 -> 179660 | Y41: =SUM(U41:W41) -> 0 | Z41: =+Y41-P41 -> -27000 | AD41: 10009239 | AE41: ="FEBRERO"&AD41&"Inventario final" -> FEBRERO10009239Inventario final | AF41: =INDEX('[1]Detalle Costos'!$L$5:$L$158,MATCH(AE41,'[1]Detalle Costos'!$C$5:$C$158,0)) -> 2.11 | AG41: =IF(ISERROR(AF41),0,Q41/1000) -> 179.66 | AH41: =IFERROR(AF41*AG41,0)*1000 -> 379082.6 | AI41: =182*AG41 -> 32698.12 | AJ41: =$AJ$59/$AG$59*AG41 -> 6561.8778 | AK41: =$AK$59/$AG$59*AG41 -> 14856.316 | AL41: =$AL$59/$AG$59*AG41 -> 12420.65 | AM41: 0 | AN41: =$BC$50 -> 0 | AO41: =AH41+AI41+AJ41+AK41 -> 433198.91 | AP41: =IFERROR(AO41/AG41,0) -> 2411.2151 | AR41: 3950 | AS41: =AR41*AG41 -> 709657 | AT41: =AS41-AO41 -> 276458.09 | AU41: =IFERROR(AT41/AS41,0) -> 0.38956579
A42: =+A41+1 -> 30 | B42: 10009251 | C42: POTA FILETE PRE COCIDO S/M S/T 0.6 - 1.0 | D42: 21620 | E42: 380 | F42: =200+440 -> 640 | G42: =480+440 -> 920 | H42: 320 | J42: 160 | N42: =+D42 -> 21620 | O42: =SUM(E42:L42) -> 2420 | Q42: =+N42+O42-P42 -> 24040 | T42: =+Q42-S42 -> 24040 | Y42: =SUM(U42:W42) -> 0 | Z42: =+Y42-P42 -> 0 | AD42: 10009239 | AE42: ="FEBRERO"&AD42&"Inventario final" -> FEBRERO10009239Inventario final | AF42: =INDEX('[1]Detalle Costos'!$L$5:$L$158,MATCH(AE42,'[1]Detalle Costos'!$C$5:$C$158,0)) -> 2.11 | AG42: =IF(ISERROR(AF42),0,Q42/1000) -> 24.04 | AH42: =IFERROR(AF42*AG42,0)*1000 -> 50724.4 | AI42: =182*AG42 -> 4375.28 | AJ42: =$AJ$59/$AG$59*AG42 -> 878.03375 | AK42: =$AK$59/$AG$59*AG42 -> 1987.8984 | AL42: =$AL$59/$AG$59*AG42 -> 1661.9862 | AM42: 0 | AN42: =$BC$50 -> 0 | AO42: =AH42+AI42+AJ42+AK42 -> 57965.612 | AP42: =IFERROR(AO42/AG42,0) -> 2411.2151 | AR42: 3950 | AS42: =AR42*AG42 -> 94958 | AT42: =AS42-AO42 -> 36992.388 | AU42: =IFERROR(AT42/AS42,0) -> 0.38956579
A43: =+A42+1 -> 31 | B43: 10009241 | C43: POTA ALAS PRE COC S/COD BL10 S20 | D43: 260 | N43: =+D43 -> 260 | O43: =SUM(E43:L43) -> 0 | Q43: =+N43+O43-P43 -> 260 | T43: =+Q43-S43 -> 260 | Y43: =SUM(U43:W43) -> 0 | Z43: =+Y43-P43 -> 0 | AD43: 10007050 | AE43: ="FEBRERO"&AD43&"Inventario final" -> FEBRERO10007050Inventario final | AF43: =INDEX('[1]Detalle Costos'!$L$5:$L$158,MATCH(AE43,'[1]Detalle Costos'!$C$5:$C$158,0)) -> 1.31 | AG43: =IF(ISERROR(AF43),0,Q43/1000) -> 0.26 | AH43: =IFERROR(AF43*AG43,0)*1000 -> 340.6 | AI43: =182*AG43 -> 47.32 | AJ43: =$AJ$59/$AG$59*AG43 -> 9.4962053 | AK43: =$AK$59/$AG$59*AG43 -> 21.499733 | AL43: =$AL$59/$AG$59*AG43 -> 17.974892 | AM43: 0 | AN43: =$BC$50 -> 0 | AO43: =AH43+AI43+AJ43+AK43 -> 418.91594 | AP43: =IFERROR(AO43/AG43,0) -> 1611.2151 | AR43: 3950 | AS43: =AR43*AG43 -> 1027 | AT43: =AS43-AO43 -> 608.08406 | AU43: =IFERROR(AT43/AS43,0) -> 0.59209743
A44: =+A43+1 -> 32 | B44: 10007050 | C44: PPTA RECORTES PRECOCIDA B10 S20 | D44: 49620 | F44: =400+400 -> 800 | G44: =40+2140 -> 2180 | H44: 200 | J44: 720 | N44: =+D44 -> 49620 | O44: =SUM(E44:L44) -> 3900 | P44: 26120 | Q44: =+N44+O44-P44 -> 27400 | T44: =+Q44-S44 -> 27400 | Y44: =SUM(U44:W44) -> 0 | Z44: =+Y44-P44 -> -26120 | AD44: 10007050 | AE44: ="FEBRERO"&AD44&"Inventario final" -> FEBRERO10007050Inventario final | AF44: =INDEX('[1]Detalle Costos'!$L$5:$L$158,MATCH(AE44,'[1]Detalle Costos'!$C$5:$C$158,0)) -> 1.31 | AG44: =IF(ISERROR(AF44),0,Q44/1000) -> 27.4 | AH44: =IFERROR(AF44*AG44,0)*1000 -> 35894 | AI44: =182*AG44 -> 4986.8 | AJ44: =$AJ$59/$AG$59*AG44 -> 1000.7539 | AK44: =$AK$59/$AG$59*AG44 -> 2265.7411 | AL44: =$AL$59/$AG$59*AG44 -> 1894.2771 | AM44: 0 | AN44: =$BC$50 -> 0 | AO44: =AH44+AI44+AJ44+AK44 -> 44147.295 | AP44: =IFERROR(AO44/AG44,0) -> 1611.2151 | AR44: 2000 | AS44: =AR44*AG44 -> 54800 | AT44: =AS44-AO44 -> 10652.705 | AU44: =IFERROR(AT44/AS44,0) -> 0.19439243
A45: =+A44+1 -> 33 | C45: FILETE FR REPROCESO x 10 | D45: 9450 | N45: =+D45 -> 9450 | O45: =SUM(E45:L45) -> 0 | P45: 9450 | Q45: =+N45+O45-P45 -> 0 | T45: =+Q45-S45 -> 0 | Y45: =SUM(U45:W45) -> 0 | Z45: =+Y45-P45 -> -9450 | AE45: ="FEBRERO"&AD45&"Inventario final" -> FEBREROInventario final | AF45: =INDEX('[1]Detalle Costos'!$L$5:$L$158,MATCH(AE45,'[1]Detalle Costos'!$C$5:$C$158,0)) -> #N/A | AG45: =IF(ISERROR(AF45),0,Q45/1000) -> 0 | AH45: =IFERROR(AF45*AG45,0)*1000 -> 0 | AI45: =182*AG45 -> 0 | AJ45: =$AJ$59/$AG$59*AG45 -> 0 | AK45: =$AK$59/$AG$59*AG45 -> 0 | AL45: =$AL$59/$AG$59*AG45 -> 0 | AM45: 0 | AN45: =$BC$50 -> 0 | AO45: =AH45+AI45+AJ45+AK45 -> 0 | AP45: =IFERROR(AO45/AG45,0) -> 0 | AS45: =AR45*AG45 -> 0 | AT45: =AS45-AO45 -> 0 | AU45: =IFERROR(AT45/AS45,0) -> 0
A46: =+A45+1 -> 34 | C46: FILETE FR S/M S/T C/M 1-2 REPROCESO x 10 | D46: 3460 | N46: =+D46 -> 3460 | O46: =SUM(E46:L46) -> 0 | P46: 3460 | Q46: =+N46+O46-P46 -> 0 | T46: =+Q46-S46 -> 0 | Y46: =SUM(U46:W46) -> 0 | Z46: =+Y46-P46 -> -3460 | AE46: ="FEBRERO"&AD46&"Inventario final" -> FEBREROInventario final | AF46: =INDEX('[1]Detalle Costos'!$L$5:$L$158,MATCH(AE46,'[1]Detalle Costos'!$C$5:$C$158,0)) -> #N/A | AG46: =IF(ISERROR(AF46),0,Q46/1000) -> 0 | AH46: =IFERROR(AF46*AG46,0)*1000 -> 0 | AI46: =182*AG46 -> 0 | AJ46: =$AJ$59/$AG$59*AG46 -> 0 | AK46: =$AK$59/$AG$59*AG46 -> 0 | AL46: =$AL$59/$AG$59*AG46 -> 0 | AM46: 0 | AN46: =$BC$50 -> 0 | AO46: =AH46+AI46+AJ46+AK46 -> 0 | AP46: =IFERROR(AO46/AG46,0) -> 0 | AS46: =AR46*AG46 -> 0 | AT46: =AS46-AO46 -> 0 | AU46: =IFERROR(AT46/AS46,0) -> 0
A47: =+A46+1 -> 35 | C47: RECORTE MEMBRANA FRESCA REPROCESO BL 10 | D47: 2380 | N47: =+D47 -> 2380 | O47: =SUM(E47:L47) -> 0 | P47: 2380 | Q47: =+N47+O47-P47 -> 0 | T47: =+Q47-S47 -> 0 | Y47: =SUM(U47:W47) -> 0 | Z47: =+Y47-P47 -> -2380 | AE47: ="FEBRERO"&AD47&"Inventario final" -> FEBREROInventario final | AF47: =INDEX('[1]Detalle Costos'!$L$5:$L$158,MATCH(AE47,'[1]Detalle Costos'!$C$5:$C$158,0)) -> #N/A | AG47: =IF(ISERROR(AF47),0,Q47/1000) -> 0 | AH47: =IFERROR(AF47*AG47,0)*1000 -> 0 | AI47: =182*AG47 -> 0 | AJ47: =$AJ$59/$AG$59*AG47 -> 0 | AK47: =$AK$59/$AG$59*AG47 -> 0 | AL47: =$AL$59/$AG$59*AG47 -> 0 | AM47: 0 | AN47: =$BC$50 -> 0 | AO47: =AH47+AI47+AJ47+AK47 -> 0 | AP47: =IFERROR(AO47/AG47,0) -> 0 | AS47: =AR47*AG47 -> 0 | AT47: =AS47-AO47 -> 0 | AU47: =IFERROR(AT47/AS47,0) -> 0
A48: =+A47+1 -> 36 | C48: RECORTE TELILLA FRESCA REPROCESO BL 10 | D48: 2200 | N48: =+D48 -> 2200 | O48: =SUM(E48:L48) -> 0 | P48: 2200 | Q48: =+N48+O48-P48 -> 0 | T48: =+Q48-S48 -> 0 | Y48: =SUM(U48:W48) -> 0 | Z48: =+Y48-P48 -> -2200 | AE48: ="FEBRERO"&AD48&"Inventario final" -> FEBREROInventario final | AF48: =INDEX('[1]Detalle Costos'!$L$5:$L$158,MATCH(AE48,'[1]Detalle Costos'!$C$5:$C$158,0)) -> #N/A | AG48: =IF(ISERROR(AF48),0,Q48/1000) -> 0 | AH48: =IFERROR(AF48*AG48,0)*1000 -> 0 | AI48: =182*AG48 -> 0 | AJ48: =$AJ$59/$AG$59*AG48 -> 0 | AK48: =$AK$59/$AG$59*AG48 -> 0 | AL48: =$AL$59/$AG$59*AG48 -> 0 | AM48: 0 | AN48: =$BC$50 -> 0 | AO48: =AH48+AI48+AJ48+AK48 -> 0 | AP48: =IFERROR(AO48/AG48,0) -> 0 | AS48: =AR48*AG48 -> 0 | AT48: =AS48-AO48 -> 0 | AU48: =IFERROR(AT48/AS48,0) -> 0
A49: =+A48+1 -> 37 | B49: 10009337 | C49: POTA RECORTE COCIDO (M) x 15 | D49: 21210 | F49: 345 | G49: 1230 | H49: 180 | J49: 300 | N49: =+D49 -> 21210 | O49: =SUM(E49:L49) -> 2055 | Q49: =+N49+O49-P49 -> 23265 | R49: 52320 | T49: =+Q49-S49 -> 23265 | Y49: =SUM(U49:W49) -> 0 | Z49: =+Y49-P49 -> 0 | AD49: 10009332 | AE49: ="FEBRERO"&AD49&"Inventario final" -> FEBRERO10009332Inventario final | AF49: =INDEX('[1]Detalle Costos'!$L$5:$L$158,MATCH(AE49,'[1]Detalle Costos'!$C$5:$C$158,0)) -> 1.53 | AG49: =IF(ISERROR(AF49),0,Q49/1000) -> 23.265 | AH49: =IFERROR(AF49*AG49,0)*1000 -> 35595.45 | AI49: =182*AG49 -> 4234.23 | AJ49: =$AJ$59/$AG$59*AG49 -> 849.72775 | AK49: =$AK$59/$AG$59*AG49 -> 1923.8127 | AL49: =$AL$59/$AG$59*AG49 -> 1608.4072 | AM49: 0 | AN49: =$BC$50 -> 0 | AO49: =AH49+AI49+AJ49+AK49 -> 42603.22 | AP49: =IFERROR(AO49/AG49,0) -> 1831.2151 | AR49: 2000 | AS49: =AR49*AG49 -> 46530 | AT49: =AS49-AO49 -> 3926.7796 | AU49: =IFERROR(AT49/AS49,0) -> 0.084392426
A50: =+A49+1 -> 38 | B50: 10009332 | C50: POTA RECORTE COCIDO (T) X 15 | D50: 39360 | F50: 345 | G50: 1080 | H50: 180 | J50: 225 | N50: =+D50 -> 39360 | O50: =SUM(E50:L50) -> 1830 | P50: 900 | Q50: =+N50+O50-P50 -> 40290 | T50: =+Q50-S50 -> 40290 | Y50: =SUM(U50:W50) -> 0 | Z50: =+Y50-P50 -> -900 | AD50: 10009332 | AE50: ="FEBRERO"&AD50&"Inventario final" -> FEBRERO10009332Inventario final | AF50: =INDEX('[1]Detalle Costos'!$L$5:$L$158,MATCH(AE50,'[1]Detalle Costos'!$C$5:$C$158,0)) -> 1.53 | AG50: =IF(ISERROR(AF50),0,Q50/1000) -> 40.29 | AH50: =IFERROR(AF50*AG50,0)*1000 -> 61643.7 | AI50: =182*AG50 -> 7332.78 | AJ50: =$AJ$59/$AG$59*AG50 -> 1471.5466 | AK50: =$AK$59/$AG$59*AG50 -> 3331.6317 | AL50: =$AL$59/$AG$59*AG50 -> 2785.4169 | AM50: 0 | AN50: =$BC$50 -> 0 | AO50: =AH50+AI50+AJ50+AK50 -> 73779.658 | AP50: =IFERROR(AO50/AG50,0) -> 1831.2151 | AR50: 2000 | AS50: =AR50*AG50 -> 80580 | AT50: =AS50-AO50 -> 6800.3417 | AU50: =IFERROR(AT50/AS50,0) -> 0.084392426
C51: POTA RECORTE FRESCO POR REPROCESO | D51: 4920 | N51: =+D51 -> 4920 | O51: =SUM(E51:L51) -> 0 | P51: 4920 | Q51: =+N51+O51-P51 -> 0 | T51: =+Q51-S51 -> 0 | AE51: ="FEBRERO"&AD51&"Inventario final" -> FEBREROInventario final | AF51: =INDEX('[1]Detalle Costos'!$L$5:$L$158,MATCH(AE51,'[1]Detalle Costos'!$C$5:$C$158,0)) -> #N/A | AG51: =IF(ISERROR(AF51),0,Q51/1000) -> 0 | AH51: =IFERROR(AF51*AG51,0)*1000 -> 0 | AI51: =182*AG51 -> 0 | AJ51: =$AJ$59/$AG$59*AG51 -> 0 | AK51: =$AK$59/$AG$59*AG51 -> 0 | AL51: =$AL$59/$AG$59*AG51 -> 0 | AM51: 0 | AN51: =$BC$50 -> 0 | AO51: =AH51+AI51+AJ51+AK51 -> 0 | AP51: =IFERROR(AO51/AG51,0) -> 0 | AS51: =AR51*AG51 -> 0 | AT51: =AS51-AO51 -> 0 | AU51: =IFERROR(AT51/AS51,0) -> 0
A52: =+A50+1 -> 39 | C52: TUBO ALETA 0.5-1.0 | D52: 20 | E52: 140 | G52: 220 | N52: =+D52 -> 20 | O52: =SUM(E52:L52) -> 360 | Q52: =+N52+O52-P52 -> 380 | T52: =+Q52-S52 -> 380 | Y52: =SUM(U52:W52) -> 0 | Z52: =+Y52-P52 -> 0 | AE52: ="FEBRERO"&AD52&"Inventario final" -> FEBREROInventario final | AF52: =INDEX('[1]Detalle Costos'!$L$5:$L$158,MATCH(AE52,'[1]Detalle Costos'!$C$5:$C$158,0)) -> #N/A | AG52: =IF(ISERROR(AF52),0,Q52/1000) -> 0 | AH52: =IFERROR(AF52*AG52,0)*1000 -> 0 | AI52: =182*AG52 -> 0 | AJ52: =$AJ$59/$AG$59*AG52 -> 0 | AK52: =$AK$59/$AG$59*AG52 -> 0 | AL52: =$AL$59/$AG$59*AG52 -> 0 | AM52: 0 | AN52: =$BC$50 -> 0 | AO52: =AH52+AI52+AJ52+AK52 -> 0 | AP52: =IFERROR(AO52/AG52,0) -> 0 | AS52: =AR52*AG52 -> 0 | AT52: =AS52-AO52 -> 0 | AU52: =IFERROR(AT52/AS52,0) -> 0
A53: =+A52+1 -> 40 | C53: TUBO ALETA 1.0-1.5 | D53: 2060 | E53: 1260 | F53: 380 | G53: =500+240 -> 740 | H53: 20 | I53: 80 | N53: =+D53 -> 2060 | O53: =SUM(E53:L53) -> 2480 | Q53: =+N53+O53-P53 -> 4540 | T53: =+Q53-S53 -> 4540 | Y53: =SUM(U53:W53) -> 0 | Z53: =+Y53-P53 -> 0 | AE53: ="FEBRERO"&AD53&"Inventario final" -> FEBREROInventario final | AF53: =INDEX('[1]Detalle Costos'!$L$5:$L$158,MATCH(AE53,'[1]Detalle Costos'!$C$5:$C$158,0)) -> #N/A | AG53: =IF(ISERROR(AF53),0,Q53/1000) -> 0 | AH53: =IFERROR(AF53*AG53,0)*1000 -> 0 | AI53: =182*AG53 -> 0 | AJ53: =$AJ$59/$AG$59*AG53 -> 0 | AK53: =$AK$59/$AG$59*AG53 -> 0 | AL53: =$AL$59/$AG$59*AG53 -> 0 | AM53: 0 | AN53: =$BC$50 -> 0 | AO53: =AH53+AI53+AJ53+AK53 -> 0 | AP53: =IFERROR(AO53/AG53,0) -> 0 | AS53: =AR53*AG53 -> 0 | AT53: =AS53-AO53 -> 0 | AU53: =IFERROR(AT53/AS53,0) -> 0
A54: =+A53+1 -> 41 | C54: LANGOSTINO COLA PVD | D54: 51.175 | N54: =+D54 -> 51.175 | O54: =SUM(E54:L54) -> 0 | Q54: =+N54+O54-P54 -> 51.175 | T54: =+Q54-S54 -> 51.175 | Y54: =SUM(U54:W54) -> 0 | Z54: =+Y54-P54 -> 0 | AE54: ="FEBRERO"&AD54&"Inventario final" -> FEBREROInventario final | AF54: =INDEX('[1]Detalle Costos'!$L$5:$L$158,MATCH(AE54,'[1]Detalle Costos'!$C$5:$C$158,0)) -> #N/A | AG54: =IF(ISERROR(AF54),0,Q54/1000) -> 0 | AH54: =IFERROR(AF54*AG54,0)*1000 -> 0 | AI54: =182*AG54 -> 0 | AJ54: =$AJ$59/$AG$59*AG54 -> 0 | AK54: =$AK$59/$AG$59*AG54 -> 0 | AL54: =$AL$59/$AG$59*AG54 -> 0 | AM54: 0 | AN54: =$BC$50 -> 0 | AO54: =AH54+AI54+AJ54+AK54 -> 0 | AP54: =IFERROR(AO54/AG54,0) -> 0 | AS54: =AR54*AG54 -> 0 | AT54: =AS54-AO54 -> 0 | AU54: =IFERROR(AT54/AS54,0) -> 0
A55: =+A54+1 -> 42 | C55: CONCHA ABANICO T/SOLO | D55: 13.775 | N55: =+D55 -> 13.775 | O55: =SUM(E55:L55) -> 0 | Q55: =+N55+O55-P55 -> 13.775 | T55: =+Q55-S55 -> 13.775 | Y55: =SUM(U55:W55) -> 0 | Z55: =+Y55-P55 -> 0 | AE55: ="FEBRERO"&AD55&"Inventario final" -> FEBREROInventario final | AF55: =INDEX('[1]Detalle Costos'!$L$5:$L$158,MATCH(AE55,'[1]Detalle Costos'!$C$5:$C$158,0)) -> #N/A | AG55: =IF(ISERROR(AF55),0,Q55/1000) -> 0 | AH55: =IFERROR(AF55*AG55,0)*1000 -> 0 | AI55: =182*AG55 -> 0 | AJ55: =$AJ$59/$AG$59*AG55 -> 0 | AK55: =$AK$59/$AG$59*AG55 -> 0 | AL55: =$AL$59/$AG$59*AG55 -> 0 | AM55: 0 | AN55: =$BC$50 -> 0 | AO55: =AH55+AI55+AJ55+AK55 -> 0 | AP55: =IFERROR(AO55/AG55,0) -> 0 | AS55: =AR55*AG55 -> 0 | AT55: =AS55-AO55 -> 0 | AU55: =IFERROR(AT55/AS55,0) -> 0
A56: =+A55+1 -> 43 | C56: CABALLA ENTERA FR S/COD | D56: 23.85 | N56: =+D56 -> 23.85 | O56: =SUM(E56:L56) -> 0 | Q56: =+N56+O56-P56 -> 23.85 | T56: =+Q56-S56 -> 23.85 | Y56: =SUM(U56:W56) -> 0 | Z56: =+Y56-P56 -> 0 | AE56: ="FEBRERO"&AD56&"Inventario final" -> FEBREROInventario final | AF56: =INDEX('[1]Detalle Costos'!$L$5:$L$158,MATCH(AE56,'[1]Detalle Costos'!$C$5:$C$158,0)) -> #N/A | AG56: =IF(ISERROR(AF56),0,Q56/1000) -> 0 | AH56: =IFERROR(AF56*AG56,0)*1000 -> 0 | AI56: =182*AG56 -> 0 | AJ56: =$AJ$59/$AG$59*AG56 -> 0 | AK56: =$AK$59/$AG$59*AG56 -> 0 | AL56: =$AL$59/$AG$59*AG56 -> 0 | AM56: 0 | AN56: =$BC$50 -> 0 | AO56: =AH56+AI56+AJ56+AK56 -> 0 | AP56: =IFERROR(AO56/AG56,0) -> 0 | AS56: =AR56*AG56 -> 0 | AT56: =AS56-AO56 -> 0 | AU56: =IFERROR(AT56/AS56,0) -> 0
A57: =+A56+1 -> 44 | B57: 10009224 | C57: BONITO ENT FR S/COD BL10 S20 | D57: 1120 | N57: =+D57 -> 1120 | O57: =SUM(E57:L57) -> 0 | Q57: =SUM(G57:N57) -> 1120 | T57: =+Q57-S57 -> 1120 | Y57: =SUM(U57:W57) -> 0 | Z57: =+Y57-P57 -> 0 | AD57: 10009224 | AE57: ="FEBRERO"&AD57&"Inventario final" -> FEBRERO10009224Inventario final | AF57: =INDEX('[1]Detalle Costos'!$L$5:$L$158,MATCH(AE57,'[1]Detalle Costos'!$C$5:$C$158,0)) -> #N/A | AG57: =IF(ISERROR(AF57),0,Q57/1000) -> 0 | AH57: =IFERROR(AF57*AG57,0)*1000 -> 0 | AI57: =182*AG57 -> 0 | AJ57: =$AJ$59/$AG$59*AG57 -> 0 | AK57: =$AK$59/$AG$59*AG57 -> 0 | AL57: =$AL$59/$AG$59*AG57 -> 0 | AM57: 0 | AN57: =$BC$50 -> 0 | AO57: =AH57+AI57+AJ57+AK57 -> 0 | AP57: =IFERROR(AO57/AG57,0) -> 0 | AS57: =AR57*AG57 -> 0 | AT57: =AS57-AO57 -> 0 | AU57: =IFERROR(AT57/AS57,0) -> 0
AG58: =IF(ISERROR(AF58),0,Q58/1000) -> 0 | AU58: =IFERROR(AT58/AS58,0) -> 0
C59: STOCK A ABRIL 2026 | D59: =SUM(D3:D57) -> 1978298.8 | E59: =SUM(E3:E57) -> 42780 | F59: =SUM(F3:F57) -> 51380 | G59: =SUM(G3:G57) -> 44130 | H59: =SUM(H3:H57) -> 41912 | L59: =SUM(L3:L57) -> 0 | M59: =SUM(M3:M48) -> 0 | N59: =SUM(N3:N57) -> 1978298.8 | O59: =SUM(O3:O57) -> 295259 | P59: =SUM(P3:P57) -> 473430 | Q59: =SUM(Q3:Q58) -> 1800127.8 | S59: =SUM(S1:S57) -> 0 | T59: =SUM(T1:T57) -> 1800127.8 | U59: =SUM(U1:U57) -> 0 | V59: =SUM(V1:V57) -> 0 | W59: =SUM(W3:W57) -> 171000 | Y59: =SUM(Y3:Y57) -> 171000 | Z59: =SUM(U59:W59) -> 171000 | AA59: =+Y59-Z59 -> 0 | AE59: TOTAL | AG59: =SUBTOTAL(9,AG3:AG57) -> 1793.999 | AH59: =SUBTOTAL(9,AH3:AH57) -> 2997838.4 | AI59: =SUBTOTAL(9,AI3:AI57) -> 326507.82 | AJ59: 65523.78 | AK59: 148348.08 | AL59: 124026.69 | AM59: =SUBTOTAL(9,AM12:AM57) -> 0 | AN59: 0 | AO59: =SUBTOTAL(9,AO3:AO57) -> 3538218.1 | AP59: =AO59/$AG$59 -> 1972.252 | AR59: =AS59/$AG$59 -> 2305.4142 | AS59: =SUBTOTAL(9,AS4:AS57) -> 4135910.8 | AT59: =SUBTOTAL(9,AT4:AT57) -> 625479.76 | AU59: =IFERROR(AT59/AS59,0) -> 0.15123144 | AW59: 426
E60: =SUM(E4:E58) -> 41000 | F60: =SUM(F4:F58) -> 50980 | G60: =SUM(G4:G58) -> 41310 | H60: =SUM(H4:H58) -> 40232
W61: =+P59-V61 -> 473430
T62: Resumen | W62: EMBARQUE | X62: DIFERENCUA | Y62: 642.5768
T63: Embarcado: | U63: =+W59/1000 -> 171 | W63: 0 | X63: 0 | Y63: 49
T64: Reproceso: | U64: =+U59/1000 -> 0 | Y64: 0
T65: Muestreo | U65: =+V59/1000 -> 0 | Y65: 0
U66: =SUM(U63:U65) -> 171 | Y66: 593.5768

Sheet Marzo2026
A1: ID | B1: CODIGO | C1: MATERIAL | D1: FECHAS DIAS RECEPCION PRODUCCION ENERO 2026 | AF1: MOVIMIENTO INVENTARIO | AK1: DATA | AL1: DIFERENCIA
B2: SAP | D2: STOCK INICIO | E2: 46084 | F2: 46085 | G2: 46086 | H2: 46087 | I2: 46180 | J2: 46089 | K2: 46090 | L2: 46091 | M2: 46092 | N2: 46093 | O2: 46094 | P2: 46095 | Q2: 46097 | R2: 46098 | S2: 20 | T2: 21 | U2: 46103 | V2: 46104 | W2: 46105 | X2: 46107 | Y2: 46108 | Z2: 46109 | AA2: 46110 | AB2: 46111 | AC2: 46112 | AF2: Stock Inicial | AG2: INGRESOS | AH2: SALIDAS | AI2: STOCK KG | AK2: MANUAL | AM2: REPROCESO | AN2: MUESTREO | AO2: EMBARQUE | AQ2: STOCK KG
A3: 1 | B3: 10006668 | C3: POTA ALAS FR C/P C/C < 0.5 BL10 S20 | D3: 180 | T3: 440 | AF3: =+D3 -> 180 | AG3: =SUM(E3:AD3) -> 440 | AI3: =+AF3+AG3-AH3 -> 620 | AJ3: =+AF3-AI3 -> -440 | AK3: 620 | AL3: =+AI3-AK3 -> 0 | AQ3: =SUM(AM3:AO3) -> 0 | AR3: =+AQ3-AH3 -> 0
A4: =+A3+1 -> 2 | B4: 10009178 | C4: POTA ALAS FR C/P C/C (B) S/COD BL10 S20 | D4: 25720 | E4: =20+820 -> 840 | F4: =340+560 -> 900 | K4: =420+400 -> 820 | L4: =520+320 -> 840 | M4: =140+240 -> 380 | N4: =800+580 -> 1380 | O4: 200 | P4: =480+160 -> 640 | Q4: =260+1260 -> 1520 | R4: =80+220 -> 300 | S4: 500 | T4: =200+540 -> 740 | V4: =600+800 -> 1400 | W4: =3600+1180 -> 4780 | X4: =1320+1060 -> 2380 | Y4: =140+1200 -> 1340 | Z4: =640+620 -> 1260 | AA4: 1960 | AB4: =840+80 -> 920 | AC4: 180 | AF4: =+D4 -> 25720 | AG4: =SUM(E4:AD4) -> 23280 | AH4: =8000+2000+3900+4000+2000 -> 19900 | AI4: =+AF4+AG4-AH4 -> 29100 | AK4: 28000 | AL4: =+AI4-AK4 -> 1100 | AO4: 19900 | AQ4: =SUM(AM4:AO4) -> 19900 | AR4: =+AQ4-AH4 -> 0
A5: =+A4+1 -> 3 | B5: 10006719 | C5: POTA ALAS FR C/P C/C 0.5-1 BL10 S20 | D5: 660 | T5: 20 | AF5: =+D5 -> 660 | AG5: =SUM(E5:AD5) -> 20 | AI5: =+AF5+AG5-AH5 -> 680 | AK5: 680 | AL5: =+AI5-AK5 -> 0 | AQ5: =SUM(AM5:AO5) -> 0 | AR5: =+AQ5-AH5 -> 0
A6: =+A5+1 -> 4 | B6: 10009265 | C6: POTA ALAS FR C/P C/C 0.3 - 0.5 BL10 S20 | D6: 680 | AF6: =+D6 -> 680 | AG6: =SUM(E6:AD6) -> 0 | AI6: =+AF6+AG6-AH6 -> 680 | AK6: 680 | AL6: =+AI6-AK6 -> 0 | AQ6: =SUM(AM6:AO6) -> 0 | AR6: =+AQ6-AH6 -> 0
A7: =+A6+1 -> 5 | B7: 10006720 | C7: POTA ALAS FR C/P C/C 1-2 BL10 S20 | D7: 370620 | E7: =12100+6700 -> 18800 | F7: =18560+10800 -> 29360 | K7: =11560+9500 -> 21060 | L7: =14880+6640 -> 21520 | M7: =8020+7140 -> 15160 | N7: =30540+3280 -> 33820 | O7: 11400 | P7: =10440+7140 -> 17580 | Q7: =22420+11520 -> 33940 | R7: =8300+260 -> 8560 | S7: 9800 | T7: =12940+7680 -> 20620 | V7: =12480+4100 -> 16580 | W7: =29040+12820 -> 41860 | X7: =9160+4600 -> 13760 | Y7: =2300+2880 -> 5180 | Z7: =8580+5100 -> 13680 | AA7: 12420 | AB7: =13640+1480 -> 15120 | AC7: 5840 | AF7: 368800 | AG7: =SUM(E7:AD7) -> 366060 | AH7: =116800+48000+100000+25000+40+80+60+50000+95600+25000+80 -> 460660 | AI7: =+AF7+AG7-AH7 -> 274200 | AK7: 253240 | AL7: =+AI7-AK7 -> 20960 | AN7: =40+80+60+80 -> 260 | AO7: =116800+48000+100000+25000+50000+95600+25000 -> 460400 | AQ7: =SUM(AM7:AO7) -> 460660 | AR7: =+AQ7-AH7 -> 0
A8: =+A7+1 -> 6 | B8: 10006722 | C8: POTA ALAS FR C/P C/C 2-UP BL10 S20 | D8: 120 | AF8: =+D8 -> 120 | AG8: =SUM(E8:AD8) -> 0 | AI8: =+AF8+AG8-AH8 -> 120 | AK8: 120 | AL8: =+AI8-AK8 -> 0 | AQ8: =SUM(AM8:AO8) -> 0 | AR8: =+AQ8-AH8 -> 0
A9: =+A8+1 -> 7 | B9: 10009331 | C9: POTA ALAS PRE COC 3-UP BL9 S18 | D9: 57168 | Y9: 5364 | Z9: 5148 | AF9: =+D9 -> 57168 | AG9: =SUM(E9:AD9) -> 10512 | AH9: 52542 | AI9: =+AF9+AG9-AH9 -> 15138 | AK9: 15138 | AL9: =+AI9-AK9 -> 0 | AO9: 52542 | AQ9: =SUM(AM9:AO9) -> 52542 | AR9: =+AQ9-AH9 -> 0
A10: =+A9+1 -> 8 | C10: POTA ALAS PRE COC 3-UP BL10 S20 | D10: 360 | AF10: =+D10 -> 360 | AG10: =SUM(E10:AD10) -> 0 | AH10: 360 | AI10: =+AF10+AG10-AH10 -> 0 | AK10: 0 | AL10: =+AI10-AK10 -> 0 | AM10: 360 | AQ10: =SUM(AM10:AO10) -> 360 | AR10: =+AQ10-AH10 -> 0
A11: =+A10+1 -> 9 | B11: 10009334 | C11: POTA ALAS PRE COC B BL9 S18 | D11: 4428 | Y11: 612 | Z11: 432 | AF11: =+D11 -> 4428 | AG11: =SUM(E11:AD11) -> 1044 | AI11: =+AF11+AG11-AH11 -> 5472 | AK11: 5472 | AL11: =+AI11-AK11 -> 0 | AQ11: =SUM(AM11:AO11) -> 0 | AR11: =+AQ11-AH11 -> 0
A12: =+A11+1 -> 10 | B12: 10009207 | C12: POTA LABIOS FR S/COD BL10 S20 | D12: 22840 | E12: 380 | F12: =300+360 -> 660 | K12: 600 | L12: 300 | M12: 740 | N12: 340 | O12: =240+0 -> 240 | P12: =240+160 -> 400 | R12: =420+200 -> 620 | S12: 180 | T12: 420 | V12: 240 | W12: =540+480 -> 1020 | X12: =220+20 -> 240 | Y12: =160+300 -> 460 | Z12: 760 | AB12: 320 | AC12: 80 | AF12: =+D12 -> 22840 | AG12: =SUM(E12:AD12) -> 8000 | AI12: =+AF12+AG12-AH12 -> 30840 | AK12: 30440 | AL12: =+AI12-AK12 -> 400 | AQ12: =SUM(AM12:AO12) -> 0 | AR12: =+AQ12-AH12 -> 0
A13: =+A12+1 -> 11 | B13: 10007969 | C13: POTA CONOS | D13: 60620 | E13: 1780 | F13: =660+2240 -> 2900 | K13: 3020 | L13: 1200 | M13: 3380 | N13: 1540 | O13: 1120 | P13: =1020+700 -> 1720 | Q13: 3440 | R13: 820 | S13: 940 | T13: =300+1500 -> 1800 | V13: 2840 | W13: =1320+1060 -> 2380 | X13: =780+380 -> 1160 | Y13: =260+1760 -> 2020 | Z13: 2180 | AB13: =720+420 -> 1140 | AC13: 380 | AF13: =+D13 -> 60620 | AG13: =SUM(E13:AD13) -> 35760 | AH13: =40+40+48000 -> 48080 | AI13: =+AF13+AG13-AH13 -> 48300 | AK13: 46780 | AL13: =+AI13-AK13 -> 1520 | AN13: =40+40 -> 80 | AO13: 48000 | AQ13: =SUM(AM13:AO13) -> 48080 | AR13: =+AQ13-AH13 -> 0
A14: =+A13+1 -> 12 | B14: 10004433 | C14: POTA FILETE C/M C/T FR 0.5-1 BL10 S20 | D14: 300 | AF14: =+D14 -> 300 | AG14: =SUM(E14:AD14) -> 0 | AI14: =+AF14+AG14-AH14 -> 300 | AK14: 300 | AL14: =+AI14-AK14 -> 0 | AQ14: =SUM(AM14:AO14) -> 0 | AR14: =+AQ14-AH14 -> 0
A15: =+A14+1 -> 13 | B15: 10004434 | C15: POTA FILETE C/M C/T FR 1-2 BL10 S20 | D15: 1120 | AF15: =+D15 -> 1120 | AG15: =SUM(E15:AD15) -> 0 | AI15: =+AF15+AG15-AH15 -> 1120 | AK15: 1120 | AL15: =+AI15-AK15 -> 0 | AQ15: =SUM(AM15:AO15) -> 0 | AR15: =+AQ15-AH15 -> 0
A16: =+A15+1 -> 14 | B16: 10005721 | C16: POTA FILETE C/M C/T FR 2-4 AA BL10 S20 | D16: 331000 | E16: =10500+10700 -> 21200 | F16: =9840+10700 -> 20540 | K16: =12200+11720 -> 23920 | L16: =6120+220 -> 6340 | M16: =9420+14200 -> 23620 | N16: =4360+3040 -> 7400 | O16: 5920 | P16: =4000+4260 -> 8260 | Q16: =2940+5700 -> 8640 | R16: =2360+280 -> 2640 | S16: 5500 | T16: =9320+9520 -> 18840 | V16: =7060+10300 -> 17360 | W16: =7340+11000 -> 18340 | X16: =3880+2360 -> 6240 | Y16: =10400+25160 -> 35560 | Z16: =10520+8620 -> 19140 | AA16: 13840 | AB16: =10380+9460 -> 19840 | AC16: 6620 | AF16: =+D16 -> 331000 | AG16: =SUM(E16:AD16) -> 289760 | AH16: =108000+26000+80+40 -> 134120 | AI16: =+AF16+AG16-AH16 -> 486640 | AK16: 460180 | AL16: =+AI16-AK16 -> 26460 | AN16: =80+40 -> 120 | AO16: =108000+26000 -> 134000 | AQ16: =SUM(AM16:AO16) -> 134120 | AR16: =+AQ16-AH16 -> 0
A17: =+A16+1 -> 15 | B17: 10004435 | C17: POTA FILETE C/M C/T FR 2-4 BL10 S20 | D17: 83980 | E17: 1880 | F17: 1280 | K17: 1180 | M17: 760 | N17: 720 | O17: 260 | P17: =100+200 -> 300 | R17: =200+80 -> 280 | S17: 1780 | T17: =1600+7840 -> 9440 | V17: 5160 | W17: 1720 | X17: 760 | Y17: =60+3620 -> 3680 | Z17: 5560 | AB17: 1180 | AC17: 1320 | AF17: =+D17 -> 83980 | AG17: =SUM(E17:AD17) -> 37260 | AH17: 40 | AI17: =+AF17+AG17-AH17 -> 121200 | AK17: 118700 | AL17: =+AI17-AK17 -> 2500 | AN17: 40 | AQ17: =SUM(AM17:AO17) -> 40 | AR17: =+AQ17-AH17 -> 0
A18: =+A17+1 -> 16 | B18: 10009184 | C18: POTA NUCAS FR ABIERTAS 0.1 - 0.3 BL10 S2 | D18: 940 | AF18: =+D18 -> 940 | AG18: =SUM(E18:AD18) -> 0 | AI18: =+AF18+AG18-AH18 -> 940 | AK18: 940 | AL18: =+AI18-AK18 -> 0 | AQ18: =SUM(AM18:AO18) -> 0 | AR18: =+AQ18-AH18 -> 0
A19: =+A18+1 -> 17 | B19: 10009271 | C19: POTA NUCAS FR CERRADA 0.1 - 0.3 BL10 S2 | D19: 240 | T19: 320 | AF19: =+D19 -> 240 | AG19: =SUM(E19:AD19) -> 320 | AI19: =+AF19+AG19-AH19 -> 560 | AK19: 560 | AL19: =+AI19-AK19 -> 0 | AQ19: =SUM(AM19:AO19) -> 0 | AR19: =+AQ19-AH19 -> 0
A20: =+A19+1 -> 18 | B20: 10005779 | C20: POTA NUCAS FR ABIERTAS 0.5-1 BL10 S20 | D20: 238560 | E20: =1720+3560 -> 5280 | F20: =4460+3840 -> 8300 | K20: =2980+5180 -> 8160 | L20: =3320+80 -> 3400 | M20: =1900+7140 -> 9040 | N20: =3640+160 -> 3800 | O20: 2920 | P20: =3040+2060 -> 5100 | Q20: =3360+5640 -> 9000 | R20: =1100+1280 -> 2380 | S20: 780 | T20: =2220+2680 -> 4900 | V20: =3120+4200 -> 7320 | W20: =1620+2220 -> 3840 | X20: =1520+880 -> 2400 | Y20: =1280+2900 -> 4180 | Z20: =1140+2760 -> 3900 | AA20: 240 | AB20: =1220+1180-900 -> 1500 | AC20: 720 | AF20: =+D20 -> 238560 | AG20: =SUM(E20:AD20) -> 87160 | AH20: =40+80+200+20+67800+67800+96000+15000 -> 246940 | AI20: =+AF20+AG20-AH20 -> 78780 | AK20: 76560 | AL20: =+AI20-AK20 -> 2220 | AN20: =40+80+200+20 -> 340 | AO20: =67800+67800+96000+15000 -> 246600 | AQ20: =SUM(AM20:AO20) -> 246940 | AR20: =+AQ20-AH20 -> 0
A21: =+A20+1 -> 19 | B21: 10005776 | C21: POTA NUCAS FR ABIERTAS 0.3-0.5 BL10 S20 | D21: 9720 | E21: =40+240 -> 280 | F21: =20+360 -> 380 | K21: =80+220 -> 300 | L21: 140 | M21: 420 | N21: =160+20 -> 180 | O21: 100 | P21: =180+80 -> 260 | Q21: 580 | R21: 120 | T21: =80+140 -> 220 | V21: 280 | W21: 120 | X21: =60+20 -> 80 | Y21: =20+120 -> 140 | Z21: =20+160 -> 180 | AB21: =80+40 -> 120 | AC21: 20 | AF21: =+D21 -> 9720 | AG21: =SUM(E21:AD21) -> 3920 | AH21: =20+10000 -> 10020 | AI21: =+AF21+AG21-AH21 -> 3620 | AK21: 3480 | AL21: =+AI21-AK21 -> 140 | AN21: =20 -> 20 | AO21: 10000 | AQ21: =SUM(AM21:AO21) -> 10020 | AR21: =+AQ21-AH21 -> 0
A22: =+A21+1 -> 20 | B22: 10005781 | C22: POTA NUCAS FR ABIERTAS 1-2 BL10 S20 | D22: 67740 | E22: =240+500 -> 740 | F22: =580+780 -> 1360 | K22: =580+1240 -> 1820 | L22: =260+540 -> 800 | M22: =360+1520 -> 1880 | N22: =980+20 -> 1000 | O22: 880 | P22: =460+260 -> 720 | Q22: =440+800 -> 1240 | R22: 380 | S22: 760 | T22: =1640+1540 -> 3180 | V22: =2300+2860 -> 5160 | W22: =1760+1740 -> 3500 | X22: =1420+1080 -> 2500 | Y22: =1100+2600 -> 3700 | Z22: =880+3120 -> 4000 | AA22: 220 | AB22: =1300+1140 -> 2440 | AC22: 1140 | AF22: =+D22 -> 67740 | AG22: =SUM(E22:AD22) -> 37420 | AH22: =40+40+48000 -> 48080 | AI22: =+AF22+AG22-AH22 -> 57080 | AK22: 53500 | AL22: =+AI22-AK22 -> 3580 | AN22: 80 | AO22: 48000 | AQ22: =SUM(AM22:AO22) -> 48080 | AR22: =+AQ22-AH22 -> 0
A23: =+A22+1 -> 21 | B23: 10009386 | C23: VENTOSAS | D23: 27480 | E23: 400 | F23: =260+380 -> 640 | K23: =220+400 -> 620 | L23: 300 | M23: 740 | N23: =200+140 -> 340 | O23: 200 | P23: =260+160 -> 420 | Q23: 720 | R23: 180 | S23: 180 | T23: 460 | V23: 800 | W23: 560 | X23: =240+140 -> 380 | Y23: 680 | Z23: 740 | AB23: 400 | AC23: 120 | AF23: =+D23 -> 27480 | AG23: =SUM(E23:AD23) -> 8880 | AI23: =+AF23+AG23-AH23 -> 36360 | AK23: 35840 | AL23: =+AI23-AK23 -> 520 | AQ23: =SUM(AM23:AO23) -> 0 | AR23: =+AQ23-AH23 -> 0
A24: =+A23+1 -> 22 | B24: 10007567 | C24: POTA REJOS OR FR LIMPIOS S/COD BL10 S20 | D24: 104880 | E24: 2660 | F24: =1040+3060 -> 4100 | K24: 4380 | L24: =600+1200 -> 1800 | M24: =1160+3720 -> 4880 | N24: 2100 | O24: 1580 | P24: =1600+1060 -> 2660 | Q24: 3620 | R24: =1260+1240 -> 2500 | S24: 1300 | T24: =200+2620 -> 2820 | V24: =560+640 -> 1200 | W24: =4980+1980 -> 6960 | X24: =1240+620 -> 1860 | Y24: =1060+2180 -> 3240 | Z24: =500+3160 -> 3660 | AB24: =340+1620 -> 1960 | AC24: 700 | AF24: =+D24 -> 104880 | AG24: =SUM(E24:AD24) -> 53980 | AH24: =25000+26000 -> 51000 | AI24: =+AF24+AG24-AH24 -> 107860 | AK24: 105200 | AL24: =+AI24-AK24 -> 2660 | AO24: =25000+26000 -> 51000 | AQ24: =SUM(AM24:AO24) -> 51000 | AR24: =+AQ24-AH24 -> 0
A25: =+A24+1 -> 23 | B25: 10009187 | C25: POTA REJOS FR C/B S/U S/V S/OR 0.3 - 0.5 | D25: 140 | AF25: =+D25 -> 140 | AG25: =SUM(E25:AD25) -> 0 | AI25: =+AF25+AG25-AH25 -> 140 | AK25: 140 | AL25: =+AI25-AK25 -> 0 | AQ25: =SUM(AM25:AO25) -> 0 | AR25: =+AQ25-AH25 -> 0
A26: =+A25+1 -> 24 | B26: 10009777 | C26: POTA REJOS FR C/B S/U S/V S/OR 0.3 - 0.5 | D26: 0 | V26: 220 | AF26: =+D26 -> 0 | AG26: =SUM(E26:AD26) -> 220 | AI26: =+AF26+AG26-AH26 -> 220 | AK26: 220 | AL26: =+AI26-AK26 -> 0 | AQ26: =SUM(AM26:AO26) -> 0 | AR26: =+AQ26-AH26 -> 0
A27: =+A25+1 -> 24 | B27: 10007161 | C27: POTA REJOS FR C/B S/U S/V S/OR 0.5-1 BL1 | D27: 6240 | E27: 260 | F27: =140+360 -> 500 | K27: =80+320 -> 400 | L27: 220 | M27: =40+480 -> 520 | N27: =60+120 -> 180 | O27: 140 | P27: =240+140 -> 380 | Q27: 560 | R27: =80+100 -> 180 | T27: =40+220 -> 260 | V27: =40+160 -> 200 | W27: =100+140 -> 240 | X27: =60+120 -> 180 | Y27: =20+160 -> 180 | Z27: =120+100 -> 220 | AB27: 180 | AC27: 40 | AF27: =+D27 -> 6240 | AG27: =SUM(E27:AD27) -> 4840 | AI27: =+AF27+AG27-AH27 -> 11080 | AK27: 10860 | AL27: =+AI27-AK27 -> 220 | AQ27: =SUM(AM27:AO27) -> 0 | AR27: =+AQ27-AH27 -> 0
A28: =+A27+1 -> 25 | B28: 10009186 | C28: POTA REJOS FR S-S/POR C/UV 0.1 - 0.3 BL1 | D28: 200 | T28: 540 | AF28: =+D28 -> 200 | AG28: =SUM(E28:AD28) -> 540 | AI28: =+AF28+AG28-AH28 -> 740 | AK28: 740 | AL28: =+AI28-AK28 -> 0 | AQ28: =SUM(AM28:AO28) -> 0 | AR28: =+AQ28-AH28 -> 0
A29: =+A28+1 -> 26 | B29: 10007162 | C29: POTA REJOS FR C/B S/U S/V S/OR 1-2 BL10 | D29: 288880 | E29: =5880+5540 -> 11420 | F29: =7660+10080 -> 17740 | K29: =8420+9320 -> 17740 | L29: 7500 | M29: =10580+9480 -> 20060 | N29: =6880+1820 -> 8700 | O29: 6920 | P29: =6540+4320 -> 10860 | Q29: =9480+9680 -> 19160 | R29: =5500+480 -> 5980 | S29: 3000 | T29: =7780+3180 -> 10960 | V29: =6860+11160 -> 18020 | W29: =5720+4740 -> 10460 | X29: =4340+2240 -> 6580 | Y29: =4340+6720 -> 11060 | Z29: =6820+4880 -> 11700 | AB29: =4380+2300 -> 6680 | AC29: 2260 | AF29: =+D29 -> 288880 | AG29: =SUM(E29:AD29) -> 206800 | AH29: =26000+177000+25000 -> 228000 | AI29: =+AF29+AG29-AH29 -> 267680 | AK29: 258740 | AL29: =+AI29-AK29 -> 8940 | AO29: =26000+177000+25000 -> 228000 | AQ29: =SUM(AM29:AO29) -> 228000 | AR29: =+AQ29-AH29 -> 0
A30: =+A29+1 -> 27 | B30: 10009658 | C30: POTA REJOS FR 1 UP | D30: 1960 | AF30: =+D30 -> 1960 | AG30: =SUM(E30:AD30) -> 0 | AI30: =+AF30+AG30-AH30 -> 1960 | AK30: 1960 | AL30: =+AI30-AK30 -> 0 | AQ30: =SUM(AM30:AO30) -> 0 | AR30: =+AQ30-AH30 -> 0
A31: =+A30+1 -> 28 | B31: 10009639 | C31: POTA REJOS FR 2 UP | D31: 47080 | E31: 980 | F31: =520+1240 -> 1760 | K31: =640+1460 -> 2100 | L31: 800 | M31: =800+1340 -> 2140 | N31: =900+420 -> 1320 | O31: 860 | P31: =460+340 -> 800 | Q31: =640+960 -> 1600 | R31: =460+460 -> 920 | S31: 980 | T31: =2740+1860 -> 4600 | V31: =2140+4460 -> 6600 | W31: =2700+2240 -> 4940 | X31: =1380+1140 -> 2520 | Y31: =1760+3560 -> 5320 | Z31: =3080+2960 -> 6040 | AB31: =2020+1080 -> 3100 | AC31: 1200 | AF31: =+D31 -> 47080 | AG31: =SUM(E31:AD31) -> 48580 | AH31: =24000+27000 -> 51000 | AI31: =+AF31+AG31-AH31 -> 44660 | AK31: 40360 | AL31: =+AI31-AK31 -> 4300 | AO31: =24000+27000 -> 51000 | AQ31: =SUM(AM31:AO31) -> 51000 | AR31: =+AQ31-AH31 -> 0
A32: =+A31+1 -> 29 | B32: 10009239 | C32: POTA FILETE PRE COCIDO S/M S/T C/P S/COD | D32: 287540 | E32: 2980 | F32: 4360 | G32: =9400+9920 -> 19320 | H32: 6580 | K32: 8240 | L32: =8740+8460 -> 17200 | M32: 9740 | N32: =7920+11360 -> 19280 | O32: 4240 | P32: =3540+13020 -> 16560 | Q32: 5120 | R32: =11820+13600 -> 25420 | S32: 2360 | T32: =2540+2840 -> 5380 | U32: 3660 | V32: 7660 | W32: =12080+14800 -> 26880 | X32: 10280 | Y32: 5960 | Z32: 3540 | AB32: 2320 | AF32: =+D32 -> 287540 | AG32: =SUM(E32:AD32) -> 207080 | AH32: =175000+125000+180 -> 300180 | AI32: =+AF32+AG32-AH32 -> 194440 | AK32: 192120 | AL32: =+AI32-AK32 -> 2320 | AN32: 180 | AO32: 300000 | AQ32: =SUM(AM32:AO32) -> 300180 | AR32: =+AQ32-AH32 -> 0
A33: =+A32+1 -> 30 | B33: 10009251 | C33: POTA FILETE PRE COCIDO S/M S/T 0.6 - 1.0 | D33: 36540 | E33: 20 | F33: 240 | G33: =400+320 -> 720 | H33: 980 | L33: =860+620 -> 1480 | M33: 1700 | N33: =300+700 -> 1000 | O33: 0 | P33: =660+420 -> 1080 | Q33: 120 | R33: 540 | T33: 80 | U33: 80 | W33: =60+220 -> 280 | X33: 180 | Y33: 100 | Z33: 420 | AB33: 60 | AF33: =+D33 -> 36540 | AG33: =SUM(E33:AD33) -> 9080 | AH33: =14000+10000 -> 24000 | AI33: =+AF33+AG33-AH33 -> 21620 | AK33: 21560 | AL33: =+AI33-AK33 -> 60 | AO33: 24000 | AQ33: =SUM(AM33:AO33) -> 24000 | AR33: =+AQ33-AH33 -> 0
A34: =+A33+1 -> 31 | B34: 10009241 | C34: POTA ALAS PRE COC S/COD BL10 S20 | D34: 260 | AF34: =+D34 -> 260 | AG34: =SUM(E34:AD34) -> 0 | AI34: =+AF34+AG34-AH34 -> 260 | AK34: 260 | AL34: =+AI34-AK34 -> 0 | AQ34: =SUM(AM34:AO34) -> 0 | AR34: =+AQ34-AH34 -> 0
A35: =+A34+1 -> 32 | B35: 10007050 | C35: PPTA RECORTES PRECOCIDA B10 S20 | D35: 26460 | E35: 660 | F35: 100 | G35: =1520+200 -> 1720 | H35: 1740 | L35: =680+1100 -> 1780 | M35: 320 | N35: =180+1980 -> 2160 | O35: 0 | P35: =560+1140 -> 1700 | Q35: 940 | R35: =2160+2220 -> 4380 | T35: 540 | U35: 1420 | V35: 80 | W35: =680+1340 -> 2020 | X35: 860 | Y35: 1100 | Z35: 1120 | AB35: 520 | AF35: =+D35 -> 26460 | AG35: =SUM(E35:AD35) -> 23160 | AI35: =+AF35+AG35-AH35 -> 49620 | AK35: 49100 | AL35: =+AI35-AK35 -> 520 | AQ35: =SUM(AM35:AO35) -> 0 | AR35: =+AQ35-AH35 -> 0
A36: =+A35+1 -> 33 | C36: FILETE FR REPROCESO x 10 | D36: 22290 | AA36: 390 | AC36: 9060 | AF36: =+D36 -> 22290 | AG36: =SUM(E36:AD36) -> 9450 | AH36: =10080+12210 -> 22290 | AI36: =+AF36+AG36-AH36 -> 9450 | AK36: 0 | AL36: =+AI36-AK36 -> 9450 | AM36: 22290 | AQ36: =SUM(AM36:AO36) -> 22290 | AR36: =+AQ36-AH36 -> 0
A37: =+A36+1 -> 34 | C37: FILETE FR S/M S/T C/M 1-2 REPROCESO x 10 | D37: 0 | AC37: 3460 | AF37: =+D37 -> 0 | AG37: =SUM(E37:AD37) -> 3460 | AI37: =+AF37+AG37-AH37 -> 3460 | AK37: 0 | AL37: =+AI37-AK37 -> 3460 | AQ37: =SUM(AM37:AO37) -> 0 | AR37: =+AQ37-AH37 -> 0
A38: =+A37+1 -> 35 | C38: RECORTE MEMBRANA FRESCA REPROCESO BL 10 | D38: 2600 | AC38: 2380 | AF38: =+D38 -> 2600 | AG38: =SUM(E38:AD38) -> 2380 | AH38: 2600 | AI38: =+AF38+AG38-AH38 -> 2380 | AK38: 0 | AL38: =+AI38-AK38 -> 2380 | AM38: 2600 | AQ38: =SUM(AM38:AO38) -> 2600 | AR38: =+AQ38-AH38 -> 0
A39: =+A38+1 -> 36 | C39: RECORTE TELILLA FRESCA REPROCESO BL 10 | D39: 2650 | AC39: 2200 | AF39: =+D39 -> 2650 | AG39: =SUM(E39:AD39) -> 2200 | AH39: 2650 | AI39: =+AF39+AG39-AH39 -> 2200 | AK39: 0 | AL39: =+AI39-AK39 -> 2200 | AM39: 2650 | AQ39: =SUM(AM39:AO39) -> 2650 | AR39: =+AQ39-AH39 -> 0
A40: =+A39+1 -> 37 | B40: 10009337 | C40: POTA RECORTE COCIDO (M) x 15 | D40: 19455 | F40: 570 | G40: =3615+30 -> 3645 | K40: 1800 | L40: =255+1125 -> 1380 | M40: 735 | N40: =1215+1740 -> 2955 | O40: 0 | P40: =825+1500 -> 2325 | Q40: 435 | R40: =3660+795 -> 4455 | T40: 600 | U40: 1005 | V40: 1440 | W40: =525+2340 -> 2865 | X40: 1305 | Y40: 780 | Z40: 855 | AF40: =+D40 -> 19455 | AG40: =SUM(E40:AD40) -> 27150 | AH40: =25500-105 -> 25395 | AI40: =+AF40+AG40-AH40 -> 21210 | AJ40: 52320 | AK40: 21210 | AL40: =+AI40-AK40 -> 0 | AO40: 25395 | AQ40: =SUM(AM40:AO40) -> 25395 | AR40: =+AQ40-AH40 -> 0
A41: =+A40+1 -> 38 | B41: 10009332 | C41: POTA RECORTE COCIDO (T) X 15 | D41: 14025 | F41: 885 | G41: =3150+15 -> 3165 | K41: 525 | L41: =1350+1200 -> 2550 | M41: 345 | N41: =1410+1650 -> 3060 | O41: 0 | P41: =780+1185 -> 1965 | Q41: 1380 | R41: =2700+780 -> 3480 | T41: 480 | U41: 900 | V41: 1650 | W41: 2175 | X41: 1185 | Y41: 1230 | Z41: 360 | AF41: =+D41 -> 14025 | AG41: =SUM(E41:AD41) -> 25335 | AI41: =+AF41+AG41-AH41 -> 39360 | AK41: 39360 | AL41: =+AI41-AK41 -> 0 | AQ41: =SUM(AM41:AO41) -> 0 | AR41: =+AQ41-AH41 -> 0
C42: POTA RECORTE FRESCO POR REPROCESO | D42: 0 | AC42: 4920 | AF42: =+D42 -> 0 | AG42: =SUM(E42:AD42) -> 4920 | AI42: =+AF42+AG42-AH42 -> 4920
A43: =+A41+1 -> 39 | C43: TUBO ALETA 0.5-1.0 | D43: 0 | T43: 20 | AF43: =+D43 -> 0 | AG43: =SUM(E43:AD43) -> 20 | AI43: =+AF43+AG43-AH43 -> 20 | AK43: 20 | AL43: =+AI43-AK43 -> 0 | AQ43: =SUM(AM43:AO43) -> 0 | AR43: =+AQ43-AH43 -> 0
A44: =+A43+1 -> 40 | C44: TUBO ALETA 1.0-1.5 | D44: 0 | T44: =880+1180 -> 2060 | AF44: =+D44 -> 0 | AG44: =SUM(E44:AD44) -> 2060 | AI44: =+AF44+AG44-AH44 -> 2060 | AK44: 2060 | AL44: =+AI44-AK44 -> 0 | AQ44: =SUM(AM44:AO44) -> 0 | AR44: =+AQ44-AH44 -> 0
A45: =+A44+1 -> 41 | C45: LANGOSTINO COLA PVD | D45: 56.175 | AF45: =+D45 -> 56.175 | AG45: =SUM(E45:AD45) -> 0 | AH45: 5 | AI45: =+AF45+AG45-AH45 -> 51.175 | AK45: 51.175 | AL45: =+AI45-AK45 -> 0 | AN45: 5 | AQ45: =SUM(AM45:AO45) -> 5 | AR45: =+AQ45-AH45 -> 0
A46: =+A45+1 -> 42 | C46: CONCHA ABANICO T/SOLO | D46: 16.775 | AF46: =+D46 -> 16.775 | AG46: =SUM(E46:AD46) -> 0 | AH46: 3 | AI46: =+AF46+AG46-AH46 -> 13.775 | AK46: 13.775 | AL46: =+AI46-AK46 -> 0 | AN46: 3 | AQ46: =SUM(AM46:AO46) -> 3 | AR46: =+AQ46-AH46 -> 0
A47: =+A46+1 -> 43 | C47: CABALLA ENTERA FR S/COD | D47: 23.85 | AF47: =+D47 -> 23.85 | AG47: =SUM(E47:AD47) -> 0 | AI47: =+AF47+AG47-AH47 -> 23.85 | AK47: 23.85 | AL47: =+AI47-AK47 -> 0 | AQ47: =SUM(AM47:AO47) -> 0 | AR47: =+AQ47-AH47 -> 0
A48: =+A47+1 -> 44 | B48: 10009224 | C48: BONITO ENT FR S/COD BL10 S20 | D48: 1120 | AF48: =+D48 -> 1120 | AG48: =SUM(E48:AD48) -> 0 | AI48: =SUM(G48:AF48) -> 1120 | AK48: 1120 | AL48: =+AI48-AK48 -> 0 | AQ48: =SUM(AM48:AO48) -> 0 | AR48: =+AQ48-AH48 -> 0
C50: STOCK A MARZO 2026 | D50: =SUM(D3:D48) -> 2166892.8 | E50: =SUM(E3:E48) -> 70560 | F50: =SUM(F3:F48) -> 96575 | G50: =SUM(G3:G48) -> 28570 | H50: =SUM(H3:H48) -> 9300 | I50: =SUM(I3:I48) -> 0 | J50: =SUM(J3:J48) -> 0 | K50: =SUM(K3:K48) -> 96685 | ... AD50: =SUM(AD3:AD48) -> 0 | AE50: =SUM(AE3:AE39) -> 0 | AF50: =SUM(AF3:AF48) -> 2165072.8 | AG50: =SUM(AG3:AG48) -> 1541091 | AH50: =SUM(AH3:AH48) -> 1727865 | AI50: =SUM(AI3:AI49) -> 1978298.8 | AK50: =SUM(AK1:AK48) -> 1877468.8 | AL50: =SUM(AL1:AL48) -> 95910 | AM50: =SUM(AM1:AM48) -> 27900 | AN50: =SUM(AN1:AN48) -> 1128 | AO50: =SUM(AO3:AO48) -> 1698837 | AQ50: =SUM(AQ3:AQ48) -> 1727865 | AR50: =SUM(AM50:AO50) -> 1727865 | AS50: =+AQ50-AR50 -> 0 | BC50: =SUM(BC4:BC49) -> 0 | BD50: =+BC50-AI50 -> -1978298.8
E51: =SUM(E4:E49) -> 70560 | F51: =SUM(F4:F49) -> 96575 | G51: =SUM(G4:G49) -> 28570 | H51: =SUM(H4:H49) -> 9300 | I51: =SUM(I4:I49) -> 0 | J51: =SUM(J4:J49) -> 0 | K51: =SUM(K4:K49) -> 96685 | L51: =SUM(L4:L49) -> 69550 | ... Z51: =SUM(Z4:Z49) -> 84895
AO52: =+AH50-AN52 -> 1727865
E53: =+E50+F50 -> 167135 | AF53: STOCK MARZO 2026 | AI53: =ROUND(+AI50/1000,0) -> 1978 | AL53: Resumen | AO53: EMBARQUE | AP53: DIFERENCUA | AQ53: 642.5768
AF54: Embarques | AI54: =+AG55+AG56 -> 324 | AL54: Embarcado: | AM54: =+AO50/1000 -> 1698.837 | AO54: 0 | AP54: 0 | AQ54: 49
E55: 115 | AF55: 46113 | AG55: =27*12 -> 324 | AI55: 0 | AL55: Reproceso: | AM55: =+AM50/1000 -> 27.9 | AQ55: 0
E56: 167 | AI56: 0 | AL56: Muestreo | AM56: =+AN50/1000 -> 1.128 | AQ56: 0
E57: =+E56-E55 -> 52 | AF57: NUEVO STOCK PARA ACTUALIZAR | AI57: =+AI53-AI54-AI55-AI56 -> 1654 | AM57: =SUM(AM54:AM56) -> 1727.865 | AQ57: 593.5768

Sheet Febrero2026
A1: ID | B1: CODIGO | C1: MATERIAL | D1: FECHAS DIAS RECEPCION PRODUCCION ENERO 2026 | AG1: MOVIMIENTO INVENTARIO | AL1: DATA | AM1: DIFERENCIA
B2: SAP | D2: STOCK INICIO | E2: 46056 | F2: 46057 | G2: 46058 | H2: 46087 | I2: 46060 | J2: 46061 | K2: 46062 | L2: 46063 | M2: 46064 | N2: 46065 | O2: 46066 | P2: 46067 | Q2: 46068 | R2: 46069 | S2: 46070 | T2: 46071 | U2: 46072 | V2: 46073 | W2: 46074 | X2: 46075 | Y2: 46076 | Z2: 46077 | AA2: 46078 | AB2: 46079 | AC2: 46080 | AD2: 46081 | AG2: Stock Inicial | AH2: INGRESOS | AI2: SALIDAS | AJ2: STOCK KG | AL2: MANUAL | AN2: REPROCESO | AO2: MUESTREO | AP2: EMBARQUE
A3: 1 | B3: 10006668 | C3: POTA ALAS FR C/P C/C < 0.5 BL10 S20 | D3: 180 | AG3: =+D3 -> 180 | AH3: =SUM(E3:AE3) -> 0 | AJ3: =+AG3+AH3-AI3 -> 180 | AK3: =+AG3-AJ3 -> 0 | AL3: 0 | AM3: =+AJ3-AL3 -> 180 | AS3: =+AL3-AR3 -> 0
A4: =+A3+1 -> 2 | B4: 10009178 | C4: POTA ALAS FR C/P C/C (B) S/COD BL10 S20 | D4: 17900 | E4: 20 | F4: 60 | I4: =100+80 -> 180 | J4: 20 | K4: =140+60 -> 200 | L4: =220+120 -> 340 | M4: 360 | N4: 220 | O4: 60 | P4: 140 | R4: =580+60 -> 640 | S4: =360+140 -> 500 | T4: =300+280 -> 580 | U4: =120+300 -> 420 | V4: 440 | W4: =20+60 -> 80 | X4: 360 | Y4: =140+340 -> 480 | Z4: =660+420 -> 1080 | AD4: =25720-24080 -> 1640 | AG4: =+D4 -> 17900 | AH4: =SUM(E4:AE4) -> 7820 | AJ4: =+AG4+AH4-AI4 -> 25720 | AL4: 0 | AM4: =+AJ4-AL4 -> 25720 | AS4: =+AL4-AR4 -> 0
A5: =+A4+1 -> 3 | B5: 10006719 | C5: POTA ALAS FR C/P C/C 0.5-1 BL10 S20 | D5: 660 | AG5: =+D5 -> 660 | AH5: =SUM(E5:AE5) -> 0 | AJ5: =+AG5+AH5-AI5 -> 660 | AL5: 0 | AM5: =+AJ5-AL5 -> 660 | AS5: =+AL5-AR5 -> 0
A6: =+A5+1 -> 4 | B6: 10009265 | C6: POTA ALAS FR C/P C/C 0.3 - 0.5 BL10 S20 | D6: 680 | AG6: =+D6 -> 680 | AH6: =SUM(E6:AE6) -> 0 | AJ6: =+AG6+AH6-AI6 -> 680 | AL6: 0 | AM6: =+AJ6-AL6 -> 680 | AS6: =+AL6-AR6 -> 0
A7: =+A6+1 -> 5 | B7: 10006720 | C7: POTA ALAS FR C/P C/C 1-2 BL10 S20 | D7: 338560 | G7: =10440+420 -> 10860 | H7: 5480 | I7: =16300+1620 -> 17920 | J7: =19280 -> 19280 | K7: =22340+3580 -> 25920 | L7: =25440+4080 -> 29520 | M7: 16000 | N7: 8040 | O7: 1120 | P7: 1620 | Q7: 12420 | R7: =19600+5300 -> 24900 | S7: =15340+5140 -> 20480 | T7: =40220+11420 -> 51640 | U7: =18600+4180 -> 22780 | V7: =9100+9980 -> 19080 | W7: 5040 | X7: 17420 | Y7: 9240 | Z7: =39020+9640 -> 48660 | AD7: =(252000-246040)+116800 -> 122760 | AG7: =+D7 -> 338560 | AH7: =SUM(E7:AE7) -> 490180 | AI7: =200+108000+108000+46800+81000+115500+80+140+140+80 -> 459940 | AJ7: =+AG7+AH7-AI7 -> 368800 | AL7: 0 | AM7: =+AJ7-AL7 -> 368800 | AO7: =200+80+140+140+80 -> 640 | AP7: =108000+108000+46800+81000+115500 -> 459300 | AS7: =+AL7-AR7 -> 0
A8: =+A7+1 -> 6 | B8: 10006722 | C8: POTA ALAS FR C/P C/C 2-UP BL10 S20 | D8: 120 | AG8: =+D8 -> 120 | AH8: =SUM(E8:AE8) -> 0 | AJ8: =+AG8+AH8-AI8 -> 120 | AL8: 0 | AM8: =+AJ8-AL8 -> 120 | AS8: =+AL8-AR8 -> 0
A9: =+A8+1 -> 7 | C9: POTA ALAS PRE COC 3-UP BL9 S18 | D9: 16650 | E9: 2124 | F9: 8352 | G9: =3960+1854 -> 5814 | H9: =4410+2682 -> 7092 | I9: =3294+10818 -> 14112 | J9: 3024 | AG9: =+D9 -> 16650 | AH9: =SUM(E9:AE9) -> 40518 | AJ9: =+AG9+AH9-AI9 -> 57168 | AL9: 0 | AM9: =+AJ9-AL9 -> 57168
C10: POTA ALAS PRE COC 3-UP BL10 S20 | D10: 0 | G10: 360 | AG10: =+D10 -> 0 | AH10: =SUM(E10:AE10) -> 360 | AJ10: =+AG10+AH10-AI10 -> 360 | AL10: 0 | AM10: =+AJ10-AL10 -> 360
C11: POTA ALAS PRE COC B BL9 S18 | D11: 1854 | F11: 540 | G11: =378+234 -> 612 | H11: =558+54 -> 612 | I11: 342 | J11: 468 | AG11: =+D11 -> 1854 | AH11: =SUM(E11:AE11) -> 2574 | AJ11: =+AG11+AH11-AI11 -> 4428 | AL11: 0 | AM11: =+AJ11-AL11 -> 4428
A12: 8 | B12: 10009207 | C12: POTA LABIOS FR S/COD BL10 S20 | D12: 12340 | E12: =100+240 -> 340 | F12: 400 | G12: =100+400 -> 500 | H12: 800 | J12: 680 | K12: 360 | L12: =300+440 -> 740 | M12: =60+80 -> 140 | N12: 0 | O12: 720 | Q12: 560 | R12: 680 | S12: 540 | T12: 300 | U12: =160+260 -> 420 | V12: 380 | W12: 460 | X12: 180 | Y12: 620 | Z12: 400 | AD12: =22840-21560 -> 1280 | AG12: =+D12 -> 12340 | AH12: =SUM(E12:AE12) -> 10500 | AJ12: =+AG12+AH12-AI12 -> 22840 | AL12: 0 | AM12: =+AJ12-AL12 -> 22840 | AS12: =+AL12-AR12 -> 0
A13: =+A12+1 -> 9 | B13: 10007969 | C13: POTA CONOS | D13: 40960 | E13: =440+460 -> 900 | F13: =540+1640 -> 2180 | G13: =340+1880 -> 2220 | H13: 3920 | I13: 1400 | J13: 1940 | K13: 3620 | L13: =800+2720 -> 3520 | M13: =140+1640 -> 1780 | N13: 940 | O13: 4240 | P13: 2900 | R13: 3760 | S13: 2640 | T13: =240+1240 -> 1480 | U13: =1360+720 -> 2080 | V13: 1860 | W13: 3020 | Y13: 2940 | Z13: 1780 | AD13: =60620-56940 -> 3680 | AG13: =+D13 -> 40960 | AH13: =SUM(E13:AE13) -> 52800 | AI13: =9140+24000 -> 33140 | AJ13: =+AG13+AH13-AI13 -> 60620 | AL13: 0 | AM13: =+AJ13-AL13 -> 60620 | AP13: =9140+24000 -> 33140 | AS13: =+AL13-AR13 -> 0
A14: =+A13+1 -> 10 | B14: 10004433 | C14: POTA FILETE C/M C/T FR 0.5-1 BL10 S20 | D14: 300 | AG14: =+D14 -> 300 | AH14: =SUM(E14:AE14) -> 0 | AJ14: =+AG14+AH14-AI14 -> 300 | AL14: 0 | AM14: =+AJ14-AL14 -> 300 | AS14: =+AL14-AR14 -> 0
A15: =+A14+1 -> 11 | B15: 10004434 | C15: POTA FILETE C/M C/T FR 1-2 BL10 S20 | D15: 1120 | AG15: =+D15 -> 1120 | AH15: =SUM(E15:AE15) -> 0 | AJ15: =+AG15+AH15-AI15 -> 1120 | AL15: 0 | AM15: =+AJ15-AL15 -> 1120 | AS15: =+AL15-AR15 -> 0
A16: =+A15+1 -> 12 | B16: 10005721 | C16: POTA FILETE C/M C/T FR 2-4 (B) BL10 S20 | D16: 472180 | E16: 10720 | F16: =7580+1500 -> 9080 | G16: =240+500 -> 740 | H16: =11320+9040 -> 20360 | I16: =42520+1260 -> 43780 | J16: 65880 | K16: =20380+14860 -> 35240 | L16: 2460 | M16: 6020 | N16: 480 | O16: 160 | P16: 8520 | Q16: 8800 | R16: =19420+7380 -> 26800 | S16: =36620+7180 -> 43800 | T16: 0 | V16: =7820+8420 -> 16240 | W16: =38380+15400 -> 53780 | X16: 19800 | Y16: =32020+27080 -> 59100 | Z16: =14340+7040 -> 21380 | AD16: =331000-226980 -> 104020 | AG16: =+D16 -> 472180 | AH16: =SUM(E16:AE16) -> 557160 | AI16: =135000+54000+135000+108000+108000+135000+23300+40 -> 698340 | AJ16: =+AG16+AH16-AI16 -> 331000 | AL16: 0 | AM16: =+AJ16-AL16 -> 331000 | AO16: 40 | AP16: =135000+54000+135000+108000+108000+135000+23300 -> 698300 | AS16: =+AL16-AR16 -> 0
A17: =+A16+1 -> 13 | B17: 10004435 | C17: POTA FILETE C/M C/T FR 2-4 BL10 S20 | D17: 65040 | E17: =1120+540 -> 1660 | F17: =2440+10600 -> 13040 | G17: =8800+7820 -> 16620 | H17: =4720+10620 -> 15340 | I17: =7180+14960 -> 22140 | K17: 4140 | L17: =2000+3140 -> 5140 | M17: 8540 | N17: 8560 | O17: 2960 | P17: 2420 | Q17: 3760 | R17: 7480 | S17: =240+6660 -> 6900 | T17: =2640+1060 -> 3700 | U17: =2220+4520 -> 6740 | W17: 2840 | X17: 4500 | Y17: =420+3220 -> 3640 | Z17: =40+1860 -> 1900 | AD17: =83980-72060 -> 11920 | AG17: =+D17 -> 65040 | AH17: =SUM(E17:AE17) -> 153940 | AI17: =54000+81000 -> 135000 | AJ17: =+AG17+AH17-AI17 -> 83980 | AL17: 0 | AM17: =+AJ17-AL17 -> 83980 | AP17: =54000+81000 -> 135000 | AS17: =+AL17-AR17 -> 0
A18: =+A17+1 -> 14 | B18: 10009184 | C18: POTA NUCAS FR ABIERTAS 0.1 - 0.3 BL10 S2 | D18: 940 | AG18: =+D18 -> 940 | AH18: =SUM(E18:AE18) -> 0 | AJ18: =+AG18+AH18-AI18 -> 940 | AL18: 0 | AM18: =+AJ18-AL18 -> 940 | AS18: =+AL18-AR18 -> 0
A19: =+A18+1 -> 15 | B19: 10009271 | C19: POTA NUCAS FR CERRADA 0.1 - 0.3 BL10 S2 | D19: 240 | AG19: =+D19 -> 240 | AH19: =SUM(E19:AE19) -> 0 | AJ19: =+AG19+AH19-AI19 -> 240 | AL19: 0 | AM19: =+AJ19-AL19 -> 240 | AS19: =+AL19-AR19 -> 0
A20: =+A19+1 -> 16 | B20: 10005779 | C20: POTA NUCAS FR ABIERTAS 0.5-1 BL10 S20 | D20: 178040 | E20: =1300+660 -> 1960 | F20: =1400+3960 -> 5360 | G20: =3000+2620 -> 5620 | H20: =4900+5680 -> 10580 | I20: =2960+6940 -> 9900 | K20: =960+7480 -> 8440 | L20: =560+8220 -> 8780 | M20: =3240+7140 -> 10380 | N20: 7000 | O20: 8080 | P20: 5280 | R20: =3320+6380 -> 9700 | S20: =3540+3960 -> 7500 | T20: =2380+1140 -> 3520 | U20: =3900+1920 -> 5820 | V20: =3200+1740 -> 4940 | W20: =4080+4100 -> 8180 | Y20: =2700+5380 -> 8080 | Z20: =2200+3000 -> 5200 | AD20: =238560-229800 -> 8760 | AG20: =+D20 -> 178040 | AH20: =SUM(E20:AE20) -> 143080 | AI20: =14860+100+67600 -> 82560 | AJ20: =+AG20+AH20-AI20 -> 238560 | AL20: 0 | AM20: =+AJ20-AL20 -> 238560 | AO20: 100 | AP20: =14860+67600 -> 82460 | AS20: =+AL20-AR20 -> 0
A21: =+A20+1 -> 17 | B21: 10005776 | C21: POTA NUCAS FR ABIERTAS 0.3-0.5 BL10 S20 | D21: 6700 | E21: 20 | F21: 80 | G21: =20+40 -> 60 | H21: =40+140 -> 180 | I21: 200 | K21: 140 | L21: =60+220 -> 280 | M21: 160 | N21: 120 | O21: 200 | P21: 168 | R21: 160 | S21: 140 | T21: =20+100 -> 120 | U21: =60+60 -> 120 | V21: 200 | W21: 220 | Y21: 180 | Z21: =60+100 -> 160 | AD21: =9720-9608 -> 112 | AG21: =+D21 -> 6700 | AH21: =SUM(E21:AE21) -> 3020 | AJ21: =+AG21+AH21-AI21 -> 9720 | AL21: 0 | AM21: =+AJ21-AL21 -> 9720 | AS21: =+AL21-AR21 -> 0
A22: =+A21+1 -> 18 | B22: 10005781 | C22: POTA NUCAS FR ABIERTAS 1-2 BL10 S20 | D22: 28680 | E22: =760+420 -> 1180 | F22: =600+2020 -> 2620 | G22: =780+1460 -> 2240 | H22: =860+2360 -> 3220 | I22: =380+2340 -> 2720 | K22: =200+1880 -> 2080 | L22: =560+2560 -> 3120 | M22: =860+1940 -> 2800 | N22: 1840 | O22: 2360 | P22: 1400 | R22: =900+1760 -> 2660 | S22: =480+1380 -> 1860 | T22: 980 | U22: =1220+300 -> 1520 | V22: 1020 | W22: =480+1200 -> 1680 | Y22: =260+1420 -> 1680 | Z22: =440+480 -> 920 | AD22: =67740-66580 -> 1160 | AG22: =+D22 -> 28680 | AH22: =SUM(E22:AE22) -> 39060 | AJ22: =+AG22+AH22-AI22 -> 67740 | AL22: 0 | AM22: =+AJ22-AL22 -> 67740 | AS22: =+AL22-AR22 -> 0
A23: =+A22+1 -> 19 | B23: 10009386 | C23: VENTOSAS | D23: 17260 | E23: =100+100 -> 200 | F23: =120+320 -> 440 | G23: 560 | I23: =260+680 -> 940 | K23: 240 | L23: =300+820 -> 1120 | M23: 800 | N23: 600 | O23: 880 | P23: 640 | R23: 560 | S23: =180+540 -> 720 | T23: =20+240 -> 260 | U23: =220+220 -> 440 | V23: 440 | W23: 520 | Y23: 460 | Z23: 400 | AG23: =+D23 -> 17260 | AH23: =SUM(E23:AE23) -> 10220 | AJ23: =+AG23+AH23-AI23 -> 27480 | AL23: 0 | AM23: =+AJ23-AL23 -> 27480 | AS23: =+AL23-AR23 -> 0
A24: =+A23+1 -> 20 | B24: 10007567 | C24: POTA REJOS OR FR LIMPIOS S/COD BL10 S20 | D24: 27900 | E24: =920+240 -> 1160 | F24: =680+2500 -> 3180 | G24: =880+2300 -> 3180 | H24: =820+4940 -> 5760 | I24: 5280 | J24: 300 | K24: =420+5060 -> 5480 | L24: =940+4400 -> 5340 | M24: =540+1920 -> 2460 | N24: 3520 | O24: 5920 | P24: 4480 | R24: 5120 | S24: 3940 | T24: =1240+520 -> 1760 | U24: =680+2420 -> 3100 | V24: 2640 | W24: 4360 | Y24: 4600 | Z24: =180+2400 -> 2580 | AD24: =104880-102060 -> 2820 | AG24: =+D24 -> 27900 | AH24: =SUM(E24:AE24) -> 76980 | AJ24: =+AG24+AH24-AI24 -> 104880 | AL24: 0 | AM24: =+AJ24-AL24 -> 104880 | AS24: =+AL24-AR24 -> 0
A25: =+A24+1 -> 21 | B25: 10009187 | C25: POTA REJOS FR C/B S/U S/V S/OR 0.3 - 0.5 | D25: 140 | AG25: =+D25 -> 140 | AH25: =SUM(E25:AE25) -> 0 | AJ25: =+AG25+AH25-AI25 -> 140 | AL25: 0 | AM25: =+AJ25-AL25 -> 140 | AS25: =+AL25-AR25 -> 0
A26: =+A25+1 -> 22 | B26: 10007161 | C26: POTA REJOS FR C/B S/U S/V S/OR 0.5-1 BL1 | D26: 3020 | E26: 40 | F26: 80 | G26: 180 | H26: 240 | I26: 180 | J26: 60 | K26: 160 | L26: =80+180 -> 260 | M26: 160 | N26: 80 | O26: 180 | P26: 80 | Q26: 80 | R26: 140 | S26: 160 | T26: 80 | U26: =40+80 -> 120 | V26: 80 | W26: 300 | Y26: 200 | Z26: =140+100 -> 240 | AD26: =6240-6120 -> 120 | AG26: =+D26 -> 3020 | AH26: =SUM(E26:AE26) -> 3220 | AJ26: =+AG26+AH26-AI26 -> 6240 | AL26: 0 | AM26: =+AJ26-AL26 -> 6240 | AS26: =+AL26-AR26 -> 0
A27: =+A26+1 -> 23 | B27: 10009186 | C27: POTA REJOS FR S-S/POR C/UV 0.1 - 0.3 BL1 | D27: 200 | AG27: =+D27 -> 200 | AH27: =SUM(E27:AE27) -> 0 | AJ27: =+AG27+AH27-AI27 -> 200 | AL27: 0 | AM27: =+AJ27-AL27 -> 200 | AS27: =+AL27-AR27 -> 0
A28: =+A27+1 -> 24 | B28: 10007162 | C28: POTA REJOS FR C/B S/U S/V S/OR 1-2 BL10 | D28: 203220 | E28: =4180+960 -> 5140 | F28: =5120+7980 -> 13100 | G28: =7840+5440 -> 13280 | H28: =10860+13240 -> 24100 | I28: =8440+13720 -> 22160 | J28: 160 | K28: =7480+13360 -> 20840 | L28: =8740+13920 -> 22660 | M28: =8140+14700 -> 22840 | N28: 10060 | O28: 15560 | P28: 9080 | Q28: 3380 | R28: =8060+12860 -> 20920 | S28: =7320+7520 -> 14840 | T28: =7280+2540 -> 9820 | U28: =5260+7460 -> 12720 | V28: =6980+3980 -> 10960 | W28: =13300+4920 -> 18220 | Y28: =6900+10560 -> 17460 | Z28: =6700+4520 -> 11220 | AD28: =288880-267740 -> 21140 | AG28: =+D28 -> 203220 | AH28: =SUM(E28:AE28) -> 319660 | AI28: =26000+104000+52000+52000 -> 234000 | AJ28: =+AG28+AH28-AI28 -> 288880 | AL28: 0 | AM28: =+AJ28-AL28 -> 288880 | AP28: =26000+104000+52000+52000 -> 234000 | AS28: =+AL28-AR28 -> 0
A29: =+A28+1 -> 25 | B29: 10009658 | C29: POTA REJOS FR 1 UP | D29: 1960 | AG29: =+D29 -> 1960 | AH29: =SUM(E29:AE29) -> 0 | AJ29: =+AG29+AH29-AI29 -> 1960 | AL29: 0 | AM29: =+AJ29-AL29 -> 1960 | AS29: =+AL29-AR29 -> 0
A30: =+A29+1 -> 26 | B30: 10009639 | C30: POTA REJOS FR 2 UP | D30: 28480 | E30: =720+280 -> 1000 | F30: =300+1760 -> 2060 | G30: =680+1360 -> 2040 | H30: =1060+2080 -> 3140 | I30: =760+2120 -> 2880 | K30: =420+2560 -> 2980 | L30: =1280+2340 -> 3620 | M30: =740+1720 -> 2460 | N30: 2000 | O30: 2080 | P30: 1520 | Q30: 860 | R30: =1000+2580 -> 3580 | S30: =740+1320 -> 2060 | T30: =660+600 -> 1260 | U30: =780+1320 -> 2100 | V30: 1280 | W30: =860+1260 -> 2120 | Y30: =680+1320 -> 2000 | Z30: =1140+460 -> 1600 | AD30: =47080-44300 -> 2780 | AG30: =+D30 -> 28480 | AH30: =SUM(E30:AE30) -> 45420 | AI30: 26820 | AJ30: =+AG30+AH30-AI30 -> 47080 | AL30: 0 | AM30: =+AJ30-AL30 -> 47080 | AP30: 26820 | AS30: =+AL30-AR30 -> 0
A31: =+A30+1 -> 27 | B31: 10009239 | C31: POTA FILETE PRE COCIDO S/M S/T C/P S/COD | D31: 102460 | F31: =3540+800 -> 4340 | G31: =5020+5440 -> 10460 | H31: =4600+3380 -> 7980 | I31: 6960 | J31: 700 | K31: 6120 | L31: =7460+9980 -> 17440 | M31: =12120+11300 -> 23420 | N31: 7720 | O31: 10440 | P31: 8940 | R31: 3660 | S31: =5040+7860 -> 12900 | T31: =18080+8920 -> 27000 | U31: =6740+5240 -> 11980 | V31: =10980+2820 -> 13800 | W31: 60 | Z31: 4040 | AD31: =287540-253420 -> 34120 | AG31: =+D31 -> 102460 | AH31: =SUM(E31:AE31) -> 212080 | AI31: 27000 | AJ31: =+AG31+AH31-AI31 -> 287540 | AL31: 0 | AM31: =+AJ31-AL31 -> 287540 | AP31: 27000 | AS31: =+AL31-AR31 -> 0
A32: =+A31+1 -> 28 | B32: 10009251 | C32: POTA FILETE PRE COCIDO S/M S/T 0.6 - 1.0 | D32: 30780 | H32: 760 | K32: 220 | L32: 380 | M32: =820+200 -> 1020 | N32: 340 | O32: 40 | P32: 100 | Q32: 60 | S32: =220+40 -> 260 | T32: =640+40 -> 680 | U32: =100+140 -> 240 | V32: 80 | Z32: 360 | AD32: =36540-35320 -> 1220 | AG32: =+D32 -> 30780 | AH32: =SUM(E32:AE32) -> 5760 | AJ32: =+AG32+AH32-AI32 -> 36540 | AL32: 0 | AM32: =+AJ32-AL32 -> 36540 | AS32: =+AL32-AR32 -> 0
A33: =+A31+1 -> 28 | B33: 10009241 | C33: POTA ALAS PRE COC S/COD BL10 S20 | D33: 260 | AG33: =+D33 -> 260 | AH33: =SUM(E33:AE33) -> 0 | AJ33: =+AG33+AH33-AI33 -> 260 | AL33: 0 | AM33: =+AJ33-AL33 -> 260 | AS33: =+AL33-AR33 -> 0
B34: 10007050 | C34: PPTA RECORTES PRECOCIDA B10 S20 | D34: 11740 | F34: 540 | G34: 380 | H34: =1000+160 -> 1160 | I34: 840 | J34: 160 | K34: 140 | L34: =600+340 -> 940 | M34: =220+1840 -> 2060 | N34: 300 | O34: 180 | P34: 860 | S34: =40+160 -> 200 | T34: =660+1840 -> 2500 | U34: =1200+420 -> 1620 | V34: =940+640 -> 1580 | W34: 40 | Z34: 340 | AD34: =26460-25580 -> 880 | AG34: =+D34 -> 11740 | AH34: =SUM(E34:AE34) -> 14720 | AJ34: =+AG34+AH34-AI34 -> 26460 | AL34: 0 | AM34: =+AJ34-AL34 -> 26460
A35: =+A32+1 -> 29 | C35: FILETE FR REPROCESO x 10 | D35: 4700 | I35: 340 | AD35: 22290 | AG35: =+D35 -> 4700 | AH35: =SUM(E35:AE35) -> 22630 | AI35: 5040 | AJ35: =+AG35+AH35-AI35 -> 22290 | AL35: 0 | AM35: =+AJ35-AL35 -> 22290 | AN35: 5040 | AS35: =+AL35-AR35 -> 0
A36: =+A33+1 -> 29 | C36: RECORTE FRESCO REPROCESO x BL10 | D36: 940 | E36: 40 | J36: 400 | AD36: 830 | AG36: =+D36 -> 940 | AH36: =SUM(E36:AE36) -> 1270 | AI36: =300+1080 -> 1380 | AJ36: =+AG36+AH36-AI36 -> 830 | AL36: 0 | AM36: =+AJ36-AL36 -> 830 | AN36: =300+1080 -> 1380 | AS36: =+AL36-AR36 -> 0
A37: =+A35+1 -> 30 | C37: MEMBRANA FRESCA REPROCESO BL 10 | D37: 1250 | AD37: 2600 | AG37: =+D37 -> 1250 | AH37: =SUM(E37:AE37) -> 2600 | AI37: 1250 | AJ37: =+AG37+AH37-AI37 -> 2600 | AL37: 0 | AM37: =+AJ37-AL37 -> 2600 | AN37: 1250 | AS37: =+AL37-AR37 -> 0
A38: =+A36+1 -> 30 | C38: TELILLA FRESCA REPROCESO BL 10 | D38: 1260 | AD38: 2650 | AG38: =+D38 -> 1260 | AH38: =SUM(E38:AE38) -> 2650 | AI38: 1260 | AJ38: =+AG38+AH38-AI38 -> 2650 | AL38: 0 | AM38: =+AJ38-AL38 -> 2650 | AN38: 1260 | AS38: =+AL38-AR38 -> 0
A39: =+A38+1 -> 31 | B39: 10009337 | C39: POTA RECORTE COCIDO (M) x 15 | D39: 20385 | F39: 390 | G39: 1455 | H39: =1170+360 -> 1530 | K39: 675 | L39: =150+1830 -> 1980 | M39: =1185+615 -> 1800 | N39: 990 | O39: 2250 | P39: 1605 | S39: =1770+1380 -> 3150 | T39: =2900+1035 -> 3935 | U39: 660 | V39: =795+2085 -> 2880 | AD39: =19455-17060 -> 2395 | AG39: =+D39 -> 20385 | AH39: =SUM(E39:AE39) -> 25695 | AI39: 26625 | AJ39: =+AG39+AH39-AI39 -> 19455 | AK39: 52320 | AL39: 0 | AM39: =+AJ39-AL39 -> 19455 | AP39: 26625 | AS39: =+AL39-AR39 -> 0
A40: =+A39+1 -> 32 | B40: 10009332 | C40: POTA RECORTE COCIDO (T) X 15 | D40: 16230 | F40: 375 | G40: 1170 | H40: =1560+120 -> 1680 | L40: =585+2055 -> 2640 | M40: =1905+555 -> 2460 | O40: 1485 | P40: 1985 | S40: =2355+930 -> 3285 | T40: =915+2220 -> 3135 | U40: 495 | V40: 2295 | Z40: 555 | AD40: =14025-11165 -> 2860 | AG40: =+D40 -> 16230 | AH40: =SUM(E40:AE40) -> 24420 | AI40: 26625 | AJ40: =+AG40+AH40-AI40 -> 14025 | AL40: 0 | AM40: =+AJ40-AL40 -> 14025 | AP40: 26625 | AS40: =+AL40-AR40 -> 0
A41: =+A40+1 -> 33 | C41: LANGOSTINO COLA PVD | D41: 66.175 | AG41: =+D41 -> 66.175 | AH41: =SUM(E41:AE41) -> 0 | AI41: 10 | AJ41: =+AG41+AH41-AI41 -> 56.175 | AL41: 0 | AM41: =+AJ41-AL41 -> 56.175 | AS41: =+AL41-AR41 -> 0
A42: =+A41+1 -> 34 | C42: CONCHA ABANICO T/SOLO | D42: 26.775 | AG42: =+D42 -> 26.775 | AH42: =SUM(E42:AE42) -> 0 | AI42: 10 | AJ42: =+AG42+AH42-AI42 -> 16.775 | AL42: 0 | AM42: =+AJ42-AL42 -> 16.775 | AS42: =+AL42-AR42 -> 0
A43: =+A42+1 -> 35 | C43: CABALLA ENTERA FR S/COD | D43: 23.85 | AG43: =+D43 -> 23.85 | AH43: =SUM(E43:AE43) -> 0 | AJ43: =+AG43+AH43-AI43 -> 23.85 | AL43: 0 | AM43: =+AJ43-AL43 -> 23.85 | AS43: =+AL43-AR43 -> 0
A44: =+A43+1 -> 36 | B44: 10009224 | C44: BONITO ENT FR S/COD BL10 S20 | D44: 1120 | AG44: =+D44 -> 1120 | AH44: =SUM(E44:AE44) -> 0 | AJ44: =SUM(G44:AG44) -> 1120 | AL44: 0 | AM44: =+AJ44-AL44 -> 1120 | AS44: =+AL44-AR44 -> 0
AQ45: =SUM(AN45:AP45) -> 0 | AR45: =+AI45-AQ45 -> 0
C46: STOCK AL DIA FEBRERO 2026 | D46: =SUM(D3:D44) -> 1656565.8 | E46: =SUM(E3:E38) -> 26504 | F46: =SUM(F3:F38) -> 65452 | G46: =SUM(G3:G38) -> 75726 | H46: =SUM(H3:H38) -> 110724 | I46: =SUM(I3:I38) -> 152274 | J46: =SUM(J3:J38) -> 93072 | K46: =SUM(K3:K38) -> 116320 | L46: =SUM(L3:L38) -> 105660 | ... AD46: =SUM(AD3:AD38) -> 346782 | AE46: =SUM(AE3:AE44) -> 0 | AF46: =SUM(AF3:AF38) -> 0 | AG46: =SUM(AG3:AG44) -> 1656565.8 | AH46: =SUM(AH3:AH44) -> 2268337 | AI46: =SUM(AI3:AI44) -> 1759000 | AJ46: =SUM(AJ3:AJ45) -> 2165902.8 | AL46: =SUM(AL1:AL44) -> 0 | AM46: =SUM(AM1:AM44) -> 2165902.8 | AN46: =SUM(AN1:AN44) -> 8930 | AO46: =SUM(AO1:AO44) -> 780 | AP46: =SUM(AP1:AP44) -> 1749270 | AQ46: =+AP46+AN46+AO46+20 -> 1759000 | BD46: =SUM(BD4:BD45) -> 0 | BE46: =+BD46-AJ46 -> -2165902.8
AG49: STOCK FEBRERO 2026 | AJ49: =+AJ46/1000 -> 2165.9028 | AM49: Resumen | AP49: EMBARQUE | AQ49: DIFERENCUA
AG50: Embarques | AJ50: 0 | AM50: Embarcado: | AN50: =+AP46/1000 -> 1749.27 | AO50: 1749.28 | AP50: =+AN50-AO50 -> -0.01 | AQ50: 0
AJ51: 0 | AM51: Reproceso: | AN51: =+AN46/1000 -> 8.93
AJ52: 0 | AM52: Muestreo | AN52: =+AO46/1000 -> 0.78
AG53: NUEVO STOCK PARA ACTUALIZAR | AJ53: =+AJ49-AJ50-AJ51-AJ52 -> 2165.9028 | AN53: =SUM(AN50:AN52) -> 1758.98

Sheet Enero2026
A1: ID | B1: CODIGO | C1: MATERIAL | D1: FECHAS DIAS RECEPCION PRODUCCION ENERO 2026 | X1: MOVIMIENTO INVENTARIO | AC1: DATA | AD1: DIFERENCIA
B2: SAP | D2: STOCK INICIO | E2: 46037 | F2: 46038 | G2: 46039 | H2: 46040 | I2: 46041 | J2: 46042 | K2: 46043 | L2: 46044 | M2: 46045 | N2: 46046 | O2: 46047 | P2: 46048 | Q2: 46049 | R2: 46050 | S2: 46051 | T2: 46052 | U2: 46053 | V2: 46054 | X2: Stock Inicial | Y2: INGRESOS | Z2: SALIDAS | AA2: STOCK KG | AC2: MANUAL | AE2: REPROCESO | AF2: MUESTREO | AG2: EMBARQUE
A3: 1 | B3: 10006668 | C3: POTA ALAS FR C/P C/C < 0.5 BL10 S20 | D3: 180 | X3: =+D3 -> 180 | Y3: =SUM(E3:V3) -> 0 | AA3: =+X3+Y3-Z3 -> 180 | AB3: =+X3-AA3 -> 0 | AC3: 180 | AD3: =+AA3-AC3 -> 0
A4: =+A3+1 -> 2 | B4: 10009178 | C4: POTA ALAS FR C/P C/C (B) S/COD BL10 S20 | D4: 12980 | E4: 120 | F4: =20+140 -> 160 | G4: =60+100 -> 160 | H4: 40 | I4: =240+260 -> 500 | J4: =80+180 -> 260 | L4: =200+180 -> 380 | M4: =40+200 -> 240 | N4: 260 | O4: 540 | Q4: =120+20 -> 140 | R4: =200+200 -> 400 | S4: =620+220 -> 840 | T4: 200 | U4: =40+20 -> 60 | V4: 620 | X4: =+D4 -> 12980 | Y4: =SUM(E4:V4) -> 4920 | AA4: =+X4+Y4-Z4 -> 17900 | AC4: 17900 | AD4: =+AA4-AC4 -> 0
A5: =+A4+1 -> 3 | B5: 10006719 | C5: POTA ALAS FR C/P C/C 0.5-1 BL10 S20 | D5: 660 | X5: =+D5 -> 660 | Y5: =SUM(E5:V5) -> 0 | AA5: =+X5+Y5-Z5 -> 660 | AC5: 660 | AD5: =+AA5-AC5 -> 0
A6: =+A5+1 -> 4 | B6: 10009265 | C6: POTA ALAS FR C/P C/C 0.3 - 0.5 BL10 S20 | D6: 680 | X6: =+D6 -> 680 | Y6: =SUM(E6:V6) -> 0 | AA6: =+X6+Y6-Z6 -> 680 | AC6: 680 | AD6: =+AA6-AC6 -> 0
A7: =+A6+1 -> 5 | B7: 10006720 | C7: POTA ALAS FR C/P C/C 1-2 BL10 S20 | D7: 95920 | E7: =8900+8240 -> 17140 | F7: =5760+5380 -> 11140 | G7: =7560+4900 -> 12460 | H7: 14360 | I7: =20740+5980 -> 26720 | J7: =20280+5820 -> 26100 | K7: 3860 | L7: =12440+2900 -> 15340 | M7: =13740+4060 -> 17800 | N7: 19440 | O7: 22640 | P7: 8660 | Q7: =3980+2680 -> 6660 | R7: =26300+13960 -> 40260 | S7: =22340+10420 -> 32760 | T7: =10980+320 -> 11300 | U7: =5240+2460 -> 7700 | V7: 18080 | X7: =+D7 -> 95920 | Y7: =SUM(E7:V7) -> 312420 | Z7: =80+69700 -> 69780 | AA7: =+X7+Y7-Z7 -> 338560 | AC7: 338560 | AD7: =+AA7-AC7 -> 0 | AF7: 80 | AG7: 69700
A8: =+A7+1 -> 6 | B8: 10006722 | C8: POTA ALAS FR C/P C/C 2-UP BL10 S20 | D8: 120 | X8: =+D8 -> 120 | Y8: =SUM(E8:V8) -> 0 | AA8: =+X8+Y8-Z8 -> 120 | AC8: 120 | AD8: =+AA8-AC8 -> 0
A9: =+A8+1 -> 7 | C9: POTA ALAS PRE COC 3-UP BL10 S20 | P9: 6390 | Q9: =4680+5292 -> 9972 | R9: 288 | X9: =+D9 -> 0 | Y9: =SUM(E9:V9) -> 16650 | AA9: =+X9+Y9-Z9 -> 16650 | AC9: 16650 | AD9: =+AA9-AC9 -> 0
C10: POTA ALAS PRE COC B BL10 S20 | Q10: =1332+468 -> 1800 | R10: 54 | X10: =+D10 -> 0 | Y10: =SUM(E10:V10) -> 1854 | AA10: =+X10+Y10-Z10 -> 1854 | AC10: 1854 | AD10: =+AA10-AC10 -> 0
A11: 8 | B11: 10009207 | C11: POTA LABIOS FR S/COD BL10 S20 | D11: 6520 | E11: 300 | F11: 460 | G11: 440 | I11: 380 | J11: 200 | K11: 60 | L11: =100+160 -> 260 | M11: 540 | N11: 60 | P11: 1060 | Q11: 380 | R11: =240+260 -> 500 | S11: =400+400 -> 800 | T11: 40 | U11: 340 | X11: =+D11 -> 6520 | Y11: =SUM(E11:V11) -> 5820 | AA11: =+X11+Y11-Z11 -> 12340 | AC11: 12340 | AD11: =+AA11-AC11 -> 0
A12: =+A11+1 -> 9 | B12: 10007969 | C12: POTA CONOS | D12: 33140 | E12: 1340 | F12: 2140 | G12: 2280 | I12: =720+1540 -> 2260 | J12: 1020 | K12: =340+480 -> 820 | L12: 760 | M12: =940+1500 -> 2440 | N12: 3440 | P12: =120+3620 -> 3740 | Q12: =200+3180 -> 3380 | R12: 3380 | S12: =240+1880 -> 2120 | T12: 200 | U12: 2520 | X12: =+D12 -> 33140 | Y12: =SUM(E12:V12) -> 31840 | Z12: =24000+20 -> 24020 | AA12: =+X12+Y12-Z12 -> 40960 | AC12: 40960 | AD12: =+AA12-AC12 -> 0 | AF12: 20 | AG12: =24000 -> 24000
A13: =+A12+1 -> 10 | B13: 10004433 | C13: POTA FILETE C/M C/T FR 0.5-1 BL10 S20 | D13: 300 | X13: =+D13 -> 300 | Y13: =SUM(E13:V13) -> 0 | AA13: =+X13+Y13-Z13 -> 300 | AC13: =120+180 -> 300 | AD13: =+AA13-AC13 -> 0
A14: =+A13+1 -> 11 | B14: 10004434 | C14: POTA FILETE C/M C/T FR 1-2 BL10 S20 | D14: 1120 | X14: =+D14 -> 1120 | Y14: =SUM(E14:V14) -> 0 | AA14: =+X14+Y14-Z14 -> 1120 | AC14: 1120 | AD14: =+AA14-AC14 -> 0
A15: =+A14+1 -> 12 | B15: 10005721 | C15: POTA FILETE C/M C/T FR 2-4 (B) BL10 S20 | D15: 155380 | E15: =14860+12480 -> 27340 | F15: =19020+30620 -> 49640 | G15: =29320+25140 -> 54460 | I15: =22180+240 -> 22420 | J15: 3500 | K15: 7760 | L15: 3800 | M15: =6620+5060 -> 11680 | N15: =6660+20840 -> 27500 | O15: 19200 | P15: =21740+11680 -> 33420 | Q15: =42220+16840 -> 59060 | R15: =27860+14020 -> 41880 | S15: =36440+4560 -> 41000 | U15: =21900+27300 -> 49200 | X15: =+D15 -> 155380 | Y15: =SUM(E15:V15) -> 451860 | Z15: =60+135000 -> 135060 | AA15: =+X15+Y15-Z15 -> 472180 | AC15: 472180 | AD15: =+AA15-AC15 -> 0 | AF15: 60 | AG15: =135000 -> 135000
A16: =+A15+1 -> 13 | B16: 10004435 | C16: POTA FILETE C/M C/T FR 2-4 BL10 S20 | D16: 55940 | E16: =3020+5980 -> 9000 | F16: =1280+6980 -> 8260 | G16: 5160 | I16: =920+1580 -> 2500 | J16: 920 | K16: 1020 | L16: =2140+3420 -> 5560 | M16: =2020+3500 -> 5520 | N16: 1820 | P16: =600+1060 -> 1660 | Q16: 1420 | R16: 540 | S16: =2960+2860 -> 5820 | T16: 820 | U16: 6480 | X16: =+D16 -> 55940 | Y16: =SUM(E16:V16) -> 56500 | Z16: =23600+23800 -> 47400 | AA16: =+X16+Y16-Z16 -> 65040 | AC16: 65040 | AD16: =+AA16-AC16 -> 0 | AG16: =23600+23800 -> 47400
A17: =+A16+1 -> 14 | B17: 10009184 | C17: POTA NUCAS FR ABIERTAS 0.1 - 0.3 BL10 S2 | D17: 940 | X17: =+D17 -> 940 | Y17: =SUM(E17:V17) -> 0 | AA17: =+X17+Y17-Z17 -> 940 | AC17: =180+760 -> 940 | AD17: =+AA17-AC17 -> 0
A18: =+A17+1 -> 15 | B18: 10009271 | C18: POTA NUCAS FR CERRADA 0.1 - 0.3 BL10 S2 | D18: 240 | X18: =+D18 -> 240 | Y18: =SUM(E18:V18) -> 0 | AA18: =+X18+Y18-Z18 -> 240 | AC18: 240 | AD18: =+AA18-AC18 -> 0
A19: =+A18+1 -> 16 | B19: 10005779 | C19: POTA NUCAS FR ABIERTAS 0.5-1 BL10 S20 | D19: 96180 | E19: =700+3300 -> 4000 | F19: =1560+4720 -> 6280 | G19: =2420+4220 -> 6640 | I19: =3980+2940 -> 6920 | J19: 3160 | K19: =980+2760 -> 3740 | L19: 1160 | M19: =4020+2700 -> 6720 | N19: =1320+5600 -> 6920 | P19: =4000+5320 -> 9320 | Q19: =2520+7060 -> 9580 | R19: =1920+6740 -> 8660 | S19: =280+4600 -> 4880 | T19: 560 | U19: =1860+4520 -> 6380 | X19: =+D19 -> 96180 | Y19: =SUM(E19:V19) -> 84920 | Z19: =40+20+3000 -> 3060 | AA19: =+X19+Y19-Z19 -> 178040 | AC19: 178040 | AD19: =+AA19-AC19 -> 0 | AF19: =40+20 -> 60 | AG19: =3000 -> 3000
A20: =+A19+1 -> 17 | B20: 10005776 | C20: POTA NUCAS FR ABIERTAS 0.3-0.5 BL10 S20 | D20: 4900 | E20: 100 | F20: =20+100 -> 120 | I20: =60+180 -> 240 | J20: 140 | L20: =80+20 -> 100 | M20: =40+60 -> 100 | N20: =140+0 -> 140 | P20: 180 | Q20: =60+160 -> 220 | R20: 180 | S20: 120 | T20: 0 | U20: 160 | X20: =+D20 -> 4900 | Y20: =SUM(E20:V20) -> 1800 | AA20: =+X20+Y20-Z20 -> 6700 | AC20: 6700 | AD20: =+AA20-AC20 -> 0
A21: =+A20+1 -> 18 | B21: 10005781 | C21: POTA NUCAS FR ABIERTAS 1-2 BL10 S20 | D21: 17040 | E21: 1720 | F21: =640+1520 -> 2160 | G21: =720+1640 -> 2360 | I21: =1260+560 -> 1820 | J21: 660 | K21: 300 | L21: =980+360 -> 1340 | M21: =1640+1500 -> 3140 | N21: 2040 | P21: =780+2240 -> 3020 | Q21: =860+2340 -> 3200 | R21: =960+1580 -> 2540 | S21: =360+1780 -> 2140 | T21: 340 | U21: =140+1800 -> 1940 | X21: =+D21 -> 17040 | Y21: =SUM(E21:V21) -> 28720 | Z21: =40+17040 -> 17080 | AA21: =+X21+Y21-Z21 -> 28680 | AC21: 28680 | AD21: =+AA21-AC21 -> 0 | AF21: 40 | AG21: =17040 -> 17040
A22: =+A21+1 -> 19 | B22: 10009386 | C22: VENTOSAS | D22: 9860 | E22: 500 | F22: 480 | G22: 520 | I22: =260+280 -> 540 | J22: 260 | K22: 100 | L22: =140+220 -> 360 | M22: 600 | N22: 760 | P22: 900 | Q22: 860 | R22: 440 | S22: =20+500 -> 520 | T22: 40 | U22: 520 | X22: =+D22 -> 9860 | Y22: =SUM(E22:V22) -> 7400 | AA22: =+X22+Y22-Z22 -> 17260 | AC22: 17260 | AD22: =+AA22-AC22 -> 0
A23: =+A22+1 -> 20 | B23: 10007567 | C23: POTA REJOS OR FR LIMPIOS S/COD BL10 S20 | D23: 30440 | E23: =220+2060 -> 2280 | F23: 3600 | G23: =620+3060 -> 3680 | I23: =380+3340 -> 3720 | J23: 1680 | K23: =560+0 -> 560 | L23: =1320+780 -> 2100 | M23: =940+2960 -> 3900 | N23: 4200 | P23: =1100+4080 -> 5180 | Q23: =540+2220 -> 2760 | R23: =2060+3500 -> 5560 | S23: =1680+1760 -> 3440 | T23: 360 | U23: =880+2520 -> 3400 | X23: =+D23 -> 30440 | Y23: =SUM(E23:V23) -> 46420 | Z23: =22660+26300 -> 48960 | AA23: =+X23+Y23-Z23 -> 27900 | AC23: 27900 | AD23: =+AA23-AC23 -> 0 | AG23: =22660+26300 -> 48960
A24: =+A23+1 -> 21 | B24: 10009187 | C24: POTA REJOS FR C/B S/U S/V S/OR 0.3 - 0.5 | D24: 140 | X24: =+D24 -> 140 | Y24: =SUM(E24:V24) -> 0 | AA24: =+X24+Y24-Z24 -> 140 | AC24: 140 | AD24: =+AA24-AC24 -> 0
A25: =+A24+1 -> 22 | B25: 10007161 | C25: POTA REJOS FR C/B S/U S/V S/OR 0.5-1 BL1 | D25: 13760 | E25: 180 | F25: 260 | G25: 240 | I25: =20+220 -> 240 | J25: 160 | K25: 20 | L25: =140+80 -> 220 | M25: =20+220 -> 240 | N25: 180 | O25: 60 | P25: =140+220 -> 360 | Q25: =80+180 -> 260 | R25: =60+200 -> 260 | S25: 120 | U25: =120+100 -> 220 | X25: =+D25 -> 13760 | Y25: =SUM(E25:V25) -> 3020 | Z25: 13760 | AA25: =+X25+Y25-Z25 -> 3020 | AC25: 3020 | AD25: =+AA25-AC25 -> 0 | AG25: 13760
A26: =+A25+1 -> 23 | B26: 10009186 | C26: POTA REJOS FR S-S/POR C/UV 0.1 - 0.3 BL1 | D26: 180 | J26: 20 | X26: =+D26 -> 180 | Y26: =SUM(E26:V26) -> 20 | AA26: =+X26+Y26-Z26 -> 200 | AC26: 200 | AD26: =+AA26-AC26 -> 0
A27: =+A26+1 -> 24 | B27: 10007162 | C27: POTA REJOS FR C/B S/U S/V S/OR 1-2 BL10 | D27: 49100 | E27: =4140+5100 -> 9240 | F27: =8900+5680 -> 14580 | G27: =4320+11660 -> 15980 | I27: =6980+9040 -> 16020 | J27: =1220+5800 -> 7020 | K27: 2200 | L27: =6960+2100 -> 9060 | M27: =8860+8000 -> 16860 | N27: =5300+10580 -> 15880 | O27: 1580 | P27: =7840+12220 -> 20060 | Q27: =9120+11040 -> 20160 | R27: =9460+12660 -> 22120 | S27: =5220+5700 -> 10920 | T27: =1260+180 -> 1440 | U27: =10460+3960 -> 14420 | X27: =+D27 -> 49100 | Y27: =SUM(E27:V27) -> 197540 | Z27: =40240+20+3160 -> 43420 | AA27: =+X27+Y27-Z27 -> 203220 | AC27: 203220 | AD27: =+AA27-AC27 -> 0 | AF27: 20 | AG27: =40240+3160 -> 43400
A28: =+A27+1 -> 25 | B28: 10009658 | C28: POTA REJOS FR 1 UP | D28: 1960 | X28: =+D28 -> 1960 | Y28: =SUM(E28:V28) -> 0 | AA28: =+X28+Y28-Z28 -> 1960 | AC28: 1960 | AD28: =+AA28-AC28 -> 0
A29: =+A28+1 -> 26 | B29: 10009639 | C29: POTA REJOS FR 2 UP | D29: 3960 | E29: =380+960 -> 1340 | F29: =40+1880 -> 1920 | G29: 1820 | I29: =940+1040 -> 1980 | J29: 620 | K29: 320 | L29: =620+380 -> 1000 | M29: =720+1480 -> 2200 | N29: 1780 | O29: 540 | P29: =840+2020 -> 2860 | Q29: =820+2280 -> 3100 | R29: =940+2200 -> 3140 | S29: =780+940 -> 1720 | T29: =120+120 -> 240 | U29: =1100+1180 -> 2280 | X29: =+D29 -> 3960 | Y29: =SUM(E29:V29) -> 26860 | Z29: 2340 | AA29: =+X29+Y29-Z29 -> 28480 | AC29: 28480 | AD29: =+AA29-AC29 -> 0 | AG29: 2340
A30: =+A29+1 -> 27 | B30: 10009239 | C30: POTA FILETE PRE COCIDO S/M S/T C/P S/COD | D30: 420 | I30: 3220 | J30: =8980+4680 -> 13660 | K30: 4900 | L30: 7600 | M30: =3140+6620 -> 9760 | N30: 11060 | O30: 8160 | Q30: 5020 | R30: =5020+5600 -> 10620 | S30: =8360+10600 -> 18960 | T30: =6440+2640 -> 9080 | X30: =+D30 -> 420 | Y30: =SUM(E30:V30) -> 102040 | AA30: =+X30+Y30-Z30 -> 102460 | AC30: 102460 | AD30: =+AA30-AC30 -> 0
A31: =+A30+1 -> 28 | B31: 10009251 | C31: POTA FILETE PRE COCIDO S/M S/T 0.6 - 1.0 | D31: 30140 | N31: 640 | X31: =+D31 -> 30140 | Y31: =SUM(E31:V31) -> 640 | AA31: =+X31+Y31-Z31 -> 30780 | AC31: 30780 | AD31: =+AA31-AC31 -> 0
A32: =+A30+1 -> 28 | B32: 10009241 | C32: POTA ALAS PRE COC S/COD BL10 S20 | D32: 260 | X32: =+D32 -> 260 | Y32: =SUM(E32:V32) -> 0 | AA32: =+X32+Y32-Z32 -> 260 | AC32: 260 | AD32: =+AA32-AC32 -> 0
B33: 10007050 | C33: PPTA RECORTES PRECOCIDA B10 S20 | D33: 0 | J33: =1080+900 -> 1980 | K33: 680 | L33: 0 | M33: 1160 | N33: 2340 | O33: 860 | Q33: 500 | R33: =720+0 -> 720 | S33: =1240+960 -> 2200 | T33: 1300 | X33: =+D33 -> 0 | Y33: =SUM(E33:V33) -> 11740 | AA33: =+X33+Y33-Z33 -> 11740 | AC33: 11740 | AD33: =+AA33-AC33 -> 0
A34: =+A31+1 -> 29 | C34: FILETE FR REPROCESO x 10 | D34: 1130 | F34: 860 | V34: 2710 | X34: =+D34 -> 1130 | Y34: =SUM(E34:V34) -> 3570 | AA34: =+X34+Y34-Z34 -> 4700 | AC34: =1990+2710 -> 4700 | AD34: =+AA34-AC34 -> 0
A35: =+A32+1 -> 29 | C35: RECORTE FRESCO REPROCESO x BL10 | D35: 300 | F35: 120 | G35: 220 | M35: 20 | O35: 80 | R35: 20 | S35: =40+20 -> 60 | U35: 120 | X35: =+D35 -> 300 | Y35: =SUM(E35:V35) -> 640 | AA35: =+X35+Y35-Z35 -> 940 | AC35: =300+640 -> 940 | AD35: =+AA35-AC35 -> 0
A36: =+A34+1 -> 30 | C36: MEMBRANA FRESCA REPROCESO BL 10 | D36: 1250 | X36: =+D36 -> 1250 | Y36: =SUM(E36:V36) -> 0 | AA36: =+X36+Y36-Z36 -> 1250 | AC36: 1250 | AD36: =+AA36-AC36 -> 0
A37: =+A35+1 -> 30 | C37: TELILLA FRESCA REPROCESO BL 10 | D37: 1260 | X37: =+D37 -> 1260 | Y37: =SUM(E37:V37) -> 0 | AA37: =+X37+Y37-Z37 -> 1260 | AC37: 1260 | AD37: =+AA37-AC37 -> 0
A38: =+A37+1 -> 31 | B38: 10009337 | C38: POTA RECORTE COCIDO (M) x 15 | D38: 9375 | J38: 1320 | K38: 945 | M38: 870 | N38: 1890 | O38: 810 | R38: 1125 | S38: =375+2730 -> 3105 | T38: =450+495 -> 945 | X38: =+D38 -> 9375 | Y38: =SUM(E38:V38) -> 11010 | AA38: =+X38+Y38-Z38 -> 20385 | AB38: 52320 | AC38: 20385 | AD38: =+AA38-AC38 -> 0
A39: =+A38+1 -> 32 | B39: 10009332 | C39: POTA RECORTE COCIDO (T) X 15 | D39: 5565 | J39: =885+315 -> 1200 | K39: 870 | M39: 780 | N39: 2355 | O39: 885 | R39: 1065 | S39: 2445 | T39: =885+180 -> 1065 | X39: =+D39 -> 5565 | Y39: =SUM(E39:V39) -> 10665 | AA39: =+X39+Y39-Z39 -> 16230 | AC39: 16230 | AD39: =+AA39-AC39 -> 0
A40: =+A39+1 -> 33 | C40: LANGOSTINO COLA PVD | D40: 66.175 | X40: =+D40 -> 66.175 | Y40: =SUM(E40:V40) -> 0 | AA40: =+X40+Y40-Z40 -> 66.175 | AC40: 66.175 | AD40: =+AA40-AC40 -> 0
A41: =+A40+1 -> 34 | C41: CONCHA ABANICO T/SOLO | D41: 26.775 | X41: =+D41 -> 26.775 | Y41: =SUM(E41:V41) -> 0 | AA41: =+X41+Y41-Z41 -> 26.775 | AC41: 26.775 | AD41: =+AA41-AC41 -> 0
A42: =+A41+1 -> 35 | C42: CABALLA ENTERA FR S/COD | D42: 23.85 | X42: =+D42 -> 23.85 | Y42: =SUM(E42:V42) -> 0 | AA42: =+X42+Y42-Z42 -> 23.85 | AC42: 23.85 | AD42: =+AA42-AC42 -> 0
A43: =+A42+1 -> 36 | B43: 10009224 | C43: BONITO ENT FR S/COD BL10 S20 | D43: 1120 | X43: =+D43 -> 1120 | Y43: =SUM(E43:V43) -> 0 | AA43: =SUM(G43:X43) -> 1120 | AC43: 1120 | AD43: =+AA43-AC43 -> 0
C45: STOCK AL ENE 2026 | D45: =SUM(D3:D43) -> 642576.8 | E45: =SUM(E3:E37) -> 74600 | F45: =SUM(F3:F43) -> 102180 | G45: =SUM(G3:G43) -> 106420 | H45: =SUM(H3:H43) -> 14400 | I45: =SUM(I3:I43) -> 89480 | J45: =SUM(J3:J43) -> 63880 | K45: =SUM(K3:K43) -> 28155 | L45: =SUM(L3:L43) -> 49040 | M45: =SUM(M3:M43) -> 84570 | ... V45: =SUM(V3:V43) -> 21410 | W45: =SUM(W3:W37) -> 0 | X45: =SUM(X3:X43) -> 642576.8 | Y45: =SUM(Y3:Y43) -> 1418869 | Z45: =SUM(Z3:Z43) -> 404880 | AA45: =SUM(AA3:AA44) -> 1656565.8 | AC45: =SUM(AC1:AC43) -> 1656565.8 | AD45: =SUM(AD1:AD43) -> 0 | AE45: =SUM(AE1:AE43) -> 0 | AF45: =SUM(AF1:AF43) -> 280 | AG45: =SUM(AG1:AG43) -> 404600 | AQ45: =SUM(AQ4:AQ44) -> 0 | AR45: =+AQ45-AA45 -> -1656565.8
X48: STOCK ENERO 2026 | AA48: =+AA45/1000 -> 1656.5658 | AD48: Resumen | AG48: EMBARQUE
X49: Embarques | AD49: Embarcado: | AE49: =+AG45/1000 -> 404.6 | AG49: 0
AD50: Reproceso: | AE50: =+AE45/1000 -> 0
AD51: Muestreo | AE51: =+AF45/1000 -> 0.28 | AG51: =+AG45/1000 -> 404.6
X52: NUEVO STOCK PARA ACTUALIZAR | AA52: =+AA48-AA49-AA50-AA51 -> 1656.5658 | AE52: =SUM(AE49:AE51) -> 404.88

Sheet Estadistica
B3: PRODUCCION 2026
B4: ENERO | C4: =+Enero2026!Y45 -> 1418869 | D4: Tn
B5: FEBRERO | C5: =+Febrero2026!AH46 -> 2268337 | D5: Tn
B6: MARZO | C6: =+Marzo2026!AG50 -> 1541091 | D6: Tn
B7: ABRIL | C7: =+Abril2026!O59 -> 295259 | D7: Tn
C8: =SUM(C4:C6) -> 5228297 | D8: Tn
