Workbook

Sheet Gráficos
B3: PERU FROST - RESUMEN RESULTADOS CONGELADOS 2026 (MILES US$)
B4: Concepto | C4: 46023 | D4: 46054 | E4: 46082 | F4: 46113 | G4: Acum 2026
B5: TM Materia Prima | C5: =[1]Resumen!$D$4 -> 1877.215 | D5: =[1]Resumen!$D$5 -> 3149.786 | E5: =[1]Resumen!$D$6 -> 2255.518 | F5: =[1]Resumen!$D$7 -> 2853.189 | G5: =SUM(C5:F5) -> 10135.708
B6: TM Vendidas PT | C6: =TD!B7 -> 248 | D6: =TD!C7 -> 1634.3 | E6: =TD!D7 -> 1995.8 | F6: =TD!E7 -> 2110.11 | G6: =TD!F7 -> 1978.33
B7: Venta | C7: =TD!B8 -> 564615.28 | D7: =TD!C8 -> 2769824.5 | E7: =TD!D8 -> 3896418.3 | F7: =TD!E8 -> 4888920 | G7: =TD!F8 -> 5016103.5
B8: Utilidad Neta | C8: =TD!B16 -> -96824.986 | D8: =TD!C16 -> -535236.79 | E8: =TD!D16 -> -326649.27 | F8: =TD!E16 -> 89405.43 | G8: =TD!F16 -> 401885.57
B9: Margen Neto % | C9: =C8/C7 -> -0.17148843 | D9: =D8/D7 -> -0.19323852 | E9: =E8/E7 -> -0.083833214 | F9: =F8/F7 -> 0.018287358 | G9: =G8/G7 -> 0.080119074
B12: 1. RESULTADOS INTERNOS
B62: 2. BENCHMARK INDUSTRIA PERUANA DE CONGELADOS (VERITRADE)
B87: Top 15 Exportadores — Productos Congelados (Alas, Filete, Nuca, Tentáculo, Reproductor) | J87: Top 15 Exportadores — Productos Cocidos (Alas Cocidas, Filete Daruma)
B89: Nro | C89: Exportador | D89: Valor FOB (US$) | E89: TM | F89: Precio por TM | J89: Nro | K89: Exportador | L89: Valor FOB (US$) | M89: TM | N89: Precio por TM
B90: 1 | C90: Industrial Pesquera Santa Monica S.A. | D90: 12800672 | E90: 7371.2 | F90: 1737 | J90: 1 | K90: Costa Mira Sociedad Anonima Cerrada | L90: 9211788 | M90: 2579.8 | N90: 3571
B91: 2 | C91: Pesquera Hermanos Cordova S.A.C. | D91: 11792528 | E91: 7242.6 | F91: 1628 | J91: 2 | K91: KSL S.A.C. | L91: 5319083 | M91: 1670.5 | N91: 3184
B92: 3 | C92: Oceano Seafood S.A. | D92: 11724680 | E92: 6746.5 | F92: 1738 | J92: 3 | K92: Pacific Freezing Company S.A.C. | L92: 4286058 | M92: 1338 | N92: 3203
B93: 4 | C93: Productora Andina De Congelados S.R.L. | D93: 8847640 | E93: 5227.2 | F93: 1693 | J93: 4 | K93: Oceano Seafood S.A. | L93: 4050574 | M93: 1190.4 | N93: 3403
B94: 5 | C94: Costa Mira Sociedad Anonima Cerrada | D94: 8496998 | E94: 4421.2 | F94: 1922 | J94: 5 | K94: Frigosa Sociedad S.A.C. | L94: 3921103 | M94: 1215 | N94: 3227
B95: 6 | C95: Novaperu S.A.C. | D95: 6857126 | E95: 3973.8 | F95: 1726 | J95: 6 | K95: Dexim Srl | L95: 3883786 | M95: 1076.8 | N95: 3607
B96: 7 | C96: Peru Frost Sociedad Anonima Cerrada | D96: 6231879 | E96: 3981.4 | F96: 1565 | J96: 7 | K96: Inversiones Holding Peru Sociedad Anonim | L96: 2905633 | M96: 847.7 | N96: 3428
B97: 8 | C97: Esmeralda Corp S.A.C. | D97: 6229395 | E97: 3736 | F97: 1667 | J97: 8 | K97: Corporacion Pesquera Del Mar Sociedad An | L97: 2751416 | M97: 796 | N97: 3457
B98: 9 | C98: Proveedora De Productos Marinos Sociedad | D98: 6166547 | E98: 3730.3 | F98: 1653 | J98: 9 | K98: Mik Carpe S.A.C. | L98: 2475284 | M98: 735 | N98: 3368
B99: 10 | C99: Peruvian Sea Food S.A. | D99: 6164559 | E99: 3692.9 | F99: 1669 | J99: 10 | K99: Seafrost S.A.C. | L99: 2135285 | M99: 602.9 | N99: 3542
B100: 11 | C100: Pesquera Supercetus S.A.C. | D100: 5928869 | E100: 3562.1 | F100: 1664 | J100: 11 | K100: Pesquera Exalmar S.A.A. | L100: 1926814 | M100: 563.2 | N100: 3421
B101: 12 | C101: Transmarina Del Peru S.A.C. | D101: 5879029 | E101: 3591.3 | F101: 1637 | J101: 12 | K101: Refrigerados Fisholg & Hijos Sociedad An | L101: 1802223 | M101: 539.5 | N101: 3340
... B104: 15 | C104: Seafrost S.A.C. | D104: 5556358 | E104: 3119.3 | F104: 1781 | J104: 15 | K104: Industrial Pesquera Santa Monica S.A. | L104: 1603048 | M104: 475.7 | N104: 3370

Sheet TD
A2: ANÁLISIS DE RENTABILIDAD
A4: EEFF PERU FROST (USD) | AG4: Enero | AH4: Febrero | AI4: Marzo | AJ4: Abril | AK4: Real | AL4: Budget
B5: Etiquetas de columna | J5: ANÁLISIS UNITARIO | T5: ANÁLISIS VÉRTICAL | AF5: Venta CFR | AG5: =B8/1000 -> 564.61528 | AH5: =C8/1000 -> 2769.8245 | AI5: =D8/1000 -> 3896.4183 | AJ5: =E8/1000 -> 4888.92 | AK5: =F8/1000 -> 5016.1035 | AL5: =H8/1000 -> 0
A6: Valores | B6: ENERO | C6: FEBRERO | D6: MARZO | E6: ABRIL | F6: MAYO | G6: Total general | J6: NOMBRE | K6: ENERO | L6: FEBRERO | M6: MARZO | N6: ABRIL | O6: TOTAL | T6: NOMBRE | U6: ENERO | V6: FEBRERO | W6: MARZO | X6: ABRIL | Y6: MAYO | Z6: TOTAL | AF6: Utilidad Neta | AG6: =B16/1000 -> -96.824986 | AH6: =C16/1000 -> -535.23679 | AI6: =D16/1000 -> -326.64927 | AJ6: =E16/1000 -> 89.40543 | AK6: =F16/1000 -> 401.88557 | AL6: =H16/1000 -> 0
A7: Suma de Cantidad | B7: 248 | C7: 1634.3 | D7: 1995.8 | E7: 2110.11 | F7: 1978.33 | G7: 7966.54
A8: Suma de VALOR CFR | B8: 564615.28 | C8: 2769824.5 | D8: 3896418.3 | E8: 4888920 | F8: 5016103.5 | G8: 17135882 | J8: Suma de VALOR CFR | K8: =B8/B$7 -> 2276.6745 | L8: =C8/C$7 -> 1694.8079 | M8: =D8/D$7 -> 1952.309 | N8: =E8/E$7 -> 2316.9029 | O8: =F8/F$7 -> 2535.5242 | T8: Suma de VALOR CFR | U8: =B8/B$8 -> 1 | V8: =C8/C$8 -> 1 | W8: =D8/D$8 -> 1 | X8: =E8/E$8 -> 1 | Y8: =F8/F$8 -> 1 | Z8: =G8/G$8 -> 1
A9: Suma de COSTO VENTAS | B9: 435516.57 | C9: 2818814 | D9: 3665924.7 | E9: 4170536.7 | F9: 4155714.9 | G9: 15246507 | J9: Suma de COSTO VENTAS | K9: =B9/B$7 -> 1756.1152 | L9: =C9/C$7 -> 1724.7837 | M9: =D9/D$7 -> 1836.8197 | N9: =E9/E$7 -> 1976.4546 | O9: =F9/F$7 -> 2100.6176 | T9: Suma de COSTO VENTAS | U9: =B9/B$8 -> 0.77135101 | V9: =C9/C$8 -> 1.0176869 | W9: =D9/D$8 -> 0.94084474 | X9: =E9/E$8 -> 0.85305889 | Y9: =F9/F$8 -> 0.8284747 | Z9: =G9/G$8 -> 0.8897416 | AN9: Resumen de Precios por TM Peru Frost vs Mercado
A10: Suma de UTILIDAD BRUTA | B10: 129098.71 | C10: -48989.478 | D10: 230493.64 | E10: 718383.33 | F10: 860388.64 | G10: 1889374.8 | J10: Suma de UTILIDAD BRUTA | K10: =B10/B$7 -> 520.55932 | L10: =C10/C$7 -> -29.975817 | M10: =D10/D$7 -> 115.48935 | N10: =E10/E$7 -> 340.44828 | O10: =F10/F$7 -> 434.90653 | T10: Suma de UTILIDAD BRUTA | U10: =B10/B$8 -> 0.22864899 | V10: =C10/C$8 -> -0.017686853 | W10: =D10/D$8 -> 0.05915526 | X10: =E10/E$8 -> 0.14694111 | Y10: =F10/F$8 -> 0.1715253 | Z10: =G10/G$8 -> 0.1102584 | AF10: Acum Abril venta y rentabilidad por producto
A11: Suma de GASTO VENTAS | B11: 59134.419 | C11: 356852.55 | D11: 432727.48 | E11: 480312.05 | F11: 369157.75 | G11: 1698184.2 | J11: Suma de GASTO VENTAS | K11: =B11/B$7 -> 238.44524 | L11: =C11/C$7 -> 218.35192 | M11: =D11/D$7 -> 216.81906 | N11: =E11/E$7 -> 227.62418 | O11: =F11/F$7 -> 186.60069 | T11: Suma de GASTO VENTAS | U11: =B11/B$8 -> 0.104734 | V11: =C11/C$8 -> 0.1288358 | W11: =D11/D$8 -> 0.11105776 | X11: =E11/E$8 -> 0.098245021 | Y11: =F11/F$8 -> 0.073594523 | Z11: =G11/G$8 -> 0.099101072 | AG11: Venta CFR | AH11: Utilidad Neta | AN11: PRODUCTO | AO11: PERU FROST | AP11: INDUSTRIA PERUANA
A12: Suma de GASTO ADM | B12: 50659 | C12: 56604 | D12: 78579 | E12: 65076 | F12: 78579 | G12: 329497 | J12: Suma de GASTO ADM | K12: =B12/B$7 -> 204.27016 | L12: =C12/C$7 -> 34.635012 | M12: =D12/D$7 -> 39.372182 | N12: =E12/E$7 -> 30.840098 | O12: =F12/F$7 -> 39.719865 | T12: Suma de GASTO ADM | U12: =B12/B$8 -> 0.089723041 | V12: =C12/C$8 -> 0.020435952 | W12: =D12/D$8 -> 0.020166983 | X12: =E12/E$8 -> 0.013310915 | Y12: =F12/F$8 -> 0.015665347 | Z12: =G12/G$8 -> 0.019228483 | AF12: FILETE CONGELADO | AG12: 3148.23 | AH12: -1138.4306 | AN12: FILETE CONGELADO | AO12: 1323 | AP12: 1525
A13: Suma de DRAWBACK | B13: 15120.72 | C13: 75707.235 | D13: 108636.57 | E13: 138095.15 | F13: 143706.68 | G13: 481266.35 | J13: Suma de DRAWBACK | K13: =B13/B$7 -> 60.970645 | L13: =C13/C$7 -> 46.323952 | M13: =D13/D$7 -> 54.432593 | N13: =E13/E$7 -> 65.444526 | O13: =F13/F$7 -> 72.640396 | T13: Suma de DRAWBACK | U13: =B13/B$8 -> 0.026780572 | V13: =C13/C$8 -> 0.027332864 | W13: =D13/D$8 -> 0.027881136 | X13: =E13/E$8 -> 0.028246555 | Y13: =F13/F$8 -> 0.028649065 | Z13: =G13/G$8 -> 0.028085298 | AF13: REJOS CONGELADOS | AG13: 2631.849 | AH13: 311.25595 | AN13: FILETE DARUMA | AO13: 3292 | AP13: 3417
A14: Suma de UTILIDAD OPERATIVA | B14: 34426.014 | C14: -386738.79 | D14: -172176.27 | E14: 311090.43 | F14: 556358.57 | G14: 342959.95 | J14: Suma de UTILIDAD OPERATIVA | K14: =B14/B$7 -> 138.81457 | L14: =C14/C$7 -> -236.6388 | M14: =D14/D$7 -> -86.269301 | N14: =E14/E$7 -> 147.42854 | O14: =F14/F$7 -> 281.22637 | T14: Suma de UTILIDAD OPERATIVA | U14: =B14/B$8 -> 0.060972515 | V14: =C14/C$8 -> -0.13962574 | W14: =D14/D$8 -> -0.044188343 | X14: =E14/E$8 -> 0.063631729 | Y14: =F14/F$8 -> 0.11091449 | Z14: =G14/G$8 -> 0.020014141 | AF14: ALAS CONGELADAS | AG14: 2273.427 | AH14: -451.32788 | AN14: REPRODUCTOR | AO14: 2724 | AP14: 2704
A15: Suma de GASTO FINANCIERO | B15: 131251 | C15: 148498 | D15: 154473 | E15: 221685 | F15: 154473 | G15: 810380 | J15: Suma de GASTO FINANCIERO | K15: =B15/B$7 -> 529.2379 | L15: =C15/C$7 -> 90.863367 | M15: =D15/D$7 -> 77.399038 | N15: =E15/E$7 -> 105.0585 | O15: =F15/F$7 -> 78.082524 | T15: Suma de GASTO FINANCIERO | U15: =B15/B$8 -> 0.23246094 | V15: =C15/C$8 -> 0.053612783 | W15: =D15/D$8 -> 0.039644871 | X15: =E15/E$8 -> 0.045344371 | Y15: =F15/F$8 -> 0.030795417 | Z15: =G15/G$8 -> 0.04729141 | AF15: FILETE DARUMA | AG15: 1927.8 | AH15: 513.07693 | AN15: NUCA | AO15: 1123 | AP15: 1171
A16: Suma de UTILIDAD NETA | B16: -96824.986 | C16: -535236.79 | D16: -326649.27 | E16: 89405.43 | F16: 401885.57 | G16: -467420.05 | J16: Suma de UTILIDAD NETA | K16: =B16/B$7 -> -390.42333 | L16: =C16/C$7 -> -327.50216 | M16: =D16/D$7 -> -163.66834 | N16: =E16/E$7 -> 42.370033 | O16: =F16/F$7 -> 203.14385 | T16: Suma de UTILIDAD NETA | U16: =B16/B$8 -> -0.17148843 | V16: =C16/C$8 -> -0.19323852 | W16: =D16/D$8 -> -0.083833214 | X16: =E16/E$8 -> 0.018287358 | Y16: =F16/F$8 -> 0.080119074 | Z16: =G16/G$8 -> -0.027277269 | AF16: REPRODUCTORES | AG16: 599.405 | AH16: 126.98725 | AN16: ALAS COCIDAS | AO16: 3240 | AP16: 3318
A17: Suma de DEPRECIACIÓN | B17: 123530 | C17: 124152.39 | D17: 123360.73 | E17: 123484.35 | F17: 123484.35 | G17: 618011.82 | J17: Suma de DEPRECIACIÓN | K17: =B17/B$7 -> 498.10484 | L17: =C17/C$7 -> 75.96671 | M17: =D17/D$7 -> 61.810166 | N17: =E17/E$7 -> 58.520338 | O17: =F17/F$7 -> 62.418479 | T17: Suma de DEPRECIACIÓN | U17: =B17/B$8 -> 0.21878614 | V17: =C17/C$8 -> 0.044823199 | W17: =D17/D$8 -> 0.031660032 | X17: =E17/E$8 -> 0.025258002 | Y17: =F17/F$8 -> 0.024617584 | Z17: =G17/G$8 -> 0.036065365 | AF17: NUCAS | AG17: 514.83 | AH17: -431.34411 | AN17: ALAS CONGELADAS | AO17: 1509 | AP17: 1579
A18: Suma de EBITDA | B18: 157956.01 | C18: -262586.39 | D18: -48815.541 | E18: 434574.78 | F18: 679842.92 | G18: 960971.78 | J18: Suma de EBITDA | K18: =B18/B$7 -> 636.91941 | L18: =C18/C$7 -> -160.67209 | M18: =D18/D$7 -> -24.459135 | N18: =E18/E$7 -> 205.94887 | O18: =F18/F$7 -> 343.64485 | T18: Suma de EBITDA | U18: =B18/B$8 -> 0.27975866 | V18: =C18/C$8 -> -0.094802539 | W18: =D18/D$8 -> -0.012528311 | X18: =E18/E$8 -> 0.08888973 | Y18: =F18/F$8 -> 0.13553208 | Z18: =G18/G$8 -> 0.056079506 | AF18: ALAS COCIDAS | AG18: 384.2577 | AH18: 138.02447 | AN18: TENTACULO | AO18: 2290 | AP18: 2288
A19: EBITDA NETO | B19: =B16+B17 -> 26705.014 | C19: =C16+C17 -> -411084.39 | D19: =D16+D17 -> -203288.54 | E19: =E16+E17 -> 212889.78 | F19: =F16+F17 -> 525369.92 | G19: =G16+G17 -> 150591.78 | AF19: OTROS | AG19: =SUM(AG20:AG23) -> 420.26689 | AH19: =SUM(AH20:AH23) -> 130.12557
AF20: POTA CONOS | AG20: 231.72 | AH20: 0.42290479
AF21: POTA RECORTES COCIDOS | AG21: 67.5 | AH21: 15.71277 | AR21: 0.0692
AF22: POTA SUCKERS CONGELADO | AG22: 30.25 | AH22: 23.193002 | AR22: 0.0637
A23: ANÁLISIS POR PRODUCTO | AF23: RESIDUOS DE POTA | AG23: 90.79689 | AH23: 90.79689 | AR23: 0.0634
AR24: 0.0478
A25: RANKING DE VENTAS (USD) | J25: UTILIDAD NETA (USD) | T25: EBITDA (USD) | AF25: Acum Abril venta y rentabilidad por cliente | AR25: 0.0459
A26: Suma de VALOR CFR | B26: Etiquetas de columna | J26: Suma de UTILIDAD NETA | K26: Etiquetas de columna | T26: Suma de EBITDA | U26: Etiquetas de columna | AG26: Venta CFR | AH26: Utilidad Neta | AR26: 0.0371
A27: Etiquetas de fila | B27: ENERO | C27: FEBRERO | D27: MARZO | E27: ABRIL | F27: MAYO | G27: Total general | H27: % | J27: Etiquetas de fila | K27: ENERO | L27: FEBRERO | M27: MARZO | N27: ABRIL | O27: MAYO | P27: Total general | Q27: MG | T27: Etiquetas de fila | U27: ENERO | V27: FEBRERO | W27: MARZO | X27: ABRIL | Y27: MAYO | Z27: Total general | AA27: MG | AF27: TSUJINO | AG27: 2790.273 | AH27: -709.0403 | AR27: 0.0337
A28: POTA FILETE CONGELADO | B28: 94800 | C28: 1147500 | D28: 430960 | E28: 1474970 | F28: 1054710 | G28: 4202940 | H28: =G28/$G$43 -> 0.2452713 | J28: POTA FILETE CONGELADO | K28: -37529.914 | L28: -527635.82 | M28: -236860.72 | N28: -426642.81 | O28: -124076.38 | P28: -1352745.6 | Q28: =P28/G28 -> -0.32185699 | T28: POTA FILETE CONGELADO | U28: 11782.537 | V28: -392498.52 | W28: -196072.42 | X28: -294323.88 | Y28: -52870.473 | Z28: -923982.76 | AA28: =Z28/G28 -> -0.21984201 | AF28: LONGKOU JIABAO AQUATIC | AG28: 1406.7 | AH28: 394.79634 | AR28: 0.0337
A29: POTA REJOS CONGELADOS | B29: 149248 | C29: 532695 | D29: 779600 | E29: 1170306 | F29: 1105650 | G29: 3737499 | H29: =G29/$G$43 -> 0.21810953 | J29: POTA REJOS CONGELADOS | K29: -6524.1514 | L29: 100438.17 | M29: 95452.995 | N29: 133277.89 | O29: 334078.31 | P29: 656723.2 | Q29: =P29/G29 -> 0.17571194 | T29: POTA REJOS CONGELADOS | U29: 53020.634 | V29: 135306.93 | W29: 141531.24 | X29: 208350.76 | Y29: 387187.69 | Z29: 925397.25 | AA29: =Z29/G29 -> 0.24759799 | AF29: KULALIA | AG29: 1378.9217 | AH29: 101.0003 | AR29: 0.0333
A30: POTA FILETE DARUMA | C30: 91800 | D30: 1004400 | E30: 831600 | F30: 1142100 | G30: 3069900 | H30: =G30/$G$43 -> 0.1791504 | J30: POTA FILETE DARUMA | L30: 27314.314 | M30: 235571.77 | N30: 258609.83 | O30: 85056.072 | P30: 606551.99 | Q30: =P30/G30 -> 0.19758037 | T30: POTA FILETE DARUMA | V30: 31818.891 | W30: 280675.55 | X30: 293942.86 | Y30: 126784.87 | Z30: 733222.17 | AA30: =Z30/G30 -> 0.23884236 | AF30: AVANCE GROUP | AG30: 1097.2 | AH30: -468.13754 | AR30: 0.0333
A31: POTA ALAS CONGELADAS | B31: 135915 | C31: 710550 | D31: 768480 | E31: 658482 | F31: 591300 | G31: 2864727 | H31: =G31/$G$43 -> 0.1671771 | J31: POTA ALAS CONGELADAS | K31: -51593.825 | L31: -196390.88 | M31: -180010.05 | N31: -99943.542 | O31: -66299.328 | P31: -594237.62 | Q31: =P31/G31 -> -0.20743255 | T31: POTA ALAS CONGELADAS | U31: 22374.852 | V31: -119763.03 | W31: -112799.84 | X31: -43734.581 | Y31: -24570.53 | Z31: -278493.13 | AA31: =Z31/G31 -> -0.097214544 | AF31: FOOD & BEVERAGES TRADERS | AG31: 935.406 | AH31: -74.238541 | AR31: 0.032
A32: POTA ALAS COCIDAS | D32: 177221.7 | E32: 207036 | F32: 423756 | G32: 808013.7 | H32: =G32/$G$43 -> 0.04715332 | J32: POTA ALAS COCIDAS | M32: 46804.601 | N32: 37657.94 | O32: 85538.437 | P32: 170000.98 | Q32: =P32/G32 -> 0.21039368 | T32: POTA ALAS COCIDAS | W32: 54321.898 | X32: 46343.977 | Y32: 100611.38 | Z32: 201277.26 | AA32: =Z32/G32 -> 0.2491013 | AF32: Qingdao Haiyujia | AG32: 595.782 | AH32: 101.96621 | AR32: 0.0318
A33: POTA REPRODUCTORES | B33: 74064 | C33: 77585 | D33: 139200 | E33: 308556 | F33: 154700 | G33: 754105 | H33: =G33/$G$43 -> 0.044007365 | J33: POTA REPRODUCTORES | K33: 4395.863 | L33: 22418.891 | M33: 34140.783 | N33: 70608.829 | O33: 46503.823 | P33: 178068.19 | Q33: =P33/G33 -> 0.23613182 | T33: POTA REPRODUCTORES | U33: 31106.774 | V33: 26923.467 | W33: 41240.453 | X33: 87588.313 | Y33: 53809.875 | Z33: 240668.88 | AA33: =Z33/G33 -> 0.31914506 | AF33: Longkou Yunfeng Aquatic Food | AG33: 575.1 | AH33: -44.789183 | AR33: 0.0316
A34: POTA NUCAS | B34: 35874 | C34: 23456 | D34: 455500 | F34: 225525 | G34: 740355 | H34: =G34/$G$43 -> 0.043204955 | J34: POTA NUCAS | K34: -19625.979 | L34: -6759.1635 | M34: -375692.17 | O34: -142861.01 | P34: -544938.33 | Q34: =P34/G34 -> -0.73605004 | T34: POTA NUCAS | U34: 961.96962 | V34: -4429.2651 | W34: -322096.63 | Y34: -117149.33 | Z34: -442713.25 | AA34: =Z34/G34 -> -0.59797429 | AF34: OTROS | AG34: =SUM(AG35:AG51) -> 2863.8454 | AH34: =SUM(AH35:AH51) -> -19.037084 | AR34: 0.0302
A35: POTA CONOS | B35: 50400 | C35: 69000 | D35: 76800 | E35: 35520 | F35: 43200 | G35: 274920 | H35: =G35/$G$43 -> 0.016043528 | J35: POTA CONOS | K35: -10261.26 | L35: 14427.098 | M35: -2235.7781 | N35: -8371.57 | O35: 1716.3337 | P35: -4725.1762 | Q35: =P35/G35 -> -0.017187459 | T35: POTA CONOS | U35: 14394.966 | V35: 20095.379 | W35: 4446.2637 | X35: -4740.1197 | Y35: 5088.3578 | Z35: 39284.847 | AA35: =Z35/G35 -> 0.14289556 | AF35: OVERSEA | AG35: 354.595 | AH35: 86.215827 | AR35: 0.03
A36: POTA RECORTES COCIDOS | E36: 67500 | F36: 130950 | G36: 198450 | H36: =G36/$G$43 -> 0.011580962 | J36: POTA RECORTES COCIDOS | N36: 12648.31 | O36: 116108.82 | P36: 128757.14 | Q36: =P36/G36 -> 0.64881398 | T36: POTA RECORTES COCIDOS | X36: 17064.939 | Y36: 123695.88 | Z36: 140760.82 | AA36: =Z36/G36 -> 0.70930117 | AF36: Pesciro Asia International LTD. | AG36: 352.35 | AH36: -117.23253
A37: POTA MEMBRANA PRECOCIDA | C37: 38606.25 | D37: 37800 | E37: 52500 | G37: 128906.25 | H37: =G37/$G$43 -> 0.0075225922 | J37: POTA MEMBRANA PRECOCIDA | L37: -4537.6993 | M37: 29722.688 | N37: 44868.518 | P37: 70053.507 | Q37: =P37/G37 -> 0.54344538 | T37: POTA MEMBRANA PRECOCIDA | V37: -33.122782 | W37: 33481.336 | X37: 49162.463 | Z37: 82610.676 | AA37: =Z37/G37 -> 0.64085858 | AF37: OCEANUS FISH | AG37: 340.564 | AH37: -36.175426
A38: POTA TELILLA PRECOCIDA | C38: 38606.25 | E38: 52200 | F38: 53812.5 | G38: 144618.75 | H38: =G38/$G$43 -> 0.0084395279 | J38: POTA TELILLA PRECOCIDA | L38: -4537.6993 | N38: 44593.734 | O38: 47651.427 | P38: 87707.461 | Q38: =P38/G38 -> 0.60647365 | T38: POTA TELILLA PRECOCIDA | V38: -33.122782 | X38: 48863.141 | Y38: 51339.578 | Z38: 100169.6 | AA38: =Z38/G38 -> 0.69264598 | AF38: LONGKOU BOHAI | AG38: 334.8 | AH38: 61.759822
A39: POTA SUCKERS CONGELADO | E39: 30250 | G39: 30250 | H39: =G39/$G$43 -> 0.0017653016 | J39: POTA SUCKERS CONGELADO | N39: 22098.301 | P39: 22098.301 | Q39: =P39/G39 -> 0.73052236 | T39: POTA SUCKERS CONGELADO | X39: 26056.909 | Z39: 26056.909 | AA39: =Z39/G39 -> 0.86138543 | AF39: GLOBAL OCEAN | AG39: 285.485 | AH39: 31.414281
A40: RESIDUOS DE POTA | B40: 24314.28 | C40: 40026 | D40: 26456.61 | G40: 90796.89 | H40: =G40/$G$43 -> 0.0052986413 | J40: RESIDUOS DE POTA | K40: 24314.28 | L40: 40026 | M40: 26456.61 | P40: 90796.89 | Q40: =P40/G40 -> 1 | T40: RESIDUOS DE POTA | U40: 24314.28 | V40: 40026 | W40: 26456.61 | Z40: 90796.89 | AA40: =Z40/G40 -> 1 | AF40: DAIRECK S.A. | AG40: 280.782 | AH40: -291.00909
A41: POTA TUBOALETA | F41: 54000 | G41: 54000 | H41: =G41/$G$43 -> 0.0031512823 | J41: POTA TUBOALETA | O41: -8875.5707 | P41: -8875.5707 | Q41: =P41/G41 -> -0.16436242 | T41: POTA TUBOALETA | Y41: -5082.0436 | Z41: -5082.0436 | AA41: =Z41/G41 -> -0.094111919 | AF41: YANTAI TAIXI FOODSTUFF | AG41: 279.504 | AH41: 19.044143
A42: POTA LABIOS CONGELADOS | F42: 36400 | G42: 36400 | H42: =G42/$G$43 -> 0.0021241977 | J42: POTA LABIOS CONGELADOS | O42: 27344.638 | P42: 27344.638 | Q42: =P42/G42 -> 0.75122632 | T42: POTA LABIOS CONGELADOS | Y42: 30997.664 | Z42: 30997.664 | AA42: =Z42/G42 -> 0.85158418
A43: Total general | B43: 564615.28 | C43: 2769824.5 | D43: 3896418.3 | E43: 4888920 | F43: 5016103.5 | G43: 17135882 | H43: =G43/$G$43 -> 1 | J43: Total general | K43: -96824.986 | L43: -535236.79 | M43: -326649.27 | N43: 89405.43 | O43: 401885.57 | P43: -467420.05 | Q43: =P43/G43 -> -0.027277269 | T43: Total general | U43: 157956.01 | V43: -262586.39 | W43: -48815.541 | X43: 434574.78 | Y43: 679842.92 | Z43: 960971.78 | AA43: =Z43/G43 -> 0.056079506
AF46: Hunan Jinyueyang | AG46: 181.9125 | AH46: 72.469656
A47: ANÁLISIS POR CLIENTE | AF47: GOLDEN SEAFOOD | AG47: 151.256 | AH47: 31.632905
AF48: SACRAMENTO CO., LTD | AG48: 91.8 | AH48: 29.126229
A49: RANKING DE VENTAS (USD) | J49: UTILIDAD NETA (USD) | T49: EBITDA (USD) | AF49: PROVEEDORA DE PRODUCTOS MARINOS | AG49: 90.79689 | AH49: 90.79689
A50: Suma de VALOR CFR | B50: Etiquetas de columna | J50: Suma de UTILIDAD NETA | K50: Etiquetas de columna | Q50: MG | T50: Suma de EBITDA | U50: Etiquetas de columna | AA50: MG | AF50: Shenzhen Yueshi | AG50: 81 | AH50: 18.351483
A51: Etiquetas de fila | B51: ENERO | C51: FEBRERO | D51: MARZO | E51: ABRIL | F51: MAYO | G51: Total general | H51: % | J51: Etiquetas de fila | K51: ENERO | L51: FEBRERO | M51: MARZO | N51: ABRIL | O51: MAYO | P51: Total general | Q51: NETO | T51: Etiquetas de fila | U51: ENERO | V51: FEBRERO | W51: MARZO | X51: ABRIL | Y51: MAYO | Z51: Total general | AA51: EBITDA | AF51: Pesciro SL | AG51: 39 | AH51: -15.431273
A52: TSUJINO | B52: 281115 | C52: 438056 | D52: 1104330 | E52: 966772 | F52: 293600 | G52: 3083873 | H52: =G52/$G$82 -> 0.17996582 | J52: TSUJINO | K52: -99384.999 | L52: -71792.728 | M52: -334523.08 | N52: -270589.32 | O52: -85979.383 | P52: -862269.5 | Q52: =P52/G52 -> -0.27960603 | T52: TSUJINO | U52: 48552.356 | V52: -27757.936 | W52: -233902.66 | X52: -182302.54 | Y52: -60127.198 | Z52: -455537.99 | AA52: =Z52/G52 -> -0.14771619
A53: LONGKOU JIABAO AQUATIC | D53: 669600 | E53: 737100 | F53: 1266156 | G53: 2672856 | H53: =G53/$G$82 -> 0.15598007 | J53: LONGKOU JIABAO AQUATIC | M53: 157047.85 | N53: 236222.97 | O53: 161477.97 | P53: 554748.79 | Q53: =P53/G53 -> 0.20754907 | T53: LONGKOU JIABAO AQUATIC | W53: 187117.03 | X53: 267139.37 | Y53: 206899.13 | Z53: 661155.54 | AA53: =Z53/G53 -> 0.24735921
A54: KULALIA | C54: 390000 | D54: 813921.7 | E54: 175000 | F54: 36400 | G54: 1415321.7 | H54: =G54/$G$82 -> 0.082594041 | J54: KULALIA | L54: 67208.075 | M54: 109432.57 | N54: -135540.56 | O54: 27344.638 | P54: 68444.719 | Q54: =P54/G54 -> 0.048359832 | T54: KULALIA | V54: 93234.517 | W54: 155510.82 | X54: -115093.21 | Y54: 30997.664 | Z54: 164649.79 | AA54: =Z54/G54 -> 0.11633383
A55: AVANCE GROUP | C55: 1066950 | E55: 30250 | F55: 1047600 | G55: 2144800 | H55: =G55/$G$82 -> 0.12516426 | J55: AVANCE GROUP | L55: -528551.03 | N55: 22098.301 | O55: 128320.67 | P55: -378132.06 | Q55: =P55/G55 -> -0.17630178 | T55: AVANCE GROUP | V55: -397868.26 | X55: 26056.909 | Y55: 189017.11 | Z55: -182794.25 | AA55: =Z55/G55 -> -0.085226709
A56: FOOD & BEVERAGES TRADERS | C56: 222750 | E56: 712656 | G56: 935406 | H56: =G56/$G$82 -> 0.054587562 | J56: FOOD & BEVERAGES TRADERS | L56: -61761.853 | N56: 33488.916 | P56: -28272.938 | Q56: =P56/G56 -> -0.030225311 | T56: FOOD & BEVERAGES TRADERS | V56: -39238.97 | X56: 82062.017 | Z56: 42823.046 | AA56: =Z56/G56 -> 0.045780171
A57: Longkou Yunfeng Aquatic Food | E57: 575100 | F57: 339780 | G57: 914880 | H57: =G57/$G$82 -> 0.053389725 | J57: Longkou Yunfeng Aquatic Food | N57: -40372.501 | O57: -25220.69 | P57: -65593.192 | Q57: =P57/G57 -> -0.071695951 | T57: Longkou Yunfeng Aquatic Food | X57: 3793.7859 | Y57: -2487.6281 | Z57: 1306.1578 | AA57: =Z57/G57 -> 0.0014276821
A58: Qingdao Haiyujia | E58: 595782 | F58: 230850 | G58: 826632 | H58: =G58/$G$82 -> 0.048239829 | J58: Qingdao Haiyujia | N58: 103402.66 | O58: 63902.716 | P58: 167305.37 | Q58: =P58/G58 -> 0.20239402 | T58: Qingdao Haiyujia | X58: 138647.35 | Y58: 75283.298 | Z58: 213930.65 | AA58: =Z58/G58 -> 0.25879793
A59: LONGKOU BOHAI | D59: 334800 | F59: 299700 | G59: 634500 | H59: =G59/$G$82 -> 0.037027567 | J59: LONGKOU BOHAI | M59: 78523.923 | O59: 9116.5423 | P59: 87640.465 | Q59: =P59/G59 -> 0.13812524 | T59: LONGKOU BOHAI | W59: 93558.517 | Y59: 20497.124 | Z59: 114055.64 | AA59: =Z59/G59 -> 0.17975672
A60: LONGKOU SANMING | F60: 490860 | G60: 490860 | H60: =G60/$G$82 -> 0.028645156 | J60: LONGKOU SANMING | O60: -73938.067 | P60: -73938.067 | Q60: =P60/G60 -> -0.15062964 | T60: LONGKOU SANMING | Y60: -39796.323 | Z60: -39796.323 | AA60: =Z60/G60 -> -0.081074691
A61: GLOBAL OCEAN | B61: 140400 | C61: 77585 | E61: 67500 | F61: 137550 | G61: 423035 | H61: =G61/$G$82 -> 0.024687087 | J61: GLOBAL OCEAN | K61: -4808.7062 | L61: 22418.891 | N61: 12648.31 | O61: 75105.724 | P61: 105364.22 | Q61: =P61/G61 -> 0.24906738 | T61: GLOBAL OCEAN | U61: 50667.802 | V61: 26923.467 | X61: 17064.939 | Y61: 82552.277 | Z61: 177208.49 | AA61: =Z61/G61 -> 0.41889793
A62: OCEANUS FISH | B62: 74064 | D62: 76700 | E62: 189800 | F62: 80600 | G62: 421164 | H62: =G62/$G$82 -> 0.024577901 | J62: OCEANUS FISH | K62: 4395.863 | M62: 23395.544 | N62: -58876.342 | O62: 26414.012 | P62: -4670.9227 | Q62: =P62/G62 -> -0.011090508 | T62: OCEANUS FISH | U62: 31106.774 | W62: 27014.984 | X62: -41864.142 | Y62: 30067.038 | Z62: 46324.654 | AA62: =Z62/G62 -> 0.10999196
A63: OVERSEA | C63: 142695 | D63: 135200 | E63: 76700 | G63: 354595 | H63: =G63/$G$82 -> 0.020693129 | J63: OVERSEA | L63: 33230.095 | M63: 27802.025 | N63: 15811.218 | P63: 76843.338 | Q63: =P63/G63 -> 0.21670734 | T63: OVERSEA | V63: 42072.412 | W63: 35040.904 | X63: 20064.268 | Z63: 97177.584 | AA63: =Z63/G63 -> 0.27405232
A64: Pesciro Asia International LTD. | D64: 352350 | G64: 352350 | H64: =G64/$G$82 -> 0.020562117 | J64: Pesciro Asia International LTD. | M64: -204581.93 | P64: -204581.93 | Q64: =P64/G64 -> -0.58062134 | T64: Pesciro Asia International LTD. | W64: -170754.09 | Z64: -170754.09 | AA64: =Z64/G64 -> -0.48461499
A65: DAIRECK S.A. | B65: 44722 | D65: 236060 | F65: 51725 | G65: 332507 | H65: =G65/$G$82 -> 0.019404137 | J65: DAIRECK S.A. | K65: -21341.424 | M65: -235285.51 | O65: -39041.511 | P65: -295668.44 | Q65: =P65/G65 -> -0.88920967 | T65: DAIRECK S.A. | U65: 3314.8017 | W65: -205077.11 | Y65: -32718.966 | Z65: -234481.27 | AA65: =Z65/G65 -> -0.70519199
A66: YANTAI TAIXI FOODSTUFF | E66: 279504 | G66: 279504 | H66: =G66/$G$82 -> 0.016311037 | J66: YANTAI TAIXI FOODSTUFF | N66: -960.525 | P66: -960.525 | Q66: =P66/G66 -> -0.003436534 | T66: YANTAI TAIXI FOODSTUFF | X66: 16647.102 | Z66: 16647.102 | AA66: =Z66/G66 -> 0.059559439
A67: Longkou Yunfeng Aquatic | C67: 222750 | D67: 37800 | G67: 260550 | H67: =G67/$G$82 -> 0.015204937 | J67: Longkou Yunfeng Aquatic | L67: -54253.153 | M67: 29722.688 | P67: -24530.465 | Q67: =P67/G67 -> -0.094148783 | T67: Longkou Yunfeng Aquatic | V67: -31730.27 | W67: 33481.336 | Z67: 1751.0658 | AA67: =Z67/G67 -> 0.0067206518
A68: SHANDONG SHEENIER | D68: 70200 | E68: 145800 | G68: 216000 | H68: =G68/$G$82 -> 0.012605129 | J68: SHANDONG SHEENIER | M68: 15768.241 | N68: 26272.723 | P68: 42040.964 | Q68: =P68/G68 -> 0.19463409 | T68: SHANDONG SHEENIER | W68: 19526.889 | X68: 35105.981 | Z68: 54632.87 | AA68: =Z68/G68 -> 0.25292995
A69: Hunan Jinyueyang | C69: 77212.5 | E69: 104700 | F69: 53812.5 | G69: 235725 | H69: =G69/$G$82 -> 0.013756223 | J69: Hunan Jinyueyang | L69: -9075.3987 | N69: 89462.252 | O69: 47651.427 | P69: 128038.28 | Q69: =P69/G69 -> 0.54316801 | T69: Hunan Jinyueyang | V69: -66.245563 | X69: 98025.604 | Y69: 51339.578 | Z69: 149298.94 | AA69: =Z69/G69 -> 0.63336064
A70: ZHOUSHAN EAST CHINA | F70: 174150 | G70: 174150 | H70: =G70/$G$82 -> 0.010162885 | J70: ZHOUSHAN EAST CHINA | O70: -13803.212 | P70: -13803.212 | Q70: =P70/G70 -> -0.079260478 | T70: ZHOUSHAN EAST CHINA | Y70: -2422.6309 | Z70: -2422.6309 | AA70: =Z70/G70 -> -0.013911174
A71: YANTAI HONGCHANG | F71: 164700 | G71: 164700 | H71: =G71/$G$82 -> 0.009611411 | J71: YANTAI HONGCHANG | O71: 53981.251 | P71: 53981.251 | Q71: =P71/G71 -> 0.32775501 | T71: YANTAI HONGCHANG | Y71: 61568.305 | Z71: 61568.305 | AA71: =Z71/G71 -> 0.37382092
A72: GOLDEN SEAFOOD | E72: 151256 | G72: 151256 | H72: =G72/$G$82 -> 0.0088268584 | J72: GOLDEN SEAFOOD | N72: 34744.667 | P72: 34744.667 | Q72: =P72/G72 -> 0.2297077 | T72: GOLDEN SEAFOOD | X72: 43218.051 | Z72: 43218.051 | AA72: =Z72/G72 -> 0.28572785
A73: ZHEJIANG ZHOUFU | F73: 109620 | G73: 109620 | H73: =G73/$G$82 -> 0.006397103 | J73: ZHEJIANG ZHOUFU | O73: -15876.541 | P73: -15876.541 | Q73: =P73/G73 -> -0.14483253 | T73: ZHEJIANG ZHOUFU | Y73: -8289.4873 | Z73: -8289.4873 | AA73: =Z73/G73 -> -0.075620209
A74: SACRAMENTO CO., LTD | C74: 91800 | G74: 91800 | H74: =G74/$G$82 -> 0.0053571799 | J74: SACRAMENTO CO., LTD | L74: 27314.314 | P74: 27314.314 | Q74: =P74/G74 -> 0.29754155 | T74: SACRAMENTO CO., LTD | V74: 31818.891 | Z74: 31818.891 | AA74: =Z74/G74 -> 0.34661101
A75: PROVEEDORA DE PRODUCTOS MARINOS | B75: 24314.28 | C75: 40026 | D75: 26456.61 | G75: 90796.89 | H75: =G75/$G$82 -> 0.0052986413 | J75: PROVEEDORA DE PRODUCTOS MARINOS | K75: 24314.28 | L75: 40026 | M75: 26456.61 | P75: 90796.89 | Q75: =P75/G75 -> 1 | T75: PROVEEDORA DE PRODUCTOS MARINOS | U75: 24314.28 | V75: 40026 | W75: 26456.61 | Z75: 90796.89 | AA75: =Z75/G75 -> 1
A76: NINGBO JUN TAO | F76: 83700 | G76: 83700 | H76: =G76/$G$82 -> 0.0048844875 | J76: NINGBO JUN TAO | O76: 28382.155 | P76: 28382.155 | Q76: =P76/G76 -> 0.33909385 | T76: NINGBO JUN TAO | Y76: 32175.683 | Z76: 32175.683 | AA76: =Z76/G76 -> 0.38441676
A77: Shenzhen Yueshi | E77: 81000 | G77: 81000 | H77: =G77/$G$82 -> 0.0047269234 | J77: Shenzhen Yueshi | N77: 21592.662 | P77: 21592.662 | Q77: =P77/G77 -> 0.26657607 | T77: Shenzhen Yueshi | X77: 26009.29 | Z77: 26009.29 | AA77: =Z77/G77 -> 0.32110235
A78: YANTAI HIZEN INTERNATIONAL | F78: 67500 | G78: 67500 | H78: =G78/$G$82 -> 0.0039391028 | J78: YANTAI HIZEN INTERNATIONAL | O78: 61092.912 | P78: 61092.912 | Q78: =P78/G78 -> 0.90508018 | T78: YANTAI HIZEN INTERNATIONAL | Y78: 64886.44 | Z78: 64886.44 | AA78: =Z78/G78 -> 0.96128059
A79: GIANT OCEAN FOOD | F79: 54000 | G79: 54000 | H79: =G79/$G$82 -> 0.0031512823 | J79: GIANT OCEAN FOOD | O79: -8875.5707 | P79: -8875.5707 | Q79: =P79/G79 -> -0.16436242 | T79: GIANT OCEAN FOOD | Y79: -5082.0436 | Z79: -5082.0436 | AA79: =Z79/G79 -> -0.094111919
A80: Pesciro SL | D80: 39000 | G80: 39000 | H80: =G80/$G$82 -> 0.0022759261 | J80: Pesciro SL | M80: -20408.207 | P80: -20408.207 | Q80: =P80/G80 -> -0.52328736 | T80: Pesciro SL | W80: -16788.768 | Z80: -16788.768 | AA80: =Z80/G80 -> -0.43048122
A81: TT INTERBIZ | F81: 33800 | G81: 33800 | H81: =G81/$G$82 -> 0.0019724693 | J81: TT INTERBIZ | O81: -18169.472 | P81: -18169.472 | Q81: =P81/G81 -> -0.53755834 | T81: TT INTERBIZ | Y81: -14516.446 | Z81: -14516.446 | AA81: =Z81/G81 -> -0.42948064
A82: Total general | B82: 564615.28 | C82: 2769824.5 | D82: 3896418.3 | E82: 4888920 | F82: 5016103.5 | G82: 17135882 | H82: =G82/$G$82 -> 1 | J82: Total general | K82: -96824.986 | L82: -535236.79 | M82: -326649.27 | N82: 89405.43 | O82: 401885.57 | P82: -467420.05 | Q82: =P82/G82 -> -0.027277269 | T82: Total general | U82: 157956.01 | V82: -262586.39 | W82: -48815.541 | X82: 434574.78 | Y82: 679842.92 | Z82: 960971.78 | AA82: =Z82/G82 -> 0.056079506

Sheet Resumen
G2: X | H2: X | M2: X | P2: X | AV2: X | AW2: X | BB2: ANÁLISIS UNITARIO
B3: MES LINK | C3: MES EJERCICIO | D3: FP | E3: Emision | F3: Fecha Embarque | G3: Cantidad | H3: Producto | I3: Corte | J3: Espec. | K3: País | L3: Puerto | M3: Cliente (Razón Social) | N3: Contacto | O3: Precio TM | P3: VALOR CFR | Q3: FOB / TM | R3: Costo Flete | S3: VALOR FOB | T3: Cantidad de FCL (Contenedores) | U3: M/V Nave | V3: Booking | W3: Naviera | X3: Puerto | Y3: CÓDIGO | Z3: Categoría | AA3: MATCH | AB3: COSTO UNITARIO | AC3: Materia Prima | AD3: MOD | AE3: Envases | AF3: CIF | AG3: COSTO VENTAS | AH3: Cant | AI3: C.U | AJ3: Cotos Vta | AK3: UTILIDAD BRUTA | AL3: MARGEN BRUTO | AM3: Flete | AN3: Otros Gastos Ventas | AO3: SS Logístico | AP3: GASTO VENTAS | AQ3: GASTO ADM | AR3: DRAWBACK | AS3: UTILIDAD OPERATIVA | AT3: MARGEN OPERATIVO | AU3: GASTO FINANCIERO | AV3: UTILIDAD NETA | AW3: MARGEN NETO | AX3: DEPRECIACIÓN | AY3: EBITDA | AZ3: MARGEN EBITDA | BB3: PRECIO CFR | BC3: Materia Prima | BD3: MOD | BE3: Envases | BF3: CIF | BG3: COSTO VENTAS | BH3: UTILIDAD BRUTA | BI3: Flete | BJ3: SS Logístico | BK3: GASTO VENTAS | BL3: GASTO ADM | BM3: DRAWBACK | BN3: UTILIDAD OPERATIVA | BO3: GASTO FINANCIERO | BP3: UTILIDAD NETA | BQ3: DEPRECIACIÓN | BR3: EBITDA
B4: ENERO | C4: =B4 -> ENERO | D4: 127-2025 | E4: 325 | F4: 46033 | G4: 26 | H4: POTA REPRODUCTORES | I4: Rejos | K4: España | L4: Valencia | M4: OCEANUS FISH | N4: Ignacio / Ives | O4: =P4/G4 -> 2848.6154 | P4: =78000*0+74064 -> 74064 | Q4: =S4/G4 -> 2670.3846 | R4: 4634 | S4: =P4-R4 -> 69430 | T4: 1 | U4: MERSIN EXPRESS 603N | V4: 26106924 | W4: HAPAG | X4: PAITA | Y4: 10007567 | Z4: Compensación | AA4: =B4&Y4&Z4 -> ENERO10007567Compensación | AB4: =INDEX('Detalle Costos'!$L$5:$L$158,MATCH(Resumen!AA4,'Detalle Costos'!$C$5:$C$158,0))*1000+4623.769999996/248 -> 1848.6442 | AC4: =IFERROR(INDEX('Detalle Costos'!$X$5:$X$158,MATCH(Resumen!AA4,'Detalle Costos'!$C$5:$C$158,0))*AG4,0) -> 30321.714 | AD4: =IFERROR(INDEX('Detalle Costos'!$Z$5:$Z$158,MATCH(Resumen!AA4,'Detalle Costos'!$C$5:$C$158,0))*AG4,0) -> 7452.4837 | AE4: =IFERROR(INDEX('Detalle Costos'!$Y$5:$Y$158,MATCH(Resumen!AA4,'Detalle Costos'!$C$5:$C$158,0))*AG4,0) -> 447.27651 | AF4: =IFERROR(INDEX('Detalle Costos'!$AA$5:$AA$158,MATCH(Resumen!AA4,'Detalle Costos'!$C$5:$C$158,0))*AG4,0) -> 7428.0104 | AG4: =AI4*G4+6518.87/248*G4-47.35*G4 -> 45649.485 | AH4: =48.96-AH17 -> 22.658 | AI4: 1776.8137 | AJ4: =89589.14-AJ17 -> 41460.14 | AK4: =P4-AG4 -> 28414.515 | AL4: =AK4/P4 -> 0.38364813 | AM4: =R4 -> 4634 | AN4: =118461.136538461/5988.21*G4 -> 514.34227 | AO4: =1882/26*G4 -> 1882 | AP4: =SUM(AM4:AO4) -> 7030.3423 | AQ4: =50659/248*G4 -> 5311.0242 | AR4: =S4*0.03 -> 2082.9 | AS4: =AK4-AP4-AQ4+AR4 -> 18156.049 | AT4: =AS4/P4 -> 0.24513999 | AU4: =131251/248*G4 -> 13760.185 | AV4: =AS4-AU4 -> 4395.863 | AW4: =AV4/P4 -> 0.059352223 | AX4: =123530/248*G4 -> 12950.726 | AY4: =AS4+AX4 -> 31106.774 | AZ4: =AY4/P4 -> 0.41999857 | BB4: =P4/$G4 -> 2848.6154 | BC4: =-AC4/$G4 -> -1166.2198 | BD4: =-AD4/$G4 -> -286.63399 | BE4: =-AE4/$G4 -> -17.202943 | BF4: =-AF4/$G4 -> -285.69271 | BG4: =-AG4/$G4 -> -1755.7494 | BH4: =AK4/$G4 -> 1092.866 | BI4: =-AM4/$G4 -> -178.23077 | BJ4: =-AO4/$G4 -> -72.384615 | BK4: =-AP4/$G4 -> -270.39778 | BL4: =-AQ4/$G4 -> -204.27016 | BM4: =AR4/$G4 -> 80.111538 | BN4: =AS4/$G4 -> 698.30956 | BO4: =-AU4/$G4 -> -529.2379 | BP4: =AV4/$G4 -> 169.07165 | BQ4: =AX4/$G4 -> 498.10484 | BR4: =AY4/$G4 -> 1196.4144
B5: ENERO | C5: =B5 -> ENERO | D5: 128-2025B | E5: 325 | F5: 46053 | G5: 17.04 | H5: POTA NUCAS | I5: Nucas | J5: 1000-up | K5: Tailandia | L5: Lat Krabang | M5: DAIRECK S.A. | N5: Julieta | O5: 1850 | P5: 31524 | Q5: 1656.338 | R5: =3300/24*G5 -> 2343 | S5: =P5-R5 -> 29181 | T5: 1 | U5: ECO SIROCCO 26005S | V5: 6443191850 | W5: COSCO | X5: PAITA | Y5: 10005779 | Z5: Compensación | AA5: =B5&Y5&Z5 -> ENERO10005779Compensación | AB5: =INDEX('Detalle Costos'!$L$5:$L$158,MATCH(Resumen!AA5,'Detalle Costos'!$C$5:$C$158,0))*1000+4623.769999996/248 -> 1948.6442 | AC5: =IFERROR(INDEX('Detalle Costos'!$X$5:$X$158,MATCH(Resumen!AA5,'Detalle Costos'!$C$5:$C$158,0))*AG5,0) -> 19902.439 | AD5: =IFERROR(INDEX('Detalle Costos'!$Z$5:$Z$158,MATCH(Resumen!AA5,'Detalle Costos'!$C$5:$C$158,0))*AG5,0) -> 6720.2922 | AE5: =IFERROR(INDEX('Detalle Costos'!$Y$5:$Y$158,MATCH(Resumen!AA5,'Detalle Costos'!$C$5:$C$158,0))*AG5,0) -> 241.50424 | AF5: =IFERROR(INDEX('Detalle Costos'!$AA$5:$AA$158,MATCH(Resumen!AA5,'Detalle Costos'!$C$5:$C$158,0))*AG5,0) -> 4759.6795 | AG5: =AI5*G5+6518.87/248*G5-47.35*G5 -> 31623.915 | AH5: 17.04 | AI5: 1876.9278 | AJ5: 33696.517 | AK5: =P5-AG5 -> -99.914788 | AL5: =AK5/P5 -> -0.0031694832 | AM5: =R5 -> 2343 | AN5: =118461.136538461/5988.21*G5 -> 337.09201 | AO5: =1882/26*G5 -> 1233.4338 | AP5: =SUM(AM5:AO5) -> 3913.5259 | AQ5: =50659/248*G5 -> 3480.7635 | AR5: =S5*0.03 -> 875.43 | AS5: =AK5-AP5-AQ5+AR5 -> -6618.7742 | AT5: =AS5/P5 -> -0.20995985 | AU5: =131251/248*G5 -> 9018.2139 | AV5: =AS5-AU5 -> -15636.988 | AW5: =AV5/P5 -> -0.49603439 | AX5: =123530/248*G5 -> 8487.7065 | AY5: =AS5+AX5 -> 1868.9323 | AZ5: =AY5/P5 -> 0.059286012 | BB5: =P5/$G5 -> 1850 | BC5: =-AC5/$G5 -> -1167.9835 | BD5: =-AD5/$G5 -> -394.38335 | BE5: =-AE5/$G5 -> -14.172784 | BF5: =-AF5/$G5 -> -279.32391 | BG5: =-AG5/$G5 -> -1855.8635 | BH5: =AK5/$G5 -> -5.8635439 | BI5: =-AM5/$G5 -> -137.5 | BJ5: =-AO5/$G5 -> -72.384615 | BK5: =-AP5/$G5 -> -229.66701 | BL5: =-AQ5/$G5 -> -204.27016 | BM5: =AR5/$G5 -> 51.375 | BN5: =AS5/$G5 -> -388.42572 | BO5: =-AU5/$G5 -> -529.2379 | BP5: =AV5/$G5 -> -917.66362 | BQ5: =AX5/$G5 -> 498.10484 | BR5: =AY5/$G5 -> 109.67912
B6: ENERO | C6: =B6 -> ENERO | D6: 128-2025B | E6: 325 | F6: 46053 | G6: 3 | H6: POTA NUCAS | I6: Nucas | J6: 500 - 1 kg. | K6: Tailandia | L6: Lat Krabang | M6: DAIRECK S.A. | N6: Julieta | O6: 1450 | P6: 4350 | Q6: 1450 | R6: =3300/24*G6 -> 412.5 | S6: =P6-R6 -> 3937.5 | T6: 0 | V6: 6443191850 | W6: COSCO | X6: PAITA | Y6: 10005781 | Z6: Compensación | AA6: =B6&Y6&Z6 -> ENERO10005781Compensación | AB6: =INDEX('Detalle Costos'!$L$5:$L$158,MATCH(Resumen!AA6,'Detalle Costos'!$C$5:$C$158,0))*1000+4623.769999996/248 -> 1998.6442 | AC6: =IFERROR(INDEX('Detalle Costos'!$X$5:$X$158,MATCH(Resumen!AA6,'Detalle Costos'!$C$5:$C$158,0))*AG6,0) -> 3521.4666 | AD6: =IFERROR(INDEX('Detalle Costos'!$Z$5:$Z$158,MATCH(Resumen!AA6,'Detalle Costos'!$C$5:$C$158,0))*AG6,0) -> 1150.8275 | AE6: =IFERROR(INDEX('Detalle Costos'!$Y$5:$Y$158,MATCH(Resumen!AA6,'Detalle Costos'!$C$5:$C$158,0))*AG6,0) -> 46.818855 | AF6: =IFERROR(INDEX('Detalle Costos'!$AA$5:$AA$158,MATCH(Resumen!AA6,'Detalle Costos'!$C$5:$C$158,0))*AG6,0) -> 848.47774 | AG6: =AI6*G6+6518.87/248*G6-47.35*G6 -> 5567.5906 | AH6: 3 | AI6: 1876.9278 | AJ6: 5803.9692 | AK6: =P6-AG6 -> -1217.5906 | AL6: =AK6/P6 -> -0.27990589 | AM6: =R6 -> 412.5 | AN6: =118461.136538461/5988.21*G6 -> 59.347185 | AO6: =1882/26*G6 -> 217.15385 | AP6: =SUM(AM6:AO6) -> 689.00103 | AQ6: =50659/248*G6 -> 612.81048 | AR6: =S6*0.03 -> 118.125 | AS6: =AK6-AP6-AQ6+AR6 -> -2401.2771 | AT6: =AS6/P6 -> -0.55201773 | AU6: =131251/248*G6 -> 1587.7137 | AV6: =AS6-AU6 -> -3988.9909 | AW6: =AV6/P6 -> -0.91700939 | AX6: =123530/248*G6 -> 1494.3145 | AY6: =AS6+AX6 -> -906.96263 | AZ6: =AY6/P6 -> -0.20849716 | BB6: =P6/$G6 -> 1450 | BC6: =-AC6/$G6 -> -1173.8222 | BD6: =-AD6/$G6 -> -383.60916 | BE6: =-AE6/$G6 -> -15.606285 | BF6: =-AF6/$G6 -> -282.82591 | BG6: =-AG6/$G6 -> -1855.8635 | BH6: =AK6/$G6 -> -405.86354 | BI6: =-AM6/$G6 -> -137.5 | BJ6: =-AO6/$G6 -> -72.384615 | BK6: =-AP6/$G6 -> -229.66701 | BL6: =-AQ6/$G6 -> -204.27016 | BM6: =AR6/$G6 -> 39.375 | BN6: =AS6/$G6 -> -800.42572 | BO6: =-AU6/$G6 -> -529.2379 | BP6: =AV6/$G6 -> -1329.6636 | BQ6: =AX6/$G6 -> 498.10484 | BR6: =AY6/$G6 -> -302.32088
B7: ENERO | C7: =B7 -> ENERO | D7: 128-2025B | E7: 325 | F7: 46053 | G7: 3.96 | H7: POTA REJOS CONGELADOS | I7: Rejos | J7: 1 - 2 kgs. | K7: Tailandia | L7: Lat Krabang | M7: DAIRECK S.A. | N7: Julieta | O7: =P7/G7 -> 2234.3434 | P7: 8848 | Q7: 2800 | R7: =3300/24*G7 -> 544.5 | S7: =P7-R7 -> 8303.5 | T7: 0 | V7: 6443191850 | W7: COSCO | X7: PAITA | Y7: 10007162 | Z7: Compensación | AA7: =B7&Y7&Z7 -> ENERO10007162Compensación | AB7: =INDEX('Detalle Costos'!$L$5:$L$158,MATCH(Resumen!AA7,'Detalle Costos'!$C$5:$C$158,0))*1000+4623.769999996/248 -> 1808.6442 | AC7: =IFERROR(INDEX('Detalle Costos'!$X$5:$X$158,MATCH(Resumen!AA7,'Detalle Costos'!$C$5:$C$158,0))*AG7,0) -> 4545.8938 | AD7: =IFERROR(INDEX('Detalle Costos'!$Z$5:$Z$158,MATCH(Resumen!AA7,'Detalle Costos'!$C$5:$C$158,0))*AG7,0) -> 1199.3899 | AE7: =IFERROR(INDEX('Detalle Costos'!$Y$5:$Y$158,MATCH(Resumen!AA7,'Detalle Costos'!$C$5:$C$158,0))*AG7,0) -> 61.113395 | AF7: =IFERROR(INDEX('Detalle Costos'!$AA$5:$AA$158,MATCH(Resumen!AA7,'Detalle Costos'!$C$5:$C$158,0))*AG7,0) -> 1191.9798 | AG7: =AI7*G7+6518.87/248*G7-47.35*G7 -> 6998.3769 | AH7: 3.16 | AI7: 1788.3311 | AJ7: 5822.9227 | AK7: =P7-AG7 -> 1849.6231 | AL7: =AK7/P7 -> 0.2090442 | AM7: =R7 -> 544.5 | AN7: =118461.136538461/5988.21*G7 -> 78.338285 | AO7: =1882/26*G7 -> 286.64308 | AP7: =SUM(AM7:AO7) -> 909.48136 | AQ7: =50659/248*G7 -> 808.90984 | AR7: =S7*0.03 -> 249.105 | AS7: =AK7-AP7-AQ7+AR7 -> 380.33691 | AT7: =AS7/P7 -> 0.042985636 | AU7: =131251/248*G7 -> 2095.7821 | AV7: =AS7-AU7 -> -1715.4452 | AW7: =AV7/P7 -> -0.19387943 | AX7: =123530/248*G7 -> 1972.4952 | AY7: =AS7+AX7 -> 2352.8321 | AZ7: =AY7/P7 -> 0.26591683 | BB7: =P7/$G7 -> 2234.3434 | BC7: =-AC7/$G7 -> -1147.953 | BD7: =-AD7/$G7 -> -302.87623 | BE7: =-AE7/$G7 -> -15.432675 | BF7: =-AF7/$G7 -> -301.00501 | BG7: =-AG7/$G7 -> -1767.2669 | BH7: =AK7/$G7 -> 467.07654 | BI7: =-AM7/$G7 -> -137.5 | BJ7: =-AO7/$G7 -> -72.384615 | BK7: =-AP7/$G7 -> -229.66701 | BL7: =-AQ7/$G7 -> -204.27016 | BM7: =AR7/$G7 -> 62.905303 | BN7: =AS7/$G7 -> 96.044674 | BO7: =-AU7/$G7 -> -529.2379 | BP7: =AV7/$G7 -> -433.19323 | BQ7: =AX7/$G7 -> 498.10484 | BR7: =AY7/$G7 -> 594.14951
B8: ENERO | C8: =B8 -> ENERO | D8: 129-2025 | E8: 45982 | F8: 46031 | G8: 24 | H8: POTA CONOS | I8: Conos | K8: Tailandia | L8: Bangkok | M8: TSUJINO | N8: Jose | O8: 2100 | P8: 50400 | Q8: 1962.5 | R8: 3300 | S8: =P8-R8 -> 47100 | T8: 1 | U8: ECO MARIN 26002S | V8: 6440924270 | W8: COSCO | X8: PAITA | Y8: 10007969 | Z8: Compensación | AA8: =B8&Y8&Z8 -> ENERO10007969Compensación | AB8: =INDEX('Detalle Costos'!$L$5:$L$158,MATCH(Resumen!AA8,'Detalle Costos'!$C$5:$C$158,0))*1000+4623.769999996/248 -> 1658.6442 | AC8: =IFERROR(INDEX('Detalle Costos'!$X$5:$X$158,MATCH(Resumen!AA8,'Detalle Costos'!$C$5:$C$158,0))*AG8,0) -> 30120.853 | AD8: =IFERROR(INDEX('Detalle Costos'!$Z$5:$Z$158,MATCH(Resumen!AA8,'Detalle Costos'!$C$5:$C$158,0))*AG8,0) -> 5277.3639 | AE8: =IFERROR(INDEX('Detalle Costos'!$Y$5:$Y$158,MATCH(Resumen!AA8,'Detalle Costos'!$C$5:$C$158,0))*AG8,0) -> 399.40993 | AF8: =IFERROR(INDEX('Detalle Costos'!$AA$5:$AA$158,MATCH(Resumen!AA8,'Detalle Costos'!$C$5:$C$158,0))*AG8,0) -> 3160.4311 | AG8: =AI8*G8+6518.87/248*G8-47.35*G8 -> 38958.058 | AH8: 24 | AI8: =+AJ8/AH8 -> 1644.3167 | AJ8: 39463.6 | AK8: =P8-AG8 -> 11441.942 | AL8: =AK8/P8 -> 0.22702266 | AM8: =R8 -> 3300 | AN8: =118461.136538461/5988.21*G8 -> 474.77748 | AO8: =1882/26*G8 -> 1737.2308 | AP8: =SUM(AM8:AO8) -> 5512.0083 | AQ8: =50659/248*G8 -> 4902.4839 | AR8: =S8*0.03 -> 1413 | AS8: =AK8-AP8-AQ8+AR8 -> 2440.4499 | AT8: =AS8/P8 -> 0.048421625 | AU8: =131251/248*G8 -> 12701.71 | AV8: =AS8-AU8 -> -10261.26 | AW8: =AV8/P8 -> -0.20359642 | AX8: =123530/248*G8 -> 11954.516 | AY8: =AS8+AX8 -> 14394.966 | AZ8: =AY8/P8 -> 0.2856144 | BB8: =P8/$G8 -> 2100 | BC8: =-AC8/$G8 -> -1255.0355 | BD8: =-AD8/$G8 -> -219.89016 | BE8: =-AE8/$G8 -> -16.642081 | BF8: =-AF8/$G8 -> -131.68463 | BG8: =-AG8/$G8 -> -1623.2524 | BH8: =AK8/$G8 -> 476.74758 | BI8: =-AM8/$G8 -> -137.5 | BJ8: =-AO8/$G8 -> -72.384615 | BK8: =-AP8/$G8 -> -229.66701 | BL8: =-AQ8/$G8 -> -204.27016 | BM8: =AR8/$G8 -> 58.875 | BN8: =AS8/$G8 -> 101.68541 | BO8: =-AU8/$G8 -> -529.2379 | BP8: =AV8/$G8 -> -427.55249 | BQ8: =AX8/$G8 -> 498.10484 | BR8: =AY8/$G8 -> 599.79025
B9: ENERO | C9: =B9 -> ENERO | D9: 137-2025 | E9: 46000 | F9: 46043 | G9: 24 | H9: POTA FILETE CONGELADO | I9: Filete | J9: 2 - 4 kg | K9: Taiwan | L9: KAOHSIUNG | M9: TSUJINO | N9: Jose | O9: =P9/G9 -> 1966.6667 | P9: =48000*0+47200 -> 47200 | Q9: =S9/G9 -> 1841.5417 | R9: 3003 | S9: =P9-R9 -> 44197 | T9: 1 | U9: ECO MARIN 25052N | V9: LIMF26385300 | W9: ONE | X9: PAITA | Y9: 10005721 | Z9: Compensación | AA9: =B9&Y9&Z9 -> ENERO10005721Compensación | AB9: =INDEX('Detalle Costos'!$L$5:$L$158,MATCH(Resumen!AA9,'Detalle Costos'!$C$5:$C$158,0))*1000+4623.769999996/248 -> 1878.6442 | AC9: =IFERROR(INDEX('Detalle Costos'!$X$5:$X$158,MATCH(Resumen!AA9,'Detalle Costos'!$C$5:$C$158,0))*AG9,0) -> 27003.901 | AD9: =IFERROR(INDEX('Detalle Costos'!$Z$5:$Z$158,MATCH(Resumen!AA9,'Detalle Costos'!$C$5:$C$158,0))*AG9,0) -> 9795.8891 | AE9: =IFERROR(INDEX('Detalle Costos'!$Y$5:$Y$158,MATCH(Resumen!AA9,'Detalle Costos'!$C$5:$C$158,0))*AG9,0) -> 426.26796 | AF9: =IFERROR(INDEX('Detalle Costos'!$AA$5:$AA$158,MATCH(Resumen!AA9,'Detalle Costos'!$C$5:$C$158,0))*AG9,0) -> 7297.1068 | AG9: =AI9*G9+6518.87/248*G9-47.35*G9 -> 44523.165 | AH9: 23.7 | AI9: 1876.1961 | AJ9: 44778.445 | AK9: =P9-AG9 -> 2676.8346 | AL9: =AK9/P9 -> 0.056712598 | AM9: =R9 -> 3003 | AN9: =118461.136538461/5988.21*G9 -> 474.77748 | AO9: =1882/26*G9 -> 1737.2308 | AP9: =SUM(AM9:AO9) -> 5215.0083 | AQ9: =50659/248*G9 -> 4902.4839 | AR9: =S9*0.03 -> 1325.91 | AS9: =AK9-AP9-AQ9+AR9 -> -6114.7475 | AT9: =AS9/P9 -> -0.12954973 | AU9: =131251/248*G9 -> 12701.71 | AV9: =AS9-AU9 -> -18816.457 | AW9: =AV9/P9 -> -0.39865375 | AX9: =123530/248*G9 -> 11954.516 | AY9: =AS9+AX9 -> 5839.7686 | AZ9: =AY9/P9 -> 0.12372391 | BB9: =P9/$G9 -> 1966.6667 | BC9: =-AC9/$G9 -> -1125.1626 | BD9: =-AD9/$G9 -> -408.16205 | BE9: =-AE9/$G9 -> -17.761165 | BF9: =-AF9/$G9 -> -304.04612 | BG9: =-AG9/$G9 -> -1855.1319 | BH9: =AK9/$G9 -> 111.53478 | BI9: =-AM9/$G9 -> -125.125 | BJ9: =-AO9/$G9 -> -72.384615 | BK9: =-AP9/$G9 -> -217.29201 | BL9: =-AQ9/$G9 -> -204.27016 | BM9: =AR9/$G9 -> 55.24625 | BN9: =AS9/$G9 -> -254.78115 | BO9: =-AU9/$G9 -> -529.2379 | BP9: =AV9/$G9 -> -784.01905 | BQ9: =AX9/$G9 -> 498.10484 | BR9: =AY9/$G9 -> 243.32369
B10: ENERO | C10: =B10 -> ENERO | D10: 140-2025 | E10: 347 | F10: 46038 | G10: 24 | H10: POTA FILETE CONGELADO | I10: Filete | J10: 2-4kg | K10: Japón | L10: Sendai | M10: TSUJINO | N10: Jose | O10: =P10/G10 -> 1983.3333 | P10: =48000*0+47600 -> 47600 | Q10: =S10/G10 -> 1845.7083 | R10: 3303 | S10: =P10-R10 -> 44297 | T10: 1 | U10: ECO SIROCCO 26003S | V10: LIMG00358300 | W10: ONE | X10: PAITA | Y10: 10005721 | Z10: Compensación | AA10: =B10&Y10&Z10 -> ENERO10005721Compensación | AB10: =INDEX('Detalle Costos'!$L$5:$L$158,MATCH(Resumen!AA10,'Detalle Costos'!$C$5:$C$158,0))*1000+4623.769999996/248 -> 1878.6442 | AC10: =IFERROR(INDEX('Detalle Costos'!$X$5:$X$158,MATCH(Resumen!AA10,'Detalle Costos'!$C$5:$C$158,0))*AG10,0) -> 27003.901 | AD10: =IFERROR(INDEX('Detalle Costos'!$Z$5:$Z$158,MATCH(Resumen!AA10,'Detalle Costos'!$C$5:$C$158,0))*AG10,0) -> 9795.8891 | AE10: =IFERROR(INDEX('Detalle Costos'!$Y$5:$Y$158,MATCH(Resumen!AA10,'Detalle Costos'!$C$5:$C$158,0))*AG10,0) -> 426.26796 | AF10: =IFERROR(INDEX('Detalle Costos'!$AA$5:$AA$158,MATCH(Resumen!AA10,'Detalle Costos'!$C$5:$C$158,0))*AG10,0) -> 7297.1068 | AG10: =AI10*G10+6518.87/248*G10-47.35*G10 -> 44523.165 | AH10: 23.7 | AI10: 1876.1961 | AJ10: 44778.445 | AK10: =P10-AG10 -> 3076.8346 | AL10: =AK10/P10 -> 0.064639383 | AM10: =R10 -> 3303 | AN10: =118461.136538461/5988.21*G10 -> 474.77748 | AO10: =1882/26*G10 -> 1737.2308 | AP10: =SUM(AM10:AO10) -> 5515.0083 | AQ10: =50659/248*G10 -> 4902.4839 | AR10: =S10*0.03 -> 1328.91 | AS10: =AK10-AP10-AQ10+AR10 -> -6011.7475 | AT10: =AS10/P10 -> -0.12629722 | AU10: =131251/248*G10 -> 12701.71 | AV10: =AS10-AU10 -> -18713.457 | AW10: =AV10/P10 -> -0.39313986 | AX10: =123530/248*G10 -> 11954.516 | AY10: =AS10+AX10 -> 5942.7686 | AZ10: =AY10/P10 -> 0.12484808 | BB10: =P10/$G10 -> 1983.3333 | BC10: =-AC10/$G10 -> -1125.1626 | BD10: =-AD10/$G10 -> -408.16205 | BE10: =-AE10/$G10 -> -17.761165 | BF10: =-AF10/$G10 -> -304.04612 | BG10: =-AG10/$G10 -> -1855.1319 | BH10: =AK10/$G10 -> 128.20144 | BI10: =-AM10/$G10 -> -137.625 | BJ10: =-AO10/$G10 -> -72.384615 | BK10: =-AP10/$G10 -> -229.79201 | BL10: =-AQ10/$G10 -> -204.27016 | BM10: =AR10/$G10 -> 55.37125 | BN10: =AS10/$G10 -> -250.48948 | BO10: =-AU10/$G10 -> -529.2379 | BP10: =AV10/$G10 -> -779.72738 | BQ10: =AX10/$G10 -> 498.10484 | BR10: =AY10/$G10 -> 247.61536
B11: ENERO | C11: =B11 -> ENERO | D11: 145-2025 | E11: 46020 | F11: 46041 | G11: 54 | H11: POTA REJOS CONGELADOS | I11: Rejos | J11: 500-1 / 1-2 | K11: España | L11: Vigo | M11: GLOBAL OCEAN | N11: Jorge | O11: 2600 | P11: 140400 | Q11: 2430.963 | R11: 9128 | S11: =P11-R11 -> 131272 | T11: 2 | U11: IZMIT EXPRESS 604N | V11: 28952064 | W11: HAPAG | X11: PAITA | Y11: 10007162 | Z11: Compensación | AA11: =B11&Y11&Z11 -> ENERO10007162Compensación | AB11: =INDEX('Detalle Costos'!$L$5:$L$158,MATCH(Resumen!AA11,'Detalle Costos'!$C$5:$C$158,0))*1000+4623.769999996/248 -> 1808.6442 | AC11: =IFERROR(INDEX('Detalle Costos'!$X$5:$X$158,MATCH(Resumen!AA11,'Detalle Costos'!$C$5:$C$158,0))*AG11,0) -> 61989.461 | AD11: =IFERROR(INDEX('Detalle Costos'!$Z$5:$Z$158,MATCH(Resumen!AA11,'Detalle Costos'!$C$5:$C$158,0))*AG11,0) -> 16355.316 | AE11: =IFERROR(INDEX('Detalle Costos'!$Y$5:$Y$158,MATCH(Resumen!AA11,'Detalle Costos'!$C$5:$C$158,0))*AG11,0) -> 833.36448 | AF11: =IFERROR(INDEX('Detalle Costos'!$AA$5:$AA$158,MATCH(Resumen!AA11,'Detalle Costos'!$C$5:$C$158,0))*AG11,0) -> 16254.27 | AG11: =AI11*G11+6518.87/248*G11-47.35*G11 -> 95432.412 | AH11: 54 | AI11: 1788.3311 | AJ11: 99505.64 | AK11: =P11-AG11 -> 44967.588 | AL11: =AK11/P11 -> 0.32028196 | AM11: =R11 -> 9128 | AN11: =118461.136538461/5988.21*G11 -> 1068.2493 | AO11: =1882/26*G11 -> 3908.7692 | AP11: =SUM(AM11:AO11) -> 14105.019 | AQ11: =50659/248*G11 -> 11030.589 | AR11: =S11*0.03 -> 3938.16 | AS11: =AK11-AP11-AQ11+AR11 -> 23770.141 | AT11: =AS11/P11 -> 0.169303 | AU11: =131251/248*G11 -> 28578.847 | AV11: =AS11-AU11 -> -4808.7062 | AW11: =AV11/P11 -> -0.034250044 | AX11: =123530/248*G11 -> 26897.661 | AY11: =AS11+AX11 -> 50667.802 | AZ11: =AY11/P11 -> 0.36088178 | BB11: =P11/$G11 -> 2600 | BC11: =-AC11/$G11 -> -1147.953 | BD11: =-AD11/$G11 -> -302.87623 | BE11: =-AE11/$G11 -> -15.432675 | BF11: =-AF11/$G11 -> -301.00501 | BG11: =-AG11/$G11 -> -1767.2669 | BH11: =AK11/$G11 -> 832.73311 | BI11: =-AM11/$G11 -> -169.03704 | BJ11: =-AO11/$G11 -> -72.384615 | BK11: =-AP11/$G11 -> -261.20405 | BL11: =-AQ11/$G11 -> -204.27016 | BM11: =AR11/$G11 -> 72.928889 | BN11: =AS11/$G11 -> 440.18779 | BO11: =-AU11/$G11 -> -529.2379 | BP11: =AV11/$G11 -> -89.050115 | BQ11: =AX11/$G11 -> 498.10484 | BR11: =AY11/$G11 -> 938.29263
B12: FEBRERO | C12: =B12 -> FEBRERO | D12: 146-2026 | E12: 46027 | F12: 46059 | G12: 10 | H12: POTA CONOS | I12: Conos | J12: 10 cm - up | K12: Tailandia | L12: Lat Krabang | M12: TSUJINO | N12: Jose | O12: 2100 | P12: 21000 | Q12: 2100 | R12: =3500/24*G12 -> 1458.3333 | S12: =P12-R12 -> 19541.667 | T12: 1 | U12: ECO MARIN 26006S | V12: 6444023300 | W12: COSCO | X12: PAITA | Y12: 10007969 | Z12: Compensación | AA12: =B12&Y12&Z12 -> FEBRERO10007969Compensación | AB12: =INDEX('Detalle Costos'!$L$5:$L$158,MATCH(Resumen!AA12,'Detalle Costos'!$C$5:$C$158,0))*1000*0+AI12+229398.68/1634.3-47.35 -> 1298.094 | AC12: =IFERROR(INDEX('Detalle Costos'!$X$5:$X$158,MATCH(Resumen!AA12,'Detalle Costos'!$C$5:$C$158,0))*AG12,0) -> 10499.591 | AD12: =IFERROR(INDEX('Detalle Costos'!$Z$5:$Z$158,MATCH(Resumen!AA12,'Detalle Costos'!$C$5:$C$158,0))*AG12,0) -> 1976.4508 | AE12: =IFERROR(INDEX('Detalle Costos'!$Y$5:$Y$158,MATCH(Resumen!AA12,'Detalle Costos'!$C$5:$C$158,0))*AG12,0) -> 154.98937 | AF12: =IFERROR(INDEX('Detalle Costos'!$AA$5:$AA$158,MATCH(Resumen!AA12,'Detalle Costos'!$C$5:$C$158,0))*AG12,0) -> 349.90907 | AG12: =AB12*G12 -> 12980.94 | AH12: =+G12 -> 10 | AI12: 1205.0789 | AJ12: =+AI12*AH12 -> 12050.789 | AK12: =P12-AG12 -> 8019.0601 | AL12: =AK12/P12 -> 0.38186001 | AM12: =R12 -> 1458.3333 | AN12: =118461.136538461/5988.21*G12 -> 197.82395 | AO12: =1882/26*G12 -> 723.84615 | AP12: =SUM(AM12:AO12) -> 2380.0034 | AQ12: =56604/1634.3*G12 -> 346.35012 | AR12: =S12*0.03 -> 586.25 | AS12: =AK12-AP12-AQ12+AR12 -> 5878.9566 | AT12: =AS12/P12 -> 0.27995031 | AU12: =148498/1634.3*G12 -> 908.63367 | AV12: =AS12-AU12 -> 4970.3229 | AW12: =AV12/P12 -> 0.23668204 | AX12: =123484.35/1634.3*G12 -> 755.57945 | AY12: =AS12+AX12 -> 6634.536 | AZ12: =AY12/P12 -> 0.31593029 | BB12: =P12/$G12 -> 2100 | BC12: =-AC12/$G12 -> -1049.9591 | BD12: =-AD12/$G12 -> -197.64508 | BE12: =-AE12/$G12 -> -15.498937 | BF12: =-AF12/$G12 -> -34.990907 | BG12: =-AG12/$G12 -> -1298.094 | BH12: =AK12/$G12 -> 801.90601 | BI12: =-AM12/$G12 -> -145.83333 | BJ12: =-AO12/$G12 -> -72.384615 | BK12: =-AP12/$G12 -> -238.00034 | BL12: =-AQ12/$G12 -> -34.635012 | BM12: =AR12/$G12 -> 58.625 | BN12: =AS12/$G12 -> 587.89566 | BO12: =-AU12/$G12 -> -90.863367 | BP12: =AV12/$G12 -> 497.03229 | BQ12: =AX12/$G12 -> 75.557945 | BR12: =AY12/$G12 -> 663.4536
B13: FEBRERO | C13: =B13 -> FEBRERO | D13: 146-2026 | E13: 46027 | F13: 46059 | G13: 14 | H13: POTA NUCAS | I13: Nucas | J13: 500-up | K13: Tailandia | L13: Lat Krabang | M13: TSUJINO | N13: Jose | O13: 1700 | P13: =23800-344 -> 23456 | Q13: 1700 | R13: =3500/24*G13 -> 2041.6667 | S13: =P13-R13 -> 21414.333 | T13: 0 | Y13: 10005779 | Z13: Compensación | AA13: =B13&Y13&Z13 -> FEBRERO10005779Compensación | AB13: =INDEX('Detalle Costos'!$L$5:$L$158,MATCH(Resumen!AA13,'Detalle Costos'!$C$5:$C$158,0))*1000*0+AI13+229398.68/1634.3-47.35 -> 1840.6151 | AC13: =IFERROR(INDEX('Detalle Costos'!$X$5:$X$158,MATCH(Resumen!AA13,'Detalle Costos'!$C$5:$C$158,0))*AG13,0) -> 15685.112 | AD13: =IFERROR(INDEX('Detalle Costos'!$Z$5:$Z$158,MATCH(Resumen!AA13,'Detalle Costos'!$C$5:$C$158,0))*AG13,0) -> 5673.5351 | AE13: =IFERROR(INDEX('Detalle Costos'!$Y$5:$Y$158,MATCH(Resumen!AA13,'Detalle Costos'!$C$5:$C$158,0))*AG13,0) -> 187.96971 | AF13: =IFERROR(INDEX('Detalle Costos'!$AA$5:$AA$158,MATCH(Resumen!AA13,'Detalle Costos'!$C$5:$C$158,0))*AG13,0) -> 4221.9946 | AG13: =AB13*G13 -> 25768.611 | AH13: 14.849 | AI13: 1747.6 | AJ13: =AI13*AH13 -> 25950.112 | AK13: =P13-AG13 -> -2312.6114 | AL13: =AK13/P13 -> -0.098593595 | AM13: =R13 -> 2041.6667 | AN13: =118461.136538461/5988.21*G13 -> 276.95353 | AO13: =1882/26*G13 -> 1013.3846 | AP13: =SUM(AM13:AO13) -> 3332.0048 | AQ13: =56604/1634.3*G13 -> 484.89017 | AR13: =S13*0.03 -> 642.43 | AS13: =AK13-AP13-AQ13+AR13 -> -5487.0764 | AT13: =AS13/P13 -> -0.23393061 | AU13: =148498/1634.3*G13 -> 1272.0871 | AV13: =AS13-AU13 -> -6759.1635 | AW13: =AV13/P13 -> -0.28816352 | AX13: =123484.35/1634.3*G13 -> 1057.8112 | AY13: =AS13+AX13 -> -4429.2651 | AZ13: =AY13/P13 -> -0.18883293 | BB13: =P13/$G13 -> 1675.4286 | BC13: =-AC13/$G13 -> -1120.3651 | BD13: =-AD13/$G13 -> -405.25251 | BE13: =-AE13/$G13 -> -13.426408 | BF13: =-AF13/$G13 -> -301.57104 | BG13: =-AG13/$G13 -> -1840.6151 | BH13: =AK13/$G13 -> -165.18653 | BI13: =-AM13/$G13 -> -145.83333 | BJ13: =-AO13/$G13 -> -72.384615 | BK13: =-AP13/$G13 -> -238.00034 | BL13: =-AQ13/$G13 -> -34.635012 | BM13: =AR13/$G13 -> 45.887857 | BN13: =AS13/$G13 -> -391.93403 | BO13: =-AU13/$G13 -> -90.863367 | BP13: =AV13/$G13 -> -482.79739 | BQ13: =AX13/$G13 -> 75.557945 | BR13: =AY13/$G13 -> -316.37608
B14: ENERO | C14: =B14 -> ENERO | D14: 147-2026 | E14: 46032 | F14: 46050 | G14: 72 | H14: POTA ALAS CONGELADAS | I14: Alas | J14: 1 - 2 KGS. | K14: Tailandia | L14: Bangkok | M14: TSUJINO | N14: Jose | O14: =P14/G14 -> 1887.7083 | P14: =140400*0+135915 -> 135915 | Q14: =S14/G14 -> 1754.25 | R14: 9609 | S14: =P14-R14 -> 126306 | T14: 3 | U14: ECO MARIN 26004N | V14: LIMG01524600 | W14: ONE | X14: PAITA | Y14: 10006720 | Z14: Compensación | AA14: =B14&Y14&Z14 -> ENERO10006720Compensación | AB14: =INDEX('Detalle Costos'!$L$5:$L$158,MATCH(Resumen!AA14,'Detalle Costos'!$C$5:$C$158,0))*1000+4623.769999996/248 -> 1738.6442 | AC14: =IFERROR(INDEX('Detalle Costos'!$X$5:$X$158,MATCH(Resumen!AA14,'Detalle Costos'!$C$5:$C$158,0))*AG14,0) -> 80708.237 | AD14: =IFERROR(INDEX('Detalle Costos'!$Z$5:$Z$158,MATCH(Resumen!AA14,'Detalle Costos'!$C$5:$C$158,0))*AG14,0) -> 18674.884 | AE14: =IFERROR(INDEX('Detalle Costos'!$Y$5:$Y$158,MATCH(Resumen!AA14,'Detalle Costos'!$C$5:$C$158,0))*AG14,0) -> 1170.5203 | AF14: =IFERROR(INDEX('Detalle Costos'!$AA$5:$AA$158,MATCH(Resumen!AA14,'Detalle Costos'!$C$5:$C$158,0))*AG14,0) -> 21686.758 | AG14: =AI14*G14+6518.87/248*G14-47.35*G14 -> 122240.4 | AH14: 69.7 | AI14: 1718.8476 | AJ14: 120156.94 | AK14: =P14-AG14 -> 13674.6 | AL14: =AK14/P14 -> 0.10061141 | AM14: =R14 -> 9609 | AN14: =118461.136538461/5988.21*G14 -> 1424.3325 | AO14: =1882/26*G14 -> 5211.6923 | AP14: =SUM(AM14:AO14) -> 16245.025 | AQ14: =50659/248*G14 -> 14707.452 | AR14: =S14*0.03 -> 3789.18 | AS14: =AK14-AP14-AQ14+AR14 -> -13488.696 | AT14: =AS14/P14 -> -0.099243615 | AU14: =131251/248*G14 -> 38105.129 | AV14: =AS14-AU14 -> -51593.825 | AW14: =AV14/P14 -> -0.37960361 | AX14: =123530/248*G14 -> 35863.548 | AY14: =AS14+AX14 -> 22374.852 | AZ14: =AY14/P14 -> 0.16462386 | BB14: =P14/$G14 -> 1887.7083 | BC14: =-AC14/$G14 -> -1120.9477 | BD14: =-AD14/$G14 -> -259.37339 | BE14: =-AE14/$G14 -> -16.257226 | BF14: =-AF14/$G14 -> -301.20497 | BG14: =-AG14/$G14 -> -1697.7833 | BH14: =AK14/$G14 -> 189.92501 | BI14: =-AM14/$G14 -> -133.45833 | BJ14: =-AO14/$G14 -> -72.384615 | BK14: =-AP14/$G14 -> -225.62534 | BL14: =-AQ14/$G14 -> -204.27016 | BM14: =AR14/$G14 -> 52.6275 | BN14: =AS14/$G14 -> -187.343 | BO14: =-AU14/$G14 -> -529.2379 | BP14: =AV14/$G14 -> -716.5809 | BQ14: =AX14/$G14 -> 498.10484 | BR14: =AY14/$G14 -> 310.76184
B15: ENERO | C15: =B15 -> ENERO | E15: 46053 | F15: 46053 | G15: 0 | H15: RESIDUOS DE POTA | I15: Residuos | J15: Residuos | K15: Residuos | L15: Residuos | M15: PROVEEDORA DE PRODUCTOS MARINOS | O15: 0 | P15: 24314.28 | Q15: 0 | R15: 0 | S15: =P15-R15 -> 24314.28 | AB15: 0 | AC15: =IFERROR(INDEX('Detalle Costos'!$X$5:$X$158,MATCH(Resumen!AA15,'Detalle Costos'!$C$5:$C$158,0))*AG15,0) -> 0 | AD15: =IFERROR(INDEX('Detalle Costos'!$Z$5:$Z$158,MATCH(Resumen!AA15,'Detalle Costos'!$C$5:$C$158,0))*AG15,0) -> 0 | AE15: =IFERROR(INDEX('Detalle Costos'!$Y$5:$Y$158,MATCH(Resumen!AA15,'Detalle Costos'!$C$5:$C$158,0))*AG15,0) -> 0 | AF15: =IFERROR(INDEX('Detalle Costos'!$AA$5:$AA$158,MATCH(Resumen!AA15,'Detalle Costos'!$C$5:$C$158,0))*AG15,0) -> 0 | AG15: =AI15*G15 -> 0 | AK15: =P15-AG15 -> 24314.28 | AL15: =AK15/P15 -> 1 | AM15: =R15 -> 0 | AN15: =118461.136538461/5988.21*G15 -> 0 | AO15: =1882/26*G15 -> 0 | AP15: =SUM(AM15:AO15) -> 0 | AQ15: =50659/248*G15 -> 0 | AR15: 0 | AS15: =AK15-AP15-AQ15+AR15 -> 24314.28 | AT15: =AS15/P15 -> 1 | AU15: =131251/248*G15 -> 0 | AV15: =AS15-AU15 -> 24314.28 | AW15: =AV15/P15 -> 1 | AX15: =123530/248*G15 -> 0 | AY15: =AS15+AX15 -> 24314.28 | AZ15: =AY15/P15 -> 1 | BB15: 0 | BC15: 0 | BD15: 0 | BE15: 0 | BF15: 0 | BG15: 0 | BH15: 0 | BI15: 0 | BJ15: 0 | BK15: 0 | BL15: 0 | BM15: 0 | BN15: 0 | BO15: 0 | BP15: 0 | BQ15: 0 | BR15: 0
B16: FEBRERO | C16: =B16 -> FEBRERO | D16: 148-2026 | E16: 15 | F16: 46055 | G16: 135 | H16: POTA FILETE CONGELADO | I16: Filete | J16: 2-4 (B) | K16: España | L16: Vigo | M16: FOOD & BEVERAGES TRADERS | N16: Jorge | O16: 1650 | P16: 222750 | Q16: 1480.963 | R16: 22820 | S16: =P16-R16 -> 199930 | T16: 5 | U16: ODYSSEUS 606N | V16: 59582082 | W16: HAPAG | X16: PAITA | Y16: 10005721 | Z16: Compensación | AA16: =B16&Y16&Z16 -> FEBRERO10005721Compensación | AB16: =INDEX('Detalle Costos'!$L$5:$L$158,MATCH(Resumen!AA16,'Detalle Costos'!$C$5:$C$158,0))*1000*0+AI16+229398.68/1634.3-47.35 -> 1765.2217 | AC16: =IFERROR(INDEX('Detalle Costos'!$X$5:$X$158,MATCH(Resumen!AA16,'Detalle Costos'!$C$5:$C$158,0))*AG16,0) -> 144612 | AD16: =IFERROR(INDEX('Detalle Costos'!$Z$5:$Z$158,MATCH(Resumen!AA16,'Detalle Costos'!$C$5:$C$158,0))*AG16,0) -> 47774.394 | AE16: =IFERROR(INDEX('Detalle Costos'!$Y$5:$Y$158,MATCH(Resumen!AA16,'Detalle Costos'!$C$5:$C$158,0))*AG16,0) -> 2541.4765 | AF16: =IFERROR(INDEX('Detalle Costos'!$AA$5:$AA$158,MATCH(Resumen!AA16,'Detalle Costos'!$C$5:$C$158,0))*AG16,0) -> 43377.054 | AG16: =AB16*G16 -> 238304.93 | AH16: =+G16 -> 135 | AI16: 1672.2066 | AJ16: 251295.39 | AK16: =P16-AG16 -> -15554.926 | AL16: =AK16/P16 -> -0.069831316 | AM16: =R16 -> 22820 | AN16: =118461.136538461/5988.21*G16 -> 2670.6233 | AO16: =1882/26*G16 -> 9771.9231 | AP16: =SUM(AM16:AO16) -> 35262.546 | AQ16: =56604/1634.3*G16 -> 4675.7266 | AR16: =S16*0.03 -> 5997.9 | AS16: =AK16-AP16-AQ16+AR16 -> -49495.299 | AT16: =AS16/P16 -> -0.22220112 | AU16: =148498/1634.3*G16 -> 12266.554 | AV16: =AS16-AU16 -> -61761.853 | AW16: =AV16/P16 -> -0.27726982 | AX16: =124162.35/1634.3*G16 -> 10256.328 | AY16: =AS16+AX16 -> -39238.97 | AZ16: =AY16/P16 -> -0.17615699 | BB16: =P16/$G16 -> 1650 | BC16: =-AC16/$G16 -> -1071.2 | BD16: =-AD16/$G16 -> -353.8844 | BE16: =-AE16/$G16 -> -18.825752 | BF16: =-AF16/$G16 -> -321.31151 | BG16: =-AG16/$G16 -> -1765.2217 | BH16: =AK16/$G16 -> -115.22167 | BI16: =-AM16/$G16 -> -169.03704 | BJ16: =-AO16/$G16 -> -72.384615 | BK16: =-AP16/$G16 -> -261.20405 | BL16: =-AQ16/$G16 -> -34.635012 | BM16: =AR16/$G16 -> 44.428889 | BN16: =AS16/$G16 -> -366.63184 | BO16: =-AU16/$G16 -> -90.863367 | BP16: =AV16/$G16 -> -457.49521 | BQ16: =AX16/$G16 -> 75.972802 | BR16: =AY16/$G16 -> -290.65904
B17: FEBRERO | C17: =B17 -> FEBRERO | D17: 149-2026 | E17: 16 | F17: 46055 | G17: 27 | H17: POTA REPRODUCTORES | I17: Rejos | K17: España | L17: Vigo | M17: GLOBAL OCEAN | N17: Jorge | O17: =P17/G17 -> 2873.5185 | P17: =79650*0+77585 -> 77585 | Q17: =S17/G17 -> 2711.8889 | R17: 4364 | S17: =P17-R17 -> 73221 | T17: 1 | Y17: 10007567 | Z17: Entradas | AA17: =B17&Y17&Z17 -> FEBRERO10007567Entradas | AB17: =INDEX('Detalle Costos'!$L$5:$L$158,MATCH(Resumen!AA17,'Detalle Costos'!$C$5:$C$158,0))*1000*0+AI17+229398.68/1634.3-47.35 -> 1745.2509 | AC17: =IFERROR(INDEX('Detalle Costos'!$X$5:$X$158,MATCH(Resumen!AA17,'Detalle Costos'!$C$5:$C$158,0))*AG17,0) -> 29088.956 | AD17: =IFERROR(INDEX('Detalle Costos'!$Z$5:$Z$158,MATCH(Resumen!AA17,'Detalle Costos'!$C$5:$C$158,0))*AG17,0) -> 8334.6849 | AE17: =IFERROR(INDEX('Detalle Costos'!$Y$5:$Y$158,MATCH(Resumen!AA17,'Detalle Costos'!$C$5:$C$158,0))*AG17,0) -> 528.83536 | AF17: =IFERROR(INDEX('Detalle Costos'!$AA$5:$AA$158,MATCH(Resumen!AA17,'Detalle Costos'!$C$5:$C$158,0))*AG17,0) -> 9169.2977 | AG17: =AB17*G17 -> 47121.774 | AH17: 26.302 | AI17: 1652.2358 | AJ17: 48129 | AK17: =P17-AG17 -> 30463.226 | AL17: =AK17/P17 -> 0.39264325 | AM17: =R17 -> 4364 | AN17: =118461.136538461/5988.21*G17 -> 534.12467 | AO17: =1882/26*G17 -> 1954.3846 | AP17: =SUM(AM17:AO17) -> 6852.5093 | AQ17: =56604/1634.3*G17 -> 935.14532 | AR17: =S17*0.03 -> 2196.63 | AS17: =AK17-AP17-AQ17+AR17 -> 24872.202 | AT17: =AS17/P17 -> 0.32058003 | AU17: =148498/1634.3*G17 -> 2453.3109 | AV17: =AS17-AU17 -> 22418.891 | AW17: =AV17/P17 -> 0.28895909 | AX17: =124162.35/1634.3*G17 -> 2051.2656 | AY17: =AS17+AX17 -> 26923.467 | AZ17: =AY17/P17 -> 0.34701898 | BB17: =P17/$G17 -> 2873.5185 | BC17: =-AC17/$G17 -> -1077.3687 | BD17: =-AD17/$G17 -> -308.69204 | BE17: =-AE17/$G17 -> -19.586495 | BF17: =-AF17/$G17 -> -339.60362 | BG17: =-AG17/$G17 -> -1745.2509 | BH17: =AK17/$G17 -> 1128.2676 | BI17: =-AM17/$G17 -> -161.62963 | BJ17: =-AO17/$G17 -> -72.384615 | BK17: =-AP17/$G17 -> -253.79664 | BL17: =-AQ17/$G17 -> -34.635012 | BM17: =AR17/$G17 -> 81.356667 | BN17: =AS17/$G17 -> 921.19266 | BO17: =-AU17/$G17 -> -90.863367 | BP17: =AV17/$G17 -> 830.32929 | BQ17: =AX17/$G17 -> 75.972802 | BR17: =AY17/$G17 -> 997.16546
B18: FEBRERO | C18: =B18 -> FEBRERO | D18: 150-2026A | E18: 325 | F18: 46069 | G18: 26 | H18: POTA REJOS CONGELADOS | I18: Rejos | J18: 1-2 KG | K18: España | L18: Vigo | M18: OVERSEA | N18: Avelino | O18: 2600 | P18: 67600 | Q18: 2432.1538 | R18: 4364 | S18: =P18-R18 -> 63236 | T18: 1 | U18: CAPE SPENCER 608N | V18: 11400418 | W18: HAPAG | X18: PAITA | Y18: 10007162 | Z18: Compensación | AA18: =B18&Y18&Z18 -> FEBRERO10007162Compensación | AB18: =INDEX('Detalle Costos'!$L$5:$L$158,MATCH(Resumen!AA18,'Detalle Costos'!$C$5:$C$158,0))*1000*0+AI18+229398.68/1634.3-47.35 -> 1758.8613 | AC18: =IFERROR(INDEX('Detalle Costos'!$X$5:$X$158,MATCH(Resumen!AA18,'Detalle Costos'!$C$5:$C$158,0))*AG18,0) -> 28707.971 | AD18: =IFERROR(INDEX('Detalle Costos'!$Z$5:$Z$158,MATCH(Resumen!AA18,'Detalle Costos'!$C$5:$C$158,0))*AG18,0) -> 8191.5895 | AE18: =IFERROR(INDEX('Detalle Costos'!$Y$5:$Y$158,MATCH(Resumen!AA18,'Detalle Costos'!$C$5:$C$158,0))*AG18,0) -> 426.49257 | AF18: =IFERROR(INDEX('Detalle Costos'!$AA$5:$AA$158,MATCH(Resumen!AA18,'Detalle Costos'!$C$5:$C$158,0))*AG18,0) -> 8404.341 | AG18: =AB18*G18 -> 45730.394 | AH18: =+G18 -> 26 | AI18: 1665.8462 | AJ18: =AI18*AH18 -> 43312.002 | AK18: =P18-AG18 -> 21869.606 | AL18: =AK18/P18 -> 0.32351488 | AM18: =R18 -> 4364 | AN18: =118461.136538461/5988.21*G18 -> 514.34227 | AO18: =1882/26*G18 -> 1882 | AP18: =SUM(AM18:AO18) -> 6760.3423 | AQ18: =56604/1634.3*G18 -> 900.51031 | AR18: =S18*0.03 -> 1897.08 | AS18: =AK18-AP18-AQ18+AR18 -> 16105.833 | AT18: =AS18/P18 -> 0.23825197 | AU18: =148498/1634.3*G18 -> 2362.4475 | AV18: =AS18-AU18 -> 13743.386 | AW18: =AV18/P18 -> 0.20330452 | AX18: =124162.35/1634.3*G18 -> 1975.2928 | AY18: =AS18+AX18 -> 18081.126 | AZ18: =AY18/P18 -> 0.26747228 | BB18: =P18/$G18 -> 2600 | BC18: =-AC18/$G18 -> -1104.1527 | BD18: =-AD18/$G18 -> -315.06113 | BE18: =-AE18/$G18 -> -16.40356 | BF18: =-AF18/$G18 -> -323.24388 | BG18: =-AG18/$G18 -> -1758.8613 | BH18: =AK18/$G18 -> 841.13869 | BI18: =-AM18/$G18 -> -167.84615 | BJ18: =-AO18/$G18 -> -72.384615 | BK18: =-AP18/$G18 -> -260.01316 | BL18: =-AQ18/$G18 -> -34.635012 | BM18: =AR18/$G18 -> 72.964615 | BN18: =AS18/$G18 -> 619.45513 | BO18: =-AU18/$G18 -> -90.863367 | BP18: =AV18/$G18 -> 528.59176 | BQ18: =AX18/$G18 -> 75.972802 | BR18: =AY18/$G18 -> 695.42793
B19: FEBRERO | C19: =B19 -> FEBRERO | D19: 151-2025 | E19: 26 | F19: 46080 | G19: 27 | H19: POTA MEMBRANA PRECOCIDA | I19: Membrana | K19: China | L19: Qingdao | M19: Hunan Jinyueyang | O19: =P19/G19 -> 1429.8611 | P19: =39150*0+38606.25 -> 38606.25 | Q19: =S19/G19 -> 1322.4537 | R19: 2900 | S19: =P19-R19 -> 35706.25 | T19: 1 | U19: ECO SIROCCO 26009S | V19: 6445502950 | W19: COSCO | X19: PAITA | Y19: 10009332 | Z19: Entradas | AA19: =B19&Y19&Z19 -> FEBRERO10009332Entradas | AB19: =INDEX('Detalle Costos'!$L$5:$L$158,MATCH(Resumen!AA19,'Detalle Costos'!$C$5:$C$158,0))*1000*0+AI19+229398.68/1634.3-47.35 -> 1312.5249 | AC19: =IFERROR(INDEX('Detalle Costos'!$X$5:$X$158,MATCH(Resumen!AA19,'Detalle Costos'!$C$5:$C$158,0))*AG19,0) -> 29388.919 | AD19: =IFERROR(INDEX('Detalle Costos'!$Z$5:$Z$158,MATCH(Resumen!AA19,'Detalle Costos'!$C$5:$C$158,0))*AG19,0) -> 5377.8939 | AE19: =IFERROR(INDEX('Detalle Costos'!$Y$5:$Y$158,MATCH(Resumen!AA19,'Detalle Costos'!$C$5:$C$158,0))*AG19,0) -> 543.21918 | AF19: =IFERROR(INDEX('Detalle Costos'!$AA$5:$AA$158,MATCH(Resumen!AA19,'Detalle Costos'!$C$5:$C$158,0))*AG19,0) -> 128.13914 | AG19: =AB19*G19 -> 35438.171 | AH19: 26.625 | AI19: 1219.5098 | AJ19: 40733.76 | AK19: =P19-AG19 -> 3168.0787 | AL19: =AK19/P19 -> 0.08206129 | AM19: =R19 -> 2900 | AN19: =118461.136538461/5988.21*G19 -> 534.12467 | AO19: =1882/26*G19 -> 1954.3846 | AP19: =SUM(AM19:AO19) -> 5388.5093 | AQ19: =56604/1634.3*G19 -> 935.14532 | AR19: =S19*0.03 -> 1071.1875 | AS19: =AK19-AP19-AQ19+AR19 -> -2084.3884 | AT19: =AS19/P19 -> -0.053990958 | AU19: =148498/1634.3*G19 -> 2453.3109 | AV19: =AS19-AU19 -> -4537.6993 | AW19: =AV19/P19 -> -0.11753795 | AX19: =124162.35/1634.3*G19 -> 2051.2656 | AY19: =AS19+AX19 -> -33.122782 | AZ19: =AY19/P19 -> -0.00085796423 | BB19: =P19/$G19 -> 1429.8611 | BC19: =-AC19/$G19 -> -1088.4785 | BD19: =-AD19/$G19 -> -199.18125 | BE19: =-AE19/$G19 -> -20.119229 | BF19: =-AF19/$G19 -> -4.7458942 | BG19: =-AG19/$G19 -> -1312.5249 | BH19: =AK19/$G19 -> 117.33625 | BI19: =-AM19/$G19 -> -107.40741 | BJ19: =-AO19/$G19 -> -72.384615 | BK19: =-AP19/$G19 -> -199.57442 | BL19: =-AQ19/$G19 -> -34.635012 | BM19: =AR19/$G19 -> 39.673611 | BN19: =AS19/$G19 -> -77.199571 | BO19: =-AU19/$G19 -> -90.863367 | BP19: =AV19/$G19 -> -168.06294 | BQ19: =AX19/$G19 -> 75.972802 | BR19: =AY19/$G19 -> -1.2267697
B20: FEBRERO | C20: =B20 -> FEBRERO | D20: 151-2025 | E20: 26 | F20: 46080 | G20: 27 | H20: POTA TELILLA PRECOCIDA | I20: Telilla | K20: China | L20: Qingdao | M20: Hunan Jinyueyang | O20: =P20/G20 -> 1429.8611 | P20: =39150*0+38606.25 -> 38606.25 | Q20: =S20/G20 -> 1322.4537 | R20: 2900 | S20: =P20-R20 -> 35706.25 | T20: 1 | U20: ECO SIROCCO 26009S | V20: 6445502950 | W20: COSCO | X20: PAITA | Y20: 10009332 | Z20: Compensación | AA20: =B20&Y20&Z20 -> FEBRERO10009332Compensación | AB20: =INDEX('Detalle Costos'!$L$5:$L$158,MATCH(Resumen!AA20,'Detalle Costos'!$C$5:$C$158,0))*1000*0+AI20+229398.68/1634.3-47.35 -> 1312.5249 | AC20: =IFERROR(INDEX('Detalle Costos'!$X$5:$X$158,MATCH(Resumen!AA20,'Detalle Costos'!$C$5:$C$158,0))*AG20,0) -> 28828.027 | AD20: =IFERROR(INDEX('Detalle Costos'!$Z$5:$Z$158,MATCH(Resumen!AA20,'Detalle Costos'!$C$5:$C$158,0))*AG20,0) -> 5033.6698 | AE20: =IFERROR(INDEX('Detalle Costos'!$Y$5:$Y$158,MATCH(Resumen!AA20,'Detalle Costos'!$C$5:$C$158,0))*AG20,0) -> 503.76196 | AF20: =IFERROR(INDEX('Detalle Costos'!$AA$5:$AA$158,MATCH(Resumen!AA20,'Detalle Costos'!$C$5:$C$158,0))*AG20,0) -> 1072.7126 | AG20: =AB20*G20 -> 35438.171 | AH20: 26.625 | AI20: 1219.5098 | AJ20: 40354.03 | AK20: =P20-AG20 -> 3168.0787 | AL20: =AK20/P20 -> 0.08206129 | AM20: =R20 -> 2900 | AN20: =118461.136538461/5988.21*G20 -> 534.12467 | AO20: =1882/26*G20 -> 1954.3846 | AP20: =SUM(AM20:AO20) -> 5388.5093 | AQ20: =56604/1634.3*G20 -> 935.14532 | AR20: =S20*0.03 -> 1071.1875 | AS20: =AK20-AP20-AQ20+AR20 -> -2084.3884 | AT20: =AS20/P20 -> -0.053990958 | AU20: =148498/1634.3*G20 -> 2453.3109 | AV20: =AS20-AU20 -> -4537.6993 | AW20: =AV20/P20 -> -0.11753795 | AX20: =124162.35/1634.3*G20 -> 2051.2656 | AY20: =AS20+AX20 -> -33.122782 | AZ20: =AY20/P20 -> -0.00085796423 | BB20: =P20/$G20 -> 1429.8611 | BC20: =-AC20/$G20 -> -1067.7047 | BD20: =-AD20/$G20 -> -186.43222 | BE20: =-AE20/$G20 -> -18.65785 | BF20: =-AF20/$G20 -> -39.730098 | BG20: =-AG20/$G20 -> -1312.5249 | BH20: =AK20/$G20 -> 117.33625 | BI20: =-AM20/$G20 -> -107.40741 | BJ20: =-AO20/$G20 -> -72.384615 | BK20: =-AP20/$G20 -> -199.57442 | BL20: =-AQ20/$G20 -> -34.635012 | BM20: =AR20/$G20 -> 39.673611 | BN20: =AS20/$G20 -> -77.199571 | BO20: =-AU20/$G20 -> -90.863367 | BP20: =AV20/$G20 -> -168.06294 | BQ20: =AX20/$G20 -> 75.972802 | BR20: =AY20/$G20 -> -1.2267697
B21: FEBRERO | C21: =B21 -> FEBRERO | D21: 152-2026 | E21: 26 | F21: 46062 | G21: 27 | H21: POTA REJOS CONGELADOS | I21: Rejos | J21: 2-UP KG | K21: España | L21: Vigo | M21: OVERSEA | N21: Avelino | O21: =P21/G21 -> 2781.2963 | P21: =75600*0+75095 -> 75095 | Q21: =S21/G21 -> 2619.6667 | R21: 4364 | S21: =P21-R21 -> 70731 | T21: 1 | U21: GEMLIK EXPRESS 607N | V21: 24312444 | W21: HAPAG | X21: PAITA | Y21: 10007162 | Z21: Compensación | AA21: =B21&Y21&Z21 -> FEBRERO10007162Compensación | AB21: =INDEX('Detalle Costos'!$L$5:$L$158,MATCH(Resumen!AA21,'Detalle Costos'!$C$5:$C$158,0))*1000*0+AI21+229398.68/1634.3-47.35 -> 1758.8613 | AC21: =IFERROR(INDEX('Detalle Costos'!$X$5:$X$158,MATCH(Resumen!AA21,'Detalle Costos'!$C$5:$C$158,0))*AG21,0) -> 29812.124 | AD21: =IFERROR(INDEX('Detalle Costos'!$Z$5:$Z$158,MATCH(Resumen!AA21,'Detalle Costos'!$C$5:$C$158,0))*AG21,0) -> 8506.6506 | AE21: =IFERROR(INDEX('Detalle Costos'!$Y$5:$Y$158,MATCH(Resumen!AA21,'Detalle Costos'!$C$5:$C$158,0))*AG21,0) -> 442.89613 | AF21: =IFERROR(INDEX('Detalle Costos'!$AA$5:$AA$158,MATCH(Resumen!AA21,'Detalle Costos'!$C$5:$C$158,0))*AG21,0) -> 8727.5849 | AG21: =AB21*G21 -> 47489.255 | AH21: =+G21 -> 27 | AI21: 1665.8462 | AJ21: =AI21*AH21 -> 44977.848 | AK21: =P21-AG21 -> 27605.745 | AL21: =AK21/P21 -> 0.36761095 | AM21: =R21 -> 4364 | AN21: =118461.136538461/5988.21*G21 -> 534.12467 | AO21: =1882/26*G21 -> 1954.3846 | AP21: =SUM(AM21:AO21) -> 6852.5093 | AQ21: =56604/1634.3*G21 -> 935.14532 | AR21: =S21*0.03 -> 2121.93 | AS21: =AK21-AP21-AQ21+AR21 -> 21940.02 | AT21: =AS21/P21 -> 0.29216353 | AU21: =148498/1634.3*G21 -> 2453.3109 | AV21: =AS21-AU21 -> 19486.709 | AW21: =AV21/P21 -> 0.2594941 | AX21: =124162.35/1634.3*G21 -> 2051.2656 | AY21: =AS21+AX21 -> 23991.286 | AZ21: =AY21/P21 -> 0.31947914 | BB21: =P21/$G21 -> 2781.2963 | BC21: =-AC21/$G21 -> -1104.1527 | BD21: =-AD21/$G21 -> -315.06113 | BE21: =-AE21/$G21 -> -16.40356 | BF21: =-AF21/$G21 -> -323.24388 | BG21: =-AG21/$G21 -> -1758.8613 | BH21: =AK21/$G21 -> 1022.435 | BI21: =-AM21/$G21 -> -161.62963 | BJ21: =-AO21/$G21 -> -72.384615 | BK21: =-AP21/$G21 -> -253.79664 | BL21: =-AQ21/$G21 -> -34.635012 | BM21: =AR21/$G21 -> 78.59 | BN21: =AS21/$G21 -> 812.59333 | BO21: =-AU21/$G21 -> -90.863367 | BP21: =AV21/$G21 -> 721.72997 | BQ21: =AX21/$G21 -> 75.972802 | BR21: =AY21/$G21 -> 888.56614
B22: FEBRERO | C22: =B22 -> FEBRERO | D22: 156-2026A | E22: 27 | F22: 46062 | G22: 54 | H22: POTA FILETE CONGELADO | I22: Filete | J22: 2-4 kg 100% blanco, No polyphosphate,no medicine | K22: China | L22: Qingdao | M22: Longkou Yunfeng Aquatic | O22: 1650 | P22: 89100 | Q22: 1534.963 | R22: 6212 | S22: =P22-R22 -> 82888 | T22: 2 | U22: CMA CGM IMAGINATION / 0DVITN1MA | V22: LMM0571149 | W22: CMA CGM | X22: PAITA | Y22: 10005721 | Z22: Compensación | AA22: =B22&Y22&Z22 -> FEBRERO10005721Compensación | AB22: =INDEX('Detalle Costos'!$L$5:$L$158,MATCH(Resumen!AA22,'Detalle Costos'!$C$5:$C$158,0))*1000*0+AI22+229398.68/1634.3-47.35 -> 1765.2217 | AC22: =IFERROR(INDEX('Detalle Costos'!$X$5:$X$158,MATCH(Resumen!AA22,'Detalle Costos'!$C$5:$C$158,0))*AG22,0) -> 57844.8 | AD22: =IFERROR(INDEX('Detalle Costos'!$Z$5:$Z$158,MATCH(Resumen!AA22,'Detalle Costos'!$C$5:$C$158,0))*AG22,0) -> 19109.758 | AE22: =IFERROR(INDEX('Detalle Costos'!$Y$5:$Y$158,MATCH(Resumen!AA22,'Detalle Costos'!$C$5:$C$158,0))*AG22,0) -> 1016.5906 | AF22: =IFERROR(INDEX('Detalle Costos'!$AA$5:$AA$158,MATCH(Resumen!AA22,'Detalle Costos'!$C$5:$C$158,0))*AG22,0) -> 17350.822 | AG22: =AB22*G22 -> 95321.97 | AH22: =+G22 -> 54 | AI22: 1672.2066 | AJ22: =+AI22*AH22 -> 90299.155 | AK22: =P22-AG22 -> -6221.9703 | AL22: =AK22/P22 -> -0.069831316 | AM22: =R22 -> 6212 | AN22: =118461.136538461/5988.21*G22 -> 1068.2493 | AO22: =1882/26*G22 -> 3908.7692 | AP22: =SUM(AM22:AO22) -> 11189.019 | AQ22: =56604/1634.3*G22 -> 1870.2906 | AR22: =S22*0.03 -> 2486.64 | AS22: =AK22-AP22-AQ22+AR22 -> -16794.639 | AT22: =AS22/P22 -> -0.18849203 | AU22: =148498/1634.3*G22 -> 4906.6218 | AV22: =AS22-AU22 -> -21701.261 | AW22: =AV22/P22 -> -0.24356073 | AX22: =124162.35/1634.3*G22 -> 4102.5313 | AY22: =AS22+AX22 -> -12692.108 | AZ22: =AY22/P22 -> -0.1424479 | BB22: =P22/$G22 -> 1650 | BC22: =-AC22/$G22 -> -1071.2 | BD22: =-AD22/$G22 -> -353.8844 | BE22: =-AE22/$G22 -> -18.825752 | BF22: =-AF22/$G22 -> -321.31151 | BG22: =-AG22/$G22 -> -1765.2217 | BH22: =AK22/$G22 -> -115.22167 | BI22: =-AM22/$G22 -> -115.03704 | BJ22: =-AO22/$G22 -> -72.384615 | BK22: =-AP22/$G22 -> -207.20405 | BL22: =-AQ22/$G22 -> -34.635012 | BM22: =AR22/$G22 -> 46.048889 | BN22: =AS22/$G22 -> -311.01184 | BO22: =-AU22/$G22 -> -90.863367 | BP22: =AV22/$G22 -> -401.87521 | BQ22: =AX22/$G22 -> 75.972802 | BR22: =AY22/$G22 -> -235.03904
B23: FEBRERO | C23: =B23 -> FEBRERO | D23: 156-2026B | E23: 27 | F23: 46071 | G23: 81 | H23: POTA FILETE CONGELADO | I23: Filete | J23: 2-4 kg 100% blanco, No polyphosphate,no medicine | K23: China | L23: Qingdao | M23: Longkou Yunfeng Aquatic | O23: 1650 | P23: 133650 | Q23: 1534.963 | R23: 9318 | S23: =P23-R23 -> 124332 | T23: 3 | U23: CMA CGM EXCELLENCE 0DVNNN1MA | V23: LMM0571699 | W23: CMA CGM | X23: PAITA | Y23: 10005721 | Z23: Compensación | AA23: =B23&Y23&Z23 -> FEBRERO10005721Compensación | AB23: =INDEX('Detalle Costos'!$L$5:$L$158,MATCH(Resumen!AA23,'Detalle Costos'!$C$5:$C$158,0))*1000*0+AI23+229398.68/1634.3-47.35 -> 1765.2217 | AC23: =IFERROR(INDEX('Detalle Costos'!$X$5:$X$158,MATCH(Resumen!AA23,'Detalle Costos'!$C$5:$C$158,0))*AG23,0) -> 86767.201 | AD23: =IFERROR(INDEX('Detalle Costos'!$Z$5:$Z$158,MATCH(Resumen!AA23,'Detalle Costos'!$C$5:$C$158,0))*AG23,0) -> 28664.636 | AE23: =IFERROR(INDEX('Detalle Costos'!$Y$5:$Y$158,MATCH(Resumen!AA23,'Detalle Costos'!$C$5:$C$158,0))*AG23,0) -> 1524.8859 | AF23: =IFERROR(INDEX('Detalle Costos'!$AA$5:$AA$158,MATCH(Resumen!AA23,'Detalle Costos'!$C$5:$C$158,0))*AG23,0) -> 26026.233 | AG23: =AB23*G23 -> 142982.96 | AH23: =+G23 -> 81 | AI23: 1672.2066 | AJ23: =+AI23*AH23 -> 135448.73 | AK23: =P23-AG23 -> -9332.9554 | AL23: =AK23/P23 -> -0.069831316 | AM23: =R23 -> 9318 | AN23: =118461.136538461/5988.21*G23 -> 1602.374 | AO23: =1882/26*G23 -> 5863.1538 | AP23: =SUM(AM23:AO23) -> 16783.528 | AQ23: =56604/1634.3*G23 -> 2805.436 | AR23: =S23*0.03 -> 3729.96 | AS23: =AK23-AP23-AQ23+AR23 -> -25191.959 | AT23: =AS23/P23 -> -0.18849203 | AU23: =148498/1634.3*G23 -> 7359.9327 | AV23: =AS23-AU23 -> -32551.892 | AW23: =AV23/P23 -> -0.24356073 | AX23: =124162.35/1634.3*G23 -> 6153.7969 | AY23: =AS23+AX23 -> -19038.162 | AZ23: =AY23/P23 -> -0.1424479 | BB23: =P23/$G23 -> 1650 | BC23: =-AC23/$G23 -> -1071.2 | BD23: =-AD23/$G23 -> -353.8844 | BE23: =-AE23/$G23 -> -18.825752 | BF23: =-AF23/$G23 -> -321.31151 | BG23: =-AG23/$G23 -> -1765.2217 | BH23: =AK23/$G23 -> -115.22167 | BI23: =-AM23/$G23 -> -115.03704 | BJ23: =-AO23/$G23 -> -72.384615 | BK23: =-AP23/$G23 -> -207.20405 | BL23: =-AQ23/$G23 -> -34.635012 | BM23: =AR23/$G23 -> 46.048889 | BN23: =AS23/$G23 -> -311.01184 | BO23: =-AU23/$G23 -> -90.863367 | BP23: =AV23/$G23 -> -401.87521 | BQ23: =AX23/$G23 -> 75.972802 | BR23: =AY23/$G23 -> -235.03904
B24: FEBRERO | C24: =B24 -> FEBRERO | D24: 157-2026 | E24: 28 | F24: 46066 | G24: 24 | H24: POTA CONOS | I24: Conos | K24: Tailandia | L24: Lat Krabang | M24: TSUJINO | N24: Jose | O24: 2000 | P24: 48000 | Q24: 1854.1667 | R24: 3500 | S24: =P24-R24 -> 44500 | T24: 1 | U24: ECO SIROCCO 26007S | V24: 6445030580 | W24: COSCO | X24: PAITA | Y24: 10007969 | Z24: Compensación | AA24: =B24&Y24&Z24 -> FEBRERO10007969Compensación | AB24: =INDEX('Detalle Costos'!$L$5:$L$158,MATCH(Resumen!AA24,'Detalle Costos'!$C$5:$C$158,0))*1000*0+AI24+229398.68/1634.3-47.35 -> 1298.094 | AC24: =IFERROR(INDEX('Detalle Costos'!$X$5:$X$158,MATCH(Resumen!AA24,'Detalle Costos'!$C$5:$C$158,0))*AG24,0) -> 25199.017 | AD24: =IFERROR(INDEX('Detalle Costos'!$Z$5:$Z$158,MATCH(Resumen!AA24,'Detalle Costos'!$C$5:$C$158,0))*AG24,0) -> 4743.482 | AE24: =IFERROR(INDEX('Detalle Costos'!$Y$5:$Y$158,MATCH(Resumen!AA24,'Detalle Costos'!$C$5:$C$158,0))*AG24,0) -> 371.97448 | AF24: =IFERROR(INDEX('Detalle Costos'!$AA$5:$AA$158,MATCH(Resumen!AA24,'Detalle Costos'!$C$5:$C$158,0))*AG24,0) -> 839.78178 | AG24: =AB24*G24 -> 31154.256 | AH24: 23.14 | AI24: 1205.0789 | AJ24: =+AI24*AH24 -> 27885.525 | AK24: =P24-AG24 -> 16845.744 | AL24: =AK24/P24 -> 0.35095301 | AM24: =R24 -> 3500 | AN24: =118461.136538461/5988.21*G24 -> 474.77748 | AO24: =1882/26*G24 -> 1737.2308 | AP24: =SUM(AM24:AO24) -> 5712.0083 | AQ24: =56604/1634.3*G24 -> 831.24029 | AR24: =S24*0.03 -> 1335 | AS24: =AK24-AP24-AQ24+AR24 -> 11637.496 | AT24: =AS24/P24 -> 0.24244783 | AU24: =148498/1634.3*G24 -> 2180.7208 | AV24: =AS24-AU24 -> 9456.775 | AW24: =AV24/P24 -> 0.19701615 | AX24: =124162.35/1634.3*G24 -> 1823.3472 | AY24: =AS24+AX24 -> 13460.843 | AZ24: =AY24/P24 -> 0.28043423 | BB24: =P24/$G24 -> 2000 | BC24: =-AC24/$G24 -> -1049.9591 | BD24: =-AD24/$G24 -> -197.64508 | BE24: =-AE24/$G24 -> -15.498937 | BF24: =-AF24/$G24 -> -34.990907 | BG24: =-AG24/$G24 -> -1298.094 | BH24: =AK24/$G24 -> 701.90601 | BI24: =-AM24/$G24 -> -145.83333 | BJ24: =-AO24/$G24 -> -72.384615 | BK24: =-AP24/$G24 -> -238.00034 | BL24: =-AQ24/$G24 -> -34.635012 | BM24: =AR24/$G24 -> 55.625 | BN24: =AS24/$G24 -> 484.89566 | BO24: =-AU24/$G24 -> -90.863367 | BP24: =AV24/$G24 -> 394.03229 | BQ24: =AX24/$G24 -> 75.972802 | BR24: =AY24/$G24 -> 560.86846
B25: FEBRERO | C25: =B25 -> FEBRERO | D25: 160-2026 | E25: 30 | F25: 46066 | G25: 108 | H25: POTA ALAS CONGELADAS | I25: Alas | K25: China | L25: Qingdao | M25: TSUJINO | N25: Jose | O25: 1600 | P25: 172800 | Q25: 1492.5926 | R25: 11600 | S25: =P25-R25 -> 161200 | T25: 4 | U25: ECO SIROCCO 26007S | V25: 6445031110 | W25: COSCO | X25: PAITA | Y25: 10006720 | Z25: Compensación | AA25: =B25&Y25&Z25 -> FEBRERO10006720Compensación | AB25: =INDEX('Detalle Costos'!$L$5:$L$158,MATCH(Resumen!AA25,'Detalle Costos'!$C$5:$C$158,0))*1000*0+AI25+229398.68/1634.3-47.35 -> 1687.5784 | AC25: =IFERROR(INDEX('Detalle Costos'!$X$5:$X$158,MATCH(Resumen!AA25,'Detalle Costos'!$C$5:$C$158,0))*AG25,0) -> 118149.04 | AD25: =IFERROR(INDEX('Detalle Costos'!$Z$5:$Z$158,MATCH(Resumen!AA25,'Detalle Costos'!$C$5:$C$158,0))*AG25,0) -> 27034.727 | AE25: =IFERROR(INDEX('Detalle Costos'!$Y$5:$Y$158,MATCH(Resumen!AA25,'Detalle Costos'!$C$5:$C$158,0))*AG25,0) -> 1770.7575 | AF25: =IFERROR(INDEX('Detalle Costos'!$AA$5:$AA$158,MATCH(Resumen!AA25,'Detalle Costos'!$C$5:$C$158,0))*AG25,0) -> 35303.945 | AG25: =AB25*G25 -> 182258.47 | AH25: =+G25 -> 108 | AI25: 1594.5633 | AJ25: =+AI25*AH25 -> 172212.84 | AK25: =P25-AG25 -> -9458.469 | AL25: =AK25/P25 -> -0.05473651 | AM25: =R25 -> 11600 | AN25: =118461.136538461/5988.21*G25 -> 2136.4987 | AO25: =1882/26*G25 -> 7817.5385 | AP25: =SUM(AM25:AO25) -> 21554.037 | AQ25: =56604/1634.3*G25 -> 3740.5813 | AR25: =S25*0.03 -> 4836 | AS25: =AK25-AP25-AQ25+AR25 -> -29917.087 | AT25: =AS25/P25 -> -0.17313129 | AU25: =148498/1634.3*G25 -> 9813.2436 | AV25: =AS25-AU25 -> -39730.331 | AW25: =AV25/P25 -> -0.2299209 | AX25: =124162.35/1634.3*G25 -> 8205.0626 | AY25: =AS25+AX25 -> -21712.025 | AZ25: =AY25/P25 -> -0.12564829 | BB25: =P25/$G25 -> 1600 | BC25: =-AC25/$G25 -> -1093.9726 | BD25: =-AD25/$G25 -> -250.32154 | BE25: =-AE25/$G25 -> -16.395903 | BF25: =-AF25/$G25 -> -326.88838 | BG25: =-AG25/$G25 -> -1687.5784 | BH25: =AK25/$G25 -> -87.578416 | BI25: =-AM25/$G25 -> -107.40741 | BJ25: =-AO25/$G25 -> -72.384615 | BK25: =-AP25/$G25 -> -199.57442 | BL25: =-AQ25/$G25 -> -34.635012 | BM25: =AR25/$G25 -> 44.777778 | BN25: =AS25/$G25 -> -277.01007 | BO25: =-AU25/$G25 -> -90.863367 | BP25: =AV25/$G25 -> -367.87344 | BQ25: =AX25/$G25 -> 75.972802 | BR25: =AY25/$G25 -> -201.03727
B26: FEBRERO | C26: =B26 -> FEBRERO | D26: 160-2026 | E26: 30 | F26: 46066 | G26: 108 | H26: POTA ALAS CONGELADAS | I26: Alas | K26: China | L26: Qingdao | M26: TSUJINO | N26: Jose | O26: 1600 | P26: 172800 | Q26: 1492.5926 | R26: 11600 | S26: =P26-R26 -> 161200 | T26: 4 | U26: ECO SIROCCO 26007S | V26: 6445031130 | W26: COSCO | X26: PAITA | Y26: 10006720 | Z26: Compensación | AA26: =B26&Y26&Z26 -> FEBRERO10006720Compensación | AB26: =INDEX('Detalle Costos'!$L$5:$L$158,MATCH(Resumen!AA26,'Detalle Costos'!$C$5:$C$158,0))*1000*0+AI26+229398.68/1634.3-47.35 -> 1687.5784 | AC26: =IFERROR(INDEX('Detalle Costos'!$X$5:$X$158,MATCH(Resumen!AA26,'Detalle Costos'!$C$5:$C$158,0))*AG26,0) -> 118149.04 | AD26: =IFERROR(INDEX('Detalle Costos'!$Z$5:$Z$158,MATCH(Resumen!AA26,'Detalle Costos'!$C$5:$C$158,0))*AG26,0) -> 27034.727 | AE26: =IFERROR(INDEX('Detalle Costos'!$Y$5:$Y$158,MATCH(Resumen!AA26,'Detalle Costos'!$C$5:$C$158,0))*AG26,0) -> 1770.7575 | AF26: =IFERROR(INDEX('Detalle Costos'!$AA$5:$AA$158,MATCH(Resumen!AA26,'Detalle Costos'!$C$5:$C$158,0))*AG26,0) -> 35303.945 | AG26: =AB26*G26 -> 182258.47 | AH26: =+G26 -> 108 | AI26: 1594.5633 | AJ26: =+AI26*AH26 -> 172212.84 | AK26: =P26-AG26 -> -9458.469 | AL26: =AK26/P26 -> -0.05473651 | AM26: =R26 -> 11600 | AN26: =118461.136538461/5988.21*G26 -> 2136.4987 | AO26: =1882/26*G26 -> 7817.5385 | AP26: =SUM(AM26:AO26) -> 21554.037 | AQ26: =56604/1634.3*G26 -> 3740.5813 | AR26: =S26*0.03 -> 4836 | AS26: =AK26-AP26-AQ26+AR26 -> -29917.087 | AT26: =AS26/P26 -> -0.17313129 | AU26: =148498/1634.3*G26 -> 9813.2436 | AV26: =AS26-AU26 -> -39730.331 | AW26: =AV26/P26 -> -0.2299209 | AX26: =124162.35/1634.3*G26 -> 8205.0626 | AY26: =AS26+AX26 -> -21712.025 | AZ26: =AY26/P26 -> -0.12564829 | BB26: =P26/$G26 -> 1600 | BC26: =-AC26/$G26 -> -1093.9726 | BD26: =-AD26/$G26 -> -250.32154 | BE26: =-AE26/$G26 -> -16.395903 | BF26: =-AF26/$G26 -> -326.88838 | BG26: =-AG26/$G26 -> -1687.5784 | BH26: =AK26/$G26 -> -87.578416 | BI26: =-AM26/$G26 -> -107.40741 | BJ26: =-AO26/$G26 -> -72.384615 | BK26: =-AP26/$G26 -> -199.57442 | BL26: =-AQ26/$G26 -> -34.635012 | BM26: =AR26/$G26 -> 44.777778 | BN26: =AS26/$G26 -> -277.01007 | BO26: =-AU26/$G26 -> -90.863367 | BP26: =AV26/$G26 -> -367.87344 | BQ26: =AX26/$G26 -> 75.972802 | BR26: =AY26/$G26 -> -201.03727
B27: FEBRERO | C27: =B27 -> FEBRERO | D27: 162-2026A | E27: 34 | F27: 46070 | G27: 115.5 | H27: POTA ALAS CONGELADAS | I27: Alas | J27: 1-2 kg | K27: China | L27: Qingdao | M27: AVANCE GROUP | N27: James | O27: 1500 | P27: 173250 | Q27: 1382.987 | R27: 13515 | S27: =P27-R27 -> 159735 | T27: 5 | U27: ECO SIROCCO 26007N | V27: LIMG02628500 | W27: ONE | X27: PAITA | Y27: 10006720 | Z27: Compensación | AA27: =B27&Y27&Z27 -> FEBRERO10006720Compensación | AB27: =INDEX('Detalle Costos'!$L$5:$L$158,MATCH(Resumen!AA27,'Detalle Costos'!$C$5:$C$158,0))*1000*0+AI27+229398.68/1634.3-47.35 -> 1687.5784 | AC27: =IFERROR(INDEX('Detalle Costos'!$X$5:$X$158,MATCH(Resumen!AA27,'Detalle Costos'!$C$5:$C$158,0))*AG27,0) -> 126353.83 | AD27: =IFERROR(INDEX('Detalle Costos'!$Z$5:$Z$158,MATCH(Resumen!AA27,'Detalle Costos'!$C$5:$C$158,0))*AG27,0) -> 28912.138 | AE27: =IFERROR(INDEX('Detalle Costos'!$Y$5:$Y$158,MATCH(Resumen!AA27,'Detalle Costos'!$C$5:$C$158,0))*AG27,0) -> 1893.7268 | AF27: =IFERROR(INDEX('Detalle Costos'!$AA$5:$AA$158,MATCH(Resumen!AA27,'Detalle Costos'!$C$5:$C$158,0))*AG27,0) -> 37755.608 | AG27: =AB27*G27 -> 194915.31 | AH27: =+G27 -> 115.5 | AI27: 1594.5633 | AJ27: =+AI27*AH27 -> 184172.06 | AK27: =P27-AG27 -> -21665.307 | AL27: =AK27/P27 -> -0.12505228 | AM27: =R27 -> 13515 | AN27: =118461.136538461/5988.21*G27 -> 2284.8666 | AO27: =1882/26*G27 -> 8360.4231 | AP27: =SUM(AM27:AO27) -> 24160.29 | AQ27: =56604/1634.3*G27 -> 4000.3439 | AR27: =S27*0.03 -> 4792.05 | AS27: =AK27-AP27-AQ27+AR27 -> -45033.891 | AT27: =AS27/P27 -> -0.25993588 | AU27: =148498/1634.3*G27 -> 10494.719 | AV27: =AS27-AU27 -> -55528.61 | AW27: =AV27/P27 -> -0.32051145 | AX27: =124162.35/1634.3*G27 -> 8774.8586 | AY27: =AS27+AX27 -> -36259.032 | AZ27: =AY27/P27 -> -0.20928734 | BB27: =P27/$G27 -> 1500 | BC27: =-AC27/$G27 -> -1093.9726 | BD27: =-AD27/$G27 -> -250.32154 | BE27: =-AE27/$G27 -> -16.395903 | BF27: =-AF27/$G27 -> -326.88838 | BG27: =-AG27/$G27 -> -1687.5784 | BH27: =AK27/$G27 -> -187.57842 | BI27: =-AM27/$G27 -> -117.01299 | BJ27: =-AO27/$G27 -> -72.384615 | BK27: =-AP27/$G27 -> -209.18 | BL27: =-AQ27/$G27 -> -34.635012 | BM27: =AR27/$G27 -> 41.48961 | BN27: =AS27/$G27 -> -389.90382 | BO27: =-AU27/$G27 -> -90.863367 | BP27: =AV27/$G27 -> -480.76718 | BQ27: =AX27/$G27 -> 75.972802 | BR27: =AY27/$G27 -> -313.93101
B28: FEBRERO | C28: =B28 -> FEBRERO | D28: 162-2026B | E28: 34 | F28: 46070 | G28: 46.8 | H28: POTA ALAS CONGELADAS | I28: Alas | J28: 1-2 kg | K28: China | L28: Dalian | M28: AVANCE GROUP | N28: James | O28: 1500 | P28: 70200 | Q28: 1380.2137 | R28: 5606 | S28: =P28-R28 -> 64594 | T28: 2 | U28: ECO SIROCCO 26007N | V28: LIMG02851300 | W28: ONE | X28: PAITA | Y28: 10006720 | Z28: Compensación | AA28: =B28&Y28&Z28 -> FEBRERO10006720Compensación | AB28: =INDEX('Detalle Costos'!$L$5:$L$158,MATCH(Resumen!AA28,'Detalle Costos'!$C$5:$C$158,0))*1000*0+AI28+229398.68/1634.3-47.35 -> 1687.5784 | AC28: =IFERROR(INDEX('Detalle Costos'!$X$5:$X$158,MATCH(Resumen!AA28,'Detalle Costos'!$C$5:$C$158,0))*AG28,0) -> 51197.917 | AD28: =IFERROR(INDEX('Detalle Costos'!$Z$5:$Z$158,MATCH(Resumen!AA28,'Detalle Costos'!$C$5:$C$158,0))*AG28,0) -> 11715.048 | AE28: =IFERROR(INDEX('Detalle Costos'!$Y$5:$Y$158,MATCH(Resumen!AA28,'Detalle Costos'!$C$5:$C$158,0))*AG28,0) -> 767.32825 | AF28: =IFERROR(INDEX('Detalle Costos'!$AA$5:$AA$158,MATCH(Resumen!AA28,'Detalle Costos'!$C$5:$C$158,0))*AG28,0) -> 15298.376 | AG28: =AB28*G28 -> 78978.67 | AH28: =+G28 -> 46.8 | AI28: 1594.5633 | AJ28: =+AI28*AH28 -> 74625.563 | AK28: =P28-AG28 -> -8778.6699 | AL28: =AK28/P28 -> -0.12505228 | AM28: =R28 -> 5606 | AN28: =118461.136538461/5988.21*G28 -> 925.81609 | AO28: =1882/26*G28 -> 3387.6 | AP28: =SUM(AM28:AO28) -> 9919.4161 | AQ28: =56604/1634.3*G28 -> 1620.9186 | AR28: =S28*0.03 -> 1937.82 | AS28: =AK28-AP28-AQ28+AR28 -> -18381.185 | AT28: =AS28/P28 -> -0.26184024 | AU28: =148498/1634.3*G28 -> 4252.4056 | AV28: =AS28-AU28 -> -22633.59 | AW28: =AV28/P28 -> -0.32241581 | AX28: =124162.35/1634.3*G28 -> 3555.5271 | AY28: =AS28+AX28 -> -14825.657 | AZ28: =AY28/P28 -> -0.2111917 | BB28: =P28/$G28 -> 1500 | BC28: =-AC28/$G28 -> -1093.9726 | BD28: =-AD28/$G28 -> -250.32154 | BE28: =-AE28/$G28 -> -16.395903 | BF28: =-AF28/$G28 -> -326.88838 | BG28: =-AG28/$G28 -> -1687.5784 | BH28: =AK28/$G28 -> -187.57842 | BI28: =-AM28/$G28 -> -119.78632 | BJ28: =-AO28/$G28 -> -72.384615 | BK28: =-AP28/$G28 -> -211.95334 | BL28: =-AQ28/$G28 -> -34.635012 | BM28: =AR28/$G28 -> 41.40641 | BN28: =AS28/$G28 -> -392.76035 | BO28: =-AU28/$G28 -> -90.863367 | BP28: =AV28/$G28 -> -483.62372 | BQ28: =AX28/$G28 -> 75.972802 | BR28: =AY28/$G28 -> -316.78755
B29: FEBRERO | C29: =B29 -> FEBRERO | D29: 162-2026C | E29: 34 | F29: 46070 | G29: 81 | H29: POTA ALAS CONGELADAS | I29: Alas | J29: 1-2 kg | K29: China | L29: Xiamen | M29: AVANCE GROUP | N29: James | O29: 1500 | P29: 121500 | Q29: 1385.0741 | R29: 9309 | S29: =P29-R29 -> 112191 | T29: 3 | U29: ECO SIROCCO 26007N | V29: LIMG02630500 | W29: ONE | X29: PAITA | Y29: 10006720 | Z29: Compensación | AA29: =B29&Y29&Z29 -> FEBRERO10006720Compensación | AB29: =INDEX('Detalle Costos'!$L$5:$L$158,MATCH(Resumen!AA29,'Detalle Costos'!$C$5:$C$158,0))*1000*0+AI29+229398.68/1634.3-47.35 -> 1687.5784 | AC29: =IFERROR(INDEX('Detalle Costos'!$X$5:$X$158,MATCH(Resumen!AA29,'Detalle Costos'!$C$5:$C$158,0))*AG29,0) -> 88611.78 | AD29: =IFERROR(INDEX('Detalle Costos'!$Z$5:$Z$158,MATCH(Resumen!AA29,'Detalle Costos'!$C$5:$C$158,0))*AG29,0) -> 20276.045 | AE29: =IFERROR(INDEX('Detalle Costos'!$Y$5:$Y$158,MATCH(Resumen!AA29,'Detalle Costos'!$C$5:$C$158,0))*AG29,0) -> 1328.0681 | AF29: =IFERROR(INDEX('Detalle Costos'!$AA$5:$AA$158,MATCH(Resumen!AA29,'Detalle Costos'!$C$5:$C$158,0))*AG29,0) -> 26477.959 | AG29: =AB29*G29 -> 136693.85 | AH29: =+G29 -> 81 | AI29: 1594.5633 | AJ29: =+AI29*AH29 -> 129159.63 | AK29: =P29-AG29 -> -15193.852 | AL29: =AK29/P29 -> -0.12505228 | AM29: =R29 -> 9309 | AN29: =118461.136538461/5988.21*G29 -> 1602.374 | AO29: =1882/26*G29 -> 5863.1538 | AP29: =SUM(AM29:AO29) -> 16774.528 | AQ29: =56604/1634.3*G29 -> 2805.436 | AR29: =S29*0.03 -> 3365.73 | AS29: =AK29-AP29-AQ29+AR29 -> -31408.086 | AT29: =AS29/P29 -> -0.25850276 | AU29: =148498/1634.3*G29 -> 7359.9327 | AV29: =AS29-AU29 -> -38768.018 | AW29: =AV29/P29 -> -0.31907834 | AX29: =124162.35/1634.3*G29 -> 6153.7969 | AY29: =AS29+AX29 -> -25254.289 | AZ29: =AY29/P29 -> -0.20785423 | BB29: =P29/$G29 -> 1500 | BC29: =-AC29/$G29 -> -1093.9726 | BD29: =-AD29/$G29 -> -250.32154 | BE29: =-AE29/$G29 -> -16.395903 | BF29: =-AF29/$G29 -> -326.88838 | BG29: =-AG29/$G29 -> -1687.5784 | BH29: =AK29/$G29 -> -187.57842 | BI29: =-AM29/$G29 -> -114.92593 | BJ29: =-AO29/$G29 -> -72.384615 | BK29: =-AP29/$G29 -> -207.09294 | BL29: =-AQ29/$G29 -> -34.635012 | BM29: =AR29/$G29 -> 41.552222 | BN29: =AS29/$G29 -> -387.75414 | BO29: =-AU29/$G29 -> -90.863367 | BP29: =AV29/$G29 -> -478.61751 | BQ29: =AX29/$G29 -> 75.972802 | BR29: =AY29/$G29 -> -311.78134
B30: FEBRERO | C30: =B30 -> FEBRERO | D30: 164-2026 | E30: 40 | F30: 46080 | G30: 27 | H30: POTA FILETE DARUMA | I30: Daruma | K30: China | L30: Yantai | M30: SACRAMENTO CO., LTD | N30: julia | O30: 3400 | P30: 91800 | Q30: 3292.5926 | R30: 2900 | S30: =P30-R30 -> 88900 | T30: 1 | U30: ECO SIROCCO 26009S | V30: 6445569300 | W30: COSCO | X30: PAITA | Y30: 10009239 | Z30: Compensación | AA30: =B30&Y30&Z30 -> FEBRERO10009239Compensación | AB30: =INDEX('Detalle Costos'!$L$5:$L$158,MATCH(Resumen!AA30,'Detalle Costos'!$C$5:$C$158,0))*1000*0+AI30+229398.68/1634.3-47.35 -> 2162.0637 | AC30: =IFERROR(INDEX('Detalle Costos'!$X$5:$X$158,MATCH(Resumen!AA30,'Detalle Costos'!$C$5:$C$158,0))*AG30,0) -> 29695.701 | AD30: =IFERROR(INDEX('Detalle Costos'!$Z$5:$Z$158,MATCH(Resumen!AA30,'Detalle Costos'!$C$5:$C$158,0))*AG30,0) -> 19399.333 | AE30: =IFERROR(INDEX('Detalle Costos'!$Y$5:$Y$158,MATCH(Resumen!AA30,'Detalle Costos'!$C$5:$C$158,0))*AG30,0) -> 373.38301 | AF30: =IFERROR(INDEX('Detalle Costos'!$AA$5:$AA$158,MATCH(Resumen!AA30,'Detalle Costos'!$C$5:$C$158,0))*AG30,0) -> 8907.3026 | AG30: =AB30*G30 -> 58375.72 | AH30: 27 | AI30: 2069.0486 | AJ30: =AI30*AH30 -> 55864.313 | AK30: =P30-AG30 -> 33424.28 | AL30: =AK30/P30 -> 0.36409891 | AM30: =R30 -> 2900 | AN30: =118461.136538461/5988.21*G30 -> 534.12467 | AO30: =1882/26*G30 -> 1954.3846 | AP30: =SUM(AM30:AO30) -> 5388.5093 | AQ30: =56604/1634.3*G30 -> 935.14532 | AR30: =S30*0.03 -> 2667 | AS30: =AK30-AP30-AQ30+AR30 -> 29767.625 | AT30: =AS30/P30 -> 0.32426607 | AU30: =148498/1634.3*G30 -> 2453.3109 | AV30: =AS30-AU30 -> 27314.314 | AW30: =AV30/P30 -> 0.29754155 | AX30: =124162.35/1634.3*G30 -> 2051.2656 | AY30: =AS30+AX30 -> 31818.891 | AZ30: =AY30/P30 -> 0.34661101 | BB30: =P30/$G30 -> 3400 | BC30: =-AC30/$G30 -> -1099.8408 | BD30: =-AD30/$G30 -> -718.49383 | BE30: =-AE30/$G30 -> -13.829 | BF30: =-AF30/$G30 -> -329.90009 | BG30: =-AG30/$G30 -> -2162.0637 | BH30: =AK30/$G30 -> 1237.9363 | BI30: =-AM30/$G30 -> -107.40741 | BJ30: =-AO30/$G30 -> -72.384615 | BK30: =-AP30/$G30 -> -199.57442 | BL30: =-AQ30/$G30 -> -34.635012 | BM30: =AR30/$G30 -> 98.777778 | BN30: =AS30/$G30 -> 1102.5046 | BO30: =-AU30/$G30 -> -90.863367 | BP30: =AV30/$G30 -> 1011.6413 | BQ30: =AX30/$G30 -> 75.972802 | BR30: =AY30/$G30 -> 1178.4774
B31: FEBRERO | C31: =B31 -> FEBRERO | D31: 168-2026A | E31: 43 | F31: 46077 | G31: 351 | H31: POTA FILETE CONGELADO | I31: Filete | J31: 2-4 AA | K31: China | L31: Qingdao | M31: AVANCE GROUP | N31: James | O31: 1300 | P31: 456300 | Q31: 1300 | R31: =3103*T31 -> 40339 | S31: =P31-R31 -> 415961 | T31: 13 | U31: ECO MARIN 26008N | V31: 6445505270 | W31: COSCO | X31: PAITA | Y31: 10005721 | Z31: Compensación | AA31: =B31&Y31&Z31 -> FEBRERO10005721Compensación | AB31: =INDEX('Detalle Costos'!$L$5:$L$158,MATCH(Resumen!AA31,'Detalle Costos'!$C$5:$C$158,0))*1000*0+AI31+229398.68/1634.3-47.35 -> 1765.2217 | AC31: =IFERROR(INDEX('Detalle Costos'!$X$5:$X$158,MATCH(Resumen!AA31,'Detalle Costos'!$C$5:$C$158,0))*AG31,0) -> 375991.2 | AD31: =IFERROR(INDEX('Detalle Costos'!$Z$5:$Z$158,MATCH(Resumen!AA31,'Detalle Costos'!$C$5:$C$158,0))*AG31,0) -> 124213.42 | AE31: =IFERROR(INDEX('Detalle Costos'!$Y$5:$Y$158,MATCH(Resumen!AA31,'Detalle Costos'!$C$5:$C$158,0))*AG31,0) -> 6607.839 | AF31: =IFERROR(INDEX('Detalle Costos'!$AA$5:$AA$158,MATCH(Resumen!AA31,'Detalle Costos'!$C$5:$C$158,0))*AG31,0) -> 112780.34 | AG31: =AB31*G31 -> 619592.81 | AH31: =+G31 -> 351 | AI31: 1672.2066 | AJ31: =+AI31*AH31 -> 586944.51 | AK31: =P31-AG31 -> -163292.81 | AL31: =AK31/P31 -> -0.35786282 | AM31: =R31 -> 40339 | AN31: =118461.136538461/5988.21*G31 -> 6943.6207 | AO31: =1882/26*G31 -> 25407 | AP31: =SUM(AM31:AO31) -> 72689.621 | AQ31: =56604/1634.3*G31 -> 12156.889 | AR31: =S31*0.03 -> 12478.83 | AS31: =AK31-AP31-AQ31+AR31 -> -235660.49 | AT31: =AS31/P31 -> -0.51645954 | AU31: =148498/1634.3*G31 -> 31893.042 | AV31: =AS31-AU31 -> -267553.53 | AW31: =AV31/P31 -> -0.58635443 | AX31: =124162.35/1634.3*G31 -> 26666.453 | AY31: =AS31+AX31 -> -208994.03 | AZ31: =AY31/P31 -> -0.45801892 | BB31: =P31/$G31 -> 1300 | BC31: =-AC31/$G31 -> -1071.2 | BD31: =-AD31/$G31 -> -353.8844 | BE31: =-AE31/$G31 -> -18.825752 | BF31: =-AF31/$G31 -> -321.31151 | BG31: =-AG31/$G31 -> -1765.2217 | BH31: =AK31/$G31 -> -465.22167 | BI31: =-AM31/$G31 -> -114.92593 | BJ31: =-AO31/$G31 -> -72.384615 | BK31: =-AP31/$G31 -> -207.09294 | BL31: =-AQ31/$G31 -> -34.635012 | BM31: =AR31/$G31 -> 35.552222 | BN31: =AS31/$G31 -> -671.3974 | BO31: =-AU31/$G31 -> -90.863367 | BP31: =AV31/$G31 -> -762.26076 | BQ31: =AX31/$G31 -> 75.972802 | BR31: =AY31/$G31 -> -595.4246
B32: FEBRERO | C32: =B32 -> FEBRERO | D32: 168-2026B | E32: 43 | F32: 46075 | G32: 135 | H32: POTA FILETE CONGELADO | I32: Filete | J32: 2-4 AA | K32: China | L32: shidao | M32: AVANCE GROUP | N32: James | O32: 1300 | P32: 175500 | Q32: 1300 | R32: =3103*T32 -> 15515 | S32: =P32-R32 -> 159985 | T32: 5 | U32: ECO MARIN 26008S | V32: 6445260920 | W32: COSCO | X32: PAITA | Y32: 10005721 | Z32: Compensación | AA32: =B32&Y32&Z32 -> FEBRERO10005721Compensación | AB32: =INDEX('Detalle Costos'!$L$5:$L$158,MATCH(Resumen!AA32,'Detalle Costos'!$C$5:$C$158,0))*1000*0+AI32+229398.68/1634.3-47.35 -> 1765.2217 | AC32: =IFERROR(INDEX('Detalle Costos'!$X$5:$X$158,MATCH(Resumen!AA32,'Detalle Costos'!$C$5:$C$158,0))*AG32,0) -> 144612 | AD32: =IFERROR(INDEX('Detalle Costos'!$Z$5:$Z$158,MATCH(Resumen!AA32,'Detalle Costos'!$C$5:$C$158,0))*AG32,0) -> 47774.394 | AE32: =IFERROR(INDEX('Detalle Costos'!$Y$5:$Y$158,MATCH(Resumen!AA32,'Detalle Costos'!$C$5:$C$158,0))*AG32,0) -> 2541.4765 | AF32: =IFERROR(INDEX('Detalle Costos'!$AA$5:$AA$158,MATCH(Resumen!AA32,'Detalle Costos'!$C$5:$C$158,0))*AG32,0) -> 43377.054 | AG32: =AB32*G32 -> 238304.93 | AH32: =+G32 -> 135 | AI32: 1672.2066 | AJ32: 238110 | AK32: =P32-AG32 -> -62804.926 | AL32: =AK32/P32 -> -0.35786282 | AM32: =R32 -> 15515 | AN32: =118461.136538461/5988.21*G32 -> 2670.6233 | AO32: =1882/26*G32 -> 9771.9231 | AP32: =SUM(AM32:AO32) -> 27957.546 | AQ32: =56604/1634.3*G32 -> 4675.7266 | AR32: =S32*0.03 -> 4799.55 | AS32: =AK32-AP32-AQ32+AR32 -> -90638.649 | AT32: =AS32/P32 -> -0.51645954 | AU32: =148498/1634.3*G32 -> 12266.554 | AV32: =AS32-AU32 -> -102905.2 | AW32: =AV32/P32 -> -0.58635443 | AX32: =124162.35/1634.3*G32 -> 10256.328 | AY32: =AS32+AX32 -> -80382.32 | AZ32: =AY32/P32 -> -0.45801892 | BB32: =P32/$G32 -> 1300 | BC32: =-AC32/$G32 -> -1071.2 | BD32: =-AD32/$G32 -> -353.8844 | BE32: =-AE32/$G32 -> -18.825752 | BF32: =-AF32/$G32 -> -321.31151 | BG32: =-AG32/$G32 -> -1765.2217 | BH32: =AK32/$G32 -> -465.22167 | BI32: =-AM32/$G32 -> -114.92593 | BJ32: =-AO32/$G32 -> -72.384615 | BK32: =-AP32/$G32 -> -207.09294 | BL32: =-AQ32/$G32 -> -34.635012 | BM32: =AR32/$G32 -> 35.552222 | BN32: =AS32/$G32 -> -671.3974 | BO32: =-AU32/$G32 -> -90.863367 | BP32: =AV32/$G32 -> -762.26076 | BQ32: =AX32/$G32 -> 75.972802 | BR32: =AY32/$G32 -> -595.4246
B33: FEBRERO | C33: =B33 -> FEBRERO | D33: 168-2026C | E33: 43 | F33: 46075 | G33: 54 | H33: POTA FILETE CONGELADO | I33: Filete | J33: 2-4 AA | K33: China | L33: Xiamen | M33: AVANCE GROUP | N33: James | O33: 1300 | P33: 70200 | Q33: 1300 | R33: =3103*T33 -> 6206 | S33: =P33-R33 -> 63994 | T33: 2 | U33: ECO MARIN 26008S | V33: 6445502930 | W33: COSCO | X33: PAITA | Y33: 10005721 | Z33: Compensación | AA33: =B33&Y33&Z33 -> FEBRERO10005721Compensación | AB33: =INDEX('Detalle Costos'!$L$5:$L$158,MATCH(Resumen!AA33,'Detalle Costos'!$C$5:$C$158,0))*1000*0+AI33+229398.68/1634.3-47.35 -> 1765.2217 | AC33: =IFERROR(INDEX('Detalle Costos'!$X$5:$X$158,MATCH(Resumen!AA33,'Detalle Costos'!$C$5:$C$158,0))*AG33,0) -> 57844.8 | AD33: =IFERROR(INDEX('Detalle Costos'!$Z$5:$Z$158,MATCH(Resumen!AA33,'Detalle Costos'!$C$5:$C$158,0))*AG33,0) -> 19109.758 | AE33: =IFERROR(INDEX('Detalle Costos'!$Y$5:$Y$158,MATCH(Resumen!AA33,'Detalle Costos'!$C$5:$C$158,0))*AG33,0) -> 1016.5906 | AF33: =IFERROR(INDEX('Detalle Costos'!$AA$5:$AA$158,MATCH(Resumen!AA33,'Detalle Costos'!$C$5:$C$158,0))*AG33,0) -> 17350.822 | AG33: =AB33*G33 -> 95321.97 | AH33: =+G33 -> 54 | AI33: 1672.2066 | AJ33: =+AI33*AH33 -> 90299.155 | AK33: =P33-AG33 -> -25121.97 | AL33: =AK33/P33 -> -0.35786282 | AM33: =R33 -> 6206 | AN33: =118461.136538461/5988.21*G33 -> 1068.2493 | AO33: =1882/26*G33 -> 3908.7692 | AP33: =SUM(AM33:AO33) -> 11183.019 | AQ33: =56604/1634.3*G33 -> 1870.2906 | AR33: =S33*0.03 -> 1919.82 | AS33: =AK33-AP33-AQ33+AR33 -> -36255.459 | AT33: =AS33/P33 -> -0.51645954 | AU33: =148498/1634.3*G33 -> 4906.6218 | AV33: =AS33-AU33 -> -41162.081 | AW33: =AV33/P33 -> -0.58635443 | AX33: =124162.35/1634.3*G33 -> 4102.5313 | AY33: =AS33+AX33 -> -32152.928 | AZ33: =AY33/P33 -> -0.45801892 | BB33: =P33/$G33 -> 1300 | BC33: =-AC33/$G33 -> -1071.2 | BD33: =-AD33/$G33 -> -353.8844 | BE33: =-AE33/$G33 -> -18.825752 | BF33: =-AF33/$G33 -> -321.31151 | BG33: =-AG33/$G33 -> -1765.2217 | BH33: =AK33/$G33 -> -465.22167 | BI33: =-AM33/$G33 -> -114.92593 | BJ33: =-AO33/$G33 -> -72.384615 | BK33: =-AP33/$G33 -> -207.09294 | BL33: =-AQ33/$G33 -> -34.635012 | BM33: =AR33/$G33 -> 35.552222 | BN33: =AS33/$G33 -> -671.3974 | BO33: =-AU33/$G33 -> -90.863367 | BP33: =AV33/$G33 -> -762.26076 | BQ33: =AX33/$G33 -> 75.972802 | BR33: =AY33/$G33 -> -595.4246
B34: FEBRERO | C34: =B34 -> FEBRERO | D34: 170-2026A | E34: 43 | F34: 46076 | G34: 156 | H34: POTA REJOS CONGELADOS | I34: Rejos | J34: 9 FCL 1-2 / 1 FCL 2-UP | K34: España | L34: Vigo | M34: KULALIA | N34: Ramon | O34: 2500 | P34: 390000 | Q34: 2337.2308 | R34: 25392 | S34: =P34-R34 -> 364608 | T34: 4 | U34: CAPE SABLE 609N | V34: 11428031 | W34: HAPAG | X34: PAITA | Y34: 10007162 | Z34: Compensación | AA34: =B34&Y34&Z34 -> FEBRERO10007162Compensación | AB34: =INDEX('Detalle Costos'!$L$5:$L$158,MATCH(Resumen!AA34,'Detalle Costos'!$C$5:$C$158,0))*1000*0+AI34+229398.68/1634.3-47.35 -> 1758.8613 | AC34: =IFERROR(INDEX('Detalle Costos'!$X$5:$X$158,MATCH(Resumen!AA34,'Detalle Costos'!$C$5:$C$158,0))*AG34,0) -> 172247.83 | AD34: =IFERROR(INDEX('Detalle Costos'!$Z$5:$Z$158,MATCH(Resumen!AA34,'Detalle Costos'!$C$5:$C$158,0))*AG34,0) -> 49149.537 | AE34: =IFERROR(INDEX('Detalle Costos'!$Y$5:$Y$158,MATCH(Resumen!AA34,'Detalle Costos'!$C$5:$C$158,0))*AG34,0) -> 2558.9554 | AF34: =IFERROR(INDEX('Detalle Costos'!$AA$5:$AA$158,MATCH(Resumen!AA34,'Detalle Costos'!$C$5:$C$158,0))*AG34,0) -> 50426.046 | AG34: =AB34*G34 -> 274382.36 | AH34: =+G34 -> 156 | AI34: 1665.8462 | AJ34: =AI34*AH34 -> 259872.01 | AK34: =P34-AG34 -> 115617.64 | AL34: =AK34/P34 -> 0.29645548 | AM34: =R34 -> 25392 | AN34: =118461.136538461/5988.21*G34 -> 3086.0536 | AO34: =1882/26*G34 -> 11292 | AP34: =SUM(AM34:AO34) -> 39770.054 | AQ34: =56604/1634.3*G34 -> 5403.0619 | AR34: =S34*0.03 -> 10938.24 | AS34: =AK34-AP34-AQ34+AR34 -> 81382.76 | AT34: =AS34/P34 -> 0.20867374 | AU34: =148498/1634.3*G34 -> 14174.685 | AV34: =AS34-AU34 -> 67208.075 | AW34: =AV34/P34 -> 0.1723284 | AX34: =124162.35/1634.3*G34 -> 11851.757 | AY34: =AS34+AX34 -> 93234.517 | AZ34: =AY34/P34 -> 0.23906286 | BB34: =P34/$G34 -> 2500 | BC34: =-AC34/$G34 -> -1104.1527 | BD34: =-AD34/$G34 -> -315.06113 | BE34: =-AE34/$G34 -> -16.40356 | BF34: =-AF34/$G34 -> -323.24388 | BG34: =-AG34/$G34 -> -1758.8613 | BH34: =AK34/$G34 -> 741.13869 | BI34: =-AM34/$G34 -> -162.76923 | BJ34: =-AO34/$G34 -> -72.384615 | BK34: =-AP34/$G34 -> -254.93624 | BL34: =-AQ34/$G34 -> -34.635012 | BM34: =AR34/$G34 -> 70.116923 | BN34: =AS34/$G34 -> 521.68436 | BO34: =-AU34/$G34 -> -90.863367 | BP34: =AV34/$G34 -> 430.82099 | BQ34: =AX34/$G34 -> 75.972802 | BR34: =AY34/$G34 -> 597.65716
B35: FEBRERO | C35: =B35 -> FEBRERO | E35: 46080 | F35: 46080 | G35: 0 | H35: RESIDUOS DE POTA | I35: Residuos | J35: Residuos | K35: Residuos | L35: Residuos | M35: PROVEEDORA DE PRODUCTOS MARINOS | O35: 0 | P35: 40026 | Q35: 0 | R35: 0 | S35: =P35-R35 -> 40026 | AB35: 0 | AC35: =IFERROR(INDEX('Detalle Costos'!$X$5:$X$158,MATCH(Resumen!AA35,'Detalle Costos'!$C$5:$C$158,0))*AG35,0) -> 0 | AD35: =IFERROR(INDEX('Detalle Costos'!$Z$5:$Z$158,MATCH(Resumen!AA35,'Detalle Costos'!$C$5:$C$158,0))*AG35,0) -> 0 | AE35: =IFERROR(INDEX('Detalle Costos'!$Y$5:$Y$158,MATCH(Resumen!AA35,'Detalle Costos'!$C$5:$C$158,0))*AG35,0) -> 0 | AF35: =IFERROR(INDEX('Detalle Costos'!$AA$5:$AA$158,MATCH(Resumen!AA35,'Detalle Costos'!$C$5:$C$158,0))*AG35,0) -> 0 | AG35: =AB35*G35 -> 0 | AK35: =P35-AG35 -> 40026 | AL35: =AK35/P35 -> 1 | AM35: =R35 -> 0 | AN35: =118461.136538461/5988.21*G35 -> 0 | AO35: =1882/26*G35 -> 0 | AP35: =SUM(AM35:AO35) -> 0 | AQ35: =56604/1634.3*G35 -> 0 | AR35: 0 | AS35: =AK35-AP35-AQ35+AR35 -> 40026 | AT35: =AS35/P35 -> 1 | AU35: =131251/248*G35 -> 0 | AV35: =AS35-AU35 -> 40026 | AW35: =AV35/P35 -> 1 | AX35: =123530/248*G35 -> 0 | AY35: =AS35+AX35 -> 40026 | AZ35: =AY35/P35 -> 1 | BB35: 0 | BC35: 0 | BD35: 0 | BE35: 0 | BF35: 0 | BG35: 0 | BH35: 0 | BI35: 0 | BJ35: 0 | BK35: 0 | BL35: 0 | BM35: 0 | BN35: 0 | BO35: 0 | BP35: 0 | BQ35: 0 | BR35: 0
B36: FEBRERO | C36: MARZO | D36: 150-2026B | E36: 325 | F36: 46084 | G36: 26 | H36: POTA REJOS CONGELADOS | I36: Rejos | J36: 1-2 KG | K36: España | L36: Vigo | M36: OVERSEA | N36: Avelino | O36: 2600 | P36: 67600 | Q36: 2518.6154 | R36: 4232 | S36: =P36-R36 -> 63368 | T36: 1 | U36: LEONIDAS Z 610N | V36: 51077247 | Y36: 10007162 | Z36: Inventario final | AA36: =B36&Y36&Z36 -> FEBRERO10007162Inventario final | AB36: =AI36-616968.19/1968.8+215187/1968.8-47.35 -> 1766.7551 | AC36: =IFERROR(INDEX('Costos Producción Febrero'!$G$34:$G$57,MATCH(Resumen!Y36,'Costos Producción Febrero'!$B$34:$B$57,0))*AB36*G36,0) -> 28165.464 | AD36: =IFERROR(INDEX('Costos Producción Febrero'!$H$34:$H$57,MATCH(Resumen!Y36,'Costos Producción Febrero'!$B$34:$B$57,0))*AB36*G36,0) -> 7996.7368 | AE36: =IFERROR(INDEX('Costos Producción Febrero'!$I$34:$I$57,MATCH(Resumen!Y36,'Costos Producción Febrero'!$B$34:$B$57,0))*AB36*G36,0) -> 425.85043 | AF36: =IFERROR(INDEX('Costos Producción Febrero'!$J$34:$J$57,MATCH(Resumen!Y36,'Costos Producción Febrero'!$B$34:$B$57,0))*AB36*G36,0) -> 9347.5826 | AG36: =SUM(AC36:AF36) -> 45935.633 | AI36: 2018.1793 | AK36: =P36-AG36 -> 21664.367 | AL36: =AK36/P36 -> 0.32047879 | AM36: =R36 -> 4232 | AN36: =118461.136538461/5988.21*G36 -> 514.34227 | AO36: =1882/26*G36 -> 1882 | AP36: =SUM(AM36:AO36) -> 6628.3423 | AQ36: =78579/1995.8*G36 -> 1023.6767 | AR36: =S36*0.03 -> 1901.04 | AS36: =AK36-AP36-AQ36+AR36 -> 15913.388 | AT36: =AS36/P36 -> 0.23540514 | AU36: =154473/1995.8*G36 -> 2012.375 | AV36: =AS36-AU36 -> 13901.013 | AW36: =AV36/P36 -> 0.20563628 | AX36: =123484.35/1997.8*G36 -> 1607.0643 | AY36: =AS36+AX36 -> 17520.452 | AZ36: =AY36/P36 -> 0.25917828 | BB36: =P36/$G36 -> 2600 | BC36: =-AC36/$G36 -> -1083.2871 | BD36: =-AD36/$G36 -> -307.5668 | BE36: =-AE36/$G36 -> -16.378863 | BF36: =-AF36/$G36 -> -359.52241 | BG36: =-AG36/$G36 -> -1766.7551 | BH36: =AK36/$G36 -> 833.24487 | BI36: =-AM36/$G36 -> -162.76923 | BJ36: =-AO36/$G36 -> -72.384615 | BK36: =-AP36/$G36 -> -254.93624 | BL36: =-AQ36/$G36 -> -39.372182 | BM36: =AR36/$G36 -> 73.116923 | BN36: =AS36/$G36 -> 612.05337 | BO36: =-AU36/$G36 -> -77.399038 | BP36: =AV36/$G36 -> 534.65433 | BQ36: =AX36/$G36 -> 61.810166 | BR36: =AY36/$G36 -> 673.86353
B37: FEBRERO | C37: MARZO | D37: 150-2026C | E37: 325 | F37: 46084 | G37: 26 | H37: POTA REJOS CONGELADOS | I37: Rejos | J37: 1-2 KG | K37: España | L37: Vigo | M37: OVERSEA | N37: Avelino | O37: 2600 | P37: 67600 | Q37: 2518.6154 | R37: 4232 | S37: =P37-R37 -> 63368 | T37: 1 | U37: LEONIDAS Z 610N | V37: 37563181 | Y37: 10007162 | Z37: Inventario final | AA37: =B37&Y37&Z37 -> FEBRERO10007162Inventario final | AB37: =AI37-616968.19/1968.8+215187/1968.8-47.35 -> 1766.7551 | AC37: =IFERROR(INDEX('Costos Producción Febrero'!$G$34:$G$57,MATCH(Resumen!Y37,'Costos Producción Febrero'!$B$34:$B$57,0))*AB37*G37,0) -> 28165.464 | AD37: =IFERROR(INDEX('Costos Producción Febrero'!$H$34:$H$57,MATCH(Resumen!Y37,'Costos Producción Febrero'!$B$34:$B$57,0))*AB37*G37,0) -> 7996.7368 | AE37: =IFERROR(INDEX('Costos Producción Febrero'!$I$34:$I$57,MATCH(Resumen!Y37,'Costos Producción Febrero'!$B$34:$B$57,0))*AB37*G37,0) -> 425.85043 | AF37: =IFERROR(INDEX('Costos Producción Febrero'!$J$34:$J$57,MATCH(Resumen!Y37,'Costos Producción Febrero'!$B$34:$B$57,0))*AB37*G37,0) -> 9347.5826 | AG37: =SUM(AC37:AF37) -> 45935.633 | AI37: 2018.1793 | AK37: =P37-AG37 -> 21664.367 | AL37: =AK37/P37 -> 0.32047879 | AM37: =R37 -> 4232 | AN37: =118461.136538461/5988.21*G37 -> 514.34227 | AO37: =1882/26*G37 -> 1882 | AP37: =SUM(AM37:AO37) -> 6628.3423 | AQ37: =78579/1995.8*G37 -> 1023.6767 | AR37: =S37*0.03 -> 1901.04 | AS37: =AK37-AP37-AQ37+AR37 -> 15913.388 | AT37: =AS37/P37 -> 0.23540514 | AU37: =154473/1995.8*G37 -> 2012.375 | AV37: =AS37-AU37 -> 13901.013 | AW37: =AV37/P37 -> 0.20563628 | AX37: =123484.35/1997.8*G37 -> 1607.0643 | AY37: =AS37+AX37 -> 17520.452 | AZ37: =AY37/P37 -> 0.25917828 | BB37: =P37/$G37 -> 2600 | BC37: =-AC37/$G37 -> -1083.2871 | BD37: =-AD37/$G37 -> -307.5668 | BE37: =-AE37/$G37 -> -16.378863 | BF37: =-AF37/$G37 -> -359.52241 | BG37: =-AG37/$G37 -> -1766.7551 | BH37: =AK37/$G37 -> 833.24487 | BI37: =-AM37/$G37 -> -162.76923 | BJ37: =-AO37/$G37 -> -72.384615 | BK37: =-AP37/$G37 -> -254.93624 | BL37: =-AQ37/$G37 -> -39.372182 | BM37: =AR37/$G37 -> 73.116923 | BN37: =AS37/$G37 -> 612.05337 | BO37: =-AU37/$G37 -> -77.399038 | BP37: =AV37/$G37 -> 534.65433 | BQ37: =AX37/$G37 -> 61.810166 | BR37: =AY37/$G37 -> 673.86353
B38: FEBRERO | C38: MARZO | D38: 159-2026A | E38: 30 | F38: 46084 | G38: 24 | H38: POTA FILETE CONGELADO | I38: Filete | J38: B | K38: Japón | L38: Sendai | M38: TSUJINO | N38: Jose | O38: 1700 | P38: =40800-1190 -> 39610 | Q38: 1562.375 | R38: 3303 | S38: =P38-R38 -> 36307 | T38: 1 | U38: ECO SIROCCO 26009N | V38: LIMG03265300 | W38: ONE | X38: PAITA | Y38: 10005721 | Z38: Inventario final | AA38: =B38&Y38&Z38 -> FEBRERO10005721Inventario final | AB38: =AI38-616968.19/1968.8+215187/1968.8-47.35 -> 1843.8447 | AC38: =IFERROR(INDEX('Costos Producción Febrero'!$G$34:$G$57,MATCH(Resumen!Y38,'Costos Producción Febrero'!$B$34:$B$57,0))*AB38*G38,0) -> 26874.889 | AD38: =IFERROR(INDEX('Costos Producción Febrero'!$H$34:$H$57,MATCH(Resumen!Y38,'Costos Producción Febrero'!$B$34:$B$57,0))*AB38*G38,0) -> 7874.9003 | AE38: =IFERROR(INDEX('Costos Producción Febrero'!$I$34:$I$57,MATCH(Resumen!Y38,'Costos Producción Febrero'!$B$34:$B$57,0))*AB38*G38,0) -> 482.43412 | AF38: =IFERROR(INDEX('Costos Producción Febrero'!$J$34:$J$57,MATCH(Resumen!Y38,'Costos Producción Febrero'!$B$34:$B$57,0))*AB38*G38,0) -> 9020.0504 | AG38: =SUM(AC38:AF38) -> 44252.273 | AI38: 2095.2689 | AK38: =P38-AG38 -> -4642.2734 | AL38: =AK38/P38 -> -0.11719953 | AM38: =R38 -> 3303 | AN38: =118461.136538461/5988.21*G38 -> 474.77748 | AO38: =1882/26*G38 -> 1737.2308 | AP38: =SUM(AM38:AO38) -> 5515.0083 | AQ38: =78579/1995.8*G38 -> 944.93236 | AR38: =S38*0.03 -> 1089.21 | AS38: =AK38-AP38-AQ38+AR38 -> -10013.004 | AT38: =AS38/P38 -> -0.2527898 | AU38: =154473/1995.8*G38 -> 1857.5769 | AV38: =AS38-AU38 -> -11870.581 | AW38: =AV38/P38 -> -0.29968647 | AX38: =123484.35/1997.8*G38 -> 1483.444 | AY38: =AS38+AX38 -> -8529.56 | AZ38: =AY38/P38 -> -0.21533855 | BB38: =P38/$G38 -> 1650.4167 | BC38: =-AC38/$G38 -> -1119.787 | BD38: =-AD38/$G38 -> -328.12085 | BE38: =-AE38/$G38 -> -20.101422 | BF38: =-AF38/$G38 -> -375.83543 | BG38: =-AG38/$G38 -> -1843.8447 | BH38: =AK38/$G38 -> -193.42806 | BI38: =-AM38/$G38 -> -137.625 | BJ38: =-AO38/$G38 -> -72.384615 | BK38: =-AP38/$G38 -> -229.79201 | BL38: =-AQ38/$G38 -> -39.372182 | BM38: =AR38/$G38 -> 45.38375 | BN38: =AS38/$G38 -> -417.2085 | BO38: =-AU38/$G38 -> -77.399038 | BP38: =AV38/$G38 -> -494.60754 | BQ38: =AX38/$G38 -> 61.810166 | BR38: =AY38/$G38 -> -355.39834
B39: FEBRERO | C39: MARZO | D39: 161-2026A | E39: 30 | F39: 46085 | G39: 72 | H39: POTA NUCAS | I39: Nucas | J39: 500-up | K39: Tailandia | L39: Lat Krabang | M39: TSUJINO | N39: Jose | O39: 1400 | P39: =100800-6160 -> 94640 | Q39: 1266.5417 | R39: 9609 | S39: =P39-R39 -> 85031 | T39: 3 | U39: ECO SIROCCO 26009N | V39: LIMG03094300 | W39: ONE LINE | X39: PAITA | Y39: 10005779 | Z39: Inventario final | AA39: =B39&Y39&Z39 -> FEBRERO10005779Inventario final | AB39: =AI39-616968.19/1968.8+215187/1968.8-47.35 -> 1848.8139 | AC39: =IFERROR(INDEX('Costos Producción Febrero'!$G$34:$G$57,MATCH(Resumen!Y39,'Costos Producción Febrero'!$B$34:$B$57,0))*AB39*G39,0) -> 77286.439 | AD39: =IFERROR(INDEX('Costos Producción Febrero'!$H$34:$H$57,MATCH(Resumen!Y39,'Costos Producción Febrero'!$B$34:$B$57,0))*AB39*G39,0) -> 29412.193 | AE39: =IFERROR(INDEX('Costos Producción Febrero'!$I$34:$I$57,MATCH(Resumen!Y39,'Costos Producción Febrero'!$B$34:$B$57,0))*AB39*G39,0) -> 850.24346 | AF39: =IFERROR(INDEX('Costos Producción Febrero'!$J$34:$J$57,MATCH(Resumen!Y39,'Costos Producción Febrero'!$B$34:$B$57,0))*AB39*G39,0) -> 25565.728 | AG39: =SUM(AC39:AF39) -> 133114.6 | AI39: 2100.2381 | AK39: =P39-AG39 -> -38474.603 | AL39: =AK39/P39 -> -0.40653638 | AM39: =R39 -> 9609 | AN39: =118461.136538461/5988.21*G39 -> 1424.3325 | AO39: =1882/26*G39 -> 5211.6923 | AP39: =SUM(AM39:AO39) -> 16245.025 | AQ39: =78579/1995.8*G39 -> 2834.7971 | AR39: =S39*0.03 -> 2550.93 | AS39: =AK39-AP39-AQ39+AR39 -> -55003.495 | AT39: =AS39/P39 -> -0.58118655 | AU39: =154473/1995.8*G39 -> 5572.7307 | AV39: =AS39-AU39 -> -60576.226 | AW39: =AV39/P39 -> -0.64007001 | AX39: =123484.35/1997.8*G39 -> 4450.332 | AY39: =AS39+AX39 -> -50553.163 | AZ39: =AY39/P39 -> -0.53416275 | BB39: =P39/$G39 -> 1314.4444 | BC39: =-AC39/$G39 -> -1073.4228 | BD39: =-AD39/$G39 -> -408.50268 | BE39: =-AE39/$G39 -> -11.808937 | BF39: =-AF39/$G39 -> -355.07956 | BG39: =-AG39/$G39 -> -1848.8139 | BH39: =AK39/$G39 -> -534.36949 | BI39: =-AM39/$G39 -> -133.45833 | BJ39: =-AO39/$G39 -> -72.384615 | BK39: =-AP39/$G39 -> -225.62534 | BL39: =-AQ39/$G39 -> -39.372182 | BM39: =AR39/$G39 -> 35.429583 | BN39: =AS39/$G39 -> -763.93743 | BO39: =-AU39/$G39 -> -77.399038 | BP39: =AV39/$G39 -> -841.33647 | BQ39: =AX39/$G39 -> 61.810166 | BR39: =AY39/$G39 -> -702.12726
B40: FEBRERO | C40: MARZO | D40: 161-2026B | E40: 30 | F40: 46108 | G40: 48 | H40: POTA NUCAS | I40: Nucas | J40: 500-up | K40: Tailandia | L40: Lat Krabang | M40: TSUJINO | N40: Jose | O40: 1400 | P40: 67200 | Q40: 1254.1667 | R40: 7000 | S40: =P40-R40 -> 60200 | T40: 2 | U40: ECO SIROCCO 26013S | V40: 6446527790 | W40: COSCO | X40: PAITA | Y40: 10005779 | Z40: Inventario final | AA40: =B40&Y40&Z40 -> FEBRERO10005779Inventario final | AB40: =AI40-616968.19/1968.8+215187/1968.8-47.35 -> 1848.8139 | AC40: =IFERROR(INDEX('Costos Producción Febrero'!$G$34:$G$57,MATCH(Resumen!Y40,'Costos Producción Febrero'!$B$34:$B$57,0))*AB40*G40,0) -> 51524.293 | AD40: =IFERROR(INDEX('Costos Producción Febrero'!$H$34:$H$57,MATCH(Resumen!Y40,'Costos Producción Febrero'!$B$34:$B$57,0))*AB40*G40,0) -> 19608.128 | AE40: =IFERROR(INDEX('Costos Producción Febrero'!$I$34:$I$57,MATCH(Resumen!Y40,'Costos Producción Febrero'!$B$34:$B$57,0))*AB40*G40,0) -> 566.82897 | AF40: =IFERROR(INDEX('Costos Producción Febrero'!$J$34:$J$57,MATCH(Resumen!Y40,'Costos Producción Febrero'!$B$34:$B$57,0))*AB40*G40,0) -> 17043.819 | AG40: =SUM(AC40:AF40) -> 88743.069 | AI40: 2100.2381 | AK40: =P40-AG40 -> -21543.069 | AL40: =AK40/P40 -> -0.32058138 | AM40: =R40 -> 7000 | AN40: =118461.136538461/5988.21*G40 -> 949.55497 | AO40: =1882/26*G40 -> 3474.4615 | AP40: =SUM(AM40:AO40) -> 11424.017 | AQ40: =78579/1995.8*G40 -> 1889.8647 | AR40: =S40*0.03 -> 1806 | AS40: =AK40-AP40-AQ40+AR40 -> -33050.95 | AT40: =AS40/P40 -> -0.49182961 | AU40: =154473/1995.8*G40 -> 3715.1538 | AV40: =AS40-AU40 -> -36766.104 | AW40: =AV40/P40 -> -0.54711464 | AX40: =123484.35/1997.8*G40 -> 2966.888 | AY40: =AS40+AX40 -> -30084.062 | AZ40: =AY40/P40 -> -0.44767949 | BB40: =P40/$G40 -> 1400 | BC40: =-AC40/$G40 -> -1073.4228 | BD40: =-AD40/$G40 -> -408.50268 | BE40: =-AE40/$G40 -> -11.808937 | BF40: =-AF40/$G40 -> -355.07956 | BG40: =-AG40/$G40 -> -1848.8139 | BH40: =AK40/$G40 -> -448.81393 | BI40: =-AM40/$G40 -> -145.83333 | BJ40: =-AO40/$G40 -> -72.384615 | BK40: =-AP40/$G40 -> -238.00034 | BL40: =-AQ40/$G40 -> -39.372182 | BM40: =AR40/$G40 -> 37.625 | BN40: =AS40/$G40 -> -688.56146 | BO40: =-AU40/$G40 -> -77.399038 | BP40: =AV40/$G40 -> -765.9605 | BQ40: =AX40/$G40 -> 61.810166 | BR40: =AY40/$G40 -> -626.75129
B41: FEBRERO | C41: MARZO | D41: 163-2026 | E41: 34 | F41: 46087 | G41: 48 | H41: POTA ALAS CONGELADAS | I41: Alas | J41: 1-up | K41: korea | L41: Busan | M41: TSUJINO | N41: Jose | O41: 1600 | P41: 76800 | Q41: 1479.1667 | R41: 5800 | S41: =P41-R41 -> 71000 | T41: 2 | U41: ECO MARIN 26010S | V41: 6445718250 | W41: COSCO | X41: PAITA | Y41: 10006720 | Z41: Inventario final | AA41: =B41&Y41&Z41 -> FEBRERO10006720Inventario final | AB41: =AI41-616968.19/1968.8+215187/1968.8-47.35 -> 1697.774 | AC41: =IFERROR(INDEX('Costos Producción Febrero'!$G$34:$G$57,MATCH(Resumen!Y41,'Costos Producción Febrero'!$B$34:$B$57,0))*AB41*G41,0) -> 52293.587 | AD41: =IFERROR(INDEX('Costos Producción Febrero'!$H$34:$H$57,MATCH(Resumen!Y41,'Costos Producción Febrero'!$B$34:$B$57,0))*AB41*G41,0) -> 10999.292 | AE41: =IFERROR(INDEX('Costos Producción Febrero'!$I$34:$I$57,MATCH(Resumen!Y41,'Costos Producción Febrero'!$B$34:$B$57,0))*AB41*G41,0) -> 761.45985 | AF41: =IFERROR(INDEX('Costos Producción Febrero'!$J$34:$J$57,MATCH(Resumen!Y41,'Costos Producción Febrero'!$B$34:$B$57,0))*AB41*G41,0) -> 17438.811 | AG41: =SUM(AC41:AF41) -> 81493.15 | AI41: 1949.1981 | AK41: =P41-AG41 -> -4693.1504 | AL41: =AK41/P41 -> -0.061108729 | AM41: =R41 -> 5800 | AN41: =118461.136538461/5988.21*G41 -> 949.55497 | AO41: =1882/26*G41 -> 3474.4615 | AP41: =SUM(AM41:AO41) -> 10224.017 | AQ41: =78579/1995.8*G41 -> 1889.8647 | AR41: =S41*0.03 -> 2130 | AS41: =AK41-AP41-AQ41+AR41 -> -14677.032 | AT41: =AS41/P41 -> -0.19110718 | AU41: =154473/1995.8*G41 -> 3715.1538 | AV41: =AS41-AU41 -> -18392.185 | AW41: =AV41/P41 -> -0.23948158 | AX41: =123484.35/1997.8*G41 -> 2966.888 | AY41: =AS41+AX41 -> -11710.144 | AZ41: =AY41/P41 -> -0.15247583 | BB41: =P41/$G41 -> 1600 | BC41: =-AC41/$G41 -> -1089.4497 | BD41: =-AD41/$G41 -> -229.15192 | BE41: =-AE41/$G41 -> -15.863747 | BF41: =-AF41/$G41 -> -363.30857 | BG41: =-AG41/$G41 -> -1697.774 | BH41: =AK41/$G41 -> -97.773966 | BI41: =-AM41/$G41 -> -120.83333 | BJ41: =-AO41/$G41 -> -72.384615 | BK41: =-AP41/$G41 -> -213.00034 | BL41: =-AQ41/$G41 -> -39.372182 | BM41: =AR41/$G41 -> 44.375 | BN41: =AS41/$G41 -> -305.77149 | BO41: =-AU41/$G41 -> -77.399038 | BP41: =AV41/$G41 -> -383.17053 | BQ41: =AX41/$G41 -> 61.810166 | BR41: =AY41/$G41 -> -243.96133
B42: FEBRERO | C42: MARZO | D42: 165-2026 | E42: 40 | F42: 46105 | G42: 27 | H42: POTA MEMBRANA PRECOCIDA | I42: Membrana | K42: China | L42: Qingdao | M42: Longkou Yunfeng Aquatic | O42: 1400 | P42: 37800 | Q42: 1271.6296 | R42: 3466 | S42: =P42-R42 -> 34334 | T42: 1 | U42: CMA CGM BETTER WAYS 0DVOHN1MA | V42: LMM0577574 | W42: CMA CGM | X42: PAITA | AB42: 0 | AC42: =IFERROR(INDEX('Costos Producción Febrero'!$G$34:$G$57,MATCH(Resumen!Y42,'Costos Producción Febrero'!$B$34:$B$57,0))*AB42*G42,0) -> 0 | AD42: =IFERROR(INDEX('Costos Producción Febrero'!$H$34:$H$57,MATCH(Resumen!Y42,'Costos Producción Febrero'!$B$34:$B$57,0))*AB42*G42,0) -> 0 | AE42: =IFERROR(INDEX('Costos Producción Febrero'!$I$34:$I$57,MATCH(Resumen!Y42,'Costos Producción Febrero'!$B$34:$B$57,0))*AB42*G42,0) -> 0 | AF42: =IFERROR(INDEX('Costos Producción Febrero'!$J$34:$J$57,MATCH(Resumen!Y42,'Costos Producción Febrero'!$B$34:$B$57,0))*AB42*G42,0) -> 0 | AG42: =SUM(AC42:AF42) -> 0 | AI42: 0 | AK42: =P42-AG42 -> 37800 | AL42: =AK42/P42 -> 1 | AM42: =R42 -> 3466 | AN42: =118461.136538461/5988.21*G42 -> 534.12467 | AO42: =1882/26*G42 -> 1954.3846 | AP42: =SUM(AM42:AO42) -> 5954.5093 | AQ42: =78579/1995.8*G42 -> 1063.0489 | AR42: =S42*0.03 -> 1030.02 | AS42: =AK42-AP42-AQ42+AR42 -> 31812.462 | AT42: =AS42/P42 -> 0.84159952 | AU42: =154473/1995.8*G42 -> 2089.774 | AV42: =AS42-AU42 -> 29722.688 | AW42: =AV42/P42 -> 0.78631449 | AX42: =123484.35/1997.8*G42 -> 1668.8745 | AY42: =AS42+AX42 -> 33481.336 | AZ42: =AY42/P42 -> 0.88574964 | BB42: =P42/$G42 -> 1400 | BC42: =-AC42/$G42 -> 0 | BD42: =-AD42/$G42 -> 0 | BE42: =-AE42/$G42 -> 0 | BF42: =-AF42/$G42 -> 0 | BG42: =-AG42/$G42 -> 0 | BH42: =AK42/$G42 -> 1400 | BI42: =-AM42/$G42 -> -128.37037 | BJ42: =-AO42/$G42 -> -72.384615 | BK42: =-AP42/$G42 -> -220.53738 | BL42: =-AQ42/$G42 -> -39.372182 | BM42: =AR42/$G42 -> 38.148889 | BN42: =AS42/$G42 -> 1178.2393 | BO42: =-AU42/$G42 -> -77.399038 | BP42: =AV42/$G42 -> 1100.8403 | BQ42: =AX42/$G42 -> 61.810166 | BR42: =AY42/$G42 -> 1240.0495
B43: FEBRERO | C43: MARZO | D43: 167-2026 | E43: 42 | F43: 46104 | G43: 48 | H43: POTA CONOS | I43: Conos | K43: Tailandia | L43: Bangkok | M43: TSUJINO | N43: Jose | O43: 1600 | P43: 76800 | Q43: 1462.5 | R43: 6600 | S43: =P43-R43 -> 70200 | T43: 2 | U43: ECO MARIN 26012S | V43: 6446513180 | W43: COSCO | X43: PAITA | Y43: 10007969 | Z43: Inventario final | AA43: =B43&Y43&Z43 -> FEBRERO10007969Inventario final | AB43: =AI43-616968.19/1968.8+215187/1968.8-47.35 -> 1344.0155 | AC43: =IFERROR(INDEX('Costos Producción Febrero'!$G$34:$G$57,MATCH(Resumen!Y43,'Costos Producción Febrero'!$B$34:$B$57,0))*AB43*G43,0) -> 54648.534 | AD43: =IFERROR(INDEX('Costos Producción Febrero'!$H$34:$H$57,MATCH(Resumen!Y43,'Costos Producción Febrero'!$B$34:$B$57,0))*AB43*G43,0) -> 10974.478 | AE43: =IFERROR(INDEX('Costos Producción Febrero'!$I$34:$I$57,MATCH(Resumen!Y43,'Costos Producción Febrero'!$B$34:$B$57,0))*AB43*G43,0) -> 844.47266 | AF43: =IFERROR(INDEX('Costos Producción Febrero'!$J$34:$J$57,MATCH(Resumen!Y43,'Costos Producción Febrero'!$B$34:$B$57,0))*AB43*G43,0) -> -1954.7419 | AG43: =SUM(AC43:AF43) -> 64512.743 | AI43: 1595.4396 | AK43: =P43-AG43 -> 12287.257 | AL43: =AK43/P43 -> 0.15999033 | AM43: =R43 -> 6600 | AN43: =118461.136538461/5988.21*G43 -> 949.55497 | AO43: =1882/26*G43 -> 3474.4615 | AP43: =SUM(AM43:AO43) -> 11024.017 | AQ43: =78579/1995.8*G43 -> 1889.8647 | AR43: =S43*0.03 -> 2106 | AS43: =AK43-AP43-AQ43+AR43 -> 1479.3758 | AT43: =AS43/P43 -> 0.019262705 | AU43: =154473/1995.8*G43 -> 3715.1538 | AV43: =AS43-AU43 -> -2235.7781 | AW43: =AV43/P43 -> -0.029111693 | AX43: =123484.35/1997.8*G43 -> 2966.888 | AY43: =AS43+AX43 -> 4446.2637 | AZ43: =AY43/P43 -> 0.057894059 | BB43: =P43/$G43 -> 1600 | BC43: =-AC43/$G43 -> -1138.5111 | BD43: =-AD43/$G43 -> -228.63497 | BE43: =-AE43/$G43 -> -17.593181 | BF43: =-AF43/$G43 -> 40.723791 | BG43: =-AG43/$G43 -> -1344.0155 | BH43: =AK43/$G43 -> 255.98452 | BI43: =-AM43/$G43 -> -137.5 | BJ43: =-AO43/$G43 -> -72.384615 | BK43: =-AP43/$G43 -> -229.66701 | BL43: =-AQ43/$G43 -> -39.372182 | BM43: =AR43/$G43 -> 43.875 | BN43: =AS43/$G43 -> 30.820329 | BO43: =-AU43/$G43 -> -77.399038 | BP43: =AV43/$G43 -> -46.578709 | BQ43: =AX43/$G43 -> 61.810166 | BR43: =AY43/$G43 -> 92.630495
B44: FEBRERO | C44: MARZO | D44: 169-2026A | E44: 43 | F44: 46084 | G44: 116.8 | H44: POTA ALAS CONGELADAS | I44: Alas | J44: 1-UP | K44: China | L44: Qingdao | M44: TSUJINO | N44: Jose | O44: 1600 | P44: 186880 | Q44: 1484.2894 | R44: 13515 | S44: =P44-R44 -> 173365 | T44: 5 | U44: ECO SIROCCO 26009N | V44: LIMG02789600 | W44: ONE | X44: PAITA | Y44: 10006720 | Z44: Inventario final | AA44: =B44&Y44&Z44 -> FEBRERO10006720Inventario final | AB44: =AI44-616968.19/1968.8+215187/1968.8-47.35 -> 1697.774 | AC44: =IFERROR(INDEX('Costos Producción Febrero'!$G$34:$G$57,MATCH(Resumen!Y44,'Costos Producción Febrero'!$B$34:$B$57,0))*AB44*G44,0) -> 127247.73 | AD44: =IFERROR(INDEX('Costos Producción Febrero'!$H$34:$H$57,MATCH(Resumen!Y44,'Costos Producción Febrero'!$B$34:$B$57,0))*AB44*G44,0) -> 26764.944 | AE44: =IFERROR(INDEX('Costos Producción Febrero'!$I$34:$I$57,MATCH(Resumen!Y44,'Costos Producción Febrero'!$B$34:$B$57,0))*AB44*G44,0) -> 1852.8856 | AF44: =IFERROR(INDEX('Costos Producción Febrero'!$J$34:$J$57,MATCH(Resumen!Y44,'Costos Producción Febrero'!$B$34:$B$57,0))*AB44*G44,0) -> 42434.441 | AG44: =SUM(AC44:AF44) -> 198300 | AI44: 1949.1981 | AK44: =P44-AG44 -> -11419.999 | AL44: =AK44/P44 -> -0.061108729 | AM44: =R44 -> 13515 | AN44: =118461.136538461/5988.21*G44 -> 2310.5838 | AO44: =1882/26*G44 -> 8454.5231 | AP44: =SUM(AM44:AO44) -> 24280.107 | AQ44: =78579/1995.8*G44 -> 4598.6708 | AR44: =S44*0.03 -> 5200.95 | AS44: =AK44-AP44-AQ44+AR44 -> -35097.827 | AT44: =AS44/P44 -> -0.18780943 | AU44: =154473/1995.8*G44 -> 9040.2076 | AV44: =AS44-AU44 -> -44138.035 | AW44: =AV44/P44 -> -0.23618383 | AX44: =123484.35/1997.8*G44 -> 7219.4274 | AY44: =AS44+AX44 -> -27878.399 | AZ44: =AY44/P44 -> -0.14917808 | BB44: =P44/$G44 -> 1600 | BC44: =-AC44/$G44 -> -1089.4497 | BD44: =-AD44/$G44 -> -229.15192 | BE44: =-AE44/$G44 -> -15.863747 | BF44: =-AF44/$G44 -> -363.30857 | BG44: =-AG44/$G44 -> -1697.774 | BH44: =AK44/$G44 -> -97.773966 | BI44: =-AM44/$G44 -> -115.71062 | BJ44: =-AO44/$G44 -> -72.384615 | BK44: =-AP44/$G44 -> -207.87763 | BL44: =-AQ44/$G44 -> -39.372182 | BM44: =AR44/$G44 -> 44.528682 | BN44: =AS44/$G44 -> -300.49509 | BO44: =-AU44/$G44 -> -77.399038 | BP44: =AV44/$G44 -> -377.89413 | BQ44: =AX44/$G44 -> 61.810166 | BR44: =AY44/$G44 -> -238.68493
B45: FEBRERO | C45: MARZO | D45: 169-2026B | E45: 43 | F45: 46091 | G45: 135 | H45: POTA ALAS CONGELADAS | I45: Alas | J45: 1-UP | K45: China | L45: Qingdao | M45: TSUJINO | N45: Jose | O45: 1600 | P45: 216000 | Q45: 1519.9111 | R45: 10812 | S45: =P45-R45 -> 205188 | T45: 4 | U45: ECO MARIN 26010N | V45: LIMG03633900 | W45: ONE | X45: PAITA | Y45: 10006720 | Z45: Inventario final | AA45: =B45&Y45&Z45 -> FEBRERO10006720Inventario final | AB45: =AI45-616968.19/1968.8+215187/1968.8-47.35 -> 1697.774 | AC45: =IFERROR(INDEX('Costos Producción Febrero'!$G$34:$G$57,MATCH(Resumen!Y45,'Costos Producción Febrero'!$B$34:$B$57,0))*AB45*G45,0) -> 147075.71 | AD45: =IFERROR(INDEX('Costos Producción Febrero'!$H$34:$H$57,MATCH(Resumen!Y45,'Costos Producción Febrero'!$B$34:$B$57,0))*AB45*G45,0) -> 30935.509 | AE45: =IFERROR(INDEX('Costos Producción Febrero'!$I$34:$I$57,MATCH(Resumen!Y45,'Costos Producción Febrero'!$B$34:$B$57,0))*AB45*G45,0) -> 2141.6058 | AF45: =IFERROR(INDEX('Costos Producción Febrero'!$J$34:$J$57,MATCH(Resumen!Y45,'Costos Producción Febrero'!$B$34:$B$57,0))*AB45*G45,0) -> 49046.657 | AG45: =SUM(AC45:AF45) -> 229199.49 | AI45: 1949.1981 | AK45: =P45-AG45 -> -13199.485 | AL45: =AK45/P45 -> -0.061108729 | AM45: =R45 -> 10812 | AN45: =118461.136538461/5988.21*G45 -> 2670.6233 | AO45: =1882/26*G45 -> 9771.9231 | AP45: =SUM(AM45:AO45) -> 23254.546 | AQ45: =78579/1995.8*G45 -> 5315.2445 | AR45: =S45*0.03 -> 6155.64 | AS45: =AK45-AP45-AQ45+AR45 -> -35613.636 | AT45: =AS45/P45 -> -0.16487795 | AU45: =154473/1995.8*G45 -> 10448.87 | AV45: =AS45-AU45 -> -46062.506 | AW45: =AV45/P45 -> -0.21325234 | AX45: =123484.35/1997.8*G45 -> 8344.3724 | AY45: =AS45+AX45 -> -27269.264 | AZ45: =AY45/P45 -> -0.12624659 | BB45: =P45/$G45 -> 1600 | BC45: =-AC45/$G45 -> -1089.4497 | BD45: =-AD45/$G45 -> -229.15192 | BE45: =-AE45/$G45 -> -15.863747 | BF45: =-AF45/$G45 -> -363.30857 | BG45: =-AG45/$G45 -> -1697.774 | BH45: =AK45/$G45 -> -97.773966 | BI45: =-AM45/$G45 -> -80.088889 | BJ45: =-AO45/$G45 -> -72.384615 | BK45: =-AP45/$G45 -> -172.2559 | BL45: =-AQ45/$G45 -> -39.372182 | BM45: =AR45/$G45 -> 45.597333 | BN45: =AS45/$G45 -> -263.80471 | BO45: =-AU45/$G45 -> -77.399038 | BP45: =AV45/$G45 -> -341.20375 | BQ45: =AX45/$G45 -> 61.810166 | BR45: =AY45/$G45 -> -201.99455
B46: FEBRERO | C46: MARZO | D46: 170-2026B | E46: 43 | F46: 46092 | G46: 78 | H46: POTA REJOS CONGELADOS | I46: Rejos | J46: 1-2 | K46: España | L46: Vigo | M46: KULALIA | N46: Ramon | O46: 2400 | P46: =187200-15600 -> 171600 | Q46: 2243.0865 | R46: 12239.25 | S46: =P46-R46 -> 159360.75 | T46: 3 | U46: CMA CGM BOLDNESS / 0DVODN1MA | V46: LMM0575562 | W46: CMA CGM | Y46: 10007162 | Z46: Inventario final | AA46: =B46&Y46&Z46 -> FEBRERO10007162Inventario final | AB46: =AI46-616968.19/1968.8+215187/1968.8-47.35 -> 1766.7551 | AC46: =IFERROR(INDEX('Costos Producción Febrero'!$G$34:$G$57,MATCH(Resumen!Y46,'Costos Producción Febrero'!$B$34:$B$57,0))*AB46*G46,0) -> 84496.391 | AD46: =IFERROR(INDEX('Costos Producción Febrero'!$H$34:$H$57,MATCH(Resumen!Y46,'Costos Producción Febrero'!$B$34:$B$57,0))*AB46*G46,0) -> 23990.21 | AE46: =IFERROR(INDEX('Costos Producción Febrero'!$I$34:$I$57,MATCH(Resumen!Y46,'Costos Producción Febrero'!$B$34:$B$57,0))*AB46*G46,0) -> 1277.5513 | AF46: =IFERROR(INDEX('Costos Producción Febrero'!$J$34:$J$57,MATCH(Resumen!Y46,'Costos Producción Febrero'!$B$34:$B$57,0))*AB46*G46,0) -> 28042.748 | AG46: =SUM(AC46:AF46) -> 137806.9 | AI46: 2018.1793 | AK46: =P46-AG46 -> 33793.1 | AL46: =AK46/P46 -> 0.19692948 | AM46: =R46 -> 12239.25 | AN46: =118461.136538461/5988.21*G46 -> 1543.0268 | AO46: =1882/26*G46 -> 5646 | AP46: =SUM(AM46:AO46) -> 19428.277 | AQ46: =78579/1995.8*G46 -> 3071.0302 | AR46: =S46*0.03 -> 4780.8225 | AS46: =AK46-AP46-AQ46+AR46 -> 16074.615 | AT46: =AS46/P46 -> 0.093674913 | AU46: =154473/1995.8*G46 -> 6037.125 | AV46: =AS46-AU46 -> 10037.49 | AW46: =AV46/P46 -> 0.058493532 | AX46: =123484.35/1997.8*G46 -> 4821.193 | AY46: =AS46+AX46 -> 20895.808 | AZ46: =AY46/P46 -> 0.12177044 | BB46: =P46/$G46 -> 2200 | BC46: =-AC46/$G46 -> -1083.2871 | BD46: =-AD46/$G46 -> -307.5668 | BE46: =-AE46/$G46 -> -16.378863 | BF46: =-AF46/$G46 -> -359.52241 | BG46: =-AG46/$G46 -> -1766.7551 | BH46: =AK46/$G46 -> 433.24487 | BI46: =-AM46/$G46 -> -156.91346 | BJ46: =-AO46/$G46 -> -72.384615 | BK46: =-AP46/$G46 -> -249.08047 | BL46: =-AQ46/$G46 -> -39.372182 | BM46: =AR46/$G46 -> 61.292596 | BN46: =AS46/$G46 -> 206.08481 | BO46: =-AU46/$G46 -> -77.399038 | BP46: =AV46/$G46 -> 128.68577 | BQ46: =AX46/$G46 -> 61.810166 | BR46: =AY46/$G46 -> 267.89497
B47: FEBRERO | C47: MARZO | D47: 171-2026 | E47: 44 | F47: 46085 | G47: 135 | H47: POTA FILETE CONGELADO | I47: Filete | J47: 2-4 AA | K47: China | L47: Shidao | M47: Pesciro Asia International LTD. | O47: 1450 | P47: 195750 | Q47: 1338.7778 | R47: 15015 | S47: =P47-R47 -> 180735 | T47: 5 | U47: ECO SIROCCO 26009N | V47: LIMG03093900 | W47: ONE | X47: PAITA | Y47: 10005721 | Z47: Inventario final | AA47: =B47&Y47&Z47 -> FEBRERO10005721Inventario final | AB47: =AI47-616968.19/1968.8+215187/1968.8-47.35 -> 2146.3203 | AC47: =IFERROR(INDEX('Costos Producción Febrero'!$G$34:$G$57,MATCH(Resumen!Y47,'Costos Producción Febrero'!$B$34:$B$57,0))*AB47*G47,0) -> 175970.31 | AD47: =IFERROR(INDEX('Costos Producción Febrero'!$H$34:$H$57,MATCH(Resumen!Y47,'Costos Producción Febrero'!$B$34:$B$57,0))*AB47*G47,0) -> 51562.953 | AE47: =IFERROR(INDEX('Costos Producción Febrero'!$I$34:$I$57,MATCH(Resumen!Y47,'Costos Producción Febrero'!$B$34:$B$57,0))*AB47*G47,0) -> 3158.8626 | AF47: =IFERROR(INDEX('Costos Producción Febrero'!$J$34:$J$57,MATCH(Resumen!Y47,'Costos Producción Febrero'!$B$34:$B$57,0))*AB47*G47,0) -> 59061.121 | AG47: =SUM(AC47:AF47) -> 289753.24 | AI47: 2397.7445 | AK47: =P47-AG47 -> -94003.243 | AL47: =AK47/P47 -> -0.48022091 | AM47: =R47 -> 15015 | AN47: =118461.136538461/5988.21*G47 -> 2670.6233 | AO47: =1882/26*G47 -> 9771.9231 | AP47: =SUM(AM47:AO47) -> 27457.546 | AQ47: =78579/1995.8*G47 -> 5315.2445 | AR47: =S47*0.03 -> 5422.05 | AS47: =AK47-AP47-AQ47+AR47 -> -121353.98 | AT47: =AS47/P47 -> -0.61994373 | AU47: =154473/1995.8*G47 -> 10448.87 | AV47: =AS47-AU47 -> -131802.85 | AW47: =AV47/P47 -> -0.67332237 | AX47: =123484.35/1997.8*G47 -> 8344.3724 | AY47: =AS47+AX47 -> -113009.61 | AZ47: =AY47/P47 -> -0.57731602 | BB47: =P47/$G47 -> 1450 | BC47: =-AC47/$G47 -> -1303.4838 | BD47: =-AD47/$G47 -> -381.9478 | BE47: =-AE47/$G47 -> -23.398982 | BF47: =-AF47/$G47 -> -437.48978 | BG47: =-AG47/$G47 -> -2146.3203 | BH47: =AK47/$G47 -> -696.32032 | BI47: =-AM47/$G47 -> -111.22222 | BJ47: =-AO47/$G47 -> -72.384615 | BK47: =-AP47/$G47 -> -203.38923 | BL47: =-AQ47/$G47 -> -39.372182 | BM47: =AR47/$G47 -> 40.163333 | BN47: =AS47/$G47 -> -898.9184 | BO47: =-AU47/$G47 -> -77.399038 | BP47: =AV47/$G47 -> -976.31744 | BQ47: =AX47/$G47 -> 61.810166 | BR47: =AY47/$G47 -> -837.10824
B48: FEBRERO | C48: MARZO | D48: 172-2026A | E48: 47 | F48: 46092 | G48: 150 | H48: POTA REJOS CONGELADOS | I48: Rejos | J48: 1-2 KG | K48: España | L48: Vigo | M48: KULALIA | N48: Ramon | O48: 2300 | P48: 345000 | Q48: 2139.1 | R48: 24135 | S48: =P48-R48 -> 320865 | T48: 6 | U48: CMA CGM BOLDNESS / 0DVODN1MA | V48: LMM0575536 | W48: CMA CGM | Y48: 10007162 | Z48: Inventario final | AA48: =B48&Y48&Z48 -> FEBRERO10007162Inventario final | AB48: =AI48-616968.19/1968.8+215187/1968.8-47.35 -> 1766.7551 | AC48: =IFERROR(INDEX('Costos Producción Febrero'!$G$34:$G$57,MATCH(Resumen!Y48,'Costos Producción Febrero'!$B$34:$B$57,0))*AB48*G48,0) -> 162493.06 | AD48: =IFERROR(INDEX('Costos Producción Febrero'!$H$34:$H$57,MATCH(Resumen!Y48,'Costos Producción Febrero'!$B$34:$B$57,0))*AB48*G48,0) -> 46135.02 | AE48: =IFERROR(INDEX('Costos Producción Febrero'!$I$34:$I$57,MATCH(Resumen!Y48,'Costos Producción Febrero'!$B$34:$B$57,0))*AB48*G48,0) -> 2456.8294 | AF48: =IFERROR(INDEX('Costos Producción Febrero'!$J$34:$J$57,MATCH(Resumen!Y48,'Costos Producción Febrero'!$B$34:$B$57,0))*AB48*G48,0) -> 53928.361 | AG48: =SUM(AC48:AF48) -> 265013.27 | AI48: 2018.1793 | AK48: =P48-AG48 -> 79986.73 | AL48: =AK48/P48 -> 0.23184559 | AM48: =R48 -> 24135 | AN48: =118461.136538461/5988.21*G48 -> 2967.3593 | AO48: =1882/26*G48 -> 10857.692 | AP48: =SUM(AM48:AO48) -> 37960.052 | AQ48: =78579/1995.8*G48 -> 5905.8272 | AR48: =S48*0.03 -> 9625.95 | AS48: =AK48-AP48-AQ48+AR48 -> 45746.801 | AT48: =AS48/P48 -> 0.13259942 | AU48: =154473/1995.8*G48 -> 11609.856 | AV48: =AS48-AU48 -> 34136.945 | AW48: =AV48/P48 -> 0.098947668 | AX48: =123484.35/1997.8*G48 -> 9271.5249 | AY48: =AS48+AX48 -> 55018.326 | AZ48: =AY48/P48 -> 0.15947341 | BB48: =P48/$G48 -> 2300 | BC48: =-AC48/$G48 -> -1083.2871 | BD48: =-AD48/$G48 -> -307.5668 | BE48: =-AE48/$G48 -> -16.378863 | BF48: =-AF48/$G48 -> -359.52241 | BG48: =-AG48/$G48 -> -1766.7551 | BH48: =AK48/$G48 -> 533.24487 | BI48: =-AM48/$G48 -> -160.9 | BJ48: =-AO48/$G48 -> -72.384615 | BK48: =-AP48/$G48 -> -253.06701 | BL48: =-AQ48/$G48 -> -39.372182 | BM48: =AR48/$G48 -> 64.173 | BN48: =AS48/$G48 -> 304.97867 | BO48: =-AU48/$G48 -> -77.399038 | BP48: =AV48/$G48 -> 227.57964 | BQ48: =AX48/$G48 -> 61.810166 | BR48: =AY48/$G48 -> 366.78884
B49: FEBRERO | C49: MARZO | D49: 172-2026A | E49: 47 | F49: 46092 | G49: 25 | H49: POTA REPRODUCTORES | I49: Rejos | K49: España | L49: Vigo | M49: KULALIA | N49: Ramon | O49: 2500 | P49: 62500 | Q49: 2336.72 | R49: 4082 | S49: =P49-R49 -> 58418 | T49: 1 | U49: CMA CGM BOLDNESS / 0DVODN1MA | V49: LMM0575536 | W49: CMA CGM | Y49: 10007567 | Z49: Inventario final | AA49: =B49&Y49&Z49 -> FEBRERO10007567Inventario final | AB49: =AI49-616968.19/1968.8+215187/1968.8-47.35 -> 1768.0738 | AC49: =IFERROR(INDEX('Costos Producción Febrero'!$G$34:$G$57,MATCH(Resumen!Y49,'Costos Producción Febrero'!$B$34:$B$57,0))*AB49*G49,0) -> 27298.29 | AD49: =IFERROR(INDEX('Costos Producción Febrero'!$H$34:$H$57,MATCH(Resumen!Y49,'Costos Producción Febrero'!$B$34:$B$57,0))*AB49*G49,0) -> 7357.0054 | AE49: =IFERROR(INDEX('Costos Producción Febrero'!$I$34:$I$57,MATCH(Resumen!Y49,'Costos Producción Febrero'!$B$34:$B$57,0))*AB49*G49,0) -> 477.08717 | AF49: =IFERROR(INDEX('Costos Producción Febrero'!$J$34:$J$57,MATCH(Resumen!Y49,'Costos Producción Febrero'!$B$34:$B$57,0))*AB49*G49,0) -> 9069.4626 | AG49: =SUM(AC49:AF49) -> 44201.845 | AI49: 2019.498 | AK49: =P49-AG49 -> 18298.155 | AL49: =AK49/P49 -> 0.29277048 | AM49: =R49 -> 4082 | AN49: =118461.136538461/5988.21*G49 -> 494.55988 | AO49: =1882/26*G49 -> 1809.6154 | AP49: =SUM(AM49:AO49) -> 6386.1753 | AQ49: =78579/1995.8*G49 -> 984.30454 | AR49: =S49*0.03 -> 1752.54 | AS49: =AK49-AP49-AQ49+AR49 -> 12680.215 | AT49: =AS49/P49 -> 0.20288344 | AU49: =154473/1995.8*G49 -> 1934.9759 | AV49: =AS49-AU49 -> 10745.239 | AW49: =AV49/P49 -> 0.17192382 | AX49: =123484.35/1997.8*G49 -> 1545.2542 | AY49: =AS49+AX49 -> 14225.469 | AZ49: =AY49/P49 -> 0.22760751 | BB49: =P49/$G49 -> 2500 | BC49: =-AC49/$G49 -> -1091.9316 | BD49: =-AD49/$G49 -> -294.28021 | BE49: =-AE49/$G49 -> -19.083487 | BF49: =-AF49/$G49 -> -362.77851 | BG49: =-AG49/$G49 -> -1768.0738 | BH49: =AK49/$G49 -> 731.92619 | BI49: =-AM49/$G49 -> -163.28 | BJ49: =-AO49/$G49 -> -72.384615 | BK49: =-AP49/$G49 -> -255.44701 | BL49: =-AQ49/$G49 -> -39.372182 | BM49: =AR49/$G49 -> 70.1016 | BN49: =AS49/$G49 -> 507.2086 | BO49: =-AU49/$G49 -> -77.399038 | BP49: =AV49/$G49 -> 429.80956 | BQ49: =AX49/$G49 -> 61.810166 | BR49: =AY49/$G49 -> 569.01876
B50: FEBRERO | C50: MARZO | D50: 172-2026B | E50: 47 | F50: 46108 | G50: 54 | H50: POTA ALAS COCIDAS | I50: Alas | J50: 0.3 - UP | K50: China | L50: Qingdao | M50: KULALIA | N50: Ramon | O50: 3350 | P50: =180900-3678.3 -> 177221.7 | Q50: 3242.5926 | R50: 5800 | S50: =P50-R50 -> 171421.7 | T50: 2 | U50: ECO SIROCCO 26013S | V50: 6446512380 | W50: COSCO | X50: PAITA | Y50: 10009331 | Z50: Inventario final | AA50: =B50&Y50&Z50 -> FEBRERO10009331Inventario final | AB50: =AI50-616968.19/1968.8+215187/1968.8-47.35 -> 2194.0201 | AC50: =IFERROR(INDEX('Costos Producción Febrero'!$G$34:$G$57,MATCH(Resumen!Y50,'Costos Producción Febrero'!$B$34:$B$57,0))*AB50*G50,0) -> 67606.199 | AD50: =IFERROR(INDEX('Costos Producción Febrero'!$H$34:$H$57,MATCH(Resumen!Y50,'Costos Producción Febrero'!$B$34:$B$57,0))*AB50*G50,0) -> 26821.672 | AE50: =IFERROR(INDEX('Costos Producción Febrero'!$I$34:$I$57,MATCH(Resumen!Y50,'Costos Producción Febrero'!$B$34:$B$57,0))*AB50*G50,0) -> 1228.4198 | AF50: =IFERROR(INDEX('Costos Producción Febrero'!$J$34:$J$57,MATCH(Resumen!Y50,'Costos Producción Febrero'!$B$34:$B$57,0))*AB50*G50,0) -> 22820.795 | AG50: =SUM(AC50:AF50) -> 118477.09 | AI50: 2445.4443 | AK50: =P50-AG50 -> 58744.614 | AL50: =AK50/P50 -> 0.33147529 | AM50: =R50 -> 5800 | AN50: =118461.136538461/5988.21*G50 -> 1068.2493 | AO50: =1882/26*G50 -> 3908.7692 | AP50: =SUM(AM50:AO50) -> 10777.019 | AQ50: =78579/1995.8*G50 -> 2126.0978 | AR50: =S50*0.03 -> 5142.651 | AS50: =AK50-AP50-AQ50+AR50 -> 50984.149 | AT50: =AS50/P50 -> 0.2876857 | AU50: =154473/1995.8*G50 -> 4179.5481 | AV50: =AS50-AU50 -> 46804.601 | AW50: =AV50/P50 -> 0.26410198 | AX50: =123484.35/1997.8*G50 -> 3337.749 | AY50: =AS50+AX50 -> 54321.898 | AZ50: =AY50/P50 -> 0.30651945 | BB50: =P50/$G50 -> 3281.8833 | BC50: =-AC50/$G50 -> -1251.9666 | BD50: =-AD50/$G50 -> -496.69763 | BE50: =-AE50/$G50 -> -22.748515 | BF50: =-AF50/$G50 -> -422.60732 | BG50: =-AG50/$G50 -> -2194.0201 | BH50: =AK50/$G50 -> 1087.8632 | BI50: =-AM50/$G50 -> -107.40741 | BJ50: =-AO50/$G50 -> -72.384615 | BK50: =-AP50/$G50 -> -199.57442 | BL50: =-AQ50/$G50 -> -39.372182 | BM50: =AR50/$G50 -> 95.234278 | BN50: =AS50/$G50 -> 944.15091 | BO50: =-AU50/$G50 -> -77.399038 | BP50: =AV50/$G50 -> 866.75187 | BQ50: =AX50/$G50 -> 61.810166 | BR50: =AY50/$G50 -> 1005.9611
B51: FEBRERO | C51: MARZO | D51: 174-2026 | E51: 49 | F51: 46091 | G51: 108 | H51: POTA FILETE CONGELADO | I51: Filete | J51: 2-4 AA | K51: China | L51: shidao | M51: Pesciro Asia International LTD. | O51: 1450 | P51: 156600 | Q51: 1338.7778 | R51: 12012 | S51: =P51-R51 -> 144588 | T51: 4 | U51: ECO MARIN 26010N | V51: LIMG03595900 | Y51: 10005721 | Z51: Inventario final | AA51: =B51&Y51&Z51 -> FEBRERO10005721Inventario final | AB51: =AI51-616968.19/1968.8+215187/1968.8-47.35 -> 1843.8447 | AC51: =IFERROR(INDEX('Costos Producción Febrero'!$G$34:$G$57,MATCH(Resumen!Y51,'Costos Producción Febrero'!$B$34:$B$57,0))*AB51*G51,0) -> 120937 | AD51: =IFERROR(INDEX('Costos Producción Febrero'!$H$34:$H$57,MATCH(Resumen!Y51,'Costos Producción Febrero'!$B$34:$B$57,0))*AB51*G51,0) -> 35437.051 | AE51: =IFERROR(INDEX('Costos Producción Febrero'!$I$34:$I$57,MATCH(Resumen!Y51,'Costos Producción Febrero'!$B$34:$B$57,0))*AB51*G51,0) -> 2170.9535 | AF51: =IFERROR(INDEX('Costos Producción Febrero'!$J$34:$J$57,MATCH(Resumen!Y51,'Costos Producción Febrero'!$B$34:$B$57,0))*AB51*G51,0) -> 40590.227 | AG51: =SUM(AC51:AF51) -> 199135.23 | AI51: 2095.2689 | AK51: =P51-AG51 -> -42535.23 | AL51: =AK51/P51 -> -0.27161705 | AM51: =R51 -> 12012 | AN51: =118461.136538461/5988.21*G51 -> 2136.4987 | AO51: =1883/26*G51 -> 7821.6923 | AP51: =SUM(AM51:AO51) -> 21970.191 | AQ51: =78579/1995.8*G51 -> 4252.1956 | AR51: =S51*0.03 -> 4337.64 | AS51: =AK51-AP51-AQ51+AR51 -> -64419.977 | AT51: =AS51/P51 -> -0.41136639 | AU51: =154473/1995.8*G51 -> 8359.0961 | AV51: =AS51-AU51 -> -72779.073 | AW51: =AV51/P51 -> -0.46474504 | AX51: =123484.35/1997.8*G51 -> 6675.4979 | AY51: =AS51+AX51 -> -57744.479 | AZ51: =AY51/P51 -> -0.36873869 | BB51: =P51/$G51 -> 1450 | BC51: =-AC51/$G51 -> -1119.787 | BD51: =-AD51/$G51 -> -328.12085 | BE51: =-AE51/$G51 -> -20.101422 | BF51: =-AF51/$G51 -> -375.83543 | BG51: =-AG51/$G51 -> -1843.8447 | BH51: =AK51/$G51 -> -393.84473 | BI51: =-AM51/$G51 -> -111.22222 | BJ51: =-AO51/$G51 -> -72.423077 | BK51: =-AP51/$G51 -> -203.42769 | BL51: =-AQ51/$G51 -> -39.372182 | BM51: =AR51/$G51 -> 40.163333 | BN51: =AS51/$G51 -> -596.48127 | BO51: =-AU51/$G51 -> -77.399038 | BP51: =AV51/$G51 -> -673.88031 | BQ51: =AX51/$G51 -> 61.810166 | BR51: =AY51/$G51 -> -534.6711
B52: FEBRERO | C52: MARZO | D52: 175-2026 | E52: 49 | F52: 46099 | G52: 26 | H52: POTA FILETE CONGELADO | I52: Filete | J52: 2-4 AA | K52: Klaipeda | L52: Lituania | M52: Pesciro SL | O52: 1500 | P52: 39000 | Q52: 1230.9615 | R52: 6995 | S52: =P52-R52 -> 32005 | T52: 1 | U52: CMA CGM VOLTAIRE / 0DVOFN1MA | V52: LMM0575667 | W52: 1 | X52: CMA CGM | Y52: 10005721 | Z52: Inventario final | AA52: =B52&Y52&Z52 -> FEBRERO10005721Inventario final | AB52: =AI52-616968.19/1968.8+215187/1968.8-47.35 -> 1843.8447 | AC52: =IFERROR(INDEX('Costos Producción Febrero'!$G$34:$G$57,MATCH(Resumen!Y52,'Costos Producción Febrero'!$B$34:$B$57,0))*AB52*G52,0) -> 29114.463 | AD52: =IFERROR(INDEX('Costos Producción Febrero'!$H$34:$H$57,MATCH(Resumen!Y52,'Costos Producción Febrero'!$B$34:$B$57,0))*AB52*G52,0) -> 8531.142 | AE52: =IFERROR(INDEX('Costos Producción Febrero'!$I$34:$I$57,MATCH(Resumen!Y52,'Costos Producción Febrero'!$B$34:$B$57,0))*AB52*G52,0) -> 522.63696 | AF52: =IFERROR(INDEX('Costos Producción Febrero'!$J$34:$J$57,MATCH(Resumen!Y52,'Costos Producción Febrero'!$B$34:$B$57,0))*AB52*G52,0) -> 9771.7213 | AG52: =SUM(AC52:AF52) -> 47939.963 | AI52: 2095.2689 | AK52: =P52-AG52 -> -8939.9629 | AL52: =AK52/P52 -> -0.22922982 | AM52: =R52 -> 6995 | AN52: =118461.136538461/5988.21*G52 -> 514.34227 | AO52: =1883/26*G52 -> 1883 | AP52: =SUM(AM52:AO52) -> 9392.3423 | AQ52: =78579/1995.8*G52 -> 1023.6767 | AR52: =S52*0.03 -> 960.15 | AS52: =AK52-AP52-AQ52+AR52 -> -18395.832 | AT52: =AS52/P52 -> -0.471688 | AU52: =154473/1995.8*G52 -> 2012.375 | AV52: =AS52-AU52 -> -20408.207 | AW52: =AV52/P52 -> -0.52328736 | AX52: =123484.35/1997.8*G52 -> 1607.0643 | AY52: =AS52+AX52 -> -16788.768 | AZ52: =AY52/P52 -> -0.43048122 | BB52: =P52/$G52 -> 1500 | BC52: =-AC52/$G52 -> -1119.787 | BD52: =-AD52/$G52 -> -328.12085 | BE52: =-AE52/$G52 -> -20.101422 | BF52: =-AF52/$G52 -> -375.83543 | BG52: =-AG52/$G52 -> -1843.8447 | BH52: =AK52/$G52 -> -343.84473 | BI52: =-AM52/$G52 -> -269.03846 | BJ52: =-AO52/$G52 -> -72.423077 | BK52: =-AP52/$G52 -> -361.24393 | BL52: =-AQ52/$G52 -> -39.372182 | BM52: =AR52/$G52 -> 36.928846 | BN52: =AS52/$G52 -> -707.53199 | BO52: =-AU52/$G52 -> -77.399038 | BP52: =AV52/$G52 -> -784.93103 | BQ52: =AX52/$G52 -> 61.810166 | BR52: =AY52/$G52 -> -645.72183
B53: FEBRERO | C53: MARZO | D53: 176-2026A | E53: 49 | F53: 46104 | G53: 54 | H53: POTA ALAS CONGELADAS | I53: Alas | J53: 1-up | K53: China | L53: Qingdao | M53: TSUJINO | N53: Jose | O53: 1600 | P53: 86400 | Q53: 1492.5926 | R53: 5800 | S53: =P53-R53 -> 80600 | T53: 2 | U53: ECO SIROCCO 26011S | V53: 6446527810 | W53: COSCO | X53: PAITA | Y53: 10006720 | Z53: Inventario final | AA53: =B53&Y53&Z53 -> FEBRERO10006720Inventario final | AB53: =AI53-616968.19/1968.8+215187/1968.8-47.35 -> 1697.774 | AC53: =IFERROR(INDEX('Costos Producción Febrero'!$G$34:$G$57,MATCH(Resumen!Y53,'Costos Producción Febrero'!$B$34:$B$57,0))*AB53*G53,0) -> 58830.285 | AD53: =IFERROR(INDEX('Costos Producción Febrero'!$H$34:$H$57,MATCH(Resumen!Y53,'Costos Producción Febrero'!$B$34:$B$57,0))*AB53*G53,0) -> 12374.204 | AE53: =IFERROR(INDEX('Costos Producción Febrero'!$I$34:$I$57,MATCH(Resumen!Y53,'Costos Producción Febrero'!$B$34:$B$57,0))*AB53*G53,0) -> 856.64233 | AF53: =IFERROR(INDEX('Costos Producción Febrero'!$J$34:$J$57,MATCH(Resumen!Y53,'Costos Producción Febrero'!$B$34:$B$57,0))*AB53*G53,0) -> 19618.663 | AG53: =SUM(AC53:AF53) -> 91679.794 | AI53: 1949.1981 | AK53: =P53-AG53 -> -5279.7942 | AL53: =AK53/P53 -> -0.061108729 | AM53: =R53 -> 5800 | AN53: =118461.136538461/5988.21*G53 -> 1068.2493 | AO53: =1883/26*G53 -> 3910.8462 | AP53: =SUM(AM53:AO53) -> 10779.095 | AQ53: =78579/1995.8*G53 -> 2126.0978 | AR53: =S53*0.03 -> 2418 | AS53: =AK53-AP53-AQ53+AR53 -> -15766.987 | AT53: =AS53/P53 -> -0.18248828 | AU53: =154473/1995.8*G53 -> 4179.5481 | AV53: =AS53-AU53 -> -19946.536 | AW53: =AV53/P53 -> -0.23086268 | AX53: =123484.35/1997.8*G53 -> 3337.749 | AY53: =AS53+AX53 -> -12429.238 | AZ53: =AY53/P53 -> -0.14385693 | BB53: =P53/$G53 -> 1600 | BC53: =-AC53/$G53 -> -1089.4497 | BD53: =-AD53/$G53 -> -229.15192 | BE53: =-AE53/$G53 -> -15.863747 | BF53: =-AF53/$G53 -> -363.30857 | BG53: =-AG53/$G53 -> -1697.774 | BH53: =AK53/$G53 -> -97.773966 | BI53: =-AM53/$G53 -> -107.40741 | BJ53: =-AO53/$G53 -> -72.423077 | BK53: =-AP53/$G53 -> -199.61288 | BL53: =-AQ53/$G53 -> -39.372182 | BM53: =AR53/$G53 -> 44.777778 | BN53: =AS53/$G53 -> -291.98125 | BO53: =-AU53/$G53 -> -77.399038 | BP53: =AV53/$G53 -> -369.38029 | BQ53: =AX53/$G53 -> 61.810166 | BR53: =AY53/$G53 -> -230.17108
B54: FEBRERO | C54: MARZO | D54: 176-2026B | E54: 49 | F54: 46108 | G54: 81 | H54: POTA ALAS CONGELADAS | I54: Alas | J54: 1-up | K54: China | L54: Qingdao | M54: TSUJINO | N54: Jose | O54: 1600 | P54: =129600-4000 -> 125600 | Q54: 1499.5185 | R54: 8139 | S54: =P54-R54 -> 117461 | T54: 3 | U54: ECO SIROCCO 26013S | V54: LIMG04326900 | W54: ONE LINE | X54: PAITA | Y54: 10006720 | Z54: Inventario final | AA54: =B54&Y54&Z54 -> FEBRERO10006720Inventario final | AB54: =AI54-616968.19/1968.8+215187/1968.8-47.35 -> 1697.774 | AC54: =IFERROR(INDEX('Costos Producción Febrero'!$G$34:$G$57,MATCH(Resumen!Y54,'Costos Producción Febrero'!$B$34:$B$57,0))*AB54*G54,0) -> 88245.428 | AD54: =IFERROR(INDEX('Costos Producción Febrero'!$H$34:$H$57,MATCH(Resumen!Y54,'Costos Producción Febrero'!$B$34:$B$57,0))*AB54*G54,0) -> 18561.306 | AE54: =IFERROR(INDEX('Costos Producción Febrero'!$I$34:$I$57,MATCH(Resumen!Y54,'Costos Producción Febrero'!$B$34:$B$57,0))*AB54*G54,0) -> 1284.9635 | AF54: =IFERROR(INDEX('Costos Producción Febrero'!$J$34:$J$57,MATCH(Resumen!Y54,'Costos Producción Febrero'!$B$34:$B$57,0))*AB54*G54,0) -> 29427.994 | AG54: =SUM(AC54:AF54) -> 137519.69 | AI54: 1949.1981 | AK54: =P54-AG54 -> -11919.691 | AL54: =AK54/P54 -> -0.094902 | AM54: =R54 -> 8139 | AN54: =118461.136538461/5988.21*G54 -> 1602.374 | AO54: =1883/26*G54 -> 5866.2692 | AP54: =SUM(AM54:AO54) -> 15607.643 | AQ54: =78579/1995.8*G54 -> 3189.1467 | AR54: =S54*0.03 -> 3523.83 | AS54: =AK54-AP54-AQ54+AR54 -> -27192.651 | AT54: =AS54/P54 -> -0.216502 | AU54: =154473/1995.8*G54 -> 6269.3221 | AV54: =AS54-AU54 -> -33461.973 | AW54: =AV54/P54 -> -0.26641698 | AX54: =123484.35/1997.8*G54 -> 5006.6235 | AY54: =AS54+AX54 -> -22186.028 | AZ54: =AY54/P54 -> -0.17664035 | BB54: =P54/$G54 -> 1550.6173 | BC54: =-AC54/$G54 -> -1089.4497 | BD54: =-AD54/$G54 -> -229.15192 | BE54: =-AE54/$G54 -> -15.863747 | BF54: =-AF54/$G54 -> -363.30857 | BG54: =-AG54/$G54 -> -1697.774 | BH54: =AK54/$G54 -> -147.15668 | BI54: =-AM54/$G54 -> -100.48148 | BJ54: =-AO54/$G54 -> -72.423077 | BK54: =-AP54/$G54 -> -192.68695 | BL54: =-AQ54/$G54 -> -39.372182 | BM54: =AR54/$G54 -> 43.504074 | BN54: =AS54/$G54 -> -335.71174 | BO54: =-AU54/$G54 -> -77.399038 | BP54: =AV54/$G54 -> -413.11078 | BQ54: =AX54/$G54 -> 61.810166 | BR54: =AY54/$G54 -> -273.90158
B55: FEBRERO | C55: MARZO | D55: 177-2026A | E55: 50 | F55: 46108 | G55: 48 | H55: POTA ALAS CONGELADAS | I55: Alas | J55: 1-up | K55: Korea | L55: Busan | M55: TSUJINO | N55: Jose | O55: 1600 | P55: 76800 | Q55: 1486.9583 | R55: 5426 | S55: =P55-R55 -> 71374 | T55: 2 | U55: ECO SIROCCO 26013S | V55: LIMG04588500 | W55: ONE LINE | X55: PAITA | Y55: 10006720 | Z55: Inventario final | AA55: =B55&Y55&Z55 -> FEBRERO10006720Inventario final | AB55: =AI55-616968.19/1968.8+215187/1968.8-47.35 -> 1697.774 | AC55: =IFERROR(INDEX('Costos Producción Febrero'!$G$34:$G$57,MATCH(Resumen!Y55,'Costos Producción Febrero'!$B$34:$B$57,0))*AB55*G55,0) -> 52293.587 | AD55: =IFERROR(INDEX('Costos Producción Febrero'!$H$34:$H$57,MATCH(Resumen!Y55,'Costos Producción Febrero'!$B$34:$B$57,0))*AB55*G55,0) -> 10999.292 | AE55: =IFERROR(INDEX('Costos Producción Febrero'!$I$34:$I$57,MATCH(Resumen!Y55,'Costos Producción Febrero'!$B$34:$B$57,0))*AB55*G55,0) -> 761.45985 | AF55: =IFERROR(INDEX('Costos Producción Febrero'!$J$34:$J$57,MATCH(Resumen!Y55,'Costos Producción Febrero'!$B$34:$B$57,0))*AB55*G55,0) -> 17438.811 | AG55: =SUM(AC55:AF55) -> 81493.15 | AI55: 1949.1981 | AK55: =P55-AG55 -> -4693.1504 | AL55: =AK55/P55 -> -0.061108729 | AM55: =R55 -> 5426 | AN55: =118461.136538461/5988.21*G55 -> 949.55497 | AO55: =1883/26*G55 -> 3476.3077 | AP55: =SUM(AM55:AO55) -> 9851.8627 | AQ55: =78579/1995.8*G55 -> 1889.8647 | AR55: =S55*0.03 -> 2141.22 | AS55: =AK55-AP55-AQ55+AR55 -> -14293.658 | AT55: =AS55/P55 -> -0.18611534 | AU55: =154473/1995.8*G55 -> 3715.1538 | AV55: =AS55-AU55 -> -18008.812 | AW55: =AV55/P55 -> -0.23448973 | AX55: =123484.35/1997.8*G55 -> 2966.888 | AY55: =AS55+AX55 -> -11326.77 | AZ55: =AY55/P55 -> -0.14748398 | BB55: =P55/$G55 -> 1600 | BC55: =-AC55/$G55 -> -1089.4497 | BD55: =-AD55/$G55 -> -229.15192 | BE55: =-AE55/$G55 -> -15.863747 | BF55: =-AF55/$G55 -> -363.30857 | BG55: =-AG55/$G55 -> -1697.774 | BH55: =AK55/$G55 -> -97.773966 | BI55: =-AM55/$G55 -> -113.04167 | BJ55: =-AO55/$G55 -> -72.423077 | BK55: =-AP55/$G55 -> -205.24714 | BL55: =-AQ55/$G55 -> -39.372182 | BM55: =AR55/$G55 -> 44.60875 | BN55: =AS55/$G55 -> -297.78454 | BO55: =-AU55/$G55 -> -77.399038 | BP55: =AV55/$G55 -> -375.18357 | BQ55: =AX55/$G55 -> 61.810166 | BR55: =AY55/$G55 -> -235.97437
B56: FEBRERO | C56: MARZO | D56: 179-2026A | E56: 54 | F56: 46101 | G56: 24 | H56: POTA NUCAS | I56: Nucas | J56: 500-up | K56: Tailandia | L56: Laem chabang | M56: DAIRECK S.A. | N56: ACER FOOD | O56: 1100 | P56: 26400 | Q56: 966.54167 | R56: 3203 | S56: =P56-R56 -> 23197 | T56: 1 | U56: ECO MARIN 26012N | V56: LIMG03918800 | W56: ONE LINE | X56: PAITA | Y56: 10005779 | Z56: Inventario final | AA56: =B56&Y56&Z56 -> FEBRERO10005779Inventario final | AB56: =AI56-616968.19/1968.8+215187/1968.8-47.35 -> 1848.8139 | AC56: =IFERROR(INDEX('Costos Producción Febrero'!$G$34:$G$57,MATCH(Resumen!Y56,'Costos Producción Febrero'!$B$34:$B$57,0))*AB56*G56,0) -> 25762.146 | AD56: =IFERROR(INDEX('Costos Producción Febrero'!$H$34:$H$57,MATCH(Resumen!Y56,'Costos Producción Febrero'!$B$34:$B$57,0))*AB56*G56,0) -> 9804.0642 | AE56: =IFERROR(INDEX('Costos Producción Febrero'!$I$34:$I$57,MATCH(Resumen!Y56,'Costos Producción Febrero'!$B$34:$B$57,0))*AB56*G56,0) -> 283.41449 | AF56: =IFERROR(INDEX('Costos Producción Febrero'!$J$34:$J$57,MATCH(Resumen!Y56,'Costos Producción Febrero'!$B$34:$B$57,0))*AB56*G56,0) -> 8521.9094 | AG56: =SUM(AC56:AF56) -> 44371.534 | AI56: 2100.2381 | AK56: =P56-AG56 -> -17971.534 | AL56: =AK56/P56 -> -0.68073994 | AM56: =R56 -> 3203 | AN56: =118461.136538461/5988.21*G56 -> 474.77748 | AO56: =1883/26*G56 -> 1738.1538 | AP56: =SUM(AM56:AO56) -> 5415.9313 | AQ56: =78579/1995.8*G56 -> 944.93236 | AR56: =S56*0.03 -> 695.91 | AS56: =AK56-AP56-AQ56+AR56 -> -23636.488 | AT56: =AS56/P56 -> -0.89532152 | AU56: =154473/1995.8*G56 -> 1857.5769 | AV56: =AS56-AU56 -> -25494.065 | AW56: =AV56/P56 -> -0.96568428 | AX56: =123484.35/1997.8*G56 -> 1483.444 | AY56: =AS56+AX56 -> -22153.044 | AZ56: =AY56/P56 -> -0.83913046 | BB56: =P56/$G56 -> 1100 | BC56: =-AC56/$G56 -> -1073.4228 | BD56: =-AD56/$G56 -> -408.50268 | BE56: =-AE56/$G56 -> -11.808937 | BF56: =-AF56/$G56 -> -355.07956 | BG56: =-AG56/$G56 -> -1848.8139 | BH56: =AK56/$G56 -> -748.81393 | BI56: =-AM56/$G56 -> -133.45833 | BJ56: =-AO56/$G56 -> -72.423077 | BK56: =-AP56/$G56 -> -225.66381 | BL56: =-AQ56/$G56 -> -39.372182 | BM56: =AR56/$G56 -> 28.99625 | BN56: =AS56/$G56 -> -984.85367 | BO56: =-AU56/$G56 -> -77.399038 | BP56: =AV56/$G56 -> -1062.2527 | BQ56: =AX56/$G56 -> 61.810166 | BR56: =AY56/$G56 -> -923.0435
B57: FEBRERO | C57: MARZO | D57: 179-2026B1 | E57: 54 | F57: 46101 | G57: 24 | H57: POTA NUCAS | I57: Nucas | J57: 500-up | K57: Tailandia | L57: Lat Krabang | M57: DAIRECK S.A. | N57: Julieta | O57: 1100 | P57: 26400 | Q57: 953.625 | R57: 3513 | S57: =P57-R57 -> 22887 | T57: 1 | U57: ECO MARIN 26012N | V57: LIMG03924500 | W57: ONE LINE | X57: PAITA | Y57: 10005779 | Z57: Inventario final | AA57: =B57&Y57&Z57 -> FEBRERO10005779Inventario final | AB57: =AI57-616968.19/1968.8+215187/1968.8-47.35 -> 1848.8139 | AC57: =IFERROR(INDEX('Costos Producción Febrero'!$G$34:$G$57,MATCH(Resumen!Y57,'Costos Producción Febrero'!$B$34:$B$57,0))*AB57*G57,0) -> 25762.146 | AD57: =IFERROR(INDEX('Costos Producción Febrero'!$H$34:$H$57,MATCH(Resumen!Y57,'Costos Producción Febrero'!$B$34:$B$57,0))*AB57*G57,0) -> 9804.0642 | AE57: =IFERROR(INDEX('Costos Producción Febrero'!$I$34:$I$57,MATCH(Resumen!Y57,'Costos Producción Febrero'!$B$34:$B$57,0))*AB57*G57,0) -> 283.41449 | AF57: =IFERROR(INDEX('Costos Producción Febrero'!$J$34:$J$57,MATCH(Resumen!Y57,'Costos Producción Febrero'!$B$34:$B$57,0))*AB57*G57,0) -> 8521.9094 | AG57: =SUM(AC57:AF57) -> 44371.534 | AI57: 2100.2381 | AK57: =P57-AG57 -> -17971.534 | AL57: =AK57/P57 -> -0.68073994 | AM57: =R57 -> 3513 | AN57: =118461.136538461/5988.21*G57 -> 474.77748 | AO57: =1883/26*G57 -> 1738.1538 | AP57: =SUM(AM57:AO57) -> 5725.9313 | AQ57: =78579/1995.8*G57 -> 944.93236 | AR57: =S57*0.03 -> 686.61 | AS57: =AK57-AP57-AQ57+AR57 -> -23955.788 | AT57: =AS57/P57 -> -0.90741621 | AU57: =154473/1995.8*G57 -> 1857.5769 | AV57: =AS57-AU57 -> -25813.365 | AW57: =AV57/P57 -> -0.97777898 | AX57: =123484.35/1997.8*G57 -> 1483.444 | AY57: =AS57+AX57 -> -22472.344 | AZ57: =AY57/P57 -> -0.85122515 | BB57: =P57/$G57 -> 1100 | BC57: =-AC57/$G57 -> -1073.4228 | BD57: =-AD57/$G57 -> -408.50268 | BE57: =-AE57/$G57 -> -11.808937 | BF57: =-AF57/$G57 -> -355.07956 | BG57: =-AG57/$G57 -> -1848.8139 | BH57: =AK57/$G57 -> -748.81393 | BI57: =-AM57/$G57 -> -146.375 | BJ57: =-AO57/$G57 -> -72.423077 | BK57: =-AP57/$G57 -> -238.58047 | BL57: =-AQ57/$G57 -> -39.372182 | BM57: =AR57/$G57 -> 28.60875 | BN57: =AS57/$G57 -> -998.15784 | BO57: =-AU57/$G57 -> -77.399038 | BP57: =AV57/$G57 -> -1075.5569 | BQ57: =AX57/$G57 -> 61.810166 | BR57: =AY57/$G57 -> -936.34767
B58: FEBRERO | C58: MARZO | D58: 179-2026B2 | E58: 54 | F58: 46101 | G58: 24 | H58: POTA NUCAS | I58: Nucas | J58: 500-up | K58: Tailandia | L58: Lat Krabang | M58: DAIRECK S.A. | N58: Julieta | O58: 1100 | P58: 26400 | Q58: 953.625 | R58: 3513 | S58: =P58-R58 -> 22887 | T58: 1 | U58: ECO MARIN 26012N | V58: LIMG03933500 | W58: ONE LINE | X58: PAITA | Y58: 10005779 | Z58: Inventario final | AA58: =B58&Y58&Z58 -> FEBRERO10005779Inventario final | AB58: =AI58-616968.19/1968.8+215187/1968.8-47.35 -> 1848.8139 | AC58: =IFERROR(INDEX('Costos Producción Febrero'!$G$34:$G$57,MATCH(Resumen!Y58,'Costos Producción Febrero'!$B$34:$B$57,0))*AB58*G58,0) -> 25762.146 | AD58: =IFERROR(INDEX('Costos Producción Febrero'!$H$34:$H$57,MATCH(Resumen!Y58,'Costos Producción Febrero'!$B$34:$B$57,0))*AB58*G58,0) -> 9804.0642 | AE58: =IFERROR(INDEX('Costos Producción Febrero'!$I$34:$I$57,MATCH(Resumen!Y58,'Costos Producción Febrero'!$B$34:$B$57,0))*AB58*G58,0) -> 283.41449 | AF58: =IFERROR(INDEX('Costos Producción Febrero'!$J$34:$J$57,MATCH(Resumen!Y58,'Costos Producción Febrero'!$B$34:$B$57,0))*AB58*G58,0) -> 8521.9094 | AG58: =SUM(AC58:AF58) -> 44371.534 | AI58: 2100.2381 | AK58: =P58-AG58 -> -17971.534 | AL58: =AK58/P58 -> -0.68073994 | AM58: =R58 -> 3513 | AN58: =118461.136538461/5988.21*G58 -> 474.77748 | AO58: =1883/26*G58 -> 1738.1538 | AP58: =SUM(AM58:AO58) -> 5725.9313 | AQ58: =78579/1995.8*G58 -> 944.93236 | AR58: =S58*0.03 -> 686.61 | AS58: =AK58-AP58-AQ58+AR58 -> -23955.788 | AT58: =AS58/P58 -> -0.90741621 | AU58: =154473/1995.8*G58 -> 1857.5769 | AV58: =AS58-AU58 -> -25813.365 | AW58: =AV58/P58 -> -0.97777898 | AX58: =123484.35/1997.8*G58 -> 1483.444 | AY58: =AS58+AX58 -> -22472.344 | AZ58: =AY58/P58 -> -0.85122515 | BB58: =P58/$G58 -> 1100 | BC58: =-AC58/$G58 -> -1073.4228 | BD58: =-AD58/$G58 -> -408.50268 | BE58: =-AE58/$G58 -> -11.808937 | BF58: =-AF58/$G58 -> -355.07956 | BG58: =-AG58/$G58 -> -1848.8139 | BH58: =AK58/$G58 -> -748.81393 | BI58: =-AM58/$G58 -> -146.375 | BJ58: =-AO58/$G58 -> -72.423077 | BK58: =-AP58/$G58 -> -238.58047 | BL58: =-AQ58/$G58 -> -39.372182 | BM58: =AR58/$G58 -> 28.60875 | BN58: =AS58/$G58 -> -998.15784 | BO58: =-AU58/$G58 -> -77.399038 | BP58: =AV58/$G58 -> -1075.5569 | BQ58: =AX58/$G58 -> 61.810166 | BR58: =AY58/$G58 -> -936.34767
B59: FEBRERO | C59: MARZO | D59: 179-2026B3 | E59: 54 | F59: 46108 | G59: 24 | H59: POTA NUCAS | I59: Nucas | J59: 500-up | K59: Tailandia | L59: Lat Krabang | M59: DAIRECK S.A. | N59: Julieta | O59: 1100 | P59: 26400 | Q59: 953.625 | R59: 3513 | S59: =P59-R59 -> 22887 | T59: 1 | U59: ECO SIROCCO 26013S | V59: LIMG03937900 | W59: ONE LINE | X59: PAITA | Y59: 10005779 | Z59: Inventario final | AA59: =B59&Y59&Z59 -> FEBRERO10005779Inventario final | AB59: =AI59-616968.19/1968.8+215187/1968.8-47.35 -> 1848.8139 | AC59: =IFERROR(INDEX('Costos Producción Febrero'!$G$34:$G$57,MATCH(Resumen!Y59,'Costos Producción Febrero'!$B$34:$B$57,0))*AB59*G59,0) -> 25762.146 | AD59: =IFERROR(INDEX('Costos Producción Febrero'!$H$34:$H$57,MATCH(Resumen!Y59,'Costos Producción Febrero'!$B$34:$B$57,0))*AB59*G59,0) -> 9804.0642 | AE59: =IFERROR(INDEX('Costos Producción Febrero'!$I$34:$I$57,MATCH(Resumen!Y59,'Costos Producción Febrero'!$B$34:$B$57,0))*AB59*G59,0) -> 283.41449 | AF59: =IFERROR(INDEX('Costos Producción Febrero'!$J$34:$J$57,MATCH(Resumen!Y59,'Costos Producción Febrero'!$B$34:$B$57,0))*AB59*G59,0) -> 8521.9094 | AG59: =SUM(AC59:AF59) -> 44371.534 | AI59: 2100.2381 | AK59: =P59-AG59 -> -17971.534 | AL59: =AK59/P59 -> -0.68073994 | AM59: =R59 -> 3513 | AN59: =118461.136538461/5988.21*G59 -> 474.77748 | AO59: =1883/26*G59 -> 1738.1538 | AP59: =SUM(AM59:AO59) -> 5725.9313 | AQ59: =78579/1995.8*G59 -> 944.93236 | AR59: =S59*0.03 -> 686.61 | AS59: =AK59-AP59-AQ59+AR59 -> -23955.788 | AT59: =AS59/P59 -> -0.90741621 | AU59: =154473/1995.8*G59 -> 1857.5769 | AV59: =AS59-AU59 -> -25813.365 | AW59: =AV59/P59 -> -0.97777898 | AX59: =123484.35/1997.8*G59 -> 1483.444 | AY59: =AS59+AX59 -> -22472.344 | AZ59: =AY59/P59 -> -0.85122515 | BB59: =P59/$G59 -> 1100 | BC59: =-AC59/$G59 -> -1073.4228 | BD59: =-AD59/$G59 -> -408.50268 | BE59: =-AE59/$G59 -> -11.808937 | BF59: =-AF59/$G59 -> -355.07956 | BG59: =-AG59/$G59 -> -1848.8139 | BH59: =AK59/$G59 -> -748.81393 | BI59: =-AM59/$G59 -> -146.375 | BJ59: =-AO59/$G59 -> -72.423077 | BK59: =-AP59/$G59 -> -238.58047 | BL59: =-AQ59/$G59 -> -39.372182 | BM59: =AR59/$G59 -> 28.60875 | BN59: =AS59/$G59 -> -998.15784 | BO59: =-AU59/$G59 -> -77.399038 | BP59: =AV59/$G59 -> -1075.5569 | BQ59: =AX59/$G59 -> 61.810166 | BR59: =AY59/$G59 -> -936.34767
B60: FEBRERO | C60: MARZO | D60: 179-2026B4 | E60: 54 | F60: 46108 | G60: 24 | H60: POTA NUCAS | I60: Nucas | J60: 500-up | K60: Tailandia | L60: Lat Krabang | M60: DAIRECK S.A. | N60: Julieta | O60: 1100 | P60: 26400 | Q60: 953.625 | R60: 3513 | S60: =P60-R60 -> 22887 | T60: 1 | U60: ECO SIROCCO 26013S | V60: LIMG03938300 | W60: ONE LINE | X60: PAITA | Y60: 10005779 | Z60: Inventario final | AA60: =B60&Y60&Z60 -> FEBRERO10005779Inventario final | AB60: =AI60-616968.19/1968.8+215187/1968.8-47.35 -> 1848.8139 | AC60: =IFERROR(INDEX('Costos Producción Febrero'!$G$34:$G$57,MATCH(Resumen!Y60,'Costos Producción Febrero'!$B$34:$B$57,0))*AB60*G60,0) -> 25762.146 | AD60: =IFERROR(INDEX('Costos Producción Febrero'!$H$34:$H$57,MATCH(Resumen!Y60,'Costos Producción Febrero'!$B$34:$B$57,0))*AB60*G60,0) -> 9804.0642 | AE60: =IFERROR(INDEX('Costos Producción Febrero'!$I$34:$I$57,MATCH(Resumen!Y60,'Costos Producción Febrero'!$B$34:$B$57,0))*AB60*G60,0) -> 283.41449 | AF60: =IFERROR(INDEX('Costos Producción Febrero'!$J$34:$J$57,MATCH(Resumen!Y60,'Costos Producción Febrero'!$B$34:$B$57,0))*AB60*G60,0) -> 8521.9094 | AG60: =SUM(AC60:AF60) -> 44371.534 | AI60: 2100.2381 | AK60: =P60-AG60 -> -17971.534 | AL60: =AK60/P60 -> -0.68073994 | AM60: =R60 -> 3513 | AN60: =118461.136538461/5988.21*G60 -> 474.77748 | AO60: =1883/26*G60 -> 1738.1538 | AP60: =SUM(AM60:AO60) -> 5725.9313 | AQ60: =78579/1995.8*G60 -> 944.93236 | AR60: =S60*0.03 -> 686.61 | AS60: =AK60-AP60-AQ60+AR60 -> -23955.788 | AT60: =AS60/P60 -> -0.90741621 | AU60: =154473/1995.8*G60 -> 1857.5769 | AV60: =AS60-AU60 -> -25813.365 | AW60: =AV60/P60 -> -0.97777898 | AX60: =123484.35/1997.8*G60 -> 1483.444 | AY60: =AS60+AX60 -> -22472.344 | AZ60: =AY60/P60 -> -0.85122515 | BB60: =P60/$G60 -> 1100 | BC60: =-AC60/$G60 -> -1073.4228 | BD60: =-AD60/$G60 -> -408.50268 | BE60: =-AE60/$G60 -> -11.808937 | BF60: =-AF60/$G60 -> -355.07956 | BG60: =-AG60/$G60 -> -1848.8139 | BH60: =AK60/$G60 -> -748.81393 | BI60: =-AM60/$G60 -> -146.375 | BJ60: =-AO60/$G60 -> -72.423077 | BK60: =-AP60/$G60 -> -238.58047 | BL60: =-AQ60/$G60 -> -39.372182 | BM60: =AR60/$G60 -> 28.60875 | BN60: =AS60/$G60 -> -998.15784 | BO60: =-AU60/$G60 -> -77.399038 | BP60: =AV60/$G60 -> -1075.5569 | BQ60: =AX60/$G60 -> 61.810166 | BR60: =AY60/$G60 -> -936.34767
B61: FEBRERO | C61: MARZO | D61: 179-2026B5 | E61: 54 | F61: 46108 | G61: 24 | H61: POTA NUCAS | I61: Nucas | J61: 500-up | K61: Tailandia | L61: Lat Krabang | M61: DAIRECK S.A. | N61: Julieta | O61: 1100 | P61: 26400 | Q61: 966.54167 | R61: 3203 | S61: =P61-R61 -> 23197 | T61: 1 | U61: ECO SIROCCO 26013S | V61: LIMG03940300 | W61: ONE LINE | X61: PAITA | Y61: 10005779 | Z61: Inventario final | AA61: =B61&Y61&Z61 -> FEBRERO10005779Inventario final | AB61: =AI61-616968.19/1968.8+215187/1968.8-47.35 -> 1848.8139 | AC61: =IFERROR(INDEX('Costos Producción Febrero'!$G$34:$G$57,MATCH(Resumen!Y61,'Costos Producción Febrero'!$B$34:$B$57,0))*AB61*G61,0) -> 25762.146 | AD61: =IFERROR(INDEX('Costos Producción Febrero'!$H$34:$H$57,MATCH(Resumen!Y61,'Costos Producción Febrero'!$B$34:$B$57,0))*AB61*G61,0) -> 9804.0642 | AE61: =IFERROR(INDEX('Costos Producción Febrero'!$I$34:$I$57,MATCH(Resumen!Y61,'Costos Producción Febrero'!$B$34:$B$57,0))*AB61*G61,0) -> 283.41449 | AF61: =IFERROR(INDEX('Costos Producción Febrero'!$J$34:$J$57,MATCH(Resumen!Y61,'Costos Producción Febrero'!$B$34:$B$57,0))*AB61*G61,0) -> 8521.9094 | AG61: =SUM(AC61:AF61) -> 44371.534 | AI61: 2100.2381 | AK61: =P61-AG61 -> -17971.534 | AL61: =AK61/P61 -> -0.68073994 | AM61: =R61 -> 3203 | AN61: =118461.136538461/5988.21*G61 -> 474.77748 | AO61: =1883/26*G61 -> 1738.1538 | AP61: =SUM(AM61:AO61) -> 5415.9313 | AQ61: =78579/1995.8*G61 -> 944.93236 | AR61: =S61*0.03 -> 695.91 | AS61: =AK61-AP61-AQ61+AR61 -> -23636.488 | AT61: =AS61/P61 -> -0.89532152 | AU61: =154473/1995.8*G61 -> 1857.5769 | AV61: =AS61-AU61 -> -25494.065 | AW61: =AV61/P61 -> -0.96568428 | AX61: =123484.35/1997.8*G61 -> 1483.444 | AY61: =AS61+AX61 -> -22153.044 | AZ61: =AY61/P61 -> -0.83913046 | BB61: =P61/$G61 -> 1100 | BC61: =-AC61/$G61 -> -1073.4228 | BD61: =-AD61/$G61 -> -408.50268 | BE61: =-AE61/$G61 -> -11.808937 | BF61: =-AF61/$G61 -> -355.07956 | BG61: =-AG61/$G61 -> -1848.8139 | BH61: =AK61/$G61 -> -748.81393 | BI61: =-AM61/$G61 -> -133.45833 | BJ61: =-AO61/$G61 -> -72.423077 | BK61: =-AP61/$G61 -> -225.66381 | BL61: =-AQ61/$G61 -> -39.372182 | BM61: =AR61/$G61 -> 28.99625 | BN61: =AS61/$G61 -> -984.85367 | BO61: =-AU61/$G61 -> -77.399038 | BP61: =AV61/$G61 -> -1062.2527 | BQ61: =AX61/$G61 -> 61.810166 | BR61: =AY61/$G61 -> -923.0435
B62: FEBRERO | C62: MARZO | D62: 179-2026C1 | E62: 54 | F62: 46108 | G62: 24 | H62: POTA NUCAS | I62: Nucas | J62: 1-2 KG | K62: Tailandia | L62: Lat Krabang | M62: DAIRECK S.A. | N62: KHUNRUNG | O62: 1200 | P62: =28800-9240 -> 19560 | Q62: 1054.1667 | R62: 3500 | S62: =P62-R62 -> 16060 | T62: 1 | U62: ECO SIROCCO 26013S | V62: 6447908140 | W62: COSCO | X62: PAITA | Y62: 10005779 | Z62: Inventario final | AA62: =B62&Y62&Z62 -> FEBRERO10005779Inventario final | AB62: =AI62-616968.19/1968.8+215187/1968.8-47.35 -> 1848.8139 | AC62: =IFERROR(INDEX('Costos Producción Febrero'!$G$34:$G$57,MATCH(Resumen!Y62,'Costos Producción Febrero'!$B$34:$B$57,0))*AB62*G62,0) -> 25762.146 | AD62: =IFERROR(INDEX('Costos Producción Febrero'!$H$34:$H$57,MATCH(Resumen!Y62,'Costos Producción Febrero'!$B$34:$B$57,0))*AB62*G62,0) -> 9804.0642 | AE62: =IFERROR(INDEX('Costos Producción Febrero'!$I$34:$I$57,MATCH(Resumen!Y62,'Costos Producción Febrero'!$B$34:$B$57,0))*AB62*G62,0) -> 283.41449 | AF62: =IFERROR(INDEX('Costos Producción Febrero'!$J$34:$J$57,MATCH(Resumen!Y62,'Costos Producción Febrero'!$B$34:$B$57,0))*AB62*G62,0) -> 8521.9094 | AG62: =SUM(AC62:AF62) -> 44371.534 | AI62: 2100.2381 | AK62: =P62-AG62 -> -24811.534 | AL62: =AK62/P62 -> -1.2684834 | AM62: =R62 -> 3500 | AN62: =118461.136538461/5988.21*G62 -> 474.77748 | AO62: =1883/26*G62 -> 1738.1538 | AP62: =SUM(AM62:AO62) -> 5712.9313 | AQ62: =78579/1995.8*G62 -> 944.93236 | AR62: =S62*0.03 -> 481.8 | AS62: =AK62-AP62-AQ62+AR62 -> -30987.598 | AT62: =AS62/P62 -> -1.584233 | AU62: =154473/1995.8*G62 -> 1857.5769 | AV62: =AS62-AU62 -> -32845.175 | AW62: =AV62/P62 -> -1.6792012 | AX62: =123484.35/1997.8*G62 -> 1483.444 | AY62: =AS62+AX62 -> -29504.154 | AZ62: =AY62/P62 -> -1.5083923 | BB62: =P62/$G62 -> 815 | BC62: =-AC62/$G62 -> -1073.4228 | BD62: =-AD62/$G62 -> -408.50268 | BE62: =-AE62/$G62 -> -11.808937 | BF62: =-AF62/$G62 -> -355.07956 | BG62: =-AG62/$G62 -> -1848.8139 | BH62: =AK62/$G62 -> -1033.8139 | BI62: =-AM62/$G62 -> -145.83333 | BJ62: =-AO62/$G62 -> -72.423077 | BK62: =-AP62/$G62 -> -238.03881 | BL62: =-AQ62/$G62 -> -39.372182 | BM62: =AR62/$G62 -> 20.075 | BN62: =AS62/$G62 -> -1291.1499 | BO62: =-AU62/$G62 -> -77.399038 | BP62: =AV62/$G62 -> -1368.549 | BQ62: =AX62/$G62 -> 61.810166 | BR62: =AY62/$G62 -> -1229.3398
B63: FEBRERO | C63: MARZO | D63: 179-2026C2 | E63: 54 | F63: 46108 | G63: 24 | H63: POTA NUCAS | I63: Nucas | J63: 1-2 KG | K63: Tailandia | L63: Lat Krabang | M63: DAIRECK S.A. | N63: KHUNRUNG | O63: 1200 | P63: 28800 | Q63: 1054.1667 | R63: 3500 | S63: =P63-R63 -> 25300 | T63: 1 | U63: ECO SIROCCO 26013S | V63: 6447908120 | W63: COSCO | X63: PAITA | Y63: 10005779 | Z63: Inventario final | AA63: =B63&Y63&Z63 -> FEBRERO10005779Inventario final | AB63: =AI63-616968.19/1968.8+215187/1968.8-47.35 -> 1848.8139 | AC63: =IFERROR(INDEX('Costos Producción Febrero'!$G$34:$G$57,MATCH(Resumen!Y63,'Costos Producción Febrero'!$B$34:$B$57,0))*AB63*G63,0) -> 25762.146 | AD63: =IFERROR(INDEX('Costos Producción Febrero'!$H$34:$H$57,MATCH(Resumen!Y63,'Costos Producción Febrero'!$B$34:$B$57,0))*AB63*G63,0) -> 9804.0642 | AE63: =IFERROR(INDEX('Costos Producción Febrero'!$I$34:$I$57,MATCH(Resumen!Y63,'Costos Producción Febrero'!$B$34:$B$57,0))*AB63*G63,0) -> 283.41449 | AF63: =IFERROR(INDEX('Costos Producción Febrero'!$J$34:$J$57,MATCH(Resumen!Y63,'Costos Producción Febrero'!$B$34:$B$57,0))*AB63*G63,0) -> 8521.9094 | AG63: =SUM(AC63:AF63) -> 44371.534 | AI63: 2100.2381 | AK63: =P63-AG63 -> -15571.534 | AL63: =AK63/P63 -> -0.54067828 | AM63: =R63 -> 3500 | AN63: =118461.136538461/5988.21*G63 -> 474.77748 | AO63: =1883/26*G63 -> 1738.1538 | AP63: =SUM(AM63:AO63) -> 5712.9313 | AQ63: =78579/1995.8*G63 -> 944.93236 | AR63: =S63*0.03 -> 759 | AS63: =AK63-AP63-AQ63+AR63 -> -21470.398 | AT63: =AS63/P63 -> -0.74549993 | AU63: =154473/1995.8*G63 -> 1857.5769 | AV63: =AS63-AU63 -> -23327.975 | AW63: =AV63/P63 -> -0.80999913 | AX63: =123484.35/1997.8*G63 -> 1483.444 | AY63: =AS63+AX63 -> -19986.954 | AZ63: =AY63/P63 -> -0.69399146 | BB63: =P63/$G63 -> 1200 | BC63: =-AC63/$G63 -> -1073.4228 | BD63: =-AD63/$G63 -> -408.50268 | BE63: =-AE63/$G63 -> -11.808937 | BF63: =-AF63/$G63 -> -355.07956 | BG63: =-AG63/$G63 -> -1848.8139 | BH63: =AK63/$G63 -> -648.81393 | BI63: =-AM63/$G63 -> -145.83333 | BJ63: =-AO63/$G63 -> -72.423077 | BK63: =-AP63/$G63 -> -238.03881 | BL63: =-AQ63/$G63 -> -39.372182 | BM63: =AR63/$G63 -> 31.625 | BN63: =AS63/$G63 -> -894.59992 | BO63: =-AU63/$G63 -> -77.399038 | BP63: =AV63/$G63 -> -971.99896 | BQ63: =AX63/$G63 -> 61.810166 | BR63: =AY63/$G63 -> -832.78975
B64: FEBRERO | C64: MARZO | D64: 181-2026 | E64: 46077 | F64: 46108 | G64: 48 | H64: POTA NUCAS | I64: Nucas | J64: 500-1000 | K64: Tailandia | L64: Lat Krabang | M64: TSUJINO | N64: Jose | O64: 1200 | P64: 57600 | Q64: 1126.8125 | R64: 3513 | S64: =P64-R64 -> 54087 | T64: 1 | U64: ECO SIROCCO 26013S | V64: LIMG04324700 | W64: ONE LINE | X64: PAITA | Y64: 10005779 | Z64: Inventario final | AA64: =B64&Y64&Z64 -> FEBRERO10005779Inventario final | AB64: =AI64-616968.19/1968.8+215187/1968.8-47.35 -> 1848.8139 | AC64: =IFERROR(INDEX('Costos Producción Febrero'!$G$34:$G$57,MATCH(Resumen!Y64,'Costos Producción Febrero'!$B$34:$B$57,0))*AB64*G64,0) -> 51524.293 | AD64: =IFERROR(INDEX('Costos Producción Febrero'!$H$34:$H$57,MATCH(Resumen!Y64,'Costos Producción Febrero'!$B$34:$B$57,0))*AB64*G64,0) -> 19608.128 | AE64: =IFERROR(INDEX('Costos Producción Febrero'!$I$34:$I$57,MATCH(Resumen!Y64,'Costos Producción Febrero'!$B$34:$B$57,0))*AB64*G64,0) -> 566.82897 | AF64: =IFERROR(INDEX('Costos Producción Febrero'!$J$34:$J$57,MATCH(Resumen!Y64,'Costos Producción Febrero'!$B$34:$B$57,0))*AB64*G64,0) -> 17043.819 | AG64: =SUM(AC64:AF64) -> 88743.069 | AI64: 2100.2381 | AK64: =P64-AG64 -> -31143.069 | AL64: =AK64/P64 -> -0.54067828 | AM64: =R64 -> 3513 | AN64: =118461.136538461/5988.21*G64 -> 949.55497 | AO64: =1883/26*G64 -> 3476.3077 | AP64: =SUM(AM64:AO64) -> 7938.8627 | AQ64: =78579/1995.8*G64 -> 1889.8647 | AR64: =S64*0.03 -> 1622.61 | AS64: =AK64-AP64-AQ64+AR64 -> -39349.186 | AT64: =AS64/P64 -> -0.68314559 | AU64: =154473/1995.8*G64 -> 3715.1538 | AV64: =AS64-AU64 -> -43064.34 | AW64: =AV64/P64 -> -0.74764479 | AX64: =123484.35/1997.8*G64 -> 2966.888 | AY64: =AS64+AX64 -> -36382.298 | AZ64: =AY64/P64 -> -0.63163712 | BB64: =P64/$G64 -> 1200 | BC64: =-AC64/$G64 -> -1073.4228 | BD64: =-AD64/$G64 -> -408.50268 | BE64: =-AE64/$G64 -> -11.808937 | BF64: =-AF64/$G64 -> -355.07956 | BG64: =-AG64/$G64 -> -1848.8139 | BH64: =AK64/$G64 -> -648.81393 | BI64: =-AM64/$G64 -> -73.1875 | BJ64: =-AO64/$G64 -> -72.423077 | BK64: =-AP64/$G64 -> -165.39297 | BL64: =-AQ64/$G64 -> -39.372182 | BM64: =AR64/$G64 -> 33.804375 | BN64: =AS64/$G64 -> -819.77471 | BO64: =-AU64/$G64 -> -77.399038 | BP64: =AV64/$G64 -> -897.17375 | BQ64: =AX64/$G64 -> 61.810166 | BR64: =AY64/$G64 -> -757.96455
B65: FEBRERO | C65: MARZO | D65: 183-2026 | E65: 58 | F65: 46108 | G65: 27 | H65: POTA REJOS CONGELADOS | I65: Rejos | J65: 2- UP LIMPIOS | K65: China | L65: Yantai | M65: SHANDONG SHEENIER | O65: 2600 | P65: 70200 | Q65: 2485.1852 | R65: 3100 | S65: =P65-R65 -> 67100 | T65: 1 | U65: ECO SIROCCO 26013S | V65: 6447908790 | W65: COSCO | X65: PAITA | Y65: 10007162 | Z65: Inventario final | AA65: =B65&Y65&Z65 -> FEBRERO10007162Inventario final | AB65: =AI65-616968.19/1968.8+215187/1968.8-47.35 -> 1766.7551 | AC65: =IFERROR(INDEX('Costos Producción Febrero'!$G$34:$G$57,MATCH(Resumen!Y65,'Costos Producción Febrero'!$B$34:$B$57,0))*AB65*G65,0) -> 29248.751 | AD65: =IFERROR(INDEX('Costos Producción Febrero'!$H$34:$H$57,MATCH(Resumen!Y65,'Costos Producción Febrero'!$B$34:$B$57,0))*AB65*G65,0) -> 8304.3036 | AE65: =IFERROR(INDEX('Costos Producción Febrero'!$I$34:$I$57,MATCH(Resumen!Y65,'Costos Producción Febrero'!$B$34:$B$57,0))*AB65*G65,0) -> 442.22929 | AF65: =IFERROR(INDEX('Costos Producción Febrero'!$J$34:$J$57,MATCH(Resumen!Y65,'Costos Producción Febrero'!$B$34:$B$57,0))*AB65*G65,0) -> 9707.105 | AG65: =SUM(AC65:AF65) -> 47702.389 | AI65: 2018.1793 | AK65: =P65-AG65 -> 22497.611 | AL65: =AK65/P65 -> 0.32047879 | AM65: =R65 -> 3100 | AN65: =118461.136538461/5988.21*G65 -> 534.12467 | AO65: =1883/26*G65 -> 1955.4231 | AP65: =SUM(AM65:AO65) -> 5589.5477 | AQ65: =78579/1995.8*G65 -> 1063.0489 | AR65: =S65*0.03 -> 2013 | AS65: =AK65-AP65-AQ65+AR65 -> 17858.015 | AT65: =AS65/P65 -> 0.25438767 | AU65: =154473/1995.8*G65 -> 2089.774 | AV65: =AS65-AU65 -> 15768.241 | AW65: =AV65/P65 -> 0.22461881 | AX65: =123484.35/1997.8*G65 -> 1668.8745 | AY65: =AS65+AX65 -> 19526.889 | AZ65: =AY65/P65 -> 0.27816081 | BB65: =P65/$G65 -> 2600 | BC65: =-AC65/$G65 -> -1083.2871 | BD65: =-AD65/$G65 -> -307.5668 | BE65: =-AE65/$G65 -> -16.378863 | BF65: =-AF65/$G65 -> -359.52241 | BG65: =-AG65/$G65 -> -1766.7551 | BH65: =AK65/$G65 -> 833.24487 | BI65: =-AM65/$G65 -> -114.81481 | BJ65: =-AO65/$G65 -> -72.423077 | BK65: =-AP65/$G65 -> -207.02029 | BL65: =-AQ65/$G65 -> -39.372182 | BM65: =AR65/$G65 -> 74.555556 | BN65: =AS65/$G65 -> 661.40795 | BO65: =-AU65/$G65 -> -77.399038 | BP65: =AV65/$G65 -> 584.00891 | BQ65: =AX65/$G65 -> 61.810166 | BR65: =AY65/$G65 -> 723.21812
B66: FEBRERO | C66: MARZO | D66: 184-2026 | E66: 59 | F66: 46104 | G66: 216 | H66: POTA FILETE DARUMA | I66: Daruma | K66: China | L66: Qingdao | M66: LONGKOU JIABAO AQUATIC | N66: James | O66: 3100 | P66: 669600 | Q66: 2992.5926 | R66: 23200 | S66: =P66-R66 -> 646400 | T66: 8 | U66: ECO MARIN 26012N | V66: 6447338820 | W66: COSCO | X66: PAITA | Y66: 10009239 | Z66: Inventario final | AA66: =B66&Y66&Z66 -> FEBRERO10009239Inventario final | AB66: =AI66-616968.19/1968.8+215187/1968.8-47.35 -> 2146.3203 | AC66: =IFERROR(INDEX('Costos Producción Febrero'!$G$34:$G$57,MATCH(Resumen!Y66,'Costos Producción Febrero'!$B$34:$B$57,0))*AB66*G66,0) -> 227981.43 | AD66: =IFERROR(INDEX('Costos Producción Febrero'!$H$34:$H$57,MATCH(Resumen!Y66,'Costos Producción Febrero'!$B$34:$B$57,0))*AB66*G66,0) -> 148631.32 | AE66: =IFERROR(INDEX('Costos Producción Febrero'!$I$34:$I$57,MATCH(Resumen!Y66,'Costos Producción Febrero'!$B$34:$B$57,0))*AB66*G66,0) -> 2721.9574 | AF66: =IFERROR(INDEX('Costos Producción Febrero'!$J$34:$J$57,MATCH(Resumen!Y66,'Costos Producción Febrero'!$B$34:$B$57,0))*AB66*G66,0) -> 84270.483 | AG66: =SUM(AC66:AF66) -> 463605.19 | AI66: 2397.7445 | AK66: =P66-AG66 -> 205994.81 | AL66: =AK66/P66 -> 0.30763861 | AM66: =R66 -> 23200 | AN66: =118461.136538461/5988.21*G66 -> 4272.9974 | AO66: =1883/26*G66 -> 15643.385 | AP66: =SUM(AM66:AO66) -> 43116.382 | AQ66: =78579/1995.8*G66 -> 8504.3912 | AR66: =S66*0.03 -> 19392 | AS66: =AK66-AP66-AQ66+AR66 -> 173766.04 | AT66: =AS66/P66 -> 0.25950722 | AU66: =154473/1995.8*G66 -> 16718.192 | AV66: =AS66-AU66 -> 157047.85 | AW66: =AV66/P66 -> 0.23453979 | AX66: =123484.35/1997.8*G66 -> 13350.996 | AY66: =AS66+AX66 -> 187117.03 | AZ66: =AY66/P66 -> 0.27944599 | BB66: =P66/$G66 -> 3100 | BC66: =-AC66/$G66 -> -1055.4696 | BD66: =-AD66/$G66 -> -688.10795 | BE66: =-AE66/$G66 -> -12.601655 | BF66: =-AF66/$G66 -> -390.14112 | BG66: =-AG66/$G66 -> -2146.3203 | BH66: =AK66/$G66 -> 953.67968 | BI66: =-AM66/$G66 -> -107.40741 | BJ66: =-AO66/$G66 -> -72.423077 | BK66: =-AP66/$G66 -> -199.61288 | BL66: =-AQ66/$G66 -> -39.372182 | BM66: =AR66/$G66 -> 89.777778 | BN66: =AS66/$G66 -> 804.4724 | BO66: =-AU66/$G66 -> -77.399038 | BP66: =AV66/$G66 -> 727.07336 | BQ66: =AX66/$G66 -> 61.810166 | BR66: =AY66/$G66 -> 866.28256
B67: FEBRERO | C67: MARZO | D67: 185-2026 | E67: 59 | F67: 46104 | G67: 108 | H67: POTA FILETE DARUMA | I67: Daruma | K67: China | L67: Qingdao | M67: LONGKOU BOHAI | N67: James | O67: 3100 | P67: 334800 | Q67: 2992.5926 | R67: 11600 | S67: =P67-R67 -> 323200 | T67: 4 | U67: ECO MARIN 26012N | V67: 6447338860 | W67: COSCO | X67: PAITA | Y67: 10009239 | Z67: Inventario final | AA67: =B67&Y67&Z67 -> FEBRERO10009239Inventario final | AB67: =AI67-616968.19/1968.8+215187/1968.8-47.35 -> 2146.3203 | AC67: =IFERROR(INDEX('Costos Producción Febrero'!$G$34:$G$57,MATCH(Resumen!Y67,'Costos Producción Febrero'!$B$34:$B$57,0))*AB67*G67,0) -> 113990.72 | AD67: =IFERROR(INDEX('Costos Producción Febrero'!$H$34:$H$57,MATCH(Resumen!Y67,'Costos Producción Febrero'!$B$34:$B$57,0))*AB67*G67,0) -> 74315.658 | AE67: =IFERROR(INDEX('Costos Producción Febrero'!$I$34:$I$57,MATCH(Resumen!Y67,'Costos Producción Febrero'!$B$34:$B$57,0))*AB67*G67,0) -> 1360.9787 | AF67: =IFERROR(INDEX('Costos Producción Febrero'!$J$34:$J$57,MATCH(Resumen!Y67,'Costos Producción Febrero'!$B$34:$B$57,0))*AB67*G67,0) -> 42135.241 | AG67: =SUM(AC67:AF67) -> 231802.59 | AI67: 2397.7445 | AK67: =P67-AG67 -> 102997.41 | AL67: =AK67/P67 -> 0.30763861 | AM67: =R67 -> 11600 | AN67: =118461.136538461/5988.21*G67 -> 2136.4987 | AO67: =1883/26*G67 -> 7821.6923 | AP67: =SUM(AM67:AO67) -> 21558.191 | AQ67: =78579/1995.8*G67 -> 4252.1956 | AR67: =S67*0.03 -> 9696 | AS67: =AK67-AP67-AQ67+AR67 -> 86883.019 | AT67: =AS67/P67 -> 0.25950722 | AU67: =154473/1995.8*G67 -> 8359.0961 | AV67: =AS67-AU67 -> 78523.923 | AW67: =AV67/P67 -> 0.23453979 | AX67: =123484.35/1997.8*G67 -> 6675.4979 | AY67: =AS67+AX67 -> 93558.517 | AZ67: =AY67/P67 -> 0.27944599 | BB67: =P67/$G67 -> 3100 | BC67: =-AC67/$G67 -> -1055.4696 | BD67: =-AD67/$G67 -> -688.10795 | BE67: =-AE67/$G67 -> -12.601655 | BF67: =-AF67/$G67 -> -390.14112 | BG67: =-AG67/$G67 -> -2146.3203 | BH67: =AK67/$G67 -> 953.67968 | BI67: =-AM67/$G67 -> -107.40741 | BJ67: =-AO67/$G67 -> -72.423077 | BK67: =-AP67/$G67 -> -199.61288 | BL67: =-AQ67/$G67 -> -39.372182 | BM67: =AR67/$G67 -> 89.777778 | BN67: =AS67/$G67 -> 804.4724 | BO67: =-AU67/$G67 -> -77.399038 | BP67: =AV67/$G67 -> 727.07336 | BQ67: =AX67/$G67 -> 61.810166 | BR67: =AY67/$G67 -> 866.28256
B68: FEBRERO | C68: MARZO | D68: 189-2026 | E68: 68 | F68: 46108 | G68: 10 | H68: POTA NUCAS | I68: Nucas | J68: 300-500 | K68: Tailandia | L68: Lat Krabang | M68: DAIRECK S.A. | N68: Julieta | O68: 1130 | P68: 11300 | Q68: 990 | R68: 1400 | S68: =P68-R68 -> 9900 | T68: 1 | U68: ECO SIROCCO 26013S | V68: 6447908000 | W68: COSCO | X68: PAITA | Y68: 10005779 | Z68: Inventario final | AA68: =B68&Y68&Z68 -> FEBRERO10005779Inventario final | AB68: =AI68-616968.19/1968.8+215187/1968.8-47.35 -> 1848.8139 | AC68: =IFERROR(INDEX('Costos Producción Febrero'!$G$34:$G$57,MATCH(Resumen!Y68,'Costos Producción Febrero'!$B$34:$B$57,0))*AB68*G68,0) -> 10734.228 | AD68: =IFERROR(INDEX('Costos Producción Febrero'!$H$34:$H$57,MATCH(Resumen!Y68,'Costos Producción Febrero'!$B$34:$B$57,0))*AB68*G68,0) -> 4085.0268 | AE68: =IFERROR(INDEX('Costos Producción Febrero'!$I$34:$I$57,MATCH(Resumen!Y68,'Costos Producción Febrero'!$B$34:$B$57,0))*AB68*G68,0) -> 118.08937 | AF68: =IFERROR(INDEX('Costos Producción Febrero'!$J$34:$J$57,MATCH(Resumen!Y68,'Costos Producción Febrero'!$B$34:$B$57,0))*AB68*G68,0) -> 3550.7956 | AG68: =SUM(AC68:AF68) -> 18488.139 | AI68: 2100.2381 | AK68: =P68-AG68 -> -7188.1393 | AL68: =AK68/P68 -> -0.63611852 | AM68: =R68 -> 1400 | AN68: =118461.136538461/5988.21*G68 -> 197.82395 | AO68: =1883/26*G68 -> 724.23077 | AP68: =SUM(AM68:AO68) -> 2322.0547 | AQ68: =78579/1995.8*G68 -> 393.72182 | AR68: =S68*0.03 -> 297 | AS68: =AK68-AP68-AQ68+AR68 -> -9606.9159 | AT68: =AS68/P68 -> -0.85016955 | AU68: =154473/1995.8*G68 -> 773.99038 | AV68: =AS68-AU68 -> -10380.906 | AW68: =AV68/P68 -> -0.91866427 | AX68: =123484.35/1997.8*G68 -> 618.10166 | AY68: =AS68+AX68 -> -8988.8142 | AZ68: =AY68/P68 -> -0.79547028 | BB68: =P68/$G68 -> 1130 | BC68: =-AC68/$G68 -> -1073.4228 | BD68: =-AD68/$G68 -> -408.50268 | BE68: =-AE68/$G68 -> -11.808937 | BF68: =-AF68/$G68 -> -355.07956 | BG68: =-AG68/$G68 -> -1848.8139 | BH68: =AK68/$G68 -> -718.81393 | BI68: =-AM68/$G68 -> -140 | BJ68: =-AO68/$G68 -> -72.423077 | BK68: =-AP68/$G68 -> -232.20547 | BL68: =-AQ68/$G68 -> -39.372182 | BM68: =AR68/$G68 -> 29.7 | BN68: =AS68/$G68 -> -960.69159 | BO68: =-AU68/$G68 -> -77.399038 | BP68: =AV68/$G68 -> -1038.0906 | BQ68: =AX68/$G68 -> 61.810166 | BR68: =AY68/$G68 -> -898.88142
B69: FEBRERO | C69: MARZO | D69: 189-2026 | E69: 68 | F69: 46108 | G69: 15 | H69: POTA NUCAS | I69: Nucas | J69: 500-1000 | K69: Tailandia | L69: Lat Krabang | M69: DAIRECK S.A. | N69: Julieta | O69: 1200 | P69: 18000 | Q69: 1060 | R69: 2100 | S69: =P69-R69 -> 15900 | T69: 0 | U69: ECO SIROCCO 26013S | V69: 6447908000 | W69: COSCO | X69: PAITA | Y69: 10005779 | Z69: Inventario final | AA69: =B69&Y69&Z69 -> FEBRERO10005779Inventario final | AB69: =AI69-616968.19/1968.8+215187/1968.8-47.35 -> 1848.8139 | AC69: =IFERROR(INDEX('Costos Producción Febrero'!$G$34:$G$57,MATCH(Resumen!Y69,'Costos Producción Febrero'!$B$34:$B$57,0))*AB69*G69,0) -> 16101.341 | AD69: =IFERROR(INDEX('Costos Producción Febrero'!$H$34:$H$57,MATCH(Resumen!Y69,'Costos Producción Febrero'!$B$34:$B$57,0))*AB69*G69,0) -> 6127.5402 | AE69: =IFERROR(INDEX('Costos Producción Febrero'!$I$34:$I$57,MATCH(Resumen!Y69,'Costos Producción Febrero'!$B$34:$B$57,0))*AB69*G69,0) -> 177.13405 | AF69: =IFERROR(INDEX('Costos Producción Febrero'!$J$34:$J$57,MATCH(Resumen!Y69,'Costos Producción Febrero'!$B$34:$B$57,0))*AB69*G69,0) -> 5326.1934 | AG69: =SUM(AC69:AF69) -> 27732.209 | AI69: 2100.2381 | AK69: =P69-AG69 -> -9732.209 | AL69: =AK69/P69 -> -0.54067828 | AM69: =R69 -> 2100 | AN69: =118461.136538461/5988.21*G69 -> 296.73593 | AO69: =1883/26*G69 -> 1086.3462 | AP69: =SUM(AM69:AO69) -> 3483.0821 | AQ69: =78579/1995.8*G69 -> 590.58272 | AR69: =S69*0.03 -> 477 | AS69: =AK69-AP69-AQ69+AR69 -> -13328.874 | AT69: =AS69/P69 -> -0.74049299 | AU69: =154473/1995.8*G69 -> 1160.9856 | AV69: =AS69-AU69 -> -14489.859 | AW69: =AV69/P69 -> -0.80499219 | AX69: =123484.35/1997.8*G69 -> 927.15249 | AY69: =AS69+AX69 -> -12401.721 | AZ69: =AY69/P69 -> -0.68898452 | BB69: =P69/$G69 -> 1200 | BC69: =-AC69/$G69 -> -1073.4228 | BD69: =-AD69/$G69 -> -408.50268 | BE69: =-AE69/$G69 -> -11.808937 | BF69: =-AF69/$G69 -> -355.07956 | BG69: =-AG69/$G69 -> -1848.8139 | BH69: =AK69/$G69 -> -648.81393 | BI69: =-AM69/$G69 -> -140 | BJ69: =-AO69/$G69 -> -72.423077 | BK69: =-AP69/$G69 -> -232.20547 | BL69: =-AQ69/$G69 -> -39.372182 | BM69: =AR69/$G69 -> 31.8 | BN69: =AS69/$G69 -> -888.59159 | BO69: =-AU69/$G69 -> -77.399038 | BP69: =AV69/$G69 -> -965.99062 | BQ69: =AX69/$G69 -> 61.810166 | BR69: =AY69/$G69 -> -826.78142
B70: FEBRERO | C70: MARZO | D70: 170-2026B | E70: 43 | F70: 46092 | G70: 24 | H70: POTA REJOS CONGELADOS | I70: Rejos | J70: 2 - UP | K70: España | L70: Vigo | M70: KULALIA | N70: Ramon | O70: 2400 | P70: =O70*G70 -> 57600 | Q70: =+S70/G70 -> 2230.0104 | R70: =4079.75 -> 4079.75 | S70: =P70-R70 -> 53520.25 | T70: 1 | U70: CMA CGM BOLDNESS / 0DVODN1MA | V70: LMM0575562 | W70: CMA CGM | Y70: 10007162 | Z70: Inventario final | AA70: =B70&Y70&Z70 -> FEBRERO10007162Inventario final | AB70: =AI70-616968.19/1968.8+215187/1968.8-47.35 -> 1766.7551 | AC70: =IFERROR(INDEX('Costos Producción Febrero'!$G$34:$G$57,MATCH(Resumen!Y70,'Costos Producción Febrero'!$B$34:$B$57,0))*AB70*G70,0) -> 25998.89 | AD70: =IFERROR(INDEX('Costos Producción Febrero'!$H$34:$H$57,MATCH(Resumen!Y70,'Costos Producción Febrero'!$B$34:$B$57,0))*AB70*G70,0) -> 7381.6032 | AE70: =IFERROR(INDEX('Costos Producción Febrero'!$I$34:$I$57,MATCH(Resumen!Y70,'Costos Producción Febrero'!$B$34:$B$57,0))*AB70*G70,0) -> 393.0927 | AF70: =IFERROR(INDEX('Costos Producción Febrero'!$J$34:$J$57,MATCH(Resumen!Y70,'Costos Producción Febrero'!$B$34:$B$57,0))*AB70*G70,0) -> 8628.5378 | AG70: =SUM(AC70:AF70) -> 42402.123 | AI70: 2018.1793 | AK70: =P70-AG70 -> 15197.877 | AL70: =AK70/P70 -> 0.26385203 | AM70: =R70 -> 4079.75 | AN70: =118461.136538461/5988.21*G70 -> 474.77748 | AO70: =1883/26*G70 -> 1738.1538 | AP70: =SUM(AM70:AO70) -> 6292.6813 | AQ70: =78579/1995.8*G70 -> 944.93236 | AR70: =S70*0.03 -> 1605.6075 | AS70: =AK70-AP70-AQ70+AR70 -> 9565.8706 | AT70: =AS70/P70 -> 0.16607414 | AU70: =154473/1995.8*G70 -> 1857.5769 | AV70: =AS70-AU70 -> 7708.2937 | AW70: =AV70/P70 -> 0.13382454 | AX70: =123484.35/1997.8*G70 -> 1483.444 | AY70: =AS70+AX70 -> 11049.315 | AZ70: =AY70/P70 -> 0.19182838 | BB70: =P70/$G70 -> 2400 | BC70: =-AC70/$G70 -> -1083.2871 | BD70: =-AD70/$G70 -> -307.5668 | BE70: =-AE70/$G70 -> -16.378863 | BF70: =-AF70/$G70 -> -359.52241 | BG70: =-AG70/$G70 -> -1766.7551 | BH70: =AK70/$G70 -> 633.24487 | BI70: =-AM70/$G70 -> -169.98958 | BJ70: =-AO70/$G70 -> -72.423077 | BK70: =-AP70/$G70 -> -262.19506 | BL70: =-AQ70/$G70 -> -39.372182 | BM70: =AR70/$G70 -> 66.900312 | BN70: =AS70/$G70 -> 398.57794 | BO70: =-AU70/$G70 -> -77.399038 | BP70: =AV70/$G70 -> 321.1789 | BQ70: =AX70/$G70 -> 61.810166 | BR70: =AY70/$G70 -> 460.38811
B71: FEBRERO | C71: MARZO | D71: 153-2026 | E71: 26 | F71: 46110 | G71: =26*1 -> 26 | H71: POTA REPRODUCTORES | I71: Rejos | K71: España | L71: Valencia | M71: OCEANUS FISH | N71: Ignacio / Ives | O71: 2950 | P71: =+G71*O71 -> 76700 | Q71: =+S71/G71 -> 2793.0865 | R71: =4079.75 -> 4079.75 | S71: =P71-R71 -> 72620.25 | T71: 1 | U71: CAPE SKAGEN 614N | V71: 19449468 | W71: HAPAG | Y71: 10007567 | Z71: Inventario final | AA71: =B71&Y71&Z71 -> FEBRERO10007567Inventario final | AB71: =AI71-616968.19/1968.8+215187/1968.8-47.35 -> 1768.0738 | AC71: =IFERROR(INDEX('Costos Producción Febrero'!$G$34:$G$57,MATCH(Resumen!Y71,'Costos Producción Febrero'!$B$34:$B$57,0))*AB71*G71,0) -> 28390.222 | AD71: =IFERROR(INDEX('Costos Producción Febrero'!$H$34:$H$57,MATCH(Resumen!Y71,'Costos Producción Febrero'!$B$34:$B$57,0))*AB71*G71,0) -> 7651.2856 | AE71: =IFERROR(INDEX('Costos Producción Febrero'!$I$34:$I$57,MATCH(Resumen!Y71,'Costos Producción Febrero'!$B$34:$B$57,0))*AB71*G71,0) -> 496.17066 | AF71: =IFERROR(INDEX('Costos Producción Febrero'!$J$34:$J$57,MATCH(Resumen!Y71,'Costos Producción Febrero'!$B$34:$B$57,0))*AB71*G71,0) -> 9432.2411 | AG71: =SUM(AC71:AF71) -> 45969.919 | AI71: 2019.498 | AK71: =P71-AG71 -> 30730.081 | AL71: =AK71/P71 -> 0.40065295 | AM71: =R71 -> 4079.75 | AN71: =118461.136538461/5988.21*G71 -> 514.34227 | AO71: =1883/26*G71 -> 1883 | AP71: =SUM(AM71:AO71) -> 6477.0923 | AQ71: =78579/1995.8*G71 -> 1023.6767 | AR71: =S71*0.03 -> 2178.6075 | AS71: =AK71-AP71-AQ71+AR71 -> 25407.919 | AT71: =AS71/P71 -> 0.33126362 | AU71: =154473/1995.8*G71 -> 2012.375 | AV71: =AS71-AU71 -> 23395.544 | AW71: =AV71/P71 -> 0.30502666 | AX71: =123484.35/1997.8*G71 -> 1607.0643 | AY71: =AS71+AX71 -> 27014.984 | AZ71: =AY71/P71 -> 0.35221622 | BB71: =P71/$G71 -> 2950 | BC71: =-AC71/$G71 -> -1091.9316 | BD71: =-AD71/$G71 -> -294.28021 | BE71: =-AE71/$G71 -> -19.083487 | BF71: =-AF71/$G71 -> -362.77851 | BG71: =-AG71/$G71 -> -1768.0738 | BH71: =AK71/$G71 -> 1181.9262 | BI71: =-AM71/$G71 -> -156.91346 | BJ71: =-AO71/$G71 -> -72.423077 | BK71: =-AP71/$G71 -> -249.11893 | BL71: =-AQ71/$G71 -> -39.372182 | BM71: =AR71/$G71 -> 83.792596 | BN71: =AS71/$G71 -> 977.22767 | BO71: =-AU71/$G71 -> -77.399038 | BP71: =AV71/$G71 -> 899.82863 | BQ71: =AX71/$G71 -> 61.810166 | BR71: =AY71/$G71 -> 1039.0378
B72: FEBRERO | C72: MARZO | E72: 46111 | F72: 46111 | G72: 0 | H72: RESIDUOS DE POTA | I72: Residuos | J72: Residuos | K72: Residuos | L72: Residuos | M72: PROVEEDORA DE PRODUCTOS MARINOS | O72: 0 | P72: 26456.61 | Q72: 0 | R72: 0 | S72: =P72-R72 -> 26456.61 | AB72: =IFERROR(AG72/G72,0) -> 0 | AC72: =IFERROR(INDEX('Costos Producción Febrero'!$G$34:$G$57,MATCH(Resumen!Y72,'Costos Producción Febrero'!$B$34:$B$57,0))*AI72*G72,0)*1.25 -> 0 | AD72: =IFERROR(INDEX('Costos Producción Febrero'!$H$34:$H$57,MATCH(Resumen!Y72,'Costos Producción Febrero'!$B$34:$B$57,0))*AI72*G72,0) -> 0 | AE72: =IFERROR(INDEX('Costos Producción Febrero'!$I$34:$I$57,MATCH(Resumen!Y72,'Costos Producción Febrero'!$B$34:$B$57,0))*AI72*G72,0) -> 0 | AF72: =IFERROR(INDEX('Costos Producción Febrero'!$J$34:$J$57,MATCH(Resumen!Y72,'Costos Producción Febrero'!$B$34:$B$57,0))*AI72*G72,0) -> 0 | AG72: =SUM(AC72:AF72) -> 0 | AK72: =P72-AG72 -> 26456.61 | AL72: =AK72/P72 -> 1 | AM72: =R72 -> 0 | AN72: =118461.136538461/5988.21*G72 -> 0 | AO72: =1882/26*G72 -> 0 | AP72: =SUM(AM72:AO72) -> 0 | AQ72: =56604/1634.3*G72 -> 0 | AR72: 0 | AS72: =AK72-AP72-AQ72+AR72 -> 26456.61 | AT72: =AS72/P72 -> 1 | AU72: =131251/248*G72 -> 0 | AV72: =AS72-AU72 -> 26456.61 | AW72: =AV72/P72 -> 1 | AX72: =123530/248*G72 -> 0 | AY72: =AS72+AX72 -> 26456.61 | AZ72: =AY72/P72 -> 1 | BB72: 0 | BC72: 0 | BD72: 0 | BE72: 0 | BF72: 0 | BG72: 0 | BH72: 0 | BI72: 0 | BJ72: 0 | BK72: 0 | BL72: 0 | BM72: 0 | BN72: 0 | BO72: 0 | BP72: 0 | BQ72: 0 | BR72: 0
B73: MARZO | C73: ABRIL | D73: 145-2025B | E73: 46020 | F73: 46123 | G73: 27 | H73: POTA RECORTES COCIDOS | I73: Recortes cocidos | K73: España | L73: Vigo | M73: GLOBAL OCEAN | N73: Jorge | O73: 2500 | P73: 67500 | Q73: 2312.2896 | R73: 5068.18 | S73: 62431.82 | T73: 1 | U73: MSC CAROLE NX614R | V73: EBKG16377153 | W73: MSC | Y73: 10007050 | AB73: =AI73-111688.22/2006.56-47.35 -> 1685.0983 | AC73: =IFERROR(INDEX('Costos Producción Febrero'!$G$34:$G$57,MATCH(Resumen!Y73,'Costos Producción Febrero'!$B$34:$B$57,0))*AB73*G73,0) -> 38051.667 | AD73: =IFERROR(INDEX('Costos Producción Febrero'!$H$34:$H$57,MATCH(Resumen!Y73,'Costos Producción Febrero'!$B$34:$B$57,0))*AB73*G73,0) -> 6983.5233 | AE73: =IFERROR(INDEX('Costos Producción Febrero'!$I$34:$I$57,MATCH(Resumen!Y73,'Costos Producción Febrero'!$B$34:$B$57,0))*AB73*G73,0) -> 663.43471 | AF73: =IFERROR(INDEX('Costos Producción Febrero'!$J$34:$J$57,MATCH(Resumen!Y73,'Costos Producción Febrero'!$B$34:$B$57,0))*AB73*G73,0) -> -200.97028 | AG73: =SUM(AC73:AF73) -> 45497.654 | AI73: 1788.1098 | AK73: =P73-AG73 -> 22002.346 | AL73: =AK73/P73 -> 0.32596068 | AM73: =R73 -> 5068.18 | AN73: =118461.136538461/5988.21*G73 -> 534.12467 | AO73: =1883/26*G73 -> 1955.4231 | AP73: =SUM(AM73:AO73) -> 7557.7277 | AQ73: =65076/2110.11*G73 -> 832.68266 | AR73: =S73*0.03 -> 1872.9546 | AS73: =AK73-AP73-AQ73+AR73 -> 15484.89 | AT73: =AS73/P73 -> 0.22940578 | AU73: =221685/2110.11*G73 -> 2836.5796 | AV73: =AS73-AU73 -> 12648.31 | AW73: =AV73/P73 -> 0.18738238 | AX73: =123484.35/2110.11*G73 -> 1580.0491 | AY73: =AS73+AX73 -> 17064.939 | AZ73: =AY73/P73 -> 0.25281391 | BB73: =P73/$G73 -> 2500 | BC73: =-AC73/$G73 -> -1409.321 | BD73: =-AD73/$G73 -> -258.64901 | BE73: =-AE73/$G73 -> -24.571656 | BF73: =-AF73/$G73 -> 7.4433438 | BG73: =-AG73/$G73 -> -1685.0983 | BH73: =AK73/$G73 -> 814.9017 | BI73: =-AM73/$G73 -> -187.71037 | BJ73: =-AO73/$G73 -> -72.423077 | BK73: =-AP73/$G73 -> -279.91584 | BL73: =-AQ73/$G73 -> -30.840098 | BM73: =AR73/$G73 -> 69.368689 | BN73: =AS73/$G73 -> 573.51444 | BO73: =-AU73/$G73 -> -105.0585 | BP73: =AV73/$G73 -> 468.45594 | BQ73: =AX73/$G73 -> 58.520338 | BR73: =AY73/$G73 -> 632.03478
B74: MARZO | C74: ABRIL | D74: 150-2026D | E74: 325 | F74: 46123 | G74: 26 | H74: POTA REPRODUCTORES | I74: Rejos | J74: s/t | K74: España | L74: Vigo | M74: OVERSEA | N74: Avelino | O74: 2950 | P74: 76700 | Q74: 2755.07 | R74: 5068.18 | S74: 71631.82 | T74: 1 | U74: MSC CAROLE NX614R | V74: EBKG16377125 | W74: MSC | Y74: 10007567 | AB74: =AI74-111688.22/2006.56-47.35 -> 2001.4942 | AC74: =IFERROR(INDEX('Costos Producción Febrero'!$G$34:$G$57,MATCH(Resumen!Y74,'Costos Producción Febrero'!$B$34:$B$57,0))*AB74*G74,0) -> 32138.288 | AD74: =IFERROR(INDEX('Costos Producción Febrero'!$H$34:$H$57,MATCH(Resumen!Y74,'Costos Producción Febrero'!$B$34:$B$57,0))*AB74*G74,0) -> 8661.4054 | AE74: =IFERROR(INDEX('Costos Producción Febrero'!$I$34:$I$57,MATCH(Resumen!Y74,'Costos Producción Febrero'!$B$34:$B$57,0))*AB74*G74,0) -> 561.67492 | AF74: =IFERROR(INDEX('Costos Producción Febrero'!$J$34:$J$57,MATCH(Resumen!Y74,'Costos Producción Febrero'!$B$34:$B$57,0))*AB74*G74,0) -> 10677.482 | AG74: =SUM(AC74:AF74) -> 52038.85 | AI74: 2104.5058 | AK74: =P74-AG74 -> 24661.15 | AL74: =AK74/P74 -> 0.32152738 | AM74: =R74 -> 5068.18 | AN74: =118461.136538461/5988.21*G74 -> 514.34227 | AO74: =1883/26*G74 -> 1883 | AP74: =SUM(AM74:AO74) -> 7465.5223 | AQ74: =65076/2110.11*G74 -> 801.84256 | AR74: =S74*0.03 -> 2148.9546 | AS74: =AK74-AP74-AQ74+AR74 -> 18542.739 | AT74: =AS74/P74 -> 0.24175671 | AU74: =221685/2110.11*G74 -> 2731.5211 | AV74: =AS74-AU74 -> 15811.218 | AW74: =AV74/P74 -> 0.20614366 | AX74: =123484.35/2110.11*G74 -> 1521.5288 | AY74: =AS74+AX74 -> 20064.268 | AZ74: =AY74/P74 -> 0.26159411 | BB74: =P74/$G74 -> 2950 | BC74: =-AC74/$G74 -> -1236.088 | BD74: =-AD74/$G74 -> -333.13098 | BE74: =-AE74/$G74 -> -21.602882 | BF74: =-AF74/$G74 -> -410.67239 | BG74: =-AG74/$G74 -> -2001.4942 | BH74: =AK74/$G74 -> 948.50576 | BI74: =-AM74/$G74 -> -194.93 | BJ74: =-AO74/$G74 -> -72.423077 | BK74: =-AP74/$G74 -> -287.13547 | BL74: =-AQ74/$G74 -> -30.840098 | BM74: =AR74/$G74 -> 82.6521 | BN74: =AS74/$G74 -> 713.18229 | BO74: =-AU74/$G74 -> -105.0585 | BP74: =AV74/$G74 -> 608.12378 | BQ74: =AX74/$G74 -> 58.520338 | BR74: =AY74/$G74 -> 771.70262
B75: MARZO | C75: ABRIL | D75: 172-2026C | E75: 47 | F75: 46120 | G75: 125 | H75: POTA FILETE CONGELADO | I75: Filete | J75: 2-4 kg AA | K75: España | L75: Vigo | M75: KULALIA | N75: Ramon | O75: 1400 | P75: 175000 | Q75: 1143.16 | R75: 32105 | S75: 142895 | T75: 5 | U75: ECO MARIN 26014N | V75: LIMG05144800 | W75: ONE | Y75: 10005721 | AB75: =AI75-111688.22/2006.56-47.35 -> 2033.6752 | AC75: =IFERROR(INDEX('Costos Producción Febrero'!$G$34:$G$57,MATCH(Resumen!Y75,'Costos Producción Febrero'!$B$34:$B$57,0))*AB75*G75,0) -> 154384.14 | AD75: =IFERROR(INDEX('Costos Producción Febrero'!$H$34:$H$57,MATCH(Resumen!Y75,'Costos Producción Febrero'!$B$34:$B$57,0))*AB75*G75,0) -> 45237.76 | AE75: =IFERROR(INDEX('Costos Producción Febrero'!$I$34:$I$57,MATCH(Resumen!Y75,'Costos Producción Febrero'!$B$34:$B$57,0))*AB75*G75,0) -> 2771.367 | AF75: =IFERROR(INDEX('Costos Producción Febrero'!$J$34:$J$57,MATCH(Resumen!Y75,'Costos Producción Febrero'!$B$34:$B$57,0))*AB75*G75,0) -> 51816.132 | AG75: =SUM(AC75:AF75) -> 254209.4 | AI75: 2136.6868 | AK75: =P75-AG75 -> -79209.403 | AL75: =AK75/P75 -> -0.45262516 | AM75: =R75 -> 32105 | AN75: =118461.136538461/5988.21*G75 -> 2472.7994 | AO75: =1883/26*G75 -> 9052.8846 | AP75: =SUM(AM75:AO75) -> 43630.684 | AQ75: =65076/2110.11*G75 -> 3855.0123 | AR75: =S75*0.03 -> 4286.85 | AS75: =AK75-AP75-AQ75+AR75 -> -122408.25 | AT75: =AS75/P75 -> -0.69947571 | AU75: =221685/2110.11*G75 -> 13132.313 | AV75: =AS75-AU75 -> -135540.56 | AW75: =AV75/P75 -> -0.7745175 | AX75: =123484.35/2110.11*G75 -> 7315.0422 | AY75: =AS75+AX75 -> -115093.21 | AZ75: =AY75/P75 -> -0.65767547 | BB75: =P75/$G75 -> 1400 | BC75: =-AC75/$G75 -> -1235.0732 | BD75: =-AD75/$G75 -> -361.90208 | BE75: =-AE75/$G75 -> -22.170936 | BF75: =-AF75/$G75 -> -414.52905 | BG75: =-AG75/$G75 -> -2033.6752 | BH75: =AK75/$G75 -> -633.67523 | BI75: =-AM75/$G75 -> -256.84 | BJ75: =-AO75/$G75 -> -72.423077 | BK75: =-AP75/$G75 -> -349.04547 | BL75: =-AQ75/$G75 -> -30.840098 | BM75: =AR75/$G75 -> 34.2948 | BN75: =AS75/$G75 -> -979.266 | BO75: =-AU75/$G75 -> -105.0585 | BP75: =AV75/$G75 -> -1084.3245 | BQ75: =AX75/$G75 -> 58.520338 | BR75: =AY75/$G75 -> -920.74566
B76: MARZO | C76: ABRIL | D76: 173-2026 | E76: 48 | F76: 46120 | G76: 120 | H76: POTA FILETE CONGELADO | I76: Filete | J76: 2-4 AA | K76: Japón | L76: Sendai | M76: TSUJINO | N76: Jose | O76: 1500 | P76: 180000 | Q76: 1371.2083 | R76: 15455 | S76: 164545 | T76: 5 | U76: ECO MARIN 26014N | V76: LIMG05163900 | W76: ONE | Y76: 10005721 | AB76: =AI76-111688.22/2006.56-47.35 -> 2033.6752 | AC76: =IFERROR(INDEX('Costos Producción Febrero'!$G$34:$G$57,MATCH(Resumen!Y76,'Costos Producción Febrero'!$B$34:$B$57,0))*AB76*G76,0) -> 148208.78 | AD76: =IFERROR(INDEX('Costos Producción Febrero'!$H$34:$H$57,MATCH(Resumen!Y76,'Costos Producción Febrero'!$B$34:$B$57,0))*AB76*G76,0) -> 43428.249 | AE76: =IFERROR(INDEX('Costos Producción Febrero'!$I$34:$I$57,MATCH(Resumen!Y76,'Costos Producción Febrero'!$B$34:$B$57,0))*AB76*G76,0) -> 2660.5123 | AF76: =IFERROR(INDEX('Costos Producción Febrero'!$J$34:$J$57,MATCH(Resumen!Y76,'Costos Producción Febrero'!$B$34:$B$57,0))*AB76*G76,0) -> 49743.487 | AG76: =SUM(AC76:AF76) -> 244041.03 | AI76: 2136.6868 | AK76: =P76-AG76 -> -64041.027 | AL76: =AK76/P76 -> -0.35578348 | AM76: =R76 -> 15455 | AN76: =118461.136538461/5988.21*G76 -> 2373.8874 | AO76: =1883/26*G76 -> 8690.7692 | AP76: =SUM(AM76:AO76) -> 26519.657 | AQ76: =65076/2110.11*G76 -> 3700.8118 | AR76: =S76*0.03 -> 4936.35 | AS76: =AK76-AP76-AQ76+AR76 -> -89325.146 | AT76: =AS76/P76 -> -0.49625081 | AU76: =221685/2110.11*G76 -> 12607.02 | AV76: =AS76-AU76 -> -101932.17 | AW76: =AV76/P76 -> -0.56628981 | AX76: =123484.35/2110.11*G76 -> 7022.4405 | AY76: =AS76+AX76 -> -82302.705 | AZ76: =AY76/P76 -> -0.45723725 | BB76: =P76/$G76 -> 1500 | BC76: =-AC76/$G76 -> -1235.0732 | BD76: =-AD76/$G76 -> -361.90208 | BE76: =-AE76/$G76 -> -22.170936 | BF76: =-AF76/$G76 -> -414.52905 | BG76: =-AG76/$G76 -> -2033.6752 | BH76: =AK76/$G76 -> -533.67523 | BI76: =-AM76/$G76 -> -128.79167 | BJ76: =-AO76/$G76 -> -72.423077 | BK76: =-AP76/$G76 -> -220.99714 | BL76: =-AQ76/$G76 -> -30.840098 | BM76: =AR76/$G76 -> 41.13625 | BN76: =AS76/$G76 -> -744.37621 | BO76: =-AU76/$G76 -> -105.0585 | BP76: =AV76/$G76 -> -849.43472 | BQ76: =AX76/$G76 -> 58.520338 | BR76: =AY76/$G76 -> -685.85588
B77: MARZO | C77: ABRIL | D77: 177-2026B | E77: 50 | F77: 46132 | G77: 68.82 | H77: POTA ALAS CONGELADAS | I77: Alas | J77: 1-up | K77: Korea | L77: Busan | M77: TSUJINO | N77: Jose | O77: 1600 | P77: 110112 | Q77: 1482.2581 | R77: 8103 | S77: 102009 | T77: 3 | U77: ECO MARIN 26016N | V77: LIMG05567300 | W77: ONE LINE | Y77: 10006720 | AB77: =AI77-111688.22/2006.56-47.35 -> 1933.6327 | AC77: =IFERROR(INDEX('Costos Producción Febrero'!$G$34:$G$57,MATCH(Resumen!Y77,'Costos Producción Febrero'!$B$34:$B$57,0))*AB77*G77,0) -> 85391.761 | AD77: =IFERROR(INDEX('Costos Producción Febrero'!$H$34:$H$57,MATCH(Resumen!Y77,'Costos Producción Febrero'!$B$34:$B$57,0))*AB77*G77,0) -> 17961.073 | AE77: =IFERROR(INDEX('Costos Producción Febrero'!$I$34:$I$57,MATCH(Resumen!Y77,'Costos Producción Febrero'!$B$34:$B$57,0))*AB77*G77,0) -> 1243.4106 | AF77: =IFERROR(INDEX('Costos Producción Febrero'!$J$34:$J$57,MATCH(Resumen!Y77,'Costos Producción Febrero'!$B$34:$B$57,0))*AB77*G77,0) -> 28476.356 | AG77: =SUM(AC77:AF77) -> 133072.6 | AI77: 2036.6442 | AK77: =P77-AG77 -> -22960.601 | AL77: =AK77/P77 -> -0.20852042 | AM77: =R77 -> 8103 | AN77: =118461.136538461/5988.21*G77 -> 1361.4244 | AO77: =1883/26*G77 -> 4984.1562 | AP77: =SUM(AM77:AO77) -> 14448.581 | AQ77: =65076/2110.11*G77 -> 2122.4156 | AR77: =S77*0.03 -> 3060.27 | AS77: =AK77-AP77-AQ77+AR77 -> -36471.327 | AT77: =AS77/P77 -> -0.33122028 | AU77: =221685/2110.11*G77 -> 7230.1262 | AV77: =AS77-AU77 -> -43701.453 | AW77: =AV77/P77 -> -0.39688184 | AX77: =123484.35/2110.11*G77 -> 4027.3696 | AY77: =AS77+AX77 -> -32443.957 | AZ77: =AY77/P77 -> -0.29464506 | BB77: =P77/$G77 -> 1600 | BC77: =-AC77/$G77 -> -1240.7986 | BD77: =-AD77/$G77 -> -260.98624 | BE77: =-AE77/$G77 -> -18.067576 | BF77: =-AF77/$G77 -> -413.78024 | BG77: =-AG77/$G77 -> -1933.6327 | BH77: =AK77/$G77 -> -333.63268 | BI77: =-AM77/$G77 -> -117.74194 | BJ77: =-AO77/$G77 -> -72.423077 | BK77: =-AP77/$G77 -> -209.94741 | BL77: =-AQ77/$G77 -> -30.840098 | BM77: =AR77/$G77 -> 44.467742 | BN77: =AS77/$G77 -> -529.95244 | BO77: =-AU77/$G77 -> -105.0585 | BP77: =AV77/$G77 -> -635.01094 | BQ77: =AX77/$G77 -> 58.520338 | BR77: =AY77/$G77 -> -471.4321
B78: MARZO | C78: ABRIL | D78: 178-2026A | E78: 50 | F78: 46125 | G78: 26 | H78: POTA FILETE CONGELADO | I78: Filete | J78: 2-4 kg | K78: España | L78: Valencia | M78: OCEANUS FISH | N78: Ignacio / Ives | O78: 1400 | P78: 36400 | Q78: 1213.4615 | R78: 4850 | S78: 31550 | T78: 1 | U78: CAPE SPENCER 608N | V78: 93351271 | W78: HAPAG | Y78: 10005721 | AB78: =AI78-111688.22/2006.56-47.35 -> 2033.6752 | AC78: =IFERROR(INDEX('Costos Producción Febrero'!$G$34:$G$57,MATCH(Resumen!Y78,'Costos Producción Febrero'!$B$34:$B$57,0))*AB78*G78,0) -> 32111.902 | AD78: =IFERROR(INDEX('Costos Producción Febrero'!$H$34:$H$57,MATCH(Resumen!Y78,'Costos Producción Febrero'!$B$34:$B$57,0))*AB78*G78,0) -> 9409.454 | AE78: =IFERROR(INDEX('Costos Producción Febrero'!$I$34:$I$57,MATCH(Resumen!Y78,'Costos Producción Febrero'!$B$34:$B$57,0))*AB78*G78,0) -> 576.44433 | AF78: =IFERROR(INDEX('Costos Producción Febrero'!$J$34:$J$57,MATCH(Resumen!Y78,'Costos Producción Febrero'!$B$34:$B$57,0))*AB78*G78,0) -> 10777.755 | AG78: =SUM(AC78:AF78) -> 52875.556 | AI78: 2136.6868 | AK78: =P78-AG78 -> -16475.556 | AL78: =AK78/P78 -> -0.45262516 | AM78: =R78 -> 4850 | AN78: =118461.136538461/5988.21*G78 -> 514.34227 | AO78: =1883/26*G78 -> 1883 | AP78: =SUM(AM78:AO78) -> 7247.3423 | AQ78: =65076/2110.11*G78 -> 801.84256 | AR78: =S78*0.03 -> 946.5 | AS78: =AK78-AP78-AQ78+AR78 -> -23578.241 | AT78: =AS78/P78 -> -0.64775387 | AU78: =221685/2110.11*G78 -> 2731.5211 | AV78: =AS78-AU78 -> -26309.762 | AW78: =AV78/P78 -> -0.72279565 | AX78: =123484.35/2110.11*G78 -> 1521.5288 | AY78: =AS78+AX78 -> -22056.712 | AZ78: =AY78/P78 -> -0.60595363 | BB78: =P78/$G78 -> 1400 | BC78: =-AC78/$G78 -> -1235.0732 | BD78: =-AD78/$G78 -> -361.90208 | BE78: =-AE78/$G78 -> -22.170936 | BF78: =-AF78/$G78 -> -414.52905 | BG78: =-AG78/$G78 -> -2033.6752 | BH78: =AK78/$G78 -> -633.67523 | BI78: =-AM78/$G78 -> -186.53846 | BJ78: =-AO78/$G78 -> -72.423077 | BK78: =-AP78/$G78 -> -278.74393 | BL78: =-AQ78/$G78 -> -30.840098 | BM78: =AR78/$G78 -> 36.403846 | BN78: =AS78/$G78 -> -906.85541 | BO78: =-AU78/$G78 -> -105.0585 | BP78: =AV78/$G78 -> -1011.9139 | BQ78: =AX78/$G78 -> 58.520338 | BR78: =AY78/$G78 -> -848.33508
