Workbook

Sheet Gráficos
B3: PERU FROST - RESUMEN RESULTADOS CONGELADOS 2026 (MILES US$)
B4: Concepto | C4: 46023 | D4: 46054 | E4: 46082 | F4: 46113 | G4: Acum 2026
B5: TM Materia Prima | C5: =[2]Resumen!$D$4 -> 1877.215 | D5: =[2]Resumen!$D$5 -> 3149.786 | E5: =[2]Resumen!$D$6 -> 2255.518 | F5: =[2]Resumen!$D$7 -> 2853.189 | G5: =SUM(C5:F5) -> 10135.708
B6: TM Vendidas PT | C6: =TD!B7 -> 248 | D6: =TD!C7 -> 1634.3 | E6: =TD!D7 -> 1995.8 | F6: =TD!E7 -> 2110.11 | G6: =TD!F7 -> 1978.33
B7: Venta | C7: =TD!B8 -> 564615.28 | D7: =TD!C8 -> 2769824.5 | E7: =TD!D8 -> 3894171.3 | F7: =TD!E8 -> 4921538.6 | G7: =TD!F8 -> 5010204.8
B8: Utilidad Neta | C8: =TD!B16 -> -92104.402 | D8: =TD!C16 -> -484146.17 | E8: =TD!D16 -> -490402.73 | F8: =TD!E16 -> -52490.241 | G8: =TD!F16 -> 417065.74
B9: Margen Neto % | C9: =C8/C7 -> -0.16312772 | D9: =D8/D7 -> -0.17479309 | E9: =E8/E7 -> -0.1259325 | F9: =F8/F7 -> -0.010665413 | G9: =G8/G7 -> 0.083243253
B12: 1. RESULTADOS INTERNOS
B62: 2. BENCHMARK INDUSTRIA PERUANA DE CONGELADOS (VERITRADE)
B87: Top 15 Exportadores — Productos Congelados (Alas, Filete, Nuca, Tentáculo, Reproductor) | J87: Top 15 Exportadores — Productos Cocidos (Alas Cocidas, Filete Daruma)
B89: Nro | C89: Exportador | D89: Valor FOB (US$) | E89: TM | F89: Precio por TM | J89: Nro | K89: Exportador | L89: Valor FOB (US$) | M89: TM | N89: Precio por TM
B90: 1 | C90: Industrial Pesquera Santa Monica S.A. | D90: 12800672 | E90: 7371.2 | F90: 1737 | J90: 1 | K90: Costa Mira Sociedad Anonima Cerrada | L90: 9211788 | M90: 2579.8 | N90: 3571
B91: 2 | C91: Pesquera Hermanos Cordova S.A.C. | D91: 11792528 | E91: 7242.6 | F91: 1628 | J91: 2 | K91: KSL S.A.C. | L91: 5319083 | M91: 1670.5 | N91: 3184
B92: 3 | C92: Oceano Seafood S.A. | D92: 11724680 | E92: 6746.5 | F92: 1738 | J92: 3 | K92: Pacific Freezing Company S.A.C. | L92: 4286058 | M92: 1338 | N92: 3203
B93: 4 | C93: Productora Andina De Congelados S.R.L. | D93: 8847640 | E93: 5227.2 | F93: 1693 | J93: 4 | K93: Oceano Seafood S.A. | L93: 4050574 | M93: 1190.4 | N93: 3403
B94: 5 | C94: Costa Mira Sociedad Anonima Cerrada | D94: 8496998 | E94: 4421.2 | F94: 1922 | J94: 5 | K94: Frigosa Sociedad S.A.C. | L94: 3921103 | M94: 1215 | N94: 3227
B95: 6 | C95: Novaperu S.A.C. | D95: 6857126 | E95: 3973.8 | F95: 1726 | J95: 6 | K95: Dexim Srl | L95: 3883786 | M95: 1076.8 | N95: 3607
B96: 7 | C96: Peru Frost Sociedad Anonima Cerrada | D96: 6231879 | E96: 3981.4 | F96: 1565 | J96: 7 | K96: Inversiones Holding Peru Sociedad Anonim | L96: 2905633 | M96: 847.7 | N96: 3428
B97: 8 | C97: Esmeralda Corp S.A.C. | D97: 6229395 | E97: 3736 | F97: 1667 | J97: 8 | K97: Corporacion Pesquera Del Mar Sociedad An | L97: 2751416 | M97: 796 | N97: 3457
B98: 9 | C98: Proveedora De Productos Marinos Sociedad | D98: 6166547 | E98: 3730.3 | F98: 1653 | J98: 9 | K98: Mik Carpe S.A.C. | L98: 2475284 | M98: 735 | N98: 3368
B99: 10 | C99: Peruvian Sea Food S.A. | D99: 6164559 | E99: 3692.9 | F99: 1669 | J99: 10 | K99: Seafrost S.A.C. | L99: 2135285 | M99: 602.9 | N99: 3542
B100: 11 | C100: Pesquera Supercetus S.A.C. | D100: 5928869 | E100: 3562.1 | F100: 1664 | J100: 11 | K100: Pesquera Exalmar S.A.A. | L100: 1926814 | M100: 563.2 | N100: 3421
B101: 12 | C101: Transmarina Del Peru S.A.C. | D101: 5879029 | E101: 3591.3 | F101: 1637 | J101: 12 | K101: Refrigerados Fisholg & Hijos Sociedad An | L101: 1802223 | M101: 539.5 | N101: 3340
... B104: 15 | C104: Seafrost S.A.C. | D104: 5556358 | E104: 3119.3 | F104: 1781 | J104: 15 | K104: Industrial Pesquera Santa Monica S.A. | L104: 1603048 | M104: 475.7 | N104: 3370

Sheet TD
I1: 20575797 | J1: -20641652 | K1: =J1+I1 -> -65855.17 | L1: diferencia de tsujino
A2: ANÁLISIS DE RENTABILIDAD | K2: 72 | L2: toneladas
A4: EEFF PERU FROST (USD) | AM4: Enero | AN4: Febrero | AO4: Marzo | AP4: Abril | AQ4: Real | AR4: Budget
B5: Etiquetas de columna | L5: ANÁLISIS UNITARIO | X5: ANÁLISIS VÉRTICAL | AL5: Venta CFR | AM5: =B8/1000 -> 564.61528 | AN5: =C8/1000 -> 2769.8245 | AO5: =D8/1000 -> 3894.1713 | AP5: =E8/1000 -> 4921.5386 | AQ5: =F8/1000 -> 5010.2047 | AR5: =H8/1000 -> 1589.3806
A6: Valores | B6: ENERO | C6: FEBRERO | D6: MARZO | E6: ABRIL | F6: MAYO | G6: JUNIO | H6: JULIO | I6: Total general | L6: NOMBRE | M6: ENERO | N6: FEBRERO | O6: MARZO | P6: ABRIL | Q6: MAYO | R6: JUNIO | S6: JULIO | T6: TOTAL | X6: NOMBRE | Y6: ENERO | Z6: FEBRERO | AA6: MARZO | AB6: ABRIL | AC6: MAYO | AD6: JUNIO | AE6: JULIO | AF6: TOTAL | AL6: Utilidad Neta | AM6: =B16/1000 -> -92.104402 | AN6: =C16/1000 -> -484.14617 | AO6: =D16/1000 -> -490.40273 | AP6: =E16/1000 -> -52.490241 | AQ6: =F16/1000 -> 417.06574 | AR6: =H16/1000 -> 91.312258
A7: Suma de Cantidad | B7: 248 | C7: 1634.3 | D7: 1995.8 | E7: 2110.11 | F7: 1978.33 | G7: 1131.78 | H7: 780.905 | I7: 9879.225 | J7: =J8/GETPIVOTDATA("Suma de Cantidad ",$A$5) -> 2221.181
A8: Suma de VALOR CFR | B8: 564615.28 | C8: 2769824.5 | D8: 3894171.3 | E8: 4921538.6 | F8: 5010204.8 | G8: 3415442.3 | H8: 1589380.6 | I8: 22165177 | J8: =GETPIVOTDATA("Suma de VALOR CFR",$A$5)-GETPIVOTDATA("VALOR CFR",$A$25,"Producto","RESIDUOS DE POTA") -> 21943547 | L8: Suma de VALOR CFR | M8: =B8/B$7 -> 2276.6745 | N8: =C8/C$7 -> 1694.8079 | O8: =D8/D$7 -> 1951.1831 | P8: =E8/E$7 -> 2332.3611 | Q8: =F8/F$7 -> 2532.5425 | R8: =G8/G$7 -> 3017.7617 | S8: =H8/H$7 -> 2035.306 | T8: =I8/I$7 -> 2243.615 | X8: Suma de VALOR CFR | Y8: =B8/B$8 -> 1 | Z8: =C8/C$8 -> 1 | AA8: =D8/D$8 -> 1 | AB8: =E8/E$8 -> 1 | AC8: =F8/F$8 -> 1 | AD8: =G8/G$8 -> 1 | AE8: =H8/H$8 -> 1 | AF8: =I8/I$8 -> 1
A9: Suma de COSTO VENTAS | B9: 447259.37 | C9: 2896198.1 | D9: 3759147.4 | E9: 4268330.6 | F9: 4074597.6 | G9: 2480210.9 | H9: 1146770.6 | I9: 19072515 | L9: Suma de COSTO VENTAS | M9: =B9/B$7 -> 1803.4652 | N9: =C9/C$7 -> 1772.1337 | O9: =D9/D$7 -> 1883.5291 | P9: =E9/E$7 -> 2022.8 | Q9: =F9/F$7 -> 2059.6147 | R9: =G9/G$7 -> 2191.4249 | S9: =H9/H$7 -> 1468.5149 | T9: =I9/I$7 -> 1930.5679 | X9: Suma de COSTO VENTAS | Y9: =B9/B$8 -> 0.79214889 | Z9: =C9/C$8 -> 1.0456251 | AA9: =D9/D$8 -> 0.96532665 | AB9: =E9/E$8 -> 0.86727565 | AC9: =F9/F$8 -> 0.8132597 | AD9: =G9/G$8 -> 0.72617561 | AE9: =H9/H$8 -> 0.72152046 | AF9: =I9/I$8 -> 0.860472 | AT9: Resumen de Precios por TM Peru Frost vs Mercado
A10: Suma de UTILIDAD BRUTA | B10: 117355.91 | C10: -126373.58 | D10: 135023.96 | E10: 653208 | F10: 935607.12 | G10: 935231.4 | H10: 442609.97 | I10: 3092662.8 | L10: Suma de UTILIDAD BRUTA | M10: =B10/B$7 -> 473.20932 | N10: =C10/C$7 -> -77.325817 | O10: =D10/D$7 -> 67.654053 | P10: =E10/E$7 -> 309.56111 | Q10: =F10/F$7 -> 472.92773 | R10: =G10/G$7 -> 826.33674 | S10: =H10/H$7 -> 566.79106 | T10: =I10/I$7 -> 313.0471 | X10: Suma de UTILIDAD BRUTA | Y10: =B10/B$8 -> 0.20785111 | Z10: =C10/C$8 -> -0.045625123 | AA10: =D10/D$8 -> 0.034673348 | AB10: =E10/E$8 -> 0.13272435 | AC10: =F10/F$8 -> 0.1867403 | AD10: =G10/G$8 -> 0.27382439 | AE10: =H10/H$8 -> 0.27847954 | AF10: =I10/I$8 -> 0.139528 | AL10: Acum Abril venta y rentabilidad por producto
A11: Suma de GASTO VENTAS | B11: 42671.034 | C11: 228377.82 | D11: 500943.85 | E11: 557032.39 | F11: 455053.16 | G11: 200714.48 | H11: 162303.3 | I11: 2147096 | L11: Suma de GASTO VENTAS | M11: =B11/B$7 -> 172.06062 | N11: =C11/C$7 -> 139.74045 | O11: =D11/D$7 -> 250.99902 | P11: =E11/E$7 -> 263.98263 | Q11: =F11/F$7 -> 230.01883 | R11: =G11/G$7 -> 177.34408 | S11: =H11/H$7 -> 207.84 | T11: =I11/I$7 -> 217.33446 | X11: Suma de GASTO VENTAS | Y11: =B11/B$8 -> 0.075575415 | Z11: =C11/C$8 -> 0.082452091 | AA11: =D11/D$8 -> 0.1286394 | AB11: =E11/E$8 -> 0.11318257 | AC11: =F11/F$8 -> 0.090825262 | AD11: =G11/G$8 -> 0.058766761 | AE11: =H11/H$8 -> 0.10211732 | AF11: =I11/I$8 -> 0.096867984 | AM11: Venta CFR | AN11: Utilidad Neta | AT11: PRODUCTO | AU11: PERU FROST | AV11: INDUSTRIA PERUANA
A12: Suma de GASTO ADM | B12: 50659 | C12: 56604 | D12: 78579 | E12: 65076 | F12: 40133.169 | G12: 87732.79 | H12: 78579 | I12: 457362.96 | L12: Suma de GASTO ADM | M12: =B12/B$7 -> 204.27016 | N12: =C12/C$7 -> 34.635012 | O12: =D12/D$7 -> 39.372182 | P12: =E12/E$7 -> 30.840098 | Q12: =F12/F$7 -> 20.286387 | R12: =G12/G$7 -> 77.51753 | S12: =H12/H$7 -> 100.62556 | T12: =I12/I$7 -> 46.295429 | X12: Suma de GASTO ADM | Y12: =B12/B$8 -> 0.089723041 | Z12: =C12/C$8 -> 0.020435952 | AA12: =D12/D$8 -> 0.020178619 | AB12: =E12/E$8 -> 0.013222694 | AC12: =F12/F$8 -> 0.0080102851 | AD12: =G12/G$8 -> 0.025687095 | AE12: =H12/H$8 -> 0.049440014 | AF12: =I12/I$8 -> 0.020634302 | AL12: FILETE CONGELADO | AM12: 3148.23 | AN12: -1138.4306 | AT12: FILETE CONGELADO | AU12: 1323 | AV12: 1525
A13: Suma de DRAWBACK | B13: 15120.72 | C13: 75707.235 | D13: 108569.16 | E13: 138095.15 | F13: 143706.68 | G13: 97402.26 | H13: 44057.58 | I13: 622658.78 | L13: Suma de DRAWBACK | M13: =B13/B$7 -> 60.970645 | N13: =C13/C$7 -> 46.323952 | O13: =D13/D$7 -> 54.398817 | P13: =E13/E$7 -> 65.444526 | Q13: =F13/F$7 -> 72.640396 | R13: =G13/G$7 -> 86.061125 | S13: =H13/H$7 -> 56.418617 | T13: =I13/I$7 -> 63.027087 | X13: Suma de DRAWBACK | Y13: =B13/B$8 -> 0.026780572 | Z13: =C13/C$8 -> 0.027332864 | AA13: =D13/D$8 -> 0.027879913 | AB13: =E13/E$8 -> 0.028059345 | AC13: =F13/F$8 -> 0.028682795 | AD13: =G13/G$8 -> 0.028518198 | AE13: =H13/H$8 -> 0.027719968 | AF13: =I13/I$8 -> 0.028091757 | AL13: REJOS CONGELADOS | AM13: 2631.849 | AN13: 311.25595 | AT13: FILETE DARUMA | AU13: 3292 | AV13: 3417
A14: Suma de UTILIDAD OPERATIVA | B14: 39146.598 | C14: -335648.17 | D14: -335929.73 | E14: 169194.76 | F14: 584127.46 | G14: 744186.39 | H14: 245785.26 | I14: 1110862.6 | L14: Suma de UTILIDAD OPERATIVA | M14: =B14/B$7 -> 157.84919 | N14: =C14/C$7 -> -205.37733 | O14: =D14/D$7 -> -168.31834 | P14: =E14/E$7 -> 80.182909 | Q14: =F14/F$7 -> 295.2629 | R14: =G14/G$7 -> 657.53626 | S14: =H14/H$7 -> 314.74412 | T14: =I14/I$7 -> 112.4443 | X14: Suma de UTILIDAD OPERATIVA | Y14: =B14/B$8 -> 0.069333225 | Z14: =C14/C$8 -> -0.1211803 | AA14: =D14/D$8 -> -0.086264755 | AB14: =E14/E$8 -> 0.034378428 | AC14: =F14/F$8 -> 0.11658754 | AD14: =G14/G$8 -> 0.21788873 | AE14: =H14/H$8 -> 0.15464216 | AF14: =I14/I$8 -> 0.050117468 | AL14: ALAS CONGELADAS | AM14: 2273.427 | AN14: -451.32788 | AT14: REPRODUCTOR | AU14: 2724 | AV14: 2704
A15: Suma de GASTO FINANCIERO | B15: 131251 | C15: 148498 | D15: 154473 | E15: 221685 | F15: 167061.72 | G15: 121364.63 | H15: 154473 | I15: 1098806.4 | L15: Suma de GASTO FINANCIERO | M15: =B15/B$7 -> 529.2379 | N15: =C15/C$7 -> 90.863367 | O15: =D15/D$7 -> 77.399038 | P15: =E15/E$7 -> 105.0585 | Q15: =F15/F$7 -> 84.445831 | R15: =G15/G$7 -> 107.23341 | S15: =H15/H$7 -> 197.81279 | T15: =I15/I$7 -> 111.22394 | X15: Suma de GASTO FINANCIERO | Y15: =B15/B$8 -> 0.23246094 | Z15: =C15/C$8 -> 0.053612783 | AA15: =D15/D$8 -> 0.039667746 | AB15: =E15/E$8 -> 0.045043841 | AC15: =F15/F$8 -> 0.03334429 | AD15: =G15/G$8 -> 0.035534089 | AE15: =H15/H$8 -> 0.097190691 | AF15: =I15/I$8 -> 0.049573542 | AL15: FILETE DARUMA | AM15: 1927.8 | AN15: 513.07693 | AT15: NUCA | AU15: 1123 | AV15: 1171
A16: Suma de UTILIDAD NETA | B16: -92104.402 | C16: -484146.17 | D16: -490402.73 | E16: -52490.241 | F16: 417065.74 | G16: 622821.76 | H16: 91312.258 | I16: 12056.214 | L16: Suma de UTILIDAD NETA | M16: =B16/B$7 -> -371.38872 | N16: =C16/C$7 -> -296.2407 | O16: =D16/D$7 -> -245.71737 | P16: =E16/E$7 -> -24.875595 | Q16: =F16/F$7 -> 210.81707 | R16: =G16/G$7 -> 550.30285 | S16: =H16/H$7 -> 116.93133 | T16: =I16/I$7 -> 1.2203603 | X16: Suma de UTILIDAD NETA | Y16: =B16/B$8 -> -0.16312772 | Z16: =C16/C$8 -> -0.17479309 | AA16: =D16/D$8 -> -0.1259325 | AB16: =E16/E$8 -> -0.010665413 | AC16: =F16/F$8 -> 0.083243253 | AD16: =G16/G$8 -> 0.18235464 | AE16: =H16/H$8 -> 0.057451474 | AF16: =I16/I$8 -> 0.0005439259 | AL16: REPRODUCTORES | AM16: 599.405 | AN16: 126.98725 | AT16: ALAS COCIDAS | AU16: 3240 | AV16: 3318
A17: Suma de DEPRECIACIÓN | B17: 123844.28 | C17: 123844.28 | D17: 123844.28 | E17: 123844.28 | F17: 123844.28 | G17: 123844.28 | H17: 123843.49 | I17: 866909.19 | L17: Suma de DEPRECIACIÓN | M17: =B17/B$7 -> 499.37211 | N17: =C17/C$7 -> 75.778182 | O17: =D17/D$7 -> 62.052452 | P17: =E17/E$7 -> 58.690913 | Q17: =F17/F$7 -> 62.600417 | R17: =G17/G$7 -> 109.42434 | S17: =H17/H$7 -> 158.5897 | T17: =I17/I$7 -> 87.750728 | X17: Suma de DEPRECIACIÓN | Y17: =B17/B$8 -> 0.21934278 | Z17: =C17/C$8 -> 0.04471196 | AA17: =D17/D$8 -> 0.031802474 | AB17: =E17/E$8 -> 0.025163733 | AC17: =F17/F$8 -> 0.024718408 | AD17: =G17/G$8 -> 0.036260101 | AE17: =H17/H$8 -> 0.077919341 | AF17: =I17/I$8 -> 0.039111313 | AL17: NUCAS | AM17: 514.83 | AN17: -431.34411 | AT17: ALAS CONGELADAS | AU17: 1509 | AV17: 1579
A18: Suma de EBITDA | B18: 162990.88 | C18: -211803.89 | D18: -212085.45 | E18: 293039.04 | F18: 707971.75 | G18: 868030.67 | H18: 369628.75 | I18: 1977771.8 | L18: Suma de EBITDA | M18: =B18/B$7 -> 657.2213 | N18: =C18/C$7 -> -129.59915 | O18: =D18/D$7 -> -106.26588 | P18: =E18/E$7 -> 138.87382 | Q18: =F18/F$7 -> 357.86332 | R18: =G18/G$7 -> 766.9606 | S18: =H18/H$7 -> 473.33382 | T18: =I18/I$7 -> 200.19503 | X18: Suma de EBITDA | Y18: =B18/B$8 -> 0.288676 | Z18: =C18/C$8 -> -0.076468342 | AA18: =D18/D$8 -> -0.05446228 | AB18: =E18/E$8 -> 0.059542161 | AC18: =F18/F$8 -> 0.14130595 | AD18: =G18/G$8 -> 0.25414883 | AE18: =H18/H$8 -> 0.23256151 | AF18: =I18/I$8 -> 0.089228781 | AL18: ALAS COCIDAS | AM18: 384.2577 | AN18: 138.02447 | AT18: TENTACULO | AU18: 2290 | AV18: 2288
AL19: OTROS | AM19: =SUM(AM20:AM22) -> 322.51689 | AN19: =SUM(AN20:AN22) -> 91.219795
AL20: POTA CONOS | AM20: 231.72 | AN20: 0.42290479
A22: ANÁLISIS POR PRODUCTO | AL22: RESIDUOS DE POTA | AM22: 90.79689 | AN22: 90.79689 | AX22: 0.0634
AX23: 0.0478
A24: RANKING DE VENTAS (USD) | L24: UTILIDAD NETA (USD) | X24: EBITDA (USD) | AL24: Acum Abril venta y rentabilidad por cliente | AX24: 0.0459
A25: Suma de VALOR CFR | B25: Etiquetas de columna | L25: Suma de UTILIDAD NETA | M25: Etiquetas de columna | X25: Suma de EBITDA | Y25: Etiquetas de columna | AM25: Venta CFR | AN25: Utilidad Neta | AX25: 0.0371 | BB25: Suma de Cantidad | BC25: Etiquetas de columna | BG25: Suma de VALOR CFR | BH25: Etiquetas de columna
A26: Etiquetas de fila | B26: ENERO | C26: FEBRERO | D26: MARZO | E26: ABRIL | F26: MAYO | G26: JUNIO | H26: JULIO | I26: Total general | J26: % | L26: Etiquetas de fila | M26: ENERO | N26: FEBRERO | O26: MARZO | P26: ABRIL | Q26: MAYO | R26: JUNIO | S26: JULIO | T26: Total general | U26: MG | X26: Etiquetas de fila | Y26: ENERO | Z26: FEBRERO | AA26: MARZO | AB26: ABRIL | AC26: MAYO | AD26: JUNIO | AE26: JULIO | AF26: Total general | AG26: MG | AL26: TSUJINO | AM26: 2790.273 | AN26: -709.0403 | AX26: 0.0337 | BB26: Etiquetas de fila | BC26: FEBRERO | BD26: MARZO | BE26: Total general | BG26: Etiquetas de fila | BH26: FEBRERO | BI26: MARZO | BJ26: Total general | BK26: precio | BL26: precio mayo | BM26: variación | BN26: valor adicional
A27: POTA REJOS CONGELADOS | B27: 149248 | C27: 532695 | D27: 779600 | E27: 1170306 | F27: 1105650 | G27: 722550 | H27: 437010 | I27: 4897059 | J27: =I27/$I$43 -> #DIV/0! | L27: POTA REJOS CONGELADOS | M27: -5420.9051 | N27: 106971.82 | O27: 68462.268 | P27: 94521.111 | Q27: 338985.51 | R27: 211762.61 | S27: 111727.25 | T27: 927009.66 | U27: =T27/I27 -> 0.18929926 | X27: POTA REJOS CONGELADOS | Y27: 54197.331 | Z27: 141799.9 | AA27: 114620.71 | AB27: 169672.27 | AC27: 394568.99 | AD27: 269610.23 | AE27: 169464.45 | AF27: 1313933.9 | AG27: =AF27/I27 -> 0.26831081 | AL27: LONGKOU JIABAO AQUATIC | AM27: 1406.7 | AN27: 394.79634 | AX27: 0.0337 | BB27: POTA REJOS CONGELADOS | BC27: 209 | BD27: 331 | BE27: 540 | BG27: POTA REJOS CONGELADOS | BH27: 532695 | BI27: 779600 | BJ27: 1312295 | BK27: =BJ27/BE27 -> 2430.1759 | BL27: =BL47 -> 2925 | BM27: =BL27-BK27 -> 494.82407 | BN27: =BM27*BE27 -> 267205
A28: POTA FILETE CONGELADO | B28: 94800 | C28: 1147500 | D28: 430960 | E28: 1471690 | F28: 1041860 | G28: 245195 | H28: 78800 | I28: 4510805 | J28: =I28/$I$43 -> #DIV/0! | L28: POTA FILETE CONGELADO | M28: -36616.253 | N28: -502314.03 | O28: -260749.39 | P28: -498233.16 | Q28: -130347.09 | R28: -33898.989 | S28: -9786.388 | T28: -1471945.3 | U28: =T28/I28 -> -0.32631544 | X28: POTA FILETE CONGELADO | Y28: 12757.028 | Z28: -367334.37 | AA28: -219890.1 | AB28: -365776.26 | AC28: -55824.052 | AD28: -5950.1391 | AE28: 3756.9068 | AF28: -998261 | AG28: =AF28/I28 -> -0.2213044 | AL28: KULALIA | AM28: 1378.9217 | AN28: 101.0003 | AX28: 0.0333 | BB28: POTA FILETE CONGELADO | BC28: 810 | BD28: 293 | BE28: 1103 | BG28: POTA FILETE CONGELADO | BH28: 1147500 | BI28: 430960 | BJ28: 1578460 | BK28: =BJ28/BE28 -> 1431.0607 | BL28: =BL45 -> 2055.7616 | BM28: =BL28-BK28 -> 624.7009 | BN28: =BM28*BE28 -> 689045.09
A29: POTA FILETE DARUMA | C29: 91800 | D29: 1004400 | E29: 831600 | F29: 1142100 | G29: 1273050 | I29: 4342950 | J29: =I29/$I$43 -> #DIV/0! | L29: POTA FILETE DARUMA | N29: 28158.374 | O29: 209162.38 | P29: 240368.96 | Q29: 88911.734 | R29: 183241.93 | T29: 749843.38 | U29: =T29/I29 -> 0.17265761 | X29: POTA FILETE DARUMA | Z29: 32657.696 | AA29: 254344.67 | AB29: 275738.84 | AC29: 132584.47 | AD29: 253439.04 | AF29: 948764.71 | AG29: =AF29/I29 -> 0.21846089 | AL29: AVANCE GROUP | AM29: 1097.2 | AN29: -468.13754 | AX29: 0.0333 | BB29: POTA FILETE DARUMA | BC29: 27 | BD29: 324 | BE29: 351 | BG29: POTA FILETE DARUMA | BH29: 91800 | BI29: 1004400 | BJ29: 1096200 | BK29: =BJ29/BE29 -> 3123.0769 | BL29: =BL52 -> 3845.4545 | BM29: =BL29-BK29 -> 722.37762 | BN29: =BM29*BE29 -> 253554.55
A30: POTA ALAS CONGELADAS | B30: 135915 | C30: 710550 | D30: 768480 | E30: 656562 | F30: 591300 | G30: 251204 | H30: 94500 | I30: 3208511 | J30: =I30/$I$43 -> #DIV/0! | L30: POTA ALAS CONGELADAS | M30: -50223.333 | N30: -182032.49 | O30: -219374.82 | P30: -130881.72 | Q30: -62443.666 | R30: -1295.0638 | S30: -22774.894 | T30: -669025.99 | U30: =T30/I30 -> -0.20851603 | X30: POTA ALAS CONGELADAS | Y30: 23836.588 | Z30: -105494.02 | AA30: -152047.64 | AB30: -74614.146 | AC30: -18770.93 | AD30: 25353.84 | AE30: -3529.1597 | AF30: -305265.47 | AG30: =AF30/I30 -> -0.095142411 | AL30: FOOD & BEVERAGES TRADERS | AM30: 935.406 | AN30: -74.238541 | AX30: 0.032 | BB30: POTA ALAS CONGELADAS | BC30: 459.3 | BD30: 482.8 | BE30: 942.1 | BG30: POTA ALAS CONGELADAS | BH30: 710550 | BI30: 768480 | BJ30: 1479030 | BK30: =BJ30/BE30 -> 1569.9289 | BL30: =BL46 -> 1990.9091 | BM30: =BL30-BK30 -> 420.98021 | BN30: =BM30*BE30 -> 396605.45
A31: POTA ALAS COCIDAS | D31: 177221.7 | E31: 207036 | F31: 417358 | G31: 668601 | I31: 1470216.7 | J31: =I31/$I$43 -> #DIV/0! | L31: POTA ALAS COCIDAS | O31: 42400.96 | P31: 33173.727 | Q31: 80533.149 | R31: 196924.08 | T31: 353031.92 | U31: =T31/I31 -> 0.24012237 | X31: POTA ALAS COCIDAS | AA31: 49931.34 | AB31: 41868.821 | AC31: 96308.271 | AD31: 231866.65 | AF31: 419975.08 | AG31: =AF31/I31 -> 0.28565522 | AL31: Qingdao Haiyujia | AM31: 595.782 | AN31: 101.96621 | AX31: 0.0318 | BB31: POTA ALAS COCIDAS | BD31: 54 | BE31: 54 | BG31: POTA ALAS COCIDAS | BI31: 177221.7 | BJ31: 177221.7 | BK31: =BJ31/BE31 -> 3281.8833 | BL31: =BL53 -> 3890.3617 | BM31: =BL31-BK31 -> 608.47834 | BN31: =BM31*BE31 -> 32857.83
A32: POTA REPRODUCTORES | B32: 74064 | C32: 77585 | D32: 139200 | E32: 308556 | F32: 154700 | G32: 70980 | H32: 214416 | I32: 1039501 | J32: =I32/$I$43 -> #DIV/0! | L32: POTA REPRODUCTORES | M32: 4890.763 | N32: 23262.951 | O32: 29982.789 | P32: 61843.08 | Q32: 47178.889 | R32: 23179.219 | S32: 57701.204 | T32: 248038.89 | U32: =T32/I32 -> 0.23861342 | X32: POTA REPRODUCTORES | Y32: 31634.623 | Z32: 27762.272 | AA32: 37094.815 | AB32: 78840.269 | AC32: 54825.294 | AD32: 28812.32 | AE32: 85857.001 | AF32: 344826.59 | AG32: =AF32/I32 -> 0.3317232 | AL32: Longkou Yunfeng Aquatic Food | AM32: 575.1 | AN32: -44.789183 | AX32: 0.0316 | BB32: POTA REPRODUCTORES | BC32: 27 | BD32: 51 | BE32: 78 | BG32: POTA REPRODUCTORES | BH32: 77585 | BI32: 139200 | BJ32: 216785 | BK32: =BJ32/BE32 -> 2779.2949 | BL32: =BL48 -> 2975 | BM32: =BL32-BK32 -> 195.70513 | BN32: =BM32*BE32 -> 15265
A33: POTA NUCAS | B33: 35874 | C33: 23456 | D33: 455500 | F33: 221025 | G33: 59625 | H33: 201300 | I33: 996780 | J33: =I33/$I$43 -> #DIV/0! | L33: POTA NUCAS | M33: -19244.525 | N33: -6321.5029 | O33: -407078.31 | Q33: -144985.3 | R33: -29502.695 | S33: -99499.18 | T33: -706631.52 | U33: =T33/I33 -> -0.70891422 | X33: POTA NUCAS | Y33: 1368.8194 | Z33: -3988.5212 | AA33: -353389.49 | AC33: -118075.84 | AD33: -18994.794 | AE33: -45326.001 | AF33: -538405.82 | AG33: =AF33/I33 -> -0.54014509 | AL33: OTROS | AM33: =SUM(AM34:AM51) -> 2863.8454 | AN33: =SUM(AN34:AN51) -> -19.037084 | AX33: 0.0302 | BB33: POTA NUCAS | BC33: 14 | BD33: 385 | BE33: 399 | BG33: POTA NUCAS | BH33: 23456 | BI33: 455500 | BJ33: 478956 | BK33: =BJ33/BE33 -> 1200.391 | BL33: =BL49 -> 1207.7869 | BM33: =BL33-BK33 -> 7.3959078 | BN33: =BM33*BE33 -> 2950.9672
A34: POTA CONOS | B34: 50400 | C34: 69000 | D34: 76800 | E34: 35520 | F34: 43200 | G34: 46018 | H34: 86400 | I34: 407338 | J34: =I34/$I$43 -> #DIV/0! | L34: POTA CONOS | M34: -9804.429 | N34: 15489.988 | O34: -6150.1256 | P34: -10246.326 | Q34: 2027.9024 | R34: 4450.8385 | S34: -4175.4894 | T34: -8407.641 | U34: =T34/I34 -> -0.020640453 | X34: POTA CONOS | Y34: 14882.211 | Z34: 21155.801 | AA34: 543.54588 | AB34: -6611.0886 | AC34: 5557.0123 | AD34: 10300.598 | AE34: 15070.245 | AF34: 60898.325 | AG34: =AF34/I34 -> 0.14950318 | AL34: OVERSEA | AM34: 354.595 | AN34: 86.215827 | AX34: 0.03 | BB34: POTA CONOS | BC34: 34 | BD34: 48 | BE34: 82 | BG34: POTA CONOS | BH34: 69000 | BI34: 76800 | BJ34: 145800 | BK34: =BJ34/BE34 -> 1778.0488 | BL34: =BL55 -> 1800 | BM34: =BL34-BK34 -> 21.95122 | BN34: =BM34*BE34 -> 1800
A35: POTA RECORTES COCIDOS | E35: 67500 | F35: 126786 | H35: 136350 | I35: 330636 | J35: =I35/$I$43 -> #DIV/0! | L35: POTA RECORTES COCIDOS | P35: 10368.202 | Q35: 110306.03 | S35: 40811.702 | T35: 161485.94 | U35: =T35/I35 -> 0.48841003 | X35: POTA RECORTES COCIDOS | AB35: 14789.436 | AC35: 118246.53 | AE35: 60057.437 | AF35: 193093.4 | AG35: =AF35/I35 -> 0.58400599 | AL35: Pesciro Asia International LTD. | AM35: 352.35 | AN35: -117.23253 | BB35: POTA TELILLA PRECOCIDA | BC35: 27 | BE35: 27 | BG35: POTA TELILLA PRECOCIDA | BH35: 38606.25 | BJ35: 38606.25 | BK35: =BJ35/BE35 -> 1429.8611 | BL35: =BL57 -> 2050 | BM35: =BL35-BK35 -> 620.13889 | BN35: =BM35*BE35 -> 16743.75
A36: POTA TELILLA PRECOCIDA | C36: 38606.25 | E36: 52200 | F36: 53812.5 | H36: 127848 | I36: 272466.75 | J36: =I36/$I$43 -> #DIV/0! | L36: POTA TELILLA PRECOCIDA | N36: -3693.6397 | P36: 43644.778 | Q36: 46854.792 | S36: -10045.752 | T36: 76760.179 | U36: =T36/I36 -> 0.2817231 | X36: POTA TELILLA PRECOCIDA | Z36: 805.68215 | AB36: 47918.638 | AC36: 50714.756 | AE36: 18432.589 | AF36: 117871.67 | AG36: =AF36/I36 -> 0.43260936 | AL36: OCEANUS FISH | AM36: 340.564 | AN36: -36.175426 | BB36: POTA MEMBRANA PRECOCIDA | BC36: 27 | BD36: 27 | BE36: 54 | BG36: POTA MEMBRANA PRECOCIDA | BH36: 38606.25 | BI36: 35553 | BJ36: 74159.25 | BK36: =BJ36/BE36 -> 1373.3194 | BL36: =BK58 -> 2000 | BM36: =BL36-BK36 -> 626.68056 | BN36: =BM36*BE36 -> 33840.75 | BQ36: venta | BR36: utilidad | BS36: margen neto
A37: POTA MEMBRANA PRECOCIDA | C37: 38606.25 | D37: 35553 | E37: 52500 | H37: 186300 | I37: 312959.25 | J37: =I37/$I$43 -> #DIV/0! | L37: POTA MEMBRANA PRECOCIDA | N37: -3693.6397 | O37: 26484.907 | P37: 43914.109 | S37: 897.19774 | T37: 67602.574 | U37: =T37/I37 -> 0.21601079 | X37: POTA MEMBRANA PRECOCIDA | Z37: 805.68215 | AA37: 30250.097 | AB37: 48212.531 | AE37: 39388.667 | AF37: 118656.98 | AG37: =AF37/I37 -> 0.37914514 | AL37: LONGKOU BOHAI | AM37: 334.8 | AN37: 61.759822 | BB37: RESIDUOS DE POTA | BC37: 0 | BD37: 0 | BE37: 0 | BG37: RESIDUOS DE POTA | BH37: 40026 | BI37: 26456.61 | BJ37: 66482.61 | BK37: =BJ37/BE37 -> #DIV/0! | BP37: feb-mar actual | BQ37: =GETPIVOTDATA("VALOR CFR",$BG$25) -> 6663995.8 | BR37: =GETPIVOTDATA("UTILIDAD NETA",$BB$44) -> -974548.9 | BS37: =BR37/BQ37 -> -0.14624092
A38: POTA LABIOS CONGELADOS | F38: 34720 | G38: 35224 | I38: 69944 | J38: =I38/$I$43 -> #DIV/0! | L38: POTA LABIOS CONGELADOS | Q38: 24875.591 | R38: 24964.528 | T38: 49840.119 | U38: =T38/I38 -> 0.71257175 | X38: POTA LABIOS CONGELADOS | AC38: 28698.793 | AD38: 30597.63 | AF38: 59296.423 | AG38: =AF38/I38 -> 0.84776997 | AL38: GLOBAL OCEAN | AM38: 285.485 | AN38: 31.414281 | BB38: Total general | BC38: 1634.3 | BD38: 1995.8 | BE38: 3630.1 | BG38: Total general | BH38: 2769824.5 | BI38: 3894171.3 | BJ38: 6663995.8 | BK38: =BJ38/BE38 -> 1835.7609 | BN38: =SUM(BN27:BN37) -> 1709868.4 | BP38: feb-mar esperando | BQ38: =GETPIVOTDATA("VALOR CFR",$BG$25)+BN38 -> 8373864.2 | BR38: =BN38+GETPIVOTDATA("UTILIDAD NETA",$BB$44)-BR41 -> 696496.64 | BS38: =BR38/BQ38 -> 0.083175058
A39: POTA TUBOALETA | F39: 54080 | I39: 54080 | J39: =I39/$I$43 -> #DIV/0! | L39: POTA TUBOALETA | Q39: -8445.056 | T39: -8445.056 | U39: =T39/I39 -> -0.15615858 | X39: POTA TUBOALETA | AC39: -4474.8073 | AF39: -4474.8073 | AG39: =AF39/I39 -> -0.082744217 | AL39: DAIRECK S.A. | AM39: 280.782 | AN39: -291.00909 | BQ39: =BQ38-BQ37 -> 1709868.4 | BR39: =BR38-BR37 -> 1671045.5 | BS39: =BS38-BS37 -> 0.22941598
A40: POTA SUCKERS CONGELADO | E40: 30300 | I40: 30300 | J40: =I40/$I$43 -> #DIV/0! | L40: POTA SUCKERS CONGELADO | P40: 21268.427 | T40: 21268.427 | U40: =T40/I40 -> 0.70192828 | X40: POTA SUCKERS CONGELADO | AB40: 25231.163 | AF40: 25231.163 | AG40: =AF40/I40 -> 0.83271164 | AL40: YANTAI TAIXI FOODSTUFF | AM40: 279.504 | AN40: 19.044143
A41: RESIDUOS DE POTA | B41: 24314.28 | C41: 40026 | D41: 26456.61 | E41: 37768.57 | F41: 23613.25 | G41: 42995.3 | H41: 26456.61 | I41: 221630.62 | J41: =I41/$I$43 -> #DIV/0! | L41: RESIDUOS DE POTA | M41: 24314.28 | N41: 40026 | O41: 26456.61 | P41: 37768.57 | Q41: 23613.25 | R41: 42995.3 | S41: 26456.61 | T41: 221630.62 | U41: =T41/I41 -> 1 | X41: RESIDUOS DE POTA | Y41: 24314.28 | Z41: 40026 | AA41: 26456.61 | AB41: 37768.57 | AC41: 23613.25 | AD41: 42995.3 | AE41: 26456.61 | AF41: 221630.62 | AG41: =AF41/I41 -> 1 | BR41: =GETPIVOTDATA("COSTO VENTAS",$BB$60)*7%/12 -> 38822.848
A42: Total general | B42: 564615.28 | C42: 2769824.5 | D42: 3894171.3 | E42: 4921538.6 | F42: 5010204.8 | G42: 3415442.3 | H42: 1589380.6 | I42: 22165177 | J42: =I42/$I$43 -> #DIV/0! | L42: Total general | M42: -92104.402 | N42: -484146.17 | O42: -490402.73 | P42: -52490.241 | Q42: 417065.74 | R42: 622821.76 | S42: 91312.258 | T42: 12056.214 | U42: =T42/I42 -> 0.0005439259 | X42: Total general | Y42: 162990.88 | Z42: -211803.89 | AA42: -212085.45 | AB42: 293039.04 | AC42: 707971.75 | AD42: 868030.67 | AE42: 369628.75 | AF42: 1977771.8 | AG42: =AF42/I42 -> 0.089228781
J43: =I43/$I$43 -> #DIV/0! | U43: =T43/I43 -> #DIV/0! | AG43: =AF43/I43 -> #DIV/0! | BG43: PRODUCTO | BH43: 46023 | BI43: 46054 | BJ43: 46082 | BK43: 46113 | BL43: 46143 | BM43: 46174 | BN43: 46204 | BO43: TOTAL
BB44: Suma de UTILIDAD NETA | BC44: Etiquetas de columna | BG44: FRESCO | BH44: 2187.058 | BI44: 1640.0882 | BJ44: 1668.2266 | BK44: 2102.9547 | BL44: 2194.6357 | BM44: 2273.8905 | BN44: 2115.5175 | BO44: 1954.7316
BB45: Etiquetas de fila | BC45: FEBRERO | BD45: MARZO | BE45: Total general | BG45: POTA FILETE CONGELADO | BH45: 1975 | BI45: 1416.6667 | BJ45: 1470.8532 | BK45: 1819.372 | BL45: 2055.7616 | BM45: 1900.7364 | BN45: 2073.6842 | BO45: 1712.7254
AL46: Hunan Jinyueyang | AM46: 181.9125 | AN46: 72.469656 | BB46: POTA REJOS CONGELADOS | BC46: 106971.82 | BD46: 68462.268 | BE46: 175434.08 | BG46: POTA ALAS CONGELADAS | BH46: 1887.7083 | BI46: 1547.0281 | BJ46: 1591.715 | BK46: 1910.7211 | BL46: 1990.9091 | BM46: 2042.3089 | BN46: 1750 | BO46: 1751.6384
A47: ANÁLISIS POR CLIENTE | AL47: GOLDEN SEAFOOD | AM47: 151.256 | AN47: 31.632905 | BB47: POTA FILETE CONGELADO | BC47: -502314.03 | BD47: -260749.39 | BE47: -763063.42 | BG47: POTA REJOS CONGELADOS | BH47: 2575.0173 | BI47: 2548.7799 | BJ47: 2355.287 | BK47: 2550.0196 | BL47: 2925 | BM47: 2706.1798 | BN47: 2697.5926 | BO47: 2627.3185
AL48: SACRAMENTO CO., LTD | AM48: 91.8 | AN48: 29.126229 | BB48: POTA FILETE DARUMA | BC48: 28158.374 | BD48: 209162.38 | BE48: 237320.76 | BG48: POTA REPRODUCTORES | BH48: 2848.6154 | BI48: 2873.5185 | BJ48: 2729.4118 | BK48: 2972.6012 | BL48: 2975 | BM48: 2730 | BN48: 2714.1266 | BO48: 2849.5093
A49: RANKING DE VENTAS (USD) | L49: UTILIDAD NETA (USD) | X49: EBITDA (USD) | AL49: PROVEEDORA DE PRODUCTOS MARINOS | AM49: 90.79689 | AN49: 90.79689 | BB49: POTA ALAS CONGELADAS | BC49: -182032.49 | BD49: -219374.82 | BE49: -401407.31 | BG49: POTA NUCAS | BH49: 1790.1198 | BI49: 1675.4286 | BJ49: 1183.1169 | BK49: 0 | BL49: 1207.7869 | BM49: 1229.3814 | BN49: 1324.3421 | BO49: 1242.0315
A50: Suma de VALOR CFR | B50: Etiquetas de columna | L50: Suma de UTILIDAD NETA | M50: Etiquetas de columna | U50: MG | X50: Suma de EBITDA | Y50: Etiquetas de columna | AG50: MG | AL50: Shenzhen Yueshi | AM50: 81 | AN50: 18.351483 | BB50: POTA ALAS COCIDAS | BD50: 42400.96 | BE50: 42400.96 | BG50: POTA TUBOALETA | BH50: 0 | BI50: 0 | BJ50: 0 | BK50: 0 | BL50: 2002.963 | BM50: 0 | BN50: 0 | BO50: 2002.963
A51: Etiquetas de fila | B51: ENERO | C51: FEBRERO | D51: MARZO | E51: ABRIL | F51: MAYO | G51: JUNIO | H51: JULIO | I51: Total general | J51: % | L51: Etiquetas de fila | M51: ENERO | N51: FEBRERO | O51: MARZO | P51: ABRIL | Q51: MAYO | R51: JUNIO | S51: JULIO | T51: Total general | U51: NETO | X51: Etiquetas de fila | Y51: ENERO | Z51: FEBRERO | AA51: MARZO | AB51: ABRIL | AC51: MAYO | AD51: JUNIO | AE51: JULIO | AF51: Total general | AG51: EBITDA | AL51: Pesciro SL | AM51: 39 | AN51: -15.431273 | BB51: POTA REPRODUCTORES | BC51: 23262.951 | BD51: 29982.789 | BE51: 53245.74 | BG51: COCIDOS | BH51: 0 | BI51: 3400 | BJ51: 3125.9833 | BK51: 3859.6656 | BL51: 3857.3711 | BM51: 4001.0942 | BN51: 0 | BO51: 3717.6667
A52: LONGKOU JIABAO AQUATIC | D52: 669600 | E52: 737100 | F52: 1259758 | G52: 737667 | I52: 3404125 | J52: =I52/$I$89 -> 0.15357987 | L52: LONGKOU JIABAO AQUATIC | O52: 139441.59 | P52: 220262.22 | Q52: 159276.8 | R52: 125882.68 | T52: 644863.29 | U52: =T52/I52 -> 0.18943584 | X52: LONGKOU JIABAO AQUATIC | AA52: 169563.11 | AB52: 251210.86 | AC52: 206813.91 | AD52: 166831 | AF52: 794418.87 | AG52: =AF52/I52 -> 0.23336948 | BB52: POTA NUCAS | BC52: -6321.5029 | BD52: -407078.31 | BE52: -413399.82 | BG52: POTA FILETE DARUMA | BH52: 0 | BI52: 3400 | BJ52: 3100 | BK52: 3850 | BL52: 3845.4545 | BM52: 3929.1667 | BN52: 0 | BO52: 3655.6818
A53: AVANCE GROUP | C53: 1066950 | E53: 30300 | F53: 1047600 | G53: 437400 | H53: 670548 | I53: 3252798 | J53: =I53/$I$89 -> 0.14675263 | L53: AVANCE GROUP | N53: -504063.92 | P53: 21268.427 | Q53: 133928.91 | R53: 130995.37 | S53: 14360.596 | T53: -203510.62 | U53: =T53/I53 -> -0.062564789 | X53: AVANCE GROUP | Z53: -373533.6 | AB53: 25231.163 | AC53: 197452.89 | AD53: 166093.93 | AE53: 139067.61 | AF53: 154311.99 | AG53: =AF53/I53 -> 0.04743977 | BB53: POTA CONOS | BC53: 15489.988 | BD53: -6150.1256 | BE53: 9339.8622 | BG53: POTA ALAS COCIDAS | BH53: 0 | BI53: 0 | BJ53: 3281.8833 | BK53: 3898.9831 | BL53: 3890.3617 | BM53: 4145.5915 | BN53: 0 | BO53: 3913.6898
A54: TSUJINO | B54: 281115 | C54: 438056 | D54: 1104330 | E54: 961572 | F54: 290840 | G54: 244354 | H54: 160400 | I54: 3480667 | J54: =I54/$I$89 -> 0.15703312 | L54: TSUJINO | M54: -96644.014 | N54: -63539.7 | O54: -393457.74 | P54: -321367.84 | Q54: -86350.689 | R54: -50338.525 | S54: -51191.989 | T54: -1062890.5 | U54: =T54/I54 -> -0.30536977 | X54: TSUJINO | Y54: 51475.827 | Z54: -19546.331 | AA54: -292662.2 | AB54: -232989 | AC54: -59294.18 | AD54: -19356.466 | AE54: -15551.739 | AF54: -587924.1 | AG54: =AF54/I54 -> -0.16891133 | BB54: POTA TELILLA PRECOCIDA | BC54: -3693.6397 | BE54: -3693.6397 | BG54: SUBPRODUCTOS | BH54: 2100 | BI54: 1661.5057 | BJ54: 1498.04 | BK54: 1892.8032 | BL54: 1984.7869 | BM54: 1532.8679 | BN54: 1814.4269 | BO54: 1797.7459
A55: LONGKOU SANMING | F55: 490860 | G55: 1367604 | I55: 1858464 | J55: =I55/$I$89 -> 0.083846115 | L55: LONGKOU SANMING | Q55: -70783.434 | R55: 243910.62 | T55: 173127.19 | U55: =T55/I55 -> 0.093156062 | X55: LONGKOU SANMING | AC55: -35051.195 | AD55: 325651.26 | AF55: 290600.06 | AG55: =AF55/I55 -> 0.15636572 | BB55: POTA MEMBRANA PRECOCIDA | BC55: -3693.6397 | BD55: 26484.907 | BE55: 22791.268 | BG55: POTA CONOS | BH55: 2100 | BI55: 2029.4118 | BJ55: 1600 | BK55: 1600 | BL55: 1800 | BM55: 1704.3704 | BN55: 1600 | BO55: 1746.7324
A56: KULALIA | C56: 390000 | D56: 813921.7 | E56: 175000 | F56: 34720 | G56: 238024 | H56: 67500 | I56: 1719165.7 | J56: =I56/$I$89 -> 0.077561559 | L56: KULALIA | N56: 72084.864 | O56: 82440.804 | P56: -146096.62 | Q56: 24875.591 | R56: 74114.206 | S56: 18303.621 | T56: 125722.47 | U56: =T56/I56 -> 0.073129929 | X56: KULALIA | Z56: 98080.946 | AA56: 128599.25 | AB56: -125627.94 | AC56: 28698.793 | AD56: 96646.612 | AE56: 27926.488 | AF56: 254324.14 | AG56: =AF56/I56 -> 0.14793463 | AL56: Suma de Cantidad | AM56: Etiquetas de columna | BB56: RESIDUOS DE POTA | BC56: 40026 | BD56: 26456.61 | BE56: 66482.61 | BG56: POTA RECORTES COCIDOS | BH56: 0 | BI56: 0 | BJ56: 0 | BK56: 2500 | BL56: 2347.8889 | BM56: 0 | BN56: 2525 | BO56: 2449.1556
A57: FOOD & BEVERAGES TRADERS | C57: 222750 | E57: 712656 | I57: 935406 | J57: =I57/$I$89 -> 0.042201602 | L57: FOOD & BEVERAGES TRADERS | N57: -57541.555 | P57: 8412.7912 | T57: -49128.764 | U57: =T57/I57 -> -0.052521326 | X57: FOOD & BEVERAGES TRADERS | Z57: -35044.946 | AB57: 57036.543 | AF57: 21991.597 | AG57: =AF57/I57 -> 0.023510216 | AL57: Etiquetas de fila | AM57: ENERO | AN57: FEBRERO | AO57: MARZO | AP57: ABRIL | AQ57: MAYO | AR57: JUNIO | AS57: JULIO | AT57: Total general | BB57: Total general | BC57: -484146.17 | BD57: -490402.73 | BE57: -974548.9 | BG57: POTA TELILLA PRECOCIDA | BH57: 0 | BI57: 1429.8611 | BJ57: 0 | BK57: 2000 | BL57: 2050 | BM57: 0 | BN57: 1600 | BO57: 1710.8835
A58: Longkou Yunfeng Aquatic Food | E58: 575100 | F58: 340200 | I58: 915300 | J58: =I58/$I$89 -> 0.041294504 | L58: Longkou Yunfeng Aquatic Food | P58: -63173.584 | Q58: -22700.198 | T58: -85873.783 | U58: =T58/I58 -> -0.093820368 | X58: Longkou Yunfeng Aquatic Food | AB58: -18961.242 | AC58: 1091.8846 | AF58: -17869.357 | AG58: =AF58/I58 -> -0.019522951 | AL58: LONGKOU JIABAO AQUATIC | AO58: 216 | AP58: 189 | AQ58: 323.28 | AR58: 189 | AT58: 917.28 | BG58: POTA MEMBRANA PRECOCIDA | BH58: 0 | BI58: 1429.8611 | BJ58: 1316.7778 | BK58: 2000 | BL58: 0 | BM58: 0 | BN58: 1725 | BO58: 1662.4661
A59: Qingdao Haiyujia | E59: 595782 | F59: 230850 | I59: 826632 | J59: =I59/$I$89 -> 0.037294175 | L59: Qingdao Haiyujia | P59: 85207.391 | Q59: 64954.261 | T59: 150161.65 | U59: =T59/I59 -> 0.18165478 | X59: Qingdao Haiyujia | AB59: 120488.84 | AC59: 76865.007 | AF59: 197353.85 | AG59: =AF59/I59 -> 0.2387445 | AL59: AVANCE GROUP | AN59: 783.3 | AP59: 24.2 | AQ59: 432 | AR59: 162 | AS59: 349.905 | AT59: 1751.405 | BG59: POTA LABIOS CONGELADOS | BH59: 0 | BI59: 0 | BJ59: 0 | BK59: 0 | BL59: 1335.3846 | BM59: 1354.7692 | BN59: 0 | BO59: 1345.0769
A60: LONGKOU BOHAI | D60: 334800 | F60: 299700 | I60: 634500 | J60: =I60/$I$89 -> 0.028625983 | L60: LONGKOU BOHAI | O60: 69720.794 | Q60: 10168.087 | T60: 79888.881 | U60: =T60/I60 -> 0.1259084 | X60: LONGKOU BOHAI | AA60: 84781.555 | AC60: 22078.833 | AF60: 106860.39 | AG60: =AF60/I60 -> 0.16841669 | AL60: TSUJINO | AM60: 144 | AN60: 264 | AO60: 722.8 | AP60: 539.72 | AQ60: 184 | AR60: 143 | AS60: 100 | AT60: 2097.52 | BB60: Suma de COSTO VENTAS | BC60: Etiquetas de columna | BG60: POTA SUCKERS CONGELADO | BH60: 0 | BI60: 0 | BJ60: 0 | BK60: 1252.0661 | BL60: 0 | BM60: 0 | BN60: 0 | BO60: 1252.0661
A61: GLOBAL OCEAN | B61: 140400 | C61: 77585 | E61: 67500 | F61: 134636 | I61: 420121 | J61: =I61/$I$89 -> 0.018954101 | L61: GLOBAL OCEAN | M61: -3780.837 | N61: 23262.951 | P61: 10368.202 | Q61: 71709.862 | T61: 101560.18 | U61: =T61/I61 -> 0.2417403 | X61: GLOBAL OCEAN | Y61: 51764.104 | Z61: 27762.272 | AB61: 14789.436 | AC61: 79503.313 | AF61: 173819.13 | AG61: =AF61/I61 -> 0.41373586 | AL61: LONGKOU SANMING | AQ61: 243 | AR61: 377.28 | AT61: 620.28 | BB61: Etiquetas de fila | BC61: FEBRERO | BD61: MARZO | BE61: Total general | BG61: TOTAL | BH61: 2178.6331 | BI61: 1670.3166 | BJ61: 1937.927 | BK61: 2314.4623 | BL61: 2520.6065 | BM61: 2979.7726 | BN61: 2001.4265 | BO61: 2221.181
A62: OCEANUS FISH | B62: 74064 | D62: 76700 | E62: 189800 | F62: 80600 | H62: 74100 | I62: 495264 | J62: =I62/$I$89 -> 0.022344238 | L62: OCEANUS FISH | M62: 4890.763 | O62: 21276.273 | P62: -67658.981 | Q62: 26751.544 | S62: 21672.963 | T62: 6932.5622 | U62: =T62/I62 -> 0.013997711 | X62: OCEANUS FISH | Y62: 31634.623 | AA62: 24902.012 | AB62: -50629.042 | AC62: 30574.747 | AE62: 30939.428 | AF62: 67421.768 | AG62: =AF62/I62 -> 0.13613299 | AL62: KULALIA | AN62: 156 | AO62: 331 | AP62: 125 | AQ62: 26 | AR62: 104 | AS62: 27 | AT62: 769 | BB62: POTA REJOS CONGELADOS | BC62: 377498.16 | BD62: 600468.8 | BE62: 977966.96
A63: GOLDEN SEAFOOD | E63: 151256 | G63: 70980 | H63: 140316 | I63: 362552 | J63: =I63/$I$89 -> 0.016356828 | L63: GOLDEN SEAFOOD | P63: 30370.237 | R63: 23179.219 | S63: 36028.24 | T63: 89577.696 | U63: =T63/I63 -> 0.24707544 | X63: GOLDEN SEAFOOD | AB63: 38852.457 | AD63: 28812.32 | AE63: 54917.573 | AF63: 122582.35 | AG63: =AF63/I63 -> 0.33810971 | AL63: FOOD & BEVERAGES TRADERS | AN63: 135 | AP63: 296.94 | AT63: 431.94 | BB63: POTA FILETE CONGELADO | BC63: 1468183.1 | BD63: 594954.26 | BE63: 2063137.3
A64: OVERSEA | C64: 142695 | D64: 135200 | E64: 76700 | I64: 354595 | J64: =I64/$I$89 -> 0.015997842 | L64: OVERSEA | N64: 34886.953 | O64: 23561.482 | P64: 13615.558 | T64: 72063.993 | U64: =T64/I64 -> 0.20322902 | X64: OVERSEA | Z64: 43718.955 | AA64: 30812.959 | AB64: 17873.043 | AF64: 92404.958 | AG64: =AF64/I64 -> 0.26059295 | AL64: Longkou Yunfeng Aquatic Food | AP64: 270 | AQ64: 161.8 | AT64: 431.8 | BB64: POTA FILETE DARUMA | BC64: 59654.17 | BD64: 710749.18 | BE64: 770403.35
A65: Pesciro Asia International LTD. | D65: 352350 | I65: 352350 | J65: =I65/$I$89 -> 0.015896557 | L65: Pesciro Asia International LTD. | O65: -224394.16 | T65: -224394.16 | U65: =T65/I65 -> -0.63685017 | X65: Pesciro Asia International LTD. | AA65: -190507.45 | AF65: -190507.45 | AG65: =AF65/I65 -> -0.54067673 | AL65: Qingdao Haiyujia | AP65: 215.46 | AQ65: 81 | AT65: 296.46 | BB65: POTA ALAS CONGELADAS | BC65: 796852.62 | BD65: 842545.85 | BE65: 1639398.5
A66: DAIRECK S.A. | B66: 44722 | D66: 236060 | F66: 51775 | I66: 332557 | J66: =I66/$I$89 -> 0.015003579 | L66: DAIRECK S.A. | M66: -20884.593 | O66: -252973.27 | Q66: -38407.32 | T66: -312265.19 | U66: =T66/I66 -> -0.93898245 | X66: DAIRECK S.A. | Y66: 3802.047 | AA66: -222712.3 | AC66: -31790.239 | AF66: -250700.49 | AG66: =AF66/I66 -> -0.75385721 | AL66: LONGKOU BOHAI | AO66: 108 | AQ66: 81 | AT66: 189 | BB66: POTA ALAS COCIDAS | BD66: 121033.99 | BE66: 121033.99
A67: YANTAI TAIXI FOODSTUFF | E67: 279504 | I67: 279504 | J67: =I67/$I$89 -> 0.01261005 | L67: YANTAI TAIXI FOODSTUFF | P67: -10050.557 | T67: -10050.557 | U67: =T67/I67 -> -0.035958544 | X67: YANTAI TAIXI FOODSTUFF | AB67: 7575.4305 | AF67: 7575.4305 | AG67: =AF67/I67 -> 0.02710312 | AL67: GLOBAL OCEAN | AM67: 54 | AN67: 27 | AP67: 27 | AQ67: 53 | AT67: 161 | BB67: POTA REPRODUCTORES | BC67: 48400.224 | BD67: 92586.614 | BE67: 140986.84
A68: Longkou Yunfeng Aquatic | C68: 222750 | D68: 35553 | I68: 258303 | J68: =I68/$I$89 -> 0.01165355 | L68: Longkou Yunfeng Aquatic | N68: -50032.855 | O68: 26484.907 | T68: -23547.948 | U68: =T68/I68 -> -0.09116405 | X68: Longkou Yunfeng Aquatic | Z68: -27536.246 | AA68: 30250.097 | AF68: 2713.8517 | AG68: =AF68/I68 -> 0.010506466 | AL68: OCEANUS FISH | AM68: 26 | AO68: 26 | AP68: 104 | AQ68: 26 | AS68: 26 | AT68: 208 | BB68: POTA NUCAS | BC68: 26431.511 | BD68: 730023.11 | BE68: 756454.63
A69: YANTAI HONGCHANG | F69: 164700 | G69: 82350 | I69: 247050 | J69: =I69/$I$89 -> 0.011145862 | L69: YANTAI HONGCHANG | Q69: 54682.28 | R69: 31617.562 | T69: 86299.842 | U69: =T69/I69 -> 0.34932136 | X69: YANTAI HONGCHANG | AC69: 62622.778 | AD69: 37467.321 | AF69: 100090.1 | AG69: =AF69/I69 -> 0.40514106 | AL69: GOLDEN SEAFOOD | AP69: 51.8 | AR69: 26 | AS69: 53 | AT69: 130.8 | BB69: POTA CONOS | BC69: 45745.096 | BD69: 66785.543 | BE69: 112530.64
A70: PROVEEDORA DE PRODUCTOS MARINOS | B70: 24314.28 | C70: 40026 | D70: 26456.61 | E70: 37768.57 | F70: 23613.25 | G70: 42995.3 | H70: 26456.61 | I70: 221630.62 | J70: =I70/$I$89 -> 0.0099990457 | L70: PROVEEDORA DE PRODUCTOS MARINOS | M70: 24314.28 | N70: 40026 | O70: 26456.61 | P70: 37768.57 | Q70: 23613.25 | R70: 42995.3 | S70: 26456.61 | T70: 221630.62 | U70: =T70/I70 -> 1 | X70: PROVEEDORA DE PRODUCTOS MARINOS | Y70: 24314.28 | Z70: 40026 | AA70: 26456.61 | AB70: 37768.57 | AC70: 23613.25 | AD70: 42995.3 | AE70: 26456.61 | AF70: 221630.62 | AG70: =AF70/I70 -> 1 | AL70: OVERSEA | AN70: 53 | AO70: 52 | AP70: 26 | AT70: 131 | BB70: POTA TELILLA PRECOCIDA | BC70: 36716.621 | BE70: 36716.621
A71: Hunan Jinyueyang | C71: 77212.5 | E71: 104700 | F71: 53812.5 | I71: 235725 | J71: =I71/$I$89 -> 0.010634925 | L71: Hunan Jinyueyang | N71: -7387.2793 | P71: 87558.887 | Q71: 46854.792 | T71: 127026.4 | U71: =T71/I71 -> 0.53887538 | X71: Hunan Jinyueyang | Z71: 1611.3643 | AB71: 96131.169 | AC71: 50714.756 | AF71: 148457.29 | AG71: =AF71/I71 -> 0.62979018 | AL71: Pesciro Asia International LTD. | AO71: 243 | AT71: 243 | BB71: POTA MEMBRANA PRECOCIDA | BC71: 36716.621 | BD71: 0 | BE71: 36716.621
A72: SHANDONG SHEENIER | D72: 70200 | E72: 145800 | I72: 216000 | J72: =I72/$I$89 -> 0.0097450157 | L72: SHANDONG SHEENIER | O72: 13567.459 | P72: 21712.507 | T72: 35279.965 | U72: =T72/I72 -> 0.16333317 | X72: SHANDONG SHEENIER | AA72: 17332.649 | AB72: 30554.975 | AF72: 47887.624 | AG72: =AF72/I72 -> 0.22170196 | AL72: DAIRECK S.A. | AM72: 24 | AO72: 217 | AQ72: 45 | AT72: 286 | BB72: RESIDUOS DE POTA | BC72: 0 | BD72: 0 | BE72: 0
A73: ZHOUSHAN EAST CHINA | F73: 167700 | I73: 167700 | J73: =I73/$I$89 -> 0.0075659219 | L73: ZHOUSHAN EAST CHINA | Q73: -19201.668 | T73: -19201.668 | U73: =T73/I73 -> -0.11450011 | X73: ZHOUSHAN EAST CHINA | AC73: -7290.9218 | AF73: -7290.9218 | AG73: =AF73/I73 -> -0.04347598 | AL73: YANTAI TAIXI FOODSTUFF | AP73: 107.64 | AT73: 107.64 | BB73: Total general | BC73: 2896198.1 | BD73: 3759147.4 | BE73: 6655345.4
A74: QINGDAO OCEAN | H74: 161610 | I74: 161610 | J74: =I74/$I$89 -> 0.0072911666 | L74: QINGDAO OCEAN | S74: 53660.616 | T74: 53660.616 | U74: =T74/I74 -> 0.33203772 | X74: QINGDAO OCEAN | AE74: 72906.351 | AF74: 72906.351 | AG74: =AF74/I74 -> 0.45112525 | AL74: Longkou Yunfeng Aquatic | AN74: 135 | AO74: 27 | AT74: 162
A75: KS FROZEN COMPANY | H75: 119700 | I75: 119700 | J75: =I75/$I$89 -> 0.0054003628 | L75: KS FROZEN COMPANY | S75: -58093.58 | T75: -58093.58 | U75: =T75/I75 -> -0.48532648 | X75: KS FROZEN COMPANY | AE75: -26017.355 | AF75: -26017.355 | AG75: =AF75/I75 -> -0.21735468 | AL75: YANTAI HONGCHANG | AQ75: 54 | AR75: 27 | AT75: 81
A76: Shenzhen Yueshi Supply | G76: 118800 | I76: 118800 | J76: =I76/$I$89 -> 0.0053597586 | L76: Shenzhen Yueshi Supply | R76: 8291.4954 | T76: 8291.4954 | U76: =T76/I76 -> 0.069793732 | X76: Shenzhen Yueshi Supply | AD76: 19991.014 | AF76: 19991.014 | AG76: =AF76/I76 -> 0.16827453 | AL76: PROVEEDORA DE PRODUCTOS MARINOS | AM76: 0 | AN76: 0 | AO76: 0 | AP76: 0 | AQ76: 0 | AR76: 0 | AS76: 0 | AT76: 0
A77: ZHEJIANG ZHOUFU | F77: 105560 | I77: 105560 | J77: =I77/$I$89 -> 0.0047624252 | L77: ZHEJIANG ZHOUFU | Q77: -19235.512 | T77: -19235.512 | U77: =T77/I77 -> -0.18222349 | X77: ZHEJIANG ZHOUFU | AC77: -11295.015 | AF77: -11295.015 | AG77: =AF77/I77 -> -0.1070009 | AL77: Hunan Jinyueyang | AN77: 54 | AP77: 52.35 | AQ77: 26.25 | AT77: 132.6
A78: SHANDONG LONGKOU XINLONG | H78: 99900 | I78: 99900 | J78: =I78/$I$89 -> 0.0045070697 | L78: SHANDONG LONGKOU XINLONG | S78: 7607.0989 | T78: 7607.0989 | U78: =T78/I78 -> 0.076147136 | X78: SHANDONG LONGKOU XINLONG | AE78: 26852.834 | AF78: 26852.834 | AG78: =AF78/I78 -> 0.26879713 | AL78: SHANDONG SHEENIER | AO78: 27 | AP78: 54 | AT78: 81
A79: SACRAMENTO CO., LTD | C79: 91800 | I79: 91800 | J79: =I79/$I$89 -> 0.0041416317 | L79: SACRAMENTO CO., LTD | N79: 28158.374 | T79: 28158.374 | U79: =T79/I79 -> 0.3067361 | X79: SACRAMENTO CO., LTD | Z79: 32657.696 | AF79: 32657.696 | AG79: =AF79/I79 -> 0.35574832 | AL79: ZHOUSHAN EAST CHINA | AQ79: 81 | AT79: 81
A80: NINGBO JUN TAO | F80: 83700 | I80: 83700 | J80: =I80/$I$89 -> 0.0037761936 | L80: NINGBO JUN TAO | Q80: 28732.67 | T80: 28732.67 | U80: =T80/I80 -> 0.3432816 | X80: NINGBO JUN TAO | AC80: 32702.919 | AF80: 32702.919 | AG80: =AF80/I80 -> 0.39071588 | AL80: QINGDAO OCEAN | AS80: 54 | AT80: 54
A81: Shenzhen Yueshi | E81: 81000 | I81: 81000 | J81: =I81/$I$89 -> 0.0036543809 | L81: Shenzhen Yueshi | P81: 19312.553 | T81: 19312.553 | U81: =T81/I81 -> 0.23842658 | X81: Shenzhen Yueshi | AB81: 23733.788 | AF81: 23733.788 | AG81: =AF81/I81 -> 0.29300972 | AL81: KS FROZEN COMPANY | AS81: 90 | AT81: 90
A82: OPTIMIZE INTEGRATION | H82: 68850 | I82: 68850 | J82: =I82/$I$89 -> 0.0031062237 | L82: OPTIMIZE INTEGRATION | S82: 22508.081 | T82: 22508.081 | U82: =T82/I82 -> 0.32691476 | X82: OPTIMIZE INTEGRATION | AE82: 32130.948 | AF82: 32130.948 | AG82: =AF82/I82 -> 0.46668044 | AL82: Shenzhen Yueshi Supply | AR82: 54 | AT82: 54
A83: YANTAI HIZEN INTERNATIONAL | F83: 66250 | I83: 66250 | J83: =I83/$I$89 -> 0.0029889226 | L83: YANTAI HIZEN INTERNATIONAL | Q83: 59023.517 | T83: 59023.517 | U83: =T83/I83 -> 0.89092101 | X83: YANTAI HIZEN INTERNATIONAL | AC83: 62993.766 | AF83: 62993.766 | AG83: =AF83/I83 -> 0.9508493 | AL83: ZHEJIANG ZHOUFU | AQ83: 54 | AT83: 54
A84: GIANT OCEAN FOOD | F84: 54080 | I84: 54080 | J84: =I84/$I$89 -> 0.0024398632 | L84: GIANT OCEAN FOOD | Q84: -8445.056 | T84: -8445.056 | U84: =T84/I84 -> -0.15615858 | X84: GIANT OCEAN FOOD | AC84: -4474.8073 | AF84: -4474.8073 | AG84: =AF84/I84 -> -0.082744217 | AL84: SHANDONG LONGKOU XINLONG | AS84: 54 | AT84: 54
A85: Pesciro SL | D85: 39000 | I85: 39000 | J85: =I85/$I$89 -> 0.0017595167 | L85: Pesciro SL | O85: -22527.478 | T85: -22527.478 | U85: =T85/I85 -> -0.57762765 | X85: Pesciro SL | AA85: -18901.74 | AF85: -18901.74 | AG85: =AF85/I85 -> -0.48465999 | AL85: SACRAMENTO CO., LTD | AN85: 27 | AT85: 27
A86: TT INTERBIZ | F86: 29250 | I86: 29250 | J86: =I86/$I$89 -> 0.0013196375 | L86: TT INTERBIZ | Q86: -22381.939 | T86: -22381.939 | U86: =T86/I86 -> -0.7651945 | X86: TT INTERBIZ | AC86: -18558.737 | AF86: -18558.737 | AG86: =AF86/I86 -> -0.63448672 | AL86: NINGBO JUN TAO | AQ86: 27 | AT86: 27
A87: PELAGICS INTERNATIONAL | G87: 29250 | I87: 29250 | J87: =I87/$I$89 -> 0.0013196375 | L87: PELAGICS INTERNATIONAL | R87: -12277.013 | T87: -12277.013 | U87: =T87/I87 -> -0.41972693 | X87: PELAGICS INTERNATIONAL | AD87: -7402.2132 | AF87: -7402.2132 | AG87: =AF87/I87 -> -0.25306712 | AL87: Shenzhen Yueshi | AP87: 27 | AT87: 27
A88: SERENE OCEAN | G88: 46018 | I88: 46018 | J88: =I88/$I$89 -> 0.0020761395 | L88: SERENE OCEAN | R88: 4450.8385 | T88: 4450.8385 | U88: =T88/I88 -> 0.096719511 | X88: SERENE OCEAN | AD88: 10300.598 | AF88: 10300.598 | AG88: =AF88/I88 -> 0.22383845 | AL88: OPTIMIZE INTEGRATION | AS88: 27 | AT88: 27
A89: Total general | B89: 564615.28 | C89: 2769824.5 | D89: 3894171.3 | E89: 4921538.6 | F89: 5010204.8 | G89: 3415442.3 | H89: 1589380.6 | I89: 22165177 | J89: =I89/$I$89 -> 1 | L89: Total general | M89: -92104.402 | N89: -484146.17 | O89: -490402.73 | P89: -52490.241 | Q89: 417065.74 | R89: 622821.76 | S89: 91312.258 | T89: 12056.214 | U89: =T89/I89 -> 0.0005439259 | X89: Total general | Y89: 162990.88 | Z89: -211803.89 | AA89: -212085.45 | AB89: 293039.04 | AC89: 707971.75 | AD89: 868030.67 | AE89: 369628.75 | AF89: 1977771.8 | AG89: =AF89/I89 -> 0.089228781 | AL89: YANTAI HIZEN INTERNATIONAL | AQ89: 27 | AT89: 27
A90: Nro de Clientes | B90: =COUNT(B52:B88) -> 5 | C90: =COUNT(C52:C88) -> 10 | D90: =COUNT(D52:D88) -> 12 | E90: =COUNT(E52:E88) -> 16 | F90: =COUNT(F52:F88) -> 20 | G90: =COUNT(G52:G88) -> 11 | H90: =COUNT(H52:H88) -> 10 | I90: =COUNT(I52:I88) -> 37 | AL90: GIANT OCEAN FOOD | AQ90: 27 | AT90: 27
AL91: Pesciro SL | AO91: 26 | AT91: 26
G92: 5004823 | H92: 644128 | I92: =H92/G92 -> 0.12870145 | AL92: TT INTERBIZ | AQ92: 26 | AT92: 26
A93: ANÁLISIS POR TIPO DE PRODUCTO | AL93: PELAGICS INTERNATIONAL | AR93: 22.5 | AT93: 22.5
AL94: SERENE OCEAN | AR94: 27 | AT94: 27
A95: RANKING DE VENTAS (USD) | L95: UTILIDAD NETA (USD) | X95: EBITDA (USD) | AL95: Total general | AM95: 248 | AN95: 1634.3 | AO95: 1995.8 | AP95: 2110.11 | AQ95: 1978.33 | AR95: 1131.78 | AS95: 780.905 | AT95: 9879.225
A96: Suma de VALOR CFR | B96: Etiquetas de columna | L96: Suma de UTILIDAD NETA | M96: Etiquetas de columna | U96: MG | X96: Suma de EBITDA | Y96: Etiquetas de columna | AG96: MG
A97: Etiquetas de fila | B97: ENERO | C97: FEBRERO | D97: MARZO | E97: ABRIL | F97: MAYO | G97: JUNIO | H97: JULIO | I97: Total general | J97: % | L97: Etiquetas de fila | M97: ENERO | N97: FEBRERO | O97: MARZO | P97: ABRIL | Q97: MAYO | R97: JUNIO | S97: JULIO | T97: Total general | U97: NETO | X97: Etiquetas de fila | Y97: ENERO | Z97: FEBRERO | AA97: MARZO | AB97: ABRIL | AC97: MAYO | AD97: JUNIO | AE97: JULIO | AF97: Total general | AG97: EBITDA
A98: Fresco | B98: 489901 | C98: 2491786 | D98: 2573740 | E98: 3607114 | F98: 3168615 | G98: 1349554 | H98: 1026026 | I98: 14706736 | J98: =I98/$I$102 -> 0.66350635 | L98: Fresco | M98: -106614.25 | N98: -560433.25 | O98: -788757.47 | P98: -472750.69 | Q98: 39943.29 | R98: 170245.08 | S98: 37367.99 | T98: -1680999.3 | U98: =T98/I98 -> -0.11430132 | X98: Fresco | Y98: 123794.39 | Z98: -307254.75 | AA98: -573611.71 | AB98: -191877.87 | AC98: 252248.66 | AD98: 298831.46 | AE98: 210223.2 | AF98: -187646.61 | AG98: =AF98/I98 -> -0.012759229
A99: Cocido | C99: 91800 | D99: 1181621.7 | E99: 1038636 | F99: 1559458 | G99: 1941651 | I99: 5813166.7 | J99: =I99/$I$102 -> 0.26226574 | L99: Cocido | N99: 28158.374 | O99: 251563.34 | P99: 273542.69 | Q99: 169444.88 | R99: 380166.01 | T99: 1102875.3 | U99: =T99/I99 -> 0.18972023 | X99: Cocido | Z99: 32657.696 | AA99: 304276.01 | AB99: 317607.66 | AC99: 228892.74 | AD99: 485305.69 | AF99: 1368739.8 | AG99: =AF99/I99 -> 0.23545511
A100: Subproducto | B100: 50400 | C100: 146212.5 | D100: 112353 | E100: 238020 | F100: 258518.5 | G100: 81242 | H100: 536898 | I100: 1423644 | J100: =I100/$I$102 -> 0.064228857 | L100: Subproducto | M100: -9804.429 | N100: 8102.7085 | O100: 20334.782 | P100: 108949.19 | Q100: 184064.32 | R100: 29415.367 | S100: 27487.658 | T100: 368549.6 | U100: =T100/I100 -> 0.25887764 | X100: Subproducto | Y100: 14882.211 | Z100: 22767.165 | AA100: 30793.643 | AB100: 129540.68 | AC100: 203217.09 | AD100: 40898.228 | AE100: 132948.94 | AF100: 575047.96 | AG100: =AF100/I100 -> 0.40392679
A101: Residuo | B101: 24314.28 | C101: 40026 | D101: 26456.61 | E101: 37768.57 | F101: 23613.25 | G101: 42995.3 | H101: 26456.61 | I101: 221630.62 | J101: =I101/$I$102 -> 0.0099990457 | L101: Residuo | M101: 24314.28 | N101: 40026 | O101: 26456.61 | P101: 37768.57 | Q101: 23613.25 | R101: 42995.3 | S101: 26456.61 | T101: 221630.62 | U101: =T101/I101 -> 1 | X101: Residuo | Y101: 24314.28 | Z101: 40026 | AA101: 26456.61 | AB101: 37768.57 | AC101: 23613.25 | AD101: 42995.3 | AE101: 26456.61 | AF101: 221630.62 | AG101: =AF101/I101 -> 1
A102: Total general | B102: 564615.28 | C102: 2769824.5 | D102: 3894171.3 | E102: 4921538.6 | F102: 5010204.8 | G102: 3415442.3 | H102: 1589380.6 | I102: 22165177 | J102: =I102/$I$102 -> 1 | L102: Total general | M102: -92104.402 | N102: -484146.17 | O102: -490402.73 | P102: -52490.241 | Q102: 417065.74 | R102: 622821.76 | S102: 91312.258 | T102: 12056.214 | U102: =T102/I102 -> 0.0005439259 | X102: Total general | Y102: 162990.88 | Z102: -211803.89 | AA102: -212085.45 | AB102: 293039.04 | AC102: 707971.75 | AD102: 868030.67 | AE102: 369628.75 | AF102: 1977771.8 | AG102: =AF102/I102 -> 0.089228781
...

Sheet Resumen
G2: X | H2: X | M2: X | P2: X | AW2: X | AX2: X | BC2: ANÁLISIS UNITARIO
B3: MES LINK | C3: MES EJERCICIO | D3: FP | E3: Emision | F3: Fecha Embarque | G3: Cantidad | H3: Producto | I3: Corte | J3: Espec. | K3: País | L3: Puerto | M3: Cliente (Razón Social) | N3: Contacto | O3: Precio TM | P3: VALOR CFR | Q3: FOB / TM | R3: Costo Flete | S3: VALOR FOB | T3: Cantidad de FCL (Contenedores) | U3: M/V Nave | V3: Booking | W3: Naviera | X3: Puerto | Y3: Tipo Producto | Z3: CÓDIGO | AA3: Categoría | AB3: MATCH | AC3: COSTO UNITARIO | AD3: Materia Prima | AE3: MOD | AF3: Envases | AG3: CIF | AH3: COSTO VENTAS | AI3: Cant | AJ3: C.U | AK3: Cotos Vta | AL3: UTILIDAD BRUTA | AM3: MARGEN BRUTO | AN3: Flete | AO3: Otros Gastos Ventas | AP3: Ajuste | AQ3: GASTO VENTAS | AR3: GASTO ADM | AS3: DRAWBACK | AT3: UTILIDAD OPERATIVA | AU3: MARGEN OPERATIVO | AV3: GASTO FINANCIERO | AW3: UTILIDAD NETA | AX3: MARGEN NETO | AY3: DEPRECIACIÓN | AZ3: EBITDA | BA3: MARGEN EBITDA | BC3: PRECIO CFR | BD3: Materia Prima | BE3: MOD | BF3: Envases | BG3: CIF | BH3: COSTO VENTAS | BI3: UTILIDAD BRUTA | BJ3: Flete | BK3: SS Logístico | BL3: GASTO VENTAS | BM3: GASTO ADM | BN3: DRAWBACK | BO3: UTILIDAD OPERATIVA | BP3: GASTO FINANCIERO | BQ3: UTILIDAD NETA | BR3: DEPRECIACIÓN | BS3: EBITDA
B4: ENERO | C4: =B4 -> ENERO | D4: 127-2025 | E4: 325 | F4: 46033 | G4: 26 | H4: POTA REPRODUCTORES | I4: Rejos | K4: España | L4: Valencia | M4: OCEANUS FISH | N4: Ignacio / Ives | O4: =P4/G4 -> 2848.6154 | P4: =78000*0+74064 -> 74064 | Q4: =S4/G4 -> 2670.3846 | R4: 4634 | S4: =P4-R4 -> 69430 | T4: 1 | U4: MERSIN EXPRESS 603N | V4: 26106924 | W4: HAPAG | X4: PAITA | Y4: Fresco | Z4: 10007567 | AA4: Compensación | AB4: =B4&Z4&AA4 -> ENERO10007567Compensación | AC4: =INDEX('Detalle Costos'!$L$5:$L$158,MATCH(Resumen!AB4,'Detalle Costos'!$C$5:$C$158,0))*1000+4623.769999996/248 -> 1848.6442 | AD4: =IFERROR(INDEX('Detalle Costos'!$X$5:$X$158,MATCH(Resumen!AB4,'Detalle Costos'!$C$5:$C$158,0))*AH4,0) -> 31139.447 | AE4: =IFERROR(INDEX('Detalle Costos'!$Z$5:$Z$158,MATCH(Resumen!AB4,'Detalle Costos'!$C$5:$C$158,0))*AH4,0) -> 7653.4663 | AF4: =IFERROR(INDEX('Detalle Costos'!$Y$5:$Y$158,MATCH(Resumen!AB4,'Detalle Costos'!$C$5:$C$158,0))*AH4,0) -> 459.33891 | AG4: =IFERROR(INDEX('Detalle Costos'!$AA$5:$AA$158,MATCH(Resumen!AB4,'Detalle Costos'!$C$5:$C$158,0))*AH4,0) -> 7628.333 | AH4: =AJ4*G4+6518.87/248*G4 -> 46880.585 | AI4: =48.96-AI17 -> 22.658 | AJ4: 1776.8137 | AK4: =89589.14-AK17 -> 41460.14 | AL4: =P4-AH4 -> 27183.415 | AM4: =AL4/P4 -> 0.36702602 | AN4: =R4 -> 4634 | AO4: =118461.136538461/5988.21*G4+6*G4 -> 670.34227 | AP4: 0 | AQ4: =SUM(AN4:AP4) -> 5304.3423 | AR4: =50659/248*G4 -> 5311.0242 | AS4: =S4*0.03 -> 2082.9 | AT4: =AL4-AQ4-AR4+AS4 -> 18650.949 | AU4: =AT4/P4 -> 0.25182205 | AV4: =131251/248*G4 -> 13760.185 | AW4: =AT4-AV4 -> 4890.763 | AX4: =AW4/P4 -> 0.066034281 | AY4: =123844.283333333/248*G4 -> 12983.675 | AZ4: =AT4+AY4 -> 31634.623 | BA4: =AZ4/P4 -> 0.4271255 | BC4: =P4/$G4 -> 2848.6154 | BD4: =-AD4/$G4 -> -1197.671 | BE4: =-AE4/$G4 -> -294.36409 | BF4: =-AF4/$G4 -> -17.666881 | BG4: =-AG4/$G4 -> -293.39742 | BH4: =-AH4/$G4 -> -1803.0994 | BI4: =AL4/$G4 -> 1045.516 | BJ4: =-AN4/$G4 -> -178.23077 | BK4: =-AP4/$G4 -> 0 | BL4: =-AQ4/$G4 -> -204.01316 | BM4: =-AR4/$G4 -> -204.27016 | BN4: =AS4/$G4 -> 80.111538 | BO4: =AT4/$G4 -> 717.34417 | BP4: =-AV4/$G4 -> -529.2379 | BQ4: =AW4/$G4 -> 188.10627 | BR4: =AY4/$G4 -> 499.37211 | BS4: =AZ4/$G4 -> 1216.7163
B5: ENERO | C5: =B5 -> ENERO | D5: 128-2025B | E5: 325 | F5: 46053 | G5: 17.04 | H5: POTA NUCAS | I5: Nucas | J5: 1000-up | K5: Tailandia | L5: Lat Krabang | M5: DAIRECK S.A. | N5: Julieta | O5: 1850 | P5: 31524 | Q5: 1656.338 | R5: =3300/24*G5 -> 2343 | S5: =P5-R5 -> 29181 | T5: 1 | U5: ECO SIROCCO 26005S | V5: 6443191850 | W5: COSCO | X5: PAITA | Y5: Fresco | Z5: 10005779 | AA5: Compensación | AB5: =B5&Z5&AA5 -> ENERO10005779Compensación | AC5: =INDEX('Detalle Costos'!$L$5:$L$158,MATCH(Resumen!AB5,'Detalle Costos'!$C$5:$C$158,0))*1000+4623.769999996/248 -> 1948.6442 | AD5: =IFERROR(INDEX('Detalle Costos'!$X$5:$X$158,MATCH(Resumen!AB5,'Detalle Costos'!$C$5:$C$158,0))*AH5,0) -> 20410.224 | AE5: =IFERROR(INDEX('Detalle Costos'!$Z$5:$Z$158,MATCH(Resumen!AB5,'Detalle Costos'!$C$5:$C$158,0))*AH5,0) -> 6891.7519 | AF5: =IFERROR(INDEX('Detalle Costos'!$Y$5:$Y$158,MATCH(Resumen!AB5,'Detalle Costos'!$C$5:$C$158,0))*AH5,0) -> 247.66592 | AG5: =IFERROR(INDEX('Detalle Costos'!$AA$5:$AA$158,MATCH(Resumen!AB5,'Detalle Costos'!$C$5:$C$158,0))*AH5,0) -> 4881.1167 | AH5: =AJ5*G5+6518.87/248*G5 -> 32430.759 | AI5: 17.04 | AJ5: 1876.9278 | AK5: 33696.517 | AL5: =P5-AH5 -> -906.75879 | AM5: =AL5/P5 -> -0.028764078 | AN5: =R5 -> 2343 | AO5: =118461.136538461/5988.21*G5+6*G5 -> 439.33201 | AP5: 0 | AQ5: =SUM(AN5:AP5) -> 2782.332 | AR5: =50659/248*G5 -> 3480.7635 | AS5: =S5*0.03 -> 875.43 | AT5: =AL5-AQ5-AR5+AS5 -> -6294.4244 | AU5: =AT5/P5 -> -0.19967087 | AV5: =131251/248*G5 -> 9018.2139 | AW5: =AT5-AV5 -> -15312.638 | AX5: =AW5/P5 -> -0.48574541 | AY5: =123844.283333333/248*G5 -> 8509.3008 | AZ5: =AT5+AY5 -> 2214.8764 | BA5: =AZ5/P5 -> 0.070260005 | BC5: =P5/$G5 -> 1850 | BD5: =-AD5/$G5 -> -1197.7831 | BE5: =-AE5/$G5 -> -404.44554 | BF5: =-AF5/$G5 -> -14.534385 | BG5: =-AG5/$G5 -> -286.45051 | BH5: =-AH5/$G5 -> -1903.2135 | BI5: =AL5/$G5 -> -53.213544 | BJ5: =-AN5/$G5 -> -137.5 | BK5: =-AP5/$G5 -> 0 | BL5: =-AQ5/$G5 -> -163.2824 | BM5: =-AR5/$G5 -> -204.27016 | BN5: =AS5/$G5 -> 51.375 | BO5: =AT5/$G5 -> -369.3911 | BP5: =-AV5/$G5 -> -529.2379 | BQ5: =AW5/$G5 -> -898.629 | BR5: =AY5/$G5 -> 499.37211 | BS5: =AZ5/$G5 -> 129.98101
B6: ENERO | C6: =B6 -> ENERO | D6: 128-2025B | E6: 325 | F6: 46053 | G6: 3 | H6: POTA NUCAS | I6: Nucas | J6: 500 - 1 kg. | K6: Tailandia | L6: Lat Krabang | M6: DAIRECK S.A. | N6: Julieta | O6: 1450 | P6: 4350 | Q6: 1450 | R6: =3300/24*G6 -> 412.5 | S6: =P6-R6 -> 3937.5 | T6: 0 | V6: 6443191850 | W6: COSCO | X6: PAITA | Y6: Fresco | Z6: 10005781 | AA6: Compensación | AB6: =B6&Z6&AA6 -> ENERO10005781Compensación | AC6: =INDEX('Detalle Costos'!$L$5:$L$158,MATCH(Resumen!AB6,'Detalle Costos'!$C$5:$C$158,0))*1000+4623.769999996/248 -> 1998.6442 | AD6: =IFERROR(INDEX('Detalle Costos'!$X$5:$X$158,MATCH(Resumen!AB6,'Detalle Costos'!$C$5:$C$158,0))*AH6,0) -> 3611.3123 | AE6: =IFERROR(INDEX('Detalle Costos'!$Z$5:$Z$158,MATCH(Resumen!AB6,'Detalle Costos'!$C$5:$C$158,0))*AH6,0) -> 1180.1894 | AF6: =IFERROR(INDEX('Detalle Costos'!$Y$5:$Y$158,MATCH(Resumen!AB6,'Detalle Costos'!$C$5:$C$158,0))*AH6,0) -> 48.013379 | AG6: =IFERROR(INDEX('Detalle Costos'!$AA$5:$AA$158,MATCH(Resumen!AB6,'Detalle Costos'!$C$5:$C$158,0))*AH6,0) -> 870.12557 | AH6: =AJ6*G6+6518.87/248*G6 -> 5709.6406 | AI6: 3 | AJ6: 1876.9278 | AK6: 5803.9692 | AL6: =P6-AH6 -> -1359.6406 | AM6: =AL6/P6 -> -0.31256106 | AN6: =R6 -> 412.5 | AO6: =118461.136538461/5988.21*G6+6*G6 -> 77.347185 | AP6: 0 | AQ6: =SUM(AN6:AP6) -> 489.84719 | AR6: =50659/248*G6 -> 612.81048 | AS6: =S6*0.03 -> 118.125 | AT6: =AL6-AQ6-AR6+AS6 -> -2344.1733 | AU6: =AT6/P6 -> -0.53889041 | AV6: =131251/248*G6 -> 1587.7137 | AW6: =AT6-AV6 -> -3931.887 | AX6: =AW6/P6 -> -0.90388207 | AY6: =123844.283333333/248*G6 -> 1498.1163 | AZ6: =AT6+AY6 -> -846.05697 | BA6: =AZ6/P6 -> -0.19449586 | BC6: =P6/$G6 -> 1450 | BD6: =-AD6/$G6 -> -1203.7708 | BE6: =-AE6/$G6 -> -393.39646 | BF6: =-AF6/$G6 -> -16.00446 | BG6: =-AG6/$G6 -> -290.04186 | BH6: =-AH6/$G6 -> -1903.2135 | BI6: =AL6/$G6 -> -453.21354 | BJ6: =-AN6/$G6 -> -137.5 | BK6: =-AP6/$G6 -> 0 | BL6: =-AQ6/$G6 -> -163.2824 | BM6: =-AR6/$G6 -> -204.27016 | BN6: =AS6/$G6 -> 39.375 | BO6: =AT6/$G6 -> -781.3911 | BP6: =-AV6/$G6 -> -529.2379 | BQ6: =AW6/$G6 -> -1310.629 | BR6: =AY6/$G6 -> 499.37211 | BS6: =AZ6/$G6 -> -282.01899
B7: ENERO | C7: =B7 -> ENERO | D7: 128-2025B | E7: 325 | F7: 46053 | G7: 3.96 | H7: POTA REJOS CONGELADOS | I7: Rejos | J7: 1 - 2 kgs. | K7: Tailandia | L7: Lat Krabang | M7: DAIRECK S.A. | N7: Julieta | O7: =P7/G7 -> 2234.3434 | P7: 8848 | Q7: 2800 | R7: =3300/24*G7 -> 544.5 | S7: =P7-R7 -> 8303.5 | T7: 0 | V7: 6443191850 | W7: COSCO | X7: PAITA | Y7: Fresco | Z7: 10007162 | AA7: Compensación | AB7: =B7&Z7&AA7 -> ENERO10007162Compensación | AC7: =INDEX('Detalle Costos'!$L$5:$L$158,MATCH(Resumen!AB7,'Detalle Costos'!$C$5:$C$158,0))*1000+4623.769999996/248 -> 1808.6442 | AD7: =IFERROR(INDEX('Detalle Costos'!$X$5:$X$158,MATCH(Resumen!AB7,'Detalle Costos'!$C$5:$C$158,0))*AH7,0) -> 4667.691 | AE7: =IFERROR(INDEX('Detalle Costos'!$Z$5:$Z$158,MATCH(Resumen!AB7,'Detalle Costos'!$C$5:$C$158,0))*AH7,0) -> 1231.5249 | AF7: =IFERROR(INDEX('Detalle Costos'!$Y$5:$Y$158,MATCH(Resumen!AB7,'Detalle Costos'!$C$5:$C$158,0))*AH7,0) -> 62.750793 | AG7: =IFERROR(INDEX('Detalle Costos'!$AA$5:$AA$158,MATCH(Resumen!AB7,'Detalle Costos'!$C$5:$C$158,0))*AH7,0) -> 1223.9163 | AH7: =AJ7*G7+6518.87/248*G7 -> 7185.8829 | AI7: 3.16 | AJ7: 1788.3311 | AK7: 5822.9227 | AL7: =P7-AH7 -> 1662.1171 | AM7: =AL7/P7 -> 0.1878523 | AN7: =R7 -> 544.5 | AO7: =118461.136538461/5988.21*G7+6*G7 -> 102.09828 | AP7: 0 | AQ7: =SUM(AN7:AP7) -> 646.59828 | AR7: =50659/248*G7 -> 808.90984 | AS7: =S7*0.03 -> 249.105 | AT7: =AL7-AQ7-AR7+AS7 -> 455.71398 | AU7: =AT7/P7 -> 0.051504745 | AV7: =131251/248*G7 -> 2095.7821 | AW7: =AT7-AV7 -> -1640.0681 | AX7: =AW7/P7 -> -0.18536032 | AY7: =123844.283333333/248*G7 -> 1977.5136 | AZ7: =AT7+AY7 -> 2433.2275 | BA7: =AZ7/P7 -> 0.27500311 | BC7: =P7/$G7 -> 2234.3434 | BD7: =-AD7/$G7 -> -1178.7098 | BE7: =-AE7/$G7 -> -310.99112 | BF7: =-AF7/$G7 -> -15.84616 | BG7: =-AG7/$G7 -> -309.06977 | BH7: =-AH7/$G7 -> -1814.6169 | BI7: =AL7/$G7 -> 419.72654 | BJ7: =-AN7/$G7 -> -137.5 | BK7: =-AP7/$G7 -> 0 | BL7: =-AQ7/$G7 -> -163.2824 | BM7: =-AR7/$G7 -> -204.27016 | BN7: =AS7/$G7 -> 62.905303 | BO7: =AT7/$G7 -> 115.07929 | BP7: =-AV7/$G7 -> -529.2379 | BQ7: =AW7/$G7 -> -414.15861 | BR7: =AY7/$G7 -> 499.37211 | BS7: =AZ7/$G7 -> 614.4514
B8: ENERO | C8: =B8 -> ENERO | D8: 129-2025 | E8: 45982 | F8: 46031 | G8: 24 | H8: POTA CONOS | I8: Conos | K8: Tailandia | L8: Bangkok | M8: TSUJINO | N8: Jose | O8: 2100 | P8: 50400 | Q8: 1962.5 | R8: 3300 | S8: =P8-R8 -> 47100 | T8: 1 | U8: ECO MARIN 26002S | V8: 6440924270 | W8: COSCO | X8: PAITA | Y8: Subproducto | Z8: 10007969 | AA8: Compensación | AB8: =B8&Z8&AA8 -> ENERO10007969Compensación | AC8: =INDEX('Detalle Costos'!$L$5:$L$158,MATCH(Resumen!AB8,'Detalle Costos'!$C$5:$C$158,0))*1000+4623.769999996/248 -> 1658.6442 | AD8: =IFERROR(INDEX('Detalle Costos'!$X$5:$X$158,MATCH(Resumen!AB8,'Detalle Costos'!$C$5:$C$158,0))*AH8,0) -> 30999.473 | AE8: =IFERROR(INDEX('Detalle Costos'!$Z$5:$Z$158,MATCH(Resumen!AB8,'Detalle Costos'!$C$5:$C$158,0))*AH8,0) -> 5431.3037 | AF8: =IFERROR(INDEX('Detalle Costos'!$Y$5:$Y$158,MATCH(Resumen!AB8,'Detalle Costos'!$C$5:$C$158,0))*AH8,0) -> 411.06065 | AG8: =IFERROR(INDEX('Detalle Costos'!$AA$5:$AA$158,MATCH(Resumen!AB8,'Detalle Costos'!$C$5:$C$158,0))*AH8,0) -> 3252.6203 | AH8: =AJ8*G8+6518.87/248*G8 -> 40094.458 | AI8: 24 | AJ8: =+AK8/AI8 -> 1644.3167 | AK8: 39463.6 | AL8: =P8-AH8 -> 10305.542 | AM8: =AL8/P8 -> 0.20447504 | AN8: =R8 -> 3300 | AO8: =118461.136538461/5988.21*G8+6*G8 -> 618.77748 | AP8: 0 | AQ8: =SUM(AN8:AP8) -> 3918.7775 | AR8: =50659/248*G8 -> 4902.4839 | AS8: =S8*0.03 -> 1413 | AT8: =AL8-AQ8-AR8+AS8 -> 2897.2806 | AU8: =AT8/P8 -> 0.057485727 | AV8: =131251/248*G8 -> 12701.71 | AW8: =AT8-AV8 -> -9804.429 | AX8: =AW8/P8 -> -0.19453232 | AY8: =123844.283333333/248*G8 -> 11984.931 | AZ8: =AT8+AY8 -> 14882.211 | BA8: =AZ8/P8 -> 0.29528197 | BC8: =P8/$G8 -> 2100 | BD8: =-AD8/$G8 -> -1291.6447 | BE8: =-AE8/$G8 -> -226.30432 | BF8: =-AF8/$G8 -> -17.127527 | BG8: =-AG8/$G8 -> -135.52585 | BH8: =-AH8/$G8 -> -1670.6024 | BI8: =AL8/$G8 -> 429.39758 | BJ8: =-AN8/$G8 -> -137.5 | BK8: =-AP8/$G8 -> 0 | BL8: =-AQ8/$G8 -> -163.2824 | BM8: =-AR8/$G8 -> -204.27016 | BN8: =AS8/$G8 -> 58.875 | BO8: =AT8/$G8 -> 120.72003 | BP8: =-AV8/$G8 -> -529.2379 | BQ8: =AW8/$G8 -> -408.51788 | BR8: =AY8/$G8 -> 499.37211 | BS8: =AZ8/$G8 -> 620.09214
B9: ENERO | C9: =B9 -> ENERO | D9: 137-2025 | E9: 46000 | F9: 46043 | G9: 24 | H9: POTA FILETE CONGELADO | I9: Filete | J9: 2 - 4 kg | K9: Taiwan | L9: KAOHSIUNG | M9: TSUJINO | N9: Jose | O9: =P9/G9 -> 1966.6667 | P9: =48000*0+47200 -> 47200 | Q9: =S9/G9 -> 1841.5417 | R9: 3003 | S9: =P9-R9 -> 44197 | T9: 1 | U9: ECO MARIN 25052N | V9: LIMF26385300 | W9: ONE | X9: PAITA | Y9: Fresco | Z9: 10005721 | AA9: Compensación | AB9: =B9&Z9&AA9 -> ENERO10005721Compensación | AC9: =INDEX('Detalle Costos'!$L$5:$L$158,MATCH(Resumen!AB9,'Detalle Costos'!$C$5:$C$158,0))*1000+4623.769999996/248 -> 1878.6442 | AD9: =IFERROR(INDEX('Detalle Costos'!$X$5:$X$158,MATCH(Resumen!AB9,'Detalle Costos'!$C$5:$C$158,0))*AH9,0) -> 27693.143 | AE9: =IFERROR(INDEX('Detalle Costos'!$Z$5:$Z$158,MATCH(Resumen!AB9,'Detalle Costos'!$C$5:$C$158,0))*AH9,0) -> 10045.917 | AF9: =IFERROR(INDEX('Detalle Costos'!$Y$5:$Y$158,MATCH(Resumen!AB9,'Detalle Costos'!$C$5:$C$158,0))*AH9,0) -> 437.14794 | AG9: =IFERROR(INDEX('Detalle Costos'!$AA$5:$AA$158,MATCH(Resumen!AB9,'Detalle Costos'!$C$5:$C$158,0))*AH9,0) -> 7483.3567 | AH9: =AJ9*G9+6518.87/248*G9 -> 45659.565 | AI9: 23.7 | AJ9: 1876.1961 | AK9: 44778.445 | AL9: =P9-AH9 -> 1540.4346 | AM9: =AL9/P9 -> 0.032636327 | AN9: =R9 -> 3003 | AO9: =118461.136538461/5988.21*G9+6*G9 -> 618.77748 | AP9: 0 | AQ9: =SUM(AN9:AP9) -> 3621.7775 | AR9: =50659/248*G9 -> 4902.4839 | AS9: =S9*0.03 -> 1325.91 | AT9: =AL9-AQ9-AR9+AS9 -> -5657.9167 | AU9: =AT9/P9 -> -0.11987112 | AV9: =131251/248*G9 -> 12701.71 | AW9: =AT9-AV9 -> -18359.626 | AX9: =AW9/P9 -> -0.38897514 | AY9: =123844.283333333/248*G9 -> 11984.931 | AZ9: =AT9+AY9 -> 6327.0139 | BA9: =AZ9/P9 -> 0.13404691 | BC9: =P9/$G9 -> 1966.6667 | BD9: =-AD9/$G9 -> -1153.881 | BE9: =-AE9/$G9 -> -418.57989 | BF9: =-AF9/$G9 -> -18.214497 | BG9: =-AG9/$G9 -> -311.80653 | BH9: =-AH9/$G9 -> -1902.4819 | BI9: =AL9/$G9 -> 64.184777 | BJ9: =-AN9/$G9 -> -125.125 | BK9: =-AP9/$G9 -> 0 | BL9: =-AQ9/$G9 -> -150.9074 | BM9: =-AR9/$G9 -> -204.27016 | BN9: =AS9/$G9 -> 55.24625 | BO9: =AT9/$G9 -> -235.74653 | BP9: =-AV9/$G9 -> -529.2379 | BQ9: =AW9/$G9 -> -764.98443 | BR9: =AY9/$G9 -> 499.37211 | BS9: =AZ9/$G9 -> 263.62558
B10: ENERO | C10: =B10 -> ENERO | D10: 140-2025 | E10: 347 | F10: 46038 | G10: 24 | H10: POTA FILETE CONGELADO | I10: Filete | J10: 2-4kg | K10: Japón | L10: Sendai | M10: TSUJINO | N10: Jose | O10: =P10/G10 -> 1983.3333 | P10: =48000*0+47600 -> 47600 | Q10: =S10/G10 -> 1845.7083 | R10: 3303 | S10: =P10-R10 -> 44297 | T10: 1 | U10: ECO SIROCCO 26003S | V10: LIMG00358300 | W10: ONE | X10: PAITA | Y10: Fresco | Z10: 10005721 | AA10: Compensación | AB10: =B10&Z10&AA10 -> ENERO10005721Compensación | AC10: =INDEX('Detalle Costos'!$L$5:$L$158,MATCH(Resumen!AB10,'Detalle Costos'!$C$5:$C$158,0))*1000+4623.769999996/248 -> 1878.6442 | AD10: =IFERROR(INDEX('Detalle Costos'!$X$5:$X$158,MATCH(Resumen!AB10,'Detalle Costos'!$C$5:$C$158,0))*AH10,0) -> 27693.143 | AE10: =IFERROR(INDEX('Detalle Costos'!$Z$5:$Z$158,MATCH(Resumen!AB10,'Detalle Costos'!$C$5:$C$158,0))*AH10,0) -> 10045.917 | AF10: =IFERROR(INDEX('Detalle Costos'!$Y$5:$Y$158,MATCH(Resumen!AB10,'Detalle Costos'!$C$5:$C$158,0))*AH10,0) -> 437.14794 | AG10: =IFERROR(INDEX('Detalle Costos'!$AA$5:$AA$158,MATCH(Resumen!AB10,'Detalle Costos'!$C$5:$C$158,0))*AH10,0) -> 7483.3567 | AH10: =AJ10*G10+6518.87/248*G10 -> 45659.565 | AI10: 23.7 | AJ10: 1876.1961 | AK10: 44778.445 | AL10: =P10-AH10 -> 1940.4346 | AM10: =AL10/P10 -> 0.040765434 | AN10: =R10 -> 3303 | AO10: =118461.136538461/5988.21*G10+6*G10 -> 618.77748 | AP10: 0 | AQ10: =SUM(AN10:AP10) -> 3921.7775 | AR10: =50659/248*G10 -> 4902.4839 | AS10: =S10*0.03 -> 1328.91 | AT10: =AL10-AQ10-AR10+AS10 -> -5554.9167 | AU10: =AT10/P10 -> -0.11669993 | AV10: =131251/248*G10 -> 12701.71 | AW10: =AT10-AV10 -> -18256.626 | AX10: =AW10/P10 -> -0.38354257 | AY10: =123844.283333333/248*G10 -> 11984.931 | AZ10: =AT10+AY10 -> 6430.0139 | BA10: =AZ10/P10 -> 0.13508433 | BC10: =P10/$G10 -> 1983.3333 | BD10: =-AD10/$G10 -> -1153.881 | BE10: =-AE10/$G10 -> -418.57989 | BF10: =-AF10/$G10 -> -18.214497 | BG10: =-AG10/$G10 -> -311.80653 | BH10: =-AH10/$G10 -> -1902.4819 | BI10: =AL10/$G10 -> 80.851443 | BJ10: =-AN10/$G10 -> -137.625 | BK10: =-AP10/$G10 -> 0 | BL10: =-AQ10/$G10 -> -163.4074 | BM10: =-AR10/$G10 -> -204.27016 | BN10: =AS10/$G10 -> 55.37125 | BO10: =AT10/$G10 -> -231.45486 | BP10: =-AV10/$G10 -> -529.2379 | BQ10: =AW10/$G10 -> -760.69277 | BR10: =AY10/$G10 -> 499.37211 | BS10: =AZ10/$G10 -> 267.91725
B11: ENERO | C11: =B11 -> ENERO | D11: 145-2025 | E11: 46020 | F11: 46041 | G11: 54 | H11: POTA REJOS CONGELADOS | I11: Rejos | J11: 500-1 / 1-2 | K11: España | L11: Vigo | M11: GLOBAL OCEAN | N11: Jorge | O11: 2600 | P11: 140400 | Q11: 2430.963 | R11: 9128 | S11: =P11-R11 -> 131272 | T11: 2 | U11: IZMIT EXPRESS 604N | V11: 28952064 | W11: HAPAG | X11: PAITA | Y11: Fresco | Z11: 10007162 | AA11: Compensación | AB11: =B11&Z11&AA11 -> ENERO10007162Compensación | AC11: =INDEX('Detalle Costos'!$L$5:$L$158,MATCH(Resumen!AB11,'Detalle Costos'!$C$5:$C$158,0))*1000+4623.769999996/248 -> 1808.6442 | AD11: =IFERROR(INDEX('Detalle Costos'!$X$5:$X$158,MATCH(Resumen!AB11,'Detalle Costos'!$C$5:$C$158,0))*AH11,0) -> 63650.331 | AE11: =IFERROR(INDEX('Detalle Costos'!$Z$5:$Z$158,MATCH(Resumen!AB11,'Detalle Costos'!$C$5:$C$158,0))*AH11,0) -> 16793.521 | AF11: =IFERROR(INDEX('Detalle Costos'!$Y$5:$Y$158,MATCH(Resumen!AB11,'Detalle Costos'!$C$5:$C$158,0))*AH11,0) -> 855.69263 | AG11: =IFERROR(INDEX('Detalle Costos'!$AA$5:$AA$158,MATCH(Resumen!AB11,'Detalle Costos'!$C$5:$C$158,0))*AH11,0) -> 16689.768 | AH11: =AJ11*G11+6518.87/248*G11 -> 97989.312 | AI11: 54 | AJ11: 1788.3311 | AK11: 99505.64 | AL11: =P11-AH11 -> 42410.688 | AM11: =AL11/P11 -> 0.30207043 | AN11: =R11 -> 9128 | AO11: =118461.136538461/5988.21*G11+6*G11 -> 1392.2493 | AP11: 0 | AQ11: =SUM(AN11:AP11) -> 10520.249 | AR11: =50659/248*G11 -> 11030.589 | AS11: =S11*0.03 -> 3938.16 | AT11: =AL11-AQ11-AR11+AS11 -> 24798.01 | AU11: =AT11/P11 -> 0.176624 | AV11: =131251/248*G11 -> 28578.847 | AW11: =AT11-AV11 -> -3780.837 | AX11: =AW11/P11 -> -0.026929038 | AY11: =123844.283333333/248*G11 -> 26966.094 | AZ11: =AT11+AY11 -> 51764.104 | BA11: =AZ11/P11 -> 0.3686902 | BC11: =P11/$G11 -> 2600 | BD11: =-AD11/$G11 -> -1178.7098 | BE11: =-AE11/$G11 -> -310.99112 | BF11: =-AF11/$G11 -> -15.84616 | BG11: =-AG11/$G11 -> -309.06977 | BH11: =-AH11/$G11 -> -1814.6169 | BI11: =AL11/$G11 -> 785.38311 | BJ11: =-AN11/$G11 -> -169.03704 | BK11: =-AP11/$G11 -> 0 | BL11: =-AQ11/$G11 -> -194.81943 | BM11: =-AR11/$G11 -> -204.27016 | BN11: =AS11/$G11 -> 72.928889 | BO11: =AT11/$G11 -> 459.2224 | BP11: =-AV11/$G11 -> -529.2379 | BQ11: =AW11/$G11 -> -70.0155 | BR11: =AY11/$G11 -> 499.37211 | BS11: =AZ11/$G11 -> 958.59451
B12: FEBRERO | C12: =B12 -> FEBRERO | D12: 146-2026 | E12: 46027 | F12: 46059 | G12: 10 | H12: POTA CONOS | I12: Conos | J12: 10 cm - up | K12: Tailandia | L12: Lat Krabang | M12: TSUJINO | N12: Jose | O12: 2100 | P12: 21000 | Q12: 2100 | R12: =3500/24*G12 -> 1458.3333 | S12: =P12-R12 -> 19541.667 | T12: 1 | U12: ECO MARIN 26006S | V12: 6444023300 | W12: COSCO | X12: PAITA | Y12: Subproducto | Z12: 10007969 | AA12: Compensación | AB12: =B12&Z12&AA12 -> FEBRERO10007969Compensación | AC12: =INDEX('Detalle Costos'!$L$5:$L$158,MATCH(Resumen!AB12,'Detalle Costos'!$C$5:$C$158,0))*1000*0+AJ12+229398.68/1634.3 -> 1345.444 | AD12: =IFERROR(INDEX('Detalle Costos'!$X$5:$X$158,MATCH(Resumen!AB12,'Detalle Costos'!$C$5:$C$158,0))*AH12,0) -> 10882.579 | AE12: =IFERROR(INDEX('Detalle Costos'!$Z$5:$Z$158,MATCH(Resumen!AB12,'Detalle Costos'!$C$5:$C$158,0))*AH12,0) -> 2048.545 | AF12: =IFERROR(INDEX('Detalle Costos'!$Y$5:$Y$158,MATCH(Resumen!AB12,'Detalle Costos'!$C$5:$C$158,0))*AH12,0) -> 160.64285 | AG12: =IFERROR(INDEX('Detalle Costos'!$AA$5:$AA$158,MATCH(Resumen!AB12,'Detalle Costos'!$C$5:$C$158,0))*AH12,0) -> 362.67255 | AH12: =AC12*G12 -> 13454.44 | AI12: =+G12 -> 10 | AJ12: 1205.0789 | AK12: =+AJ12*AI12 -> 12050.789 | AL12: =P12-AH12 -> 7545.5601 | AM12: =AL12/P12 -> 0.35931239 | AN12: =R12 -> 1458.3333 | AO12: =118461.136538461/5988.21*G12 -> 197.82395 | AP12: =-10174.6784147361/1634*G12 -> -62.268534 | AQ12: =SUM(AN12:AP12) -> 1593.8888 | AR12: =56604/1634.3*G12 -> 346.35012 | AS12: =S12*0.03 -> 586.25 | AT12: =AL12-AQ12-AR12+AS12 -> 6191.5713 | AU12: =AT12/P12 -> 0.29483673 | AV12: =148498/1634.3*G12 -> 908.63367 | AW12: =AT12-AV12 -> 5282.9376 | AX12: =AW12/P12 -> 0.25156846 | AY12: =123844.283333333/1634.3*G12 -> 757.78182 | AZ12: =AT12+AY12 -> 6949.3531 | BA12: =AZ12/P12 -> 0.33092158 | BC12: =P12/$G12 -> 2100 | BD12: =-AD12/$G12 -> -1088.2579 | BE12: =-AE12/$G12 -> -204.8545 | BF12: =-AF12/$G12 -> -16.064285 | BG12: =-AG12/$G12 -> -36.267255 | BH12: =-AH12/$G12 -> -1345.444 | BI12: =AL12/$G12 -> 754.55601 | BJ12: =-AN12/$G12 -> -145.83333 | BK12: =-AP12/$G12 -> 6.2268534 | BL12: =-AQ12/$G12 -> -159.38888 | BM12: =-AR12/$G12 -> -34.635012 | BN12: =AS12/$G12 -> 58.625 | BO12: =AT12/$G12 -> 619.15713 | BP12: =-AV12/$G12 -> -90.863367 | BQ12: =AW12/$G12 -> 528.29376 | BR12: =AY12/$G12 -> 75.778182 | BS12: =AZ12/$G12 -> 694.93531
B13: FEBRERO | C13: =B13 -> FEBRERO | D13: 146-2026 | E13: 46027 | F13: 46059 | G13: 14 | H13: POTA NUCAS | I13: Nucas | J13: 500-up | K13: Tailandia | L13: Lat Krabang | M13: TSUJINO | N13: Jose | O13: 1700 | P13: =23800-344 -> 23456 | Q13: 1700 | R13: =3500/24*G13 -> 2041.6667 | S13: =P13-R13 -> 21414.333 | T13: 0 | Y13: Fresco | Z13: 10005779 | AA13: Compensación | AB13: =B13&Z13&AA13 -> FEBRERO10005779Compensación | AC13: =INDEX('Detalle Costos'!$L$5:$L$158,MATCH(Resumen!AB13,'Detalle Costos'!$C$5:$C$158,0))*1000*0+AJ13+229398.68/1634.3 -> 1887.9651 | AD13: =IFERROR(INDEX('Detalle Costos'!$X$5:$X$158,MATCH(Resumen!AB13,'Detalle Costos'!$C$5:$C$158,0))*AH13,0) -> 16088.613 | AE13: =IFERROR(INDEX('Detalle Costos'!$Z$5:$Z$158,MATCH(Resumen!AB13,'Detalle Costos'!$C$5:$C$158,0))*AH13,0) -> 5819.4874 | AF13: =IFERROR(INDEX('Detalle Costos'!$Y$5:$Y$158,MATCH(Resumen!AB13,'Detalle Costos'!$C$5:$C$158,0))*AH13,0) -> 192.80525 | AG13: =IFERROR(INDEX('Detalle Costos'!$AA$5:$AA$158,MATCH(Resumen!AB13,'Detalle Costos'!$C$5:$C$158,0))*AH13,0) -> 4330.6058 | AH13: =AC13*G13 -> 26431.511 | AI13: 14.849 | AJ13: 1747.6 | AK13: =AJ13*AI13 -> 25950.112 | AL13: =P13-AH13 -> -2975.5114 | AM13: =AL13/P13 -> -0.12685502 | AN13: =R13 -> 2041.6667 | AO13: =118461.136538461/5988.21*G13 -> 276.95353 | AP13: =-10174.6784147361/1634*G13 -> -87.175947 | AQ13: =SUM(AN13:AP13) -> 2231.4443 | AR13: =56604/1634.3*G13 -> 484.89017 | AS13: =S13*0.03 -> 642.43 | AT13: =AL13-AQ13-AR13+AS13 -> -5049.4158 | AU13: =AT13/P13 -> -0.21527182 | AV13: =148498/1634.3*G13 -> 1272.0871 | AW13: =AT13-AV13 -> -6321.5029 | AX13: =AW13/P13 -> -0.26950473 | AY13: =123844.283333333/1634.3*G13 -> 1060.8946 | AZ13: =AT13+AY13 -> -3988.5212 | BA13: =AZ13/P13 -> -0.17004269 | BC13: =P13/$G13 -> 1675.4286 | BD13: =-AD13/$G13 -> -1149.1866 | BE13: =-AE13/$G13 -> -415.67767 | BF13: =-AF13/$G13 -> -13.771803 | BG13: =-AG13/$G13 -> -309.32898 | BH13: =-AH13/$G13 -> -1887.9651 | BI13: =AL13/$G13 -> -212.53653 | BJ13: =-AN13/$G13 -> -145.83333 | BK13: =-AP13/$G13 -> 6.2268534 | BL13: =-AQ13/$G13 -> -159.38888 | BM13: =-AR13/$G13 -> -34.635012 | BN13: =AS13/$G13 -> 45.887857 | BO13: =AT13/$G13 -> -360.67256 | BP13: =-AV13/$G13 -> -90.863367 | BQ13: =AW13/$G13 -> -451.53592 | BR13: =AY13/$G13 -> 75.778182 | BS13: =AZ13/$G13 -> -284.89437
B14: ENERO | C14: =B14 -> ENERO | D14: 147-2026 | E14: 46032 | F14: 46050 | G14: 72 | H14: POTA ALAS CONGELADAS | I14: Alas | J14: 1 - 2 KGS. | K14: Tailandia | L14: Bangkok | M14: TSUJINO | N14: Jose | O14: =P14/G14 -> 1887.7083 | P14: =140400*0+135915 -> 135915 | Q14: =S14/G14 -> 1754.25 | R14: 9609 | S14: =P14-R14 -> 126306 | T14: 3 | U14: ECO MARIN 26004N | V14: LIMG01524600 | W14: ONE | X14: PAITA | Y14: Fresco | Z14: 10006720 | AA14: Compensación | AB14: =B14&Z14&AA14 -> ENERO10006720Compensación | AC14: =INDEX('Detalle Costos'!$L$5:$L$158,MATCH(Resumen!AB14,'Detalle Costos'!$C$5:$C$158,0))*1000+4623.769999996/248 -> 1738.6442 | AD14: =IFERROR(INDEX('Detalle Costos'!$X$5:$X$158,MATCH(Resumen!AB14,'Detalle Costos'!$C$5:$C$158,0))*AH14,0) -> 82959.134 | AE14: =IFERROR(INDEX('Detalle Costos'!$Z$5:$Z$158,MATCH(Resumen!AB14,'Detalle Costos'!$C$5:$C$158,0))*AH14,0) -> 19195.713 | AF14: =IFERROR(INDEX('Detalle Costos'!$Y$5:$Y$158,MATCH(Resumen!AB14,'Detalle Costos'!$C$5:$C$158,0))*AH14,0) -> 1203.1653 | AG14: =IFERROR(INDEX('Detalle Costos'!$AA$5:$AA$158,MATCH(Resumen!AB14,'Detalle Costos'!$C$5:$C$158,0))*AH14,0) -> 22291.587 | AH14: =AJ14*G14+6518.87/248*G14 -> 125649.6 | AI14: 69.7 | AJ14: 1718.8476 | AK14: 120156.94 | AL14: =P14-AH14 -> 10265.4 | AM14: =AL14/P14 -> 0.075528091 | AN14: =R14 -> 9609 | AO14: =118461.136538461/5988.21*G14+6*G14 -> 1856.3325 | AP14: 0 | AQ14: =SUM(AN14:AP14) -> 11465.332 | AR14: =50659/248*G14 -> 14707.452 | AS14: =S14*0.03 -> 3789.18 | AT14: =AL14-AQ14-AR14+AS14 -> -12118.204 | AU14: =AT14/P14 -> -0.089160163 | AV14: =131251/248*G14 -> 38105.129 | AW14: =AT14-AV14 -> -50223.333 | AX14: =AW14/P14 -> -0.36952016 | AY14: =123844.283333333/248*G14 -> 35954.792 | AZ14: =AT14+AY14 -> 23836.588 | BA14: =AZ14/P14 -> 0.17537864 | BC14: =P14/$G14 -> 1887.7083 | BD14: =-AD14/$G14 -> -1152.2102 | BE14: =-AE14/$G14 -> -266.60713 | BF14: =-AF14/$G14 -> -16.710629 | BG14: =-AG14/$G14 -> -309.60537 | BH14: =-AH14/$G14 -> -1745.1333 | BI14: =AL14/$G14 -> 142.57501 | BJ14: =-AN14/$G14 -> -133.45833 | BK14: =-AP14/$G14 -> 0 | BL14: =-AQ14/$G14 -> -159.24073 | BM14: =-AR14/$G14 -> -204.27016 | BN14: =AS14/$G14 -> 52.6275 | BO14: =AT14/$G14 -> -168.30838 | BP14: =-AV14/$G14 -> -529.2379 | BQ14: =AW14/$G14 -> -697.54629 | BR14: =AY14/$G14 -> 499.37211 | BS14: =AZ14/$G14 -> 331.06373
B15: ENERO | C15: =B15 -> ENERO | E15: 46053 | F15: 46053 | G15: 0 | H15: RESIDUOS DE POTA | I15: Residuos | J15: Residuos | K15: Residuos | L15: Residuos | M15: PROVEEDORA DE PRODUCTOS MARINOS | O15: 0 | P15: 24314.28 | Q15: 0 | R15: 0 | S15: =P15-R15 -> 24314.28 | Y15: Residuo | AC15: 0 | AD15: =IFERROR(INDEX('Detalle Costos'!$X$5:$X$158,MATCH(Resumen!AB15,'Detalle Costos'!$C$5:$C$158,0))*AH15,0) -> 0 | AE15: =IFERROR(INDEX('Detalle Costos'!$Z$5:$Z$158,MATCH(Resumen!AB15,'Detalle Costos'!$C$5:$C$158,0))*AH15,0) -> 0 | AF15: =IFERROR(INDEX('Detalle Costos'!$Y$5:$Y$158,MATCH(Resumen!AB15,'Detalle Costos'!$C$5:$C$158,0))*AH15,0) -> 0 | AG15: =IFERROR(INDEX('Detalle Costos'!$AA$5:$AA$158,MATCH(Resumen!AB15,'Detalle Costos'!$C$5:$C$158,0))*AH15,0) -> 0 | AH15: =AJ15*G15 -> 0 | AL15: =P15-AH15 -> 24314.28 | AM15: =AL15/P15 -> 1 | AN15: =R15 -> 0 | AO15: =118461.136538461/5988.21*G15 -> 0 | AP15: 0 | AQ15: =SUM(AN15:AP15) -> 0 | AR15: =50659/248*G15 -> 0 | AS15: 0 | AT15: =AL15-AQ15-AR15+AS15 -> 24314.28 | AU15: =AT15/P15 -> 1 | AV15: =131251/248*G15 -> 0 | AW15: =AT15-AV15 -> 24314.28 | AX15: =AW15/P15 -> 1 | AY15: =123844.283333333/248*G15 -> 0 | AZ15: =AT15+AY15 -> 24314.28 | BA15: =AZ15/P15 -> 1 | BC15: =P15/$G15 -> #DIV/0! | BD15: =-AD15/$G15 -> #DIV/0! | BE15: =-AE15/$G15 -> #DIV/0! | BF15: =-AF15/$G15 -> #DIV/0! | BG15: =-AG15/$G15 -> #DIV/0! | BH15: =-AH15/$G15 -> #DIV/0! | BI15: =AL15/$G15 -> #DIV/0! | BJ15: =-AN15/$G15 -> #DIV/0! | BK15: =-AP15/$G15 -> #DIV/0! | BL15: =-AQ15/$G15 -> #DIV/0! | BM15: =-AR15/$G15 -> #DIV/0! | BN15: =AS15/$G15 -> #DIV/0! | BO15: =AT15/$G15 -> #DIV/0! | BP15: =-AV15/$G15 -> #DIV/0! | BQ15: =AW15/$G15 -> #DIV/0! | BR15: =AY15/$G15 -> #DIV/0! | BS15: =AZ15/$G15 -> #DIV/0!
B16: FEBRERO | C16: =B16 -> FEBRERO | D16: 148-2026 | E16: 15 | F16: 46055 | G16: 135 | H16: POTA FILETE CONGELADO | I16: Filete | J16: 2-4 (B) | K16: España | L16: Vigo | M16: FOOD & BEVERAGES TRADERS | N16: Jorge | O16: 1650 | P16: 222750 | Q16: 1480.963 | R16: 22820 | S16: =P16-R16 -> 199930 | T16: 5 | U16: ODYSSEUS 606N | V16: 59582082 | W16: HAPAG | X16: PAITA | Y16: Fresco | Z16: 10005721 | AA16: Compensación | AB16: =B16&Z16&AA16 -> FEBRERO10005721Compensación | AC16: =INDEX('Detalle Costos'!$L$5:$L$158,MATCH(Resumen!AB16,'Detalle Costos'!$C$5:$C$158,0))*1000*0+AJ16+229398.68/1634.3 -> 1812.5717 | AD16: =IFERROR(INDEX('Detalle Costos'!$X$5:$X$158,MATCH(Resumen!AB16,'Detalle Costos'!$C$5:$C$158,0))*AH16,0) -> 148491.05 | AE16: =IFERROR(INDEX('Detalle Costos'!$Z$5:$Z$158,MATCH(Resumen!AB16,'Detalle Costos'!$C$5:$C$158,0))*AH16,0) -> 49055.886 | AF16: =IFERROR(INDEX('Detalle Costos'!$Y$5:$Y$158,MATCH(Resumen!AB16,'Detalle Costos'!$C$5:$C$158,0))*AH16,0) -> 2609.6487 | AG16: =IFERROR(INDEX('Detalle Costos'!$AA$5:$AA$158,MATCH(Resumen!AB16,'Detalle Costos'!$C$5:$C$158,0))*AH16,0) -> 44540.593 | AH16: =AC16*G16 -> 244697.18 | AI16: =+G16 -> 135 | AJ16: 1672.2066 | AK16: 251295.39 | AL16: =P16-AH16 -> -21947.176 | AM16: =AL16/P16 -> -0.098528286 | AN16: =R16 -> 22820 | AO16: =118461.136538461/5988.21*G16 -> 2670.6233 | AP16: =-10174.6784147361/1634*G16 -> -840.62521 | AQ16: =SUM(AN16:AP16) -> 24649.998 | AR16: =56604/1634.3*G16 -> 4675.7266 | AS16: =S16*0.03 -> 5997.9 | AT16: =AL16-AQ16-AR16+AS16 -> -45275 | AU16: =AT16/P16 -> -0.20325477 | AV16: =148498/1634.3*G16 -> 12266.554 | AW16: =AT16-AV16 -> -57541.555 | AX16: =AW16/P16 -> -0.25832348 | AY16: =123844.283333333/1634.3*G16 -> 10230.055 | AZ16: =AT16+AY16 -> -35044.946 | BA16: =AZ16/P16 -> -0.1573286 | BC16: =P16/$G16 -> 1650 | BD16: =-AD16/$G16 -> -1099.9337 | BE16: =-AE16/$G16 -> -363.37693 | BF16: =-AF16/$G16 -> -19.330731 | BG16: =-AG16/$G16 -> -329.93032 | BH16: =-AH16/$G16 -> -1812.5717 | BI16: =AL16/$G16 -> -162.57167 | BJ16: =-AN16/$G16 -> -169.03704 | BK16: =-AP16/$G16 -> 6.2268534 | BL16: =-AQ16/$G16 -> -182.59258 | BM16: =-AR16/$G16 -> -34.635012 | BN16: =AS16/$G16 -> 44.428889 | BO16: =AT16/$G16 -> -335.37037 | BP16: =-AV16/$G16 -> -90.863367 | BQ16: =AW16/$G16 -> -426.23374 | BR16: =AY16/$G16 -> 75.778182 | BS16: =AZ16/$G16 -> -259.59219
B17: FEBRERO | C17: =B17 -> FEBRERO | D17: 149-2026 | E17: 16 | F17: 46055 | G17: 27 | H17: POTA REPRODUCTORES | I17: Rejos | K17: España | L17: Vigo | M17: GLOBAL OCEAN | N17: Jorge | O17: =P17/G17 -> 2873.5185 | P17: =79650*0+77585 -> 77585 | Q17: =S17/G17 -> 2711.8889 | R17: 4364 | S17: =P17-R17 -> 73221 | T17: 1 | Y17: Fresco | Z17: 10007567 | AA17: Entradas | AB17: =B17&Z17&AA17 -> FEBRERO10007567Entradas | AC17: =INDEX('Detalle Costos'!$L$5:$L$158,MATCH(Resumen!AB17,'Detalle Costos'!$C$5:$C$158,0))*1000*0+AJ17+229398.68/1634.3 -> 1792.6009 | AD17: =IFERROR(INDEX('Detalle Costos'!$X$5:$X$158,MATCH(Resumen!AB17,'Detalle Costos'!$C$5:$C$158,0))*AH17,0) -> 29878.161 | AE17: =IFERROR(INDEX('Detalle Costos'!$Z$5:$Z$158,MATCH(Resumen!AB17,'Detalle Costos'!$C$5:$C$158,0))*AH17,0) -> 8560.8114 | AF17: =IFERROR(INDEX('Detalle Costos'!$Y$5:$Y$158,MATCH(Resumen!AB17,'Detalle Costos'!$C$5:$C$158,0))*AH17,0) -> 543.18307 | AG17: =IFERROR(INDEX('Detalle Costos'!$AA$5:$AA$158,MATCH(Resumen!AB17,'Detalle Costos'!$C$5:$C$158,0))*AH17,0) -> 9418.0679 | AH17: =AC17*G17 -> 48400.224 | AI17: 26.302 | AJ17: 1652.2358 | AK17: 48129 | AL17: =P17-AH17 -> 29184.776 | AM17: =AL17/P17 -> 0.37616519 | AN17: =R17 -> 4364 | AO17: =118461.136538461/5988.21*G17 -> 534.12467 | AP17: =-10174.6784147361/1634*G17 -> -168.12504 | AQ17: =SUM(AN17:AP17) -> 4729.9996 | AR17: =56604/1634.3*G17 -> 935.14532 | AS17: =S17*0.03 -> 2196.63 | AT17: =AL17-AQ17-AR17+AS17 -> 25716.261 | AU17: =AT17/P17 -> 0.33145919 | AV17: =148498/1634.3*G17 -> 2453.3109 | AW17: =AT17-AV17 -> 23262.951 | AX17: =AW17/P17 -> 0.29983825 | AY17: =123844.283333333/1634.3*G17 -> 2046.0109 | AZ17: =AT17+AY17 -> 27762.272 | BA17: =AZ17/P17 -> 0.35783041 | BC17: =P17/$G17 -> 2873.5185 | BD17: =-AD17/$G17 -> -1106.5986 | BE17: =-AE17/$G17 -> -317.06709 | BF17: =-AF17/$G17 -> -20.117891 | BG17: =-AG17/$G17 -> -348.81733 | BH17: =-AH17/$G17 -> -1792.6009 | BI17: =AL17/$G17 -> 1080.9176 | BJ17: =-AN17/$G17 -> -161.62963 | BK17: =-AP17/$G17 -> 6.2268534 | BL17: =-AQ17/$G17 -> -175.18517 | BM17: =-AR17/$G17 -> -34.635012 | BN17: =AS17/$G17 -> 81.356667 | BO17: =AT17/$G17 -> 952.45413 | BP17: =-AV17/$G17 -> -90.863367 | BQ17: =AW17/$G17 -> 861.59076 | BR17: =AY17/$G17 -> 75.778182 | BS17: =AZ17/$G17 -> 1028.2323
B18: FEBRERO | C18: =B18 -> FEBRERO | D18: 150-2026A | E18: 325 | F18: 46069 | G18: 26 | H18: POTA REJOS CONGELADOS | I18: Rejos | J18: 1-2 KG | K18: España | L18: Vigo | M18: OVERSEA | N18: Avelino | O18: 2600 | P18: 67600 | Q18: 2432.1538 | R18: 4364 | S18: =P18-R18 -> 63236 | T18: 1 | U18: CAPE SPENCER 608N | V18: 11400418 | W18: HAPAG | X18: PAITA | Y18: Fresco | Z18: 10007162 | AA18: Compensación | AB18: =B18&Z18&AA18 -> FEBRERO10007162Compensación | AC18: =INDEX('Detalle Costos'!$L$5:$L$158,MATCH(Resumen!AB18,'Detalle Costos'!$C$5:$C$158,0))*1000*0+AJ18+229398.68/1634.3 -> 1806.2113 | AD18: =IFERROR(INDEX('Detalle Costos'!$X$5:$X$158,MATCH(Resumen!AB18,'Detalle Costos'!$C$5:$C$158,0))*AH18,0) -> 29480.813 | AE18: =IFERROR(INDEX('Detalle Costos'!$Z$5:$Z$158,MATCH(Resumen!AB18,'Detalle Costos'!$C$5:$C$158,0))*AH18,0) -> 8412.1138 | AF18: =IFERROR(INDEX('Detalle Costos'!$Y$5:$Y$158,MATCH(Resumen!AB18,'Detalle Costos'!$C$5:$C$158,0))*AH18,0) -> 437.9741 | AG18: =IFERROR(INDEX('Detalle Costos'!$AA$5:$AA$158,MATCH(Resumen!AB18,'Detalle Costos'!$C$5:$C$158,0))*AH18,0) -> 8630.5928 | AH18: =AC18*G18 -> 46961.494 | AI18: =+G18 -> 26 | AJ18: 1665.8462 | AK18: =AJ18*AI18 -> 43312.002 | AL18: =P18-AH18 -> 20638.506 | AM18: =AL18/P18 -> 0.30530334 | AN18: =R18 -> 4364 | AO18: =118461.136538461/5988.21*G18 -> 514.34227 | AP18: =-10174.6784147361/1634*G18 -> -161.89819 | AQ18: =SUM(AN18:AP18) -> 4716.4441 | AR18: =56604/1634.3*G18 -> 900.51031 | AS18: =S18*0.03 -> 1897.08 | AT18: =AL18-AQ18-AR18+AS18 -> 16918.632 | AU18: =AT18/P18 -> 0.25027561 | AV18: =148498/1634.3*G18 -> 2362.4475 | AW18: =AT18-AV18 -> 14556.184 | AX18: =AW18/P18 -> 0.21532817 | AY18: =123844.283333333/1634.3*G18 -> 1970.2327 | AZ18: =AT18+AY18 -> 18888.864 | BA18: =AZ18/P18 -> 0.27942107 | BC18: =P18/$G18 -> 2600 | BD18: =-AD18/$G18 -> -1133.8774 | BE18: =-AE18/$G18 -> -323.54284 | BF18: =-AF18/$G18 -> -16.845158 | BG18: =-AG18/$G18 -> -331.94588 | BH18: =-AH18/$G18 -> -1806.2113 | BI18: =AL18/$G18 -> 793.78869 | BJ18: =-AN18/$G18 -> -167.84615 | BK18: =-AP18/$G18 -> 6.2268534 | BL18: =-AQ18/$G18 -> -181.4017 | BM18: =-AR18/$G18 -> -34.635012 | BN18: =AS18/$G18 -> 72.964615 | BO18: =AT18/$G18 -> 650.7166 | BP18: =-AV18/$G18 -> -90.863367 | BQ18: =AW18/$G18 -> 559.85323 | BR18: =AY18/$G18 -> 75.778182 | BS18: =AZ18/$G18 -> 726.49478
B19: FEBRERO | C19: =B19 -> FEBRERO | D19: 151-2025 | E19: 26 | F19: 46080 | G19: 27 | H19: POTA MEMBRANA PRECOCIDA | I19: Membrana | K19: China | L19: Qingdao | M19: Hunan Jinyueyang | O19: =P19/G19 -> 1429.8611 | P19: =39150*0+38606.25 -> 38606.25 | Q19: =S19/G19 -> 1322.4537 | R19: 2900 | S19: =P19-R19 -> 35706.25 | T19: 1 | U19: ECO SIROCCO 26009S | V19: 6445502950 | W19: COSCO | X19: PAITA | Y19: Subproducto | Z19: 10009332 | AA19: Entradas | AB19: =B19&Z19&AA19 -> FEBRERO10009332Entradas | AC19: =INDEX('Detalle Costos'!$L$5:$L$158,MATCH(Resumen!AB19,'Detalle Costos'!$C$5:$C$158,0))*1000*0+AJ19+229398.68/1634.3 -> 1359.8749 | AD19: =IFERROR(INDEX('Detalle Costos'!$X$5:$X$158,MATCH(Resumen!AB19,'Detalle Costos'!$C$5:$C$158,0))*AH19,0) -> 30449.139 | AE19: =IFERROR(INDEX('Detalle Costos'!$Z$5:$Z$158,MATCH(Resumen!AB19,'Detalle Costos'!$C$5:$C$158,0))*AH19,0) -> 5571.9041 | AF19: =IFERROR(INDEX('Detalle Costos'!$Y$5:$Y$158,MATCH(Resumen!AB19,'Detalle Costos'!$C$5:$C$158,0))*AH19,0) -> 562.81608 | AG19: =IFERROR(INDEX('Detalle Costos'!$AA$5:$AA$158,MATCH(Resumen!AB19,'Detalle Costos'!$C$5:$C$158,0))*AH19,0) -> 132.76183 | AH19: =AC19*G19 -> 36716.621 | AI19: 26.625 | AJ19: 1219.5098 | AK19: 40733.76 | AL19: =P19-AH19 -> 1889.6287 | AM19: =AL19/P19 -> 0.048946186 | AN19: =R19 -> 2900 | AO19: =118461.136538461/5988.21*G19 -> 534.12467 | AP19: =-10174.6784147361/1634*G19 -> -168.12504 | AQ19: =SUM(AN19:AP19) -> 3265.9996 | AR19: =56604/1634.3*G19 -> 935.14532 | AS19: =S19*0.03 -> 1071.1875 | AT19: =AL19-AQ19-AR19+AS19 -> -1240.3288 | AU19: =AT19/P19 -> -0.032127668 | AV19: =148498/1634.3*G19 -> 2453.3109 | AW19: =AT19-AV19 -> -3693.6397 | AX19: =AW19/P19 -> -0.095674656 | AY19: =123844.283333333/1634.3*G19 -> 2046.0109 | AZ19: =AT19+AY19 -> 805.68215 | BA19: =AZ19/P19 -> 0.020869215 | BC19: =P19/$G19 -> 1429.8611 | BD19: =-AD19/$G19 -> -1127.7459 | BE19: =-AE19/$G19 -> -206.36682 | BF19: =-AF19/$G19 -> -20.84504 | BG19: =-AG19/$G19 -> -4.9171047 | BH19: =-AH19/$G19 -> -1359.8749 | BI19: =AL19/$G19 -> 69.986247 | BJ19: =-AN19/$G19 -> -107.40741 | BK19: =-AP19/$G19 -> 6.2268534 | BL19: =-AQ19/$G19 -> -120.96295 | BM19: =-AR19/$G19 -> -34.635012 | BN19: =AS19/$G19 -> 39.673611 | BO19: =AT19/$G19 -> -45.938103 | BP19: =-AV19/$G19 -> -90.863367 | BQ19: =AW19/$G19 -> -136.80147 | BR19: =AY19/$G19 -> 75.778182 | BS19: =AZ19/$G19 -> 29.84008
B20: FEBRERO | C20: =B20 -> FEBRERO | D20: 151-2025 | E20: 26 | F20: 46080 | G20: 27 | H20: POTA TELILLA PRECOCIDA | I20: Telilla | K20: China | L20: Qingdao | M20: Hunan Jinyueyang | O20: =P20/G20 -> 1429.8611 | P20: =39150*0+38606.25 -> 38606.25 | Q20: =S20/G20 -> 1322.4537 | R20: 2900 | S20: =P20-R20 -> 35706.25 | T20: 1 | U20: ECO SIROCCO 26009S | V20: 6445502950 | W20: COSCO | X20: PAITA | Y20: Subproducto | Z20: 10009332 | AA20: Compensación | AB20: =B20&Z20&AA20 -> FEBRERO10009332Compensación | AC20: =INDEX('Detalle Costos'!$L$5:$L$158,MATCH(Resumen!AB20,'Detalle Costos'!$C$5:$C$158,0))*1000*0+AJ20+229398.68/1634.3 -> 1359.8749 | AD20: =IFERROR(INDEX('Detalle Costos'!$X$5:$X$158,MATCH(Resumen!AB20,'Detalle Costos'!$C$5:$C$158,0))*AH20,0) -> 29868.013 | AE20: =IFERROR(INDEX('Detalle Costos'!$Z$5:$Z$158,MATCH(Resumen!AB20,'Detalle Costos'!$C$5:$C$158,0))*AH20,0) -> 5215.262 | AF20: =IFERROR(INDEX('Detalle Costos'!$Y$5:$Y$158,MATCH(Resumen!AB20,'Detalle Costos'!$C$5:$C$158,0))*AH20,0) -> 521.93543 | AG20: =IFERROR(INDEX('Detalle Costos'!$AA$5:$AA$158,MATCH(Resumen!AB20,'Detalle Costos'!$C$5:$C$158,0))*AH20,0) -> 1111.4113 | AH20: =AC20*G20 -> 36716.621 | AI20: 26.625 | AJ20: 1219.5098 | AK20: 40354.03 | AL20: =P20-AH20 -> 1889.6287 | AM20: =AL20/P20 -> 0.048946186 | AN20: =R20 -> 2900 | AO20: =118461.136538461/5988.21*G20 -> 534.12467 | AP20: =-10174.6784147361/1634*G20 -> -168.12504 | AQ20: =SUM(AN20:AP20) -> 3265.9996 | AR20: =56604/1634.3*G20 -> 935.14532 | AS20: =S20*0.03 -> 1071.1875 | AT20: =AL20-AQ20-AR20+AS20 -> -1240.3288 | AU20: =AT20/P20 -> -0.032127668 | AV20: =148498/1634.3*G20 -> 2453.3109 | AW20: =AT20-AV20 -> -3693.6397 | AX20: =AW20/P20 -> -0.095674656 | AY20: =123844.283333333/1634.3*G20 -> 2046.0109 | AZ20: =AT20+AY20 -> 805.68215 | BA20: =AZ20/P20 -> 0.020869215 | BC20: =P20/$G20 -> 1429.8611 | BD20: =-AD20/$G20 -> -1106.2227 | BE20: =-AE20/$G20 -> -193.15785 | BF20: =-AF20/$G20 -> -19.330942 | BG20: =-AG20/$G20 -> -41.163382 | BH20: =-AH20/$G20 -> -1359.8749 | BI20: =AL20/$G20 -> 69.986247 | BJ20: =-AN20/$G20 -> -107.40741 | BK20: =-AP20/$G20 -> 6.2268534 | BL20: =-AQ20/$G20 -> -120.96295 | BM20: =-AR20/$G20 -> -34.635012 | BN20: =AS20/$G20 -> 39.673611 | BO20: =AT20/$G20 -> -45.938103 | BP20: =-AV20/$G20 -> -90.863367 | BQ20: =AW20/$G20 -> -136.80147 | BR20: =AY20/$G20 -> 75.778182 | BS20: =AZ20/$G20 -> 29.84008
B21: FEBRERO | C21: =B21 -> FEBRERO | D21: 152-2026 | E21: 26 | F21: 46062 | G21: 27 | H21: POTA REJOS CONGELADOS | I21: Rejos | J21: 2-UP KG | K21: España | L21: Vigo | M21: OVERSEA | N21: Avelino | O21: =P21/G21 -> 2781.2963 | P21: =75600*0+75095 -> 75095 | Q21: =S21/G21 -> 2619.6667 | R21: 4364 | S21: =P21-R21 -> 70731 | T21: 1 | U21: GEMLIK EXPRESS 607N | V21: 24312444 | W21: HAPAG | X21: PAITA | Y21: Fresco | Z21: 10007162 | AA21: Compensación | AB21: =B21&Z21&AA21 -> FEBRERO10007162Compensación | AC21: =INDEX('Detalle Costos'!$L$5:$L$158,MATCH(Resumen!AB21,'Detalle Costos'!$C$5:$C$158,0))*1000*0+AJ21+229398.68/1634.3 -> 1806.2113 | AD21: =IFERROR(INDEX('Detalle Costos'!$X$5:$X$158,MATCH(Resumen!AB21,'Detalle Costos'!$C$5:$C$158,0))*AH21,0) -> 30614.691 | AE21: =IFERROR(INDEX('Detalle Costos'!$Z$5:$Z$158,MATCH(Resumen!AB21,'Detalle Costos'!$C$5:$C$158,0))*AH21,0) -> 8735.6567 | AF21: =IFERROR(INDEX('Detalle Costos'!$Y$5:$Y$158,MATCH(Resumen!AB21,'Detalle Costos'!$C$5:$C$158,0))*AH21,0) -> 454.81926 | AG21: =IFERROR(INDEX('Detalle Costos'!$AA$5:$AA$158,MATCH(Resumen!AB21,'Detalle Costos'!$C$5:$C$158,0))*AH21,0) -> 8962.5387 | AH21: =AC21*G21 -> 48767.705 | AI21: =+G21 -> 27 | AJ21: 1665.8462 | AK21: =AJ21*AI21 -> 44977.848 | AL21: =P21-AH21 -> 26327.295 | AM21: =AL21/P21 -> 0.35058652 | AN21: =R21 -> 4364 | AO21: =118461.136538461/5988.21*G21 -> 534.12467 | AP21: =-10174.6784147361/1634*G21 -> -168.12504 | AQ21: =SUM(AN21:AP21) -> 4729.9996 | AR21: =56604/1634.3*G21 -> 935.14532 | AS21: =S21*0.03 -> 2121.93 | AT21: =AL21-AQ21-AR21+AS21 -> 22784.08 | AU21: =AT21/P21 -> 0.30340342 | AV21: =148498/1634.3*G21 -> 2453.3109 | AW21: =AT21-AV21 -> 20330.769 | AX21: =AW21/P21 -> 0.27073399 | AY21: =123844.283333333/1634.3*G21 -> 2046.0109 | AZ21: =AT21+AY21 -> 24830.091 | BA21: =AZ21/P21 -> 0.33064905 | BC21: =P21/$G21 -> 2781.2963 | BD21: =-AD21/$G21 -> -1133.8774 | BE21: =-AE21/$G21 -> -323.54284 | BF21: =-AF21/$G21 -> -16.845158 | BG21: =-AG21/$G21 -> -331.94588 | BH21: =-AH21/$G21 -> -1806.2113 | BI21: =AL21/$G21 -> 975.08499 | BJ21: =-AN21/$G21 -> -161.62963 | BK21: =-AP21/$G21 -> 6.2268534 | BL21: =-AQ21/$G21 -> -175.18517 | BM21: =-AR21/$G21 -> -34.635012 | BN21: =AS21/$G21 -> 78.59 | BO21: =AT21/$G21 -> 843.8548 | BP21: =-AV21/$G21 -> -90.863367 | BQ21: =AW21/$G21 -> 752.99144 | BR21: =AY21/$G21 -> 75.778182 | BS21: =AZ21/$G21 -> 919.63299
B22: FEBRERO | C22: =B22 -> FEBRERO | D22: 156-2026A | E22: 27 | F22: 46062 | G22: 54 | H22: POTA FILETE CONGELADO | I22: Filete | J22: 2-4 kg 100% blanco, No polyphosphate,no medicine | K22: China | L22: Qingdao | M22: Longkou Yunfeng Aquatic | O22: 1650 | P22: 89100 | Q22: 1534.963 | R22: 6212 | S22: =P22-R22 -> 82888 | T22: 2 | U22: CMA CGM IMAGINATION / 0DVITN1MA | V22: LMM0571149 | W22: CMA CGM | X22: PAITA | Y22: Fresco | Z22: 10005721 | AA22: Compensación | AB22: =B22&Z22&AA22 -> FEBRERO10005721Compensación | AC22: =INDEX('Detalle Costos'!$L$5:$L$158,MATCH(Resumen!AB22,'Detalle Costos'!$C$5:$C$158,0))*1000*0+AJ22+229398.68/1634.3 -> 1812.5717 | AD22: =IFERROR(INDEX('Detalle Costos'!$X$5:$X$158,MATCH(Resumen!AB22,'Detalle Costos'!$C$5:$C$158,0))*AH22,0) -> 59396.419 | AE22: =IFERROR(INDEX('Detalle Costos'!$Z$5:$Z$158,MATCH(Resumen!AB22,'Detalle Costos'!$C$5:$C$158,0))*AH22,0) -> 19622.354 | AF22: =IFERROR(INDEX('Detalle Costos'!$Y$5:$Y$158,MATCH(Resumen!AB22,'Detalle Costos'!$C$5:$C$158,0))*AH22,0) -> 1043.8595 | AG22: =IFERROR(INDEX('Detalle Costos'!$AA$5:$AA$158,MATCH(Resumen!AB22,'Detalle Costos'!$C$5:$C$158,0))*AH22,0) -> 17816.237 | AH22: =AC22*G22 -> 97878.87 | AI22: =+G22 -> 54 | AJ22: 1672.2066 | AK22: =+AJ22*AI22 -> 90299.155 | AL22: =P22-AH22 -> -8778.8703 | AM22: =AL22/P22 -> -0.098528286 | AN22: =R22 -> 6212 | AO22: =118461.136538461/5988.21*G22 -> 1068.2493 | AP22: =-10174.6784147361/1634*G22 -> -336.25008 | AQ22: =SUM(AN22:AP22) -> 6943.9993 | AR22: =56604/1634.3*G22 -> 1870.2906 | AS22: =S22*0.03 -> 2486.64 | AT22: =AL22-AQ22-AR22+AS22 -> -15106.52 | AU22: =AT22/P22 -> -0.16954568 | AV22: =148498/1634.3*G22 -> 4906.6218 | AW22: =AT22-AV22 -> -20013.142 | AX22: =AW22/P22 -> -0.22461439 | AY22: =123844.283333333/1634.3*G22 -> 4092.0218 | AZ22: =AT22+AY22 -> -11014.498 | BA22: =AZ22/P22 -> -0.12361951 | BC22: =P22/$G22 -> 1650 | BD22: =-AD22/$G22 -> -1099.9337 | BE22: =-AE22/$G22 -> -363.37693 | BF22: =-AF22/$G22 -> -19.330731 | BG22: =-AG22/$G22 -> -329.93032 | BH22: =-AH22/$G22 -> -1812.5717 | BI22: =AL22/$G22 -> -162.57167 | BJ22: =-AN22/$G22 -> -115.03704 | BK22: =-AP22/$G22 -> 6.2268534 | BL22: =-AQ22/$G22 -> -128.59258 | BM22: =-AR22/$G22 -> -34.635012 | BN22: =AS22/$G22 -> 46.048889 | BO22: =AT22/$G22 -> -279.75037 | BP22: =-AV22/$G22 -> -90.863367 | BQ22: =AW22/$G22 -> -370.61374 | BR22: =AY22/$G22 -> 75.778182 | BS22: =AZ22/$G22 -> -203.97219
B23: FEBRERO | C23: =B23 -> FEBRERO | D23: 156-2026B | E23: 27 | F23: 46071 | G23: 81 | H23: POTA FILETE CONGELADO | I23: Filete | J23: 2-4 kg 100% blanco, No polyphosphate,no medicine | K23: China | L23: Qingdao | M23: Longkou Yunfeng Aquatic | O23: 1650 | P23: 133650 | Q23: 1534.963 | R23: 9318 | S23: =P23-R23 -> 124332 | T23: 3 | U23: CMA CGM EXCELLENCE 0DVNNN1MA | V23: LMM0571699 | W23: CMA CGM | X23: PAITA | Y23: Fresco | Z23: 10005721 | AA23: Compensación | AB23: =B23&Z23&AA23 -> FEBRERO10005721Compensación | AC23: =INDEX('Detalle Costos'!$L$5:$L$158,MATCH(Resumen!AB23,'Detalle Costos'!$C$5:$C$158,0))*1000*0+AJ23+229398.68/1634.3 -> 1812.5717 | AD23: =IFERROR(INDEX('Detalle Costos'!$X$5:$X$158,MATCH(Resumen!AB23,'Detalle Costos'!$C$5:$C$158,0))*AH23,0) -> 89094.629 | AE23: =IFERROR(INDEX('Detalle Costos'!$Z$5:$Z$158,MATCH(Resumen!AB23,'Detalle Costos'!$C$5:$C$158,0))*AH23,0) -> 29433.532 | AF23: =IFERROR(INDEX('Detalle Costos'!$Y$5:$Y$158,MATCH(Resumen!AB23,'Detalle Costos'!$C$5:$C$158,0))*AH23,0) -> 1565.7892 | AG23: =IFERROR(INDEX('Detalle Costos'!$AA$5:$AA$158,MATCH(Resumen!AB23,'Detalle Costos'!$C$5:$C$158,0))*AH23,0) -> 26724.356 | AH23: =AC23*G23 -> 146818.31 | AI23: =+G23 -> 81 | AJ23: 1672.2066 | AK23: =+AJ23*AI23 -> 135448.73 | AL23: =P23-AH23 -> -13168.305 | AM23: =AL23/P23 -> -0.098528286 | AN23: =R23 -> 9318 | AO23: =118461.136538461/5988.21*G23 -> 1602.374 | AP23: =-10174.6784147361/1634*G23 -> -504.37512 | AQ23: =SUM(AN23:AP23) -> 10415.999 | AR23: =56604/1634.3*G23 -> 2805.436 | AS23: =S23*0.03 -> 3729.96 | AT23: =AL23-AQ23-AR23+AS23 -> -22659.78 | AU23: =AT23/P23 -> -0.16954568 | AV23: =148498/1634.3*G23 -> 7359.9327 | AW23: =AT23-AV23 -> -30019.713 | AX23: =AW23/P23 -> -0.22461439 | AY23: =123844.283333333/1634.3*G23 -> 6138.0328 | AZ23: =AT23+AY23 -> -16521.747 | BA23: =AZ23/P23 -> -0.12361951 | BC23: =P23/$G23 -> 1650 | BD23: =-AD23/$G23 -> -1099.9337 | BE23: =-AE23/$G23 -> -363.37693 | BF23: =-AF23/$G23 -> -19.330731 | BG23: =-AG23/$G23 -> -329.93032 | BH23: =-AH23/$G23 -> -1812.5717 | BI23: =AL23/$G23 -> -162.57167 | BJ23: =-AN23/$G23 -> -115.03704 | BK23: =-AP23/$G23 -> 6.2268534 | BL23: =-AQ23/$G23 -> -128.59258 | BM23: =-AR23/$G23 -> -34.635012 | BN23: =AS23/$G23 -> 46.048889 | BO23: =AT23/$G23 -> -279.75037 | BP23: =-AV23/$G23 -> -90.863367 | BQ23: =AW23/$G23 -> -370.61374 | BR23: =AY23/$G23 -> 75.778182 | BS23: =AZ23/$G23 -> -203.97219
B24: FEBRERO | C24: =B24 -> FEBRERO | D24: 157-2026 | E24: 28 | F24: 46066 | G24: 24 | H24: POTA CONOS | I24: Conos | K24: Tailandia | L24: Lat Krabang | M24: TSUJINO | N24: Jose | O24: 2000 | P24: 48000 | Q24: 1854.1667 | R24: 3500 | S24: =P24-R24 -> 44500 | T24: 1 | U24: ECO SIROCCO 26007S | V24: 6445030580 | W24: COSCO | X24: PAITA | Y24: Subproducto | Z24: 10007969 | AA24: Compensación | AB24: =B24&Z24&AA24 -> FEBRERO10007969Compensación | AC24: =INDEX('Detalle Costos'!$L$5:$L$158,MATCH(Resumen!AB24,'Detalle Costos'!$C$5:$C$158,0))*1000*0+AJ24+229398.68/1634.3 -> 1345.444 | AD24: =IFERROR(INDEX('Detalle Costos'!$X$5:$X$158,MATCH(Resumen!AB24,'Detalle Costos'!$C$5:$C$158,0))*AH24,0) -> 26118.191 | AE24: =IFERROR(INDEX('Detalle Costos'!$Z$5:$Z$158,MATCH(Resumen!AB24,'Detalle Costos'!$C$5:$C$158,0))*AH24,0) -> 4916.5079 | AF24: =IFERROR(INDEX('Detalle Costos'!$Y$5:$Y$158,MATCH(Resumen!AB24,'Detalle Costos'!$C$5:$C$158,0))*AH24,0) -> 385.54283 | AG24: =IFERROR(INDEX('Detalle Costos'!$AA$5:$AA$158,MATCH(Resumen!AB24,'Detalle Costos'!$C$5:$C$158,0))*AH24,0) -> 870.41413 | AH24: =AC24*G24 -> 32290.656 | AI24: 23.14 | AJ24: 1205.0789 | AK24: =+AJ24*AI24 -> 27885.525 | AL24: =P24-AH24 -> 15709.344 | AM24: =AL24/P24 -> 0.32727801 | AN24: =R24 -> 3500 | AO24: =118461.136538461/5988.21*G24 -> 474.77748 | AP24: =-10174.6784147361/1634*G24 -> -149.44448 | AQ24: =SUM(AN24:AP24) -> 3825.333 | AR24: =56604/1634.3*G24 -> 831.24029 | AS24: =S24*0.03 -> 1335 | AT24: =AL24-AQ24-AR24+AS24 -> 12387.771 | AU24: =AT24/P24 -> 0.25807856 | AV24: =148498/1634.3*G24 -> 2180.7208 | AW24: =AT24-AV24 -> 10207.05 | AX24: =AW24/P24 -> 0.21264688 | AY24: =123844.283333333/1634.3*G24 -> 1818.6764 | AZ24: =AT24+AY24 -> 14206.447 | BA24: =AZ24/P24 -> 0.29596765 | BC24: =P24/$G24 -> 2000 | BD24: =-AD24/$G24 -> -1088.2579 | BE24: =-AE24/$G24 -> -204.8545 | BF24: =-AF24/$G24 -> -16.064285 | BG24: =-AG24/$G24 -> -36.267255 | BH24: =-AH24/$G24 -> -1345.444 | BI24: =AL24/$G24 -> 654.55601 | BJ24: =-AN24/$G24 -> -145.83333 | BK24: =-AP24/$G24 -> 6.2268534 | BL24: =-AQ24/$G24 -> -159.38888 | BM24: =-AR24/$G24 -> -34.635012 | BN24: =AS24/$G24 -> 55.625 | BO24: =AT24/$G24 -> 516.15713 | BP24: =-AV24/$G24 -> -90.863367 | BQ24: =AW24/$G24 -> 425.29376 | BR24: =AY24/$G24 -> 75.778182 | BS24: =AZ24/$G24 -> 591.93531
B25: FEBRERO | C25: =B25 -> FEBRERO | D25: 160-2026 | E25: 30 | F25: 46066 | G25: 108 | H25: POTA ALAS CONGELADAS | I25: Alas | K25: China | L25: Qingdao | M25: TSUJINO | N25: Jose | O25: 1600 | P25: 172800 | Q25: 1492.5926 | R25: 11600 | S25: =P25-R25 -> 161200 | T25: 4 | U25: ECO SIROCCO 26007S | V25: 6445031110 | W25: COSCO | X25: PAITA | Y25: Fresco | Z25: 10006720 | AA25: Compensación | AB25: =B25&Z25&AA25 -> FEBRERO10006720Compensación | AC25: =INDEX('Detalle Costos'!$L$5:$L$158,MATCH(Resumen!AB25,'Detalle Costos'!$C$5:$C$158,0))*1000*0+AJ25+229398.68/1634.3 -> 1734.9284 | AD25: =IFERROR(INDEX('Detalle Costos'!$X$5:$X$158,MATCH(Resumen!AB25,'Detalle Costos'!$C$5:$C$158,0))*AH25,0) -> 121464.06 | AE25: =IFERROR(INDEX('Detalle Costos'!$Z$5:$Z$158,MATCH(Resumen!AB25,'Detalle Costos'!$C$5:$C$158,0))*AH25,0) -> 27793.266 | AF25: =IFERROR(INDEX('Detalle Costos'!$Y$5:$Y$158,MATCH(Resumen!AB25,'Detalle Costos'!$C$5:$C$158,0))*AH25,0) -> 1820.4413 | AG25: =IFERROR(INDEX('Detalle Costos'!$AA$5:$AA$158,MATCH(Resumen!AB25,'Detalle Costos'!$C$5:$C$158,0))*AH25,0) -> 36294.502 | AH25: =AC25*G25 -> 187372.27 | AI25: =+G25 -> 108 | AJ25: 1594.5633 | AK25: =+AJ25*AI25 -> 172212.84 | AL25: =P25-AH25 -> -14572.269 | AM25: =AL25/P25 -> -0.08433026 | AN25: =R25 -> 11600 | AO25: =118461.136538461/5988.21*G25 -> 2136.4987 | AP25: =-10174.6784147361/1634*G25 -> -672.50016 | AQ25: =SUM(AN25:AP25) -> 13063.999 | AR25: =56604/1634.3*G25 -> 3740.5813 | AS25: =S25*0.03 -> 4836 | AT25: =AL25-AQ25-AR25+AS25 -> -26540.849 | AU25: =AT25/P25 -> -0.15359287 | AV25: =148498/1634.3*G25 -> 9813.2436 | AW25: =AT25-AV25 -> -36354.092 | AX25: =AW25/P25 -> -0.21038248 | AY25: =123844.283333333/1634.3*G25 -> 8184.0437 | AZ25: =AT25+AY25 -> -18356.805 | BA25: =AZ25/P25 -> -0.10623151 | BC25: =P25/$G25 -> 1600 | BD25: =-AD25/$G25 -> -1124.6672 | BE25: =-AE25/$G25 -> -257.34505 | BF25: =-AF25/$G25 -> -16.855938 | BG25: =-AG25/$G25 -> -336.0602 | BH25: =-AH25/$G25 -> -1734.9284 | BI25: =AL25/$G25 -> -134.92842 | BJ25: =-AN25/$G25 -> -107.40741 | BK25: =-AP25/$G25 -> 6.2268534 | BL25: =-AQ25/$G25 -> -120.96295 | BM25: =-AR25/$G25 -> -34.635012 | BN25: =AS25/$G25 -> 44.777778 | BO25: =AT25/$G25 -> -245.7486 | BP25: =-AV25/$G25 -> -90.863367 | BQ25: =AW25/$G25 -> -336.61197 | BR25: =AY25/$G25 -> 75.778182 | BS25: =AZ25/$G25 -> -169.97042
B26: FEBRERO | C26: =B26 -> FEBRERO | D26: 160-2026 | E26: 30 | F26: 46066 | G26: 108 | H26: POTA ALAS CONGELADAS | I26: Alas | K26: China | L26: Qingdao | M26: TSUJINO | N26: Jose | O26: 1600 | P26: 172800 | Q26: 1492.5926 | R26: 11600 | S26: =P26-R26 -> 161200 | T26: 4 | U26: ECO SIROCCO 26007S | V26: 6445031130 | W26: COSCO | X26: PAITA | Y26: Fresco | Z26: 10006720 | AA26: Compensación | AB26: =B26&Z26&AA26 -> FEBRERO10006720Compensación | AC26: =INDEX('Detalle Costos'!$L$5:$L$158,MATCH(Resumen!AB26,'Detalle Costos'!$C$5:$C$158,0))*1000*0+AJ26+229398.68/1634.3 -> 1734.9284 | AD26: =IFERROR(INDEX('Detalle Costos'!$X$5:$X$158,MATCH(Resumen!AB26,'Detalle Costos'!$C$5:$C$158,0))*AH26,0) -> 121464.06 | AE26: =IFERROR(INDEX('Detalle Costos'!$Z$5:$Z$158,MATCH(Resumen!AB26,'Detalle Costos'!$C$5:$C$158,0))*AH26,0) -> 27793.266 | AF26: =IFERROR(INDEX('Detalle Costos'!$Y$5:$Y$158,MATCH(Resumen!AB26,'Detalle Costos'!$C$5:$C$158,0))*AH26,0) -> 1820.4413 | AG26: =IFERROR(INDEX('Detalle Costos'!$AA$5:$AA$158,MATCH(Resumen!AB26,'Detalle Costos'!$C$5:$C$158,0))*AH26,0) -> 36294.502 | AH26: =AC26*G26 -> 187372.27 | AI26: =+G26 -> 108 | AJ26: 1594.5633 | AK26: =+AJ26*AI26 -> 172212.84 | AL26: =P26-AH26 -> -14572.269 | AM26: =AL26/P26 -> -0.08433026 | AN26: =R26 -> 11600 | AO26: =118461.136538461/5988.21*G26 -> 2136.4987 | AP26: =-10174.6784147361/1634*G26 -> -672.50016 | AQ26: =SUM(AN26:AP26) -> 13063.999 | AR26: =56604/1634.3*G26 -> 3740.5813 | AS26: =S26*0.03 -> 4836 | AT26: =AL26-AQ26-AR26+AS26 -> -26540.849 | AU26: =AT26/P26 -> -0.15359287 | AV26: =148498/1634.3*G26 -> 9813.2436 | AW26: =AT26-AV26 -> -36354.092 | AX26: =AW26/P26 -> -0.21038248 | AY26: =123844.283333333/1634.3*G26 -> 8184.0437 | AZ26: =AT26+AY26 -> -18356.805 | BA26: =AZ26/P26 -> -0.10623151 | BC26: =P26/$G26 -> 1600 | BD26: =-AD26/$G26 -> -1124.6672 | BE26: =-AE26/$G26 -> -257.34505 | BF26: =-AF26/$G26 -> -16.855938 | BG26: =-AG26/$G26 -> -336.0602 | BH26: =-AH26/$G26 -> -1734.9284 | BI26: =AL26/$G26 -> -134.92842 | BJ26: =-AN26/$G26 -> -107.40741 | BK26: =-AP26/$G26 -> 6.2268534 | BL26: =-AQ26/$G26 -> -120.96295 | BM26: =-AR26/$G26 -> -34.635012 | BN26: =AS26/$G26 -> 44.777778 | BO26: =AT26/$G26 -> -245.7486 | BP26: =-AV26/$G26 -> -90.863367 | BQ26: =AW26/$G26 -> -336.61197 | BR26: =AY26/$G26 -> 75.778182 | BS26: =AZ26/$G26 -> -169.97042
B27: FEBRERO | C27: =B27 -> FEBRERO | D27: 162-2026A | E27: 34 | F27: 46070 | G27: 115.5 | H27: POTA ALAS CONGELADAS | I27: Alas | J27: 1-2 kg | K27: China | L27: Qingdao | M27: AVANCE GROUP | N27: James | O27: 1500 | P27: 173250 | Q27: 1382.987 | R27: 13515 | S27: =P27-R27 -> 159735 | T27: 5 | U27: ECO SIROCCO 26007N | V27: LIMG02628500 | W27: ONE | X27: PAITA | Y27: Fresco | Z27: 10006720 | AA27: Compensación | AB27: =B27&Z27&AA27 -> FEBRERO10006720Compensación | AC27: =INDEX('Detalle Costos'!$L$5:$L$158,MATCH(Resumen!AB27,'Detalle Costos'!$C$5:$C$158,0))*1000*0+AJ27+229398.68/1634.3 -> 1734.9284 | AD27: =IFERROR(INDEX('Detalle Costos'!$X$5:$X$158,MATCH(Resumen!AB27,'Detalle Costos'!$C$5:$C$158,0))*AH27,0) -> 129899.06 | AE27: =IFERROR(INDEX('Detalle Costos'!$Z$5:$Z$158,MATCH(Resumen!AB27,'Detalle Costos'!$C$5:$C$158,0))*AH27,0) -> 29723.354 | AF27: =IFERROR(INDEX('Detalle Costos'!$Y$5:$Y$158,MATCH(Resumen!AB27,'Detalle Costos'!$C$5:$C$158,0))*AH27,0) -> 1946.8609 | AG27: =IFERROR(INDEX('Detalle Costos'!$AA$5:$AA$158,MATCH(Resumen!AB27,'Detalle Costos'!$C$5:$C$158,0))*AH27,0) -> 38814.953 | AH27: =AC27*G27 -> 200384.23 | AI27: =+G27 -> 115.5 | AJ27: 1594.5633 | AK27: =+AJ27*AI27 -> 184172.06 | AL27: =P27-AH27 -> -27134.232 | AM27: =AL27/P27 -> -0.15661894 | AN27: =R27 -> 13515 | AO27: =118461.136538461/5988.21*G27 -> 2284.8666 | AP27: =-10174.6784147361/1634*G27 -> -719.20156 | AQ27: =SUM(AN27:AP27) -> 15080.665 | AR27: =56604/1634.3*G27 -> 4000.3439 | AS27: =S27*0.03 -> 4792.05 | AT27: =AL27-AQ27-AR27+AS27 -> -41423.191 | AU27: =AT27/P27 -> -0.2390949 | AV27: =148498/1634.3*G27 -> 10494.719 | AW27: =AT27-AV27 -> -51917.91 | AX27: =AW27/P27 -> -0.29967048 | AY27: =123844.283333333/1634.3*G27 -> 8752.3801 | AZ27: =AT27+AY27 -> -32670.811 | BA27: =AZ27/P27 -> -0.18857611 | BC27: =P27/$G27 -> 1500 | BD27: =-AD27/$G27 -> -1124.6672 | BE27: =-AE27/$G27 -> -257.34505 | BF27: =-AF27/$G27 -> -16.855938 | BG27: =-AG27/$G27 -> -336.0602 | BH27: =-AH27/$G27 -> -1734.9284 | BI27: =AL27/$G27 -> -234.92842 | BJ27: =-AN27/$G27 -> -117.01299 | BK27: =-AP27/$G27 -> 6.2268534 | BL27: =-AQ27/$G27 -> -130.56853 | BM27: =-AR27/$G27 -> -34.635012 | BN27: =AS27/$G27 -> 41.48961 | BO27: =AT27/$G27 -> -358.64235 | BP27: =-AV27/$G27 -> -90.863367 | BQ27: =AW27/$G27 -> -449.50571 | BR27: =AY27/$G27 -> 75.778182 | BS27: =AZ27/$G27 -> -282.86416
B28: FEBRERO | C28: =B28 -> FEBRERO | D28: 162-2026B | E28: 34 | F28: 46070 | G28: 46.8 | H28: POTA ALAS CONGELADAS | I28: Alas | J28: 1-2 kg | K28: China | L28: Dalian | M28: AVANCE GROUP | N28: James | O28: 1500 | P28: 70200 | Q28: 1380.2137 | R28: 5606 | S28: =P28-R28 -> 64594 | T28: 2 | U28: ECO SIROCCO 26007N | V28: LIMG02851300 | W28: ONE | X28: PAITA | Y28: Fresco | Z28: 10006720 | AA28: Compensación | AB28: =B28&Z28&AA28 -> FEBRERO10006720Compensación | AC28: =INDEX('Detalle Costos'!$L$5:$L$158,MATCH(Resumen!AB28,'Detalle Costos'!$C$5:$C$158,0))*1000*0+AJ28+229398.68/1634.3 -> 1734.9284 | AD28: =IFERROR(INDEX('Detalle Costos'!$X$5:$X$158,MATCH(Resumen!AB28,'Detalle Costos'!$C$5:$C$158,0))*AH28,0) -> 52634.426 | AE28: =IFERROR(INDEX('Detalle Costos'!$Z$5:$Z$158,MATCH(Resumen!AB28,'Detalle Costos'!$C$5:$C$158,0))*AH28,0) -> 12043.748 | AF28: =IFERROR(INDEX('Detalle Costos'!$Y$5:$Y$158,MATCH(Resumen!AB28,'Detalle Costos'!$C$5:$C$158,0))*AH28,0) -> 788.85791 | AG28: =IFERROR(INDEX('Detalle Costos'!$AA$5:$AA$158,MATCH(Resumen!AB28,'Detalle Costos'!$C$5:$C$158,0))*AH28,0) -> 15727.617 | AH28: =AC28*G28 -> 81194.65 | AI28: =+G28 -> 46.8 | AJ28: 1594.5633 | AK28: =+AJ28*AI28 -> 74625.563 | AL28: =P28-AH28 -> -10994.65 | AM28: =AL28/P28 -> -0.15661894 | AN28: =R28 -> 5606 | AO28: =118461.136538461/5988.21*G28 -> 925.81609 | AP28: =-10174.6784147361/1634*G28 -> -291.41674 | AQ28: =SUM(AN28:AP28) -> 6240.3994 | AR28: =56604/1634.3*G28 -> 1620.9186 | AS28: =S28*0.03 -> 1937.82 | AT28: =AL28-AQ28-AR28+AS28 -> -16918.148 | AU28: =AT28/P28 -> -0.24099926 | AV28: =148498/1634.3*G28 -> 4252.4056 | AW28: =AT28-AV28 -> -21170.553 | AX28: =AW28/P28 -> -0.30157483 | AY28: =123844.283333333/1634.3*G28 -> 3546.4189 | AZ28: =AT28+AY28 -> -13371.729 | BA28: =AZ28/P28 -> -0.19048047 | BC28: =P28/$G28 -> 1500 | BD28: =-AD28/$G28 -> -1124.6672 | BE28: =-AE28/$G28 -> -257.34505 | BF28: =-AF28/$G28 -> -16.855938 | BG28: =-AG28/$G28 -> -336.0602 | BH28: =-AH28/$G28 -> -1734.9284 | BI28: =AL28/$G28 -> -234.92842 | BJ28: =-AN28/$G28 -> -119.78632 | BK28: =-AP28/$G28 -> 6.2268534 | BL28: =-AQ28/$G28 -> -133.34187 | BM28: =-AR28/$G28 -> -34.635012 | BN28: =AS28/$G28 -> 41.40641 | BO28: =AT28/$G28 -> -361.49888 | BP28: =-AV28/$G28 -> -90.863367 | BQ28: =AW28/$G28 -> -452.36225 | BR28: =AY28/$G28 -> 75.778182 | BS28: =AZ28/$G28 -> -285.7207
B29: FEBRERO | C29: =B29 -> FEBRERO | D29: 162-2026C | E29: 34 | F29: 46070 | G29: 81 | H29: POTA ALAS CONGELADAS | I29: Alas | J29: 1-2 kg | K29: China | L29: Xiamen | M29: AVANCE GROUP | N29: James | O29: 1500 | P29: 121500 | Q29: 1385.0741 | R29: 9309 | S29: =P29-R29 -> 112191 | T29: 3 | U29: ECO SIROCCO 26007N | V29: LIMG02630500 | W29: ONE | X29: PAITA | Y29: Fresco | Z29: 10006720 | AA29: Compensación | AB29: =B29&Z29&AA29 -> FEBRERO10006720Compensación | AC29: =INDEX('Detalle Costos'!$L$5:$L$158,MATCH(Resumen!AB29,'Detalle Costos'!$C$5:$C$158,0))*1000*0+AJ29+229398.68/1634.3 -> 1734.9284 | AD29: =IFERROR(INDEX('Detalle Costos'!$X$5:$X$158,MATCH(Resumen!AB29,'Detalle Costos'!$C$5:$C$158,0))*AH29,0) -> 91098.045 | AE29: =IFERROR(INDEX('Detalle Costos'!$Z$5:$Z$158,MATCH(Resumen!AB29,'Detalle Costos'!$C$5:$C$158,0))*AH29,0) -> 20844.949 | AF29: =IFERROR(INDEX('Detalle Costos'!$Y$5:$Y$158,MATCH(Resumen!AB29,'Detalle Costos'!$C$5:$C$158,0))*AH29,0) -> 1365.331 | AG29: =IFERROR(INDEX('Detalle Costos'!$AA$5:$AA$158,MATCH(Resumen!AB29,'Detalle Costos'!$C$5:$C$158,0))*AH29,0) -> 27220.876 | AH29: =AC29*G29 -> 140529.2 | AI29: =+G29 -> 81 | AJ29: 1594.5633 | AK29: =+AJ29*AI29 -> 129159.63 | AL29: =P29-AH29 -> -19029.202 | AM29: =AL29/P29 -> -0.15661894 | AN29: =R29 -> 9309 | AO29: =118461.136538461/5988.21*G29 -> 1602.374 | AP29: =-10174.6784147361/1634*G29 -> -504.37512 | AQ29: =SUM(AN29:AP29) -> 10406.999 | AR29: =56604/1634.3*G29 -> 2805.436 | AS29: =S29*0.03 -> 3365.73 | AT29: =AL29-AQ29-AR29+AS29 -> -28875.907 | AU29: =AT29/P29 -> -0.23766178 | AV29: =148498/1634.3*G29 -> 7359.9327 | AW29: =AT29-AV29 -> -36235.839 | AX29: =AW29/P29 -> -0.29823736 | AY29: =123844.283333333/1634.3*G29 -> 6138.0328 | AZ29: =AT29+AY29 -> -22737.874 | BA29: =AZ29/P29 -> -0.18714299 | BC29: =P29/$G29 -> 1500 | BD29: =-AD29/$G29 -> -1124.6672 | BE29: =-AE29/$G29 -> -257.34505 | BF29: =-AF29/$G29 -> -16.855938 | BG29: =-AG29/$G29 -> -336.0602 | BH29: =-AH29/$G29 -> -1734.9284 | BI29: =AL29/$G29 -> -234.92842 | BJ29: =-AN29/$G29 -> -114.92593 | BK29: =-AP29/$G29 -> 6.2268534 | BL29: =-AQ29/$G29 -> -128.48147 | BM29: =-AR29/$G29 -> -34.635012 | BN29: =AS29/$G29 -> 41.552222 | BO29: =AT29/$G29 -> -356.49267 | BP29: =-AV29/$G29 -> -90.863367 | BQ29: =AW29/$G29 -> -447.35604 | BR29: =AY29/$G29 -> 75.778182 | BS29: =AZ29/$G29 -> -280.71449
B30: FEBRERO | C30: =B30 -> FEBRERO | D30: 164-2026 | E30: 40 | F30: 46080 | G30: 27 | H30: POTA FILETE DARUMA | I30: Daruma | K30: China | L30: Yantai | M30: SACRAMENTO CO., LTD | N30: julia | O30: 3400 | P30: 91800 | Q30: 3292.5926 | R30: 2900 | S30: =P30-R30 -> 88900 | T30: 1 | U30: ECO SIROCCO 26009S | V30: 6445569300 | W30: COSCO | X30: PAITA | Y30: Cocido | Z30: 10009239 | AA30: Compensación | AB30: =B30&Z30&AA30 -> FEBRERO10009239Compensación | AC30: =INDEX('Detalle Costos'!$L$5:$L$158,MATCH(Resumen!AB30,'Detalle Costos'!$C$5:$C$158,0))*1000*0+AJ30+229398.68/1634.3 -> 2209.4137 | AD30: =IFERROR(INDEX('Detalle Costos'!$X$5:$X$158,MATCH(Resumen!AB30,'Detalle Costos'!$C$5:$C$158,0))*AH30,0) -> 30346.048 | AE30: =IFERROR(INDEX('Detalle Costos'!$Z$5:$Z$158,MATCH(Resumen!AB30,'Detalle Costos'!$C$5:$C$158,0))*AH30,0) -> 19824.186 | AF30: =IFERROR(INDEX('Detalle Costos'!$Y$5:$Y$158,MATCH(Resumen!AB30,'Detalle Costos'!$C$5:$C$158,0))*AH30,0) -> 381.56023 | AG30: =IFERROR(INDEX('Detalle Costos'!$AA$5:$AA$158,MATCH(Resumen!AB30,'Detalle Costos'!$C$5:$C$158,0))*AH30,0) -> 9102.3758 | AH30: =AC30*G30 -> 59654.17 | AI30: 27 | AJ30: 2069.0486 | AK30: =AJ30*AI30 -> 55864.313 | AL30: =P30-AH30 -> 32145.83 | AM30: =AL30/P30 -> 0.35017244 | AN30: =R30 -> 2900 | AO30: =118461.136538461/5988.21*G30 -> 534.12467 | AP30: =-10174.6784147361/1634*G30 -> -168.12504 | AQ30: =SUM(AN30:AP30) -> 3265.9996 | AR30: =56604/1634.3*G30 -> 935.14532 | AS30: =S30*0.03 -> 2667 | AT30: =AL30-AQ30-AR30+AS30 -> 30611.685 | AU30: =AT30/P30 -> 0.33346062 | AV30: =148498/1634.3*G30 -> 2453.3109 | AW30: =AT30-AV30 -> 28158.374 | AX30: =AW30/P30 -> 0.3067361 | AY30: =123844.283333333/1634.3*G30 -> 2046.0109 | AZ30: =AT30+AY30 -> 32657.696 | BA30: =AZ30/P30 -> 0.35574832 | BC30: =P30/$G30 -> 3400 | BD30: =-AD30/$G30 -> -1123.9277 | BE30: =-AE30/$G30 -> -734.22911 | BF30: =-AF30/$G30 -> -14.13186 | BG30: =-AG30/$G30 -> -337.12503 | BH30: =-AH30/$G30 -> -2209.4137 | BI30: =AL30/$G30 -> 1190.5863 | BJ30: =-AN30/$G30 -> -107.40741 | BK30: =-AP30/$G30 -> 6.2268534 | BL30: =-AQ30/$G30 -> -120.96295 | BM30: =-AR30/$G30 -> -34.635012 | BN30: =AS30/$G30 -> 98.777778 | BO30: =AT30/$G30 -> 1133.7661 | BP30: =-AV30/$G30 -> -90.863367 | BQ30: =AW30/$G30 -> 1042.9027 | BR30: =AY30/$G30 -> 75.778182 | BS30: =AZ30/$G30 -> 1209.5443
B31: FEBRERO | C31: =B31 -> FEBRERO | D31: 168-2026A | E31: 43 | F31: 46077 | G31: 351 | H31: POTA FILETE CONGELADO | I31: Filete | J31: 2-4 AA | K31: China | L31: Qingdao | M31: AVANCE GROUP | N31: James | O31: 1300 | P31: 456300 | Q31: 1300 | R31: =3103*T31 -> 40339 | S31: =P31-R31 -> 415961 | T31: 13 | U31: ECO MARIN 26008N | V31: 6445505270 | W31: COSCO | X31: PAITA | Y31: Fresco | Z31: 10005721 | AA31: Compensación | AB31: =B31&Z31&AA31 -> FEBRERO10005721Compensación | AC31: =INDEX('Detalle Costos'!$L$5:$L$158,MATCH(Resumen!AB31,'Detalle Costos'!$C$5:$C$158,0))*1000*0+AJ31+229398.68/1634.3 -> 1812.5717 | AD31: =IFERROR(INDEX('Detalle Costos'!$X$5:$X$158,MATCH(Resumen!AB31,'Detalle Costos'!$C$5:$C$158,0))*AH31,0) -> 386076.73 | AE31: =IFERROR(INDEX('Detalle Costos'!$Z$5:$Z$158,MATCH(Resumen!AB31,'Detalle Costos'!$C$5:$C$158,0))*AH31,0) -> 127545.3 | AF31: =IFERROR(INDEX('Detalle Costos'!$Y$5:$Y$158,MATCH(Resumen!AB31,'Detalle Costos'!$C$5:$C$158,0))*AH31,0) -> 6785.0865 | AG31: =IFERROR(INDEX('Detalle Costos'!$AA$5:$AA$158,MATCH(Resumen!AB31,'Detalle Costos'!$C$5:$C$158,0))*AH31,0) -> 115805.54 | AH31: =AC31*G31 -> 636212.66 | AI31: =+G31 -> 351 | AJ31: 1672.2066 | AK31: =+AJ31*AI31 -> 586944.51 | AL31: =P31-AH31 -> -179912.66 | AM31: =AL31/P31 -> -0.3942859 | AN31: =R31 -> 40339 | AO31: =118461.136538461/5988.21*G31 -> 6943.6207 | AP31: =-10174.6784147361/1634*G31 -> -2185.6255 | AQ31: =SUM(AN31:AP31) -> 45096.995 | AR31: =56604/1634.3*G31 -> 12156.889 | AS31: =S31*0.03 -> 12478.83 | AT31: =AL31-AQ31-AR31+AS31 -> -224687.71 | AU31: =AT31/P31 -> -0.49241225 | AV31: =148498/1634.3*G31 -> 31893.042 | AW31: =AT31-AV31 -> -256580.75 | AX31: =AW31/P31 -> -0.56230715 | AY31: =123844.283333333/1634.3*G31 -> 26598.142 | AZ31: =AT31+AY31 -> -198089.57 | BA31: =AZ31/P31 -> -0.43412134 | BC31: =P31/$G31 -> 1300 | BD31: =-AD31/$G31 -> -1099.9337 | BE31: =-AE31/$G31 -> -363.37693 | BF31: =-AF31/$G31 -> -19.330731 | BG31: =-AG31/$G31 -> -329.93032 | BH31: =-AH31/$G31 -> -1812.5717 | BI31: =AL31/$G31 -> -512.57167 | BJ31: =-AN31/$G31 -> -114.92593 | BK31: =-AP31/$G31 -> 6.2268534 | BL31: =-AQ31/$G31 -> -128.48147 | BM31: =-AR31/$G31 -> -34.635012 | BN31: =AS31/$G31 -> 35.552222 | BO31: =AT31/$G31 -> -640.13593 | BP31: =-AV31/$G31 -> -90.863367 | BQ31: =AW31/$G31 -> -730.9993 | BR31: =AY31/$G31 -> 75.778182 | BS31: =AZ31/$G31 -> -564.35775
B32: FEBRERO | C32: =B32 -> FEBRERO | D32: 168-2026B | E32: 43 | F32: 46075 | G32: 135 | H32: POTA FILETE CONGELADO | I32: Filete | J32: 2-4 AA | K32: China | L32: shidao | M32: AVANCE GROUP | N32: James | O32: 1300 | P32: 175500 | Q32: 1300 | R32: =3103*T32 -> 15515 | S32: =P32-R32 -> 159985 | T32: 5 | U32: ECO MARIN 26008S | V32: 6445260920 | W32: COSCO | X32: PAITA | Y32: Fresco | Z32: 10005721 | AA32: Compensación | AB32: =B32&Z32&AA32 -> FEBRERO10005721Compensación | AC32: =INDEX('Detalle Costos'!$L$5:$L$158,MATCH(Resumen!AB32,'Detalle Costos'!$C$5:$C$158,0))*1000*0+AJ32+229398.68/1634.3 -> 1812.5717 | AD32: =IFERROR(INDEX('Detalle Costos'!$X$5:$X$158,MATCH(Resumen!AB32,'Detalle Costos'!$C$5:$C$158,0))*AH32,0) -> 148491.05 | AE32: =IFERROR(INDEX('Detalle Costos'!$Z$5:$Z$158,MATCH(Resumen!AB32,'Detalle Costos'!$C$5:$C$158,0))*AH32,0) -> 49055.886 | AF32: =IFERROR(INDEX('Detalle Costos'!$Y$5:$Y$158,MATCH(Resumen!AB32,'Detalle Costos'!$C$5:$C$158,0))*AH32,0) -> 2609.6487 | AG32: =IFERROR(INDEX('Detalle Costos'!$AA$5:$AA$158,MATCH(Resumen!AB32,'Detalle Costos'!$C$5:$C$158,0))*AH32,0) -> 44540.593 | AH32: =AC32*G32 -> 244697.18 | AI32: =+G32 -> 135 | AJ32: 1672.2066 | AK32: 238110 | AL32: =P32-AH32 -> -69197.176 | AM32: =AL32/P32 -> -0.3942859 | AN32: =R32 -> 15515 | AO32: =118461.136538461/5988.21*G32 -> 2670.6233 | AP32: =-10174.6784147361/1634*G32 -> -840.62521 | AQ32: =SUM(AN32:AP32) -> 17344.998 | AR32: =56604/1634.3*G32 -> 4675.7266 | AS32: =S32*0.03 -> 4799.55 | AT32: =AL32-AQ32-AR32+AS32 -> -86418.35 | AU32: =AT32/P32 -> -0.49241225 | AV32: =148498/1634.3*G32 -> 12266.554 | AW32: =AT32-AV32 -> -98684.905 | AX32: =AW32/P32 -> -0.56230715 | AY32: =123844.283333333/1634.3*G32 -> 10230.055 | AZ32: =AT32+AY32 -> -76188.296 | BA32: =AZ32/P32 -> -0.43412134 | BC32: =P32/$G32 -> 1300 | BD32: =-AD32/$G32 -> -1099.9337 | BE32: =-AE32/$G32 -> -363.37693 | BF32: =-AF32/$G32 -> -19.330731 | BG32: =-AG32/$G32 -> -329.93032 | BH32: =-AH32/$G32 -> -1812.5717 | BI32: =AL32/$G32 -> -512.57167 | BJ32: =-AN32/$G32 -> -114.92593 | BK32: =-AP32/$G32 -> 6.2268534 | BL32: =-AQ32/$G32 -> -128.48147 | BM32: =-AR32/$G32 -> -34.635012 | BN32: =AS32/$G32 -> 35.552222 | BO32: =AT32/$G32 -> -640.13593 | BP32: =-AV32/$G32 -> -90.863367 | BQ32: =AW32/$G32 -> -730.9993 | BR32: =AY32/$G32 -> 75.778182 | BS32: =AZ32/$G32 -> -564.35775
B33: FEBRERO | C33: =B33 -> FEBRERO | D33: 168-2026C | E33: 43 | F33: 46075 | G33: 54 | H33: POTA FILETE CONGELADO | I33: Filete | J33: 2-4 AA | K33: China | L33: Xiamen | M33: AVANCE GROUP | N33: James | O33: 1300 | P33: 70200 | Q33: 1300 | R33: =3103*T33 -> 6206 | S33: =P33-R33 -> 63994 | T33: 2 | U33: ECO MARIN 26008S | V33: 6445502930 | W33: COSCO | X33: PAITA | Y33: Fresco | Z33: 10005721 | AA33: Compensación | AB33: =B33&Z33&AA33 -> FEBRERO10005721Compensación | AC33: =INDEX('Detalle Costos'!$L$5:$L$158,MATCH(Resumen!AB33,'Detalle Costos'!$C$5:$C$158,0))*1000*0+AJ33+229398.68/1634.3 -> 1812.5717 | AD33: =IFERROR(INDEX('Detalle Costos'!$X$5:$X$158,MATCH(Resumen!AB33,'Detalle Costos'!$C$5:$C$158,0))*AH33,0) -> 59396.419 | AE33: =IFERROR(INDEX('Detalle Costos'!$Z$5:$Z$158,MATCH(Resumen!AB33,'Detalle Costos'!$C$5:$C$158,0))*AH33,0) -> 19622.354 | AF33: =IFERROR(INDEX('Detalle Costos'!$Y$5:$Y$158,MATCH(Resumen!AB33,'Detalle Costos'!$C$5:$C$158,0))*AH33,0) -> 1043.8595 | AG33: =IFERROR(INDEX('Detalle Costos'!$AA$5:$AA$158,MATCH(Resumen!AB33,'Detalle Costos'!$C$5:$C$158,0))*AH33,0) -> 17816.237 | AH33: =AC33*G33 -> 97878.87 | AI33: =+G33 -> 54 | AJ33: 1672.2066 | AK33: =+AJ33*AI33 -> 90299.155 | AL33: =P33-AH33 -> -27678.87 | AM33: =AL33/P33 -> -0.3942859 | AN33: =R33 -> 6206 | AO33: =118461.136538461/5988.21*G33 -> 1068.2493 | AP33: =-10174.6784147361/1634*G33 -> -336.25008 | AQ33: =SUM(AN33:AP33) -> 6937.9993 | AR33: =56604/1634.3*G33 -> 1870.2906 | AS33: =S33*0.03 -> 1919.82 | AT33: =AL33-AQ33-AR33+AS33 -> -34567.34 | AU33: =AT33/P33 -> -0.49241225 | AV33: =148498/1634.3*G33 -> 4906.6218 | AW33: =AT33-AV33 -> -39473.962 | AX33: =AW33/P33 -> -0.56230715 | AY33: =123844.283333333/1634.3*G33 -> 4092.0218 | AZ33: =AT33+AY33 -> -30475.318 | BA33: =AZ33/P33 -> -0.43412134 | BC33: =P33/$G33 -> 1300 | BD33: =-AD33/$G33 -> -1099.9337 | BE33: =-AE33/$G33 -> -363.37693 | BF33: =-AF33/$G33 -> -19.330731 | BG33: =-AG33/$G33 -> -329.93032 | BH33: =-AH33/$G33 -> -1812.5717 | BI33: =AL33/$G33 -> -512.57167 | BJ33: =-AN33/$G33 -> -114.92593 | BK33: =-AP33/$G33 -> 6.2268534 | BL33: =-AQ33/$G33 -> -128.48147 | BM33: =-AR33/$G33 -> -34.635012 | BN33: =AS33/$G33 -> 35.552222 | BO33: =AT33/$G33 -> -640.13593 | BP33: =-AV33/$G33 -> -90.863367 | BQ33: =AW33/$G33 -> -730.9993 | BR33: =AY33/$G33 -> 75.778182 | BS33: =AZ33/$G33 -> -564.35775
B34: FEBRERO | C34: =B34 -> FEBRERO | D34: 170-2026A | E34: 43 | F34: 46076 | G34: 156 | H34: POTA REJOS CONGELADOS | I34: Rejos | J34: 9 FCL 1-2 / 1 FCL 2-UP | K34: España | L34: Vigo | M34: KULALIA | N34: Ramon | O34: 2500 | P34: 390000 | Q34: 2337.2308 | R34: 25392 | S34: =P34-R34 -> 364608 | T34: 4 | U34: CAPE SABLE 609N | V34: 11428031 | W34: HAPAG | X34: PAITA | Y34: Fresco | Z34: 10007162 | AA34: Compensación | AB34: =B34&Z34&AA34 -> FEBRERO10007162Compensación | AC34: =INDEX('Detalle Costos'!$L$5:$L$158,MATCH(Resumen!AB34,'Detalle Costos'!$C$5:$C$158,0))*1000*0+AJ34+229398.68/1634.3 -> 1806.2113 | AD34: =IFERROR(INDEX('Detalle Costos'!$X$5:$X$158,MATCH(Resumen!AB34,'Detalle Costos'!$C$5:$C$158,0))*AH34,0) -> 176884.88 | AE34: =IFERROR(INDEX('Detalle Costos'!$Z$5:$Z$158,MATCH(Resumen!AB34,'Detalle Costos'!$C$5:$C$158,0))*AH34,0) -> 50472.683 | AF34: =IFERROR(INDEX('Detalle Costos'!$Y$5:$Y$158,MATCH(Resumen!AB34,'Detalle Costos'!$C$5:$C$158,0))*AH34,0) -> 2627.8446 | AG34: =IFERROR(INDEX('Detalle Costos'!$AA$5:$AA$158,MATCH(Resumen!AB34,'Detalle Costos'!$C$5:$C$158,0))*AH34,0) -> 51783.557 | AH34: =AC34*G34 -> 281768.96 | AI34: =+G34 -> 156 | AJ34: 1665.8462 | AK34: =AJ34*AI34 -> 259872.01 | AL34: =P34-AH34 -> 108231.04 | AM34: =AL34/P34 -> 0.27751548 | AN34: =R34 -> 25392 | AO34: =118461.136538461/5988.21*G34 -> 3086.0536 | AP34: =-10174.6784147361/1634*G34 -> -971.38913 | AQ34: =SUM(AN34:AP34) -> 27506.665 | AR34: =56604/1634.3*G34 -> 5403.0619 | AS34: =S34*0.03 -> 10938.24 | AT34: =AL34-AQ34-AR34+AS34 -> 86259.549 | AU34: =AT34/P34 -> 0.22117833 | AV34: =148498/1634.3*G34 -> 14174.685 | AW34: =AT34-AV34 -> 72084.864 | AX34: =AW34/P34 -> 0.18483298 | AY34: =123844.283333333/1634.3*G34 -> 11821.396 | AZ34: =AT34+AY34 -> 98080.946 | BA34: =AZ34/P34 -> 0.2514896 | BC34: =P34/$G34 -> 2500 | BD34: =-AD34/$G34 -> -1133.8774 | BE34: =-AE34/$G34 -> -323.54284 | BF34: =-AF34/$G34 -> -16.845158 | BG34: =-AG34/$G34 -> -331.94588 | BH34: =-AH34/$G34 -> -1806.2113 | BI34: =AL34/$G34 -> 693.78869 | BJ34: =-AN34/$G34 -> -162.76923 | BK34: =-AP34/$G34 -> 6.2268534 | BL34: =-AQ34/$G34 -> -176.32477 | BM34: =-AR34/$G34 -> -34.635012 | BN34: =AS34/$G34 -> 70.116923 | BO34: =AT34/$G34 -> 552.94583 | BP34: =-AV34/$G34 -> -90.863367 | BQ34: =AW34/$G34 -> 462.08246 | BR34: =AY34/$G34 -> 75.778182 | BS34: =AZ34/$G34 -> 628.72401
B35: FEBRERO | C35: =B35 -> FEBRERO | E35: 46080 | F35: 46080 | G35: 0 | H35: RESIDUOS DE POTA | I35: Residuos | J35: Residuos | K35: Residuos | L35: Residuos | M35: PROVEEDORA DE PRODUCTOS MARINOS | O35: 0 | P35: 40026 | Q35: 0 | R35: 0 | S35: =P35-R35 -> 40026 | Y35: Residuo | AC35: 0 | AD35: =IFERROR(INDEX('Detalle Costos'!$X$5:$X$158,MATCH(Resumen!AB35,'Detalle Costos'!$C$5:$C$158,0))*AH35,0) -> 0 | AE35: =IFERROR(INDEX('Detalle Costos'!$Z$5:$Z$158,MATCH(Resumen!AB35,'Detalle Costos'!$C$5:$C$158,0))*AH35,0) -> 0 | AF35: =IFERROR(INDEX('Detalle Costos'!$Y$5:$Y$158,MATCH(Resumen!AB35,'Detalle Costos'!$C$5:$C$158,0))*AH35,0) -> 0 | AG35: =IFERROR(INDEX('Detalle Costos'!$AA$5:$AA$158,MATCH(Resumen!AB35,'Detalle Costos'!$C$5:$C$158,0))*AH35,0) -> 0 | AH35: =AC35*G35 -> 0 | AL35: =P35-AH35 -> 40026 | AM35: =AL35/P35 -> 1 | AN35: =R35 -> 0 | AO35: =118461.136538461/5988.21*G35 -> 0 | AP35: 0 | AQ35: =SUM(AN35:AP35) -> 0 | AR35: =56604/1634.3*G35 -> 0 | AS35: 0 | AT35: =AL35-AQ35-AR35+AS35 -> 40026 | AU35: =AT35/P35 -> 1 | AV35: =131251/248*G35 -> 0 | AW35: =AT35-AV35 -> 40026 | AX35: =AW35/P35 -> 1 | AY35: =123844.283333333/1634.3*G35 -> 0 | AZ35: =AT35+AY35 -> 40026 | BA35: =AZ35/P35 -> 1 | BC35: =P35/$G35 -> #DIV/0! | BD35: =-AD35/$G35 -> #DIV/0! | BE35: =-AE35/$G35 -> #DIV/0! | BF35: =-AF35/$G35 -> #DIV/0! | BG35: =-AG35/$G35 -> #DIV/0! | BH35: =-AH35/$G35 -> #DIV/0! | BI35: =AL35/$G35 -> #DIV/0! | BJ35: =-AN35/$G35 -> #DIV/0! | BK35: =-AP35/$G35 -> #DIV/0! | BL35: =-AQ35/$G35 -> #DIV/0! | BM35: =-AR35/$G35 -> #DIV/0! | BN35: =AS35/$G35 -> #DIV/0! | BO35: =AT35/$G35 -> #DIV/0! | BP35: =-AV35/$G35 -> #DIV/0! | BQ35: =AW35/$G35 -> #DIV/0! | BR35: =AY35/$G35 -> #DIV/0! | BS35: =AZ35/$G35 -> #DIV/0!
B36: FEBRERO | C36: MARZO | D36: 150-2026B | E36: 325 | F36: 46084 | G36: 26 | H36: POTA REJOS CONGELADOS | I36: Rejos | J36: 1-2 KG | K36: España | L36: Vigo | M36: OVERSEA | N36: Avelino | O36: 2600 | P36: 67600 | Q36: 2518.6154 | R36: 4232 | S36: =P36-R36 -> 63368 | T36: 1 | U36: LEONIDAS Z 610N | V36: 51077247 | Y36: Fresco | Z36: 10007162 | AA36: Inventario final | AB36: =B36&Z36&AA36 -> FEBRERO10007162Inventario final | AC36: =AJ36-616968.19/1968.8+215187/1968.8 -> 1814.1051 | AD36: =IFERROR(INDEX('Costos Producción Febrero'!$G$34:$G$57,MATCH(Resumen!Z36,'Costos Producción Febrero'!$B$34:$B$57,0))*AC36*G36,0) -> 28920.313 | AE36: =IFERROR(INDEX('Costos Producción Febrero'!$H$34:$H$57,MATCH(Resumen!Z36,'Costos Producción Febrero'!$B$34:$B$57,0))*AC36*G36,0) -> 8211.0537 | AF36: =IFERROR(INDEX('Costos Producción Febrero'!$I$34:$I$57,MATCH(Resumen!Z36,'Costos Producción Febrero'!$B$34:$B$57,0))*AC36*G36,0) -> 437.26345 | AG36: =IFERROR(INDEX('Costos Producción Febrero'!$J$34:$J$57,MATCH(Resumen!Z36,'Costos Producción Febrero'!$B$34:$B$57,0))*AC36*G36,0) -> 9598.1029 | AH36: =SUM(AD36:AG36) -> 47166.733 | AJ36: 2018.1793 | AL36: =P36-AH36 -> 20433.267 | AM36: =AL36/P36 -> 0.30226726 | AN36: =R36 -> 4232 | AO36: =118461.136538461/5988.21*G36 -> 514.34227 | AP36: =106.583523265795*G36 -> 2771.1716 | AQ36: =SUM(AN36:AP36) -> 7517.5139 | AR36: =78579/1995.8*G36 -> 1023.6767 | AS36: =S36*0.03 -> 1901.04 | AT36: =AL36-AQ36-AR36+AS36 -> 13793.116 | AU36: =AT36/P36 -> 0.20404018 | AV36: =154473/1995.8*G36 -> 2012.375 | AW36: =AT36-AV36 -> 11780.741 | AX36: =AW36/P36 -> 0.17427132 | AY36: =123844.283333333/1995.8*G36 -> 1613.3637 | AZ36: =AT36+AY36 -> 15406.48 | BA36: =AZ36/P36 -> 0.2279065 | BC36: =P36/$G36 -> 2600 | BD36: =-AD36/$G36 -> -1112.3197 | BE36: =-AE36/$G36 -> -315.80976 | BF36: =-AF36/$G36 -> -16.817825 | BG36: =-AG36/$G36 -> -369.15781 | BH36: =-AH36/$G36 -> -1814.1051 | BI36: =AL36/$G36 -> 785.89487 | BJ36: =-AN36/$G36 -> -162.76923 | BK36: =-AP36/$G36 -> -106.58352 | BL36: =-AQ36/$G36 -> -289.13515 | BM36: =-AR36/$G36 -> -39.372182 | BN36: =AS36/$G36 -> 73.116923 | BO36: =AT36/$G36 -> 530.50446 | BP36: =-AV36/$G36 -> -77.399038 | BQ36: =AW36/$G36 -> 453.10542 | BR36: =AY36/$G36 -> 62.052452 | BS36: =AZ36/$G36 -> 592.55691
B37: FEBRERO | C37: MARZO | D37: 150-2026C | E37: 325 | F37: 46084 | G37: 26 | H37: POTA REJOS CONGELADOS | I37: Rejos | J37: 1-2 KG | K37: España | L37: Vigo | M37: OVERSEA | N37: Avelino | O37: 2600 | P37: 67600 | Q37: 2518.6154 | R37: 4232 | S37: =P37-R37 -> 63368 | T37: 1 | U37: LEONIDAS Z 610N | V37: 37563181 | Y37: Fresco | Z37: 10007162 | AA37: Inventario final | AB37: =B37&Z37&AA37 -> FEBRERO10007162Inventario final | AC37: =AJ37-616968.19/1968.8+215187/1968.8 -> 1814.1051 | AD37: =IFERROR(INDEX('Costos Producción Febrero'!$G$34:$G$57,MATCH(Resumen!Z37,'Costos Producción Febrero'!$B$34:$B$57,0))*AC37*G37,0) -> 28920.313 | AE37: =IFERROR(INDEX('Costos Producción Febrero'!$H$34:$H$57,MATCH(Resumen!Z37,'Costos Producción Febrero'!$B$34:$B$57,0))*AC37*G37,0) -> 8211.0537 | AF37: =IFERROR(INDEX('Costos Producción Febrero'!$I$34:$I$57,MATCH(Resumen!Z37,'Costos Producción Febrero'!$B$34:$B$57,0))*AC37*G37,0) -> 437.26345 | AG37: =IFERROR(INDEX('Costos Producción Febrero'!$J$34:$J$57,MATCH(Resumen!Z37,'Costos Producción Febrero'!$B$34:$B$57,0))*AC37*G37,0) -> 9598.1029 | AH37: =SUM(AD37:AG37) -> 47166.733 | AJ37: 2018.1793 | AL37: =P37-AH37 -> 20433.267 | AM37: =AL37/P37 -> 0.30226726 | AN37: =R37 -> 4232 | AO37: =118461.136538461/5988.21*G37 -> 514.34227 | AP37: =106.583523265795*G37 -> 2771.1716 | AQ37: =SUM(AN37:AP37) -> 7517.5139 | AR37: =78579/1995.8*G37 -> 1023.6767 | AS37: =S37*0.03 -> 1901.04 | AT37: =AL37-AQ37-AR37+AS37 -> 13793.116 | AU37: =AT37/P37 -> 0.20404018 | AV37: =154473/1995.8*G37 -> 2012.375 | AW37: =AT37-AV37 -> 11780.741 | AX37: =AW37/P37 -> 0.17427132 | AY37: =123844.283333333/1995.8*G37 -> 1613.3637 | AZ37: =AT37+AY37 -> 15406.48 | BA37: =AZ37/P37 -> 0.2279065 | BC37: =P37/$G37 -> 2600 | BD37: =-AD37/$G37 -> -1112.3197 | BE37: =-AE37/$G37 -> -315.80976 | BF37: =-AF37/$G37 -> -16.817825 | BG37: =-AG37/$G37 -> -369.15781 | BH37: =-AH37/$G37 -> -1814.1051 | BI37: =AL37/$G37 -> 785.89487 | BJ37: =-AN37/$G37 -> -162.76923 | BK37: =-AP37/$G37 -> -106.58352 | BL37: =-AQ37/$G37 -> -289.13515 | BM37: =-AR37/$G37 -> -39.372182 | BN37: =AS37/$G37 -> 73.116923 | BO37: =AT37/$G37 -> 530.50446 | BP37: =-AV37/$G37 -> -77.399038 | BQ37: =AW37/$G37 -> 453.10542 | BR37: =AY37/$G37 -> 62.052452 | BS37: =AZ37/$G37 -> 592.55691
B38: FEBRERO | C38: MARZO | D38: 159-2026A | E38: 30 | F38: 46084 | G38: 24 | H38: POTA FILETE CONGELADO | I38: Filete | J38: B | K38: Japón | L38: Sendai | M38: TSUJINO | N38: Jose | O38: 1700 | P38: =40800-1190 -> 39610 | Q38: 1562.375 | R38: 3303 | S38: =P38-R38 -> 36307 | T38: 1 | U38: ECO SIROCCO 26009N | V38: LIMG03265300 | W38: ONE | X38: PAITA | Y38: Fresco | Z38: 10005721 | AA38: Inventario final | AB38: =B38&Z38&AA38 -> FEBRERO10005721Inventario final | AC38: =AJ38-616968.19/1968.8+215187/1968.8 -> 1891.1947 | AD38: =IFERROR(INDEX('Costos Producción Febrero'!$G$34:$G$57,MATCH(Resumen!Z38,'Costos Producción Febrero'!$B$34:$B$57,0))*AC38*G38,0) -> 27565.037 | AE38: =IFERROR(INDEX('Costos Producción Febrero'!$H$34:$H$57,MATCH(Resumen!Z38,'Costos Producción Febrero'!$B$34:$B$57,0))*AC38*G38,0) -> 8077.128 | AF38: =IFERROR(INDEX('Costos Producción Febrero'!$I$34:$I$57,MATCH(Resumen!Z38,'Costos Producción Febrero'!$B$34:$B$57,0))*AC38*G38,0) -> 494.82304 | AG38: =IFERROR(INDEX('Costos Producción Febrero'!$J$34:$J$57,MATCH(Resumen!Z38,'Costos Producción Febrero'!$B$34:$B$57,0))*AC38*G38,0) -> 9251.6856 | AH38: =SUM(AD38:AG38) -> 45388.673 | AJ38: 2095.2689 | AL38: =P38-AH38 -> -5778.6734 | AM38: =AL38/P38 -> -0.14588926 | AN38: =R38 -> 3303 | AO38: =118461.136538461/5988.21*G38 -> 474.77748 | AP38: =106.583523265795*G38 -> 2558.0046 | AQ38: =SUM(AN38:AP38) -> 6335.782 | AR38: =78579/1995.8*G38 -> 944.93236 | AS38: =S38*0.03 -> 1089.21 | AT38: =AL38-AQ38-AR38+AS38 -> -11970.178 | AU38: =AT38/P38 -> -0.3022009 | AV38: =154473/1995.8*G38 -> 1857.5769 | AW38: =AT38-AV38 -> -13827.755 | AX38: =AW38/P38 -> -0.34909757 | AY38: =123844.283333333/1995.8*G38 -> 1489.2588 | AZ38: =AT38+AY38 -> -10480.919 | BA38: =AZ38/P38 -> -0.26460285 | BC38: =P38/$G38 -> 1650.4167 | BD38: =-AD38/$G38 -> -1148.5432 | BE38: =-AE38/$G38 -> -336.547 | BF38: =-AF38/$G38 -> -20.617627 | BG38: =-AG38/$G38 -> -385.4869 | BH38: =-AH38/$G38 -> -1891.1947 | BI38: =AL38/$G38 -> -240.77806 | BJ38: =-AN38/$G38 -> -137.625 | BK38: =-AP38/$G38 -> -106.58352 | BL38: =-AQ38/$G38 -> -263.99092 | BM38: =-AR38/$G38 -> -39.372182 | BN38: =AS38/$G38 -> 45.38375 | BO38: =AT38/$G38 -> -498.75741 | BP38: =-AV38/$G38 -> -77.399038 | BQ38: =AW38/$G38 -> -576.15645 | BR38: =AY38/$G38 -> 62.052452 | BS38: =AZ38/$G38 -> -436.70496
B39: FEBRERO | C39: MARZO | D39: 161-2026A | E39: 30 | F39: 46085 | G39: 72 | H39: POTA NUCAS | I39: Nucas | J39: 500-up | K39: Tailandia | L39: Lat Krabang | M39: TSUJINO | N39: Jose | O39: 1400 | P39: =100800-6160 -> 94640 | Q39: 1266.5417 | R39: 9609 | S39: =P39-R39 -> 85031 | T39: 3 | U39: ECO SIROCCO 26009N | V39: LIMG03094300 | W39: ONE LINE | X39: PAITA | Y39: Fresco | Z39: 10005779 | AA39: Inventario final | AB39: =B39&Z39&AA39 -> FEBRERO10005779Inventario final | AC39: =AJ39-616968.19/1968.8+215187/1968.8 -> 1896.1639 | AD39: =IFERROR(INDEX('Costos Producción Febrero'!$G$34:$G$57,MATCH(Resumen!Z39,'Costos Producción Febrero'!$B$34:$B$57,0))*AC39*G39,0) -> 79265.823 | AE39: =IFERROR(INDEX('Costos Producción Febrero'!$H$34:$H$57,MATCH(Resumen!Z39,'Costos Producción Febrero'!$B$34:$B$57,0))*AC39*G39,0) -> 30165.469 | AF39: =IFERROR(INDEX('Costos Producción Febrero'!$I$34:$I$57,MATCH(Resumen!Z39,'Costos Producción Febrero'!$B$34:$B$57,0))*AC39*G39,0) -> 872.01905 | AG39: =IFERROR(INDEX('Costos Producción Febrero'!$J$34:$J$57,MATCH(Resumen!Z39,'Costos Producción Febrero'!$B$34:$B$57,0))*AC39*G39,0) -> 26220.492 | AH39: =SUM(AD39:AG39) -> 136523.8 | AJ39: 2100.2381 | AL39: =P39-AH39 -> -41883.803 | AM39: =AL39/P39 -> -0.4425592 | AN39: =R39 -> 9609 | AO39: =118461.136538461/5988.21*G39 -> 1424.3325 | AP39: =106.583523265795*G39 -> 7674.0137 | AQ39: =SUM(AN39:AP39) -> 18707.346 | AR39: =78579/1995.8*G39 -> 2834.7971 | AS39: =S39*0.03 -> 2550.93 | AT39: =AL39-AQ39-AR39+AS39 -> -60875.016 | AU39: =AT39/P39 -> -0.64322714 | AV39: =154473/1995.8*G39 -> 5572.7307 | AW39: =AT39-AV39 -> -66447.747 | AX39: =AW39/P39 -> -0.7021106 | AY39: =123844.283333333/1995.8*G39 -> 4467.7765 | AZ39: =AT39+AY39 -> -56407.24 | BA39: =AZ39/P39 -> -0.59601902 | BC39: =P39/$G39 -> 1314.4444 | BD39: =-AD39/$G39 -> -1100.9142 | BE39: =-AE39/$G39 -> -418.96484 | BF39: =-AF39/$G39 -> -12.111376 | BG39: =-AG39/$G39 -> -364.17351 | BH39: =-AH39/$G39 -> -1896.1639 | BI39: =AL39/$G39 -> -581.71949 | BJ39: =-AN39/$G39 -> -133.45833 | BK39: =-AP39/$G39 -> -106.58352 | BL39: =-AQ39/$G39 -> -259.82425 | BM39: =-AR39/$G39 -> -39.372182 | BN39: =AS39/$G39 -> 35.429583 | BO39: =AT39/$G39 -> -845.48634 | BP39: =-AV39/$G39 -> -77.399038 | BQ39: =AW39/$G39 -> -922.88538 | BR39: =AY39/$G39 -> 62.052452 | BS39: =AZ39/$G39 -> -783.43389
B40: FEBRERO | C40: MARZO | D40: 161-2026B | E40: 30 | F40: 46108 | G40: 48 | H40: POTA NUCAS | I40: Nucas | J40: 500-up | K40: Tailandia | L40: Lat Krabang | M40: TSUJINO | N40: Jose | O40: 1400 | P40: 67200 | Q40: 1254.1667 | R40: 7000 | S40: =P40-R40 -> 60200 | T40: 2 | U40: ECO SIROCCO 26013S | V40: 6446527790 | W40: COSCO | X40: PAITA | Y40: Fresco | Z40: 10005779 | AA40: Inventario final | AB40: =B40&Z40&AA40 -> FEBRERO10005779Inventario final | AC40: =AJ40-616968.19/1968.8+215187/1968.8 -> 1896.1639 | AD40: =IFERROR(INDEX('Costos Producción Febrero'!$G$34:$G$57,MATCH(Resumen!Z40,'Costos Producción Febrero'!$B$34:$B$57,0))*AC40*G40,0) -> 52843.882 | AE40: =IFERROR(INDEX('Costos Producción Febrero'!$H$34:$H$57,MATCH(Resumen!Z40,'Costos Producción Febrero'!$B$34:$B$57,0))*AC40*G40,0) -> 20110.313 | AF40: =IFERROR(INDEX('Costos Producción Febrero'!$I$34:$I$57,MATCH(Resumen!Z40,'Costos Producción Febrero'!$B$34:$B$57,0))*AC40*G40,0) -> 581.34604 | AG40: =IFERROR(INDEX('Costos Producción Febrero'!$J$34:$J$57,MATCH(Resumen!Z40,'Costos Producción Febrero'!$B$34:$B$57,0))*AC40*G40,0) -> 17480.328 | AH40: =SUM(AD40:AG40) -> 91015.869 | AJ40: 2100.2381 | AL40: =P40-AH40 -> -23815.869 | AM40: =AL40/P40 -> -0.35440281 | AN40: =R40 -> 7000 | AO40: =118461.136538461/5988.21*G40 -> 949.55497 | AP40: =106.583523265795*G40 -> 5116.0091 | AQ40: =SUM(AN40:AP40) -> 13065.564 | AR40: =78579/1995.8*G40 -> 1889.8647 | AS40: =S40*0.03 -> 1806 | AT40: =AL40-AQ40-AR40+AS40 -> -36965.298 | AU40: =AT40/P40 -> -0.55007883 | AV40: =154473/1995.8*G40 -> 3715.1538 | AW40: =AT40-AV40 -> -40680.451 | AX40: =AW40/P40 -> -0.60536386 | AY40: =123844.283333333/1995.8*G40 -> 2978.5177 | AZ40: =AT40+AY40 -> -33986.78 | BA40: =AZ40/P40 -> -0.50575565 | BC40: =P40/$G40 -> 1400 | BD40: =-AD40/$G40 -> -1100.9142 | BE40: =-AE40/$G40 -> -418.96484 | BF40: =-AF40/$G40 -> -12.111376 | BG40: =-AG40/$G40 -> -364.17351 | BH40: =-AH40/$G40 -> -1896.1639 | BI40: =AL40/$G40 -> -496.16393 | BJ40: =-AN40/$G40 -> -145.83333 | BK40: =-AP40/$G40 -> -106.58352 | BL40: =-AQ40/$G40 -> -272.19925 | BM40: =-AR40/$G40 -> -39.372182 | BN40: =AS40/$G40 -> 37.625 | BO40: =AT40/$G40 -> -770.11037 | BP40: =-AV40/$G40 -> -77.399038 | BQ40: =AW40/$G40 -> -847.5094 | BR40: =AY40/$G40 -> 62.052452 | BS40: =AZ40/$G40 -> -708.05791
B41: FEBRERO | C41: MARZO | D41: 163-2026 | E41: 34 | F41: 46087 | G41: 48 | H41: POTA ALAS CONGELADAS | I41: Alas | J41: 1-up | K41: Corea | L41: Busan | M41: TSUJINO | N41: Jose | O41: 1600 | P41: 76800 | Q41: 1479.1667 | R41: 5800 | S41: =P41-R41 -> 71000 | T41: 2 | U41: ECO MARIN 26010S | V41: 6445718250 | W41: COSCO | X41: PAITA | Y41: Fresco | Z41: 10006720 | AA41: Inventario final | AB41: =B41&Z41&AA41 -> FEBRERO10006720Inventario final | AC41: =AJ41-616968.19/1968.8+215187/1968.8 -> 1745.124 | AD41: =IFERROR(INDEX('Costos Producción Febrero'!$G$34:$G$57,MATCH(Resumen!Z41,'Costos Producción Febrero'!$B$34:$B$57,0))*AC41*G41,0) -> 53752.027 | AE41: =IFERROR(INDEX('Costos Producción Febrero'!$H$34:$H$57,MATCH(Resumen!Z41,'Costos Producción Febrero'!$B$34:$B$57,0))*AC41*G41,0) -> 11306.056 | AF41: =IFERROR(INDEX('Costos Producción Febrero'!$I$34:$I$57,MATCH(Resumen!Z41,'Costos Producción Febrero'!$B$34:$B$57,0))*AC41*G41,0) -> 782.69656 | AG41: =IFERROR(INDEX('Costos Producción Febrero'!$J$34:$J$57,MATCH(Resumen!Z41,'Costos Producción Febrero'!$B$34:$B$57,0))*AC41*G41,0) -> 17925.17 | AH41: =SUM(AD41:AG41) -> 83765.95 | AJ41: 1949.1981 | AL41: =P41-AH41 -> -6965.9504 | AM41: =AL41/P41 -> -0.090702479 | AN41: =R41 -> 5800 | AO41: =118461.136538461/5988.21*G41 -> 949.55497 | AP41: =106.583523265795*G41 -> 5116.0091 | AQ41: =SUM(AN41:AP41) -> 11865.564 | AR41: =78579/1995.8*G41 -> 1889.8647 | AS41: =S41*0.03 -> 2130 | AT41: =AL41-AQ41-AR41+AS41 -> -18591.379 | AU41: =AT41/P41 -> -0.24207525 | AV41: =154473/1995.8*G41 -> 3715.1538 | AW41: =AT41-AV41 -> -22306.533 | AX41: =AW41/P41 -> -0.29044965 | AY41: =123844.283333333/1995.8*G41 -> 2978.5177 | AZ41: =AT41+AY41 -> -15612.861 | BA41: =AZ41/P41 -> -0.20329247 | BC41: =P41/$G41 -> 1600 | BD41: =-AD41/$G41 -> -1119.8339 | BE41: =-AE41/$G41 -> -235.54284 | BF41: =-AF41/$G41 -> -16.306178 | BG41: =-AG41/$G41 -> -373.44105 | BH41: =-AH41/$G41 -> -1745.124 | BI41: =AL41/$G41 -> -145.12397 | BJ41: =-AN41/$G41 -> -120.83333 | BK41: =-AP41/$G41 -> -106.58352 | BL41: =-AQ41/$G41 -> -247.19925 | BM41: =-AR41/$G41 -> -39.372182 | BN41: =AS41/$G41 -> 44.375 | BO41: =AT41/$G41 -> -387.3204 | BP41: =-AV41/$G41 -> -77.399038 | BQ41: =AW41/$G41 -> -464.71944 | BR41: =AY41/$G41 -> 62.052452 | BS41: =AZ41/$G41 -> -325.26795
B42: FEBRERO | C42: MARZO | D42: 165-2026 | E42: 40 | F42: 46105 | G42: 27 | H42: POTA MEMBRANA PRECOCIDA | I42: Membrana | K42: China | L42: Qingdao | M42: Longkou Yunfeng Aquatic | O42: 1400 | P42: 35553 | Q42: 1271.6296 | R42: 3466 | S42: =P42-R42 -> 32087 | T42: 1 | U42: CMA CGM BETTER WAYS 0DVOHN1MA | V42: LMM0577574 | W42: CMA CGM | X42: PAITA | Y42: Subproducto | AC42: 0 | AD42: =IFERROR(INDEX('Costos Producción Febrero'!$G$34:$G$57,MATCH(Resumen!Z42,'Costos Producción Febrero'!$B$34:$B$57,0))*AC42*G42,0) -> 0 | AE42: =IFERROR(INDEX('Costos Producción Febrero'!$H$34:$H$57,MATCH(Resumen!Z42,'Costos Producción Febrero'!$B$34:$B$57,0))*AC42*G42,0) -> 0 | AF42: =IFERROR(INDEX('Costos Producción Febrero'!$I$34:$I$57,MATCH(Resumen!Z42,'Costos Producción Febrero'!$B$34:$B$57,0))*AC42*G42,0) -> 0 | AG42: =IFERROR(INDEX('Costos Producción Febrero'!$J$34:$J$57,MATCH(Resumen!Z42,'Costos Producción Febrero'!$B$34:$B$57,0))*AC42*G42,0) -> 0 | AH42: =SUM(AD42:AG42) -> 0 | AJ42: 0 | AL42: =P42-AH42 -> 35553 | AM42: =AL42/P42 -> 1 | AN42: =R42 -> 3466 | AO42: =118461.136538461/5988.21*G42 -> 534.12467 | AP42: =106.583523265795*G42 -> 2877.7551 | AQ42: =SUM(AN42:AP42) -> 6877.8798 | AR42: =78579/1995.8*G42 -> 1063.0489 | AS42: =S42*0.03 -> 962.61 | AT42: =AL42-AQ42-AR42+AS42 -> 28574.681 | AU42: =AT42/P42 -> 0.80372068 | AV42: =154473/1995.8*G42 -> 2089.774 | AW42: =AT42-AV42 -> 26484.907 | AX42: =AW42/P42 -> 0.74494156 | AY42: =123844.283333333/1995.8*G42 -> 1675.4162 | AZ42: =AT42+AY42 -> 30250.097 | BA42: =AZ42/P42 -> 0.85084515 | BC42: =P42/$G42 -> 1316.7778 | BD42: =-AD42/$G42 -> 0 | BE42: =-AE42/$G42 -> 0 | BF42: =-AF42/$G42 -> 0 | BG42: =-AG42/$G42 -> 0 | BH42: =-AH42/$G42 -> 0 | BI42: =AL42/$G42 -> 1316.7778 | BJ42: =-AN42/$G42 -> -128.37037 | BK42: =-AP42/$G42 -> -106.58352 | BL42: =-AQ42/$G42 -> -254.73629 | BM42: =-AR42/$G42 -> -39.372182 | BN42: =AS42/$G42 -> 35.652222 | BO42: =AT42/$G42 -> 1058.3215 | BP42: =-AV42/$G42 -> -77.399038 | BQ42: =AW42/$G42 -> 980.92249 | BR42: =AY42/$G42 -> 62.052452 | BS42: =AZ42/$G42 -> 1120.374
B43: FEBRERO | C43: MARZO | D43: 167-2026 | E43: 42 | F43: 46104 | G43: 48 | H43: POTA CONOS | I43: Conos | K43: Tailandia | L43: Bangkok | M43: TSUJINO | N43: Jose | O43: 1600 | P43: 76800 | Q43: 1462.5 | R43: 6600 | S43: =P43-R43 -> 70200 | T43: 2 | U43: ECO MARIN 26012S | V43: 6446513180 | W43: COSCO | X43: PAITA | Y43: Subproducto | Z43: 10007969 | AA43: Inventario final | AB43: =B43&Z43&AA43 -> FEBRERO10007969Inventario final | AC43: =AJ43-616968.19/1968.8+215187/1968.8 -> 1391.3655 | AD43: =IFERROR(INDEX('Costos Producción Febrero'!$G$34:$G$57,MATCH(Resumen!Z43,'Costos Producción Febrero'!$B$34:$B$57,0))*AC43*G43,0) -> 56573.815 | AE43: =IFERROR(INDEX('Costos Producción Febrero'!$H$34:$H$57,MATCH(Resumen!Z43,'Costos Producción Febrero'!$B$34:$B$57,0))*AC43*G43,0) -> 11361.112 | AF43: =IFERROR(INDEX('Costos Producción Febrero'!$I$34:$I$57,MATCH(Resumen!Z43,'Costos Producción Febrero'!$B$34:$B$57,0))*AC43*G43,0) -> 874.22365 | AG43: =IFERROR(INDEX('Costos Producción Febrero'!$J$34:$J$57,MATCH(Resumen!Z43,'Costos Producción Febrero'!$B$34:$B$57,0))*AC43*G43,0) -> -2023.608 | AH43: =SUM(AD43:AG43) -> 66785.543 | AJ43: 1595.4396 | AL43: =P43-AH43 -> 10014.457 | AM43: =AL43/P43 -> 0.13039658 | AN43: =R43 -> 6600 | AO43: =118461.136538461/5988.21*G43 -> 949.55497 | AP43: =106.583523265795*G43 -> 5116.0091 | AQ43: =SUM(AN43:AP43) -> 12665.564 | AR43: =78579/1995.8*G43 -> 1889.8647 | AS43: =S43*0.03 -> 2106 | AT43: =AL43-AQ43-AR43+AS43 -> -2434.9718 | AU43: =AT43/P43 -> -0.031705362 | AV43: =154473/1995.8*G43 -> 3715.1538 | AW43: =AT43-AV43 -> -6150.1256 | AX43: =AW43/P43 -> -0.080079761 | AY43: =123844.283333333/1995.8*G43 -> 2978.5177 | AZ43: =AT43+AY43 -> 543.54588 | BA43: =AZ43/P43 -> 0.0070774203 | BC43: =P43/$G43 -> 1600 | BD43: =-AD43/$G43 -> -1178.6212 | BE43: =-AE43/$G43 -> -236.68984 | BF43: =-AF43/$G43 -> -18.212993 | BG43: =-AG43/$G43 -> 42.1585 | BH43: =-AH43/$G43 -> -1391.3655 | BI43: =AL43/$G43 -> 208.63452 | BJ43: =-AN43/$G43 -> -137.5 | BK43: =-AP43/$G43 -> -106.58352 | BL43: =-AQ43/$G43 -> -263.86592 | BM43: =-AR43/$G43 -> -39.372182 | BN43: =AS43/$G43 -> 43.875 | BO43: =AT43/$G43 -> -50.728579 | BP43: =-AV43/$G43 -> -77.399038 | BQ43: =AW43/$G43 -> -128.12762 | BR43: =AY43/$G43 -> 62.052452 | BS43: =AZ43/$G43 -> 11.323872
B44: FEBRERO | C44: MARZO | D44: 169-2026A | E44: 43 | F44: 46084 | G44: 116.8 | H44: POTA ALAS CONGELADAS | I44: Alas | J44: 1-UP | K44: China | L44: Qingdao | M44: TSUJINO | N44: Jose | O44: 1600 | P44: 186880 | Q44: 1484.2894 | R44: 13515 | S44: =P44-R44 -> 173365 | T44: 5 | U44: ECO SIROCCO 26009N | V44: LIMG02789600 | W44: ONE | X44: PAITA | Y44: Fresco | Z44: 10006720 | AA44: Inventario final | AB44: =B44&Z44&AA44 -> FEBRERO10006720Inventario final | AC44: =AJ44-616968.19/1968.8+215187/1968.8 -> 1745.124 | AD44: =IFERROR(INDEX('Costos Producción Febrero'!$G$34:$G$57,MATCH(Resumen!Z44,'Costos Producción Febrero'!$B$34:$B$57,0))*AC44*G44,0) -> 130796.6 | AE44: =IFERROR(INDEX('Costos Producción Febrero'!$H$34:$H$57,MATCH(Resumen!Z44,'Costos Producción Febrero'!$B$34:$B$57,0))*AC44*G44,0) -> 27511.404 | AF44: =IFERROR(INDEX('Costos Producción Febrero'!$I$34:$I$57,MATCH(Resumen!Z44,'Costos Producción Febrero'!$B$34:$B$57,0))*AC44*G44,0) -> 1904.5616 | AG44: =IFERROR(INDEX('Costos Producción Febrero'!$J$34:$J$57,MATCH(Resumen!Z44,'Costos Producción Febrero'!$B$34:$B$57,0))*AC44*G44,0) -> 43617.915 | AH44: =SUM(AD44:AG44) -> 203830.48 | AJ44: 1949.1981 | AL44: =P44-AH44 -> -16950.479 | AM44: =AL44/P44 -> -0.090702479 | AN44: =R44 -> 13515 | AO44: =118461.136538461/5988.21*G44 -> 2310.5838 | AP44: =106.583523265795*G44 -> 12448.956 | AQ44: =SUM(AN44:AP44) -> 28274.539 | AR44: =78579/1995.8*G44 -> 4598.6708 | AS44: =S44*0.03 -> 5200.95 | AT44: =AL44-AQ44-AR44+AS44 -> -44622.739 | AU44: =AT44/P44 -> -0.2387775 | AV44: =154473/1995.8*G44 -> 9040.2076 | AW44: =AT44-AV44 -> -53662.947 | AX44: =AW44/P44 -> -0.2871519 | AY44: =123844.283333333/1995.8*G44 -> 7247.7264 | AZ44: =AT44+AY44 -> -37375.013 | BA44: =AZ44/P44 -> -0.19999472 | BC44: =P44/$G44 -> 1600 | BD44: =-AD44/$G44 -> -1119.8339 | BE44: =-AE44/$G44 -> -235.54284 | BF44: =-AF44/$G44 -> -16.306178 | BG44: =-AG44/$G44 -> -373.44105 | BH44: =-AH44/$G44 -> -1745.124 | BI44: =AL44/$G44 -> -145.12397 | BJ44: =-AN44/$G44 -> -115.71062 | BK44: =-AP44/$G44 -> -106.58352 | BL44: =-AQ44/$G44 -> -242.07653 | BM44: =-AR44/$G44 -> -39.372182 | BN44: =AS44/$G44 -> 44.528682 | BO44: =AT44/$G44 -> -382.044 | BP44: =-AV44/$G44 -> -77.399038 | BQ44: =AW44/$G44 -> -459.44304 | BR44: =AY44/$G44 -> 62.052452 | BS44: =AZ44/$G44 -> -319.99155
B45: FEBRERO | C45: MARZO | D45: 169-2026B | E45: 43 | F45: 46091 | G45: 135 | H45: POTA ALAS CONGELADAS | I45: Alas | J45: 1-UP | K45: China | L45: Qingdao | M45: TSUJINO | N45: Jose | O45: 1600 | P45: 216000 | Q45: 1519.9111 | R45: 10812 | S45: =P45-R45 -> 205188 | T45: 4 | U45: ECO MARIN 26010N | V45: LIMG03633900 | W45: ONE | X45: PAITA | Y45: Fresco | Z45: 10006720 | AA45: Inventario final | AB45: =B45&Z45&AA45 -> FEBRERO10006720Inventario final | AC45: =AJ45-616968.19/1968.8+215187/1968.8 -> 1745.124 | AD45: =IFERROR(INDEX('Costos Producción Febrero'!$G$34:$G$57,MATCH(Resumen!Z45,'Costos Producción Febrero'!$B$34:$B$57,0))*AC45*G45,0) -> 151177.58 | AE45: =IFERROR(INDEX('Costos Producción Febrero'!$H$34:$H$57,MATCH(Resumen!Z45,'Costos Producción Febrero'!$B$34:$B$57,0))*AC45*G45,0) -> 31798.284 | AF45: =IFERROR(INDEX('Costos Producción Febrero'!$I$34:$I$57,MATCH(Resumen!Z45,'Costos Producción Febrero'!$B$34:$B$57,0))*AC45*G45,0) -> 2201.3341 | AG45: =IFERROR(INDEX('Costos Producción Febrero'!$J$34:$J$57,MATCH(Resumen!Z45,'Costos Producción Febrero'!$B$34:$B$57,0))*AC45*G45,0) -> 50414.542 | AH45: =SUM(AD45:AG45) -> 235591.74 | AJ45: 1949.1981 | AL45: =P45-AH45 -> -19591.735 | AM45: =AL45/P45 -> -0.090702479 | AN45: =R45 -> 10812 | AO45: =118461.136538461/5988.21*G45 -> 2670.6233 | AP45: =106.583523265795*G45 -> 14388.776 | AQ45: =SUM(AN45:AP45) -> 27871.399 | AR45: =78579/1995.8*G45 -> 5315.2445 | AS45: =S45*0.03 -> 6155.64 | AT45: =AL45-AQ45-AR45+AS45 -> -46622.739 | AU45: =AT45/P45 -> -0.21584601 | AV45: =154473/1995.8*G45 -> 10448.87 | AW45: =AT45-AV45 -> -57071.609 | AX45: =AW45/P45 -> -0.26422041 | AY45: =123844.283333333/1995.8*G45 -> 8377.081 | AZ45: =AT45+AY45 -> -38245.658 | BA45: =AZ45/P45 -> -0.17706323 | BC45: =P45/$G45 -> 1600 | BD45: =-AD45/$G45 -> -1119.8339 | BE45: =-AE45/$G45 -> -235.54284 | BF45: =-AF45/$G45 -> -16.306178 | BG45: =-AG45/$G45 -> -373.44105 | BH45: =-AH45/$G45 -> -1745.124 | BI45: =AL45/$G45 -> -145.12397 | BJ45: =-AN45/$G45 -> -80.088889 | BK45: =-AP45/$G45 -> -106.58352 | BL45: =-AQ45/$G45 -> -206.45481 | BM45: =-AR45/$G45 -> -39.372182 | BN45: =AS45/$G45 -> 45.597333 | BO45: =AT45/$G45 -> -345.35362 | BP45: =-AV45/$G45 -> -77.399038 | BQ45: =AW45/$G45 -> -422.75266 | BR45: =AY45/$G45 -> 62.052452 | BS45: =AZ45/$G45 -> -283.30117
B46: FEBRERO | C46: MARZO | D46: 170-2026B | E46: 43 | F46: 46092 | G46: 78 | H46: POTA REJOS CONGELADOS | I46: Rejos | J46: 1-2 | K46: España | L46: Vigo | M46: KULALIA | N46: Ramon | O46: 2400 | P46: =187200-15600 -> 171600 | Q46: 2243.0865 | R46: 12239.25 | S46: =P46-R46 -> 159360.75 | T46: 3 | U46: CMA CGM BOLDNESS / 0DVODN1MA | V46: LMM0575562 | W46: CMA CGM | Y46: Fresco | Z46: 10007162 | AA46: Inventario final | AB46: =B46&Z46&AA46 -> FEBRERO10007162Inventario final | AC46: =AJ46-616968.19/1968.8+215187/1968.8 -> 1814.1051 | AD46: =IFERROR(INDEX('Costos Producción Febrero'!$G$34:$G$57,MATCH(Resumen!Z46,'Costos Producción Febrero'!$B$34:$B$57,0))*AC46*G46,0) -> 86760.94 | AE46: =IFERROR(INDEX('Costos Producción Febrero'!$H$34:$H$57,MATCH(Resumen!Z46,'Costos Producción Febrero'!$B$34:$B$57,0))*AC46*G46,0) -> 24633.161 | AF46: =IFERROR(INDEX('Costos Producción Febrero'!$I$34:$I$57,MATCH(Resumen!Z46,'Costos Producción Febrero'!$B$34:$B$57,0))*AC46*G46,0) -> 1311.7904 | AG46: =IFERROR(INDEX('Costos Producción Febrero'!$J$34:$J$57,MATCH(Resumen!Z46,'Costos Producción Febrero'!$B$34:$B$57,0))*AC46*G46,0) -> 28794.309 | AH46: =SUM(AD46:AG46) -> 141500.2 | AJ46: 2018.1793 | AL46: =P46-AH46 -> 30099.8 | AM46: =AL46/P46 -> 0.17540676 | AN46: =R46 -> 12239.25 | AO46: =118461.136538461/5988.21*G46 -> 1543.0268 | AP46: =106.583523265795*G46 -> 8313.5148 | AQ46: =SUM(AN46:AP46) -> 22095.792 | AR46: =78579/1995.8*G46 -> 3071.0302 | AS46: =S46*0.03 -> 4780.8225 | AT46: =AL46-AQ46-AR46+AS46 -> 9713.8002 | AU46: =AT46/P46 -> 0.056607227 | AV46: =154473/1995.8*G46 -> 6037.125 | AW46: =AT46-AV46 -> 3676.6752 | AX46: =AW46/P46 -> 0.021425846 | AY46: =123844.283333333/1995.8*G46 -> 4840.0912 | AZ46: =AT46+AY46 -> 14553.891 | BA46: =AZ46/P46 -> 0.084812887 | BC46: =P46/$G46 -> 2200 | BD46: =-AD46/$G46 -> -1112.3197 | BE46: =-AE46/$G46 -> -315.80976 | BF46: =-AF46/$G46 -> -16.817825 | BG46: =-AG46/$G46 -> -369.15781 | BH46: =-AH46/$G46 -> -1814.1051 | BI46: =AL46/$G46 -> 385.89487 | BJ46: =-AN46/$G46 -> -156.91346 | BK46: =-AP46/$G46 -> -106.58352 | BL46: =-AQ46/$G46 -> -283.27938 | BM46: =-AR46/$G46 -> -39.372182 | BN46: =AS46/$G46 -> 61.292596 | BO46: =AT46/$G46 -> 124.5359 | BP46: =-AV46/$G46 -> -77.399038 | BQ46: =AW46/$G46 -> 47.136862 | BR46: =AY46/$G46 -> 62.052452 | BS46: =AZ46/$G46 -> 186.58835
B47: FEBRERO | C47: MARZO | D47: 171-2026 | E47: 44 | F47: 46085 | G47: 135 | H47: POTA FILETE CONGELADO | I47: Filete | J47: 2-4 AA | K47: China | L47: Shidao | M47: Pesciro Asia International LTD. | O47: 1450 | P47: 195750 | Q47: 1338.7778 | R47: 15015 | S47: =P47-R47 -> 180735 | T47: 5 | U47: ECO SIROCCO 26009N | V47: LIMG03093900 | W47: ONE | X47: PAITA | Y47: Fresco | Z47: 10005721 | AA47: Inventario final | AB47: =B47&Z47&AA47 -> FEBRERO10005721Inventario final | AC47: =AJ47-616968.19/1968.8+215187/1968.8 -> 2193.6703 | AD47: =IFERROR(INDEX('Costos Producción Febrero'!$G$34:$G$57,MATCH(Resumen!Z47,'Costos Producción Febrero'!$B$34:$B$57,0))*AC47*G47,0) -> 179852.39 | AE47: =IFERROR(INDEX('Costos Producción Febrero'!$H$34:$H$57,MATCH(Resumen!Z47,'Costos Producción Febrero'!$B$34:$B$57,0))*AC47*G47,0) -> 52700.484 | AF47: =IFERROR(INDEX('Costos Producción Febrero'!$I$34:$I$57,MATCH(Resumen!Z47,'Costos Producción Febrero'!$B$34:$B$57,0))*AC47*G47,0) -> 3228.5503 | AG47: =IFERROR(INDEX('Costos Producción Febrero'!$J$34:$J$57,MATCH(Resumen!Z47,'Costos Producción Febrero'!$B$34:$B$57,0))*AC47*G47,0) -> 60364.069 | AH47: =SUM(AD47:AG47) -> 296145.49 | AJ47: 2397.7445 | AL47: =P47-AH47 -> -100395.49 | AM47: =AL47/P47 -> -0.51287608 | AN47: =R47 -> 15015 | AO47: =118461.136538461/5988.21*G47 -> 2670.6233 | AP47: =106.583523265795*G47 -> 14388.776 | AQ47: =SUM(AN47:AP47) -> 32074.399 | AR47: =78579/1995.8*G47 -> 5315.2445 | AS47: =S47*0.03 -> 5422.05 | AT47: =AL47-AQ47-AR47+AS47 -> -132363.09 | AU47: =AT47/P47 -> -0.67618435 | AV47: =154473/1995.8*G47 -> 10448.87 | AW47: =AT47-AV47 -> -142811.96 | AX47: =AW47/P47 -> -0.729563 | AY47: =123844.283333333/1995.8*G47 -> 8377.081 | AZ47: =AT47+AY47 -> -123986.01 | BA47: =AZ47/P47 -> -0.63338956 | BC47: =P47/$G47 -> 1450 | BD47: =-AD47/$G47 -> -1332.2399 | BE47: =-AE47/$G47 -> -390.37396 | BF47: =-AF47/$G47 -> -23.915187 | BG47: =-AG47/$G47 -> -447.14125 | BH47: =-AH47/$G47 -> -2193.6703 | BI47: =AL47/$G47 -> -743.67032 | BJ47: =-AN47/$G47 -> -111.22222 | BK47: =-AP47/$G47 -> -106.58352 | BL47: =-AQ47/$G47 -> -237.58814 | BM47: =-AR47/$G47 -> -39.372182 | BN47: =AS47/$G47 -> 40.163333 | BO47: =AT47/$G47 -> -980.46731 | BP47: =-AV47/$G47 -> -77.399038 | BQ47: =AW47/$G47 -> -1057.8663 | BR47: =AY47/$G47 -> 62.052452 | BS47: =AZ47/$G47 -> -918.41486
B48: FEBRERO | C48: MARZO | D48: 172-2026A | E48: 47 | F48: 46092 | G48: 150 | H48: POTA REJOS CONGELADOS | I48: Rejos | J48: 1-2 KG | K48: España | L48: Vigo | M48: KULALIA | N48: Ramon | O48: 2300 | P48: 345000 | Q48: 2139.1 | R48: 24135 | S48: =P48-R48 -> 320865 | T48: 6 | U48: CMA CGM BOLDNESS / 0DVODN1MA | V48: LMM0575536 | W48: CMA CGM | Y48: Fresco | Z48: 10007162 | AA48: Inventario final | AB48: =B48&Z48&AA48 -> FEBRERO10007162Inventario final | AC48: =AJ48-616968.19/1968.8+215187/1968.8 -> 1814.1051 | AD48: =IFERROR(INDEX('Costos Producción Febrero'!$G$34:$G$57,MATCH(Resumen!Z48,'Costos Producción Febrero'!$B$34:$B$57,0))*AC48*G48,0) -> 166847.96 | AE48: =IFERROR(INDEX('Costos Producción Febrero'!$H$34:$H$57,MATCH(Resumen!Z48,'Costos Producción Febrero'!$B$34:$B$57,0))*AC48*G48,0) -> 47371.464 | AF48: =IFERROR(INDEX('Costos Producción Febrero'!$I$34:$I$57,MATCH(Resumen!Z48,'Costos Producción Febrero'!$B$34:$B$57,0))*AC48*G48,0) -> 2522.6738 | AG48: =IFERROR(INDEX('Costos Producción Febrero'!$J$34:$J$57,MATCH(Resumen!Z48,'Costos Producción Febrero'!$B$34:$B$57,0))*AC48*G48,0) -> 55373.671 | AH48: =SUM(AD48:AG48) -> 272115.77 | AJ48: 2018.1793 | AL48: =P48-AH48 -> 72884.23 | AM48: =AL48/P48 -> 0.21125864 | AN48: =R48 -> 24135 | AO48: =118461.136538461/5988.21*G48 -> 2967.3593 | AP48: =106.583523265795*G48 -> 15987.528 | AQ48: =SUM(AN48:AP48) -> 43089.888 | AR48: =78579/1995.8*G48 -> 5905.8272 | AS48: =S48*0.03 -> 9625.95 | AT48: =AL48-AQ48-AR48+AS48 -> 33514.465 | AU48: =AT48/P48 -> 0.097143376 | AV48: =154473/1995.8*G48 -> 11609.856 | AW48: =AT48-AV48 -> 21904.609 | AX48: =AW48/P48 -> 0.063491621 | AY48: =123844.283333333/1995.8*G48 -> 9307.8678 | AZ48: =AT48+AY48 -> 42822.333 | BA48: =AZ48/P48 -> 0.1241227 | BC48: =P48/$G48 -> 2300 | BD48: =-AD48/$G48 -> -1112.3197 | BE48: =-AE48/$G48 -> -315.80976 | BF48: =-AF48/$G48 -> -16.817825 | BG48: =-AG48/$G48 -> -369.15781 | BH48: =-AH48/$G48 -> -1814.1051 | BI48: =AL48/$G48 -> 485.89487 | BJ48: =-AN48/$G48 -> -160.9 | BK48: =-AP48/$G48 -> -106.58352 | BL48: =-AQ48/$G48 -> -287.26592 | BM48: =-AR48/$G48 -> -39.372182 | BN48: =AS48/$G48 -> 64.173 | BO48: =AT48/$G48 -> 223.42977 | BP48: =-AV48/$G48 -> -77.399038 | BQ48: =AW48/$G48 -> 146.03073 | BR48: =AY48/$G48 -> 62.052452 | BS48: =AZ48/$G48 -> 285.48222
B49: FEBRERO | C49: MARZO | D49: 172-2026A | E49: 47 | F49: 46092 | G49: 25 | H49: POTA REPRODUCTORES | I49: Rejos | K49: España | L49: Vigo | M49: KULALIA | N49: Ramon | O49: 2500 | P49: 62500 | Q49: 2336.72 | R49: 4082 | S49: =P49-R49 -> 58418 | T49: 1 | U49: CMA CGM BOLDNESS / 0DVODN1MA | V49: LMM0575536 | W49: CMA CGM | Y49: Fresco | Z49: 10007567 | AA49: Inventario final | AB49: =B49&Z49&AA49 -> FEBRERO10007567Inventario final | AC49: =AJ49-616968.19/1968.8+215187/1968.8 -> 1815.4238 | AD49: =IFERROR(INDEX('Costos Producción Febrero'!$G$34:$G$57,MATCH(Resumen!Z49,'Costos Producción Febrero'!$B$34:$B$57,0))*AC49*G49,0) -> 28029.353 | AE49: =IFERROR(INDEX('Costos Producción Febrero'!$H$34:$H$57,MATCH(Resumen!Z49,'Costos Producción Febrero'!$B$34:$B$57,0))*AC49*G49,0) -> 7554.03 | AF49: =IFERROR(INDEX('Costos Producción Febrero'!$I$34:$I$57,MATCH(Resumen!Z49,'Costos Producción Febrero'!$B$34:$B$57,0))*AC49*G49,0) -> 489.86383 | AG49: =IFERROR(INDEX('Costos Producción Febrero'!$J$34:$J$57,MATCH(Resumen!Z49,'Costos Producción Febrero'!$B$34:$B$57,0))*AC49*G49,0) -> 9312.3479 | AH49: =SUM(AD49:AG49) -> 45385.595 | AJ49: 2019.498 | AL49: =P49-AH49 -> 17114.405 | AM49: =AL49/P49 -> 0.27383048 | AN49: =R49 -> 4082 | AO49: =118461.136538461/5988.21*G49 -> 494.55988 | AP49: =106.583523265795*G49 -> 2664.5881 | AQ49: =SUM(AN49:AP49) -> 7241.148 | AR49: =78579/1995.8*G49 -> 984.30454 | AS49: =S49*0.03 -> 1752.54 | AT49: =AL49-AQ49-AR49+AS49 -> 10641.492 | AU49: =AT49/P49 -> 0.17026388 | AV49: =154473/1995.8*G49 -> 1934.9759 | AW49: =AT49-AV49 -> 8706.5163 | AX49: =AW49/P49 -> 0.13930426 | AY49: =123844.283333333/1995.8*G49 -> 1551.3113 | AZ49: =AT49+AY49 -> 12192.804 | BA49: =AZ49/P49 -> 0.19508486 | BC49: =P49/$G49 -> 2500 | BD49: =-AD49/$G49 -> -1121.1741 | BE49: =-AE49/$G49 -> -302.1612 | BF49: =-AF49/$G49 -> -19.594553 | BG49: =-AG49/$G49 -> -372.49392 | BH49: =-AH49/$G49 -> -1815.4238 | BI49: =AL49/$G49 -> 684.57619 | BJ49: =-AN49/$G49 -> -163.28 | BK49: =-AP49/$G49 -> -106.58352 | BL49: =-AQ49/$G49 -> -289.64592 | BM49: =-AR49/$G49 -> -39.372182 | BN49: =AS49/$G49 -> 70.1016 | BO49: =AT49/$G49 -> 425.65969 | BP49: =-AV49/$G49 -> -77.399038 | BQ49: =AW49/$G49 -> 348.26065 | BR49: =AY49/$G49 -> 62.052452 | BS49: =AZ49/$G49 -> 487.71214
B50: FEBRERO | C50: MARZO | D50: 172-2026B | E50: 47 | F50: 46108 | G50: 54 | H50: POTA ALAS COCIDAS | I50: Alas | J50: 0.3 - UP | K50: China | L50: Qingdao | M50: KULALIA | N50: Ramon | O50: 3350 | P50: =180900-3678.3 -> 177221.7 | Q50: 3242.5926 | R50: 5800 | S50: =P50-R50 -> 171421.7 | T50: 2 | U50: ECO SIROCCO 26013S | V50: 6446512380 | W50: COSCO | X50: PAITA | Y50: Cocido | Z50: 10009331 | AA50: Inventario final | AB50: =B50&Z50&AA50 -> FEBRERO10009331Inventario final | AC50: =AJ50-616968.19/1968.8+215187/1968.8 -> 2241.3701 | AD50: =IFERROR(INDEX('Costos Producción Febrero'!$G$34:$G$57,MATCH(Resumen!Z50,'Costos Producción Febrero'!$B$34:$B$57,0))*AC50*G50,0) -> 69065.234 | AE50: =IFERROR(INDEX('Costos Producción Febrero'!$H$34:$H$57,MATCH(Resumen!Z50,'Costos Producción Febrero'!$B$34:$B$57,0))*AC50*G50,0) -> 27400.521 | AF50: =IFERROR(INDEX('Costos Producción Febrero'!$I$34:$I$57,MATCH(Resumen!Z50,'Costos Producción Febrero'!$B$34:$B$57,0))*AC50*G50,0) -> 1254.9308 | AG50: =IFERROR(INDEX('Costos Producción Febrero'!$J$34:$J$57,MATCH(Resumen!Z50,'Costos Producción Febrero'!$B$34:$B$57,0))*AC50*G50,0) -> 23313.3 | AH50: =SUM(AD50:AG50) -> 121033.99 | AJ50: 2445.4443 | AL50: =P50-AH50 -> 56187.714 | AM50: =AL50/P50 -> 0.3170476 | AN50: =R50 -> 5800 | AO50: =118461.136538461/5988.21*G50 -> 1068.2493 | AP50: =106.583523265795*G50 -> 5755.5103 | AQ50: =SUM(AN50:AP50) -> 12623.76 | AR50: =78579/1995.8*G50 -> 2126.0978 | AS50: =S50*0.03 -> 5142.651 | AT50: =AL50-AQ50-AR50+AS50 -> 46580.508 | AU50: =AT50/P50 -> 0.2628375 | AV50: =154473/1995.8*G50 -> 4179.5481 | AW50: =AT50-AV50 -> 42400.96 | AX50: =AW50/P50 -> 0.23925377 | AY50: =123844.283333333/1995.8*G50 -> 3350.8324 | AZ50: =AT50+AY50 -> 49931.34 | BA50: =AZ50/P50 -> 0.28174507 | BC50: =P50/$G50 -> 3281.8833 | BD50: =-AD50/$G50 -> -1278.9858 | BE50: =-AE50/$G50 -> -507.41705 | BF50: =-AF50/$G50 -> -23.23946 | BG50: =-AG50/$G50 -> -431.72777 | BH50: =-AH50/$G50 -> -2241.3701 | BI50: =AL50/$G50 -> 1040.5132 | BJ50: =-AN50/$G50 -> -107.40741 | BK50: =-AP50/$G50 -> -106.58352 | BL50: =-AQ50/$G50 -> -233.77333 | BM50: =-AR50/$G50 -> -39.372182 | BN50: =AS50/$G50 -> 95.234278 | BO50: =AT50/$G50 -> 862.602 | BP50: =-AV50/$G50 -> -77.399038 | BQ50: =AW50/$G50 -> 785.20296 | BR50: =AY50/$G50 -> 62.052452 | BS50: =AZ50/$G50 -> 924.65445
B51: FEBRERO | C51: MARZO | D51: 174-2026 | E51: 49 | F51: 46091 | G51: 108 | H51: POTA FILETE CONGELADO | I51: Filete | J51: 2-4 AA | K51: China | L51: shidao | M51: Pesciro Asia International LTD. | O51: 1450 | P51: 156600 | Q51: 1338.7778 | R51: 12012 | S51: =P51-R51 -> 144588 | T51: 4 | U51: ECO MARIN 26010N | V51: LIMG03595900 | Y51: Fresco | Z51: 10005721 | AA51: Inventario final | AB51: =B51&Z51&AA51 -> FEBRERO10005721Inventario final | AC51: =AJ51-616968.19/1968.8+215187/1968.8 -> 1891.1947 | AD51: =IFERROR(INDEX('Costos Producción Febrero'!$G$34:$G$57,MATCH(Resumen!Z51,'Costos Producción Febrero'!$B$34:$B$57,0))*AC51*G51,0) -> 124042.67 | AE51: =IFERROR(INDEX('Costos Producción Febrero'!$H$34:$H$57,MATCH(Resumen!Z51,'Costos Producción Febrero'!$B$34:$B$57,0))*AC51*G51,0) -> 36347.076 | AF51: =IFERROR(INDEX('Costos Producción Febrero'!$I$34:$I$57,MATCH(Resumen!Z51,'Costos Producción Febrero'!$B$34:$B$57,0))*AC51*G51,0) -> 2226.7037 | AG51: =IFERROR(INDEX('Costos Producción Febrero'!$J$34:$J$57,MATCH(Resumen!Z51,'Costos Producción Febrero'!$B$34:$B$57,0))*AC51*G51,0) -> 41632.585 | AH51: =SUM(AD51:AG51) -> 204249.03 | AJ51: 2095.2689 | AL51: =P51-AH51 -> -47649.03 | AM51: =AL51/P51 -> -0.30427222 | AN51: =R51 -> 12012 | AO51: =118461.136538461/5988.21*G51 -> 2136.4987 | AP51: =106.583523265795*G51 -> 11511.021 | AQ51: =SUM(AN51:AP51) -> 25659.519 | AR51: =78579/1995.8*G51 -> 4252.1956 | AS51: =S51*0.03 -> 4337.64 | AT51: =AL51-AQ51-AR51+AS51 -> -73223.105 | AU51: =AT51/P51 -> -0.46758049 | AV51: =154473/1995.8*G51 -> 8359.0961 | AW51: =AT51-AV51 -> -81582.201 | AX51: =AW51/P51 -> -0.52095914 | AY51: =123844.283333333/1995.8*G51 -> 6701.6648 | AZ51: =AT51+AY51 -> -66521.44 | BA51: =AZ51/P51 -> -0.4247857 | BC51: =P51/$G51 -> 1450 | BD51: =-AD51/$G51 -> -1148.5432 | BE51: =-AE51/$G51 -> -336.547 | BF51: =-AF51/$G51 -> -20.617627 | BG51: =-AG51/$G51 -> -385.4869 | BH51: =-AH51/$G51 -> -1891.1947 | BI51: =AL51/$G51 -> -441.19473 | BJ51: =-AN51/$G51 -> -111.22222 | BK51: =-AP51/$G51 -> -106.58352 | BL51: =-AQ51/$G51 -> -237.58814 | BM51: =-AR51/$G51 -> -39.372182 | BN51: =AS51/$G51 -> 40.163333 | BO51: =AT51/$G51 -> -677.99171 | BP51: =-AV51/$G51 -> -77.399038 | BQ51: =AW51/$G51 -> -755.39075 | BR51: =AY51/$G51 -> 62.052452 | BS51: =AZ51/$G51 -> -615.93926
B52: FEBRERO | C52: MARZO | D52: 175-2026 | E52: 49 | F52: 46099 | G52: 26 | H52: POTA FILETE CONGELADO | I52: Filete | J52: 2-4 AA | K52: Lituania | L52: Lituania | M52: Pesciro SL | O52: 1500 | P52: 39000 | Q52: 1230.9615 | R52: 6995 | S52: =P52-R52 -> 32005 | T52: 1 | U52: CMA CGM VOLTAIRE / 0DVOFN1MA | V52: LMM0575667 | W52: 1 | X52: CMA CGM | Y52: Fresco | Z52: 10005721 | AA52: Inventario final | AB52: =B52&Z52&AA52 -> FEBRERO10005721Inventario final | AC52: =AJ52-616968.19/1968.8+215187/1968.8 -> 1891.1947 | AD52: =IFERROR(INDEX('Costos Producción Febrero'!$G$34:$G$57,MATCH(Resumen!Z52,'Costos Producción Febrero'!$B$34:$B$57,0))*AC52*G52,0) -> 29862.123 | AE52: =IFERROR(INDEX('Costos Producción Febrero'!$H$34:$H$57,MATCH(Resumen!Z52,'Costos Producción Febrero'!$B$34:$B$57,0))*AC52*G52,0) -> 8750.222 | AF52: =IFERROR(INDEX('Costos Producción Febrero'!$I$34:$I$57,MATCH(Resumen!Z52,'Costos Producción Febrero'!$B$34:$B$57,0))*AC52*G52,0) -> 536.0583 | AG52: =IFERROR(INDEX('Costos Producción Febrero'!$J$34:$J$57,MATCH(Resumen!Z52,'Costos Producción Febrero'!$B$34:$B$57,0))*AC52*G52,0) -> 10022.659 | AH52: =SUM(AD52:AG52) -> 49171.063 | AJ52: 2095.2689 | AL52: =P52-AH52 -> -10171.063 | AM52: =AL52/P52 -> -0.26079648 | AN52: =R52 -> 6995 | AO52: =118461.136538461/5988.21*G52 -> 514.34227 | AP52: =106.583523265795*G52 -> 2771.1716 | AQ52: =SUM(AN52:AP52) -> 10280.514 | AR52: =78579/1995.8*G52 -> 1023.6767 | AS52: =S52*0.03 -> 960.15 | AT52: =AL52-AQ52-AR52+AS52 -> -20515.103 | AU52: =AT52/P52 -> -0.52602829 | AV52: =154473/1995.8*G52 -> 2012.375 | AW52: =AT52-AV52 -> -22527.478 | AX52: =AW52/P52 -> -0.57762765 | AY52: =123844.283333333/1995.8*G52 -> 1613.3637 | AZ52: =AT52+AY52 -> -18901.74 | BA52: =AZ52/P52 -> -0.48465999 | BC52: =P52/$G52 -> 1500 | BD52: =-AD52/$G52 -> -1148.5432 | BE52: =-AE52/$G52 -> -336.547 | BF52: =-AF52/$G52 -> -20.617627 | BG52: =-AG52/$G52 -> -385.4869 | BH52: =-AH52/$G52 -> -1891.1947 | BI52: =AL52/$G52 -> -391.19473 | BJ52: =-AN52/$G52 -> -269.03846 | BK52: =-AP52/$G52 -> -106.58352 | BL52: =-AQ52/$G52 -> -395.40438 | BM52: =-AR52/$G52 -> -39.372182 | BN52: =AS52/$G52 -> 36.928846 | BO52: =AT52/$G52 -> -789.04244 | BP52: =-AV52/$G52 -> -77.399038 | BQ52: =AW52/$G52 -> -866.44148 | BR52: =AY52/$G52 -> 62.052452 | BS52: =AZ52/$G52 -> -726.98999
B53: FEBRERO | C53: MARZO | D53: 176-2026A | E53: 49 | F53: 46104 | G53: 54 | H53: POTA ALAS CONGELADAS | I53: Alas | J53: 1-up | K53: China | L53: Qingdao | M53: TSUJINO | N53: Jose | O53: 1600 | P53: 86400 | Q53: 1492.5926 | R53: 5800 | S53: =P53-R53 -> 80600 | T53: 2 | U53: ECO SIROCCO 26011S | V53: 6446527810 | W53: COSCO | X53: PAITA | Y53: Fresco | Z53: 10006720 | AA53: Inventario final | AB53: =B53&Z53&AA53 -> FEBRERO10006720Inventario final | AC53: =AJ53-616968.19/1968.8+215187/1968.8 -> 1745.124 | AD53: =IFERROR(INDEX('Costos Producción Febrero'!$G$34:$G$57,MATCH(Resumen!Z53,'Costos Producción Febrero'!$B$34:$B$57,0))*AC53*G53,0) -> 60471.03 | AE53: =IFERROR(INDEX('Costos Producción Febrero'!$H$34:$H$57,MATCH(Resumen!Z53,'Costos Producción Febrero'!$B$34:$B$57,0))*AC53*G53,0) -> 12719.314 | AF53: =IFERROR(INDEX('Costos Producción Febrero'!$I$34:$I$57,MATCH(Resumen!Z53,'Costos Producción Febrero'!$B$34:$B$57,0))*AC53*G53,0) -> 880.53363 | AG53: =IFERROR(INDEX('Costos Producción Febrero'!$J$34:$J$57,MATCH(Resumen!Z53,'Costos Producción Febrero'!$B$34:$B$57,0))*AC53*G53,0) -> 20165.817 | AH53: =SUM(AD53:AG53) -> 94236.694 | AJ53: 1949.1981 | AL53: =P53-AH53 -> -7836.6942 | AM53: =AL53/P53 -> -0.090702479 | AN53: =R53 -> 5800 | AO53: =118461.136538461/5988.21*G53 -> 1068.2493 | AP53: =106.583523265795*G53 -> 5755.5103 | AQ53: =SUM(AN53:AP53) -> 12623.76 | AR53: =78579/1995.8*G53 -> 2126.0978 | AS53: =S53*0.03 -> 2418 | AT53: =AL53-AQ53-AR53+AS53 -> -20168.552 | AU53: =AT53/P53 -> -0.23343231 | AV53: =154473/1995.8*G53 -> 4179.5481 | AW53: =AT53-AV53 -> -24348.1 | AX53: =AW53/P53 -> -0.28180671 | AY53: =123844.283333333/1995.8*G53 -> 3350.8324 | AZ53: =AT53+AY53 -> -16817.719 | BA53: =AZ53/P53 -> -0.19464953 | BC53: =P53/$G53 -> 1600 | BD53: =-AD53/$G53 -> -1119.8339 | BE53: =-AE53/$G53 -> -235.54284 | BF53: =-AF53/$G53 -> -16.306178 | BG53: =-AG53/$G53 -> -373.44105 | BH53: =-AH53/$G53 -> -1745.124 | BI53: =AL53/$G53 -> -145.12397 | BJ53: =-AN53/$G53 -> -107.40741 | BK53: =-AP53/$G53 -> -106.58352 | BL53: =-AQ53/$G53 -> -233.77333 | BM53: =-AR53/$G53 -> -39.372182 | BN53: =AS53/$G53 -> 44.777778 | BO53: =AT53/$G53 -> -373.4917 | BP53: =-AV53/$G53 -> -77.399038 | BQ53: =AW53/$G53 -> -450.89073 | BR53: =AY53/$G53 -> 62.052452 | BS53: =AZ53/$G53 -> -311.43924
B54: FEBRERO | C54: MARZO | D54: 176-2026B | E54: 49 | F54: 46108 | G54: 81 | H54: POTA ALAS CONGELADAS | I54: Alas | J54: 1-up | K54: China | L54: Qingdao | M54: TSUJINO | N54: Jose | O54: 1600 | P54: =129600-4000 -> 125600 | Q54: 1499.5185 | R54: 8139 | S54: =P54-R54 -> 117461 | T54: 3 | U54: ECO SIROCCO 26013S | V54: LIMG04326900 | W54: ONE LINE | X54: PAITA | Y54: Fresco | Z54: 10006720 | AA54: Inventario final | AB54: =B54&Z54&AA54 -> FEBRERO10006720Inventario final | AC54: =AJ54-616968.19/1968.8+215187/1968.8 -> 1745.124 | AD54: =IFERROR(INDEX('Costos Producción Febrero'!$G$34:$G$57,MATCH(Resumen!Z54,'Costos Producción Febrero'!$B$34:$B$57,0))*AC54*G54,0) -> 90706.545 | AE54: =IFERROR(INDEX('Costos Producción Febrero'!$H$34:$H$57,MATCH(Resumen!Z54,'Costos Producción Febrero'!$B$34:$B$57,0))*AC54*G54,0) -> 19078.97 | AF54: =IFERROR(INDEX('Costos Producción Febrero'!$I$34:$I$57,MATCH(Resumen!Z54,'Costos Producción Febrero'!$B$34:$B$57,0))*AC54*G54,0) -> 1320.8004 | AG54: =IFERROR(INDEX('Costos Producción Febrero'!$J$34:$J$57,MATCH(Resumen!Z54,'Costos Producción Febrero'!$B$34:$B$57,0))*AC54*G54,0) -> 30248.725 | AH54: =SUM(AD54:AG54) -> 141355.04 | AJ54: 1949.1981 | AL54: =P54-AH54 -> -15755.041 | AM54: =AL54/P54 -> -0.12543823 | AN54: =R54 -> 8139 | AO54: =118461.136538461/5988.21*G54 -> 1602.374 | AP54: =106.583523265795*G54 -> 8633.2654 | AQ54: =SUM(AN54:AP54) -> 18374.639 | AR54: =78579/1995.8*G54 -> 3189.1467 | AS54: =S54*0.03 -> 3523.83 | AT54: =AL54-AQ54-AR54+AS54 -> -33794.997 | AU54: =AT54/P54 -> -0.26906845 | AV54: =154473/1995.8*G54 -> 6269.3221 | AW54: =AT54-AV54 -> -40064.319 | AX54: =AW54/P54 -> -0.31898343 | AY54: =123844.283333333/1995.8*G54 -> 5026.2486 | AZ54: =AT54+AY54 -> -28768.749 | BA54: =AZ54/P54 -> -0.22905055 | BC54: =P54/$G54 -> 1550.6173 | BD54: =-AD54/$G54 -> -1119.8339 | BE54: =-AE54/$G54 -> -235.54284 | BF54: =-AF54/$G54 -> -16.306178 | BG54: =-AG54/$G54 -> -373.44105 | BH54: =-AH54/$G54 -> -1745.124 | BI54: =AL54/$G54 -> -194.50668 | BJ54: =-AN54/$G54 -> -100.48148 | BK54: =-AP54/$G54 -> -106.58352 | BL54: =-AQ54/$G54 -> -226.8474 | BM54: =-AR54/$G54 -> -39.372182 | BN54: =AS54/$G54 -> 43.504074 | BO54: =AT54/$G54 -> -417.22219 | BP54: =-AV54/$G54 -> -77.399038 | BQ54: =AW54/$G54 -> -494.62123 | BR54: =AY54/$G54 -> 62.052452 | BS54: =AZ54/$G54 -> -355.16974
B55: FEBRERO | C55: MARZO | D55: 177-2026A | E55: 50 | F55: 46108 | G55: 48 | H55: POTA ALAS CONGELADAS | I55: Alas | J55: 1-up | K55: Corea | L55: Busan | M55: TSUJINO | N55: Jose | O55: 1600 | P55: 76800 | Q55: 1486.9583 | R55: 5426 | S55: =P55-R55 -> 71374 | T55: 2 | U55: ECO SIROCCO 26013S | V55: LIMG04588500 | W55: ONE LINE | X55: PAITA | Y55: Fresco | Z55: 10006720 | AA55: Inventario final | AB55: =B55&Z55&AA55 -> FEBRERO10006720Inventario final | AC55: =AJ55-616968.19/1968.8+215187/1968.8 -> 1745.124 | AD55: =IFERROR(INDEX('Costos Producción Febrero'!$G$34:$G$57,MATCH(Resumen!Z55,'Costos Producción Febrero'!$B$34:$B$57,0))*AC55*G55,0) -> 53752.027 | AE55: =IFERROR(INDEX('Costos Producción Febrero'!$H$34:$H$57,MATCH(Resumen!Z55,'Costos Producción Febrero'!$B$34:$B$57,0))*AC55*G55,0) -> 11306.056 | AF55: =IFERROR(INDEX('Costos Producción Febrero'!$I$34:$I$57,MATCH(Resumen!Z55,'Costos Producción Febrero'!$B$34:$B$57,0))*AC55*G55,0) -> 782.69656 | AG55: =IFERROR(INDEX('Costos Producción Febrero'!$J$34:$J$57,MATCH(Resumen!Z55,'Costos Producción Febrero'!$B$34:$B$57,0))*AC55*G55,0) -> 17925.17 | AH55: =SUM(AD55:AG55) -> 83765.95 | AJ55: 1949.1981 | AL55: =P55-AH55 -> -6965.9504 | AM55: =AL55/P55 -> -0.090702479 | AN55: =R55 -> 5426 | AO55: =118461.136538461/5988.21*G55 -> 949.55497 | AP55: =106.583523265795*G55 -> 5116.0091 | AQ55: =SUM(AN55:AP55) -> 11491.564 | AR55: =78579/1995.8*G55 -> 1889.8647 | AS55: =S55*0.03 -> 2141.22 | AT55: =AL55-AQ55-AR55+AS55 -> -18206.159 | AU55: =AT55/P55 -> -0.23705936 | AV55: =154473/1995.8*G55 -> 3715.1538 | AW55: =AT55-AV55 -> -21921.313 | AX55: =AW55/P55 -> -0.28543376 | AY55: =123844.283333333/1995.8*G55 -> 2978.5177 | AZ55: =AT55+AY55 -> -15227.641 | BA55: =AZ55/P55 -> -0.19827658 | BC55: =P55/$G55 -> 1600 | BD55: =-AD55/$G55 -> -1119.8339 | BE55: =-AE55/$G55 -> -235.54284 | BF55: =-AF55/$G55 -> -16.306178 | BG55: =-AG55/$G55 -> -373.44105 | BH55: =-AH55/$G55 -> -1745.124 | BI55: =AL55/$G55 -> -145.12397 | BJ55: =-AN55/$G55 -> -113.04167 | BK55: =-AP55/$G55 -> -106.58352 | BL55: =-AQ55/$G55 -> -239.40759 | BM55: =-AR55/$G55 -> -39.372182 | BN55: =AS55/$G55 -> 44.60875 | BO55: =AT55/$G55 -> -379.29498 | BP55: =-AV55/$G55 -> -77.399038 | BQ55: =AW55/$G55 -> -456.69402 | BR55: =AY55/$G55 -> 62.052452 | BS55: =AZ55/$G55 -> -317.24253
B56: FEBRERO | C56: MARZO | D56: 179-2026A | E56: 54 | F56: 46101 | G56: 24 | H56: POTA NUCAS | I56: Nucas | J56: 500-up | K56: Tailandia | L56: Laem chabang | M56: DAIRECK S.A. | N56: ACER FOOD | O56: 1100 | P56: 26400 | Q56: 966.54167 | R56: 3203 | S56: =P56-R56 -> 23197 | T56: 1 | U56: ECO MARIN 26012N | V56: LIMG03918800 | W56: ONE LINE | X56: PAITA | Y56: Fresco | Z56: 10005779 | AA56: Inventario final | AB56: =B56&Z56&AA56 -> FEBRERO10005779Inventario final | AC56: =AJ56-616968.19/1968.8+215187/1968.8 -> 1896.1639 | AD56: =IFERROR(INDEX('Costos Producción Febrero'!$G$34:$G$57,MATCH(Resumen!Z56,'Costos Producción Febrero'!$B$34:$B$57,0))*AC56*G56,0) -> 26421.941 | AE56: =IFERROR(INDEX('Costos Producción Febrero'!$H$34:$H$57,MATCH(Resumen!Z56,'Costos Producción Febrero'!$B$34:$B$57,0))*AC56*G56,0) -> 10055.156 | AF56: =IFERROR(INDEX('Costos Producción Febrero'!$I$34:$I$57,MATCH(Resumen!Z56,'Costos Producción Febrero'!$B$34:$B$57,0))*AC56*G56,0) -> 290.67302 | AG56: =IFERROR(INDEX('Costos Producción Febrero'!$J$34:$J$57,MATCH(Resumen!Z56,'Costos Producción Febrero'!$B$34:$B$57,0))*AC56*G56,0) -> 8740.1641 | AH56: =SUM(AD56:AG56) -> 45507.934 | AJ56: 2100.2381 | AL56: =P56-AH56 -> -19107.934 | AM56: =AL56/P56 -> -0.72378539 | AN56: =R56 -> 3203 | AO56: =118461.136538461/5988.21*G56 -> 474.77748 | AP56: =106.583523265795*G56 -> 2558.0046 | AQ56: =SUM(AN56:AP56) -> 6235.782 | AR56: =78579/1995.8*G56 -> 944.93236 | AS56: =S56*0.03 -> 695.91 | AT56: =AL56-AQ56-AR56+AS56 -> -25592.739 | AU56: =AT56/P56 -> -0.96942192 | AV56: =154473/1995.8*G56 -> 1857.5769 | AW56: =AT56-AV56 -> -27450.316 | AX56: =AW56/P56 -> -1.0397847 | AY56: =123844.283333333/1995.8*G56 -> 1489.2588 | AZ56: =AT56+AY56 -> -24103.48 | BA56: =AZ56/P56 -> -0.9130106 | BC56: =P56/$G56 -> 1100 | BD56: =-AD56/$G56 -> -1100.9142 | BE56: =-AE56/$G56 -> -418.96484 | BF56: =-AF56/$G56 -> -12.111376 | BG56: =-AG56/$G56 -> -364.17351 | BH56: =-AH56/$G56 -> -1896.1639 | BI56: =AL56/$G56 -> -796.16393 | BJ56: =-AN56/$G56 -> -133.45833 | BK56: =-AP56/$G56 -> -106.58352 | BL56: =-AQ56/$G56 -> -259.82425 | BM56: =-AR56/$G56 -> -39.372182 | BN56: =AS56/$G56 -> 28.99625 | BO56: =AT56/$G56 -> -1066.3641 | BP56: =-AV56/$G56 -> -77.399038 | BQ56: =AW56/$G56 -> -1143.7632 | BR56: =AY56/$G56 -> 62.052452 | BS56: =AZ56/$G56 -> -1004.3117
B57: FEBRERO | C57: MARZO | D57: 179-2026B1 | E57: 54 | F57: 46101 | G57: 24 | H57: POTA NUCAS | I57: Nucas | J57: 500-up | K57: Tailandia | L57: Lat Krabang | M57: DAIRECK S.A. | N57: Julieta | O57: 1100 | P57: 26400 | Q57: 953.625 | R57: 3513 | S57: =P57-R57 -> 22887 | T57: 1 | U57: ECO MARIN 26012N | V57: LIMG03924500 | W57: ONE LINE | X57: PAITA | Y57: Fresco | Z57: 10005779 | AA57: Inventario final | AB57: =B57&Z57&AA57 -> FEBRERO10005779Inventario final | AC57: =AJ57-616968.19/1968.8+215187/1968.8 -> 1896.1639 | AD57: =IFERROR(INDEX('Costos Producción Febrero'!$G$34:$G$57,MATCH(Resumen!Z57,'Costos Producción Febrero'!$B$34:$B$57,0))*AC57*G57,0) -> 26421.941 | AE57: =IFERROR(INDEX('Costos Producción Febrero'!$H$34:$H$57,MATCH(Resumen!Z57,'Costos Producción Febrero'!$B$34:$B$57,0))*AC57*G57,0) -> 10055.156 | AF57: =IFERROR(INDEX('Costos Producción Febrero'!$I$34:$I$57,MATCH(Resumen!Z57,'Costos Producción Febrero'!$B$34:$B$57,0))*AC57*G57,0) -> 290.67302 | AG57: =IFERROR(INDEX('Costos Producción Febrero'!$J$34:$J$57,MATCH(Resumen!Z57,'Costos Producción Febrero'!$B$34:$B$57,0))*AC57*G57,0) -> 8740.1641 | AH57: =SUM(AD57:AG57) -> 45507.934 | AJ57: 2100.2381 | AL57: =P57-AH57 -> -19107.934 | AM57: =AL57/P57 -> -0.72378539 | AN57: =R57 -> 3513 | AO57: =118461.136538461/5988.21*G57 -> 474.77748 | AP57: =106.583523265795*G57 -> 2558.0046 | AQ57: =SUM(AN57:AP57) -> 6545.782 | AR57: =78579/1995.8*G57 -> 944.93236 | AS57: =S57*0.03 -> 686.61 | AT57: =AL57-AQ57-AR57+AS57 -> -25912.039 | AU57: =AT57/P57 -> -0.98151662 | AV57: =154473/1995.8*G57 -> 1857.5769 | AW57: =AT57-AV57 -> -27769.616 | AX57: =AW57/P57 -> -1.0518794 | AY57: =123844.283333333/1995.8*G57 -> 1489.2588 | AZ57: =AT57+AY57 -> -24422.78 | BA57: =AZ57/P57 -> -0.9251053 | BC57: =P57/$G57 -> 1100 | BD57: =-AD57/$G57 -> -1100.9142 | BE57: =-AE57/$G57 -> -418.96484 | BF57: =-AF57/$G57 -> -12.111376 | BG57: =-AG57/$G57 -> -364.17351 | BH57: =-AH57/$G57 -> -1896.1639 | BI57: =AL57/$G57 -> -796.16393 | BJ57: =-AN57/$G57 -> -146.375 | BK57: =-AP57/$G57 -> -106.58352 | BL57: =-AQ57/$G57 -> -272.74092 | BM57: =-AR57/$G57 -> -39.372182 | BN57: =AS57/$G57 -> 28.60875 | BO57: =AT57/$G57 -> -1079.6683 | BP57: =-AV57/$G57 -> -77.399038 | BQ57: =AW57/$G57 -> -1157.0673 | BR57: =AY57/$G57 -> 62.052452 | BS57: =AZ57/$G57 -> -1017.6158
B58: FEBRERO | C58: MARZO | D58: 179-2026B2 | E58: 54 | F58: 46101 | G58: 24 | H58: POTA NUCAS | I58: Nucas | J58: 500-up | K58: Tailandia | L58: Lat Krabang | M58: DAIRECK S.A. | N58: Julieta | O58: 1100 | P58: 26400 | Q58: 953.625 | R58: 3513 | S58: =P58-R58 -> 22887 | T58: 1 | U58: ECO MARIN 26012N | V58: LIMG03933500 | W58: ONE LINE | X58: PAITA | Y58: Fresco | Z58: 10005779 | AA58: Inventario final | AB58: =B58&Z58&AA58 -> FEBRERO10005779Inventario final | AC58: =AJ58-616968.19/1968.8+215187/1968.8 -> 1896.1639 | AD58: =IFERROR(INDEX('Costos Producción Febrero'!$G$34:$G$57,MATCH(Resumen!Z58,'Costos Producción Febrero'!$B$34:$B$57,0))*AC58*G58,0) -> 26421.941 | AE58: =IFERROR(INDEX('Costos Producción Febrero'!$H$34:$H$57,MATCH(Resumen!Z58,'Costos Producción Febrero'!$B$34:$B$57,0))*AC58*G58,0) -> 10055.156 | AF58: =IFERROR(INDEX('Costos Producción Febrero'!$I$34:$I$57,MATCH(Resumen!Z58,'Costos Producción Febrero'!$B$34:$B$57,0))*AC58*G58,0) -> 290.67302 | AG58: =IFERROR(INDEX('Costos Producción Febrero'!$J$34:$J$57,MATCH(Resumen!Z58,'Costos Producción Febrero'!$B$34:$B$57,0))*AC58*G58,0) -> 8740.1641 | AH58: =SUM(AD58:AG58) -> 45507.934 | AJ58: 2100.2381 | AL58: =P58-AH58 -> -19107.934 | AM58: =AL58/P58 -> -0.72378539 | AN58: =R58 -> 3513 | AO58: =118461.136538461/5988.21*G58 -> 474.77748 | AP58: =106.583523265795*G58 -> 2558.0046 | AQ58: =SUM(AN58:AP58) -> 6545.782 | AR58: =78579/1995.8*G58 -> 944.93236 | AS58: =S58*0.03 -> 686.61 | AT58: =AL58-AQ58-AR58+AS58 -> -25912.039 | AU58: =AT58/P58 -> -0.98151662 | AV58: =154473/1995.8*G58 -> 1857.5769 | AW58: =AT58-AV58 -> -27769.616 | AX58: =AW58/P58 -> -1.0518794 | AY58: =123844.283333333/1995.8*G58 -> 1489.2588 | AZ58: =AT58+AY58 -> -24422.78 | BA58: =AZ58/P58 -> -0.9251053 | BC58: =P58/$G58 -> 1100 | BD58: =-AD58/$G58 -> -1100.9142 | BE58: =-AE58/$G58 -> -418.96484 | BF58: =-AF58/$G58 -> -12.111376 | BG58: =-AG58/$G58 -> -364.17351 | BH58: =-AH58/$G58 -> -1896.1639 | BI58: =AL58/$G58 -> -796.16393 | BJ58: =-AN58/$G58 -> -146.375 | BK58: =-AP58/$G58 -> -106.58352 | BL58: =-AQ58/$G58 -> -272.74092 | BM58: =-AR58/$G58 -> -39.372182 | BN58: =AS58/$G58 -> 28.60875 | BO58: =AT58/$G58 -> -1079.6683 | BP58: =-AV58/$G58 -> -77.399038 | BQ58: =AW58/$G58 -> -1157.0673 | BR58: =AY58/$G58 -> 62.052452 | BS58: =AZ58/$G58 -> -1017.6158
B59: FEBRERO | C59: MARZO | D59: 179-2026B3 | E59: 54 | F59: 46108 | G59: 24 | H59: POTA NUCAS | I59: Nucas | J59: 500-up | K59: Tailandia | L59: Lat Krabang | M59: DAIRECK S.A. | N59: Julieta | O59: 1100 | P59: 26400 | Q59: 953.625 | R59: 3513 | S59: =P59-R59 -> 22887 | T59: 1 | U59: ECO SIROCCO 26013S | V59: LIMG03937900 | W59: ONE LINE | X59: PAITA | Y59: Fresco | Z59: 10005779 | AA59: Inventario final | AB59: =B59&Z59&AA59 -> FEBRERO10005779Inventario final | AC59: =AJ59-616968.19/1968.8+215187/1968.8 -> 1896.1639 | AD59: =IFERROR(INDEX('Costos Producción Febrero'!$G$34:$G$57,MATCH(Resumen!Z59,'Costos Producción Febrero'!$B$34:$B$57,0))*AC59*G59,0) -> 26421.941 | AE59: =IFERROR(INDEX('Costos Producción Febrero'!$H$34:$H$57,MATCH(Resumen!Z59,'Costos Producción Febrero'!$B$34:$B$57,0))*AC59*G59,0) -> 10055.156 | AF59: =IFERROR(INDEX('Costos Producción Febrero'!$I$34:$I$57,MATCH(Resumen!Z59,'Costos Producción Febrero'!$B$34:$B$57,0))*AC59*G59,0) -> 290.67302 | AG59: =IFERROR(INDEX('Costos Producción Febrero'!$J$34:$J$57,MATCH(Resumen!Z59,'Costos Producción Febrero'!$B$34:$B$57,0))*AC59*G59,0) -> 8740.1641 | AH59: =SUM(AD59:AG59) -> 45507.934 | AJ59: 2100.2381 | AL59: =P59-AH59 -> -19107.934 | AM59: =AL59/P59 -> -0.72378539 | AN59: =R59 -> 3513 | AO59: =118461.136538461/5988.21*G59 -> 474.77748 | AP59: =106.583523265795*G59 -> 2558.0046 | AQ59: =SUM(AN59:AP59) -> 6545.782 | AR59: =78579/1995.8*G59 -> 944.93236 | AS59: =S59*0.03 -> 686.61 | AT59: =AL59-AQ59-AR59+AS59 -> -25912.039 | AU59: =AT59/P59 -> -0.98151662 | AV59: =154473/1995.8*G59 -> 1857.5769 | AW59: =AT59-AV59 -> -27769.616 | AX59: =AW59/P59 -> -1.0518794 | AY59: =123844.283333333/1995.8*G59 -> 1489.2588 | AZ59: =AT59+AY59 -> -24422.78 | BA59: =AZ59/P59 -> -0.9251053 | BC59: =P59/$G59 -> 1100 | BD59: =-AD59/$G59 -> -1100.9142 | BE59: =-AE59/$G59 -> -418.96484 | BF59: =-AF59/$G59 -> -12.111376 | BG59: =-AG59/$G59 -> -364.17351 | BH59: =-AH59/$G59 -> -1896.1639 | BI59: =AL59/$G59 -> -796.16393 | BJ59: =-AN59/$G59 -> -146.375 | BK59: =-AP59/$G59 -> -106.58352 | BL59: =-AQ59/$G59 -> -272.74092 | BM59: =-AR59/$G59 -> -39.372182 | BN59: =AS59/$G59 -> 28.60875 | BO59: =AT59/$G59 -> -1079.6683 | BP59: =-AV59/$G59 -> -77.399038 | BQ59: =AW59/$G59 -> -1157.0673 | BR59: =AY59/$G59 -> 62.052452 | BS59: =AZ59/$G59 -> -1017.6158
B60: FEBRERO | C60: MARZO | D60: 179-2026B4 | E60: 54 | F60: 46108 | G60: 24 | H60: POTA NUCAS | I60: Nucas | J60: 500-up | K60: Tailandia | L60: Lat Krabang | M60: DAIRECK S.A. | N60: Julieta | O60: 1100 | P60: 26400 | Q60: 953.625 | R60: 3513 | S60: =P60-R60 -> 22887 | T60: 1 | U60: ECO SIROCCO 26013S | V60: LIMG03938300 | W60: ONE LINE | X60: PAITA | Y60: Fresco | Z60: 10005779 | AA60: Inventario final | AB60: =B60&Z60&AA60 -> FEBRERO10005779Inventario final | AC60: =AJ60-616968.19/1968.8+215187/1968.8 -> 1896.1639 | AD60: =IFERROR(INDEX('Costos Producción Febrero'!$G$34:$G$57,MATCH(Resumen!Z60,'Costos Producción Febrero'!$B$34:$B$57,0))*AC60*G60,0) -> 26421.941 | AE60: =IFERROR(INDEX('Costos Producción Febrero'!$H$34:$H$57,MATCH(Resumen!Z60,'Costos Producción Febrero'!$B$34:$B$57,0))*AC60*G60,0) -> 10055.156 | AF60: =IFERROR(INDEX('Costos Producción Febrero'!$I$34:$I$57,MATCH(Resumen!Z60,'Costos Producción Febrero'!$B$34:$B$57,0))*AC60*G60,0) -> 290.67302 | AG60: =IFERROR(INDEX('Costos Producción Febrero'!$J$34:$J$57,MATCH(Resumen!Z60,'Costos Producción Febrero'!$B$34:$B$57,0))*AC60*G60,0) -> 8740.1641 | AH60: =SUM(AD60:AG60) -> 45507.934 | AJ60: 2100.2381 | AL60: =P60-AH60 -> -19107.934 | AM60: =AL60/P60 -> -0.72378539 | AN60: =R60 -> 3513 | AO60: =118461.136538461/5988.21*G60 -> 474.77748 | AP60: =106.583523265795*G60 -> 2558.0046 | AQ60: =SUM(AN60:AP60) -> 6545.782 | AR60: =78579/1995.8*G60 -> 944.93236 | AS60: =S60*0.03 -> 686.61 | AT60: =AL60-AQ60-AR60+AS60 -> -25912.039 | AU60: =AT60/P60 -> -0.98151662 | AV60: =154473/1995.8*G60 -> 1857.5769 | AW60: =AT60-AV60 -> -27769.616 | AX60: =AW60/P60 -> -1.0518794 | AY60: =123844.283333333/1995.8*G60 -> 1489.2588 | AZ60: =AT60+AY60 -> -24422.78 | BA60: =AZ60/P60 -> -0.9251053 | BC60: =P60/$G60 -> 1100 | BD60: =-AD60/$G60 -> -1100.9142 | BE60: =-AE60/$G60 -> -418.96484 | BF60: =-AF60/$G60 -> -12.111376 | BG60: =-AG60/$G60 -> -364.17351 | BH60: =-AH60/$G60 -> -1896.1639 | BI60: =AL60/$G60 -> -796.16393 | BJ60: =-AN60/$G60 -> -146.375 | BK60: =-AP60/$G60 -> -106.58352 | BL60: =-AQ60/$G60 -> -272.74092 | BM60: =-AR60/$G60 -> -39.372182 | BN60: =AS60/$G60 -> 28.60875 | BO60: =AT60/$G60 -> -1079.6683 | BP60: =-AV60/$G60 -> -77.399038 | BQ60: =AW60/$G60 -> -1157.0673 | BR60: =AY60/$G60 -> 62.052452 | BS60: =AZ60/$G60 -> -1017.6158
B61: FEBRERO | C61: MARZO | D61: 179-2026B5 | E61: 54 | F61: 46108 | G61: 24 | H61: POTA NUCAS | I61: Nucas | J61: 500-up | K61: Tailandia | L61: Lat Krabang | M61: DAIRECK S.A. | N61: Julieta | O61: 1100 | P61: 26400 | Q61: 966.54167 | R61: 3203 | S61: =P61-R61 -> 23197 | T61: 1 | U61: ECO SIROCCO 26013S | V61: LIMG03940300 | W61: ONE LINE | X61: PAITA | Y61: Fresco | Z61: 10005779 | AA61: Inventario final | AB61: =B61&Z61&AA61 -> FEBRERO10005779Inventario final | AC61: =AJ61-616968.19/1968.8+215187/1968.8 -> 1896.1639 | AD61: =IFERROR(INDEX('Costos Producción Febrero'!$G$34:$G$57,MATCH(Resumen!Z61,'Costos Producción Febrero'!$B$34:$B$57,0))*AC61*G61,0) -> 26421.941 | AE61: =IFERROR(INDEX('Costos Producción Febrero'!$H$34:$H$57,MATCH(Resumen!Z61,'Costos Producción Febrero'!$B$34:$B$57,0))*AC61*G61,0) -> 10055.156 | AF61: =IFERROR(INDEX('Costos Producción Febrero'!$I$34:$I$57,MATCH(Resumen!Z61,'Costos Producción Febrero'!$B$34:$B$57,0))*AC61*G61,0) -> 290.67302 | AG61: =IFERROR(INDEX('Costos Producción Febrero'!$J$34:$J$57,MATCH(Resumen!Z61,'Costos Producción Febrero'!$B$34:$B$57,0))*AC61*G61,0) -> 8740.1641 | AH61: =SUM(AD61:AG61) -> 45507.934 | AJ61: 2100.2381 | AL61: =P61-AH61 -> -19107.934 | AM61: =AL61/P61 -> -0.72378539 | AN61: =R61 -> 3203 | AO61: =118461.136538461/5988.21*G61 -> 474.77748 | AP61: =106.583523265795*G61 -> 2558.0046 | AQ61: =SUM(AN61:AP61) -> 6235.782 | AR61: =78579/1995.8*G61 -> 944.93236 | AS61: =S61*0.03 -> 695.91 | AT61: =AL61-AQ61-AR61+AS61 -> -25592.739 | AU61: =AT61/P61 -> -0.96942192 | AV61: =154473/1995.8*G61 -> 1857.5769 | AW61: =AT61-AV61 -> -27450.316 | AX61: =AW61/P61 -> -1.0397847 | AY61: =123844.283333333/1995.8*G61 -> 1489.2588 | AZ61: =AT61+AY61 -> -24103.48 | BA61: =AZ61/P61 -> -0.9130106 | BC61: =P61/$G61 -> 1100 | BD61: =-AD61/$G61 -> -1100.9142 | BE61: =-AE61/$G61 -> -418.96484 | BF61: =-AF61/$G61 -> -12.111376 | BG61: =-AG61/$G61 -> -364.17351 | BH61: =-AH61/$G61 -> -1896.1639 | BI61: =AL61/$G61 -> -796.16393 | BJ61: =-AN61/$G61 -> -133.45833 | BK61: =-AP61/$G61 -> -106.58352 | BL61: =-AQ61/$G61 -> -259.82425 | BM61: =-AR61/$G61 -> -39.372182 | BN61: =AS61/$G61 -> 28.99625 | BO61: =AT61/$G61 -> -1066.3641 | BP61: =-AV61/$G61 -> -77.399038 | BQ61: =AW61/$G61 -> -1143.7632 | BR61: =AY61/$G61 -> 62.052452 | BS61: =AZ61/$G61 -> -1004.3117
B62: FEBRERO | C62: MARZO | D62: 179-2026C1 | E62: 54 | F62: 46108 | G62: 24 | H62: POTA NUCAS | I62: Nucas | J62: 1-2 KG | K62: Tailandia | L62: Lat Krabang | M62: DAIRECK S.A. | N62: KHUNRUNG | O62: 1200 | P62: =28800-9240 -> 19560 | Q62: 1054.1667 | R62: 3500 | S62: =P62-R62 -> 16060 | T62: 1 | U62: ECO SIROCCO 26013S | V62: 6447908140 | W62: COSCO | X62: PAITA | Y62: Fresco | Z62: 10005779 | AA62: Inventario final | AB62: =B62&Z62&AA62 -> FEBRERO10005779Inventario final | AC62: =AJ62-616968.19/1968.8+215187/1968.8 -> 1896.1639 | AD62: =IFERROR(INDEX('Costos Producción Febrero'!$G$34:$G$57,MATCH(Resumen!Z62,'Costos Producción Febrero'!$B$34:$B$57,0))*AC62*G62,0) -> 26421.941 | AE62: =IFERROR(INDEX('Costos Producción Febrero'!$H$34:$H$57,MATCH(Resumen!Z62,'Costos Producción Febrero'!$B$34:$B$57,0))*AC62*G62,0) -> 10055.156 | AF62: =IFERROR(INDEX('Costos Producción Febrero'!$I$34:$I$57,MATCH(Resumen!Z62,'Costos Producción Febrero'!$B$34:$B$57,0))*AC62*G62,0) -> 290.67302 | AG62: =IFERROR(INDEX('Costos Producción Febrero'!$J$34:$J$57,MATCH(Resumen!Z62,'Costos Producción Febrero'!$B$34:$B$57,0))*AC62*G62,0) -> 8740.1641 | AH62: =SUM(AD62:AG62) -> 45507.934 | AJ62: 2100.2381 | AL62: =P62-AH62 -> -25947.934 | AM62: =AL62/P62 -> -1.3265815 | AN62: =R62 -> 3500 | AO62: =118461.136538461/5988.21*G62 -> 474.77748 | AP62: =106.583523265795*G62 -> 2558.0046 | AQ62: =SUM(AN62:AP62) -> 6532.782 | AR62: =78579/1995.8*G62 -> 944.93236 | AS62: =S62*0.03 -> 481.8 | AT62: =AL62-AQ62-AR62+AS62 -> -32943.849 | AU62: =AT62/P62 -> -1.6842458 | AV62: =154473/1995.8*G62 -> 1857.5769 | AW62: =AT62-AV62 -> -34801.426 | AX62: =AW62/P62 -> -1.779214 | AY62: =123844.283333333/1995.8*G62 -> 1489.2588 | AZ62: =AT62+AY62 -> -31454.59 | BA62: =AZ62/P62 -> -1.6081079 | BC62: =P62/$G62 -> 815 | BD62: =-AD62/$G62 -> -1100.9142 | BE62: =-AE62/$G62 -> -418.96484 | BF62: =-AF62/$G62 -> -12.111376 | BG62: =-AG62/$G62 -> -364.17351 | BH62: =-AH62/$G62 -> -1896.1639 | BI62: =AL62/$G62 -> -1081.1639 | BJ62: =-AN62/$G62 -> -145.83333 | BK62: =-AP62/$G62 -> -106.58352 | BL62: =-AQ62/$G62 -> -272.19925 | BM62: =-AR62/$G62 -> -39.372182 | BN62: =AS62/$G62 -> 20.075 | BO62: =AT62/$G62 -> -1372.6604 | BP62: =-AV62/$G62 -> -77.399038 | BQ62: =AW62/$G62 -> -1450.0594 | BR62: =AY62/$G62 -> 62.052452 | BS62: =AZ62/$G62 -> -1310.6079
B63: FEBRERO | C63: MARZO | D63: 179-2026C2 | E63: 54 | F63: 46108 | G63: 24 | H63: POTA NUCAS | I63: Nucas | J63: 1-2 KG | K63: Tailandia | L63: Lat Krabang | M63: DAIRECK S.A. | N63: KHUNRUNG | O63: 1200 | P63: 28800 | Q63: 1054.1667 | R63: 3500 | S63: =P63-R63 -> 25300 | T63: 1 | U63: ECO SIROCCO 26013S | V63: 6447908120 | W63: COSCO | X63: PAITA | Y63: Fresco | Z63: 10005779 | AA63: Inventario final | AB63: =B63&Z63&AA63 -> FEBRERO10005779Inventario final | AC63: =AJ63-616968.19/1968.8+215187/1968.8 -> 1896.1639 | AD63: =IFERROR(INDEX('Costos Producción Febrero'!$G$34:$G$57,MATCH(Resumen!Z63,'Costos Producción Febrero'!$B$34:$B$57,0))*AC63*G63,0) -> 26421.941 | AE63: =IFERROR(INDEX('Costos Producción Febrero'!$H$34:$H$57,MATCH(Resumen!Z63,'Costos Producción Febrero'!$B$34:$B$57,0))*AC63*G63,0) -> 10055.156 | AF63: =IFERROR(INDEX('Costos Producción Febrero'!$I$34:$I$57,MATCH(Resumen!Z63,'Costos Producción Febrero'!$B$34:$B$57,0))*AC63*G63,0) -> 290.67302 | AG63: =IFERROR(INDEX('Costos Producción Febrero'!$J$34:$J$57,MATCH(Resumen!Z63,'Costos Producción Febrero'!$B$34:$B$57,0))*AC63*G63,0) -> 8740.1641 | AH63: =SUM(AD63:AG63) -> 45507.934 | AJ63: 2100.2381 | AL63: =P63-AH63 -> -16707.934 | AM63: =AL63/P63 -> -0.58013661 | AN63: =R63 -> 3500 | AO63: =118461.136538461/5988.21*G63 -> 474.77748 | AP63: =106.583523265795*G63 -> 2558.0046 | AQ63: =SUM(AN63:AP63) -> 6532.782 | AR63: =78579/1995.8*G63 -> 944.93236 | AS63: =S63*0.03 -> 759 | AT63: =AL63-AQ63-AR63+AS63 -> -23426.649 | AU63: =AT63/P63 -> -0.81342531 | AV63: =154473/1995.8*G63 -> 1857.5769 | AW63: =AT63-AV63 -> -25284.226 | AX63: =AW63/P63 -> -0.8779245 | AY63: =123844.283333333/1995.8*G63 -> 1489.2588 | AZ63: =AT63+AY63 -> -21937.39 | BA63: =AZ63/P63 -> -0.76171493 | BC63: =P63/$G63 -> 1200 | BD63: =-AD63/$G63 -> -1100.9142 | BE63: =-AE63/$G63 -> -418.96484 | BF63: =-AF63/$G63 -> -12.111376 | BG63: =-AG63/$G63 -> -364.17351 | BH63: =-AH63/$G63 -> -1896.1639 | BI63: =AL63/$G63 -> -696.16393 | BJ63: =-AN63/$G63 -> -145.83333 | BK63: =-AP63/$G63 -> -106.58352 | BL63: =-AQ63/$G63 -> -272.19925 | BM63: =-AR63/$G63 -> -39.372182 | BN63: =AS63/$G63 -> 31.625 | BO63: =AT63/$G63 -> -976.11037 | BP63: =-AV63/$G63 -> -77.399038 | BQ63: =AW63/$G63 -> -1053.5094 | BR63: =AY63/$G63 -> 62.052452 | BS63: =AZ63/$G63 -> -914.05791
B64: FEBRERO | C64: MARZO | D64: 181-2026 | E64: 46077 | F64: 46108 | G64: 48 | H64: POTA NUCAS | I64: Nucas | J64: 500-1000 | K64: Tailandia | L64: Lat Krabang | M64: TSUJINO | N64: Jose | O64: 1200 | P64: 57600 | Q64: 1126.8125 | R64: 3513 | S64: =P64-R64 -> 54087 | T64: 1 | U64: ECO SIROCCO 26013S | V64: LIMG04324700 | W64: ONE LINE | X64: PAITA | Y64: Fresco | Z64: 10005779 | AA64: Inventario final | AB64: =B64&Z64&AA64 -> FEBRERO10005779Inventario final | AC64: =AJ64-616968.19/1968.8+215187/1968.8 -> 1896.1639 | AD64: =IFERROR(INDEX('Costos Producción Febrero'!$G$34:$G$57,MATCH(Resumen!Z64,'Costos Producción Febrero'!$B$34:$B$57,0))*AC64*G64,0) -> 52843.882 | AE64: =IFERROR(INDEX('Costos Producción Febrero'!$H$34:$H$57,MATCH(Resumen!Z64,'Costos Producción Febrero'!$B$34:$B$57,0))*AC64*G64,0) -> 20110.313 | AF64: =IFERROR(INDEX('Costos Producción Febrero'!$I$34:$I$57,MATCH(Resumen!Z64,'Costos Producción Febrero'!$B$34:$B$57,0))*AC64*G64,0) -> 581.34604 | AG64: =IFERROR(INDEX('Costos Producción Febrero'!$J$34:$J$57,MATCH(Resumen!Z64,'Costos Producción Febrero'!$B$34:$B$57,0))*AC64*G64,0) -> 17480.328 | AH64: =SUM(AD64:AG64) -> 91015.869 | AJ64: 2100.2381 | AL64: =P64-AH64 -> -33415.869 | AM64: =AL64/P64 -> -0.58013661 | AN64: =R64 -> 3513 | AO64: =118461.136538461/5988.21*G64 -> 949.55497 | AP64: =106.583523265795*G64 -> 5116.0091 | AQ64: =SUM(AN64:AP64) -> 9578.5641 | AR64: =78579/1995.8*G64 -> 1889.8647 | AS64: =S64*0.03 -> 1622.61 | AT64: =AL64-AQ64-AR64+AS64 -> -43261.688 | AU64: =AT64/P64 -> -0.75107096 | AV64: =154473/1995.8*G64 -> 3715.1538 | AW64: =AT64-AV64 -> -46976.841 | AX64: =AW64/P64 -> -0.81557016 | AY64: =123844.283333333/1995.8*G64 -> 2978.5177 | AZ64: =AT64+AY64 -> -40283.17 | BA64: =AZ64/P64 -> -0.69936059 | BC64: =P64/$G64 -> 1200 | BD64: =-AD64/$G64 -> -1100.9142 | BE64: =-AE64/$G64 -> -418.96484 | BF64: =-AF64/$G64 -> -12.111376 | BG64: =-AG64/$G64 -> -364.17351 | BH64: =-AH64/$G64 -> -1896.1639 | BI64: =AL64/$G64 -> -696.16393 | BJ64: =-AN64/$G64 -> -73.1875 | BK64: =-AP64/$G64 -> -106.58352 | BL64: =-AQ64/$G64 -> -199.55342 | BM64: =-AR64/$G64 -> -39.372182 | BN64: =AS64/$G64 -> 33.804375 | BO64: =AT64/$G64 -> -901.28516 | BP64: =-AV64/$G64 -> -77.399038 | BQ64: =AW64/$G64 -> -978.6842 | BR64: =AY64/$G64 -> 62.052452 | BS64: =AZ64/$G64 -> -839.23271
B65: FEBRERO | C65: MARZO | D65: 183-2026 | E65: 58 | F65: 46108 | G65: 27 | H65: POTA REJOS CONGELADOS | I65: Rejos | J65: 2- UP LIMPIOS | K65: China | L65: Yantai | M65: SHANDONG SHEENIER | O65: 2600 | P65: 70200 | Q65: 2485.1852 | R65: 3100 | S65: =P65-R65 -> 67100 | T65: 1 | U65: ECO SIROCCO 26013S | V65: 6447908790 | W65: COSCO | X65: PAITA | Y65: Fresco | Z65: 10007162 | AA65: Inventario final | AB65: =B65&Z65&AA65 -> FEBRERO10007162Inventario final | AC65: =AJ65-616968.19/1968.8+215187/1968.8 -> 1814.1051 | AD65: =IFERROR(INDEX('Costos Producción Febrero'!$G$34:$G$57,MATCH(Resumen!Z65,'Costos Producción Febrero'!$B$34:$B$57,0))*AC65*G65,0) -> 30032.633 | AE65: =IFERROR(INDEX('Costos Producción Febrero'!$H$34:$H$57,MATCH(Resumen!Z65,'Costos Producción Febrero'!$B$34:$B$57,0))*AC65*G65,0) -> 8526.8635 | AF65: =IFERROR(INDEX('Costos Producción Febrero'!$I$34:$I$57,MATCH(Resumen!Z65,'Costos Producción Febrero'!$B$34:$B$57,0))*AC65*G65,0) -> 454.08128 | AG65: =IFERROR(INDEX('Costos Producción Febrero'!$J$34:$J$57,MATCH(Resumen!Z65,'Costos Producción Febrero'!$B$34:$B$57,0))*AC65*G65,0) -> 9967.2608 | AH65: =SUM(AD65:AG65) -> 48980.839 | AJ65: 2018.1793 | AL65: =P65-AH65 -> 21219.161 | AM65: =AL65/P65 -> 0.30226726 | AN65: =R65 -> 3100 | AO65: =118461.136538461/5988.21*G65 -> 534.12467 | AP65: =106.583523265795*G65 -> 2877.7551 | AQ65: =SUM(AN65:AP65) -> 6511.8798 | AR65: =78579/1995.8*G65 -> 1063.0489 | AS65: =S65*0.03 -> 2013 | AT65: =AL65-AQ65-AR65+AS65 -> 15657.233 | AU65: =AT65/P65 -> 0.2230375 | AV65: =154473/1995.8*G65 -> 2089.774 | AW65: =AT65-AV65 -> 13567.459 | AX65: =AW65/P65 -> 0.19326864 | AY65: =123844.283333333/1995.8*G65 -> 1675.4162 | AZ65: =AT65+AY65 -> 17332.649 | BA65: =AZ65/P65 -> 0.24690383 | BC65: =P65/$G65 -> 2600 | BD65: =-AD65/$G65 -> -1112.3197 | BE65: =-AE65/$G65 -> -315.80976 | BF65: =-AF65/$G65 -> -16.817825 | BG65: =-AG65/$G65 -> -369.15781 | BH65: =-AH65/$G65 -> -1814.1051 | BI65: =AL65/$G65 -> 785.89487 | BJ65: =-AN65/$G65 -> -114.81481 | BK65: =-AP65/$G65 -> -106.58352 | BL65: =-AQ65/$G65 -> -241.18073 | BM65: =-AR65/$G65 -> -39.372182 | BN65: =AS65/$G65 -> 74.555556 | BO65: =AT65/$G65 -> 579.89751 | BP65: =-AV65/$G65 -> -77.399038 | BQ65: =AW65/$G65 -> 502.49847 | BR65: =AY65/$G65 -> 62.052452 | BS65: =AZ65/$G65 -> 641.94996
B66: FEBRERO | C66: MARZO | D66: 184-2026 | E66: 59 | F66: 46104 | G66: 216 | H66: POTA FILETE DARUMA | I66: Daruma | K66: China | L66: Qingdao | M66: LONGKOU JIABAO AQUATIC | N66: James | O66: 3100 | P66: 669600 | Q66: 2992.5926 | R66: 23200 | S66: =P66-R66 -> 646400 | T66: 8 | U66: ECO MARIN 26012N | V66: 6447338820 | W66: COSCO | X66: PAITA | Y66: Cocido | Z66: 10009239 | AA66: Inventario final | AB66: =B66&Z66&AA66 -> FEBRERO10009239Inventario final | AC66: =AJ66-616968.19/1968.8+215187/1968.8 -> 2193.6703 | AD66: =IFERROR(INDEX('Costos Producción Febrero'!$G$34:$G$57,MATCH(Resumen!Z66,'Costos Producción Febrero'!$B$34:$B$57,0))*AC66*G66,0) -> 233010.93 | AE66: =IFERROR(INDEX('Costos Producción Febrero'!$H$34:$H$57,MATCH(Resumen!Z66,'Costos Producción Febrero'!$B$34:$B$57,0))*AC66*G66,0) -> 151910.27 | AF66: =IFERROR(INDEX('Costos Producción Febrero'!$I$34:$I$57,MATCH(Resumen!Z66,'Costos Producción Febrero'!$B$34:$B$57,0))*AC66*G66,0) -> 2782.0066 | AG66: =IFERROR(INDEX('Costos Producción Febrero'!$J$34:$J$57,MATCH(Resumen!Z66,'Costos Producción Febrero'!$B$34:$B$57,0))*AC66*G66,0) -> 86129.575 | AH66: =SUM(AD66:AG66) -> 473832.79 | AJ66: 2397.7445 | AL66: =P66-AH66 -> 195767.21 | AM66: =AL66/P66 -> 0.29236441 | AN66: =R66 -> 23200 | AO66: =118461.136538461/5988.21*G66 -> 4272.9974 | AP66: =106.583523265795*G66 -> 23022.041 | AQ66: =SUM(AN66:AP66) -> 50495.038 | AR66: =78579/1995.8*G66 -> 8504.3912 | AS66: =S66*0.03 -> 19392 | AT66: =AL66-AQ66-AR66+AS66 -> 156159.78 | AU66: =AT66/P66 -> 0.23321353 | AV66: =154473/1995.8*G66 -> 16718.192 | AW66: =AT66-AV66 -> 139441.59 | AX66: =AW66/P66 -> 0.2082461 | AY66: =123844.283333333/1995.8*G66 -> 13403.33 | AZ66: =AT66+AY66 -> 169563.11 | BA66: =AZ66/P66 -> 0.25323045 | BC66: =P66/$G66 -> 3100 | BD66: =-AD66/$G66 -> -1078.7543 | BE66: =-AE66/$G66 -> -703.28831 | BF66: =-AF66/$G66 -> -12.87966 | BG66: =-AG66/$G66 -> -398.74803 | BH66: =-AH66/$G66 -> -2193.6703 | BI66: =AL66/$G66 -> 906.32968 | BJ66: =-AN66/$G66 -> -107.40741 | BK66: =-AP66/$G66 -> -106.58352 | BL66: =-AQ66/$G66 -> -233.77333 | BM66: =-AR66/$G66 -> -39.372182 | BN66: =AS66/$G66 -> 89.777778 | BO66: =AT66/$G66 -> 722.96195 | BP66: =-AV66/$G66 -> -77.399038 | BQ66: =AW66/$G66 -> 645.56291 | BR66: =AY66/$G66 -> 62.052452 | BS66: =AZ66/$G66 -> 785.0144
B67: FEBRERO | C67: MARZO | D67: 185-2026 | E67: 59 | F67: 46104 | G67: 108 | H67: POTA FILETE DARUMA | I67: Daruma | K67: China | L67: Qingdao | M67: LONGKOU BOHAI | N67: James | O67: 3100 | P67: 334800 | Q67: 2992.5926 | R67: 11600 | S67: =P67-R67 -> 323200 | T67: 4 | U67: ECO MARIN 26012N | V67: 6447338860 | W67: COSCO | X67: PAITA | Y67: Cocido | Z67: 10009239 | AA67: Inventario final | AB67: =B67&Z67&AA67 -> FEBRERO10009239Inventario final | AC67: =AJ67-616968.19/1968.8+215187/1968.8 -> 2193.6703 | AD67: =IFERROR(INDEX('Costos Producción Febrero'!$G$34:$G$57,MATCH(Resumen!Z67,'Costos Producción Febrero'!$B$34:$B$57,0))*AC67*G67,0) -> 116505.47 | AE67: =IFERROR(INDEX('Costos Producción Febrero'!$H$34:$H$57,MATCH(Resumen!Z67,'Costos Producción Febrero'!$B$34:$B$57,0))*AC67*G67,0) -> 75955.137 | AF67: =IFERROR(INDEX('Costos Producción Febrero'!$I$34:$I$57,MATCH(Resumen!Z67,'Costos Producción Febrero'!$B$34:$B$57,0))*AC67*G67,0) -> 1391.0033 | AG67: =IFERROR(INDEX('Costos Producción Febrero'!$J$34:$J$57,MATCH(Resumen!Z67,'Costos Producción Febrero'!$B$34:$B$57,0))*AC67*G67,0) -> 43064.787 | AH67: =SUM(AD67:AG67) -> 236916.39 | AJ67: 2397.7445 | AL67: =P67-AH67 -> 97883.605 | AM67: =AL67/P67 -> 0.29236441 | AN67: =R67 -> 11600 | AO67: =118461.136538461/5988.21*G67 -> 2136.4987 | AP67: =106.583523265795*G67 -> 11511.021 | AQ67: =SUM(AN67:AP67) -> 25247.519 | AR67: =78579/1995.8*G67 -> 4252.1956 | AS67: =S67*0.03 -> 9696 | AT67: =AL67-AQ67-AR67+AS67 -> 78079.89 | AU67: =AT67/P67 -> 0.23321353 | AV67: =154473/1995.8*G67 -> 8359.0961 | AW67: =AT67-AV67 -> 69720.794 | AX67: =AW67/P67 -> 0.2082461 | AY67: =123844.283333333/1995.8*G67 -> 6701.6648 | AZ67: =AT67+AY67 -> 84781.555 | BA67: =AZ67/P67 -> 0.25323045 | BC67: =P67/$G67 -> 3100 | BD67: =-AD67/$G67 -> -1078.7543 | BE67: =-AE67/$G67 -> -703.28831 | BF67: =-AF67/$G67 -> -12.87966 | BG67: =-AG67/$G67 -> -398.74803 | BH67: =-AH67/$G67 -> -2193.6703 | BI67: =AL67/$G67 -> 906.32968 | BJ67: =-AN67/$G67 -> -107.40741 | BK67: =-AP67/$G67 -> -106.58352 | BL67: =-AQ67/$G67 -> -233.77333 | BM67: =-AR67/$G67 -> -39.372182 | BN67: =AS67/$G67 -> 89.777778 | BO67: =AT67/$G67 -> 722.96195 | BP67: =-AV67/$G67 -> -77.399038 | BQ67: =AW67/$G67 -> 645.56291 | BR67: =AY67/$G67 -> 62.052452 | BS67: =AZ67/$G67 -> 785.0144
