Workbook

Sheet Gráficos ppt
S3: ='Tablas ppt'!S46-'Tablas ppt'!S44 -> -0.27
B5: 1. RESULTADOS INTERNOS
B63: 2. BENCHMARK INDUSTRIA PERUANA DE CONGELADOS (VERITRADE)
B88: Top 15 Exportadores — Productos Congelados (Alas, Filete, Nuca, Tentáculo, Reproductor)
B90: Nro | C90: Exportador | D90: Valor FOB (US$) | E90: TM | F90: Precio por TM
B91: 1 | C91: Industrial Pesquera Santa Monica S.A. | D91: 12800672 | E91: 7371.2 | F91: 1737
B92: 2 | C92: Pesquera Hermanos Cordova S.A.C. | D92: 11792528 | E92: 7242.6 | F92: 1628
B93: 3 | C93: Oceano Seafood S.A. | D93: 11724680 | E93: 6746.5 | F93: 1738
B94: 4 | C94: Productora Andina De Congelados S.R.L. | D94: 8847640 | E94: 5227.2 | F94: 1693
B95: 5 | C95: Costa Mira Sociedad Anonima Cerrada | D95: 8496998 | E95: 4421.2 | F95: 1922
B96: 6 | C96: Novaperu S.A.C. | D96: 6857126 | E96: 3973.8 | F96: 1726
B97: 7 | C97: Peru Frost Sociedad Anonima Cerrada | D97: 6231879 | E97: 3981.4 | F97: 1565
B98: 8 | C98: Esmeralda Corp S.A.C. | D98: 6229395 | E98: 3736 | F98: 1667
B99: 9 | C99: Proveedora De Productos Marinos Sociedad | D99: 6166547 | E99: 3730.3 | F99: 1653
B100: 10 | C100: Peruvian Sea Food S.A. | D100: 6164559 | E100: 3692.9 | F100: 1669
B101: 11 | C101: Pesquera Supercetus S.A.C. | D101: 5928869 | E101: 3562.1 | F101: 1664
B102: 12 | C102: Transmarina Del Peru S.A.C. | D102: 5879029 | E102: 3591.3 | F102: 1637
... B105: 15 | C105: Seafrost S.A.C. | D105: 5556358 | E105: 3119.3 | F105: 1781
B107: Top 15 Exportadores — Productos Cocidos (Alas Cocidas, Filete Daruma)
B109: Nro | C109: Exportador | D109: Valor FOB (US$) | E109: TM | F109: Precio por TM
B110: 1 | C110: Costa Mira Sociedad Anonima Cerrada | D110: 9211788 | E110: 2579.8 | F110: 3571
B111: 2 | C111: KSL S.A.C. | D111: 5319083 | E111: 1670.5 | F111: 3184
B112: 3 | C112: Pacific Freezing Company S.A.C. | D112: 4286058 | E112: 1338 | F112: 3203
B113: 4 | C113: Oceano Seafood S.A. | D113: 4050574 | E113: 1190.4 | F113: 3403
B114: 5 | C114: Frigosa Sociedad S.A.C. | D114: 3921103 | E114: 1215 | F114: 3227
B115: 6 | C115: Dexim Srl | D115: 3883786 | E115: 1076.8 | F115: 3607
B116: 7 | C116: Inversiones Holding Peru Sociedad Anonim | D116: 2905633 | E116: 847.7 | F116: 3428
B117: 8 | C117: Corporacion Pesquera Del Mar Sociedad An | D117: 2751416 | E117: 796 | F117: 3457
B118: 9 | C118: Mik Carpe S.A.C. | D118: 2475284 | E118: 735 | F118: 3368
B119: 10 | C119: Seafrost S.A.C. | D119: 2135285 | E119: 602.9 | F119: 3542
B120: 11 | C120: Pesquera Exalmar S.A.A. | D120: 1926814 | E120: 563.2 | F120: 3421
B121: 12 | C121: Refrigerados Fisholg & Hijos Sociedad An | D121: 1802223 | E121: 539.5 | F121: 3340
... B124: 15 | C124: Industrial Pesquera Santa Monica S.A. | D124: 1603048 | E124: 475.7 | F124: 3370

Sheet Tablas ppt
B5: PERU FROST - CONGELADOS 2026 (MILES US$)
B6: Concepto | C6: 46023 | D6: 46054 | E6: 46082 | F6: 46113 | G6: Acum 2026 | H6: Presupuesto | I6: Variación | M6: cambiar a nombre a presupuesto
B7: TM Materia Prima | C7: =[1]Resumen!$D$4 -> 1877.215 | D7: =[1]Resumen!$D$5 -> 3149.786 | E7: =[1]Resumen!$D$6 -> 2255.518 | F7: =[1]Resumen!$D$7 -> 2853.189 | G7: =SUM(C7:F7) -> 10135.708 | H7: 8550 | I7: =G7-H7 -> 1585.708 | M7: el presupuesto incluye todo de muelle y demas, añadirlos
B8: TM Vendidas PT | C8: =TD!B7 -> 248 | D8: =TD!C7 -> 1634.3 | E8: =TD!D7 -> 1995.8 | F8: =TD!E7 -> 2110.11 | G8: =TD!F7 -> 5988.21 | H8: =TD!G7 -> 5834 | I8: =G8-H8 -> 154.21 | M8: separar cuanto es congelados y muelle
B9: Venta | C9: =TD!B8/1000 -> 564.61528 | D9: =TD!C8/1000 -> 2769.8245 | E9: =TD!D8/1000 -> 3896.4183 | F9: =TD!E8/1000 -> 4888.92 | G9: =TD!F8/1000 -> 12119.778 | H9: =O36/1000 -> 15333.647 | I9: =G9-H9 -> -3213.8689 | M9: añadir fecha de corte
B10: Utilidad Neta | C10: =TD!B16/1000 -> -99.037985 | D10: =TD!C16/1000 -> -488.40746 | E10: =TD!D16/1000 -> -201.20764 | F10: =TD!E16/1000 -> 89.7471 | G10: =TD!F16/1000 -> -698.90598 | H10: =O44/1000 -> 572.67244 | I10: =G10-H10 -> -1271.5784 | M10: colocar en power point
B11: Margen Neto % | C11: =C10/C9 -> -0.17540791 | D11: =D10/D9 -> -0.17633155 | E11: =E10/E9 -> -0.051639126 | F11: =F10/F9 -> 0.018357244 | G11: =G10/G9 -> -0.057666566 | H11: =H10/H9 -> 0.037347439 | I11: =G11-H11 -> -0.095014004
B13: PERU FROST - MERLUZA Y PERICO 2026 (MILES US$)
B14: Concepto | C14: 46023 | D14: 46054 | E14: 46082 | F14: 46113 | G14: Acum 2026 | H14: Presupuesto | I14: Variación
B15: TM Materia Prima | H15: 300 | I15: =G15-H15 -> -300
B16: TM Vendidas PT | C16: 0 | D16: 0 | E16: 0 | F16: 0 | G16: 0 | H16: 129 | I16: =G16-H16 -> -129
B17: Venta | C17: 0 | D17: 0 | E17: 0 | F17: 0 | G17: =SUM(C17:F17) -> 0 | H17: =P36/1000 -> 278.3254 | I17: =G17-H17 -> -278.3254
B18: Utilidad Neta | C18: =-7871.79/1000 -> -7.87179 | D18: -13.224 | E18: =-10009.96/1000 -> -10.00996 | F18: -10 | G18: =SUM(C18:F18) -> -41.10575 | H18: =P44/1000 -> 59.37017 | I18: =G18-H18 -> -100.47592 | L18: Merluza
B19: Margen Neto % | H19: =H18/H17 -> 0.21331208 | I19: =G19-H19 -> -0.21331208 | L19: Presupuesto
K20: Venta | L20: 278325.4
B21: PERU FROST - SERVIOS DE CONGELAMIENTO 2026 (MILES US$)
B22: Concepto | C22: 46023 | D22: 46054 | E22: 46082 | F22: 46113 | G22: Acum 2026 | H22: Presupuesto | I22: Variación
B23: Venta | C23: 0 | D23: 0 | E23: 0 | F23: 0 | G23: =SUM(C23:F23) -> 0 | H23: =Q36/1000 -> 333.33333 | I23: =G23-H23 -> -333.33333
B24: Utilidad Neta | C24: 0 | D24: 0 | E24: 0 | F24: 0 | G24: =SUM(C24:F24) -> 0 | H24: =Q44/1000 -> 333.33333 | I24: =G24-H24 -> -333.33333
B25: Margen Neto % | H25: =H24/H23 -> 1 | I25: =G25-H25 -> -1
B27: PERU FROST - MUELLE 2026 (MILES US$)
B28: Concepto | C28: 46023 | D28: 46054 | E28: 46082 | F28: 46113 | G28: Acum 2026 | H28: Presupuesto | I28: Variación
B29: Venta | C29: =45444/3.35/1000 -> 13.565373 | D29: =57239.28/3.4/1000 -> 16.835082 | E29: =54636.38/3.45/1000 -> 15.836632 | F29: =216375.28/3.5/1000 -> 61.821509 | G29: =SUM(C29:F29) -> 108.0586 | H29: =R36/1000 -> 290.90909 | I29: =G29-H29 -> -182.85049
B30: Utilidad Neta | C30: =C29-41.889 -> -28.323627 | D30: =D29-34.4 -> -17.564918 | E30: =E29-53.1 -> -37.263368 | F30: =F29-43 -> 18.821509 | G30: =SUM(C30:F30) -> -64.330404 | H30: =R44/1000 -> 172.42886 | I30: =G30-H30 -> -236.75926
B31: Margen Neto % | H31: =H30/H29 -> 0.59272421 | I31: =G31-H31 -> -0.59272421
B33: PERU FROST - CONSOLIDADO 2026 (MILES US$)
B34: Concepto | C34: 46023 | D34: 46054 | E34: 46082 | F34: 46113 | G34: Acum 2026 | H34: Presupuesto | I34: Variación
B35: TM Materia Prima | C35: =C15+C7 -> 1877.215 | D35: =D15+D7 -> 3149.786 | E35: =E15+E7 -> 2255.518 | F35: =F15+F7 -> 2853.189 | G35: =SUM(C35:F35) -> 10135.708 | H35: =H15+H7 -> 8850 | I35: =G35-H35 -> 1285.708 | O35: Congelados Pota | P35: Merluza | Q35: SS | R35: Muelle | S35: Total
B36: TM Vendidas PT | C36: =C16+C8 -> 248 | D36: =D16+D8 -> 1634.3 | E36: =E16+E8 -> 1995.8 | F36: =F16+F8 -> 2110.11 | G36: =SUM(C36:F36) -> 5988.21 | H36: =H16+H8 -> 5963 | I36: =G36-H36 -> 25.21 | N36: Suma de VALOR CFR | O36: 15333647 | P36: =L20 -> 278325.4 | Q36: 333333.33 | R36: 290909.09 | S36: =SUM(O36:R36) -> 16236215
B37: Venta | C37: =C17+C9+C23+C29 -> 578.18065 | D37: =D17+D9+D23+D29 -> 2786.6596 | E37: =E17+E9+E23+E29 -> 3912.2549 | F37: =F17+F9+F23+F29 -> 4950.7415 | G37: =SUM(C37:F37) -> 12227.837 | H37: =H17+H9+H23+H29 -> 16236.215 | I37: =G37-H37 -> -4008.3781 | N37: Suma de COSTO VENTAS | O37: 12916735 | P37: =L38-4251 -> 194785.42 | Q37: 0 | R37: =L44 -> 118480.23 | S37: =SUM(O37:R37) -> 13230000
B38: Utilidad Neta | C38: =C18+C10+C30 -> -135.2334 | D38: =D18+D10+D30 -> -519.19638 | E38: =E18+E10+E30 -> -248.48096 | F38: =F18+F10+F30 -> 98.568608 | G38: =SUM(C38:F38) -> -804.34213 | H38: =H18+H10+H24+H30 -> 1137.8048 | I38: =G38-H38 -> -1942.1469 | K38: Costo | L38: 199036.42 | N38: Suma de UTILIDAD BRUTA | O38: =O36-O37 -> 2416912.4 | P38: =P36-P37 -> 83539.98 | Q38: =Q36-Q37 -> 333333.33 | R38: =R36-R37 -> 172428.86 | S38: =SUM(O38:R38) -> 3006214.6
B39: Margen Neto % | C39: =C38/C37 -> -0.23389472 | D39: =D38/D37 -> -0.18631496 | E39: =E38/E37 -> -0.06351349 | F39: =F38/F37 -> 0.019909868 | G39: =G38/G37 -> -0.065779594 | H39: =H38/H37 -> 0.070078206 | I39: =G39-H39 -> -0.1358578 | K39: gasto ventas | L39: =L20-L38 -> 79288.98 | N39: Suma de GASTO VENTAS | O39: 1313000 | P39: =1341135.81-O39 -> 28135.81 | R39: 0 | S39: =SUM(O39:R39) -> 1341135.8
N40: Suma de GASTO ADM | O40: 273515.96 | P40: 0 | R40: 0 | S40: =SUM(O40:R40) -> 273515.96
N41: Suma de DRAWBACK | O41: 283276 | P41: =287242-O41 -> 3966 | R41: 0 | S41: =SUM(O41:R41) -> 287242
B42: Venta | C42: =45444/3.35/1000 -> 13.565373 | D42: =57239/3.4/1000 -> 16.835 | E42: =54636.38/3.45/1000 -> 15.836632 | F42: =216375.28/3.5/1000 -> 61.821509 | G42: =SUM(C42:F42) -> 108.05851 | L42: Muelle | N42: Suma de UTILIDAD OPERATIVA | O42: =O38-O39-O40+O41 -> 1113672.4 | P42: =P38-P39-P40+P41 -> 59370.17 | Q42: =Q38-Q39-Q40+Q41 -> 333333.33 | R42: =R38-R39-R40+R41 -> 172428.86 | S42: =SUM(O42:R42) -> 1678804.8
B43: Costos | C43: =49761/1000 -> 49.761 | D43: =47645/1000 -> 47.645 | E43: =63202/1000 -> 63.202 | G43: =SUM(C43:F43) -> 160.608 | K43: Venta | L43: 333333.33 | N43: Suma de GASTO FINANCIERO | O43: 541000 | P43: 0 | R43: 0 | S43: =SUM(O43:R43) -> 541000
B44: Utilidad | C44: =C42-C43 -> -36.195627 | D44: =D42-D43 -> -30.81 | E44: =E42-E43 -> -47.365368 | G44: =G42-G43 -> -52.549486 | K44: Costo | L44: 118480.23 | N44: Suma de UTILIDAD NETA | O44: =O42-O43 -> 572672.44 | P44: =P42-P43 -> 59370.17 | Q44: =Q42-Q43 -> 333333.33 | R44: =R42-R43 -> 172428.86 | S44: =SUM(O44:R44) -> 1137804.8
K45: Utilidad | L45: =L43-L44 -> 214853.1 | N45: Suma de DEPRECIACIÓN | O45: 466666.67
N46: Suma de EBITDA | O46: =O45+O42 -> 1580339.1 | S46: 1137804.5
B48: PERÚ FROST - RESULTADOS CONGELADOS 2026 (EN MILES DE US$)
B50: Concepto | C50: 46023 | D50: 46054 | E50: 46082 | F50: 46113 | G50: Acum Abril
B51: TM Vendidas | C51: 248 | D51: 1634.3 | E51: 1995.8 | F51: 2110.11 | G51: 5988.21
B53: Venta | C53: =I53/1000 -> 564.61528 | D53: =J53/1000 -> 2769.8245 | E53: =K53/1000 -> 3896.4183 | F53: =L53/1000 -> 4888.92 | G53: =M53/1000 -> 12119.778 | I53: 564615.28 | J53: 2769824.5 | K53: 3896418.3 | L53: 4888920 | M53: 12119778
B54: Costo de Ventas | C54: =I54/1000 -> 442.6356 | D54: =J54/1000 -> 2804.315 | E54: =K54/1000 -> 3579.9647 | F54: =L54/1000 -> 4265.647 | G54: =M54/1000 -> 11092.562 | I54: 442635.6 | J54: 2804315 | K54: 3579964.7 | L54: 4265647 | M54: 11092562
B55: Utilidad Bruta | C55: =I55/1000 -> 121.97968 | D55: =J55/1000 -> -34.490515 | E55: =K55/1000 -> 316.45357 | F55: =L55/1000 -> 623.27297 | G55: =M55/1000 -> 1027.2157 | I55: 121979.68 | J55: -34490.515 | K55: 316453.57 | L55: 623272.97 | M55: 1027215.7
B56: Margen Bruto | C56: =C55/C$53 -> 0.21604035 | D56: =D55/D$53 -> -0.012452239 | E56: =E55/E$53 -> 0.081216529 | F56: =F55/F$53 -> 0.12748684 | G56: =G55/G$53 -> 0.084755323
B58: Gasto de Ventas | C58: =I58/1000 -> 54.228385 | D58: =J58/1000 -> 324.52218 | E58: =K58/1000 -> 393.24577 | F58: =L58/1000 -> 438.56902 | G58: =M58/1000 -> 1210.5654 | I58: 54228.385 | J58: 324522.18 | K58: 393245.77 | L58: 438569.02 | M58: 1210565.4
B59: Gasto Adm | C59: =I59/1000 -> 50.659 | D59: =J59/1000 -> 56.604 | E59: =K59/1000 -> 78.579 | F59: =L59/1000 -> 78.579 | G59: =M59/1000 -> 264.421 | I59: 50659 | J59: 56604 | K59: 78579 | L59: 78579 | M59: 264421
B60: Otros Ingresos | C60: =I60/1000 -> 15.12072 | D60: =J60/1000 -> 75.707235 | E60: =K60/1000 -> 108.63657 | F60: =L60/1000 -> 138.09515 | G60: =M60/1000 -> 337.55967 | I60: 15120.72 | J60: 75707.235 | K60: 108636.57 | L60: 138095.15 | M60: 337559.67
B61: Utilidad Operativa | C61: =I61/1000 -> 32.213015 | D61: =J61/1000 -> -339.90946 | E61: =K61/1000 -> -46.734635 | F61: =L61/1000 -> 244.2201 | G61: =M61/1000 -> -110.21098 | I61: 32213.015 | J61: -339909.46 | K61: -46734.635 | L61: 244220.1 | M61: -110210.98
B62: Margen Operativo | C62: =C61/C$53 -> 0.057053035 | D62: =D61/D$53 -> -0.12271877 | E62: =E61/E$53 -> -0.011994255 | F62: =F61/F$53 -> 0.049953793 | G62: =G61/G$53 -> -0.0090934815
B64: Gasto Financiero | C64: =I64/1000 -> 131.251 | D64: =J64/1000 -> 148.498 | E64: =K64/1000 -> 154.473 | F64: =L64/1000 -> 154.473 | G64: =M64/1000 -> 588.695 | I64: 131251 | J64: 148498 | K64: 154473 | L64: 154473 | M64: 588695
B65: UAIR | C65: =I65/1000 -> -99.037985 | D65: =J65/1000 -> -488.40746 | E65: =K65/1000 -> -201.20764 | F65: =L65/1000 -> 89.7471 | G65: =M65/1000 -> -698.90598 | I65: -99037.985 | J65: -488407.46 | K65: -201207.64 | L65: 89747.1 | M65: -698905.98
B66: Mg UAIR | C66: =C65/C$53 -> -0.17540791 | D66: =D65/D$53 -> -0.17633155 | E66: =E65/E$53 -> -0.051639126 | F66: =F65/F$53 -> 0.018357244 | G66: =G65/G$53 -> -0.057666566
B68: Depreciación | C68: =I68/1000 -> 123.53 | D68: =J68/1000 -> 124.15239 | E68: =K68/1000 -> 123.36073 | F68: =L68/1000 -> 123.48435 | G68: =M68/1000 -> 494.52747 | I68: 123530 | J68: 124152.39 | K68: 123360.73 | L68: 123484.35 | M68: 494527.47
B69: EBITDA | C69: =I69/1000 -> 155.74302 | D69: =J69/1000 -> -215.75706 | E69: =K69/1000 -> 76.626094 | F69: =L69/1000 -> 367.70445 | G69: =M69/1000 -> 384.3165 | I69: 155743.02 | J69: -215757.06 | K69: 76626.094 | L69: 367704.45 | M69: 384316.5
B70: Mg EBITDA | C70: =C69/C$53 -> 0.27583918 | D70: =D69/D$53 -> -0.077895572 | E70: =E69/E$53 -> 0.019665777 | F70: =F69/F$53 -> 0.075211795 | G70: =G69/G$53 -> 0.031709862
B73: PERÚ FROST - RESULTADOS CONSOLIDADOS 2026 (EN MILES DE US$)
B75: Concepto | C75: 46023 | D75: 46054 | E75: 46082 | F75: 46113 | G75: Acum Abril
B76: TM Vendidas | C76: 248 | D76: 1634.3 | E76: 1995.8 | F76: 2110.11 | G76: 5988.21
B78: Venta | C78: =C53+C17+C29 -> 578.18065 | D78: =D53+D17+D29 -> 2786.6596 | E78: =E53+E17+E29 -> 3912.2549 | F78: =F53+F17+F29 -> 4950.7415 | G78: =SUM(C78:F78) -> 12227.837
B79: Costo de Ventas | C79: =C54-C18+41.88 -> 492.38739 | D79: =D54-D18+(D29+D30)+35.1298352941174 -> 2851.939 | E79: =E54-E18+(E29+E30)+74.5267362318833 -> 3643.0747 | F79: =F54-F18+(F29+F30)-37.6430171428565 -> 4318.647 | G79: =SUM(C79:F79) -> 11306.048 | J79: =G78-G79-G83-G84+G85 -> -215.63813
B80: Utilidad Bruta | C80: =C78-C79 -> 85.793263 | D80: =D78-D79 -> -65.279433 | E80: =E78-E79 -> 269.18024 | F80: =F78-F79 -> 632.09448 | G80: =SUM(C80:F80) -> 921.78855 | J80: =J79-G89 -> -804.33313
B81: Margen Bruto | C81: =C80/C$53 -> 0.15194995 | D81: =D80/D$53 -> -0.023568076 | E81: =E80/E$53 -> 0.06908402 | F81: =F80/F$53 -> 0.12929123 | G81: =G80/G$53 -> 0.076056553 | J81: =G86+G93 -> 278.88934
B83: Gasto de Ventas | C83: =C58 -> 54.228385 | D83: =D58 -> 324.52218 | E83: =E58 -> 393.24577 | F83: =F58 -> 438.56902 | G83: =SUM(C83:F83) -> 1210.5654
B84: Gasto Adm | C84: =C59 -> 50.659 | D84: =D59 -> 56.604 | E84: =E59 -> 78.579 | F84: =F59 -> 78.579 | G84: =SUM(C84:F84) -> 264.421
B85: Otros Ingresos | C85: =C60 -> 15.12072 | D85: =D60 -> 75.707235 | E85: =E60 -> 108.63657 | F85: =F60 -> 138.09515 | G85: =SUM(C85:F85) -> 337.55967
B86: Utilidad Operativa | C86: =C80-C83-C84+C85 -> -3.9734015 | D86: =D80-D83-D84+D85 -> -370.69838 | E86: =E80-E83-E84+E85 -> -94.007963 | F86: =F80-F83-F84+F85 -> 253.04161 | G86: =SUM(C86:F86) -> -215.63813
B87: Margen Operativo | C87: =C86/C$53 -> -0.0070373609 | D87: =D86/D$53 -> -0.13383461 | E87: =E86/E$53 -> -0.024126764 | F87: =F86/F$53 -> 0.051758181 | G87: =G86/G$53 -> -0.017792251
B89: Gasto Financiero | C89: =C64 -> 131.251 | D89: =D64 -> 148.498 | E89: =E64 -> 154.473 | F89: =F64 -> 154.473 | G89: =SUM(C89:F89) -> 588.695
B90: UAIR | C90: =C86-C89 -> -135.2244 | D90: =D86-D89 -> -519.19638 | E90: =E86-E89 -> -248.48096 | F90: =F86-F89 -> 98.568608 | G90: =SUM(C90:F90) -> -804.33313
B91: Mg UAIR | C91: =C90/C$53 -> -0.2394983 | D91: =D90/D$53 -> -0.18744739 | E91: =E90/E$53 -> -0.063771634 | F91: =F90/F$53 -> 0.020161632 | G91: =G90/G$53 -> -0.066365335
B93: Depreciación | C93: =C68 -> 123.53 | D93: =D68 -> 124.15239 | E93: =E68 -> 123.36073 | F93: =F68 -> 123.48435 | G93: =SUM(C93:F93) -> 494.52747
B94: EBITDA | C94: =C93+C86 -> 119.5566 | D94: =D93+D86 -> -246.54598 | E94: =E93+E86 -> 29.352766 | F94: =F93+F86 -> 376.52596 | G94: =SUM(C94:F94) -> 278.88934
B95: Mg EBITDA | C95: =C94/C$53 -> 0.21174878 | D95: =D94/D$53 -> -0.089011409 | E95: =E94/E$53 -> 0.0075332687 | F95: =F94/F$53 -> 0.077016183 | G95: =G94/G$53 -> 0.023011093
C98: =C78-C37 -> 0 | D98: =D78-D37 -> 0 | E98: =E78-E37 -> 0 | F98: =F78-F37 -> 0
C99: =C90-C38 -> 0.009 | D99: =D90-D38 -> 0 | E99: =E90-E38 -> 0 | F99: =F90-F38 -> 0
C100: 0.009 | D100: 35.129835 | E100: 74.526736 | F100: -37.643017

Sheet TD
N1: Real | O1: Budget | P1: Var
A2: ANÁLISIS DE RENTABILIDAD | M2: Precio Compra MP por TM | N2: =3024.94326918258/3.4 -> 889.6892 | O2: 1119 | P2: =N2/O2-1 -> -0.20492476
M3: Ratio Costo / Compra | N3: =N9/N2 -> 2.0820758 | O3: =O9/O2 -> 1.9865383 | P3: =N3/O3-1 -> 0.04809244
A4: EEFF PERU FROST (USD) | M4: Ratio Precio / Costo | N4: =N8/N2 -> 2.2748844 | O4: =O8/O2 -> 2.3488157 | P4: =N4/O4-1 -> -0.031476018 | AD4: Enero | AE4: Febrero | AF4: Marzo | AG4: Abril | AH4: Real | AI4: Presupuesto
B5: Etiquetas de columna | I5: ANÁLISIS UNITARIO | P5: =P3-P4 -> 0.079568458 | R5: ANÁLISIS VÉRTICAL | AC5: Venta CFR | AD5: =B8/1000 -> 564.61528 | AE5: =C8/1000 -> 2769.8245 | AF5: =D8/1000 -> 3896.4183 | AG5: =E8/1000 -> 4888.92 | AH5: =F8/1000 -> 12119.778 | AI5: =G8/1000 -> 15333.647
A6: Valores | B6: ENERO | C6: FEBRERO | D6: MARZO | E6: ABRIL | F6: Total general | G6: Budget | H6: Var | I6: NOMBRE | J6: ENERO | K6: FEBRERO | L6: MARZO | M6: ABRIL | N6: TOTAL | O6: Budget | R6: NOMBRE | S6: ENERO | T6: FEBRERO | U6: MARZO | V6: ABRIL | W6: TOTAL | X6: Budget | AC6: Utilidad Neta | AD6: =B16/1000 -> -99.037985 | AE6: =C16/1000 -> -488.40746 | AF6: =D16/1000 -> -201.20764 | AG6: =E16/1000 -> 89.7471 | AH6: =F16/1000 -> -698.90598 | AI6: =G16/1000 -> 520.036
A7: Suma de Cantidad | B7: 248 | C7: 1634.3 | D7: 1995.8 | E7: 2110.11 | F7: 5988.21 | G7: 5834 | H7: =(F7-G7)/G7 -> 0.026432979
A8: Suma de VALOR CFR | B8: 564615.28 | C8: 2769824.5 | D8: 3896418.3 | E8: 4888920 | F8: 12119778 | G8: 15333647 | H8: =(F8-G8)/G8 -> -0.20959586 | I8: Suma de VALOR CFR | J8: =B8/B$7 -> 2276.6745 | K8: =C8/C$7 -> 1694.8079 | L8: =D8/D$7 -> 1952.309 | M8: =E8/E$7 -> 2316.9029 | N8: =F8/F$7 -> 2023.9401 | O8: =G8/G$7 -> 2628.3248 | R8: Suma de VALOR CFR | S8: =B8/B$8 -> 1 | T8: =C8/C$8 -> 1 | U8: =D8/D$8 -> 1 | V8: =E8/E$8 -> 1 | W8: =F8/F$8 -> 1 | X8: =G8/G$8 -> 1
A9: Suma de COSTO VENTAS | B9: 442635.6 | C9: 2804315 | D9: 3579964.7 | E9: 4265647 | F9: 11092562 | G9: 12968611 | H9: =(F9-G9)/G9 -> -0.14466072 | I9: Suma de COSTO VENTAS | J9: =B9/B$7 -> 1784.821 | K9: =C9/C$7 -> 1715.912 | L9: =D9/D$7 -> 1793.7492 | M9: =E9/E$7 -> 2021.5283 | N9: =F9/F$7 -> 1852.4004 | O9: =G9/G$7 -> 2222.9364 | R9: Suma de COSTO VENTAS | S9: =B9/B$8 -> 0.78395965 | T9: =C9/C$8 -> 1.0124522 | U9: =D9/D$8 -> 0.91878347 | V9: =E9/E$8 -> 0.87251316 | W9: =F9/F$8 -> 0.91524468 | X9: =G9/G$8 -> 0.84576168 | AK9: Resumen de Precios por TM Peru Frost vs Mercado
A10: Suma de UTILIDAD BRUTA | B10: 121979.68 | C10: -34490.515 | D10: 316453.57 | E10: 623272.97 | F10: 1027215.7 | G10: =G8-G9 -> 2365036 | H10: =(F10-G10)/G10 -> -0.56566593 | I10: Suma de UTILIDAD BRUTA | J10: =B10/B$7 -> 491.85355 | K10: =C10/C$7 -> -21.104152 | L10: =D10/D$7 -> 158.55976 | M10: =E10/E$7 -> 295.37463 | N10: =F10/F$7 -> 171.53969 | O10: =G10/G$7 -> 405.38841 | R10: Suma de UTILIDAD BRUTA | S10: =B10/B$8 -> 0.21604035 | T10: =C10/C$8 -> -0.012452239 | U10: =D10/D$8 -> 0.081216529 | V10: =E10/E$8 -> 0.12748684 | W10: =F10/F$8 -> 0.084755323 | X10: =G10/G$8 -> 0.15423832 | AC10: Acum Abril venta y rentabilidad por producto
A11: Suma de GASTO VENTAS | B11: 54228.385 | C11: 324522.18 | D11: 393245.77 | E11: 438569.02 | F11: 1210565.4 | G11: 1313000 | H11: =(F11-G11)/G11 -> -0.078015725 | I11: Suma de GASTO VENTAS | J11: =B11/B$7 -> 218.66284 | K11: =C11/C$7 -> 198.56953 | L11: =D11/D$7 -> 197.03666 | M11: =E11/E$7 -> 207.84178 | N11: =F11/F$7 -> 202.15813 | O11: =G11/G$7 -> 225.05999 | R11: Suma de GASTO VENTAS | S11: =B11/B$8 -> 0.096044841 | T11: =C11/C$8 -> 0.11716344 | U11: =D11/D$8 -> 0.10092494 | V11: =E11/E$8 -> 0.089706728 | W11: =F11/F$8 -> 0.099883459 | X11: =G11/G$8 -> 0.085628683 | AD11: Venta CFR | AE11: Utilidad Neta | AK11: PRODUCTO | AL11: PERU FROST | AM11: INDUSTRIA PERUANA
A12: Suma de GASTO ADM | B12: 50659 | C12: 56604 | D12: 78579 | E12: 78579 | F12: 264421 | G12: 274000 | H12: =(F12-G12)/G12 -> -0.034959854 | I12: Suma de GASTO ADM | J12: =B12/B$7 -> 204.27016 | K12: =C12/C$7 -> 34.635012 | L12: =D12/D$7 -> 39.372182 | M12: =E12/E$7 -> 37.239291 | N12: =F12/F$7 -> 44.156935 | O12: =G12/G$7 -> 46.966061 | R12: Suma de GASTO ADM | S12: =B12/B$8 -> 0.089723041 | T12: =C12/C$8 -> 0.020435952 | U12: =D12/D$8 -> 0.020166983 | V12: =E12/E$8 -> 0.016072875 | W12: =F12/F$8 -> 0.021817314 | X12: =G12/G$8 -> 0.0178692 | AC12: FILETE CONGELADO | AD12: 3148.23 | AE12: -1138.4306 | AK12: FILETE CONGELADO | AL12: 1323 | AM12: 1525
A13: Suma de DRAWBACK | B13: 15120.72 | C13: 75707.235 | D13: 108636.57 | E13: 138095.15 | F13: 337559.67 | G13: 283000 | H13: =(F13-G13)/G13 -> 0.19279036 | I13: Suma de DRAWBACK | J13: =B13/B$7 -> 60.970645 | K13: =C13/C$7 -> 46.323952 | L13: =D13/D$7 -> 54.432593 | M13: =E13/E$7 -> 65.444526 | N13: =F13/F$7 -> 56.370714 | O13: =G13/G$7 -> 48.508742 | R13: Suma de DRAWBACK | S13: =B13/B$8 -> 0.026780572 | T13: =C13/C$8 -> 0.027332864 | U13: =D13/D$8 -> 0.027881136 | V13: =E13/E$8 -> 0.028246555 | W13: =F13/F$8 -> 0.027851968 | X13: =G13/G$8 -> 0.018456144 | AC13: REJOS CONGELADOS | AD13: 2631.849 | AE13: 311.25595 | AK13: FILETE DARUMA | AL13: 3292 | AM13: 3417
A14: Suma de UTILIDAD OPERATIVA | B14: 32213.015 | C14: -339909.46 | D14: -46734.635 | E14: 244220.1 | F14: -110210.98 | G14: =G10-G11-G12+G13 -> 1061036 | H14: =(F14-G14)/G14 -> -1.1038711 | I14: Suma de UTILIDAD OPERATIVA | J14: =B14/B$7 -> 129.89119 | K14: =C14/C$7 -> -207.98474 | L14: =D14/D$7 -> -23.416492 | M14: =E14/E$7 -> 115.73809 | N14: =F14/F$7 -> -18.404661 | O14: =G14/G$7 -> 181.8711 | R14: Suma de UTILIDAD OPERATIVA | S14: =B14/B$8 -> 0.057053035 | T14: =C14/C$8 -> -0.12271877 | U14: =D14/D$8 -> -0.011994255 | V14: =E14/E$8 -> 0.049953793 | W14: =F14/F$8 -> -0.0090934815 | X14: =G14/G$8 -> 0.069196584 | AC14: ALAS CONGELADAS | AD14: 2273.427 | AE14: -451.32788 | AK14: REPRODUCTOR | AL14: 2724 | AM14: 2704
A15: Suma de GASTO FINANCIERO | B15: 131251 | C15: 148498 | D15: 154473 | E15: 154473 | F15: 588695 | G15: 541000 | H15: =(F15-G15)/G15 -> 0.088160813 | I15: Suma de GASTO FINANCIERO | J15: =B15/B$7 -> 529.2379 | K15: =C15/C$7 -> 90.863367 | L15: =D15/D$7 -> 77.399038 | M15: =E15/E$7 -> 73.206136 | N15: =F15/F$7 -> 98.309011 | O15: =G15/G$7 -> 92.732259 | R15: Suma de GASTO FINANCIERO | S15: =B15/B$8 -> 0.23246094 | T15: =C15/C$8 -> 0.053612783 | U15: =D15/D$8 -> 0.039644871 | V15: =E15/E$8 -> 0.031596549 | W15: =F15/F$8 -> 0.048573084 | X15: =G15/G$8 -> 0.035281887 | AC15: FILETE DARUMA | AD15: 1927.8 | AE15: 513.07693 | AK15: NUCA | AL15: 1123 | AM15: 1171
A16: Suma de UTILIDAD NETA | B16: -99037.985 | C16: -488407.46 | D16: -201207.64 | E16: 89747.1 | F16: -698905.98 | G16: =G14-G15 -> 520036 | H16: =(F16-G16)/G16 -> -2.3439569 | I16: Suma de UTILIDAD NETA | J16: =B16/B$7 -> -399.34671 | K16: =C16/C$7 -> -298.8481 | L16: =D16/D$7 -> -100.81553 | M16: =E16/E$7 -> 42.531953 | N16: =F16/F$7 -> -116.71367 | O16: =G16/G$7 -> 89.138841 | R16: Suma de UTILIDAD NETA | S16: =B16/B$8 -> -0.17540791 | T16: =C16/C$8 -> -0.17633155 | U16: =D16/D$8 -> -0.051639126 | V16: =E16/E$8 -> 0.018357244 | W16: =F16/F$8 -> -0.057666566 | X16: =G16/G$8 -> 0.033914698 | AC16: REPRODUCTORES | AD16: 599.405 | AE16: 126.98725 | AK16: ALAS COCIDAS | AL16: 3240 | AM16: 3318
A17: Suma de DEPRECIACIÓN | B17: 123530 | C17: 124152.39 | D17: 123360.73 | E17: 123484.35 | F17: 494527.47 | G17: 466666.67 | H17: =(F17-G17)/G17 -> 0.059701728 | I17: Suma de DEPRECIACIÓN | J17: =B17/B$7 -> 498.10484 | K17: =C17/C$7 -> 75.96671 | L17: =D17/D$7 -> 61.810166 | M17: =E17/E$7 -> 58.520338 | N17: =F17/F$7 -> 82.583522 | O17: =G17/G$7 -> 79.990858 | R17: Suma de DEPRECIACIÓN | S17: =B17/B$8 -> 0.21878614 | T17: =C17/C$8 -> 0.044823199 | U17: =D17/D$8 -> 0.031660032 | V17: =E17/E$8 -> 0.025258002 | W17: =F17/F$8 -> 0.040803344 | X17: =G17/G$8 -> 0.03043416 | AC17: NUCAS | AD17: 514.83 | AE17: -431.34411 | AK17: ALAS CONGELADAS | AL17: 1509 | AM17: 1579
A18: Suma de EBITDA | B18: 155743.02 | C18: -215757.06 | D18: 76626.094 | E18: 367704.45 | F18: 384316.5 | G18: =G17+G14 -> 1527702.7 | H18: =(F18-G18)/G18 -> -0.74843502 | I18: Suma de EBITDA | J18: =B18/B$7 -> 627.99603 | K18: =C18/C$7 -> -132.01803 | L18: =D18/D$7 -> 38.393674 | M18: =E18/E$7 -> 174.25843 | N18: =F18/F$7 -> 64.178861 | O18: =G18/G$7 -> 261.86196 | R18: Suma de EBITDA | S18: =B18/B$8 -> 0.27583918 | T18: =C18/C$8 -> -0.077895572 | U18: =D18/D$8 -> 0.019665777 | V18: =E18/E$8 -> 0.075211795 | W18: =F18/F$8 -> 0.031709862 | X18: =G18/G$8 -> 0.099630745 | AC18: ALAS COCIDAS | AD18: 384.2577 | AE18: 138.02447 | AK18: TENTACULO | AL18: 2290 | AM18: 2288
A19: EBITDA NETO | B19: =B16+B17 -> 24492.015 | C19: =C16+C17 -> -364255.06 | D19: =D16+D17 -> -77846.906 | E19: =E16+E17 -> 213231.45 | F19: =F16+F17 -> -204378.5 | G19: =G16+G17 -> 986702.67 | H19: =(F19-G19)/G19 -> -1.2071328 | AC19: OTROS | AD19: =SUM(AD20:AD25) -> 639.97939 | AE19: =SUM(AE20:AE25) -> 232.85204
N20: Budget Aprob | O20: Budget Meta | AC20: POTA CONOS | AD20: 231.72 | AE20: 0.42290479
M21: CIF total | N21: 3400000 | O21: 3400000 | AC21: POTA MEMBRANA PRECOCIDA | AD21: 128.90625 | AE21: 66.439886
M22: tm MP | N22: 16000 | O22: 22500 | AC22: POTA TELILLA PRECOCIDA | AD22: 90.80625 | AE22: 36.286582 | AO22: % FOB
M23: tm PT | N23: 10975 | O23: 16500 | AC23: POTA RECORTES COCIDOS | AD23: 67.5 | AE23: 15.71277 | AO23: 0.0692
M24: cif x tm | N24: =N21/N23 -> 309.79499 | O24: =O21/O23 -> 206.06061 | AC24: POTA SUCKERS CONGELADO | AD24: 30.25 | AE24: 23.193002 | AO24: 0.0637
A25: ANÁLISIS POR PRODUCTO | AC25: RESIDUOS DE POTA | AD25: 90.79689 | AE25: 90.79689 | AO25: 0.0634
AO26: 0.0478
A27: RANKING DE VENTAS (USD) | I27: UTILIDAD NETA (USD) | R27: EBITDA (USD) | AC27: Acum Abril venta y rentabilidad por cliente | AO27: 0.0459
A28: Suma de VALOR CFR | B28: Etiquetas de columna | I28: Suma de UTILIDAD NETA | J28: Etiquetas de columna | R28: Suma de EBITDA | S28: Etiquetas de columna | AD28: Venta CFR | AE28: Utilidad Neta | AO28: 0.0371
A29: Etiquetas de fila | B29: ENERO | C29: FEBRERO | D29: MARZO | E29: ABRIL | F29: Total general | G29: % | I29: Etiquetas de fila | J29: ENERO | K29: FEBRERO | L29: MARZO | M29: ABRIL | N29: Total general | O29: MG | R29: Etiquetas de fila | S29: ENERO | T29: FEBRERO | U29: MARZO | V29: ABRIL | W29: Total general | X29: MG | AC29: TSUJINO | AD29: 2790.273 | AE29: -709.0403 | AO29: 0.0337
A30: POTA FILETE CONGELADO | B30: 94800 | C30: 1147500 | D30: 430960 | E30: 1474970 | F30: 3148230 | G30: =E30/$E$43 -> 0.30169649 | I30: POTA FILETE CONGELADO | J30: -36814.029 | K30: -511210.58 | L30: -139940.29 | M30: -450465.71 | N30: -1138430.6 | O30: =N30/F30 -> -0.36160973 | R30: POTA FILETE CONGELADO | S30: 12498.423 | T30: -376073.28 | U30: -99151.993 | V30: -343912.16 | W30: -806639.02 | X30: =W30/F30 -> -0.25621985 | AC30: LONGKOU JIABAO AQUATIC | AD30: 1406.7 | AE30: 394.79634 | AO30: 0.0337
A31: POTA REJOS CONGELADOS | B31: 149248 | C31: 532695 | D31: 779600 | E31: 1170306 | F31: 2631849 | G31: =E31/$E$43 -> 0.23937925 | I31: POTA REJOS CONGELADOS | J31: -6695.1747 | K31: 112709.73 | L31: 122378.78 | M31: 82862.605 | N31: 311255.95 | O31: =N31/F31 -> 0.11826512 | R31: POTA REJOS CONGELADOS | S31: 52849.611 | T31: 147578.49 | U31: 168457.03 | V31: 143317.15 | W31: 512202.29 | X31: =W31/F31 -> 0.1946169 | AC31: KULALIA | AD31: 1378.9217 | AE31: 101.0003 | AO31: 0.0333
A32: POTA ALAS CONGELADAS | B32: 135915 | C32: 710550 | D32: 768480 | E32: 658482 | F32: 2273427 | G32: =E32/$E$43 -> 0.13468864 | I32: POTA ALAS CONGELADAS | J32: -51769.093 | K32: -165345.58 | L32: -132907.65 | M32: -101305.56 | N32: -451327.88 | O32: =N32/F32 -> -0.19852315 | R32: POTA ALAS CONGELADAS | S32: 22199.584 | T32: -88717.727 | U32: -65697.444 | V32: -56041.712 | W32: -188257.3 | X32: =W32/F32 -> -0.082807717 | AC32: AVANCE GROUP | AD32: 1097.2 | AE32: -468.13754 | AO32: 0.0333
A33: POTA FILETE DARUMA | C33: 91800 | D33: 1004400 | E33: 831600 | F33: 1927800 | G33: =E33/$E$43 -> 0.17009892 | I33: POTA FILETE DARUMA | K33: 29126.229 | L33: 185279.47 | M33: 298671.23 | N33: 513076.93 | O33: =N33/F33 -> 0.26614635 | R33: POTA FILETE DARUMA | T33: 33630.806 | U33: 230383.25 | V33: 327124.15 | W33: 591138.2 | X33: =W33/F33 -> 0.30663876 | AC33: FOOD & BEVERAGES TRADERS | AD33: 935.406 | AE33: -74.238541 | AO33: 0.032
A34: POTA REPRODUCTORES | B34: 74064 | C34: 77585 | D34: 139200 | E34: 308556 | F34: 599405 | G34: =E34/$E$43 -> 0.063113326 | I34: POTA REPRODUCTORES | J34: 2979.6903 | K34: 20669.556 | L34: 34424.877 | M34: 68913.124 | N34: 126987.25 | O34: =N34/F34 -> 0.2118555 | R34: POTA REPRODUCTORES | S34: 29690.602 | T34: 25174.132 | U34: 41524.546 | V34: 82586.332 | W34: 178975.61 | X34: =W34/F34 -> 0.29858879 | AC34: Qingdao Haiyujia | AD34: 595.782 | AE34: 101.96621 | AO34: 0.0318
A35: POTA NUCAS | B35: 35874 | C35: 23456 | D35: 455500 | F35: 514830 | G35: =E35/$E$43 -> 0 | I35: POTA NUCAS | J35: -20865.234 | K35: -6749.602 | L35: -403729.28 | N35: -431344.11 | O35: =N35/F35 -> -0.83783795 | R35: POTA ALAS COCIDAS | U35: 78707.593 | V35: 73828.848 | W35: 152536.44 | X35: =W35/F35 -> 0.29628507 | AC35: Longkou Yunfeng Aquatic Food | AD35: 575.1 | AE35: -44.789183 | AO35: 0.0316
A36: POTA ALAS COCIDAS | D36: 177221.7 | E36: 207036 | F36: 384257.7 | G36: =E36/$E$43 -> 0.042348003 | I36: POTA ALAS COCIDAS | L36: 71190.296 | M36: 66834.173 | N36: 138024.47 | O36: =N36/F36 -> 0.35919766 | R36: POTA CONOS | S36: 14467.801 | T36: 17395.748 | U36: 12064.775 | V36: -3574.5429 | W36: 40353.781 | X36: =W36/F36 -> 0.1050175 | AC36: OTROS | AD36: =SUM(AD37:AD51) -> 3340.3954 | AE36: =SUM(AE37:AE51) -> -0.46326558 | AO36: 0.0302
A37: POTA CONOS | B37: 50400 | C37: 69000 | D37: 76800 | E37: 35520 | F37: 231720 | G37: =E37/$E$43 -> 0.0072654083 | I37: POTA CONOS | J37: -10188.424 | K37: 11727.466 | L37: 5382.7333 | M37: -6498.8706 | N37: 422.90479 | O37: =N37/F37 -> 0.0018250681 | R37: POTA MEMBRANA PRECOCIDA | T37: -5368.3017 | U37: 34015.461 | V37: 49513.772 | W37: 78160.931 | X37: =W37/F37 -> 0.33730766 | AC37: OVERSEA | AD37: 354.595 | AE37: 86.215827 | AO37: 0.03
A38: POTA MEMBRANA PRECOCIDA | C38: 38606.25 | D38: 37800 | E38: 52500 | F38: 128906.25 | G38: =E38/$E$43 -> 0.010738568 | I38: POTA MEMBRANA PRECOCIDA | K38: -9872.8783 | L38: 30256.812 | M38: 46055.952 | N38: 66439.886 | O38: =N38/F38 -> 0.51541245 | R38: POTA TELILLA PRECOCIDA | T38: -4983.2234 | V38: 49212.443 | W38: 44229.22 | X38: =W38/F38 -> 0.34311152 | AC38: Pesciro Asia International LTD. | AD38: 352.35 | AE38: -117.23253
A39: POTA TELILLA PRECOCIDA | C39: 38606.25 | E39: 52200 | F39: 90806.25 | G39: =E39/$E$43 -> 0.010677205 | I39: POTA TELILLA PRECOCIDA | K39: -9487.8 | M39: 45774.382 | N39: 36286.582 | O39: =N39/F39 -> 0.39960446 | R39: POTA RECORTES COCIDOS | V39: 19269.385 | W39: 19269.385 | X39: =W39/F39 -> 0.21220329 | AC39: OCEANUS FISH | AD39: 340.564 | AE39: -36.175426
A40: POTA RECORTES COCIDOS | E40: 67500 | F40: 67500 | G40: =E40/$E$43 -> 0.01380673 | I40: POTA RECORTES COCIDOS | M40: 15712.77 | N40: 15712.77 | O40: =N40/F40 -> 0.23278178 | R40: POTA SUCKERS CONGELADO | V40: 26380.783 | W40: 26380.783 | X40: =W40/F40 -> 0.39082641 | AC40: LONGKOU BOHAI | AD40: 334.8 | AE40: 61.759822
A41: POTA SUCKERS CONGELADO | E41: 30250 | F41: 30250 | G41: =E41/$E$43 -> 0.0061874606 | I41: POTA SUCKERS CONGELADO | M41: 23193.002 | N41: 23193.002 | O41: =N41/F41 -> 0.76671082 | R41: RESIDUOS DE POTA | S41: 24314.28 | T41: 40026 | U41: 26456.61 | W41: 90796.89 | X41: =W41/F41 -> 3.0015501 | AC41: GLOBAL OCEAN | AD41: 285.485 | AE41: 31.414281
A42: RESIDUOS DE POTA | B42: 24314.28 | C42: 40026 | D42: 26456.61 | F42: 90796.89 | G42: =E42/$E$43 -> 0 | I42: RESIDUOS DE POTA | J42: 24314.28 | K42: 40026 | L42: 26456.61 | N42: 90796.89 | O42: =N42/F42 -> 1 | R42: POTA NUCAS | S42: -277.28576 | T42: -4419.7036 | U42: -350133.73 | W42: -354830.72 | X42: =W42/F42 -> -3.9079612 | AC42: DAIRECK S.A. | AD42: 280.782 | AE42: -291.00909
A43: Total general | B43: 564615.28 | C43: 2769824.5 | D43: 3896418.3 | E43: 4888920 | F43: 12119778 | G43: =E43/$E$43 -> 1 | I43: Total general | J43: -99037.985 | K43: -488407.46 | L43: -201207.64 | M43: 89747.1 | N43: -698905.98 | O43: =N43/F43 -> -0.057666566 | R43: Total general | S43: 155743.02 | T43: -215757.06 | U43: 76626.094 | V43: 367704.45 | W43: 384316.5 | X43: =W43/F43 -> 0.031709862 | AC43: YANTAI TAIXI FOODSTUFF | AD43: 279.504 | AE43: 19.044143
AC44: Longkou Yunfeng Aquatic | AD44: 260.55 | AE44: -18.026458
AC45: SHANDONG SHEENIER | AD45: 216 | AE45: 36.600276
AC46: Hunan Jinyueyang | AD46: 181.9125 | AE46: 72.469656
A47: ANÁLISIS POR CLIENTE | AC47: GOLDEN SEAFOOD | AD47: 151.256 | AE47: 31.632905
AC48: SACRAMENTO CO., LTD | AD48: 91.8 | AE48: 29.126229
A49: RANKING DE VENTAS (USD) | I49: UTILIDAD NETA (USD) | R49: EBITDA (USD) | AC49: PROVEEDORA DE PRODUCTOS MARINOS | AD49: 90.79689 | AE49: 90.79689
A50: Suma de VALOR CFR | B50: Etiquetas de columna | I50: Suma de UTILIDAD NETA | J50: Etiquetas de columna | O50: MG | R50: Suma de EBITDA | S50: Etiquetas de columna | X50: MG | AC50: Shenzhen Yueshi | AD50: 81 | AE50: 18.351483
A51: Etiquetas de fila | B51: ENERO | C51: FEBRERO | D51: MARZO | E51: ABRIL | F51: Total general | G51: % | I51: Etiquetas de fila | J51: ENERO | K51: FEBRERO | L51: MARZO | M51: ABRIL | N51: Total general | O51: NETO | R51: Etiquetas de fila | S51: ENERO | T51: FEBRERO | U51: MARZO | V51: ABRIL | W51: Total general | X51: EBITDA | AC51: Pesciro SL | AD51: 39 | AE51: -15.431273
A52: TSUJINO | B52: 281115 | C52: 438056 | D52: 1104330 | E52: 966772 | F52: 2790273 | G52: =F52/$F$74 -> 0.23022476 | I52: TSUJINO | J52: -98771.546 | K52: -59882.787 | L52: -270113.95 | M52: -280272.02 | N52: -709040.3 | O52: =N52/F52 -> -0.25411144 | R52: TSUJINO | S52: 49165.809 | T52: -15847.995 | U52: -169493.54 | V52: -209176.6 | W52: -345352.33 | X52: =W52/F52 -> -0.12377009
A53: LONGKOU JIABAO AQUATIC | D53: 669600 | E53: 737100 | F53: 1406700 | G53: =F53/$F$74 -> 0.11606648 | I53: LONGKOU JIABAO AQUATIC | L53: 123519.64 | M53: 271276.7 | N53: 394796.34 | O53: =N53/F53 -> 0.28065426 | R53: LONGKOU JIABAO AQUATIC | U53: 153588.83 | V53: 296173 | W53: 449761.84 | X53: =W53/F53 -> 0.31972833
A54: KULALIA | C54: 390000 | D54: 813921.7 | E54: 175000 | F54: 1378921.7 | G54: =F54/$F$74 -> 0.1137745 | I54: KULALIA | K54: 77091.125 | L54: 161494.5 | M54: -137585.32 | N54: 101000.3 | O54: =N54/F54 -> 0.073245857 | R54: KULALIA | T54: 103117.57 | U54: 207572.75 | V54: -121119.51 | W54: 189570.8 | X54: =W54/F54 -> 0.13747757
A55: AVANCE GROUP | C55: 1066950 | E55: 30250 | F55: 1097200 | G55: =F55/$F$74 -> 0.09052971 | I55: AVANCE GROUP | K55: -491330.54 | M55: 23193.002 | N55: -468137.54 | O55: =N55/F55 -> -0.42666564 | R55: AVANCE GROUP | T55: -360647.77 | V55: 26380.783 | W55: -334266.99 | X55: =W55/F55 -> -0.30465457
A56: FOOD & BEVERAGES TRADERS | C56: 222750 | E56: 712656 | F56: 935406 | G56: =F56/$F$74 -> 0.077180126 | I56: FOOD & BEVERAGES TRADERS | K56: -72081.694 | M56: -2156.8463 | N56: -74238.541 | O56: =N56/F56 -> -0.079365046 | R56: FOOD & BEVERAGES TRADERS | T56: -49558.811 | V56: 36958.013 | W56: -12600.799 | X56: =W56/F56 -> -0.013470941
A57: Qingdao Haiyujia | E57: 595782 | F57: 595782 | G57: =F57/$F$74 -> 0.049157831 | I57: Qingdao Haiyujia | M57: 101966.21 | N57: 101966.21 | O57: =N57/F57 -> 0.17114685 | R57: Qingdao Haiyujia | V57: 130348 | W57: 130348 | X57: =W57/F57 -> 0.21878472
A58: Longkou Yunfeng Aquatic Food | E58: 575100 | F58: 575100 | G58: =F58/$F$74 -> 0.047451364 | I58: Longkou Yunfeng Aquatic Food | M58: -44789.183 | N58: -44789.183 | O58: =N58/F58 -> -0.077880687 | R58: Longkou Yunfeng Aquatic Food | V58: -9223.0351 | W58: -9223.0351 | X58: =W58/F58 -> -0.016037272
A59: OVERSEA | C59: 142695 | D59: 135200 | E59: 76700 | F59: 354595 | G59: =F59/$F$74 -> 0.029257549 | I59: OVERSEA | K59: 35618.606 | L59: 34077.974 | M59: 16519.246 | N59: 86215.827 | O59: =N59/F59 -> 0.24313887 | R59: Pesciro Asia International LTD. | U59: -83404.692 | W59: -83404.692 | X59: =W59/F59 -> -0.23521114
A60: Pesciro Asia International LTD. | D60: 352350 | F60: 352350 | G60: =F60/$F$74 -> 0.029072314 | I60: Pesciro Asia International LTD. | L60: -117232.53 | N60: -117232.53 | O60: =N60/F60 -> -0.33271613 | R60: OVERSEA | T60: 44460.923 | U60: 41316.852 | V60: 19944.135 | W60: 105721.91 | X60: =W60/F60 -> 0.30004799
A61: OCEANUS FISH | B61: 74064 | D61: 76700 | E61: 189800 | F61: 340564 | G61: =F61/$F$74 -> 0.028099854 | I61: OCEANUS FISH | J61: 2979.6903 | L61: 20289.127 | M61: -59444.244 | N61: -36175.426 | O61: =N61/F61 -> -0.10622211 | R61: OCEANUS FISH | S61: 29690.602 | U61: 23908.567 | V61: -45744.691 | W61: 7854.4776 | X61: =W61/F61 -> 0.023063147
A62: LONGKOU BOHAI | D62: 334800 | F62: 334800 | G62: =F62/$F$74 -> 0.027624268 | I62: LONGKOU BOHAI | L62: 61759.822 | N62: 61759.822 | O62: =N62/F62 -> 0.18446781 | R62: LONGKOU BOHAI | U62: 76794.416 | W62: 76794.416 | X62: =W62/F62 -> 0.229374
A63: GLOBAL OCEAN | B63: 140400 | C63: 77585 | E63: 67500 | F63: 285485 | G63: =F63/$F$74 -> 0.023555299 | I63: GLOBAL OCEAN | J63: -4968.0447 | K63: 20669.556 | M63: 15712.77 | N63: 31414.281 | O63: =N63/F63 -> 0.11003829 | R63: DAIRECK S.A. | S63: 2063.8615 | U63: -238208.33 | W63: -236144.47 | X63: =W63/F63 -> -0.82716944
A64: DAIRECK S.A. | B64: 44722 | D64: 236060 | F64: 280782 | G64: =F64/$F$74 -> 0.023167256 | I64: DAIRECK S.A. | J64: -22592.364 | L64: -268416.73 | N64: -291009.09 | O64: =N64/F64 -> -1.0364236 | R64: GLOBAL OCEAN | S64: 50508.463 | T64: 25174.132 | V64: 19269.385 | W64: 94951.981 | X64: =W64/F64 -> 0.33816976
A65: YANTAI TAIXI FOODSTUFF | E65: 279504 | F65: 279504 | G65: =F65/$F$74 -> 0.023061808 | I65: YANTAI TAIXI FOODSTUFF | M65: 19044.143 | N65: 19044.143 | O65: =N65/F65 -> 0.068135493 | R65: YANTAI TAIXI FOODSTUFF | V65: 33223.18 | W65: 33223.18 | X65: =W65/F65 -> 0.11886478
A66: Longkou Yunfeng Aquatic | C66: 222750 | D66: 37800 | F66: 260550 | G66: =F66/$F$74 -> 0.021497918 | I66: Longkou Yunfeng Aquatic | K66: -48283.271 | L66: 30256.812 | N66: -18026.458 | O66: =N66/F66 -> -0.069186176 | R66: Longkou Yunfeng Aquatic | T66: -25760.388 | U66: 34015.461 | W66: 8255.073 | X66: =W66/F66 -> 0.031683258
A67: SHANDONG SHEENIER | D67: 70200 | E67: 145800 | F67: 216000 | G67: =F67/$F$74 -> 0.017822108 | I67: SHANDONG SHEENIER | L67: 12132.357 | M67: 24467.919 | N67: 36600.276 | O67: =N67/F67 -> 0.16944572 | R67: SHANDONG SHEENIER | U67: 15891.006 | V67: 31581.149 | W67: 47472.155 | X67: =W67/F67 -> 0.21977849
A68: Hunan Jinyueyang | C68: 77212.5 | E68: 104700 | F68: 181912.5 | G68: =F68/$F$74 -> 0.015009557 | I68: Hunan Jinyueyang | K68: -19360.678 | M68: 91830.334 | N68: 72469.656 | O68: =N68/F68 -> 0.39837645 | R68: GOLDEN SEAFOOD | V68: 38456.337 | W68: 38456.337 | X68: =W68/F68 -> 0.21140019
A69: GOLDEN SEAFOOD | E69: 151256 | F69: 151256 | G69: =F69/$F$74 -> 0.012480096 | I69: GOLDEN SEAFOOD | M69: 31632.905 | N69: 31632.905 | O69: =N69/F69 -> 0.20913488 | R69: Hunan Jinyueyang | T69: -10351.525 | V69: 98726.215 | W69: 88374.69 | X69: =W69/F69 -> 0.58427229
A70: SACRAMENTO CO., LTD | C70: 91800 | F70: 91800 | G70: =F70/$F$74 -> 0.0075743961 | I70: SACRAMENTO CO., LTD | K70: 29126.229 | N70: 29126.229 | O70: =N70/F70 -> 0.31727918 | R70: SACRAMENTO CO., LTD | T70: 33630.806 | W70: 33630.806 | X70: =W70/F70 -> 0.36634865
A71: PROVEEDORA DE PRODUCTOS MARINOS | B71: 24314.28 | C71: 40026 | D71: 26456.61 | F71: 90796.89 | G71: =F71/$F$74 -> 0.0074916297 | I71: PROVEEDORA DE PRODUCTOS MARINOS | J71: 24314.28 | K71: 40026 | L71: 26456.61 | N71: 90796.89 | O71: =N71/F71 -> 1 | R71: Shenzhen Yueshi | V71: 21908.098 | W71: 21908.098 | X71: =W71/F71 -> 0.24128687
A72: Shenzhen Yueshi | E72: 81000 | F72: 81000 | G72: =F72/$F$74 -> 0.0066832907 | I72: Shenzhen Yueshi | M72: 18351.483 | N72: 18351.483 | O72: =N72/F72 -> 0.22656152 | R72: PROVEEDORA DE PRODUCTOS MARINOS | S72: 24314.28 | T72: 40026 | U72: 26456.61 | W72: 90796.89 | X72: =W72/F72 -> 1.1209493
A73: Pesciro SL | D73: 39000 | F73: 39000 | G73: =F73/$F$74 -> 0.0032178807 | I73: Pesciro SL | L73: -15431.273 | N73: -15431.273 | O73: =N73/F73 -> -0.39567366 | R73: Pesciro SL | U73: -11811.833 | W73: -11811.833 | X73: =W73/F73 -> -0.30286752
A74: Total general | B74: 564615.28 | C74: 2769824.5 | D74: 3896418.3 | E74: 4888920 | F74: 12119778 | G74: =F74/$F$74 -> 1 | I74: Total general | J74: -99037.985 | K74: -488407.46 | L74: -201207.64 | M74: 89747.1 | N74: -698905.98 | O74: =N74/F74 -> -0.057666566 | R74: Total general | S74: 155743.02 | T74: -215757.06 | U74: 76626.094 | V74: 367704.45 | W74: 384316.5 | X74: =W74/F74 -> 0.031709862
A84: Suma de Cantidad | B84: Etiquetas de columna
A85: Etiquetas de fila | B85: ENERO | C85: FEBRERO | D85: MARZO | E85: ABRIL | F85: Total general
A86: POTA FILETE CONGELADO | B86: 48 | C86: 810 | D86: 293 | E86: 808.9 | F86: 1959.9
A87: POTA REJOS CONGELADOS | B87: 57.96 | C87: 209 | D87: 331 | E87: 458.94 | F87: 1056.9
A88: POTA ALAS CONGELADAS | B88: 72 | C88: 459.3 | D88: 482.8 | E88: 343.62 | F88: 1357.72
A89: POTA FILETE DARUMA | C89: 27 | D89: 324 | E89: 216 | F89: 567
A90: POTA REPRODUCTORES | B90: 26 | C90: 27 | D90: 51 | E90: 103.8 | F90: 207.8
A91: POTA NUCAS | B91: 20.04 | C91: 14 | D91: 385 | F91: 419.04
A92: POTA ALAS COCIDAS | D92: 54 | E92: 53.1 | F92: 107.1
A93: POTA CONOS | B93: 24 | C93: 34 | D93: 48 | E93: 22.2 | F93: 128.2
A94: POTA MEMBRANA PRECOCIDA | C94: 27 | D94: 27 | E94: 26.25 | F94: 80.25
A95: POTA TELILLA PRECOCIDA | C95: 27 | E95: 26.1 | F95: 53.1
A96: POTA RECORTES COCIDOS | E96: 27 | F96: 27
A97: POTA SUCKERS CONGELADO | E97: 24.2 | F97: 24.2
A98: RESIDUOS DE POTA | B98: 0 | C98: 0 | D98: 0 | F98: 0
A99: Total general | B99: 248 | C99: 1634.3 | D99: 1995.8 | E99: 2110.11 | F99: 5988.21
B103: Etiquetas de columna
A104: Valores | B104: ENERO | C104: FEBRERO | D104: MARZO | E104: ABRIL | F104: Total general | G104: Budget
A105: Suma de Cantidad | B105: 248 | C105: 1634.3 | D105: 1995.8 | E105: 2110.11 | F105: 5988.21 | G105: 5834
A106: Suma de CIF | B106: 71063.949 | C106: 497398.5 | D106: 662941.55 | E106: 833915.75 | F106: 2065319.7 | G106: 15333647
A107: Suma de DEPRECIACIÓN | B107: 123530 | C107: 124152.39 | D107: 123360.73 | E107: 123484.35 | F107: 494527.47 | G107: 12968611
I108: 7100 | J108: PRODUCCIÓN TERMINADO ABRIL
E109: CIF X TM | F109: =F106/F105 -> 344.89768 | H109: CIF X TM | I109: =F106/I108 -> 290.8901
E110: CIF SIN DEPRECIACIÓN X TM | F110: =(F106-F107)/F105 -> 262.31416 | H110: CIF SIN DEPRECIACIÓN X TM | I110: =(F106-F107)/I108 -> 221.23835 | J110: *PAYER, ELECTRICIDAD, MANTENIMIENTO, CALIDAD,
E111: GASTO ADM | F111: =N12 -> 44.156935 | H111: GASTO ADM | I111: =F111 -> 44.156935 | J111: PERSONAL ADM
E112: GASTO VENTAS | F112: 0 | H112: GASTO VENTAS | I112: 0
...

Sheet Resumen
C2: X | F2: X | G2: X | H2: X | K2: X | M2: X | P2: X | S2: X | AU2: X | AV2: X | BA2: ANÁLISIS UNITARIO
B3: MES LINK | C3: MES EJERCICIO | D3: FP | E3: Emision | F3: Fecha Embarque | G3: Cantidad | H3: Producto | I3: Corte | J3: Espec. | K3: País | L3: Puerto | M3: Cliente (Razón Social) | N3: Contacto | O3: Precio TM | P3: VALOR CFR | Q3: FOB / TM | R3: Costo Flete | S3: VALOR FOB | T3: Cantidad de FCL (Contenedores) | U3: M/V Nave | V3: Booking | W3: Naviera | X3: Puerto | Y3: CÓDIGO | Z3: Categoría | AA3: MATCH | AB3: COSTO UNITARIO | AC3: Materia Prima | AD3: MOD | AE3: Envases | AF3: CIF | AG3: COSTO VENTAS | AH3: Cant | AI3: C.U | AJ3: Cotos Vta | AK3: UTILIDAD BRUTA | AL3: MARGEN BRUTO | AM3: Flete | AN3: SS Logístico | AO3: GASTO VENTAS | AP3: GASTO ADM | AQ3: DRAWBACK | AR3: UTILIDAD OPERATIVA | AS3: MARGEN OPERATIVO | AT3: GASTO FINANCIERO | AU3: UTILIDAD NETA | AV3: MARGEN NETO | AW3: DEPRECIACIÓN | AX3: EBITDA | AY3: MARGEN EBITDA | BA3: PRECIO CFR | BB3: Materia Prima | BC3: MOD | BD3: Envases | BE3: CIF | BF3: COSTO VENTAS | BG3: UTILIDAD BRUTA | BH3: Flete | BI3: SS Logístico | BJ3: GASTO VENTAS | BK3: GASTO ADM | BL3: DRAWBACK | BM3: UTILIDAD OPERATIVA | BN3: GASTO FINANCIERO | BO3: UTILIDAD NETA | BP3: DEPRECIACIÓN | BQ3: EBITDA
B4: ENERO | C4: =B4 -> ENERO | D4: 127-2025 | E4: 325 | F4: 46033 | G4: 26 | H4: POTA REPRODUCTORES | I4: Rejos | K4: España | L4: Valencia | M4: OCEANUS FISH | N4: Ignacio / Ives | O4: =P4/G4 -> 2848.6154 | P4: =78000*0+74064 -> 74064 | Q4: =S4/G4 -> 2670.3846 | R4: 4634 | S4: =P4-R4 -> 69430 | T4: 1 | U4: MERSIN EXPRESS 603N | V4: 26106924 | W4: HAPAG | X4: PAITA | Y4: 10007567 | Z4: Compensación | AA4: =B4&Y4&Z4 -> ENERO10007567Compensación | AB4: =INDEX('Detalle Costos'!$L$5:$L$158,MATCH(Resumen!AA4,'Detalle Costos'!$C$5:$C$158,0))*1000 -> 1830 | AC4: =IFERROR(INDEX('Detalle Costos'!$X$5:$X$158,MATCH(Resumen!AA4,'Detalle Costos'!$C$5:$C$158,0))*AG4,0) -> 31604.019 | AD4: =IFERROR(INDEX('Detalle Costos'!$Z$5:$Z$158,MATCH(Resumen!AA4,'Detalle Costos'!$C$5:$C$158,0))*AG4,0) -> 7767.649 | AE4: =IFERROR(INDEX('Detalle Costos'!$Y$5:$Y$158,MATCH(Resumen!AA4,'Detalle Costos'!$C$5:$C$158,0))*AG4,0) -> 466.19182 | AF4: =IFERROR(INDEX('Detalle Costos'!$AA$5:$AA$158,MATCH(Resumen!AA4,'Detalle Costos'!$C$5:$C$158,0))*AG4,0) -> 7742.1407 | AG4: =AB4*G4 -> 47580 | AH4: =48.96-AH17 -> 22.658 | AI4: =+AJ4/AH4 -> 1829.8235 | AJ4: =89589.14-AJ17 -> 41460.14 | AK4: =P4-AG4 -> 26484 | AL4: =AK4/P4 -> 0.35758263 | AM4: =R4 -> 4634 | AN4: =1882/26*G4 -> 1882 | AO4: =SUM(AM4:AN4) -> 6516 | AP4: =50659/248*G4 -> 5311.0242 | AQ4: =S4*0.03 -> 2082.9 | AR4: =AK4-AO4-AP4+AQ4 -> 16739.876 | AS4: =AR4/P4 -> 0.22601906 | AT4: =131251/248*G4 -> 13760.185 | AU4: =AR4-AT4 -> 2979.6903 | AV4: =AU4/P4 -> 0.040231291 | AW4: =123530/248*G4 -> 12950.726 | AX4: =AR4+AW4 -> 29690.602 | AY4: =AX4/P4 -> 0.40087764 | BA4: =P4/$G4 -> 2848.6154 | BB4: =-AC4/$G4 -> -1215.5392 | BC4: =-AD4/$G4 -> -298.75573 | BD4: =-AE4/$G4 -> -17.930455 | BE4: =-AF4/$G4 -> -297.77464 | BF4: =-AG4/$G4 -> -1830 | BG4: =AK4/$G4 -> 1018.6154 | BH4: =-AM4/$G4 -> -178.23077 | BI4: =-AN4/$G4 -> -72.384615 | BJ4: =-AO4/$G4 -> -250.61538 | BK4: =-AP4/$G4 -> -204.27016 | BL4: =AQ4/$G4 -> 80.111538 | BM4: =AR4/$G4 -> 643.84138 | BN4: =-AT4/$G4 -> -529.2379 | BO4: =AU4/$G4 -> 114.60347 | BP4: =AW4/$G4 -> 498.10484 | BQ4: =AX4/$G4 -> 1141.9462
B5: ENERO | C5: =B5 -> ENERO | D5: 128-2025B | E5: 325 | F5: 46053 | G5: 17.04 | H5: POTA NUCAS | I5: Nucas | J5: 1000-up | K5: Tailandia | L5: Lat Krabang | M5: DAIRECK S.A. | N5: Julieta | O5: 1850 | P5: 31524 | Q5: 1656.338 | R5: =3300/24*G5 -> 2343 | S5: =P5-R5 -> 29181 | T5: 1 | U5: ECO SIROCCO 26005S | V5: 6443191850 | W5: COSCO | X5: PAITA | Y5: 10005779 | Z5: Compensación | AA5: =B5&Y5&Z5 -> ENERO10005779Compensación | AB5: =INDEX('Detalle Costos'!$L$5:$L$158,MATCH(Resumen!AA5,'Detalle Costos'!$C$5:$C$158,0))*1000 -> 1930 | AC5: =IFERROR(INDEX('Detalle Costos'!$X$5:$X$158,MATCH(Resumen!AA5,'Detalle Costos'!$C$5:$C$158,0))*AG5,0) -> 20697.485 | AD5: =IFERROR(INDEX('Detalle Costos'!$Z$5:$Z$158,MATCH(Resumen!AA5,'Detalle Costos'!$C$5:$C$158,0))*AG5,0) -> 6988.7487 | AE5: =IFERROR(INDEX('Detalle Costos'!$Y$5:$Y$158,MATCH(Resumen!AA5,'Detalle Costos'!$C$5:$C$158,0))*AG5,0) -> 251.15165 | AF5: =IFERROR(INDEX('Detalle Costos'!$AA$5:$AA$158,MATCH(Resumen!AA5,'Detalle Costos'!$C$5:$C$158,0))*AG5,0) -> 4949.8151 | AG5: =AB5*G5 -> 32887.2 | AH5: 17.04 | AI5: =+AJ5/AH5 -> 1977.4951 | AJ5: 33696.517 | AK5: =P5-AG5 -> -1363.2 | AL5: =AK5/P5 -> -0.043243243 | AM5: =R5 -> 2343 | AN5: =1882/26*G5 -> 1233.4338 | AO5: =SUM(AM5:AN5) -> 3576.4338 | AP5: =50659/248*G5 -> 3480.7635 | AQ5: =S5*0.03 -> 875.43 | AR5: =AK5-AO5-AP5+AQ5 -> -7544.9674 | AS5: =AR5/P5 -> -0.23934042 | AT5: =131251/248*G5 -> 9018.2139 | AU5: =AR5-AT5 -> -16563.181 | AV5: =AU5/P5 -> -0.52541496 | AW5: =123530/248*G5 -> 8487.7065 | AX5: =AR5+AW5 -> 942.73906 | AY5: =AX5/P5 -> 0.029905439 | BA5: =P5/$G5 -> 1850 | BB5: =-AC5/$G5 -> -1214.6411 | BC5: =-AD5/$G5 -> -410.13784 | BD5: =-AE5/$G5 -> -14.738946 | BE5: =-AF5/$G5 -> -290.48211 | BF5: =-AG5/$G5 -> -1930 | BG5: =AK5/$G5 -> -80 | BH5: =-AM5/$G5 -> -137.5 | BI5: =-AN5/$G5 -> -72.384615 | BJ5: =-AO5/$G5 -> -209.88462 | BK5: =-AP5/$G5 -> -204.27016 | BL5: =AQ5/$G5 -> 51.375 | BM5: =AR5/$G5 -> -442.77978 | BN5: =-AT5/$G5 -> -529.2379 | BO5: =AU5/$G5 -> -972.01768 | BP5: =AW5/$G5 -> 498.10484 | BQ5: =AX5/$G5 -> 55.325062
B6: ENERO | C6: =B6 -> ENERO | D6: 128-2025B | E6: 325 | F6: 46053 | G6: 3 | H6: POTA NUCAS | I6: Nucas | J6: 500 - 1 kg. | K6: Tailandia | L6: Lat Krabang | M6: DAIRECK S.A. | N6: Julieta | O6: 1450 | P6: 4350 | Q6: 1450 | R6: =3300/24*G6 -> 412.5 | S6: =P6-R6 -> 3937.5 | T6: 0 | V6: 6443191850 | W6: COSCO | X6: PAITA | Y6: 10005781 | Z6: Compensación | AA6: =B6&Y6&Z6 -> ENERO10005781Compensación | AB6: =INDEX('Detalle Costos'!$L$5:$L$158,MATCH(Resumen!AA6,'Detalle Costos'!$C$5:$C$158,0))*1000 -> 1980 | AC6: =IFERROR(INDEX('Detalle Costos'!$X$5:$X$158,MATCH(Resumen!AA6,'Detalle Costos'!$C$5:$C$158,0))*AG6,0) -> 3757.0132 | AD6: =IFERROR(INDEX('Detalle Costos'!$Z$5:$Z$158,MATCH(Resumen!AA6,'Detalle Costos'!$C$5:$C$158,0))*AG6,0) -> 1227.8049 | AE6: =IFERROR(INDEX('Detalle Costos'!$Y$5:$Y$158,MATCH(Resumen!AA6,'Detalle Costos'!$C$5:$C$158,0))*AG6,0) -> 49.950511 | AF6: =IFERROR(INDEX('Detalle Costos'!$AA$5:$AA$158,MATCH(Resumen!AA6,'Detalle Costos'!$C$5:$C$158,0))*AG6,0) -> 905.23138 | AG6: =AB6*G6 -> 5940 | AH6: 3 | AI6: =+AJ6/AH6 -> 1934.6564 | AJ6: 5803.9692 | AK6: =P6-AG6 -> -1590 | AL6: =AK6/P6 -> -0.36551724 | AM6: =R6 -> 412.5 | AN6: =1882/26*G6 -> 217.15385 | AO6: =SUM(AM6:AN6) -> 629.65385 | AP6: =50659/248*G6 -> 612.81048 | AQ6: =S6*0.03 -> 118.125 | AR6: =AK6-AO6-AP6+AQ6 -> -2714.3393 | AS6: =AR6/P6 -> -0.62398605 | AT6: =131251/248*G6 -> 1587.7137 | AU6: =AR6-AT6 -> -4302.053 | AV6: =AU6/P6 -> -0.98897771 | AW6: =123530/248*G6 -> 1494.3145 | AX6: =AR6+AW6 -> -1220.0248 | AY6: =AX6/P6 -> -0.28046547 | BA6: =P6/$G6 -> 1450 | BB6: =-AC6/$G6 -> -1252.3377 | BC6: =-AD6/$G6 -> -409.26831 | BD6: =-AE6/$G6 -> -16.65017 | BE6: =-AF6/$G6 -> -301.74379 | BF6: =-AG6/$G6 -> -1980 | BG6: =AK6/$G6 -> -530 | BH6: =-AM6/$G6 -> -137.5 | BI6: =-AN6/$G6 -> -72.384615 | BJ6: =-AO6/$G6 -> -209.88462 | BK6: =-AP6/$G6 -> -204.27016 | BL6: =AQ6/$G6 -> 39.375 | BM6: =AR6/$G6 -> -904.77978 | BN6: =-AT6/$G6 -> -529.2379 | BO6: =AU6/$G6 -> -1434.0177 | BP6: =AW6/$G6 -> 498.10484 | BQ6: =AX6/$G6 -> -406.67494
B7: ENERO | C7: =B7 -> ENERO | D7: 128-2025B | E7: 325 | F7: 46053 | G7: 3.96 | H7: POTA REJOS CONGELADOS | I7: Rejos | J7: 1 - 2 kgs. | K7: Tailandia | L7: Lat Krabang | M7: DAIRECK S.A. | N7: Julieta | O7: =P7/G7 -> 2234.3434 | P7: 8848 | Q7: 2800 | R7: =3300/24*G7 -> 544.5 | S7: =P7-R7 -> 8303.5 | T7: 0 | V7: 6443191850 | W7: COSCO | X7: PAITA | Y7: 10007162 | Z7: Compensación | AA7: =B7&Y7&Z7 -> ENERO10007162Compensación | AB7: =INDEX('Detalle Costos'!$L$5:$L$158,MATCH(Resumen!AA7,'Detalle Costos'!$C$5:$C$158,0))*1000 -> 1790 | AC7: =IFERROR(INDEX('Detalle Costos'!$X$5:$X$158,MATCH(Resumen!AA7,'Detalle Costos'!$C$5:$C$158,0))*AG7,0) -> 4604.3696 | AD7: =IFERROR(INDEX('Detalle Costos'!$Z$5:$Z$158,MATCH(Resumen!AA7,'Detalle Costos'!$C$5:$C$158,0))*AG7,0) -> 1214.8181 | AE7: =IFERROR(INDEX('Detalle Costos'!$Y$5:$Y$158,MATCH(Resumen!AA7,'Detalle Costos'!$C$5:$C$158,0))*AG7,0) -> 61.899523 | AF7: =IFERROR(INDEX('Detalle Costos'!$AA$5:$AA$158,MATCH(Resumen!AA7,'Detalle Costos'!$C$5:$C$158,0))*AG7,0) -> 1207.3128 | AG7: =AB7*G7 -> 7088.4 | AH7: 3.16 | AI7: =+AJ7/AH7 -> 1842.697 | AJ7: 5822.9227 | AK7: =P7-AG7 -> 1759.6 | AL7: =AK7/P7 -> 0.1988698 | AM7: =R7 -> 544.5 | AN7: =1882/26*G7 -> 286.64308 | AO7: =SUM(AM7:AN7) -> 831.14308 | AP7: =50659/248*G7 -> 808.90984 | AQ7: =S7*0.03 -> 249.105 | AR7: =AK7-AO7-AP7+AQ7 -> 368.65208 | AS7: =AR7/P7 -> 0.041665019 | AT7: =131251/248*G7 -> 2095.7821 | AU7: =AR7-AT7 -> -1727.13 | AV7: =AU7/P7 -> -0.19520005 | AW7: =123530/248*G7 -> 1972.4952 | AX7: =AR7+AW7 -> 2341.1472 | AY7: =AX7/P7 -> 0.26459621 | BA7: =P7/$G7 -> 2234.3434 | BB7: =-AC7/$G7 -> -1162.7196 | BC7: =-AD7/$G7 -> -306.77225 | BD7: =-AE7/$G7 -> -15.631193 | BE7: =-AF7/$G7 -> -304.87696 | BF7: =-AG7/$G7 -> -1790 | BG7: =AK7/$G7 -> 444.34343 | BH7: =-AM7/$G7 -> -137.5 | BI7: =-AN7/$G7 -> -72.384615 | BJ7: =-AO7/$G7 -> -209.88462 | BK7: =-AP7/$G7 -> -204.27016 | BL7: =AQ7/$G7 -> 62.905303 | BM7: =AR7/$G7 -> 93.093961 | BN7: =-AT7/$G7 -> -529.2379 | BO7: =AU7/$G7 -> -436.14394 | BP7: =AW7/$G7 -> 498.10484 | BQ7: =AX7/$G7 -> 591.1988
B8: ENERO | C8: =B8 -> ENERO | D8: 129-2025 | E8: 45982 | F8: 46031 | G8: 24 | H8: POTA CONOS | I8: Conos | K8: Tailandia | L8: Bangkok | M8: TSUJINO | N8: Jose | O8: 2100 | P8: 50400 | Q8: 1962.5 | R8: 3300 | S8: =P8-R8 -> 47100 | T8: 1 | U8: ECO MARIN 26002S | V8: 6440924270 | W8: COSCO | X8: PAITA | Y8: 10007969 | Z8: Compensación | AA8: =B8&Y8&Z8 -> ENERO10007969Compensación | AB8: =INDEX('Detalle Costos'!$L$5:$L$158,MATCH(Resumen!AA8,'Detalle Costos'!$C$5:$C$158,0))*1000 -> 1640 | AC8: =IFERROR(INDEX('Detalle Costos'!$X$5:$X$158,MATCH(Resumen!AA8,'Detalle Costos'!$C$5:$C$158,0))*AG8,0) -> 30431.619 | AD8: =IFERROR(INDEX('Detalle Costos'!$Z$5:$Z$158,MATCH(Resumen!AA8,'Detalle Costos'!$C$5:$C$158,0))*AG8,0) -> 5331.8121 | AE8: =IFERROR(INDEX('Detalle Costos'!$Y$5:$Y$158,MATCH(Resumen!AA8,'Detalle Costos'!$C$5:$C$158,0))*AG8,0) -> 403.53077 | AF8: =IFERROR(INDEX('Detalle Costos'!$AA$5:$AA$158,MATCH(Resumen!AA8,'Detalle Costos'!$C$5:$C$158,0))*AG8,0) -> 3193.0382 | AG8: =AB8*G8 -> 39360 | AH8: 24 | AI8: =+AJ8/AH8 -> 1644.3167 | AJ8: 39463.6 | AK8: =P8-AG8 -> 11040 | AL8: =AK8/P8 -> 0.21904762 | AM8: =R8 -> 3300 | AN8: =1882/26*G8 -> 1737.2308 | AO8: =SUM(AM8:AN8) -> 5037.2308 | AP8: =50659/248*G8 -> 4902.4839 | AQ8: =S8*0.03 -> 1413 | AR8: =AK8-AO8-AP8+AQ8 -> 2513.2854 | AS8: =AR8/P8 -> 0.049866773 | AT8: =131251/248*G8 -> 12701.71 | AU8: =AR8-AT8 -> -10188.424 | AV8: =AU8/P8 -> -0.20215128 | AW8: =123530/248*G8 -> 11954.516 | AX8: =AR8+AW8 -> 14467.801 | AY8: =AX8/P8 -> 0.28705955 | BA8: =P8/$G8 -> 2100 | BB8: =-AC8/$G8 -> -1267.9841 | BC8: =-AD8/$G8 -> -222.15884 | BD8: =-AE8/$G8 -> -16.813782 | BE8: =-AF8/$G8 -> -133.04326 | BF8: =-AG8/$G8 -> -1640 | BG8: =AK8/$G8 -> 460 | BH8: =-AM8/$G8 -> -137.5 | BI8: =-AN8/$G8 -> -72.384615 | BJ8: =-AO8/$G8 -> -209.88462 | BK8: =-AP8/$G8 -> -204.27016 | BL8: =AQ8/$G8 -> 58.875 | BM8: =AR8/$G8 -> 104.72022 | BN8: =-AT8/$G8 -> -529.2379 | BO8: =AU8/$G8 -> -424.51768 | BP8: =AW8/$G8 -> 498.10484 | BQ8: =AX8/$G8 -> 602.82506
B9: ENERO | C9: =B9 -> ENERO | D9: 137-2025 | E9: 46000 | F9: 46043 | G9: 24 | H9: POTA FILETE CONGELADO | I9: Filete | J9: 2 - 4 kg | K9: Taiwan | L9: KAOHSIUNG | M9: TSUJINO | N9: Jose | O9: =P9/G9 -> 1966.6667 | P9: =48000*0+47200 -> 47200 | Q9: =S9/G9 -> 1841.5417 | R9: 3003 | S9: =P9-R9 -> 44197 | T9: 1 | U9: ECO MARIN 25052N | V9: LIMF26385300 | W9: ONE | X9: PAITA | Y9: 10005721 | Z9: Compensación | AA9: =B9&Y9&Z9 -> ENERO10005721Compensación | AB9: =INDEX('Detalle Costos'!$L$5:$L$158,MATCH(Resumen!AA9,'Detalle Costos'!$C$5:$C$158,0))*1000 -> 1860 | AC9: =IFERROR(INDEX('Detalle Costos'!$X$5:$X$158,MATCH(Resumen!AA9,'Detalle Costos'!$C$5:$C$158,0))*AG9,0) -> 27074.763 | AD9: =IFERROR(INDEX('Detalle Costos'!$Z$5:$Z$158,MATCH(Resumen!AA9,'Detalle Costos'!$C$5:$C$158,0))*AG9,0) -> 9821.5948 | AE9: =IFERROR(INDEX('Detalle Costos'!$Y$5:$Y$158,MATCH(Resumen!AA9,'Detalle Costos'!$C$5:$C$158,0))*AG9,0) -> 427.38655 | AF9: =IFERROR(INDEX('Detalle Costos'!$AA$5:$AA$158,MATCH(Resumen!AA9,'Detalle Costos'!$C$5:$C$158,0))*AG9,0) -> 7316.2554 | AG9: =AB9*G9 -> 44640 | AH9: 23.7 | AI9: =+AJ9/AH9 -> 1889.3859 | AJ9: 44778.445 | AK9: =P9-AG9 -> 2560 | AL9: =AK9/P9 -> 0.054237288 | AM9: =R9 -> 3003 | AN9: =1882/26*G9 -> 1737.2308 | AO9: =SUM(AM9:AN9) -> 4740.2308 | AP9: =50659/248*G9 -> 4902.4839 | AQ9: =S9*0.03 -> 1325.91 | AR9: =AK9-AO9-AP9+AQ9 -> -5756.8046 | AS9: =AR9/P9 -> -0.1219662 | AT9: =131251/248*G9 -> 12701.71 | AU9: =AR9-AT9 -> -18458.514 | AV9: =AU9/P9 -> -0.39107022 | AW9: =123530/248*G9 -> 11954.516 | AX9: =AR9+AW9 -> 6197.7115 | AY9: =AX9/P9 -> 0.13130745 | BA9: =P9/$G9 -> 1966.6667 | BB9: =-AC9/$G9 -> -1128.1151 | BC9: =-AD9/$G9 -> -409.23312 | BD9: =-AE9/$G9 -> -17.807773 | BE9: =-AF9/$G9 -> -304.84398 | BF9: =-AG9/$G9 -> -1860 | BG9: =AK9/$G9 -> 106.66667 | BH9: =-AM9/$G9 -> -125.125 | BI9: =-AN9/$G9 -> -72.384615 | BJ9: =-AO9/$G9 -> -197.50962 | BK9: =-AP9/$G9 -> -204.27016 | BL9: =AQ9/$G9 -> 55.24625 | BM9: =AR9/$G9 -> -239.86686 | BN9: =-AT9/$G9 -> -529.2379 | BO9: =AU9/$G9 -> -769.10476 | BP9: =AW9/$G9 -> 498.10484 | BQ9: =AX9/$G9 -> 258.23798
B10: ENERO | C10: =B10 -> ENERO | D10: 140-2025 | E10: 347 | F10: 46038 | G10: 24 | H10: POTA FILETE CONGELADO | I10: Filete | J10: 2-4kg | K10: Japón | L10: Sendai | M10: TSUJINO | N10: Jose | O10: =P10/G10 -> 1983.3333 | P10: =48000*0+47600 -> 47600 | Q10: =S10/G10 -> 1845.7083 | R10: 3303 | S10: =P10-R10 -> 44297 | T10: 1 | U10: ECO SIROCCO 26003S | V10: LIMG00358300 | W10: ONE | X10: PAITA | Y10: 10005721 | Z10: Compensación | AA10: =B10&Y10&Z10 -> ENERO10005721Compensación | AB10: =INDEX('Detalle Costos'!$L$5:$L$158,MATCH(Resumen!AA10,'Detalle Costos'!$C$5:$C$158,0))*1000 -> 1860 | AC10: =IFERROR(INDEX('Detalle Costos'!$X$5:$X$158,MATCH(Resumen!AA10,'Detalle Costos'!$C$5:$C$158,0))*AG10,0) -> 27074.763 | AD10: =IFERROR(INDEX('Detalle Costos'!$Z$5:$Z$158,MATCH(Resumen!AA10,'Detalle Costos'!$C$5:$C$158,0))*AG10,0) -> 9821.5948 | AE10: =IFERROR(INDEX('Detalle Costos'!$Y$5:$Y$158,MATCH(Resumen!AA10,'Detalle Costos'!$C$5:$C$158,0))*AG10,0) -> 427.38655 | AF10: =IFERROR(INDEX('Detalle Costos'!$AA$5:$AA$158,MATCH(Resumen!AA10,'Detalle Costos'!$C$5:$C$158,0))*AG10,0) -> 7316.2554 | AG10: =AB10*G10 -> 44640 | AH10: 23.7 | AI10: =+AJ10/AH10 -> 1889.3859 | AJ10: 44778.445 | AK10: =P10-AG10 -> 2960 | AL10: =AK10/P10 -> 0.062184874 | AM10: =R10 -> 3303 | AN10: =1882/26*G10 -> 1737.2308 | AO10: =SUM(AM10:AN10) -> 5040.2308 | AP10: =50659/248*G10 -> 4902.4839 | AQ10: =S10*0.03 -> 1328.91 | AR10: =AK10-AO10-AP10+AQ10 -> -5653.8046 | AS10: =AR10/P10 -> -0.11877741 | AT10: =131251/248*G10 -> 12701.71 | AU10: =AR10-AT10 -> -18355.514 | AV10: =AU10/P10 -> -0.38562005 | AW10: =123530/248*G10 -> 11954.516 | AX10: =AR10+AW10 -> 6300.7115 | AY10: =AX10/P10 -> 0.13236789 | BA10: =P10/$G10 -> 1983.3333 | BB10: =-AC10/$G10 -> -1128.1151 | BC10: =-AD10/$G10 -> -409.23312 | BD10: =-AE10/$G10 -> -17.807773 | BE10: =-AF10/$G10 -> -304.84398 | BF10: =-AG10/$G10 -> -1860 | BG10: =AK10/$G10 -> 123.33333 | BH10: =-AM10/$G10 -> -137.625 | BI10: =-AN10/$G10 -> -72.384615 | BJ10: =-AO10/$G10 -> -210.00962 | BK10: =-AP10/$G10 -> -204.27016 | BL10: =AQ10/$G10 -> 55.37125 | BM10: =AR10/$G10 -> -235.57519 | BN10: =-AT10/$G10 -> -529.2379 | BO10: =AU10/$G10 -> -764.8131 | BP10: =AW10/$G10 -> 498.10484 | BQ10: =AX10/$G10 -> 262.52965
B11: ENERO | C11: =B11 -> ENERO | D11: 145-2025 | E11: 46020 | F11: 46041 | G11: 54 | H11: POTA REJOS CONGELADOS | I11: Rejos | J11: 500-1 / 1-2 | K11: España | L11: Vigo | M11: GLOBAL OCEAN | N11: Jorge | O11: 2600 | P11: 140400 | Q11: 2430.963 | R11: 9128 | S11: =P11-R11 -> 131272 | T11: 2 | U11: IZMIT EXPRESS 604N | V11: 28952064 | W11: HAPAG | X11: PAITA | Y11: 10007162 | Z11: Compensación | AA11: =B11&Y11&Z11 -> ENERO10007162Compensación | AB11: =INDEX('Detalle Costos'!$L$5:$L$158,MATCH(Resumen!AA11,'Detalle Costos'!$C$5:$C$158,0))*1000 -> 1790 | AC11: =IFERROR(INDEX('Detalle Costos'!$X$5:$X$158,MATCH(Resumen!AA11,'Detalle Costos'!$C$5:$C$158,0))*AG11,0) -> 62786.858 | AD11: =IFERROR(INDEX('Detalle Costos'!$Z$5:$Z$158,MATCH(Resumen!AA11,'Detalle Costos'!$C$5:$C$158,0))*AG11,0) -> 16565.702 | AE11: =IFERROR(INDEX('Detalle Costos'!$Y$5:$Y$158,MATCH(Resumen!AA11,'Detalle Costos'!$C$5:$C$158,0))*AG11,0) -> 844.0844 | AF11: =IFERROR(INDEX('Detalle Costos'!$AA$5:$AA$158,MATCH(Resumen!AA11,'Detalle Costos'!$C$5:$C$158,0))*AG11,0) -> 16463.356 | AG11: =AB11*G11 -> 96660 | AH11: 54 | AI11: =+AJ11/AH11 -> 1842.697 | AJ11: 99505.64 | AK11: =P11-AG11 -> 43740 | AL11: =AK11/P11 -> 0.31153846 | AM11: =R11 -> 9128 | AN11: =1882/26*G11 -> 3908.7692 | AO11: =SUM(AM11:AN11) -> 13036.769 | AP11: =50659/248*G11 -> 11030.589 | AQ11: =S11*0.03 -> 3938.16 | AR11: =AK11-AO11-AP11+AQ11 -> 23610.802 | AS11: =AR11/P11 -> 0.16816811 | AT11: =131251/248*G11 -> 28578.847 | AU11: =AR11-AT11 -> -4968.0447 | AV11: =AU11/P11 -> -0.035384934 | AW11: =123530/248*G11 -> 26897.661 | AX11: =AR11+AW11 -> 50508.463 | AY11: =AX11/P11 -> 0.35974689 | BA11: =P11/$G11 -> 2600 | BB11: =-AC11/$G11 -> -1162.7196 | BC11: =-AD11/$G11 -> -306.77225 | BD11: =-AE11/$G11 -> -15.631193 | BE11: =-AF11/$G11 -> -304.87696 | BF11: =-AG11/$G11 -> -1790 | BG11: =AK11/$G11 -> 810 | BH11: =-AM11/$G11 -> -169.03704 | BI11: =-AN11/$G11 -> -72.384615 | BJ11: =-AO11/$G11 -> -241.42165 | BK11: =-AP11/$G11 -> -204.27016 | BL11: =AQ11/$G11 -> 72.928889 | BM11: =AR11/$G11 -> 437.23708 | BN11: =-AT11/$G11 -> -529.2379 | BO11: =AU11/$G11 -> -92.000828 | BP11: =AW11/$G11 -> 498.10484 | BQ11: =AX11/$G11 -> 935.34191
B12: FEBRERO | C12: =B12 -> FEBRERO | D12: 146-2026 | E12: 46027 | F12: 46059 | G12: 10 | H12: POTA CONOS | I12: Conos | J12: 10 cm - up | K12: Tailandia | L12: Lat Krabang | M12: TSUJINO | N12: Jose | O12: 2100 | P12: 21000 | Q12: 2100 | R12: =3500/24*G12 -> 1458.3333 | S12: =P12-R12 -> 19541.667 | T12: 1 | U12: ECO MARIN 26006S | V12: 6444023300 | W12: COSCO | X12: PAITA | Y12: 10007969 | Z12: Compensación | AA12: =B12&Y12&Z12 -> FEBRERO10007969Compensación | AB12: =INDEX('Detalle Costos'!$L$5:$L$158,MATCH(Resumen!AA12,'Detalle Costos'!$C$5:$C$158,0))*1000*0+AI12 -> 1397.2773 | AC12: =IFERROR(INDEX('Detalle Costos'!$X$5:$X$158,MATCH(Resumen!AA12,'Detalle Costos'!$C$5:$C$158,0))*AG12,0) -> 11301.832 | AD12: =IFERROR(INDEX('Detalle Costos'!$Z$5:$Z$158,MATCH(Resumen!AA12,'Detalle Costos'!$C$5:$C$158,0))*AG12,0) -> 2127.4653 | AE12: =IFERROR(INDEX('Detalle Costos'!$Y$5:$Y$158,MATCH(Resumen!AA12,'Detalle Costos'!$C$5:$C$158,0))*AG12,0) -> 166.83162 | AF12: =IFERROR(INDEX('Detalle Costos'!$AA$5:$AA$158,MATCH(Resumen!AA12,'Detalle Costos'!$C$5:$C$158,0))*AG12,0) -> 376.64454 | AG12: =AB12*G12 -> 13972.773 | AH12: =+G12 -> 10 | AI12: 1397.2773 | AJ12: =+AI12*AH12 -> 13972.773 | AK12: =P12-AG12 -> 7027.2269 | AL12: =AK12/P12 -> 0.33462985 | AM12: =R12 -> 1458.3333 | AN12: =1882/26*G12 -> 723.84615 | AO12: =SUM(AM12:AN12) -> 2182.1795 | AP12: =56604/1634.3*G12 -> 346.35012 | AQ12: =S12*0.03 -> 586.25 | AR12: =AK12-AO12-AP12+AQ12 -> 5084.9473 | AS12: =AR12/P12 -> 0.24214035 | AT12: =148498/1634.3*G12 -> 908.63367 | AU12: =AR12-AT12 -> 4176.3136 | AV12: =AU12/P12 -> 0.19887208 | AW12: =123484.35/1634.3*G12 -> 755.57945 | AX12: =AR12+AW12 -> 5840.5268 | AY12: =AX12/P12 -> 0.27812032 | BA12: =P12/$G12 -> 2100 | BB12: =-AC12/$G12 -> -1130.1832 | BC12: =-AD12/$G12 -> -212.74653 | BD12: =-AE12/$G12 -> -16.683162 | BE12: =-AF12/$G12 -> -37.664454 | BF12: =-AG12/$G12 -> -1397.2773 | BG12: =AK12/$G12 -> 702.72269 | BH12: =-AM12/$G12 -> -145.83333 | BI12: =-AN12/$G12 -> -72.384615 | BJ12: =-AO12/$G12 -> -218.21795 | BK12: =-AP12/$G12 -> -34.635012 | BL12: =AQ12/$G12 -> 58.625 | BM12: =AR12/$G12 -> 508.49473 | BN12: =-AT12/$G12 -> -90.863367 | BO12: =AU12/$G12 -> 417.63136 | BP12: =AW12/$G12 -> 75.557945 | BQ12: =AX12/$G12 -> 584.05268
B13: FEBRERO | C13: =B13 -> FEBRERO | D13: 146-2026 | E13: 46027 | F13: 46059 | G13: 14 | H13: POTA NUCAS | I13: Nucas | J13: 500-up | K13: Tailandia | L13: Lat Krabang | M13: TSUJINO | N13: Jose | O13: 1700 | P13: =23800-344 -> 23456 | Q13: 1700 | R13: =3500/24*G13 -> 2041.6667 | S13: =P13-R13 -> 21414.333 | T13: 0 | Y13: 10005779 | Z13: Compensación | AA13: =B13&Y13&Z13 -> FEBRERO10005779Compensación | AB13: =INDEX('Detalle Costos'!$L$5:$L$158,MATCH(Resumen!AA13,'Detalle Costos'!$C$5:$C$158,0))*1000*0+AI13 -> 1859.7145 | AC13: =IFERROR(INDEX('Detalle Costos'!$X$5:$X$158,MATCH(Resumen!AA13,'Detalle Costos'!$C$5:$C$158,0))*AG13,0) -> 15847.871 | AD13: =IFERROR(INDEX('Detalle Costos'!$Z$5:$Z$158,MATCH(Resumen!AA13,'Detalle Costos'!$C$5:$C$158,0))*AG13,0) -> 5732.4075 | AE13: =IFERROR(INDEX('Detalle Costos'!$Y$5:$Y$158,MATCH(Resumen!AA13,'Detalle Costos'!$C$5:$C$158,0))*AG13,0) -> 189.9202 | AF13: =IFERROR(INDEX('Detalle Costos'!$AA$5:$AA$158,MATCH(Resumen!AA13,'Detalle Costos'!$C$5:$C$158,0))*AG13,0) -> 4265.8048 | AG13: =AB13*G13 -> 26036.003 | AH13: 14.849 | AI13: 1859.7145 | AJ13: =AI13*AH13 -> 27614.901 | AK13: =P13-AG13 -> -2580.0034 | AL13: =AK13/P13 -> -0.10999332 | AM13: =R13 -> 2041.6667 | AN13: =1882/26*G13 -> 1013.3846 | AO13: =SUM(AM13:AN13) -> 3055.0513 | AP13: =56604/1634.3*G13 -> 484.89017 | AQ13: =S13*0.03 -> 642.43 | AR13: =AK13-AO13-AP13+AQ13 -> -5477.5148 | AS13: =AR13/P13 -> -0.23352297 | AT13: =148498/1634.3*G13 -> 1272.0871 | AU13: =AR13-AT13 -> -6749.602 | AV13: =AU13/P13 -> -0.28775588 | AW13: =123484.35/1634.3*G13 -> 1057.8112 | AX13: =AR13+AW13 -> -4419.7036 | AY13: =AX13/P13 -> -0.18842529 | BA13: =P13/$G13 -> 1675.4286 | BB13: =-AC13/$G13 -> -1131.9908 | BC13: =-AD13/$G13 -> -409.45768 | BD13: =-AE13/$G13 -> -13.565729 | BE13: =-AF13/$G13 -> -304.70034 | BF13: =-AG13/$G13 -> -1859.7145 | BG13: =AK13/$G13 -> -184.28596 | BH13: =-AM13/$G13 -> -145.83333 | BI13: =-AN13/$G13 -> -72.384615 | BJ13: =-AO13/$G13 -> -218.21795 | BK13: =-AP13/$G13 -> -34.635012 | BL13: =AQ13/$G13 -> 45.887857 | BM13: =AR13/$G13 -> -391.25106 | BN13: =-AT13/$G13 -> -90.863367 | BO13: =AU13/$G13 -> -482.11443 | BP13: =AW13/$G13 -> 75.557945 | BQ13: =AX13/$G13 -> -315.69312
B14: ENERO | C14: =B14 -> ENERO | D14: 147-2026 | E14: 46032 | F14: 46050 | G14: 72 | H14: POTA ALAS CONGELADAS | I14: Alas | J14: 1 - 2 KGS. | K14: Tailandia | L14: Bangkok | M14: TSUJINO | N14: Jose | O14: =P14/G14 -> 1887.7083 | P14: =140400*0+135915 -> 135915 | Q14: =S14/G14 -> 1754.25 | R14: 9609 | S14: =P14-R14 -> 126306 | T14: 3 | U14: ECO MARIN 26004N | V14: LIMG01524600 | W14: ONE | X14: PAITA | Y14: 10006720 | Z14: Compensación | AA14: =B14&Y14&Z14 -> ENERO10006720Compensación | AB14: =INDEX('Detalle Costos'!$L$5:$L$158,MATCH(Resumen!AA14,'Detalle Costos'!$C$5:$C$158,0))*1000 -> 1720 | AC14: =IFERROR(INDEX('Detalle Costos'!$X$5:$X$158,MATCH(Resumen!AA14,'Detalle Costos'!$C$5:$C$158,0))*AG14,0) -> 81764.361 | AD14: =IFERROR(INDEX('Detalle Costos'!$Z$5:$Z$158,MATCH(Resumen!AA14,'Detalle Costos'!$C$5:$C$158,0))*AG14,0) -> 18919.258 | AE14: =IFERROR(INDEX('Detalle Costos'!$Y$5:$Y$158,MATCH(Resumen!AA14,'Detalle Costos'!$C$5:$C$158,0))*AG14,0) -> 1185.8374 | AF14: =IFERROR(INDEX('Detalle Costos'!$AA$5:$AA$158,MATCH(Resumen!AA14,'Detalle Costos'!$C$5:$C$158,0))*AG14,0) -> 21970.544 | AG14: =AB14*G14 -> 123840 | AH14: 69.7 | AI14: =+AJ14/AH14 -> 1723.916 | AJ14: 120156.94 | AK14: =P14-AG14 -> 12075 | AL14: =AK14/P14 -> 0.088842291 | AM14: =R14 -> 9609 | AN14: =1882/26*G14 -> 5211.6923 | AO14: =SUM(AM14:AN14) -> 14820.692 | AP14: =50659/248*G14 -> 14707.452 | AQ14: =S14*0.03 -> 3789.18 | AR14: =AK14-AO14-AP14+AQ14 -> -13663.964 | AS14: =AR14/P14 -> -0.10053316 | AT14: =131251/248*G14 -> 38105.129 | AU14: =AR14-AT14 -> -51769.093 | AV14: =AU14/P14 -> -0.38089315 | AW14: =123530/248*G14 -> 35863.548 | AX14: =AR14+AW14 -> 22199.584 | AY14: =AX14/P14 -> 0.16333432 | BA14: =P14/$G14 -> 1887.7083 | BB14: =-AC14/$G14 -> -1135.6161 | BC14: =-AD14/$G14 -> -262.76747 | BD14: =-AE14/$G14 -> -16.469963 | BE14: =-AF14/$G14 -> -305.14645 | BF14: =-AG14/$G14 -> -1720 | BG14: =AK14/$G14 -> 167.70833 | BH14: =-AM14/$G14 -> -133.45833 | BI14: =-AN14/$G14 -> -72.384615 | BJ14: =-AO14/$G14 -> -205.84295 | BK14: =-AP14/$G14 -> -204.27016 | BL14: =AQ14/$G14 -> 52.6275 | BM14: =AR14/$G14 -> -189.77728 | BN14: =-AT14/$G14 -> -529.2379 | BO14: =AU14/$G14 -> -719.01518 | BP14: =AW14/$G14 -> 498.10484 | BQ14: =AX14/$G14 -> 308.32756
B15: ENERO | C15: =B15 -> ENERO | E15: 46053 | F15: 46053 | G15: 0 | H15: RESIDUOS DE POTA | I15: Residuos | J15: Residuos | K15: Residuos | L15: Residuos | M15: PROVEEDORA DE PRODUCTOS MARINOS | O15: 0 | P15: 24314.28 | Q15: 0 | R15: 0 | S15: =P15-R15 -> 24314.28 | AB15: 0 | AC15: =IFERROR(INDEX('Detalle Costos'!$X$5:$X$158,MATCH(Resumen!AA15,'Detalle Costos'!$C$5:$C$158,0))*AG15,0) -> 0 | AD15: =IFERROR(INDEX('Detalle Costos'!$Z$5:$Z$158,MATCH(Resumen!AA15,'Detalle Costos'!$C$5:$C$158,0))*AG15,0) -> 0 | AE15: =IFERROR(INDEX('Detalle Costos'!$Y$5:$Y$158,MATCH(Resumen!AA15,'Detalle Costos'!$C$5:$C$158,0))*AG15,0) -> 0 | AF15: =IFERROR(INDEX('Detalle Costos'!$AA$5:$AA$158,MATCH(Resumen!AA15,'Detalle Costos'!$C$5:$C$158,0))*AG15,0) -> 0 | AG15: =AB15*G15 -> 0 | AK15: =P15-AG15 -> 24314.28 | AL15: =AK15/P15 -> 1 | AM15: =R15 -> 0 | AN15: =1882/26*G15 -> 0 | AO15: =SUM(AM15:AN15) -> 0 | AP15: =50659/248*G15 -> 0 | AQ15: 0 | AR15: =AK15-AO15-AP15+AQ15 -> 24314.28 | AS15: =AR15/P15 -> 1 | AT15: =131251/248*G15 -> 0 | AU15: =AR15-AT15 -> 24314.28 | AV15: =AU15/P15 -> 1 | AW15: =123530/248*G15 -> 0 | AX15: =AR15+AW15 -> 24314.28 | AY15: =AX15/P15 -> 1 | BA15: 0 | BB15: 0 | BC15: 0 | BD15: 0 | BE15: 0 | BF15: 0 | BG15: 0 | BH15: 0 | BI15: 0 | BJ15: 0 | BK15: 0 | BL15: 0 | BM15: 0 | BN15: 0 | BO15: 0 | BP15: 0 | BQ15: 0
B16: FEBRERO | C16: =B16 -> FEBRERO | D16: 148-2026 | E16: 15 | F16: 46055 | G16: 135 | H16: POTA FILETE CONGELADO | I16: Filete | J16: 2-4 (B) | K16: España | L16: Vigo | M16: FOOD & BEVERAGES TRADERS | N16: Jorge | O16: 1650 | P16: 222750 | Q16: 1480.963 | R16: 22820 | S16: =P16-R16 -> 199930 | T16: 5 | U16: ODYSSEUS 606N | V16: 59582082 | W16: HAPAG | X16: PAITA | Y16: 10005721 | Z16: Compensación | AA16: =B16&Y16&Z16 -> FEBRERO10005721Compensación | AB16: =INDEX('Detalle Costos'!$L$5:$L$158,MATCH(Resumen!AA16,'Detalle Costos'!$C$5:$C$158,0))*1000*0+AI16 -> 1861.4473 | AC16: =IFERROR(INDEX('Detalle Costos'!$X$5:$X$158,MATCH(Resumen!AA16,'Detalle Costos'!$C$5:$C$158,0))*AG16,0) -> 152495.08 | AD16: =IFERROR(INDEX('Detalle Costos'!$Z$5:$Z$158,MATCH(Resumen!AA16,'Detalle Costos'!$C$5:$C$158,0))*AG16,0) -> 50378.669 | AE16: =IFERROR(INDEX('Detalle Costos'!$Y$5:$Y$158,MATCH(Resumen!AA16,'Detalle Costos'!$C$5:$C$158,0))*AG16,0) -> 2680.0174 | AF16: =IFERROR(INDEX('Detalle Costos'!$AA$5:$AA$158,MATCH(Resumen!AA16,'Detalle Costos'!$C$5:$C$158,0))*AG16,0) -> 45741.622 | AG16: =AB16*G16 -> 251295.39 | AH16: =+G16 -> 135 | AI16: =AJ16/AH16 -> 1861.4473 | AJ16: 251295.39 | AK16: =P16-AG16 -> -28545.39 | AL16: =AK16/P16 -> -0.1281499 | AM16: =R16 -> 22820 | AN16: =1882/26*G16 -> 9771.9231 | AO16: =SUM(AM16:AN16) -> 32591.923 | AP16: =56604/1634.3*G16 -> 4675.7266 | AQ16: =S16*0.03 -> 5997.9 | AR16: =AK16-AO16-AP16+AQ16 -> -59815.14 | AS16: =AR16/P16 -> -0.26853037 | AT16: =148498/1634.3*G16 -> 12266.554 | AU16: =AR16-AT16 -> -72081.694 | AV16: =AU16/P16 -> -0.32359908 | AW16: =124162.35/1634.3*G16 -> 10256.328 | AX16: =AR16+AW16 -> -49558.811 | AY16: =AX16/P16 -> -0.22248625 | BA16: =P16/$G16 -> 1650 | BB16: =-AC16/$G16 -> -1129.5932 | BC16: =-AD16/$G16 -> -373.17533 | BD16: =-AE16/$G16 -> -19.85198 | BE16: =-AF16/$G16 -> -338.82683 | BF16: =-AG16/$G16 -> -1861.4473 | BG16: =AK16/$G16 -> -211.44733 | BH16: =-AM16/$G16 -> -169.03704 | BI16: =-AN16/$G16 -> -72.384615 | BJ16: =-AO16/$G16 -> -241.42165 | BK16: =-AP16/$G16 -> -34.635012 | BL16: =AQ16/$G16 -> 44.428889 | BM16: =AR16/$G16 -> -443.07511 | BN16: =-AT16/$G16 -> -90.863367 | BO16: =AU16/$G16 -> -533.93848 | BP16: =AW16/$G16 -> 75.972802 | BQ16: =AX16/$G16 -> -367.10231
B17: FEBRERO | C17: =B17 -> FEBRERO | D17: 149-2026 | E17: 16 | F17: 46055 | G17: 27 | H17: POTA REPRODUCTORES | I17: Rejos | K17: España | L17: Vigo | M17: GLOBAL OCEAN | N17: Jorge | O17: =P17/G17 -> 2873.5185 | P17: =79650*0+77585 -> 77585 | Q17: =S17/G17 -> 2711.8889 | R17: 4364 | S17: =P17-R17 -> 73221 | T17: 1 | Y17: 10007567 | Z17: Entradas | AA17: =B17&Y17&Z17 -> FEBRERO10007567Entradas | AB17: =INDEX('Detalle Costos'!$L$5:$L$158,MATCH(Resumen!AA17,'Detalle Costos'!$C$5:$C$158,0))*1000*0+AI17 -> 1829.8235 | AC17: =IFERROR(INDEX('Detalle Costos'!$X$5:$X$158,MATCH(Resumen!AA17,'Detalle Costos'!$C$5:$C$158,0))*AG17,0) -> 30498.569 | AD17: =IFERROR(INDEX('Detalle Costos'!$Z$5:$Z$158,MATCH(Resumen!AA17,'Detalle Costos'!$C$5:$C$158,0))*AG17,0) -> 8738.5729 | AE17: =IFERROR(INDEX('Detalle Costos'!$Y$5:$Y$158,MATCH(Resumen!AA17,'Detalle Costos'!$C$5:$C$158,0))*AG17,0) -> 554.46203 | AF17: =IFERROR(INDEX('Detalle Costos'!$AA$5:$AA$158,MATCH(Resumen!AA17,'Detalle Costos'!$C$5:$C$158,0))*AG17,0) -> 9613.63 | AG17: =AB17*G17 -> 49405.233 | AH17: 26.302 | AI17: =+AI4 -> 1829.8235 | AJ17: 48129 | AK17: =P17-AG17 -> 28179.767 | AL17: =AK17/P17 -> 0.36321153 | AM17: =R17 -> 4364 | AN17: =1882/26*G17 -> 1954.3846 | AO17: =SUM(AM17:AN17) -> 6318.3846 | AP17: =56604/1634.3*G17 -> 935.14532 | AQ17: =S17*0.03 -> 2196.63 | AR17: =AK17-AO17-AP17+AQ17 -> 23122.867 | AS17: =AR17/P17 -> 0.29803269 | AT17: =148498/1634.3*G17 -> 2453.3109 | AU17: =AR17-AT17 -> 20669.556 | AV17: =AU17/P17 -> 0.26641175 | AW17: =124162.35/1634.3*G17 -> 2051.2656 | AX17: =AR17+AW17 -> 25174.132 | AY17: =AX17/P17 -> 0.32447164 | BA17: =P17/$G17 -> 2873.5185 | BB17: =-AC17/$G17 -> -1129.5766 | BC17: =-AD17/$G17 -> -323.65085 | BD17: =-AE17/$G17 -> -20.535631 | BE17: =-AF17/$G17 -> -356.06037 | BF17: =-AG17/$G17 -> -1829.8235 | BG17: =AK17/$G17 -> 1043.6951 | BH17: =-AM17/$G17 -> -161.62963 | BI17: =-AN17/$G17 -> -72.384615 | BJ17: =-AO17/$G17 -> -234.01425 | BK17: =-AP17/$G17 -> -34.635012 | BL17: =AQ17/$G17 -> 81.356667 | BM17: =AR17/$G17 -> 856.40247 | BN17: =-AT17/$G17 -> -90.863367 | BO17: =AU17/$G17 -> 765.5391 | BP17: =AW17/$G17 -> 75.972802 | BQ17: =AX17/$G17 -> 932.37527
B18: FEBRERO | C18: =B18 -> FEBRERO | D18: 150-2026A | E18: 325 | F18: 46069 | G18: 26 | H18: POTA REJOS CONGELADOS | I18: Rejos | J18: 1-2 KG | K18: España | L18: Vigo | M18: OVERSEA | N18: Avelino | O18: 2600 | P18: 67600 | Q18: 2432.1538 | R18: 4364 | S18: =P18-R18 -> 63236 | T18: 1 | U18: CAPE SPENCER 608N | V18: 11400418 | W18: HAPAG | X18: PAITA | Y18: 10007162 | Z18: Compensación | AA18: =B18&Y18&Z18 -> FEBRERO10007162Compensación | AB18: =INDEX('Detalle Costos'!$L$5:$L$158,MATCH(Resumen!AA18,'Detalle Costos'!$C$5:$C$158,0))*1000*0+AI18 -> 1715.2908 | AC18: =IFERROR(INDEX('Detalle Costos'!$X$5:$X$158,MATCH(Resumen!AA18,'Detalle Costos'!$C$5:$C$158,0))*AG18,0) -> 27996.818 | AD18: =IFERROR(INDEX('Detalle Costos'!$Z$5:$Z$158,MATCH(Resumen!AA18,'Detalle Costos'!$C$5:$C$158,0))*AG18,0) -> 7988.6675 | AE18: =IFERROR(INDEX('Detalle Costos'!$Y$5:$Y$158,MATCH(Resumen!AA18,'Detalle Costos'!$C$5:$C$158,0))*AG18,0) -> 415.9275 | AF18: =IFERROR(INDEX('Detalle Costos'!$AA$5:$AA$158,MATCH(Resumen!AA18,'Detalle Costos'!$C$5:$C$158,0))*AG18,0) -> 8196.1487 | AG18: =AB18*G18 -> 44597.561 | AH18: =+G18 -> 26 | AI18: 1715.2908 | AJ18: =AI18*AH18 -> 44597.561 | AK18: =P18-AG18 -> 23002.439 | AL18: =AK18/P18 -> 0.34027276 | AM18: =R18 -> 4364 | AN18: =1882/26*G18 -> 1882 | AO18: =SUM(AM18:AN18) -> 6246 | AP18: =56604/1634.3*G18 -> 900.51031 | AQ18: =S18*0.03 -> 1897.08 | AR18: =AK18-AO18-AP18+AQ18 -> 17753.008 | AS18: =AR18/P18 -> 0.26261847 | AT18: =148498/1634.3*G18 -> 2362.4475 | AU18: =AR18-AT18 -> 15390.561 | AV18: =AU18/P18 -> 0.22767102 | AW18: =124162.35/1634.3*G18 -> 1975.2928 | AX18: =AR18+AW18 -> 19728.301 | AY18: =AX18/P18 -> 0.29183878 | BA18: =P18/$G18 -> 2600 | BB18: =-AC18/$G18 -> -1076.8007 | BC18: =-AD18/$G18 -> -307.25644 | BD18: =-AE18/$G18 -> -15.997212 | BE18: =-AF18/$G18 -> -315.23649 | BF18: =-AG18/$G18 -> -1715.2908 | BG18: =AK18/$G18 -> 884.70918 | BH18: =-AM18/$G18 -> -167.84615 | BI18: =-AN18/$G18 -> -72.384615 | BJ18: =-AO18/$G18 -> -240.23077 | BK18: =-AP18/$G18 -> -34.635012 | BL18: =AQ18/$G18 -> 72.964615 | BM18: =AR18/$G18 -> 682.80802 | BN18: =-AT18/$G18 -> -90.863367 | BO18: =AU18/$G18 -> 591.94465 | BP18: =AW18/$G18 -> 75.972802 | BQ18: =AX18/$G18 -> 758.78082
B19: FEBRERO | C19: =B19 -> FEBRERO | D19: 151-2025 | E19: 26 | F19: 46080 | G19: 27 | H19: POTA MEMBRANA PRECOCIDA | I19: Membrana | K19: China | L19: Qingdao | M19: Hunan Jinyueyang | O19: =P19/G19 -> 1429.8611 | P19: =39150*0+38606.25 -> 38606.25 | Q19: =S19/G19 -> 1322.4537 | R19: 2900 | S19: =P19-R19 -> 35706.25 | T19: 1 | U19: ECO SIROCCO 26009S | V19: 6445502950 | W19: COSCO | X19: PAITA | Y19: 10009332 | Z19: Entradas | AA19: =B19&Y19&Z19 -> FEBRERO10009332Entradas | AB19: =AI19 -> 1529.9065 | AC19: =IFERROR(INDEX('Detalle Costos'!$X$5:$X$158,MATCH(Resumen!AA19,'Detalle Costos'!$C$5:$C$158,0))*AG19,0) -> 34256.34 | AD19: =IFERROR(INDEX('Detalle Costos'!$Z$5:$Z$158,MATCH(Resumen!AA19,'Detalle Costos'!$C$5:$C$158,0))*AG19,0) -> 6268.5858 | AE19: =IFERROR(INDEX('Detalle Costos'!$Y$5:$Y$158,MATCH(Resumen!AA19,'Detalle Costos'!$C$5:$C$158,0))*AG19,0) -> 633.18765 | AF19: =IFERROR(INDEX('Detalle Costos'!$AA$5:$AA$158,MATCH(Resumen!AA19,'Detalle Costos'!$C$5:$C$158,0))*AG19,0) -> 149.36167 | AG19: =AB19*G19 -> 41307.475 | AH19: 26.625 | AI19: =AJ19/AH19 -> 1529.9065 | AJ19: 40733.76 | AK19: =P19-AG19 -> -2701.2249 | AL19: =AK19/P19 -> -0.069968591 | AM19: =R19 -> 2900 | AN19: =1882/26*G19 -> 1954.3846 | AO19: =SUM(AM19:AN19) -> 4854.3846 | AP19: =56604/1634.3*G19 -> 935.14532 | AQ19: =S19*0.03 -> 1071.1875 | AR19: =AK19-AO19-AP19+AQ19 -> -7419.5674 | AS19: =AR19/P19 -> -0.19218565 | AT19: =148498/1634.3*G19 -> 2453.3109 | AU19: =AR19-AT19 -> -9872.8783 | AV19: =AU19/P19 -> -0.25573264 | AW19: =124162.35/1634.3*G19 -> 2051.2656 | AX19: =AR19+AW19 -> -5368.3017 | AY19: =AX19/P19 -> -0.13905266 | BA19: =P19/$G19 -> 1429.8611 | BB19: =-AC19/$G19 -> -1268.7533 | BC19: =-AD19/$G19 -> -232.16984 | BD19: =-AE19/$G19 -> -23.451395 | BE19: =-AF19/$G19 -> -5.5319137 | BF19: =-AG19/$G19 -> -1529.9065 | BG19: =AK19/$G19 -> -100.04537 | BH19: =-AM19/$G19 -> -107.40741 | BI19: =-AN19/$G19 -> -72.384615 | BJ19: =-AO19/$G19 -> -179.79202 | BK19: =-AP19/$G19 -> -34.635012 | BL19: =AQ19/$G19 -> 39.673611 | BM19: =AR19/$G19 -> -274.79879 | BN19: =-AT19/$G19 -> -90.863367 | BO19: =AU19/$G19 -> -365.66216 | BP19: =AW19/$G19 -> 75.972802 | BQ19: =AX19/$G19 -> -198.82599
B20: FEBRERO | C20: =B20 -> FEBRERO | D20: 151-2025 | E20: 26 | F20: 46080 | G20: 27 | H20: POTA TELILLA PRECOCIDA | I20: Telilla | K20: China | L20: Qingdao | M20: Hunan Jinyueyang | O20: =P20/G20 -> 1429.8611 | P20: =39150*0+38606.25 -> 38606.25 | Q20: =S20/G20 -> 1322.4537 | R20: 2900 | S20: =P20-R20 -> 35706.25 | T20: 1 | U20: ECO SIROCCO 26009S | V20: 6445502950 | W20: COSCO | X20: PAITA | Y20: 10009332 | Z20: Compensación | AA20: =B20&Y20&Z20 -> FEBRERO10009332Compensación | AB20: =INDEX('Detalle Costos'!$L$5:$L$158,MATCH(Resumen!AA20,'Detalle Costos'!$C$5:$C$158,0))*1000*0+AI20 -> 1515.6443 | AC20: =IFERROR(INDEX('Detalle Costos'!$X$5:$X$158,MATCH(Resumen!AA20,'Detalle Costos'!$C$5:$C$158,0))*AG20,0) -> 33289.301 | AD20: =IFERROR(INDEX('Detalle Costos'!$Z$5:$Z$158,MATCH(Resumen!AA20,'Detalle Costos'!$C$5:$C$158,0))*AG20,0) -> 5812.6541 | AE20: =IFERROR(INDEX('Detalle Costos'!$Y$5:$Y$158,MATCH(Resumen!AA20,'Detalle Costos'!$C$5:$C$158,0))*AG20,0) -> 581.72151 | AF20: =IFERROR(INDEX('Detalle Costos'!$AA$5:$AA$158,MATCH(Resumen!AA20,'Detalle Costos'!$C$5:$C$158,0))*AG20,0) -> 1238.72 | AG20: =AB20*G20 -> 40922.397 | AH20: 26.625 | AI20: =AJ20/AH20 -> 1515.6443 | AJ20: 40354.03 | AK20: =P20-AG20 -> -2316.1466 | AL20: =AK20/P20 -> -0.059994084 | AM20: =R20 -> 2900 | AN20: =1882/26*G20 -> 1954.3846 | AO20: =SUM(AM20:AN20) -> 4854.3846 | AP20: =56604/1634.3*G20 -> 935.14532 | AQ20: =S20*0.03 -> 1071.1875 | AR20: =AK20-AO20-AP20+AQ20 -> -7034.4891 | AS20: =AR20/P20 -> -0.18221115 | AT20: =148498/1634.3*G20 -> 2453.3109 | AU20: =AR20-AT20 -> -9487.8 | AV20: =AU20/P20 -> -0.24575813 | AW20: =124162.35/1634.3*G20 -> 2051.2656 | AX20: =AR20+AW20 -> -4983.2234 | AY20: =AX20/P20 -> -0.12907815 | BA20: =P20/$G20 -> 1429.8611 | BB20: =-AC20/$G20 -> -1232.9371 | BC20: =-AD20/$G20 -> -215.28349 | BD20: =-AE20/$G20 -> -21.545241 | BE20: =-AF20/$G20 -> -45.878519 | BF20: =-AG20/$G20 -> -1515.6443 | BG20: =AK20/$G20 -> -85.783208 | BH20: =-AM20/$G20 -> -107.40741 | BI20: =-AN20/$G20 -> -72.384615 | BJ20: =-AO20/$G20 -> -179.79202 | BK20: =-AP20/$G20 -> -34.635012 | BL20: =AQ20/$G20 -> 39.673611 | BM20: =AR20/$G20 -> -260.53663 | BN20: =-AT20/$G20 -> -90.863367 | BO20: =AU20/$G20 -> -351.4 | BP20: =AW20/$G20 -> 75.972802 | BQ20: =AX20/$G20 -> -184.56383
B21: FEBRERO | C21: =B21 -> FEBRERO | D21: 152-2026 | E21: 26 | F21: 46062 | G21: 27 | H21: POTA REJOS CONGELADOS | I21: Rejos | J21: 2-UP KG | K21: España | L21: Vigo | M21: OVERSEA | N21: Avelino | O21: =P21/G21 -> 2781.2963 | P21: =75600*0+75095 -> 75095 | Q21: =S21/G21 -> 2619.6667 | R21: 4364 | S21: =P21-R21 -> 70731 | T21: 1 | U21: GEMLIK EXPRESS 607N | V21: 24312444 | W21: HAPAG | X21: PAITA | Y21: 10007162 | Z21: Compensación | AA21: =B21&Y21&Z21 -> FEBRERO10007162Compensación | AB21: =INDEX('Detalle Costos'!$L$5:$L$158,MATCH(Resumen!AA21,'Detalle Costos'!$C$5:$C$158,0))*1000*0+AI21 -> 1751.1868 | AC21: =IFERROR(INDEX('Detalle Costos'!$X$5:$X$158,MATCH(Resumen!AA21,'Detalle Costos'!$C$5:$C$158,0))*AG21,0) -> 29682.043 | AD21: =IFERROR(INDEX('Detalle Costos'!$Z$5:$Z$158,MATCH(Resumen!AA21,'Detalle Costos'!$C$5:$C$158,0))*AG21,0) -> 8469.5332 | AE21: =IFERROR(INDEX('Detalle Costos'!$Y$5:$Y$158,MATCH(Resumen!AA21,'Detalle Costos'!$C$5:$C$158,0))*AG21,0) -> 440.96362 | AF21: =IFERROR(INDEX('Detalle Costos'!$AA$5:$AA$158,MATCH(Resumen!AA21,'Detalle Costos'!$C$5:$C$158,0))*AG21,0) -> 8689.5035 | AG21: =AB21*G21 -> 47282.044 | AH21: =+G21 -> 27 | AI21: =1.75118680089485*1000 -> 1751.1868 | AJ21: =AI21*AH21 -> 47282.044 | AK21: =P21-AG21 -> 27812.956 | AL21: =AK21/P21 -> 0.37037028 | AM21: =R21 -> 4364 | AN21: =1882/26*G21 -> 1954.3846 | AO21: =SUM(AM21:AN21) -> 6318.3846 | AP21: =56604/1634.3*G21 -> 935.14532 | AQ21: =S21*0.03 -> 2121.93 | AR21: =AK21-AO21-AP21+AQ21 -> 22681.356 | AS21: =AR21/P21 -> 0.30203551 | AT21: =148498/1634.3*G21 -> 2453.3109 | AU21: =AR21-AT21 -> 20228.046 | AV21: =AU21/P21 -> 0.26936608 | AW21: =124162.35/1634.3*G21 -> 2051.2656 | AX21: =AR21+AW21 -> 24732.622 | AY21: =AX21/P21 -> 0.32935112 | BA21: =P21/$G21 -> 2781.2963 | BB21: =-AC21/$G21 -> -1099.3349 | BC21: =-AD21/$G21 -> -313.68641 | BD21: =-AE21/$G21 -> -16.331986 | BE21: =-AF21/$G21 -> -321.83346 | BF21: =-AG21/$G21 -> -1751.1868 | BG21: =AK21/$G21 -> 1030.1095 | BH21: =-AM21/$G21 -> -161.62963 | BI21: =-AN21/$G21 -> -72.384615 | BJ21: =-AO21/$G21 -> -234.01425 | BK21: =-AP21/$G21 -> -34.635012 | BL21: =AQ21/$G21 -> 78.59 | BM21: =AR21/$G21 -> 840.05024 | BN21: =-AT21/$G21 -> -90.863367 | BO21: =AU21/$G21 -> 749.18687 | BP21: =AW21/$G21 -> 75.972802 | BQ21: =AX21/$G21 -> 916.02304
B22: FEBRERO | C22: =B22 -> FEBRERO | D22: 156-2026A | E22: 27 | F22: 46062 | G22: 54 | H22: POTA FILETE CONGELADO | I22: Filete | J22: 2-4 kg 100% blanco, No polyphosphate,no medicine | K22: China | L22: Qingdao | M22: Longkou Yunfeng Aquatic | O22: 1650 | P22: 89100 | Q22: 1534.963 | R22: 6212 | S22: =P22-R22 -> 82888 | T22: 2 | U22: CMA CGM IMAGINATION / 0DVITN1MA | V22: LMM0571149 | W22: CMA CGM | X22: PAITA | Y22: 10005721 | Z22: Compensación | AA22: =B22&Y22&Z22 -> FEBRERO10005721Compensación | AB22: =INDEX('Detalle Costos'!$L$5:$L$158,MATCH(Resumen!AA22,'Detalle Costos'!$C$5:$C$158,0))*1000*0+AI22 -> 1740.7827 | AC22: =IFERROR(INDEX('Detalle Costos'!$X$5:$X$158,MATCH(Resumen!AA22,'Detalle Costos'!$C$5:$C$158,0))*AG22,0) -> 57043.957 | AD22: =IFERROR(INDEX('Detalle Costos'!$Z$5:$Z$158,MATCH(Resumen!AA22,'Detalle Costos'!$C$5:$C$158,0))*AG22,0) -> 18845.189 | AE22: =IFERROR(INDEX('Detalle Costos'!$Y$5:$Y$158,MATCH(Resumen!AA22,'Detalle Costos'!$C$5:$C$158,0))*AG22,0) -> 1002.5162 | AF22: =IFERROR(INDEX('Detalle Costos'!$AA$5:$AA$158,MATCH(Resumen!AA22,'Detalle Costos'!$C$5:$C$158,0))*AG22,0) -> 17110.605 | AG22: =AB22*G22 -> 94002.267 | AH22: =+G22 -> 54 | AI22: =1.7407827151654*1000 -> 1740.7827 | AJ22: =+AI22*AH22 -> 94002.267 | AK22: =P22-AG22 -> -4902.2666 | AL22: =AK22/P22 -> -0.055019827 | AM22: =R22 -> 6212 | AN22: =1882/26*G22 -> 3908.7692 | AO22: =SUM(AM22:AN22) -> 10120.769 | AP22: =56604/1634.3*G22 -> 1870.2906 | AQ22: =S22*0.03 -> 2486.64 | AR22: =AK22-AO22-AP22+AQ22 -> -14406.686 | AS22: =AR22/P22 -> -0.16169121 | AT22: =148498/1634.3*G22 -> 4906.6218 | AU22: =AR22-AT22 -> -19313.308 | AV22: =AU22/P22 -> -0.21675991 | AW22: =124162.35/1634.3*G22 -> 4102.5313 | AX22: =AR22+AW22 -> -10304.155 | AY22: =AX22/P22 -> -0.11564708 | BA22: =P22/$G22 -> 1650 | BB22: =-AC22/$G22 -> -1056.3696 | BC22: =-AD22/$G22 -> -348.98498 | BD22: =-AE22/$G22 -> -18.565115 | BE22: =-AF22/$G22 -> -316.86305 | BF22: =-AG22/$G22 -> -1740.7827 | BG22: =AK22/$G22 -> -90.782715 | BH22: =-AM22/$G22 -> -115.03704 | BI22: =-AN22/$G22 -> -72.384615 | BJ22: =-AO22/$G22 -> -187.42165 | BK22: =-AP22/$G22 -> -34.635012 | BL22: =AQ22/$G22 -> 46.048889 | BM22: =AR22/$G22 -> -266.79049 | BN22: =-AT22/$G22 -> -90.863367 | BO22: =AU22/$G22 -> -357.65386 | BP22: =AW22/$G22 -> 75.972802 | BQ22: =AX22/$G22 -> -190.81769
B23: FEBRERO | C23: =B23 -> FEBRERO | D23: 156-2026B | E23: 27 | F23: 46071 | G23: 81 | H23: POTA FILETE CONGELADO | I23: Filete | J23: 2-4 kg 100% blanco, No polyphosphate,no medicine | K23: China | L23: Qingdao | M23: Longkou Yunfeng Aquatic | O23: 1650 | P23: 133650 | Q23: 1534.963 | R23: 9318 | S23: =P23-R23 -> 124332 | T23: 3 | U23: CMA CGM EXCELLENCE 0DVNNN1MA | V23: LMM0571699 | W23: CMA CGM | X23: PAITA | Y23: 10005721 | Z23: Compensación | AA23: =B23&Y23&Z23 -> FEBRERO10005721Compensación | AB23: =INDEX('Detalle Costos'!$L$5:$L$158,MATCH(Resumen!AA23,'Detalle Costos'!$C$5:$C$158,0))*1000*0+AI23 -> 1740.7827 | AC23: =IFERROR(INDEX('Detalle Costos'!$X$5:$X$158,MATCH(Resumen!AA23,'Detalle Costos'!$C$5:$C$158,0))*AG23,0) -> 85565.935 | AD23: =IFERROR(INDEX('Detalle Costos'!$Z$5:$Z$158,MATCH(Resumen!AA23,'Detalle Costos'!$C$5:$C$158,0))*AG23,0) -> 28267.783 | AE23: =IFERROR(INDEX('Detalle Costos'!$Y$5:$Y$158,MATCH(Resumen!AA23,'Detalle Costos'!$C$5:$C$158,0))*AG23,0) -> 1503.7743 | AF23: =IFERROR(INDEX('Detalle Costos'!$AA$5:$AA$158,MATCH(Resumen!AA23,'Detalle Costos'!$C$5:$C$158,0))*AG23,0) -> 25665.907 | AG23: =AB23*G23 -> 141003.4 | AH23: =+G23 -> 81 | AI23: =1.7407827151654*1000 -> 1740.7827 | AJ23: =+AI23*AH23 -> 141003.4 | AK23: =P23-AG23 -> -7353.3999 | AL23: =AK23/P23 -> -0.055019827 | AM23: =R23 -> 9318 | AN23: =1882/26*G23 -> 5863.1538 | AO23: =SUM(AM23:AN23) -> 15181.154 | AP23: =56604/1634.3*G23 -> 2805.436 | AQ23: =S23*0.03 -> 3729.96 | AR23: =AK23-AO23-AP23+AQ23 -> -21610.03 | AS23: =AR23/P23 -> -0.16169121 | AT23: =148498/1634.3*G23 -> 7359.9327 | AU23: =AR23-AT23 -> -28969.962 | AV23: =AU23/P23 -> -0.21675991 | AW23: =124162.35/1634.3*G23 -> 6153.7969 | AX23: =AR23+AW23 -> -15456.233 | AY23: =AX23/P23 -> -0.11564708 | BA23: =P23/$G23 -> 1650 | BB23: =-AC23/$G23 -> -1056.3696 | BC23: =-AD23/$G23 -> -348.98498 | BD23: =-AE23/$G23 -> -18.565115 | BE23: =-AF23/$G23 -> -316.86305 | BF23: =-AG23/$G23 -> -1740.7827 | BG23: =AK23/$G23 -> -90.782715 | BH23: =-AM23/$G23 -> -115.03704 | BI23: =-AN23/$G23 -> -72.384615 | BJ23: =-AO23/$G23 -> -187.42165 | BK23: =-AP23/$G23 -> -34.635012 | BL23: =AQ23/$G23 -> 46.048889 | BM23: =AR23/$G23 -> -266.79049 | BN23: =-AT23/$G23 -> -90.863367 | BO23: =AU23/$G23 -> -357.65386 | BP23: =AW23/$G23 -> 75.972802 | BQ23: =AX23/$G23 -> -190.81769
B24: FEBRERO | C24: =B24 -> FEBRERO | D24: 157-2026 | E24: 28 | F24: 46066 | G24: 24 | H24: POTA CONOS | I24: Conos | K24: Tailandia | L24: Lat Krabang | M24: TSUJINO | N24: Jose | O24: 2000 | P24: 48000 | Q24: 1854.1667 | R24: 3500 | S24: =P24-R24 -> 44500 | T24: 1 | U24: ECO SIROCCO 26007S | V24: 6445030580 | W24: COSCO | X24: PAITA | Y24: 10007969 | Z24: Compensación | AA24: =B24&Y24&Z24 -> FEBRERO10007969Compensación | AB24: =INDEX('Detalle Costos'!$L$5:$L$158,MATCH(Resumen!AA24,'Detalle Costos'!$C$5:$C$158,0))*1000*0+AI24 -> 1397.2773 | AC24: =IFERROR(INDEX('Detalle Costos'!$X$5:$X$158,MATCH(Resumen!AA24,'Detalle Costos'!$C$5:$C$158,0))*AG24,0) -> 27124.396 | AD24: =IFERROR(INDEX('Detalle Costos'!$Z$5:$Z$158,MATCH(Resumen!AA24,'Detalle Costos'!$C$5:$C$158,0))*AG24,0) -> 5105.9167 | AE24: =IFERROR(INDEX('Detalle Costos'!$Y$5:$Y$158,MATCH(Resumen!AA24,'Detalle Costos'!$C$5:$C$158,0))*AG24,0) -> 400.3959 | AF24: =IFERROR(INDEX('Detalle Costos'!$AA$5:$AA$158,MATCH(Resumen!AA24,'Detalle Costos'!$C$5:$C$158,0))*AG24,0) -> 903.94689 | AG24: =AB24*G24 -> 33534.655 | AH24: 23.14 | AI24: 1397.2773 | AJ24: =+AI24*AH24 -> 32332.997 | AK24: =P24-AG24 -> 14465.345 | AL24: =AK24/P24 -> 0.30136135 | AM24: =R24 -> 3500 | AN24: =1882/26*G24 -> 1737.2308 | AO24: =SUM(AM24:AN24) -> 5237.2308 | AP24: =56604/1634.3*G24 -> 831.24029 | AQ24: =S24*0.03 -> 1335 | AR24: =AK24-AO24-AP24+AQ24 -> 9731.8735 | AS24: =AR24/P24 -> 0.20274737 | AT24: =148498/1634.3*G24 -> 2180.7208 | AU24: =AR24-AT24 -> 7551.1527 | AV24: =AU24/P24 -> 0.15731568 | AW24: =124162.35/1634.3*G24 -> 1823.3472 | AX24: =AR24+AW24 -> 11555.221 | AY24: =AX24/P24 -> 0.24073377 | BA24: =P24/$G24 -> 2000 | BB24: =-AC24/$G24 -> -1130.1832 | BC24: =-AD24/$G24 -> -212.74653 | BD24: =-AE24/$G24 -> -16.683162 | BE24: =-AF24/$G24 -> -37.664454 | BF24: =-AG24/$G24 -> -1397.2773 | BG24: =AK24/$G24 -> 602.72269 | BH24: =-AM24/$G24 -> -145.83333 | BI24: =-AN24/$G24 -> -72.384615 | BJ24: =-AO24/$G24 -> -218.21795 | BK24: =-AP24/$G24 -> -34.635012 | BL24: =AQ24/$G24 -> 55.625 | BM24: =AR24/$G24 -> 405.49473 | BN24: =-AT24/$G24 -> -90.863367 | BO24: =AU24/$G24 -> 314.63136 | BP24: =AW24/$G24 -> 75.972802 | BQ24: =AX24/$G24 -> 481.46753
B25: FEBRERO | C25: =B25 -> FEBRERO | D25: 160-2026 | E25: 30 | F25: 46066 | G25: 108 | H25: POTA ALAS CONGELADAS | I25: Alas | K25: China | L25: Qingdao | M25: TSUJINO | N25: Jose | O25: 1600 | P25: 172800 | Q25: 1492.5926 | R25: 11600 | S25: =P25-R25 -> 161200 | T25: 4 | U25: ECO SIROCCO 26007S | V25: 6445031110 | W25: COSCO | X25: PAITA | Y25: 10006720 | Z25: Compensación | AA25: =B25&Y25&Z25 -> FEBRERO10006720Compensación | AB25: =INDEX('Detalle Costos'!$L$5:$L$158,MATCH(Resumen!AA25,'Detalle Costos'!$C$5:$C$158,0))*1000*0+AI25 -> 1639.7682 | AC25: =IFERROR(INDEX('Detalle Costos'!$X$5:$X$158,MATCH(Resumen!AA25,'Detalle Costos'!$C$5:$C$158,0))*AG25,0) -> 114801.8 | AD25: =IFERROR(INDEX('Detalle Costos'!$Z$5:$Z$158,MATCH(Resumen!AA25,'Detalle Costos'!$C$5:$C$158,0))*AG25,0) -> 26268.814 | AE25: =IFERROR(INDEX('Detalle Costos'!$Y$5:$Y$158,MATCH(Resumen!AA25,'Detalle Costos'!$C$5:$C$158,0))*AG25,0) -> 1720.5907 | AF25: =IFERROR(INDEX('Detalle Costos'!$AA$5:$AA$158,MATCH(Resumen!AA25,'Detalle Costos'!$C$5:$C$158,0))*AG25,0) -> 34303.76 | AG25: =AB25*G25 -> 177094.96 | AH25: =+G25 -> 108 | AI25: =1.63976816895275*1000 -> 1639.7682 | AJ25: =+AI25*AH25 -> 177094.96 | AK25: =P25-AG25 -> -4294.9622 | AL25: =AK25/P25 -> -0.024855106 | AM25: =R25 -> 11600 | AN25: =1882/26*G25 -> 7817.5385 | AO25: =SUM(AM25:AN25) -> 19417.538 | AP25: =56604/1634.3*G25 -> 3740.5813 | AQ25: =S25*0.03 -> 4836 | AR25: =AK25-AO25-AP25+AQ25 -> -22617.082 | AS25: =AR25/P25 -> -0.13088589 | AT25: =148498/1634.3*G25 -> 9813.2436 | AU25: =AR25-AT25 -> -32430.326 | AV25: =AU25/P25 -> -0.1876755 | AW25: =124162.35/1634.3*G25 -> 8205.0626 | AX25: =AR25+AW25 -> -14412.019 | AY25: =AX25/P25 -> -0.08340289 | BA25: =P25/$G25 -> 1600 | BB25: =-AC25/$G25 -> -1062.9796 | BC25: =-AD25/$G25 -> -243.22976 | BD25: =-AE25/$G25 -> -15.931396 | BE25: =-AF25/$G25 -> -317.62741 | BF25: =-AG25/$G25 -> -1639.7682 | BG25: =AK25/$G25 -> -39.768169 | BH25: =-AM25/$G25 -> -107.40741 | BI25: =-AN25/$G25 -> -72.384615 | BJ25: =-AO25/$G25 -> -179.79202 | BK25: =-AP25/$G25 -> -34.635012 | BL25: =AQ25/$G25 -> 44.777778 | BM25: =AR25/$G25 -> -209.41743 | BN25: =-AT25/$G25 -> -90.863367 | BO25: =AU25/$G25 -> -300.28079 | BP25: =AW25/$G25 -> 75.972802 | BQ25: =AX25/$G25 -> -133.44462
B26: FEBRERO | C26: =B26 -> FEBRERO | D26: 160-2026 | E26: 30 | F26: 46066 | G26: 108 | H26: POTA ALAS CONGELADAS | I26: Alas | K26: China | L26: Qingdao | M26: TSUJINO | N26: Jose | O26: 1600 | P26: 172800 | Q26: 1492.5926 | R26: 11600 | S26: =P26-R26 -> 161200 | T26: 4 | U26: ECO SIROCCO 26007S | V26: 6445031130 | W26: COSCO | X26: PAITA | Y26: 10006720 | Z26: Compensación | AA26: =B26&Y26&Z26 -> FEBRERO10006720Compensación | AB26: =INDEX('Detalle Costos'!$L$5:$L$158,MATCH(Resumen!AA26,'Detalle Costos'!$C$5:$C$158,0))*1000*0+AI26 -> 1639.7682 | AC26: =IFERROR(INDEX('Detalle Costos'!$X$5:$X$158,MATCH(Resumen!AA26,'Detalle Costos'!$C$5:$C$158,0))*AG26,0) -> 114801.8 | AD26: =IFERROR(INDEX('Detalle Costos'!$Z$5:$Z$158,MATCH(Resumen!AA26,'Detalle Costos'!$C$5:$C$158,0))*AG26,0) -> 26268.814 | AE26: =IFERROR(INDEX('Detalle Costos'!$Y$5:$Y$158,MATCH(Resumen!AA26,'Detalle Costos'!$C$5:$C$158,0))*AG26,0) -> 1720.5907 | AF26: =IFERROR(INDEX('Detalle Costos'!$AA$5:$AA$158,MATCH(Resumen!AA26,'Detalle Costos'!$C$5:$C$158,0))*AG26,0) -> 34303.76 | AG26: =AB26*G26 -> 177094.96 | AH26: =+G26 -> 108 | AI26: =1.63976816895275*1000 -> 1639.7682 | AJ26: =+AI26*AH26 -> 177094.96 | AK26: =P26-AG26 -> -4294.9622 | AL26: =AK26/P26 -> -0.024855106 | AM26: =R26 -> 11600 | AN26: =1882/26*G26 -> 7817.5385 | AO26: =SUM(AM26:AN26) -> 19417.538 | AP26: =56604/1634.3*G26 -> 3740.5813 | AQ26: =S26*0.03 -> 4836 | AR26: =AK26-AO26-AP26+AQ26 -> -22617.082 | AS26: =AR26/P26 -> -0.13088589 | AT26: =148498/1634.3*G26 -> 9813.2436 | AU26: =AR26-AT26 -> -32430.326 | AV26: =AU26/P26 -> -0.1876755 | AW26: =124162.35/1634.3*G26 -> 8205.0626 | AX26: =AR26+AW26 -> -14412.019 | AY26: =AX26/P26 -> -0.08340289 | BA26: =P26/$G26 -> 1600 | BB26: =-AC26/$G26 -> -1062.9796 | BC26: =-AD26/$G26 -> -243.22976 | BD26: =-AE26/$G26 -> -15.931396 | BE26: =-AF26/$G26 -> -317.62741 | BF26: =-AG26/$G26 -> -1639.7682 | BG26: =AK26/$G26 -> -39.768169 | BH26: =-AM26/$G26 -> -107.40741 | BI26: =-AN26/$G26 -> -72.384615 | BJ26: =-AO26/$G26 -> -179.79202 | BK26: =-AP26/$G26 -> -34.635012 | BL26: =AQ26/$G26 -> 44.777778 | BM26: =AR26/$G26 -> -209.41743 | BN26: =-AT26/$G26 -> -90.863367 | BO26: =AU26/$G26 -> -300.28079 | BP26: =AW26/$G26 -> 75.972802 | BQ26: =AX26/$G26 -> -133.44462
B27: FEBRERO | C27: =B27 -> FEBRERO | D27: 162-2026A | E27: 34 | F27: 46070 | G27: 115.5 | H27: POTA ALAS CONGELADAS | I27: Alas | J27: 1-2 kg | K27: China | L27: Qingdao | M27: AVANCE GROUP | N27: James | O27: 1500 | P27: 173250 | Q27: 1382.987 | R27: 13515 | S27: =P27-R27 -> 159735 | T27: 5 | U27: ECO SIROCCO 26007N | V27: LIMG02628500 | W27: ONE | X27: PAITA | Y27: 10006720 | Z27: Compensación | AA27: =B27&Y27&Z27 -> FEBRERO10006720Compensación | AB27: =INDEX('Detalle Costos'!$L$5:$L$158,MATCH(Resumen!AA27,'Detalle Costos'!$C$5:$C$158,0))*1000*0+AI27 -> 1639.7682 | AC27: =IFERROR(INDEX('Detalle Costos'!$X$5:$X$158,MATCH(Resumen!AA27,'Detalle Costos'!$C$5:$C$158,0))*AG27,0) -> 122774.14 | AD27: =IFERROR(INDEX('Detalle Costos'!$Z$5:$Z$158,MATCH(Resumen!AA27,'Detalle Costos'!$C$5:$C$158,0))*AG27,0) -> 28093.038 | AE27: =IFERROR(INDEX('Detalle Costos'!$Y$5:$Y$158,MATCH(Resumen!AA27,'Detalle Costos'!$C$5:$C$158,0))*AG27,0) -> 1840.0762 | AF27: =IFERROR(INDEX('Detalle Costos'!$AA$5:$AA$158,MATCH(Resumen!AA27,'Detalle Costos'!$C$5:$C$158,0))*AG27,0) -> 36685.966 | AG27: =AB27*G27 -> 189393.22 | AH27: =+G27 -> 115.5 | AI27: =1.63976816895275*1000 -> 1639.7682 | AJ27: =+AI27*AH27 -> 189393.22 | AK27: =P27-AG27 -> -16143.224 | AL27: =AK27/P27 -> -0.093178779 | AM27: =R27 -> 13515 | AN27: =1882/26*G27 -> 8360.4231 | AO27: =SUM(AM27:AN27) -> 21875.423 | AP27: =56604/1634.3*G27 -> 4000.3439 | AQ27: =S27*0.03 -> 4792.05 | AR27: =AK27-AO27-AP27+AQ27 -> -37226.94 | AS27: =AR27/P27 -> -0.21487412 | AT27: =148498/1634.3*G27 -> 10494.719 | AU27: =AR27-AT27 -> -47721.659 | AV27: =AU27/P27 -> -0.27544969 | AW27: =124162.35/1634.3*G27 -> 8774.8586 | AX27: =AR27+AW27 -> -28452.082 | AY27: =AX27/P27 -> -0.16422558 | BA27: =P27/$G27 -> 1500 | BB27: =-AC27/$G27 -> -1062.9796 | BC27: =-AD27/$G27 -> -243.22976 | BD27: =-AE27/$G27 -> -15.931396 | BE27: =-AF27/$G27 -> -317.62741 | BF27: =-AG27/$G27 -> -1639.7682 | BG27: =AK27/$G27 -> -139.76817 | BH27: =-AM27/$G27 -> -117.01299 | BI27: =-AN27/$G27 -> -72.384615 | BJ27: =-AO27/$G27 -> -189.3976 | BK27: =-AP27/$G27 -> -34.635012 | BL27: =AQ27/$G27 -> 41.48961 | BM27: =AR27/$G27 -> -322.31117 | BN27: =-AT27/$G27 -> -90.863367 | BO27: =AU27/$G27 -> -413.17454 | BP27: =AW27/$G27 -> 75.972802 | BQ27: =AX27/$G27 -> -246.33837
B28: FEBRERO | C28: =B28 -> FEBRERO | D28: 162-2026B | E28: 34 | F28: 46070 | G28: 46.8 | H28: POTA ALAS CONGELADAS | I28: Alas | J28: 1-2 kg | K28: China | L28: Dalian | M28: AVANCE GROUP | N28: James | O28: 1500 | P28: 70200 | Q28: 1380.2137 | R28: 5606 | S28: =P28-R28 -> 64594 | T28: 2 | U28: ECO SIROCCO 26007N | V28: LIMG02851300 | W28: ONE | X28: PAITA | Y28: 10006720 | Z28: Compensación | AA28: =B28&Y28&Z28 -> FEBRERO10006720Compensación | AB28: =INDEX('Detalle Costos'!$L$5:$L$158,MATCH(Resumen!AA28,'Detalle Costos'!$C$5:$C$158,0))*1000*0+AI28 -> 1639.7682 | AC28: =IFERROR(INDEX('Detalle Costos'!$X$5:$X$158,MATCH(Resumen!AA28,'Detalle Costos'!$C$5:$C$158,0))*AG28,0) -> 49747.445 | AD28: =IFERROR(INDEX('Detalle Costos'!$Z$5:$Z$158,MATCH(Resumen!AA28,'Detalle Costos'!$C$5:$C$158,0))*AG28,0) -> 11383.153 | AE28: =IFERROR(INDEX('Detalle Costos'!$Y$5:$Y$158,MATCH(Resumen!AA28,'Detalle Costos'!$C$5:$C$158,0))*AG28,0) -> 745.58931 | AF28: =IFERROR(INDEX('Detalle Costos'!$AA$5:$AA$158,MATCH(Resumen!AA28,'Detalle Costos'!$C$5:$C$158,0))*AG28,0) -> 14864.963 | AG28: =AB28*G28 -> 76741.15 | AH28: =+G28 -> 46.8 | AI28: =1.63976816895275*1000 -> 1639.7682 | AJ28: =+AI28*AH28 -> 76741.15 | AK28: =P28-AG28 -> -6541.1503 | AL28: =AK28/P28 -> -0.093178779 | AM28: =R28 -> 5606 | AN28: =1882/26*G28 -> 3387.6 | AO28: =SUM(AM28:AN28) -> 8993.6 | AP28: =56604/1634.3*G28 -> 1620.9186 | AQ28: =S28*0.03 -> 1937.82 | AR28: =AK28-AO28-AP28+AQ28 -> -15217.849 | AS28: =AR28/P28 -> -0.21677847 | AT28: =148498/1634.3*G28 -> 4252.4056 | AU28: =AR28-AT28 -> -19470.254 | AV28: =AU28/P28 -> -0.27735405 | AW28: =124162.35/1634.3*G28 -> 3555.5271 | AX28: =AR28+AW28 -> -11662.322 | AY28: =AX28/P28 -> -0.16612994 | BA28: =P28/$G28 -> 1500 | BB28: =-AC28/$G28 -> -1062.9796 | BC28: =-AD28/$G28 -> -243.22976 | BD28: =-AE28/$G28 -> -15.931396 | BE28: =-AF28/$G28 -> -317.62741 | BF28: =-AG28/$G28 -> -1639.7682 | BG28: =AK28/$G28 -> -139.76817 | BH28: =-AM28/$G28 -> -119.78632 | BI28: =-AN28/$G28 -> -72.384615 | BJ28: =-AO28/$G28 -> -192.17094 | BK28: =-AP28/$G28 -> -34.635012 | BL28: =AQ28/$G28 -> 41.40641 | BM28: =AR28/$G28 -> -325.16771 | BN28: =-AT28/$G28 -> -90.863367 | BO28: =AU28/$G28 -> -416.03108 | BP28: =AW28/$G28 -> 75.972802 | BQ28: =AX28/$G28 -> -249.19491
B29: FEBRERO | C29: =B29 -> FEBRERO | D29: 162-2026C | E29: 34 | F29: 46070 | G29: 81 | H29: POTA ALAS CONGELADAS | I29: Alas | J29: 1-2 kg | K29: China | L29: Xiamen | M29: AVANCE GROUP | N29: James | O29: 1500 | P29: 121500 | Q29: 1385.0741 | R29: 9309 | S29: =P29-R29 -> 112191 | T29: 3 | U29: ECO SIROCCO 26007N | V29: LIMG02630500 | W29: ONE | X29: PAITA | Y29: 10006720 | Z29: Compensación | AA29: =B29&Y29&Z29 -> FEBRERO10006720Compensación | AB29: =INDEX('Detalle Costos'!$L$5:$L$158,MATCH(Resumen!AA29,'Detalle Costos'!$C$5:$C$158,0))*1000*0+AI29 -> 1639.7682 | AC29: =IFERROR(INDEX('Detalle Costos'!$X$5:$X$158,MATCH(Resumen!AA29,'Detalle Costos'!$C$5:$C$158,0))*AG29,0) -> 86101.348 | AD29: =IFERROR(INDEX('Detalle Costos'!$Z$5:$Z$158,MATCH(Resumen!AA29,'Detalle Costos'!$C$5:$C$158,0))*AG29,0) -> 19701.611 | AE29: =IFERROR(INDEX('Detalle Costos'!$Y$5:$Y$158,MATCH(Resumen!AA29,'Detalle Costos'!$C$5:$C$158,0))*AG29,0) -> 1290.443 | AF29: =IFERROR(INDEX('Detalle Costos'!$AA$5:$AA$158,MATCH(Resumen!AA29,'Detalle Costos'!$C$5:$C$158,0))*AG29,0) -> 25727.82 | AG29: =AB29*G29 -> 132821.22 | AH29: =+G29 -> 81 | AI29: =1.63976816895275*1000 -> 1639.7682 | AJ29: =+AI29*AH29 -> 132821.22 | AK29: =P29-AG29 -> -11321.222 | AL29: =AK29/P29 -> -0.093178779 | AM29: =R29 -> 9309 | AN29: =1882/26*G29 -> 5863.1538 | AO29: =SUM(AM29:AN29) -> 15172.154 | AP29: =56604/1634.3*G29 -> 2805.436 | AQ29: =S29*0.03 -> 3365.73 | AR29: =AK29-AO29-AP29+AQ29 -> -25933.081 | AS29: =AR29/P29 -> -0.213441 | AT29: =148498/1634.3*G29 -> 7359.9327 | AU29: =AR29-AT29 -> -33293.014 | AV29: =AU29/P29 -> -0.27401658 | AW29: =124162.35/1634.3*G29 -> 6153.7969 | AX29: =AR29+AW29 -> -19779.285 | AY29: =AX29/P29 -> -0.16279247 | BA29: =P29/$G29 -> 1500 | BB29: =-AC29/$G29 -> -1062.9796 | BC29: =-AD29/$G29 -> -243.22976 | BD29: =-AE29/$G29 -> -15.931396 | BE29: =-AF29/$G29 -> -317.62741 | BF29: =-AG29/$G29 -> -1639.7682 | BG29: =AK29/$G29 -> -139.76817 | BH29: =-AM29/$G29 -> -114.92593 | BI29: =-AN29/$G29 -> -72.384615 | BJ29: =-AO29/$G29 -> -187.31054 | BK29: =-AP29/$G29 -> -34.635012 | BL29: =AQ29/$G29 -> 41.552222 | BM29: =AR29/$G29 -> -320.1615 | BN29: =-AT29/$G29 -> -90.863367 | BO29: =AU29/$G29 -> -411.02487 | BP29: =AW29/$G29 -> 75.972802 | BQ29: =AX29/$G29 -> -244.1887
B30: FEBRERO | C30: =B30 -> FEBRERO | D30: 164-2026 | E30: 40 | F30: 46080 | G30: 27 | H30: POTA FILETE DARUMA | I30: Daruma | K30: China | L30: Yantai | M30: SACRAMENTO CO., LTD | N30: julia | O30: 3400 | P30: 91800 | Q30: 3292.5926 | R30: 2900 | S30: =P30-R30 -> 88900 | T30: 1 | U30: ECO SIROCCO 26009S | V30: 6445569300 | W30: COSCO | X30: PAITA | Y30: 10009239 | Z30: Compensación | AA30: =B30&Y30&Z30 -> FEBRERO10009239Compensación | AB30: =INDEX('Detalle Costos'!$L$5:$L$158,MATCH(Resumen!AA30,'Detalle Costos'!$C$5:$C$158,0))*1000*0+AI30 -> 2114.7381 | AC30: =IFERROR(INDEX('Detalle Costos'!$X$5:$X$158,MATCH(Resumen!AA30,'Detalle Costos'!$C$5:$C$158,0))*AG30,0) -> 29045.69 | AD30: =IFERROR(INDEX('Detalle Costos'!$Z$5:$Z$158,MATCH(Resumen!AA30,'Detalle Costos'!$C$5:$C$158,0))*AG30,0) -> 18974.7 | AE30: =IFERROR(INDEX('Detalle Costos'!$Y$5:$Y$158,MATCH(Resumen!AA30,'Detalle Costos'!$C$5:$C$158,0))*AG30,0) -> 365.21 | AF30: =IFERROR(INDEX('Detalle Costos'!$AA$5:$AA$158,MATCH(Resumen!AA30,'Detalle Costos'!$C$5:$C$158,0))*AG30,0) -> 8712.33 | AG30: =AB30*G30 -> 57097.93 | AH30: 27 | AI30: =2.11473814814815*1000 -> 2114.7381 | AJ30: =AI30*AH30 -> 57097.93 | AK30: =P30-AG30 -> 34702.07 | AL30: =AK30/P30 -> 0.37801819 | AM30: =R30 -> 2900 | AN30: =1882/26*G30 -> 1954.3846 | AO30: =SUM(AM30:AN30) -> 4854.3846 | AP30: =56604/1634.3*G30 -> 935.14532 | AQ30: =S30*0.03 -> 2667 | AR30: =AK30-AO30-AP30+AQ30 -> 31579.54 | AS30: =AR30/P30 -> 0.3440037 | AT30: =148498/1634.3*G30 -> 2453.3109 | AU30: =AR30-AT30 -> 29126.229 | AV30: =AU30/P30 -> 0.31727918 | AW30: =124162.35/1634.3*G30 -> 2051.2656 | AX30: =AR30+AW30 -> 33630.806 | AY30: =AX30/P30 -> 0.36634865 | BA30: =P30/$G30 -> 3400 | BB30: =-AC30/$G30 -> -1075.7663 | BC30: =-AD30/$G30 -> -702.76667 | BD30: =-AE30/$G30 -> -13.526296 | BE30: =-AF30/$G30 -> -322.67889 | BF30: =-AG30/$G30 -> -2114.7381 | BG30: =AK30/$G30 -> 1285.2619 | BH30: =-AM30/$G30 -> -107.40741 | BI30: =-AN30/$G30 -> -72.384615 | BJ30: =-AO30/$G30 -> -179.79202 | BK30: =-AP30/$G30 -> -34.635012 | BL30: =AQ30/$G30 -> 98.777778 | BM30: =AR30/$G30 -> 1169.6126 | BN30: =-AT30/$G30 -> -90.863367 | BO30: =AU30/$G30 -> 1078.7492 | BP30: =AW30/$G30 -> 75.972802 | BQ30: =AX30/$G30 -> 1245.5854
B31: FEBRERO | C31: =B31 -> FEBRERO | D31: 168-2026A | E31: 43 | F31: 46077 | G31: 351 | H31: POTA FILETE CONGELADO | I31: Filete | J31: 2-4 AA | K31: China | L31: Qingdao | M31: AVANCE GROUP | N31: James | O31: 1300 | P31: 456300 | Q31: 1300 | R31: =3103*T31 -> 40339 | S31: =P31-R31 -> 415961 | T31: 13 | U31: ECO MARIN 26008N | V31: 6445505270 | W31: COSCO | X31: PAITA | Y31: 10005721 | Z31: Compensación | AA31: =B31&Y31&Z31 -> FEBRERO10005721Compensación | AB31: =INDEX('Detalle Costos'!$L$5:$L$158,MATCH(Resumen!AA31,'Detalle Costos'!$C$5:$C$158,0))*1000*0+AI31 -> 1740.7827 | AC31: =IFERROR(INDEX('Detalle Costos'!$X$5:$X$158,MATCH(Resumen!AA31,'Detalle Costos'!$C$5:$C$158,0))*AG31,0) -> 370785.72 | AD31: =IFERROR(INDEX('Detalle Costos'!$Z$5:$Z$158,MATCH(Resumen!AA31,'Detalle Costos'!$C$5:$C$158,0))*AG31,0) -> 122493.73 | AE31: =IFERROR(INDEX('Detalle Costos'!$Y$5:$Y$158,MATCH(Resumen!AA31,'Detalle Costos'!$C$5:$C$158,0))*AG31,0) -> 6516.3555 | AF31: =IFERROR(INDEX('Detalle Costos'!$AA$5:$AA$158,MATCH(Resumen!AA31,'Detalle Costos'!$C$5:$C$158,0))*AG31,0) -> 111218.93 | AG31: =AB31*G31 -> 611014.73 | AH31: =+G31 -> 351 | AI31: =1.7407827151654*1000 -> 1740.7827 | AJ31: =+AI31*AH31 -> 611014.73 | AK31: =P31-AG31 -> -154714.73 | AL31: =AK31/P31 -> -0.33906363 | AM31: =R31 -> 40339 | AN31: =1882/26*G31 -> 25407 | AO31: =SUM(AM31:AN31) -> 65746 | AP31: =56604/1634.3*G31 -> 12156.889 | AQ31: =S31*0.03 -> 12478.83 | AR31: =AK31-AO31-AP31+AQ31 -> -220138.79 | AS31: =AR31/P31 -> -0.48244311 | AT31: =148498/1634.3*G31 -> 31893.042 | AU31: =AR31-AT31 -> -252031.83 | AV31: =AU31/P31 -> -0.55233801 | AW31: =124162.35/1634.3*G31 -> 26666.453 | AX31: =AR31+AW31 -> -193472.34 | AY31: =AX31/P31 -> -0.4240025 | BA31: =P31/$G31 -> 1300 | BB31: =-AC31/$G31 -> -1056.3696 | BC31: =-AD31/$G31 -> -348.98498 | BD31: =-AE31/$G31 -> -18.565115 | BE31: =-AF31/$G31 -> -316.86305 | BF31: =-AG31/$G31 -> -1740.7827 | BG31: =AK31/$G31 -> -440.78272 | BH31: =-AM31/$G31 -> -114.92593 | BI31: =-AN31/$G31 -> -72.384615 | BJ31: =-AO31/$G31 -> -187.31054 | BK31: =-AP31/$G31 -> -34.635012 | BL31: =AQ31/$G31 -> 35.552222 | BM31: =AR31/$G31 -> -627.17605 | BN31: =-AT31/$G31 -> -90.863367 | BO31: =AU31/$G31 -> -718.03941 | BP31: =AW31/$G31 -> 75.972802 | BQ31: =AX31/$G31 -> -551.20324
B32: FEBRERO | C32: =B32 -> FEBRERO | D32: 168-2026B | E32: 43 | F32: 46075 | G32: 135 | H32: POTA FILETE CONGELADO | I32: Filete | J32: 2-4 AA | K32: China | L32: shidao | M32: AVANCE GROUP | N32: James | O32: 1300 | P32: 175500 | Q32: 1300 | R32: =3103*T32 -> 15515 | S32: =P32-R32 -> 159985 | T32: 5 | U32: ECO MARIN 26008S | V32: 6445260920 | W32: COSCO | X32: PAITA | Y32: 10005721 | Z32: Compensación | AA32: =B32&Y32&Z32 -> FEBRERO10005721Compensación | AB32: =INDEX('Detalle Costos'!$L$5:$L$158,MATCH(Resumen!AA32,'Detalle Costos'!$C$5:$C$158,0))*1000*0+AI32 -> 1763.7778 | AC32: =IFERROR(INDEX('Detalle Costos'!$X$5:$X$158,MATCH(Resumen!AA32,'Detalle Costos'!$C$5:$C$158,0))*AG32,0) -> 144493.71 | AD32: =IFERROR(INDEX('Detalle Costos'!$Z$5:$Z$158,MATCH(Resumen!AA32,'Detalle Costos'!$C$5:$C$158,0))*AG32,0) -> 47735.316 | AE32: =IFERROR(INDEX('Detalle Costos'!$Y$5:$Y$158,MATCH(Resumen!AA32,'Detalle Costos'!$C$5:$C$158,0))*AG32,0) -> 2539.3977 | AF32: =IFERROR(INDEX('Detalle Costos'!$AA$5:$AA$158,MATCH(Resumen!AA32,'Detalle Costos'!$C$5:$C$158,0))*AG32,0) -> 43341.573 | AG32: =AB32*G32 -> 238110 | AH32: =+G32 -> 135 | AI32: =+AJ32/AH32 -> 1763.7778 | AJ32: 238110 | AK32: =P32-AG32 -> -62610 | AL32: =AK32/P32 -> -0.35675214 | AM32: =R32 -> 15515 | AN32: =1882/26*G32 -> 9771.9231 | AO32: =SUM(AM32:AN32) -> 25286.923 | AP32: =56604/1634.3*G32 -> 4675.7266 | AQ32: =S32*0.03 -> 4799.55 | AR32: =AK32-AO32-AP32+AQ32 -> -87773.1 | AS32: =AR32/P32 -> -0.50013162 | AT32: =148498/1634.3*G32 -> 12266.554 | AU32: =AR32-AT32 -> -100039.65 | AV32: =AU32/P32 -> -0.57002652 | AW32: =124162.35/1634.3*G32 -> 10256.328 | AX32: =AR32+AW32 -> -77516.771 | AY32: =AX32/P32 -> -0.44169101 | BA32: =P32/$G32 -> 1300 | BB32: =-AC32/$G32 -> -1070.3238 | BC32: =-AD32/$G32 -> -353.59493 | BD32: =-AE32/$G32 -> -18.810353 | BE32: =-AF32/$G32 -> -321.04869 | BF32: =-AG32/$G32 -> -1763.7778 | BG32: =AK32/$G32 -> -463.77778 | BH32: =-AM32/$G32 -> -114.92593 | BI32: =-AN32/$G32 -> -72.384615 | BJ32: =-AO32/$G32 -> -187.31054 | BK32: =-AP32/$G32 -> -34.635012 | BL32: =AQ32/$G32 -> 35.552222 | BM32: =AR32/$G32 -> -650.17111 | BN32: =-AT32/$G32 -> -90.863367 | BO32: =AU32/$G32 -> -741.03448 | BP32: =AW32/$G32 -> 75.972802 | BQ32: =AX32/$G32 -> -574.19831
B33: FEBRERO | C33: =B33 -> FEBRERO | D33: 168-2026C | E33: 43 | F33: 46075 | G33: 54 | H33: POTA FILETE CONGELADO | I33: Filete | J33: 2-4 AA | K33: China | L33: Xiamen | M33: AVANCE GROUP | N33: James | O33: 1300 | P33: 70200 | Q33: 1300 | R33: =3103*T33 -> 6206 | S33: =P33-R33 -> 63994 | T33: 2 | U33: ECO MARIN 26008S | V33: 6445502930 | W33: COSCO | X33: PAITA | Y33: 10005721 | Z33: Compensación | AA33: =B33&Y33&Z33 -> FEBRERO10005721Compensación | AB33: =INDEX('Detalle Costos'!$L$5:$L$158,MATCH(Resumen!AA33,'Detalle Costos'!$C$5:$C$158,0))*1000*0+AI33 -> 1740.7827 | AC33: =IFERROR(INDEX('Detalle Costos'!$X$5:$X$158,MATCH(Resumen!AA33,'Detalle Costos'!$C$5:$C$158,0))*AG33,0) -> 57043.957 | AD33: =IFERROR(INDEX('Detalle Costos'!$Z$5:$Z$158,MATCH(Resumen!AA33,'Detalle Costos'!$C$5:$C$158,0))*AG33,0) -> 18845.189 | AE33: =IFERROR(INDEX('Detalle Costos'!$Y$5:$Y$158,MATCH(Resumen!AA33,'Detalle Costos'!$C$5:$C$158,0))*AG33,0) -> 1002.5162 | AF33: =IFERROR(INDEX('Detalle Costos'!$AA$5:$AA$158,MATCH(Resumen!AA33,'Detalle Costos'!$C$5:$C$158,0))*AG33,0) -> 17110.605 | AG33: =AB33*G33 -> 94002.267 | AH33: =+G33 -> 54 | AI33: =1.7407827151654*1000 -> 1740.7827 | AJ33: =+AI33*AH33 -> 94002.267 | AK33: =P33-AG33 -> -23802.267 | AL33: =AK33/P33 -> -0.33906363 | AM33: =R33 -> 6206 | AN33: =1882/26*G33 -> 3908.7692 | AO33: =SUM(AM33:AN33) -> 10114.769 | AP33: =56604/1634.3*G33 -> 1870.2906 | AQ33: =S33*0.03 -> 1919.82 | AR33: =AK33-AO33-AP33+AQ33 -> -33867.506 | AS33: =AR33/P33 -> -0.48244311 | AT33: =148498/1634.3*G33 -> 4906.6218 | AU33: =AR33-AT33 -> -38774.128 | AV33: =AU33/P33 -> -0.55233801 | AW33: =124162.35/1634.3*G33 -> 4102.5313 | AX33: =AR33+AW33 -> -29764.975 | AY33: =AX33/P33 -> -0.4240025 | BA33: =P33/$G33 -> 1300 | BB33: =-AC33/$G33 -> -1056.3696 | BC33: =-AD33/$G33 -> -348.98498 | BD33: =-AE33/$G33 -> -18.565115 | BE33: =-AF33/$G33 -> -316.86305 | BF33: =-AG33/$G33 -> -1740.7827 | BG33: =AK33/$G33 -> -440.78272 | BH33: =-AM33/$G33 -> -114.92593 | BI33: =-AN33/$G33 -> -72.384615 | BJ33: =-AO33/$G33 -> -187.31054 | BK33: =-AP33/$G33 -> -34.635012 | BL33: =AQ33/$G33 -> 35.552222 | BM33: =AR33/$G33 -> -627.17605 | BN33: =-AT33/$G33 -> -90.863367 | BO33: =AU33/$G33 -> -718.03941 | BP33: =AW33/$G33 -> 75.972802 | BQ33: =AX33/$G33 -> -551.20324
B34: FEBRERO | C34: =B34 -> FEBRERO | D34: 170-2026A | E34: 43 | F34: 46076 | G34: 156 | H34: POTA REJOS CONGELADOS | I34: Rejos | J34: 9 FCL 1-2 / 1 FCL 2-UP | K34: España | L34: Vigo | M34: KULALIA | N34: Ramon | O34: 2500 | P34: 390000 | Q34: 2337.2308 | R34: 25392 | S34: =P34-R34 -> 364608 | T34: 4 | U34: CAPE SABLE 609N | V34: 11428031 | W34: HAPAG | X34: PAITA | Y34: 10007162 | Z34: Compensación | AA34: =B34&Y34&Z34 -> FEBRERO10007162Compensación | AB34: =INDEX('Detalle Costos'!$L$5:$L$158,MATCH(Resumen!AA34,'Detalle Costos'!$C$5:$C$158,0))*1000*0+AI34 -> 1715.2908 | AC34: =IFERROR(INDEX('Detalle Costos'!$X$5:$X$158,MATCH(Resumen!AA34,'Detalle Costos'!$C$5:$C$158,0))*AG34,0) -> 167980.9 | AD34: =IFERROR(INDEX('Detalle Costos'!$Z$5:$Z$158,MATCH(Resumen!AA34,'Detalle Costos'!$C$5:$C$158,0))*AG34,0) -> 47932.005 | AE34: =IFERROR(INDEX('Detalle Costos'!$Y$5:$Y$158,MATCH(Resumen!AA34,'Detalle Costos'!$C$5:$C$158,0))*AG34,0) -> 2495.565 | AF34: =IFERROR(INDEX('Detalle Costos'!$AA$5:$AA$158,MATCH(Resumen!AA34,'Detalle Costos'!$C$5:$C$158,0))*AG34,0) -> 49176.892 | AG34: =AB34*G34 -> 267585.37 | AH34: =+G34 -> 156 | AI34: 1715.2908 | AJ34: =AI34*AH34 -> 267585.37 | AK34: =P34-AG34 -> 122414.63 | AL34: =AK34/P34 -> 0.31388367 | AM34: =R34 -> 25392 | AN34: =1882/26*G34 -> 11292 | AO34: =SUM(AM34:AN34) -> 36684 | AP34: =56604/1634.3*G34 -> 5403.0619 | AQ34: =S34*0.03 -> 10938.24 | AR34: =AK34-AO34-AP34+AQ34 -> 91265.811 | AS34: =AR34/P34 -> 0.2340149 | AT34: =148498/1634.3*G34 -> 14174.685 | AU34: =AR34-AT34 -> 77091.125 | AV34: =AU34/P34 -> 0.19766955 | AW34: =124162.35/1634.3*G34 -> 11851.757 | AX34: =AR34+AW34 -> 103117.57 | AY34: =AX34/P34 -> 0.26440402 | BA34: =P34/$G34 -> 2500 | BB34: =-AC34/$G34 -> -1076.8007 | BC34: =-AD34/$G34 -> -307.25644 | BD34: =-AE34/$G34 -> -15.997212 | BE34: =-AF34/$G34 -> -315.23649 | BF34: =-AG34/$G34 -> -1715.2908 | BG34: =AK34/$G34 -> 784.70918 | BH34: =-AM34/$G34 -> -162.76923 | BI34: =-AN34/$G34 -> -72.384615 | BJ34: =-AO34/$G34 -> -235.15385 | BK34: =-AP34/$G34 -> -34.635012 | BL34: =AQ34/$G34 -> 70.116923 | BM34: =AR34/$G34 -> 585.03725 | BN34: =-AT34/$G34 -> -90.863367 | BO34: =AU34/$G34 -> 494.17388 | BP34: =AW34/$G34 -> 75.972802 | BQ34: =AX34/$G34 -> 661.01005
B35: FEBRERO | C35: =B35 -> FEBRERO | E35: 46080 | F35: 46080 | G35: 0 | H35: RESIDUOS DE POTA | I35: Residuos | J35: Residuos | K35: Residuos | L35: Residuos | M35: PROVEEDORA DE PRODUCTOS MARINOS | O35: 0 | P35: 40026 | Q35: 0 | R35: 0 | S35: =P35-R35 -> 40026 | AB35: 0 | AC35: =IFERROR(INDEX('Detalle Costos'!$X$5:$X$158,MATCH(Resumen!AA35,'Detalle Costos'!$C$5:$C$158,0))*AG35,0) -> 0 | AD35: =IFERROR(INDEX('Detalle Costos'!$Z$5:$Z$158,MATCH(Resumen!AA35,'Detalle Costos'!$C$5:$C$158,0))*AG35,0) -> 0 | AE35: =IFERROR(INDEX('Detalle Costos'!$Y$5:$Y$158,MATCH(Resumen!AA35,'Detalle Costos'!$C$5:$C$158,0))*AG35,0) -> 0 | AF35: =IFERROR(INDEX('Detalle Costos'!$AA$5:$AA$158,MATCH(Resumen!AA35,'Detalle Costos'!$C$5:$C$158,0))*AG35,0) -> 0 | AG35: =AB35*G35 -> 0 | AK35: =P35-AG35 -> 40026 | AL35: =AK35/P35 -> 1 | AM35: =R35 -> 0 | AN35: =1882/26*G35 -> 0 | AO35: =SUM(AM35:AN35) -> 0 | AP35: =56604/1634.3*G35 -> 0 | AQ35: 0 | AR35: =AK35-AO35-AP35+AQ35 -> 40026 | AS35: =AR35/P35 -> 1 | AT35: =131251/248*G35 -> 0 | AU35: =AR35-AT35 -> 40026 | AV35: =AU35/P35 -> 1 | AW35: =123530/248*G35 -> 0 | AX35: =AR35+AW35 -> 40026 | AY35: =AX35/P35 -> 1 | BA35: 0 | BB35: 0 | BC35: 0 | BD35: 0 | BE35: 0 | BF35: 0 | BG35: 0 | BH35: 0 | BI35: 0 | BJ35: 0 | BK35: 0 | BL35: 0 | BM35: 0 | BN35: 0 | BO35: 0 | BP35: 0 | BQ35: 0
B36: FEBRERO | C36: MARZO | D36: 150-2026B | E36: 325 | F36: 46084 | G36: 26 | H36: POTA REJOS CONGELADOS | I36: Rejos | J36: 1-2 KG | K36: España | L36: Vigo | M36: OVERSEA | N36: Avelino | O36: 2600 | P36: 67600 | Q36: 2518.6154 | R36: 4232 | S36: =P36-R36 -> 63368 | T36: 1 | U36: LEONIDAS Z 610N | V36: 51077247 | Y36: 10007162 | Z36: Inventario final | AA36: =B36&Y36&Z36 -> FEBRERO10007162Inventario final | AB36: =IFERROR(AG36/G36,0) -> 1665.8462 | AC36: =IFERROR(INDEX('Costos Producción Febrero'!$G$34:$G$57,MATCH(Resumen!Y36,'Costos Producción Febrero'!$B$34:$B$57,0))*AI36*G36,0) -> 26556.782 | AD36: =IFERROR(INDEX('Costos Producción Febrero'!$H$34:$H$57,MATCH(Resumen!Y36,'Costos Producción Febrero'!$B$34:$B$57,0))*AI36*G36,0) -> 7540 | AE36: =IFERROR(INDEX('Costos Producción Febrero'!$I$34:$I$57,MATCH(Resumen!Y36,'Costos Producción Febrero'!$B$34:$B$57,0))*AI36*G36,0) -> 401.52781 | AF36: =IFERROR(INDEX('Costos Producción Febrero'!$J$34:$J$57,MATCH(Resumen!Y36,'Costos Producción Febrero'!$B$34:$B$57,0))*AI36*G36,0) -> 8813.6917 | AG36: =SUM(AC36:AF36) -> 43312.002 | AI36: =INDEX('Costos Producción Febrero'!$F$5:$F$28,MATCH(Resumen!Y36,'Costos Producción Febrero'!$B$5:$B$28,0)) -> 1665.8462 | AK36: =P36-AG36 -> 24287.998 | AL36: =AK36/P36 -> 0.35928992 | AM36: =R36 -> 4232 | AN36: =1882/26*G36 -> 1882 | AO36: =SUM(AM36:AN36) -> 6114 | AP36: =78579/1995.8*G36 -> 1023.6767 | AQ36: =S36*0.03 -> 1901.04 | AR36: =AK36-AO36-AP36+AQ36 -> 19051.362 | AS36: =AR36/P36 -> 0.28182488 | AT36: =154473/1995.8*G36 -> 2012.375 | AU36: =AR36-AT36 -> 17038.987 | AV36: =AU36/P36 -> 0.25205602 | AW36: =123484.35/1997.8*G36 -> 1607.0643 | AX36: =AR36+AW36 -> 20658.426 | AY36: =AX36/P36 -> 0.30559802 | BA36: =P36/$G36 -> 2600 | BB36: =-AC36/$G36 -> -1021.4147 | BC36: =-AD36/$G36 -> -290 | BD36: =-AE36/$G36 -> -15.443377 | BE36: =-AF36/$G36 -> -338.98814 | BF36: =-AG36/$G36 -> -1665.8462 | BG36: =AK36/$G36 -> 934.15379 | BH36: =-AM36/$G36 -> -162.76923 | BI36: =-AN36/$G36 -> -72.384615 | BJ36: =-AO36/$G36 -> -235.15385 | BK36: =-AP36/$G36 -> -39.372182 | BL36: =AQ36/$G36 -> 73.116923 | BM36: =AR36/$G36 -> 732.74468 | BN36: =-AT36/$G36 -> -77.399038 | BO36: =AU36/$G36 -> 655.34565 | BP36: =AW36/$G36 -> 61.810166 | BQ36: =AX36/$G36 -> 794.55485
B37: FEBRERO | C37: MARZO | D37: 150-2026C | E37: 325 | F37: 46084 | G37: 26 | H37: POTA REJOS CONGELADOS | I37: Rejos | J37: 1-2 KG | K37: España | L37: Vigo | M37: OVERSEA | N37: Avelino | O37: 2600 | P37: 67600 | Q37: 2518.6154 | R37: 4232 | S37: =P37-R37 -> 63368 | T37: 1 | U37: LEONIDAS Z 610N | V37: 37563181 | Y37: 10007162 | Z37: Inventario final | AA37: =B37&Y37&Z37 -> FEBRERO10007162Inventario final | AB37: =IFERROR(AG37/G37,0) -> 1665.8462 | AC37: =IFERROR(INDEX('Costos Producción Febrero'!$G$34:$G$57,MATCH(Resumen!Y37,'Costos Producción Febrero'!$B$34:$B$57,0))*AI37*G37,0) -> 26556.782 | AD37: =IFERROR(INDEX('Costos Producción Febrero'!$H$34:$H$57,MATCH(Resumen!Y37,'Costos Producción Febrero'!$B$34:$B$57,0))*AI37*G37,0) -> 7540 | AE37: =IFERROR(INDEX('Costos Producción Febrero'!$I$34:$I$57,MATCH(Resumen!Y37,'Costos Producción Febrero'!$B$34:$B$57,0))*AI37*G37,0) -> 401.52781 | AF37: =IFERROR(INDEX('Costos Producción Febrero'!$J$34:$J$57,MATCH(Resumen!Y37,'Costos Producción Febrero'!$B$34:$B$57,0))*AI37*G37,0) -> 8813.6917 | AG37: =SUM(AC37:AF37) -> 43312.002 | AI37: =INDEX('Costos Producción Febrero'!$F$5:$F$28,MATCH(Resumen!Y37,'Costos Producción Febrero'!$B$5:$B$28,0)) -> 1665.8462 | AK37: =P37-AG37 -> 24287.998 | AL37: =AK37/P37 -> 0.35928992 | AM37: =R37 -> 4232 | AN37: =1882/26*G37 -> 1882 | AO37: =SUM(AM37:AN37) -> 6114 | AP37: =78579/1995.8*G37 -> 1023.6767 | AQ37: =S37*0.03 -> 1901.04 | AR37: =AK37-AO37-AP37+AQ37 -> 19051.362 | AS37: =AR37/P37 -> 0.28182488 | AT37: =154473/1995.8*G37 -> 2012.375 | AU37: =AR37-AT37 -> 17038.987 | AV37: =AU37/P37 -> 0.25205602 | AW37: =123484.35/1997.8*G37 -> 1607.0643 | AX37: =AR37+AW37 -> 20658.426 | AY37: =AX37/P37 -> 0.30559802 | BA37: =P37/$G37 -> 2600 | BB37: =-AC37/$G37 -> -1021.4147 | BC37: =-AD37/$G37 -> -290 | BD37: =-AE37/$G37 -> -15.443377 | BE37: =-AF37/$G37 -> -338.98814 | BF37: =-AG37/$G37 -> -1665.8462 | BG37: =AK37/$G37 -> 934.15379 | BH37: =-AM37/$G37 -> -162.76923 | BI37: =-AN37/$G37 -> -72.384615 | BJ37: =-AO37/$G37 -> -235.15385 | BK37: =-AP37/$G37 -> -39.372182 | BL37: =AQ37/$G37 -> 73.116923 | BM37: =AR37/$G37 -> 732.74468 | BN37: =-AT37/$G37 -> -77.399038 | BO37: =AU37/$G37 -> 655.34565 | BP37: =AW37/$G37 -> 61.810166 | BQ37: =AX37/$G37 -> 794.55485
B38: FEBRERO | C38: MARZO | D38: 159-2026A | E38: 30 | F38: 46084 | G38: 24 | H38: POTA FILETE CONGELADO | I38: Filete | J38: B | K38: Japón | L38: Sendai | M38: TSUJINO | N38: Jose | O38: 1700 | P38: =40800-1190 -> 39610 | Q38: 1562.375 | R38: 3303 | S38: =P38-R38 -> 36307 | T38: 1 | U38: ECO SIROCCO 26009N | V38: LIMG03265300 | W38: ONE | X38: PAITA | Y38: 10005721 | Z38: Inventario final | AA38: =B38&Y38&Z38 -> FEBRERO10005721Inventario final | AB38: =IFERROR(AG38/G38,0) -> 1672.2066 | AC38: =IFERROR(INDEX('Costos Producción Febrero'!$G$34:$G$57,MATCH(Resumen!Y38,'Costos Producción Febrero'!$B$34:$B$57,0))*AI38*G38,0) -> 24373.183 | AD38: =IFERROR(INDEX('Costos Producción Febrero'!$H$34:$H$57,MATCH(Resumen!Y38,'Costos Producción Febrero'!$B$34:$B$57,0))*AI38*G38,0) -> 7141.8487 | AE38: =IFERROR(INDEX('Costos Producción Febrero'!$I$34:$I$57,MATCH(Resumen!Y38,'Costos Producción Febrero'!$B$34:$B$57,0))*AI38*G38,0) -> 437.52573 | AF38: =IFERROR(INDEX('Costos Producción Febrero'!$J$34:$J$57,MATCH(Resumen!Y38,'Costos Producción Febrero'!$B$34:$B$57,0))*AI38*G38,0) -> 8180.4001 | AG38: =SUM(AC38:AF38) -> 40132.958 | AI38: =INDEX('Costos Producción Febrero'!$F$5:$F$28,MATCH(Resumen!Y38,'Costos Producción Febrero'!$B$5:$B$28,0)) -> 1672.2066 | AK38: =P38-AG38 -> -522.95776 | AL38: =AK38/P38 -> -0.01320267 | AM38: =R38 -> 3303 | AN38: =1882/26*G38 -> 1737.2308 | AO38: =SUM(AM38:AN38) -> 5040.2308 | AP38: =78579/1995.8*G38 -> 944.93236 | AQ38: =S38*0.03 -> 1089.21 | AR38: =AK38-AO38-AP38+AQ38 -> -5418.9109 | AS38: =AR38/P38 -> -0.13680664 | AT38: =154473/1995.8*G38 -> 1857.5769 | AU38: =AR38-AT38 -> -7276.4878 | AV38: =AU38/P38 -> -0.1837033 | AW38: =123484.35/1997.8*G38 -> 1483.444 | AX38: =AR38+AW38 -> -3935.4669 | AY38: =AX38/P38 -> -0.099355388 | BA38: =P38/$G38 -> 1650.4167 | BB38: =-AC38/$G38 -> -1015.5493 | BC38: =-AD38/$G38 -> -297.57703 | BD38: =-AE38/$G38 -> -18.230239 | BE38: =-AF38/$G38 -> -340.85 | BF38: =-AG38/$G38 -> -1672.2066 | BG38: =AK38/$G38 -> -21.789907 | BH38: =-AM38/$G38 -> -137.625 | BI38: =-AN38/$G38 -> -72.384615 | BJ38: =-AO38/$G38 -> -210.00962 | BK38: =-AP38/$G38 -> -39.372182 | BL38: =AQ38/$G38 -> 45.38375 | BM38: =AR38/$G38 -> -225.78795 | BN38: =-AT38/$G38 -> -77.399038 | BO38: =AU38/$G38 -> -303.18699 | BP38: =AW38/$G38 -> 61.810166 | BQ38: =AX38/$G38 -> -163.97779
B39: FEBRERO | C39: MARZO | D39: 161-2026A | E39: 30 | F39: 46085 | G39: 72 | H39: POTA NUCAS | I39: Nucas | J39: 500-up | K39: Tailandia | L39: Lat Krabang | M39: TSUJINO | N39: Jose | O39: 1400 | P39: =100800-6160 -> 94640 | Q39: 1266.5417 | R39: 9609 | S39: =P39-R39 -> 85031 | T39: 3 | U39: ECO SIROCCO 26009N | V39: LIMG03094300 | W39: ONE LINE | X39: PAITA | Y39: 10005779 | Z39: Inventario final | AA39: =B39&Y39&Z39 -> FEBRERO10005779Inventario final | AB39: =IFERROR(AG39/G39,0) -> 1765.074 | AC39: =IFERROR(INDEX('Costos Producción Febrero'!$G$34:$G$57,MATCH(Resumen!Y39,'Costos Producción Febrero'!$B$34:$B$57,0))*AI39*G39,0) -> 73785.835 | AD39: =IFERROR(INDEX('Costos Producción Febrero'!$H$34:$H$57,MATCH(Resumen!Y39,'Costos Producción Febrero'!$B$34:$B$57,0))*AI39*G39,0) -> 28080 | AE39: =IFERROR(INDEX('Costos Producción Febrero'!$I$34:$I$57,MATCH(Resumen!Y39,'Costos Producción Febrero'!$B$34:$B$57,0))*AI39*G39,0) -> 811.73262 | AF39: =IFERROR(INDEX('Costos Producción Febrero'!$J$34:$J$57,MATCH(Resumen!Y39,'Costos Producción Febrero'!$B$34:$B$57,0))*AI39*G39,0) -> 24407.757 | AG39: =SUM(AC39:AF39) -> 127085.32 | AI39: =INDEX('Costos Producción Febrero'!$F$5:$F$28,MATCH(Resumen!Y39,'Costos Producción Febrero'!$B$5:$B$28,0)) -> 1765.074 | AK39: =P39-AG39 -> -32445.325 | AL39: =AK39/P39 -> -0.34282887 | AM39: =R39 -> 9609 | AN39: =1882/26*G39 -> 5211.6923 | AO39: =SUM(AM39:AN39) -> 14820.692 | AP39: =78579/1995.8*G39 -> 2834.7971 | AQ39: =S39*0.03 -> 2550.93 | AR39: =AK39-AO39-AP39+AQ39 -> -47549.884 | AS39: =AR39/P39 -> -0.50242904 | AT39: =154473/1995.8*G39 -> 5572.7307 | AU39: =AR39-AT39 -> -53122.615 | AV39: =AU39/P39 -> -0.5613125 | AW39: =123484.35/1997.8*G39 -> 4450.332 | AX39: =AR39+AW39 -> -43099.552 | AY39: =AX39/P39 -> -0.45540524 | BA39: =P39/$G39 -> 1314.4444 | BB39: =-AC39/$G39 -> -1024.8033 | BC39: =-AD39/$G39 -> -390 | BD39: =-AE39/$G39 -> -11.274064 | BE39: =-AF39/$G39 -> -338.99662 | BF39: =-AG39/$G39 -> -1765.074 | BG39: =AK39/$G39 -> -450.62951 | BH39: =-AM39/$G39 -> -133.45833 | BI39: =-AN39/$G39 -> -72.384615 | BJ39: =-AO39/$G39 -> -205.84295 | BK39: =-AP39/$G39 -> -39.372182 | BL39: =AQ39/$G39 -> 35.429583 | BM39: =AR39/$G39 -> -660.41505 | BN39: =-AT39/$G39 -> -77.399038 | BO39: =AU39/$G39 -> -737.81409 | BP39: =AW39/$G39 -> 61.810166 | BQ39: =AX39/$G39 -> -598.60489
B40: FEBRERO | C40: MARZO | D40: 161-2026B | E40: 30 | F40: 46108 | G40: 48 | H40: POTA NUCAS | I40: Nucas | J40: 500-up | K40: Tailandia | L40: Lat Krabang | M40: TSUJINO | N40: Jose | O40: 1400 | P40: 67200 | Q40: 1254.1667 | R40: 7000 | S40: =P40-R40 -> 60200 | T40: 2 | U40: ECO SIROCCO 26013S | V40: 6446527790 | W40: COSCO | X40: PAITA | Y40: 10005779 | Z40: Inventario final | AA40: =B40&Y40&Z40 -> FEBRERO10005779Inventario final | AB40: =IFERROR(AG40/G40,0) -> 1765.074 | AC40: =IFERROR(INDEX('Costos Producción Febrero'!$G$34:$G$57,MATCH(Resumen!Y40,'Costos Producción Febrero'!$B$34:$B$57,0))*AI40*G40,0) -> 49190.557 | AD40: =IFERROR(INDEX('Costos Producción Febrero'!$H$34:$H$57,MATCH(Resumen!Y40,'Costos Producción Febrero'!$B$34:$B$57,0))*AI40*G40,0) -> 18720 | AE40: =IFERROR(INDEX('Costos Producción Febrero'!$I$34:$I$57,MATCH(Resumen!Y40,'Costos Producción Febrero'!$B$34:$B$57,0))*AI40*G40,0) -> 541.15508 | AF40: =IFERROR(INDEX('Costos Producción Febrero'!$J$34:$J$57,MATCH(Resumen!Y40,'Costos Producción Febrero'!$B$34:$B$57,0))*AI40*G40,0) -> 16271.838 | AG40: =SUM(AC40:AF40) -> 84723.55 | AI40: =INDEX('Costos Producción Febrero'!$F$5:$F$28,MATCH(Resumen!Y40,'Costos Producción Febrero'!$B$5:$B$28,0)) -> 1765.074 | AK40: =P40-AG40 -> -17523.55 | AL40: =AK40/P40 -> -0.26076711 | AM40: =R40 -> 7000 | AN40: =1882/26*G40 -> 3474.4615 | AO40: =SUM(AM40:AN40) -> 10474.462 | AP40: =78579/1995.8*G40 -> 1889.8647 | AQ40: =S40*0.03 -> 1806 | AR40: =AK40-AO40-AP40+AQ40 -> -28081.876 | AS40: =AR40/P40 -> -0.41788506 | AT40: =154473/1995.8*G40 -> 3715.1538 | AU40: =AR40-AT40 -> -31797.03 | AV40: =AU40/P40 -> -0.47317009 | AW40: =123484.35/1997.8*G40 -> 2966.888 | AX40: =AR40+AW40 -> -25114.988 | AY40: =AX40/P40 -> -0.37373494 | BA40: =P40/$G40 -> 1400 | BB40: =-AC40/$G40 -> -1024.8033 | BC40: =-AD40/$G40 -> -390 | BD40: =-AE40/$G40 -> -11.274064 | BE40: =-AF40/$G40 -> -338.99662 | BF40: =-AG40/$G40 -> -1765.074 | BG40: =AK40/$G40 -> -365.07395 | BH40: =-AM40/$G40 -> -145.83333 | BI40: =-AN40/$G40 -> -72.384615 | BJ40: =-AO40/$G40 -> -218.21795 | BK40: =-AP40/$G40 -> -39.372182 | BL40: =AQ40/$G40 -> 37.625 | BM40: =AR40/$G40 -> -585.03908 | BN40: =-AT40/$G40 -> -77.399038 | BO40: =AU40/$G40 -> -662.43812 | BP40: =AW40/$G40 -> 61.810166 | BQ40: =AX40/$G40 -> -523.22892
B41: FEBRERO | C41: MARZO | D41: 163-2026 | E41: 34 | F41: 46087 | G41: 48 | H41: POTA ALAS CONGELADAS | I41: Alas | J41: 1-up | K41: korea | L41: Busan | M41: TSUJINO | N41: Jose | O41: 1600 | P41: 76800 | Q41: 1479.1667 | R41: 5800 | S41: =P41-R41 -> 71000 | T41: 2 | U41: ECO MARIN 26010S | V41: 6445718250 | W41: COSCO | X41: PAITA | Y41: 10006720 | Z41: Inventario final | AA41: =B41&Y41&Z41 -> FEBRERO10006720Inventario final | AB41: =IFERROR(AG41/G41,0) -> 1594.5633 | AC41: =IFERROR(INDEX('Costos Producción Febrero'!$G$34:$G$57,MATCH(Resumen!Y41,'Costos Producción Febrero'!$B$34:$B$57,0))*AI41*G41,0) -> 49114.568 | AD41: =IFERROR(INDEX('Costos Producción Febrero'!$H$34:$H$57,MATCH(Resumen!Y41,'Costos Producción Febrero'!$B$34:$B$57,0))*AI41*G41,0) -> 10330.626 | AE41: =IFERROR(INDEX('Costos Producción Febrero'!$I$34:$I$57,MATCH(Resumen!Y41,'Costos Producción Febrero'!$B$34:$B$57,0))*AI41*G41,0) -> 715.16938 | AF41: =IFERROR(INDEX('Costos Producción Febrero'!$J$34:$J$57,MATCH(Resumen!Y41,'Costos Producción Febrero'!$B$34:$B$57,0))*AI41*G41,0) -> 16378.676 | AG41: =SUM(AC41:AF41) -> 76539.039 | AI41: =INDEX('Costos Producción Febrero'!$F$5:$F$28,MATCH(Resumen!Y41,'Costos Producción Febrero'!$B$5:$B$28,0)) -> 1594.5633 | AK41: =P41-AG41 -> 260.96073 | AL41: =AK41/P41 -> 0.0033979261 | AM41: =R41 -> 5800 | AN41: =1882/26*G41 -> 3474.4615 | AO41: =SUM(AM41:AN41) -> 9274.4615 | AP41: =78579/1995.8*G41 -> 1889.8647 | AQ41: =S41*0.03 -> 2130 | AR41: =AK41-AO41-AP41+AQ41 -> -8773.3655 | AS41: =AR41/P41 -> -0.11423653 | AT41: =154473/1995.8*G41 -> 3715.1538 | AU41: =AR41-AT41 -> -12488.519 | AV41: =AU41/P41 -> -0.16261093 | AW41: =123484.35/1997.8*G41 -> 2966.888 | AX41: =AR41+AW41 -> -5806.4776 | AY41: =AX41/P41 -> -0.075605176 | BA41: =P41/$G41 -> 1600 | BB41: =-AC41/$G41 -> -1023.2202 | BC41: =-AD41/$G41 -> -215.22137 | BD41: =-AE41/$G41 -> -14.899362 | BE41: =-AF41/$G41 -> -341.22241 | BF41: =-AG41/$G41 -> -1594.5633 | BG41: =AK41/$G41 -> 5.4366818 | BH41: =-AM41/$G41 -> -120.83333 | BI41: =-AN41/$G41 -> -72.384615 | BJ41: =-AO41/$G41 -> -193.21795 | BK41: =-AP41/$G41 -> -39.372182 | BL41: =AQ41/$G41 -> 44.375 | BM41: =AR41/$G41 -> -182.77845 | BN41: =-AT41/$G41 -> -77.399038 | BO41: =AU41/$G41 -> -260.17749 | BP41: =AW41/$G41 -> 61.810166 | BQ41: =AX41/$G41 -> -120.96828
B42: FEBRERO | C42: MARZO | D42: 165-2026 | E42: 40 | F42: 46105 | G42: 27 | H42: POTA MEMBRANA PRECOCIDA | I42: Membrana | K42: China | L42: Qingdao | M42: Longkou Yunfeng Aquatic | O42: 1400 | P42: 37800 | Q42: 1271.6296 | R42: 3466 | S42: =P42-R42 -> 34334 | T42: 1 | U42: CMA CGM BETTER WAYS 0DVOHN1MA | V42: LMM0577574 | W42: CMA CGM | X42: PAITA | AB42: =IFERROR(AG42/G42,0) -> 0 | AC42: =IFERROR(INDEX('Costos Producción Febrero'!$G$34:$G$57,MATCH(Resumen!Y42,'Costos Producción Febrero'!$B$34:$B$57,0))*AI42*G42,0) -> 0 | AD42: =IFERROR(INDEX('Costos Producción Febrero'!$H$34:$H$57,MATCH(Resumen!Y42,'Costos Producción Febrero'!$B$34:$B$57,0))*AI42*G42,0) -> 0 | AE42: =IFERROR(INDEX('Costos Producción Febrero'!$I$34:$I$57,MATCH(Resumen!Y42,'Costos Producción Febrero'!$B$34:$B$57,0))*AI42*G42,0) -> 0 | AF42: =IFERROR(INDEX('Costos Producción Febrero'!$J$34:$J$57,MATCH(Resumen!Y42,'Costos Producción Febrero'!$B$34:$B$57,0))*AI42*G42,0) -> 0 | AG42: =SUM(AC42:AF42) -> 0 | AI42: 0 | AK42: =P42-AG42 -> 37800 | AL42: =AK42/P42 -> 1 | AM42: =R42 -> 3466 | AN42: =1882/26*G42 -> 1954.3846 | AO42: =SUM(AM42:AN42) -> 5420.3846 | AP42: =78579/1995.8*G42 -> 1063.0489 | AQ42: =S42*0.03 -> 1030.02 | AR42: =AK42-AO42-AP42+AQ42 -> 32346.586 | AS42: =AR42/P42 -> 0.8557298 | AT42: =154473/1995.8*G42 -> 2089.774 | AU42: =AR42-AT42 -> 30256.812 | AV42: =AU42/P42 -> 0.80044477 | AW42: =123484.35/1997.8*G42 -> 1668.8745 | AX42: =AR42+AW42 -> 34015.461 | AY42: =AX42/P42 -> 0.89987992 | BA42: =P42/$G42 -> 1400 | BB42: =-AC42/$G42 -> 0 | BC42: =-AD42/$G42 -> 0 | BD42: =-AE42/$G42 -> 0 | BE42: =-AF42/$G42 -> 0 | BF42: =-AG42/$G42 -> 0 | BG42: =AK42/$G42 -> 1400 | BH42: =-AM42/$G42 -> -128.37037 | BI42: =-AN42/$G42 -> -72.384615 | BJ42: =-AO42/$G42 -> -200.75499 | BK42: =-AP42/$G42 -> -39.372182 | BL42: =AQ42/$G42 -> 38.148889 | BM42: =AR42/$G42 -> 1198.0217 | BN42: =-AT42/$G42 -> -77.399038 | BO42: =AU42/$G42 -> 1120.6227 | BP42: =AW42/$G42 -> 61.810166 | BQ42: =AX42/$G42 -> 1259.8319
B43: FEBRERO | C43: MARZO | D43: 167-2026 | E43: 42 | F43: 46104 | G43: 48 | H43: POTA CONOS | I43: Conos | K43: Tailandia | L43: Bangkok | M43: TSUJINO | N43: Jose | O43: 1600 | P43: 76800 | Q43: 1462.5 | R43: 6600 | S43: =P43-R43 -> 70200 | T43: 2 | U43: ECO MARIN 26012S | V43: 6446513180 | W43: COSCO | X43: PAITA | Y43: 10007969 | Z43: Inventario final | AA43: =B43&Y43&Z43 -> FEBRERO10007969Inventario final | AB43: =IFERROR(AG43/G43,0) -> 1205.0789 | AC43: =IFERROR(INDEX('Costos Producción Febrero'!$G$34:$G$57,MATCH(Resumen!Y43,'Costos Producción Febrero'!$B$34:$B$57,0))*AI43*G43,0) -> 48999.283 | AD43: =IFERROR(INDEX('Costos Producción Febrero'!$H$34:$H$57,MATCH(Resumen!Y43,'Costos Producción Febrero'!$B$34:$B$57,0))*AI43*G43,0) -> 9840 | AE43: =IFERROR(INDEX('Costos Producción Febrero'!$I$34:$I$57,MATCH(Resumen!Y43,'Costos Producción Febrero'!$B$34:$B$57,0))*AI43*G43,0) -> 757.17594 | AF43: =IFERROR(INDEX('Costos Producción Febrero'!$J$34:$J$57,MATCH(Resumen!Y43,'Costos Producción Febrero'!$B$34:$B$57,0))*AI43*G43,0) -> -1752.672 | AG43: =SUM(AC43:AF43) -> 57843.787 | AI43: =INDEX('Costos Producción Febrero'!$F$5:$F$28,MATCH(Resumen!Y43,'Costos Producción Febrero'!$B$5:$B$28,0)) -> 1205.0789 | AK43: =P43-AG43 -> 18956.213 | AL43: =AK43/P43 -> 0.2468257 | AM43: =R43 -> 6600 | AN43: =1882/26*G43 -> 3474.4615 | AO43: =SUM(AM43:AN43) -> 10074.462 | AP43: =78579/1995.8*G43 -> 1889.8647 | AQ43: =S43*0.03 -> 2106 | AR43: =AK43-AO43-AP43+AQ43 -> 9097.8871 | AS43: =AR43/P43 -> 0.11846207 | AT43: =154473/1995.8*G43 -> 3715.1538 | AU43: =AR43-AT43 -> 5382.7333 | AV43: =AU43/P43 -> 0.070087673 | AW43: =123484.35/1997.8*G43 -> 2966.888 | AX43: =AR43+AW43 -> 12064.775 | AY43: =AX43/P43 -> 0.15709343 | BA43: =P43/$G43 -> 1600 | BB43: =-AC43/$G43 -> -1020.8184 | BC43: =-AD43/$G43 -> -205 | BD43: =-AE43/$G43 -> -15.774499 | BE43: =-AF43/$G43 -> 36.513999 | BF43: =-AG43/$G43 -> -1205.0789 | BG43: =AK43/$G43 -> 394.92111 | BH43: =-AM43/$G43 -> -137.5 | BI43: =-AN43/$G43 -> -72.384615 | BJ43: =-AO43/$G43 -> -209.88462 | BK43: =-AP43/$G43 -> -39.372182 | BL43: =AQ43/$G43 -> 43.875 | BM43: =AR43/$G43 -> 189.53932 | BN43: =-AT43/$G43 -> -77.399038 | BO43: =AU43/$G43 -> 112.14028 | BP43: =AW43/$G43 -> 61.810166 | BQ43: =AX43/$G43 -> 251.34948
B44: FEBRERO | C44: MARZO | D44: 169-2026A | E44: 43 | F44: 46084 | G44: 116.8 | H44: POTA ALAS CONGELADAS | I44: Alas | J44: 1-UP | K44: China | L44: Qingdao | M44: TSUJINO | N44: Jose | O44: 1600 | P44: 186880 | Q44: 1484.2894 | R44: 13515 | S44: =P44-R44 -> 173365 | T44: 5 | U44: ECO SIROCCO 26009N | V44: LIMG02789600 | W44: ONE | X44: PAITA | Y44: 10006720 | Z44: Inventario final | AA44: =B44&Y44&Z44 -> FEBRERO10006720Inventario final | AB44: =IFERROR(AG44/G44,0) -> 1594.5633 | AC44: =IFERROR(INDEX('Costos Producción Febrero'!$G$34:$G$57,MATCH(Resumen!Y44,'Costos Producción Febrero'!$B$34:$B$57,0))*AI44*G44,0) -> 119512.12 | AD44: =IFERROR(INDEX('Costos Producción Febrero'!$H$34:$H$57,MATCH(Resumen!Y44,'Costos Producción Febrero'!$B$34:$B$57,0))*AI44*G44,0) -> 25137.856 | AE44: =IFERROR(INDEX('Costos Producción Febrero'!$I$34:$I$57,MATCH(Resumen!Y44,'Costos Producción Febrero'!$B$34:$B$57,0))*AI44*G44,0) -> 1740.2455 | AF44: =IFERROR(INDEX('Costos Producción Febrero'!$J$34:$J$57,MATCH(Resumen!Y44,'Costos Producción Febrero'!$B$34:$B$57,0))*AI44*G44,0) -> 39854.777 | AG44: =SUM(AC44:AF44) -> 186245 | AI44: =INDEX('Costos Producción Febrero'!$F$5:$F$28,MATCH(Resumen!Y44,'Costos Producción Febrero'!$B$5:$B$28,0)) -> 1594.5633 | AK44: =P44-AG44 -> 635.00443 | AL44: =AK44/P44 -> 0.0033979261 | AM44: =R44 -> 13515 | AN44: =1882/26*G44 -> 8454.5231 | AO44: =SUM(AM44:AN44) -> 21969.523 | AP44: =78579/1995.8*G44 -> 4598.6708 | AQ44: =S44*0.03 -> 5200.95 | AR44: =AK44-AO44-AP44+AQ44 -> -20732.239 | AS44: =AR44/P44 -> -0.11093878 | AT44: =154473/1995.8*G44 -> 9040.2076 | AU44: =AR44-AT44 -> -29772.447 | AV44: =AU44/P44 -> -0.15931318 | AW44: =123484.35/1997.8*G44 -> 7219.4274 | AX44: =AR44+AW44 -> -13512.812 | AY44: =AX44/P44 -> -0.072307427 | BA44: =P44/$G44 -> 1600 | BB44: =-AC44/$G44 -> -1023.2202 | BC44: =-AD44/$G44 -> -215.22137 | BD44: =-AE44/$G44 -> -14.899362 | BE44: =-AF44/$G44 -> -341.22241 | BF44: =-AG44/$G44 -> -1594.5633 | BG44: =AK44/$G44 -> 5.4366818 | BH44: =-AM44/$G44 -> -115.71062 | BI44: =-AN44/$G44 -> -72.384615 | BJ44: =-AO44/$G44 -> -188.09523 | BK44: =-AP44/$G44 -> -39.372182 | BL44: =AQ44/$G44 -> 44.528682 | BM44: =AR44/$G44 -> -177.50205 | BN44: =-AT44/$G44 -> -77.399038 | BO44: =AU44/$G44 -> -254.90109 | BP44: =AW44/$G44 -> 61.810166 | BQ44: =AX44/$G44 -> -115.69188
B45: FEBRERO | C45: MARZO | D45: 169-2026B | E45: 43 | F45: 46091 | G45: 135 | H45: POTA ALAS CONGELADAS | I45: Alas | J45: 1-UP | K45: China | L45: Qingdao | M45: TSUJINO | N45: Jose | O45: 1600 | P45: 216000 | Q45: 1519.9111 | R45: 10812 | S45: =P45-R45 -> 205188 | T45: 4 | U45: ECO MARIN 26010N | V45: LIMG03633900 | W45: ONE | X45: PAITA | Y45: 10006720 | Z45: Inventario final | AA45: =B45&Y45&Z45 -> FEBRERO10006720Inventario final | AB45: =IFERROR(AG45/G45,0) -> 1594.5633 | AC45: =IFERROR(INDEX('Costos Producción Febrero'!$G$34:$G$57,MATCH(Resumen!Y45,'Costos Producción Febrero'!$B$34:$B$57,0))*AI45*G45,0) -> 138134.72 | AD45: =IFERROR(INDEX('Costos Producción Febrero'!$H$34:$H$57,MATCH(Resumen!Y45,'Costos Producción Febrero'!$B$34:$B$57,0))*AI45*G45,0) -> 29054.885 | AE45: =IFERROR(INDEX('Costos Producción Febrero'!$I$34:$I$57,MATCH(Resumen!Y45,'Costos Producción Febrero'!$B$34:$B$57,0))*AI45*G45,0) -> 2011.4139 | AF45: =IFERROR(INDEX('Costos Producción Febrero'!$J$34:$J$57,MATCH(Resumen!Y45,'Costos Producción Febrero'!$B$34:$B$57,0))*AI45*G45,0) -> 46065.025 | AG45: =SUM(AC45:AF45) -> 215266.05 | AI45: =INDEX('Costos Producción Febrero'!$F$5:$F$28,MATCH(Resumen!Y45,'Costos Producción Febrero'!$B$5:$B$28,0)) -> 1594.5633 | AK45: =P45-AG45 -> 733.95204 | AL45: =AK45/P45 -> 0.0033979261 | AM45: =R45 -> 10812 | AN45: =1882/26*G45 -> 9771.9231 | AO45: =SUM(AM45:AN45) -> 20583.923 | AP45: =78579/1995.8*G45 -> 5315.2445 | AQ45: =S45*0.03 -> 6155.64 | AR45: =AK45-AO45-AP45+AQ45 -> -19009.576 | AS45: =AR45/P45 -> -0.088007294 | AT45: =154473/1995.8*G45 -> 10448.87 | AU45: =AR45-AT45 -> -29458.446 | AV45: =AU45/P45 -> -0.13638169 | AW45: =123484.35/1997.8*G45 -> 8344.3724 | AX45: =AR45+AW45 -> -10665.203 | AY45: =AX45/P45 -> -0.04937594 | BA45: =P45/$G45 -> 1600 | BB45: =-AC45/$G45 -> -1023.2202 | BC45: =-AD45/$G45 -> -215.22137 | BD45: =-AE45/$G45 -> -14.899362 | BE45: =-AF45/$G45 -> -341.22241 | BF45: =-AG45/$G45 -> -1594.5633 | BG45: =AK45/$G45 -> 5.4366818 | BH45: =-AM45/$G45 -> -80.088889 | BI45: =-AN45/$G45 -> -72.384615 | BJ45: =-AO45/$G45 -> -152.4735 | BK45: =-AP45/$G45 -> -39.372182 | BL45: =AQ45/$G45 -> 45.597333 | BM45: =AR45/$G45 -> -140.81167 | BN45: =-AT45/$G45 -> -77.399038 | BO45: =AU45/$G45 -> -218.21071 | BP45: =AW45/$G45 -> 61.810166 | BQ45: =AX45/$G45 -> -79.001505
B46: FEBRERO | C46: MARZO | D46: 170-2026B | E46: 43 | F46: 46092 | G46: 78 | H46: POTA REJOS CONGELADOS | I46: Rejos | J46: 1-2 | K46: España | L46: Vigo | M46: KULALIA | N46: Ramon | O46: 2400 | P46: =187200-15600 -> 171600 | Q46: 2243.0865 | R46: 12239.25 | S46: =P46-R46 -> 159360.75 | T46: 3 | U46: CMA CGM BOLDNESS / 0DVODN1MA | V46: LMM0575562 | W46: CMA CGM | Y46: 10007162 | Z46: Inventario final | AA46: =B46&Y46&Z46 -> FEBRERO10007162Inventario final | AB46: =IFERROR(AG46/G46,0) -> 1665.8462 | AC46: =IFERROR(INDEX('Costos Producción Febrero'!$G$34:$G$57,MATCH(Resumen!Y46,'Costos Producción Febrero'!$B$34:$B$57,0))*AI46*G46,0) -> 79670.346 | AD46: =IFERROR(INDEX('Costos Producción Febrero'!$H$34:$H$57,MATCH(Resumen!Y46,'Costos Producción Febrero'!$B$34:$B$57,0))*AI46*G46,0) -> 22620 | AE46: =IFERROR(INDEX('Costos Producción Febrero'!$I$34:$I$57,MATCH(Resumen!Y46,'Costos Producción Febrero'!$B$34:$B$57,0))*AI46*G46,0) -> 1204.5834 | AF46: =IFERROR(INDEX('Costos Producción Febrero'!$J$34:$J$57,MATCH(Resumen!Y46,'Costos Producción Febrero'!$B$34:$B$57,0))*AI46*G46,0) -> 26441.075 | AG46: =SUM(AC46:AF46) -> 129936 | AI46: =INDEX('Costos Producción Febrero'!$F$5:$F$28,MATCH(Resumen!Y46,'Costos Producción Febrero'!$B$5:$B$28,0)) -> 1665.8462 | AK46: =P46-AG46 -> 41663.995 | AL46: =AK46/P46 -> 0.24279718 | AM46: =R46 -> 12239.25 | AN46: =1882/26*G46 -> 5646 | AO46: =SUM(AM46:AN46) -> 17885.25 | AP46: =78579/1995.8*G46 -> 3071.0302 | AQ46: =S46*0.03 -> 4780.8225 | AR46: =AK46-AO46-AP46+AQ46 -> 25488.538 | AS46: =AR46/P46 -> 0.1485346 | AT46: =154473/1995.8*G46 -> 6037.125 | AU46: =AR46-AT46 -> 19451.413 | AV46: =AU46/P46 -> 0.11335322 | AW46: =123484.35/1997.8*G46 -> 4821.193 | AX46: =AR46+AW46 -> 30309.731 | AY46: =AX46/P46 -> 0.17663013 | BA46: =P46/$G46 -> 2200 | BB46: =-AC46/$G46 -> -1021.4147 | BC46: =-AD46/$G46 -> -290 | BD46: =-AE46/$G46 -> -15.443377 | BE46: =-AF46/$G46 -> -338.98814 | BF46: =-AG46/$G46 -> -1665.8462 | BG46: =AK46/$G46 -> 534.15379 | BH46: =-AM46/$G46 -> -156.91346 | BI46: =-AN46/$G46 -> -72.384615 | BJ46: =-AO46/$G46 -> -229.29808 | BK46: =-AP46/$G46 -> -39.372182 | BL46: =AQ46/$G46 -> 61.292596 | BM46: =AR46/$G46 -> 326.77613 | BN46: =-AT46/$G46 -> -77.399038 | BO46: =AU46/$G46 -> 249.37709 | BP46: =AW46/$G46 -> 61.810166 | BQ46: =AX46/$G46 -> 388.58629
B47: FEBRERO | C47: MARZO | D47: 171-2026 | E47: 44 | F47: 46085 | G47: 135 | H47: POTA FILETE CONGELADO | I47: Filete | J47: 2-4 AA | K47: China | L47: Shidao | M47: Pesciro Asia International LTD. | O47: 1450 | P47: 195750 | Q47: 1338.7778 | R47: 15015 | S47: =P47-R47 -> 180735 | T47: 5 | U47: ECO SIROCCO 26009N | V47: LIMG03093900 | W47: ONE | X47: PAITA | Y47: 10005721 | Z47: Inventario final | AA47: =B47&Y47&Z47 -> FEBRERO10005721Inventario final | AB47: =IFERROR(AG47/G47,0) -> 1672.2066 | AC47: =IFERROR(INDEX('Costos Producción Febrero'!$G$34:$G$57,MATCH(Resumen!Y47,'Costos Producción Febrero'!$B$34:$B$57,0))*AI47*G47,0) -> 137099.16 | AD47: =IFERROR(INDEX('Costos Producción Febrero'!$H$34:$H$57,MATCH(Resumen!Y47,'Costos Producción Febrero'!$B$34:$B$57,0))*AI47*G47,0) -> 40172.899 | AE47: =IFERROR(INDEX('Costos Producción Febrero'!$I$34:$I$57,MATCH(Resumen!Y47,'Costos Producción Febrero'!$B$34:$B$57,0))*AI47*G47,0) -> 2461.0822 | AF47: =IFERROR(INDEX('Costos Producción Febrero'!$J$34:$J$57,MATCH(Resumen!Y47,'Costos Producción Febrero'!$B$34:$B$57,0))*AI47*G47,0) -> 46014.751 | AG47: =SUM(AC47:AF47) -> 225747.89 | AI47: =INDEX('Costos Producción Febrero'!$F$5:$F$28,MATCH(Resumen!Y47,'Costos Producción Febrero'!$B$5:$B$28,0)) -> 1672.2066 | AK47: =P47-AG47 -> -29997.887 | AL47: =AK47/P47 -> -0.15324591 | AM47: =R47 -> 15015 | AN47: =1882/26*G47 -> 9771.9231 | AO47: =SUM(AM47:AN47) -> 24786.923 | AP47: =78579/1995.8*G47 -> 5315.2445 | AQ47: =S47*0.03 -> 5422.05 | AR47: =AK47-AO47-AP47+AQ47 -> -54678.005 | AS47: =AR47/P47 -> -0.2793257 | AT47: =154473/1995.8*G47 -> 10448.87 | AU47: =AR47-AT47 -> -65126.875 | AV47: =AU47/P47 -> -0.33270434 | AW47: =123484.35/1997.8*G47 -> 8344.3724 | AX47: =AR47+AW47 -> -46333.633 | AY47: =AX47/P47 -> -0.236698 | BA47: =P47/$G47 -> 1450 | BB47: =-AC47/$G47 -> -1015.5493 | BC47: =-AD47/$G47 -> -297.57703 | BD47: =-AE47/$G47 -> -18.230239 | BE47: =-AF47/$G47 -> -340.85 | BF47: =-AG47/$G47 -> -1672.2066 | BG47: =AK47/$G47 -> -222.20657 | BH47: =-AM47/$G47 -> -111.22222 | BI47: =-AN47/$G47 -> -72.384615 | BJ47: =-AO47/$G47 -> -183.60684 | BK47: =-AP47/$G47 -> -39.372182 | BL47: =AQ47/$G47 -> 40.163333 | BM47: =AR47/$G47 -> -405.02226 | BN47: =-AT47/$G47 -> -77.399038 | BO47: =AU47/$G47 -> -482.4213 | BP47: =AW47/$G47 -> 61.810166 | BQ47: =AX47/$G47 -> -343.21209
B48: FEBRERO | C48: MARZO | D48: 172-2026A | E48: 47 | F48: 46092 | G48: 150 | H48: POTA REJOS CONGELADOS | I48: Rejos | J48: 1-2 KG | K48: España | L48: Vigo | M48: KULALIA | N48: Ramon | O48: 2300 | P48: 345000 | Q48: 2139.1 | R48: 24135 | S48: =P48-R48 -> 320865 | T48: 6 | U48: CMA CGM BOLDNESS / 0DVODN1MA | V48: LMM0575536 | W48: CMA CGM | Y48: 10007162 | Z48: Inventario final | AA48: =B48&Y48&Z48 -> FEBRERO10007162Inventario final | AB48: =IFERROR(AG48/G48,0) -> 1665.8462 | AC48: =IFERROR(INDEX('Costos Producción Febrero'!$G$34:$G$57,MATCH(Resumen!Y48,'Costos Producción Febrero'!$B$34:$B$57,0))*AI48*G48,0) -> 153212.2 | AD48: =IFERROR(INDEX('Costos Producción Febrero'!$H$34:$H$57,MATCH(Resumen!Y48,'Costos Producción Febrero'!$B$34:$B$57,0))*AI48*G48,0) -> 43500 | AE48: =IFERROR(INDEX('Costos Producción Febrero'!$I$34:$I$57,MATCH(Resumen!Y48,'Costos Producción Febrero'!$B$34:$B$57,0))*AI48*G48,0) -> 2316.5066 | AF48: =IFERROR(INDEX('Costos Producción Febrero'!$J$34:$J$57,MATCH(Resumen!Y48,'Costos Producción Febrero'!$B$34:$B$57,0))*AI48*G48,0) -> 50848.222 | AG48: =SUM(AC48:AF48) -> 249876.93 | AI48: =INDEX('Costos Producción Febrero'!$F$5:$F$28,MATCH(Resumen!Y48,'Costos Producción Febrero'!$B$5:$B$28,0)) -> 1665.8462 | AK48: =P48-AG48 -> 95123.068 | AL48: =AK48/P48 -> 0.27571904 | AM48: =R48 -> 24135 | AN48: =1882/26*G48 -> 10857.692 | AO48: =SUM(AM48:AN48) -> 34992.692 | AP48: =78579/1995.8*G48 -> 5905.8272 | AQ48: =S48*0.03 -> 9625.95 | AR48: =AK48-AO48-AP48+AQ48 -> 63850.499 | AS48: =AR48/P48 -> 0.18507391 | AT48: =154473/1995.8*G48 -> 11609.856 | AU48: =AR48-AT48 -> 52240.643 | AV48: =AU48/P48 -> 0.15142215 | AW48: =123484.35/1997.8*G48 -> 9271.5249 | AX48: =AR48+AW48 -> 73122.024 | AY48: =AX48/P48 -> 0.21194789 | BA48: =P48/$G48 -> 2300 | BB48: =-AC48/$G48 -> -1021.4147 | BC48: =-AD48/$G48 -> -290 | BD48: =-AE48/$G48 -> -15.443377 | BE48: =-AF48/$G48 -> -338.98814 | BF48: =-AG48/$G48 -> -1665.8462 | BG48: =AK48/$G48 -> 634.15379 | BH48: =-AM48/$G48 -> -160.9 | BI48: =-AN48/$G48 -> -72.384615 | BJ48: =-AO48/$G48 -> -233.28462 | BK48: =-AP48/$G48 -> -39.372182 | BL48: =AQ48/$G48 -> 64.173 | BM48: =AR48/$G48 -> 425.66999 | BN48: =-AT48/$G48 -> -77.399038 | BO48: =AU48/$G48 -> 348.27095 | BP48: =AW48/$G48 -> 61.810166 | BQ48: =AX48/$G48 -> 487.48016
B49: FEBRERO | C49: MARZO | D49: 172-2026A | E49: 47 | F49: 46092 | G49: 25 | H49: POTA REPRODUCTORES | I49: Rejos | K49: España | L49: Vigo | M49: KULALIA | N49: Ramon | O49: 2500 | P49: 62500 | Q49: 2336.72 | R49: 4082 | S49: =P49-R49 -> 58418 | T49: 1 | U49: CMA CGM BOLDNESS / 0DVODN1MA | V49: LMM0575536 | W49: CMA CGM | Y49: 10007567 | Z49: Inventario final | AA49: =B49&Y49&Z49 -> FEBRERO10007567Inventario final | AB49: =IFERROR(AG49/G49,0) -> 1652.2358 | AC49: =IFERROR(INDEX('Costos Producción Febrero'!$G$34:$G$57,MATCH(Resumen!Y49,'Costos Producción Febrero'!$B$34:$B$57,0))*AI49*G49,0) -> 25509.801 | AD49: =IFERROR(INDEX('Costos Producción Febrero'!$H$34:$H$57,MATCH(Resumen!Y49,'Costos Producción Febrero'!$B$34:$B$57,0))*AI49*G49,0) -> 6875 | AE49: =IFERROR(INDEX('Costos Producción Febrero'!$I$34:$I$57,MATCH(Resumen!Y49,'Costos Producción Febrero'!$B$34:$B$57,0))*AI49*G49,0) -> 445.83009 | AF49: =IFERROR(INDEX('Costos Producción Febrero'!$J$34:$J$57,MATCH(Resumen!Y49,'Costos Producción Febrero'!$B$34:$B$57,0))*AI49*G49,0) -> 8475.2631 | AG49: =SUM(AC49:AF49) -> 41305.894 | AI49: =INDEX('Costos Producción Febrero'!$F$5:$F$28,MATCH(Resumen!Y49,'Costos Producción Febrero'!$B$5:$B$28,0)) -> 1652.2358 | AK49: =P49-AG49 -> 21194.106 | AL49: =AK49/P49 -> 0.33910569 | AM49: =R49 -> 4082 | AN49: =1882/26*G49 -> 1809.6154 | AO49: =SUM(AM49:AN49) -> 5891.6154 | AP49: =78579/1995.8*G49 -> 984.30454 | AQ49: =S49*0.03 -> 1752.54 | AR49: =AK49-AO49-AP49+AQ49 -> 16070.726 | AS49: =AR49/P49 -> 0.25713161 | AT49: =154473/1995.8*G49 -> 1934.9759 | AU49: =AR49-AT49 -> 14135.75 | AV49: =AU49/P49 -> 0.226172 | AW49: =123484.35/1997.8*G49 -> 1545.2542 | AX49: =AR49+AW49 -> 17615.98 | AY49: =AX49/P49 -> 0.28185568 | BA49: =P49/$G49 -> 2500 | BB49: =-AC49/$G49 -> -1020.392 | BC49: =-AD49/$G49 -> -275 | BD49: =-AE49/$G49 -> -17.833203 | BE49: =-AF49/$G49 -> -339.01052 | BF49: =-AG49/$G49 -> -1652.2358 | BG49: =AK49/$G49 -> 847.76422 | BH49: =-AM49/$G49 -> -163.28 | BI49: =-AN49/$G49 -> -72.384615 | BJ49: =-AO49/$G49 -> -235.66462 | BK49: =-AP49/$G49 -> -39.372182 | BL49: =AQ49/$G49 -> 70.1016 | BM49: =AR49/$G49 -> 642.82903 | BN49: =-AT49/$G49 -> -77.399038 | BO49: =AU49/$G49 -> 565.42999 | BP49: =AW49/$G49 -> 61.810166 | BQ49: =AX49/$G49 -> 704.63919
B50: FEBRERO | C50: MARZO | D50: 172-2026B | E50: 47 | F50: 46108 | G50: 54 | H50: POTA ALAS COCIDAS | I50: Alas | J50: 0.3 - UP | K50: China | L50: Qingdao | M50: KULALIA | N50: Ramon | O50: 3350 | P50: =180900-3678.3 -> 177221.7 | Q50: 3242.5926 | R50: 5800 | S50: =P50-R50 -> 171421.7 | T50: 2 | U50: ECO SIROCCO 26013S | V50: 6446512380 | W50: COSCO | X50: PAITA | Y50: 10009331 | Z50: Inventario final | AA50: =B50&Y50&Z50 -> FEBRERO10009331Inventario final | AB50: =IFERROR(AG50/G50,0) -> 1762.2156 | AC50: =IFERROR(INDEX('Costos Producción Febrero'!$G$34:$G$57,MATCH(Resumen!Y50,'Costos Producción Febrero'!$B$34:$B$57,0))*AI50*G50,0) -> 54300.64 | AD50: =IFERROR(INDEX('Costos Producción Febrero'!$H$34:$H$57,MATCH(Resumen!Y50,'Costos Producción Febrero'!$B$34:$B$57,0))*AI50*G50,0) -> 21542.905 | AE50: =IFERROR(INDEX('Costos Producción Febrero'!$I$34:$I$57,MATCH(Resumen!Y50,'Costos Producción Febrero'!$B$34:$B$57,0))*AI50*G50,0) -> 986.65482 | AF50: =IFERROR(INDEX('Costos Producción Febrero'!$J$34:$J$57,MATCH(Resumen!Y50,'Costos Producción Febrero'!$B$34:$B$57,0))*AI50*G50,0) -> 18329.44 | AG50: =SUM(AC50:AF50) -> 95159.64 | AI50: =INDEX('Costos Producción Febrero'!$F$5:$F$28,MATCH(Resumen!Y50,'Costos Producción Febrero'!$B$5:$B$28,0)) -> 1762.2156 | AK50: =P50-AG50 -> 82062.06 | AL50: =AK50/P50 -> 0.46304747 | AM50: =R50 -> 5800 | AN50: =1882/26*G50 -> 3908.7692 | AO50: =SUM(AM50:AN50) -> 9708.7692 | AP50: =78579/1995.8*G50 -> 2126.0978 | AQ50: =S50*0.03 -> 5142.651 | AR50: =AK50-AO50-AP50+AQ50 -> 75369.844 | AS50: =AR50/P50 -> 0.42528564 | AT50: =154473/1995.8*G50 -> 4179.5481 | AU50: =AR50-AT50 -> 71190.296 | AV50: =AU50/P50 -> 0.40170191 | AW50: =123484.35/1997.8*G50 -> 3337.749 | AX50: =AR50+AW50 -> 78707.593 | AY50: =AX50/P50 -> 0.44411939 | BA50: =P50/$G50 -> 3281.8833 | BB50: =-AC50/$G50 -> -1005.5674 | BC50: =-AD50/$G50 -> -398.94269 | BD50: =-AE50/$G50 -> -18.271386 | BE50: =-AF50/$G50 -> -339.43408 | BF50: =-AG50/$G50 -> -1762.2156 | BG50: =AK50/$G50 -> 1519.6678 | BH50: =-AM50/$G50 -> -107.40741 | BI50: =-AN50/$G50 -> -72.384615 | BJ50: =-AO50/$G50 -> -179.79202 | BK50: =-AP50/$G50 -> -39.372182 | BL50: =AQ50/$G50 -> 95.234278 | BM50: =AR50/$G50 -> 1395.7378 | BN50: =-AT50/$G50 -> -77.399038 | BO50: =AU50/$G50 -> 1318.3388 | BP50: =AW50/$G50 -> 61.810166 | BQ50: =AX50/$G50 -> 1457.548
B51: FEBRERO | C51: MARZO | D51: 174-2026 | E51: 49 | F51: 46091 | G51: 108 | H51: POTA FILETE CONGELADO | I51: Filete | J51: 2-4 AA | K51: China | L51: shidao | M51: Pesciro Asia International LTD. | O51: 1450 | P51: 156600 | Q51: 1338.7778 | R51: 12012 | S51: =P51-R51 -> 144588 | T51: 4 | U51: ECO MARIN 26010N | V51: LIMG03595900 | Y51: 10005721 | Z51: Inventario final | AA51: =B51&Y51&Z51 -> FEBRERO10005721Inventario final | AB51: =IFERROR(AG51/G51,0) -> 1672.2066 | AC51: =IFERROR(INDEX('Costos Producción Febrero'!$G$34:$G$57,MATCH(Resumen!Y51,'Costos Producción Febrero'!$B$34:$B$57,0))*AI51*G51,0) -> 109679.32 | AD51: =IFERROR(INDEX('Costos Producción Febrero'!$H$34:$H$57,MATCH(Resumen!Y51,'Costos Producción Febrero'!$B$34:$B$57,0))*AI51*G51,0) -> 32138.319 | AE51: =IFERROR(INDEX('Costos Producción Febrero'!$I$34:$I$57,MATCH(Resumen!Y51,'Costos Producción Febrero'!$B$34:$B$57,0))*AI51*G51,0) -> 1968.8658 | AF51: =IFERROR(INDEX('Costos Producción Febrero'!$J$34:$J$57,MATCH(Resumen!Y51,'Costos Producción Febrero'!$B$34:$B$57,0))*AI51*G51,0) -> 36811.8 | AG51: =SUM(AC51:AF51) -> 180598.31 | AI51: =INDEX('Costos Producción Febrero'!$F$5:$F$28,MATCH(Resumen!Y51,'Costos Producción Febrero'!$B$5:$B$28,0)) -> 1672.2066 | AK51: =P51-AG51 -> -23998.31 | AL51: =AK51/P51 -> -0.15324591 | AM51: =R51 -> 12012 | AN51: =1883/26*G51 -> 7821.6923 | AO51: =SUM(AM51:AN51) -> 19833.692 | AP51: =78579/1995.8*G51 -> 4252.1956 | AQ51: =S51*0.03 -> 4337.64 | AR51: =AK51-AO51-AP51+AQ51 -> -43746.558 | AS51: =AR51/P51 -> -0.27935222 | AT51: =154473/1995.8*G51 -> 8359.0961 | AU51: =AR51-AT51 -> -52105.654 | AV51: =AU51/P51 -> -0.33273087 | AW51: =123484.35/1997.8*G51 -> 6675.4979 | AX51: =AR51+AW51 -> -37071.06 | AY51: =AX51/P51 -> -0.23672452 | BA51: =P51/$G51 -> 1450 | BB51: =-AC51/$G51 -> -1015.5493 | BC51: =-AD51/$G51 -> -297.57703 | BD51: =-AE51/$G51 -> -18.230239 | BE51: =-AF51/$G51 -> -340.85 | BF51: =-AG51/$G51 -> -1672.2066 | BG51: =AK51/$G51 -> -222.20657 | BH51: =-AM51/$G51 -> -111.22222 | BI51: =-AN51/$G51 -> -72.423077 | BJ51: =-AO51/$G51 -> -183.6453 | BK51: =-AP51/$G51 -> -39.372182 | BL51: =AQ51/$G51 -> 40.163333 | BM51: =AR51/$G51 -> -405.06072 | BN51: =-AT51/$G51 -> -77.399038 | BO51: =AU51/$G51 -> -482.45976 | BP51: =AW51/$G51 -> 61.810166 | BQ51: =AX51/$G51 -> -343.25055
B52: FEBRERO | C52: MARZO | D52: 175-2026 | E52: 49 | F52: 46099 | G52: 26 | H52: POTA FILETE CONGELADO | I52: Filete | J52: 2-4 AA | K52: Klaipeda | L52: Lituania | M52: Pesciro SL | O52: 1500 | P52: 39000 | Q52: 1230.9615 | R52: 6995 | S52: =P52-R52 -> 32005 | T52: 1 | U52: CMA CGM VOLTAIRE / 0DVOFN1MA | V52: LMM0575667 | W52: 1 | X52: CMA CGM | Y52: 10005721 | Z52: Inventario final | AA52: =B52&Y52&Z52 -> FEBRERO10005721Inventario final | AB52: =IFERROR(AG52/G52,0) -> 1672.2066 | AC52: =IFERROR(INDEX('Costos Producción Febrero'!$G$34:$G$57,MATCH(Resumen!Y52,'Costos Producción Febrero'!$B$34:$B$57,0))*AI52*G52,0) -> 26404.282 | AD52: =IFERROR(INDEX('Costos Producción Febrero'!$H$34:$H$57,MATCH(Resumen!Y52,'Costos Producción Febrero'!$B$34:$B$57,0))*AI52*G52,0) -> 7737.0028 | AE52: =IFERROR(INDEX('Costos Producción Febrero'!$I$34:$I$57,MATCH(Resumen!Y52,'Costos Producción Febrero'!$B$34:$B$57,0))*AI52*G52,0) -> 473.9862 | AF52: =IFERROR(INDEX('Costos Producción Febrero'!$J$34:$J$57,MATCH(Resumen!Y52,'Costos Producción Febrero'!$B$34:$B$57,0))*AI52*G52,0) -> 8862.1001 | AG52: =SUM(AC52:AF52) -> 43477.371 | AI52: =INDEX('Costos Producción Febrero'!$F$5:$F$28,MATCH(Resumen!Y52,'Costos Producción Febrero'!$B$5:$B$28,0)) -> 1672.2066 | AK52: =P52-AG52 -> -4477.3709 | AL52: =AK52/P52 -> -0.11480438 | AM52: =R52 -> 6995 | AN52: =1883/26*G52 -> 1883 | AO52: =SUM(AM52:AN52) -> 8878 | AP52: =78579/1995.8*G52 -> 1023.6767 | AQ52: =S52*0.03 -> 960.15 | AR52: =AK52-AO52-AP52+AQ52 -> -13418.898 | AS52: =AR52/P52 -> -0.3440743 | AT52: =154473/1995.8*G52 -> 2012.375 | AU52: =AR52-AT52 -> -15431.273 | AV52: =AU52/P52 -> -0.39567366 | AW52: =123484.35/1997.8*G52 -> 1607.0643 | AX52: =AR52+AW52 -> -11811.833 | AY52: =AX52/P52 -> -0.30286752 | BA52: =P52/$G52 -> 1500 | BB52: =-AC52/$G52 -> -1015.5493 | BC52: =-AD52/$G52 -> -297.57703 | BD52: =-AE52/$G52 -> -18.230239 | BE52: =-AF52/$G52 -> -340.85 | BF52: =-AG52/$G52 -> -1672.2066 | BG52: =AK52/$G52 -> -172.20657 | BH52: =-AM52/$G52 -> -269.03846 | BI52: =-AN52/$G52 -> -72.423077 | BJ52: =-AO52/$G52 -> -341.46154 | BK52: =-AP52/$G52 -> -39.372182 | BL52: =AQ52/$G52 -> 36.928846 | BM52: =AR52/$G52 -> -516.11145 | BN52: =-AT52/$G52 -> -77.399038 | BO52: =AU52/$G52 -> -593.51049 | BP52: =AW52/$G52 -> 61.810166 | BQ52: =AX52/$G52 -> -454.30128
B53: FEBRERO | C53: MARZO | D53: 176-2026A | E53: 49 | F53: 46104 | G53: 54 | H53: POTA ALAS CONGELADAS | I53: Alas | J53: 1-up | K53: China | L53: Qingdao | M53: TSUJINO | N53: Jose | O53: 1600 | P53: 86400 | Q53: 1492.5926 | R53: 5800 | S53: =P53-R53 -> 80600 | T53: 2 | U53: ECO SIROCCO 26011S | V53: 6446527810 | W53: COSCO | X53: PAITA | Y53: 10006720 | Z53: Inventario final | AA53: =B53&Y53&Z53 -> FEBRERO10006720Inventario final | AB53: =IFERROR(AG53/G53,0) -> 1594.5633 | AC53: =IFERROR(INDEX('Costos Producción Febrero'!$G$34:$G$57,MATCH(Resumen!Y53,'Costos Producción Febrero'!$B$34:$B$57,0))*AI53*G53,0) -> 55253.889 | AD53: =IFERROR(INDEX('Costos Producción Febrero'!$H$34:$H$57,MATCH(Resumen!Y53,'Costos Producción Febrero'!$B$34:$B$57,0))*AI53*G53,0) -> 11621.954 | AE53: =IFERROR(INDEX('Costos Producción Febrero'!$I$34:$I$57,MATCH(Resumen!Y53,'Costos Producción Febrero'!$B$34:$B$57,0))*AI53*G53,0) -> 804.56555 | AF53: =IFERROR(INDEX('Costos Producción Febrero'!$J$34:$J$57,MATCH(Resumen!Y53,'Costos Producción Febrero'!$B$34:$B$57,0))*AI53*G53,0) -> 18426.01 | AG53: =SUM(AC53:AF53) -> 86106.419 | AI53: =INDEX('Costos Producción Febrero'!$F$5:$F$28,MATCH(Resumen!Y53,'Costos Producción Febrero'!$B$5:$B$28,0)) -> 1594.5633 | AK53: =P53-AG53 -> 293.58082 | AL53: =AK53/P53 -> 0.0033979261 | AM53: =R53 -> 5800 | AN53: =1883/26*G53 -> 3910.8462 | AO53: =SUM(AM53:AN53) -> 9710.8462 | AP53: =78579/1995.8*G53 -> 2126.0978 | AQ53: =S53*0.03 -> 2418 | AR53: =AK53-AO53-AP53+AQ53 -> -9125.3631 | AS53: =AR53/P53 -> -0.10561763 | AT53: =154473/1995.8*G53 -> 4179.5481 | AU53: =AR53-AT53 -> -13304.911 | AV53: =AU53/P53 -> -0.15399203 | AW53: =123484.35/1997.8*G53 -> 3337.749 | AX53: =AR53+AW53 -> -5787.6142 | AY53: =AX53/P53 -> -0.066986275 | BA53: =P53/$G53 -> 1600 | BB53: =-AC53/$G53 -> -1023.2202 | BC53: =-AD53/$G53 -> -215.22137 | BD53: =-AE53/$G53 -> -14.899362 | BE53: =-AF53/$G53 -> -341.22241 | BF53: =-AG53/$G53 -> -1594.5633 | BG53: =AK53/$G53 -> 5.4366818 | BH53: =-AM53/$G53 -> -107.40741 | BI53: =-AN53/$G53 -> -72.423077 | BJ53: =-AO53/$G53 -> -179.83048 | BK53: =-AP53/$G53 -> -39.372182 | BL53: =AQ53/$G53 -> 44.777778 | BM53: =AR53/$G53 -> -168.98821 | BN53: =-AT53/$G53 -> -77.399038 | BO53: =AU53/$G53 -> -246.38724 | BP53: =AW53/$G53 -> 61.810166 | BQ53: =AX53/$G53 -> -107.17804
B54: FEBRERO | C54: MARZO | D54: 176-2026B | E54: 49 | F54: 46108 | G54: 81 | H54: POTA ALAS CONGELADAS | I54: Alas | J54: 1-up | K54: China | L54: Qingdao | M54: TSUJINO | N54: Jose | O54: 1600 | P54: =129600-4000 -> 125600 | Q54: 1499.5185 | R54: 8139 | S54: =P54-R54 -> 117461 | T54: 3 | U54: ECO SIROCCO 26013S | V54: LIMG04326900 | W54: ONE LINE | X54: PAITA | Y54: 10006720 | Z54: Inventario final | AA54: =B54&Y54&Z54 -> FEBRERO10006720Inventario final | AB54: =IFERROR(AG54/G54,0) -> 1594.5633 | AC54: =IFERROR(INDEX('Costos Producción Febrero'!$G$34:$G$57,MATCH(Resumen!Y54,'Costos Producción Febrero'!$B$34:$B$57,0))*AI54*G54,0) -> 82880.834 | AD54: =IFERROR(INDEX('Costos Producción Febrero'!$H$34:$H$57,MATCH(Resumen!Y54,'Costos Producción Febrero'!$B$34:$B$57,0))*AI54*G54,0) -> 17432.931 | AE54: =IFERROR(INDEX('Costos Producción Febrero'!$I$34:$I$57,MATCH(Resumen!Y54,'Costos Producción Febrero'!$B$34:$B$57,0))*AI54*G54,0) -> 1206.8483 | AF54: =IFERROR(INDEX('Costos Producción Febrero'!$J$34:$J$57,MATCH(Resumen!Y54,'Costos Producción Febrero'!$B$34:$B$57,0))*AI54*G54,0) -> 27639.015 | AG54: =SUM(AC54:AF54) -> 129159.63 | AI54: =INDEX('Costos Producción Febrero'!$F$5:$F$28,MATCH(Resumen!Y54,'Costos Producción Febrero'!$B$5:$B$28,0)) -> 1594.5633 | AK54: =P54-AG54 -> -3559.6288 | AL54: =AK54/P54 -> -0.028340993 | AM54: =R54 -> 8139 | AN54: =1883/26*G54 -> 5866.2692 | AO54: =SUM(AM54:AN54) -> 14005.269 | AP54: =78579/1995.8*G54 -> 3189.1467 | AQ54: =S54*0.03 -> 3523.83 | AR54: =AK54-AO54-AP54+AQ54 -> -17230.215 | AS54: =AR54/P54 -> -0.13718324 | AT54: =154473/1995.8*G54 -> 6269.3221 | AU54: =AR54-AT54 -> -23499.537 | AV54: =AU54/P54 -> -0.18709822 | AW54: =123484.35/1997.8*G54 -> 5006.6235 | AX54: =AR54+AW54 -> -12223.591 | AY54: =AX54/P54 -> -0.097321586 | BA54: =P54/$G54 -> 1550.6173 | BB54: =-AC54/$G54 -> -1023.2202 | BC54: =-AD54/$G54 -> -215.22137 | BD54: =-AE54/$G54 -> -14.899362 | BE54: =-AF54/$G54 -> -341.22241 | BF54: =-AG54/$G54 -> -1594.5633 | BG54: =AK54/$G54 -> -43.946034 | BH54: =-AM54/$G54 -> -100.48148 | BI54: =-AN54/$G54 -> -72.423077 | BJ54: =-AO54/$G54 -> -172.90456 | BK54: =-AP54/$G54 -> -39.372182 | BL54: =AQ54/$G54 -> 43.504074 | BM54: =AR54/$G54 -> -212.7187 | BN54: =-AT54/$G54 -> -77.399038 | BO54: =AU54/$G54 -> -290.11774 | BP54: =AW54/$G54 -> 61.810166 | BQ54: =AX54/$G54 -> -150.90853
B55: FEBRERO | C55: MARZO | D55: 177-2026A | E55: 50 | F55: 46108 | G55: 48 | H55: POTA ALAS CONGELADAS | I55: Alas | J55: 1-up | K55: Korea | L55: Busan | M55: TSUJINO | N55: Jose | O55: 1600 | P55: 76800 | Q55: 1486.9583 | R55: 5426 | S55: =P55-R55 -> 71374 | T55: 2 | U55: ECO SIROCCO 26013S | V55: LIMG04588500 | W55: ONE LINE | X55: PAITA | Y55: 10006720 | Z55: Inventario final | AA55: =B55&Y55&Z55 -> FEBRERO10006720Inventario final | AB55: =IFERROR(AG55/G55,0) -> 1850.3684 | AC55: =IFERROR(INDEX('Costos Producción Febrero'!$G$34:$G$57,MATCH(Resumen!Y55,'Costos Producción Febrero'!$B$34:$B$57,0))*AI55*G55,0)*1.25 -> 61393.211 | AD55: =IFERROR(INDEX('Costos Producción Febrero'!$H$34:$H$57,MATCH(Resumen!Y55,'Costos Producción Febrero'!$B$34:$B$57,0))*AI55*G55,0) -> 10330.626 | AE55: =IFERROR(INDEX('Costos Producción Febrero'!$I$34:$I$57,MATCH(Resumen!Y55,'Costos Producción Febrero'!$B$34:$B$57,0))*AI55*G55,0) -> 715.16938 | AF55: =IFERROR(INDEX('Costos Producción Febrero'!$J$34:$J$57,MATCH(Resumen!Y55,'Costos Producción Febrero'!$B$34:$B$57,0))*AI55*G55,0) -> 16378.676 | AG55: =SUM(AC55:AF55) -> 88817.681 | AI55: =INDEX('Costos Producción Febrero'!$F$5:$F$28,MATCH(Resumen!Y55,'Costos Producción Febrero'!$B$5:$B$28,0)) -> 1594.5633 | AK55: =P55-AG55 -> -12017.681 | AL55: =AK55/P55 -> -0.15648023 | AM55: =R55 -> 5426 | AN55: =1883/26*G55 -> 3476.3077 | AO55: =SUM(AM55:AN55) -> 8902.3077 | AP55: =78579/1995.8*G55 -> 1889.8647 | AQ55: =S55*0.03 -> 2141.22 | AR55: =AK55-AO55-AP55+AQ55 -> -20668.634 | AS55: =AR55/P55 -> -0.26912284 | AT55: =154473/1995.8*G55 -> 3715.1538 | AU55: =AR55-AT55 -> -24383.788 | AV55: =AU55/P55 -> -0.31749723 | AW55: =123484.35/1997.8*G55 -> 2966.888 | AX55: =AR55+AW55 -> -17701.746 | AY55: =AX55/P55 -> -0.23049148 | BA55: =P55/$G55 -> 1600 | BB55: =-AC55/$G55 -> -1279.0252 | BC55: =-AD55/$G55 -> -215.22137 | BD55: =-AE55/$G55 -> -14.899362 | BE55: =-AF55/$G55 -> -341.22241 | BF55: =-AG55/$G55 -> -1850.3684 | BG55: =AK55/$G55 -> -250.36836 | BH55: =-AM55/$G55 -> -113.04167 | BI55: =-AN55/$G55 -> -72.423077 | BJ55: =-AO55/$G55 -> -185.46474 | BK55: =-AP55/$G55 -> -39.372182 | BL55: =AQ55/$G55 -> 44.60875 | BM55: =AR55/$G55 -> -430.59654 | BN55: =-AT55/$G55 -> -77.399038 | BO55: =AU55/$G55 -> -507.99558 | BP55: =AW55/$G55 -> 61.810166 | BQ55: =AX55/$G55 -> -368.78637
B56: FEBRERO | C56: MARZO | D56: 179-2026A | E56: 54 | F56: 46101 | G56: 24 | H56: POTA NUCAS | I56: Nucas | J56: 500-up | K56: Tailandia | L56: Laem chabang | M56: DAIRECK S.A. | N56: ACER FOOD | O56: 1100 | P56: 26400 | Q56: 966.54167 | R56: 3203 | S56: =P56-R56 -> 23197 | T56: 1 | U56: ECO MARIN 26012N | V56: LIMG03918800 | W56: ONE LINE | X56: PAITA | Y56: 10005779 | Z56: Inventario final | AA56: =B56&Y56&Z56 -> FEBRERO10005779Inventario final | AB56: =IFERROR(AG56/G56,0) -> 2021.2748 | AC56: =IFERROR(INDEX('Costos Producción Febrero'!$G$34:$G$57,MATCH(Resumen!Y56,'Costos Producción Febrero'!$B$34:$B$57,0))*AI56*G56,0)*1.25 -> 30744.098 | AD56: =IFERROR(INDEX('Costos Producción Febrero'!$H$34:$H$57,MATCH(Resumen!Y56,'Costos Producción Febrero'!$B$34:$B$57,0))*AI56*G56,0) -> 9360 | AE56: =IFERROR(INDEX('Costos Producción Febrero'!$I$34:$I$57,MATCH(Resumen!Y56,'Costos Producción Febrero'!$B$34:$B$57,0))*AI56*G56,0) -> 270.57754 | AF56: =IFERROR(INDEX('Costos Producción Febrero'!$J$34:$J$57,MATCH(Resumen!Y56,'Costos Producción Febrero'!$B$34:$B$57,0))*AI56*G56,0) -> 8135.9189 | AG56: =SUM(AC56:AF56) -> 48510.594 | AI56: =INDEX('Costos Producción Febrero'!$F$5:$F$28,MATCH(Resumen!Y56,'Costos Producción Febrero'!$B$5:$B$28,0)) -> 1765.074 | AK56: =P56-AG56 -> -22110.594 | AL56: =AK56/P56 -> -0.83752252 | AM56: =R56 -> 3203 | AN56: =1883/26*G56 -> 1738.1538 | AO56: =SUM(AM56:AN56) -> 4941.1538 | AP56: =78579/1995.8*G56 -> 944.93236 | AQ56: =S56*0.03 -> 695.91 | AR56: =AK56-AO56-AP56+AQ56 -> -27300.771 | AS56: =AR56/P56 -> -1.0341201 | AT56: =154473/1995.8*G56 -> 1857.5769 | AU56: =AR56-AT56 -> -29158.348 | AV56: =AU56/P56 -> -1.1044829 | AW56: =123484.35/1997.8*G56 -> 1483.444 | AX56: =AR56+AW56 -> -25817.327 | AY56: =AX56/P56 -> -0.97792904 | BA56: =P56/$G56 -> 1100 | BB56: =-AC56/$G56 -> -1281.0041 | BC56: =-AD56/$G56 -> -390 | BD56: =-AE56/$G56 -> -11.274064 | BE56: =-AF56/$G56 -> -338.99662 | BF56: =-AG56/$G56 -> -2021.2748 | BG56: =AK56/$G56 -> -921.27477 | BH56: =-AM56/$G56 -> -133.45833 | BI56: =-AN56/$G56 -> -72.423077 | BJ56: =-AO56/$G56 -> -205.88141 | BK56: =-AP56/$G56 -> -39.372182 | BL56: =AQ56/$G56 -> 28.99625 | BM56: =AR56/$G56 -> -1137.5321 | BN56: =-AT56/$G56 -> -77.399038 | BO56: =AU56/$G56 -> -1214.9311 | BP56: =AW56/$G56 -> 61.810166 | BQ56: =AX56/$G56 -> -1075.7219
B57: FEBRERO | C57: MARZO | D57: 179-2026B1 | E57: 54 | F57: 46101 | G57: 24 | H57: POTA NUCAS | I57: Nucas | J57: 500-up | K57: Tailandia | L57: Lat Krabang | M57: DAIRECK S.A. | N57: Julieta | O57: 1100 | P57: 26400 | Q57: 953.625 | R57: 3513 | S57: =P57-R57 -> 22887 | T57: 1 | U57: ECO MARIN 26012N | V57: LIMG03924500 | W57: ONE LINE | X57: PAITA | Y57: 10005779 | Z57: Inventario final | AA57: =B57&Y57&Z57 -> FEBRERO10005779Inventario final | AB57: =IFERROR(AG57/G57,0) -> 2021.2748 | AC57: =IFERROR(INDEX('Costos Producción Febrero'!$G$34:$G$57,MATCH(Resumen!Y57,'Costos Producción Febrero'!$B$34:$B$57,0))*AI57*G57,0)*1.25 -> 30744.098 | AD57: =IFERROR(INDEX('Costos Producción Febrero'!$H$34:$H$57,MATCH(Resumen!Y57,'Costos Producción Febrero'!$B$34:$B$57,0))*AI57*G57,0) -> 9360 | AE57: =IFERROR(INDEX('Costos Producción Febrero'!$I$34:$I$57,MATCH(Resumen!Y57,'Costos Producción Febrero'!$B$34:$B$57,0))*AI57*G57,0) -> 270.57754 | AF57: =IFERROR(INDEX('Costos Producción Febrero'!$J$34:$J$57,MATCH(Resumen!Y57,'Costos Producción Febrero'!$B$34:$B$57,0))*AI57*G57,0) -> 8135.9189 | AG57: =SUM(AC57:AF57) -> 48510.594 | AI57: =INDEX('Costos Producción Febrero'!$F$5:$F$28,MATCH(Resumen!Y57,'Costos Producción Febrero'!$B$5:$B$28,0)) -> 1765.074 | AK57: =P57-AG57 -> -22110.594 | AL57: =AK57/P57 -> -0.83752252 | AM57: =R57 -> 3513 | AN57: =1883/26*G57 -> 1738.1538 | AO57: =SUM(AM57:AN57) -> 5251.1538 | AP57: =78579/1995.8*G57 -> 944.93236 | AQ57: =S57*0.03 -> 686.61 | AR57: =AK57-AO57-AP57+AQ57 -> -27620.071 | AS57: =AR57/P57 -> -1.0462148 | AT57: =154473/1995.8*G57 -> 1857.5769 | AU57: =AR57-AT57 -> -29477.648 | AV57: =AU57/P57 -> -1.1165776 | AW57: =123484.35/1997.8*G57 -> 1483.444 | AX57: =AR57+AW57 -> -26136.627 | AY57: =AX57/P57 -> -0.99002374 | BA57: =P57/$G57 -> 1100 | BB57: =-AC57/$G57 -> -1281.0041 | BC57: =-AD57/$G57 -> -390 | BD57: =-AE57/$G57 -> -11.274064 | BE57: =-AF57/$G57 -> -338.99662 | BF57: =-AG57/$G57 -> -2021.2748 | BG57: =AK57/$G57 -> -921.27477 | BH57: =-AM57/$G57 -> -146.375 | BI57: =-AN57/$G57 -> -72.423077 | BJ57: =-AO57/$G57 -> -218.79808 | BK57: =-AP57/$G57 -> -39.372182 | BL57: =AQ57/$G57 -> 28.60875 | BM57: =AR57/$G57 -> -1150.8363 | BN57: =-AT57/$G57 -> -77.399038 | BO57: =AU57/$G57 -> -1228.2353 | BP57: =AW57/$G57 -> 61.810166 | BQ57: =AX57/$G57 -> -1089.0261
B58: FEBRERO | C58: MARZO | D58: 179-2026B2 | E58: 54 | F58: 46101 | G58: 24 | H58: POTA NUCAS | I58: Nucas | J58: 500-up | K58: Tailandia | L58: Lat Krabang | M58: DAIRECK S.A. | N58: Julieta | O58: 1100 | P58: 26400 | Q58: 953.625 | R58: 3513 | S58: =P58-R58 -> 22887 | T58: 1 | U58: ECO MARIN 26012N | V58: LIMG03933500 | W58: ONE LINE | X58: PAITA | Y58: 10005779 | Z58: Inventario final | AA58: =B58&Y58&Z58 -> FEBRERO10005779Inventario final | AB58: =IFERROR(AG58/G58,0) -> 2021.2748 | AC58: =IFERROR(INDEX('Costos Producción Febrero'!$G$34:$G$57,MATCH(Resumen!Y58,'Costos Producción Febrero'!$B$34:$B$57,0))*AI58*G58,0)*1.25 -> 30744.098 | AD58: =IFERROR(INDEX('Costos Producción Febrero'!$H$34:$H$57,MATCH(Resumen!Y58,'Costos Producción Febrero'!$B$34:$B$57,0))*AI58*G58,0) -> 9360 | AE58: =IFERROR(INDEX('Costos Producción Febrero'!$I$34:$I$57,MATCH(Resumen!Y58,'Costos Producción Febrero'!$B$34:$B$57,0))*AI58*G58,0) -> 270.57754 | AF58: =IFERROR(INDEX('Costos Producción Febrero'!$J$34:$J$57,MATCH(Resumen!Y58,'Costos Producción Febrero'!$B$34:$B$57,0))*AI58*G58,0) -> 8135.9189 | AG58: =SUM(AC58:AF58) -> 48510.594 | AI58: =INDEX('Costos Producción Febrero'!$F$5:$F$28,MATCH(Resumen!Y58,'Costos Producción Febrero'!$B$5:$B$28,0)) -> 1765.074 | AK58: =P58-AG58 -> -22110.594 | AL58: =AK58/P58 -> -0.83752252 | AM58: =R58 -> 3513 | AN58: =1883/26*G58 -> 1738.1538 | AO58: =SUM(AM58:AN58) -> 5251.1538 | AP58: =78579/1995.8*G58 -> 944.93236 | AQ58: =S58*0.03 -> 686.61 | AR58: =AK58-AO58-AP58+AQ58 -> -27620.071 | AS58: =AR58/P58 -> -1.0462148 | AT58: =154473/1995.8*G58 -> 1857.5769 | AU58: =AR58-AT58 -> -29477.648 | AV58: =AU58/P58 -> -1.1165776 | AW58: =123484.35/1997.8*G58 -> 1483.444 | AX58: =AR58+AW58 -> -26136.627 | AY58: =AX58/P58 -> -0.99002374 | BA58: =P58/$G58 -> 1100 | BB58: =-AC58/$G58 -> -1281.0041 | BC58: =-AD58/$G58 -> -390 | BD58: =-AE58/$G58 -> -11.274064 | BE58: =-AF58/$G58 -> -338.99662 | BF58: =-AG58/$G58 -> -2021.2748 | BG58: =AK58/$G58 -> -921.27477 | BH58: =-AM58/$G58 -> -146.375 | BI58: =-AN58/$G58 -> -72.423077 | BJ58: =-AO58/$G58 -> -218.79808 | BK58: =-AP58/$G58 -> -39.372182 | BL58: =AQ58/$G58 -> 28.60875 | BM58: =AR58/$G58 -> -1150.8363 | BN58: =-AT58/$G58 -> -77.399038 | BO58: =AU58/$G58 -> -1228.2353 | BP58: =AW58/$G58 -> 61.810166 | BQ58: =AX58/$G58 -> -1089.0261
B59: FEBRERO | C59: MARZO | D59: 179-2026B3 | E59: 54 | F59: 46108 | G59: 24 | H59: POTA NUCAS | I59: Nucas | J59: 500-up | K59: Tailandia | L59: Lat Krabang | M59: DAIRECK S.A. | N59: Julieta | O59: 1100 | P59: 26400 | Q59: 953.625 | R59: 3513 | S59: =P59-R59 -> 22887 | T59: 1 | U59: ECO SIROCCO 26013S | V59: LIMG03937900 | W59: ONE LINE | X59: PAITA | Y59: 10005779 | Z59: Inventario final | AA59: =B59&Y59&Z59 -> FEBRERO10005779Inventario final | AB59: =IFERROR(AG59/G59,0) -> 2021.2748 | AC59: =IFERROR(INDEX('Costos Producción Febrero'!$G$34:$G$57,MATCH(Resumen!Y59,'Costos Producción Febrero'!$B$34:$B$57,0))*AI59*G59,0)*1.25 -> 30744.098 | AD59: =IFERROR(INDEX('Costos Producción Febrero'!$H$34:$H$57,MATCH(Resumen!Y59,'Costos Producción Febrero'!$B$34:$B$57,0))*AI59*G59,0) -> 9360 | AE59: =IFERROR(INDEX('Costos Producción Febrero'!$I$34:$I$57,MATCH(Resumen!Y59,'Costos Producción Febrero'!$B$34:$B$57,0))*AI59*G59,0) -> 270.57754 | AF59: =IFERROR(INDEX('Costos Producción Febrero'!$J$34:$J$57,MATCH(Resumen!Y59,'Costos Producción Febrero'!$B$34:$B$57,0))*AI59*G59,0) -> 8135.9189 | AG59: =SUM(AC59:AF59) -> 48510.594 | AI59: =INDEX('Costos Producción Febrero'!$F$5:$F$28,MATCH(Resumen!Y59,'Costos Producción Febrero'!$B$5:$B$28,0)) -> 1765.074 | AK59: =P59-AG59 -> -22110.594 | AL59: =AK59/P59 -> -0.83752252 | AM59: =R59 -> 3513 | AN59: =1883/26*G59 -> 1738.1538 | AO59: =SUM(AM59:AN59) -> 5251.1538 | AP59: =78579/1995.8*G59 -> 944.93236 | AQ59: =S59*0.03 -> 686.61 | AR59: =AK59-AO59-AP59+AQ59 -> -27620.071 | AS59: =AR59/P59 -> -1.0462148 | AT59: =154473/1995.8*G59 -> 1857.5769 | AU59: =AR59-AT59 -> -29477.648 | AV59: =AU59/P59 -> -1.1165776 | AW59: =123484.35/1997.8*G59 -> 1483.444 | AX59: =AR59+AW59 -> -26136.627 | AY59: =AX59/P59 -> -0.99002374 | BA59: =P59/$G59 -> 1100 | BB59: =-AC59/$G59 -> -1281.0041 | BC59: =-AD59/$G59 -> -390 | BD59: =-AE59/$G59 -> -11.274064 | BE59: =-AF59/$G59 -> -338.99662 | BF59: =-AG59/$G59 -> -2021.2748 | BG59: =AK59/$G59 -> -921.27477 | BH59: =-AM59/$G59 -> -146.375 | BI59: =-AN59/$G59 -> -72.423077 | BJ59: =-AO59/$G59 -> -218.79808 | BK59: =-AP59/$G59 -> -39.372182 | BL59: =AQ59/$G59 -> 28.60875 | BM59: =AR59/$G59 -> -1150.8363 | BN59: =-AT59/$G59 -> -77.399038 | BO59: =AU59/$G59 -> -1228.2353 | BP59: =AW59/$G59 -> 61.810166 | BQ59: =AX59/$G59 -> -1089.0261
B60: FEBRERO | C60: MARZO | D60: 179-2026B4 | E60: 54 | F60: 46108 | G60: 24 | H60: POTA NUCAS | I60: Nucas | J60: 500-up | K60: Tailandia | L60: Lat Krabang | M60: DAIRECK S.A. | N60: Julieta | O60: 1100 | P60: 26400 | Q60: 953.625 | R60: 3513 | S60: =P60-R60 -> 22887 | T60: 1 | U60: ECO SIROCCO 26013S | V60: LIMG03938300 | W60: ONE LINE | X60: PAITA | Y60: 10005779 | Z60: Inventario final | AA60: =B60&Y60&Z60 -> FEBRERO10005779Inventario final | AB60: =IFERROR(AG60/G60,0) -> 2021.2748 | AC60: =IFERROR(INDEX('Costos Producción Febrero'!$G$34:$G$57,MATCH(Resumen!Y60,'Costos Producción Febrero'!$B$34:$B$57,0))*AI60*G60,0)*1.25 -> 30744.098 | AD60: =IFERROR(INDEX('Costos Producción Febrero'!$H$34:$H$57,MATCH(Resumen!Y60,'Costos Producción Febrero'!$B$34:$B$57,0))*AI60*G60,0) -> 9360 | AE60: =IFERROR(INDEX('Costos Producción Febrero'!$I$34:$I$57,MATCH(Resumen!Y60,'Costos Producción Febrero'!$B$34:$B$57,0))*AI60*G60,0) -> 270.57754 | AF60: =IFERROR(INDEX('Costos Producción Febrero'!$J$34:$J$57,MATCH(Resumen!Y60,'Costos Producción Febrero'!$B$34:$B$57,0))*AI60*G60,0) -> 8135.9189 | AG60: =SUM(AC60:AF60) -> 48510.594 | AI60: =INDEX('Costos Producción Febrero'!$F$5:$F$28,MATCH(Resumen!Y60,'Costos Producción Febrero'!$B$5:$B$28,0)) -> 1765.074 | AK60: =P60-AG60 -> -22110.594 | AL60: =AK60/P60 -> -0.83752252 | AM60: =R60 -> 3513 | AN60: =1883/26*G60 -> 1738.1538 | AO60: =SUM(AM60:AN60) -> 5251.1538 | AP60: =78579/1995.8*G60 -> 944.93236 | AQ60: =S60*0.03 -> 686.61 | AR60: =AK60-AO60-AP60+AQ60 -> -27620.071 | AS60: =AR60/P60 -> -1.0462148 | AT60: =154473/1995.8*G60 -> 1857.5769 | AU60: =AR60-AT60 -> -29477.648 | AV60: =AU60/P60 -> -1.1165776 | AW60: =123484.35/1997.8*G60 -> 1483.444 | AX60: =AR60+AW60 -> -26136.627 | AY60: =AX60/P60 -> -0.99002374 | BA60: =P60/$G60 -> 1100 | BB60: =-AC60/$G60 -> -1281.0041 | BC60: =-AD60/$G60 -> -390 | BD60: =-AE60/$G60 -> -11.274064 | BE60: =-AF60/$G60 -> -338.99662 | BF60: =-AG60/$G60 -> -2021.2748 | BG60: =AK60/$G60 -> -921.27477 | BH60: =-AM60/$G60 -> -146.375 | BI60: =-AN60/$G60 -> -72.423077 | BJ60: =-AO60/$G60 -> -218.79808 | BK60: =-AP60/$G60 -> -39.372182 | BL60: =AQ60/$G60 -> 28.60875 | BM60: =AR60/$G60 -> -1150.8363 | BN60: =-AT60/$G60 -> -77.399038 | BO60: =AU60/$G60 -> -1228.2353 | BP60: =AW60/$G60 -> 61.810166 | BQ60: =AX60/$G60 -> -1089.0261
B61: FEBRERO | C61: MARZO | D61: 179-2026B5 | E61: 54 | F61: 46108 | G61: 24 | H61: POTA NUCAS | I61: Nucas | J61: 500-up | K61: Tailandia | L61: Lat Krabang | M61: DAIRECK S.A. | N61: Julieta | O61: 1100 | P61: 26400 | Q61: 966.54167 | R61: 3203 | S61: =P61-R61 -> 23197 | T61: 1 | U61: ECO SIROCCO 26013S | V61: LIMG03940300 | W61: ONE LINE | X61: PAITA | Y61: 10005779 | Z61: Inventario final | AA61: =B61&Y61&Z61 -> FEBRERO10005779Inventario final | AB61: =IFERROR(AG61/G61,0) -> 2021.2748 | AC61: =IFERROR(INDEX('Costos Producción Febrero'!$G$34:$G$57,MATCH(Resumen!Y61,'Costos Producción Febrero'!$B$34:$B$57,0))*AI61*G61,0)*1.25 -> 30744.098 | AD61: =IFERROR(INDEX('Costos Producción Febrero'!$H$34:$H$57,MATCH(Resumen!Y61,'Costos Producción Febrero'!$B$34:$B$57,0))*AI61*G61,0) -> 9360 | AE61: =IFERROR(INDEX('Costos Producción Febrero'!$I$34:$I$57,MATCH(Resumen!Y61,'Costos Producción Febrero'!$B$34:$B$57,0))*AI61*G61,0) -> 270.57754 | AF61: =IFERROR(INDEX('Costos Producción Febrero'!$J$34:$J$57,MATCH(Resumen!Y61,'Costos Producción Febrero'!$B$34:$B$57,0))*AI61*G61,0) -> 8135.9189 | AG61: =SUM(AC61:AF61) -> 48510.594 | AI61: =INDEX('Costos Producción Febrero'!$F$5:$F$28,MATCH(Resumen!Y61,'Costos Producción Febrero'!$B$5:$B$28,0)) -> 1765.074 | AK61: =P61-AG61 -> -22110.594 | AL61: =AK61/P61 -> -0.83752252 | AM61: =R61 -> 3203 | AN61: =1883/26*G61 -> 1738.1538 | AO61: =SUM(AM61:AN61) -> 4941.1538 | AP61: =78579/1995.8*G61 -> 944.93236 | AQ61: =S61*0.03 -> 695.91 | AR61: =AK61-AO61-AP61+AQ61 -> -27300.771 | AS61: =AR61/P61 -> -1.0341201 | AT61: =154473/1995.8*G61 -> 1857.5769 | AU61: =AR61-AT61 -> -29158.348 | AV61: =AU61/P61 -> -1.1044829 | AW61: =123484.35/1997.8*G61 -> 1483.444 | AX61: =AR61+AW61 -> -25817.327 | AY61: =AX61/P61 -> -0.97792904 | BA61: =P61/$G61 -> 1100 | BB61: =-AC61/$G61 -> -1281.0041 | BC61: =-AD61/$G61 -> -390 | BD61: =-AE61/$G61 -> -11.274064 | BE61: =-AF61/$G61 -> -338.99662 | BF61: =-AG61/$G61 -> -2021.2748 | BG61: =AK61/$G61 -> -921.27477 | BH61: =-AM61/$G61 -> -133.45833 | BI61: =-AN61/$G61 -> -72.423077 | BJ61: =-AO61/$G61 -> -205.88141 | BK61: =-AP61/$G61 -> -39.372182 | BL61: =AQ61/$G61 -> 28.99625 | BM61: =AR61/$G61 -> -1137.5321 | BN61: =-AT61/$G61 -> -77.399038 | BO61: =AU61/$G61 -> -1214.9311 | BP61: =AW61/$G61 -> 61.810166 | BQ61: =AX61/$G61 -> -1075.7219
B62: FEBRERO | C62: MARZO | D62: 179-2026C1 | E62: 54 | F62: 46108 | G62: 24 | H62: POTA NUCAS | I62: Nucas | J62: 1-2 KG | K62: Tailandia | L62: Lat Krabang | M62: DAIRECK S.A. | N62: KHUNRUNG | O62: 1200 | P62: =28800-9240 -> 19560 | Q62: 1054.1667 | R62: 3500 | S62: =P62-R62 -> 16060 | T62: 1 | U62: ECO SIROCCO 26013S | V62: 6447908140 | W62: COSCO | X62: PAITA | Y62: 10005779 | Z62: Inventario final | AA62: =B62&Y62&Z62 -> FEBRERO10005779Inventario final | AB62: =IFERROR(AG62/G62,0) -> 2021.2748 | AC62: =IFERROR(INDEX('Costos Producción Febrero'!$G$34:$G$57,MATCH(Resumen!Y62,'Costos Producción Febrero'!$B$34:$B$57,0))*AI62*G62,0)*1.25 -> 30744.098 | AD62: =IFERROR(INDEX('Costos Producción Febrero'!$H$34:$H$57,MATCH(Resumen!Y62,'Costos Producción Febrero'!$B$34:$B$57,0))*AI62*G62,0) -> 9360 | AE62: =IFERROR(INDEX('Costos Producción Febrero'!$I$34:$I$57,MATCH(Resumen!Y62,'Costos Producción Febrero'!$B$34:$B$57,0))*AI62*G62,0) -> 270.57754 | AF62: =IFERROR(INDEX('Costos Producción Febrero'!$J$34:$J$57,MATCH(Resumen!Y62,'Costos Producción Febrero'!$B$34:$B$57,0))*AI62*G62,0) -> 8135.9189 | AG62: =SUM(AC62:AF62) -> 48510.594 | AI62: =INDEX('Costos Producción Febrero'!$F$5:$F$28,MATCH(Resumen!Y62,'Costos Producción Febrero'!$B$5:$B$28,0)) -> 1765.074 | AK62: =P62-AG62 -> -28950.594 | AL62: =AK62/P62 -> -1.4800917 | AM62: =R62 -> 3500 | AN62: =1883/26*G62 -> 1738.1538 | AO62: =SUM(AM62:AN62) -> 5238.1538 | AP62: =78579/1995.8*G62 -> 944.93236 | AQ62: =S62*0.03 -> 481.8 | AR62: =AK62-AO62-AP62+AQ62 -> -34651.881 | AS62: =AR62/P62 -> -1.7715685 | AT62: =154473/1995.8*G62 -> 1857.5769 | AU62: =AR62-AT62 -> -36509.458 | AV62: =AU62/P62 -> -1.8665367 | AW62: =123484.35/1997.8*G62 -> 1483.444 | AX62: =AR62+AW62 -> -33168.437 | AY62: =AX62/P62 -> -1.6957278 | BA62: =P62/$G62 -> 815 | BB62: =-AC62/$G62 -> -1281.0041 | BC62: =-AD62/$G62 -> -390 | BD62: =-AE62/$G62 -> -11.274064 | BE62: =-AF62/$G62 -> -338.99662 | BF62: =-AG62/$G62 -> -2021.2748 | BG62: =AK62/$G62 -> -1206.2748 | BH62: =-AM62/$G62 -> -145.83333 | BI62: =-AN62/$G62 -> -72.423077 | BJ62: =-AO62/$G62 -> -218.25641 | BK62: =-AP62/$G62 -> -39.372182 | BL62: =AQ62/$G62 -> 20.075 | BM62: =AR62/$G62 -> -1443.8284 | BN62: =-AT62/$G62 -> -77.399038 | BO62: =AU62/$G62 -> -1521.2274 | BP62: =AW62/$G62 -> 61.810166 | BQ62: =AX62/$G62 -> -1382.0182
B63: FEBRERO | C63: MARZO | D63: 179-2026C2 | E63: 54 | F63: 46108 | G63: 24 | H63: POTA NUCAS | I63: Nucas | J63: 1-2 KG | K63: Tailandia | L63: Lat Krabang | M63: DAIRECK S.A. | N63: KHUNRUNG | O63: 1200 | P63: 28800 | Q63: 1054.1667 | R63: 3500 | S63: =P63-R63 -> 25300 | T63: 1 | U63: ECO SIROCCO 26013S | V63: 6447908120 | W63: COSCO | X63: PAITA | Y63: 10005779 | Z63: Inventario final | AA63: =B63&Y63&Z63 -> FEBRERO10005779Inventario final | AB63: =IFERROR(AG63/G63,0) -> 2021.2748 | AC63: =IFERROR(INDEX('Costos Producción Febrero'!$G$34:$G$57,MATCH(Resumen!Y63,'Costos Producción Febrero'!$B$34:$B$57,0))*AI63*G63,0)*1.25 -> 30744.098 | AD63: =IFERROR(INDEX('Costos Producción Febrero'!$H$34:$H$57,MATCH(Resumen!Y63,'Costos Producción Febrero'!$B$34:$B$57,0))*AI63*G63,0) -> 9360 | AE63: =IFERROR(INDEX('Costos Producción Febrero'!$I$34:$I$57,MATCH(Resumen!Y63,'Costos Producción Febrero'!$B$34:$B$57,0))*AI63*G63,0) -> 270.57754 | AF63: =IFERROR(INDEX('Costos Producción Febrero'!$J$34:$J$57,MATCH(Resumen!Y63,'Costos Producción Febrero'!$B$34:$B$57,0))*AI63*G63,0) -> 8135.9189 | AG63: =SUM(AC63:AF63) -> 48510.594 | AI63: =INDEX('Costos Producción Febrero'!$F$5:$F$28,MATCH(Resumen!Y63,'Costos Producción Febrero'!$B$5:$B$28,0)) -> 1765.074 | AK63: =P63-AG63 -> -19710.594 | AL63: =AK63/P63 -> -0.68439564 | AM63: =R63 -> 3500 | AN63: =1883/26*G63 -> 1738.1538 | AO63: =SUM(AM63:AN63) -> 5238.1538 | AP63: =78579/1995.8*G63 -> 944.93236 | AQ63: =S63*0.03 -> 759 | AR63: =AK63-AO63-AP63+AQ63 -> -25134.681 | AS63: =AR63/P63 -> -0.87273197 | AT63: =154473/1995.8*G63 -> 1857.5769 | AU63: =AR63-AT63 -> -26992.258 | AV63: =AU63/P63 -> -0.93723116 | AW63: =123484.35/1997.8*G63 -> 1483.444 | AX63: =AR63+AW63 -> -23651.237 | AY63: =AX63/P63 -> -0.82122349 | BA63: =P63/$G63 -> 1200 | BB63: =-AC63/$G63 -> -1281.0041 | BC63: =-AD63/$G63 -> -390 | BD63: =-AE63/$G63 -> -11.274064 | BE63: =-AF63/$G63 -> -338.99662 | BF63: =-AG63/$G63 -> -2021.2748 | BG63: =AK63/$G63 -> -821.27477 | BH63: =-AM63/$G63 -> -145.83333 | BI63: =-AN63/$G63 -> -72.423077 | BJ63: =-AO63/$G63 -> -218.25641 | BK63: =-AP63/$G63 -> -39.372182 | BL63: =AQ63/$G63 -> 31.625 | BM63: =AR63/$G63 -> -1047.2784 | BN63: =-AT63/$G63 -> -77.399038 | BO63: =AU63/$G63 -> -1124.6774 | BP63: =AW63/$G63 -> 61.810166 | BQ63: =AX63/$G63 -> -985.46819
B64: FEBRERO | C64: MARZO | D64: 181-2026 | E64: 46077 | F64: 46108 | G64: 48 | H64: POTA NUCAS | I64: Nucas | J64: 500-1000 | K64: Tailandia | L64: Lat Krabang | M64: TSUJINO | N64: Jose | O64: 1200 | P64: 57600 | Q64: 1126.8125 | R64: 3513 | S64: =P64-R64 -> 54087 | T64: 1 | U64: ECO SIROCCO 26013S | V64: LIMG04324700 | W64: ONE LINE | X64: PAITA | Y64: 10005779 | Z64: Inventario final | AA64: =B64&Y64&Z64 -> FEBRERO10005779Inventario final | AB64: =IFERROR(AG64/G64,0) -> 2021.2748 | AC64: =IFERROR(INDEX('Costos Producción Febrero'!$G$34:$G$57,MATCH(Resumen!Y64,'Costos Producción Febrero'!$B$34:$B$57,0))*AI64*G64,0)*1.25 -> 61488.196 | AD64: =IFERROR(INDEX('Costos Producción Febrero'!$H$34:$H$57,MATCH(Resumen!Y64,'Costos Producción Febrero'!$B$34:$B$57,0))*AI64*G64,0) -> 18720 | AE64: =IFERROR(INDEX('Costos Producción Febrero'!$I$34:$I$57,MATCH(Resumen!Y64,'Costos Producción Febrero'!$B$34:$B$57,0))*AI64*G64,0) -> 541.15508 | AF64: =IFERROR(INDEX('Costos Producción Febrero'!$J$34:$J$57,MATCH(Resumen!Y64,'Costos Producción Febrero'!$B$34:$B$57,0))*AI64*G64,0) -> 16271.838 | AG64: =SUM(AC64:AF64) -> 97021.189 | AI64: =INDEX('Costos Producción Febrero'!$F$5:$F$28,MATCH(Resumen!Y64,'Costos Producción Febrero'!$B$5:$B$28,0)) -> 1765.074 | AK64: =P64-AG64 -> -39421.189 | AL64: =AK64/P64 -> -0.68439564 | AM64: =R64 -> 3513 | AN64: =1883/26*G64 -> 3476.3077 | AO64: =SUM(AM64:AN64) -> 6989.3077 | AP64: =78579/1995.8*G64 -> 1889.8647 | AQ64: =S64*0.03 -> 1622.61 | AR64: =AK64-AO64-AP64+AQ64 -> -46677.751 | AS64: =AR64/P64 -> -0.81037763 | AT64: =154473/1995.8*G64 -> 3715.1538 | AU64: =AR64-AT64 -> -50392.905 | AV64: =AU64/P64 -> -0.87487682 | AW64: =123484.35/1997.8*G64 -> 2966.888 | AX64: =AR64+AW64 -> -43710.863 | AY64: =AX64/P64 -> -0.75886915 | BA64: =P64/$G64 -> 1200 | BB64: =-AC64/$G64 -> -1281.0041 | BC64: =-AD64/$G64 -> -390 | BD64: =-AE64/$G64 -> -11.274064 | BE64: =-AF64/$G64 -> -338.99662 | BF64: =-AG64/$G64 -> -2021.2748 | BG64: =AK64/$G64 -> -821.27477 | BH64: =-AM64/$G64 -> -73.1875 | BI64: =-AN64/$G64 -> -72.423077 | BJ64: =-AO64/$G64 -> -145.61058 | BK64: =-AP64/$G64 -> -39.372182 | BL64: =AQ64/$G64 -> 33.804375 | BM64: =AR64/$G64 -> -972.45315 | BN64: =-AT64/$G64 -> -77.399038 | BO64: =AU64/$G64 -> -1049.8522 | BP64: =AW64/$G64 -> 61.810166 | BQ64: =AX64/$G64 -> -910.64299
B65: FEBRERO | C65: MARZO | D65: 183-2026 | E65: 58 | F65: 46108 | G65: 27 | H65: POTA REJOS CONGELADOS | I65: Rejos | J65: 2- UP LIMPIOS | K65: China | L65: Yantai | M65: SHANDONG SHEENIER | O65: 2600 | P65: 70200 | Q65: 2485.1852 | R65: 3100 | S65: =P65-R65 -> 67100 | T65: 1 | U65: ECO SIROCCO 26013S | V65: 6447908790 | W65: COSCO | X65: PAITA | Y65: 10007162 | Z65: Inventario final | AA65: =B65&Y65&Z65 -> FEBRERO10007162Inventario final | AB65: =IFERROR(AG65/G65,0) -> 1921.1999 | AC65: =IFERROR(INDEX('Costos Producción Febrero'!$G$34:$G$57,MATCH(Resumen!Y65,'Costos Producción Febrero'!$B$34:$B$57,0))*AI65*G65,0)*1.25 -> 34472.746 | AD65: =IFERROR(INDEX('Costos Producción Febrero'!$H$34:$H$57,MATCH(Resumen!Y65,'Costos Producción Febrero'!$B$34:$B$57,0))*AI65*G65,0) -> 7830 | AE65: =IFERROR(INDEX('Costos Producción Febrero'!$I$34:$I$57,MATCH(Resumen!Y65,'Costos Producción Febrero'!$B$34:$B$57,0))*AI65*G65,0) -> 416.97119 | AF65: =IFERROR(INDEX('Costos Producción Febrero'!$J$34:$J$57,MATCH(Resumen!Y65,'Costos Producción Febrero'!$B$34:$B$57,0))*AI65*G65,0) -> 9152.6799 | AG65: =SUM(AC65:AF65) -> 51872.397 | AI65: =INDEX('Costos Producción Febrero'!$F$5:$F$28,MATCH(Resumen!Y65,'Costos Producción Febrero'!$B$5:$B$28,0)) -> 1665.8462 | AK65: =P65-AG65 -> 18327.603 | AL65: =AK65/P65 -> 0.26107697 | AM65: =R65 -> 3100 | AN65: =1883/26*G65 -> 1955.4231 | AO65: =SUM(AM65:AN65) -> 5055.4231 | AP65: =78579/1995.8*G65 -> 1063.0489 | AQ65: =S65*0.03 -> 2013 | AR65: =AK65-AO65-AP65+AQ65 -> 14222.131 | AS65: =AR65/P65 -> 0.20259446 | AT65: =154473/1995.8*G65 -> 2089.774 | AU65: =AR65-AT65 -> 12132.357 | AV65: =AU65/P65 -> 0.1728256 | AW65: =123484.35/1997.8*G65 -> 1668.8745 | AX65: =AR65+AW65 -> 15891.006 | AY65: =AX65/P65 -> 0.2263676 | BA65: =P65/$G65 -> 2600 | BB65: =-AC65/$G65 -> -1276.7684 | BC65: =-AD65/$G65 -> -290 | BD65: =-AE65/$G65 -> -15.443377 | BE65: =-AF65/$G65 -> -338.98814 | BF65: =-AG65/$G65 -> -1921.1999 | BG65: =AK65/$G65 -> 678.80012 | BH65: =-AM65/$G65 -> -114.81481 | BI65: =-AN65/$G65 -> -72.423077 | BJ65: =-AO65/$G65 -> -187.23789 | BK65: =-AP65/$G65 -> -39.372182 | BL65: =AQ65/$G65 -> 74.555556 | BM65: =AR65/$G65 -> 526.7456 | BN65: =-AT65/$G65 -> -77.399038 | BO65: =AU65/$G65 -> 449.34656 | BP65: =AW65/$G65 -> 61.810166 | BQ65: =AX65/$G65 -> 588.55576
B66: FEBRERO | C66: MARZO | D66: 184-2026 | E66: 59 | F66: 46104 | G66: 216 | H66: POTA FILETE DARUMA | I66: Daruma | K66: China | L66: Qingdao | M66: LONGKOU JIABAO AQUATIC | N66: James | O66: 3100 | P66: 669600 | Q66: 2992.5926 | R66: 23200 | S66: =P66-R66 -> 646400 | T66: 8 | U66: ECO MARIN 26012N | V66: 6447338820 | W66: COSCO | X66: PAITA | Y66: 10009239 | Z66: Inventario final | AA66: =B66&Y66&Z66 -> FEBRERO10009239Inventario final | AB66: =IFERROR(AG66/G66,0) -> 2321.3259 | AC66: =IFERROR(INDEX('Costos Producción Febrero'!$G$34:$G$57,MATCH(Resumen!Y66,'Costos Producción Febrero'!$B$34:$B$57,0))*AI66*G66,0)*1.25 -> 274469.91 | AD66: =IFERROR(INDEX('Costos Producción Febrero'!$H$34:$H$57,MATCH(Resumen!Y66,'Costos Producción Febrero'!$B$34:$B$57,0))*AI66*G66,0) -> 143151.39 | AE66: =IFERROR(INDEX('Costos Producción Febrero'!$I$34:$I$57,MATCH(Resumen!Y66,'Costos Producción Febrero'!$B$34:$B$57,0))*AI66*G66,0) -> 2621.6009 | AF66: =IFERROR(INDEX('Costos Producción Febrero'!$J$34:$J$57,MATCH(Resumen!Y66,'Costos Producción Febrero'!$B$34:$B$57,0))*AI66*G66,0) -> 81163.492 | AG66: =SUM(AC66:AF66) -> 501406.39 | AI66: =INDEX('Costos Producción Febrero'!$F$5:$F$28,MATCH(Resumen!Y66,'Costos Producción Febrero'!$B$5:$B$28,0)) -> 2067.1871 | AK66: =P66-AG66 -> 168193.61 | AL66: =AK66/P66 -> 0.2511852 | AM66: =R66 -> 23200 | AN66: =1883/26*G66 -> 15643.385 | AO66: =SUM(AM66:AN66) -> 38843.385 | AP66: =78579/1995.8*G66 -> 8504.3912 | AQ66: =S66*0.03 -> 19392 | AR66: =AK66-AO66-AP66+AQ66 -> 140237.84 | AS66: =AR66/P66 -> 0.20943524 | AT66: =154473/1995.8*G66 -> 16718.192 | AU66: =AR66-AT66 -> 123519.64 | AV66: =AU66/P66 -> 0.18446781 | AW66: =123484.35/1997.8*G66 -> 13350.996 | AX66: =AR66+AW66 -> 153588.83 | AY66: =AX66/P66 -> 0.229374 | BA66: =P66/$G66 -> 3100 | BB66: =-AC66/$G66 -> -1270.694 | BC66: =-AD66/$G66 -> -662.73791 | BD66: =-AE66/$G66 -> -12.137041 | BE66: =-AF66/$G66 -> -375.75691 | BF66: =-AG66/$G66 -> -2321.3259 | BG66: =AK66/$G66 -> 778.67413 | BH66: =-AM66/$G66 -> -107.40741 | BI66: =-AN66/$G66 -> -72.423077 | BJ66: =-AO66/$G66 -> -179.83048 | BK66: =-AP66/$G66 -> -39.372182 | BL66: =AQ66/$G66 -> 89.777778 | BM66: =AR66/$G66 -> 649.24924 | BN66: =-AT66/$G66 -> -77.399038 | BO66: =AU66/$G66 -> 571.8502 | BP66: =AW66/$G66 -> 61.810166 | BQ66: =AX66/$G66 -> 711.05941
B67: FEBRERO | C67: MARZO | D67: 185-2026 | E67: 59 | F67: 46104 | G67: 108 | H67: POTA FILETE DARUMA | I67: Daruma | K67: China | L67: Qingdao | M67: LONGKOU BOHAI | N67: James | O67: 3100 | P67: 334800 | Q67: 2992.5926 | R67: 11600 | S67: =P67-R67 -> 323200 | T67: 4 | U67: ECO MARIN 26012N | V67: 6447338860 | W67: COSCO | X67: PAITA | Y67: 10009239 | Z67: Inventario final | AA67: =B67&Y67&Z67 -> FEBRERO10009239Inventario final | AB67: =IFERROR(AG67/G67,0) -> 2321.3259 | AC67: =IFERROR(INDEX('Costos Producción Febrero'!$G$34:$G$57,MATCH(Resumen!Y67,'Costos Producción Febrero'!$B$34:$B$57,0))*AI67*G67,0)*1.25 -> 137234.95 | AD67: =IFERROR(INDEX('Costos Producción Febrero'!$H$34:$H$57,MATCH(Resumen!Y67,'Costos Producción Febrero'!$B$34:$B$57,0))*AI67*G67,0) -> 71575.695 | AE67: =IFERROR(INDEX('Costos Producción Febrero'!$I$34:$I$57,MATCH(Resumen!Y67,'Costos Producción Febrero'!$B$34:$B$57,0))*AI67*G67,0) -> 1310.8004 | AF67: =IFERROR(INDEX('Costos Producción Febrero'!$J$34:$J$57,MATCH(Resumen!Y67,'Costos Producción Febrero'!$B$34:$B$57,0))*AI67*G67,0) -> 40581.746 | AG67: =SUM(AC67:AF67) -> 250703.19 | AI67: =INDEX('Costos Producción Febrero'!$F$5:$F$28,MATCH(Resumen!Y67,'Costos Producción Febrero'!$B$5:$B$28,0)) -> 2067.1871 | AK67: =P67-AG67 -> 84096.806 | AL67: =AK67/P67 -> 0.2511852 | AM67: =R67 -> 11600 | AN67: =1883/26*G67 -> 7821.6923 | AO67: =SUM(AM67:AN67) -> 19421.692 | AP67: =78579/1995.8*G67 -> 4252.1956 | AQ67: =S67*0.03 -> 9696 | AR67: =AK67-AO67-AP67+AQ67 -> 70118.918 | AS67: =AR67/P67 -> 0.20943524 | AT67: =154473/1995.8*G67 -> 8359.0961 | AU67: =AR67-AT67 -> 61759.822 | AV67: =AU67/P67 -> 0.18446781 | AW67: =123484.35/1997.8*G67 -> 6675.4979 | AX67: =AR67+AW67 -> 76794.416 | AY67: =AX67/P67 -> 0.229374 | BA67: =P67/$G67 -> 3100 | BB67: =-AC67/$G67 -> -1270.694 | BC67: =-AD67/$G67 -> -662.73791 | BD67: =-AE67/$G67 -> -12.137041 | BE67: =-AF67/$G67 -> -375.75691 | BF67: =-AG67/$G67 -> -2321.3259 | BG67: =AK67/$G67 -> 778.67413 | BH67: =-AM67/$G67 -> -107.40741 | BI67: =-AN67/$G67 -> -72.423077 | BJ67: =-AO67/$G67 -> -179.83048 | BK67: =-AP67/$G67 -> -39.372182 | BL67: =AQ67/$G67 -> 89.777778 | BM67: =AR67/$G67 -> 649.24924 | BN67: =-AT67/$G67 -> -77.399038 | BO67: =AU67/$G67 -> 571.8502 | BP67: =AW67/$G67 -> 61.810166 | BQ67: =AX67/$G67 -> 711.05941
B68: FEBRERO | C68: MARZO | D68: 189-2026 | E68: 68 | F68: 46108 | G68: 10 | H68: POTA NUCAS | I68: Nucas | J68: 300-500 | K68: Tailandia | L68: Lat Krabang | M68: DAIRECK S.A. | N68: Julieta | O68: 1130 | P68: 11300 | Q68: 990 | R68: 1400 | S68: =P68-R68 -> 9900 | T68: 1 | U68: ECO SIROCCO 26013S | V68: 6447908000 | W68: COSCO | X68: PAITA | Y68: 10005779 | Z68: Inventario final | AA68: =B68&Y68&Z68 -> FEBRERO10005779Inventario final | AB68: =IFERROR(AG68/G68,0) -> 2021.2748 | AC68: =IFERROR(INDEX('Costos Producción Febrero'!$G$34:$G$57,MATCH(Resumen!Y68,'Costos Producción Febrero'!$B$34:$B$57,0))*AI68*G68,0)*1.25 -> 12810.041 | AD68: =IFERROR(INDEX('Costos Producción Febrero'!$H$34:$H$57,MATCH(Resumen!Y68,'Costos Producción Febrero'!$B$34:$B$57,0))*AI68*G68,0) -> 3900 | AE68: =IFERROR(INDEX('Costos Producción Febrero'!$I$34:$I$57,MATCH(Resumen!Y68,'Costos Producción Febrero'!$B$34:$B$57,0))*AI68*G68,0) -> 112.74064 | AF68: =IFERROR(INDEX('Costos Producción Febrero'!$J$34:$J$57,MATCH(Resumen!Y68,'Costos Producción Febrero'!$B$34:$B$57,0))*AI68*G68,0) -> 3389.9662 | AG68: =SUM(AC68:AF68) -> 20212.748 | AI68: =INDEX('Costos Producción Febrero'!$F$5:$F$28,MATCH(Resumen!Y68,'Costos Producción Febrero'!$B$5:$B$28,0)) -> 1765.074 | AK68: =P68-AG68 -> -8912.7477 | AL68: =AK68/P68 -> -0.78873873 | AM68: =R68 -> 1400 | AN68: =1883/26*G68 -> 724.23077 | AO68: =SUM(AM68:AN68) -> 2124.2308 | AP68: =78579/1995.8*G68 -> 393.72182 | AQ68: =S68*0.03 -> 297 | AR68: =AK68-AO68-AP68+AQ68 -> -11133.7 | AS68: =AR68/P68 -> -0.98528321 | AT68: =154473/1995.8*G68 -> 773.99038 | AU68: =AR68-AT68 -> -11907.691 | AV68: =AU68/P68 -> -1.0537779 | AW68: =123484.35/1997.8*G68 -> 618.10166 | AX68: =AR68+AW68 -> -10515.599 | AY68: =AX68/P68 -> -0.93058395 | BA68: =P68/$G68 -> 1130 | BB68: =-AC68/$G68 -> -1281.0041 | BC68: =-AD68/$G68 -> -390 | BD68: =-AE68/$G68 -> -11.274064 | BE68: =-AF68/$G68 -> -338.99662 | BF68: =-AG68/$G68 -> -2021.2748 | BG68: =AK68/$G68 -> -891.27477 | BH68: =-AM68/$G68 -> -140 | BI68: =-AN68/$G68 -> -72.423077 | BJ68: =-AO68/$G68 -> -212.42308 | BK68: =-AP68/$G68 -> -39.372182 | BL68: =AQ68/$G68 -> 29.7 | BM68: =AR68/$G68 -> -1113.37 | BN68: =-AT68/$G68 -> -77.399038 | BO68: =AU68/$G68 -> -1190.7691 | BP68: =AW68/$G68 -> 61.810166 | BQ68: =AX68/$G68 -> -1051.5599
B69: FEBRERO | C69: MARZO | D69: 189-2026 | E69: 68 | F69: 46108 | G69: 15 | H69: POTA NUCAS | I69: Nucas | J69: 500-1000 | K69: Tailandia | L69: Lat Krabang | M69: DAIRECK S.A. | N69: Julieta | O69: 1200 | P69: 18000 | Q69: 1060 | R69: 2100 | S69: =P69-R69 -> 15900 | T69: 0 | U69: ECO SIROCCO 26013S | V69: 6447908000 | W69: COSCO | X69: PAITA | Y69: 10005779 | Z69: Inventario final | AA69: =B69&Y69&Z69 -> FEBRERO10005779Inventario final | AB69: =IFERROR(AG69/G69,0) -> 2021.2748 | AC69: =IFERROR(INDEX('Costos Producción Febrero'!$G$34:$G$57,MATCH(Resumen!Y69,'Costos Producción Febrero'!$B$34:$B$57,0))*AI69*G69,0)*1.25 -> 19215.061 | AD69: =IFERROR(INDEX('Costos Producción Febrero'!$H$34:$H$57,MATCH(Resumen!Y69,'Costos Producción Febrero'!$B$34:$B$57,0))*AI69*G69,0) -> 5850 | AE69: =IFERROR(INDEX('Costos Producción Febrero'!$I$34:$I$57,MATCH(Resumen!Y69,'Costos Producción Febrero'!$B$34:$B$57,0))*AI69*G69,0) -> 169.11096 | AF69: =IFERROR(INDEX('Costos Producción Febrero'!$J$34:$J$57,MATCH(Resumen!Y69,'Costos Producción Febrero'!$B$34:$B$57,0))*AI69*G69,0) -> 5084.9493 | AG69: =SUM(AC69:AF69) -> 30319.122 | AI69: =INDEX('Costos Producción Febrero'!$F$5:$F$28,MATCH(Resumen!Y69,'Costos Producción Febrero'!$B$5:$B$28,0)) -> 1765.074 | AK69: =P69-AG69 -> -12319.122 | AL69: =AK69/P69 -> -0.68439564 | AM69: =R69 -> 2100 | AN69: =1883/26*G69 -> 1086.3462 | AO69: =SUM(AM69:AN69) -> 3186.3462 | AP69: =78579/1995.8*G69 -> 590.58272 | AQ69: =S69*0.03 -> 477 | AR69: =AK69-AO69-AP69+AQ69 -> -15619.05 | AS69: =AR69/P69 -> -0.86772502 | AT69: =154473/1995.8*G69 -> 1160.9856 | AU69: =AR69-AT69 -> -16780.036 | AV69: =AU69/P69 -> -0.93222422 | AW69: =123484.35/1997.8*G69 -> 927.15249 | AX69: =AR69+AW69 -> -14691.898 | AY69: =AX69/P69 -> -0.81621655 | BA69: =P69/$G69 -> 1200 | BB69: =-AC69/$G69 -> -1281.0041 | BC69: =-AD69/$G69 -> -390 | BD69: =-AE69/$G69 -> -11.274064 | BE69: =-AF69/$G69 -> -338.99662 | BF69: =-AG69/$G69 -> -2021.2748 | BG69: =AK69/$G69 -> -821.27477 | BH69: =-AM69/$G69 -> -140 | BI69: =-AN69/$G69 -> -72.423077 | BJ69: =-AO69/$G69 -> -212.42308 | BK69: =-AP69/$G69 -> -39.372182 | BL69: =AQ69/$G69 -> 31.8 | BM69: =AR69/$G69 -> -1041.27 | BN69: =-AT69/$G69 -> -77.399038 | BO69: =AU69/$G69 -> -1118.6691 | BP69: =AW69/$G69 -> 61.810166 | BQ69: =AX69/$G69 -> -979.45986
B70: FEBRERO | C70: MARZO | D70: 170-2026B | E70: 43 | F70: 46092 | G70: 24 | H70: POTA REJOS CONGELADOS | I70: Rejos | J70: 2 - UP | K70: España | L70: Vigo | M70: KULALIA | N70: Ramon | O70: 2400 | P70: =O70*G70 -> 57600 | Q70: =+S70/G70 -> 2230.0104 | R70: =4079.75 -> 4079.75 | S70: =P70-R70 -> 53520.25 | T70: 1 | U70: CMA CGM BOLDNESS / 0DVODN1MA | V70: LMM0575562 | W70: CMA CGM | Y70: 10007162 | Z70: Inventario final | AA70: =B70&Y70&Z70 -> FEBRERO10007162Inventario final | AB70: =IFERROR(AG70/G70,0) -> 1921.1999 | AC70: =IFERROR(INDEX('Costos Producción Febrero'!$G$34:$G$57,MATCH(Resumen!Y70,'Costos Producción Febrero'!$B$34:$B$57,0))*AI70*G70,0)*1.25 -> 30642.441 | AD70: =IFERROR(INDEX('Costos Producción Febrero'!$H$34:$H$57,MATCH(Resumen!Y70,'Costos Producción Febrero'!$B$34:$B$57,0))*AI70*G70,0) -> 6960 | AE70: =IFERROR(INDEX('Costos Producción Febrero'!$I$34:$I$57,MATCH(Resumen!Y70,'Costos Producción Febrero'!$B$34:$B$57,0))*AI70*G70,0) -> 370.64106 | AF70: =IFERROR(INDEX('Costos Producción Febrero'!$J$34:$J$57,MATCH(Resumen!Y70,'Costos Producción Febrero'!$B$34:$B$57,0))*AI70*G70,0) -> 8135.7154 | AG70: =SUM(AC70:AF70) -> 46108.797 | AI70: =INDEX('Costos Producción Febrero'!$F$5:$F$28,MATCH(Resumen!Y70,'Costos Producción Febrero'!$B$5:$B$28,0)) -> 1665.8462 | AK70: =P70-AG70 -> 11491.203 | AL70: =AK70/P70 -> 0.19950005 | AM70: =R70 -> 4079.75 | AN70: =1883/26*G70 -> 1738.1538 | AO70: =SUM(AM70:AN70) -> 5817.9038 | AP70: =78579/1995.8*G70 -> 944.93236 | AQ70: =S70*0.03 -> 1605.6075 | AR70: =AK70-AO70-AP70+AQ70 -> 6333.9741 | AS70: =AR70/P70 -> 0.10996483 | AT70: =154473/1995.8*G70 -> 1857.5769 | AU70: =AR70-AT70 -> 4476.3972 | AV70: =AU70/P70 -> 0.077715229 | AW70: =123484.35/1997.8*G70 -> 1483.444 | AX70: =AR70+AW70 -> 7817.4181 | AY70: =AX70/P70 -> 0.13571906 | BA70: =P70/$G70 -> 2400 | BB70: =-AC70/$G70 -> -1276.7684 | BC70: =-AD70/$G70 -> -290 | BD70: =-AE70/$G70 -> -15.443377 | BE70: =-AF70/$G70 -> -338.98814 | BF70: =-AG70/$G70 -> -1921.1999 | BG70: =AK70/$G70 -> 478.80012 | BH70: =-AM70/$G70 -> -169.98958 | BI70: =-AN70/$G70 -> -72.423077 | BJ70: =-AO70/$G70 -> -242.41266 | BK70: =-AP70/$G70 -> -39.372182 | BL70: =AQ70/$G70 -> 66.900312 | BM70: =AR70/$G70 -> 263.91559 | BN70: =-AT70/$G70 -> -77.399038 | BO70: =AU70/$G70 -> 186.51655 | BP70: =AW70/$G70 -> 61.810166 | BQ70: =AX70/$G70 -> 325.72575
B71: FEBRERO | C71: MARZO | D71: 153-2026 | E71: 26 | F71: 46110 | G71: =26*1 -> 26 | H71: POTA REPRODUCTORES | I71: Rejos | K71: España | L71: Valencia | M71: OCEANUS FISH | N71: Ignacio / Ives | O71: 2950 | P71: =+G71*O71 -> 76700 | Q71: =+S71/G71 -> 2793.0865 | R71: =4079.75 -> 4079.75 | S71: =P71-R71 -> 72620.25 | T71: 1 | U71: CAPE SKAGEN 614N | V71: 19449468 | W71: HAPAG | Y71: 10007567 | Z71: Inventario final | AA71: =B71&Y71&Z71 -> FEBRERO10007567Inventario final | AB71: =IFERROR(AG71/G71,0) -> 1907.3338 | AC71: =IFERROR(INDEX('Costos Producción Febrero'!$G$34:$G$57,MATCH(Resumen!Y71,'Costos Producción Febrero'!$B$34:$B$57,0))*AI71*G71,0)*1.25 -> 33162.742 | AD71: =IFERROR(INDEX('Costos Producción Febrero'!$H$34:$H$57,MATCH(Resumen!Y71,'Costos Producción Febrero'!$B$34:$B$57,0))*AI71*G71,0) -> 7150 | AE71: =IFERROR(INDEX('Costos Producción Febrero'!$I$34:$I$57,MATCH(Resumen!Y71,'Costos Producción Febrero'!$B$34:$B$57,0))*AI71*G71,0) -> 463.66329 | AF71: =IFERROR(INDEX('Costos Producción Febrero'!$J$34:$J$57,MATCH(Resumen!Y71,'Costos Producción Febrero'!$B$34:$B$57,0))*AI71*G71,0) -> 8814.2736 | AG71: =SUM(AC71:AF71) -> 49590.678 | AI71: =INDEX('Costos Producción Febrero'!$F$5:$F$28,MATCH(Resumen!Y71,'Costos Producción Febrero'!$B$5:$B$28,0)) -> 1652.2358 | AK71: =P71-AG71 -> 27109.322 | AL71: =AK71/P71 -> 0.35344617 | AM71: =R71 -> 4079.75 | AN71: =1883/26*G71 -> 1883 | AO71: =SUM(AM71:AN71) -> 5962.75 | AP71: =78579/1995.8*G71 -> 1023.6767 | AQ71: =S71*0.03 -> 2178.6075 | AR71: =AK71-AO71-AP71+AQ71 -> 22301.502 | AS71: =AR71/P71 -> 0.29076274 | AT71: =154473/1995.8*G71 -> 2012.375 | AU71: =AR71-AT71 -> 20289.127 | AV71: =AU71/P71 -> 0.26452578 | AW71: =123484.35/1997.8*G71 -> 1607.0643 | AX71: =AR71+AW71 -> 23908.567 | AY71: =AX71/P71 -> 0.31171534 | BA71: =P71/$G71 -> 2950 | BB71: =-AC71/$G71 -> -1275.4901 | BC71: =-AD71/$G71 -> -275 | BD71: =-AE71/$G71 -> -17.833203 | BE71: =-AF71/$G71 -> -339.01052 | BF71: =-AG71/$G71 -> -1907.3338 | BG71: =AK71/$G71 -> 1042.6662 | BH71: =-AM71/$G71 -> -156.91346 | BI71: =-AN71/$G71 -> -72.423077 | BJ71: =-AO71/$G71 -> -229.33654 | BK71: =-AP71/$G71 -> -39.372182 | BL71: =AQ71/$G71 -> 83.792596 | BM71: =AR71/$G71 -> 857.75009 | BN71: =-AT71/$G71 -> -77.399038 | BO71: =AU71/$G71 -> 780.35105 | BP71: =AW71/$G71 -> 61.810166 | BQ71: =AX71/$G71 -> 919.56025
B72: FEBRERO | C72: MARZO | E72: 46111 | F72: 46111 | G72: 0 | H72: RESIDUOS DE POTA | I72: Residuos | J72: Residuos | K72: Residuos | L72: Residuos | M72: PROVEEDORA DE PRODUCTOS MARINOS | O72: 0 | P72: 26456.61 | Q72: 0 | R72: 0 | S72: =P72-R72 -> 26456.61 | AB72: =IFERROR(AG72/G72,0) -> 0 | AC72: =IFERROR(INDEX('Costos Producción Febrero'!$G$34:$G$57,MATCH(Resumen!Y72,'Costos Producción Febrero'!$B$34:$B$57,0))*AI72*G72,0)*1.25 -> 0 | AD72: =IFERROR(INDEX('Costos Producción Febrero'!$H$34:$H$57,MATCH(Resumen!Y72,'Costos Producción Febrero'!$B$34:$B$57,0))*AI72*G72,0) -> 0 | AE72: =IFERROR(INDEX('Costos Producción Febrero'!$I$34:$I$57,MATCH(Resumen!Y72,'Costos Producción Febrero'!$B$34:$B$57,0))*AI72*G72,0) -> 0 | AF72: =IFERROR(INDEX('Costos Producción Febrero'!$J$34:$J$57,MATCH(Resumen!Y72,'Costos Producción Febrero'!$B$34:$B$57,0))*AI72*G72,0) -> 0 | AG72: =SUM(AC72:AF72) -> 0 | AK72: =P72-AG72 -> 26456.61 | AL72: =AK72/P72 -> 1 | AM72: =R72 -> 0 | AN72: =1882/26*G72 -> 0 | AO72: =SUM(AM72:AN72) -> 0 | AP72: =56604/1634.3*G72 -> 0 | AQ72: 0 | AR72: =AK72-AO72-AP72+AQ72 -> 26456.61 | AS72: =AR72/P72 -> 1 | AT72: =131251/248*G72 -> 0 | AU72: =AR72-AT72 -> 26456.61 | AV72: =AU72/P72 -> 1 | AW72: =123530/248*G72 -> 0 | AX72: =AR72+AW72 -> 26456.61 | AY72: =AX72/P72 -> 1 | BA72: 0 | BB72: 0 | BC72: 0 | BD72: 0 | BE72: 0 | BF72: 0 | BG72: 0 | BH72: 0 | BI72: 0 | BJ72: 0 | BK72: 0 | BL72: 0 | BM72: 0 | BN72: 0 | BO72: 0 | BP72: 0 | BQ72: 0
