Workbook

Sheet TD
H1: 64340.28
A2: ANÁLISIS DE RENTABILIDAD
A4: EEFF PERU FROST (USD)
B5: Etiquetas de columna | H5: ANÁLISIS UNITARIO | O5: ANÁLISIS VÉRTICAL
A6: Valores | B6: ENERO | C6: FEBRERO | D6: MARZO | E6: Total general | H6: NOMBRE | I6: ENERO | J6: FEBRERO | K6: MARZO | L6: TOTAL | O6: NOMBRE | P6: ENERO | Q6: FEBRERO | R6: MARZO | S6: TOTAL
A7: Suma de Cantidad | B7: 248 | C7: 1634.3 | D7: 1995.8 | E7: 3878.1
A8: Suma de VALOR CFR | B8: 564615.28 | C8: 2769824.5 | D8: 3909830 | E8: 7244269.8 | H8: Suma de VALOR CFR | I8: =B8/B$7 -> 2276.6745 | J8: =C8/C$7 -> 1694.8079 | K8: =D8/D$7 -> 1959.029 | L8: =E8/E$7 -> 1867.9946 | O8: Suma de VALOR CFR | P8: =B8/B$8 -> 1 | Q8: =C8/C$8 -> 1 | R8: =D8/D$8 -> 1 | S8: =E8/E$8 -> 1
A9: Suma de COSTO VENTAS | B9: 442635.6 | C9: 2804315 | D9: 3522312 | E9: 6769262.6 | H9: Suma de COSTO VENTAS | I9: =B9/B$7 -> 1784.821 | J9: =C9/C$7 -> 1715.912 | K9: =D9/D$7 -> 1764.8622 | L9: =E9/E$7 -> 1745.5101 | O9: Suma de COSTO VENTAS | P9: =B9/B$8 -> 0.78395965 | Q9: =C9/C$8 -> 1.0124522 | R9: =D9/D$8 -> 0.90088623 | S9: =E9/E$8 -> 0.93442995
A10: Suma de UTILIDAD BRUTA | B10: 121979.68 | C10: -34490.515 | D10: 387518 | E10: 475007.16 | H10: Suma de UTILIDAD BRUTA | I10: =B10/B$7 -> 491.85355 | J10: =C10/C$7 -> -21.104152 | K10: =D10/D$7 -> 194.16675 | L10: =E10/E$7 -> 122.48451 | O10: Suma de UTILIDAD BRUTA | P10: =B10/B$8 -> 0.21604035 | Q10: =C10/C$8 -> -0.012452239 | R10: =D10/D$8 -> 0.099113772 | S10: =E10/E$8 -> 0.065570055
A11: Suma de GASTO VENTAS | B11: 50584.692 | C11: 300510.54 | D11: 363885.06 | E11: 714980.29 | H11: Suma de GASTO VENTAS | I11: =B11/B$7 -> 203.97053 | J11: =C11/C$7 -> 183.87722 | K11: =D11/D$7 -> 182.32541 | L11: =E11/E$7 -> 184.36355 | O11: Suma de GASTO VENTAS | P11: =B11/B$8 -> 0.089591433 | Q11: =C11/C$8 -> 0.10849443 | R11: =D11/D$8 -> 0.093069279 | S11: =E11/E$8 -> 0.098695978
A12: Suma de GASTO ADM | B12: 60070 | C12: 65590 | D12: 70585.576 | E12: 196245.58 | H12: Suma de GASTO ADM | I12: =B12/B$7 -> 242.21774 | J12: =C12/C$7 -> 40.13339 | K12: =D12/D$7 -> 35.367059 | L12: =E12/E$7 -> 50.603537 | O12: Suma de GASTO ADM | P12: =B12/B$8 -> 0.10639103 | Q12: =C12/C$8 -> 0.023680201 | R12: =D12/D$8 -> 0.018053362 | S12: =E12/E$8 -> 0.027089766
A13: Suma de DRAWBACK | B13: 15120.72 | C13: 75707.235 | D13: 109832.62 | E13: 200660.57 | H13: Suma de DRAWBACK | I13: =B13/B$7 -> 60.970645 | J13: =C13/C$7 -> 46.323952 | K13: =D13/D$7 -> 55.031876 | L13: =E13/E$7 -> 51.74198 | O13: Suma de DRAWBACK | P13: =B13/B$8 -> 0.026780572 | Q13: =C13/C$8 -> 0.027332864 | R13: =D13/D$8 -> 0.028091405 | S13: =E13/E$8 -> 0.027699213
A14: Suma de UTILIDAD OPERATIVA | B14: 26445.708 | C14: -324883.82 | D14: 62879.984 | E14: -235558.13 | H14: Suma de UTILIDAD OPERATIVA | I14: =B14/B$7 -> 106.63592 | J14: =C14/C$7 -> -198.79081 | K14: =D14/D$7 -> 31.506155 | L14: =E14/E$7 -> -60.740602 | O14: Suma de UTILIDAD OPERATIVA | P14: =B14/B$8 -> 0.046838456 | Q14: =C14/C$8 -> -0.11729401 | R14: =D14/D$8 -> 0.016082537 | S14: =E14/E$8 -> -0.032516476
A15: Suma de GASTO FINANCIERO | B15: 131251 | C15: 148498 | D15: 105578.68 | E15: 385327.68 | H15: Suma de GASTO FINANCIERO | I15: =B15/B$7 -> 529.2379 | J15: =C15/C$7 -> 90.863367 | K15: =D15/D$7 -> 52.90043 | L15: =E15/E$7 -> 99.359913 | O15: Suma de GASTO FINANCIERO | P15: =B15/B$8 -> 0.23246094 | Q15: =C15/C$8 -> 0.053612783 | R15: =D15/D$8 -> 0.027003394 | S15: =E15/E$8 -> 0.053190686
A16: Suma de UTILIDAD NETA | B16: -104805.29 | C16: -473381.82 | D16: -42698.695 | E16: -620885.81 | H16: Suma de UTILIDAD NETA | I16: =B16/B$7 -> -422.60199 | J16: =C16/C$7 -> -289.65418 | K16: =D16/D$7 -> -21.394276 | L16: =E16/E$7 -> -160.10051 | O16: Suma de UTILIDAD NETA | P16: =B16/B$8 -> -0.18562249 | Q16: =C16/C$8 -> -0.17090679 | R16: =D16/D$8 -> -0.010920857 | S16: =E16/E$8 -> -0.085707162
A17: Suma de DEPRECIACIÓN | B17: 123530 | C17: 124152.39 | D17: 123360.73 | E17: 371043.12 | H17: Suma de DEPRECIACIÓN | I17: =B17/B$7 -> 498.10484 | J17: =C17/C$7 -> 75.96671 | K17: =D17/D$7 -> 61.810166 | L17: =E17/E$7 -> 95.676523 | O17: Suma de DEPRECIACIÓN | P17: =B17/B$8 -> 0.21878614 | Q17: =C17/C$8 -> 0.044823199 | R17: =D17/D$8 -> 0.031551431 | S17: =E17/E$8 -> 0.051218844
A18: Suma de EBITDA | B18: 149975.71 | C18: -200731.43 | D18: 186240.71 | E18: 135485 | H18: Suma de EBITDA | I18: =B18/B$7 -> 604.74076 | J18: =C18/C$7 -> -122.8241 | K18: =D18/D$7 -> 93.316321 | L18: =E18/E$7 -> 34.935921 | O18: Suma de EBITDA | P18: =B18/B$8 -> 0.2656246 | Q18: =C18/C$8 -> -0.07247081 | R18: =D18/D$8 -> 0.047633967 | S18: =E18/E$8 -> 0.018702368
A24: ANÁLISIS POR PRODUCTO
A26: RANKING DE VENTAS (USD) | H26: UTILIDAD NETA (USD) | O26: EBITDA (USD)
A27: Suma de VALOR CFR | B27: Etiquetas de columna | H27: Suma de UTILIDAD NETA | I27: Etiquetas de columna | O27: Suma de EBITDA | P27: Etiquetas de columna
A28: Etiquetas de fila | B28: ENERO | C28: FEBRERO | D28: MARZO | E28: Total general | F28: % | H28: Etiquetas de fila | I28: ENERO | J28: FEBRERO | K28: MARZO | L28: Total general | M28: MG | O28: Etiquetas de fila | P28: ENERO | Q28: FEBRERO | R28: MARZO | S28: Total general | T28: MG
A29: POTA REJOS CONGELADOS | B29: 149248 | C29: 532695 | D29: 795200 | E29: 1477143 | F29: =E29/$E$40 -> 0.20390502 | H29: POTA REJOS CONGELADOS | I29: -8043.0503 | J29: 114631.26 | K29: 147844.77 | L29: 254432.98 | M29: =L29/E29 -> 0.17224668 | O29: POTA REJOS CONGELADOS | P29: 51501.735 | Q29: 149500.02 | R29: 185813.97 | S29: 386815.73 | T29: =S29/E29 -> 0.26186749
A30: POTA ALAS CONGELADAS | B30: 135915 | C30: 710550 | D30: 772480 | E30: 1618945 | F30: =E30/$E$40 -> 0.22347939 | H30: POTA ALAS CONGELADAS | I30: -53443.473 | J30: -161122.81 | K30: -117583.75 | L30: -332150.03 | M30: =L30/E30 -> -0.20516449 | O30: POTA ALAS CONGELADAS | P30: 20525.205 | Q30: -84494.955 | R30: -62201.474 | S30: -126171.22 | T30: =S30/E30 -> -0.077934225
A31: POTA FILETE CONGELADO | B31: 94800 | C31: 1147500 | D31: 432150 | E31: 1674450 | F31: =E31/$E$40 -> 0.23114131 | H31: POTA FILETE CONGELADO | I31: -37930.282 | J31: -503763.5 | K31: -145916.47 | L31: -687610.25 | M31: =L31/E31 -> -0.41064842 | O31: POTA FILETE CONGELADO | P31: 11382.17 | Q31: -368626.2 | R31: -112306.27 | S31: -469550.3 | T31: =S31/E31 -> -0.28042061
A32: POTA FILETE PRECOCIDO | C32: 91800 | D32: 1004400 | E32: 1096200 | F32: =E32/$E$40 -> 0.1513196 | H32: POTA FILETE PRECOCIDO | J32: 29374.465 | K32: 267757.03 | L32: 297131.49 | M32: =L32/E32 -> 0.27105591 | O32: POTA FILETE PRECOCIDO | Q32: 33879.042 | R32: 304923.26 | S32: 338802.3 | T32: =S32/E32 -> 0.30906979
A33: POTA NUCAS | B33: 35874 | C33: 23456 | D33: 470900 | E33: 530230 | F33: =E33/$E$40 -> 0.073193022 | H33: POTA NUCAS | I33: -21331.27 | J33: -6620.887 | K33: -339879.92 | L33: -367832.08 | M33: =L33/E33 -> -0.69372174 | O33: POTA NUCAS | P33: -743.32143 | Q33: -4290.9886 | R33: -295716.34 | S33: -300750.65 | T33: =S33/E33 -> -0.56720791
A34: POTA ALAS COCIDAS | D34: 180900 | E34: 180900 | F34: =E34/$E$40 -> 0.024971461 | H34: POTA ALAS COCIDAS | K34: 74731.171 | L34: 74731.171 | M34: =L34/E34 -> 0.41310763 | O34: POTA ALAS COCIDAS | R34: 80925.543 | S34: 80925.543 | T34: =S34/E34 -> 0.4473496
A35: POTA REPRODUCTORES | B35: 74064 | C35: 77585 | D35: 139200 | E35: 290849 | F35: =E35/$E$40 -> 0.040148836 | H35: POTA REPRODUCTORES | I35: 2375.0532 | J35: 20917.792 | K35: 40825.448 | L35: 64118.293 | M35: =L35/E35 -> 0.22045217 | O35: POTA REPRODUCTORES | P35: 29085.965 | Q35: 25422.368 | R35: 46675.688 | S35: 101184.02 | T35: =S35/E35 -> 0.34789193
A36: POTA CONOS | B36: 50400 | C36: 69000 | D36: 76800 | E36: 196200 | F36: =E36/$E$40 -> 0.027083475 | H36: POTA CONOS | I36: -10746.551 | J36: 12040.06 | K36: -1900.0703 | L36: -606.56114 | M36: =L36/E36 -> -0.0030915451 | O36: POTA CONOS | P36: 13909.675 | Q36: 17708.341 | R36: 3606.0384 | S36: 35224.054 | T36: =S36/E36 -> 0.17953137
A37: POTA MEMBRANA PRECOCIDA | C37: 38606.25 | D37: 37800 | E37: 76406.25 | F37: =E37/$E$40 -> 0.010547129 | H37: POTA MEMBRANA PRECOCIDA | J37: -9624.6422 | K37: 31423.105 | L37: 21798.463 | M37: =L37/E37 -> 0.28529686 | O37: POTA MEMBRANA PRECOCIDA | Q37: -5120.0656 | R37: 34520.292 | S37: 29400.226 | T37: =S37/E37 -> 0.38478823
A38: POTA TELILLA PRECOCIDA | C38: 38606.25 | E38: 38606.25 | F38: =E38/$E$40 -> 0.0053292121 | H38: POTA TELILLA PRECOCIDA | J38: -9239.5639 | L38: -9239.5639 | M38: =L38/E38 -> -0.23932819 | O38: POTA TELILLA PRECOCIDA | Q38: -4734.9873 | S38: -4734.9873 | T38: =S38/E38 -> -0.12264821
A39: RESIDUOS DE POTA | B39: 24314.28 | C39: 40026 | E39: 64340.28 | F39: =E39/$E$40 -> 0.0088815411 | H39: RESIDUOS DE POTA | I39: 24314.28 | J39: 40026 | L39: 64340.28 | M39: =L39/E39 -> 1 | O39: RESIDUOS DE POTA | P39: 24314.28 | Q39: 40026 | S39: 64340.28 | T39: =S39/E39 -> 1
A40: Total general | B40: 564615.28 | C40: 2769824.5 | D40: 3909830 | E40: 7244269.8 | F40: =E40/$E$40 -> 1 | H40: Total general | I40: -104805.29 | J40: -473381.82 | K40: -42698.695 | L40: -620885.81 | M40: =L40/E40 -> -0.085707162 | O40: Total general | P40: 149975.71 | Q40: -200731.43 | R40: 186240.71 | S40: 135485
A46: ANÁLISIS POR CLIENTE
A48: RANKING DE VENTAS (USD) | H48: UTILIDAD NETA (USD) | O48: EBITDA (USD) | V48: UTILIDAD BRUTA (USD)
A49: Suma de VALOR CFR | B49: Etiquetas de columna | H49: Suma de UTILIDAD NETA | I49: Etiquetas de columna | M49: MG | O49: Suma de EBITDA | P49: Etiquetas de columna | T49: MG | V49: Suma de UTILIDAD BRUTA | W49: Etiquetas de columna | AA49: MG
A50: Etiquetas de fila | B50: ENERO | C50: FEBRERO | D50: MARZO | E50: Total general | F50: % | H50: Etiquetas de fila | I50: ENERO | J50: FEBRERO | K50: MARZO | L50: Total general | M50: NETO | O50: Etiquetas de fila | P50: ENERO | Q50: FEBRERO | R50: MARZO | S50: Total general | T50: EBITDA | V50: Etiquetas de fila | W50: ENERO | X50: FEBRERO | Y50: MARZO | Z50: Total general | AA50: BRUTO
A51: TSUJINO | B51: 281115 | C51: 438056 | D51: 1115680 | E51: 1834851 | F51: =E51/$E$68 -> 0.25328309 | H51: TSUJINO | I51: -102120.31 | J51: -57455.589 | K51: -251483.85 | L51: -411059.75 | M51: =L51/E51 -> -0.22402895 | O51: TSUJINO | P51: 45817.05 | Q51: -13420.798 | R51: -168571.03 | S51: -136174.78 | T51: =S51/E51 -> -0.074215716 | V51: TSUJINO | W51: 28635 | X51: 10322.644 | Y51: -97552 | Z51: -58594.356 | AA51: =Z51/E51 -> -0.031934122
A52: KULALIA | C52: 390000 | D52: 833200 | E52: 1223200 | F52: =E52/$E$68 -> 0.1688507 | H52: KULALIA | J52: 78525.378 | K52: 184357.23 | L52: 262882.61 | M52: =L52/E52 -> 0.21491384 | O52: KULALIA | Q52: 104551.82 | R52: 222326.43 | S52: 326878.26 | T52: =S52/E52 -> 0.26723206 | V52: KULALIA | X52: 122414.63 | Y52: 259520 | Z52: 381934.63 | AA52: =Z52/E52 -> 0.31224218
A53: AVANCE GROUP | C53: 1066950 | E53: 1066950 | F53: =E53/$E$68 -> 0.14728193 | H53: AVANCE GROUP | J53: -484128.94 | L53: -484128.94 | M53: =L53/E53 -> -0.45375035 | O53: AVANCE GROUP | Q53: -353446.17 | S53: -353446.17 | T53: =S53/E53 -> -0.33126779 | V53: AVANCE GROUP | X53: -275132.6 | Z53: -275132.6 | AA53: =Z53/E53 -> -0.25786831
A54: Pesciro Asia International LTD. | D54: 352350 | E54: 352350 | F54: =E54/$E$68 -> 0.048638443 | H54: Pesciro Asia International LTD. | K54: -123205.54 | L54: -123205.54 | M54: =L54/E54 -> -0.34966806 | O54: Pesciro Asia International LTD. | R54: -95330.866 | S54: -95330.866 | T54: =S54/E54 -> -0.2705573 | V54: Pesciro Asia International LTD. | Y54: -70470 | Z54: -70470 | AA54: =Z54/E54 -> -0.2
A55: LONGKOU JIABAO AQUATIC | D55: 669600 | E55: 669600 | F55: =E55/$E$68 -> 0.092431676 | H55: LONGKOU JIABAO AQUATIC | K55: 178504.68 | L55: 178504.68 | M55: =L55/E55 -> 0.26658406 | O55: LONGKOU JIABAO AQUATIC | R55: 203282.17 | S55: 203282.17 | T55: =S55/E55 -> 0.30358747 | V55: LONGKOU JIABAO AQUATIC | Y55: 213840 | Z55: 213840 | AA55: =Z55/E55 -> 0.31935484
A56: OVERSEA | C56: 142695 | D56: 135200 | E56: 277895 | F56: =E56/$E$68 -> 0.038360664 | H56: OVERSEA | J56: 36105.885 | K56: 33508.171 | L56: 69614.055 | M56: =L56/E56 -> 0.25050489 | O56: OVERSEA | Q56: 44948.202 | R56: 39473.122 | S56: 84421.323 | T56: =S56/E56 -> 0.30378856 | V56: OVERSEA | X56: 50815.395 | Y56: 45760 | Z56: 96575.395 | AA56: =Z56/E56 -> 0.34752477
A57: LONGKOU BOHAI | D57: 334800 | E57: 334800 | F57: =E57/$E$68 -> 0.046215838 | H57: LONGKOU BOHAI | K57: 89252.342 | L57: 89252.342 | M57: =L57/E57 -> 0.26658406 | O57: LONGKOU BOHAI | R57: 101641.09 | S57: 101641.09 | T57: =S57/E57 -> 0.30358747 | V57: LONGKOU BOHAI | Y57: 106920 | Z57: 106920 | AA57: =Z57/E57 -> 0.31935484
A58: DAIRECK S.A. | B58: 44722 | D58: 245300 | E58: 290022 | F58: =E58/$E$68 -> 0.040034677 | H58: DAIRECK S.A. | I58: -23150.491 | K58: -214521.02 | L58: -237671.51 | M58: =L58/E58 -> -0.81949475 | O58: DAIRECK S.A. | P58: 1505.7349 | R58: -189628.82 | S58: -188123.08 | T58: =S58/E58 -> -0.64865107 | V58: DAIRECK S.A. | W58: -1193.6 | Y58: -158320 | Z58: -159513.6 | AA58: =Z58/E58 -> -0.55000517
A59: Longkou Yunfeng Aquatic | C59: 222750 | D59: 37800 | E59: 260550 | F59: =E59/$E$68 -> 0.035966358 | H59: Longkou Yunfeng Aquatic | J59: -47042.09 | K59: 31423.105 | L59: -15618.985 | M59: =L59/E59 -> -0.059946209 | O59: Longkou Yunfeng Aquatic | Q59: -24519.208 | R59: 34520.292 | S59: 10001.084 | T59: =S59/E59 -> 0.03838451 | V59: Longkou Yunfeng Aquatic | X59: -12255.667 | Y59: 37800 | Z59: 25544.333 | AA59: =Z59/E59 -> 0.098040044
A60: FOOD & BEVERAGES TRADERS | C60: 222750 | E60: 222750 | F60: =E60/$E$68 -> 0.030748441 | H60: FOOD & BEVERAGES TRADERS | J60: -70840.514 | L60: -70840.514 | M60: =L60/E60 -> -0.318027 | O60: FOOD & BEVERAGES TRADERS | Q60: -48317.631 | S60: -48317.631 | T60: =S60/E60 -> -0.21691417 | V60: FOOD & BEVERAGES TRADERS | X60: -28545.39 | Z60: -28545.39 | AA60: =Z60/E60 -> -0.1281499
A61: GLOBAL OCEAN | B61: 140400 | C61: 77585 | E61: 217985 | F61: =E61/$E$68 -> 0.030090679 | H61: GLOBAL OCEAN | I61: -6223.8295 | J61: 20917.792 | L61: 14693.962 | M61: =L61/E61 -> 0.067408135 | O61: GLOBAL OCEAN | P61: 49252.679 | Q61: 25422.368 | S61: 74675.047 | T61: =S61/E61 -> 0.34256966 | V61: GLOBAL OCEAN | W61: 43740 | X61: 28179.767 | Z61: 71919.767 | AA61: =Z61/E61 -> 0.32992989
A62: SACRAMENTO CO., LTD | C62: 91800 | E62: 91800 | F62: =E62/$E$68 -> 0.012672085 | H62: SACRAMENTO CO., LTD | J62: 29374.465 | L62: 29374.465 | M62: =L62/E62 -> 0.31998328 | O62: SACRAMENTO CO., LTD | Q62: 33879.042 | S62: 33879.042 | T62: =S62/E62 -> 0.36905274 | V62: SACRAMENTO CO., LTD | X62: 34702.07 | Z62: 34702.07 | AA62: =Z62/E62 -> 0.37801819
A63: Hunan Jinyueyang | C63: 77212.5 | E63: 77212.5 | F63: =E63/$E$68 -> 0.010658424 | H63: Hunan Jinyueyang | J63: -18864.206 | L63: -18864.206 | M63: =L63/E63 -> -0.24431544 | O63: Hunan Jinyueyang | Q63: -9855.053 | S63: -9855.053 | T63: =S63/E63 -> -0.12763546 | V63: Hunan Jinyueyang | X63: -5017.3715 | Z63: -5017.3715 | AA63: =Z63/E63 -> -0.064981338
A64: OCEANUS FISH | B64: 74064 | D64: 76700 | E64: 150764 | F64: =E64/$E$68 -> 0.020811483 | H64: OCEANUS FISH | I64: 2375.0532 | K64: 26803.903 | L64: 29178.956 | M64: =L64/E64 -> 0.19354061 | O64: OCEANUS FISH | P64: 29085.965 | R64: 29786.378 | S64: 58872.343 | T64: =S64/E64 -> 0.39049337 | V64: OCEANUS FISH | W64: 26484 | Y64: 32500 | Z64: 58984 | AA64: =Z64/E64 -> 0.39123398
A65: Pesciro SL | D65: 39000 | E65: 39000 | F65: =E65/$E$68 -> 0.0053835654 | H65: Pesciro SL | K65: -16069.805 | L65: -16069.805 | M65: =L65/E65 -> -0.41204627 | O65: Pesciro SL | R65: -13087.329 | S65: -13087.329 | T65: =S65/E65 -> -0.33557254 | V65: Pesciro SL | Y65: -6240 | Z65: -6240 | AA65: =Z65/E65 -> -0.16
A66: SHANDONG SHEENIER | D66: 70200 | E66: 70200 | F66: =E66/$E$68 -> 0.0096904177 | H66: SHANDONG SHEENIER | K66: 18732.085 | L66: 18732.085 | M66: =L66/E66 -> 0.26683882 | O66: SHANDONG SHEENIER | R66: 21829.272 | S66: 21829.272 | T66: =S66/E66 -> 0.31095828 | V66: SHANDONG SHEENIER | Y66: 23760 | Z66: 23760 | AA66: =Z66/E66 -> 0.33846154
A67: PROVEEDORA DE PRODUCTOS MARINOS | B67: 24314.28 | C67: 40026 | E67: 64340.28 | F67: =E67/$E$68 -> 0.0088815411 | H67: PROVEEDORA DE PRODUCTOS MARINOS | I67: 24314.28 | J67: 40026 | L67: 64340.28 | M67: =L67/E67 -> 1 | O67: PROVEEDORA DE PRODUCTOS MARINOS | P67: 24314.28 | Q67: 40026 | S67: 64340.28 | T67: =S67/E67 -> 1 | V67: PROVEEDORA DE PRODUCTOS MARINOS | W67: 24314.28 | X67: 40026 | Z67: 64340.28 | AA67: =Z67/E67 -> 1
A68: Total general | B68: 564615.28 | C68: 2769824.5 | D68: 3909830 | E68: 7244269.8 | F68: =E68/$E$68 -> 1 | H68: Total general | I68: -104805.29 | J68: -473381.82 | K68: -42698.695 | L68: -620885.81 | M68: =L68/E68 -> -0.085707162 | O68: Total general | P68: 149975.71 | Q68: -200731.43 | R68: 186240.71 | S68: 135485 | T68: =S68/E68 -> 0.018702368 | V68: Total general | W68: 121979.68 | X68: -34490.515 | Y68: 387518 | Z68: 475007.16 | AA68: =Z68/E68 -> 0.065570055

Sheet Resumen
G2: X | H2: X | M2: X | P2: X | AU2: X | AV2: X | BA2: ANÁLISIS UNITARIO
B3: MES LINK | C3: MES EJERCICIO | D3: FP | E3: Emision | F3: Fecha Embarque | G3: Cantidad | H3: Producto | I3: Corte | J3: Espec. | K3: País | L3: Puerto | M3: Cliente (Razón Social) | N3: Contacto | O3: Precio TM | P3: VALOR CFR | Q3: FOB / TM | R3: Costo Flete | S3: VALOR FOB | T3: Cantidad de FCL (Contenedores) | U3: M/V Nave | V3: Booking | W3: Naviera | X3: Puerto | Y3: CÓDIGO | Z3: Categoría | AA3: MATCH | AB3: COSTO UNITARIO | AC3: Materia Prima | AD3: MOD | AE3: Envases | AF3: CIF | AG3: COSTO VENTAS | AH3: Cant | AI3: C.U | AJ3: Cotos Vta | AK3: UTILIDAD BRUTA | AL3: MARGEN BRUTO | AM3: Flete | AN3: SS Logístico | AO3: GASTO VENTAS | AP3: GASTO ADM | AQ3: DRAWBACK | AR3: UTILIDAD OPERATIVA | AS3: MARGEN OPERATIVO | AT3: GASTO FINANCIERO | AU3: UTILIDAD NETA | AV3: MARGEN NETO | AW3: DEPRECIACIÓN | AX3: EBITDA | AY3: MARGEN EBITDA | BA3: PRECIO CFR | BB3: Materia Prima | BC3: MOD | BD3: Envases | BE3: CIF | BF3: COSTO VENTAS | BG3: UTILIDAD BRUTA | BH3: Flete | BI3: SS Logístico | BJ3: GASTO VENTAS | BK3: GASTO ADM | BL3: DRAWBACK | BM3: UTILIDAD OPERATIVA | BN3: GASTO FINANCIERO | BO3: UTILIDAD NETA | BP3: DEPRECIACIÓN | BQ3: EBITDA
B4: ENERO | C4: =B4 -> ENERO | D4: 127-2025 | E4: 325 | F4: 46033 | G4: 26 | H4: POTA REPRODUCTORES | I4: Rejos | K4: España | L4: Valencia | M4: OCEANUS FISH | N4: Ignacio / Ives | O4: =P4/G4 -> 2848.6154 | P4: =78000*0+74064 -> 74064 | Q4: =S4/G4 -> 2670.3846 | R4: 4634 | S4: =P4-R4 -> 69430 | T4: 1 | U4: MERSIN EXPRESS 603N | V4: 26106924 | W4: HAPAG | X4: PAITA | Y4: 10007567 | Z4: Compensación | AA4: =B4&Y4&Z4 -> ENERO10007567Compensación | AB4: =INDEX('Detalle Costos'!$L$5:$L$158,MATCH(Resumen!AA4,'Detalle Costos'!$C$5:$C$158,0))*1000 -> 1830 | AC4: =IFERROR(INDEX('Detalle Costos'!$X$5:$X$158,MATCH(Resumen!AA4,'Detalle Costos'!$C$5:$C$158,0))*AG4,0) -> 31604.019 | AD4: =IFERROR(INDEX('Detalle Costos'!$Z$5:$Z$158,MATCH(Resumen!AA4,'Detalle Costos'!$C$5:$C$158,0))*AG4,0) -> 7767.649 | AE4: =IFERROR(INDEX('Detalle Costos'!$Y$5:$Y$158,MATCH(Resumen!AA4,'Detalle Costos'!$C$5:$C$158,0))*AG4,0) -> 466.19182 | AF4: =IFERROR(INDEX('Detalle Costos'!$AA$5:$AA$158,MATCH(Resumen!AA4,'Detalle Costos'!$C$5:$C$158,0))*AG4,0) -> 7742.1407 | AG4: =AB4*G4 -> 47580 | AH4: =48.96-AH17 -> 22.658 | AI4: =+AJ4/AH4 -> 1829.8235 | AJ4: =89589.14-AJ17 -> 41460.14 | AK4: =P4-AG4 -> 26484 | AL4: =AK4/P4 -> 0.35758263 | AM4: =R4 -> 4634 | AN4: =1500/26*G4 -> 1500 | AO4: =SUM(AM4:AN4) -> 6134 | AP4: =60070/248*G4 -> 6297.6613 | AQ4: =S4*0.03 -> 2082.9 | AR4: =AK4-AO4-AP4+AQ4 -> 16135.239 | AS4: =AR4/P4 -> 0.21785535 | AT4: =131251/248*G4 -> 13760.185 | AU4: =AR4-AT4 -> 2375.0532 | AV4: =AU4/P4 -> 0.03206758 | AW4: =123530/248*G4 -> 12950.726 | AX4: =AR4+AW4 -> 29085.965 | AY4: =AX4/P4 -> 0.39271393 | BA4: =P4/$G4 -> 2848.6154 | BB4: =-AC4/$G4 -> -1215.5392 | BC4: =-AD4/$G4 -> -298.75573 | BD4: =-AE4/$G4 -> -17.930455 | BE4: =-AF4/$G4 -> -297.77464 | BF4: =-AG4/$G4 -> -1830 | BG4: =AK4/$G4 -> 1018.6154 | BH4: =-AM4/$G4 -> -178.23077 | BI4: =-AN4/$G4 -> -57.692308 | BJ4: =-AO4/$G4 -> -235.92308 | BK4: =-AP4/$G4 -> -242.21774 | BL4: =AQ4/$G4 -> 80.111538 | BM4: =AR4/$G4 -> 620.5861 | BN4: =-AT4/$G4 -> -529.2379 | BO4: =AU4/$G4 -> 91.348201 | BP4: =AW4/$G4 -> 498.10484 | BQ4: =AX4/$G4 -> 1118.6909
B5: ENERO | C5: =B5 -> ENERO | D5: 128-2025B | E5: 325 | F5: 46053 | G5: 17.04 | H5: POTA NUCAS | I5: Nucas | J5: 1000-up | K5: Tailandia | L5: Lat Krabang | M5: DAIRECK S.A. | N5: Julieta | O5: 1850 | P5: 31524 | Q5: 1656.338 | R5: =3300/24*G5 -> 2343 | S5: =P5-R5 -> 29181 | T5: 1 | U5: ECO SIROCCO 26005S | V5: 6443191850 | W5: COSCO | X5: PAITA | Y5: 10005779 | Z5: Compensación | AA5: =B5&Y5&Z5 -> ENERO10005779Compensación | AB5: =INDEX('Detalle Costos'!$L$5:$L$158,MATCH(Resumen!AA5,'Detalle Costos'!$C$5:$C$158,0))*1000 -> 1930 | AC5: =IFERROR(INDEX('Detalle Costos'!$X$5:$X$158,MATCH(Resumen!AA5,'Detalle Costos'!$C$5:$C$158,0))*AG5,0) -> 20697.485 | AD5: =IFERROR(INDEX('Detalle Costos'!$Z$5:$Z$158,MATCH(Resumen!AA5,'Detalle Costos'!$C$5:$C$158,0))*AG5,0) -> 6988.7487 | AE5: =IFERROR(INDEX('Detalle Costos'!$Y$5:$Y$158,MATCH(Resumen!AA5,'Detalle Costos'!$C$5:$C$158,0))*AG5,0) -> 251.15165 | AF5: =IFERROR(INDEX('Detalle Costos'!$AA$5:$AA$158,MATCH(Resumen!AA5,'Detalle Costos'!$C$5:$C$158,0))*AG5,0) -> 4949.8151 | AG5: =AB5*G5 -> 32887.2 | AH5: 17.04 | AI5: =+AJ5/AH5 -> 1977.4951 | AJ5: 33696.517 | AK5: =P5-AG5 -> -1363.2 | AL5: =AK5/P5 -> -0.043243243 | AM5: =R5 -> 2343 | AN5: =1500/26*G5 -> 983.07692 | AO5: =SUM(AM5:AN5) -> 3326.0769 | AP5: =60070/248*G5 -> 4127.3903 | AQ5: =S5*0.03 -> 875.43 | AR5: =AK5-AO5-AP5+AQ5 -> -7941.2372 | AS5: =AR5/P5 -> -0.25191084 | AT5: =131251/248*G5 -> 9018.2139 | AU5: =AR5-AT5 -> -16959.451 | AV5: =AU5/P5 -> -0.53798538 | AW5: =123530/248*G5 -> 8487.7065 | AX5: =AR5+AW5 -> 546.46921 | AY5: =AX5/P5 -> 0.017335021 | BA5: =P5/$G5 -> 1850 | BB5: =-AC5/$G5 -> -1214.6411 | BC5: =-AD5/$G5 -> -410.13784 | BD5: =-AE5/$G5 -> -14.738946 | BE5: =-AF5/$G5 -> -290.48211 | BF5: =-AG5/$G5 -> -1930 | BG5: =AK5/$G5 -> -80 | BH5: =-AM5/$G5 -> -137.5 | BI5: =-AN5/$G5 -> -57.692308 | BJ5: =-AO5/$G5 -> -195.19231 | BK5: =-AP5/$G5 -> -242.21774 | BL5: =AQ5/$G5 -> 51.375 | BM5: =AR5/$G5 -> -466.03505 | BN5: =-AT5/$G5 -> -529.2379 | BO5: =AU5/$G5 -> -995.27295 | BP5: =AW5/$G5 -> 498.10484 | BQ5: =AX5/$G5 -> 32.069789
B6: ENERO | C6: =B6 -> ENERO | D6: 128-2025B | E6: 325 | F6: 46053 | G6: 3 | H6: POTA NUCAS | I6: Nucas | J6: 500 - 1 kg. | K6: Tailandia | L6: Lat Krabang | M6: DAIRECK S.A. | N6: Julieta | O6: 1450 | P6: 4350 | Q6: 1450 | R6: =3300/24*G6 -> 412.5 | S6: =P6-R6 -> 3937.5 | T6: 0 | V6: 6443191850 | W6: COSCO | X6: PAITA | Y6: 10005781 | Z6: Compensación | AA6: =B6&Y6&Z6 -> ENERO10005781Compensación | AB6: =INDEX('Detalle Costos'!$L$5:$L$158,MATCH(Resumen!AA6,'Detalle Costos'!$C$5:$C$158,0))*1000 -> 1980 | AC6: =IFERROR(INDEX('Detalle Costos'!$X$5:$X$158,MATCH(Resumen!AA6,'Detalle Costos'!$C$5:$C$158,0))*AG6,0) -> 3757.0132 | AD6: =IFERROR(INDEX('Detalle Costos'!$Z$5:$Z$158,MATCH(Resumen!AA6,'Detalle Costos'!$C$5:$C$158,0))*AG6,0) -> 1227.8049 | AE6: =IFERROR(INDEX('Detalle Costos'!$Y$5:$Y$158,MATCH(Resumen!AA6,'Detalle Costos'!$C$5:$C$158,0))*AG6,0) -> 49.950511 | AF6: =IFERROR(INDEX('Detalle Costos'!$AA$5:$AA$158,MATCH(Resumen!AA6,'Detalle Costos'!$C$5:$C$158,0))*AG6,0) -> 905.23138 | AG6: =AB6*G6 -> 5940 | AH6: 3 | AI6: =+AJ6/AH6 -> 1934.6564 | AJ6: 5803.9692 | AK6: =P6-AG6 -> -1590 | AL6: =AK6/P6 -> -0.36551724 | AM6: =R6 -> 412.5 | AN6: =1500/26*G6 -> 173.07692 | AO6: =SUM(AM6:AN6) -> 585.57692 | AP6: =60070/248*G6 -> 726.65323 | AQ6: =S6*0.03 -> 118.125 | AR6: =AK6-AO6-AP6+AQ6 -> -2784.1051 | AS6: =AR6/P6 -> -0.64002417 | AT6: =131251/248*G6 -> 1587.7137 | AU6: =AR6-AT6 -> -4371.8189 | AV6: =AU6/P6 -> -1.0050158 | AW6: =123530/248*G6 -> 1494.3145 | AX6: =AR6+AW6 -> -1289.7906 | AY6: =AX6/P6 -> -0.29650359 | BA6: =P6/$G6 -> 1450 | BB6: =-AC6/$G6 -> -1252.3377 | BC6: =-AD6/$G6 -> -409.26831 | BD6: =-AE6/$G6 -> -16.65017 | BE6: =-AF6/$G6 -> -301.74379 | BF6: =-AG6/$G6 -> -1980 | BG6: =AK6/$G6 -> -530 | BH6: =-AM6/$G6 -> -137.5 | BI6: =-AN6/$G6 -> -57.692308 | BJ6: =-AO6/$G6 -> -195.19231 | BK6: =-AP6/$G6 -> -242.21774 | BL6: =AQ6/$G6 -> 39.375 | BM6: =AR6/$G6 -> -928.03505 | BN6: =-AT6/$G6 -> -529.2379 | BO6: =AU6/$G6 -> -1457.273 | BP6: =AW6/$G6 -> 498.10484 | BQ6: =AX6/$G6 -> -429.93021
B7: ENERO | C7: =B7 -> ENERO | D7: 128-2025B | E7: 325 | F7: 46053 | G7: 3.96 | H7: POTA REJOS CONGELADOS | I7: Rejos | J7: 1 - 2 kgs. | K7: Tailandia | L7: Lat Krabang | M7: DAIRECK S.A. | N7: Julieta | O7: =P7/G7 -> 2234.3434 | P7: 8848 | Q7: 2800 | R7: =3300/24*G7 -> 544.5 | S7: =P7-R7 -> 8303.5 | T7: 0 | V7: 6443191850 | W7: COSCO | X7: PAITA | Y7: 10007162 | Z7: Compensación | AA7: =B7&Y7&Z7 -> ENERO10007162Compensación | AB7: =INDEX('Detalle Costos'!$L$5:$L$158,MATCH(Resumen!AA7,'Detalle Costos'!$C$5:$C$158,0))*1000 -> 1790 | AC7: =IFERROR(INDEX('Detalle Costos'!$X$5:$X$158,MATCH(Resumen!AA7,'Detalle Costos'!$C$5:$C$158,0))*AG7,0) -> 4604.3696 | AD7: =IFERROR(INDEX('Detalle Costos'!$Z$5:$Z$158,MATCH(Resumen!AA7,'Detalle Costos'!$C$5:$C$158,0))*AG7,0) -> 1214.8181 | AE7: =IFERROR(INDEX('Detalle Costos'!$Y$5:$Y$158,MATCH(Resumen!AA7,'Detalle Costos'!$C$5:$C$158,0))*AG7,0) -> 61.899523 | AF7: =IFERROR(INDEX('Detalle Costos'!$AA$5:$AA$158,MATCH(Resumen!AA7,'Detalle Costos'!$C$5:$C$158,0))*AG7,0) -> 1207.3128 | AG7: =AB7*G7 -> 7088.4 | AH7: 3.16 | AI7: =+AJ7/AH7 -> 1842.697 | AJ7: 5822.9227 | AK7: =P7-AG7 -> 1759.6 | AL7: =AK7/P7 -> 0.1988698 | AM7: =R7 -> 544.5 | AN7: =1500/26*G7 -> 228.46154 | AO7: =SUM(AM7:AN7) -> 772.96154 | AP7: =60070/248*G7 -> 959.18226 | AQ7: =S7*0.03 -> 249.105 | AR7: =AK7-AO7-AP7+AQ7 -> 276.5612 | AS7: =AR7/P7 -> 0.031256917 | AT7: =131251/248*G7 -> 2095.7821 | AU7: =AR7-AT7 -> -1819.2209 | AV7: =AU7/P7 -> -0.20560815 | AW7: =123530/248*G7 -> 1972.4952 | AX7: =AR7+AW7 -> 2249.0564 | AY7: =AX7/P7 -> 0.25418811 | BA7: =P7/$G7 -> 2234.3434 | BB7: =-AC7/$G7 -> -1162.7196 | BC7: =-AD7/$G7 -> -306.77225 | BD7: =-AE7/$G7 -> -15.631193 | BE7: =-AF7/$G7 -> -304.87696 | BF7: =-AG7/$G7 -> -1790 | BG7: =AK7/$G7 -> 444.34343 | BH7: =-AM7/$G7 -> -137.5 | BI7: =-AN7/$G7 -> -57.692308 | BJ7: =-AO7/$G7 -> -195.19231 | BK7: =-AP7/$G7 -> -242.21774 | BL7: =AQ7/$G7 -> 62.905303 | BM7: =AR7/$G7 -> 69.838688 | BN7: =-AT7/$G7 -> -529.2379 | BO7: =AU7/$G7 -> -459.39922 | BP7: =AW7/$G7 -> 498.10484 | BQ7: =AX7/$G7 -> 567.94353
B8: ENERO | C8: =B8 -> ENERO | D8: 129-2025 | E8: 45982 | F8: 46031 | G8: 24 | H8: POTA CONOS | I8: Conos | K8: Tailandia | L8: Bangkok | M8: TSUJINO | N8: Jose | O8: 2100 | P8: 50400 | Q8: 1962.5 | R8: 3300 | S8: =P8-R8 -> 47100 | T8: 1 | U8: ECO MARIN 26002S | V8: 6440924270 | W8: COSCO | X8: PAITA | Y8: 10007969 | Z8: Compensación | AA8: =B8&Y8&Z8 -> ENERO10007969Compensación | AB8: =INDEX('Detalle Costos'!$L$5:$L$158,MATCH(Resumen!AA8,'Detalle Costos'!$C$5:$C$158,0))*1000 -> 1640 | AC8: =IFERROR(INDEX('Detalle Costos'!$X$5:$X$158,MATCH(Resumen!AA8,'Detalle Costos'!$C$5:$C$158,0))*AG8,0) -> 30431.619 | AD8: =IFERROR(INDEX('Detalle Costos'!$Z$5:$Z$158,MATCH(Resumen!AA8,'Detalle Costos'!$C$5:$C$158,0))*AG8,0) -> 5331.8121 | AE8: =IFERROR(INDEX('Detalle Costos'!$Y$5:$Y$158,MATCH(Resumen!AA8,'Detalle Costos'!$C$5:$C$158,0))*AG8,0) -> 403.53077 | AF8: =IFERROR(INDEX('Detalle Costos'!$AA$5:$AA$158,MATCH(Resumen!AA8,'Detalle Costos'!$C$5:$C$158,0))*AG8,0) -> 3193.0382 | AG8: =AB8*G8 -> 39360 | AH8: 24 | AI8: =+AJ8/AH8 -> 1644.3167 | AJ8: 39463.6 | AK8: =P8-AG8 -> 11040 | AL8: =AK8/P8 -> 0.21904762 | AM8: =R8 -> 3300 | AN8: =1500/26*G8 -> 1384.6154 | AO8: =SUM(AM8:AN8) -> 4684.6154 | AP8: =60070/248*G8 -> 5813.2258 | AQ8: =S8*0.03 -> 1413 | AR8: =AK8-AO8-AP8+AQ8 -> 1955.1588 | AS8: =AR8/P8 -> 0.038792834 | AT8: =131251/248*G8 -> 12701.71 | AU8: =AR8-AT8 -> -10746.551 | AV8: =AU8/P8 -> -0.21322522 | AW8: =123530/248*G8 -> 11954.516 | AX8: =AR8+AW8 -> 13909.675 | AY8: =AX8/P8 -> 0.27598561 | BA8: =P8/$G8 -> 2100 | BB8: =-AC8/$G8 -> -1267.9841 | BC8: =-AD8/$G8 -> -222.15884 | BD8: =-AE8/$G8 -> -16.813782 | BE8: =-AF8/$G8 -> -133.04326 | BF8: =-AG8/$G8 -> -1640 | BG8: =AK8/$G8 -> 460 | BH8: =-AM8/$G8 -> -137.5 | BI8: =-AN8/$G8 -> -57.692308 | BJ8: =-AO8/$G8 -> -195.19231 | BK8: =-AP8/$G8 -> -242.21774 | BL8: =AQ8/$G8 -> 58.875 | BM8: =AR8/$G8 -> 81.46495 | BN8: =-AT8/$G8 -> -529.2379 | BO8: =AU8/$G8 -> -447.77295 | BP8: =AW8/$G8 -> 498.10484 | BQ8: =AX8/$G8 -> 579.56979
B9: ENERO | C9: =B9 -> ENERO | D9: 137-2025 | E9: 46000 | F9: 46043 | G9: 24 | H9: POTA FILETE CONGELADO | I9: Filete | J9: 2 - 4 kg | K9: Taiwan | L9: KAOHSIUNG | M9: TSUJINO | N9: Jose | O9: =P9/G9 -> 1966.6667 | P9: =48000*0+47200 -> 47200 | Q9: =S9/G9 -> 1841.5417 | R9: 3003 | S9: =P9-R9 -> 44197 | T9: 1 | U9: ECO MARIN 25052N | V9: LIMF26385300 | W9: ONE | X9: PAITA | Y9: 10005721 | Z9: Compensación | AA9: =B9&Y9&Z9 -> ENERO10005721Compensación | AB9: =INDEX('Detalle Costos'!$L$5:$L$158,MATCH(Resumen!AA9,'Detalle Costos'!$C$5:$C$158,0))*1000 -> 1860 | AC9: =IFERROR(INDEX('Detalle Costos'!$X$5:$X$158,MATCH(Resumen!AA9,'Detalle Costos'!$C$5:$C$158,0))*AG9,0) -> 27074.763 | AD9: =IFERROR(INDEX('Detalle Costos'!$Z$5:$Z$158,MATCH(Resumen!AA9,'Detalle Costos'!$C$5:$C$158,0))*AG9,0) -> 9821.5948 | AE9: =IFERROR(INDEX('Detalle Costos'!$Y$5:$Y$158,MATCH(Resumen!AA9,'Detalle Costos'!$C$5:$C$158,0))*AG9,0) -> 427.38655 | AF9: =IFERROR(INDEX('Detalle Costos'!$AA$5:$AA$158,MATCH(Resumen!AA9,'Detalle Costos'!$C$5:$C$158,0))*AG9,0) -> 7316.2554 | AG9: =AB9*G9 -> 44640 | AH9: 23.7 | AI9: =+AJ9/AH9 -> 1889.3859 | AJ9: 44778.445 | AK9: =P9-AG9 -> 2560 | AL9: =AK9/P9 -> 0.054237288 | AM9: =R9 -> 3003 | AN9: =1500/26*G9 -> 1384.6154 | AO9: =SUM(AM9:AN9) -> 4387.6154 | AP9: =60070/248*G9 -> 5813.2258 | AQ9: =S9*0.03 -> 1325.91 | AR9: =AK9-AO9-AP9+AQ9 -> -6314.9312 | AS9: =AR9/P9 -> -0.13379092 | AT9: =131251/248*G9 -> 12701.71 | AU9: =AR9-AT9 -> -19016.641 | AV9: =AU9/P9 -> -0.40289493 | AW9: =123530/248*G9 -> 11954.516 | AX9: =AR9+AW9 -> 5639.5849 | AY9: =AX9/P9 -> 0.11948273 | BA9: =P9/$G9 -> 1966.6667 | BB9: =-AC9/$G9 -> -1128.1151 | BC9: =-AD9/$G9 -> -409.23312 | BD9: =-AE9/$G9 -> -17.807773 | BE9: =-AF9/$G9 -> -304.84398 | BF9: =-AG9/$G9 -> -1860 | BG9: =AK9/$G9 -> 106.66667 | BH9: =-AM9/$G9 -> -125.125 | BI9: =-AN9/$G9 -> -57.692308 | BJ9: =-AO9/$G9 -> -182.81731 | BK9: =-AP9/$G9 -> -242.21774 | BL9: =AQ9/$G9 -> 55.24625 | BM9: =AR9/$G9 -> -263.12213 | BN9: =-AT9/$G9 -> -529.2379 | BO9: =AU9/$G9 -> -792.36004 | BP9: =AW9/$G9 -> 498.10484 | BQ9: =AX9/$G9 -> 234.98271
B10: ENERO | C10: =B10 -> ENERO | D10: 140-2025 | E10: 347 | F10: 46038 | G10: 24 | H10: POTA FILETE CONGELADO | I10: Filete | J10: 2-4kg | K10: Japón | L10: Sendai | M10: TSUJINO | N10: Jose | O10: =P10/G10 -> 1983.3333 | P10: =48000*0+47600 -> 47600 | Q10: =S10/G10 -> 1845.7083 | R10: 3303 | S10: =P10-R10 -> 44297 | T10: 1 | U10: ECO SIROCCO 26003S | V10: LIMG00358300 | W10: ONE | X10: PAITA | Y10: 10005721 | Z10: Compensación | AA10: =B10&Y10&Z10 -> ENERO10005721Compensación | AB10: =INDEX('Detalle Costos'!$L$5:$L$158,MATCH(Resumen!AA10,'Detalle Costos'!$C$5:$C$158,0))*1000 -> 1860 | AC10: =IFERROR(INDEX('Detalle Costos'!$X$5:$X$158,MATCH(Resumen!AA10,'Detalle Costos'!$C$5:$C$158,0))*AG10,0) -> 27074.763 | AD10: =IFERROR(INDEX('Detalle Costos'!$Z$5:$Z$158,MATCH(Resumen!AA10,'Detalle Costos'!$C$5:$C$158,0))*AG10,0) -> 9821.5948 | AE10: =IFERROR(INDEX('Detalle Costos'!$Y$5:$Y$158,MATCH(Resumen!AA10,'Detalle Costos'!$C$5:$C$158,0))*AG10,0) -> 427.38655 | AF10: =IFERROR(INDEX('Detalle Costos'!$AA$5:$AA$158,MATCH(Resumen!AA10,'Detalle Costos'!$C$5:$C$158,0))*AG10,0) -> 7316.2554 | AG10: =AB10*G10 -> 44640 | AH10: 23.7 | AI10: =+AJ10/AH10 -> 1889.3859 | AJ10: 44778.445 | AK10: =P10-AG10 -> 2960 | AL10: =AK10/P10 -> 0.062184874 | AM10: =R10 -> 3303 | AN10: =1500/26*G10 -> 1384.6154 | AO10: =SUM(AM10:AN10) -> 4687.6154 | AP10: =60070/248*G10 -> 5813.2258 | AQ10: =S10*0.03 -> 1328.91 | AR10: =AK10-AO10-AP10+AQ10 -> -6211.9312 | AS10: =AR10/P10 -> -0.13050276 | AT10: =131251/248*G10 -> 12701.71 | AU10: =AR10-AT10 -> -18913.641 | AV10: =AU10/P10 -> -0.3973454 | AW10: =123530/248*G10 -> 11954.516 | AX10: =AR10+AW10 -> 5742.5849 | AY10: =AX10/P10 -> 0.12064254 | BA10: =P10/$G10 -> 1983.3333 | BB10: =-AC10/$G10 -> -1128.1151 | BC10: =-AD10/$G10 -> -409.23312 | BD10: =-AE10/$G10 -> -17.807773 | BE10: =-AF10/$G10 -> -304.84398 | BF10: =-AG10/$G10 -> -1860 | BG10: =AK10/$G10 -> 123.33333 | BH10: =-AM10/$G10 -> -137.625 | BI10: =-AN10/$G10 -> -57.692308 | BJ10: =-AO10/$G10 -> -195.31731 | BK10: =-AP10/$G10 -> -242.21774 | BL10: =AQ10/$G10 -> 55.37125 | BM10: =AR10/$G10 -> -258.83047 | BN10: =-AT10/$G10 -> -529.2379 | BO10: =AU10/$G10 -> -788.06837 | BP10: =AW10/$G10 -> 498.10484 | BQ10: =AX10/$G10 -> 239.27437
B11: ENERO | C11: =B11 -> ENERO | D11: 145-2025 | E11: 46020 | F11: 46041 | G11: 54 | H11: POTA REJOS CONGELADOS | I11: Rejos | J11: 500-1 / 1-2 | K11: España | L11: Vigo | M11: GLOBAL OCEAN | N11: Jorge | O11: 2600 | P11: 140400 | Q11: 2430.963 | R11: 9128 | S11: =P11-R11 -> 131272 | T11: 2 | U11: IZMIT EXPRESS 604N | V11: 28952064 | W11: HAPAG | X11: PAITA | Y11: 10007162 | Z11: Compensación | AA11: =B11&Y11&Z11 -> ENERO10007162Compensación | AB11: =INDEX('Detalle Costos'!$L$5:$L$158,MATCH(Resumen!AA11,'Detalle Costos'!$C$5:$C$158,0))*1000 -> 1790 | AC11: =IFERROR(INDEX('Detalle Costos'!$X$5:$X$158,MATCH(Resumen!AA11,'Detalle Costos'!$C$5:$C$158,0))*AG11,0) -> 62786.858 | AD11: =IFERROR(INDEX('Detalle Costos'!$Z$5:$Z$158,MATCH(Resumen!AA11,'Detalle Costos'!$C$5:$C$158,0))*AG11,0) -> 16565.702 | AE11: =IFERROR(INDEX('Detalle Costos'!$Y$5:$Y$158,MATCH(Resumen!AA11,'Detalle Costos'!$C$5:$C$158,0))*AG11,0) -> 844.0844 | AF11: =IFERROR(INDEX('Detalle Costos'!$AA$5:$AA$158,MATCH(Resumen!AA11,'Detalle Costos'!$C$5:$C$158,0))*AG11,0) -> 16463.356 | AG11: =AB11*G11 -> 96660 | AH11: 54 | AI11: =+AJ11/AH11 -> 1842.697 | AJ11: 99505.64 | AK11: =P11-AG11 -> 43740 | AL11: =AK11/P11 -> 0.31153846 | AM11: =R11 -> 9128 | AN11: =1500/26*G11 -> 3115.3846 | AO11: =SUM(AM11:AN11) -> 12243.385 | AP11: =60070/248*G11 -> 13079.758 | AQ11: =S11*0.03 -> 3938.16 | AR11: =AK11-AO11-AP11+AQ11 -> 22355.017 | AS11: =AR11/P11 -> 0.15922377 | AT11: =131251/248*G11 -> 28578.847 | AU11: =AR11-AT11 -> -6223.8295 | AV11: =AU11/P11 -> -0.04432927 | AW11: =123530/248*G11 -> 26897.661 | AX11: =AR11+AW11 -> 49252.679 | AY11: =AX11/P11 -> 0.35080255 | BA11: =P11/$G11 -> 2600 | BB11: =-AC11/$G11 -> -1162.7196 | BC11: =-AD11/$G11 -> -306.77225 | BD11: =-AE11/$G11 -> -15.631193 | BE11: =-AF11/$G11 -> -304.87696 | BF11: =-AG11/$G11 -> -1790 | BG11: =AK11/$G11 -> 810 | BH11: =-AM11/$G11 -> -169.03704 | BI11: =-AN11/$G11 -> -57.692308 | BJ11: =-AO11/$G11 -> -226.72934 | BK11: =-AP11/$G11 -> -242.21774 | BL11: =AQ11/$G11 -> 72.928889 | BM11: =AR11/$G11 -> 413.9818 | BN11: =-AT11/$G11 -> -529.2379 | BO11: =AU11/$G11 -> -115.2561 | BP11: =AW11/$G11 -> 498.10484 | BQ11: =AX11/$G11 -> 912.08664
B12: FEBRERO | C12: =B12 -> FEBRERO | D12: 146-2026 | E12: 46027 | F12: 46059 | G12: 10 | H12: POTA CONOS | I12: Conos | J12: 10 cm - up | K12: Tailandia | L12: Lat Krabang | M12: TSUJINO | N12: Jose | O12: 2100 | P12: 21000 | Q12: 2100 | R12: =3500/24*G12 -> 1458.3333 | S12: =P12-R12 -> 19541.667 | T12: 1 | U12: ECO MARIN 26006S | V12: 6444023300 | W12: COSCO | X12: PAITA | Y12: 10007969 | Z12: Compensación | AA12: =B12&Y12&Z12 -> FEBRERO10007969Compensación | AB12: =INDEX('Detalle Costos'!$L$5:$L$158,MATCH(Resumen!AA12,'Detalle Costos'!$C$5:$C$158,0))*1000*0+AI12 -> 1397.2773 | AC12: =IFERROR(INDEX('Detalle Costos'!$X$5:$X$158,MATCH(Resumen!AA12,'Detalle Costos'!$C$5:$C$158,0))*AG12,0) -> 11301.832 | AD12: =IFERROR(INDEX('Detalle Costos'!$Z$5:$Z$158,MATCH(Resumen!AA12,'Detalle Costos'!$C$5:$C$158,0))*AG12,0) -> 2127.4653 | AE12: =IFERROR(INDEX('Detalle Costos'!$Y$5:$Y$158,MATCH(Resumen!AA12,'Detalle Costos'!$C$5:$C$158,0))*AG12,0) -> 166.83162 | AF12: =IFERROR(INDEX('Detalle Costos'!$AA$5:$AA$158,MATCH(Resumen!AA12,'Detalle Costos'!$C$5:$C$158,0))*AG12,0) -> 376.64454 | AG12: =AB12*G12 -> 13972.773 | AH12: =+G12 -> 10 | AI12: 1397.2773 | AJ12: =+AI12*AH12 -> 13972.773 | AK12: =P12-AG12 -> 7027.2269 | AL12: =AK12/P12 -> 0.33462985 | AM12: =R12 -> 1458.3333 | AN12: =1500/26*G12 -> 576.92308 | AO12: =SUM(AM12:AN12) -> 2035.2564 | AP12: =65590/1634.3*G12 -> 401.3339 | AQ12: =S12*0.03 -> 586.25 | AR12: =AK12-AO12-AP12+AQ12 -> 5176.8866 | AS12: =AR12/P12 -> 0.24651841 | AT12: =148498/1634.3*G12 -> 908.63367 | AU12: =AR12-AT12 -> 4268.2529 | AV12: =AU12/P12 -> 0.20325014 | AW12: =123484.35/1634.3*G12 -> 755.57945 | AX12: =AR12+AW12 -> 5932.4661 | AY12: =AX12/P12 -> 0.28249838 | BA12: =P12/$G12 -> 2100 | BB12: =-AC12/$G12 -> -1130.1832 | BC12: =-AD12/$G12 -> -212.74653 | BD12: =-AE12/$G12 -> -16.683162 | BE12: =-AF12/$G12 -> -37.664454 | BF12: =-AG12/$G12 -> -1397.2773 | BG12: =AK12/$G12 -> 702.72269 | BH12: =-AM12/$G12 -> -145.83333 | BI12: =-AN12/$G12 -> -57.692308 | BJ12: =-AO12/$G12 -> -203.52564 | BK12: =-AP12/$G12 -> -40.13339 | BL12: =AQ12/$G12 -> 58.625 | BM12: =AR12/$G12 -> 517.68866 | BN12: =-AT12/$G12 -> -90.863367 | BO12: =AU12/$G12 -> 426.82529 | BP12: =AW12/$G12 -> 75.557945 | BQ12: =AX12/$G12 -> 593.24661
B13: FEBRERO | C13: =B13 -> FEBRERO | D13: 146-2026 | E13: 46027 | F13: 46059 | G13: 14 | H13: POTA NUCAS | I13: Nucas | J13: 500-up | K13: Tailandia | L13: Lat Krabang | M13: TSUJINO | N13: Jose | O13: 1700 | P13: =23800-344 -> 23456 | Q13: 1700 | R13: =3500/24*G13 -> 2041.6667 | S13: =P13-R13 -> 21414.333 | T13: 0 | Y13: 10005779 | Z13: Compensación | AA13: =B13&Y13&Z13 -> FEBRERO10005779Compensación | AB13: =INDEX('Detalle Costos'!$L$5:$L$158,MATCH(Resumen!AA13,'Detalle Costos'!$C$5:$C$158,0))*1000*0+AI13 -> 1859.7145 | AC13: =IFERROR(INDEX('Detalle Costos'!$X$5:$X$158,MATCH(Resumen!AA13,'Detalle Costos'!$C$5:$C$158,0))*AG13,0) -> 15847.871 | AD13: =IFERROR(INDEX('Detalle Costos'!$Z$5:$Z$158,MATCH(Resumen!AA13,'Detalle Costos'!$C$5:$C$158,0))*AG13,0) -> 5732.4075 | AE13: =IFERROR(INDEX('Detalle Costos'!$Y$5:$Y$158,MATCH(Resumen!AA13,'Detalle Costos'!$C$5:$C$158,0))*AG13,0) -> 189.9202 | AF13: =IFERROR(INDEX('Detalle Costos'!$AA$5:$AA$158,MATCH(Resumen!AA13,'Detalle Costos'!$C$5:$C$158,0))*AG13,0) -> 4265.8048 | AG13: =AB13*G13 -> 26036.003 | AH13: 14.849 | AI13: 1859.7145 | AJ13: =AI13*AH13 -> 27614.901 | AK13: =P13-AG13 -> -2580.0034 | AL13: =AK13/P13 -> -0.10999332 | AM13: =R13 -> 2041.6667 | AN13: =1500/26*G13 -> 807.69231 | AO13: =SUM(AM13:AN13) -> 2849.359 | AP13: =65590/1634.3*G13 -> 561.86747 | AQ13: =S13*0.03 -> 642.43 | AR13: =AK13-AO13-AP13+AQ13 -> -5348.7998 | AS13: =AR13/P13 -> -0.22803546 | AT13: =148498/1634.3*G13 -> 1272.0871 | AU13: =AR13-AT13 -> -6620.887 | AV13: =AU13/P13 -> -0.28226837 | AW13: =123484.35/1634.3*G13 -> 1057.8112 | AX13: =AR13+AW13 -> -4290.9886 | AY13: =AX13/P13 -> -0.18293778 | BA13: =P13/$G13 -> 1675.4286 | BB13: =-AC13/$G13 -> -1131.9908 | BC13: =-AD13/$G13 -> -409.45768 | BD13: =-AE13/$G13 -> -13.565729 | BE13: =-AF13/$G13 -> -304.70034 | BF13: =-AG13/$G13 -> -1859.7145 | BG13: =AK13/$G13 -> -184.28596 | BH13: =-AM13/$G13 -> -145.83333 | BI13: =-AN13/$G13 -> -57.692308 | BJ13: =-AO13/$G13 -> -203.52564 | BK13: =-AP13/$G13 -> -40.13339 | BL13: =AQ13/$G13 -> 45.887857 | BM13: =AR13/$G13 -> -382.05713 | BN13: =-AT13/$G13 -> -90.863367 | BO13: =AU13/$G13 -> -472.9205 | BP13: =AW13/$G13 -> 75.557945 | BQ13: =AX13/$G13 -> -306.49919
B14: ENERO | C14: =B14 -> ENERO | D14: 147-2026 | E14: 46032 | F14: 46050 | G14: 72 | H14: POTA ALAS CONGELADAS | I14: Alas | J14: 1 - 2 KGS. | K14: Tailandia | L14: Bangkok | M14: TSUJINO | N14: Jose | O14: =P14/G14 -> 1887.7083 | P14: =140400*0+135915 -> 135915 | Q14: =S14/G14 -> 1754.25 | R14: 9609 | S14: =P14-R14 -> 126306 | T14: 3 | U14: ECO MARIN 26004N | V14: LIMG01524600 | W14: ONE | X14: PAITA | Y14: 10006720 | Z14: Compensación | AA14: =B14&Y14&Z14 -> ENERO10006720Compensación | AB14: =INDEX('Detalle Costos'!$L$5:$L$158,MATCH(Resumen!AA14,'Detalle Costos'!$C$5:$C$158,0))*1000 -> 1720 | AC14: =IFERROR(INDEX('Detalle Costos'!$X$5:$X$158,MATCH(Resumen!AA14,'Detalle Costos'!$C$5:$C$158,0))*AG14,0) -> 81764.361 | AD14: =IFERROR(INDEX('Detalle Costos'!$Z$5:$Z$158,MATCH(Resumen!AA14,'Detalle Costos'!$C$5:$C$158,0))*AG14,0) -> 18919.258 | AE14: =IFERROR(INDEX('Detalle Costos'!$Y$5:$Y$158,MATCH(Resumen!AA14,'Detalle Costos'!$C$5:$C$158,0))*AG14,0) -> 1185.8374 | AF14: =IFERROR(INDEX('Detalle Costos'!$AA$5:$AA$158,MATCH(Resumen!AA14,'Detalle Costos'!$C$5:$C$158,0))*AG14,0) -> 21970.544 | AG14: =AB14*G14 -> 123840 | AH14: 69.7 | AI14: =+AJ14/AH14 -> 1723.916 | AJ14: 120156.94 | AK14: =P14-AG14 -> 12075 | AL14: =AK14/P14 -> 0.088842291 | AM14: =R14 -> 9609 | AN14: =1500/26*G14 -> 4153.8462 | AO14: =SUM(AM14:AN14) -> 13762.846 | AP14: =60070/248*G14 -> 17439.677 | AQ14: =S14*0.03 -> 3789.18 | AR14: =AK14-AO14-AP14+AQ14 -> -15338.344 | AS14: =AR14/P14 -> -0.11285247 | AT14: =131251/248*G14 -> 38105.129 | AU14: =AR14-AT14 -> -53443.473 | AV14: =AU14/P14 -> -0.39321247 | AW14: =123530/248*G14 -> 35863.548 | AX14: =AR14+AW14 -> 20525.205 | AY14: =AX14/P14 -> 0.15101501 | BA14: =P14/$G14 -> 1887.7083 | BB14: =-AC14/$G14 -> -1135.6161 | BC14: =-AD14/$G14 -> -262.76747 | BD14: =-AE14/$G14 -> -16.469963 | BE14: =-AF14/$G14 -> -305.14645 | BF14: =-AG14/$G14 -> -1720 | BG14: =AK14/$G14 -> 167.70833 | BH14: =-AM14/$G14 -> -133.45833 | BI14: =-AN14/$G14 -> -57.692308 | BJ14: =-AO14/$G14 -> -191.15064 | BK14: =-AP14/$G14 -> -242.21774 | BL14: =AQ14/$G14 -> 52.6275 | BM14: =AR14/$G14 -> -213.03255 | BN14: =-AT14/$G14 -> -529.2379 | BO14: =AU14/$G14 -> -742.27045 | BP14: =AW14/$G14 -> 498.10484 | BQ14: =AX14/$G14 -> 285.07229
B15: ENERO | C15: =B15 -> ENERO | E15: 46053 | F15: 46053 | G15: 0 | H15: RESIDUOS DE POTA | I15: Residuos | J15: Residuos | K15: Residuos | L15: Residuos | M15: PROVEEDORA DE PRODUCTOS MARINOS | O15: 0 | P15: 24314.28 | Q15: 0 | R15: 0 | S15: =P15-R15 -> 24314.28 | AB15: 0 | AC15: =IFERROR(INDEX('Detalle Costos'!$X$5:$X$158,MATCH(Resumen!AA15,'Detalle Costos'!$C$5:$C$158,0))*AG15,0) -> 0 | AD15: =IFERROR(INDEX('Detalle Costos'!$Z$5:$Z$158,MATCH(Resumen!AA15,'Detalle Costos'!$C$5:$C$158,0))*AG15,0) -> 0 | AE15: =IFERROR(INDEX('Detalle Costos'!$Y$5:$Y$158,MATCH(Resumen!AA15,'Detalle Costos'!$C$5:$C$158,0))*AG15,0) -> 0 | AF15: =IFERROR(INDEX('Detalle Costos'!$AA$5:$AA$158,MATCH(Resumen!AA15,'Detalle Costos'!$C$5:$C$158,0))*AG15,0) -> 0 | AG15: =AB15*G15 -> 0 | AK15: =P15-AG15 -> 24314.28 | AL15: =AK15/P15 -> 1 | AM15: =R15 -> 0 | AN15: =1500/26*G15 -> 0 | AO15: =SUM(AM15:AN15) -> 0 | AP15: =60070/248*G15 -> 0 | AQ15: 0 | AR15: =AK15-AO15-AP15+AQ15 -> 24314.28 | AS15: =AR15/P15 -> 1 | AT15: =131251/248*G15 -> 0 | AU15: =AR15-AT15 -> 24314.28 | AV15: =AU15/P15 -> 1 | AW15: =123530/248*G15 -> 0 | AX15: =AR15+AW15 -> 24314.28 | AY15: =AX15/P15 -> 1 | BA15: 0 | BB15: 0 | BC15: 0 | BD15: 0 | BE15: 0 | BF15: 0 | BG15: 0 | BH15: 0 | BI15: 0 | BJ15: 0 | BK15: 0 | BL15: 0 | BM15: 0 | BN15: 0 | BO15: 0 | BP15: 0 | BQ15: 0
B16: FEBRERO | C16: =B16 -> FEBRERO | D16: 148-2026 | E16: 15 | F16: 46055 | G16: 135 | H16: POTA FILETE CONGELADO | I16: Filete | J16: 2-4 (B) | K16: España | L16: Vigo | M16: FOOD & BEVERAGES TRADERS | N16: Jorge | O16: 1650 | P16: 222750 | Q16: 1480.963 | R16: 22820 | S16: =P16-R16 -> 199930 | T16: 5 | U16: ODYSSEUS 606N | V16: 59582082 | W16: HAPAG | X16: PAITA | Y16: 10005721 | Z16: Compensación | AA16: =B16&Y16&Z16 -> FEBRERO10005721Compensación | AB16: =INDEX('Detalle Costos'!$L$5:$L$158,MATCH(Resumen!AA16,'Detalle Costos'!$C$5:$C$158,0))*1000*0+AI16 -> 1861.4473 | AC16: =IFERROR(INDEX('Detalle Costos'!$X$5:$X$158,MATCH(Resumen!AA16,'Detalle Costos'!$C$5:$C$158,0))*AG16,0) -> 152495.08 | AD16: =IFERROR(INDEX('Detalle Costos'!$Z$5:$Z$158,MATCH(Resumen!AA16,'Detalle Costos'!$C$5:$C$158,0))*AG16,0) -> 50378.669 | AE16: =IFERROR(INDEX('Detalle Costos'!$Y$5:$Y$158,MATCH(Resumen!AA16,'Detalle Costos'!$C$5:$C$158,0))*AG16,0) -> 2680.0174 | AF16: =IFERROR(INDEX('Detalle Costos'!$AA$5:$AA$158,MATCH(Resumen!AA16,'Detalle Costos'!$C$5:$C$158,0))*AG16,0) -> 45741.622 | AG16: =AB16*G16 -> 251295.39 | AH16: =+G16 -> 135 | AI16: =AJ16/AH16 -> 1861.4473 | AJ16: 251295.39 | AK16: =P16-AG16 -> -28545.39 | AL16: =AK16/P16 -> -0.1281499 | AM16: =R16 -> 22820 | AN16: =1500/26*G16 -> 7788.4615 | AO16: =SUM(AM16:AN16) -> 30608.462 | AP16: =65590/1634.3*G16 -> 5418.0077 | AQ16: =S16*0.03 -> 5997.9 | AR16: =AK16-AO16-AP16+AQ16 -> -58573.959 | AS16: =AR16/P16 -> -0.26295829 | AT16: =148498/1634.3*G16 -> 12266.554 | AU16: =AR16-AT16 -> -70840.514 | AV16: =AU16/P16 -> -0.318027 | AW16: =124162.35/1634.3*G16 -> 10256.328 | AX16: =AR16+AW16 -> -48317.631 | AY16: =AX16/P16 -> -0.21691417 | BA16: =P16/$G16 -> 1650 | BB16: =-AC16/$G16 -> -1129.5932 | BC16: =-AD16/$G16 -> -373.17533 | BD16: =-AE16/$G16 -> -19.85198 | BE16: =-AF16/$G16 -> -338.82683 | BF16: =-AG16/$G16 -> -1861.4473 | BG16: =AK16/$G16 -> -211.44733 | BH16: =-AM16/$G16 -> -169.03704 | BI16: =-AN16/$G16 -> -57.692308 | BJ16: =-AO16/$G16 -> -226.72934 | BK16: =-AP16/$G16 -> -40.13339 | BL16: =AQ16/$G16 -> 44.428889 | BM16: =AR16/$G16 -> -433.88118 | BN16: =-AT16/$G16 -> -90.863367 | BO16: =AU16/$G16 -> -524.74455 | BP16: =AW16/$G16 -> 75.972802 | BQ16: =AX16/$G16 -> -357.90838
B17: FEBRERO | C17: =B17 -> FEBRERO | D17: 149-2026 | E17: 16 | F17: 46055 | G17: 27 | H17: POTA REPRODUCTORES | I17: Rejos | K17: España | L17: Vigo | M17: GLOBAL OCEAN | N17: Jorge | O17: =P17/G17 -> 2873.5185 | P17: =79650*0+77585 -> 77585 | Q17: =S17/G17 -> 2711.8889 | R17: 4364 | S17: =P17-R17 -> 73221 | T17: 1 | Y17: 10007567 | Z17: Entradas | AA17: =B17&Y17&Z17 -> FEBRERO10007567Entradas | AB17: =INDEX('Detalle Costos'!$L$5:$L$158,MATCH(Resumen!AA17,'Detalle Costos'!$C$5:$C$158,0))*1000*0+AI17 -> 1829.8235 | AC17: =IFERROR(INDEX('Detalle Costos'!$X$5:$X$158,MATCH(Resumen!AA17,'Detalle Costos'!$C$5:$C$158,0))*AG17,0) -> 30498.569 | AD17: =IFERROR(INDEX('Detalle Costos'!$Z$5:$Z$158,MATCH(Resumen!AA17,'Detalle Costos'!$C$5:$C$158,0))*AG17,0) -> 8738.5729 | AE17: =IFERROR(INDEX('Detalle Costos'!$Y$5:$Y$158,MATCH(Resumen!AA17,'Detalle Costos'!$C$5:$C$158,0))*AG17,0) -> 554.46203 | AF17: =IFERROR(INDEX('Detalle Costos'!$AA$5:$AA$158,MATCH(Resumen!AA17,'Detalle Costos'!$C$5:$C$158,0))*AG17,0) -> 9613.63 | AG17: =AB17*G17 -> 49405.233 | AH17: 26.302 | AI17: =+AI4 -> 1829.8235 | AJ17: 48129 | AK17: =P17-AG17 -> 28179.767 | AL17: =AK17/P17 -> 0.36321153 | AM17: =R17 -> 4364 | AN17: =1500/26*G17 -> 1557.6923 | AO17: =SUM(AM17:AN17) -> 5921.6923 | AP17: =65590/1634.3*G17 -> 1083.6015 | AQ17: =S17*0.03 -> 2196.63 | AR17: =AK17-AO17-AP17+AQ17 -> 23371.103 | AS17: =AR17/P17 -> 0.30123223 | AT17: =148498/1634.3*G17 -> 2453.3109 | AU17: =AR17-AT17 -> 20917.792 | AV17: =AU17/P17 -> 0.26961129 | AW17: =124162.35/1634.3*G17 -> 2051.2656 | AX17: =AR17+AW17 -> 25422.368 | AY17: =AX17/P17 -> 0.32767118 | BA17: =P17/$G17 -> 2873.5185 | BB17: =-AC17/$G17 -> -1129.5766 | BC17: =-AD17/$G17 -> -323.65085 | BD17: =-AE17/$G17 -> -20.535631 | BE17: =-AF17/$G17 -> -356.06037 | BF17: =-AG17/$G17 -> -1829.8235 | BG17: =AK17/$G17 -> 1043.6951 | BH17: =-AM17/$G17 -> -161.62963 | BI17: =-AN17/$G17 -> -57.692308 | BJ17: =-AO17/$G17 -> -219.32194 | BK17: =-AP17/$G17 -> -40.13339 | BL17: =AQ17/$G17 -> 81.356667 | BM17: =AR17/$G17 -> 865.5964 | BN17: =-AT17/$G17 -> -90.863367 | BO17: =AU17/$G17 -> 774.73303 | BP17: =AW17/$G17 -> 75.972802 | BQ17: =AX17/$G17 -> 941.5692
B18: FEBRERO | C18: =B18 -> FEBRERO | D18: 150-2026A | E18: 325 | F18: 46069 | G18: 26 | H18: POTA REJOS CONGELADOS | I18: Rejos | J18: 1-2 KG | K18: España | L18: Vigo | M18: OVERSEA | N18: Avelino | O18: 2600 | P18: 67600 | Q18: 2432.1538 | R18: 4364 | S18: =P18-R18 -> 63236 | T18: 1 | U18: CAPE SPENCER 608N | V18: 11400418 | W18: HAPAG | X18: PAITA | Y18: 10007162 | Z18: Compensación | AA18: =B18&Y18&Z18 -> FEBRERO10007162Compensación | AB18: =INDEX('Detalle Costos'!$L$5:$L$158,MATCH(Resumen!AA18,'Detalle Costos'!$C$5:$C$158,0))*1000*0+AI18 -> 1715.2908 | AC18: =IFERROR(INDEX('Detalle Costos'!$X$5:$X$158,MATCH(Resumen!AA18,'Detalle Costos'!$C$5:$C$158,0))*AG18,0) -> 27996.818 | AD18: =IFERROR(INDEX('Detalle Costos'!$Z$5:$Z$158,MATCH(Resumen!AA18,'Detalle Costos'!$C$5:$C$158,0))*AG18,0) -> 7988.6675 | AE18: =IFERROR(INDEX('Detalle Costos'!$Y$5:$Y$158,MATCH(Resumen!AA18,'Detalle Costos'!$C$5:$C$158,0))*AG18,0) -> 415.9275 | AF18: =IFERROR(INDEX('Detalle Costos'!$AA$5:$AA$158,MATCH(Resumen!AA18,'Detalle Costos'!$C$5:$C$158,0))*AG18,0) -> 8196.1487 | AG18: =AB18*G18 -> 44597.561 | AH18: =+G18 -> 26 | AI18: 1715.2908 | AJ18: =AI18*AH18 -> 44597.561 | AK18: =P18-AG18 -> 23002.439 | AL18: =AK18/P18 -> 0.34027276 | AM18: =R18 -> 4364 | AN18: =1500/26*G18 -> 1500 | AO18: =SUM(AM18:AN18) -> 5864 | AP18: =65590/1634.3*G18 -> 1043.4682 | AQ18: =S18*0.03 -> 1897.08 | AR18: =AK18-AO18-AP18+AQ18 -> 17992.051 | AS18: =AR18/P18 -> 0.26615459 | AT18: =148498/1634.3*G18 -> 2362.4475 | AU18: =AR18-AT18 -> 15629.603 | AV18: =AU18/P18 -> 0.23120715 | AW18: =124162.35/1634.3*G18 -> 1975.2928 | AX18: =AR18+AW18 -> 19967.343 | AY18: =AX18/P18 -> 0.2953749 | BA18: =P18/$G18 -> 2600 | BB18: =-AC18/$G18 -> -1076.8007 | BC18: =-AD18/$G18 -> -307.25644 | BD18: =-AE18/$G18 -> -15.997212 | BE18: =-AF18/$G18 -> -315.23649 | BF18: =-AG18/$G18 -> -1715.2908 | BG18: =AK18/$G18 -> 884.70918 | BH18: =-AM18/$G18 -> -167.84615 | BI18: =-AN18/$G18 -> -57.692308 | BJ18: =-AO18/$G18 -> -225.53846 | BK18: =-AP18/$G18 -> -40.13339 | BL18: =AQ18/$G18 -> 72.964615 | BM18: =AR18/$G18 -> 692.00195 | BN18: =-AT18/$G18 -> -90.863367 | BO18: =AU18/$G18 -> 601.13858 | BP18: =AW18/$G18 -> 75.972802 | BQ18: =AX18/$G18 -> 767.97475
B19: FEBRERO | C19: =B19 -> FEBRERO | D19: 151-2025 | E19: 26 | F19: 46080 | G19: 27 | H19: POTA MEMBRANA PRECOCIDA | I19: Membrana | K19: China | L19: Qingdao | M19: Hunan Jinyueyang | O19: =P19/G19 -> 1429.8611 | P19: =39150*0+38606.25 -> 38606.25 | Q19: =S19/G19 -> 1322.4537 | R19: 2900 | S19: =P19-R19 -> 35706.25 | T19: 1 | U19: ECO SIROCCO 26009S | V19: 6445502950 | W19: COSCO | X19: PAITA | Y19: 10009332 | Z19: Entradas | AA19: =B19&Y19&Z19 -> FEBRERO10009332Entradas | AB19: =AI19 -> 1529.9065 | AC19: =IFERROR(INDEX('Detalle Costos'!$X$5:$X$158,MATCH(Resumen!AA19,'Detalle Costos'!$C$5:$C$158,0))*AG19,0) -> 34256.34 | AD19: =IFERROR(INDEX('Detalle Costos'!$Z$5:$Z$158,MATCH(Resumen!AA19,'Detalle Costos'!$C$5:$C$158,0))*AG19,0) -> 6268.5858 | AE19: =IFERROR(INDEX('Detalle Costos'!$Y$5:$Y$158,MATCH(Resumen!AA19,'Detalle Costos'!$C$5:$C$158,0))*AG19,0) -> 633.18765 | AF19: =IFERROR(INDEX('Detalle Costos'!$AA$5:$AA$158,MATCH(Resumen!AA19,'Detalle Costos'!$C$5:$C$158,0))*AG19,0) -> 149.36167 | AG19: =AB19*G19 -> 41307.475 | AH19: 26.625 | AI19: =AJ19/AH19 -> 1529.9065 | AJ19: 40733.76 | AK19: =P19-AG19 -> -2701.2249 | AL19: =AK19/P19 -> -0.069968591 | AM19: =R19 -> 2900 | AN19: =1500/26*G19 -> 1557.6923 | AO19: =SUM(AM19:AN19) -> 4457.6923 | AP19: =65590/1634.3*G19 -> 1083.6015 | AQ19: =S19*0.03 -> 1071.1875 | AR19: =AK19-AO19-AP19+AQ19 -> -7171.3313 | AS19: =AR19/P19 -> -0.18575571 | AT19: =148498/1634.3*G19 -> 2453.3109 | AU19: =AR19-AT19 -> -9624.6422 | AV19: =AU19/P19 -> -0.2493027 | AW19: =124162.35/1634.3*G19 -> 2051.2656 | AX19: =AR19+AW19 -> -5120.0656 | AY19: =AX19/P19 -> -0.13262271 | BA19: =P19/$G19 -> 1429.8611 | BB19: =-AC19/$G19 -> -1268.7533 | BC19: =-AD19/$G19 -> -232.16984 | BD19: =-AE19/$G19 -> -23.451395 | BE19: =-AF19/$G19 -> -5.5319137 | BF19: =-AG19/$G19 -> -1529.9065 | BG19: =AK19/$G19 -> -100.04537 | BH19: =-AM19/$G19 -> -107.40741 | BI19: =-AN19/$G19 -> -57.692308 | BJ19: =-AO19/$G19 -> -165.09972 | BK19: =-AP19/$G19 -> -40.13339 | BL19: =AQ19/$G19 -> 39.673611 | BM19: =AR19/$G19 -> -265.60486 | BN19: =-AT19/$G19 -> -90.863367 | BO19: =AU19/$G19 -> -356.46823 | BP19: =AW19/$G19 -> 75.972802 | BQ19: =AX19/$G19 -> -189.63206
B20: FEBRERO | C20: =B20 -> FEBRERO | D20: 151-2025 | E20: 26 | F20: 46080 | G20: 27 | H20: POTA TELILLA PRECOCIDA | I20: Telilla | K20: China | L20: Qingdao | M20: Hunan Jinyueyang | O20: =P20/G20 -> 1429.8611 | P20: =39150*0+38606.25 -> 38606.25 | Q20: =S20/G20 -> 1322.4537 | R20: 2900 | S20: =P20-R20 -> 35706.25 | T20: 1 | U20: ECO SIROCCO 26009S | V20: 6445502950 | W20: COSCO | X20: PAITA | Y20: 10009332 | Z20: Compensación | AA20: =B20&Y20&Z20 -> FEBRERO10009332Compensación | AB20: =INDEX('Detalle Costos'!$L$5:$L$158,MATCH(Resumen!AA20,'Detalle Costos'!$C$5:$C$158,0))*1000*0+AI20 -> 1515.6443 | AC20: =IFERROR(INDEX('Detalle Costos'!$X$5:$X$158,MATCH(Resumen!AA20,'Detalle Costos'!$C$5:$C$158,0))*AG20,0) -> 33289.301 | AD20: =IFERROR(INDEX('Detalle Costos'!$Z$5:$Z$158,MATCH(Resumen!AA20,'Detalle Costos'!$C$5:$C$158,0))*AG20,0) -> 5812.6541 | AE20: =IFERROR(INDEX('Detalle Costos'!$Y$5:$Y$158,MATCH(Resumen!AA20,'Detalle Costos'!$C$5:$C$158,0))*AG20,0) -> 581.72151 | AF20: =IFERROR(INDEX('Detalle Costos'!$AA$5:$AA$158,MATCH(Resumen!AA20,'Detalle Costos'!$C$5:$C$158,0))*AG20,0) -> 1238.72 | AG20: =AB20*G20 -> 40922.397 | AH20: 26.625 | AI20: =AJ20/AH20 -> 1515.6443 | AJ20: 40354.03 | AK20: =P20-AG20 -> -2316.1466 | AL20: =AK20/P20 -> -0.059994084 | AM20: =R20 -> 2900 | AN20: =1500/26*G20 -> 1557.6923 | AO20: =SUM(AM20:AN20) -> 4457.6923 | AP20: =65590/1634.3*G20 -> 1083.6015 | AQ20: =S20*0.03 -> 1071.1875 | AR20: =AK20-AO20-AP20+AQ20 -> -6786.253 | AS20: =AR20/P20 -> -0.1757812 | AT20: =148498/1634.3*G20 -> 2453.3109 | AU20: =AR20-AT20 -> -9239.5639 | AV20: =AU20/P20 -> -0.23932819 | AW20: =124162.35/1634.3*G20 -> 2051.2656 | AX20: =AR20+AW20 -> -4734.9873 | AY20: =AX20/P20 -> -0.12264821 | BA20: =P20/$G20 -> 1429.8611 | BB20: =-AC20/$G20 -> -1232.9371 | BC20: =-AD20/$G20 -> -215.28349 | BD20: =-AE20/$G20 -> -21.545241 | BE20: =-AF20/$G20 -> -45.878519 | BF20: =-AG20/$G20 -> -1515.6443 | BG20: =AK20/$G20 -> -85.783208 | BH20: =-AM20/$G20 -> -107.40741 | BI20: =-AN20/$G20 -> -57.692308 | BJ20: =-AO20/$G20 -> -165.09972 | BK20: =-AP20/$G20 -> -40.13339 | BL20: =AQ20/$G20 -> 39.673611 | BM20: =AR20/$G20 -> -251.3427 | BN20: =-AT20/$G20 -> -90.863367 | BO20: =AU20/$G20 -> -342.20607 | BP20: =AW20/$G20 -> 75.972802 | BQ20: =AX20/$G20 -> -175.3699
B21: FEBRERO | C21: =B21 -> FEBRERO | D21: 152-2026 | E21: 26 | F21: 46062 | G21: 27 | H21: POTA REJOS CONGELADOS | I21: Rejos | J21: 2-UP KG | K21: España | L21: Vigo | M21: OVERSEA | N21: Avelino | O21: =P21/G21 -> 2781.2963 | P21: =75600*0+75095 -> 75095 | Q21: =S21/G21 -> 2619.6667 | R21: 4364 | S21: =P21-R21 -> 70731 | T21: 1 | U21: GEMLIK EXPRESS 607N | V21: 24312444 | W21: HAPAG | X21: PAITA | Y21: 10007162 | Z21: Compensación | AA21: =B21&Y21&Z21 -> FEBRERO10007162Compensación | AB21: =INDEX('Detalle Costos'!$L$5:$L$158,MATCH(Resumen!AA21,'Detalle Costos'!$C$5:$C$158,0))*1000*0+AI21 -> 1751.1868 | AC21: =IFERROR(INDEX('Detalle Costos'!$X$5:$X$158,MATCH(Resumen!AA21,'Detalle Costos'!$C$5:$C$158,0))*AG21,0) -> 29682.043 | AD21: =IFERROR(INDEX('Detalle Costos'!$Z$5:$Z$158,MATCH(Resumen!AA21,'Detalle Costos'!$C$5:$C$158,0))*AG21,0) -> 8469.5332 | AE21: =IFERROR(INDEX('Detalle Costos'!$Y$5:$Y$158,MATCH(Resumen!AA21,'Detalle Costos'!$C$5:$C$158,0))*AG21,0) -> 440.96362 | AF21: =IFERROR(INDEX('Detalle Costos'!$AA$5:$AA$158,MATCH(Resumen!AA21,'Detalle Costos'!$C$5:$C$158,0))*AG21,0) -> 8689.5035 | AG21: =AB21*G21 -> 47282.044 | AH21: =+G21 -> 27 | AI21: =1.75118680089485*1000 -> 1751.1868 | AJ21: =AI21*AH21 -> 47282.044 | AK21: =P21-AG21 -> 27812.956 | AL21: =AK21/P21 -> 0.37037028 | AM21: =R21 -> 4364 | AN21: =1500/26*G21 -> 1557.6923 | AO21: =SUM(AM21:AN21) -> 5921.6923 | AP21: =65590/1634.3*G21 -> 1083.6015 | AQ21: =S21*0.03 -> 2121.93 | AR21: =AK21-AO21-AP21+AQ21 -> 22929.593 | AS21: =AR21/P21 -> 0.30534113 | AT21: =148498/1634.3*G21 -> 2453.3109 | AU21: =AR21-AT21 -> 20476.282 | AV21: =AU21/P21 -> 0.2726717 | AW21: =124162.35/1634.3*G21 -> 2051.2656 | AX21: =AR21+AW21 -> 24980.858 | AY21: =AX21/P21 -> 0.33265674 | BA21: =P21/$G21 -> 2781.2963 | BB21: =-AC21/$G21 -> -1099.3349 | BC21: =-AD21/$G21 -> -313.68641 | BD21: =-AE21/$G21 -> -16.331986 | BE21: =-AF21/$G21 -> -321.83346 | BF21: =-AG21/$G21 -> -1751.1868 | BG21: =AK21/$G21 -> 1030.1095 | BH21: =-AM21/$G21 -> -161.62963 | BI21: =-AN21/$G21 -> -57.692308 | BJ21: =-AO21/$G21 -> -219.32194 | BK21: =-AP21/$G21 -> -40.13339 | BL21: =AQ21/$G21 -> 78.59 | BM21: =AR21/$G21 -> 849.24417 | BN21: =-AT21/$G21 -> -90.863367 | BO21: =AU21/$G21 -> 758.3808 | BP21: =AW21/$G21 -> 75.972802 | BQ21: =AX21/$G21 -> 925.21697
B22: FEBRERO | C22: =B22 -> FEBRERO | D22: 156-2026A | E22: 27 | F22: 46062 | G22: 54 | H22: POTA FILETE CONGELADO | I22: Filete | J22: 2-4 kg 100% blanco, No polyphosphate,no medicine | K22: China | L22: Qingdao | M22: Longkou Yunfeng Aquatic | O22: 1650 | P22: 89100 | Q22: 1534.963 | R22: 6212 | S22: =P22-R22 -> 82888 | T22: 2 | U22: CMA CGM IMAGINATION / 0DVITN1MA | V22: LMM0571149 | W22: CMA CGM | X22: PAITA | Y22: 10005721 | Z22: Compensación | AA22: =B22&Y22&Z22 -> FEBRERO10005721Compensación | AB22: =INDEX('Detalle Costos'!$L$5:$L$158,MATCH(Resumen!AA22,'Detalle Costos'!$C$5:$C$158,0))*1000*0+AI22 -> 1740.7827 | AC22: =IFERROR(INDEX('Detalle Costos'!$X$5:$X$158,MATCH(Resumen!AA22,'Detalle Costos'!$C$5:$C$158,0))*AG22,0) -> 57043.957 | AD22: =IFERROR(INDEX('Detalle Costos'!$Z$5:$Z$158,MATCH(Resumen!AA22,'Detalle Costos'!$C$5:$C$158,0))*AG22,0) -> 18845.189 | AE22: =IFERROR(INDEX('Detalle Costos'!$Y$5:$Y$158,MATCH(Resumen!AA22,'Detalle Costos'!$C$5:$C$158,0))*AG22,0) -> 1002.5162 | AF22: =IFERROR(INDEX('Detalle Costos'!$AA$5:$AA$158,MATCH(Resumen!AA22,'Detalle Costos'!$C$5:$C$158,0))*AG22,0) -> 17110.605 | AG22: =AB22*G22 -> 94002.267 | AH22: =+G22 -> 54 | AI22: =1.7407827151654*1000 -> 1740.7827 | AJ22: =+AI22*AH22 -> 94002.267 | AK22: =P22-AG22 -> -4902.2666 | AL22: =AK22/P22 -> -0.055019827 | AM22: =R22 -> 6212 | AN22: =1500/26*G22 -> 3115.3846 | AO22: =SUM(AM22:AN22) -> 9327.3846 | AP22: =65590/1634.3*G22 -> 2167.2031 | AQ22: =S22*0.03 -> 2486.64 | AR22: =AK22-AO22-AP22+AQ22 -> -13910.214 | AS22: =AR22/P22 -> -0.15611913 | AT22: =148498/1634.3*G22 -> 4906.6218 | AU22: =AR22-AT22 -> -18816.836 | AV22: =AU22/P22 -> -0.21118784 | AW22: =124162.35/1634.3*G22 -> 4102.5313 | AX22: =AR22+AW22 -> -9807.683 | AY22: =AX22/P22 -> -0.11007501 | BA22: =P22/$G22 -> 1650 | BB22: =-AC22/$G22 -> -1056.3696 | BC22: =-AD22/$G22 -> -348.98498 | BD22: =-AE22/$G22 -> -18.565115 | BE22: =-AF22/$G22 -> -316.86305 | BF22: =-AG22/$G22 -> -1740.7827 | BG22: =AK22/$G22 -> -90.782715 | BH22: =-AM22/$G22 -> -115.03704 | BI22: =-AN22/$G22 -> -57.692308 | BJ22: =-AO22/$G22 -> -172.72934 | BK22: =-AP22/$G22 -> -40.13339 | BL22: =AQ22/$G22 -> 46.048889 | BM22: =AR22/$G22 -> -257.59656 | BN22: =-AT22/$G22 -> -90.863367 | BO22: =AU22/$G22 -> -348.45993 | BP22: =AW22/$G22 -> 75.972802 | BQ22: =AX22/$G22 -> -181.62376
B23: FEBRERO | C23: =B23 -> FEBRERO | D23: 156-2026B | E23: 27 | F23: 46071 | G23: 81 | H23: POTA FILETE CONGELADO | I23: Filete | J23: 2-4 kg 100% blanco, No polyphosphate,no medicine | K23: China | L23: Qingdao | M23: Longkou Yunfeng Aquatic | O23: 1650 | P23: 133650 | Q23: 1534.963 | R23: 9318 | S23: =P23-R23 -> 124332 | T23: 3 | U23: CMA CGM EXCELLENCE 0DVNNN1MA | V23: LMM0571699 | W23: CMA CGM | X23: PAITA | Y23: 10005721 | Z23: Compensación | AA23: =B23&Y23&Z23 -> FEBRERO10005721Compensación | AB23: =INDEX('Detalle Costos'!$L$5:$L$158,MATCH(Resumen!AA23,'Detalle Costos'!$C$5:$C$158,0))*1000*0+AI23 -> 1740.7827 | AC23: =IFERROR(INDEX('Detalle Costos'!$X$5:$X$158,MATCH(Resumen!AA23,'Detalle Costos'!$C$5:$C$158,0))*AG23,0) -> 85565.935 | AD23: =IFERROR(INDEX('Detalle Costos'!$Z$5:$Z$158,MATCH(Resumen!AA23,'Detalle Costos'!$C$5:$C$158,0))*AG23,0) -> 28267.783 | AE23: =IFERROR(INDEX('Detalle Costos'!$Y$5:$Y$158,MATCH(Resumen!AA23,'Detalle Costos'!$C$5:$C$158,0))*AG23,0) -> 1503.7743 | AF23: =IFERROR(INDEX('Detalle Costos'!$AA$5:$AA$158,MATCH(Resumen!AA23,'Detalle Costos'!$C$5:$C$158,0))*AG23,0) -> 25665.907 | AG23: =AB23*G23 -> 141003.4 | AH23: =+G23 -> 81 | AI23: =1.7407827151654*1000 -> 1740.7827 | AJ23: =+AI23*AH23 -> 141003.4 | AK23: =P23-AG23 -> -7353.3999 | AL23: =AK23/P23 -> -0.055019827 | AM23: =R23 -> 9318 | AN23: =1500/26*G23 -> 4673.0769 | AO23: =SUM(AM23:AN23) -> 13991.077 | AP23: =65590/1634.3*G23 -> 3250.8046 | AQ23: =S23*0.03 -> 3729.96 | AR23: =AK23-AO23-AP23+AQ23 -> -20865.321 | AS23: =AR23/P23 -> -0.15611913 | AT23: =148498/1634.3*G23 -> 7359.9327 | AU23: =AR23-AT23 -> -28225.254 | AV23: =AU23/P23 -> -0.21118784 | AW23: =124162.35/1634.3*G23 -> 6153.7969 | AX23: =AR23+AW23 -> -14711.525 | AY23: =AX23/P23 -> -0.11007501 | BA23: =P23/$G23 -> 1650 | BB23: =-AC23/$G23 -> -1056.3696 | BC23: =-AD23/$G23 -> -348.98498 | BD23: =-AE23/$G23 -> -18.565115 | BE23: =-AF23/$G23 -> -316.86305 | BF23: =-AG23/$G23 -> -1740.7827 | BG23: =AK23/$G23 -> -90.782715 | BH23: =-AM23/$G23 -> -115.03704 | BI23: =-AN23/$G23 -> -57.692308 | BJ23: =-AO23/$G23 -> -172.72934 | BK23: =-AP23/$G23 -> -40.13339 | BL23: =AQ23/$G23 -> 46.048889 | BM23: =AR23/$G23 -> -257.59656 | BN23: =-AT23/$G23 -> -90.863367 | BO23: =AU23/$G23 -> -348.45993 | BP23: =AW23/$G23 -> 75.972802 | BQ23: =AX23/$G23 -> -181.62376
B24: FEBRERO | C24: =B24 -> FEBRERO | D24: 157-2026 | E24: 28 | F24: 46066 | G24: 24 | H24: POTA CONOS | I24: Conos | K24: Tailandia | L24: Lat Krabang | M24: TSUJINO | N24: Jose | O24: 2000 | P24: 48000 | Q24: 1854.1667 | R24: 3500 | S24: =P24-R24 -> 44500 | T24: 1 | U24: ECO SIROCCO 26007S | V24: 6445030580 | W24: COSCO | X24: PAITA | Y24: 10007969 | Z24: Compensación | AA24: =B24&Y24&Z24 -> FEBRERO10007969Compensación | AB24: =INDEX('Detalle Costos'!$L$5:$L$158,MATCH(Resumen!AA24,'Detalle Costos'!$C$5:$C$158,0))*1000*0+AI24 -> 1397.2773 | AC24: =IFERROR(INDEX('Detalle Costos'!$X$5:$X$158,MATCH(Resumen!AA24,'Detalle Costos'!$C$5:$C$158,0))*AG24,0) -> 27124.396 | AD24: =IFERROR(INDEX('Detalle Costos'!$Z$5:$Z$158,MATCH(Resumen!AA24,'Detalle Costos'!$C$5:$C$158,0))*AG24,0) -> 5105.9167 | AE24: =IFERROR(INDEX('Detalle Costos'!$Y$5:$Y$158,MATCH(Resumen!AA24,'Detalle Costos'!$C$5:$C$158,0))*AG24,0) -> 400.3959 | AF24: =IFERROR(INDEX('Detalle Costos'!$AA$5:$AA$158,MATCH(Resumen!AA24,'Detalle Costos'!$C$5:$C$158,0))*AG24,0) -> 903.94689 | AG24: =AB24*G24 -> 33534.655 | AH24: 23.14 | AI24: 1397.2773 | AJ24: =+AI24*AH24 -> 32332.997 | AK24: =P24-AG24 -> 14465.345 | AL24: =AK24/P24 -> 0.30136135 | AM24: =R24 -> 3500 | AN24: =1500/26*G24 -> 1384.6154 | AO24: =SUM(AM24:AN24) -> 4884.6154 | AP24: =65590/1634.3*G24 -> 963.20137 | AQ24: =S24*0.03 -> 1335 | AR24: =AK24-AO24-AP24+AQ24 -> 9952.5278 | AS24: =AR24/P24 -> 0.20734433 | AT24: =148498/1634.3*G24 -> 2180.7208 | AU24: =AR24-AT24 -> 7771.807 | AV24: =AU24/P24 -> 0.16191265 | AW24: =124162.35/1634.3*G24 -> 1823.3472 | AX24: =AR24+AW24 -> 11775.875 | AY24: =AX24/P24 -> 0.24533073 | BA24: =P24/$G24 -> 2000 | BB24: =-AC24/$G24 -> -1130.1832 | BC24: =-AD24/$G24 -> -212.74653 | BD24: =-AE24/$G24 -> -16.683162 | BE24: =-AF24/$G24 -> -37.664454 | BF24: =-AG24/$G24 -> -1397.2773 | BG24: =AK24/$G24 -> 602.72269 | BH24: =-AM24/$G24 -> -145.83333 | BI24: =-AN24/$G24 -> -57.692308 | BJ24: =-AO24/$G24 -> -203.52564 | BK24: =-AP24/$G24 -> -40.13339 | BL24: =AQ24/$G24 -> 55.625 | BM24: =AR24/$G24 -> 414.68866 | BN24: =-AT24/$G24 -> -90.863367 | BO24: =AU24/$G24 -> 323.82529 | BP24: =AW24/$G24 -> 75.972802 | BQ24: =AX24/$G24 -> 490.66146
B25: FEBRERO | C25: =B25 -> FEBRERO | D25: 160-2026 | E25: 30 | F25: 46066 | G25: 108 | H25: POTA ALAS CONGELADAS | I25: Alas | K25: China | L25: Qingdao | M25: TSUJINO | N25: Jose | O25: 1600 | P25: 172800 | Q25: 1492.5926 | R25: 11600 | S25: =P25-R25 -> 161200 | T25: 4 | U25: ECO SIROCCO 26007S | V25: 6445031110 | W25: COSCO | X25: PAITA | Y25: 10006720 | Z25: Compensación | AA25: =B25&Y25&Z25 -> FEBRERO10006720Compensación | AB25: =INDEX('Detalle Costos'!$L$5:$L$158,MATCH(Resumen!AA25,'Detalle Costos'!$C$5:$C$158,0))*1000*0+AI25 -> 1639.7682 | AC25: =IFERROR(INDEX('Detalle Costos'!$X$5:$X$158,MATCH(Resumen!AA25,'Detalle Costos'!$C$5:$C$158,0))*AG25,0) -> 114801.8 | AD25: =IFERROR(INDEX('Detalle Costos'!$Z$5:$Z$158,MATCH(Resumen!AA25,'Detalle Costos'!$C$5:$C$158,0))*AG25,0) -> 26268.814 | AE25: =IFERROR(INDEX('Detalle Costos'!$Y$5:$Y$158,MATCH(Resumen!AA25,'Detalle Costos'!$C$5:$C$158,0))*AG25,0) -> 1720.5907 | AF25: =IFERROR(INDEX('Detalle Costos'!$AA$5:$AA$158,MATCH(Resumen!AA25,'Detalle Costos'!$C$5:$C$158,0))*AG25,0) -> 34303.76 | AG25: =AB25*G25 -> 177094.96 | AH25: =+G25 -> 108 | AI25: =1.63976816895275*1000 -> 1639.7682 | AJ25: =+AI25*AH25 -> 177094.96 | AK25: =P25-AG25 -> -4294.9622 | AL25: =AK25/P25 -> -0.024855106 | AM25: =R25 -> 11600 | AN25: =1500/26*G25 -> 6230.7692 | AO25: =SUM(AM25:AN25) -> 17830.769 | AP25: =65590/1634.3*G25 -> 4334.4062 | AQ25: =S25*0.03 -> 4836 | AR25: =AK25-AO25-AP25+AQ25 -> -21624.138 | AS25: =AR25/P25 -> -0.12513969 | AT25: =148498/1634.3*G25 -> 9813.2436 | AU25: =AR25-AT25 -> -31437.381 | AV25: =AU25/P25 -> -0.18192929 | AW25: =124162.35/1634.3*G25 -> 8205.0626 | AX25: =AR25+AW25 -> -13419.075 | AY25: =AX25/P25 -> -0.077656684 | BA25: =P25/$G25 -> 1600 | BB25: =-AC25/$G25 -> -1062.9796 | BC25: =-AD25/$G25 -> -243.22976 | BD25: =-AE25/$G25 -> -15.931396 | BE25: =-AF25/$G25 -> -317.62741 | BF25: =-AG25/$G25 -> -1639.7682 | BG25: =AK25/$G25 -> -39.768169 | BH25: =-AM25/$G25 -> -107.40741 | BI25: =-AN25/$G25 -> -57.692308 | BJ25: =-AO25/$G25 -> -165.09972 | BK25: =-AP25/$G25 -> -40.13339 | BL25: =AQ25/$G25 -> 44.777778 | BM25: =AR25/$G25 -> -200.2235 | BN25: =-AT25/$G25 -> -90.863367 | BO25: =AU25/$G25 -> -291.08686 | BP25: =AW25/$G25 -> 75.972802 | BQ25: =AX25/$G25 -> -124.25069
B26: FEBRERO | C26: =B26 -> FEBRERO | D26: 160-2026 | E26: 30 | F26: 46066 | G26: 108 | H26: POTA ALAS CONGELADAS | I26: Alas | K26: China | L26: Qingdao | M26: TSUJINO | N26: Jose | O26: 1600 | P26: 172800 | Q26: 1492.5926 | R26: 11600 | S26: =P26-R26 -> 161200 | T26: 4 | U26: ECO SIROCCO 26007S | V26: 6445031130 | W26: COSCO | X26: PAITA | Y26: 10006720 | Z26: Compensación | AA26: =B26&Y26&Z26 -> FEBRERO10006720Compensación | AB26: =INDEX('Detalle Costos'!$L$5:$L$158,MATCH(Resumen!AA26,'Detalle Costos'!$C$5:$C$158,0))*1000*0+AI26 -> 1639.7682 | AC26: =IFERROR(INDEX('Detalle Costos'!$X$5:$X$158,MATCH(Resumen!AA26,'Detalle Costos'!$C$5:$C$158,0))*AG26,0) -> 114801.8 | AD26: =IFERROR(INDEX('Detalle Costos'!$Z$5:$Z$158,MATCH(Resumen!AA26,'Detalle Costos'!$C$5:$C$158,0))*AG26,0) -> 26268.814 | AE26: =IFERROR(INDEX('Detalle Costos'!$Y$5:$Y$158,MATCH(Resumen!AA26,'Detalle Costos'!$C$5:$C$158,0))*AG26,0) -> 1720.5907 | AF26: =IFERROR(INDEX('Detalle Costos'!$AA$5:$AA$158,MATCH(Resumen!AA26,'Detalle Costos'!$C$5:$C$158,0))*AG26,0) -> 34303.76 | AG26: =AB26*G26 -> 177094.96 | AH26: =+G26 -> 108 | AI26: =1.63976816895275*1000 -> 1639.7682 | AJ26: =+AI26*AH26 -> 177094.96 | AK26: =P26-AG26 -> -4294.9622 | AL26: =AK26/P26 -> -0.024855106 | AM26: =R26 -> 11600 | AN26: =1500/26*G26 -> 6230.7692 | AO26: =SUM(AM26:AN26) -> 17830.769 | AP26: =65590/1634.3*G26 -> 4334.4062 | AQ26: =S26*0.03 -> 4836 | AR26: =AK26-AO26-AP26+AQ26 -> -21624.138 | AS26: =AR26/P26 -> -0.12513969 | AT26: =148498/1634.3*G26 -> 9813.2436 | AU26: =AR26-AT26 -> -31437.381 | AV26: =AU26/P26 -> -0.18192929 | AW26: =124162.35/1634.3*G26 -> 8205.0626 | AX26: =AR26+AW26 -> -13419.075 | AY26: =AX26/P26 -> -0.077656684 | BA26: =P26/$G26 -> 1600 | BB26: =-AC26/$G26 -> -1062.9796 | BC26: =-AD26/$G26 -> -243.22976 | BD26: =-AE26/$G26 -> -15.931396 | BE26: =-AF26/$G26 -> -317.62741 | BF26: =-AG26/$G26 -> -1639.7682 | BG26: =AK26/$G26 -> -39.768169 | BH26: =-AM26/$G26 -> -107.40741 | BI26: =-AN26/$G26 -> -57.692308 | BJ26: =-AO26/$G26 -> -165.09972 | BK26: =-AP26/$G26 -> -40.13339 | BL26: =AQ26/$G26 -> 44.777778 | BM26: =AR26/$G26 -> -200.2235 | BN26: =-AT26/$G26 -> -90.863367 | BO26: =AU26/$G26 -> -291.08686 | BP26: =AW26/$G26 -> 75.972802 | BQ26: =AX26/$G26 -> -124.25069
B27: FEBRERO | C27: =B27 -> FEBRERO | D27: 162-2026A | E27: 34 | F27: 46070 | G27: 115.5 | H27: POTA ALAS CONGELADAS | I27: Alas | J27: 1-2 kg | K27: China | L27: Qingdao | M27: AVANCE GROUP | N27: James | O27: 1500 | P27: 173250 | Q27: 1382.987 | R27: 13515 | S27: =P27-R27 -> 159735 | T27: 5 | U27: ECO SIROCCO 26007N | V27: LIMG02628500 | W27: ONE | X27: PAITA | Y27: 10006720 | Z27: Compensación | AA27: =B27&Y27&Z27 -> FEBRERO10006720Compensación | AB27: =INDEX('Detalle Costos'!$L$5:$L$158,MATCH(Resumen!AA27,'Detalle Costos'!$C$5:$C$158,0))*1000*0+AI27 -> 1639.7682 | AC27: =IFERROR(INDEX('Detalle Costos'!$X$5:$X$158,MATCH(Resumen!AA27,'Detalle Costos'!$C$5:$C$158,0))*AG27,0) -> 122774.14 | AD27: =IFERROR(INDEX('Detalle Costos'!$Z$5:$Z$158,MATCH(Resumen!AA27,'Detalle Costos'!$C$5:$C$158,0))*AG27,0) -> 28093.038 | AE27: =IFERROR(INDEX('Detalle Costos'!$Y$5:$Y$158,MATCH(Resumen!AA27,'Detalle Costos'!$C$5:$C$158,0))*AG27,0) -> 1840.0762 | AF27: =IFERROR(INDEX('Detalle Costos'!$AA$5:$AA$158,MATCH(Resumen!AA27,'Detalle Costos'!$C$5:$C$158,0))*AG27,0) -> 36685.966 | AG27: =AB27*G27 -> 189393.22 | AH27: =+G27 -> 115.5 | AI27: =1.63976816895275*1000 -> 1639.7682 | AJ27: =+AI27*AH27 -> 189393.22 | AK27: =P27-AG27 -> -16143.224 | AL27: =AK27/P27 -> -0.093178779 | AM27: =R27 -> 13515 | AN27: =1500/26*G27 -> 6663.4615 | AO27: =SUM(AM27:AN27) -> 20178.462 | AP27: =65590/1634.3*G27 -> 4635.4066 | AQ27: =S27*0.03 -> 4792.05 | AR27: =AK27-AO27-AP27+AQ27 -> -36165.042 | AS27: =AR27/P27 -> -0.20874483 | AT27: =148498/1634.3*G27 -> 10494.719 | AU27: =AR27-AT27 -> -46659.76 | AV27: =AU27/P27 -> -0.26932041 | AW27: =124162.35/1634.3*G27 -> 8774.8586 | AX27: =AR27+AW27 -> -27390.183 | AY27: =AX27/P27 -> -0.15809629 | BA27: =P27/$G27 -> 1500 | BB27: =-AC27/$G27 -> -1062.9796 | BC27: =-AD27/$G27 -> -243.22976 | BD27: =-AE27/$G27 -> -15.931396 | BE27: =-AF27/$G27 -> -317.62741 | BF27: =-AG27/$G27 -> -1639.7682 | BG27: =AK27/$G27 -> -139.76817 | BH27: =-AM27/$G27 -> -117.01299 | BI27: =-AN27/$G27 -> -57.692308 | BJ27: =-AO27/$G27 -> -174.70529 | BK27: =-AP27/$G27 -> -40.13339 | BL27: =AQ27/$G27 -> 41.48961 | BM27: =AR27/$G27 -> -313.11724 | BN27: =-AT27/$G27 -> -90.863367 | BO27: =AU27/$G27 -> -403.98061 | BP27: =AW27/$G27 -> 75.972802 | BQ27: =AX27/$G27 -> -237.14444
B28: FEBRERO | C28: =B28 -> FEBRERO | D28: 162-2026B | E28: 34 | F28: 46070 | G28: 46.8 | H28: POTA ALAS CONGELADAS | I28: Alas | J28: 1-2 kg | K28: China | L28: Dalian | M28: AVANCE GROUP | N28: James | O28: 1500 | P28: 70200 | Q28: 1380.2137 | R28: 5606 | S28: =P28-R28 -> 64594 | T28: 2 | U28: ECO SIROCCO 26007N | V28: LIMG02851300 | W28: ONE | X28: PAITA | Y28: 10006720 | Z28: Compensación | AA28: =B28&Y28&Z28 -> FEBRERO10006720Compensación | AB28: =INDEX('Detalle Costos'!$L$5:$L$158,MATCH(Resumen!AA28,'Detalle Costos'!$C$5:$C$158,0))*1000*0+AI28 -> 1639.7682 | AC28: =IFERROR(INDEX('Detalle Costos'!$X$5:$X$158,MATCH(Resumen!AA28,'Detalle Costos'!$C$5:$C$158,0))*AG28,0) -> 49747.445 | AD28: =IFERROR(INDEX('Detalle Costos'!$Z$5:$Z$158,MATCH(Resumen!AA28,'Detalle Costos'!$C$5:$C$158,0))*AG28,0) -> 11383.153 | AE28: =IFERROR(INDEX('Detalle Costos'!$Y$5:$Y$158,MATCH(Resumen!AA28,'Detalle Costos'!$C$5:$C$158,0))*AG28,0) -> 745.58931 | AF28: =IFERROR(INDEX('Detalle Costos'!$AA$5:$AA$158,MATCH(Resumen!AA28,'Detalle Costos'!$C$5:$C$158,0))*AG28,0) -> 14864.963 | AG28: =AB28*G28 -> 76741.15 | AH28: =+G28 -> 46.8 | AI28: =1.63976816895275*1000 -> 1639.7682 | AJ28: =+AI28*AH28 -> 76741.15 | AK28: =P28-AG28 -> -6541.1503 | AL28: =AK28/P28 -> -0.093178779 | AM28: =R28 -> 5606 | AN28: =1500/26*G28 -> 2700 | AO28: =SUM(AM28:AN28) -> 8306 | AP28: =65590/1634.3*G28 -> 1878.2427 | AQ28: =S28*0.03 -> 1937.82 | AR28: =AK28-AO28-AP28+AQ28 -> -14787.573 | AS28: =AR28/P28 -> -0.21064919 | AT28: =148498/1634.3*G28 -> 4252.4056 | AU28: =AR28-AT28 -> -19039.979 | AV28: =AU28/P28 -> -0.27122477 | AW28: =124162.35/1634.3*G28 -> 3555.5271 | AX28: =AR28+AW28 -> -11232.046 | AY28: =AX28/P28 -> -0.16000065 | BA28: =P28/$G28 -> 1500 | BB28: =-AC28/$G28 -> -1062.9796 | BC28: =-AD28/$G28 -> -243.22976 | BD28: =-AE28/$G28 -> -15.931396 | BE28: =-AF28/$G28 -> -317.62741 | BF28: =-AG28/$G28 -> -1639.7682 | BG28: =AK28/$G28 -> -139.76817 | BH28: =-AM28/$G28 -> -119.78632 | BI28: =-AN28/$G28 -> -57.692308 | BJ28: =-AO28/$G28 -> -177.47863 | BK28: =-AP28/$G28 -> -40.13339 | BL28: =AQ28/$G28 -> 41.40641 | BM28: =AR28/$G28 -> -315.97378 | BN28: =-AT28/$G28 -> -90.863367 | BO28: =AU28/$G28 -> -406.83715 | BP28: =AW28/$G28 -> 75.972802 | BQ28: =AX28/$G28 -> -240.00098
B29: FEBRERO | C29: =B29 -> FEBRERO | D29: 162-2026C | E29: 34 | F29: 46070 | G29: 81 | H29: POTA ALAS CONGELADAS | I29: Alas | J29: 1-2 kg | K29: China | L29: Xiamen | M29: AVANCE GROUP | N29: James | O29: 1500 | P29: 121500 | Q29: 1385.0741 | R29: 9309 | S29: =P29-R29 -> 112191 | T29: 3 | U29: ECO SIROCCO 26007N | V29: LIMG02630500 | W29: ONE | X29: PAITA | Y29: 10006720 | Z29: Compensación | AA29: =B29&Y29&Z29 -> FEBRERO10006720Compensación | AB29: =INDEX('Detalle Costos'!$L$5:$L$158,MATCH(Resumen!AA29,'Detalle Costos'!$C$5:$C$158,0))*1000*0+AI29 -> 1639.7682 | AC29: =IFERROR(INDEX('Detalle Costos'!$X$5:$X$158,MATCH(Resumen!AA29,'Detalle Costos'!$C$5:$C$158,0))*AG29,0) -> 86101.348 | AD29: =IFERROR(INDEX('Detalle Costos'!$Z$5:$Z$158,MATCH(Resumen!AA29,'Detalle Costos'!$C$5:$C$158,0))*AG29,0) -> 19701.611 | AE29: =IFERROR(INDEX('Detalle Costos'!$Y$5:$Y$158,MATCH(Resumen!AA29,'Detalle Costos'!$C$5:$C$158,0))*AG29,0) -> 1290.443 | AF29: =IFERROR(INDEX('Detalle Costos'!$AA$5:$AA$158,MATCH(Resumen!AA29,'Detalle Costos'!$C$5:$C$158,0))*AG29,0) -> 25727.82 | AG29: =AB29*G29 -> 132821.22 | AH29: =+G29 -> 81 | AI29: =1.63976816895275*1000 -> 1639.7682 | AJ29: =+AI29*AH29 -> 132821.22 | AK29: =P29-AG29 -> -11321.222 | AL29: =AK29/P29 -> -0.093178779 | AM29: =R29 -> 9309 | AN29: =1500/26*G29 -> 4673.0769 | AO29: =SUM(AM29:AN29) -> 13982.077 | AP29: =65590/1634.3*G29 -> 3250.8046 | AQ29: =S29*0.03 -> 3365.73 | AR29: =AK29-AO29-AP29+AQ29 -> -25188.373 | AS29: =AR29/P29 -> -0.20731171 | AT29: =148498/1634.3*G29 -> 7359.9327 | AU29: =AR29-AT29 -> -32548.306 | AV29: =AU29/P29 -> -0.26788729 | AW29: =124162.35/1634.3*G29 -> 6153.7969 | AX29: =AR29+AW29 -> -19034.576 | AY29: =AX29/P29 -> -0.15666318 | BA29: =P29/$G29 -> 1500 | BB29: =-AC29/$G29 -> -1062.9796 | BC29: =-AD29/$G29 -> -243.22976 | BD29: =-AE29/$G29 -> -15.931396 | BE29: =-AF29/$G29 -> -317.62741 | BF29: =-AG29/$G29 -> -1639.7682 | BG29: =AK29/$G29 -> -139.76817 | BH29: =-AM29/$G29 -> -114.92593 | BI29: =-AN29/$G29 -> -57.692308 | BJ29: =-AO29/$G29 -> -172.61823 | BK29: =-AP29/$G29 -> -40.13339 | BL29: =AQ29/$G29 -> 41.552222 | BM29: =AR29/$G29 -> -310.96757 | BN29: =-AT29/$G29 -> -90.863367 | BO29: =AU29/$G29 -> -401.83094 | BP29: =AW29/$G29 -> 75.972802 | BQ29: =AX29/$G29 -> -234.99477
B30: FEBRERO | C30: =B30 -> FEBRERO | D30: 164-2026 | E30: 40 | F30: 46080 | G30: 27 | H30: POTA FILETE PRECOCIDO | I30: Daruma | K30: China | L30: Yantai | M30: SACRAMENTO CO., LTD | N30: julia | O30: 3400 | P30: 91800 | Q30: 3292.5926 | R30: 2900 | S30: =P30-R30 -> 88900 | T30: 1 | U30: ECO SIROCCO 26009S | V30: 6445569300 | W30: COSCO | X30: PAITA | Y30: 10009239 | Z30: Compensación | AA30: =B30&Y30&Z30 -> FEBRERO10009239Compensación | AB30: =INDEX('Detalle Costos'!$L$5:$L$158,MATCH(Resumen!AA30,'Detalle Costos'!$C$5:$C$158,0))*1000*0+AI30 -> 2114.7381 | AC30: =IFERROR(INDEX('Detalle Costos'!$X$5:$X$158,MATCH(Resumen!AA30,'Detalle Costos'!$C$5:$C$158,0))*AG30,0) -> 29045.69 | AD30: =IFERROR(INDEX('Detalle Costos'!$Z$5:$Z$158,MATCH(Resumen!AA30,'Detalle Costos'!$C$5:$C$158,0))*AG30,0) -> 18974.7 | AE30: =IFERROR(INDEX('Detalle Costos'!$Y$5:$Y$158,MATCH(Resumen!AA30,'Detalle Costos'!$C$5:$C$158,0))*AG30,0) -> 365.21 | AF30: =IFERROR(INDEX('Detalle Costos'!$AA$5:$AA$158,MATCH(Resumen!AA30,'Detalle Costos'!$C$5:$C$158,0))*AG30,0) -> 8712.33 | AG30: =AB30*G30 -> 57097.93 | AH30: 27 | AI30: =2.11473814814815*1000 -> 2114.7381 | AJ30: =AI30*AH30 -> 57097.93 | AK30: =P30-AG30 -> 34702.07 | AL30: =AK30/P30 -> 0.37801819 | AM30: =R30 -> 2900 | AN30: =1500/26*G30 -> 1557.6923 | AO30: =SUM(AM30:AN30) -> 4457.6923 | AP30: =65590/1634.3*G30 -> 1083.6015 | AQ30: =S30*0.03 -> 2667 | AR30: =AK30-AO30-AP30+AQ30 -> 31827.776 | AS30: =AR30/P30 -> 0.3467078 | AT30: =148498/1634.3*G30 -> 2453.3109 | AU30: =AR30-AT30 -> 29374.465 | AV30: =AU30/P30 -> 0.31998328 | AW30: =124162.35/1634.3*G30 -> 2051.2656 | AX30: =AR30+AW30 -> 33879.042 | AY30: =AX30/P30 -> 0.36905274 | BA30: =P30/$G30 -> 3400 | BB30: =-AC30/$G30 -> -1075.7663 | BC30: =-AD30/$G30 -> -702.76667 | BD30: =-AE30/$G30 -> -13.526296 | BE30: =-AF30/$G30 -> -322.67889 | BF30: =-AG30/$G30 -> -2114.7381 | BG30: =AK30/$G30 -> 1285.2619 | BH30: =-AM30/$G30 -> -107.40741 | BI30: =-AN30/$G30 -> -57.692308 | BJ30: =-AO30/$G30 -> -165.09972 | BK30: =-AP30/$G30 -> -40.13339 | BL30: =AQ30/$G30 -> 98.777778 | BM30: =AR30/$G30 -> 1178.8065 | BN30: =-AT30/$G30 -> -90.863367 | BO30: =AU30/$G30 -> 1087.9432 | BP30: =AW30/$G30 -> 75.972802 | BQ30: =AX30/$G30 -> 1254.7793
B31: FEBRERO | C31: =B31 -> FEBRERO | D31: 168-2026A | E31: 43 | F31: 46077 | G31: 351 | H31: POTA FILETE CONGELADO | I31: Filete | J31: 2-4 AA | K31: China | L31: Qingdao | M31: AVANCE GROUP | N31: James | O31: 1300 | P31: 456300 | Q31: 1300 | R31: =3103*T31 -> 40339 | S31: =P31-R31 -> 415961 | T31: 13 | U31: ECO MARIN 26008N | V31: 6445505270 | W31: COSCO | X31: PAITA | Y31: 10005721 | Z31: Compensación | AA31: =B31&Y31&Z31 -> FEBRERO10005721Compensación | AB31: =INDEX('Detalle Costos'!$L$5:$L$158,MATCH(Resumen!AA31,'Detalle Costos'!$C$5:$C$158,0))*1000*0+AI31 -> 1740.7827 | AC31: =IFERROR(INDEX('Detalle Costos'!$X$5:$X$158,MATCH(Resumen!AA31,'Detalle Costos'!$C$5:$C$158,0))*AG31,0) -> 370785.72 | AD31: =IFERROR(INDEX('Detalle Costos'!$Z$5:$Z$158,MATCH(Resumen!AA31,'Detalle Costos'!$C$5:$C$158,0))*AG31,0) -> 122493.73 | AE31: =IFERROR(INDEX('Detalle Costos'!$Y$5:$Y$158,MATCH(Resumen!AA31,'Detalle Costos'!$C$5:$C$158,0))*AG31,0) -> 6516.3555 | AF31: =IFERROR(INDEX('Detalle Costos'!$AA$5:$AA$158,MATCH(Resumen!AA31,'Detalle Costos'!$C$5:$C$158,0))*AG31,0) -> 111218.93 | AG31: =AB31*G31 -> 611014.73 | AH31: =+G31 -> 351 | AI31: =1.7407827151654*1000 -> 1740.7827 | AJ31: =+AI31*AH31 -> 611014.73 | AK31: =P31-AG31 -> -154714.73 | AL31: =AK31/P31 -> -0.33906363 | AM31: =R31 -> 40339 | AN31: =1500/26*G31 -> 20250 | AO31: =SUM(AM31:AN31) -> 60589 | AP31: =65590/1634.3*G31 -> 14086.82 | AQ31: =S31*0.03 -> 12478.83 | AR31: =AK31-AO31-AP31+AQ31 -> -216911.72 | AS31: =AR31/P31 -> -0.47537086 | AT31: =148498/1634.3*G31 -> 31893.042 | AU31: =AR31-AT31 -> -248804.76 | AV31: =AU31/P31 -> -0.54526576 | AW31: =124162.35/1634.3*G31 -> 26666.453 | AX31: =AR31+AW31 -> -190245.27 | AY31: =AX31/P31 -> -0.41693024 | BA31: =P31/$G31 -> 1300 | BB31: =-AC31/$G31 -> -1056.3696 | BC31: =-AD31/$G31 -> -348.98498 | BD31: =-AE31/$G31 -> -18.565115 | BE31: =-AF31/$G31 -> -316.86305 | BF31: =-AG31/$G31 -> -1740.7827 | BG31: =AK31/$G31 -> -440.78272 | BH31: =-AM31/$G31 -> -114.92593 | BI31: =-AN31/$G31 -> -57.692308 | BJ31: =-AO31/$G31 -> -172.61823 | BK31: =-AP31/$G31 -> -40.13339 | BL31: =AQ31/$G31 -> 35.552222 | BM31: =AR31/$G31 -> -617.98212 | BN31: =-AT31/$G31 -> -90.863367 | BO31: =AU31/$G31 -> -708.84548 | BP31: =AW31/$G31 -> 75.972802 | BQ31: =AX31/$G31 -> -542.00932
B32: FEBRERO | C32: =B32 -> FEBRERO | D32: 168-2026B | E32: 43 | F32: 46075 | G32: 135 | H32: POTA FILETE CONGELADO | I32: Filete | J32: 2-4 AA | K32: China | L32: shidao | M32: AVANCE GROUP | N32: James | O32: 1300 | P32: 175500 | Q32: 1300 | R32: =3103*T32 -> 15515 | S32: =P32-R32 -> 159985 | T32: 5 | U32: ECO MARIN 26008S | V32: 6445260920 | W32: COSCO | X32: PAITA | Y32: 10005721 | Z32: Compensación | AA32: =B32&Y32&Z32 -> FEBRERO10005721Compensación | AB32: =INDEX('Detalle Costos'!$L$5:$L$158,MATCH(Resumen!AA32,'Detalle Costos'!$C$5:$C$158,0))*1000*0+AI32 -> 1763.7778 | AC32: =IFERROR(INDEX('Detalle Costos'!$X$5:$X$158,MATCH(Resumen!AA32,'Detalle Costos'!$C$5:$C$158,0))*AG32,0) -> 144493.71 | AD32: =IFERROR(INDEX('Detalle Costos'!$Z$5:$Z$158,MATCH(Resumen!AA32,'Detalle Costos'!$C$5:$C$158,0))*AG32,0) -> 47735.316 | AE32: =IFERROR(INDEX('Detalle Costos'!$Y$5:$Y$158,MATCH(Resumen!AA32,'Detalle Costos'!$C$5:$C$158,0))*AG32,0) -> 2539.3977 | AF32: =IFERROR(INDEX('Detalle Costos'!$AA$5:$AA$158,MATCH(Resumen!AA32,'Detalle Costos'!$C$5:$C$158,0))*AG32,0) -> 43341.573 | AG32: =AB32*G32 -> 238110 | AH32: =+G32 -> 135 | AI32: =+AJ32/AH32 -> 1763.7778 | AJ32: 238110 | AK32: =P32-AG32 -> -62610 | AL32: =AK32/P32 -> -0.35675214 | AM32: =R32 -> 15515 | AN32: =1500/26*G32 -> 7788.4615 | AO32: =SUM(AM32:AN32) -> 23303.462 | AP32: =65590/1634.3*G32 -> 5418.0077 | AQ32: =S32*0.03 -> 4799.55 | AR32: =AK32-AO32-AP32+AQ32 -> -86531.919 | AS32: =AR32/P32 -> -0.49305937 | AT32: =148498/1634.3*G32 -> 12266.554 | AU32: =AR32-AT32 -> -98798.474 | AV32: =AU32/P32 -> -0.56295427 | AW32: =124162.35/1634.3*G32 -> 10256.328 | AX32: =AR32+AW32 -> -76275.591 | AY32: =AX32/P32 -> -0.43461875 | BA32: =P32/$G32 -> 1300 | BB32: =-AC32/$G32 -> -1070.3238 | BC32: =-AD32/$G32 -> -353.59493 | BD32: =-AE32/$G32 -> -18.810353 | BE32: =-AF32/$G32 -> -321.04869 | BF32: =-AG32/$G32 -> -1763.7778 | BG32: =AK32/$G32 -> -463.77778 | BH32: =-AM32/$G32 -> -114.92593 | BI32: =-AN32/$G32 -> -57.692308 | BJ32: =-AO32/$G32 -> -172.61823 | BK32: =-AP32/$G32 -> -40.13339 | BL32: =AQ32/$G32 -> 35.552222 | BM32: =AR32/$G32 -> -640.97718 | BN32: =-AT32/$G32 -> -90.863367 | BO32: =AU32/$G32 -> -731.84055 | BP32: =AW32/$G32 -> 75.972802 | BQ32: =AX32/$G32 -> -565.00438
B33: FEBRERO | C33: =B33 -> FEBRERO | D33: 168-2026C | E33: 43 | F33: 46075 | G33: 54 | H33: POTA FILETE CONGELADO | I33: Filete | J33: 2-4 AA | K33: China | L33: Xiamen | M33: AVANCE GROUP | N33: James | O33: 1300 | P33: 70200 | Q33: 1300 | R33: =3103*T33 -> 6206 | S33: =P33-R33 -> 63994 | T33: 2 | U33: ECO MARIN 26008S | V33: 6445502930 | W33: COSCO | X33: PAITA | Y33: 10005721 | Z33: Compensación | AA33: =B33&Y33&Z33 -> FEBRERO10005721Compensación | AB33: =INDEX('Detalle Costos'!$L$5:$L$158,MATCH(Resumen!AA33,'Detalle Costos'!$C$5:$C$158,0))*1000*0+AI33 -> 1740.7827 | AC33: =IFERROR(INDEX('Detalle Costos'!$X$5:$X$158,MATCH(Resumen!AA33,'Detalle Costos'!$C$5:$C$158,0))*AG33,0) -> 57043.957 | AD33: =IFERROR(INDEX('Detalle Costos'!$Z$5:$Z$158,MATCH(Resumen!AA33,'Detalle Costos'!$C$5:$C$158,0))*AG33,0) -> 18845.189 | AE33: =IFERROR(INDEX('Detalle Costos'!$Y$5:$Y$158,MATCH(Resumen!AA33,'Detalle Costos'!$C$5:$C$158,0))*AG33,0) -> 1002.5162 | AF33: =IFERROR(INDEX('Detalle Costos'!$AA$5:$AA$158,MATCH(Resumen!AA33,'Detalle Costos'!$C$5:$C$158,0))*AG33,0) -> 17110.605 | AG33: =AB33*G33 -> 94002.267 | AH33: =+G33 -> 54 | AI33: =1.7407827151654*1000 -> 1740.7827 | AJ33: =+AI33*AH33 -> 94002.267 | AK33: =P33-AG33 -> -23802.267 | AL33: =AK33/P33 -> -0.33906363 | AM33: =R33 -> 6206 | AN33: =1500/26*G33 -> 3115.3846 | AO33: =SUM(AM33:AN33) -> 9321.3846 | AP33: =65590/1634.3*G33 -> 2167.2031 | AQ33: =S33*0.03 -> 1919.82 | AR33: =AK33-AO33-AP33+AQ33 -> -33371.034 | AS33: =AR33/P33 -> -0.47537086 | AT33: =148498/1634.3*G33 -> 4906.6218 | AU33: =AR33-AT33 -> -38277.656 | AV33: =AU33/P33 -> -0.54526576 | AW33: =124162.35/1634.3*G33 -> 4102.5313 | AX33: =AR33+AW33 -> -29268.503 | AY33: =AX33/P33 -> -0.41693024 | BA33: =P33/$G33 -> 1300 | BB33: =-AC33/$G33 -> -1056.3696 | BC33: =-AD33/$G33 -> -348.98498 | BD33: =-AE33/$G33 -> -18.565115 | BE33: =-AF33/$G33 -> -316.86305 | BF33: =-AG33/$G33 -> -1740.7827 | BG33: =AK33/$G33 -> -440.78272 | BH33: =-AM33/$G33 -> -114.92593 | BI33: =-AN33/$G33 -> -57.692308 | BJ33: =-AO33/$G33 -> -172.61823 | BK33: =-AP33/$G33 -> -40.13339 | BL33: =AQ33/$G33 -> 35.552222 | BM33: =AR33/$G33 -> -617.98212 | BN33: =-AT33/$G33 -> -90.863367 | BO33: =AU33/$G33 -> -708.84548 | BP33: =AW33/$G33 -> 75.972802 | BQ33: =AX33/$G33 -> -542.00932
B34: FEBRERO | C34: =B34 -> FEBRERO | D34: 170-2026A | E34: 43 | F34: 46076 | G34: 156 | H34: POTA REJOS CONGELADOS | I34: Rejos | J34: 9 FCL 1-2 / 1 FCL 2-UP | K34: España | L34: Vigo | M34: KULALIA | N34: Ramon | O34: 2500 | P34: 390000 | Q34: 2337.2308 | R34: 25392 | S34: =P34-R34 -> 364608 | T34: 4 | U34: CAPE SABLE 609N | V34: 11428031 | W34: HAPAG | X34: PAITA | Y34: 10007162 | Z34: Compensación | AA34: =B34&Y34&Z34 -> FEBRERO10007162Compensación | AB34: =INDEX('Detalle Costos'!$L$5:$L$158,MATCH(Resumen!AA34,'Detalle Costos'!$C$5:$C$158,0))*1000*0+AI34 -> 1715.2908 | AC34: =IFERROR(INDEX('Detalle Costos'!$X$5:$X$158,MATCH(Resumen!AA34,'Detalle Costos'!$C$5:$C$158,0))*AG34,0) -> 167980.9 | AD34: =IFERROR(INDEX('Detalle Costos'!$Z$5:$Z$158,MATCH(Resumen!AA34,'Detalle Costos'!$C$5:$C$158,0))*AG34,0) -> 47932.005 | AE34: =IFERROR(INDEX('Detalle Costos'!$Y$5:$Y$158,MATCH(Resumen!AA34,'Detalle Costos'!$C$5:$C$158,0))*AG34,0) -> 2495.565 | AF34: =IFERROR(INDEX('Detalle Costos'!$AA$5:$AA$158,MATCH(Resumen!AA34,'Detalle Costos'!$C$5:$C$158,0))*AG34,0) -> 49176.892 | AG34: =AB34*G34 -> 267585.37 | AH34: =+G34 -> 156 | AI34: 1715.2908 | AJ34: =AI34*AH34 -> 267585.37 | AK34: =P34-AG34 -> 122414.63 | AL34: =AK34/P34 -> 0.31388367 | AM34: =R34 -> 25392 | AN34: =1500/26*G34 -> 9000 | AO34: =SUM(AM34:AN34) -> 34392 | AP34: =65590/1634.3*G34 -> 6260.8089 | AQ34: =S34*0.03 -> 10938.24 | AR34: =AK34-AO34-AP34+AQ34 -> 92700.064 | AS34: =AR34/P34 -> 0.23769247 | AT34: =148498/1634.3*G34 -> 14174.685 | AU34: =AR34-AT34 -> 78525.378 | AV34: =AU34/P34 -> 0.20134712 | AW34: =124162.35/1634.3*G34 -> 11851.757 | AX34: =AR34+AW34 -> 104551.82 | AY34: =AX34/P34 -> 0.26808159 | BA34: =P34/$G34 -> 2500 | BB34: =-AC34/$G34 -> -1076.8007 | BC34: =-AD34/$G34 -> -307.25644 | BD34: =-AE34/$G34 -> -15.997212 | BE34: =-AF34/$G34 -> -315.23649 | BF34: =-AG34/$G34 -> -1715.2908 | BG34: =AK34/$G34 -> 784.70918 | BH34: =-AM34/$G34 -> -162.76923 | BI34: =-AN34/$G34 -> -57.692308 | BJ34: =-AO34/$G34 -> -220.46154 | BK34: =-AP34/$G34 -> -40.13339 | BL34: =AQ34/$G34 -> 70.116923 | BM34: =AR34/$G34 -> 594.23118 | BN34: =-AT34/$G34 -> -90.863367 | BO34: =AU34/$G34 -> 503.36781 | BP34: =AW34/$G34 -> 75.972802 | BQ34: =AX34/$G34 -> 670.20398
B35: FEBRERO | C35: =B35 -> FEBRERO | E35: 46080 | F35: 46080 | G35: 0 | H35: RESIDUOS DE POTA | I35: Residuos | J35: Residuos | K35: Residuos | L35: Residuos | M35: PROVEEDORA DE PRODUCTOS MARINOS | O35: 0 | P35: 40026 | Q35: 0 | R35: 0 | S35: =P35-R35 -> 40026 | AB35: 0 | AC35: =IFERROR(INDEX('Detalle Costos'!$X$5:$X$158,MATCH(Resumen!AA35,'Detalle Costos'!$C$5:$C$158,0))*AG35,0) -> 0 | AD35: =IFERROR(INDEX('Detalle Costos'!$Z$5:$Z$158,MATCH(Resumen!AA35,'Detalle Costos'!$C$5:$C$158,0))*AG35,0) -> 0 | AE35: =IFERROR(INDEX('Detalle Costos'!$Y$5:$Y$158,MATCH(Resumen!AA35,'Detalle Costos'!$C$5:$C$158,0))*AG35,0) -> 0 | AF35: =IFERROR(INDEX('Detalle Costos'!$AA$5:$AA$158,MATCH(Resumen!AA35,'Detalle Costos'!$C$5:$C$158,0))*AG35,0) -> 0 | AG35: =AB35*G35 -> 0 | AK35: =P35-AG35 -> 40026 | AL35: =AK35/P35 -> 1 | AM35: =R35 -> 0 | AN35: =1500/26*G35 -> 0 | AO35: =SUM(AM35:AN35) -> 0 | AP35: =60070/248*G35 -> 0 | AQ35: 0 | AR35: =AK35-AO35-AP35+AQ35 -> 40026 | AS35: =AR35/P35 -> 1 | AT35: =131251/248*G35 -> 0 | AU35: =AR35-AT35 -> 40026 | AV35: =AU35/P35 -> 1 | AW35: =123530/248*G35 -> 0 | AX35: =AR35+AW35 -> 40026 | AY35: =AX35/P35 -> 1 | BA35: 0 | BB35: 0 | BC35: 0 | BD35: 0 | BE35: 0 | BF35: 0 | BG35: 0 | BH35: 0 | BI35: 0 | BJ35: 0 | BK35: 0 | BL35: 0 | BM35: 0 | BN35: 0 | BO35: 0 | BP35: 0 | BQ35: 0
B36: FEBRERO | C36: MARZO | D36: 150-2026B | E36: 325 | F36: 46084 | G36: 26 | H36: POTA REJOS CONGELADOS | I36: Rejos | J36: 1-2 KG | K36: España | L36: Vigo | M36: OVERSEA | N36: Avelino | O36: 2600 | P36: 67600 | Q36: 2518.6154 | R36: 4232 | S36: =P36-R36 -> 63368 | T36: 1 | U36: LEONIDAS Z 610N | V36: 51077247 | Y36: 10007162 | Z36: Inventario final | AA36: =B36&Y36&Z36 -> FEBRERO10007162Inventario final | AB36: =INDEX('Detalle Costos'!$L$5:$L$158,MATCH(Resumen!AA36,'Detalle Costos'!$C$5:$C$158,0))*1000 -> 1720 | AC36: =IFERROR(INDEX('Detalle Costos'!$X$5:$X$158,MATCH(Resumen!AA36,'Detalle Costos'!$C$5:$C$158,0))*AG36,0) -> 28073.68 | AD36: =IFERROR(INDEX('Detalle Costos'!$Z$5:$Z$158,MATCH(Resumen!AA36,'Detalle Costos'!$C$5:$C$158,0))*AG36,0) -> 8010.6002 | AE36: =IFERROR(INDEX('Detalle Costos'!$Y$5:$Y$158,MATCH(Resumen!AA36,'Detalle Costos'!$C$5:$C$158,0))*AG36,0) -> 417.07006 | AF36: =IFERROR(INDEX('Detalle Costos'!$AA$5:$AA$158,MATCH(Resumen!AA36,'Detalle Costos'!$C$5:$C$158,0))*AG36,0) -> 8218.6496 | AG36: =AB36*G36 -> 44720 | AK36: =P36-AG36 -> 22880 | AL36: =AK36/P36 -> 0.33846154 | AM36: =R36 -> 4232 | AN36: =1500/26*G36 -> 1500 | AO36: =SUM(AM36:AN36) -> 5732 | AP36: =70656.31/1997.8*G36 -> 919.54353 | AQ36: =S36*0.03 -> 1901.04 | AR36: =AK36-AO36-AP36+AQ36 -> 18129.496 | AS36: =AR36/P36 -> 0.26818782 | AT36: =105684.48/1997.8*G36 -> 1375.4112 | AU36: =AR36-AT36 -> 16754.085 | AV36: =AU36/P36 -> 0.2478415 | AW36: =123484.35/1997.8*G36 -> 1607.0643 | AX36: =AR36+AW36 -> 19736.561 | AY36: =AX36/P36 -> 0.29196096 | BA36: =P36/$G36 -> 2600 | BB36: =-AC36/$G36 -> -1079.7569 | BC36: =-AD36/$G36 -> -308.10001 | BD36: =-AE36/$G36 -> -16.041156 | BE36: =-AF36/$G36 -> -316.10191 | BF36: =-AG36/$G36 -> -1720 | BG36: =AK36/$G36 -> 880 | BH36: =-AM36/$G36 -> -162.76923 | BI36: =-AN36/$G36 -> -57.692308 | BJ36: =-AO36/$G36 -> -220.46154 | BK36: =-AP36/$G36 -> -35.367059 | BL36: =AQ36/$G36 -> 73.116923 | BM36: =AR36/$G36 -> 697.28833 | BN36: =-AT36/$G36 -> -52.90043 | BO36: =AU36/$G36 -> 644.3879 | BP36: =AW36/$G36 -> 61.810166 | BQ36: =AX36/$G36 -> 759.09849
B37: FEBRERO | C37: MARZO | D37: 150-2026C | E37: 325 | F37: 46084 | G37: 26 | H37: POTA REJOS CONGELADOS | I37: Rejos | J37: 1-2 KG | K37: España | L37: Vigo | M37: OVERSEA | N37: Avelino | O37: 2600 | P37: 67600 | Q37: 2518.6154 | R37: 4232 | S37: =P37-R37 -> 63368 | T37: 1 | U37: LEONIDAS Z 610N | V37: 37563181 | Y37: 10007162 | Z37: Inventario final | AA37: =B37&Y37&Z37 -> FEBRERO10007162Inventario final | AB37: =INDEX('Detalle Costos'!$L$5:$L$158,MATCH(Resumen!AA37,'Detalle Costos'!$C$5:$C$158,0))*1000 -> 1720 | AC37: =IFERROR(INDEX('Detalle Costos'!$X$5:$X$158,MATCH(Resumen!AA37,'Detalle Costos'!$C$5:$C$158,0))*AG37,0) -> 28073.68 | AD37: =IFERROR(INDEX('Detalle Costos'!$Z$5:$Z$158,MATCH(Resumen!AA37,'Detalle Costos'!$C$5:$C$158,0))*AG37,0) -> 8010.6002 | AE37: =IFERROR(INDEX('Detalle Costos'!$Y$5:$Y$158,MATCH(Resumen!AA37,'Detalle Costos'!$C$5:$C$158,0))*AG37,0) -> 417.07006 | AF37: =IFERROR(INDEX('Detalle Costos'!$AA$5:$AA$158,MATCH(Resumen!AA37,'Detalle Costos'!$C$5:$C$158,0))*AG37,0) -> 8218.6496 | AG37: =AB37*G37 -> 44720 | AK37: =P37-AG37 -> 22880 | AL37: =AK37/P37 -> 0.33846154 | AM37: =R37 -> 4232 | AN37: =1500/26*G37 -> 1500 | AO37: =SUM(AM37:AN37) -> 5732 | AP37: =70656.31/1997.8*G37 -> 919.54353 | AQ37: =S37*0.03 -> 1901.04 | AR37: =AK37-AO37-AP37+AQ37 -> 18129.496 | AS37: =AR37/P37 -> 0.26818782 | AT37: =105684.48/1997.8*G37 -> 1375.4112 | AU37: =AR37-AT37 -> 16754.085 | AV37: =AU37/P37 -> 0.2478415 | AW37: =123484.35/1997.8*G37 -> 1607.0643 | AX37: =AR37+AW37 -> 19736.561 | AY37: =AX37/P37 -> 0.29196096 | BA37: =P37/$G37 -> 2600 | BB37: =-AC37/$G37 -> -1079.7569 | BC37: =-AD37/$G37 -> -308.10001 | BD37: =-AE37/$G37 -> -16.041156 | BE37: =-AF37/$G37 -> -316.10191 | BF37: =-AG37/$G37 -> -1720 | BG37: =AK37/$G37 -> 880 | BH37: =-AM37/$G37 -> -162.76923 | BI37: =-AN37/$G37 -> -57.692308 | BJ37: =-AO37/$G37 -> -220.46154 | BK37: =-AP37/$G37 -> -35.367059 | BL37: =AQ37/$G37 -> 73.116923 | BM37: =AR37/$G37 -> 697.28833 | BN37: =-AT37/$G37 -> -52.90043 | BO37: =AU37/$G37 -> 644.3879 | BP37: =AW37/$G37 -> 61.810166 | BQ37: =AX37/$G37 -> 759.09849
B38: FEBRERO | C38: MARZO | D38: 159-2026A | E38: 30 | F38: 46084 | G38: 24 | H38: POTA FILETE CONGELADO | I38: Filete | J38: B | K38: Japón | L38: Sendai | M38: TSUJINO | N38: Jose | O38: 1700 | P38: 40800 | Q38: 1562.375 | R38: 3303 | S38: =P38-R38 -> 37497 | T38: 1 | U38: ECO SIROCCO 26009N | V38: LIMG03265300 | W38: ONE | X38: PAITA | Y38: 10005721 | Z38: Inventario final | AA38: =B38&Y38&Z38 -> FEBRERO10005721Inventario final | AB38: =INDEX('Detalle Costos'!$L$5:$L$158,MATCH(Resumen!AA38,'Detalle Costos'!$C$5:$C$158,0))*1000 -> 1740 | AC38: =IFERROR(INDEX('Detalle Costos'!$X$5:$X$158,MATCH(Resumen!AA38,'Detalle Costos'!$C$5:$C$158,0))*AG38,0) -> 25341.47 | AD38: =IFERROR(INDEX('Detalle Costos'!$Z$5:$Z$158,MATCH(Resumen!AA38,'Detalle Costos'!$C$5:$C$158,0))*AG38,0) -> 8371.8735 | AE38: =IFERROR(INDEX('Detalle Costos'!$Y$5:$Y$158,MATCH(Resumen!AA38,'Detalle Costos'!$C$5:$C$158,0))*AG38,0) -> 445.3629 | AF38: =IFERROR(INDEX('Detalle Costos'!$AA$5:$AA$158,MATCH(Resumen!AA38,'Detalle Costos'!$C$5:$C$158,0))*AG38,0) -> 7601.2938 | AG38: =AB38*G38 -> 41760 | AK38: =P38-AG38 -> -960 | AL38: =AK38/P38 -> -0.023529412 | AM38: =R38 -> 3303 | AN38: =1500/26*G38 -> 1384.6154 | AO38: =SUM(AM38:AN38) -> 4687.6154 | AP38: =70656.31/1997.8*G38 -> 848.80941 | AQ38: =S38*0.03 -> 1124.91 | AR38: =AK38-AO38-AP38+AQ38 -> -5371.5148 | AS38: =AR38/P38 -> -0.13165477 | AT38: =105684.48/1997.8*G38 -> 1269.6103 | AU38: =AR38-AT38 -> -6641.1251 | AV38: =AU38/P38 -> -0.16277267 | AW38: =123484.35/1997.8*G38 -> 1483.444 | AX38: =AR38+AW38 -> -3888.0708 | AY38: =AX38/P38 -> -0.095295853 | BA38: =P38/$G38 -> 1700 | BB38: =-AC38/$G38 -> -1055.8946 | BC38: =-AD38/$G38 -> -348.82806 | BD38: =-AE38/$G38 -> -18.556788 | BE38: =-AF38/$G38 -> -316.72057 | BF38: =-AG38/$G38 -> -1740 | BG38: =AK38/$G38 -> -40 | BH38: =-AM38/$G38 -> -137.625 | BI38: =-AN38/$G38 -> -57.692308 | BJ38: =-AO38/$G38 -> -195.31731 | BK38: =-AP38/$G38 -> -35.367059 | BL38: =AQ38/$G38 -> 46.87125 | BM38: =AR38/$G38 -> -223.81312 | BN38: =-AT38/$G38 -> -52.90043 | BO38: =AU38/$G38 -> -276.71355 | BP38: =AW38/$G38 -> 61.810166 | BQ38: =AX38/$G38 -> -162.00295
B39: FEBRERO | C39: MARZO | D39: 161-2026A | E39: 30 | F39: 46085 | G39: 72 | H39: POTA NUCAS | I39: Nucas | J39: 500-up | K39: Tailandia | L39: Lat Krabang | M39: TSUJINO | N39: Jose | O39: 1400 | P39: 100800 | Q39: 1266.5417 | R39: 9609 | S39: =P39-R39 -> 91191 | T39: 3 | U39: ECO SIROCCO 26009N | V39: LIMG03094300 | W39: ONE LINE | X39: PAITA | Y39: 10005779 | Z39: Inventario final | AA39: =B39&Y39&Z39 -> FEBRERO10005779Inventario final | AB39: =INDEX('Detalle Costos'!$L$5:$L$158,MATCH(Resumen!AA39,'Detalle Costos'!$C$5:$C$158,0))*1000 -> 1860 | AC39: =IFERROR(INDEX('Detalle Costos'!$X$5:$X$158,MATCH(Resumen!AA39,'Detalle Costos'!$C$5:$C$158,0))*AG39,0) -> 81515.847 | AD39: =IFERROR(INDEX('Detalle Costos'!$Z$5:$Z$158,MATCH(Resumen!AA39,'Detalle Costos'!$C$5:$C$158,0))*AG39,0) -> 29485.476 | AE39: =IFERROR(INDEX('Detalle Costos'!$Y$5:$Y$158,MATCH(Resumen!AA39,'Detalle Costos'!$C$5:$C$158,0))*AG39,0) -> 976.89119 | AF39: =IFERROR(INDEX('Detalle Costos'!$AA$5:$AA$158,MATCH(Resumen!AA39,'Detalle Costos'!$C$5:$C$158,0))*AG39,0) -> 21941.786 | AG39: =AB39*G39 -> 133920 | AK39: =P39-AG39 -> -33120 | AL39: =AK39/P39 -> -0.32857143 | AM39: =R39 -> 9609 | AN39: =1500/26*G39 -> 4153.8462 | AO39: =SUM(AM39:AN39) -> 13762.846 | AP39: =70656.31/1997.8*G39 -> 2546.4282 | AQ39: =S39*0.03 -> 2735.73 | AR39: =AK39-AO39-AP39+AQ39 -> -46693.544 | AS39: =AR39/P39 -> -0.46322961 | AT39: =105684.48/1997.8*G39 -> 3808.831 | AU39: =AR39-AT39 -> -50502.375 | AV39: =AU39/P39 -> -0.50101563 | AW39: =123484.35/1997.8*G39 -> 4450.332 | AX39: =AR39+AW39 -> -42243.212 | AY39: =AX39/P39 -> -0.41907949 | BA39: =P39/$G39 -> 1400 | BB39: =-AC39/$G39 -> -1132.1645 | BC39: =-AD39/$G39 -> -409.5205 | BD39: =-AE39/$G39 -> -13.567933 | BE39: =-AF39/$G39 -> -304.74703 | BF39: =-AG39/$G39 -> -1860 | BG39: =AK39/$G39 -> -460 | BH39: =-AM39/$G39 -> -133.45833 | BI39: =-AN39/$G39 -> -57.692308 | BJ39: =-AO39/$G39 -> -191.15064 | BK39: =-AP39/$G39 -> -35.367059 | BL39: =AQ39/$G39 -> 37.99625 | BM39: =AR39/$G39 -> -648.52145 | BN39: =-AT39/$G39 -> -52.90043 | BO39: =AU39/$G39 -> -701.42188 | BP39: =AW39/$G39 -> 61.810166 | BQ39: =AX39/$G39 -> -586.71128
B40: FEBRERO | C40: MARZO | D40: 161-2026B | E40: 30 | F40: 46108 | G40: 48 | H40: POTA NUCAS | I40: Nucas | J40: 500-up | K40: Tailandia | L40: Lat Krabang | M40: TSUJINO | N40: Jose | O40: 1400 | P40: 67200 | Q40: 1254.1667 | R40: 7000 | S40: =P40-R40 -> 60200 | T40: 2 | U40: ECO SIROCCO 26013S | V40: 6446527790 | W40: COSCO | X40: PAITA | Y40: 10005779 | Z40: Inventario final | AA40: =B40&Y40&Z40 -> FEBRERO10005779Inventario final | AB40: =INDEX('Detalle Costos'!$L$5:$L$158,MATCH(Resumen!AA40,'Detalle Costos'!$C$5:$C$158,0))*1000 -> 1860 | AC40: =IFERROR(INDEX('Detalle Costos'!$X$5:$X$158,MATCH(Resumen!AA40,'Detalle Costos'!$C$5:$C$158,0))*AG40,0) -> 54343.898 | AD40: =IFERROR(INDEX('Detalle Costos'!$Z$5:$Z$158,MATCH(Resumen!AA40,'Detalle Costos'!$C$5:$C$158,0))*AG40,0) -> 19656.984 | AE40: =IFERROR(INDEX('Detalle Costos'!$Y$5:$Y$158,MATCH(Resumen!AA40,'Detalle Costos'!$C$5:$C$158,0))*AG40,0) -> 651.26079 | AF40: =IFERROR(INDEX('Detalle Costos'!$AA$5:$AA$158,MATCH(Resumen!AA40,'Detalle Costos'!$C$5:$C$158,0))*AG40,0) -> 14627.857 | AG40: =AB40*G40 -> 89280 | AK40: =P40-AG40 -> -22080 | AL40: =AK40/P40 -> -0.32857143 | AM40: =R40 -> 7000 | AN40: =1500/26*G40 -> 2769.2308 | AO40: =SUM(AM40:AN40) -> 9769.2308 | AP40: =70656.31/1997.8*G40 -> 1697.6188 | AQ40: =S40*0.03 -> 1806 | AR40: =AK40-AO40-AP40+AQ40 -> -31740.85 | AS40: =AR40/P40 -> -0.47233407 | AT40: =105684.48/1997.8*G40 -> 2539.2207 | AU40: =AR40-AT40 -> -34280.07 | AV40: =AU40/P40 -> -0.51012009 | AW40: =123484.35/1997.8*G40 -> 2966.888 | AX40: =AR40+AW40 -> -28773.962 | AY40: =AX40/P40 -> -0.42818395 | BA40: =P40/$G40 -> 1400 | BB40: =-AC40/$G40 -> -1132.1645 | BC40: =-AD40/$G40 -> -409.5205 | BD40: =-AE40/$G40 -> -13.567933 | BE40: =-AF40/$G40 -> -304.74703 | BF40: =-AG40/$G40 -> -1860 | BG40: =AK40/$G40 -> -460 | BH40: =-AM40/$G40 -> -145.83333 | BI40: =-AN40/$G40 -> -57.692308 | BJ40: =-AO40/$G40 -> -203.52564 | BK40: =-AP40/$G40 -> -35.367059 | BL40: =AQ40/$G40 -> 37.625 | BM40: =AR40/$G40 -> -661.2677 | BN40: =-AT40/$G40 -> -52.90043 | BO40: =AU40/$G40 -> -714.16813 | BP40: =AW40/$G40 -> 61.810166 | BQ40: =AX40/$G40 -> -599.45753
B41: FEBRERO | C41: MARZO | D41: 163-2026 | E41: 34 | F41: 46087 | G41: 48 | H41: POTA ALAS CONGELADAS | I41: Alas | J41: 1-up | K41: korea | L41: Busan | M41: TSUJINO | N41: Jose | O41: 1600 | P41: 76800 | Q41: 1479.1667 | R41: 5800 | S41: =P41-R41 -> 71000 | T41: 2 | U41: ECO MARIN 26010S | V41: 6445718250 | W41: COSCO | X41: PAITA | Y41: 10006720 | Z41: Inventario final | AA41: =B41&Y41&Z41 -> FEBRERO10006720Inventario final | AB41: =INDEX('Detalle Costos'!$L$5:$L$158,MATCH(Resumen!AA41,'Detalle Costos'!$C$5:$C$158,0))*1000 -> 1640 | AC41: =IFERROR(INDEX('Detalle Costos'!$X$5:$X$158,MATCH(Resumen!AA41,'Detalle Costos'!$C$5:$C$158,0))*AG41,0) -> 51030.234 | AD41: =IFERROR(INDEX('Detalle Costos'!$Z$5:$Z$158,MATCH(Resumen!AA41,'Detalle Costos'!$C$5:$C$158,0))*AG41,0) -> 11676.68 | AE41: =IFERROR(INDEX('Detalle Costos'!$Y$5:$Y$158,MATCH(Resumen!AA41,'Detalle Costos'!$C$5:$C$158,0))*AG41,0) -> 764.81419 | AF41: =IFERROR(INDEX('Detalle Costos'!$AA$5:$AA$158,MATCH(Resumen!AA41,'Detalle Costos'!$C$5:$C$158,0))*AG41,0) -> 15248.272 | AG41: =AB41*G41 -> 78720 | AK41: =P41-AG41 -> -1920 | AL41: =AK41/P41 -> -0.025 | AM41: =R41 -> 5800 | AN41: =1500/26*G41 -> 2769.2308 | AO41: =SUM(AM41:AN41) -> 8569.2308 | AP41: =70656.31/1997.8*G41 -> 1697.6188 | AQ41: =S41*0.03 -> 2130 | AR41: =AK41-AO41-AP41+AQ41 -> -10056.85 | AS41: =AR41/P41 -> -0.13094856 | AT41: =105684.48/1997.8*G41 -> 2539.2207 | AU41: =AR41-AT41 -> -12596.07 | AV41: =AU41/P41 -> -0.16401133 | AW41: =123484.35/1997.8*G41 -> 2966.888 | AX41: =AR41+AW41 -> -7089.9616 | AY41: =AX41/P41 -> -0.092317209 | BA41: =P41/$G41 -> 1600 | BB41: =-AC41/$G41 -> -1063.1299 | BC41: =-AD41/$G41 -> -243.26417 | BD41: =-AE41/$G41 -> -15.933629 | BE41: =-AF41/$G41 -> -317.67233 | BF41: =-AG41/$G41 -> -1640 | BG41: =AK41/$G41 -> -40 | BH41: =-AM41/$G41 -> -120.83333 | BI41: =-AN41/$G41 -> -57.692308 | BJ41: =-AO41/$G41 -> -178.52564 | BK41: =-AP41/$G41 -> -35.367059 | BL41: =AQ41/$G41 -> 44.375 | BM41: =AR41/$G41 -> -209.5177 | BN41: =-AT41/$G41 -> -52.90043 | BO41: =AU41/$G41 -> -262.41813 | BP41: =AW41/$G41 -> 61.810166 | BQ41: =AX41/$G41 -> -147.70753
B42: FEBRERO | C42: MARZO | D42: 165-2026 | E42: 40 | F42: 46105 | G42: 27 | H42: POTA MEMBRANA PRECOCIDA | I42: Membrana | K42: China | L42: Qingdao | M42: Longkou Yunfeng Aquatic | O42: 1400 | P42: 37800 | Q42: 1271.6296 | R42: 3466 | S42: =P42-R42 -> 34334 | T42: 1 | U42: CMA CGM BETTER WAYS 0DVOHN1MA | V42: LMM0577574 | W42: CMA CGM | X42: PAITA | AB42: 0 | AC42: =IFERROR(INDEX('Detalle Costos'!$X$5:$X$158,MATCH(Resumen!AA42,'Detalle Costos'!$C$5:$C$158,0))*AG42,0) -> 0 | AD42: =IFERROR(INDEX('Detalle Costos'!$Z$5:$Z$158,MATCH(Resumen!AA42,'Detalle Costos'!$C$5:$C$158,0))*AG42,0) -> 0 | AE42: =IFERROR(INDEX('Detalle Costos'!$Y$5:$Y$158,MATCH(Resumen!AA42,'Detalle Costos'!$C$5:$C$158,0))*AG42,0) -> 0 | AF42: =IFERROR(INDEX('Detalle Costos'!$AA$5:$AA$158,MATCH(Resumen!AA42,'Detalle Costos'!$C$5:$C$158,0))*AG42,0) -> 0 | AG42: =AB42*G42 -> 0 | AK42: =P42-AG42 -> 37800 | AL42: =AK42/P42 -> 1 | AM42: =R42 -> 3466 | AN42: =1500/26*G42 -> 1557.6923 | AO42: =SUM(AM42:AN42) -> 5023.6923 | AP42: =70656.31/1997.8*G42 -> 954.91059 | AQ42: =S42*0.03 -> 1030.02 | AR42: =AK42-AO42-AP42+AQ42 -> 32851.417 | AS42: =AR42/P42 -> 0.86908511 | AT42: =105684.48/1997.8*G42 -> 1428.3116 | AU42: =AR42-AT42 -> 31423.105 | AV42: =AU42/P42 -> 0.83129909 | AW42: =123484.35/1997.8*G42 -> 1668.8745 | AX42: =AR42+AW42 -> 34520.292 | AY42: =AX42/P42 -> 0.91323523 | BA42: =P42/$G42 -> 1400 | BB42: =-AC42/$G42 -> 0 | BC42: =-AD42/$G42 -> 0 | BD42: =-AE42/$G42 -> 0 | BE42: =-AF42/$G42 -> 0 | BF42: =-AG42/$G42 -> 0 | BG42: =AK42/$G42 -> 1400 | BH42: =-AM42/$G42 -> -128.37037 | BI42: =-AN42/$G42 -> -57.692308 | BJ42: =-AO42/$G42 -> -186.06268 | BK42: =-AP42/$G42 -> -35.367059 | BL42: =AQ42/$G42 -> 38.148889 | BM42: =AR42/$G42 -> 1216.7192 | BN42: =-AT42/$G42 -> -52.90043 | BO42: =AU42/$G42 -> 1163.8187 | BP42: =AW42/$G42 -> 61.810166 | BQ42: =AX42/$G42 -> 1278.5293
B43: FEBRERO | C43: MARZO | D43: 167-2026 | E43: 42 | F43: 46104 | G43: 48 | H43: POTA CONOS | I43: Conos | K43: Tailandia | L43: Bangkok | M43: TSUJINO | N43: Jose | O43: 1600 | P43: 76800 | Q43: 1462.5 | R43: 6600 | S43: =P43-R43 -> 70200 | T43: 2 | U43: ECO MARIN 26012S | V43: 6446513180 | W43: COSCO | X43: PAITA | Y43: 10007969 | Z43: Inventario final | AA43: =B43&Y43&Z43 -> FEBRERO10007969Inventario final | AB43: =INDEX('Detalle Costos'!$L$5:$L$158,MATCH(Resumen!AA43,'Detalle Costos'!$C$5:$C$158,0))*1000 -> 1400 | AC43: =IFERROR(INDEX('Detalle Costos'!$X$5:$X$158,MATCH(Resumen!AA43,'Detalle Costos'!$C$5:$C$158,0))*AG43,0) -> 54354.508 | AD43: =IFERROR(INDEX('Detalle Costos'!$Z$5:$Z$158,MATCH(Resumen!AA43,'Detalle Costos'!$C$5:$C$158,0))*AG43,0) -> 10231.733 | AE43: =IFERROR(INDEX('Detalle Costos'!$Y$5:$Y$158,MATCH(Resumen!AA43,'Detalle Costos'!$C$5:$C$158,0))*AG43,0) -> 802.34093 | AF43: =IFERROR(INDEX('Detalle Costos'!$AA$5:$AA$158,MATCH(Resumen!AA43,'Detalle Costos'!$C$5:$C$158,0))*AG43,0) -> 1811.4175 | AG43: =AB43*G43 -> 67200 | AK43: =P43-AG43 -> 9600 | AL43: =AK43/P43 -> 0.125 | AM43: =R43 -> 6600 | AN43: =1500/26*G43 -> 2769.2308 | AO43: =SUM(AM43:AN43) -> 9369.2308 | AP43: =70656.31/1997.8*G43 -> 1697.6188 | AQ43: =S43*0.03 -> 2106 | AR43: =AK43-AO43-AP43+AQ43 -> 639.15041 | AS43: =AR43/P43 -> 0.008322271 | AT43: =105684.48/1997.8*G43 -> 2539.2207 | AU43: =AR43-AT43 -> -1900.0703 | AV43: =AU43/P43 -> -0.024740498 | AW43: =123484.35/1997.8*G43 -> 2966.888 | AX43: =AR43+AW43 -> 3606.0384 | AY43: =AX43/P43 -> 0.046953625 | BA43: =P43/$G43 -> 1600 | BB43: =-AC43/$G43 -> -1132.3856 | BC43: =-AD43/$G43 -> -213.16111 | BD43: =-AE43/$G43 -> -16.715436 | BE43: =-AF43/$G43 -> -37.737864 | BF43: =-AG43/$G43 -> -1400 | BG43: =AK43/$G43 -> 200 | BH43: =-AM43/$G43 -> -137.5 | BI43: =-AN43/$G43 -> -57.692308 | BJ43: =-AO43/$G43 -> -195.19231 | BK43: =-AP43/$G43 -> -35.367059 | BL43: =AQ43/$G43 -> 43.875 | BM43: =AR43/$G43 -> 13.315634 | BN43: =-AT43/$G43 -> -52.90043 | BO43: =AU43/$G43 -> -39.584797 | BP43: =AW43/$G43 -> 61.810166 | BQ43: =AX43/$G43 -> 75.1258
B44: FEBRERO | C44: MARZO | D44: 169-2026A | E44: 43 | F44: 46084 | G44: 116.8 | H44: POTA ALAS CONGELADAS | I44: Alas | J44: 1-UP | K44: China | L44: Qingdao | M44: TSUJINO | N44: Jose | O44: 1600 | P44: 186880 | Q44: 1484.2894 | R44: 13515 | S44: =P44-R44 -> 173365 | T44: 5 | U44: ECO SIROCCO 26009N | V44: LIMG02789600 | W44: ONE | X44: PAITA | Y44: 10006720 | Z44: Inventario final | AA44: =B44&Y44&Z44 -> FEBRERO10006720Inventario final | AB44: =INDEX('Detalle Costos'!$L$5:$L$158,MATCH(Resumen!AA44,'Detalle Costos'!$C$5:$C$158,0))*1000 -> 1640 | AC44: =IFERROR(INDEX('Detalle Costos'!$X$5:$X$158,MATCH(Resumen!AA44,'Detalle Costos'!$C$5:$C$158,0))*AG44,0) -> 124173.57 | AD44: =IFERROR(INDEX('Detalle Costos'!$Z$5:$Z$158,MATCH(Resumen!AA44,'Detalle Costos'!$C$5:$C$158,0))*AG44,0) -> 28413.255 | AE44: =IFERROR(INDEX('Detalle Costos'!$Y$5:$Y$158,MATCH(Resumen!AA44,'Detalle Costos'!$C$5:$C$158,0))*AG44,0) -> 1861.0479 | AF44: =IFERROR(INDEX('Detalle Costos'!$AA$5:$AA$158,MATCH(Resumen!AA44,'Detalle Costos'!$C$5:$C$158,0))*AG44,0) -> 37104.128 | AG44: =AB44*G44 -> 191552 | AK44: =P44-AG44 -> -4672 | AL44: =AK44/P44 -> -0.025 | AM44: =R44 -> 13515 | AN44: =1500/26*G44 -> 6738.4615 | AO44: =SUM(AM44:AN44) -> 20253.462 | AP44: =70656.31/1997.8*G44 -> 4130.8725 | AQ44: =S44*0.03 -> 5200.95 | AR44: =AK44-AO44-AP44+AQ44 -> -23855.384 | AS44: =AR44/P44 -> -0.12765081 | AT44: =105684.48/1997.8*G44 -> 6178.7703 | AU44: =AR44-AT44 -> -30034.154 | AV44: =AU44/P44 -> -0.16071358 | AW44: =123484.35/1997.8*G44 -> 7219.4274 | AX44: =AR44+AW44 -> -16635.957 | AY44: =AX44/P44 -> -0.08901946 | BA44: =P44/$G44 -> 1600 | BB44: =-AC44/$G44 -> -1063.1299 | BC44: =-AD44/$G44 -> -243.26417 | BD44: =-AE44/$G44 -> -15.933629 | BE44: =-AF44/$G44 -> -317.67233 | BF44: =-AG44/$G44 -> -1640 | BG44: =AK44/$G44 -> -40 | BH44: =-AM44/$G44 -> -115.71062 | BI44: =-AN44/$G44 -> -57.692308 | BJ44: =-AO44/$G44 -> -173.40292 | BK44: =-AP44/$G44 -> -35.367059 | BL44: =AQ44/$G44 -> 44.528682 | BM44: =AR44/$G44 -> -204.2413 | BN44: =-AT44/$G44 -> -52.90043 | BO44: =AU44/$G44 -> -257.14173 | BP44: =AW44/$G44 -> 61.810166 | BQ44: =AX44/$G44 -> -142.43114
B45: FEBRERO | C45: MARZO | D45: 169-2026B | E45: 43 | F45: 46091 | G45: 135 | H45: POTA ALAS CONGELADAS | I45: Alas | J45: 1-UP | K45: China | L45: Qingdao | M45: TSUJINO | N45: Jose | O45: 1600 | P45: 216000 | Q45: 1519.9111 | R45: 10812 | S45: =P45-R45 -> 205188 | T45: 4 | U45: ECO MARIN 26010N | V45: LIMG03633900 | W45: ONE | X45: PAITA | Y45: 10006720 | Z45: Inventario final | AA45: =B45&Y45&Z45 -> FEBRERO10006720Inventario final | AB45: =INDEX('Detalle Costos'!$L$5:$L$158,MATCH(Resumen!AA45,'Detalle Costos'!$C$5:$C$158,0))*1000 -> 1640 | AC45: =IFERROR(INDEX('Detalle Costos'!$X$5:$X$158,MATCH(Resumen!AA45,'Detalle Costos'!$C$5:$C$158,0))*AG45,0) -> 143522.53 | AD45: =IFERROR(INDEX('Detalle Costos'!$Z$5:$Z$158,MATCH(Resumen!AA45,'Detalle Costos'!$C$5:$C$158,0))*AG45,0) -> 32840.662 | AE45: =IFERROR(INDEX('Detalle Costos'!$Y$5:$Y$158,MATCH(Resumen!AA45,'Detalle Costos'!$C$5:$C$158,0))*AG45,0) -> 2151.0399 | AF45: =IFERROR(INDEX('Detalle Costos'!$AA$5:$AA$158,MATCH(Resumen!AA45,'Detalle Costos'!$C$5:$C$158,0))*AG45,0) -> 42885.765 | AG45: =AB45*G45 -> 221400 | AK45: =P45-AG45 -> -5400 | AL45: =AK45/P45 -> -0.025 | AM45: =R45 -> 10812 | AN45: =1500/26*G45 -> 7788.4615 | AO45: =SUM(AM45:AN45) -> 18600.462 | AP45: =70656.31/1997.8*G45 -> 4774.5529 | AQ45: =S45*0.03 -> 6155.64 | AR45: =AK45-AO45-AP45+AQ45 -> -22619.374 | AS45: =AR45/P45 -> -0.10471933 | AT45: =105684.48/1997.8*G45 -> 7141.5581 | AU45: =AR45-AT45 -> -29760.933 | AV45: =AU45/P45 -> -0.1377821 | AW45: =123484.35/1997.8*G45 -> 8344.3724 | AX45: =AR45+AW45 -> -14275.002 | AY45: =AX45/P45 -> -0.066087972 | BA45: =P45/$G45 -> 1600 | BB45: =-AC45/$G45 -> -1063.1299 | BC45: =-AD45/$G45 -> -243.26417 | BD45: =-AE45/$G45 -> -15.933629 | BE45: =-AF45/$G45 -> -317.67233 | BF45: =-AG45/$G45 -> -1640 | BG45: =AK45/$G45 -> -40 | BH45: =-AM45/$G45 -> -80.088889 | BI45: =-AN45/$G45 -> -57.692308 | BJ45: =-AO45/$G45 -> -137.7812 | BK45: =-AP45/$G45 -> -35.367059 | BL45: =AQ45/$G45 -> 45.597333 | BM45: =AR45/$G45 -> -167.55092 | BN45: =-AT45/$G45 -> -52.90043 | BO45: =AU45/$G45 -> -220.45135 | BP45: =AW45/$G45 -> 61.810166 | BQ45: =AX45/$G45 -> -105.74076
B46: FEBRERO | C46: MARZO | D46: 170-2026B | E46: 43 | F46: 46092 | G46: 78 | H46: POTA REJOS CONGELADOS | I46: Rejos | J46: 1-2 | K46: España | L46: Vigo | M46: KULALIA | N46: Ramon | O46: 2400 | P46: 187200 | Q46: 2243.0865 | R46: 12239.25 | S46: =P46-R46 -> 174960.75 | T46: 3 | U46: CMA CGM BOLDNESS / 0DVODN1MA | V46: LMM0575562 | W46: CMA CGM | Y46: 10007162 | Z46: Inventario final | AA46: =B46&Y46&Z46 -> FEBRERO10007162Inventario final | AB46: =INDEX('Detalle Costos'!$L$5:$L$158,MATCH(Resumen!AA46,'Detalle Costos'!$C$5:$C$158,0))*1000 -> 1720 | AC46: =IFERROR(INDEX('Detalle Costos'!$X$5:$X$158,MATCH(Resumen!AA46,'Detalle Costos'!$C$5:$C$158,0))*AG46,0) -> 84221.04 | AD46: =IFERROR(INDEX('Detalle Costos'!$Z$5:$Z$158,MATCH(Resumen!AA46,'Detalle Costos'!$C$5:$C$158,0))*AG46,0) -> 24031.801 | AE46: =IFERROR(INDEX('Detalle Costos'!$Y$5:$Y$158,MATCH(Resumen!AA46,'Detalle Costos'!$C$5:$C$158,0))*AG46,0) -> 1251.2102 | AF46: =IFERROR(INDEX('Detalle Costos'!$AA$5:$AA$158,MATCH(Resumen!AA46,'Detalle Costos'!$C$5:$C$158,0))*AG46,0) -> 24655.949 | AG46: =AB46*G46 -> 134160 | AK46: =P46-AG46 -> 53040 | AL46: =AK46/P46 -> 0.28333333 | AM46: =R46 -> 12239.25 | AN46: =1500/26*G46 -> 4500 | AO46: =SUM(AM46:AN46) -> 16739.25 | AP46: =70656.31/1997.8*G46 -> 2758.6306 | AQ46: =S46*0.03 -> 5248.8225 | AR46: =AK46-AO46-AP46+AQ46 -> 38790.942 | AS46: =AR46/P46 -> 0.20721657 | AT46: =105684.48/1997.8*G46 -> 4126.2336 | AU46: =AR46-AT46 -> 34664.708 | AV46: =AU46/P46 -> 0.18517472 | AW46: =123484.35/1997.8*G46 -> 4821.193 | AX46: =AR46+AW46 -> 43612.135 | AY46: =AX46/P46 -> 0.23297081 | BA46: =P46/$G46 -> 2400 | BB46: =-AC46/$G46 -> -1079.7569 | BC46: =-AD46/$G46 -> -308.10001 | BD46: =-AE46/$G46 -> -16.041156 | BE46: =-AF46/$G46 -> -316.10191 | BF46: =-AG46/$G46 -> -1720 | BG46: =AK46/$G46 -> 680 | BH46: =-AM46/$G46 -> -156.91346 | BI46: =-AN46/$G46 -> -57.692308 | BJ46: =-AO46/$G46 -> -214.60577 | BK46: =-AP46/$G46 -> -35.367059 | BL46: =AQ46/$G46 -> 67.292596 | BM46: =AR46/$G46 -> 497.31977 | BN46: =-AT46/$G46 -> -52.90043 | BO46: =AU46/$G46 -> 444.41934 | BP46: =AW46/$G46 -> 61.810166 | BQ46: =AX46/$G46 -> 559.12993
B47: FEBRERO | C47: MARZO | D47: 171-2026 | E47: 44 | F47: 46085 | G47: 135 | H47: POTA FILETE CONGELADO | I47: Filete | J47: 2-4 AA | K47: China | L47: Shidao | M47: Pesciro Asia International LTD. | O47: 1450 | P47: 195750 | Q47: 1338.7778 | R47: 15015 | S47: =P47-R47 -> 180735 | T47: 5 | U47: ECO SIROCCO 26009N | V47: LIMG03093900 | W47: ONE | X47: PAITA | Y47: 10005721 | Z47: Inventario final | AA47: =B47&Y47&Z47 -> FEBRERO10005721Inventario final | AB47: =INDEX('Detalle Costos'!$L$5:$L$158,MATCH(Resumen!AA47,'Detalle Costos'!$C$5:$C$158,0))*1000 -> 1740 | AC47: =IFERROR(INDEX('Detalle Costos'!$X$5:$X$158,MATCH(Resumen!AA47,'Detalle Costos'!$C$5:$C$158,0))*AG47,0) -> 142545.77 | AD47: =IFERROR(INDEX('Detalle Costos'!$Z$5:$Z$158,MATCH(Resumen!AA47,'Detalle Costos'!$C$5:$C$158,0))*AG47,0) -> 47091.788 | AE47: =IFERROR(INDEX('Detalle Costos'!$Y$5:$Y$158,MATCH(Resumen!AA47,'Detalle Costos'!$C$5:$C$158,0))*AG47,0) -> 2505.1663 | AF47: =IFERROR(INDEX('Detalle Costos'!$AA$5:$AA$158,MATCH(Resumen!AA47,'Detalle Costos'!$C$5:$C$158,0))*AG47,0) -> 42757.278 | AG47: =AB47*G47 -> 234900 | AK47: =P47-AG47 -> -39150 | AL47: =AK47/P47 -> -0.2 | AM47: =R47 -> 15015 | AN47: =1500/26*G47 -> 7788.4615 | AO47: =SUM(AM47:AN47) -> 22803.462 | AP47: =70656.31/1997.8*G47 -> 4774.5529 | AQ47: =S47*0.03 -> 5422.05 | AR47: =AK47-AO47-AP47+AQ47 -> -61305.964 | AS47: =AR47/P47 -> -0.313185 | AT47: =105684.48/1997.8*G47 -> 7141.5581 | AU47: =AR47-AT47 -> -68447.523 | AV47: =AU47/P47 -> -0.34966806 | AW47: =123484.35/1997.8*G47 -> 8344.3724 | AX47: =AR47+AW47 -> -52961.592 | AY47: =AX47/P47 -> -0.2705573 | BA47: =P47/$G47 -> 1450 | BB47: =-AC47/$G47 -> -1055.8946 | BC47: =-AD47/$G47 -> -348.82806 | BD47: =-AE47/$G47 -> -18.556788 | BE47: =-AF47/$G47 -> -316.72057 | BF47: =-AG47/$G47 -> -1740 | BG47: =AK47/$G47 -> -290 | BH47: =-AM47/$G47 -> -111.22222 | BI47: =-AN47/$G47 -> -57.692308 | BJ47: =-AO47/$G47 -> -168.91453 | BK47: =-AP47/$G47 -> -35.367059 | BL47: =AQ47/$G47 -> 40.163333 | BM47: =AR47/$G47 -> -454.11826 | BN47: =-AT47/$G47 -> -52.90043 | BO47: =AU47/$G47 -> -507.01869 | BP47: =AW47/$G47 -> 61.810166 | BQ47: =AX47/$G47 -> -392.30809
B48: FEBRERO | C48: MARZO | D48: 172-2026A | E48: 47 | F48: 46092 | G48: 150 | H48: POTA REJOS CONGELADOS | I48: Rejos | J48: 1-2 KG | K48: España | L48: Vigo | M48: KULALIA | N48: Ramon | O48: 2300 | P48: 345000 | Q48: 2139.1 | R48: 24135 | S48: =P48-R48 -> 320865 | T48: 6 | U48: CMA CGM BOLDNESS / 0DVODN1MA | V48: LMM0575536 | W48: CMA CGM | Y48: 10007162 | Z48: Inventario final | AA48: =B48&Y48&Z48 -> FEBRERO10007162Inventario final | AB48: =INDEX('Detalle Costos'!$L$5:$L$158,MATCH(Resumen!AA48,'Detalle Costos'!$C$5:$C$158,0))*1000 -> 1720 | AC48: =IFERROR(INDEX('Detalle Costos'!$X$5:$X$158,MATCH(Resumen!AA48,'Detalle Costos'!$C$5:$C$158,0))*AG48,0) -> 161963.54 | AD48: =IFERROR(INDEX('Detalle Costos'!$Z$5:$Z$158,MATCH(Resumen!AA48,'Detalle Costos'!$C$5:$C$158,0))*AG48,0) -> 46215.001 | AE48: =IFERROR(INDEX('Detalle Costos'!$Y$5:$Y$158,MATCH(Resumen!AA48,'Detalle Costos'!$C$5:$C$158,0))*AG48,0) -> 2406.1734 | AF48: =IFERROR(INDEX('Detalle Costos'!$AA$5:$AA$158,MATCH(Resumen!AA48,'Detalle Costos'!$C$5:$C$158,0))*AG48,0) -> 47415.286 | AG48: =AB48*G48 -> 258000 | AK48: =P48-AG48 -> 87000 | AL48: =AK48/P48 -> 0.25217391 | AM48: =R48 -> 24135 | AN48: =1500/26*G48 -> 8653.8462 | AO48: =SUM(AM48:AN48) -> 32788.846 | AP48: =70656.31/1997.8*G48 -> 5305.0588 | AQ48: =S48*0.03 -> 9625.95 | AR48: =AK48-AO48-AP48+AQ48 -> 58532.045 | AS48: =AR48/P48 -> 0.1696581 | AT48: =105684.48/1997.8*G48 -> 7935.0646 | AU48: =AR48-AT48 -> 50596.98 | AV48: =AU48/P48 -> 0.14665791 | AW48: =123484.35/1997.8*G48 -> 9271.5249 | AX48: =AR48+AW48 -> 67803.57 | AY48: =AX48/P48 -> 0.19653209 | BA48: =P48/$G48 -> 2300 | BB48: =-AC48/$G48 -> -1079.7569 | BC48: =-AD48/$G48 -> -308.10001 | BD48: =-AE48/$G48 -> -16.041156 | BE48: =-AF48/$G48 -> -316.10191 | BF48: =-AG48/$G48 -> -1720 | BG48: =AK48/$G48 -> 580 | BH48: =-AM48/$G48 -> -160.9 | BI48: =-AN48/$G48 -> -57.692308 | BJ48: =-AO48/$G48 -> -218.59231 | BK48: =-AP48/$G48 -> -35.367059 | BL48: =AQ48/$G48 -> 64.173 | BM48: =AR48/$G48 -> 390.21363 | BN48: =-AT48/$G48 -> -52.90043 | BO48: =AU48/$G48 -> 337.3132 | BP48: =AW48/$G48 -> 61.810166 | BQ48: =AX48/$G48 -> 452.0238
B49: FEBRERO | C49: MARZO | D49: 172-2026A | E49: 47 | F49: 46092 | G49: 25 | H49: POTA REPRODUCTORES | I49: Rejos | K49: España | L49: Vigo | M49: KULALIA | N49: Ramon | O49: 2500 | P49: 62500 | Q49: 2336.72 | R49: 4082 | S49: =P49-R49 -> 58418 | T49: 1 | U49: CMA CGM BOLDNESS / 0DVODN1MA | V49: LMM0575536 | W49: CMA CGM | Y49: 10007567 | Z49: Inventario final | AA49: =B49&Y49&Z49 -> FEBRERO10007567Inventario final | AB49: =INDEX('Detalle Costos'!$L$5:$L$158,MATCH(Resumen!AA49,'Detalle Costos'!$C$5:$C$158,0))*1000 -> 1700 | AC49: =IFERROR(INDEX('Detalle Costos'!$X$5:$X$158,MATCH(Resumen!AA49,'Detalle Costos'!$C$5:$C$158,0))*AG49,0) -> 26806.784 | AD49: =IFERROR(INDEX('Detalle Costos'!$Z$5:$Z$158,MATCH(Resumen!AA49,'Detalle Costos'!$C$5:$C$158,0))*AG49,0) -> 7351.4498 | AE49: =IFERROR(INDEX('Detalle Costos'!$Y$5:$Y$158,MATCH(Resumen!AA49,'Detalle Costos'!$C$5:$C$158,0))*AG49,0) -> 459.62755 | AF49: =IFERROR(INDEX('Detalle Costos'!$AA$5:$AA$158,MATCH(Resumen!AA49,'Detalle Costos'!$C$5:$C$158,0))*AG49,0) -> 7882.1391 | AG49: =AB49*G49 -> 42500 | AK49: =P49-AG49 -> 20000 | AL49: =AK49/P49 -> 0.32 | AM49: =R49 -> 4082 | AN49: =1500/26*G49 -> 1442.3077 | AO49: =SUM(AM49:AN49) -> 5524.3077 | AP49: =70656.31/1997.8*G49 -> 884.17647 | AQ49: =S49*0.03 -> 1752.54 | AR49: =AK49-AO49-AP49+AQ49 -> 15344.056 | AS49: =AR49/P49 -> 0.24550489 | AT49: =105684.48/1997.8*G49 -> 1322.5108 | AU49: =AR49-AT49 -> 14021.545 | AV49: =AU49/P49 -> 0.22434472 | AW49: =123484.35/1997.8*G49 -> 1545.2542 | AX49: =AR49+AW49 -> 16889.31 | AY49: =AX49/P49 -> 0.27022896 | BA49: =P49/$G49 -> 2500 | BB49: =-AC49/$G49 -> -1072.2713 | BC49: =-AD49/$G49 -> -294.05799 | BD49: =-AE49/$G49 -> -18.385102 | BE49: =-AF49/$G49 -> -315.28557 | BF49: =-AG49/$G49 -> -1700 | BG49: =AK49/$G49 -> 800 | BH49: =-AM49/$G49 -> -163.28 | BI49: =-AN49/$G49 -> -57.692308 | BJ49: =-AO49/$G49 -> -220.97231 | BK49: =-AP49/$G49 -> -35.367059 | BL49: =AQ49/$G49 -> 70.1016 | BM49: =AR49/$G49 -> 613.76223 | BN49: =-AT49/$G49 -> -52.90043 | BO49: =AU49/$G49 -> 560.8618 | BP49: =AW49/$G49 -> 61.810166 | BQ49: =AX49/$G49 -> 675.5724
B50: FEBRERO | C50: MARZO | D50: 172-2026B | E50: 47 | F50: 46108 | G50: 54 | H50: POTA ALAS COCIDAS | I50: Alas | J50: 0.3 - UP | K50: China | L50: Qingdao | M50: KULALIA | N50: Ramon | O50: 3350 | P50: 180900 | Q50: 3242.5926 | R50: 5800 | S50: =P50-R50 -> 175100 | T50: 2 | U50: ECO SIROCCO 26013S | V50: 6446512380 | W50: COSCO | X50: PAITA | Y50: 10009331 | Z50: Inventario final | AA50: =B50&Y50&Z50 -> FEBRERO10009331Inventario final | AB50: =INDEX('Detalle Costos'!$L$5:$L$158,MATCH(Resumen!AA50,'Detalle Costos'!$C$5:$C$158,0))*1000 -> 1810 | AC50: =IFERROR(INDEX('Detalle Costos'!$X$5:$X$158,MATCH(Resumen!AA50,'Detalle Costos'!$C$5:$C$158,0))*AG50,0) -> 56742.199 | AD50: =IFERROR(INDEX('Detalle Costos'!$Z$5:$Z$158,MATCH(Resumen!AA50,'Detalle Costos'!$C$5:$C$158,0))*AG50,0) -> 22722.69 | AE50: =IFERROR(INDEX('Detalle Costos'!$Y$5:$Y$158,MATCH(Resumen!AA50,'Detalle Costos'!$C$5:$C$158,0))*AG50,0) -> 1023.6041 | AF50: =IFERROR(INDEX('Detalle Costos'!$AA$5:$AA$158,MATCH(Resumen!AA50,'Detalle Costos'!$C$5:$C$158,0))*AG50,0) -> 17251.508 | AG50: =AB50*G50 -> 97740 | AK50: =P50-AG50 -> 83160 | AL50: =AK50/P50 -> 0.45970149 | AM50: =R50 -> 5800 | AN50: =1500/26*G50 -> 3115.3846 | AO50: =SUM(AM50:AN50) -> 8915.3846 | AP50: =70656.31/1997.8*G50 -> 1909.8212 | AQ50: =S50*0.03 -> 5253 | AR50: =AK50-AO50-AP50+AQ50 -> 77587.794 | AS50: =AR50/P50 -> 0.42889881 | AT50: =105684.48/1997.8*G50 -> 2856.6232 | AU50: =AR50-AT50 -> 74731.171 | AV50: =AU50/P50 -> 0.41310763 | AW50: =123484.35/1997.8*G50 -> 3337.749 | AX50: =AR50+AW50 -> 80925.543 | AY50: =AX50/P50 -> 0.4473496 | BA50: =P50/$G50 -> 3350 | BB50: =-AC50/$G50 -> -1050.7815 | BC50: =-AD50/$G50 -> -420.79055 | BD50: =-AE50/$G50 -> -18.955631 | BE50: =-AF50/$G50 -> -319.47236 | BF50: =-AG50/$G50 -> -1810 | BG50: =AK50/$G50 -> 1540 | BH50: =-AM50/$G50 -> -107.40741 | BI50: =-AN50/$G50 -> -57.692308 | BJ50: =-AO50/$G50 -> -165.09972 | BK50: =-AP50/$G50 -> -35.367059 | BL50: =AQ50/$G50 -> 97.277778 | BM50: =AR50/$G50 -> 1436.811 | BN50: =-AT50/$G50 -> -52.90043 | BO50: =AU50/$G50 -> 1383.9106 | BP50: =AW50/$G50 -> 61.810166 | BQ50: =AX50/$G50 -> 1498.6212
B51: FEBRERO | C51: MARZO | D51: 174-2026 | E51: 49 | F51: 46091 | G51: 108 | H51: POTA FILETE CONGELADO | I51: Filete | J51: 2-4 AA | K51: China | L51: shidao | M51: Pesciro Asia International LTD. | O51: 1450 | P51: 156600 | Q51: 1338.7778 | R51: 12012 | S51: =P51-R51 -> 144588 | T51: 4 | U51: ECO MARIN 26010N | V51: LIMG03595900 | Y51: 10005721 | Z51: Inventario final | AA51: =B51&Y51&Z51 -> FEBRERO10005721Inventario final | AB51: =INDEX('Detalle Costos'!$L$5:$L$158,MATCH(Resumen!AA51,'Detalle Costos'!$C$5:$C$158,0))*1000 -> 1740 | AC51: =IFERROR(INDEX('Detalle Costos'!$X$5:$X$158,MATCH(Resumen!AA51,'Detalle Costos'!$C$5:$C$158,0))*AG51,0) -> 114036.61 | AD51: =IFERROR(INDEX('Detalle Costos'!$Z$5:$Z$158,MATCH(Resumen!AA51,'Detalle Costos'!$C$5:$C$158,0))*AG51,0) -> 37673.431 | AE51: =IFERROR(INDEX('Detalle Costos'!$Y$5:$Y$158,MATCH(Resumen!AA51,'Detalle Costos'!$C$5:$C$158,0))*AG51,0) -> 2004.1331 | AF51: =IFERROR(INDEX('Detalle Costos'!$AA$5:$AA$158,MATCH(Resumen!AA51,'Detalle Costos'!$C$5:$C$158,0))*AG51,0) -> 34205.822 | AG51: =AB51*G51 -> 187920 | AK51: =P51-AG51 -> -31320 | AL51: =AK51/P51 -> -0.2 | AM51: =R51 -> 12012 | AN51: =1500/26*G51 -> 6230.7692 | AO51: =SUM(AM51:AN51) -> 18242.769 | AP51: =70656.31/1997.8*G51 -> 3819.6423 | AQ51: =S51*0.03 -> 4337.64 | AR51: =AK51-AO51-AP51+AQ51 -> -49044.772 | AS51: =AR51/P51 -> -0.313185 | AT51: =105684.48/1997.8*G51 -> 5713.2465 | AU51: =AR51-AT51 -> -54758.018 | AV51: =AU51/P51 -> -0.34966806 | AW51: =123484.35/1997.8*G51 -> 6675.4979 | AX51: =AR51+AW51 -> -42369.274 | AY51: =AX51/P51 -> -0.2705573 | BA51: =P51/$G51 -> 1450 | BB51: =-AC51/$G51 -> -1055.8946 | BC51: =-AD51/$G51 -> -348.82806 | BD51: =-AE51/$G51 -> -18.556788 | BE51: =-AF51/$G51 -> -316.72057 | BF51: =-AG51/$G51 -> -1740 | BG51: =AK51/$G51 -> -290 | BH51: =-AM51/$G51 -> -111.22222 | BI51: =-AN51/$G51 -> -57.692308 | BJ51: =-AO51/$G51 -> -168.91453 | BK51: =-AP51/$G51 -> -35.367059 | BL51: =AQ51/$G51 -> 40.163333 | BM51: =AR51/$G51 -> -454.11826 | BN51: =-AT51/$G51 -> -52.90043 | BO51: =AU51/$G51 -> -507.01869 | BP51: =AW51/$G51 -> 61.810166 | BQ51: =AX51/$G51 -> -392.30809
B52: FEBRERO | C52: MARZO | D52: 175-2026 | E52: 49 | F52: 46099 | G52: 26 | H52: POTA FILETE CONGELADO | I52: Filete | J52: 2-4 AA | K52: Klaipeda | L52: Lituania | M52: Pesciro SL | O52: 1500 | P52: 39000 | Q52: 1230.9615 | R52: 6995 | S52: =P52-R52 -> 32005 | T52: 1 | U52: CMA CGM VOLTAIRE / 0DVOFN1MA | V52: LMM0575667 | W52: 1 | X52: CMA CGM | Y52: 10005721 | Z52: Inventario final | AA52: =B52&Y52&Z52 -> FEBRERO10005721Inventario final | AB52: =INDEX('Detalle Costos'!$L$5:$L$158,MATCH(Resumen!AA52,'Detalle Costos'!$C$5:$C$158,0))*1000 -> 1740 | AC52: =IFERROR(INDEX('Detalle Costos'!$X$5:$X$158,MATCH(Resumen!AA52,'Detalle Costos'!$C$5:$C$158,0))*AG52,0) -> 27453.259 | AD52: =IFERROR(INDEX('Detalle Costos'!$Z$5:$Z$158,MATCH(Resumen!AA52,'Detalle Costos'!$C$5:$C$158,0))*AG52,0) -> 9069.5296 | AE52: =IFERROR(INDEX('Detalle Costos'!$Y$5:$Y$158,MATCH(Resumen!AA52,'Detalle Costos'!$C$5:$C$158,0))*AG52,0) -> 482.47648 | AF52: =IFERROR(INDEX('Detalle Costos'!$AA$5:$AA$158,MATCH(Resumen!AA52,'Detalle Costos'!$C$5:$C$158,0))*AG52,0) -> 8234.7349 | AG52: =AB52*G52 -> 45240 | AK52: =P52-AG52 -> -6240 | AL52: =AK52/P52 -> -0.16 | AM52: =R52 -> 6995 | AN52: =1500/26*G52 -> 1500 | AO52: =SUM(AM52:AN52) -> 8495 | AP52: =70656.31/1997.8*G52 -> 919.54353 | AQ52: =S52*0.03 -> 960.15 | AR52: =AK52-AO52-AP52+AQ52 -> -14694.394 | AS52: =AR52/P52 -> -0.37677932 | AT52: =105684.48/1997.8*G52 -> 1375.4112 | AU52: =AR52-AT52 -> -16069.805 | AV52: =AU52/P52 -> -0.41204627 | AW52: =123484.35/1997.8*G52 -> 1607.0643 | AX52: =AR52+AW52 -> -13087.329 | AY52: =AX52/P52 -> -0.33557254 | BA52: =P52/$G52 -> 1500 | BB52: =-AC52/$G52 -> -1055.8946 | BC52: =-AD52/$G52 -> -348.82806 | BD52: =-AE52/$G52 -> -18.556788 | BE52: =-AF52/$G52 -> -316.72057 | BF52: =-AG52/$G52 -> -1740 | BG52: =AK52/$G52 -> -240 | BH52: =-AM52/$G52 -> -269.03846 | BI52: =-AN52/$G52 -> -57.692308 | BJ52: =-AO52/$G52 -> -326.73077 | BK52: =-AP52/$G52 -> -35.367059 | BL52: =AQ52/$G52 -> 36.928846 | BM52: =AR52/$G52 -> -565.16898 | BN52: =-AT52/$G52 -> -52.90043 | BO52: =AU52/$G52 -> -618.06941 | BP52: =AW52/$G52 -> 61.810166 | BQ52: =AX52/$G52 -> -503.35882
B53: FEBRERO | C53: MARZO | D53: 176-2026A | E53: 49 | F53: 46104 | G53: 54 | H53: POTA ALAS CONGELADAS | I53: Alas | J53: 1-up | K53: China | L53: Qingdao | M53: TSUJINO | N53: Jose | O53: 1600 | P53: 86400 | Q53: 1492.5926 | R53: 5800 | S53: =P53-R53 -> 80600 | T53: 2 | U53: ECO SIROCCO 26011S | V53: 6446527810 | W53: COSCO | X53: PAITA | Y53: 10006720 | Z53: Inventario final | AA53: =B53&Y53&Z53 -> FEBRERO10006720Inventario final | AB53: =INDEX('Detalle Costos'!$L$5:$L$158,MATCH(Resumen!AA53,'Detalle Costos'!$C$5:$C$158,0))*1000 -> 1640 | AC53: =IFERROR(INDEX('Detalle Costos'!$X$5:$X$158,MATCH(Resumen!AA53,'Detalle Costos'!$C$5:$C$158,0))*AG53,0) -> 57409.013 | AD53: =IFERROR(INDEX('Detalle Costos'!$Z$5:$Z$158,MATCH(Resumen!AA53,'Detalle Costos'!$C$5:$C$158,0))*AG53,0) -> 13136.265 | AE53: =IFERROR(INDEX('Detalle Costos'!$Y$5:$Y$158,MATCH(Resumen!AA53,'Detalle Costos'!$C$5:$C$158,0))*AG53,0) -> 860.41596 | AF53: =IFERROR(INDEX('Detalle Costos'!$AA$5:$AA$158,MATCH(Resumen!AA53,'Detalle Costos'!$C$5:$C$158,0))*AG53,0) -> 17154.306 | AG53: =AB53*G53 -> 88560 | AK53: =P53-AG53 -> -2160 | AL53: =AK53/P53 -> -0.025 | AM53: =R53 -> 5800 | AN53: =1500/26*G53 -> 3115.3846 | AO53: =SUM(AM53:AN53) -> 8915.3846 | AP53: =70656.31/1997.8*G53 -> 1909.8212 | AQ53: =S53*0.03 -> 2418 | AR53: =AK53-AO53-AP53+AQ53 -> -10567.206 | AS53: =AR53/P53 -> -0.12230562 | AT53: =105684.48/1997.8*G53 -> 2856.6232 | AU53: =AR53-AT53 -> -13423.829 | AV53: =AU53/P53 -> -0.15536839 | AW53: =123484.35/1997.8*G53 -> 3337.749 | AX53: =AR53+AW53 -> -7229.4568 | AY53: =AX53/P53 -> -0.083674269 | BA53: =P53/$G53 -> 1600 | BB53: =-AC53/$G53 -> -1063.1299 | BC53: =-AD53/$G53 -> -243.26417 | BD53: =-AE53/$G53 -> -15.933629 | BE53: =-AF53/$G53 -> -317.67233 | BF53: =-AG53/$G53 -> -1640 | BG53: =AK53/$G53 -> -40 | BH53: =-AM53/$G53 -> -107.40741 | BI53: =-AN53/$G53 -> -57.692308 | BJ53: =-AO53/$G53 -> -165.09972 | BK53: =-AP53/$G53 -> -35.367059 | BL53: =AQ53/$G53 -> 44.777778 | BM53: =AR53/$G53 -> -195.689 | BN53: =-AT53/$G53 -> -52.90043 | BO53: =AU53/$G53 -> -248.58943 | BP53: =AW53/$G53 -> 61.810166 | BQ53: =AX53/$G53 -> -133.87883
B54: FEBRERO | C54: MARZO | D54: 176-2026B | E54: 49 | F54: 46108 | G54: 81 | H54: POTA ALAS CONGELADAS | I54: Alas | J54: 1-up | K54: China | L54: Qingdao | M54: TSUJINO | N54: Jose | O54: 1600 | P54: 129600 | Q54: 1499.5185 | R54: 8139 | S54: =P54-R54 -> 121461 | T54: 3 | U54: ECO SIROCCO 26013S | V54: LIMG04326900 | W54: ONE LINE | X54: PAITA | Y54: 10006720 | Z54: Inventario final | AA54: =B54&Y54&Z54 -> FEBRERO10006720Inventario final | AB54: =INDEX('Detalle Costos'!$L$5:$L$158,MATCH(Resumen!AA54,'Detalle Costos'!$C$5:$C$158,0))*1000 -> 1640 | AC54: =IFERROR(INDEX('Detalle Costos'!$X$5:$X$158,MATCH(Resumen!AA54,'Detalle Costos'!$C$5:$C$158,0))*AG54,0) -> 86113.52 | AD54: =IFERROR(INDEX('Detalle Costos'!$Z$5:$Z$158,MATCH(Resumen!AA54,'Detalle Costos'!$C$5:$C$158,0))*AG54,0) -> 19704.397 | AE54: =IFERROR(INDEX('Detalle Costos'!$Y$5:$Y$158,MATCH(Resumen!AA54,'Detalle Costos'!$C$5:$C$158,0))*AG54,0) -> 1290.6239 | AF54: =IFERROR(INDEX('Detalle Costos'!$AA$5:$AA$158,MATCH(Resumen!AA54,'Detalle Costos'!$C$5:$C$158,0))*AG54,0) -> 25731.459 | AG54: =AB54*G54 -> 132840 | AK54: =P54-AG54 -> -3240 | AL54: =AK54/P54 -> -0.025 | AM54: =R54 -> 8139 | AN54: =1500/26*G54 -> 4673.0769 | AO54: =SUM(AM54:AN54) -> 12812.077 | AP54: =70656.31/1997.8*G54 -> 2864.7318 | AQ54: =S54*0.03 -> 3643.83 | AR54: =AK54-AO54-AP54+AQ54 -> -15272.979 | AS54: =AR54/P54 -> -0.11784706 | AT54: =105684.48/1997.8*G54 -> 4284.9349 | AU54: =AR54-AT54 -> -19557.914 | AV54: =AU54/P54 -> -0.15090983 | AW54: =123484.35/1997.8*G54 -> 5006.6235 | AX54: =AR54+AW54 -> -10266.355 | AY54: =AX54/P54 -> -0.079215704 | BA54: =P54/$G54 -> 1600 | BB54: =-AC54/$G54 -> -1063.1299 | BC54: =-AD54/$G54 -> -243.26417 | BD54: =-AE54/$G54 -> -15.933629 | BE54: =-AF54/$G54 -> -317.67233 | BF54: =-AG54/$G54 -> -1640 | BG54: =AK54/$G54 -> -40 | BH54: =-AM54/$G54 -> -100.48148 | BI54: =-AN54/$G54 -> -57.692308 | BJ54: =-AO54/$G54 -> -158.17379 | BK54: =-AP54/$G54 -> -35.367059 | BL54: =AQ54/$G54 -> 44.985556 | BM54: =AR54/$G54 -> -188.55529 | BN54: =-AT54/$G54 -> -52.90043 | BO54: =AU54/$G54 -> -241.45572 | BP54: =AW54/$G54 -> 61.810166 | BQ54: =AX54/$G54 -> -126.74513
B55: FEBRERO | C55: MARZO | D55: 177-2026A | E55: 50 | F55: 46108 | G55: 48 | H55: POTA ALAS CONGELADAS | I55: Alas | J55: 1-up | K55: Korea | L55: Busan | M55: TSUJINO | N55: Jose | O55: 1600 | P55: 76800 | Q55: 1486.9583 | R55: 5426 | S55: =P55-R55 -> 71374 | T55: 2 | U55: ECO SIROCCO 26013S | V55: LIMG04588500 | W55: ONE LINE | X55: PAITA | Y55: 10006720 | Z55: Inventario final | AA55: =B55&Y55&Z55 -> FEBRERO10006720Inventario final | AB55: =INDEX('Detalle Costos'!$L$5:$L$158,MATCH(Resumen!AA55,'Detalle Costos'!$C$5:$C$158,0))*1000 -> 1640 | AC55: =IFERROR(INDEX('Detalle Costos'!$X$5:$X$158,MATCH(Resumen!AA55,'Detalle Costos'!$C$5:$C$158,0))*AG55,0) -> 51030.234 | AD55: =IFERROR(INDEX('Detalle Costos'!$Z$5:$Z$158,MATCH(Resumen!AA55,'Detalle Costos'!$C$5:$C$158,0))*AG55,0) -> 11676.68 | AE55: =IFERROR(INDEX('Detalle Costos'!$Y$5:$Y$158,MATCH(Resumen!AA55,'Detalle Costos'!$C$5:$C$158,0))*AG55,0) -> 764.81419 | AF55: =IFERROR(INDEX('Detalle Costos'!$AA$5:$AA$158,MATCH(Resumen!AA55,'Detalle Costos'!$C$5:$C$158,0))*AG55,0) -> 15248.272 | AG55: =AB55*G55 -> 78720 | AK55: =P55-AG55 -> -1920 | AL55: =AK55/P55 -> -0.025 | AM55: =R55 -> 5426 | AN55: =1500/26*G55 -> 2769.2308 | AO55: =SUM(AM55:AN55) -> 8195.2308 | AP55: =70656.31/1997.8*G55 -> 1697.6188 | AQ55: =S55*0.03 -> 2141.22 | AR55: =AK55-AO55-AP55+AQ55 -> -9671.6296 | AS55: =AR55/P55 -> -0.12593268 | AT55: =105684.48/1997.8*G55 -> 2539.2207 | AU55: =AR55-AT55 -> -12210.85 | AV55: =AU55/P55 -> -0.15899545 | AW55: =123484.35/1997.8*G55 -> 2966.888 | AX55: =AR55+AW55 -> -6704.7416 | AY55: =AX55/P55 -> -0.087301323 | BA55: =P55/$G55 -> 1600 | BB55: =-AC55/$G55 -> -1063.1299 | BC55: =-AD55/$G55 -> -243.26417 | BD55: =-AE55/$G55 -> -15.933629 | BE55: =-AF55/$G55 -> -317.67233 | BF55: =-AG55/$G55 -> -1640 | BG55: =AK55/$G55 -> -40 | BH55: =-AM55/$G55 -> -113.04167 | BI55: =-AN55/$G55 -> -57.692308 | BJ55: =-AO55/$G55 -> -170.73397 | BK55: =-AP55/$G55 -> -35.367059 | BL55: =AQ55/$G55 -> 44.60875 | BM55: =AR55/$G55 -> -201.49228 | BN55: =-AT55/$G55 -> -52.90043 | BO55: =AU55/$G55 -> -254.39271 | BP55: =AW55/$G55 -> 61.810166 | BQ55: =AX55/$G55 -> -139.68212
B56: FEBRERO | C56: MARZO | D56: 179-2026A | E56: 54 | F56: 46101 | G56: 24 | H56: POTA NUCAS | I56: Nucas | J56: 500-up | K56: Tailandia | L56: Laem chabang | M56: DAIRECK S.A. | N56: ACER FOOD | O56: 1100 | P56: 26400 | Q56: 966.54167 | R56: 3203 | S56: =P56-R56 -> 23197 | T56: 1 | U56: ECO MARIN 26012N | V56: LIMG03918800 | W56: ONE LINE | X56: PAITA | Y56: 10005779 | Z56: Inventario final | AA56: =B56&Y56&Z56 -> FEBRERO10005779Inventario final | AB56: =INDEX('Detalle Costos'!$L$5:$L$158,MATCH(Resumen!AA56,'Detalle Costos'!$C$5:$C$158,0))*1000 -> 1860 | AC56: =IFERROR(INDEX('Detalle Costos'!$X$5:$X$158,MATCH(Resumen!AA56,'Detalle Costos'!$C$5:$C$158,0))*AG56,0) -> 27171.949 | AD56: =IFERROR(INDEX('Detalle Costos'!$Z$5:$Z$158,MATCH(Resumen!AA56,'Detalle Costos'!$C$5:$C$158,0))*AG56,0) -> 9828.4919 | AE56: =IFERROR(INDEX('Detalle Costos'!$Y$5:$Y$158,MATCH(Resumen!AA56,'Detalle Costos'!$C$5:$C$158,0))*AG56,0) -> 325.6304 | AF56: =IFERROR(INDEX('Detalle Costos'!$AA$5:$AA$158,MATCH(Resumen!AA56,'Detalle Costos'!$C$5:$C$158,0))*AG56,0) -> 7313.9286 | AG56: =AB56*G56 -> 44640 | AK56: =P56-AG56 -> -18240 | AL56: =AK56/P56 -> -0.69090909 | AM56: =R56 -> 3203 | AN56: =1500/26*G56 -> 1384.6154 | AO56: =SUM(AM56:AN56) -> 4587.6154 | AP56: =70656.31/1997.8*G56 -> 848.80941 | AQ56: =S56*0.03 -> 695.91 | AR56: =AK56-AO56-AP56+AQ56 -> -22980.515 | AS56: =AR56/P56 -> -0.87047405 | AT56: =105684.48/1997.8*G56 -> 1269.6103 | AU56: =AR56-AT56 -> -24250.125 | AV56: =AU56/P56 -> -0.91856535 | AW56: =123484.35/1997.8*G56 -> 1483.444 | AX56: =AR56+AW56 -> -21497.071 | AY56: =AX56/P56 -> -0.81428299 | BA56: =P56/$G56 -> 1100 | BB56: =-AC56/$G56 -> -1132.1645 | BC56: =-AD56/$G56 -> -409.5205 | BD56: =-AE56/$G56 -> -13.567933 | BE56: =-AF56/$G56 -> -304.74703 | BF56: =-AG56/$G56 -> -1860 | BG56: =AK56/$G56 -> -760 | BH56: =-AM56/$G56 -> -133.45833 | BI56: =-AN56/$G56 -> -57.692308 | BJ56: =-AO56/$G56 -> -191.15064 | BK56: =-AP56/$G56 -> -35.367059 | BL56: =AQ56/$G56 -> 28.99625 | BM56: =AR56/$G56 -> -957.52145 | BN56: =-AT56/$G56 -> -52.90043 | BO56: =AU56/$G56 -> -1010.4219 | BP56: =AW56/$G56 -> 61.810166 | BQ56: =AX56/$G56 -> -895.71128
B57: FEBRERO | C57: MARZO | D57: 179-2026B1 | E57: 54 | F57: 46101 | G57: 24 | H57: POTA NUCAS | I57: Nucas | J57: 500-up | K57: Tailandia | L57: Lat Krabang | M57: DAIRECK S.A. | N57: Julieta | O57: 1100 | P57: 26400 | Q57: 953.625 | R57: 3513 | S57: =P57-R57 -> 22887 | T57: 1 | U57: ECO MARIN 26012N | V57: LIMG03924500 | W57: ONE LINE | X57: PAITA | Y57: 10005779 | Z57: Inventario final | AA57: =B57&Y57&Z57 -> FEBRERO10005779Inventario final | AB57: =INDEX('Detalle Costos'!$L$5:$L$158,MATCH(Resumen!AA57,'Detalle Costos'!$C$5:$C$158,0))*1000 -> 1860 | AC57: =IFERROR(INDEX('Detalle Costos'!$X$5:$X$158,MATCH(Resumen!AA57,'Detalle Costos'!$C$5:$C$158,0))*AG57,0) -> 27171.949 | AD57: =IFERROR(INDEX('Detalle Costos'!$Z$5:$Z$158,MATCH(Resumen!AA57,'Detalle Costos'!$C$5:$C$158,0))*AG57,0) -> 9828.4919 | AE57: =IFERROR(INDEX('Detalle Costos'!$Y$5:$Y$158,MATCH(Resumen!AA57,'Detalle Costos'!$C$5:$C$158,0))*AG57,0) -> 325.6304 | AF57: =IFERROR(INDEX('Detalle Costos'!$AA$5:$AA$158,MATCH(Resumen!AA57,'Detalle Costos'!$C$5:$C$158,0))*AG57,0) -> 7313.9286 | AG57: =AB57*G57 -> 44640 | AK57: =P57-AG57 -> -18240 | AL57: =AK57/P57 -> -0.69090909 | AM57: =R57 -> 3513 | AN57: =1500/26*G57 -> 1384.6154 | AO57: =SUM(AM57:AN57) -> 4897.6154 | AP57: =70656.31/1997.8*G57 -> 848.80941 | AQ57: =S57*0.03 -> 686.61 | AR57: =AK57-AO57-AP57+AQ57 -> -23299.815 | AS57: =AR57/P57 -> -0.88256874 | AT57: =105684.48/1997.8*G57 -> 1269.6103 | AU57: =AR57-AT57 -> -24569.425 | AV57: =AU57/P57 -> -0.93066004 | AW57: =123484.35/1997.8*G57 -> 1483.444 | AX57: =AR57+AW57 -> -21816.371 | AY57: =AX57/P57 -> -0.82637768 | BA57: =P57/$G57 -> 1100 | BB57: =-AC57/$G57 -> -1132.1645 | BC57: =-AD57/$G57 -> -409.5205 | BD57: =-AE57/$G57 -> -13.567933 | BE57: =-AF57/$G57 -> -304.74703 | BF57: =-AG57/$G57 -> -1860 | BG57: =AK57/$G57 -> -760 | BH57: =-AM57/$G57 -> -146.375 | BI57: =-AN57/$G57 -> -57.692308 | BJ57: =-AO57/$G57 -> -204.06731 | BK57: =-AP57/$G57 -> -35.367059 | BL57: =AQ57/$G57 -> 28.60875 | BM57: =AR57/$G57 -> -970.82562 | BN57: =-AT57/$G57 -> -52.90043 | BO57: =AU57/$G57 -> -1023.726 | BP57: =AW57/$G57 -> 61.810166 | BQ57: =AX57/$G57 -> -909.01545
B58: FEBRERO | C58: MARZO | D58: 179-2026B2 | E58: 54 | F58: 46101 | G58: 24 | H58: POTA NUCAS | I58: Nucas | J58: 500-up | K58: Tailandia | L58: Lat Krabang | M58: DAIRECK S.A. | N58: Julieta | O58: 1100 | P58: 26400 | Q58: 953.625 | R58: 3513 | S58: =P58-R58 -> 22887 | T58: 1 | U58: ECO MARIN 26012N | V58: LIMG03933500 | W58: ONE LINE | X58: PAITA | Y58: 10005779 | Z58: Inventario final | AA58: =B58&Y58&Z58 -> FEBRERO10005779Inventario final | AB58: =INDEX('Detalle Costos'!$L$5:$L$158,MATCH(Resumen!AA58,'Detalle Costos'!$C$5:$C$158,0))*1000 -> 1860 | AC58: =IFERROR(INDEX('Detalle Costos'!$X$5:$X$158,MATCH(Resumen!AA58,'Detalle Costos'!$C$5:$C$158,0))*AG58,0) -> 27171.949 | AD58: =IFERROR(INDEX('Detalle Costos'!$Z$5:$Z$158,MATCH(Resumen!AA58,'Detalle Costos'!$C$5:$C$158,0))*AG58,0) -> 9828.4919 | AE58: =IFERROR(INDEX('Detalle Costos'!$Y$5:$Y$158,MATCH(Resumen!AA58,'Detalle Costos'!$C$5:$C$158,0))*AG58,0) -> 325.6304 | AF58: =IFERROR(INDEX('Detalle Costos'!$AA$5:$AA$158,MATCH(Resumen!AA58,'Detalle Costos'!$C$5:$C$158,0))*AG58,0) -> 7313.9286 | AG58: =AB58*G58 -> 44640 | AK58: =P58-AG58 -> -18240 | AL58: =AK58/P58 -> -0.69090909 | AM58: =R58 -> 3513 | AN58: =1500/26*G58 -> 1384.6154 | AO58: =SUM(AM58:AN58) -> 4897.6154 | AP58: =70656.31/1997.8*G58 -> 848.80941 | AQ58: =S58*0.03 -> 686.61 | AR58: =AK58-AO58-AP58+AQ58 -> -23299.815 | AS58: =AR58/P58 -> -0.88256874 | AT58: =105684.48/1997.8*G58 -> 1269.6103 | AU58: =AR58-AT58 -> -24569.425 | AV58: =AU58/P58 -> -0.93066004 | AW58: =123484.35/1997.8*G58 -> 1483.444 | AX58: =AR58+AW58 -> -21816.371 | AY58: =AX58/P58 -> -0.82637768 | BA58: =P58/$G58 -> 1100 | BB58: =-AC58/$G58 -> -1132.1645 | BC58: =-AD58/$G58 -> -409.5205 | BD58: =-AE58/$G58 -> -13.567933 | BE58: =-AF58/$G58 -> -304.74703 | BF58: =-AG58/$G58 -> -1860 | BG58: =AK58/$G58 -> -760 | BH58: =-AM58/$G58 -> -146.375 | BI58: =-AN58/$G58 -> -57.692308 | BJ58: =-AO58/$G58 -> -204.06731 | BK58: =-AP58/$G58 -> -35.367059 | BL58: =AQ58/$G58 -> 28.60875 | BM58: =AR58/$G58 -> -970.82562 | BN58: =-AT58/$G58 -> -52.90043 | BO58: =AU58/$G58 -> -1023.726 | BP58: =AW58/$G58 -> 61.810166 | BQ58: =AX58/$G58 -> -909.01545
B59: FEBRERO | C59: MARZO | D59: 179-2026B3 | E59: 54 | F59: 46108 | G59: 24 | H59: POTA NUCAS | I59: Nucas | J59: 500-up | K59: Tailandia | L59: Lat Krabang | M59: DAIRECK S.A. | N59: Julieta | O59: 1100 | P59: 26400 | Q59: 953.625 | R59: 3513 | S59: =P59-R59 -> 22887 | T59: 1 | U59: ECO SIROCCO 26013S | V59: LIMG03937900 | W59: ONE LINE | X59: PAITA | Y59: 10005779 | Z59: Inventario final | AA59: =B59&Y59&Z59 -> FEBRERO10005779Inventario final | AB59: =INDEX('Detalle Costos'!$L$5:$L$158,MATCH(Resumen!AA59,'Detalle Costos'!$C$5:$C$158,0))*1000 -> 1860 | AC59: =IFERROR(INDEX('Detalle Costos'!$X$5:$X$158,MATCH(Resumen!AA59,'Detalle Costos'!$C$5:$C$158,0))*AG59,0) -> 27171.949 | AD59: =IFERROR(INDEX('Detalle Costos'!$Z$5:$Z$158,MATCH(Resumen!AA59,'Detalle Costos'!$C$5:$C$158,0))*AG59,0) -> 9828.4919 | AE59: =IFERROR(INDEX('Detalle Costos'!$Y$5:$Y$158,MATCH(Resumen!AA59,'Detalle Costos'!$C$5:$C$158,0))*AG59,0) -> 325.6304 | AF59: =IFERROR(INDEX('Detalle Costos'!$AA$5:$AA$158,MATCH(Resumen!AA59,'Detalle Costos'!$C$5:$C$158,0))*AG59,0) -> 7313.9286 | AG59: =AB59*G59 -> 44640 | AK59: =P59-AG59 -> -18240 | AL59: =AK59/P59 -> -0.69090909 | AM59: =R59 -> 3513 | AN59: =1500/26*G59 -> 1384.6154 | AO59: =SUM(AM59:AN59) -> 4897.6154 | AP59: =70656.31/1997.8*G59 -> 848.80941 | AQ59: =S59*0.03 -> 686.61 | AR59: =AK59-AO59-AP59+AQ59 -> -23299.815 | AS59: =AR59/P59 -> -0.88256874 | AT59: =105684.48/1997.8*G59 -> 1269.6103 | AU59: =AR59-AT59 -> -24569.425 | AV59: =AU59/P59 -> -0.93066004 | AW59: =123484.35/1997.8*G59 -> 1483.444 | AX59: =AR59+AW59 -> -21816.371 | AY59: =AX59/P59 -> -0.82637768 | BA59: =P59/$G59 -> 1100 | BB59: =-AC59/$G59 -> -1132.1645 | BC59: =-AD59/$G59 -> -409.5205 | BD59: =-AE59/$G59 -> -13.567933 | BE59: =-AF59/$G59 -> -304.74703 | BF59: =-AG59/$G59 -> -1860 | BG59: =AK59/$G59 -> -760 | BH59: =-AM59/$G59 -> -146.375 | BI59: =-AN59/$G59 -> -57.692308 | BJ59: =-AO59/$G59 -> -204.06731 | BK59: =-AP59/$G59 -> -35.367059 | BL59: =AQ59/$G59 -> 28.60875 | BM59: =AR59/$G59 -> -970.82562 | BN59: =-AT59/$G59 -> -52.90043 | BO59: =AU59/$G59 -> -1023.726 | BP59: =AW59/$G59 -> 61.810166 | BQ59: =AX59/$G59 -> -909.01545
B60: FEBRERO | C60: MARZO | D60: 179-2026B4 | E60: 54 | F60: 46108 | G60: 24 | H60: POTA NUCAS | I60: Nucas | J60: 500-up | K60: Tailandia | L60: Lat Krabang | M60: DAIRECK S.A. | N60: Julieta | O60: 1100 | P60: 26400 | Q60: 953.625 | R60: 3513 | S60: =P60-R60 -> 22887 | T60: 1 | U60: ECO SIROCCO 26013S | V60: LIMG03938300 | W60: ONE LINE | X60: PAITA | Y60: 10005779 | Z60: Inventario final | AA60: =B60&Y60&Z60 -> FEBRERO10005779Inventario final | AB60: =INDEX('Detalle Costos'!$L$5:$L$158,MATCH(Resumen!AA60,'Detalle Costos'!$C$5:$C$158,0))*1000 -> 1860 | AC60: =IFERROR(INDEX('Detalle Costos'!$X$5:$X$158,MATCH(Resumen!AA60,'Detalle Costos'!$C$5:$C$158,0))*AG60,0) -> 27171.949 | AD60: =IFERROR(INDEX('Detalle Costos'!$Z$5:$Z$158,MATCH(Resumen!AA60,'Detalle Costos'!$C$5:$C$158,0))*AG60,0) -> 9828.4919 | AE60: =IFERROR(INDEX('Detalle Costos'!$Y$5:$Y$158,MATCH(Resumen!AA60,'Detalle Costos'!$C$5:$C$158,0))*AG60,0) -> 325.6304 | AF60: =IFERROR(INDEX('Detalle Costos'!$AA$5:$AA$158,MATCH(Resumen!AA60,'Detalle Costos'!$C$5:$C$158,0))*AG60,0) -> 7313.9286 | AG60: =AB60*G60 -> 44640 | AK60: =P60-AG60 -> -18240 | AL60: =AK60/P60 -> -0.69090909 | AM60: =R60 -> 3513 | AN60: =1500/26*G60 -> 1384.6154 | AO60: =SUM(AM60:AN60) -> 4897.6154 | AP60: =70656.31/1997.8*G60 -> 848.80941 | AQ60: =S60*0.03 -> 686.61 | AR60: =AK60-AO60-AP60+AQ60 -> -23299.815 | AS60: =AR60/P60 -> -0.88256874 | AT60: =105684.48/1997.8*G60 -> 1269.6103 | AU60: =AR60-AT60 -> -24569.425 | AV60: =AU60/P60 -> -0.93066004 | AW60: =123484.35/1997.8*G60 -> 1483.444 | AX60: =AR60+AW60 -> -21816.371 | AY60: =AX60/P60 -> -0.82637768 | BA60: =P60/$G60 -> 1100 | BB60: =-AC60/$G60 -> -1132.1645 | BC60: =-AD60/$G60 -> -409.5205 | BD60: =-AE60/$G60 -> -13.567933 | BE60: =-AF60/$G60 -> -304.74703 | BF60: =-AG60/$G60 -> -1860 | BG60: =AK60/$G60 -> -760 | BH60: =-AM60/$G60 -> -146.375 | BI60: =-AN60/$G60 -> -57.692308 | BJ60: =-AO60/$G60 -> -204.06731 | BK60: =-AP60/$G60 -> -35.367059 | BL60: =AQ60/$G60 -> 28.60875 | BM60: =AR60/$G60 -> -970.82562 | BN60: =-AT60/$G60 -> -52.90043 | BO60: =AU60/$G60 -> -1023.726 | BP60: =AW60/$G60 -> 61.810166 | BQ60: =AX60/$G60 -> -909.01545
B61: FEBRERO | C61: MARZO | D61: 179-2026B5 | E61: 54 | F61: 46108 | G61: 24 | H61: POTA NUCAS | I61: Nucas | J61: 500-up | K61: Tailandia | L61: Lat Krabang | M61: DAIRECK S.A. | N61: Julieta | O61: 1100 | P61: 26400 | Q61: 966.54167 | R61: 3203 | S61: =P61-R61 -> 23197 | T61: 1 | U61: ECO SIROCCO 26013S | V61: LIMG03940300 | W61: ONE LINE | X61: PAITA | Y61: 10005779 | Z61: Inventario final | AA61: =B61&Y61&Z61 -> FEBRERO10005779Inventario final | AB61: =INDEX('Detalle Costos'!$L$5:$L$158,MATCH(Resumen!AA61,'Detalle Costos'!$C$5:$C$158,0))*1000 -> 1860 | AC61: =IFERROR(INDEX('Detalle Costos'!$X$5:$X$158,MATCH(Resumen!AA61,'Detalle Costos'!$C$5:$C$158,0))*AG61,0) -> 27171.949 | AD61: =IFERROR(INDEX('Detalle Costos'!$Z$5:$Z$158,MATCH(Resumen!AA61,'Detalle Costos'!$C$5:$C$158,0))*AG61,0) -> 9828.4919 | AE61: =IFERROR(INDEX('Detalle Costos'!$Y$5:$Y$158,MATCH(Resumen!AA61,'Detalle Costos'!$C$5:$C$158,0))*AG61,0) -> 325.6304 | AF61: =IFERROR(INDEX('Detalle Costos'!$AA$5:$AA$158,MATCH(Resumen!AA61,'Detalle Costos'!$C$5:$C$158,0))*AG61,0) -> 7313.9286 | AG61: =AB61*G61 -> 44640 | AK61: =P61-AG61 -> -18240 | AL61: =AK61/P61 -> -0.69090909 | AM61: =R61 -> 3203 | AN61: =1500/26*G61 -> 1384.6154 | AO61: =SUM(AM61:AN61) -> 4587.6154 | AP61: =70656.31/1997.8*G61 -> 848.80941 | AQ61: =S61*0.03 -> 695.91 | AR61: =AK61-AO61-AP61+AQ61 -> -22980.515 | AS61: =AR61/P61 -> -0.87047405 | AT61: =105684.48/1997.8*G61 -> 1269.6103 | AU61: =AR61-AT61 -> -24250.125 | AV61: =AU61/P61 -> -0.91856535 | AW61: =123484.35/1997.8*G61 -> 1483.444 | AX61: =AR61+AW61 -> -21497.071 | AY61: =AX61/P61 -> -0.81428299 | BA61: =P61/$G61 -> 1100 | BB61: =-AC61/$G61 -> -1132.1645 | BC61: =-AD61/$G61 -> -409.5205 | BD61: =-AE61/$G61 -> -13.567933 | BE61: =-AF61/$G61 -> -304.74703 | BF61: =-AG61/$G61 -> -1860 | BG61: =AK61/$G61 -> -760 | BH61: =-AM61/$G61 -> -133.45833 | BI61: =-AN61/$G61 -> -57.692308 | BJ61: =-AO61/$G61 -> -191.15064 | BK61: =-AP61/$G61 -> -35.367059 | BL61: =AQ61/$G61 -> 28.99625 | BM61: =AR61/$G61 -> -957.52145 | BN61: =-AT61/$G61 -> -52.90043 | BO61: =AU61/$G61 -> -1010.4219 | BP61: =AW61/$G61 -> 61.810166 | BQ61: =AX61/$G61 -> -895.71128
B62: FEBRERO | C62: MARZO | D62: 179-2026C1 | E62: 54 | F62: 46108 | G62: 24 | H62: POTA NUCAS | I62: Nucas | J62: 1-2 KG | K62: Tailandia | L62: Lat Krabang | M62: DAIRECK S.A. | N62: KHUNRUNG | O62: 1200 | P62: 28800 | Q62: 1054.1667 | R62: 3500 | S62: =P62-R62 -> 25300 | T62: 1 | U62: ECO SIROCCO 26013S | V62: 6447908140 | W62: COSCO | X62: PAITA | Y62: 10005779 | Z62: Inventario final | AA62: =B62&Y62&Z62 -> FEBRERO10005779Inventario final | AB62: =INDEX('Detalle Costos'!$L$5:$L$158,MATCH(Resumen!AA62,'Detalle Costos'!$C$5:$C$158,0))*1000 -> 1860 | AC62: =IFERROR(INDEX('Detalle Costos'!$X$5:$X$158,MATCH(Resumen!AA62,'Detalle Costos'!$C$5:$C$158,0))*AG62,0) -> 27171.949 | AD62: =IFERROR(INDEX('Detalle Costos'!$Z$5:$Z$158,MATCH(Resumen!AA62,'Detalle Costos'!$C$5:$C$158,0))*AG62,0) -> 9828.4919 | AE62: =IFERROR(INDEX('Detalle Costos'!$Y$5:$Y$158,MATCH(Resumen!AA62,'Detalle Costos'!$C$5:$C$158,0))*AG62,0) -> 325.6304 | AF62: =IFERROR(INDEX('Detalle Costos'!$AA$5:$AA$158,MATCH(Resumen!AA62,'Detalle Costos'!$C$5:$C$158,0))*AG62,0) -> 7313.9286 | AG62: =AB62*G62 -> 44640 | AK62: =P62-AG62 -> -15840 | AL62: =AK62/P62 -> -0.55 | AM62: =R62 -> 3500 | AN62: =1500/26*G62 -> 1384.6154 | AO62: =SUM(AM62:AN62) -> 4884.6154 | AP62: =70656.31/1997.8*G62 -> 848.80941 | AQ62: =S62*0.03 -> 759 | AR62: =AK62-AO62-AP62+AQ62 -> -20814.425 | AS62: =AR62/P62 -> -0.72272308 | AT62: =105684.48/1997.8*G62 -> 1269.6103 | AU62: =AR62-AT62 -> -22084.035 | AV62: =AU62/P62 -> -0.76680678 | AW62: =123484.35/1997.8*G62 -> 1483.444 | AX62: =AR62+AW62 -> -19330.981 | AY62: =AX62/P62 -> -0.67121461 | BA62: =P62/$G62 -> 1200 | BB62: =-AC62/$G62 -> -1132.1645 | BC62: =-AD62/$G62 -> -409.5205 | BD62: =-AE62/$G62 -> -13.567933 | BE62: =-AF62/$G62 -> -304.74703 | BF62: =-AG62/$G62 -> -1860 | BG62: =AK62/$G62 -> -660 | BH62: =-AM62/$G62 -> -145.83333 | BI62: =-AN62/$G62 -> -57.692308 | BJ62: =-AO62/$G62 -> -203.52564 | BK62: =-AP62/$G62 -> -35.367059 | BL62: =AQ62/$G62 -> 31.625 | BM62: =AR62/$G62 -> -867.2677 | BN62: =-AT62/$G62 -> -52.90043 | BO62: =AU62/$G62 -> -920.16813 | BP62: =AW62/$G62 -> 61.810166 | BQ62: =AX62/$G62 -> -805.45753
B63: FEBRERO | C63: MARZO | D63: 179-2026C2 | E63: 54 | F63: 46108 | G63: 24 | H63: POTA NUCAS | I63: Nucas | J63: 1-2 KG | K63: Tailandia | L63: Lat Krabang | M63: DAIRECK S.A. | N63: KHUNRUNG | O63: 1200 | P63: 28800 | Q63: 1054.1667 | R63: 3500 | S63: =P63-R63 -> 25300 | T63: 1 | U63: ECO SIROCCO 26013S | V63: 6447908120 | W63: COSCO | X63: PAITA | Y63: 10005779 | Z63: Inventario final | AA63: =B63&Y63&Z63 -> FEBRERO10005779Inventario final | AB63: =INDEX('Detalle Costos'!$L$5:$L$158,MATCH(Resumen!AA63,'Detalle Costos'!$C$5:$C$158,0))*1000 -> 1860 | AC63: =IFERROR(INDEX('Detalle Costos'!$X$5:$X$158,MATCH(Resumen!AA63,'Detalle Costos'!$C$5:$C$158,0))*AG63,0) -> 27171.949 | AD63: =IFERROR(INDEX('Detalle Costos'!$Z$5:$Z$158,MATCH(Resumen!AA63,'Detalle Costos'!$C$5:$C$158,0))*AG63,0) -> 9828.4919 | AE63: =IFERROR(INDEX('Detalle Costos'!$Y$5:$Y$158,MATCH(Resumen!AA63,'Detalle Costos'!$C$5:$C$158,0))*AG63,0) -> 325.6304 | AF63: =IFERROR(INDEX('Detalle Costos'!$AA$5:$AA$158,MATCH(Resumen!AA63,'Detalle Costos'!$C$5:$C$158,0))*AG63,0) -> 7313.9286 | AG63: =AB63*G63 -> 44640 | AK63: =P63-AG63 -> -15840 | AL63: =AK63/P63 -> -0.55 | AM63: =R63 -> 3500 | AN63: =1500/26*G63 -> 1384.6154 | AO63: =SUM(AM63:AN63) -> 4884.6154 | AP63: =70656.31/1997.8*G63 -> 848.80941 | AQ63: =S63*0.03 -> 759 | AR63: =AK63-AO63-AP63+AQ63 -> -20814.425 | AS63: =AR63/P63 -> -0.72272308 | AT63: =105684.48/1997.8*G63 -> 1269.6103 | AU63: =AR63-AT63 -> -22084.035 | AV63: =AU63/P63 -> -0.76680678 | AW63: =123484.35/1997.8*G63 -> 1483.444 | AX63: =AR63+AW63 -> -19330.981 | AY63: =AX63/P63 -> -0.67121461 | BA63: =P63/$G63 -> 1200 | BB63: =-AC63/$G63 -> -1132.1645 | BC63: =-AD63/$G63 -> -409.5205 | BD63: =-AE63/$G63 -> -13.567933 | BE63: =-AF63/$G63 -> -304.74703 | BF63: =-AG63/$G63 -> -1860 | BG63: =AK63/$G63 -> -660 | BH63: =-AM63/$G63 -> -145.83333 | BI63: =-AN63/$G63 -> -57.692308 | BJ63: =-AO63/$G63 -> -203.52564 | BK63: =-AP63/$G63 -> -35.367059 | BL63: =AQ63/$G63 -> 31.625 | BM63: =AR63/$G63 -> -867.2677 | BN63: =-AT63/$G63 -> -52.90043 | BO63: =AU63/$G63 -> -920.16813 | BP63: =AW63/$G63 -> 61.810166 | BQ63: =AX63/$G63 -> -805.45753
B64: FEBRERO | C64: MARZO | D64: 181-2026 | E64: 46077 | F64: 46108 | G64: 48 | H64: POTA NUCAS | I64: Nucas | J64: 500-1000 | K64: Tailandia | L64: Lat Krabang | M64: TSUJINO | N64: Jose | O64: 1200 | P64: 57600 | Q64: 1126.8125 | R64: 3513 | S64: =P64-R64 -> 54087 | T64: 1 | U64: ECO SIROCCO 26013S | V64: LIMG04324700 | W64: ONE LINE | X64: PAITA | Y64: 10005779 | Z64: Inventario final | AA64: =B64&Y64&Z64 -> FEBRERO10005779Inventario final | AB64: =INDEX('Detalle Costos'!$L$5:$L$158,MATCH(Resumen!AA64,'Detalle Costos'!$C$5:$C$158,0))*1000 -> 1860 | AC64: =IFERROR(INDEX('Detalle Costos'!$X$5:$X$158,MATCH(Resumen!AA64,'Detalle Costos'!$C$5:$C$158,0))*AG64,0) -> 54343.898 | AD64: =IFERROR(INDEX('Detalle Costos'!$Z$5:$Z$158,MATCH(Resumen!AA64,'Detalle Costos'!$C$5:$C$158,0))*AG64,0) -> 19656.984 | AE64: =IFERROR(INDEX('Detalle Costos'!$Y$5:$Y$158,MATCH(Resumen!AA64,'Detalle Costos'!$C$5:$C$158,0))*AG64,0) -> 651.26079 | AF64: =IFERROR(INDEX('Detalle Costos'!$AA$5:$AA$158,MATCH(Resumen!AA64,'Detalle Costos'!$C$5:$C$158,0))*AG64,0) -> 14627.857 | AG64: =AB64*G64 -> 89280 | AK64: =P64-AG64 -> -31680 | AL64: =AK64/P64 -> -0.55 | AM64: =R64 -> 3513 | AN64: =1500/26*G64 -> 2769.2308 | AO64: =SUM(AM64:AN64) -> 6282.2308 | AP64: =70656.31/1997.8*G64 -> 1697.6188 | AQ64: =S64*0.03 -> 1622.61 | AR64: =AK64-AO64-AP64+AQ64 -> -38037.24 | AS64: =AR64/P64 -> -0.66036874 | AT64: =105684.48/1997.8*G64 -> 2539.2207 | AU64: =AR64-AT64 -> -40576.46 | AV64: =AU64/P64 -> -0.70445243 | AW64: =123484.35/1997.8*G64 -> 2966.888 | AX64: =AR64+AW64 -> -35070.352 | AY64: =AX64/P64 -> -0.60886027 | BA64: =P64/$G64 -> 1200 | BB64: =-AC64/$G64 -> -1132.1645 | BC64: =-AD64/$G64 -> -409.5205 | BD64: =-AE64/$G64 -> -13.567933 | BE64: =-AF64/$G64 -> -304.74703 | BF64: =-AG64/$G64 -> -1860 | BG64: =AK64/$G64 -> -660 | BH64: =-AM64/$G64 -> -73.1875 | BI64: =-AN64/$G64 -> -57.692308 | BJ64: =-AO64/$G64 -> -130.87981 | BK64: =-AP64/$G64 -> -35.367059 | BL64: =AQ64/$G64 -> 33.804375 | BM64: =AR64/$G64 -> -792.44249 | BN64: =-AT64/$G64 -> -52.90043 | BO64: =AU64/$G64 -> -845.34292 | BP64: =AW64/$G64 -> 61.810166 | BQ64: =AX64/$G64 -> -730.63233
B65: FEBRERO | C65: MARZO | D65: 183-2026 | E65: 58 | F65: 46108 | G65: 27 | H65: POTA REJOS CONGELADOS | I65: Rejos | J65: 2- UP LIMPIOS | K65: China | L65: Yantai | M65: SHANDONG SHEENIER | O65: 2600 | P65: 70200 | Q65: 2485.1852 | R65: 3100 | S65: =P65-R65 -> 67100 | T65: 1 | U65: ECO SIROCCO 26013S | V65: 6447908790 | W65: COSCO | X65: PAITA | Y65: 10007162 | Z65: Inventario final | AA65: =B65&Y65&Z65 -> FEBRERO10007162Inventario final | AB65: =INDEX('Detalle Costos'!$L$5:$L$158,MATCH(Resumen!AA65,'Detalle Costos'!$C$5:$C$158,0))*1000 -> 1720 | AC65: =IFERROR(INDEX('Detalle Costos'!$X$5:$X$158,MATCH(Resumen!AA65,'Detalle Costos'!$C$5:$C$158,0))*AG65,0) -> 29153.437 | AD65: =IFERROR(INDEX('Detalle Costos'!$Z$5:$Z$158,MATCH(Resumen!AA65,'Detalle Costos'!$C$5:$C$158,0))*AG65,0) -> 8318.7002 | AE65: =IFERROR(INDEX('Detalle Costos'!$Y$5:$Y$158,MATCH(Resumen!AA65,'Detalle Costos'!$C$5:$C$158,0))*AG65,0) -> 433.11122 | AF65: =IFERROR(INDEX('Detalle Costos'!$AA$5:$AA$158,MATCH(Resumen!AA65,'Detalle Costos'!$C$5:$C$158,0))*AG65,0) -> 8534.7516 | AG65: =AB65*G65 -> 46440 | AK65: =P65-AG65 -> 23760 | AL65: =AK65/P65 -> 0.33846154 | AM65: =R65 -> 3100 | AN65: =1500/26*G65 -> 1557.6923 | AO65: =SUM(AM65:AN65) -> 4657.6923 | AP65: =70656.31/1997.8*G65 -> 954.91059 | AQ65: =S65*0.03 -> 2013 | AR65: =AK65-AO65-AP65+AQ65 -> 20160.397 | AS65: =AR65/P65 -> 0.28718514 | AT65: =105684.48/1997.8*G65 -> 1428.3116 | AU65: =AR65-AT65 -> 18732.085 | AV65: =AU65/P65 -> 0.26683882 | AW65: =123484.35/1997.8*G65 -> 1668.8745 | AX65: =AR65+AW65 -> 21829.272 | AY65: =AX65/P65 -> 0.31095828 | BA65: =P65/$G65 -> 2600 | BB65: =-AC65/$G65 -> -1079.7569 | BC65: =-AD65/$G65 -> -308.10001 | BD65: =-AE65/$G65 -> -16.041156 | BE65: =-AF65/$G65 -> -316.10191 | BF65: =-AG65/$G65 -> -1720 | BG65: =AK65/$G65 -> 880 | BH65: =-AM65/$G65 -> -114.81481 | BI65: =-AN65/$G65 -> -57.692308 | BJ65: =-AO65/$G65 -> -172.50712 | BK65: =-AP65/$G65 -> -35.367059 | BL65: =AQ65/$G65 -> 74.555556 | BM65: =AR65/$G65 -> 746.68137 | BN65: =-AT65/$G65 -> -52.90043 | BO65: =AU65/$G65 -> 693.78094 | BP65: =AW65/$G65 -> 61.810166 | BQ65: =AX65/$G65 -> 808.49154
B66: FEBRERO | C66: MARZO | D66: 184-2026 | E66: 59 | F66: 46104 | G66: 216 | H66: POTA FILETE PRECOCIDO | I66: Daruma | K66: China | L66: Qingdao | M66: LONGKOU JIABAO AQUATIC | N66: James | O66: 3100 | P66: 669600 | Q66: 2992.5926 | R66: 23200 | S66: =P66-R66 -> 646400 | T66: 8 | U66: ECO MARIN 26012N | V66: 6447338820 | W66: COSCO | X66: PAITA | Y66: 10009239 | Z66: Inventario final | AA66: =B66&Y66&Z66 -> FEBRERO10009239Inventario final | AB66: =INDEX('Detalle Costos'!$L$5:$L$158,MATCH(Resumen!AA66,'Detalle Costos'!$C$5:$C$158,0))*1000 -> 2110 | AC66: =IFERROR(INDEX('Detalle Costos'!$X$5:$X$158,MATCH(Resumen!AA66,'Detalle Costos'!$C$5:$C$158,0))*AG66,0) -> 231844.89 | AD66: =IFERROR(INDEX('Detalle Costos'!$Z$5:$Z$158,MATCH(Resumen!AA66,'Detalle Costos'!$C$5:$C$158,0))*AG66,0) -> 151457.5 | AE66: =IFERROR(INDEX('Detalle Costos'!$Y$5:$Y$158,MATCH(Resumen!AA66,'Detalle Costos'!$C$5:$C$158,0))*AG66,0) -> 2915.1834 | AF66: =IFERROR(INDEX('Detalle Costos'!$AA$5:$AA$158,MATCH(Resumen!AA66,'Detalle Costos'!$C$5:$C$158,0))*AG66,0) -> 69542.433 | AG66: =AB66*G66 -> 455760 | AK66: =P66-AG66 -> 213840 | AL66: =AK66/P66 -> 0.31935484 | AM66: =R66 -> 23200 | AN66: =1500/26*G66 -> 12461.538 | AO66: =SUM(AM66:AN66) -> 35661.538 | AP66: =70656.31/1997.8*G66 -> 7639.2847 | AQ66: =S66*0.03 -> 19392 | AR66: =AK66-AO66-AP66+AQ66 -> 189931.18 | AS66: =AR66/P66 -> 0.28364871 | AT66: =105684.48/1997.8*G66 -> 11426.493 | AU66: =AR66-AT66 -> 178504.68 | AV66: =AU66/P66 -> 0.26658406 | AW66: =123484.35/1997.8*G66 -> 13350.996 | AX66: =AR66+AW66 -> 203282.17 | AY66: =AX66/P66 -> 0.30358747 | BA66: =P66/$G66 -> 3100 | BB66: =-AC66/$G66 -> -1073.356 | BC66: =-AD66/$G66 -> -701.19211 | BD66: =-AE66/$G66 -> -13.496219 | BE66: =-AF66/$G66 -> -321.95571 | BF66: =-AG66/$G66 -> -2110 | BG66: =AK66/$G66 -> 990 | BH66: =-AM66/$G66 -> -107.40741 | BI66: =-AN66/$G66 -> -57.692308 | BJ66: =-AO66/$G66 -> -165.09972 | BK66: =-AP66/$G66 -> -35.367059 | BL66: =AQ66/$G66 -> 89.777778 | BM66: =AR66/$G66 -> 879.311 | BN66: =-AT66/$G66 -> -52.90043 | BO66: =AU66/$G66 -> 826.41057 | BP66: =AW66/$G66 -> 61.810166 | BQ66: =AX66/$G66 -> 941.12117
B67: FEBRERO | C67: MARZO | D67: 185-2026 | E67: 59 | F67: 46104 | G67: 108 | H67: POTA FILETE PRECOCIDO | I67: Daruma | K67: China | L67: Qingdao | M67: LONGKOU BOHAI | N67: James | O67: 3100 | P67: 334800 | Q67: 2992.5926 | R67: 11600 | S67: =P67-R67 -> 323200 | T67: 4 | U67: ECO MARIN 26012N | V67: 6447338860 | W67: COSCO | X67: PAITA | Y67: 10009239 | Z67: Inventario final | AA67: =B67&Y67&Z67 -> FEBRERO10009239Inventario final | AB67: =INDEX('Detalle Costos'!$L$5:$L$158,MATCH(Resumen!AA67,'Detalle Costos'!$C$5:$C$158,0))*1000 -> 2110 | AC67: =IFERROR(INDEX('Detalle Costos'!$X$5:$X$158,MATCH(Resumen!AA67,'Detalle Costos'!$C$5:$C$158,0))*AG67,0) -> 115922.44 | AD67: =IFERROR(INDEX('Detalle Costos'!$Z$5:$Z$158,MATCH(Resumen!AA67,'Detalle Costos'!$C$5:$C$158,0))*AG67,0) -> 75728.748 | AE67: =IFERROR(INDEX('Detalle Costos'!$Y$5:$Y$158,MATCH(Resumen!AA67,'Detalle Costos'!$C$5:$C$158,0))*AG67,0) -> 1457.5917 | AF67: =IFERROR(INDEX('Detalle Costos'!$AA$5:$AA$158,MATCH(Resumen!AA67,'Detalle Costos'!$C$5:$C$158,0))*AG67,0) -> 34771.216 | AG67: =AB67*G67 -> 227880 | AK67: =P67-AG67 -> 106920 | AL67: =AK67/P67 -> 0.31935484 | AM67: =R67 -> 11600 | AN67: =1500/26*G67 -> 6230.7692 | AO67: =SUM(AM67:AN67) -> 17830.769 | AP67: =70656.31/1997.8*G67 -> 3819.6423 | AQ67: =S67*0.03 -> 9696 | AR67: =AK67-AO67-AP67+AQ67 -> 94965.588 | AS67: =AR67/P67 -> 0.28364871 | AT67: =105684.48/1997.8*G67 -> 5713.2465 | AU67: =AR67-AT67 -> 89252.342 | AV67: =AU67/P67 -> 0.26658406 | AW67: =123484.35/1997.8*G67 -> 6675.4979 | AX67: =AR67+AW67 -> 101641.09 | AY67: =AX67/P67 -> 0.30358747 | BA67: =P67/$G67 -> 3100 | BB67: =-AC67/$G67 -> -1073.356 | BC67: =-AD67/$G67 -> -701.19211 | BD67: =-AE67/$G67 -> -13.496219 | BE67: =-AF67/$G67 -> -321.95571 | BF67: =-AG67/$G67 -> -2110 | BG67: =AK67/$G67 -> 990 | BH67: =-AM67/$G67 -> -107.40741 | BI67: =-AN67/$G67 -> -57.692308 | BJ67: =-AO67/$G67 -> -165.09972 | BK67: =-AP67/$G67 -> -35.367059 | BL67: =AQ67/$G67 -> 89.777778 | BM67: =AR67/$G67 -> 879.311 | BN67: =-AT67/$G67 -> -52.90043 | BO67: =AU67/$G67 -> 826.41057 | BP67: =AW67/$G67 -> 61.810166 | BQ67: =AX67/$G67 -> 941.12117
B68: FEBRERO | C68: MARZO | D68: 189-2026 | E68: 68 | F68: 46108 | G68: 10 | H68: POTA NUCAS | I68: Nucas | J68: 300-500 | K68: Tailandia | L68: Lat Krabang | M68: DAIRECK S.A. | N68: Julieta | O68: 1130 | P68: 11300 | Q68: 990 | R68: 1400 | S68: =P68-R68 -> 9900 | T68: 1 | U68: ECO SIROCCO 26013S | V68: 6447908000 | W68: COSCO | X68: PAITA | Y68: 10005779 | Z68: Inventario final | AA68: =B68&Y68&Z68 -> FEBRERO10005779Inventario final | AB68: =INDEX('Detalle Costos'!$L$5:$L$158,MATCH(Resumen!AA68,'Detalle Costos'!$C$5:$C$158,0))*1000 -> 1860 | AC68: =IFERROR(INDEX('Detalle Costos'!$X$5:$X$158,MATCH(Resumen!AA68,'Detalle Costos'!$C$5:$C$158,0))*AG68,0) -> 11321.645 | AD68: =IFERROR(INDEX('Detalle Costos'!$Z$5:$Z$158,MATCH(Resumen!AA68,'Detalle Costos'!$C$5:$C$158,0))*AG68,0) -> 4095.205 | AE68: =IFERROR(INDEX('Detalle Costos'!$Y$5:$Y$158,MATCH(Resumen!AA68,'Detalle Costos'!$C$5:$C$158,0))*AG68,0) -> 135.67933 | AF68: =IFERROR(INDEX('Detalle Costos'!$AA$5:$AA$158,MATCH(Resumen!AA68,'Detalle Costos'!$C$5:$C$158,0))*AG68,0) -> 3047.4703 | AG68: =AB68*G68 -> 18600 | AK68: =P68-AG68 -> -7300 | AL68: =AK68/P68 -> -0.6460177 | AM68: =R68 -> 1400 | AN68: =1500/26*G68 -> 576.92308 | AO68: =SUM(AM68:AN68) -> 1976.9231 | AP68: =70656.31/1997.8*G68 -> 353.67059 | AQ68: =S68*0.03 -> 297 | AR68: =AK68-AO68-AP68+AQ68 -> -9333.5937 | AS68: =AR68/P68 -> -0.82598174 | AT68: =105684.48/1997.8*G68 -> 529.0043 | AU68: =AR68-AT68 -> -9862.598 | AV68: =AU68/P68 -> -0.87279628 | AW68: =123484.35/1997.8*G68 -> 618.10166 | AX68: =AR68+AW68 -> -8715.492 | AY68: =AX68/P68 -> -0.77128248 | BA68: =P68/$G68 -> 1130 | BB68: =-AC68/$G68 -> -1132.1645 | BC68: =-AD68/$G68 -> -409.5205 | BD68: =-AE68/$G68 -> -13.567933 | BE68: =-AF68/$G68 -> -304.74703 | BF68: =-AG68/$G68 -> -1860 | BG68: =AK68/$G68 -> -730 | BH68: =-AM68/$G68 -> -140 | BI68: =-AN68/$G68 -> -57.692308 | BJ68: =-AO68/$G68 -> -197.69231 | BK68: =-AP68/$G68 -> -35.367059 | BL68: =AQ68/$G68 -> 29.7 | BM68: =AR68/$G68 -> -933.35937 | BN68: =-AT68/$G68 -> -52.90043 | BO68: =AU68/$G68 -> -986.2598 | BP68: =AW68/$G68 -> 61.810166 | BQ68: =AX68/$G68 -> -871.5492
B69: FEBRERO | C69: MARZO | D69: 189-2026 | E69: 68 | F69: 46108 | G69: 15 | H69: POTA NUCAS | I69: Nucas | J69: 500-1000 | K69: Tailandia | L69: Lat Krabang | M69: DAIRECK S.A. | N69: Julieta | O69: 1200 | P69: 18000 | Q69: 1060 | R69: 2100 | S69: =P69-R69 -> 15900 | T69: 0 | U69: ECO SIROCCO 26013S | V69: 6447908000 | W69: COSCO | X69: PAITA | Y69: 10005779 | Z69: Inventario final | AA69: =B69&Y69&Z69 -> FEBRERO10005779Inventario final | AB69: =INDEX('Detalle Costos'!$L$5:$L$158,MATCH(Resumen!AA69,'Detalle Costos'!$C$5:$C$158,0))*1000 -> 1860 | AC69: =IFERROR(INDEX('Detalle Costos'!$X$5:$X$158,MATCH(Resumen!AA69,'Detalle Costos'!$C$5:$C$158,0))*AG69,0) -> 16982.468 | AD69: =IFERROR(INDEX('Detalle Costos'!$Z$5:$Z$158,MATCH(Resumen!AA69,'Detalle Costos'!$C$5:$C$158,0))*AG69,0) -> 6142.8074 | AE69: =IFERROR(INDEX('Detalle Costos'!$Y$5:$Y$158,MATCH(Resumen!AA69,'Detalle Costos'!$C$5:$C$158,0))*AG69,0) -> 203.519 | AF69: =IFERROR(INDEX('Detalle Costos'!$AA$5:$AA$158,MATCH(Resumen!AA69,'Detalle Costos'!$C$5:$C$158,0))*AG69,0) -> 4571.2054 | AG69: =AB69*G69 -> 27900 | AK69: =P69-AG69 -> -9900 | AL69: =AK69/P69 -> -0.55 | AM69: =R69 -> 2100 | AN69: =1500/26*G69 -> 865.38462 | AO69: =SUM(AM69:AN69) -> 2965.3846 | AP69: =70656.31/1997.8*G69 -> 530.50588 | AQ69: =S69*0.03 -> 477 | AR69: =AK69-AO69-AP69+AQ69 -> -12918.89 | AS69: =AR69/P69 -> -0.71771614 | AT69: =105684.48/1997.8*G69 -> 793.50646 | AU69: =AR69-AT69 -> -13712.397 | AV69: =AU69/P69 -> -0.76179983 | AW69: =123484.35/1997.8*G69 -> 927.15249 | AX69: =AR69+AW69 -> -11991.738 | AY69: =AX69/P69 -> -0.66620767 | BA69: =P69/$G69 -> 1200 | BB69: =-AC69/$G69 -> -1132.1645 | BC69: =-AD69/$G69 -> -409.5205 | BD69: =-AE69/$G69 -> -13.567933 | BE69: =-AF69/$G69 -> -304.74703 | BF69: =-AG69/$G69 -> -1860 | BG69: =AK69/$G69 -> -660 | BH69: =-AM69/$G69 -> -140 | BI69: =-AN69/$G69 -> -57.692308 | BJ69: =-AO69/$G69 -> -197.69231 | BK69: =-AP69/$G69 -> -35.367059 | BL69: =AQ69/$G69 -> 31.8 | BM69: =AR69/$G69 -> -861.25937 | BN69: =-AT69/$G69 -> -52.90043 | BO69: =AU69/$G69 -> -914.1598 | BP69: =AW69/$G69 -> 61.810166 | BQ69: =AX69/$G69 -> -799.4492
B70: FEBRERO | C70: MARZO | D70: 170-2026B | E70: 43 | F70: 46092 | G70: 24 | H70: POTA REJOS CONGELADOS | I70: Rejos | J70: 2 - UP | K70: España | L70: Vigo | M70: KULALIA | N70: Ramon | O70: 2400 | P70: =O70*G70 -> 57600 | Q70: =+S70/G70 -> 2230.0104 | R70: =4079.75 -> 4079.75 | S70: =P70-R70 -> 53520.25 | T70: 1 | U70: CMA CGM BOLDNESS / 0DVODN1MA | V70: LMM0575562 | W70: CMA CGM | Y70: 10007162 | Z70: Inventario final | AA70: =B70&Y70&Z70 -> FEBRERO10007162Inventario final | AB70: =INDEX('Detalle Costos'!$L$5:$L$158,MATCH(Resumen!AA70,'Detalle Costos'!$C$5:$C$158,0))*1000 -> 1720 | AC70: =IFERROR(INDEX('Detalle Costos'!$X$5:$X$158,MATCH(Resumen!AA70,'Detalle Costos'!$C$5:$C$158,0))*AG70,0) -> 25914.166 | AD70: =IFERROR(INDEX('Detalle Costos'!$Z$5:$Z$158,MATCH(Resumen!AA70,'Detalle Costos'!$C$5:$C$158,0))*AG70,0) -> 7394.4002 | AE70: =IFERROR(INDEX('Detalle Costos'!$Y$5:$Y$158,MATCH(Resumen!AA70,'Detalle Costos'!$C$5:$C$158,0))*AG70,0) -> 384.98775 | AF70: =IFERROR(INDEX('Detalle Costos'!$AA$5:$AA$158,MATCH(Resumen!AA70,'Detalle Costos'!$C$5:$C$158,0))*AG70,0) -> 7586.4458 | AG70: =AB70*G70 -> 41280 | AK70: =P70-AG70 -> 16320 | AL70: =AK70/P70 -> 0.28333333 | AM70: =R70 -> 4079.75 | AN70: =1500/26*G70 -> 1384.6154 | AO70: =SUM(AM70:AN70) -> 5464.3654 | AP70: =70656.31/1997.8*G70 -> 848.80941 | AQ70: =S70*0.03 -> 1605.6075 | AR70: =AK70-AO70-AP70+AQ70 -> 11612.433 | AS70: =AR70/P70 -> 0.20160473 | AT70: =105684.48/1997.8*G70 -> 1269.6103 | AU70: =AR70-AT70 -> 10342.822 | AV70: =AU70/P70 -> 0.17956289 | AW70: =123484.35/1997.8*G70 -> 1483.444 | AX70: =AR70+AW70 -> 13095.877 | AY70: =AX70/P70 -> 0.22735897 | BA70: =P70/$G70 -> 2400 | BB70: =-AC70/$G70 -> -1079.7569 | BC70: =-AD70/$G70 -> -308.10001 | BD70: =-AE70/$G70 -> -16.041156 | BE70: =-AF70/$G70 -> -316.10191 | BF70: =-AG70/$G70 -> -1720 | BG70: =AK70/$G70 -> 680 | BH70: =-AM70/$G70 -> -169.98958 | BI70: =-AN70/$G70 -> -57.692308 | BJ70: =-AO70/$G70 -> -227.68189 | BK70: =-AP70/$G70 -> -35.367059 | BL70: =AQ70/$G70 -> 66.900312 | BM70: =AR70/$G70 -> 483.85136 | BN70: =-AT70/$G70 -> -52.90043 | BO70: =AU70/$G70 -> 430.95093 | BP70: =AW70/$G70 -> 61.810166 | BQ70: =AX70/$G70 -> 545.66153
B71: FEBRERO | C71: MARZO | D71: 153-2026 | E71: 26 | F71: 46110 | G71: =26*1 -> 26 | H71: POTA REPRODUCTORES | I71: Rejos | K71: España | L71: Valencia | M71: OCEANUS FISH | N71: Ignacio / Ives | O71: 2950 | P71: =+G71*O71 -> 76700 | Q71: =+S71/G71 -> 2793.0865 | R71: =4079.75 -> 4079.75 | S71: =P71-R71 -> 72620.25 | T71: 1 | U71: CAPE SKAGEN 614N | V71: 19449468 | W71: HAPAG | Y71: 10007567 | Z71: Inventario final | AA71: =B71&Y71&Z71 -> FEBRERO10007567Inventario final | AB71: =INDEX('Detalle Costos'!$L$5:$L$158,MATCH(Resumen!AA71,'Detalle Costos'!$C$5:$C$158,0))*1000 -> 1700 | AC71: =IFERROR(INDEX('Detalle Costos'!$X$5:$X$158,MATCH(Resumen!AA71,'Detalle Costos'!$C$5:$C$158,0))*AG71,0) -> 27879.055 | AD71: =IFERROR(INDEX('Detalle Costos'!$Z$5:$Z$158,MATCH(Resumen!AA71,'Detalle Costos'!$C$5:$C$158,0))*AG71,0) -> 7645.5078 | AE71: =IFERROR(INDEX('Detalle Costos'!$Y$5:$Y$158,MATCH(Resumen!AA71,'Detalle Costos'!$C$5:$C$158,0))*AG71,0) -> 478.01265 | AF71: =IFERROR(INDEX('Detalle Costos'!$AA$5:$AA$158,MATCH(Resumen!AA71,'Detalle Costos'!$C$5:$C$158,0))*AG71,0) -> 8197.4247 | AG71: =AB71*G71 -> 44200 | AK71: =P71-AG71 -> 32500 | AL71: =AK71/P71 -> 0.42372881 | AM71: =R71 -> 4079.75 | AN71: =1500/26*G71 -> 1500 | AO71: =SUM(AM71:AN71) -> 5579.75 | AP71: =70656.31/1997.8*G71 -> 919.54353 | AQ71: =S71*0.03 -> 2178.6075 | AR71: =AK71-AO71-AP71+AQ71 -> 28179.314 | AS71: =AR71/P71 -> 0.36739653 | AT71: =105684.48/1997.8*G71 -> 1375.4112 | AU71: =AR71-AT71 -> 26803.903 | AV71: =AU71/P71 -> 0.34946418 | AW71: =123484.35/1997.8*G71 -> 1607.0643 | AX71: =AR71+AW71 -> 29786.378 | AY71: =AX71/P71 -> 0.38834913 | BA71: =P71/$G71 -> 2950 | BB71: =-AC71/$G71 -> -1072.2713 | BC71: =-AD71/$G71 -> -294.05799 | BD71: =-AE71/$G71 -> -18.385102 | BE71: =-AF71/$G71 -> -315.28557 | BF71: =-AG71/$G71 -> -1700 | BG71: =AK71/$G71 -> 1250 | BH71: =-AM71/$G71 -> -156.91346 | BI71: =-AN71/$G71 -> -57.692308 | BJ71: =-AO71/$G71 -> -214.60577 | BK71: =-AP71/$G71 -> -35.367059 | BL71: =AQ71/$G71 -> 83.792596 | BM71: =AR71/$G71 -> 1083.8198 | BN71: =-AT71/$G71 -> -52.90043 | BO71: =AU71/$G71 -> 1030.9193 | BP71: =AW71/$G71 -> 61.810166 | BQ71: =AX71/$G71 -> 1145.6299
F73: TOTAL | G73: =SUBTOTAL(9,G4:G71) -> 116 | O73: TOTAL | P73: =SUBTOTAL(9,P4:P71) -> 292956 | Q73: =SUBTOTAL(9,Q4:Q71) -> 11760.328 | R73: =SUBTOTAL(9,R4:R71) -> 18665.167 | S73: =SUBTOTAL(9,S4:S71) -> 274290.83 | AC73: =SUBTOTAL(9,AC4:AC71) -> 125788.45 | AD73: =SUBTOTAL(9,AD4:AD71) -> 36793.516 | AE73: =SUBTOTAL(9,AE4:AE71) -> 1887.0607 | AF73: =SUBTOTAL(9,AF4:AF71) -> 36486.975 | AG73: =SUBTOTAL(9,AG4:AG71) -> 200956 | AH73: =SUBTOTAL(9,AH4:AH71) -> 14.849 | AI73: =SUBTOTAL(9,AI4:AI71) -> 1859.7145 | AJ73: =SUBTOTAL(9,AJ4:AJ71) -> 27614.901 | AK73: =SUBTOTAL(9,AK4:AK71) -> 91999.997 | AL73: =AK73/$P73 -> 0.31404032 | AM73: =SUBTOTAL(9,AM4:AM71) -> 18665.167 | AN73: =SUBTOTAL(9,AN4:AN71) -> 6692.3077 | AO73: =SUBTOTAL(9,AO4:AO71) -> 25357.474 | AP73: =SUBTOTAL(9,AP4:AP71) -> 4169.3075 | AQ73: =SUBTOTAL(9,AQ4:AQ71) -> 8228.725 | AR73: =SUBTOTAL(9,AR4:AR71) -> 70701.94 | AS73: =AR73/$P73 -> 0.24133979 | AT73: =SUBTOTAL(9,AT4:AT71) -> 6667.931 | AU73: =SUBTOTAL(9,AU4:AU71) -> 64034.009 | AV73: =AU73/$P73 -> 0.21857893 | AW73: =SUBTOTAL(9,AW4:AW71) -> 7362.4482 | AX73: =SUBTOTAL(9,AX4:AX71) -> 78064.388 | AY73: =AX73/$P73 -> 0.26647137 | BA73: =P73/$G73 -> 2525.4828 | BB73: =-AC73/$G73 -> -1084.3832 | BC73: =-AD73/$G73 -> -317.18548 | BD73: =-AE73/$G73 -> -16.267765 | BE73: =-AF73/$G73 -> -314.54288 | BF73: =-AG73/$G73 -> -1732.3793 | BG73: =AK73/$G73 -> 793.10342 | BH73: =-AM73/$G73 -> -160.90661 | BI73: =-AN73/$G73 -> -57.692308 | BJ73: =-AO73/$G73 -> -218.59892 | BK73: =-AP73/$G73 -> -35.942306 | BL73: =AQ73/$G73 -> 70.937284 | BM73: =AR73/$G73 -> 609.49948 | BN73: =-AT73/$G73 -> -57.482164 | BO73: =AU73/$G73 -> 552.01732 | BP73: =AW73/$G73 -> 63.469381 | BQ73: =AX73/$G73 -> 672.96886
AA75: =C75&Y75&Z75
AB77: Ventas | AG77: 100000
AB78: Costo Ventas | AG78: -70000 | AK78: Materia Prima, Mano obra, CIF: Payer, Depreciación, Electricidad, Mantenimiento, Calidad, etc) | AW78: 123484.35
AB79: Utilidad Bruta | AG79: =AG77+AG78 -> 30000 | AW79: 678
T80: 312060.49 | AW80: 124162.35
AB81: Gasto Ventas | AG81: =AG82+AG83 -> -13000
AB82: Fletes | AG82: -10000
AB83: Port | AG83: -3000
AB84: Gasto Adm | AG84: -10000 | AK84: Equipo Lima, ss contabilidad, sistemas, mantenimiento,
AB85: Ingreso Div | AG85: =AG77*0.03 -> 3000 | AK85: Drawback
AB86: Utd Operativa | AG86: =AG79+AG81+AG84+AG85 -> 10000
AB88: Gasto Financ | AG88: =-1000 -> -1000 | AK88: Intereses por financiamientos
AB89: Utd Neta | AG89: =AG86+AG88 -> 9000

Sheet Detalle Costos
A4: MES | B4: CÓDIGO | C4: MATCH | D4: PRODUCTO | E4: Categoría | F4: Cant.oper. | G4: Un. | H4: Val.prov. | I4: Dif.prec. | J4: DifTpoCam | K4: Valor real | L4: Precio | M4: Mater.Prim | N4: Envases y | O4: Servicio de Terceros | P4: CIF | Q4: CIF-Otros | R4: CIF-Gastos | S4: CIF-Manten | T4: CIF-Serv. | U4: CIF-Deprec | V4: CIF- Otros 2 | W4: TOTAL | X4: Mater.Prim | Y4: Envases y | Z4: Servicio de Terceros | AA4: CIF
A5: ENERO | B5: 10009178 | C5: =A5&B5&E5 -> ENERO10009178Inventario inicial | D5: POTA ALAS FR C/P C/C (B) S/COD BL10 S20 | E5: Inventario inicial | F5: 11760 | G5: KG | H5: 24460.8 | I5: -2861.14 | J5: 0 | K5: 21599.66 | L5: 1.84 | M5: 15386.06 | N5: 192.1 | O5: 2941.72 | P5: =SUM(Q5:V5) -> 3079.78 | Q5: 119.29 | R5: 316.65 | S5: 1240.72 | T5: 0.08 | U5: 0.07 | V5: 1402.97 | W5: =SUM(M5:P5) -> 21599.66 | X5: =M5/$W5 -> 0.71232881 | Y5: =N5/$W5 -> 0.0088936585 | Z5: =O5/$W5 -> 0.13619288 | AA5: =P5/$W5 -> 0.14258465
A6: ENERO | B6: 10009178 | C6: =A6&B6&E6 -> ENERO10009178Revalorización | D6: POTA ALAS FR C/P C/C (B) S/COD BL10 S20 | E6: Revalorización | F6: 0 | G6: KG | H6: -352.8 | I6: 352.8 | J6: 0 | K6: 0 | L6: 0 | M6: 0 | N6: 0 | O6: 0 | P6: =SUM(Q6:V6) -> 0 | Q6: 0 | R6: 0 | S6: 0 | T6: 0 | U6: 0 | V6: 0 | W6: =SUM(M6:P6) -> 0 | X6: =M6/$W6 -> #DIV/0! | Y6: =N6/$W6 -> #DIV/0! | Z6: =O6/$W6 -> #DIV/0! | AA6: =P6/$W6 -> #DIV/0!
A7: ENERO | B7: 10009178 | C7: =A7&B7&E7 -> ENERO10009178Entradas | D7: POTA ALAS FR C/P C/C (B) S/COD BL10 S20 | E7: Entradas | F7: 4920 | G7: KG | H7: 10086 | I7: -1629.21 | J7: 0 | K7: 8456.79 | L7: 1.72 | M7: 5674.08 | N7: 83.7 | O7: 1150.54 | P7: =SUM(Q7:V7) -> 1548.47 | Q7: 11.05 | R7: 84.57 | S7: 772.75 | T7: 0.02 | U7: 0 | V7: 680.08 | W7: =SUM(M7:P7) -> 8456.79 | X7: =M7/$W7 -> 0.67094962 | Y7: =N7/$W7 -> 0.0098973724 | Z7: =O7/$W7 -> 0.13604926 | AA7: =P7/$W7 -> 0.18310375
A8: ENERO | B8: 10009178 | C8: =A8&B8&E8 -> ENERO10009178Inventario acumulado | D8: POTA ALAS FR C/P C/C (B) S/COD BL10 S20 | E8: Inventario acumulado | F8: 16680 | G8: KG | H8: 34194 | I8: -4137.55 | J8: 0 | K8: 30056.45 | L8: 1.8 | M8: 21060.14 | N8: 275.8 | O8: 4092.26 | P8: =SUM(Q8:V8) -> 4628.25 | Q8: 130.34 | R8: 401.22 | S8: 2013.47 | T8: 0.1 | U8: 0.07 | V8: 2083.05 | W8: =SUM(M8:P8) -> 30056.45 | X8: =M8/$W8 -> 0.70068621 | Y8: =N8/$W8 -> 0.009176067 | Z8: =O8/$W8 -> 0.13615247 | AA8: =P8/$W8 -> 0.15398525
A9: ENERO | B9: 10009178 | C9: =A9&B9&E9 -> ENERO10009178Inventario final | D9: POTA ALAS FR C/P C/C (B) S/COD BL10 S20 | E9: Inventario final | F9: 16680 | G9: KG | H9: 34194 | I9: -4137.55 | J9: 0 | K9: 30056.45 | L9: 1.8 | M9: 21060.14 | N9: 275.8 | O9: 4092.26 | P9: =SUM(Q9:V9) -> 4628.25 | Q9: 130.34 | R9: 401.22 | S9: 2013.47 | T9: 0.1 | U9: 0.07 | V9: 2083.05 | W9: =SUM(M9:P9) -> 30056.45 | X9: =M9/$W9 -> 0.70068621 | Y9: =N9/$W9 -> 0.009176067 | Z9: =O9/$W9 -> 0.13615247 | AA9: =P9/$W9 -> 0.15398525
A10: FEBRERO | B10: 10009178 | C10: =A10&B10&E10 -> FEBRERO10009178Inventario inicial | D10: POTA ALAS FR C/P C/C (B) S/COD BL10 S20 | E10: Inventario inicial | F10: 16680 | G10: KG | H10: 34194 | I10: 4,137.55- | J10: 0 | K10: 30056.45 | L10: 1.8 | M10: 21060.14 | N10: 275.8 | O10: 4092.26 | P10: =SUM(Q10:V10) -> 4628.25 | Q10: 130.34 | R10: 401.22 | S10: 2013.47 | T10: 0.1 | U10: 1944.83 | V10: 138.29 | W10: =SUM(M10:P10) -> 30056.45 | X10: =M10/$W10 -> 0.70068621 | Y10: =N10/$W10 -> 0.009176067 | Z10: =O10/$W10 -> 0.13615247 | AA10: =P10/$W10 -> 0.15398525
A11: FEBRERO | B11: 10009178 | C11: =A11&B11&E11 -> FEBRERO10009178Revalorización | D11: POTA ALAS FR C/P C/C (B) S/COD BL10 S20 | E11: Revalorización | F11: 0 | G11: KG | H11: 3,502.80- | I11: 3502.8 | J11: 0 | K11: 0 | L11: 0 | M11: 0 | N11: 0 | O11: 0 | P11: =SUM(Q11:V11) -> 0 | Q11: 0 | R11: 0 | S11: 0 | T11: 0 | U11: 0 | V11: 0 | W11: =SUM(M11:P11) -> 0 | X11: =M11/$W11 -> #DIV/0! | Y11: =N11/$W11 -> #DIV/0! | Z11: =O11/$W11 -> #DIV/0! | AA11: =P11/$W11 -> #DIV/0!
A12: FEBRERO | B12: 10009178 | C12: =A12&B12&E12 -> FEBRERO10009178Entradas | D12: POTA ALAS FR C/P C/C (B) S/COD BL10 S20 | E12: Entradas | F12: 8220 | G12: KG | H12: 15124.8 | I12: 2,200.35- | J12: 0 | K12: 12924.45 | L12: 1.57 | M12: 8381.4 | N12: 139.88 | O12: 1759.88 | P12: =SUM(Q12:V12) -> 2643.29 | Q12: 57.66 | R12: 141.81 | S12: 1295.34 | T12: 0.12- | U12: 1048.63 | V12: 99.85 | W12: =SUM(M12:P12) -> 12924.45 | X12: =M12/$W12 -> 0.64849181 | Y12: =N12/$W12 -> 0.010822898 | Z12: =O12/$W12 -> 0.13616672 | AA12: =P12/$W12 -> 0.20451857
A13: FEBRERO | B13: 10009178 | C13: =A13&B13&E13 -> FEBRERO10009178Inventario acumulado | D13: POTA ALAS FR C/P C/C (B) S/COD BL10 S20 | E13: Inventario acumulado | F13: 24900 | G13: KG | H13: 45816 | I13: 2,835.10- | J13: 0 | K13: 42980.9 | L13: 1.73 | M13: 29441.54 | N13: 415.68 | O13: 5852.14 | P13: =SUM(Q13:V13) -> 7271.54 | Q13: 188 | R13: 543.03 | S13: 3308.81 | T13: 0.02- | U13: 2993.46 | V13: 238.24 | W13: =SUM(M13:P13) -> 42980.9 | X13: =M13/$W13 -> 0.68499124 | Y13: =N13/$W13 -> 0.0096712726 | Z13: =O13/$W13 -> 0.13615676 | AA13: =P13/$W13 -> 0.16918073
A14: FEBRERO | B14: 10009178 | C14: =A14&B14&E14 -> FEBRERO10009178Inventario final | D14: POTA ALAS FR C/P C/C (B) S/COD BL10 S20 | E14: Inventario final | F14: 24900 | G14: KG | H14: 45816 | I14: 2,835.10- | J14: 0 | K14: 42980.9 | L14: 1.73 | M14: 29441.54 | N14: 415.68 | O14: 5852.14 | P14: =SUM(Q14:V14) -> 7271.54 | Q14: 188 | R14: 543.03 | S14: 3308.81 | T14: 0.02- | U14: 2993.46 | V14: 238.24 | W14: =SUM(M14:P14) -> 42980.9 | X14: =M14/$W14 -> 0.68499124 | Y14: =N14/$W14 -> 0.0096712726 | Z14: =O14/$W14 -> 0.13615676 | AA14: =P14/$W14 -> 0.16918073
A15: ENERO | B15: 10006720 | C15: =A15&B15&E15 -> ENERO10006720Inventario inicial | D15: POTA ALAS FR C/P C/C 1-2 BL10 S20 | E15: Inventario inicial | F15: 80180 | G15: KG | H15: 138711.4 | I15: 2617.91 | K15: 141329.31 | L15: 1.76 | M15: 96628.24 | N15: 1272.01 | O15: 21487.27 | P15: =SUM(Q15:V15) -> 21941.79 | Q15: 716.19 | R15: 2221.84 | S15: 8915.09 | T15: 9554.37 | U15: 17.13 | V15: 517.17 | W15: =SUM(M15:P15) -> 141329.31 | X15: =M15/$W15 -> 0.68370984 | Y15: =N15/$W15 -> 0.009000327 | Z15: =O15/$W15 -> 0.1520369 | AA15: =P15/$W15 -> 0.15525293
A16: ENERO | B16: 10006720 | C16: =A16&B16&E16 -> ENERO10006720Revalorización | D16: POTA ALAS FR C/P C/C 1-2 BL10 S20 | E16: Revalorización | F16: 0 | G16: KG | H16: 4009 | I16: -4009 | K16: 0 | L16: 0 | M16: 0 | N16: 0 | O16: 0 | P16: =SUM(Q16:V16) -> 0 | Q16: 0 | R16: 0 | S16: 0 | T16: 0 | U16: 0 | V16: 0 | W16: =SUM(M16:P16) -> 0 | X16: =M16/$W16 -> #DIV/0! | Y16: =N16/$W16 -> #DIV/0! | Z16: =O16/$W16 -> #DIV/0! | AA16: =P16/$W16 -> #DIV/0!
A17: ENERO | B17: 10006720 | C17: =A17&B17&E17 -> ENERO10006720Entradas | D17: POTA ALAS FR C/P C/C 1-2 BL10 S20 | E17: Entradas | F17: 276180 | G17: KG | H17: 491600.4 | I17: -18595.02 | K17: 473005.38 | L17: 1.71 | M17: 308981.27 | N17: 4610.57 | O17: 72365.76 | P17: =SUM(Q17:V17) -> 87047.78 | Q17: 620.31 | R17: 4747.81 | S17: 43377.94 | T17: 35110.76 | U17: 0 | V17: 3190.96 | W17: =SUM(M17:P17) -> 473005.38 | X17: =M17/$W17 -> 0.65322993 | Y17: =N17/$W17 -> 0.0097473944 | Z17: =O17/$W17 -> 0.15299141 | AA17: =P17/$W17 -> 0.18403127
A18: ENERO | B18: 10006720 | C18: =A18&B18&E18 -> ENERO10006720Inv. acumulado | D18: POTA ALAS FR C/P C/C 1-2 BL10 S20 | E18: Inv. acumulado | F18: 356360 | G18: KG | H18: 634320.8 | I18: -19986.11 | K18: 614334.69 | L18: 1.72 | M18: 405609.51 | N18: 5882.58 | O18: 93853.03 | P18: =SUM(Q18:V18) -> 108989.57 | Q18: 1336.5 | R18: 6969.65 | S18: 52293.03 | T18: 44665.13 | U18: 17.13 | V18: 3708.13 | W18: =SUM(M18:P18) -> 614334.69 | X18: =M18/$W18 -> 0.66024191 | Y18: =N18/$W18 -> 0.0095755296 | Z18: =O18/$W18 -> 0.15277182 | AA18: =P18/$W18 -> 0.17741074
A19: ENERO | B19: 10006720 | C19: =A19&B19&E19 -> ENERO10006720Compensación | D19: POTA ALAS FR C/P C/C 1-2 BL10 S20 | E19: Compensación | F19: 69700 | G19: KG | H19: 124066 | I19: -3909.06 | K19: 120156.94 | L19: 1.72 | M19: 79332.65 | N19: 1150.57 | O19: 18356.59 | P19: =SUM(Q19:V19) -> 21317.13 | Q19: 261.4 | R19: 1363.19 | S19: 10227.93 | T19: 8735.99 | U19: 3.35 | V19: 725.27 | W19: =SUM(M19:P19) -> 120156.94 | X19: =M19/$W19 -> 0.66024193 | Y19: =N19/$W19 -> 0.0095755601 | Z19: =O19/$W19 -> 0.15277178 | AA19: =P19/$W19 -> 0.17741073
A20: ENERO | B20: 10006720 | C20: =A20&B20&E20 -> ENERO10006720Inventario final | D20: POTA ALAS FR C/P C/C 1-2 BL10 S20 | E20: Inventario final | F20: 286660 | G20: KG | H20: 510254.8 | I20: -16077.05 | K20: 494177.75 | L20: 1.72 | M20: 326276.86 | N20: 4732.01 | O20: 75496.44 | P20: =SUM(Q20:V20) -> 87672.44 | Q20: 1075.1 | R20: 5606.46 | S20: 42065.1 | T20: 35929.14 | U20: 13.78 | V20: 2982.86 | W20: =SUM(M20:P20) -> 494177.75 | X20: =M20/$W20 -> 0.66024191 | Y20: =N20/$W20 -> 0.0095755222 | Z20: =O20/$W20 -> 0.15277183 | AA20: =P20/$W20 -> 0.17741074
A21: FEBRERO | B21: 10006720 | C21: =A21&B21&E21 -> FEBRERO10006720Inventario inicial | D21: POTA ALAS FR C/P C/C 1-2 BL10 S20 | E21: Inventario inicial | F21: 286660 | G21: KG | H21: 510254.8 | I21: 16,077.05- | J21: 0 | K21: 494177.75 | L21: 1.72 | M21: 326276.86 | N21: 4732.01 | O21: 75496.44 | P21: =SUM(Q21:V21) -> 87672.44 | Q21: 1075.1 | R21: 5606.46 | S21: 42065.1 | T21: 0.13 | U21: 35929.14 | V21: 2996.51 | W21: =SUM(M21:P21) -> 494177.75 | X21: =M21/$W21 -> 0.66024191 | Y21: =N21/$W21 -> 0.0095755222 | Z21: =O21/$W21 -> 0.15277183 | AA21: =P21/$W21 -> 0.17741074
A22: FEBRERO | B22: 10006720 | C22: =A22&B22&E22 -> FEBRERO10006720Revalorización | D22: POTA ALAS FR C/P C/C 1-2 BL10 S20 | E22: Revalorización | F22: 0 | G22: KG | H22: 5,733.20- | I22: 5733.2 | J22: 0 | K22: 0 | L22: 0 | M22: 0 | N22: 0 | O22: 0 | P22: =SUM(Q22:V22) -> 0 | Q22: 0 | R22: 0 | S22: 0 | T22: 0 | U22: 0 | V22: 0 | W22: =SUM(M22:P22) -> 0 | X22: =M22/$W22 -> #DIV/0! | Y22: =N22/$W22 -> #DIV/0! | Z22: =O22/$W22 -> #DIV/0! | AA22: =P22/$W22 -> #DIV/0!
A23: FEBRERO | B23: 10006720 | C23: =A23&B23&E23 -> FEBRERO10006720Entradas | D23: POTA ALAS FR C/P C/C 1-2 BL10 S20 | E23: Entradas | F23: 542340 | G23: KG | H23: 954518.4 | I23: 89,328.33- | J23: 0 | K23: 865190.07 | L23: 1.6 | M23: 554933.23 | N23: 8475.11 | O23: 126141.04 | P23: =SUM(Q23:V23) -> 175640.69 | Q23: 3804.51 | R23: 9355.37 | S23: 85463.56 | T23: 0.15- | U23: 69186.31 | V23: 7830.94 | W23: =SUM(M23:P23) -> 865190.07 | X23: =M23/$W23 -> 0.64140037 | Y23: =N23/$W23 -> 0.0097956626 | Z23: =O23/$W23 -> 0.14579576 | AA23: =P23/$W23 -> 0.20300821
A24: FEBRERO | B24: 10006720 | C24: =A24&B24&E24 -> FEBRERO10006720Inventario acumulado | D24: POTA ALAS FR C/P C/C 1-2 BL10 S20 | E24: Inventario acumulado | F24: 829000 | G24: KG | H24: 1459040 | I24: 99,672.18- | J24: 0 | K24: 1359367.8 | L24: 1.64 | M24: 881210.09 | N24: 13207.12 | O24: 201637.48 | P24: =SUM(Q24:V24) -> 263313.13 | Q24: 4879.61 | R24: 14961.83 | S24: 127528.66 | T24: 0.02- | U24: 105115.45 | V24: 10827.58 | W24: =SUM(M24:P24) -> 1359367.8 | X24: =M24/$W24 -> 0.64824993 | Y24: =N24/$W24 -> 0.0097156338 | Z24: =O24/$W24 -> 0.1483318 | AA24: =P24/$W24 -> 0.19370264
A25: FEBRERO | B25: 10006720 | C25: =A25&B25&E25 -> FEBRERO10006720Compensación | D25: POTA ALAS FR C/P C/C 1-2 BL10 S20 | E25: Compensación | F25: 459300 | G25: KG | H25: 808368 | I25: 55,222.48- | J25: 0 | K25: 753145.52 | L25: 1.64 | M25: 488226.53 | N25: 7317.29 | O25: 111715.43 | P25: =SUM(Q25:V25) -> 145886.27 | Q25: 2703.51 | R25: 8289.46 | S25: 70656.11 | T25: 0.01- | U25: 58238.27 | V25: 5998.92 | W25: =SUM(M25:P25) -> 753145.52 | X25: =M25/$W25 -> 0.64824993 | Y25: =N25/$W25 -> 0.009715639 | Z25: =O25/$W25 -> 0.1483318 | AA25: =P25/$W25 -> 0.19370263
A26: FEBRERO | B26: 10006720 | C26: =A26&B26&E26 -> FEBRERO10006720Inventario final | D26: POTA ALAS FR C/P C/C 1-2 BL10 S20 | E26: Inventario final | F26: 369700 | G26: KG | H26: 650672 | I26: 44,449.70- | J26: 0 | K26: 606222.3 | L26: 1.64 | M26: 392983.56 | N26: 5889.83 | O26: 89922.05 | P26: =SUM(Q26:V26) -> 117426.86 | Q26: 2176.1 | R26: 6672.37 | S26: 56872.55 | T26: 0.01- | U26: 46877.18 | V26: 4828.66 | W26: =SUM(M26:P26) -> 606222.3 | X26: =M26/$W26 -> 0.64824992 | Y26: =N26/$W26 -> 0.0097156274 | Z26: =O26/$W26 -> 0.14833181 | AA26: =P26/$W26 -> 0.19370264
A27: ENERO | B27: 10006722 | C27: =A27&B27&E27 -> ENERO10006722Inventario inicial | D27: POTA ALAS FR C/P C/C 2-UP BL10 S20 | E27: Inventario inicial | F27: 120 | G27: KG | H27: 224.4 | I27: -0.37 | K27: 224.03 | L27: 1.87 | M27: 184.53 | N27: 2.57 | O27: 24.03 | P27: =SUM(Q27:V27) -> 12.9 | Q27: 0.61 | R27: 2.37 | S27: 4.28 | T27: -0.06 | U27: 0.02 | V27: 5.68 | W27: =SUM(M27:P27) -> 224.03 | X27: =M27/$W27 -> 0.82368433 | Y27: =N27/$W27 -> 0.011471678 | Z27: =O27/$W27 -> 0.10726242 | AA27: =P27/$W27 -> 0.057581574
A28: ENERO | B28: 10006722 | C28: =A28&B28&E28 -> ENERO10006722Revalorización | D28: POTA ALAS FR C/P C/C 2-UP BL10 S20 | E28: Revalorización | F28: 0 | G28: KG | H28: 0 | I28: 0 | K28: 0 | L28: 0 | M28: 0 | N28: 0 | O28: 0 | P28: =SUM(Q28:V28) -> 0 | Q28: 0 | R28: 0 | S28: 0 | T28: 0 | U28: 0 | V28: 0 | W28: =SUM(M28:P28) -> 0 | X28: =M28/$W28 -> #DIV/0! | Y28: =N28/$W28 -> #DIV/0! | Z28: =O28/$W28 -> #DIV/0! | AA28: =P28/$W28 -> #DIV/0!
A29: ENERO | B29: 10006722 | C29: =A29&B29&E29 -> ENERO10006722Inv. acumulado | D29: POTA ALAS FR C/P C/C 2-UP BL10 S20 | E29: Inv. acumulado | F29: 120 | G29: KG | H29: 224.4 | I29: -0.37 | K29: 224.03 | L29: 1.87 | M29: 184.53 | N29: 2.57 | O29: 24.03 | P29: =SUM(Q29:V29) -> 12.9 | Q29: 0.61 | R29: 2.37 | S29: 4.28 | T29: -0.06 | U29: 0.02 | V29: 5.68 | W29: =SUM(M29:P29) -> 224.03 | X29: =M29/$W29 -> 0.82368433 | Y29: =N29/$W29 -> 0.011471678 | Z29: =O29/$W29 -> 0.10726242 | AA29: =P29/$W29 -> 0.057581574
A30: ENERO | B30: 10006722 | C30: =A30&B30&E30 -> ENERO10006722Inventario final | D30: POTA ALAS FR C/P C/C 2-UP BL10 S20 | E30: Inventario final | F30: 120 | G30: KG | H30: 224.4 | I30: -0.37 | K30: 224.03 | L30: 1.87 | M30: 184.53 | N30: 2.57 | O30: 24.03 | P30: =SUM(Q30:V30) -> 12.9 | Q30: 0.61 | R30: 2.37 | S30: 4.28 | T30: -0.06 | U30: 0.02 | V30: 5.68 | W30: =SUM(M30:P30) -> 224.03 | X30: =M30/$W30 -> 0.82368433 | Y30: =N30/$W30 -> 0.011471678 | Z30: =O30/$W30 -> 0.10726242 | AA30: =P30/$W30 -> 0.057581574
A31: FEBRERO | B31: 10006722 | C31: =A31&B31&E31 -> FEBRERO10006722Inventario inicial | D31: POTA ALAS FR C/P C/C 2-UP BL10 S20 | E31: Inventario inicial | F31: 120 | G31: KG | H31: 224.4 | I31: 0.37- | J31: 0 | K31: 224.03 | L31: 1.87 | M31: 184.53 | N31: 2.57 | O31: 24.03 | P31: =SUM(Q31:V31) -> 12.9 | Q31: 0.61 | R31: 2.37 | S31: 4.28 | T31: 0.06- | U31: 3.41 | V31: 2.23 | W31: =SUM(M31:P31) -> 224.03 | X31: =M31/$W31 -> 0.82368433 | Y31: =N31/$W31 -> 0.011471678 | Z31: =O31/$W31 -> 0.10726242 | AA31: =P31/$W31 -> 0.057581574
A32: FEBRERO | B32: 10006722 | C32: =A32&B32&E32 -> FEBRERO10006722Revalorización | D32: POTA ALAS FR C/P C/C 2-UP BL10 S20 | E32: Revalorización | F32: 0 | G32: KG | H32: 0 | I32: 0 | J32: 0 | K32: 0 | L32: 0 | M32: 0 | N32: 0 | O32: 0 | P32: =SUM(Q32:V32) -> 0 | Q32: 0 | R32: 0 | S32: 0 | T32: 0 | U32: 0 | V32: 0 | W32: =SUM(M32:P32) -> 0 | X32: =M32/$W32 -> #DIV/0! | Y32: =N32/$W32 -> #DIV/0! | Z32: =O32/$W32 -> #DIV/0! | AA32: =P32/$W32 -> #DIV/0!
A33: FEBRERO | B33: 10006722 | C33: =A33&B33&E33 -> FEBRERO10006722Inventario acumulado | D33: POTA ALAS FR C/P C/C 2-UP BL10 S20 | E33: Inventario acumulado | F33: 120 | G33: KG | H33: 224.4 | I33: 0.37- | J33: 0 | K33: 224.03 | L33: 1.87 | M33: 184.53 | N33: 2.57 | O33: 24.03 | P33: =SUM(Q33:V33) -> 12.9 | Q33: 0.61 | R33: 2.37 | S33: 4.28 | T33: 0.06- | U33: 3.41 | V33: 2.23 | W33: =SUM(M33:P33) -> 224.03 | X33: =M33/$W33 -> 0.82368433 | Y33: =N33/$W33 -> 0.011471678 | Z33: =O33/$W33 -> 0.10726242 | AA33: =P33/$W33 -> 0.057581574
A34: FEBRERO | B34: 10006722 | C34: =A34&B34&E34 -> FEBRERO10006722Inventario final | D34: POTA ALAS FR C/P C/C 2-UP BL10 S20 | E34: Inventario final | F34: 120 | G34: KG | H34: 224.4 | I34: 0.37- | J34: 0 | K34: 224.03 | L34: 1.87 | M34: 184.53 | N34: 2.57 | O34: 24.03 | P34: =SUM(Q34:V34) -> 12.9 | Q34: 0.61 | R34: 2.37 | S34: 4.28 | T34: 0.06- | U34: 3.41 | V34: 2.23 | W34: =SUM(M34:P34) -> 224.03 | X34: =M34/$W34 -> 0.82368433 | Y34: =N34/$W34 -> 0.011471678 | Z34: =O34/$W34 -> 0.10726242 | AA34: =P34/$W34 -> 0.057581574
A35: ENERO | B35: 10007969 | C35: =A35&B35&E35 -> ENERO10007969Inventario inicial | D35: POTA CONOS | E35: Inventario inicial | F35: 33140 | G35: KG | H35: 66611.4 | I35: -3356.06 | K35: 63255.34 | L35: 1.91 | M35: 45896.74 | N35: 553.85 | O35: 7946.71 | P35: =SUM(Q35:V35) -> 8858.04 | Q35: 164.9 | R35: 915.37 | S35: 3681.16 | T35: 3942.02 | V35: 154.59 | W35: =SUM(M35:P35) -> 63255.34 | X35: =M35/$W35 -> 0.7255789 | Y35: =N35/$W35 -> 0.0087557825 | Z35: =O35/$W35 -> 0.12562908 | AA35: =P35/$W35 -> 0.14003624
A36: ENERO | B36: 10007969 | C36: =A36&B36&E36 -> ENERO10007969Revalorización | D36: POTA CONOS | E36: Revalorización | F36: 0 | G36: KG | H36: 1325.6 | I36: -1325.6 | K36: 0 | L36: 0 | M36: 0 | N36: 0 | O36: 0 | P36: =SUM(Q36:V36) -> 0 | Q36: 0 | R36: 0 | S36: 0 | T36: 0 | V36: 0 | W36: =SUM(M36:P36) -> 0 | X36: =M36/$W36 -> #DIV/0! | Y36: =N36/$W36 -> #DIV/0! | Z36: =O36/$W36 -> #DIV/0! | AA36: =P36/$W36 -> #DIV/0!
A37: ENERO | B37: 10007969 | C37: =A37&B37&E37 -> ENERO10007969Entradas | D37: POTA CONOS | E37: Entradas | F37: 31840 | G37: KG | H37: 65272 | I37: -21679.65 | K37: 43592.35 | L37: 1.37 | M37: 36713.73 | N37: 541.57 | O37: 6527.17 | P37: =SUM(Q37:V37) -> -190.12 | Q37: 0 | R37: 0 | S37: 0 | T37: 0 | V37: -190.12 | W37: =SUM(M37:P37) -> 43592.35 | X37: =M37/$W37 -> 0.8422058 | Y37: =N37/$W37 -> 0.01242351 | Z37: =O37/$W37 -> 0.14973201 | AA37: =P37/$W37 -> -0.0043613157
A38: ENERO | B38: 10007969 | C38: =A38&B38&E38 -> ENERO10007969Inv. acumulado | D38: POTA CONOS | E38: Inv. acumulado | F38: 64980 | G38: KG | H38: 133209 | I38: -26361.31 | K38: 106847.69 | L38: 1.64 | M38: 82610.47 | N38: 1095.42 | O38: 14473.88 | P38: =SUM(Q38:V38) -> 8667.92 | Q38: 164.9 | R38: 915.37 | S38: 3681.16 | T38: 3942.02 | V38: -35.53 | W38: =SUM(M38:P38) -> 106847.69 | X38: =M38/$W38 -> 0.77316103 | Y38: =N38/$W38 -> 0.010252164 | Z38: =O38/$W38 -> 0.13546273 | AA38: =P38/$W38 -> 0.081124075
A39: ENERO | B39: 10007969 | C39: =A39&B39&E39 -> ENERO10007969Compensación | D39: POTA CONOS | E39: Compensación | F39: 24020 | G39: KG | H39: 49241 | I39: -9744.52 | K39: 39496.48 | L39: 1.64 | M39: 30537.14 | N39: 404.93 | O39: 5350.3 | P39: =SUM(Q39:V39) -> 3204.11 | Q39: 60.95 | R39: 338.37 | S39: 1360.75 | T39: 1457.17 | V39: -13.13 | W39: =SUM(M39:P39) -> 39496.48 | X39: =M39/$W39 -> 0.77316105 | Y39: =N39/$W39 -> 0.010252306 | Z39: =O39/$W39 -> 0.1354627 | AA39: =P39/$W39 -> 0.081123938
A40: ENERO | B40: 10007969 | C40: =A40&B40&E40 -> ENERO10007969Inventario final | D40: POTA CONOS | E40: Inventario final | F40: 40960 | G40: KG | H40: 83968 | I40: -16616.79 | K40: 67351.21 | L40: 1.64 | M40: 52073.33 | N40: 690.49 | O40: 9123.58 | P40: =SUM(Q40:V40) -> 5463.81 | Q40: 103.95 | R40: 577 | S40: 2320.41 | T40: 2484.85 | V40: -22.4 | W40: =SUM(M40:P40) -> 67351.21 | X40: =M40/$W40 -> 0.77316102 | Y40: =N40/$W40 -> 0.01025208 | Z40: =O40/$W40 -> 0.13546275 | AA40: =P40/$W40 -> 0.081124155
A41: FEBRERO | B41: 10007969 | C41: =A41&B41&E41 -> FEBRERO10007969Inventario inicial | D41: POTA CONOS | E41: Inventario inicial | F41: 40960 | G41: KG | H41: 83968 | I41: 16,616.79- | K41: 67351.21 | L41: 1.64 | M41: 52073.33 | N41: 690.49 | O41: 9123.58 | P41: =SUM(Q41:V41) -> 5463.81 | Q41: 103.95 | R41: 577 | S41: 2320.41 | T41: 0.01 | U41: 2484.85 | V41: -22.41 | W41: =SUM(M41:P41) -> 67351.21 | X41: =M41/$W41 -> 0.77316102 | Y41: =N41/$W41 -> 0.01025208 | Z41: =O41/$W41 -> 0.13546275 | AA41: =P41/$W41 -> 0.081124155
A42: FEBRERO | B42: 10007969 | C42: =A42&B42&E42 -> FEBRERO10007969Revalorización | D42: POTA CONOS | E42: Revalorización | F42: 0 | G42: KG | H42: 5,734.40- | I42: 5734.4 | K42: 0 | L42: 0 | M42: 0 | N42: 0 | O42: 0 | P42: =SUM(Q42:V42) -> 0 | Q42: 0 | R42: 0 | S42: 0 | T42: 0 | U42: 0 | V42: 0 | W42: =SUM(M42:P42) -> 0 | X42: =M42/$W42 -> #DIV/0! | Y42: =N42/$W42 -> #DIV/0! | Z42: =O42/$W42 -> #DIV/0! | AA42: =P42/$W42 -> #DIV/0!
A43: FEBRERO | B43: 10007969 | C43: =A43&B43&E43 -> FEBRERO10007969Entradas | D43: POTA CONOS | E43: Entradas | F43: 52860 | G43: KG | H43: 100962.6 | I43: 37,221.26- | K43: 63741.34 | L43: 1.21 | M43: 53960.46 | N43: 874.71 | O43: 10836.3 | P43: =SUM(Q43:V43) -> -1930.13 | Q43: 0 | R43: 0 | S43: 0 | T43: 0 | U43: 0 | V43: -1930.13 | W43: =SUM(M43:P43) -> 63741.34 | X43: =M43/$W43 -> 0.84655359 | Y43: =N43/$W43 -> 0.013722805 | Z43: =O43/$W43 -> 0.17000427 | AA43: =P43/$W43 -> -0.030280662
A44: FEBRERO | B44: 10007969 | C44: =A44&B44&E44 -> FEBRERO10007969Inventario acumulado | D44: POTA CONOS | E44: Inventario acumulado | F44: 93820 | G44: KG | H44: 179196.2 | I44: 48,103.65- | K44: 131092.55 | L44: 1.4 | M44: 106033.79 | N44: 1565.2 | O44: 19959.88 | P44: =SUM(Q44:V44) -> 3533.68 | Q44: 103.95 | R44: 577 | S44: 2320.41 | T44: 0.01 | U44: 2484.85 | V44: -1952.54 | W44: =SUM(M44:P44) -> 131092.55 | X44: =M44/$W44 -> 0.8088468 | Y44: =N44/$W44 -> 0.011939656 | Z44: =O44/$W44 -> 0.15225793 | AA44: =P44/$W44 -> 0.026955613
A45: FEBRERO | B45: 10007969 | C45: =A45&B45&E45 -> FEBRERO10007969Compensación | D45: POTA CONOS | E45: Compensación | F45: 33140 | G45: KG | H45: 63297.4 | I45: 16,991.63- | K45: 46305.77 | L45: 1.4 | M45: 37454.27 | N45: 552.88 | O45: 7050.42 | P45: =SUM(Q45:V45) -> 1248.2 | Q45: 36.72 | R45: 203.81 | S45: 819.64 | T45: 0 | U45: 877.72 | V45: -689.69 | W45: =SUM(M45:P45) -> 46305.77 | X45: =M45/$W45 -> 0.80884672 | Y45: =N45/$W45 -> 0.011939765 | Z45: =O45/$W45 -> 0.15225792 | AA45: =P45/$W45 -> 0.026955604
A46: FEBRERO | B46: 10007969 | C46: =A46&B46&E46 -> FEBRERO10007969Inventario final | D46: POTA CONOS | E46: Inventario final | F46: 60680 | G46: KG | H46: 115898.8 | I46: 31,112.02- | K46: 84786.78 | L46: 1.4 | M46: 68579.52 | N46: 1012.32 | O46: 12909.46 | P46: =SUM(Q46:V46) -> 2285.48 | Q46: 67.23 | R46: 373.19 | S46: 1500.77 | T46: 0.01 | U46: 1607.13 | V46: -1262.85 | W46: =SUM(M46:P46) -> 84786.78 | X46: =M46/$W46 -> 0.80884685 | Y46: =N46/$W46 -> 0.011939597 | Z46: =O46/$W46 -> 0.15225793 | AA46: =P46/$W46 -> 0.026955617
A47: ENERO | B47: 10005721 | C47: =A47&B47&E47 -> ENERO10005721Inventario inicial | D47: POTA FILETE C/M C/T FR 2-4 (B) BL10 S20 | E47: Inventario inicial | F47: 130100 | G47: KG | H47: 291424 | I47: -57699.72 | K47: 233724.28 | L47: 1.8 | M47: 143788.37 | N47: 1889.83 | O47: 52372.25 | P47: =SUM(Q47:V47) -> 35673.83 | Q47: 302.23 | R47: 3651.9 | S47: 15184.88 | T47: 15872.2 | V47: 662.62 | W47: =SUM(M47:P47) -> 233724.28 | X47: =M47/$W47 -> 0.6152051 | Y47: =N47/$W47 -> 0.0080857239 | Z47: =O47/$W47 -> 0.22407706 | AA47: =P47/$W47 -> 0.15263211
A48: ENERO | B48: 10005721 | C48: =A48&B48&E48 -> ENERO10005721Revalorización | D48: POTA FILETE C/M C/T FR 2-4 (B) BL10 S20 | E48: Revalorización | F48: 0 | G48: KG | H48: 0 | I48: 0 | K48: 0 | L48: 0 | M48: 0 | N48: 0 | O48: 0 | P48: =SUM(Q48:V48) -> 0 | Q48: 0 | R48: 0 | S48: 0 | T48: 0 | V48: 0 | W48: =SUM(M48:P48) -> 0 | X48: =M48/$W48 -> #DIV/0! | Y48: =N48/$W48 -> #DIV/0! | Z48: =O48/$W48 -> #DIV/0! | AA48: =P48/$W48 -> #DIV/0!
A49: ENERO | B49: 10005721 | C49: =A49&B49&E49 -> ENERO10005721Entradas | D49: POTA FILETE C/M C/T FR 2-4 (B) BL10 S20 | E49: Entradas | F49: 375660 | G49: KG | H49: 841478.4 | I49: -133757.06 | K49: 707721.34 | L49: 1.88 | M49: 427211.12 | N49: 7123.62 | O49: 154762.57 | P49: =SUM(Q49:V49) -> 118624.03 | Q49: 843.73 | R49: 6457.97 | S49: 59002.66 | T49: 47757.66 | V49: 4562.01 | W49: =SUM(M49:P49) -> 707721.34 | X49: =M49/$W49 -> 0.60364312 | Y49: =N49/$W49 -> 0.010065572 | Z49: =O49/$W49 -> 0.21867727 | AA49: =P49/$W49 -> 0.16761404
A50: ENERO | B50: 10005721 | C50: =A50&B50&E50 -> ENERO10005721Inv. acumulado | D50: POTA FILETE C/M C/T FR 2-4 (B) BL10 S20 | E50: Inv. acumulado | F50: 505760 | G50: KG | H50: 1132902.4 | I50: -191456.78 | K50: 941445.62 | L50: 1.86 | M50: 570999.49 | N50: 9013.45 | O50: 207134.82 | P50: =SUM(Q50:V50) -> 154297.86 | Q50: 1145.96 | R50: 10109.87 | S50: 74187.54 | T50: 63629.86 | V50: 5224.63 | W50: =SUM(M50:P50) -> 941445.62 | X50: =M50/$W50 -> 0.60651351 | Y50: =N50/$W50 -> 0.0095740527 | Z50: =O50/$W50 -> 0.22001783 | AA50: =P50/$W50 -> 0.16389461
A51: ENERO | B51: 10005721 | C51: =A51&B51&E51 -> ENERO10005721Compensación | D51: POTA FILETE C/M C/T FR 2-4 (B) BL10 S20 | E51: Compensación | F51: 135000 | G51: KG | H51: 302400 | I51: -51104.61 | K51: 251295.39 | L51: 1.86 | M51: 152414.05 | N51: 2405.92 | O51: 55289.46 | P51: =SUM(Q51:V51) -> 41185.96 | Q51: 305.89 | R51: 2698.58 | S51: 19802.51 | T51: 16984.4 | V51: 1394.58 | W51: =SUM(M51:P51) -> 251295.39 | X51: =M51/$W51 -> 0.60651351 | Y51: =N51/$W51 -> 0.0095740714 | Z51: =O51/$W51 -> 0.2200178 | AA51: =P51/$W51 -> 0.16389461
A52: ENERO | B52: 10005721 | C52: =A52&B52&E52 -> ENERO10005721Inventario final | D52: POTA FILETE C/M C/T FR 2-4 (B) BL10 S20 | E52: Inventario final | F52: 370760 | G52: KG | H52: 830502.4 | I52: -140352.17 | K52: 690150.23 | L52: 1.86 | M52: 418585.44 | N52: 6607.53 | O52: 151845.36 | P52: =SUM(Q52:V52) -> 113111.9 | Q52: 840.07 | R52: 7411.29 | S52: 54385.03 | T52: 46645.46 | V52: 3830.05 | W52: =SUM(M52:P52) -> 690150.23 | X52: =M52/$W52 -> 0.60651351 | Y52: =N52/$W52 -> 0.0095740459 | Z52: =O52/$W52 -> 0.22001784 | AA52: =P52/$W52 -> 0.16389461
A53: FEBRERO | B53: 10005721 | C53: =A53&B53&E53 -> FEBRERO10005721Inventario inicial | D53: POTA FILETE C/M C/T FR 2-4 (B) BL10 S20 | E53: Inventario inicial | F53: 370760 | G53: KG | H53: 830502.4 | I53: 140,352.17- | K53: 690150.23 | L53: 1.86 | M53: 418585.44 | N53: 6607.53 | O53: 151845.36 | P53: =SUM(Q53:V53) -> 113111.9 | Q53: 840.07 | R53: 7411.29 | S53: 54385.03 | T53: 0 | U53: 46645.46 | V53: 3830.05 | W53: =SUM(M53:P53) -> 690150.23 | X53: =M53/$W53 -> 0.60651351 | Y53: =N53/$W53 -> 0.0095740459 | Z53: =O53/$W53 -> 0.22001784 | AA53: =P53/$W53 -> 0.16389461
A54: FEBRERO | B54: 10005721 | C54: =A54&B54&E54 -> FEBRERO10005721Revalorización | D54: POTA FILETE C/M C/T FR 2-4 (B) BL10 S20 | E54: Revalorización | F54: 0 | G54: KG | H54: 163,134.40- | I54: 163134.4 | K54: 0 | L54: 0 | M54: 0 | N54: 0 | O54: 0 | P54: =SUM(Q54:V54) -> 0 | Q54: 0 | R54: 0 | S54: 0 | T54: 0 | U54: 0 | V54: 0 | W54: =SUM(M54:P54) -> 0 | X54: =M54/$W54 -> #DIV/0! | Y54: =N54/$W54 -> #DIV/0! | Z54: =O54/$W54 -> #DIV/0! | AA54: =P54/$W54 -> #DIV/0!
A55: FEBRERO | B55: 10005721 | C55: =A55&B55&E55 -> FEBRERO10005721Entradas | D55: POTA FILETE C/M C/T FR 2-4 (B) BL10 S20 | E55: Entradas | F55: 659620 | G55: KG | H55: 1187316 | I55: 83,798.54- | K55: 1103517.5 | L55: 1.67 | M55: 669876.63 | N55: 12521.6 | O55: 207741.78 | P55: =SUM(Q55:V55) -> 213377.45 | Q55: 4627.24 | R55: 11378.45 | S55: 103944.9 | T55: 0.29 | U55: 84147.72 | V55: 9278.85 | W55: =SUM(M55:P55) -> 1103517.5 | X55: =M55/$W55 -> 0.60703764 | Y55: =N55/$W55 -> 0.011346989 | Z55: =O55/$W55 -> 0.18825418 | AA55: =P55/$W55 -> 0.19336119
A56: FEBRERO | B56: 10005721 | C56: =A56&B56&E56 -> FEBRERO10005721Inventario acumulado | D56: POTA FILETE C/M C/T FR 2-4 (B) BL10 S20 | E56: Inventario acumulado | F56: 1030380 | G56: KG | H56: 1854684 | I56: 61,016.31- | K56: 1793667.7 | L56: 1.74 | M56: 1088462.1 | N56: 19129.13 | O56: 359587.14 | P56: =SUM(Q56:V56) -> 326489.35 | Q56: 5467.31 | R56: 18789.74 | S56: 158329.93 | T56: 0.29 | U56: 130793.18 | V56: 13108.9 | W56: =SUM(M56:P56) -> 1793667.7 | X56: =M56/$W56 -> 0.60683597 | Y56: =N56/$W56 -> 0.010664813 | Z56: =O56/$W56 -> 0.2004759 | AA56: =P56/$W56 -> 0.18202332
A57: FEBRERO | B57: 10005721 | C57: =A57&B57&E57 -> FEBRERO10005721Compensación | D57: POTA FILETE C/M C/T FR 2-4 (B) BL10 S20 | E57: Compensación | F57: 698300 | G57: KG | H57: 1256940 | I57: 41,351.43- | K57: 1215588.6 | L57: 1.74 | M57: 737662.87 | N57: 12964.02 | O57: 243696.21 | P57: =SUM(Q57:V57) -> 221265.47 | Q57: 3705.26 | R57: 12734.01 | S57: 107301.96 | T57: 0.2 | U57: 88639.99 | V57: 8884.05 | W57: =SUM(M57:P57) -> 1215588.6 | X57: =M57/$W57 -> 0.60683597 | Y57: =N57/$W57 -> 0.010664809 | Z57: =O57/$W57 -> 0.2004759 | AA57: =P57/$W57 -> 0.18202332
A58: FEBRERO | B58: 10005721 | C58: =A58&B58&E58 -> FEBRERO10005721Inventario final | D58: POTA FILETE C/M C/T FR 2-4 (B) BL10 S20 | E58: Inventario final | F58: 332080 | G58: KG | H58: 597744 | I58: 19,664.88- | K58: 578079.12 | L58: 1.74 | M58: 350799.2 | N58: 6165.11 | O58: 115890.93 | P58: =SUM(Q58:V58) -> 105223.88 | Q58: 1762.05 | R58: 6055.73 | S58: 51027.97 | T58: 0.09 | U58: 42153.19 | V58: 4224.85 | W58: =SUM(M58:P58) -> 578079.12 | X58: =M58/$W58 -> 0.60683596 | Y58: =N58/$W58 -> 0.01066482 | Z58: =O58/$W58 -> 0.2004759 | AA58: =P58/$W58 -> 0.18202332
A59: ENERO | B59: 10005779 | C59: =A59&B59&E59 -> ENERO10005779Inventario inicial | D59: POTA NUCAS FR ABIERTAS 0.5-1 BL10 S20 | E59: Inventario inicial | F59: 96140 | G59: KG | H59: 204778.2 | I59: -14558.56 | K59: 190219.64 | L59: 1.98 | M59: 122437 | N59: 1608.88 | O59: 40184.82 | P59: =SUM(Q59:V59) -> 25988.94 | Q59: 756.12 | R59: 2669.29 | S59: 10708.82 | T59: 11526.48 | V59: 328.23 | W59: =SUM(M59:P59) -> 190219.64 | X59: =M59/$W59 -> 0.64366119 | Y59: =N59/$W59 -> 0.008458012 | Z59: =O59/$W59 -> 0.21125484 | AA59: =P59/$W59 -> 0.13662596
A60: ENERO | B60: 10005779 | C60: =A60&B60&E60 -> ENERO10005779Revalorización | D60: POTA NUCAS FR ABIERTAS 0.5-1 BL10 S20 | E60: Revalorización | F60: 0 | G60: KG | H60: -1922.8 | I60: 1922.8 | K60: 0 | L60: 0 | M60: 0 | N60: 0 | O60: 0 | P60: =SUM(Q60:V60) -> 0 | Q60: 0 | R60: 0 | S60: 0 | T60: 0 | V60: 0 | W60: =SUM(M60:P60) -> 0 | X60: =M60/$W60 -> #DIV/0! | Y60: =N60/$W60 -> #DIV/0! | Z60: =O60/$W60 -> #DIV/0! | AA60: =P60/$W60 -> #DIV/0!
A61: ENERO | B61: 10005779 | C61: =A61&B61&E61 -> ENERO10005779Entradas | D61: POTA NUCAS FR ABIERTAS 0.5-1 BL10 S20 | E61: Entradas | F61: 84920 | G61: KG | H61: 179181.2 | I61: -19111.95 | K61: 160069.25 | L61: 1.88 | M61: 98016.61 | N61: 1066.1 | O61: 34253.93 | P61: =SUM(Q61:V61) -> 26732.61 | Q61: 190.73 | R61: 1459.86 | S61: 13337.87 | T61: 10795.88 | V61: 948.27 | W61: =SUM(M61:P61) -> 160069.25 | X61: =M61/$W61 -> 0.61233878 | Y61: =N61/$W61 -> 0.0066602424 | Z61: =O61/$W61 -> 0.21399444 | AA61: =P61/$W61 -> 0.16700653
A62: ENERO | B62: 10005779 | C62: =A62&B62&E62 -> ENERO10005779Inv. acumulado | D62: POTA NUCAS FR ABIERTAS 0.5-1 BL10 S20 | E62: Inv. acumulado | F62: 181060 | G62: KG | H62: 382036.6 | I62: -31747.71 | K62: 350288.89 | L62: 1.93 | M62: 220453.61 | N62: 2674.98 | O62: 74438.75 | P62: =SUM(Q62:V62) -> 52721.55 | Q62: 946.85 | R62: 4129.15 | S62: 24046.69 | T62: 22322.36 | V62: 1276.5 | W62: =SUM(M62:P62) -> 350288.89 | X62: =M62/$W62 -> 0.62934799 | Y62: =N62/$W62 -> 0.0076364968 | Z62: =O62/$W62 -> 0.21250674 | AA62: =P62/$W62 -> 0.15050877
A63: ENERO | B63: 10005779 | C63: =A63&B63&E63 -> ENERO10005779Compensación | D63: POTA NUCAS FR ABIERTAS 0.5-1 BL10 S20 | E63: Compensación | F63: 3060 | G63: KG | H63: 6456.6 | I63: -536.55 | K63: 5920.05 | L63: 1.93 | M63: 3725.77 | N63: 45.21 | O63: 1258.05 | P63: =SUM(Q63:V63) -> 891.02 | Q63: 16 | R63: 69.79 | S63: 406.4 | T63: 377.25 | V63: 21.58 | W63: =SUM(M63:P63) -> 5920.05 | X63: =M63/$W63 -> 0.62934773 | Y63: =N63/$W63 -> 0.0076367598 | Z63: =O63/$W63 -> 0.21250665 | AA63: =P63/$W63 -> 0.15050886
A64: ENERO | B64: 10005779 | C64: =A64&B64&E64 -> ENERO10005779Inventario final | D64: POTA NUCAS FR ABIERTAS 0.5-1 BL10 S20 | E64: Inventario final | F64: 178000 | G64: KG | H64: 375580 | I64: -31211.16 | K64: 344368.84 | L64: 1.93 | M64: 216727.84 | N64: 2629.77 | O64: 73180.7 | P64: =SUM(Q64:V64) -> 51830.53 | Q64: 930.85 | R64: 4059.36 | S64: 23640.29 | T64: 21945.11 | V64: 1254.92 | W64: =SUM(M64:P64) -> 344368.84 | X64: =M64/$W64 -> 0.629348 | Y64: =N64/$W64 -> 0.0076364923 | Z64: =O64/$W64 -> 0.21250674 | AA64: =P64/$W64 -> 0.15050877
A65: FEBRERO | B65: 10005779 | C65: =A65&B65&E65 -> FEBRERO10005779Inventario inicial | D65: POTA NUCAS FR ABIERTAS 0.5-1 BL10 S20 | E65: Inventario inicial | F65: 178000 | G65: KG | H65: 375580 | I65: 31,211.16- | K65: 344368.84 | L65: 1.93 | M65: 216727.84 | N65: 2629.77 | O65: 73180.7 | P65: =SUM(Q65:V65) -> 51830.53 | Q65: 930.85 | R65: 4059.36 | S65: 23640.29 | T65: 0.01- | U65: 21945.11 | V65: 1254.92 | W65: =SUM(M65:P65) -> 344368.84 | X65: =M65/$W65 -> 0.629348 | Y65: =N65/$W65 -> 0.0076364923 | Z65: =O65/$W65 -> 0.21250674 | AA65: =P65/$W65 -> 0.15050877
A66: FEBRERO | B66: 10005779 | C66: =A66&B66&E66 -> FEBRERO10005779Revalorización | D66: POTA NUCAS FR ABIERTAS 0.5-1 BL10 S20 | E66: Revalorización | F66: 0 | G66: KG | H66: 23,140.00- | I66: 23140 | K66: 0 | L66: 0 | M66: 0 | N66: 0 | O66: 0 | P66: =SUM(Q66:V66) -> 0 | Q66: 0 | R66: 0 | S66: 0 | T66: 0 | U66: 0 | V66: 0 | W66: =SUM(M66:P66) -> 0 | X66: =M66/$W66 -> #DIV/0! | Y66: =N66/$W66 -> #DIV/0! | Z66: =O66/$W66 -> #DIV/0! | AA66: =P66/$W66 -> #DIV/0!
A67: FEBRERO | B67: 10005779 | C67: =A67&B67&E67 -> FEBRERO10005779Entradas | D67: POTA NUCAS FR ABIERTAS 0.5-1 BL10 S20 | E67: Entradas | F67: 142120 | G67: KG | H67: 281397.6 | I67: 30,434.64- | K67: 250962.96 | L67: 1.77 | M67: 145645.04 | N67: 1712.92 | O67: 57894.88 | P67: =SUM(Q67:V67) -> 45710.12 | Q67: 996.97 | R67: 2451.58 | S67: 22395.7 | T67: 0.16- | U67: 18130.25 | V67: 1735.62 | W67: =SUM(M67:P67) -> 250962.96 | X67: =M67/$W67 -> 0.58034476 | Y67: =N67/$W67 -> 0.0068253897 | Z67: =O67/$W67 -> 0.23069094 | AA67: =P67/$W67 -> 0.18213891
